Workbook
Name ActuaryCredentialsGASB: [1]DeveloperInfo!$D$19
Name ActuaryNameGASB: [1]DeveloperInfo!$D$17
Name ActuaryTitleGASB: [1]DeveloperInfo!$D$18
Name AdjCNSDate: [1]DeveloperInfo!$D$33
Name AdjCNSDate1: [1]DeveloperInfo!$E$33
Name AdjCNSDateTempEnable: [1]DeveloperInfo!$F$34
Name AgencyCode: #REF!
Name AgencyCode1: #REF!
Name AnalystGASB: [1]DeveloperInfo!$D$20
Name Annuity: #REF!
Name Annuity1: #REF!
Name AnnuityLY: #REF!
Name ASTABPF: [1]DeveloperInfo!$D$36
Name ASTABPF1: [1]DeveloperInfo!$D$37
Name ASTEBPF: [1]DeveloperInfo!$F$37
Name ClientShortGASB: [1]DeveloperInfo!$D$9
Name CLPOWERDisc: [1]Adjust!$H$199
Name CLPOWERDiscMinus1: [1]Adjust!$L$199
Name CLPOWERDiscPlus1: [1]Adjust!$K$199
Name CLPOWERExp: [1]Adjust!$G$199
Name CNSDateDisc: [1]DeveloperInfo!$D$32
Name CNSDateDisc1: [1]DeveloperInfo!$E$32
Name ColaRate: [1]DeveloperInfo!$D$40
Name ConsultantNameGASB: [1]DeveloperInfo!$D$22
Name ConsultantTitleGASB: [1]DeveloperInfo!$D$23
Name Disc1DELTACENSUS: [1]Adjust!$G$102
Name Disc1INTNDIV12: [1]Adjust!$H$195
Name Disc1SINTADJBOM: [1]Adjust!$I$197
Name Disc1SINTNDIV12: [1]Adjust!$I$195
Name DiscDELTACENSUS: [1]Adjust!$H$102
Name DiscINTADJBOM: [1]Adjust!$J$197
Name DiscINTNDIV12: [1]Adjust!$J$195
Name DiscMinusOneINTADJBOM: [1]Adjust!$L$197
Name DiscMinusOneINTNDIV12: [1]Adjust!$L$195
Name DiscPlusOneINTADJBOM: [1]Adjust!$K$197
Name DiscPlusOneINTNDIV12: [1]Adjust!$K$195
Name EmployerRates: #REF!
Name EmployerRates1: #REF!
Name EmployerRatesLEO: #REF!
Name EmployerRatesLEO1: #REF!
Name ERData: [1]ER_DATA!$B$16:$EN$318
Name ERID: [1]ER_NPLExpense!$L$8
Name ERInfo: [1]ER_Input!$B$16:$Y$318
Name Exp1INTADJBOM: [1]Adjust!$G$197
Name Exp1INTNDIV12: [1]Adjust!$G$195
Name FracYearProj: [1]TPL!$C$43
Name FundOfficeContactGASB: [1]DeveloperInfo!$D$10
Name FYrsGASB: [1]DeveloperInfo!$D$54
Name GainLoss: [1]ER_Allocation!$P$12
Name GASBDiscMinusOneINTADJBOM: [1]Adjust!$L$197
Name GASBDiscMinusOneINTNDIV12: [1]Adjust!$L$195
Name InflRate: [1]DeveloperInfo!$D$38
Name InflRate1: [1]DeveloperInfo!$E$38
Name IntDisc: [1]DeveloperInfo!$F$47
Name IntDisc1: [1]DeveloperInfo!$D$47
Name IntDisc1S: [1]DeveloperInfo!$E$47
Name INTDiscMinusOne: [1]DeveloperInfo!$H$47
Name INTDiscPlusOne: [1]DeveloperInfo!$G$47
Name IntExp1: [1]DeveloperInfo!$I$47
Name MeasureDate: [1]DeveloperInfo!$D$31

Sheet Fund 0200 Journal Entries
A1: GASB 96 - SBITA Contracts Fund-by-Fund Journal Entries Form (to be submitted to the SCO annually—one form per fund)
A2: Manually complete every yellow field in this worksheet—there are no automatically calculated data-entry cells in this worksheet.
A3: Fiscal year: | F3: 2022–2023
A4: Organization Name: | F4: Department of Fish and Wildlife
A5: Organization Code (Business Unit): | F5: 3600
A6: Fund Number: | F6: 200
A7: Fund Type: | F7: Governmental Fund
A8: Fund Classification: | F8: =IF(OR($F$7='Drop Down Menus'!B2,$F$7='Drop Down Menus'!$B$3),'Drop Down Menus'!$D$9,IFERROR(VLOOKUP($F$5,GAAP02Aindex!$A$2:$D$900,4,FALSE),"Unidentified")) -> RESOURCES
A12: =IF($F$3="2022–2023","Establish Beginning Balances (SBITAs commenced on or before 07/01/2022)","Establish Beginning Balances (existing SBITAs only)") -> Establish Beginning Balances (SBITAs commenced on or before 07/01/2022)
A13: Entry #
A14: 0 | B14: =IF($F$3="2022–2023","To establish the beginning balance of SBITAs as of 07/01/2022.","Roll forward prior year right-to-use SBITAs to record opening balances.") -> To establish the beginning balance of SBITAs as of 07/01/2022.
B15: Dr: Acct 0480 - RIGHT-TO-USE SBITA - AMORTIZABLE | J15: 1437815
B16: Dr: Acct 0950 - BEGINNING FUND BALANCE
B17: Dr: Acct 0952 - BEG FB ADJ/PRIOR PERIOD ADJUSTMENT
C18: Cr. Acct 0475 - ACCUMULATED AMORTIZATION - RIGHT-TO-USE SBITA
C19: Cr: Acct 0674 - RIGHT-TO-USE SBITA LIABILITY | K19: 689814
C20: Cr: Acct 0950 - BEGINNING FUND BALANCE
C21: Cr: Acct 0952 - BEG FB ADJ/PRIOR PERIOD ADJUSTMENT | K21: 748001
J22: =ROUND(SUM(J15:J17),2) -> 1437815 | K22: =ROUND(SUM(K18:K21),2) -> 1437815 | L22: =IF(J22=K22,"<- Debits and Credits equal each other.","<- Debits and Credits do not equal each other.") -> <- Debits and Credits equal each other.
B24: SBITA ASSET (Acct 0480) AMOUNT SHOULD BE REPORTED AS BEGINNING BALANCE ON REPORT 18.
A26: =IF($F$3="2022–2023","Record SBITAs Commenced on or after 07/02/2022","Record New SBITAs (new SBITAs only)") -> Record SBITAs Commenced on or after 07/02/2022
A27: 1 | B27: Record at inception of SBITA in accordance with Fund-Based accounting (Governmental Funds Only).
B28: Dr: Acct 0842 - CAPITAL OUTLAY
C29: Cr: Acct 0789 - LEASE AND OTHER FINANCING PROCEEDS
C30: =VLOOKUP($F$8,'Drop Down Menus'!$D$2:$G$10,4,FALSE) -> Cr: Acct 0820 - NAT RES & ENVIRON (GAAP ADJ)
J31: =ROUND(SUM(J28:J30),2) -> 0 | K31: =ROUND(SUM(K28:K30),2) -> 0 | L31: =IF(J31=K31,"<- Debits and Credits equal each other.","<- Debits and Credits do not equal each other.") -> <- Debits and Credits equal each other.
A33: 2 | B33: Reverse the fund-based entry in #1 above, if any, and record an inception of SBITA in accordance with GAAP Govt Wide.
B34: Dr: Acct 0480 - RIGHT-TO-USE SBITA - AMORTIZABLE
B35: Dr: Acct 0789 - LEASE AND OTHER FINANCING PROCEEDS
C36: Cr: Acct 0842 - CAPITAL OUTLAY
C37: Cr: Acct 0674 - RIGHT-TO-USE SBITA LIABILITY
C38: =VLOOKUP($F$8,'Drop Down Menus'!$D$2:$G$10,4,FALSE) -> Cr: Acct 0820 - NAT RES & ENVIRON (GAAP ADJ)
J39: =ROUND(SUM(J34:J35),2) -> 0 | K39: =ROUND(SUM(K36:K38),2) -> 0 | L39: =IF(J39=K39,"<- Debits and Credits equal each other.","<- Debits and Credits do not equal each other.") -> <- Debits and Credits equal each other.
B41: SBITA ASSET (Acct 0480) AMOUNT SHOULD BE INCLUDED AS "ADDITIONS" ON REPORT 18.
A43: Record Annual Activity (all SBITAs)
A44: 3 | B44: Record amortization of the SBITA asset for the year.
B45: Dr: Acct 0875 - DEPRECIATION/AMORTIZATION | J45: 40422
C46: Cr. Acct 0475 - ACCUMULATED AMORTIZATION - RIGHT-TO-USE SBITA | K46: =J45 -> 40422
J47: =ROUND(SUM(J45:J45),2) -> 40422 | K47: =ROUND(SUM(K46),2) -> 40422 | L47: =IF(J47=K47,"<- Debits and Credits equal each other.","<- Debits and Credits do not equal each other.") -> <- Debits and Credits equal each other.
A49: 4 | B49: Reclassify information technology subscription exp. to debt service principal and interest exp.
B50: Dr: Acct 0848 - DEBT SERVICE - PRINCIPAL LEASES | J50: 689814
B51: =IF(OR($F$7="Proprietary - Internal Service Fund",$F$7="Proprietary - Enterprise Fund"),"Dr: Acct 0894 - INTEREST EXPENSE AND FISCAL CHARGES","Dr: Acct 0851 - DEBT SERVICE - INTEREST LEASES") -> Dr: Acct 0851 - DEBT SERVICE - INTEREST LEASES | J51: 645
C52: =VLOOKUP($F$8,'Drop Down Menus'!$D$2:$G$10,4,FALSE) -> Cr: Acct 0820 - NAT RES & ENVIRON (GAAP ADJ) | K52: =+J50+J51 -> 690459
J53: =ROUND(SUM(J50:J51),2) -> 690459 | K53: =ROUND(SUM(K52,),2) -> 690459 | L53: =IF(J53=K53,"<- Debits and Credits equal each other.","<- Debits and Credits do not equal each other.") -> <- Debits and Credits equal each other.
A55: 5 | B55: Reduce SBITA liability for total current year principal payments.
B56: Dr: Acct 0674 - RIGHT-TO-USE SBITA LIABILITY | J56: =K57 -> 689814
C57: Cr: Acct 0848 - DEBT SERVICE - PRINCIPAL LEASES | K57: =J50 -> 689814
J58: =ROUND(SUM(J56:J56),2) -> 689814 | K58: =ROUND(SUM(K57),2) -> 689814 | L58: =IF(J58=K58,"<- Debits and Credits equal each other.","<- Debits and Credits do not equal each other.") -> <- Debits and Credits equal each other.
A60: 6 | B60: Reclassify the principal amount due in the next FY to the current liability.
B61: Dr: Acct 0674 - RIGHT-TO-USE SBITA LIABILITY
C62: Cr. Acct 0651 - RIGHT-TO-USE SBITA LIABILITY (CURRENT PORTION LT) | K62: =J61 -> 0
B63: NOTE: This is an annual accrual. The RTU SBITA Liability - Current portion will be added back to the RTU SBITA Liability in entry #0 when reestablishing the beginning balances next year. | J63: =ROUND(SUM(J61:J61),2) -> 0 | K63: =ROUND(SUM(K62),2) -> 0 | L63: =IF(J63=K63,"<- Debits and Credits equal each other.","<- Debits and Credits do not equal each other.") -> <- Debits and Credits equal each other.
A66: Remove SBITA Asset at the End of the Subscription Term (only at the end of the subscription term)
A67: 7 | B67: Record entry to write off the SBITA asset and accumulated amortization at the end of the subscription term.
B68: Dr: Acct 0475 - ACCUMULATED AMORTIZATION - RIGHT-TO-USE SBITA
C69: Cr: Acct 0480 - RIGHT-TO-USE SBITA - AMORTIZABLE | K69: =J68 -> 0
J70: =SUM(J68) -> 0 | K70: =SUM(K69) -> 0 | L70: =IF(J70=K70,"<- Debits and Credits equal each other.","<- Debits and Credits do not equal each other.") -> <- Debits and Credits equal each other.
B72: SBITA ASSET (Acct 0480) SHOULD BE INCLUDED AS "DEDUCTIONS" ON REPORT 18.
A74: Record SBITA Remeasurement and Modifications (only if a significant modification occurred during the fiscal year)
A75: 8 | B75: Record early termination of SBITA contract or SBITA modifications to decrease in the RTU SBITA asset.
B76: Cr: Acct 0674 - RIGHT-TO-USE SBITA LIABILITY
B77: Dr: Acct 0475 - ACCUMULATED AMORTIZATION - RIGHT-TO-USE SBITA
B78: =VLOOKUP($F$8,'Drop Down Menus'!$D$2:$G$10,4,FALSE) -> Cr: Acct 0820 - NAT RES & ENVIRON (GAAP ADJ)
C79: Cr: Acct 0480 - RIGHT-TO-USE SBITA - AMORTIZABLE
C80: =VLOOKUP($F$8,'Drop Down Menus'!$D$2:$G$10,4,FALSE) -> Cr: Acct 0820 - NAT RES & ENVIRON (GAAP ADJ)
J81: =ROUND(SUM(J76:J78),2) -> 0 | K81: =ROUND(SUM(K79:K80),2) -> 0 | L81: =IF(J81=K81,"<- Debits and Credits equal each other.","<- Debits and Credits do not equal each other.") -> <- Debits and Credits equal each other.
A83: 9 | B83: Record SBITA modifications to increase in the RTU SBITA asset.
B84: Dr: Acct 0480 - RIGHT-TO-USE SBITA - AMORTIZABLE
C85: Cr: Acct 0674 - RIGHT-TO-USE SBITA LIABILITY
J86: =SUM(J84) -> 0 | K86: =SUM(K85) -> 0 | L86: =IF(J86=K86,"<- Debits and Credits equal each other.","<- Debits and Credits do not equal each other.") -> <- Debits and Credits equal each other.
B88: NOTE: Please check the instructions for remeasurement and modifications on the SCO website.
D92: Informational - Ending Balances of Assets and Liabilities
K93: Debit (Credit)
D94: Acct 0480 - RIGHT-TO-USE SBITA - AMORTIZABLE | K94: =+J15+J34-K69+J76-K85 -> 1437815
D95: Acct 0475 - ACCUMULATED AMORTIZATION - RIGHT-TO-USE SBITA | K95: =-K18-K46+J68+J77 -> -40422
D96: Acct 0674 - RIGHT-TO-USE SBITA LIABILITY | K96: =-K19-K37+J56+J61+J76-K85 -> 0
D97: Acct 0651 - RIGHT-TO-USE SBITA LIABILITY (CURRENT PORTION LT) | K97: =-K62 -> 0

Sheet Department Note Disclosure
A1: GASB 96 - SBITA Note Disclosure Form ( Submit one form for the department to the SCO annually)
A3: Note: There are three tables of note disclosures on this form —1) governmental funds, 2) proprietary - internal service funds, and 3) proprietary - enterprise funds. Complete all applicable tables before submitting to the SCO.
A4: Manually complete every yellow field in this worksheet—there are no automatically calculated cells in this worksheet.
A5: Complete the fields below using aggregated and summarized information from all of your department's completed contract template forms.
A7: The fields in this worksheet should contain the sums of the department's contracts' corresponding information in their note disclosure worksheets.
A10: I. Governmental Funds
A11: Fiscal Year: | B11: 2022–2023
A12: Org Code/Business Unit: | B12: 3600
A13: Reporting Department Name: | B13: Department of Fish and Wildlife
A14: The below information must be entered manually.
B15: Principal Payments | C15: Interest Payments | D15: ="All of the below questions are for Fiscal Year "&$B$11&":" -> All of the below questions are for Fiscal Year 2022–2023:
A16: =RIGHT(B11,4)&"–"&RIGHT(B11,4)+1 -> 2023–2024 | B16: 0 | C16: 0 | D16: 1. Did your SBITAs have any variable payments which ARE NOT included in the measurement of the subscription liability?
A17: =LEFT(A16,4)+1&"–"&RIGHT(A16,4)+1 -> 2024–2025
A18: =LEFT(A17,4)+1&"–"&RIGHT(A17,4)+1 -> 2025–2026 | D18: No
A19: =LEFT(A18,4)+1&"–"&RIGHT(A18,4)+1 -> 2026–2027 | D19: ="If yes, record the dollar amount of variable payments below for fiscal year "&$B$11&":" -> If yes, record the dollar amount of variable payments below for fiscal year 2022–2023:
A20: =LEFT(A19,4)+1&"–"&RIGHT(A19,4)+1 -> 2027–2028 | D20: 0
A21: =LEFT(A20,4)+1&"–"&RIGHT(A20,4)+5 -> 2028–2033 | D21: ="2. Record the dollar amount of any other payments for your SBITAs, such as termination penalties, not previously recorded in the payment schedule for fiscal year "&$B$11&":" -> 2. Record the dollar amount of any other payments for your SBITAs, such as termination penalties, not previously recorded in the payment schedule for fiscal year 2022–2023:
A22: =LEFT(A21,4)+5&"–"&RIGHT(A21,4)+5 -> 2033–2038
A23: =LEFT(A22,4)+5&"–"&RIGHT(A22,4)+5 -> 2038–2043 | D23: 0
A24: =LEFT(A23,4)+5&"–"&RIGHT(A23,4)+5 -> 2043–2048 | D24: ="3. Did you receive any SBITA incentives from the SBITA vendor (not already included in the SBITA measurement) during fiscal year "&$B$11&"? If so, record the amount below:" -> 3. Did you receive any SBITA incentives from the SBITA vendor (not already included in the SBITA measurement) during fiscal year 2022–2023? If so, record the amount below:
A25: =LEFT(A24,4)+5&"–"&RIGHT(A24,4)+5 -> 2048–2053
A26: =LEFT(A25,4)+5&"–"&RIGHT(A25,4)+5 -> 2053–2058 | D26: 0
A27: =LEFT(A26,4)+5&"–"&RIGHT(A26,4)+5 -> 2058–2063 | D27: ="4. Are there any SBITA commitments known that have yet to commence as of June 30, "&RIGHT($B$11,4)&"?" -> 4. Are there any SBITA commitments known that have yet to commence as of June 30, 2023?
A28: =LEFT(A27,4)+5&"–"&RIGHT(A27,4)+5 -> 2063–2068
A29: =LEFT(A28,4)+5&"–"&RIGHT(A28,4)+5 -> 2068–2073 | D29: No
A30: =LEFT(A29,4)+5&"–"&RIGHT(A29,4)+5 -> 2073–2078 | D30: ="If yes, record the dollar amount of any SBITA commitments not commenced below for fiscal year "&$A$16&":" -> If yes, record the dollar amount of any SBITA commitments not commenced below for fiscal year 2023–2024:
A31: =LEFT(A30,4)+5&"–"&RIGHT(A30,4)+5 -> 2078–2083
A32: =LEFT(A31,4)+5&"–"&RIGHT(A31,4)+5 -> 2083–2088 | D32: 0
A33: =LEFT(A32,4)+5&"–"&RIGHT(A32,4)+5 -> 2088–2093
A34: =LEFT(A33,4)+5&"–"&RIGHT(A33,4)+5 -> 2093–2098
A35: =LEFT(A34,4)+5&"–"&RIGHT(A34,4)+5 -> 2098–2103
A36: =LEFT(A35,4)+5&"–"&RIGHT(A35,4)+5 -> 2103–2108
A37: =LEFT(A36,4)+5&"–"&RIGHT(A36,4)+5 -> 2108–2113
A38: =LEFT(A37,4)+5&"–"&RIGHT(A37,4)+5 -> 2113–2118
A39: =LEFT(A38,4)+5&"–"&RIGHT(A38,4)+5 -> 2118–2123
A41: II. Proprietary - Internal Service Funds
A42: Fiscal Year: | B42: =B11 -> 2022–2023
A43: Org Code/Business Unit: | B43: =B12 -> 3600
A44: Reporting Department Name: | B44: =B13 -> Department of Fish and Wildlife
A45: The below information must be entered manually.
B46: Principal Payments | C46: Interest Payments | D46: ="All of the below questions are for Fiscal Year "&$B$11&":" -> All of the below questions are for Fiscal Year 2022–2023:
A47: =RIGHT(B42,4)&"–"&RIGHT(B42,4)+1 -> 2023–2024 | D47: 1. Did your SBITAs have any variable payments which ARE NOT included in the measurement of the subscription liability?
A48: =LEFT(A47,4)+1&"–"&RIGHT(A47,4)+1 -> 2024–2025
A49: =LEFT(A48,4)+1&"–"&RIGHT(A48,4)+1 -> 2025–2026
A50: =LEFT(A49,4)+1&"–"&RIGHT(A49,4)+1 -> 2026–2027 | D50: ="If yes, record the dollar amount of variable payments below for fiscal year "&$B$11&":" -> If yes, record the dollar amount of variable payments below for fiscal year 2022–2023:
A51: =LEFT(A50,4)+1&"–"&RIGHT(A50,4)+1 -> 2027–2028
A52: =LEFT(A51,4)+1&"–"&RIGHT(A51,4)+5 -> 2028–2033 | D52: ="2. Record the dollar amount of any other payments for your SBITAs, such as termination penalties, not previously recorded in the payment schedule for fiscal year "&$B$11&":" -> 2. Record the dollar amount of any other payments for your SBITAs, such as termination penalties, not previously recorded in the payment schedule for fiscal year 2022–2023:
A53: =LEFT(A52,4)+5&"–"&RIGHT(A52,4)+5 -> 2033–2038
A54: =LEFT(A53,4)+5&"–"&RIGHT(A53,4)+5 -> 2038–2043
A55: =LEFT(A54,4)+5&"–"&RIGHT(A54,4)+5 -> 2043–2048 | D55: ="3. Did you receive any SBITA incentives from the SBITA vendor (not already included in the SBITA measurement) during fiscal year "&$B$11&"? If so, record the amount below:" -> 3. Did you receive any SBITA incentives from the SBITA vendor (not already included in the SBITA measurement) during fiscal year 2022–2023? If so, record the amount below:
A56: =LEFT(A55,4)+5&"–"&RIGHT(A55,4)+5 -> 2048–2053
A57: =LEFT(A56,4)+5&"–"&RIGHT(A56,4)+5 -> 2053–2058
A58: =LEFT(A57,4)+5&"–"&RIGHT(A57,4)+5 -> 2058–2063 | D58: ="4. Are there any SBITA commitments known that have yet to commence as of June 30, "&RIGHT($B$11,4)&"?" -> 4. Are there any SBITA commitments known that have yet to commence as of June 30, 2023?
A59: =LEFT(A58,4)+5&"–"&RIGHT(A58,4)+5 -> 2063–2068
A60: =LEFT(A59,4)+5&"–"&RIGHT(A59,4)+5 -> 2068–2073
A61: =LEFT(A60,4)+5&"–"&RIGHT(A60,4)+5 -> 2073–2078 | D61: ="If yes, record the dollar amount of any SBITA commitments not commenced below for fiscal year "&$A$16&":" -> If yes, record the dollar amount of any SBITA commitments not commenced below for fiscal year 2023–2024:
A62: =LEFT(A61,4)+5&"–"&RIGHT(A61,4)+5 -> 2078–2083
A63: =LEFT(A62,4)+5&"–"&RIGHT(A62,4)+5 -> 2083–2088
A64: =LEFT(A63,4)+5&"–"&RIGHT(A63,4)+5 -> 2088–2093
A65: =LEFT(A64,4)+5&"–"&RIGHT(A64,4)+5 -> 2093–2098
A66: =LEFT(A65,4)+5&"–"&RIGHT(A65,4)+5 -> 2098–2103
A67: =LEFT(A66,4)+5&"–"&RIGHT(A66,4)+5 -> 2103–2108
A68: =LEFT(A67,4)+5&"–"&RIGHT(A67,4)+5 -> 2108–2113
A69: =LEFT(A68,4)+5&"–"&RIGHT(A68,4)+5 -> 2113–2118
A70: =LEFT(A69,4)+5&"–"&RIGHT(A69,4)+5 -> 2118–2123
A72: III. Proprietary - Enterprise Funds
A73: Fiscal Year: | B73: =B11 -> 2022–2023
A74: Org Code/Business Unit: | B74: =B12 -> 3600
A75: Reporting Department Name: | B75: =B13 -> Department of Fish and Wildlife
A76: The below information must be entered manually.
B77: Principal Payments | C77: Interest Payments | D77: ="All of the below questions are for Fiscal Year "&$B$11&":" -> All of the below questions are for Fiscal Year 2022–2023:
A78: =RIGHT(B73,4)&"–"&RIGHT(B73,4)+1 -> 2023–2024 | D78: 1. Did your SBITAs have any variable payments which ARE NOT included in the measurement of the subscription liability?
A79: =LEFT(A78,4)+1&"–"&RIGHT(A78,4)+1 -> 2024–2025
A80: =LEFT(A79,4)+1&"–"&RIGHT(A79,4)+1 -> 2025–2026
A81: =LEFT(A80,4)+1&"–"&RIGHT(A80,4)+1 -> 2026–2027 | D81: ="If yes, record the dollar amount of variable payments below for fiscal year "&$B$11&":" -> If yes, record the dollar amount of variable payments below for fiscal year 2022–2023:
A82: =LEFT(A81,4)+1&"–"&RIGHT(A81,4)+1 -> 2027–2028
A83: =LEFT(A82,4)+1&"–"&RIGHT(A82,4)+5 -> 2028–2033 | D83: ="2. Record the dollar amount of any other payments for your SBITAs, such as termination penalties, not previously recorded in the payment schedule for fiscal year "&$B$11&":" -> 2. Record the dollar amount of any other payments for your SBITAs, such as termination penalties, not previously recorded in the payment schedule for fiscal year 2022–2023:
A84: =LEFT(A83,4)+5&"–"&RIGHT(A83,4)+5 -> 2033–2038
A85: =LEFT(A84,4)+5&"–"&RIGHT(A84,4)+5 -> 2038–2043
A86: =LEFT(A85,4)+5&"–"&RIGHT(A85,4)+5 -> 2043–2048 | D86: ="3. Did you receive any SBITA incentives from the SBITA vendor (not already included in the SBITA measurement) during fiscal year "&$B$11&"? If so, record the amount below:" -> 3. Did you receive any SBITA incentives from the SBITA vendor (not already included in the SBITA measurement) during fiscal year 2022–2023? If so, record the amount below:
A87: =LEFT(A86,4)+5&"–"&RIGHT(A86,4)+5 -> 2048–2053
A88: =LEFT(A87,4)+5&"–"&RIGHT(A87,4)+5 -> 2053–2058
A89: =LEFT(A88,4)+5&"–"&RIGHT(A88,4)+5 -> 2058–2063 | D89: ="4. Are there any SBITA commitments known that have yet to commence as of June 30, "&RIGHT($B$11,4)&"?" -> 4. Are there any SBITA commitments known that have yet to commence as of June 30, 2023?
A90: =LEFT(A89,4)+5&"–"&RIGHT(A89,4)+5 -> 2063–2068
A91: =LEFT(A90,4)+5&"–"&RIGHT(A90,4)+5 -> 2068–2073
A92: =LEFT(A91,4)+5&"–"&RIGHT(A91,4)+5 -> 2073–2078 | D92: ="If yes, record the dollar amount of any SBITA commitments not commenced below for fiscal year "&$A$16&":" -> If yes, record the dollar amount of any SBITA commitments not commenced below for fiscal year 2023–2024:
A93: =LEFT(A92,4)+5&"–"&RIGHT(A92,4)+5 -> 2078–2083
A94: =LEFT(A93,4)+5&"–"&RIGHT(A93,4)+5 -> 2083–2088
A95: =LEFT(A94,4)+5&"–"&RIGHT(A94,4)+5 -> 2088–2093
A96: =LEFT(A95,4)+5&"–"&RIGHT(A95,4)+5 -> 2093–2098
A97: =LEFT(A96,4)+5&"–"&RIGHT(A96,4)+5 -> 2098–2103
A98: =LEFT(A97,4)+5&"–"&RIGHT(A97,4)+5 -> 2103–2108
A99: =LEFT(A98,4)+5&"–"&RIGHT(A98,4)+5 -> 2108–2113
A100: =LEFT(A99,4)+5&"–"&RIGHT(A99,4)+5 -> 2113–2118
A101: =LEFT(A100,4)+5&"–"&RIGHT(A100,4)+5 -> 2118–2123

Sheet SBITA Liabilities
G3: Schedule of Changes in SBITA Liabilities
G4: ="FY "&'Department Note Disclosure'!$B$11 -> FY 2022–2023
G5: ="Business Unit " &'Fund 0200 Journal Entries'!$F$5&" "&'Fund 0200 Journal Entries'!$F$4 -> Business Unit 3600 Department of Fish and Wildlife
C7: Source: Tab "Fund #### Journal Entries" | F7: ENTRY #0 | H7: ENTRY #2 | J7: ENTRY #5 | N7: ENTRY #6
F8: ="Balance July 1, "&LEFT('Fund 0200 Journal Entries'!$F$3,4) -> Balance July 1, 2022 | H8: Additions | J8: Deductions | L8: ="Balance June 30, "&RIGHT('Fund 0200 Journal Entries'!$F$3,4) -> Balance June 30, 2023 | N8: Due Within One Year | P8: Noncurrent Liabilities
C9: Governmental Funds
D10: SBITA Liability | F10: =IF('Fund 0200 Journal Entries'!$F$7="Governmental Fund",'Fund 0200 Journal Entries'!$K$19,0) -> 689814 | H10: =IF('Fund 0200 Journal Entries'!$F$7="Governmental Fund",'Fund 0200 Journal Entries'!$K$37,0) -> 0 | J10: =IF('Fund 0200 Journal Entries'!$F$7="Governmental Fund",'Fund 0200 Journal Entries'!$J$56,0) -> 689814 | L10: =SUM(F10+H10-J10) -> 0 | N10: =IF('Fund 0200 Journal Entries'!$F$7="Governmental Fund",'Fund 0200 Journal Entries'!$J$61,0) -> 0 | P10: =L10-N10 -> 0
C11: Total Governmental Funds | F11: =SUM(F10:F10) -> 689814 | H11: =SUM(H10:H10) -> 0 | J11: =SUM(J10:J10) -> 689814 | L11: =SUM(L10:L10) -> 0 | N11: =SUM(N10:N10) -> 0 | P11: =SUM(P10:P10) -> 0
C13: Proprietary - Internal Service Funds
D14: SBITA Liability | F14: =IF('Fund 0200 Journal Entries'!$F$7="Proprietary - Internal Service Fund",'Fund 0200 Journal Entries'!$K$19,0) -> 0 | H14: =IF('Fund 0200 Journal Entries'!$F$7="Proprietary - Internal Service Fund",'Fund 0200 Journal Entries'!$K$37,0) -> 0 | J14: =IF('Fund 0200 Journal Entries'!$F$7="Proprietary - Internal Service Fund",'Fund 0200 Journal Entries'!$J$56,0) -> 0 | L14: =SUM(F14+H14-J14) -> 0 | N14: =IF('Fund 0200 Journal Entries'!$F$7="Proprietary - Internal Service Fund",'Fund 0200 Journal Entries'!$J$61,0) -> 0 | P14: =L14-N14 -> 0
C15: Total Proprietary - Internal Service Funds | F15: =SUM(F14:F14) -> 0 | H15: =SUM(H14:H14) -> 0 | J15: =SUM(J14:J14) -> 0 | L15: =SUM(L14:L14) -> 0 | N15: =SUM(N14:N14) -> 0 | P15: =SUM(P14:P14) -> 0
C17: Proprietary - Enterprise Funds
D18: SBITA Liability | F18: =IF('Fund 0200 Journal Entries'!$F$7="Proprietary - Enterprise Fund",'Fund 0200 Journal Entries'!$K$19,0) -> 0 | H18: =IF('Fund 0200 Journal Entries'!$F$7="Proprietary - Enterprise Fund",'Fund 0200 Journal Entries'!$K$37,0) -> 0 | J18: =IF('Fund 0200 Journal Entries'!$F$7="Proprietary - Enterprise Fund",'Fund 0200 Journal Entries'!$J$56,0) -> 0 | L18: =SUM(F18+H18-J18) -> 0 | N18: =IF('Fund 0200 Journal Entries'!$F$7="Proprietary - Enterprise Fund",'Fund 0200 Journal Entries'!$J$61,0) -> 0 | P18: =L18-N18 -> 0
C19: Total Proprietary - Enterprise Funds | F19: =SUM(F18:F18) -> 0 | H19: =SUM(H18:H18) -> 0 | J19: =SUM(J18:J18) -> 0 | L19: =SUM(L18:L18) -> 0 | N19: =SUM(N18:N18) -> 0 | P19: =SUM(P18:P18) -> 0
A25: NOTE: The yellow highlighted fields have formulas embedded to generate the amounts automatically based on inputs (Acct 0674 - RIGHT-TO-USE SBITA LIABILITY) in the journal entries tab. If multiple funds are included in this Workbook, overwrite the yellow highlighted fields to update the amounts.

Sheet Check Figures 
A1: GASB Statement No. 96 Subscription-Based Information Technology Arrangements
A2: Check Figures
A4: Purpose:
A5: The purpose of this workbook is to check the figures entered in the journal entries reconcile to the future principal payments disclosed and the changes in the schedule of the SBITA liabilities.
A8: NOTE: The yellow highlighted fields have formulas embedded to generate the amounts automatically based on inputs in the journal entries tab. If multiple funds are included in this Workbook, manually complete every yellow field by consolidating the entries by fund type (Governmental Fund, Proprietary - Internal Service Fund, and Proprietary - Enterprise Fund).
A11: 1. To reconcile the journal entries of RTU SBITA Liability with the principal payments in Note Disclosure.
B12: a) Governmental Funds
B14: Journal Entries (Acct 0674 - RIGHT-TO-USE SBITA LIABILITY) | J14: Department Note Disclosure
B15: Entry #0 | C15: + | D15: Entry #2 | E15: - | F15: Entry #5 | J15: Sum Principal Payments | L15: Variance
B16: =IF('Fund 0200 Journal Entries'!$F$7="Governmental Fund",ROUND('Fund 0200 Journal Entries'!$K$19,0),0) -> 689814 | C16: + | D16: =IF('Fund 0200 Journal Entries'!$F$7="Governmental Fund",ROUND('Fund 0200 Journal Entries'!$K$37,0),0) -> 0 | E16: - | F16: =IF('Fund 0200 Journal Entries'!$F$7="Governmental Fund",ROUND('Fund 0200 Journal Entries'!$J$56,0),0) -> 689814 | G16: = | H16: =+B16+D16-F16 -> 0 | J16: =ROUND(SUM('Department Note Disclosure'!$B$16:$B$39),0) -> 0 | L16: =H16-J16 -> 0
D17: =IF(OR(L16>0, (L16<0)), "Please review and correct the variance.","")
B19: b) Proprietary - Internal Service Funds
B21: Journal Entries (Acct 0674 - RIGHT-TO-USE SBITA LIABILITY) | J21: Department Note Disclosure
B22: Entry #0 | C22: + | D22: Entry #2 | E22: - | F22: Entry #5 | J22: Sum Principal Payments | L22: Variance
B23: =IF('Fund 0200 Journal Entries'!$F$7="Proprietary - Internal Service Fund",ROUND('Fund 0200 Journal Entries'!$K$19,0),0) -> 0 | C23: + | D23: =IF('Fund 0200 Journal Entries'!$F$7="Proprietary - Internal Service Fund",ROUND('Fund 0200 Journal Entries'!$K$37,0),0) -> 0 | E23: - | F23: =IF('Fund 0200 Journal Entries'!$F$7="Proprietary - Internal Service Fund",ROUND('Fund 0200 Journal Entries'!$J$56,0),0) -> 0 | G23: = | H23: =+B23+D23-F23 -> 0 | J23: =ROUND(SUM('Department Note Disclosure'!$B$47:$B$70),0) -> 0 | L23: =H23-J23 -> 0
D25: =IF(OR(L23>0, (L23<0)), "Please review and correct the variance.","")
B27: c) Proprietary - Enterprise Funds
B29: Journal Entries (Acct 0674 - RIGHT-TO-USE SBITA LIABILITY) | J29: Department Note Disclosure
B30: Entry #0 | C30: + | D30: Entry #2 | E30: - | F30: Entry #5 | J30: Sum Principal Payments | L30: Variance
B31: =IF('Fund 0200 Journal Entries'!$F$7="Proprietary - Enterprise Fund",ROUND('Fund 0200 Journal Entries'!$K$19,0),0) -> 0 | C31: + | D31: =IF('Fund 0200 Journal Entries'!$F$7="Proprietary - Enterprise Fund",ROUND('Fund 0200 Journal Entries'!$K$37,0),0) -> 0 | E31: - | F31: =IF('Fund 0200 Journal Entries'!$F$7="Proprietary - Enterprise Fund",ROUND('Fund 0200 Journal Entries'!$J$56,0),0) -> 0 | G31: = | H31: =+B31+D31-F31 -> 0 | J31: =ROUND(SUM('Department Note Disclosure'!$B$78:$B$101),0) -> 0 | L31: =H31-J31 -> 0
D32: =IF(OR(L31>0, (L31<0)), "Please review and correct the variance.","")
A34: 2. To match the journal entry to the principal amount due in the next fiscal year in Note Disclosure.
B35: a) Governmental Funds
B37: Journal Entries (Acct 0674 - RIGHT-TO-USE SBITA LIABILITY) | J37: Department Note Disclosure
F38: Entry #6 | J38: ='Department Note Disclosure'!$A$16&" Principal Payments" -> 2023–2024 Principal Payments | L38: Variance
F39: =IF('Fund 0200 Journal Entries'!$F$7="Governmental Fund",ROUND('Fund 0200 Journal Entries'!$K$62,0),0) -> 0 | J39: =ROUND('Department Note Disclosure'!$B$16,0) -> 0 | L39: =F39-J39 -> 0
D40: =IF(OR(L39>0, (L39<0)), "Please review and correct the variance.","")
B42: b) Proprietary - Internal Service Funds
B44: Journal Entries (Acct 0674 - RIGHT-TO-USE SBITA LIABILITY) | J44: Department Note Disclosure
F45: Entry #6 | J45: ='Department Note Disclosure'!$A$47&" Principal Payments" -> 2023–2024 Principal Payments | L45: Variance
F46: =IF('Fund 0200 Journal Entries'!$F$7="Proprietary - Internal Service Fund",ROUND('Fund 0200 Journal Entries'!$K$62,0),0) -> 0 | J46: =ROUND('Department Note Disclosure'!$B$47,0) -> 0 | L46: =F46-J46 -> 0
D47: =IF(OR(L46>0, (L46<0)), "Please review and correct the variance.","")
B49: c) Proprietary - Enterprise Funds
B51: Journal Entries (Acct 0674 - RIGHT-TO-USE SBITA LIABILITY) | J51: Department Note Disclosure
F52: Entry #6 | J52: ='Department Note Disclosure'!$A$47&" Principal Payments" -> 2023–2024 Principal Payments | L52: Variance
F53: =IF('Fund 0200 Journal Entries'!$F$7="Proprietary - Enterprise Fund",ROUND('Fund 0200 Journal Entries'!$K$62,0),0) -> 0 | J53: =ROUND('Department Note Disclosure'!$B$78,0) -> 0 | L53: =F53-J53 -> 0
D54: =IF(OR(L53>0, (L53<0)), "Please review and correct the variance.","")
A56: 3. To reconcile the journal entries of RTU SBITA Liability with the schedule of changes in SBITA Liabilities.
B57: a) Governmental Funds
B59: Journal Entries (Acct 0674 - RIGHT-TO-USE SBITA LIABILITY) | H59: Schedule of Changes in SBITA Liabilities
L60: Variance
B61: Entry #0 | D61: =$B$16 -> 689814 | H61: ="Balance July 1, "&LEFT('Fund 0200 Journal Entries'!$F$3,4) -> Balance July 1, 2022 | J61: =ROUND('SBITA Liabilities'!$F$10,0) -> 689814 | L61: =D61-J61 -> 0
B62: Entry #2 | D62: =$D$16 -> 0 | H62: Additions | J62: =ROUND('SBITA Liabilities'!$H$10,0) -> 0 | L62: =D62-J62 -> 0
B63: Entry #5 | D63: =$F$16 -> 689814 | H63: Deductions | J63: =ROUND('SBITA Liabilities'!$J$10,0) -> 689814 | L63: =D63-J63 -> 0
B64: Entry #6 | D64: =$F$39 -> 0 | H64: Due Within One Year | J64: =ROUND('SBITA Liabilities'!$N$10,0) -> 0 | L64: =D64-J64 -> 0
D65: =IF(OR(L61>0, (L61<0),L62>0,L62<0,L63>0,L63<0,L64>0,L64<0), "Please review and correct the variance.","")
B67: b) Proprietary - Internal Service Funds
B69: Journal Entries (Acct 0674 - RIGHT-TO-USE SBITA LIABILITY) | H69: Schedule of Changes in SBITA Liabilities
L70: Variance
B71: Entry #0 | D71: =$B$23 -> 0 | H71: ="Balance July 1, "&LEFT('Fund 0200 Journal Entries'!$F$3,4) -> Balance July 1, 2022 | J71: =ROUND('SBITA Liabilities'!$F$14,0) -> 0 | L71: =D71-J71 -> 0
B72: Entry #2 | D72: =D23 -> 0 | H72: Additions | J72: =ROUND('SBITA Liabilities'!$H$14,0) -> 0 | L72: =D72-J72 -> 0
B73: Entry #5 | D73: =F23 -> 0 | H73: Deductions | J73: =ROUND('SBITA Liabilities'!$J$14,0) -> 0 | L73: =D73-J73 -> 0
B74: Entry #6 | D74: =F46 -> 0 | H74: Due Within One Year | J74: =ROUND('SBITA Liabilities'!$N$14,0) -> 0 | L74: =D74-J74 -> 0
D75: =IF(OR(L71>0, (L71<0),L72>0,L72<0,L73>0,L73<0,L74>0,L74<0), "Please review and correct the variance.","")
B77: c) Proprietary - Enterprise Funds
B79: Journal Entries (Acct 0674 - RIGHT-TO-USE SBITA LIABILITY) | H79: Schedule of Changes in SBITA Liabilities
L80: Variance
B81: Entry #0 | D81: =$B$31 -> 0 | H81: ="Balance July 1, "&LEFT('Fund 0200 Journal Entries'!$F$3,4) -> Balance July 1, 2022 | J81: =ROUND('SBITA Liabilities'!$F$18,0) -> 0 | L81: =D81-J81 -> 0
B82: Entry #2 | D82: =D31 -> 0 | H82: Additions | J82: =ROUND('SBITA Liabilities'!$H$18,0) -> 0 | L82: =D82-J82 -> 0
B83: Entry #5 | D83: =F31 -> 0 | H83: Deductions | J83: =ROUND('SBITA Liabilities'!$J$18,0) -> 0 | L83: =D83-J83 -> 0
B84: Entry #6 | D84: =F53 -> 0 | H84: Due Within One Year | J84: =ROUND('SBITA Liabilities'!$N$18,0) -> 0 | L84: =D84-J84 -> 0
D85: =IF(OR(L81>0, (L81<0),L82>0,L82<0,L83>0,L83<0,L84>0,L84<0), "Please review and correct the variance.","")

Sheet Drop Down Menus
A1: 2022–2023 | B1: Governmental Fund | C1: Yes | E1: Please select fund type above. | F1: Please select fund type above. | G1: Please select fund type above.
A2: 2023–2024 | B2: Proprietary - Internal Service Fund | C2: No | D2: GENERAL GOVERNMENT | E2: Dr: Acct 5808 - GENERAL GOV. (REV & EXP) | F2: Dr: Acct 0808 - GENERAL GOV. (GAAP ADJ) | G2: Cr: Acct 0808 - GENERAL GOV. (GAAP ADJ)
A3: 2024–2025 | B3: Proprietary - Enterprise Fund | D3: EDUCATION | E3: Dr: Acct 5810 - EDUCATION EXP (REV-EXP) | F3: Dr: Acct 0810 - EDUCATION EXP (GAAP ADJ) | G3: Cr: Acct 0810 - EDUCATION EXP (GAAP ADJ)
A4: 2025–2026 | D4: HEALTH AND HUMAN SERVICES | E4: Dr: Acct 5815 - HEALTH HM SRV & LAB (REV-EXP) | F4: Dr: Acct 0815 - HLTH&HUM SV SV.LAB(GAAP ADJ) | G4: Cr: Acct 0815 - HLTH&HUM SV SV.LAB(GAAP ADJ)
A5: 2026–2027 | D5: RESOURCES | E5: Dr: Acct 5820 - NATURL RSRCS & ENVIR (REV-EXP) | F5: Dr: Acct 0820 - NAT RES & ENVIRON (GAAP ADJ) | G5: Cr: Acct 0820 - NAT RES & ENVIRON (GAAP ADJ)
A6: 2027–2028 | D6: BUS, CONSUMER SERV, HOUSING | E6: Dr: Acct 5825 - BUS, CONS SERV, HS (REV-EXP) | F6: Dr: Acct 0825 - BUS, CONSUMER SERV, HOUSING | G6: Cr: Acct 0825 - BUS, CONSUMER SERV, HOUSING
A7: 2028–2029 | D7: TRANSPORTATION | E7: Dr: Acct 5830 - TRANSPORTATION (REV-EXP) | F7: Dr: Acct 0830 - TRANSPORTATION (GAAP ADJ) | G7: Cr: Acct 0830 - TRANSPORTATION (GAAP ADJ)
A8: 2029–2030 | D8: CORRECTIONS AND REHABILITATION | E8: Dr: Acct 5835 - CORRECTIONAL PROG. (REV-EXP) | F8: Dr: Acct 0835 - CORRECTIONS AND REHABILITATION | G8: Cr: Acct 0835 - CORRECTIONS AND REHABILITATION
A9: 2030–2031 | D9: PROPRIETARY FUND | E9: Dr: Acct 0870 - SERVICES & CHARGES (MG ADJ) | F9: Dr: Acct 0875 - DEPRECIATION/AMORTIZATION (MG ADJ) | G9: Cr: Acct 0870 - SERVICES & CHARGES (MG ADJ)
A10: 2031–2032 | D10: UNIDENTIFIED | E10: Dr: Acct 0XXX - FUNCTIONAL EXPENSE | F10: Dr: Acct 0XXX - FUNCTIONAL EXPENSE | G10: Cr: Acct 0XXX - FUNCTIONAL EXPENSE
A11: 2032–2033
A12: 2033–2034
A13: 2034–2035
A14: 2035–2036
A15: 2036–2037
A16: 2037–2038
A17: 2038–2039
A18: 2039–2040
A19: 2040–2041
A20: 2041–2042
A21: 2042–2043
A22: 2043–2044
... A101: 2022–2023

Sheet GAAP02Aindex
A1: Agency | B1: Title | C1: Hier1 | D1: Desc1 | E1: Desc2 | F1: Hier2 | G1: Hier3 | H1: Hier4 | I1: Hier5 | J1: EffectiveDate | K1: CancelDate
A2: 0000 | B2: BOND INTEREST AND REDEMPTION | C2: 9000 | D2: BOND INTEREST AND REDEMPTION | F2: 9030 | G2: 9600 | H2: 0000 | I2: 0000 | J2: 04/04/1984 | K2: 00/00/0000
A3: 0010 | B3: LEGISLATIVE, JUDICIAL AND EXEC | C3: 0808 | D3: GENERAL GOVERNMENT | F3: 0000 | G3: 0000 | H3: 0000 | I3: 0000 | J3: 07/11/2006 | K3: 00/00/0000
A4: 0015 | B4: ADD AGENCY TEST | C4: 0808 | D4: GENERAL GOVERNMENT | F4: 0000 | G4: 0000 | H4: 0000 | I4: 0000 | J4: 99/99/9999 | K4: 00/00/0000
A5: 0020 | B5: LEGISLATIVE | C5: 0808 | D5: GENERAL GOVERNMENT | F5: 0000 | G5: 0000 | H5: 0000 | I5: 0000 | J5: 99/99/9999 | K5: 00/00/0000
A6: 0100 | B6: LEGISLATURE | C6: 0808 | D6: GENERAL GOVERNMENT | F6: 0000 | G6: 0000 | H6: 0000 | I6: 0000 | J6: 99/99/9999 | K6: 00/00/0000
A7: 0110 | B7: SENATE | C7: 0808 | D7: GENERAL GOVERNMENT | F7: 0000 | G7: 0000 | H7: 0000 | I7: 0000 | J7: 06/26/1985 | K7: 00/00/0000
A8: 0120 | B8: ASSEMBLY | C8: 0808 | D8: GENERAL GOVERNMENT | F8: 0000 | G8: 0000 | H8: 0000 | I8: 0000 | J8: 06/26/1985 | K8: 00/00/0000
A9: 0130 | B9: LEGISLATIVE JOINT EXPENSES | C9: 0808 | D9: GENERAL GOVERNMENT | F9: 0000 | G9: 0000 | H9: 0000 | I9: 0000 | J9: 06/26/1985 | K9: 00/00/0000
A10: 0150 | B10: CONTRIB TO LEGIS RETIRE FUND | C10: 0808 | D10: GENERAL GOVERNMENT | F10: 0000 | G10: 0000 | H10: 0000 | I10: 0000 | J10: 07/11/2006 | K10: 00/00/0000
A11: 0155 | B11: AUDITOR GENERAL OFFICE | C11: 0808 | D11: GENERAL GOVERNMENT | F11: 0000 | G11: 0000 | H11: 0000 | I11: 0000 | J11: 99/99/9999 | K11: 00/00/0000
A12: 0160 | B12: LEGISLATIVE COUNSEL BUREAU | C12: 0808 | D12: GENERAL GOVERNMENT | F12: 0000 | G12: 0000 | H12: 0000 | I12: 0000 | J12: 04/04/1984 | K12: 00/00/0000
A13: 0170 | B13: CA LAW REVISION COMMISSION | C13: 0808 | D13: GENERAL GOVERNMENT | F13: 0000 | G13: 0000 | H13: 0000 | I13: 0000 | J13: 99/99/9999 | K13: 07/01/1985
... A190: 2140 | B190: STATE BANKING DEPARTMENT | C190: 0825 | D190: BUS, CONSUMER SERV, HOUSING | F190: 0000 | G190: 0000 | H190: 0000 | I190: 0000 | J190: 12/21/2016 | K190: 00/00/0000
A191: 2150 | B191: FINANCIAL INSTITUTIONS | C191: 0825 | D191: ADD BACK TO POST PY REVERSAL | E191: DELETE 16/17 | F191: 0000 | G191: 0000 | H191: 0000 | I191: 0000 | J191: 08/18/2016 | K191: 00/00/0000
A192: 2180 | B192: DEPART OF CORPORATIONS | C192: 0825 | D192: ADD BACK TO POST PY REVERSAL | E192: DELETE 16/17 | F192: 0000 | G192: 0000 | H192: 0000 | I192: 0000 | J192: 08/24/2016 | K192: 00/00/0000
A193: 2190 | B193: MAJOR MEDICAL INSURANCE BOARD | C193: 0825 | D193: BUS, CONSUMER SERV, HOUSING | F193: 0000 | G193: 0000 | H193: 0000 | I193: 0000 | J193: 12/21/2016 | K193: 00/00/0000
A194: 2200 | B194: DEPARTMENT OF COMMERCE | C194: 0825 | D194: BUS, CONSUMER SERV, HOUSING | F194: 0000 | G194: 0000 | H194: 0000 | I194: 0000 | J194: 12/21/2016 | K194: 00/00/0000
A195: 2220 | B195: OFFICE OF SMALL BUSINESS DEVEL | C195: 0825 | D195: BUS, CONSUMER SERV, HOUSING | F195: 0000 | G195: 0000 | H195: 0000 | I195: 0000 | J195: 12/21/2016 | K195: 00/00/0000
A196: 2222 | B196: ST ASST FD FOR ENTERPRISE | C196: 0825 | D196: BUS, CONSUMER SERV, HOUSING | F196: 0000 | G196: 0000 | H196: 0000 | I196: 0000 | J196: 12/21/2016 | K196: 00/00/0000
A197: 2225 | B197: UNITARY FUND PROGRAMS | C197: 0825 | D197: BUS, CONSUMER SERV, HOUSING | F197: 0000 | G197: 0000 | H197: 0000 | I197: 0000 | J197: 12/21/2016 | K197: 00/00/0000
A198: 2230 | B198: CA INDTRL DEV FINCL ADVRY COMM | C198: 0825 | D198: BUS, CONSUMER SERV, HOUSING | F198: 0000 | G198: 0000 | H198: 0000 | I198: 0000 | J198: 12/21/2016 | K198: 07/01/1985
A199: 2235 | B199: CA HOME LOAN MORTGAGE ASSN | C199: 0825 | D199: BUS, CONSUMER SERV, HOUSING | F199: 0000 | G199: 0000 | H199: 0000 | I199: 0000 | J199: 12/21/2016 | K199: 00/00/0000
A200: 2240 | B200: DEPT-HOUSING/COMMUNITY DEVEL | C200: 0825 | D200: BUS, CONSUMER SERV, HOUSING | F200: 0000 | G200: 0000 | H200: 0000 | I200: 0000 | J200: 12/12/2016 | K200: 00/00/1999
A201: 2245 | B201: CALIFORNIA HOUSING FINANCE AGY | C201: 0825 | D201: BUS, CONSUMER SERV, HOUSING | F201: 0000 | G201: 0000 | H201: 0000 | I201: 0000 | J201: 08/19/2016 | K201: 00/00/0000
A202: 2265 | B202: CALIFORNIA HOUSING INSURANCE | C202: 0825 | D202: BUS, CONSUMER SERV, HOUSING | F202: 0000 | G202: 0000 | H202: 0000 | I202: 0000 | J202: 12/21/2016 | K202: 00/00/0000
A203: 2270 | B203: MORTGAGE BOND ALLOC COMMITTEE | C203: 0825 | D203: BUS, CONSUMER SERV, HOUSING | F203: 0000 | G203: 0000 | H203: 0000 | I203: 0000 | J203: 12/21/2016 | K203: 07/01/1985
A204: 2290 | B204: DEPARTMENT OF INSURANCE | C204: 0825 | D204: BUS, CONSUMER SERV, HOUSING | F204: 0000 | G204: 0000 | H204: 0000 | I204: 0000 | J204: 12/21/2016 | K204: 00/00/1999
... A214: 2670 | B214: BD OF PILOT COMMISSIONERS-SF | C214: 0830 | D214: TRANSPORTATION | F214: 0000 | G214: 0000 | H214: 0000 | I214: 0000 | J214: 08/03/2017 | K214: 00/00/0000
A215: 2700 | B215: OFFICE OF TRAFFIC SAFETY | C215: 0830 | D215: TRANSPORTATION | E215: MERGED W/0521-ADD 4 PY ACCR RV | F215: 0000 | G215: 0000 | H215: 0000 | I215: 0000 | J215: 09/28/2016 | K215: 00/00/0000
A216: 2720 | B216: DEPT OF CAL HIGHWAY PATROL | C216: 0830 | D216: TRANSPORTATION | F216: 0000 | G216: 0000 | H216: 0000 | I216: 0000 | J216: 10/28/2016 | K216: 00/00/1999
A217: 2740 | B217: DEPARTMENT OF MOTOR VEHICLES | C217: 0830 | D217: TRANSPORTATION | F217: 0000 | G217: 0000 | H217: 0000 | I217: 0000 | J217: 10/28/2016 | K217: 00/00/0000
A218: 2780 | B218: STEPHEN P TEALE DATA CENTER | C218: 0825 | D218: BUS, CONSUMER SERV, HOUSING | F218: 0000 | G218: 0000 | H218: 0000 | I218: 0000 | J218: 12/21/2016 | K218: 00/00/0000
A219: 2900 | B219: TRADE AND COMMERCE | C219: 0825 | D219: BUS, CONSUMER SERV, HOUSING | F219: 0000 | G219: 0000 | H219: 0000 | I219: 0000 | J219: 12/21/2016 | K219: 00/00/0000
A220: 2920 | B220: TECHNOLOGY TRADE & COMMERCE AG | C220: 0825 | D220: BUS, CONSUMER SERV, HOUSING | F220: 0000 | G220: 0000 | H220: 0000 | I220: 0000 | J220: 12/21/2016 | K220: 00/00/0000
A221: 3000 | B221: NATURAL RESOURCES | C221: 0820 | D221: RESOURCES | F221: 0000 | G221: 0000 | H221: 0000 | I221: 0000 | J221: 08/25/2010 | K221: 00/00/0000
A222: 3100 | B222: EXPOSITION PARK | C222: 0820 | D222: RESOURCES | F222: 0000 | G222: 0000 | H222: 0000 | I222: 0000 | J222: 10/17/2018 | K222: 00/00/0000
A223: 3105 | B223: CALIFORNIA AFRO-AMERICAN MUSEU | C223: 0820 | D223: RESOURCES | F223: 0000 | G223: 0000 | H223: 0000 | I223: 0000 | J223: 09/05/2014 | K223: 00/00/0000
A224: 3110 | B224: SPECIAL RESOURCES PROGRAMS | C224: 0820 | D224: RESOURCES | F224: 0000 | G224: 0000 | H224: 0000 | I224: 0000 | J224: 07/11/2006 | K224: 00/00/1999
A225: 3125 | B225: CALIF TAHOE CONSERVANCY | C225: 0820 | D225: RESOURCES | F225: 0000 | G225: 0000 | H225: 0000 | I225: 0000 | J225: 04/18/1988 | K225: 00/00/1999
A226: 3130 | B226: WATERWAYS MANAGEMENT PLANNING | C226: 0820 | D226: RESOURCES | F226: 0000 | G226: 0000 | H226: 0000 | I226: 0000 | J226: 99/99/9999 | K226: 00/00/0000
A227: 3140 | B227: SEA GRANT PROGRAM | C227: 0820 | D227: RESOURCES | F227: 0000 | G227: 0000 | H227: 0000 | I227: 0000 | J227: 99/99/9999 | K227: 00/00/0000
... A278: 4140 | B278: OFFICE OF HEALTH PLAN & DEV | C278: 0815 | D278: HEALTH AND HUMAN SERVICES | F278: 0000 | G278: 0000 | H278: 0000 | I278: 0000 | J278: 10/28/2016 | K278: 00/00/0000
A279: 4150 | B279: DEPT OF MANAGED HEALTH CARE | C279: 0815 | D279: HEALTH AND HUMAN SERVICES | E279: RENUMBERED FROM 2400 | F279: 0000 | G279: 0000 | H279: 0000 | I279: 0000 | J279: 10/28/2016 | K279: 00/00/0000
A280: 4170 | B280: DEPARTMENT OF AGING | C280: 0815 | D280: HEALTH AND HUMAN SERVICES | F280: 0000 | G280: 0000 | H280: 0000 | I280: 0000 | J280: 10/28/2016 | K280: 00/00/1999
A281: 4180 | B281: COMMISSION ON AGING | C281: 0815 | D281: HEALTH AND HUMAN SERVICES | F281: 0000 | G281: 0000 | H281: 0000 | I281: 0000 | J281: 10/28/2016 | K281: 00/00/1999
A282: 4185 | B282: CALIFORNIA SENIOR LEGISLATURE | C282: 0815 | D282: HEALTH AND HUMAN SERVICES | F282: 0000 | G282: 0000 | H282: 0000 | I282: 0000 | J282: 10/28/2016 | K282: 00/00/0000
A283: 4210 | B283: GOV COUNCIL DRUG/ALCOHOL ABUSE | C283: 0815 | D283: HEALTH AND HUMAN SERVICES | F283: 0000 | G283: 0000 | H283: 0000 | I283: 0000 | J283: 10/28/2016 | K283: 00/00/0000
A284: 4220 | B284: GOV ADV COM CHILD DEVEL PROG | C284: 0815 | D284: HEALTH AND HUMAN SERVICES | F284: 0000 | G284: 0000 | H284: 0000 | I284: 0000 | J284: 10/28/2016 | K284: 00/00/0000
A285: 4250 | B285: CA. CHILDREN AND FAMILIES COMM | C285: 0815 | D285: HEALTH AND HUMAN SERVICES | F285: 0000 | G285: 0000 | H285: 0000 | I285: 0000 | J285: 10/28/2016 | K285: 00/00/0000
A286: 4260 | B286: DEPARTMENT OF HEALTH CARE SVCS | C286: 0815 | D286: HEALTH AND HUMAN SERVICES | F286: 0000 | G286: 0000 | H286: 0000 | I286: 0000 | J286: 10/28/2016 | K286: 00/00/0000
A287: 4265 | B287: DEPARTMENT OF PUBLIC HEALTH | C287: 0815 | D287: HEALTH AND HUMAN SERVICES | F287: 0000 | G287: 0000 | H287: 0000 | I287: 0000 | J287: 10/28/2016 | K287: 00/00/0000
A288: 4270 | B288: CAL MED ASSISTANCE COMMISSION | C288: 0815 | D288: HEALTH AND HUMAN SERVICES | F288: 0000 | G288: 0000 | H288: 0000 | I288: 0000 | J288: 10/28/2016 | K288: 00/00/1999
A289: 4280 | B289: MANAGED RISK MED INSUR BD. | C289: 0815 | D289: HEALTH AND HUMAN SERVICES | F289: 0000 | G289: 0000 | H289: 0000 | I289: 0000 | J289: 10/28/2016 | K289: 00/00/0000
A290: 4300 | B290: DEPT. DEVELOPMENTAL SVCS | C290: 0815 | D290: HEALTH AND HUMAN SERVICES | F290: 0000 | G290: 0000 | H290: 0000 | I290: 0000 | J290: 10/28/2016 | K290: 00/00/0000
A291: 4310 | B291: DO NOT USE AGENCY MERGED WITH | C291: 0815 | F291: 0000 | G291: 0000 | H291: 0000 | I291: 0000 | J291: 09/07/2018 | K291: 00/00/0000
A292: 4320 | B292: STATE HOSPITALS | C292: 0815 | D292: HEALTH AND HUMAN SERVICES | F292: 0000 | G292: 0000 | H292: 0000 | I292: 0000 | J292: 10/28/2016 | K292: 00/00/0000
A293: 4350 | B293: DO NOT USE AGENCY MERGED WITH | C293: 0815 | F293: 0000 | G293: 0000 | H293: 0000 | I293: 0000 | J293: 09/07/2018 | K293: 00/00/0000
A294: 4370 | B294: DO NOT USE AGENCY MERGED WITH | C294: 0815 | F294: 0000 | G294: 0000 | H294: 0000 | I294: 0000 | J294: 09/07/2018 | K294: 00/00/0000
A295: 4390 | B295: DO NOT USE AGENCY MERGED WITH | C295: 0815 | F295: 0000 | G295: 0000 | H295: 0000 | I295: 0000 | J295: 09/07/2018 | K295: 00/00/0000
A296: 4400 | B296: DO NOT USE AGENCY MERGED WITH | C296: 0815 | F296: 0000 | G296: 0000 | H296: 0000 | I296: 0000 | J296: 09/07/2018 | K296: 00/00/0000
A297: 4430 | B297: DO NOT USE AGENCY MERGED WITH | C297: 0815 | F297: 0000 | G297: 0000 | H297: 0000 | I297: 0000 | J297: 09/07/2018 | K297: 00/00/0000
A298: 4440 | B298: DEPT. OF STATE HOSPITAL | C298: 0815 | D298: HEALTH AND HUMAN SERVICES | F298: 0000 | G298: 0000 | H298: 0000 | I298: 0000 | J298: 10/28/2016 | K298: 00/00/0000
A299: 4450 | B299: SACRAMENTO STATE HOSPITAL | C299: 0815 | D299: HEALTH AND HUMAN SERVICES | F299: 0000 | G299: 0000 | H299: 0000 | I299: 0000 | J299: 10/28/2016 | K299: 00/00/1999
A300: 4460 | B300: STATE HOSPITALS | C300: 0815 | D300: HEALTH AND HUMAN SERVICES | F300: 0000 | G300: 0000 | H300: 0000 | I300: 0000 | J300: 10/28/2016 | K300: 00/00/0000
A301: 4470 | B301: ATASCADERO STATE HOSPITAL | C301: 0815 | D301: HEALTH AND HUMAN SERVICES | F301: 0000 | G301: 0000 | H301: 0000 | I301: 0000 | J301: 10/28/2016 | K301: 00/00/1999
A302: 4490 | B302: METROPOLITAN STATE HOSPITAL | C302: 0815 | D302: HEALTH AND HUMAN SERVICES | F302: 0000 | G302: 0000 | H302: 0000 | I302: 0000 | J302: 10/28/2016 | K302: 00/00/1999
A303: 4500 | B303: NAPA STATE HOSPITAL | C303: 0815 | D303: HEALTH AND HUMAN SERVICES | F303: 0000 | G303: 0000 | H303: 0000 | I303: 0000 | J303: 10/28/2016 | K303: 00/00/1999
A304: 4510 | B304: PATTON STATE HOSPITAL | C304: 0815 | D304: HEALTH AND HUMAN SERVICES | F304: 0000 | G304: 0000 | H304: 0000 | I304: 0000 | J304: 10/28/2016 | K304: 00/00/1999
A305: 4520 | B305: STOCKTON STATE HOSPITAL-DMH | C305: 0815 | D305: HEALTH AND HUMAN SERVICES | F305: 0000 | G305: 0000 | H305: 0000 | I305: 0000 | J305: 10/28/2016 | K305: 00/00/1999
A306: 4530 | B306: VACAVILLE STATE HOSPITAL | C306: 0815 | D306: HEALTH AND HUMAN SERVICES | F306: 0000 | G306: 0000 | H306: 0000 | I306: 0000 | J306: 10/28/2016 | K306: 00/00/0000
A307: 4540 | B307: COALINGA STATE HOSPITAL | C307: 0815 | D307: HEALTH AND HUMAN SERVICES | F307: 0000 | G307: 0000 | H307: 0000 | I307: 0000 | J307: 10/28/2016 | K307: 00/00/0000
A308: 4550 | B308: SALINAS STATE HOSPITAL | C308: 0815 | D308: HEALTH AND HUMAN SERVICES | F308: 0000 | G308: 0000 | H308: 0000 | I308: 0000 | J308: 10/28/2016 | K308: 00/00/0000
A309: 4560 | B309: MENTAL HEALTH SVCS OVERSIGHT | C309: 0815 | D309: HEALTH AND HUMAN SERVICES | F309: 0000 | G309: 0000 | H309: 0000 | I309: 0000 | J309: 10/28/2016 | K309: 00/00/0000
... A597: 9610 | B597: LEASE-REV NOTES & BONDS | C597: 9000 | D597: DEBT SERVICE INT & FISCAL CHGS | F597: 9030 | G597: 9610 | H597: 0000 | I597: 0000 | J597: 08/19/2016 | K597: 00/00/0000
A598: 9612 | B598: ENHN TOBAC ASSET-BACKED BND | C598: 0847 | D598: BOND INTEREST AND REDEMPTION | E598: WHEN TOBACCO REVENUE IS SHORT | F598: 0000 | G598: 0000 | H598: 0000 | I598: 0000 | J598: 08/19/2016 | K598: 00/00/0000
A599: 9613 | B599: UNENHANCED TOBACCO BD PROCEEDS | C599: 0808 | D599: GENERAL GOVERNMENT | F599: 0000 | G599: 0000 | H599: 0000 | I599: 0000 | J599: 02/26/2008 | K599: 00/00/0000
A600: 9618 | B600: ECONOMIC RECOVERY FINANCE COMM | C600: 0808 | D600: GENERAL GOVERNMENT | F600: 0000 | G600: 0000 | H600: 0000 | I600: 0000 | J600: 10/28/2005 | K600: 00/00/0000
A601: 9620 | B601: CASH MGMT & BUDGETARY LOANS | C601: 0850 | D601: DEBT SERVICE INT & FISCAL CHGS | F601: 0000 | G601: 0000 | H601: 0000 | I601: 0000 | J601: 08/19/2016 | K601: 00/00/0000
A602: 9625 | B602: INT PYMTS TO FEDERAL GOVT | C602: 0846 | D602: DEBT SERVICE INT & FISCAL CHGS | F602: 0000 | G602: 0000 | H602: 0000 | I602: 0000 | J602: 08/19/2016 | K602: 00/00/0000
A603: 9632 | B603: STATE MANDATED LOCAL COSTS | C603: 0808 | D603: GENERAL GOVERNMENT | F603: 0000 | G603: 0000 | H603: 0000 | I603: 0000 | J603: 99/99/9999 | K603: 00/00/0000
A604: 9634 | B604: GENERAL OBLIGATION BONDS | C604: 9000 | D604: GENERAL OBLIGATION BONDS | F604: 9030 | G604: 9634 | H604: 0000 | I604: 0000 | J604: 06/13/1988 | K604: 00/00/0000
A605: 9636 | B605: MISCELLANEOUS ADJUSTMENTS | C605: 9000 | D605: MISCELLANEOUS ADJUSTMENTS | F605: 9030 | G605: 9636 | H605: 0000 | I605: 0000 | J605: 06/13/1988 | K605: 00/00/0000
A606: 9650 | B606: HEALTH BENEFITS FOR ANNUITANTS | C606: 0808 | D606: GENERAL GOVERNMENT | F606: 0000 | G606: 0000 | H606: 0000 | I606: 0000 | J606: 04/04/1984 | K606: 00/00/0000
A607: 9651 | B607: PREFUND HEALTH & DENTAL BEN | C607: 0808 | D607: GENERAL GOVERNMENT | F607: 0000 | G607: 0000 | H607: 0000 | I607: 0000 | J607: 08/25/2010 | K607: 00/00/0000
A608: 9658 | B608: BUDGET STABILIZATION ACCOUNT | C608: 0808 | D608: GENERAL GOVERNMENT | F608: 0000 | G608: 0000 | H608: 0000 | I608: 0000 | J608: 07/11/2006 | K608: 00/00/0000
A609: 9670 | B609: LEGISLATIVE CLAIMS | C609: 0808 | D609: GENERAL GOVERNMENT | F609: 0000 | G609: 0000 | H609: 0000 | I609: 0000 | J609: 04/04/1984 | K609: 00/00/0000
A610: 9671 | B610: EQUITY CLAIMS OF BD OF CONTROL | C610: 0808 | D610: GENERAL GOVERNMENT | F610: 0000 | G610: 0000 | H610: 0000 | I610: 0000 | J610: 03/30/1994 | K610: 00/00/0000
... A635: 9885 | B635: RESERVE FOR ENCUMBRANCE | C635: 0808 | D635: GENERAL GOVERNMENT | F635: 0000 | G635: 0000 | H635: 0000 | I635: 0000 | J635: 01/23/1991 | K635: 00/00/0000
A636: 9889 | B636: PUBLIC SCHOOL SYSTEM STABILIZA | C636: 0810 | D636: PUBLIC SCHOOL SYSTEM | E636: STABILIZATION ACCOUNT | F636: 0000 | G636: 0000 | H636: 0000 | I636: 0000 | J636: 04/01/2020 | K636: 00/00/0000
A637: 9890 | B637: RES FOR ECONOMIC UNCERTAINTIES | C637: 0808 | D637: GENERAL GOVERNMENT | F637: 0000 | G637: 0000 | H637: 0000 | I637: 0000 | J637: 07/11/2006 | K637: 00/00/0000
A638: 9891 | B638: DEPT OF HEALTH HUMAN SERVICES | C638: 0815 | D638: HEALTH AND HUMAN SERVICES | F638: 0000 | G638: 0000 | H638: 0000 | I638: 0000 | J638: 10/28/2016 | K638: 00/00/0000
A639: 9892 | B639: SUPPLEMENTAL PENSION PAYMENTS | C639: 0843 | D639: INT. ON INTERFUND LOANS | F639: 0000 | G639: 0000 | H639: 0000 | I639: 0000 | J639: 11/22/2019 | K639: 00/00/0000
A640: 9895 | B640: PETROLEUM VIOLATION ESCROW PRO | C640: 0808 | D640: GENERAL GOVERNMENT | F640: 0000 | G640: 0000 | H640: 0000 | I640: 0000 | J640: 07/11/2006 | K640: 00/00/0000
A641: 9896 | B641: OUTER CONT SHELF LAND ACT | C641: 0808 | D641: GENERAL GOVERNMENT | F641: 0000 | G641: 0000 | H641: 0000 | I641: 0000 | J641: 07/11/2006 | K641: 00/00/0000
A642: 9898 | B642: PERS GENERAL FUND PAYMENT | C642: 0808 | D642: GENERAL GOVERNMENT | F642: 0000 | G642: 0000 | H642: 0000 | I642: 0000 | J642: 11/04/1998 | K642: 00/00/0000
A643: 9900 | B643: GEN FD CREDITS FROM SPEC FUNDS | C643: 0808 | D643: GENERAL GOVERNMENT | F643: 0000 | G643: 0000 | H643: 0000 | I643: 0000 | J643: 07/11/2006 | K643: 00/00/0000
A644: 9901 | B644: STATEWIDE GEN ADM EXP (PR) | C644: 0808 | D644: GENERAL GOVERNMENT | F644: 0000 | G644: 0000 | H644: 0000 | I644: 0000 | J644: 07/11/2006 | K644: 00/00/0000
A645: 9909 | B645: HLTH INS PORTABLTY ACCTABLTY | C645: 0815 | D645: HEALTH AND HUMAN SERVICES | F645: 0000 | G645: 0000 | H645: 0000 | I645: 0000 | J645: 10/28/2016 | K645: 00/00/0000
A646: 9910 | B646: GEN FD CREDITS FROM FED FUNDS | C646: 0808 | D646: GENERAL GOVERNMENT | F646: 0000 | G646: 0000 | H646: 0000 | I646: 0000 | J646: 07/11/2006 | K646: 00/00/0000
...
