Workbook

Sheet Outstanding BUs
A1: EMAILED | C1: Last Day of Correspondence with department | D1: Days since last Correspondence
A2: 3790 | B2: EMAILED | C2: 45119 | D2: =TODAY()-C2 -> 579
A4: =COUNTIFS(B2:B3,"EMAILED") -> 1 | B4: EMAILED | K4: =I36 -> 2.4777798e+09 | M4: ='1. Rpt 18s (non-CSU)'!AF556 -> 1.6944546e+08
K5: % of Outstanding total | M5: % of Non-CSU total
A6: # of funds outstanding | D6: BU | E6: Fund | F6: Department Name | G6: Fund Name | H6: Ending Balance
A7: 1 | B7: EMAILED | C7: F | D7: 3790 | E7: 0001 | F7: DEPT OF PARKS AND RECREATION | G7: GENERAL FUND | H7: 8.8640915e+08
A8: =A7+1 -> 2 | B8: EMAILED | C8: F | D8: 3790 | E8: 0005 | F8: DEPT OF PARKS AND RECREATION | G8: SAFE NEIGHBRHD PARK, CLEAN WAT | H8: 4.6337999e+08
A9: =A8+1 -> 3 | B9: EMAILED | C9: F | D9: 3790 | E9: 0013 | F9: DEPT OF PARKS AND RECREATION | G9: Park & Rec Revolving Account | H9: 6145690
A10: =A9+1 -> 4 | B10: EMAILED | C10: F | D10: 3790 | E10: 0018 | F10: DEPT OF PARKS AND RECREATION | G10: SITE REMEDIATION ACCOUNT | H10: 550000
A11: =A10+1 -> 5 | B11: EMAILED | C11: F | D11: 3790 | E11: 0036 | F11: DEPT OF PARKS AND RECREATION | G11: SPECIAL ACCOUNT FOR CAP OUTLAY | H11: 5746101.5
A12: =A11+1 -> 6 | B12: EMAILED | C12: F | D12: 3790 | E12: 0132 | F12: DEPT OF PARKS AND RECREATION | G12: WORKERS COMP MANAGED CARE FUND | H12: 1.05552e+08
A13: =A12+1 -> 7 | B13: EMAILED | C13: F | D13: 3790 | E13: 0140 | F13: DEPT OF PARKS AND RECREATION | G13: ENVIRONMENTL LICENSE PLATE FD | H13: 422064.25
A14: =A13+1 -> 8 | B14: EMAILED | C14: F | D14: 3790 | E14: 0156 | F14: DEPT OF PARKS AND RECREATION | G14: CALIFORNIA HERITAGE FUND | H14: 15488246
A15: =A14+1 -> 9 | B15: EMAILED | C15: F | D15: 3790 | E15: 0188 | F15: DEPT OF PARKS AND RECREATION | G15: ENERGY AND RESOURCES FUND | H15: 67000
A16: =A15+1 -> 10 | B16: EMAILED | C16: F | D16: 3790 | E16: 0190 | F16: DEPT OF PARKS AND RECREATION | G16: ENERGY AND RESOURCES FUND | H16: 6922668.9
A17: =A16+1 -> 11 | B17: EMAILED | C17: F | D17: 3790 | E17: 0235 | F17: DEPT OF PARKS AND RECREATION | G17: CIGARETTE&TOBACCO FD, PUB RES | H17: 745065.03
A18: =A17+1 -> 12 | B18: EMAILED | C18: F | D18: 3790 | E18: 0262 | F18: DEPT OF PARKS AND RECREATION | G18: HABITAT CONSERVATION FUND | H18: 69333048
A19: =A18+1 -> 13 | B19: EMAILED | C19: F | D19: 3790 | E19: 0263 | F19: DEPT OF PARKS AND RECREATION | G19: OFF-HIGHWAY VEHICLE TRUST FUND | H19: 1.1142941e+08
... A34: =A33+1 -> 28 | B34: EMAILED | C34: F | D34: 3790 | E34: 6029 | F34: DEPT OF PARKS AND RECREATION | G34: CA CLEAN WATER AIR ETC | H34: 1.2884846e+08
A35: =A34+1 -> 29 | B35: EMAILED | C35: F | D35: 3790 | E35: 6051 | F35: DEPT OF PARKS AND RECREATION | G35: SAFE DRINKING WATER OF 2006 | H35: 11995281 | I35: =SUM(H7:H35) -> 2.4777798e+09 | K35: =I35/$K$4 -> 1 | M35: =I35/$M$4 -> 14.622875
H36: =SUM(H7:H35) -> 2.4777798e+09 | I36: =SUM(I7:I35) -> 2.4777798e+09 | K36: =SUM(K7:K35) -> 1 | M36: =SUM(M7:M35) -> 14.6229
A37: =A35/515 -> 0.06
A38: % outstanding

Sheet 1. Rpt 18s (non-CSU)
A1: Capital Assets - Governmental and Proprietary Funds (Non-CSU) | G1: Source: | H1: Prior year's Non-CSU Workbook and Report 18s submitted with the GAAP Agency Requests.
G2: Purpose: | H2: To record capital asset balances (Right-to-Use Leases, SBITAs and APAs) and activity by BU and fund.
A3: as of June 30, 2024 | G3: Procedures: | H3: Record data reflected on the Report 18s for unaudited governmental and proprietary funds. | N3: Highlight yellow if restatement
N5: Beginning | O5: Beginning | P5: Beginning | Q5: Beginning | R5: Beginning | S5: Beginning | T5: Beginning | U5: Additions | V5: Additions | W5: Additions | X5: Additions | Y5: Additions | Z5: Deductions | AA5: Deductions | AB5: Deductions | AC5: Deductions | AD5: Deductions | AE5: Ending | AF5: Ending | AG5: Ending | AH5: Ending | AI5: Ending | AJ5: Ending | AK5: Ending
N6: Right-to-Use Leased Land | O6: Right-to-Use Leased Buildings | P6: Right-to-Use Leased Equipment | Q6: Right-to-Use SBITAs | R6: APA Land | S6: APA Buildings | T6: Total | U6: Right-to-Use Leased Land | V6: Right-to-Use Leased Buildings | W6: Right-to-Use Leased Equipment | X6: Right-to-Use SBITAs | Y6: Total | Z6: Right-to-Use Leased Land | AA6: Right-to-Use Leased Buildings | AB6: Right-to-Use Leased Equipment | AC6: Right-to-Use SBITAs | AD6: Total | AE6: Right-to-Use Leased Land | AF6: Right-to-Use Leased Buildings | AG6: Right-to-Use Leased Equipment | AH6: Right-to-Use SBITAs | AI6: APA Land | AJ6: APA Buildings | AK6: Total
A7: See bottom for legend | D7: GASB 87 | E7: GASB 96 | N7: Amortizable | O7: Amortizable | P7: Amortizable | Q7: Amortizable | S7: Depreciable | U7: Amortizable | V7: Amortizable | W7: Amortizable | X7: Amortizable | Z7: Amortizable | AA7: Amortizable | AB7: Amortizable | AC7: Amortizable | AE7: Amortizable | AF7: Amortizable | AG7: Amortizable | AH7: Amortizable | AI7: Depreciable
B8: Input | C8: FI$Cal Status | D8: GASB 87 Review | E8: GASB 96 Review | F8: Agency | G8: Fund | H8: Concatenate | I8: Fd Hier | J8: Agy Function | K8: Function | L8: Agency Name | M8: Fund Name | N8: (0476 GABX) | O8: (0477 GABX) | P8: (0478 GABX) | Q8: (0480 GABX) | R8: (0446 GABR) | S8: (0448 GABS) | U8: (0476 GABX) | V8: (0477 GABX) | W8: (0478 GABX) | X8: (0480 GABX) | Z8: (0476 GABX) | AA8: (0477 GABX) | AB8: (0478 GABX) | AC8: (0480 GABX) | AE8: (0476 GABX) | AF8: (0477 GABX) | AG8: (0478 GABX) | AH8: (0480 GABX) | AI8: (0446 GABR) | AJ8: (0448 GABS)
A9: 19 | C9: E | F9: 0160 | G9: 0001 | H9: =F9&G9 -> 01600001 | I9: =IF(ISNA(VLOOKUP(G9,GAAP02F[[#All],[Column1]:[FundHier1]],5,FALSE)),"Leases",(VLOOKUP(G9,GAAP02F[[#All],[Column1]:[FundHier1]],5,FALSE))) -> 100 | J9: =IF(ISNA(VLOOKUP(F9,Table_GAAP02A[[#All],[Agency]:[Hier1]],4,FALSE)),"Abolished Agency",(VLOOKUP(F9,Table_GAAP02A[[#All],[Agency]:[Hier1]],4,FALSE))) -> 0808 | K9: =IF(ISNA(VLOOKUP(F9,Table_GAAP02A[[#All],[Agency]:[Hier1]],2,FALSE)),"Abolished Agency",(VLOOKUP(F9,Table_GAAP02A[[#All],[Agency]:[Hier1]],2,FALSE))) -> GENERAL GOVERNMENT | L9: =IF(ISNA(VLOOKUP(F9,Table_GAAP02A[[#All],[Agency]:[Hier1]],3,FALSE)),"Abolished Agency",(VLOOKUP(F9,Table_GAAP02A[[#All],[Agency]:[Hier1]],3,FALSE))) -> LEGISLATIVE COUNSEL BUREAU | M9: =IF(ISNA(VLOOKUP(G9,GAAP02F[[#All],[Column1]:[FundName]],2,FALSE)),"Leases",(VLOOKUP(G9,GAAP02F[[#All],[Column1]:[FundName]],2,FALSE))) -> GENERAL FUND | N9: 0 | O9: 0 | P9: 0 | Q9: 0 | R9: 0 | S9: 0 | T9: =SUM(N9:S9) -> 0 | U9: 0 | V9: 0 | W9: 0 | X9: 0 | Y9: =SUM(U9:X9) -> 0 | Z9: 0 | AA9: 0 | AB9: 0 | AC9: 0 | AD9: =SUM(Z9:AC9) -> 0 | AE9: =N9 +U9-Z9 -> 0 | AF9: =O9 +V9-AA9 -> 0 | AG9: =P9 +W9-AB9 -> 0 | AH9: =Q9 +X9-AC9 -> 0 | AI9: =R9 -> 0 | AJ9: =S9 -> 0 | AK9: =SUM(AE9:AJ9) -> 0
A10: 19 | C10: F | F10: 0250 | G10: 0001 | H10: =F10&G10 -> 02500001 | I10: =IF(ISNA(VLOOKUP(G10,GAAP02F[[#All],[Column1]:[FundHier1]],5,FALSE)),"Leases",(VLOOKUP(G10,GAAP02F[[#All],[Column1]:[FundHier1]],5,FALSE))) -> 100 | J10: =IF(ISNA(VLOOKUP(F10,Table_GAAP02A[[#All],[Agency]:[Hier1]],4,FALSE)),"Abolished Agency",(VLOOKUP(F10,Table_GAAP02A[[#All],[Agency]:[Hier1]],4,FALSE))) -> 0808 | K10: =IF(ISNA(VLOOKUP(F10,Table_GAAP02A[[#All],[Agency]:[Hier1]],2,FALSE)),"Abolished Agency",(VLOOKUP(F10,Table_GAAP02A[[#All],[Agency]:[Hier1]],2,FALSE))) -> GENERAL GOVERNMENT | L10: =IF(ISNA(VLOOKUP(F10,Table_GAAP02A[[#All],[Agency]:[Hier1]],3,FALSE)),"Abolished Agency",(VLOOKUP(F10,Table_GAAP02A[[#All],[Agency]:[Hier1]],3,FALSE))) -> JUDICIARY | M10: =IF(ISNA(VLOOKUP(G10,GAAP02F[[#All],[Column1]:[FundName]],2,FALSE)),"Leases",(VLOOKUP(G10,GAAP02F[[#All],[Column1]:[FundName]],2,FALSE))) -> GENERAL FUND | N10: 0 | O10: 0 | P10: 0 | Q10: 0 | R10: 0 | S10: 0 | T10: =SUM(N10:S10) -> 0 | U10: 0 | V10: 0 | W10: 0 | X10: 0 | Y10: =SUM(U10:X10) -> 0 | Z10: 0 | AA10: 0 | AB10: 0 | AC10: 0 | AD10: =SUM(Z10:AC10) -> 0 | AE10: =N10 +U10-Z10 -> 0 | AF10: =O10 +V10-AA10 -> 0 | AG10: =P10 +W10-AB10 -> 0 | AH10: =Q10 +X10-AC10 -> 0 | AI10: =R10 -> 0 | AJ10: =S10 -> 0 | AK10: =SUM(AE10:AJ10) -> 0
A11: 19 | C11: F | F11: 0250 | G11: 0159 | H11: =F11&G11 -> 02500159 | I11: =IF(ISNA(VLOOKUP(G11,GAAP02F[[#All],[Column1]:[FundHier1]],5,FALSE)),"Leases",(VLOOKUP(G11,GAAP02F[[#All],[Column1]:[FundHier1]],5,FALSE))) -> 200 | J11: =IF(ISNA(VLOOKUP(F11,Table_GAAP02A[[#All],[Agency]:[Hier1]],4,FALSE)),"Abolished Agency",(VLOOKUP(F11,Table_GAAP02A[[#All],[Agency]:[Hier1]],4,FALSE))) -> 0808 | K11: =IF(ISNA(VLOOKUP(F11,Table_GAAP02A[[#All],[Agency]:[Hier1]],2,FALSE)),"Abolished Agency",(VLOOKUP(F11,Table_GAAP02A[[#All],[Agency]:[Hier1]],2,FALSE))) -> GENERAL GOVERNMENT | L11: =IF(ISNA(VLOOKUP(F11,Table_GAAP02A[[#All],[Agency]:[Hier1]],3,FALSE)),"Abolished Agency",(VLOOKUP(F11,Table_GAAP02A[[#All],[Agency]:[Hier1]],3,FALSE))) -> JUDICIARY | M11: =IF(ISNA(VLOOKUP(G11,GAAP02F[[#All],[Column1]:[FundName]],2,FALSE)),"Leases",(VLOOKUP(G11,GAAP02F[[#All],[Column1]:[FundName]],2,FALSE))) -> TRIAL COURT IMPROVEMENT FUND | N11: 0 | O11: 0 | P11: 0 | Q11: 0 | R11: 0 | S11: 0 | T11: =SUM(N11:S11) -> 0 | U11: 0 | V11: 0 | W11: 0 | X11: 0 | Y11: =SUM(U11:X11) -> 0 | Z11: 0 | AA11: 0 | AB11: 0 | AC11: 0 | AD11: =SUM(Z11:AC11) -> 0 | AE11: =N11 +U11-Z11 -> 0 | AF11: =O11 +V11-AA11 -> 0 | AG11: =P11 +W11-AB11 -> 0 | AH11: =Q11 +X11-AC11 -> 0 | AI11: =R11 -> 0 | AJ11: =S11 -> 0 | AK11: =SUM(AE11:AJ11) -> 0
A12: 19 | C12: F | F12: 0250 | G12: 0587 | H12: =F12&G12 -> 02500587 | I12: =IF(ISNA(VLOOKUP(G12,GAAP02F[[#All],[Column1]:[FundHier1]],5,FALSE)),"Leases",(VLOOKUP(G12,GAAP02F[[#All],[Column1]:[FundHier1]],5,FALSE))) -> 200 | J12: =IF(ISNA(VLOOKUP(F12,Table_GAAP02A[[#All],[Agency]:[Hier1]],4,FALSE)),"Abolished Agency",(VLOOKUP(F12,Table_GAAP02A[[#All],[Agency]:[Hier1]],4,FALSE))) -> 0808 | K12: =IF(ISNA(VLOOKUP(F12,Table_GAAP02A[[#All],[Agency]:[Hier1]],2,FALSE)),"Abolished Agency",(VLOOKUP(F12,Table_GAAP02A[[#All],[Agency]:[Hier1]],2,FALSE))) -> GENERAL GOVERNMENT | L12: =IF(ISNA(VLOOKUP(F12,Table_GAAP02A[[#All],[Agency]:[Hier1]],3,FALSE)),"Abolished Agency",(VLOOKUP(F12,Table_GAAP02A[[#All],[Agency]:[Hier1]],3,FALSE))) -> JUDICIARY | M12: =IF(ISNA(VLOOKUP(G12,GAAP02F[[#All],[Column1]:[FundName]],2,FALSE)),"Leases",(VLOOKUP(G12,GAAP02F[[#All],[Column1]:[FundName]],2,FALSE))) -> FAMILY LAW TRUST FUND | N12: 0 | O12: 0 | P12: 0 | Q12: 0 | R12: 0 | S12: 0 | T12: =SUM(N12:S12) -> 0 | U12: 0 | V12: 0 | W12: 0 | X12: 0 | Y12: =SUM(U12:X12) -> 0 | Z12: 0 | AA12: 0 | AB12: 0 | AC12: 0 | AD12: =SUM(Z12:AC12) -> 0 | AE12: =N12 +U12-Z12 -> 0 | AF12: =O12 +V12-AA12 -> 0 | AG12: =P12 +W12-AB12 -> 0 | AH12: =Q12 +X12-AC12 -> 0 | AI12: =R12 -> 0 | AJ12: =S12 -> 0 | AK12: =SUM(AE12:AJ12) -> 0
A13: 19 | C13: F | F13: 0250 | G13: 0890 | H13: =F13&G13 -> 02500890 | I13: =IF(ISNA(VLOOKUP(G13,GAAP02F[[#All],[Column1]:[FundHier1]],5,FALSE)),"Leases",(VLOOKUP(G13,GAAP02F[[#All],[Column1]:[FundHier1]],5,FALSE))) -> 200 | J13: =IF(ISNA(VLOOKUP(F13,Table_GAAP02A[[#All],[Agency]:[Hier1]],4,FALSE)),"Abolished Agency",(VLOOKUP(F13,Table_GAAP02A[[#All],[Agency]:[Hier1]],4,FALSE))) -> 0808 | K13: =IF(ISNA(VLOOKUP(F13,Table_GAAP02A[[#All],[Agency]:[Hier1]],2,FALSE)),"Abolished Agency",(VLOOKUP(F13,Table_GAAP02A[[#All],[Agency]:[Hier1]],2,FALSE))) -> GENERAL GOVERNMENT | L13: =IF(ISNA(VLOOKUP(F13,Table_GAAP02A[[#All],[Agency]:[Hier1]],3,FALSE)),"Abolished Agency",(VLOOKUP(F13,Table_GAAP02A[[#All],[Agency]:[Hier1]],3,FALSE))) -> JUDICIARY | M13: =IF(ISNA(VLOOKUP(G13,GAAP02F[[#All],[Column1]:[FundName]],2,FALSE)),"Leases",(VLOOKUP(G13,GAAP02F[[#All],[Column1]:[FundName]],2,FALSE))) -> FEDERAL TRUST FUND | N13: 0 | O13: 0 | P13: 0 | Q13: 0 | R13: 0 | S13: 0 | T13: =SUM(N13:S13) -> 0 | U13: 0 | V13: 0 | W13: 0 | X13: 0 | Y13: =SUM(U13:X13) -> 0 | Z13: 0 | AA13: 0 | AB13: 0 | AC13: 0 | AD13: =SUM(Z13:AC13) -> 0 | AE13: =N13 +U13-Z13 -> 0 | AF13: =O13 +V13-AA13 -> 0 | AG13: =P13 +W13-AB13 -> 0 | AH13: =Q13 +X13-AC13 -> 0 | AI13: =R13 -> 0 | AJ13: =S13 -> 0 | AK13: =SUM(AE13:AJ13) -> 0
A14: 19 | C14: F | F14: 0250 | G14: 0932 | H14: =F14&G14 -> 02500932 | I14: =IF(ISNA(VLOOKUP(G14,GAAP02F[[#All],[Column1]:[FundHier1]],5,FALSE)),"Leases",(VLOOKUP(G14,GAAP02F[[#All],[Column1]:[FundHier1]],5,FALSE))) -> 200 | J14: =IF(ISNA(VLOOKUP(F14,Table_GAAP02A[[#All],[Agency]:[Hier1]],4,FALSE)),"Abolished Agency",(VLOOKUP(F14,Table_GAAP02A[[#All],[Agency]:[Hier1]],4,FALSE))) -> 0808 | K14: =IF(ISNA(VLOOKUP(F14,Table_GAAP02A[[#All],[Agency]:[Hier1]],2,FALSE)),"Abolished Agency",(VLOOKUP(F14,Table_GAAP02A[[#All],[Agency]:[Hier1]],2,FALSE))) -> GENERAL GOVERNMENT | L14: =IF(ISNA(VLOOKUP(F14,Table_GAAP02A[[#All],[Agency]:[Hier1]],3,FALSE)),"Abolished Agency",(VLOOKUP(F14,Table_GAAP02A[[#All],[Agency]:[Hier1]],3,FALSE))) -> JUDICIARY | M14: =IF(ISNA(VLOOKUP(G14,GAAP02F[[#All],[Column1]:[FundName]],2,FALSE)),"Leases",(VLOOKUP(G14,GAAP02F[[#All],[Column1]:[FundName]],2,FALSE))) -> TRIAL COURT TRUST FUND | N14: 0 | O14: 0 | P14: 0 | Q14: 0 | R14: 0 | S14: 0 | T14: =SUM(N14:S14) -> 0 | U14: 0 | V14: 0 | W14: 0 | X14: 0 | Y14: =SUM(U14:X14) -> 0 | Z14: 0 | AA14: 0 | AB14: 0 | AC14: 0 | AD14: =SUM(Z14:AC14) -> 0 | AE14: =N14 +U14-Z14 -> 0 | AF14: =O14 +V14-AA14 -> 0 | AG14: =P14 +W14-AB14 -> 0 | AH14: =Q14 +X14-AC14 -> 0 | AI14: =R14 -> 0 | AJ14: =S14 -> 0 | AK14: =SUM(AE14:AJ14) -> 0
A15: G | C15: F | F15: 0250 | G15: 0991 | H15: =F15&G15 -> 02500991 | I15: =IF(ISNA(VLOOKUP(G15,GAAP02F[[#All],[Column1]:[FundHier1]],5,FALSE)),"Leases",(VLOOKUP(G15,GAAP02F[[#All],[Column1]:[FundHier1]],5,FALSE))) -> 200 | J15: =IF(ISNA(VLOOKUP(F15,Table_GAAP02A[[#All],[Agency]:[Hier1]],4,FALSE)),"Abolished Agency",(VLOOKUP(F15,Table_GAAP02A[[#All],[Agency]:[Hier1]],4,FALSE))) -> 0808 | K15: =IF(ISNA(VLOOKUP(F15,Table_GAAP02A[[#All],[Agency]:[Hier1]],2,FALSE)),"Abolished Agency",(VLOOKUP(F15,Table_GAAP02A[[#All],[Agency]:[Hier1]],2,FALSE))) -> GENERAL GOVERNMENT | L15: =IF(ISNA(VLOOKUP(F15,Table_GAAP02A[[#All],[Agency]:[Hier1]],3,FALSE)),"Abolished Agency",(VLOOKUP(F15,Table_GAAP02A[[#All],[Agency]:[Hier1]],3,FALSE))) -> JUDICIARY | M15: =IF(ISNA(VLOOKUP(G15,GAAP02F[[#All],[Column1]:[FundName]],2,FALSE)),"Leases",(VLOOKUP(G15,GAAP02F[[#All],[Column1]:[FundName]],2,FALSE))) -> TRIAL COURTS FUND | N15: 0 | O15: 0 | P15: 0 | Q15: 0 | R15: 0 | S15: 0 | T15: =SUM(N15:S15) -> 0 | U15: 0 | V15: 0 | W15: 0 | X15: 0 | Y15: =SUM(U15:X15) -> 0 | Z15: 0 | AA15: 0 | AB15: 0 | AC15: 0 | AD15: =SUM(Z15:AC15) -> 0 | AE15: =N15 +U15-Z15 -> 0 | AF15: =O15 +V15-AA15 -> 0 | AG15: =P15 +W15-AB15 -> 0 | AH15: =Q15 +X15-AC15 -> 0 | AI15: =R15 -> 0 | AJ15: =S15 -> 0 | AK15: =SUM(AE15:AJ15) -> 0
A16: 19 | C16: F | F16: 0250 | G16: 3037 | H16: =F16&G16 -> 02503037 | I16: =IF(ISNA(VLOOKUP(G16,GAAP02F[[#All],[Column1]:[FundHier1]],5,FALSE)),"Leases",(VLOOKUP(G16,GAAP02F[[#All],[Column1]:[FundHier1]],5,FALSE))) -> 200 | J16: =IF(ISNA(VLOOKUP(F16,Table_GAAP02A[[#All],[Agency]:[Hier1]],4,FALSE)),"Abolished Agency",(VLOOKUP(F16,Table_GAAP02A[[#All],[Agency]:[Hier1]],4,FALSE))) -> 0808 | K16: =IF(ISNA(VLOOKUP(F16,Table_GAAP02A[[#All],[Agency]:[Hier1]],2,FALSE)),"Abolished Agency",(VLOOKUP(F16,Table_GAAP02A[[#All],[Agency]:[Hier1]],2,FALSE))) -> GENERAL GOVERNMENT | L16: =IF(ISNA(VLOOKUP(F16,Table_GAAP02A[[#All],[Agency]:[Hier1]],3,FALSE)),"Abolished Agency",(VLOOKUP(F16,Table_GAAP02A[[#All],[Agency]:[Hier1]],3,FALSE))) -> JUDICIARY | M16: =IF(ISNA(VLOOKUP(G16,GAAP02F[[#All],[Column1]:[FundName]],2,FALSE)),"Leases",(VLOOKUP(G16,GAAP02F[[#All],[Column1]:[FundName]],2,FALSE))) -> STATE COURT FACILITIES CONST F | N16: 0 | O16: 0 | P16: 0 | Q16: 0 | R16: 0 | S16: 0 | T16: =SUM(N16:S16) -> 0 | U16: 0 | V16: 0 | W16: 0 | X16: 0 | Y16: =SUM(U16:X16) -> 0 | Z16: 0 | AA16: 0 | AB16: 0 | AC16: 0 | AD16: =SUM(Z16:AC16) -> 0 | AE16: =N16 +U16-Z16 -> 0 | AF16: =O16 +V16-AA16 -> 0 | AG16: =P16 +W16-AB16 -> 0 | AH16: =Q16 +X16-AC16 -> 0 | AI16: =R16 -> 0 | AJ16: =S16 -> 0 | AK16: =SUM(AE16:AJ16) -> 0
A17: 19 | C17: F | F17: 0250 | G17: 3060 | H17: =F17&G17 -> 02503060 | I17: =IF(ISNA(VLOOKUP(G17,GAAP02F[[#All],[Column1]:[FundHier1]],5,FALSE)),"Leases",(VLOOKUP(G17,GAAP02F[[#All],[Column1]:[FundHier1]],5,FALSE))) -> 200 | J17: =IF(ISNA(VLOOKUP(F17,Table_GAAP02A[[#All],[Agency]:[Hier1]],4,FALSE)),"Abolished Agency",(VLOOKUP(F17,Table_GAAP02A[[#All],[Agency]:[Hier1]],4,FALSE))) -> 0808 | K17: =IF(ISNA(VLOOKUP(F17,Table_GAAP02A[[#All],[Agency]:[Hier1]],2,FALSE)),"Abolished Agency",(VLOOKUP(F17,Table_GAAP02A[[#All],[Agency]:[Hier1]],2,FALSE))) -> GENERAL GOVERNMENT | L17: =IF(ISNA(VLOOKUP(F17,Table_GAAP02A[[#All],[Agency]:[Hier1]],3,FALSE)),"Abolished Agency",(VLOOKUP(F17,Table_GAAP02A[[#All],[Agency]:[Hier1]],3,FALSE))) -> JUDICIARY | M17: =IF(ISNA(VLOOKUP(G17,GAAP02F[[#All],[Column1]:[FundName]],2,FALSE)),"Leases",(VLOOKUP(G17,GAAP02F[[#All],[Column1]:[FundName]],2,FALSE))) -> APPELLATE COURT TRUST FUND | N17: 0 | O17: 0 | P17: 0 | Q17: 0 | R17: 0 | S17: 0 | T17: =SUM(N17:S17) -> 0 | U17: 0 | V17: 0 | W17: 0 | X17: 0 | Y17: =SUM(U17:X17) -> 0 | Z17: 0 | AA17: 0 | AB17: 0 | AC17: 0 | AD17: =SUM(Z17:AC17) -> 0 | AE17: =N17 +U17-Z17 -> 0 | AF17: =O17 +V17-AA17 -> 0 | AG17: =P17 +W17-AB17 -> 0 | AH17: =Q17 +X17-AC17 -> 0 | AI17: =R17 -> 0 | AJ17: =S17 -> 0 | AK17: =SUM(AE17:AJ17) -> 0
A18: 19 | C18: F | F18: 0250 | G18: 3066 | H18: =F18&G18 -> 02503066 | I18: =IF(ISNA(VLOOKUP(G18,GAAP02F[[#All],[Column1]:[FundHier1]],5,FALSE)),"Leases",(VLOOKUP(G18,GAAP02F[[#All],[Column1]:[FundHier1]],5,FALSE))) -> 200 | J18: =IF(ISNA(VLOOKUP(F18,Table_GAAP02A[[#All],[Agency]:[Hier1]],4,FALSE)),"Abolished Agency",(VLOOKUP(F18,Table_GAAP02A[[#All],[Agency]:[Hier1]],4,FALSE))) -> 0808 | K18: =IF(ISNA(VLOOKUP(F18,Table_GAAP02A[[#All],[Agency]:[Hier1]],2,FALSE)),"Abolished Agency",(VLOOKUP(F18,Table_GAAP02A[[#All],[Agency]:[Hier1]],2,FALSE))) -> GENERAL GOVERNMENT | L18: =IF(ISNA(VLOOKUP(F18,Table_GAAP02A[[#All],[Agency]:[Hier1]],3,FALSE)),"Abolished Agency",(VLOOKUP(F18,Table_GAAP02A[[#All],[Agency]:[Hier1]],3,FALSE))) -> JUDICIARY | M18: =IF(ISNA(VLOOKUP(G18,GAAP02F[[#All],[Column1]:[FundName]],2,FALSE)),"Leases",(VLOOKUP(G18,GAAP02F[[#All],[Column1]:[FundName]],2,FALSE))) -> COURT FACILITIES TRUST FUND | N18: 0 | O18: 0 | P18: 0 | Q18: 0 | R18: 0 | S18: 0 | T18: =SUM(N18:S18) -> 0 | U18: 0 | V18: 0 | W18: 0 | X18: 0 | Y18: =SUM(U18:X18) -> 0 | Z18: 0 | AA18: 0 | AB18: 0 | AC18: 0 | AD18: =SUM(Z18:AC18) -> 0 | AE18: =N18 +U18-Z18 -> 0 | AF18: =O18 +V18-AA18 -> 0 | AG18: =P18 +W18-AB18 -> 0 | AH18: =Q18 +X18-AC18 -> 0 | AI18: =R18 -> 0 | AJ18: =S18 -> 0 | AK18: =SUM(AE18:AJ18) -> 0
A19: 19 | C19: F | F19: 0250 | G19: 3085 | H19: =F19&G19 -> 02503085 | I19: =IF(ISNA(VLOOKUP(G19,GAAP02F[[#All],[Column1]:[FundHier1]],5,FALSE)),"Leases",(VLOOKUP(G19,GAAP02F[[#All],[Column1]:[FundHier1]],5,FALSE))) -> 200 | J19: =IF(ISNA(VLOOKUP(F19,Table_GAAP02A[[#All],[Agency]:[Hier1]],4,FALSE)),"Abolished Agency",(VLOOKUP(F19,Table_GAAP02A[[#All],[Agency]:[Hier1]],4,FALSE))) -> 0808 | K19: =IF(ISNA(VLOOKUP(F19,Table_GAAP02A[[#All],[Agency]:[Hier1]],2,FALSE)),"Abolished Agency",(VLOOKUP(F19,Table_GAAP02A[[#All],[Agency]:[Hier1]],2,FALSE))) -> GENERAL GOVERNMENT | L19: =IF(ISNA(VLOOKUP(F19,Table_GAAP02A[[#All],[Agency]:[Hier1]],3,FALSE)),"Abolished Agency",(VLOOKUP(F19,Table_GAAP02A[[#All],[Agency]:[Hier1]],3,FALSE))) -> JUDICIARY | M19: =IF(ISNA(VLOOKUP(G19,GAAP02F[[#All],[Column1]:[FundName]],2,FALSE)),"Leases",(VLOOKUP(G19,GAAP02F[[#All],[Column1]:[FundName]],2,FALSE))) -> MENTAL HEALTH SERVICE FUND | N19: 0 | O19: 0 | P19: 0 | Q19: 0 | R19: 0 | S19: 0 | T19: =SUM(N19:S19) -> 0 | U19: 0 | V19: 0 | W19: 0 | X19: 0 | Y19: =SUM(U19:X19) -> 0 | Z19: 0 | AA19: 0 | AB19: 0 | AC19: 0 | AD19: =SUM(Z19:AC19) -> 0 | AE19: =N19 +U19-Z19 -> 0 | AF19: =O19 +V19-AA19 -> 0 | AG19: =P19 +W19-AB19 -> 0 | AH19: =Q19 +X19-AC19 -> 0 | AI19: =R19 -> 0 | AJ19: =S19 -> 0 | AK19: =SUM(AE19:AJ19) -> 0
A20: 19 | C20: F | F20: 0250 | G20: 3138 | H20: =F20&G20 -> 02503138 | I20: =IF(ISNA(VLOOKUP(G20,GAAP02F[[#All],[Column1]:[FundHier1]],5,FALSE)),"Leases",(VLOOKUP(G20,GAAP02F[[#All],[Column1]:[FundHier1]],5,FALSE))) -> 200 | J20: =IF(ISNA(VLOOKUP(F20,Table_GAAP02A[[#All],[Agency]:[Hier1]],4,FALSE)),"Abolished Agency",(VLOOKUP(F20,Table_GAAP02A[[#All],[Agency]:[Hier1]],4,FALSE))) -> 0808 | K20: =IF(ISNA(VLOOKUP(F20,Table_GAAP02A[[#All],[Agency]:[Hier1]],2,FALSE)),"Abolished Agency",(VLOOKUP(F20,Table_GAAP02A[[#All],[Agency]:[Hier1]],2,FALSE))) -> GENERAL GOVERNMENT | L20: =IF(ISNA(VLOOKUP(F20,Table_GAAP02A[[#All],[Agency]:[Hier1]],3,FALSE)),"Abolished Agency",(VLOOKUP(F20,Table_GAAP02A[[#All],[Agency]:[Hier1]],3,FALSE))) -> JUDICIARY | M20: =IF(ISNA(VLOOKUP(G20,GAAP02F[[#All],[Column1]:[FundName]],2,FALSE)),"Leases",(VLOOKUP(G20,GAAP02F[[#All],[Column1]:[FundName]],2,FALSE))) -> IMMEDIATE & CRITICAL NEEDS | N20: 0 | O20: 0 | P20: 0 | Q20: 0 | R20: 0 | S20: 0 | T20: =SUM(N20:S20) -> 0 | U20: 0 | V20: 0 | W20: 0 | X20: 0 | Y20: =SUM(U20:X20) -> 0 | Z20: 0 | AA20: 0 | AB20: 0 | AC20: 0 | AD20: =SUM(Z20:AC20) -> 0 | AE20: =N20 +U20-Z20 -> 0 | AF20: =O20 +V20-AA20 -> 0 | AG20: =P20 +W20-AB20 -> 0 | AH20: =Q20 +X20-AC20 -> 0 | AI20: =R20 -> 0 | AJ20: =S20 -> 0 | AK20: =SUM(AE20:AJ20) -> 0
A21: 19 | C21: F | F21: 0280 | G21: 0001 | H21: =F21&G21 -> 02800001 | I21: =IF(ISNA(VLOOKUP(G21,GAAP02F[[#All],[Column1]:[FundHier1]],5,FALSE)),"Leases",(VLOOKUP(G21,GAAP02F[[#All],[Column1]:[FundHier1]],5,FALSE))) -> 100 | J21: =IF(ISNA(VLOOKUP(F21,Table_GAAP02A[[#All],[Agency]:[Hier1]],4,FALSE)),"Abolished Agency",(VLOOKUP(F21,Table_GAAP02A[[#All],[Agency]:[Hier1]],4,FALSE))) -> 0808 | K21: =IF(ISNA(VLOOKUP(F21,Table_GAAP02A[[#All],[Agency]:[Hier1]],2,FALSE)),"Abolished Agency",(VLOOKUP(F21,Table_GAAP02A[[#All],[Agency]:[Hier1]],2,FALSE))) -> GENERAL GOVERNMENT | L21: =IF(ISNA(VLOOKUP(F21,Table_GAAP02A[[#All],[Agency]:[Hier1]],3,FALSE)),"Abolished Agency",(VLOOKUP(F21,Table_GAAP02A[[#All],[Agency]:[Hier1]],3,FALSE))) -> COMM ON JUDICIAL PERFORMANCE | M21: =IF(ISNA(VLOOKUP(G21,GAAP02F[[#All],[Column1]:[FundName]],2,FALSE)),"Leases",(VLOOKUP(G21,GAAP02F[[#All],[Column1]:[FundName]],2,FALSE))) -> GENERAL FUND | N21: 0 | O21: 0 | P21: 0 | Q21: 0 | R21: 0 | S21: 0 | T21: =SUM(N21:S21) -> 0 | U21: 0 | V21: 0 | W21: 0 | X21: 0 | Y21: =SUM(U21:X21) -> 0 | Z21: 0 | AA21: 0 | AB21: 0 | AC21: 0 | AD21: =SUM(Z21:AC21) -> 0 | AE21: =N21 +U21-Z21 -> 0 | AF21: =O21 +V21-AA21 -> 0 | AG21: =P21 +W21-AB21 -> 0 | AH21: =Q21 +X21-AC21 -> 0 | AI21: =R21 -> 0 | AJ21: =S21 -> 0 | AK21: =SUM(AE21:AJ21) -> 0
F22: 0500 | G22: 9740 | H22: =F22&G22 -> 05009740 | I22: =IF(ISNA(VLOOKUP(G22,GAAP02F[[#All],[Column1]:[FundHier1]],5,FALSE)),"Leases",(VLOOKUP(G22,GAAP02F[[#All],[Column1]:[FundHier1]],5,FALSE))) -> 500 | J22: =IF(ISNA(VLOOKUP(F22,Table_GAAP02A[[#All],[Agency]:[Hier1]],4,FALSE)),"Abolished Agency",(VLOOKUP(F22,Table_GAAP02A[[#All],[Agency]:[Hier1]],4,FALSE))) -> 0808 | K22: =IF(ISNA(VLOOKUP(F22,Table_GAAP02A[[#All],[Agency]:[Hier1]],2,FALSE)),"Abolished Agency",(VLOOKUP(F22,Table_GAAP02A[[#All],[Agency]:[Hier1]],2,FALSE))) -> GENERAL GOVERNMENT | L22: =IF(ISNA(VLOOKUP(F22,Table_GAAP02A[[#All],[Agency]:[Hier1]],3,FALSE)),"Abolished Agency",(VLOOKUP(F22,Table_GAAP02A[[#All],[Agency]:[Hier1]],3,FALSE))) -> GOVERNORS OFFICE | M22: =IF(ISNA(VLOOKUP(G22,GAAP02F[[#All],[Column1]:[FundName]],2,FALSE)),"Leases",(VLOOKUP(G22,GAAP02F[[#All],[Column1]:[FundName]],2,FALSE))) -> CENTRAL SERVICE COST RECOVERY | N22: 0 | O22: 0 | P22: 0 | Q22: 0 | R22: 0 | S22: 0 | T22: =SUM(N22:S22) -> 0 | U22: 0 | V22: 0 | W22: 0 | X22: 0 | Y22: =SUM(U22:X22) -> 0 | Z22: 0 | AA22: 0 | AB22: 0 | AC22: 0 | AD22: =SUM(Z22:AC22) -> 0 | AE22: =N22 +U22-Z22 -> 0 | AF22: =O22 +V22-AA22 -> 0 | AG22: =P22 +W22-AB22 -> 0 | AH22: =Q22 +X22-AC22 -> 0 | AI22: =R22 -> 0 | AJ22: =S22 -> 0 | AK22: =SUM(AE22:AJ22) -> 0
A23: 19 | C23: F | F23: 0509 | G23: 0001 | H23: =F23&G23 -> 05090001 | I23: =IF(ISNA(VLOOKUP(G23,GAAP02F[[#All],[Column1]:[FundHier1]],5,FALSE)),"Leases",(VLOOKUP(G23,GAAP02F[[#All],[Column1]:[FundHier1]],5,FALSE))) -> 100 | J23: =IF(ISNA(VLOOKUP(F23,Table_GAAP02A[[#All],[Agency]:[Hier1]],4,FALSE)),"Abolished Agency",(VLOOKUP(F23,Table_GAAP02A[[#All],[Agency]:[Hier1]],4,FALSE))) -> 0808 | K23: =IF(ISNA(VLOOKUP(F23,Table_GAAP02A[[#All],[Agency]:[Hier1]],2,FALSE)),"Abolished Agency",(VLOOKUP(F23,Table_GAAP02A[[#All],[Agency]:[Hier1]],2,FALSE))) -> GENERAL GOVERNMENT | L23: =IF(ISNA(VLOOKUP(F23,Table_GAAP02A[[#All],[Agency]:[Hier1]],3,FALSE)),"Abolished Agency",(VLOOKUP(F23,Table_GAAP02A[[#All],[Agency]:[Hier1]],3,FALSE))) -> GOV OFC OF BUSINESS & ECONOMIC | M23: =IF(ISNA(VLOOKUP(G23,GAAP02F[[#All],[Column1]:[FundName]],2,FALSE)),"Leases",(VLOOKUP(G23,GAAP02F[[#All],[Column1]:[FundName]],2,FALSE))) -> GENERAL FUND | N23: 0 | O23: 0 | P23: 0 | Q23: 0 | R23: 0 | S23: 0 | T23: =SUM(N23:S23) -> 0 | U23: 0 | V23: 0 | W23: 0 | X23: 0 | Y23: =SUM(U23:X23) -> 0 | Z23: 0 | AA23: 0 | AB23: 0 | AC23: 0 | AD23: =SUM(Z23:AC23) -> 0 | AE23: =N23 +U23-Z23 -> 0 | AF23: =O23 +V23-AA23 -> 0 | AG23: =P23 +W23-AB23 -> 0 | AH23: =Q23 +X23-AC23 -> 0 | AI23: =R23 -> 0 | AJ23: =S23 -> 0 | AK23: =SUM(AE23:AJ23) -> 0
A24: 19 | C24: F | F24: 0511 | G24: 0001 | H24: =F24&G24 -> 05110001 | I24: =IF(ISNA(VLOOKUP(G24,GAAP02F[[#All],[Column1]:[FundHier1]],5,FALSE)),"Leases",(VLOOKUP(G24,GAAP02F[[#All],[Column1]:[FundHier1]],5,FALSE))) -> 100 | J24: =IF(ISNA(VLOOKUP(F24,Table_GAAP02A[[#All],[Agency]:[Hier1]],4,FALSE)),"Abolished Agency",(VLOOKUP(F24,Table_GAAP02A[[#All],[Agency]:[Hier1]],4,FALSE))) -> 0808 | K24: =IF(ISNA(VLOOKUP(F24,Table_GAAP02A[[#All],[Agency]:[Hier1]],2,FALSE)),"Abolished Agency",(VLOOKUP(F24,Table_GAAP02A[[#All],[Agency]:[Hier1]],2,FALSE))) -> GENERAL GOVERNMENT | L24: =IF(ISNA(VLOOKUP(F24,Table_GAAP02A[[#All],[Agency]:[Hier1]],3,FALSE)),"Abolished Agency",(VLOOKUP(F24,Table_GAAP02A[[#All],[Agency]:[Hier1]],3,FALSE))) -> SEC FOR GOVERNMENT OPERATIONS | M24: =IF(ISNA(VLOOKUP(G24,GAAP02F[[#All],[Column1]:[FundName]],2,FALSE)),"Leases",(VLOOKUP(G24,GAAP02F[[#All],[Column1]:[FundName]],2,FALSE))) -> GENERAL FUND | N24: 0 | O24: 0 | P24: 0 | Q24: 0 | R24: 0 | S24: 0 | T24: =SUM(N24:S24) -> 0 | U24: 0 | V24: 0 | W24: 0 | X24: 0 | Y24: =SUM(U24:X24) -> 0 | Z24: 0 | AA24: 0 | AB24: 0 | AC24: 0 | AD24: =SUM(Z24:AC24) -> 0 | AE24: =N24 +U24-Z24 -> 0 | AF24: =O24 +V24-AA24 -> 0 | AG24: =P24 +W24-AB24 -> 0 | AH24: =Q24 +X24-AC24 -> 0 | AI24: =R24 -> 0 | AJ24: =S24 -> 0 | AK24: =SUM(AE24:AJ24) -> 0
A25: 19 | C25: F | D25: JR 12/18 | E25: NO SBITA | F25: 0515 | G25: 0001 | H25: =F25&G25 -> 05150001 | I25: =IF(ISNA(VLOOKUP(G25,GAAP02F[[#All],[Column1]:[FundHier1]],5,FALSE)),"Leases",(VLOOKUP(G25,GAAP02F[[#All],[Column1]:[FundHier1]],5,FALSE))) -> 100 | J25: =IF(ISNA(VLOOKUP(F25,Table_GAAP02A[[#All],[Agency]:[Hier1]],4,FALSE)),"Abolished Agency",(VLOOKUP(F25,Table_GAAP02A[[#All],[Agency]:[Hier1]],4,FALSE))) -> 0825 | K25: =IF(ISNA(VLOOKUP(F25,Table_GAAP02A[[#All],[Agency]:[Hier1]],2,FALSE)),"Abolished Agency",(VLOOKUP(F25,Table_GAAP02A[[#All],[Agency]:[Hier1]],2,FALSE))) -> BUS, CONSUMER SERV, HOUSING | L25: =IF(ISNA(VLOOKUP(F25,Table_GAAP02A[[#All],[Agency]:[Hier1]],3,FALSE)),"Abolished Agency",(VLOOKUP(F25,Table_GAAP02A[[#All],[Agency]:[Hier1]],3,FALSE))) -> SEC FOR BUS-CONSUM-SERV & HOUS | M25: =IF(ISNA(VLOOKUP(G25,GAAP02F[[#All],[Column1]:[FundName]],2,FALSE)),"Leases",(VLOOKUP(G25,GAAP02F[[#All],[Column1]:[FundName]],2,FALSE))) -> GENERAL FUND | N25: 0 | O25: 2296229.7 | P25: 0 | Q25: 0 | R25: 0 | S25: 0 | T25: =SUM(N25:S25) -> 2296229.7 | U25: 0 | V25: 0 | W25: 0 | X25: 0 | Y25: =SUM(U25:X25) -> 0 | Z25: 0 | AA25: 0 | AB25: 0 | AC25: 0 | AD25: =SUM(Z25:AC25) -> 0 | AE25: =N25 +U25-Z25 -> 0 | AF25: =O25 +V25-AA25 -> 2296229.7 | AG25: =P25 +W25-AB25 -> 0 | AH25: =Q25 +X25-AC25 -> 0 | AI25: =R25 -> 0 | AJ25: =S25 -> 0 | AK25: =SUM(AE25:AJ25) -> 2296229.7
A26: 19 | C26: F | F26: 0521 | G26: 0042 | H26: =F26&G26 -> 05210042 | I26: =IF(ISNA(VLOOKUP(G26,GAAP02F[[#All],[Column1]:[FundHier1]],5,FALSE)),"Leases",(VLOOKUP(G26,GAAP02F[[#All],[Column1]:[FundHier1]],5,FALSE))) -> 200 | J26: =IF(ISNA(VLOOKUP(F26,Table_GAAP02A[[#All],[Agency]:[Hier1]],4,FALSE)),"Abolished Agency",(VLOOKUP(F26,Table_GAAP02A[[#All],[Agency]:[Hier1]],4,FALSE))) -> 0830 | K26: =IF(ISNA(VLOOKUP(F26,Table_GAAP02A[[#All],[Agency]:[Hier1]],2,FALSE)),"Abolished Agency",(VLOOKUP(F26,Table_GAAP02A[[#All],[Agency]:[Hier1]],2,FALSE))) -> TRANSPORTATION | L26: =IF(ISNA(VLOOKUP(F26,Table_GAAP02A[[#All],[Agency]:[Hier1]],3,FALSE)),"Abolished Agency",(VLOOKUP(F26,Table_GAAP02A[[#All],[Agency]:[Hier1]],3,FALSE))) -> SECRETARY OF TRANSPORTATION AG | M26: =IF(ISNA(VLOOKUP(G26,GAAP02F[[#All],[Column1]:[FundName]],2,FALSE)),"Leases",(VLOOKUP(G26,GAAP02F[[#All],[Column1]:[FundName]],2,FALSE))) -> STATE HIGHWAY ACCOUNT | N26: 0 | O26: 0 | P26: 0 | Q26: 0 | R26: 0 | S26: 0 | T26: =SUM(N26:S26) -> 0 | U26: 0 | V26: 0 | W26: 0 | X26: 0 | Y26: =SUM(U26:X26) -> 0 | Z26: 0 | AA26: 0 | AB26: 0 | AC26: 0 | AD26: =SUM(Z26:AC26) -> 0 | AE26: =N26 +U26-Z26 -> 0 | AF26: =O26 +V26-AA26 -> 0 | AG26: =P26 +W26-AB26 -> 0 | AH26: =Q26 +X26-AC26 -> 0 | AI26: =R26 -> 0 | AJ26: =S26 -> 0 | AK26: =SUM(AE26:AJ26) -> 0
A27: 19 | C27: F | F27: 0521 | G27: 0044 | H27: =F27&G27 -> 05210044 | I27: =IF(ISNA(VLOOKUP(G27,GAAP02F[[#All],[Column1]:[FundHier1]],5,FALSE)),"Leases",(VLOOKUP(G27,GAAP02F[[#All],[Column1]:[FundHier1]],5,FALSE))) -> 200 | J27: =IF(ISNA(VLOOKUP(F27,Table_GAAP02A[[#All],[Agency]:[Hier1]],4,FALSE)),"Abolished Agency",(VLOOKUP(F27,Table_GAAP02A[[#All],[Agency]:[Hier1]],4,FALSE))) -> 0830 | K27: =IF(ISNA(VLOOKUP(F27,Table_GAAP02A[[#All],[Agency]:[Hier1]],2,FALSE)),"Abolished Agency",(VLOOKUP(F27,Table_GAAP02A[[#All],[Agency]:[Hier1]],2,FALSE))) -> TRANSPORTATION | L27: =IF(ISNA(VLOOKUP(F27,Table_GAAP02A[[#All],[Agency]:[Hier1]],3,FALSE)),"Abolished Agency",(VLOOKUP(F27,Table_GAAP02A[[#All],[Agency]:[Hier1]],3,FALSE))) -> SECRETARY OF TRANSPORTATION AG | M27: =IF(ISNA(VLOOKUP(G27,GAAP02F[[#All],[Column1]:[FundName]],2,FALSE)),"Leases",(VLOOKUP(G27,GAAP02F[[#All],[Column1]:[FundName]],2,FALSE))) -> MOTOR VEHICLE ACCOUNT | N27: 0 | O27: 0 | P27: 0 | Q27: 0 | R27: 0 | S27: 0 | T27: =SUM(N27:S27) -> 0 | U27: 0 | V27: 0 | W27: 0 | X27: 0 | Y27: =SUM(U27:X27) -> 0 | Z27: 0 | AA27: 0 | AB27: 0 | AC27: 0 | AD27: =SUM(Z27:AC27) -> 0 | AE27: =N27 +U27-Z27 -> 0 | AF27: =O27 +V27-AA27 -> 0 | AG27: =P27 +W27-AB27 -> 0 | AH27: =Q27 +X27-AC27 -> 0 | AI27: =R27 -> 0 | AJ27: =S27 -> 0 | AK27: =SUM(AE27:AJ27) -> 0
A28: 19 | C28: F | F28: 0521 | G28: 0046 | H28: =F28&G28 -> 05210046 | I28: =IF(ISNA(VLOOKUP(G28,GAAP02F[[#All],[Column1]:[FundHier1]],5,FALSE)),"Leases",(VLOOKUP(G28,GAAP02F[[#All],[Column1]:[FundHier1]],5,FALSE))) -> 200 | J28: =IF(ISNA(VLOOKUP(F28,Table_GAAP02A[[#All],[Agency]:[Hier1]],4,FALSE)),"Abolished Agency",(VLOOKUP(F28,Table_GAAP02A[[#All],[Agency]:[Hier1]],4,FALSE))) -> 0830 | K28: =IF(ISNA(VLOOKUP(F28,Table_GAAP02A[[#All],[Agency]:[Hier1]],2,FALSE)),"Abolished Agency",(VLOOKUP(F28,Table_GAAP02A[[#All],[Agency]:[Hier1]],2,FALSE))) -> TRANSPORTATION | L28: =IF(ISNA(VLOOKUP(F28,Table_GAAP02A[[#All],[Agency]:[Hier1]],3,FALSE)),"Abolished Agency",(VLOOKUP(F28,Table_GAAP02A[[#All],[Agency]:[Hier1]],3,FALSE))) -> SECRETARY OF TRANSPORTATION AG | M28: =IF(ISNA(VLOOKUP(G28,GAAP02F[[#All],[Column1]:[FundName]],2,FALSE)),"Leases",(VLOOKUP(G28,GAAP02F[[#All],[Column1]:[FundName]],2,FALSE))) -> PUBLIC TRANSPORTATION ACCT STF | N28: 0 | O28: 0 | P28: 0 | Q28: 0 | R28: 0 | S28: 0 | T28: =SUM(N28:S28) -> 0 | U28: 0 | V28: 0 | W28: 0 | X28: 0 | Y28: =SUM(U28:X28) -> 0 | Z28: 0 | AA28: 0 | AB28: 0 | AC28: 0 | AD28: =SUM(Z28:AC28) -> 0 | AE28: =N28 +U28-Z28 -> 0 | AF28: =O28 +V28-AA28 -> 0 | AG28: =P28 +W28-AB28 -> 0 | AH28: =Q28 +X28-AC28 -> 0 | AI28: =R28 -> 0 | AJ28: =S28 -> 0 | AK28: =SUM(AE28:AJ28) -> 0
A29: 19 | C29: F | F29: 0521 | G29: 0917 | H29: =F29&G29 -> 05210917 | I29: =IF(ISNA(VLOOKUP(G29,GAAP02F[[#All],[Column1]:[FundHier1]],5,FALSE)),"Leases",(VLOOKUP(G29,GAAP02F[[#All],[Column1]:[FundHier1]],5,FALSE))) -> 400 | J29: =IF(ISNA(VLOOKUP(F29,Table_GAAP02A[[#All],[Agency]:[Hier1]],4,FALSE)),"Abolished Agency",(VLOOKUP(F29,Table_GAAP02A[[#All],[Agency]:[Hier1]],4,FALSE))) -> 0830 | K29: =IF(ISNA(VLOOKUP(F29,Table_GAAP02A[[#All],[Agency]:[Hier1]],2,FALSE)),"Abolished Agency",(VLOOKUP(F29,Table_GAAP02A[[#All],[Agency]:[Hier1]],2,FALSE))) -> TRANSPORTATION | L29: =IF(ISNA(VLOOKUP(F29,Table_GAAP02A[[#All],[Agency]:[Hier1]],3,FALSE)),"Abolished Agency",(VLOOKUP(F29,Table_GAAP02A[[#All],[Agency]:[Hier1]],3,FALSE))) -> SECRETARY OF TRANSPORTATION AG | M29: =IF(ISNA(VLOOKUP(G29,GAAP02F[[#All],[Column1]:[FundName]],2,FALSE)),"Leases",(VLOOKUP(G29,GAAP02F[[#All],[Column1]:[FundName]],2,FALSE))) -> INMATES' WELFARE FUND | N29: 0 | O29: 0 | P29: 0 | Q29: 585419 | R29: 0 | S29: 0 | T29: =SUM(N29:S29) -> 585419 | U29: 0 | V29: 0 | W29: 0 | X29: 0 | Y29: =SUM(U29:X29) -> 0 | Z29: 0 | AA29: 0 | AB29: 0 | AC29: 0 | AD29: =SUM(Z29:AC29) -> 0 | AE29: =N29 +U29-Z29 -> 0 | AF29: =O29 +V29-AA29 -> 0 | AG29: =P29 +W29-AB29 -> 0 | AH29: =Q29 +X29-AC29 -> 585419 | AI29: =R29 -> 0 | AJ29: =S29 -> 0 | AK29: =SUM(AE29:AJ29) -> 585419
A30: 19 | C30: F | F30: 0521 | G30: 6043 | H30: =F30&G30 -> 05216043 | I30: =IF(ISNA(VLOOKUP(G30,GAAP02F[[#All],[Column1]:[FundHier1]],5,FALSE)),"Leases",(VLOOKUP(G30,GAAP02F[[#All],[Column1]:[FundHier1]],5,FALSE))) -> 200 | J30: =IF(ISNA(VLOOKUP(F30,Table_GAAP02A[[#All],[Agency]:[Hier1]],4,FALSE)),"Abolished Agency",(VLOOKUP(F30,Table_GAAP02A[[#All],[Agency]:[Hier1]],4,FALSE))) -> 0830 | K30: =IF(ISNA(VLOOKUP(F30,Table_GAAP02A[[#All],[Agency]:[Hier1]],2,FALSE)),"Abolished Agency",(VLOOKUP(F30,Table_GAAP02A[[#All],[Agency]:[Hier1]],2,FALSE))) -> TRANSPORTATION | L30: =IF(ISNA(VLOOKUP(F30,Table_GAAP02A[[#All],[Agency]:[Hier1]],3,FALSE)),"Abolished Agency",(VLOOKUP(F30,Table_GAAP02A[[#All],[Agency]:[Hier1]],3,FALSE))) -> SECRETARY OF TRANSPORTATION AG | M30: =IF(ISNA(VLOOKUP(G30,GAAP02F[[#All],[Column1]:[FundName]],2,FALSE)),"Leases",(VLOOKUP(G30,GAAP02F[[#All],[Column1]:[FundName]],2,FALSE))) -> HIGH-SPEED PASSENGER TRAIN | N30: 0 | O30: 0 | P30: 0 | Q30: 585419 | R30: 0 | S30: 0 | T30: =SUM(N30:S30) -> 585419 | U30: 0 | V30: 0 | W30: 0 | X30: 0 | Y30: =SUM(U30:X30) -> 0 | Z30: 0 | AA30: 0 | AB30: 0 | AC30: 0 | AD30: =SUM(Z30:AC30) -> 0 | AE30: =N30 +U30-Z30 -> 0 | AF30: =O30 +V30-AA30 -> 0 | AG30: =P30 +W30-AB30 -> 0 | AH30: =Q30 +X30-AC30 -> 585419 | AI30: =R30 -> 0 | AJ30: =S30 -> 0 | AK30: =SUM(AE30:AJ30) -> 585419
A31: 19 | C31: F | F31: 0521 | G31: 9730 | H31: =F31&G31 -> 05219730 | I31: =IF(ISNA(VLOOKUP(G31,GAAP02F[[#All],[Column1]:[FundHier1]],5,FALSE)),"Leases",(VLOOKUP(G31,GAAP02F[[#All],[Column1]:[FundHier1]],5,FALSE))) -> 500 | J31: =IF(ISNA(VLOOKUP(F31,Table_GAAP02A[[#All],[Agency]:[Hier1]],4,FALSE)),"Abolished Agency",(VLOOKUP(F31,Table_GAAP02A[[#All],[Agency]:[Hier1]],4,FALSE))) -> 0830 | K31: =IF(ISNA(VLOOKUP(F31,Table_GAAP02A[[#All],[Agency]:[Hier1]],2,FALSE)),"Abolished Agency",(VLOOKUP(F31,Table_GAAP02A[[#All],[Agency]:[Hier1]],2,FALSE))) -> TRANSPORTATION | L31: =IF(ISNA(VLOOKUP(F31,Table_GAAP02A[[#All],[Agency]:[Hier1]],3,FALSE)),"Abolished Agency",(VLOOKUP(F31,Table_GAAP02A[[#All],[Agency]:[Hier1]],3,FALSE))) -> SECRETARY OF TRANSPORTATION AG | M31: =IF(ISNA(VLOOKUP(G31,GAAP02F[[#All],[Column1]:[FundName]],2,FALSE)),"Leases",(VLOOKUP(G31,GAAP02F[[#All],[Column1]:[FundName]],2,FALSE))) -> TECHNOLOGY SERVICES REVOLVING | N31: 0 | O31: 0 | P31: 0 | Q31: 25927171 | R31: 0 | S31: 0 | T31: =SUM(N31:S31) -> 25927171 | U31: 0 | V31: 0 | W31: 0 | X31: 3919547 | Y31: =SUM(U31:X31) -> 3919547 | Z31: 0 | AA31: 0 | AB31: 0 | AC31: 1486301 | AD31: =SUM(Z31:AC31) -> 1486301 | AE31: =N31 +U31-Z31 -> 0 | AF31: =O31 +V31-AA31 -> 0 | AG31: =P31 +W31-AB31 -> 0 | AH31: =Q31 +X31-AC31 -> 28360417 | AI31: =R31 -> 0 | AJ31: =S31 -> 0 | AK31: =SUM(AE31:AJ31) -> 28360417
A32: 19 | C32: F | D32: JR 12/18 | E32: JR 12/18 | F32: 0530 | G32: 0001 | H32: =F32&G32 -> 05300001 | I32: =IF(ISNA(VLOOKUP(G32,GAAP02F[[#All],[Column1]:[FundHier1]],5,FALSE)),"Leases",(VLOOKUP(G32,GAAP02F[[#All],[Column1]:[FundHier1]],5,FALSE))) -> 100 | J32: =IF(ISNA(VLOOKUP(F32,Table_GAAP02A[[#All],[Agency]:[Hier1]],4,FALSE)),"Abolished Agency",(VLOOKUP(F32,Table_GAAP02A[[#All],[Agency]:[Hier1]],4,FALSE))) -> 0815 | K32: =IF(ISNA(VLOOKUP(F32,Table_GAAP02A[[#All],[Agency]:[Hier1]],2,FALSE)),"Abolished Agency",(VLOOKUP(F32,Table_GAAP02A[[#All],[Agency]:[Hier1]],2,FALSE))) -> HEALTH AND HUMAN SERVICES | L32: =IF(ISNA(VLOOKUP(F32,Table_GAAP02A[[#All],[Agency]:[Hier1]],3,FALSE)),"Abolished Agency",(VLOOKUP(F32,Table_GAAP02A[[#All],[Agency]:[Hier1]],3,FALSE))) -> HEALTH AND WELFARE AGENCY | M32: =IF(ISNA(VLOOKUP(G32,GAAP02F[[#All],[Column1]:[FundName]],2,FALSE)),"Leases",(VLOOKUP(G32,GAAP02F[[#All],[Column1]:[FundName]],2,FALSE))) -> GENERAL FUND | N32: 0 | O32: 733592.64 | P32: 0 | Q32: 199130 | R32: 0 | S32: 0 | T32: =SUM(N32:S32) -> 932722.64 | U32: 0 | V32: 0 | W32: 0 | X32: 0 | Y32: =SUM(U32:X32) -> 0 | Z32: 0 | AA32: 0 | AB32: 0 | AC32: 0 | AD32: =SUM(Z32:AC32) -> 0 | AE32: =N32 +U32-Z32 -> 0 | AF32: =O32 +V32-AA32 -> 733592.64 | AG32: =P32 +W32-AB32 -> 0 | AH32: =Q32 +X32-AC32 -> 199130 | AI32: =R32 -> 0 | AJ32: =S32 -> 0 | AK32: =SUM(AE32:AJ32) -> 932722.64
A33: 19 | C33: F | F33: 0531 | G33: 9745 | H33: =F33&G33 -> 05319745 | I33: =IF(ISNA(VLOOKUP(G33,GAAP02F[[#All],[Column1]:[FundHier1]],5,FALSE)),"Leases",(VLOOKUP(G33,GAAP02F[[#All],[Column1]:[FundHier1]],5,FALSE))) -> 500 | J33: =IF(ISNA(VLOOKUP(F33,Table_GAAP02A[[#All],[Agency]:[Hier1]],4,FALSE)),"Abolished Agency",(VLOOKUP(F33,Table_GAAP02A[[#All],[Agency]:[Hier1]],4,FALSE))) -> 0815 | K33: =IF(ISNA(VLOOKUP(F33,Table_GAAP02A[[#All],[Agency]:[Hier1]],2,FALSE)),"Abolished Agency",(VLOOKUP(F33,Table_GAAP02A[[#All],[Agency]:[Hier1]],2,FALSE))) -> HEALTH AND HUMAN SERVICES | L33: =IF(ISNA(VLOOKUP(F33,Table_GAAP02A[[#All],[Agency]:[Hier1]],3,FALSE)),"Abolished Agency",(VLOOKUP(F33,Table_GAAP02A[[#All],[Agency]:[Hier1]],3,FALSE))) -> OFFICE OF SYSTEM INTEGRATION | M33: =IF(ISNA(VLOOKUP(G33,GAAP02F[[#All],[Column1]:[FundName]],2,FALSE)),"Leases",(VLOOKUP(G33,GAAP02F[[#All],[Column1]:[FundName]],2,FALSE))) -> HEALTH&HUMAN SVCS AUTOMATION | N33: 0 | O33: 0 | P33: 0 | Q33: 0 | R33: 0 | S33: 0 | T33: =SUM(N33:S33) -> 0 | U33: 0 | V33: 0 | W33: 0 | X33: 0 | Y33: =SUM(U33:X33) -> 0 | Z33: 0 | AA33: 0 | AB33: 0 | AC33: 0 | AD33: =SUM(Z33:AC33) -> 0 | AE33: =N33 +U33-Z33 -> 0 | AF33: =O33 +V33-AA33 -> 0 | AG33: =P33 +W33-AB33 -> 0 | AH33: =Q33 +X33-AC33 -> 0 | AI33: =R33 -> 0 | AJ33: =S33 -> 0 | AK33: =SUM(AE33:AJ33) -> 0
A34: 19 | C34: F | F34: 0540 | G34: 0001 | H34: =F34&G34 -> 05400001 | I34: =IF(ISNA(VLOOKUP(G34,GAAP02F[[#All],[Column1]:[FundHier1]],5,FALSE)),"Leases",(VLOOKUP(G34,GAAP02F[[#All],[Column1]:[FundHier1]],5,FALSE))) -> 100 | J34: =IF(ISNA(VLOOKUP(F34,Table_GAAP02A[[#All],[Agency]:[Hier1]],4,FALSE)),"Abolished Agency",(VLOOKUP(F34,Table_GAAP02A[[#All],[Agency]:[Hier1]],4,FALSE))) -> 0820 | K34: =IF(ISNA(VLOOKUP(F34,Table_GAAP02A[[#All],[Agency]:[Hier1]],2,FALSE)),"Abolished Agency",(VLOOKUP(F34,Table_GAAP02A[[#All],[Agency]:[Hier1]],2,FALSE))) -> RESOURCES | L34: =IF(ISNA(VLOOKUP(F34,Table_GAAP02A[[#All],[Agency]:[Hier1]],3,FALSE)),"Abolished Agency",(VLOOKUP(F34,Table_GAAP02A[[#All],[Agency]:[Hier1]],3,FALSE))) -> NATURAL RESOURCES AGENCY, SECY | M34: =IF(ISNA(VLOOKUP(G34,GAAP02F[[#All],[Column1]:[FundName]],2,FALSE)),"Leases",(VLOOKUP(G34,GAAP02F[[#All],[Column1]:[FundName]],2,FALSE))) -> GENERAL FUND | N34: 0 | O34: 0 | P34: 0 | Q34: 0 | R34: 0 | S34: 0 | T34: =SUM(N34:S34) -> 0 | U34: 0 | V34: 0 | W34: 0 | X34: 0 | Y34: =SUM(U34:X34) -> 0 | Z34: 0 | AA34: 0 | AB34: 0 | AC34: 0 | AD34: =SUM(Z34:AC34) -> 0 | AE34: =N34 +U34-Z34 -> 0 | AF34: =O34 +V34-AA34 -> 0 | AG34: =P34 +W34-AB34 -> 0 | AH34: =Q34 +X34-AC34 -> 0 | AI34: =R34 -> 0 | AJ34: =S34 -> 0 | AK34: =SUM(AE34:AJ34) -> 0
A35: 19 | C35: F | F35: 0540 | G35: 0140 | H35: =F35&G35 -> 05400140 | I35: =IF(ISNA(VLOOKUP(G35,GAAP02F[[#All],[Column1]:[FundHier1]],5,FALSE)),"Leases",(VLOOKUP(G35,GAAP02F[[#All],[Column1]:[FundHier1]],5,FALSE))) -> 200 | J35: =IF(ISNA(VLOOKUP(F35,Table_GAAP02A[[#All],[Agency]:[Hier1]],4,FALSE)),"Abolished Agency",(VLOOKUP(F35,Table_GAAP02A[[#All],[Agency]:[Hier1]],4,FALSE))) -> 0820 | K35: =IF(ISNA(VLOOKUP(F35,Table_GAAP02A[[#All],[Agency]:[Hier1]],2,FALSE)),"Abolished Agency",(VLOOKUP(F35,Table_GAAP02A[[#All],[Agency]:[Hier1]],2,FALSE))) -> RESOURCES | L35: =IF(ISNA(VLOOKUP(F35,Table_GAAP02A[[#All],[Agency]:[Hier1]],3,FALSE)),"Abolished Agency",(VLOOKUP(F35,Table_GAAP02A[[#All],[Agency]:[Hier1]],3,FALSE))) -> NATURAL RESOURCES AGENCY, SECY | M35: =IF(ISNA(VLOOKUP(G35,GAAP02F[[#All],[Column1]:[FundName]],2,FALSE)),"Leases",(VLOOKUP(G35,GAAP02F[[#All],[Column1]:[FundName]],2,FALSE))) -> ENVIRONMENTL LICENSE PLATE FD | N35: 0 | O35: 0 | P35: 0 | Q35: 0 | R35: 0 | S35: 0 | T35: =SUM(N35:S35) -> 0 | U35: 0 | V35: 0 | W35: 0 | X35: 0 | Y35: =SUM(U35:X35) -> 0 | Z35: 0 | AA35: 0 | AB35: 0 | AC35: 0 | AD35: =SUM(Z35:AC35) -> 0 | AE35: =N35 +U35-Z35 -> 0 | AF35: =O35 +V35-AA35 -> 0 | AG35: =P35 +W35-AB35 -> 0 | AH35: =Q35 +X35-AC35 -> 0 | AI35: =R35 -> 0 | AJ35: =S35 -> 0 | AK35: =SUM(AE35:AJ35) -> 0
A36: 19 | C36: F | E36: JR 12/20 | F36: 0552 | G36: 0001 | H36: =F36&G36 -> 05520001 | I36: =IF(ISNA(VLOOKUP(G36,GAAP02F[[#All],[Column1]:[FundHier1]],5,FALSE)),"Leases",(VLOOKUP(G36,GAAP02F[[#All],[Column1]:[FundHier1]],5,FALSE))) -> 100 | J36: =IF(ISNA(VLOOKUP(F36,Table_GAAP02A[[#All],[Agency]:[Hier1]],4,FALSE)),"Abolished Agency",(VLOOKUP(F36,Table_GAAP02A[[#All],[Agency]:[Hier1]],4,FALSE))) -> 0808 | K36: =IF(ISNA(VLOOKUP(F36,Table_GAAP02A[[#All],[Agency]:[Hier1]],2,FALSE)),"Abolished Agency",(VLOOKUP(F36,Table_GAAP02A[[#All],[Agency]:[Hier1]],2,FALSE))) -> GENERAL GOVERNMENT | L36: =IF(ISNA(VLOOKUP(F36,Table_GAAP02A[[#All],[Agency]:[Hier1]],3,FALSE)),"Abolished Agency",(VLOOKUP(F36,Table_GAAP02A[[#All],[Agency]:[Hier1]],3,FALSE))) -> OFFICE OF THE INSPECTOR GENERL | M36: =IF(ISNA(VLOOKUP(G36,GAAP02F[[#All],[Column1]:[FundName]],2,FALSE)),"Leases",(VLOOKUP(G36,GAAP02F[[#All],[Column1]:[FundName]],2,FALSE))) -> GENERAL FUND | N36: 0 | O36: 0 | P36: 0 | Q36: 431793.04 | R36: 0 | S36: 0 | T36: =SUM(N36:S36) -> 431793.04 | U36: 0 | V36: 0 | W36: 0 | X36: 0 | Y36: =SUM(U36:X36) -> 0 | Z36: 0 | AA36: 0 | AB36: 0 | AC36: 0 | AD36: =SUM(Z36:AC36) -> 0 | AE36: =N36 +U36-Z36 -> 0 | AF36: =O36 +V36-AA36 -> 0 | AG36: =P36 +W36-AB36 -> 0 | AH36: =Q36 +X36-AC36 -> 431793.04 | AI36: =R36 -> 0 | AJ36: =S36 -> 0 | AK36: =SUM(AE36:AJ36) -> 431793.04
A37: 19 | C37: F | F37: 0555 | G37: 0044 | H37: =F37&G37 -> 05550044 | I37: =IF(ISNA(VLOOKUP(G37,GAAP02F[[#All],[Column1]:[FundHier1]],5,FALSE)),"Leases",(VLOOKUP(G37,GAAP02F[[#All],[Column1]:[FundHier1]],5,FALSE))) -> 200 | J37: =IF(ISNA(VLOOKUP(F37,Table_GAAP02A[[#All],[Agency]:[Hier1]],4,FALSE)),"Abolished Agency",(VLOOKUP(F37,Table_GAAP02A[[#All],[Agency]:[Hier1]],4,FALSE))) -> 0820 | K37: =IF(ISNA(VLOOKUP(F37,Table_GAAP02A[[#All],[Agency]:[Hier1]],2,FALSE)),"Abolished Agency",(VLOOKUP(F37,Table_GAAP02A[[#All],[Agency]:[Hier1]],2,FALSE))) -> RESOURCES | L37: =IF(ISNA(VLOOKUP(F37,Table_GAAP02A[[#All],[Agency]:[Hier1]],3,FALSE)),"Abolished Agency",(VLOOKUP(F37,Table_GAAP02A[[#All],[Agency]:[Hier1]],3,FALSE))) -> ENVIRONMENTAL PROTECTION, SECY | M37: =IF(ISNA(VLOOKUP(G37,GAAP02F[[#All],[Column1]:[FundName]],2,FALSE)),"Leases",(VLOOKUP(G37,GAAP02F[[#All],[Column1]:[FundName]],2,FALSE))) -> MOTOR VEHICLE ACCOUNT | N37: 0 | O37: 0 | P37: 0 | Q37: 0 | R37: 0 | S37: 0 | T37: =SUM(N37:S37) -> 0 | U37: 0 | V37: 0 | W37: 0 | X37: 0 | Y37: =SUM(U37:X37) -> 0 | Z37: 0 | AA37: 0 | AB37: 0 | AC37: 0 | AD37: =SUM(Z37:AC37) -> 0 | AE37: =N37 +U37-Z37 -> 0 | AF37: =O37 +V37-AA37 -> 0 | AG37: =P37 +W37-AB37 -> 0 | AH37: =Q37 +X37-AC37 -> 0 | AI37: =R37 -> 0 | AJ37: =S37 -> 0 | AK37: =SUM(AE37:AJ37) -> 0
A38: 19 | C38: F | F38: 0559 | G38: 0001 | H38: =F38&G38 -> 05590001 | I38: =IF(ISNA(VLOOKUP(G38,GAAP02F[[#All],[Column1]:[FundHier1]],5,FALSE)),"Leases",(VLOOKUP(G38,GAAP02F[[#All],[Column1]:[FundHier1]],5,FALSE))) -> 100 | J38: =IF(ISNA(VLOOKUP(F38,Table_GAAP02A[[#All],[Agency]:[Hier1]],4,FALSE)),"Abolished Agency",(VLOOKUP(F38,Table_GAAP02A[[#All],[Agency]:[Hier1]],4,FALSE))) -> 0815 | K38: =IF(ISNA(VLOOKUP(F38,Table_GAAP02A[[#All],[Agency]:[Hier1]],2,FALSE)),"Abolished Agency",(VLOOKUP(F38,Table_GAAP02A[[#All],[Agency]:[Hier1]],2,FALSE))) -> HEALTH AND HUMAN SERVICES | L38: =IF(ISNA(VLOOKUP(F38,Table_GAAP02A[[#All],[Agency]:[Hier1]],3,FALSE)),"Abolished Agency",(VLOOKUP(F38,Table_GAAP02A[[#All],[Agency]:[Hier1]],3,FALSE))) -> SEC-LABOR-AND-WORKFORCE-DEVLMT | M38: =IF(ISNA(VLOOKUP(G38,GAAP02F[[#All],[Column1]:[FundName]],2,FALSE)),"Leases",(VLOOKUP(G38,GAAP02F[[#All],[Column1]:[FundName]],2,FALSE))) -> GENERAL FUND | N38: 0 | O38: 0 | P38: 0 | Q38: 0 | R38: 0 | S38: 0 | T38: =SUM(N38:S38) -> 0 | U38: 0 | V38: 0 | W38: 0 | X38: 0 | Y38: =SUM(U38:X38) -> 0 | Z38: 0 | AA38: 0 | AB38: 0 | AC38: 0 | AD38: =SUM(Z38:AC38) -> 0 | AE38: =N38 +U38-Z38 -> 0 | AF38: =O38 +V38-AA38 -> 0 | AG38: =P38 +W38-AB38 -> 0 | AH38: =Q38 +X38-AC38 -> 0 | AI38: =R38 -> 0 | AJ38: =S38 -> 0 | AK38: =SUM(AE38:AJ38) -> 0
A39: 19 | C39: F | F39: 0650 | G39: 0001 | H39: =F39&G39 -> 06500001 | I39: =IF(ISNA(VLOOKUP(G39,GAAP02F[[#All],[Column1]:[FundHier1]],5,FALSE)),"Leases",(VLOOKUP(G39,GAAP02F[[#All],[Column1]:[FundHier1]],5,FALSE))) -> 100 | J39: =IF(ISNA(VLOOKUP(F39,Table_GAAP02A[[#All],[Agency]:[Hier1]],4,FALSE)),"Abolished Agency",(VLOOKUP(F39,Table_GAAP02A[[#All],[Agency]:[Hier1]],4,FALSE))) -> 0808 | K39: =IF(ISNA(VLOOKUP(F39,Table_GAAP02A[[#All],[Agency]:[Hier1]],2,FALSE)),"Abolished Agency",(VLOOKUP(F39,Table_GAAP02A[[#All],[Agency]:[Hier1]],2,FALSE))) -> GENERAL GOVERNMENT | L39: =IF(ISNA(VLOOKUP(F39,Table_GAAP02A[[#All],[Agency]:[Hier1]],3,FALSE)),"Abolished Agency",(VLOOKUP(F39,Table_GAAP02A[[#All],[Agency]:[Hier1]],3,FALSE))) -> OFFICE OF PLANNING & RESEARCH | M39: =IF(ISNA(VLOOKUP(G39,GAAP02F[[#All],[Column1]:[FundName]],2,FALSE)),"Leases",(VLOOKUP(G39,GAAP02F[[#All],[Column1]:[FundName]],2,FALSE))) -> GENERAL FUND | N39: 0 | O39: 0 | P39: 0 | Q39: 0 | R39: 0 | S39: 0 | T39: =SUM(N39:S39) -> 0 | U39: 0 | V39: 0 | W39: 0 | X39: 0 | Y39: =SUM(U39:X39) -> 0 | Z39: 0 | AA39: 0 | AB39: 0 | AC39: 0 | AD39: =SUM(Z39:AC39) -> 0 | AE39: =N39 +U39-Z39 -> 0 | AF39: =O39 +V39-AA39 -> 0 | AG39: =P39 +W39-AB39 -> 0 | AH39: =Q39 +X39-AC39 -> 0 | AI39: =R39 -> 0 | AJ39: =S39 -> 0 | AK39: =SUM(AE39:AJ39) -> 0
A40: 19 | C40: F | F40: 0650 | G40: 0890 | H40: =F40&G40 -> 06500890 | I40: =IF(ISNA(VLOOKUP(G40,GAAP02F[[#All],[Column1]:[FundHier1]],5,FALSE)),"Leases",(VLOOKUP(G40,GAAP02F[[#All],[Column1]:[FundHier1]],5,FALSE))) -> 200 | J40: =IF(ISNA(VLOOKUP(F40,Table_GAAP02A[[#All],[Agency]:[Hier1]],4,FALSE)),"Abolished Agency",(VLOOKUP(F40,Table_GAAP02A[[#All],[Agency]:[Hier1]],4,FALSE))) -> 0808 | K40: =IF(ISNA(VLOOKUP(F40,Table_GAAP02A[[#All],[Agency]:[Hier1]],2,FALSE)),"Abolished Agency",(VLOOKUP(F40,Table_GAAP02A[[#All],[Agency]:[Hier1]],2,FALSE))) -> GENERAL GOVERNMENT | L40: =IF(ISNA(VLOOKUP(F40,Table_GAAP02A[[#All],[Agency]:[Hier1]],3,FALSE)),"Abolished Agency",(VLOOKUP(F40,Table_GAAP02A[[#All],[Agency]:[Hier1]],3,FALSE))) -> OFFICE OF PLANNING & RESEARCH | M40: =IF(ISNA(VLOOKUP(G40,GAAP02F[[#All],[Column1]:[FundName]],2,FALSE)),"Leases",(VLOOKUP(G40,GAAP02F[[#All],[Column1]:[FundName]],2,FALSE))) -> FEDERAL TRUST FUND | N40: 0 | O40: 0 | P40: 0 | Q40: 0 | R40: 0 | S40: 0 | T40: =SUM(N40:S40) -> 0 | U40: 0 | V40: 0 | W40: 0 | X40: 0 | Y40: =SUM(U40:X40) -> 0 | Z40: 0 | AA40: 0 | AB40: 0 | AC40: 0 | AD40: =SUM(Z40:AC40) -> 0 | AE40: =N40 +U40-Z40 -> 0 | AF40: =O40 +V40-AA40 -> 0 | AG40: =P40 +W40-AB40 -> 0 | AH40: =Q40 +X40-AC40 -> 0 | AI40: =R40 -> 0 | AJ40: =S40 -> 0 | AK40: =SUM(AE40:AJ40) -> 0
A41: 19 | C41: F | F41: 0650 | G41: 3228 | H41: =F41&G41 -> 06503228 | I41: =IF(ISNA(VLOOKUP(G41,GAAP02F[[#All],[Column1]:[FundHier1]],5,FALSE)),"Leases",(VLOOKUP(G41,GAAP02F[[#All],[Column1]:[FundHier1]],5,FALSE))) -> 200 | J41: =IF(ISNA(VLOOKUP(F41,Table_GAAP02A[[#All],[Agency]:[Hier1]],4,FALSE)),"Abolished Agency",(VLOOKUP(F41,Table_GAAP02A[[#All],[Agency]:[Hier1]],4,FALSE))) -> 0808 | K41: =IF(ISNA(VLOOKUP(F41,Table_GAAP02A[[#All],[Agency]:[Hier1]],2,FALSE)),"Abolished Agency",(VLOOKUP(F41,Table_GAAP02A[[#All],[Agency]:[Hier1]],2,FALSE))) -> GENERAL GOVERNMENT | L41: =IF(ISNA(VLOOKUP(F41,Table_GAAP02A[[#All],[Agency]:[Hier1]],3,FALSE)),"Abolished Agency",(VLOOKUP(F41,Table_GAAP02A[[#All],[Agency]:[Hier1]],3,FALSE))) -> OFFICE OF PLANNING & RESEARCH | M41: =IF(ISNA(VLOOKUP(G41,GAAP02F[[#All],[Column1]:[FundName]],2,FALSE)),"Leases",(VLOOKUP(G41,GAAP02F[[#All],[Column1]:[FundName]],2,FALSE))) -> GREENHOUSE GAS REDUCTION FD | N41: 0 | O41: 0 | P41: 0 | Q41: 0 | R41: 0 | S41: 0 | T41: =SUM(N41:S41) -> 0 | U41: 0 | V41: 0 | W41: 0 | X41: 0 | Y41: =SUM(U41:X41) -> 0 | Z41: 0 | AA41: 0 | AB41: 0 | AC41: 0 | AD41: =SUM(Z41:AC41) -> 0 | AE41: =N41 +U41-Z41 -> 0 | AF41: =O41 +V41-AA41 -> 0 | AG41: =P41 +W41-AB41 -> 0 | AH41: =Q41 +X41-AC41 -> 0 | AI41: =R41 -> 0 | AJ41: =S41 -> 0 | AK41: =SUM(AE41:AJ41) -> 0
A42: 19 | C42: F | F42: 0690 | G42: 0001 | H42: =F42&G42 -> 06900001 | I42: =IF(ISNA(VLOOKUP(G42,GAAP02F[[#All],[Column1]:[FundHier1]],5,FALSE)),"Leases",(VLOOKUP(G42,GAAP02F[[#All],[Column1]:[FundHier1]],5,FALSE))) -> 100 | J42: =IF(ISNA(VLOOKUP(F42,Table_GAAP02A[[#All],[Agency]:[Hier1]],4,FALSE)),"Abolished Agency",(VLOOKUP(F42,Table_GAAP02A[[#All],[Agency]:[Hier1]],4,FALSE))) -> 0808 | K42: =IF(ISNA(VLOOKUP(F42,Table_GAAP02A[[#All],[Agency]:[Hier1]],2,FALSE)),"Abolished Agency",(VLOOKUP(F42,Table_GAAP02A[[#All],[Agency]:[Hier1]],2,FALSE))) -> GENERAL GOVERNMENT | L42: =IF(ISNA(VLOOKUP(F42,Table_GAAP02A[[#All],[Agency]:[Hier1]],3,FALSE)),"Abolished Agency",(VLOOKUP(F42,Table_GAAP02A[[#All],[Agency]:[Hier1]],3,FALSE))) -> CA EMERGENCY MANAGEMENT AGENCY | M42: =IF(ISNA(VLOOKUP(G42,GAAP02F[[#All],[Column1]:[FundName]],2,FALSE)),"Leases",(VLOOKUP(G42,GAAP02F[[#All],[Column1]:[FundName]],2,FALSE))) -> GENERAL FUND | N42: 0 | O42: 0 | P42: 0 | Q42: 0 | R42: 0 | S42: 0 | T42: =SUM(N42:S42) -> 0 | U42: 0 | V42: 0 | W42: 0 | X42: 0 | Y42: =SUM(U42:X42) -> 0 | Z42: 0 | AA42: 0 | AB42: 0 | AC42: 0 | AD42: =SUM(Z42:AC42) -> 0 | AE42: =N42 +U42-Z42 -> 0 | AF42: =O42 +V42-AA42 -> 0 | AG42: =P42 +W42-AB42 -> 0 | AH42: =Q42 +X42-AC42 -> 0 | AI42: =R42 -> 0 | AJ42: =S42 -> 0 | AK42: =SUM(AE42:AJ42) -> 0
A43: 19 | C43: F | F43: 0690 | G43: 0022 | H43: =F43&G43 -> 06900022 | I43: =IF(ISNA(VLOOKUP(G43,GAAP02F[[#All],[Column1]:[FundHier1]],5,FALSE)),"Leases",(VLOOKUP(G43,GAAP02F[[#All],[Column1]:[FundHier1]],5,FALSE))) -> 200 | J43: =IF(ISNA(VLOOKUP(F43,Table_GAAP02A[[#All],[Agency]:[Hier1]],4,FALSE)),"Abolished Agency",(VLOOKUP(F43,Table_GAAP02A[[#All],[Agency]:[Hier1]],4,FALSE))) -> 0808 | K43: =IF(ISNA(VLOOKUP(F43,Table_GAAP02A[[#All],[Agency]:[Hier1]],2,FALSE)),"Abolished Agency",(VLOOKUP(F43,Table_GAAP02A[[#All],[Agency]:[Hier1]],2,FALSE))) -> GENERAL GOVERNMENT | L43: =IF(ISNA(VLOOKUP(F43,Table_GAAP02A[[#All],[Agency]:[Hier1]],3,FALSE)),"Abolished Agency",(VLOOKUP(F43,Table_GAAP02A[[#All],[Agency]:[Hier1]],3,FALSE))) -> CA EMERGENCY MANAGEMENT AGENCY | M43: =IF(ISNA(VLOOKUP(G43,GAAP02F[[#All],[Column1]:[FundName]],2,FALSE)),"Leases",(VLOOKUP(G43,GAAP02F[[#All],[Column1]:[FundName]],2,FALSE))) -> STATE EMERGENCY TEL NO ACCOUNT | N43: 0 | O43: 0 | P43: 0 | Q43: 0 | R43: 0 | S43: 0 | T43: =SUM(N43:S43) -> 0 | U43: 0 | V43: 0 | W43: 0 | X43: 0 | Y43: =SUM(U43:X43) -> 0 | Z43: 0 | AA43: 0 | AB43: 0 | AC43: 0 | AD43: =SUM(Z43:AC43) -> 0 | AE43: =N43 +U43-Z43 -> 0 | AF43: =O43 +V43-AA43 -> 0 | AG43: =P43 +W43-AB43 -> 0 | AH43: =Q43 +X43-AC43 -> 0 | AI43: =R43 -> 0 | AJ43: =S43 -> 0 | AK43: =SUM(AE43:AJ43) -> 0
A44: 19 | C44: F | F44: 0690 | G44: 0029 | H44: =F44&G44 -> 06900029 | I44: =IF(ISNA(VLOOKUP(G44,GAAP02F[[#All],[Column1]:[FundHier1]],5,FALSE)),"Leases",(VLOOKUP(G44,GAAP02F[[#All],[Column1]:[FundHier1]],5,FALSE))) -> 200 | J44: =IF(ISNA(VLOOKUP(F44,Table_GAAP02A[[#All],[Agency]:[Hier1]],4,FALSE)),"Abolished Agency",(VLOOKUP(F44,Table_GAAP02A[[#All],[Agency]:[Hier1]],4,FALSE))) -> 0808 | K44: =IF(ISNA(VLOOKUP(F44,Table_GAAP02A[[#All],[Agency]:[Hier1]],2,FALSE)),"Abolished Agency",(VLOOKUP(F44,Table_GAAP02A[[#All],[Agency]:[Hier1]],2,FALSE))) -> GENERAL GOVERNMENT | L44: =IF(ISNA(VLOOKUP(F44,Table_GAAP02A[[#All],[Agency]:[Hier1]],3,FALSE)),"Abolished Agency",(VLOOKUP(F44,Table_GAAP02A[[#All],[Agency]:[Hier1]],3,FALSE))) -> CA EMERGENCY MANAGEMENT AGENCY | M44: =IF(ISNA(VLOOKUP(G44,GAAP02F[[#All],[Column1]:[FundName]],2,FALSE)),"Leases",(VLOOKUP(G44,GAAP02F[[#All],[Column1]:[FundName]],2,FALSE))) -> NUCLEAR PLANNING ASSMT ACCOUNT | N44: 0 | O44: 0 | P44: 0 | Q44: 0 | R44: 0 | S44: 0 | T44: =SUM(N44:S44) -> 0 | U44: 0 | V44: 0 | W44: 0 | X44: 0 | Y44: =SUM(U44:X44) -> 0 | Z44: 0 | AA44: 0 | AB44: 0 | AC44: 0 | AD44: =SUM(Z44:AC44) -> 0 | AE44: =N44 +U44-Z44 -> 0 | AF44: =O44 +V44-AA44 -> 0 | AG44: =P44 +W44-AB44 -> 0 | AH44: =Q44 +X44-AC44 -> 0 | AI44: =R44 -> 0 | AJ44: =S44 -> 0 | AK44: =SUM(AE44:AJ44) -> 0
A45: 19 | C45: F | F45: 0690 | G45: 0890 | H45: =F45&G45 -> 06900890 | I45: =IF(ISNA(VLOOKUP(G45,GAAP02F[[#All],[Column1]:[FundHier1]],5,FALSE)),"Leases",(VLOOKUP(G45,GAAP02F[[#All],[Column1]:[FundHier1]],5,FALSE))) -> 200 | J45: =IF(ISNA(VLOOKUP(F45,Table_GAAP02A[[#All],[Agency]:[Hier1]],4,FALSE)),"Abolished Agency",(VLOOKUP(F45,Table_GAAP02A[[#All],[Agency]:[Hier1]],4,FALSE))) -> 0808 | K45: =IF(ISNA(VLOOKUP(F45,Table_GAAP02A[[#All],[Agency]:[Hier1]],2,FALSE)),"Abolished Agency",(VLOOKUP(F45,Table_GAAP02A[[#All],[Agency]:[Hier1]],2,FALSE))) -> GENERAL GOVERNMENT | L45: =IF(ISNA(VLOOKUP(F45,Table_GAAP02A[[#All],[Agency]:[Hier1]],3,FALSE)),"Abolished Agency",(VLOOKUP(F45,Table_GAAP02A[[#All],[Agency]:[Hier1]],3,FALSE))) -> CA EMERGENCY MANAGEMENT AGENCY | M45: =IF(ISNA(VLOOKUP(G45,GAAP02F[[#All],[Column1]:[FundName]],2,FALSE)),"Leases",(VLOOKUP(G45,GAAP02F[[#All],[Column1]:[FundName]],2,FALSE))) -> FEDERAL TRUST FUND | N45: 0 | O45: 0 | P45: 0 | Q45: 0 | R45: 0 | S45: 0 | T45: =SUM(N45:S45) -> 0 | U45: 0 | V45: 0 | W45: 0 | X45: 0 | Y45: =SUM(U45:X45) -> 0 | Z45: 0 | AA45: 0 | AB45: 0 | AC45: 0 | AD45: =SUM(Z45:AC45) -> 0 | AE45: =N45 +U45-Z45 -> 0 | AF45: =O45 +V45-AA45 -> 0 | AG45: =P45 +W45-AB45 -> 0 | AH45: =Q45 +X45-AC45 -> 0 | AI45: =R45 -> 0 | AJ45: =S45 -> 0 | AK45: =SUM(AE45:AJ45) -> 0
A46: 19 | C46: F | F46: 0690 | G46: 3034 | H46: =F46&G46 -> 06903034 | I46: =IF(ISNA(VLOOKUP(G46,GAAP02F[[#All],[Column1]:[FundHier1]],5,FALSE)),"Leases",(VLOOKUP(G46,GAAP02F[[#All],[Column1]:[FundHier1]],5,FALSE))) -> 200 | J46: =IF(ISNA(VLOOKUP(F46,Table_GAAP02A[[#All],[Agency]:[Hier1]],4,FALSE)),"Abolished Agency",(VLOOKUP(F46,Table_GAAP02A[[#All],[Agency]:[Hier1]],4,FALSE))) -> 0808 | K46: =IF(ISNA(VLOOKUP(F46,Table_GAAP02A[[#All],[Agency]:[Hier1]],2,FALSE)),"Abolished Agency",(VLOOKUP(F46,Table_GAAP02A[[#All],[Agency]:[Hier1]],2,FALSE))) -> GENERAL GOVERNMENT | L46: =IF(ISNA(VLOOKUP(F46,Table_GAAP02A[[#All],[Agency]:[Hier1]],3,FALSE)),"Abolished Agency",(VLOOKUP(F46,Table_GAAP02A[[#All],[Agency]:[Hier1]],3,FALSE))) -> CA EMERGENCY MANAGEMENT AGENCY | M46: =IF(ISNA(VLOOKUP(G46,GAAP02F[[#All],[Column1]:[FundName]],2,FALSE)),"Leases",(VLOOKUP(G46,GAAP02F[[#All],[Column1]:[FundName]],2,FALSE))) -> ANTITERRORISM FUND | N46: 0 | O46: 0 | P46: 0 | Q46: 0 | R46: 0 | S46: 0 | T46: =SUM(N46:S46) -> 0 | U46: 0 | V46: 0 | W46: 0 | X46: 0 | Y46: =SUM(U46:X46) -> 0 | Z46: 0 | AA46: 0 | AB46: 0 | AC46: 0 | AD46: =SUM(Z46:AC46) -> 0 | AE46: =N46 +U46-Z46 -> 0 | AF46: =O46 +V46-AA46 -> 0 | AG46: =P46 +W46-AB46 -> 0 | AH46: =Q46 +X46-AC46 -> 0 | AI46: =R46 -> 0 | AJ46: =S46 -> 0 | AK46: =SUM(AE46:AJ46) -> 0
A47: 19 | C47: F | F47: 0690 | G47: 3260 | H47: =F47&G47 -> 06903260 | I47: =IF(ISNA(VLOOKUP(G47,GAAP02F[[#All],[Column1]:[FundHier1]],5,FALSE)),"Leases",(VLOOKUP(G47,GAAP02F[[#All],[Column1]:[FundHier1]],5,FALSE))) -> 200 | J47: =IF(ISNA(VLOOKUP(F47,Table_GAAP02A[[#All],[Agency]:[Hier1]],4,FALSE)),"Abolished Agency",(VLOOKUP(F47,Table_GAAP02A[[#All],[Agency]:[Hier1]],4,FALSE))) -> 0808 | K47: =IF(ISNA(VLOOKUP(F47,Table_GAAP02A[[#All],[Agency]:[Hier1]],2,FALSE)),"Abolished Agency",(VLOOKUP(F47,Table_GAAP02A[[#All],[Agency]:[Hier1]],2,FALSE))) -> GENERAL GOVERNMENT | L47: =IF(ISNA(VLOOKUP(F47,Table_GAAP02A[[#All],[Agency]:[Hier1]],3,FALSE)),"Abolished Agency",(VLOOKUP(F47,Table_GAAP02A[[#All],[Agency]:[Hier1]],3,FALSE))) -> CA EMERGENCY MANAGEMENT AGENCY | M47: =IF(ISNA(VLOOKUP(G47,GAAP02F[[#All],[Column1]:[FundName]],2,FALSE)),"Leases",(VLOOKUP(G47,GAAP02F[[#All],[Column1]:[FundName]],2,FALSE))) -> REG RR ACCIDENT P & I RESPONSE | N47: 0 | O47: 0 | P47: 0 | Q47: 0 | R47: 0 | S47: 0 | T47: =SUM(N47:S47) -> 0 | U47: 0 | V47: 0 | W47: 0 | X47: 0 | Y47: =SUM(U47:X47) -> 0 | Z47: 0 | AA47: 0 | AB47: 0 | AC47: 0 | AD47: =SUM(Z47:AC47) -> 0 | AE47: =N47 +U47-Z47 -> 0 | AF47: =O47 +V47-AA47 -> 0 | AG47: =P47 +W47-AB47 -> 0 | AH47: =Q47 +X47-AC47 -> 0 | AI47: =R47 -> 0 | AJ47: =S47 -> 0 | AK47: =SUM(AE47:AJ47) -> 0
C48: F | F48: 0690 | G48: 9751 | H48: =F48&G48 -> 06909751 | I48: =IF(ISNA(VLOOKUP(G48,GAAP02F[[#All],[Column1]:[FundHier1]],5,FALSE)),"Leases",(VLOOKUP(G48,GAAP02F[[#All],[Column1]:[FundHier1]],5,FALSE))) -> 500 | J48: =IF(ISNA(VLOOKUP(F48,Table_GAAP02A[[#All],[Agency]:[Hier1]],4,FALSE)),"Abolished Agency",(VLOOKUP(F48,Table_GAAP02A[[#All],[Agency]:[Hier1]],4,FALSE))) -> 0808 | K48: =IF(ISNA(VLOOKUP(F48,Table_GAAP02A[[#All],[Agency]:[Hier1]],2,FALSE)),"Abolished Agency",(VLOOKUP(F48,Table_GAAP02A[[#All],[Agency]:[Hier1]],2,FALSE))) -> GENERAL GOVERNMENT | L48: =IF(ISNA(VLOOKUP(F48,Table_GAAP02A[[#All],[Agency]:[Hier1]],3,FALSE)),"Abolished Agency",(VLOOKUP(F48,Table_GAAP02A[[#All],[Agency]:[Hier1]],3,FALSE))) -> CA EMERGENCY MANAGEMENT AGENCY | M48: =IF(ISNA(VLOOKUP(G48,GAAP02F[[#All],[Column1]:[FundName]],2,FALSE)),"Leases",(VLOOKUP(G48,GAAP02F[[#All],[Column1]:[FundName]],2,FALSE))) -> PUB SAFETY COMM REVOLVING FUND | N48: 0 | O48: 0 | P48: 0 | Q48: 0 | R48: 0 | S48: 0 | T48: =SUM(N48:S48) -> 0 | U48: 0 | V48: 0 | W48: 0 | X48: 0 | Y48: =SUM(U48:X48) -> 0 | Z48: 0 | AA48: 0 | AB48: 0 | AC48: 0 | AD48: =SUM(Z48:AC48) -> 0 | AE48: =N48 +U48-Z48 -> 0 | AF48: =O48 +V48-AA48 -> 0 | AG48: =P48 +W48-AB48 -> 0 | AH48: =Q48 +X48-AC48 -> 0 | AI48: =R48 -> 0 | AJ48: =S48 -> 0 | AK48: =SUM(AE48:AJ48) -> 0
A49: 19 | C49: D | F49: 0820 | G49: 0001 | H49: =F49&G49 -> 08200001 | I49: =IF(ISNA(VLOOKUP(G49,GAAP02F[[#All],[Column1]:[FundHier1]],5,FALSE)),"Leases",(VLOOKUP(G49,GAAP02F[[#All],[Column1]:[FundHier1]],5,FALSE))) -> 100 | J49: =IF(ISNA(VLOOKUP(F49,Table_GAAP02A[[#All],[Agency]:[Hier1]],4,FALSE)),"Abolished Agency",(VLOOKUP(F49,Table_GAAP02A[[#All],[Agency]:[Hier1]],4,FALSE))) -> 0808 | K49: =IF(ISNA(VLOOKUP(F49,Table_GAAP02A[[#All],[Agency]:[Hier1]],2,FALSE)),"Abolished Agency",(VLOOKUP(F49,Table_GAAP02A[[#All],[Agency]:[Hier1]],2,FALSE))) -> GENERAL GOVERNMENT | L49: =IF(ISNA(VLOOKUP(F49,Table_GAAP02A[[#All],[Agency]:[Hier1]],3,FALSE)),"Abolished Agency",(VLOOKUP(F49,Table_GAAP02A[[#All],[Agency]:[Hier1]],3,FALSE))) -> DEPARTMENT OF JUSTICE | M49: =IF(ISNA(VLOOKUP(G49,GAAP02F[[#All],[Column1]:[FundName]],2,FALSE)),"Leases",(VLOOKUP(G49,GAAP02F[[#All],[Column1]:[FundName]],2,FALSE))) -> GENERAL FUND | N49: 0 | O49: 0 | P49: 0 | Q49: 0 | R49: 0 | S49: 0 | T49: =SUM(N49:S49) -> 0 | U49: 0 | V49: 0 | W49: 0 | X49: 0 | Y49: =SUM(U49:X49) -> 0 | Z49: 0 | AA49: 0 | AB49: 0 | AC49: 0 | AD49: =SUM(Z49:AC49) -> 0 | AE49: =N49 +U49-Z49 -> 0 | AF49: =O49 +V49-AA49 -> 0 | AG49: =P49 +W49-AB49 -> 0 | AH49: =Q49 +X49-AC49 -> 0 | AI49: =R49 -> 0 | AJ49: =S49 -> 0 | AK49: =SUM(AE49:AJ49) -> 0
C50: D | F50: 0820 | G50: 0012 | H50: =F50&G50 -> 08200012 | I50: =IF(ISNA(VLOOKUP(G50,GAAP02F[[#All],[Column1]:[FundHier1]],5,FALSE)),"Leases",(VLOOKUP(G50,GAAP02F[[#All],[Column1]:[FundHier1]],5,FALSE))) -> 200 | J50: =IF(ISNA(VLOOKUP(F50,Table_GAAP02A[[#All],[Agency]:[Hier1]],4,FALSE)),"Abolished Agency",(VLOOKUP(F50,Table_GAAP02A[[#All],[Agency]:[Hier1]],4,FALSE))) -> 0808 | K50: =IF(ISNA(VLOOKUP(F50,Table_GAAP02A[[#All],[Agency]:[Hier1]],2,FALSE)),"Abolished Agency",(VLOOKUP(F50,Table_GAAP02A[[#All],[Agency]:[Hier1]],2,FALSE))) -> GENERAL GOVERNMENT | L50: =IF(ISNA(VLOOKUP(F50,Table_GAAP02A[[#All],[Agency]:[Hier1]],3,FALSE)),"Abolished Agency",(VLOOKUP(F50,Table_GAAP02A[[#All],[Agency]:[Hier1]],3,FALSE))) -> DEPARTMENT OF JUSTICE | M50: =IF(ISNA(VLOOKUP(G50,GAAP02F[[#All],[Column1]:[FundName]],2,FALSE)),"Leases",(VLOOKUP(G50,GAAP02F[[#All],[Column1]:[FundName]],2,FALSE))) -> ATTY GEN ANTITRUST ACCOUNT | N50: 0 | O50: 0 | P50: 0 | Q50: 0 | R50: 0 | S50: 0 | T50: =SUM(N50:S50) -> 0 | U50: 0 | V50: 0 | W50: 0 | X50: 0 | Y50: =SUM(U50:X50) -> 0 | Z50: 0 | AA50: 0 | AB50: 0 | AC50: 0 | AD50: =SUM(Z50:AC50) -> 0 | AE50: =N50 +U50-Z50 -> 0 | AF50: =O50 +V50-AA50 -> 0 | AG50: =P50 +W50-AB50 -> 0 | AH50: =Q50 +X50-AC50 -> 0 | AI50: =R50 -> 0 | AJ50: =S50 -> 0 | AK50: =SUM(AE50:AJ50) -> 0
C51: D | F51: 0820 | G51: 0017 | H51: =F51&G51 -> 08200017 | I51: =IF(ISNA(VLOOKUP(G51,GAAP02F[[#All],[Column1]:[FundHier1]],5,FALSE)),"Leases",(VLOOKUP(G51,GAAP02F[[#All],[Column1]:[FundHier1]],5,FALSE))) -> 200 | J51: =IF(ISNA(VLOOKUP(F51,Table_GAAP02A[[#All],[Agency]:[Hier1]],4,FALSE)),"Abolished Agency",(VLOOKUP(F51,Table_GAAP02A[[#All],[Agency]:[Hier1]],4,FALSE))) -> 0808 | K51: =IF(ISNA(VLOOKUP(F51,Table_GAAP02A[[#All],[Agency]:[Hier1]],2,FALSE)),"Abolished Agency",(VLOOKUP(F51,Table_GAAP02A[[#All],[Agency]:[Hier1]],2,FALSE))) -> GENERAL GOVERNMENT | L51: =IF(ISNA(VLOOKUP(F51,Table_GAAP02A[[#All],[Agency]:[Hier1]],3,FALSE)),"Abolished Agency",(VLOOKUP(F51,Table_GAAP02A[[#All],[Agency]:[Hier1]],3,FALSE))) -> DEPARTMENT OF JUSTICE | M51: =IF(ISNA(VLOOKUP(G51,GAAP02F[[#All],[Column1]:[FundName]],2,FALSE)),"Leases",(VLOOKUP(G51,GAAP02F[[#All],[Column1]:[FundName]],2,FALSE))) -> FINGERPRINT FEES ACCOUNT | N51: 0 | O51: 0 | P51: 0 | Q51: 0 | R51: 0 | S51: 0 | T51: =SUM(N51:S51) -> 0 | U51: 0 | V51: 0 | W51: 0 | X51: 0 | Y51: =SUM(U51:X51) -> 0 | Z51: 0 | AA51: 0 | AB51: 0 | AC51: 0 | AD51: =SUM(Z51:AC51) -> 0 | AE51: =N51 +U51-Z51 -> 0 | AF51: =O51 +V51-AA51 -> 0 | AG51: =P51 +W51-AB51 -> 0 | AH51: =Q51 +X51-AC51 -> 0 | AI51: =R51 -> 0 | AJ51: =S51 -> 0 | AK51: =SUM(AE51:AJ51) -> 0
C52: D | F52: 0820 | G52: 0044 | H52: =F52&G52 -> 08200044 | I52: =IF(ISNA(VLOOKUP(G52,GAAP02F[[#All],[Column1]:[FundHier1]],5,FALSE)),"Leases",(VLOOKUP(G52,GAAP02F[[#All],[Column1]:[FundHier1]],5,FALSE))) -> 200 | J52: =IF(ISNA(VLOOKUP(F52,Table_GAAP02A[[#All],[Agency]:[Hier1]],4,FALSE)),"Abolished Agency",(VLOOKUP(F52,Table_GAAP02A[[#All],[Agency]:[Hier1]],4,FALSE))) -> 0808 | K52: =IF(ISNA(VLOOKUP(F52,Table_GAAP02A[[#All],[Agency]:[Hier1]],2,FALSE)),"Abolished Agency",(VLOOKUP(F52,Table_GAAP02A[[#All],[Agency]:[Hier1]],2,FALSE))) -> GENERAL GOVERNMENT | L52: =IF(ISNA(VLOOKUP(F52,Table_GAAP02A[[#All],[Agency]:[Hier1]],3,FALSE)),"Abolished Agency",(VLOOKUP(F52,Table_GAAP02A[[#All],[Agency]:[Hier1]],3,FALSE))) -> DEPARTMENT OF JUSTICE | M52: =IF(ISNA(VLOOKUP(G52,GAAP02F[[#All],[Column1]:[FundName]],2,FALSE)),"Leases",(VLOOKUP(G52,GAAP02F[[#All],[Column1]:[FundName]],2,FALSE))) -> MOTOR VEHICLE ACCOUNT | N52: 0 | O52: 0 | P52: 0 | Q52: 0 | R52: 0 | S52: 0 | T52: =SUM(N52:S52) -> 0 | U52: 0 | V52: 0 | W52: 0 | X52: 0 | Y52: =SUM(U52:X52) -> 0 | Z52: 0 | AA52: 0 | AB52: 0 | AC52: 0 | AD52: =SUM(Z52:AC52) -> 0 | AE52: =N52 +U52-Z52 -> 0 | AF52: =O52 +V52-AA52 -> 0 | AG52: =P52 +W52-AB52 -> 0 | AH52: =Q52 +X52-AC52 -> 0 | AI52: =R52 -> 0 | AJ52: =S52 -> 0 | AK52: =SUM(AE52:AJ52) -> 0
C53: D | F53: 0820 | G53: 0142 | H53: =F53&G53 -> 08200142 | I53: =IF(ISNA(VLOOKUP(G53,GAAP02F[[#All],[Column1]:[FundHier1]],5,FALSE)),"Leases",(VLOOKUP(G53,GAAP02F[[#All],[Column1]:[FundHier1]],5,FALSE))) -> 200 | J53: =IF(ISNA(VLOOKUP(F53,Table_GAAP02A[[#All],[Agency]:[Hier1]],4,FALSE)),"Abolished Agency",(VLOOKUP(F53,Table_GAAP02A[[#All],[Agency]:[Hier1]],4,FALSE))) -> 0808 | K53: =IF(ISNA(VLOOKUP(F53,Table_GAAP02A[[#All],[Agency]:[Hier1]],2,FALSE)),"Abolished Agency",(VLOOKUP(F53,Table_GAAP02A[[#All],[Agency]:[Hier1]],2,FALSE))) -> GENERAL GOVERNMENT | L53: =IF(ISNA(VLOOKUP(F53,Table_GAAP02A[[#All],[Agency]:[Hier1]],3,FALSE)),"Abolished Agency",(VLOOKUP(F53,Table_GAAP02A[[#All],[Agency]:[Hier1]],3,FALSE))) -> DEPARTMENT OF JUSTICE | M53: =IF(ISNA(VLOOKUP(G53,GAAP02F[[#All],[Column1]:[FundName]],2,FALSE)),"Leases",(VLOOKUP(G53,GAAP02F[[#All],[Column1]:[FundName]],2,FALSE))) -> SEXUAL HABITUAL OFFENDER DOJ | N53: 0 | O53: 0 | P53: 0 | Q53: 0 | R53: 0 | S53: 0 | T53: =SUM(N53:S53) -> 0 | U53: 0 | V53: 0 | W53: 0 | X53: 0 | Y53: =SUM(U53:X53) -> 0 | Z53: 0 | AA53: 0 | AB53: 0 | AC53: 0 | AD53: =SUM(Z53:AC53) -> 0 | AE53: =N53 +U53-Z53 -> 0 | AF53: =O53 +V53-AA53 -> 0 | AG53: =P53 +W53-AB53 -> 0 | AH53: =Q53 +X53-AC53 -> 0 | AI53: =R53 -> 0 | AJ53: =S53 -> 0 | AK53: =SUM(AE53:AJ53) -> 0
C54: D | F54: 0820 | G54: 0158 | H54: =F54&G54 -> 08200158 | I54: =IF(ISNA(VLOOKUP(G54,GAAP02F[[#All],[Column1]:[FundHier1]],5,FALSE)),"Leases",(VLOOKUP(G54,GAAP02F[[#All],[Column1]:[FundHier1]],5,FALSE))) -> 200 | J54: =IF(ISNA(VLOOKUP(F54,Table_GAAP02A[[#All],[Agency]:[Hier1]],4,FALSE)),"Abolished Agency",(VLOOKUP(F54,Table_GAAP02A[[#All],[Agency]:[Hier1]],4,FALSE))) -> 0808 | K54: =IF(ISNA(VLOOKUP(F54,Table_GAAP02A[[#All],[Agency]:[Hier1]],2,FALSE)),"Abolished Agency",(VLOOKUP(F54,Table_GAAP02A[[#All],[Agency]:[Hier1]],2,FALSE))) -> GENERAL GOVERNMENT | L54: =IF(ISNA(VLOOKUP(F54,Table_GAAP02A[[#All],[Agency]:[Hier1]],3,FALSE)),"Abolished Agency",(VLOOKUP(F54,Table_GAAP02A[[#All],[Agency]:[Hier1]],3,FALSE))) -> DEPARTMENT OF JUSTICE | M54: =IF(ISNA(VLOOKUP(G54,GAAP02F[[#All],[Column1]:[FundName]],2,FALSE)),"Leases",(VLOOKUP(G54,GAAP02F[[#All],[Column1]:[FundName]],2,FALSE))) -> TRAVEL SELLER FUND | N54: 0 | O54: 0 | P54: 0 | Q54: 0 | R54: 0 | S54: 0 | T54: =SUM(N54:S54) -> 0 | U54: 0 | V54: 0 | W54: 0 | X54: 0 | Y54: =SUM(U54:X54) -> 0 | Z54: 0 | AA54: 0 | AB54: 0 | AC54: 0 | AD54: =SUM(Z54:AC54) -> 0 | AE54: =N54 +U54-Z54 -> 0 | AF54: =O54 +V54-AA54 -> 0 | AG54: 0 | AH54: =Q54 +X54-AC54 -> 0 | AI54: =R54 -> 0 | AJ54: =S54 -> 0 | AK54: =SUM(AE54:AJ54) -> 0
C55: D | F55: 0820 | G55: 0256 | H55: =F55&G55 -> 08200256 | I55: =IF(ISNA(VLOOKUP(G55,GAAP02F[[#All],[Column1]:[FundHier1]],5,FALSE)),"Leases",(VLOOKUP(G55,GAAP02F[[#All],[Column1]:[FundHier1]],5,FALSE))) -> 200 | J55: =IF(ISNA(VLOOKUP(F55,Table_GAAP02A[[#All],[Agency]:[Hier1]],4,FALSE)),"Abolished Agency",(VLOOKUP(F55,Table_GAAP02A[[#All],[Agency]:[Hier1]],4,FALSE))) -> 0808 | K55: =IF(ISNA(VLOOKUP(F55,Table_GAAP02A[[#All],[Agency]:[Hier1]],2,FALSE)),"Abolished Agency",(VLOOKUP(F55,Table_GAAP02A[[#All],[Agency]:[Hier1]],2,FALSE))) -> GENERAL GOVERNMENT | L55: =IF(ISNA(VLOOKUP(F55,Table_GAAP02A[[#All],[Agency]:[Hier1]],3,FALSE)),"Abolished Agency",(VLOOKUP(F55,Table_GAAP02A[[#All],[Agency]:[Hier1]],3,FALSE))) -> DEPARTMENT OF JUSTICE | M55: =IF(ISNA(VLOOKUP(G55,GAAP02F[[#All],[Column1]:[FundName]],2,FALSE)),"Leases",(VLOOKUP(G55,GAAP02F[[#All],[Column1]:[FundName]],2,FALSE))) -> SEXUAL PREDATOR PUB INFO ACCT | N55: 0 | O55: 0 | P55: 0 | Q55: 0 | R55: 0 | S55: 0 | T55: =SUM(N55:S55) -> 0 | U55: 0 | V55: 0 | W55: 0 | X55: 0 | Y55: =SUM(U55:X55) -> 0 | Z55: 0 | AA55: 0 | AB55: 0 | AC55: 0 | AD55: =SUM(Z55:AC55) -> 0 | AE55: =N55 +U55-Z55 -> 0 | AF55: =O55 +V55-AA55 -> 0 | AG55: =P55 +W55-AB55 -> 0 | AH55: =Q55 +X55-AC55 -> 0 | AI55: =R55 -> 0 | AJ55: =S55 -> 0 | AK55: =SUM(AE55:AJ55) -> 0
C56: D | F56: 0820 | G56: 0367 | H56: =F56&G56 -> 08200367 | I56: =IF(ISNA(VLOOKUP(G56,GAAP02F[[#All],[Column1]:[FundHier1]],5,FALSE)),"Leases",(VLOOKUP(G56,GAAP02F[[#All],[Column1]:[FundHier1]],5,FALSE))) -> 200 | J56: =IF(ISNA(VLOOKUP(F56,Table_GAAP02A[[#All],[Agency]:[Hier1]],4,FALSE)),"Abolished Agency",(VLOOKUP(F56,Table_GAAP02A[[#All],[Agency]:[Hier1]],4,FALSE))) -> 0808 | K56: =IF(ISNA(VLOOKUP(F56,Table_GAAP02A[[#All],[Agency]:[Hier1]],2,FALSE)),"Abolished Agency",(VLOOKUP(F56,Table_GAAP02A[[#All],[Agency]:[Hier1]],2,FALSE))) -> GENERAL GOVERNMENT | L56: =IF(ISNA(VLOOKUP(F56,Table_GAAP02A[[#All],[Agency]:[Hier1]],3,FALSE)),"Abolished Agency",(VLOOKUP(F56,Table_GAAP02A[[#All],[Agency]:[Hier1]],3,FALSE))) -> DEPARTMENT OF JUSTICE | M56: =IF(ISNA(VLOOKUP(G56,GAAP02F[[#All],[Column1]:[FundName]],2,FALSE)),"Leases",(VLOOKUP(G56,GAAP02F[[#All],[Column1]:[FundName]],2,FALSE))) -> INDIAN GAME SPEC DISTR FD | N56: 0 | O56: 0 | P56: 0 | Q56: 0 | R56: 0 | S56: 0 | T56: =SUM(N56:S56) -> 0 | U56: 0 | V56: 0 | W56: 0 | X56: 0 | Y56: =SUM(U56:X56) -> 0 | Z56: 0 | AA56: 0 | AB56: 0 | AC56: 0 | AD56: =SUM(Z56:AC56) -> 0 | AE56: =N56 +U56-Z56 -> 0 | AF56: =O56 +V56-AA56 -> 0 | AG56: =P56 +W56-AB56 -> 0 | AH56: =Q56 +X56-AC56 -> 0 | AI56: =R56 -> 0 | AJ56: =S56 -> 0 | AK56: =SUM(AE56:AJ56) -> 0
C57: D | F57: 0820 | G57: 0378 | H57: =F57&G57 -> 08200378 | I57: =IF(ISNA(VLOOKUP(G57,GAAP02F[[#All],[Column1]:[FundHier1]],5,FALSE)),"Leases",(VLOOKUP(G57,GAAP02F[[#All],[Column1]:[FundHier1]],5,FALSE))) -> 200 | J57: =IF(ISNA(VLOOKUP(F57,Table_GAAP02A[[#All],[Agency]:[Hier1]],4,FALSE)),"Abolished Agency",(VLOOKUP(F57,Table_GAAP02A[[#All],[Agency]:[Hier1]],4,FALSE))) -> 0808 | K57: =IF(ISNA(VLOOKUP(F57,Table_GAAP02A[[#All],[Agency]:[Hier1]],2,FALSE)),"Abolished Agency",(VLOOKUP(F57,Table_GAAP02A[[#All],[Agency]:[Hier1]],2,FALSE))) -> GENERAL GOVERNMENT | L57: =IF(ISNA(VLOOKUP(F57,Table_GAAP02A[[#All],[Agency]:[Hier1]],3,FALSE)),"Abolished Agency",(VLOOKUP(F57,Table_GAAP02A[[#All],[Agency]:[Hier1]],3,FALSE))) -> DEPARTMENT OF JUSTICE | M57: =IF(ISNA(VLOOKUP(G57,GAAP02F[[#All],[Column1]:[FundName]],2,FALSE)),"Leases",(VLOOKUP(G57,GAAP02F[[#All],[Column1]:[FundName]],2,FALSE))) -> ATTORNEY GEN FALSE CLAIMS ACT | N57: 0 | O57: 0 | P57: 0 | Q57: 0 | R57: 0 | S57: 0 | T57: =SUM(N57:S57) -> 0 | U57: 0 | V57: 0 | W57: 0 | X57: 0 | Y57: =SUM(U57:X57) -> 0 | Z57: 0 | AA57: 0 | AB57: 0 | AC57: 0 | AD57: =SUM(Z57:AC57) -> 0 | AE57: =N57 +U57-Z57 -> 0 | AF57: =O57 +V57-AA57 -> 0 | AG57: =P57 +W57-AB57 -> 0 | AH57: =Q57 +X57-AC57 -> 0 | AI57: =R57 -> 0 | AJ57: =S57 -> 0 | AK57: =SUM(AE57:AJ57) -> 0
C58: D | F58: 0820 | G58: 0460 | H58: =F58&G58 -> 08200460 | I58: =IF(ISNA(VLOOKUP(G58,GAAP02F[[#All],[Column1]:[FundHier1]],5,FALSE)),"Leases",(VLOOKUP(G58,GAAP02F[[#All],[Column1]:[FundHier1]],5,FALSE))) -> 200 | J58: =IF(ISNA(VLOOKUP(F58,Table_GAAP02A[[#All],[Agency]:[Hier1]],4,FALSE)),"Abolished Agency",(VLOOKUP(F58,Table_GAAP02A[[#All],[Agency]:[Hier1]],4,FALSE))) -> 0808 | K58: =IF(ISNA(VLOOKUP(F58,Table_GAAP02A[[#All],[Agency]:[Hier1]],2,FALSE)),"Abolished Agency",(VLOOKUP(F58,Table_GAAP02A[[#All],[Agency]:[Hier1]],2,FALSE))) -> GENERAL GOVERNMENT | L58: =IF(ISNA(VLOOKUP(F58,Table_GAAP02A[[#All],[Agency]:[Hier1]],3,FALSE)),"Abolished Agency",(VLOOKUP(F58,Table_GAAP02A[[#All],[Agency]:[Hier1]],3,FALSE))) -> DEPARTMENT OF JUSTICE | M58: =IF(ISNA(VLOOKUP(G58,GAAP02F[[#All],[Column1]:[FundName]],2,FALSE)),"Leases",(VLOOKUP(G58,GAAP02F[[#All],[Column1]:[FundName]],2,FALSE))) -> DEALERS RECORD OF SALE SP ACT | N58: 0 | O58: 0 | P58: 0 | Q58: 0 | R58: 0 | S58: 0 | T58: =SUM(N58:S58) -> 0 | U58: 0 | V58: 0 | W58: 0 | X58: 0 | Y58: =SUM(U58:X58) -> 0 | Z58: 0 | AA58: 0 | AB58: 0 | AC58: 0 | AD58: =SUM(Z58:AC58) -> 0 | AE58: =N58 +U58-Z58 -> 0 | AF58: =O58 +V58-AA58 -> 0 | AG58: =P58 +W58-AB58 -> 0 | AH58: =Q58 +X58-AC58 -> 0 | AI58: =R58 -> 0 | AJ58: =S58 -> 0 | AK58: =SUM(AE58:AJ58) -> 0
C59: D | F59: 0820 | G59: 0566 | H59: =F59&G59 -> 08200566 | I59: =IF(ISNA(VLOOKUP(G59,GAAP02F[[#All],[Column1]:[FundHier1]],5,FALSE)),"Leases",(VLOOKUP(G59,GAAP02F[[#All],[Column1]:[FundHier1]],5,FALSE))) -> 200 | J59: =IF(ISNA(VLOOKUP(F59,Table_GAAP02A[[#All],[Agency]:[Hier1]],4,FALSE)),"Abolished Agency",(VLOOKUP(F59,Table_GAAP02A[[#All],[Agency]:[Hier1]],4,FALSE))) -> 0808 | K59: =IF(ISNA(VLOOKUP(F59,Table_GAAP02A[[#All],[Agency]:[Hier1]],2,FALSE)),"Abolished Agency",(VLOOKUP(F59,Table_GAAP02A[[#All],[Agency]:[Hier1]],2,FALSE))) -> GENERAL GOVERNMENT | L59: =IF(ISNA(VLOOKUP(F59,Table_GAAP02A[[#All],[Agency]:[Hier1]],3,FALSE)),"Abolished Agency",(VLOOKUP(F59,Table_GAAP02A[[#All],[Agency]:[Hier1]],3,FALSE))) -> DEPARTMENT OF JUSTICE | M59: =IF(ISNA(VLOOKUP(G59,GAAP02F[[#All],[Column1]:[FundName]],2,FALSE)),"Leases",(VLOOKUP(G59,GAAP02F[[#All],[Column1]:[FundName]],2,FALSE))) -> CHILD ABUSE FUND, DOJ | N59: 0 | O59: 0 | P59: 0 | Q59: 0 | R59: 0 | S59: 0 | T59: =SUM(N59:S59) -> 0 | U59: 0 | V59: 0 | W59: 0 | X59: 0 | Y59: =SUM(U59:X59) -> 0 | Z59: 0 | AA59: 0 | AB59: 0 | AC59: 0 | AD59: =SUM(Z59:AC59) -> 0 | AE59: =N59 +U59-Z59 -> 0 | AF59: =O59 +V59-AA59 -> 0 | AG59: =P59 +W59-AB59 -> 0 | AH59: =Q59 +X59-AC59 -> 0 | AI59: =R59 -> 0 | AJ59: =S59 -> 0 | AK59: =SUM(AE59:AJ59) -> 0
C60: D | F60: 0820 | G60: 0567 | H60: =F60&G60 -> 08200567 | I60: =IF(ISNA(VLOOKUP(G60,GAAP02F[[#All],[Column1]:[FundHier1]],5,FALSE)),"Leases",(VLOOKUP(G60,GAAP02F[[#All],[Column1]:[FundHier1]],5,FALSE))) -> 200 | J60: =IF(ISNA(VLOOKUP(F60,Table_GAAP02A[[#All],[Agency]:[Hier1]],4,FALSE)),"Abolished Agency",(VLOOKUP(F60,Table_GAAP02A[[#All],[Agency]:[Hier1]],4,FALSE))) -> 0808 | K60: =IF(ISNA(VLOOKUP(F60,Table_GAAP02A[[#All],[Agency]:[Hier1]],2,FALSE)),"Abolished Agency",(VLOOKUP(F60,Table_GAAP02A[[#All],[Agency]:[Hier1]],2,FALSE))) -> GENERAL GOVERNMENT | L60: =IF(ISNA(VLOOKUP(F60,Table_GAAP02A[[#All],[Agency]:[Hier1]],3,FALSE)),"Abolished Agency",(VLOOKUP(F60,Table_GAAP02A[[#All],[Agency]:[Hier1]],3,FALSE))) -> DEPARTMENT OF JUSTICE | M60: =IF(ISNA(VLOOKUP(G60,GAAP02F[[#All],[Column1]:[FundName]],2,FALSE)),"Leases",(VLOOKUP(G60,GAAP02F[[#All],[Column1]:[FundName]],2,FALSE))) -> GAMBLING CONTROL FUND | N60: 0 | O60: 0 | P60: 0 | Q60: 0 | R60: 0 | S60: 0 | T60: =SUM(N60:S60) -> 0 | U60: 0 | V60: 0 | W60: 0 | X60: 0 | Y60: =SUM(U60:X60) -> 0 | Z60: 0 | AA60: 0 | AB60: 0 | AC60: 0 | AD60: =SUM(Z60:AC60) -> 0 | AE60: =N60 +U60-Z60 -> 0 | AF60: =O60 +V60-AA60 -> 0 | AG60: =P60 +W60-AB60 -> 0 | AH60: =Q60 +X60-AC60 -> 0 | AI60: =R60 -> 0 | AJ60: =S60 -> 0 | AK60: =SUM(AE60:AJ60) -> 0
C61: D | F61: 0820 | G61: 0569 | H61: =F61&G61 -> 08200569 | I61: =IF(ISNA(VLOOKUP(G61,GAAP02F[[#All],[Column1]:[FundHier1]],5,FALSE)),"Leases",(VLOOKUP(G61,GAAP02F[[#All],[Column1]:[FundHier1]],5,FALSE))) -> 200 | J61: =IF(ISNA(VLOOKUP(F61,Table_GAAP02A[[#All],[Agency]:[Hier1]],4,FALSE)),"Abolished Agency",(VLOOKUP(F61,Table_GAAP02A[[#All],[Agency]:[Hier1]],4,FALSE))) -> 0808 | K61: =IF(ISNA(VLOOKUP(F61,Table_GAAP02A[[#All],[Agency]:[Hier1]],2,FALSE)),"Abolished Agency",(VLOOKUP(F61,Table_GAAP02A[[#All],[Agency]:[Hier1]],2,FALSE))) -> GENERAL GOVERNMENT | L61: =IF(ISNA(VLOOKUP(F61,Table_GAAP02A[[#All],[Agency]:[Hier1]],3,FALSE)),"Abolished Agency",(VLOOKUP(F61,Table_GAAP02A[[#All],[Agency]:[Hier1]],3,FALSE))) -> DEPARTMENT OF JUSTICE | M61: =IF(ISNA(VLOOKUP(G61,GAAP02F[[#All],[Column1]:[FundName]],2,FALSE)),"Leases",(VLOOKUP(G61,GAAP02F[[#All],[Column1]:[FundName]],2,FALSE))) -> GAMBLING CONTROL FINES & PENT | N61: 0 | O61: 0 | P61: 0 | Q61: 0 | R61: 0 | S61: 0 | T61: =SUM(N61:S61) -> 0 | U61: 0 | V61: 0 | W61: 0 | X61: 0 | Y61: =SUM(U61:X61) -> 0 | Z61: 0 | AA61: 0 | AB61: 0 | AC61: 0 | AD61: =SUM(Z61:AC61) -> 0 | AE61: =N61 +U61-Z61 -> 0 | AF61: =O61 +V61-AA61 -> 0 | AG61: =P61 +W61-AB61 -> 0 | AH61: =Q61 +X61-AC61 -> 0 | AI61: =R61 -> 0 | AJ61: =S61 -> 0 | AK61: =SUM(AE61:AJ61) -> 0
C62: D | F62: 0820 | G62: 0890 | H62: =F62&G62 -> 08200890 | I62: =IF(ISNA(VLOOKUP(G62,GAAP02F[[#All],[Column1]:[FundHier1]],5,FALSE)),"Leases",(VLOOKUP(G62,GAAP02F[[#All],[Column1]:[FundHier1]],5,FALSE))) -> 200 | J62: =IF(ISNA(VLOOKUP(F62,Table_GAAP02A[[#All],[Agency]:[Hier1]],4,FALSE)),"Abolished Agency",(VLOOKUP(F62,Table_GAAP02A[[#All],[Agency]:[Hier1]],4,FALSE))) -> 0808 | K62: =IF(ISNA(VLOOKUP(F62,Table_GAAP02A[[#All],[Agency]:[Hier1]],2,FALSE)),"Abolished Agency",(VLOOKUP(F62,Table_GAAP02A[[#All],[Agency]:[Hier1]],2,FALSE))) -> GENERAL GOVERNMENT | L62: =IF(ISNA(VLOOKUP(F62,Table_GAAP02A[[#All],[Agency]:[Hier1]],3,FALSE)),"Abolished Agency",(VLOOKUP(F62,Table_GAAP02A[[#All],[Agency]:[Hier1]],3,FALSE))) -> DEPARTMENT OF JUSTICE | M62: =IF(ISNA(VLOOKUP(G62,GAAP02F[[#All],[Column1]:[FundName]],2,FALSE)),"Leases",(VLOOKUP(G62,GAAP02F[[#All],[Column1]:[FundName]],2,FALSE))) -> FEDERAL TRUST FUND | N62: 0 | O62: 0 | P62: 0 | Q62: 0 | R62: 0 | S62: 0 | T62: =SUM(N62:S62) -> 0 | U62: 0 | V62: 0 | W62: 0 | X62: 0 | Y62: =SUM(U62:X62) -> 0 | Z62: 0 | AA62: 0 | AB62: 0 | AC62: 0 | AD62: =SUM(Z62:AC62) -> 0 | AE62: =N62 +U62-Z62 -> 0 | AF62: =O62 +V62-AA62 -> 0 | AG62: =P62 +W62-AB62 -> 0 | AH62: =Q62 +X62-AC62 -> 0 | AI62: =R62 -> 0 | AJ62: =S62 -> 0 | AK62: =SUM(AE62:AJ62) -> 0
C63: D | F63: 0820 | G63: 1008 | H63: =F63&G63 -> 08201008 | I63: =IF(ISNA(VLOOKUP(G63,GAAP02F[[#All],[Column1]:[FundHier1]],5,FALSE)),"Leases",(VLOOKUP(G63,GAAP02F[[#All],[Column1]:[FundHier1]],5,FALSE))) -> 200 | J63: =IF(ISNA(VLOOKUP(F63,Table_GAAP02A[[#All],[Agency]:[Hier1]],4,FALSE)),"Abolished Agency",(VLOOKUP(F63,Table_GAAP02A[[#All],[Agency]:[Hier1]],4,FALSE))) -> 0808 | K63: =IF(ISNA(VLOOKUP(F63,Table_GAAP02A[[#All],[Agency]:[Hier1]],2,FALSE)),"Abolished Agency",(VLOOKUP(F63,Table_GAAP02A[[#All],[Agency]:[Hier1]],2,FALSE))) -> GENERAL GOVERNMENT | L63: =IF(ISNA(VLOOKUP(F63,Table_GAAP02A[[#All],[Agency]:[Hier1]],3,FALSE)),"Abolished Agency",(VLOOKUP(F63,Table_GAAP02A[[#All],[Agency]:[Hier1]],3,FALSE))) -> DEPARTMENT OF JUSTICE | M63: =IF(ISNA(VLOOKUP(G63,GAAP02F[[#All],[Column1]:[FundName]],2,FALSE)),"Leases",(VLOOKUP(G63,GAAP02F[[#All],[Column1]:[FundName]],2,FALSE))) -> FIRFARMS SAFETY & ENFORCEMENT | N63: 0 | O63: 0 | P63: 0 | Q63: 0 | R63: 0 | S63: 0 | T63: =SUM(N63:S63) -> 0 | U63: 0 | V63: 0 | W63: 0 | X63: 0 | Y63: =SUM(U63:X63) -> 0 | Z63: 0 | AA63: 0 | AB63: 0 | AC63: 0 | AD63: =SUM(Z63:AC63) -> 0 | AE63: =N63 +U63-Z63 -> 0 | AF63: =O63 +V63-AA63 -> 0 | AG63: =P63 +W63-AB63 -> 0 | AH63: =Q63 +X63-AC63 -> 0 | AI63: =R63 -> 0 | AJ63: =S63 -> 0 | AK63: =SUM(AE63:AJ63) -> 0
C64: D | F64: 0820 | G64: 3016 | H64: =F64&G64 -> 08203016 | I64: =IF(ISNA(VLOOKUP(G64,GAAP02F[[#All],[Column1]:[FundHier1]],5,FALSE)),"Leases",(VLOOKUP(G64,GAAP02F[[#All],[Column1]:[FundHier1]],5,FALSE))) -> 200 | J64: =IF(ISNA(VLOOKUP(F64,Table_GAAP02A[[#All],[Agency]:[Hier1]],4,FALSE)),"Abolished Agency",(VLOOKUP(F64,Table_GAAP02A[[#All],[Agency]:[Hier1]],4,FALSE))) -> 0808 | K64: =IF(ISNA(VLOOKUP(F64,Table_GAAP02A[[#All],[Agency]:[Hier1]],2,FALSE)),"Abolished Agency",(VLOOKUP(F64,Table_GAAP02A[[#All],[Agency]:[Hier1]],2,FALSE))) -> GENERAL GOVERNMENT | L64: =IF(ISNA(VLOOKUP(F64,Table_GAAP02A[[#All],[Agency]:[Hier1]],3,FALSE)),"Abolished Agency",(VLOOKUP(F64,Table_GAAP02A[[#All],[Agency]:[Hier1]],3,FALSE))) -> DEPARTMENT OF JUSTICE | M64: =IF(ISNA(VLOOKUP(G64,GAAP02F[[#All],[Column1]:[FundName]],2,FALSE)),"Leases",(VLOOKUP(G64,GAAP02F[[#All],[Column1]:[FundName]],2,FALSE))) -> MISSING PERSONS DNA DATA BASE | N64: 0 | O64: 0 | P64: 0 | Q64: 0 | R64: 0 | S64: 0 | T64: =SUM(N64:S64) -> 0 | U64: 0 | V64: 0 | W64: 0 | X64: 0 | Y64: =SUM(U64:X64) -> 0 | Z64: 0 | AA64: 0 | AB64: 0 | AC64: 0 | AD64: =SUM(Z64:AC64) -> 0 | AF64: =O64 +V64-AA64 -> 0 | AH64: =Q64 +X64-AC64 -> 0 | AI64: =R64 -> 0 | AJ64: =S64 -> 0 | AK64: =SUM(AE64:AJ64) -> 0
C65: D | F65: 0820 | G65: 3053 | H65: =F65&G65 -> 08203053 | I65: =IF(ISNA(VLOOKUP(G65,GAAP02F[[#All],[Column1]:[FundHier1]],5,FALSE)),"Leases",(VLOOKUP(G65,GAAP02F[[#All],[Column1]:[FundHier1]],5,FALSE))) -> 200 | J65: =IF(ISNA(VLOOKUP(F65,Table_GAAP02A[[#All],[Agency]:[Hier1]],4,FALSE)),"Abolished Agency",(VLOOKUP(F65,Table_GAAP02A[[#All],[Agency]:[Hier1]],4,FALSE))) -> 0808 | K65: =IF(ISNA(VLOOKUP(F65,Table_GAAP02A[[#All],[Agency]:[Hier1]],2,FALSE)),"Abolished Agency",(VLOOKUP(F65,Table_GAAP02A[[#All],[Agency]:[Hier1]],2,FALSE))) -> GENERAL GOVERNMENT | L65: =IF(ISNA(VLOOKUP(F65,Table_GAAP02A[[#All],[Agency]:[Hier1]],3,FALSE)),"Abolished Agency",(VLOOKUP(F65,Table_GAAP02A[[#All],[Agency]:[Hier1]],3,FALSE))) -> DEPARTMENT OF JUSTICE | M65: =IF(ISNA(VLOOKUP(G65,GAAP02F[[#All],[Column1]:[FundName]],2,FALSE)),"Leases",(VLOOKUP(G65,GAAP02F[[#All],[Column1]:[FundName]],2,FALSE))) -> PUB RGHT LAW ENFORC SP FUND | N65: 0 | O65: 0 | P65: 0 | Q65: 0 | R65: 0 | S65: 0 | T65: =SUM(N65:S65) -> 0 | U65: 0 | V65: 0 | W65: 0 | X65: 0 | Y65: =SUM(U65:X65) -> 0 | Z65: 0 | AA65: 0 | AB65: 0 | AC65: 0 | AD65: =SUM(Z65:AC65) -> 0 | AE65: =N65 +U65-Z65 -> 0 | AF65: =O65 +V65-AA65 -> 0 | AG65: =P65 +W65-AB65 -> 0 | AH65: =Q65 +X65-AC65 -> 0 | AI65: =R65 -> 0 | AJ65: =S65 -> 0 | AK65: =SUM(AE65:AJ65) -> 0
C66: D | F66: 0820 | G66: 3086 | H66: =F66&G66 -> 08203086 | I66: =IF(ISNA(VLOOKUP(G66,GAAP02F[[#All],[Column1]:[FundHier1]],5,FALSE)),"Leases",(VLOOKUP(G66,GAAP02F[[#All],[Column1]:[FundHier1]],5,FALSE))) -> 200 | J66: =IF(ISNA(VLOOKUP(F66,Table_GAAP02A[[#All],[Agency]:[Hier1]],4,FALSE)),"Abolished Agency",(VLOOKUP(F66,Table_GAAP02A[[#All],[Agency]:[Hier1]],4,FALSE))) -> 0808 | K66: =IF(ISNA(VLOOKUP(F66,Table_GAAP02A[[#All],[Agency]:[Hier1]],2,FALSE)),"Abolished Agency",(VLOOKUP(F66,Table_GAAP02A[[#All],[Agency]:[Hier1]],2,FALSE))) -> GENERAL GOVERNMENT | L66: =IF(ISNA(VLOOKUP(F66,Table_GAAP02A[[#All],[Agency]:[Hier1]],3,FALSE)),"Abolished Agency",(VLOOKUP(F66,Table_GAAP02A[[#All],[Agency]:[Hier1]],3,FALSE))) -> DEPARTMENT OF JUSTICE | M66: =IF(ISNA(VLOOKUP(G66,GAAP02F[[#All],[Column1]:[FundName]],2,FALSE)),"Leases",(VLOOKUP(G66,GAAP02F[[#All],[Column1]:[FundName]],2,FALSE))) -> DNA IDENTIFICATION | N66: 0 | O66: 0 | P66: 0 | Q66: 0 | R66: 0 | S66: 0 | T66: =SUM(N66:S66) -> 0 | U66: 0 | V66: 0 | W66: 0 | X66: 0 | Y66: =SUM(U66:X66) -> 0 | Z66: 0 | AA66: 0 | AB66: 0 | AC66: 0 | AD66: =SUM(Z66:AC66) -> 0 | AE66: =N66 +U66-Z66 -> 0 | AF66: =O66 +V66-AA66 -> 0 | AG66: =P66 +W66-AB66 -> 0 | AH66: =Q66 +X66-AC66 -> 0 | AI66: =R66 -> 0 | AJ66: =S66 -> 0 | AK66: =SUM(AE66:AJ66) -> 0
C67: D | F67: 0820 | G67: 3087 | H67: =F67&G67 -> 08203087 | I67: =IF(ISNA(VLOOKUP(G67,GAAP02F[[#All],[Column1]:[FundHier1]],5,FALSE)),"Leases",(VLOOKUP(G67,GAAP02F[[#All],[Column1]:[FundHier1]],5,FALSE))) -> 200 | J67: =IF(ISNA(VLOOKUP(F67,Table_GAAP02A[[#All],[Agency]:[Hier1]],4,FALSE)),"Abolished Agency",(VLOOKUP(F67,Table_GAAP02A[[#All],[Agency]:[Hier1]],4,FALSE))) -> 0808 | K67: =IF(ISNA(VLOOKUP(F67,Table_GAAP02A[[#All],[Agency]:[Hier1]],2,FALSE)),"Abolished Agency",(VLOOKUP(F67,Table_GAAP02A[[#All],[Agency]:[Hier1]],2,FALSE))) -> GENERAL GOVERNMENT | L67: =IF(ISNA(VLOOKUP(F67,Table_GAAP02A[[#All],[Agency]:[Hier1]],3,FALSE)),"Abolished Agency",(VLOOKUP(F67,Table_GAAP02A[[#All],[Agency]:[Hier1]],3,FALSE))) -> DEPARTMENT OF JUSTICE | M67: =IF(ISNA(VLOOKUP(G67,GAAP02F[[#All],[Column1]:[FundName]],2,FALSE)),"Leases",(VLOOKUP(G67,GAAP02F[[#All],[Column1]:[FundName]],2,FALSE))) -> UNFAIR COMPETITION LAW FUND | N67: 0 | O67: 0 | P67: 0 | Q67: 0 | R67: 0 | S67: 0 | T67: =SUM(N67:S67) -> 0 | U67: 0 | V67: 0 | W67: 0 | X67: 0 | Y67: =SUM(U67:X67) -> 0 | Z67: 0 | AA67: 0 | AB67: 0 | AC67: 0 | AD67: =SUM(Z67:AC67) -> 0 | AE67: =N67 +U67-Z67 -> 0 | AF67: =O67 +V67-AA67 -> 0 | AG67: =P67 +W67-AB67 -> 0 | AH67: =Q67 +X67-AC67 -> 0 | AI67: =R67 -> 0 | AJ67: =S67 -> 0 | AK67: =SUM(AE67:AJ67) -> 0
C68: D | F68: 0820 | G68: 3088 | H68: =F68&G68 -> 08203088 | I68: =IF(ISNA(VLOOKUP(G68,GAAP02F[[#All],[Column1]:[FundHier1]],5,FALSE)),"Leases",(VLOOKUP(G68,GAAP02F[[#All],[Column1]:[FundHier1]],5,FALSE))) -> 200 | J68: =IF(ISNA(VLOOKUP(F68,Table_GAAP02A[[#All],[Agency]:[Hier1]],4,FALSE)),"Abolished Agency",(VLOOKUP(F68,Table_GAAP02A[[#All],[Agency]:[Hier1]],4,FALSE))) -> 0808 | K68: =IF(ISNA(VLOOKUP(F68,Table_GAAP02A[[#All],[Agency]:[Hier1]],2,FALSE)),"Abolished Agency",(VLOOKUP(F68,Table_GAAP02A[[#All],[Agency]:[Hier1]],2,FALSE))) -> GENERAL GOVERNMENT | L68: =IF(ISNA(VLOOKUP(F68,Table_GAAP02A[[#All],[Agency]:[Hier1]],3,FALSE)),"Abolished Agency",(VLOOKUP(F68,Table_GAAP02A[[#All],[Agency]:[Hier1]],3,FALSE))) -> DEPARTMENT OF JUSTICE | M68: =IF(ISNA(VLOOKUP(G68,GAAP02F[[#All],[Column1]:[FundName]],2,FALSE)),"Leases",(VLOOKUP(G68,GAAP02F[[#All],[Column1]:[FundName]],2,FALSE))) -> REGISTRY OF CHARITABLE TRUSTS | N68: 0 | O68: 0 | P68: 0 | Q68: 0 | R68: 0 | S68: 0 | T68: =SUM(N68:S68) -> 0 | U68: 0 | V68: 0 | W68: 0 | X68: 0 | Y68: =SUM(U68:X68) -> 0 | Z68: 0 | AA68: 0 | AB68: 0 | AC68: 0 | AD68: =SUM(Z68:AC68) -> 0 | AE68: =N68 +U68-Z68 -> 0 | AF68: =O68 +V68-AA68 -> 0 | AG68: =P68 +W68-AB68 -> 0 | AH68: =Q68 +X68-AC68 -> 0 | AI68: =R68 -> 0 | AJ68: =S68 -> 0 | AK68: =SUM(AE68:AJ68) -> 0
C69: D | F69: 0820 | G69: 3297 | H69: =F69&G69 -> 08203297 | I69: =IF(ISNA(VLOOKUP(G69,GAAP02F[[#All],[Column1]:[FundHier1]],5,FALSE)),"Leases",(VLOOKUP(G69,GAAP02F[[#All],[Column1]:[FundHier1]],5,FALSE))) -> 200 | J69: =IF(ISNA(VLOOKUP(F69,Table_GAAP02A[[#All],[Agency]:[Hier1]],4,FALSE)),"Abolished Agency",(VLOOKUP(F69,Table_GAAP02A[[#All],[Agency]:[Hier1]],4,FALSE))) -> 0808 | K69: =IF(ISNA(VLOOKUP(F69,Table_GAAP02A[[#All],[Agency]:[Hier1]],2,FALSE)),"Abolished Agency",(VLOOKUP(F69,Table_GAAP02A[[#All],[Agency]:[Hier1]],2,FALSE))) -> GENERAL GOVERNMENT | L69: =IF(ISNA(VLOOKUP(F69,Table_GAAP02A[[#All],[Agency]:[Hier1]],3,FALSE)),"Abolished Agency",(VLOOKUP(F69,Table_GAAP02A[[#All],[Agency]:[Hier1]],3,FALSE))) -> DEPARTMENT OF JUSTICE | M69: =IF(ISNA(VLOOKUP(G69,GAAP02F[[#All],[Column1]:[FundName]],2,FALSE)),"Leases",(VLOOKUP(G69,GAAP02F[[#All],[Column1]:[FundName]],2,FALSE))) -> MAJOR LEAGUE SPORT EVENT RAFFL | N69: 0 | O69: 0 | P69: 0 | Q69: 0 | R69: 0 | S69: 0 | T69: =SUM(N69:S69) -> 0 | U69: 0 | V69: 0 | W69: 0 | X69: 0 | Y69: =SUM(U69:X69) -> 0 | Z69: 0 | AA69: 0 | AB69: 0 | AC69: 0 | AD69: =SUM(Z69:AC69) -> 0 | AE69: =N69 +U69-Z69 -> 0 | AF69: =O69 +V69-AA69 -> 0 | AG69: =P69 +W69-AB69 -> 0 | AH69: =Q69 +X69-AC69 -> 0 | AI69: =R69 -> 0 | AJ69: =S69 -> 0 | AK69: =SUM(AE69:AJ69) -> 0
C70: D | F70: 0820 | G70: 3320 | H70: =F70&G70 -> 08203320 | I70: =IF(ISNA(VLOOKUP(G70,GAAP02F[[#All],[Column1]:[FundHier1]],5,FALSE)),"Leases",(VLOOKUP(G70,GAAP02F[[#All],[Column1]:[FundHier1]],5,FALSE))) -> 200 | J70: =IF(ISNA(VLOOKUP(F70,Table_GAAP02A[[#All],[Agency]:[Hier1]],4,FALSE)),"Abolished Agency",(VLOOKUP(F70,Table_GAAP02A[[#All],[Agency]:[Hier1]],4,FALSE))) -> 0808 | K70: =IF(ISNA(VLOOKUP(F70,Table_GAAP02A[[#All],[Agency]:[Hier1]],2,FALSE)),"Abolished Agency",(VLOOKUP(F70,Table_GAAP02A[[#All],[Agency]:[Hier1]],2,FALSE))) -> GENERAL GOVERNMENT | L70: =IF(ISNA(VLOOKUP(F70,Table_GAAP02A[[#All],[Agency]:[Hier1]],3,FALSE)),"Abolished Agency",(VLOOKUP(F70,Table_GAAP02A[[#All],[Agency]:[Hier1]],3,FALSE))) -> DEPARTMENT OF JUSTICE | M70: =IF(ISNA(VLOOKUP(G70,GAAP02F[[#All],[Column1]:[FundName]],2,FALSE)),"Leases",(VLOOKUP(G70,GAAP02F[[#All],[Column1]:[FundName]],2,FALSE))) -> DOJ, TOBACCO LAW ENFOR ACCT | N70: 0 | O70: 0 | P70: 0 | Q70: 0 | R70: 0 | S70: 0 | T70: =SUM(N70:S70) -> 0 | U70: 0 | V70: 0 | W70: 0 | X70: 0 | Y70: =SUM(U70:X70) -> 0 | Z70: 0 | AA70: 0 | AB70: 0 | AC70: 0 | AD70: =SUM(Z70:AC70) -> 0 | AE70: =N70 +U70-Z70 -> 0 | AF70: =O70 +V70-AA70 -> 0 | AG70: =P70 +W70-AB70 -> 0 | AH70: =Q70 +X70-AC70 -> 0 | AI70: =R70 -> 0 | AJ70: =S70 -> 0 | AK70: =SUM(AE70:AJ70) -> 0
C71: D | F71: 0820 | G71: 9731 | H71: =F71&G71 -> 08209731 | I71: =IF(ISNA(VLOOKUP(G71,GAAP02F[[#All],[Column1]:[FundHier1]],5,FALSE)),"Leases",(VLOOKUP(G71,GAAP02F[[#All],[Column1]:[FundHier1]],5,FALSE))) -> 500 | J71: =IF(ISNA(VLOOKUP(F71,Table_GAAP02A[[#All],[Agency]:[Hier1]],4,FALSE)),"Abolished Agency",(VLOOKUP(F71,Table_GAAP02A[[#All],[Agency]:[Hier1]],4,FALSE))) -> 0808 | K71: =IF(ISNA(VLOOKUP(F71,Table_GAAP02A[[#All],[Agency]:[Hier1]],2,FALSE)),"Abolished Agency",(VLOOKUP(F71,Table_GAAP02A[[#All],[Agency]:[Hier1]],2,FALSE))) -> GENERAL GOVERNMENT | L71: =IF(ISNA(VLOOKUP(F71,Table_GAAP02A[[#All],[Agency]:[Hier1]],3,FALSE)),"Abolished Agency",(VLOOKUP(F71,Table_GAAP02A[[#All],[Agency]:[Hier1]],3,FALSE))) -> DEPARTMENT OF JUSTICE | M71: =IF(ISNA(VLOOKUP(G71,GAAP02F[[#All],[Column1]:[FundName]],2,FALSE)),"Leases",(VLOOKUP(G71,GAAP02F[[#All],[Column1]:[FundName]],2,FALSE))) -> LEGAL SERVICES REVOLVING FUND | N71: 0 | O71: 0 | P71: 0 | Q71: 0 | R71: 0 | S71: 0 | T71: =SUM(N71:S71) -> 0 | U71: 0 | V71: 0 | W71: 0 | X71: 0 | Y71: =SUM(U71:X71) -> 0 | Z71: 0 | AA71: 0 | AB71: 0 | AC71: 0 | AE71: =N71 +U71-Z71 -> 0 | AF71: =O71 +V71-AA71 -> 0 | AG71: =P71 +W71-AB71 -> 0 | AH71: =Q71 +X71-AC71 -> 0 | AI71: =R71 -> 0 | AJ71: =S71 -> 0 | AK71: =SUM(AE71:AJ71) -> 0
C72: D | F72: 0820 | G72: 9740 | H72: =F72&G72 -> 08209740 | I72: =IF(ISNA(VLOOKUP(G72,GAAP02F[[#All],[Column1]:[FundHier1]],5,FALSE)),"Leases",(VLOOKUP(G72,GAAP02F[[#All],[Column1]:[FundHier1]],5,FALSE))) -> 500 | J72: =IF(ISNA(VLOOKUP(F72,Table_GAAP02A[[#All],[Agency]:[Hier1]],4,FALSE)),"Abolished Agency",(VLOOKUP(F72,Table_GAAP02A[[#All],[Agency]:[Hier1]],4,FALSE))) -> 0808 | K72: =IF(ISNA(VLOOKUP(F72,Table_GAAP02A[[#All],[Agency]:[Hier1]],2,FALSE)),"Abolished Agency",(VLOOKUP(F72,Table_GAAP02A[[#All],[Agency]:[Hier1]],2,FALSE))) -> GENERAL GOVERNMENT | L72: =IF(ISNA(VLOOKUP(F72,Table_GAAP02A[[#All],[Agency]:[Hier1]],3,FALSE)),"Abolished Agency",(VLOOKUP(F72,Table_GAAP02A[[#All],[Agency]:[Hier1]],3,FALSE))) -> DEPARTMENT OF JUSTICE | M72: =IF(ISNA(VLOOKUP(G72,GAAP02F[[#All],[Column1]:[FundName]],2,FALSE)),"Leases",(VLOOKUP(G72,GAAP02F[[#All],[Column1]:[FundName]],2,FALSE))) -> CENTRAL SERVICE COST RECOVERY | N72: 0 | O72: 0 | P72: 0 | Q72: 0 | R72: 0 | S72: 0 | T72: =SUM(N72:S72) -> 0 | U72: 0 | V72: 0 | W72: 0 | X72: 0 | Y72: =SUM(U72:X72) -> 0 | Z72: 0 | AA72: 0 | AB72: 0 | AC72: 0 | AE72: =N72 +U72-Z72 -> 0 | AF72: =O72 +V72-AA72 -> 0 | AG72: =P72 +W72-AB72 -> 0 | AH72: =Q72 +X72-AC72 -> 0 | AI72: =R72 -> 0 | AJ72: =S72 -> 0 | AK72: =SUM(AE72:AJ72) -> 0
A73: 19 | C73: F | F73: 0840 | G73: 0001 | H73: =F73&G73 -> 08400001 | I73: =IF(ISNA(VLOOKUP(G73,GAAP02F[[#All],[Column1]:[FundHier1]],5,FALSE)),"Leases",(VLOOKUP(G73,GAAP02F[[#All],[Column1]:[FundHier1]],5,FALSE))) -> 100 | J73: =IF(ISNA(VLOOKUP(F73,Table_GAAP02A[[#All],[Agency]:[Hier1]],4,FALSE)),"Abolished Agency",(VLOOKUP(F73,Table_GAAP02A[[#All],[Agency]:[Hier1]],4,FALSE))) -> 0808 | K73: =IF(ISNA(VLOOKUP(F73,Table_GAAP02A[[#All],[Agency]:[Hier1]],2,FALSE)),"Abolished Agency",(VLOOKUP(F73,Table_GAAP02A[[#All],[Agency]:[Hier1]],2,FALSE))) -> GENERAL GOVERNMENT | L73: =IF(ISNA(VLOOKUP(F73,Table_GAAP02A[[#All],[Agency]:[Hier1]],3,FALSE)),"Abolished Agency",(VLOOKUP(F73,Table_GAAP02A[[#All],[Agency]:[Hier1]],3,FALSE))) -> STATE CONTROLLER | M73: =IF(ISNA(VLOOKUP(G73,GAAP02F[[#All],[Column1]:[FundName]],2,FALSE)),"Leases",(VLOOKUP(G73,GAAP02F[[#All],[Column1]:[FundName]],2,FALSE))) -> GENERAL FUND | N73: 0 | O73: 0 | P73: 0 | Q73: 0 | R73: 0 | S73: 0 | T73: =SUM(N73:S73) -> 0 | U73: 0 | V73: 0 | W73: 0 | X73: 0 | Y73: =SUM(U73:X73) -> 0 | Z73: 0 | AA73: 0 | AB73: 0 | AC73: 0 | AD73: =SUM(Z73:AC73) -> 0 | AE73: =N73 +U73-Z73 -> 0 | AF73: =O73 +V73-AA73 -> 0 | AG73: =P73 +W73-AB73 -> 0 | AH73: =Q73 +X73-AC73 -> 0 | AI73: =R73 -> 0 | AJ73: =S73 -> 0 | AK73: =SUM(AE73:AJ73) -> 0
C74: F | F74: 0845 | G74: 0001 | H74: =F74&G74 -> 08450001 | I74: =IF(ISNA(VLOOKUP(G74,GAAP02F[[#All],[Column1]:[FundHier1]],5,FALSE)),"Leases",(VLOOKUP(G74,GAAP02F[[#All],[Column1]:[FundHier1]],5,FALSE))) -> 100 | J74: =IF(ISNA(VLOOKUP(F74,Table_GAAP02A[[#All],[Agency]:[Hier1]],4,FALSE)),"Abolished Agency",(VLOOKUP(F74,Table_GAAP02A[[#All],[Agency]:[Hier1]],4,FALSE))) -> 0808 | K74: =IF(ISNA(VLOOKUP(F74,Table_GAAP02A[[#All],[Agency]:[Hier1]],2,FALSE)),"Abolished Agency",(VLOOKUP(F74,Table_GAAP02A[[#All],[Agency]:[Hier1]],2,FALSE))) -> GENERAL GOVERNMENT | L74: =IF(ISNA(VLOOKUP(F74,Table_GAAP02A[[#All],[Agency]:[Hier1]],3,FALSE)),"Abolished Agency",(VLOOKUP(F74,Table_GAAP02A[[#All],[Agency]:[Hier1]],3,FALSE))) -> DEPARTMENT OF INSURANCE | M74: =IF(ISNA(VLOOKUP(G74,GAAP02F[[#All],[Column1]:[FundName]],2,FALSE)),"Leases",(VLOOKUP(G74,GAAP02F[[#All],[Column1]:[FundName]],2,FALSE))) -> GENERAL FUND | N74: 0 | O74: 0 | P74: 0 | Q74: 0 | R74: 0 | S74: 0 | T74: =SUM(N74:S74) -> 0 | U74: 0 | V74: 0 | W74: 0 | X74: 0 | Y74: =SUM(U74:X74) -> 0 | Z74: 0 | AA74: 0 | AB74: 0 | AC74: 0 | AD74: =SUM(Z74:AC74) -> 0 | AE74: =N74 +U74-Z74 -> 0 | AF74: =O74 +V74-AA74 -> 0 | AG74: =P74 +W74-AB74 -> 0 | AH74: =Q74 +X74-AC74 -> 0 | AI74: =R74 -> 0 | AJ74: =S74 -> 0 | AK74: =SUM(AE74:AJ74) -> 0
A75: 19 | C75: F | F75: 0845 | G75: 0217 | H75: =F75&G75 -> 08450217 | I75: =IF(ISNA(VLOOKUP(G75,GAAP02F[[#All],[Column1]:[FundHier1]],5,FALSE)),"Leases",(VLOOKUP(G75,GAAP02F[[#All],[Column1]:[FundHier1]],5,FALSE))) -> 200 | J75: =IF(ISNA(VLOOKUP(F75,Table_GAAP02A[[#All],[Agency]:[Hier1]],4,FALSE)),"Abolished Agency",(VLOOKUP(F75,Table_GAAP02A[[#All],[Agency]:[Hier1]],4,FALSE))) -> 0808 | K75: =IF(ISNA(VLOOKUP(F75,Table_GAAP02A[[#All],[Agency]:[Hier1]],2,FALSE)),"Abolished Agency",(VLOOKUP(F75,Table_GAAP02A[[#All],[Agency]:[Hier1]],2,FALSE))) -> GENERAL GOVERNMENT | L75: =IF(ISNA(VLOOKUP(F75,Table_GAAP02A[[#All],[Agency]:[Hier1]],3,FALSE)),"Abolished Agency",(VLOOKUP(F75,Table_GAAP02A[[#All],[Agency]:[Hier1]],3,FALSE))) -> DEPARTMENT OF INSURANCE | M75: =IF(ISNA(VLOOKUP(G75,GAAP02F[[#All],[Column1]:[FundName]],2,FALSE)),"Leases",(VLOOKUP(G75,GAAP02F[[#All],[Column1]:[FundName]],2,FALSE))) -> INSURANCE FUND | N75: 0 | O75: 0 | P75: 0 | Q75: 0 | R75: 0 | S75: 0 | T75: =SUM(N75:S75) -> 0 | U75: 0 | V75: 0 | W75: 0 | X75: 0 | Y75: =SUM(U75:X75) -> 0 | Z75: 0 | AA75: 0 | AB75: 0 | AC75: 0 | AD75: =SUM(Z75:AC75) -> 0 | AE75: =N75 +U75-Z75 -> 0 | AF75: =O75 +V75-AA75 -> 0 | AG75: =P75 +W75-AB75 -> 0 | AH75: =Q75 +X75-AC75 -> 0 | AI75: =R75 -> 0 | AJ75: =S75 -> 0 | AK75: =SUM(AE75:AJ75) -> 0
A76: 19 | C76: F | F76: 0855 | G76: 0001 | H76: =F76&G76 -> 08550001 | I76: =IF(ISNA(VLOOKUP(G76,GAAP02F[[#All],[Column1]:[FundHier1]],5,FALSE)),"Leases",(VLOOKUP(G76,GAAP02F[[#All],[Column1]:[FundHier1]],5,FALSE))) -> 100 | J76: =IF(ISNA(VLOOKUP(F76,Table_GAAP02A[[#All],[Agency]:[Hier1]],4,FALSE)),"Abolished Agency",(VLOOKUP(F76,Table_GAAP02A[[#All],[Agency]:[Hier1]],4,FALSE))) -> 0808 | K76: =IF(ISNA(VLOOKUP(F76,Table_GAAP02A[[#All],[Agency]:[Hier1]],2,FALSE)),"Abolished Agency",(VLOOKUP(F76,Table_GAAP02A[[#All],[Agency]:[Hier1]],2,FALSE))) -> GENERAL GOVERNMENT | L76: =IF(ISNA(VLOOKUP(F76,Table_GAAP02A[[#All],[Agency]:[Hier1]],3,FALSE)),"Abolished Agency",(VLOOKUP(F76,Table_GAAP02A[[#All],[Agency]:[Hier1]],3,FALSE))) -> GAMBLING CONTROL COMMISSION | M76: =IF(ISNA(VLOOKUP(G76,GAAP02F[[#All],[Column1]:[FundName]],2,FALSE)),"Leases",(VLOOKUP(G76,GAAP02F[[#All],[Column1]:[FundName]],2,FALSE))) -> GENERAL FUND | N76: 0 | O76: 0 | P76: 0 | Q76: 0 | R76: 0 | S76: 0 | T76: =SUM(N76:S76) -> 0 | U76: 0 | V76: 0 | W76: 0 | X76: 0 | Y76: =SUM(U76:X76) -> 0 | Z76: 0 | AA76: 0 | AB76: 0 | AC76: 0 | AD76: =SUM(Z76:AC76) -> 0 | AE76: =N76 +U76-Z76 -> 0 | AF76: =O76 +V76-AA76 -> 0 | AG76: =P76 +W76-AB76 -> 0 | AH76: =Q76 +X76-AC76 -> 0 | AI76: =R76 -> 0 | AJ76: =S76 -> 0 | AK76: =SUM(AE76:AJ76) -> 0
A77: 19 | C77: F | D77: JR 12/20 | E77: JR 12/20 | F77: 0855 | G77: 0567 | H77: =F77&G77 -> 08550567 | I77: =IF(ISNA(VLOOKUP(G77,GAAP02F[[#All],[Column1]:[FundHier1]],5,FALSE)),"Leases",(VLOOKUP(G77,GAAP02F[[#All],[Column1]:[FundHier1]],5,FALSE))) -> 200 | J77: =IF(ISNA(VLOOKUP(F77,Table_GAAP02A[[#All],[Agency]:[Hier1]],4,FALSE)),"Abolished Agency",(VLOOKUP(F77,Table_GAAP02A[[#All],[Agency]:[Hier1]],4,FALSE))) -> 0808 | K77: =IF(ISNA(VLOOKUP(F77,Table_GAAP02A[[#All],[Agency]:[Hier1]],2,FALSE)),"Abolished Agency",(VLOOKUP(F77,Table_GAAP02A[[#All],[Agency]:[Hier1]],2,FALSE))) -> GENERAL GOVERNMENT | L77: =IF(ISNA(VLOOKUP(F77,Table_GAAP02A[[#All],[Agency]:[Hier1]],3,FALSE)),"Abolished Agency",(VLOOKUP(F77,Table_GAAP02A[[#All],[Agency]:[Hier1]],3,FALSE))) -> GAMBLING CONTROL COMMISSION | M77: =IF(ISNA(VLOOKUP(G77,GAAP02F[[#All],[Column1]:[FundName]],2,FALSE)),"Leases",(VLOOKUP(G77,GAAP02F[[#All],[Column1]:[FundName]],2,FALSE))) -> GAMBLING CONTROL FUND | N77: 0 | O77: 2045118.7 | P77: 0 | Q77: 93070.49 | R77: 0 | S77: 0 | T77: =SUM(N77:S77) -> 2138189.2 | U77: 0 | V77: 68866.85 | W77: 0 | X77: 0 | Y77: =SUM(U77:X77) -> 68866.85 | Z77: 0 | AA77: 0 | AB77: 0 | AC77: 0 | AD77: =SUM(Z77:AC77) -> 0 | AE77: =N77 +U77-Z77 -> 0 | AF77: =O77 +V77-AA77 -> 2113985.5 | AG77: =P77 +W77-AB77 -> 0 | AH77: =Q77 +X77-AC77 -> 93070.49 | AI77: =R77 -> 0 | AJ77: =S77 -> 0 | AK77: =SUM(AE77:AJ77) -> 2207056
A78: 19 | C78: F | F78: 0860 | G78: 0001 | H78: =F78&G78 -> 08600001 | I78: =IF(ISNA(VLOOKUP(G78,GAAP02F[[#All],[Column1]:[FundHier1]],5,FALSE)),"Leases",(VLOOKUP(G78,GAAP02F[[#All],[Column1]:[FundHier1]],5,FALSE))) -> 100 | J78: =IF(ISNA(VLOOKUP(F78,Table_GAAP02A[[#All],[Agency]:[Hier1]],4,FALSE)),"Abolished Agency",(VLOOKUP(F78,Table_GAAP02A[[#All],[Agency]:[Hier1]],4,FALSE))) -> 0808 | K78: =IF(ISNA(VLOOKUP(F78,Table_GAAP02A[[#All],[Agency]:[Hier1]],2,FALSE)),"Abolished Agency",(VLOOKUP(F78,Table_GAAP02A[[#All],[Agency]:[Hier1]],2,FALSE))) -> GENERAL GOVERNMENT | L78: =IF(ISNA(VLOOKUP(F78,Table_GAAP02A[[#All],[Agency]:[Hier1]],3,FALSE)),"Abolished Agency",(VLOOKUP(F78,Table_GAAP02A[[#All],[Agency]:[Hier1]],3,FALSE))) -> STATE BOARD OF EQUALIZATION | M78: =IF(ISNA(VLOOKUP(G78,GAAP02F[[#All],[Column1]:[FundName]],2,FALSE)),"Leases",(VLOOKUP(G78,GAAP02F[[#All],[Column1]:[FundName]],2,FALSE))) -> GENERAL FUND | N78: 0 | O78: 0 | P78: 0 | Q78: 0 | R78: 0 | S78: 0 | T78: =SUM(N78:S78) -> 0 | U78: 0 | V78: 0 | W78: 0 | X78: 0 | Y78: =SUM(U78:X78) -> 0 | Z78: 0 | AA78: 0 | AB78: 0 | AC78: 0 | AD78: =SUM(Z78:AC78) -> 0 | AE78: =N78 +U78-Z78 -> 0 | AF78: =O78 +V78-AA78 -> 0 | AG78: =P78 +W78-AB78 -> 0 | AH78: =Q78 +X78-AC78 -> 0 | AI78: =R78 -> 0 | AJ78: =S78 -> 0 | AK78: =SUM(AE78:AJ78) -> 0
A79: 19 | C79: F | D79: JR 12/18 | E79: NO SBITA | F79: 0870 | G79: 0001 | H79: =F79&G79 -> 08700001 | I79: =IF(ISNA(VLOOKUP(G79,GAAP02F[[#All],[Column1]:[FundHier1]],5,FALSE)),"Leases",(VLOOKUP(G79,GAAP02F[[#All],[Column1]:[FundHier1]],5,FALSE))) -> 100 | J79: =IF(ISNA(VLOOKUP(F79,Table_GAAP02A[[#All],[Agency]:[Hier1]],4,FALSE)),"Abolished Agency",(VLOOKUP(F79,Table_GAAP02A[[#All],[Agency]:[Hier1]],4,FALSE))) -> 0808 | K79: =IF(ISNA(VLOOKUP(F79,Table_GAAP02A[[#All],[Agency]:[Hier1]],2,FALSE)),"Abolished Agency",(VLOOKUP(F79,Table_GAAP02A[[#All],[Agency]:[Hier1]],2,FALSE))) -> GENERAL GOVERNMENT | L79: =IF(ISNA(VLOOKUP(F79,Table_GAAP02A[[#All],[Agency]:[Hier1]],3,FALSE)),"Abolished Agency",(VLOOKUP(F79,Table_GAAP02A[[#All],[Agency]:[Hier1]],3,FALSE))) -> OFFICE OF TAX APPEALS | M79: =IF(ISNA(VLOOKUP(G79,GAAP02F[[#All],[Column1]:[FundName]],2,FALSE)),"Leases",(VLOOKUP(G79,GAAP02F[[#All],[Column1]:[FundName]],2,FALSE))) -> GENERAL FUND | N79: 0 | O79: 13025748 | P79: 0 | R79: 0 | S79: 0 | T79: =SUM(N79:S79) -> 13025748 | U79: 0 | V79: 0 | W79: 0 | X79: 0 | Y79: =SUM(U79:X79) -> 0 | Z79: 0 | AA79: 0 | AB79: 0 | AC79: 0 | AD79: =SUM(Z79:AC79) -> 0 | AE79: =N79 +U79-Z79 -> 0 | AF79: =O79 +V79-AA79 -> 13025748 | AG79: =P79 +W79-AB79 -> 0 | AH79: =Q79 +X79-AC79 -> 0 | AI79: =R79 -> 0 | AJ79: =S79 -> 0 | AK79: =SUM(AE79:AJ79) -> 13025748
A80: 19 | C80: F | F80: 0890 | G80: 0001 | H80: =F80&G80 -> 08900001 | I80: =IF(ISNA(VLOOKUP(G80,GAAP02F[[#All],[Column1]:[FundHier1]],5,FALSE)),"Leases",(VLOOKUP(G80,GAAP02F[[#All],[Column1]:[FundHier1]],5,FALSE))) -> 100 | J80: =IF(ISNA(VLOOKUP(F80,Table_GAAP02A[[#All],[Agency]:[Hier1]],4,FALSE)),"Abolished Agency",(VLOOKUP(F80,Table_GAAP02A[[#All],[Agency]:[Hier1]],4,FALSE))) -> 0808 | K80: =IF(ISNA(VLOOKUP(F80,Table_GAAP02A[[#All],[Agency]:[Hier1]],2,FALSE)),"Abolished Agency",(VLOOKUP(F80,Table_GAAP02A[[#All],[Agency]:[Hier1]],2,FALSE))) -> GENERAL GOVERNMENT | L80: =IF(ISNA(VLOOKUP(F80,Table_GAAP02A[[#All],[Agency]:[Hier1]],3,FALSE)),"Abolished Agency",(VLOOKUP(F80,Table_GAAP02A[[#All],[Agency]:[Hier1]],3,FALSE))) -> SECRETARY OF STATE | M80: =IF(ISNA(VLOOKUP(G80,GAAP02F[[#All],[Column1]:[FundName]],2,FALSE)),"Leases",(VLOOKUP(G80,GAAP02F[[#All],[Column1]:[FundName]],2,FALSE))) -> GENERAL FUND | N80: 0 | O80: 0 | P80: 0 | Q80: 0 | R80: 0 | S80: 0 | T80: =SUM(N80:S80) -> 0 | U80: 0 | V80: 0 | W80: 0 | X80: 0 | Y80: =SUM(U80:X80) -> 0 | Z80: 0 | AA80: 0 | AB80: 0 | AC80: 0 | AD80: =SUM(Z80:AC80) -> 0 | AE80: =N80 +U80-Z80 -> 0 | AF80: =O80 +V80-AA80 -> 0 | AG80: =P80 +W80-AB80 -> 0 | AH80: =Q80 +X80-AC80 -> 0 | AI80: =R80 -> 0 | AJ80: =S80 -> 0 | AK80: =SUM(AE80:AJ80) -> 0
A81: 19 | C81: F | F81: 0890 | G81: 0228 | H81: =F81&G81 -> 08900228 | I81: =IF(ISNA(VLOOKUP(G81,GAAP02F[[#All],[Column1]:[FundHier1]],5,FALSE)),"Leases",(VLOOKUP(G81,GAAP02F[[#All],[Column1]:[FundHier1]],5,FALSE))) -> 200 | J81: =IF(ISNA(VLOOKUP(F81,Table_GAAP02A[[#All],[Agency]:[Hier1]],4,FALSE)),"Abolished Agency",(VLOOKUP(F81,Table_GAAP02A[[#All],[Agency]:[Hier1]],4,FALSE))) -> 0808 | K81: =IF(ISNA(VLOOKUP(F81,Table_GAAP02A[[#All],[Agency]:[Hier1]],2,FALSE)),"Abolished Agency",(VLOOKUP(F81,Table_GAAP02A[[#All],[Agency]:[Hier1]],2,FALSE))) -> GENERAL GOVERNMENT | L81: =IF(ISNA(VLOOKUP(F81,Table_GAAP02A[[#All],[Agency]:[Hier1]],3,FALSE)),"Abolished Agency",(VLOOKUP(F81,Table_GAAP02A[[#All],[Agency]:[Hier1]],3,FALSE))) -> SECRETARY OF STATE | M81: =IF(ISNA(VLOOKUP(G81,GAAP02F[[#All],[Column1]:[FundName]],2,FALSE)),"Leases",(VLOOKUP(G81,GAAP02F[[#All],[Column1]:[FundName]],2,FALSE))) -> SEC OF STATE'S BUSINESS FEE FD | N81: 0 | O81: 0 | P81: 0 | Q81: 0 | R81: 0 | S81: 0 | T81: =SUM(N81:S81) -> 0 | U81: 0 | V81: 0 | W81: 0 | X81: 0 | Y81: =SUM(U81:X81) -> 0 | Z81: 0 | AA81: 0 | AB81: 0 | AC81: 0 | AD81: =SUM(Z81:AC81) -> 0 | AE81: =N81 +U81-Z81 -> 0 | AF81: =O81 +V81-AA81 -> 0 | AG81: =P81 +W81-AB81 -> 0 | AH81: =Q81 +X81-AC81 -> 0 | AI81: =R81 -> 0 | AJ81: =S81 -> 0 | AK81: =SUM(AE81:AJ81) -> 0
A82: 19 | C82: F | F82: 0890 | G82: 0890 | H82: =F82&G82 -> 08900890 | I82: =IF(ISNA(VLOOKUP(G82,GAAP02F[[#All],[Column1]:[FundHier1]],5,FALSE)),"Leases",(VLOOKUP(G82,GAAP02F[[#All],[Column1]:[FundHier1]],5,FALSE))) -> 200 | J82: =IF(ISNA(VLOOKUP(F82,Table_GAAP02A[[#All],[Agency]:[Hier1]],4,FALSE)),"Abolished Agency",(VLOOKUP(F82,Table_GAAP02A[[#All],[Agency]:[Hier1]],4,FALSE))) -> 0808 | K82: =IF(ISNA(VLOOKUP(F82,Table_GAAP02A[[#All],[Agency]:[Hier1]],2,FALSE)),"Abolished Agency",(VLOOKUP(F82,Table_GAAP02A[[#All],[Agency]:[Hier1]],2,FALSE))) -> GENERAL GOVERNMENT | L82: =IF(ISNA(VLOOKUP(F82,Table_GAAP02A[[#All],[Agency]:[Hier1]],3,FALSE)),"Abolished Agency",(VLOOKUP(F82,Table_GAAP02A[[#All],[Agency]:[Hier1]],3,FALSE))) -> SECRETARY OF STATE | M82: =IF(ISNA(VLOOKUP(G82,GAAP02F[[#All],[Column1]:[FundName]],2,FALSE)),"Leases",(VLOOKUP(G82,GAAP02F[[#All],[Column1]:[FundName]],2,FALSE))) -> FEDERAL TRUST FUND | N82: 0 | O82: 0 | P82: 0 | Q82: 0 | R82: 0 | S82: 0 | T82: =SUM(N82:S82) -> 0 | U82: 0 | V82: 0 | W82: 0 | X82: 0 | Y82: =SUM(U82:X82) -> 0 | Z82: 0 | AA82: 0 | AB82: 0 | AC82: 0 | AD82: =SUM(Z82:AC82) -> 0 | AE82: =N82 +U82-Z82 -> 0 | AF82: =O82 +V82-AA82 -> 0 | AG82: =P82 +W82-AB82 -> 0 | AH82: =Q82 +X82-AC82 -> 0 | AI82: =R82 -> 0 | AJ82: =S82 -> 0 | AK82: =SUM(AE82:AJ82) -> 0
A83: 19 | C83: F | F83: 0890 | G83: 3254 | H83: =F83&G83 -> 08903254 | I83: =IF(ISNA(VLOOKUP(G83,GAAP02F[[#All],[Column1]:[FundHier1]],5,FALSE)),"Leases",(VLOOKUP(G83,GAAP02F[[#All],[Column1]:[FundHier1]],5,FALSE))) -> 200 | J83: =IF(ISNA(VLOOKUP(F83,Table_GAAP02A[[#All],[Agency]:[Hier1]],4,FALSE)),"Abolished Agency",(VLOOKUP(F83,Table_GAAP02A[[#All],[Agency]:[Hier1]],4,FALSE))) -> 0808 | K83: =IF(ISNA(VLOOKUP(F83,Table_GAAP02A[[#All],[Agency]:[Hier1]],2,FALSE)),"Abolished Agency",(VLOOKUP(F83,Table_GAAP02A[[#All],[Agency]:[Hier1]],2,FALSE))) -> GENERAL GOVERNMENT | L83: =IF(ISNA(VLOOKUP(F83,Table_GAAP02A[[#All],[Agency]:[Hier1]],3,FALSE)),"Abolished Agency",(VLOOKUP(F83,Table_GAAP02A[[#All],[Agency]:[Hier1]],3,FALSE))) -> SECRETARY OF STATE | M83: =IF(ISNA(VLOOKUP(G83,GAAP02F[[#All],[Column1]:[FundName]],2,FALSE)),"Leases",(VLOOKUP(G83,GAAP02F[[#All],[Column1]:[FundName]],2,FALSE))) -> BUSINESS PROG MODENIZATION | N83: 0 | O83: 0 | P83: 0 | Q83: 0 | R83: 0 | S83: 0 | T83: =SUM(N83:S83) -> 0 | U83: 0 | V83: 0 | W83: 0 | X83: 0 | Y83: =SUM(U83:X83) -> 0 | Z83: 0 | AA83: 0 | AB83: 0 | AC83: 0 | AD83: =SUM(Z83:AC83) -> 0 | AE83: =N83 +U83-Z83 -> 0 | AF83: =O83 +V83-AA83 -> 0 | AG83: =P83 +W83-AB83 -> 0 | AH83: =Q83 +X83-AC83 -> 0 | AI83: =R83 -> 0 | AJ83: =S83 -> 0 | AK83: =SUM(AE83:AJ83) -> 0
A84: 19 | C84: F | F84: 0950 | G84: 0001 | H84: =F84&G84 -> 09500001 | I84: =IF(ISNA(VLOOKUP(G84,GAAP02F[[#All],[Column1]:[FundHier1]],5,FALSE)),"Leases",(VLOOKUP(G84,GAAP02F[[#All],[Column1]:[FundHier1]],5,FALSE))) -> 100 | J84: =IF(ISNA(VLOOKUP(F84,Table_GAAP02A[[#All],[Agency]:[Hier1]],4,FALSE)),"Abolished Agency",(VLOOKUP(F84,Table_GAAP02A[[#All],[Agency]:[Hier1]],4,FALSE))) -> 0808 | K84: =IF(ISNA(VLOOKUP(F84,Table_GAAP02A[[#All],[Agency]:[Hier1]],2,FALSE)),"Abolished Agency",(VLOOKUP(F84,Table_GAAP02A[[#All],[Agency]:[Hier1]],2,FALSE))) -> GENERAL GOVERNMENT | L84: =IF(ISNA(VLOOKUP(F84,Table_GAAP02A[[#All],[Agency]:[Hier1]],3,FALSE)),"Abolished Agency",(VLOOKUP(F84,Table_GAAP02A[[#All],[Agency]:[Hier1]],3,FALSE))) -> STATE TREASURER | M84: =IF(ISNA(VLOOKUP(G84,GAAP02F[[#All],[Column1]:[FundName]],2,FALSE)),"Leases",(VLOOKUP(G84,GAAP02F[[#All],[Column1]:[FundName]],2,FALSE))) -> GENERAL FUND | N84: 0 | O84: 0 | P84: 0 | Q84: 0 | R84: 0 | S84: 0 | T84: =SUM(N84:S84) -> 0 | U84: 0 | V84: 0 | W84: 0 | X84: 0 | Y84: =SUM(U84:X84) -> 0 | Z84: 0 | AA84: 0 | AB84: 0 | AC84: 0 | AD84: =SUM(Z84:AC84) -> 0 | AE84: =N84 +U84-Z84 -> 0 | AF84: =O84 +V84-AA84 -> 0 | AG84: =P84 +W84-AB84 -> 0 | AH84: =Q84 +X84-AC84 -> 0 | AI84: =R84 -> 0 | AJ84: =S84 -> 0 | AK84: =SUM(AE84:AJ84) -> 0
A85: 19 | C85: F | F85: 0956 | G85: 0171 | H85: =F85&G85 -> 09560171 | I85: =IF(ISNA(VLOOKUP(G85,GAAP02F[[#All],[Column1]:[FundHier1]],5,FALSE)),"Leases",(VLOOKUP(G85,GAAP02F[[#All],[Column1]:[FundHier1]],5,FALSE))) -> 200 | J85: =IF(ISNA(VLOOKUP(F85,Table_GAAP02A[[#All],[Agency]:[Hier1]],4,FALSE)),"Abolished Agency",(VLOOKUP(F85,Table_GAAP02A[[#All],[Agency]:[Hier1]],4,FALSE))) -> 0808 | K85: =IF(ISNA(VLOOKUP(F85,Table_GAAP02A[[#All],[Agency]:[Hier1]],2,FALSE)),"Abolished Agency",(VLOOKUP(F85,Table_GAAP02A[[#All],[Agency]:[Hier1]],2,FALSE))) -> GENERAL GOVERNMENT | L85: =IF(ISNA(VLOOKUP(F85,Table_GAAP02A[[#All],[Agency]:[Hier1]],3,FALSE)),"Abolished Agency",(VLOOKUP(F85,Table_GAAP02A[[#All],[Agency]:[Hier1]],3,FALSE))) -> DEBT ADVISORY COMMISSION | M85: =IF(ISNA(VLOOKUP(G85,GAAP02F[[#All],[Column1]:[FundName]],2,FALSE)),"Leases",(VLOOKUP(G85,GAAP02F[[#All],[Column1]:[FundName]],2,FALSE))) -> CALIF DEBT & INVEST ADVISORY | N85: 0 | O85: 0 | P85: 0 | Q85: 0 | R85: 0 | S85: 0 | T85: =SUM(N85:S85) -> 0 | U85: 0 | V85: 0 | W85: 0 | X85: 0 | Y85: =SUM(U85:X85) -> 0 | Z85: 0 | AA85: 0 | AB85: 0 | AC85: 0 | AD85: =SUM(Z85:AC85) -> 0 | AE85: =N85 +U85-Z85 -> 0 | AF85: =O85 +V85-AA85 -> 0 | AG85: =P85 +W85-AB85 -> 0 | AH85: =Q85 +X85-AC85 -> 0 | AI85: =R85 -> 0 | AJ85: =S85 -> 0 | AK85: =SUM(AE85:AJ85) -> 0
A86: 19 | C86: F | F86: 0959 | G86: 0169 | H86: =F86&G86 -> 09590169 | I86: =IF(ISNA(VLOOKUP(G86,GAAP02F[[#All],[Column1]:[FundHier1]],5,FALSE)),"Leases",(VLOOKUP(G86,GAAP02F[[#All],[Column1]:[FundHier1]],5,FALSE))) -> 200 | J86: =IF(ISNA(VLOOKUP(F86,Table_GAAP02A[[#All],[Agency]:[Hier1]],4,FALSE)),"Abolished Agency",(VLOOKUP(F86,Table_GAAP02A[[#All],[Agency]:[Hier1]],4,FALSE))) -> 0808 | K86: =IF(ISNA(VLOOKUP(F86,Table_GAAP02A[[#All],[Agency]:[Hier1]],2,FALSE)),"Abolished Agency",(VLOOKUP(F86,Table_GAAP02A[[#All],[Agency]:[Hier1]],2,FALSE))) -> GENERAL GOVERNMENT | L86: =IF(ISNA(VLOOKUP(F86,Table_GAAP02A[[#All],[Agency]:[Hier1]],3,FALSE)),"Abolished Agency",(VLOOKUP(F86,Table_GAAP02A[[#All],[Agency]:[Hier1]],3,FALSE))) -> CA DEBT LIMIT ALLOCATN COMMITE | M86: =IF(ISNA(VLOOKUP(G86,GAAP02F[[#All],[Column1]:[FundName]],2,FALSE)),"Leases",(VLOOKUP(G86,GAAP02F[[#All],[Column1]:[FundName]],2,FALSE))) -> CALIF DEBT LIMIT ALLOC COMM FD | N86: 0 | O86: 0 | P86: 0 | Q86: 0 | R86: 0 | S86: 0 | T86: =SUM(N86:S86) -> 0 | U86: 0 | V86: 0 | W86: 0 | X86: 0 | Y86: =SUM(U86:X86) -> 0 | Z86: 0 | AA86: 0 | AB86: 0 | AC86: 0 | AD86: =SUM(Z86:AC86) -> 0 | AE86: =N86 +U86-Z86 -> 0 | AF86: =O86 +V86-AA86 -> 0 | AG86: =P86 +W86-AB86 -> 0 | AH86: =Q86 +X86-AC86 -> 0 | AI86: =R86 -> 0 | AJ86: =S86 -> 0 | AK86: =SUM(AE86:AJ86) -> 0
A87: 19 | C87: F | F87: 0968 | G87: 0448 | H87: =F87&G87 -> 09680448 | I87: =IF(ISNA(VLOOKUP(G87,GAAP02F[[#All],[Column1]:[FundHier1]],5,FALSE)),"Leases",(VLOOKUP(G87,GAAP02F[[#All],[Column1]:[FundHier1]],5,FALSE))) -> 200 | J87: =IF(ISNA(VLOOKUP(F87,Table_GAAP02A[[#All],[Agency]:[Hier1]],4,FALSE)),"Abolished Agency",(VLOOKUP(F87,Table_GAAP02A[[#All],[Agency]:[Hier1]],4,FALSE))) -> 0808 | K87: =IF(ISNA(VLOOKUP(F87,Table_GAAP02A[[#All],[Agency]:[Hier1]],2,FALSE)),"Abolished Agency",(VLOOKUP(F87,Table_GAAP02A[[#All],[Agency]:[Hier1]],2,FALSE))) -> GENERAL GOVERNMENT | L87: =IF(ISNA(VLOOKUP(F87,Table_GAAP02A[[#All],[Agency]:[Hier1]],3,FALSE)),"Abolished Agency",(VLOOKUP(F87,Table_GAAP02A[[#All],[Agency]:[Hier1]],3,FALSE))) -> MORTGAGE BOND ALLOC COMMITTEE | M87: =IF(ISNA(VLOOKUP(G87,GAAP02F[[#All],[Column1]:[FundName]],2,FALSE)),"Leases",(VLOOKUP(G87,GAAP02F[[#All],[Column1]:[FundName]],2,FALSE))) -> OCCUPANCY COMPL, MONITOR, ACCT | N87: 0 | O87: 0 | P87: 0 | Q87: 0 | R87: 0 | S87: 0 | T87: =SUM(N87:S87) -> 0 | U87: 0 | V87: 0 | W87: 0 | X87: 0 | Y87: =SUM(U87:X87) -> 0 | Z87: 0 | AA87: 0 | AB87: 0 | AC87: 0 | AD87: =SUM(Z87:AC87) -> 0 | AE87: =N87 +U87-Z87 -> 0 | AF87: =O87 +V87-AA87 -> 0 | AG87: =P87 +W87-AB87 -> 0 | AH87: =Q87 +X87-AC87 -> 0 | AI87: =R87 -> 0 | AJ87: =S87 -> 0 | AK87: =SUM(AE87:AJ87) -> 0
A88: 19 | C88: F | F88: 0968 | G88: 0457 | H88: =F88&G88 -> 09680457 | I88: =IF(ISNA(VLOOKUP(G88,GAAP02F[[#All],[Column1]:[FundHier1]],5,FALSE)),"Leases",(VLOOKUP(G88,GAAP02F[[#All],[Column1]:[FundHier1]],5,FALSE))) -> 200 | J88: =IF(ISNA(VLOOKUP(F88,Table_GAAP02A[[#All],[Agency]:[Hier1]],4,FALSE)),"Abolished Agency",(VLOOKUP(F88,Table_GAAP02A[[#All],[Agency]:[Hier1]],4,FALSE))) -> 0808 | K88: =IF(ISNA(VLOOKUP(F88,Table_GAAP02A[[#All],[Agency]:[Hier1]],2,FALSE)),"Abolished Agency",(VLOOKUP(F88,Table_GAAP02A[[#All],[Agency]:[Hier1]],2,FALSE))) -> GENERAL GOVERNMENT | L88: =IF(ISNA(VLOOKUP(F88,Table_GAAP02A[[#All],[Agency]:[Hier1]],3,FALSE)),"Abolished Agency",(VLOOKUP(F88,Table_GAAP02A[[#All],[Agency]:[Hier1]],3,FALSE))) -> MORTGAGE BOND ALLOC COMMITTEE | M88: =IF(ISNA(VLOOKUP(G88,GAAP02F[[#All],[Column1]:[FundName]],2,FALSE)),"Leases",(VLOOKUP(G88,GAAP02F[[#All],[Column1]:[FundName]],2,FALSE))) -> TAX CREDIT ALLOCATION FEE ACCT | N88: 0 | O88: 0 | P88: 0 | Q88: 0 | R88: 0 | S88: 0 | T88: =SUM(N88:S88) -> 0 | U88: 0 | V88: 0 | W88: 0 | X88: 0 | Y88: =SUM(U88:X88) -> 0 | Z88: 0 | AA88: 0 | AB88: 0 | AC88: 0 | AD88: =SUM(Z88:AC88) -> 0 | AE88: =N88 +U88-Z88 -> 0 | AF88: =O88 +V88-AA88 -> 0 | AG88: =P88 +W88-AB88 -> 0 | AH88: =Q88 +X88-AC88 -> 0 | AI88: =R88 -> 0 | AJ88: =S88 -> 0 | AK88: =SUM(AE88:AJ88) -> 0
A89: G | C89: F | F89: 0978 | G89: 0538 | H89: =F89&G89 -> 09780538 | I89: =IF(ISNA(VLOOKUP(G89,GAAP02F[[#All],[Column1]:[FundHier1]],5,FALSE)),"Leases",(VLOOKUP(G89,GAAP02F[[#All],[Column1]:[FundHier1]],5,FALSE))) -> 300 | J89: =IF(ISNA(VLOOKUP(F89,Table_GAAP02A[[#All],[Agency]:[Hier1]],4,FALSE)),"Abolished Agency",(VLOOKUP(F89,Table_GAAP02A[[#All],[Agency]:[Hier1]],4,FALSE))) -> 0808 | K89: =IF(ISNA(VLOOKUP(F89,Table_GAAP02A[[#All],[Agency]:[Hier1]],2,FALSE)),"Abolished Agency",(VLOOKUP(F89,Table_GAAP02A[[#All],[Agency]:[Hier1]],2,FALSE))) -> GENERAL GOVERNMENT | L89: =IF(ISNA(VLOOKUP(F89,Table_GAAP02A[[#All],[Agency]:[Hier1]],3,FALSE)),"Abolished Agency",(VLOOKUP(F89,Table_GAAP02A[[#All],[Agency]:[Hier1]],3,FALSE))) -> S.F. STATE BLDG AUTHORITY | M89: =IF(ISNA(VLOOKUP(G89,GAAP02F[[#All],[Column1]:[FundName]],2,FALSE)),"Leases",(VLOOKUP(G89,GAAP02F[[#All],[Column1]:[FundName]],2,FALSE))) -> SAN FRANCISCO ST BLDG FUND | N89: 0 | O89: 0 | P89: 0 | Q89: 0 | R89: 0 | S89: 0 | T89: =SUM(N89:S89) -> 0 | U89: 0 | V89: 0 | W89: 0 | X89: 0 | Y89: =SUM(U89:X89) -> 0 | Z89: 0 | AA89: 0 | AB89: 0 | AC89: 0 | AD89: =SUM(Z89:AC89) -> 0 | AE89: =N89 +U89-Z89 -> 0 | AF89: =O89 +V89-AA89 -> 0 | AG89: =P89 +W89-AB89 -> 0 | AH89: =Q89 +X89-AC89 -> 0 | AI89: =R89 -> 0 | AJ89: =S89 -> 0 | AK89: =SUM(AE89:AJ89) -> 0
A90: G | C90: F | F90: 0979 | G90: 0539 | H90: =F90&G90 -> 09790539 | I90: =IF(ISNA(VLOOKUP(G90,GAAP02F[[#All],[Column1]:[FundHier1]],5,FALSE)),"Leases",(VLOOKUP(G90,GAAP02F[[#All],[Column1]:[FundHier1]],5,FALSE))) -> 300 | J90: =IF(ISNA(VLOOKUP(F90,Table_GAAP02A[[#All],[Agency]:[Hier1]],4,FALSE)),"Abolished Agency",(VLOOKUP(F90,Table_GAAP02A[[#All],[Agency]:[Hier1]],4,FALSE))) -> 0808 | K90: =IF(ISNA(VLOOKUP(F90,Table_GAAP02A[[#All],[Agency]:[Hier1]],2,FALSE)),"Abolished Agency",(VLOOKUP(F90,Table_GAAP02A[[#All],[Agency]:[Hier1]],2,FALSE))) -> GENERAL GOVERNMENT | L90: =IF(ISNA(VLOOKUP(F90,Table_GAAP02A[[#All],[Agency]:[Hier1]],3,FALSE)),"Abolished Agency",(VLOOKUP(F90,Table_GAAP02A[[#All],[Agency]:[Hier1]],3,FALSE))) -> OAKLAND JOINT POWERS AUTHORITY | M90: =IF(ISNA(VLOOKUP(G90,GAAP02F[[#All],[Column1]:[FundName]],2,FALSE)),"Leases",(VLOOKUP(G90,GAAP02F[[#All],[Column1]:[FundName]],2,FALSE))) -> OAKLAND STATE BLDG AUTH FUND | N90: 0 | O90: 0 | P90: 0 | Q90: 0 | R90: 0 | S90: 0 | T90: =SUM(N90:S90) -> 0 | U90: 0 | V90: 0 | W90: 0 | X90: 0 | Y90: =SUM(U90:X90) -> 0 | Z90: 0 | AA90: 0 | AB90: 0 | AC90: 0 | AD90: =SUM(Z90:AC90) -> 0 | AE90: =N90 +U90-Z90 -> 0 | AF90: =O90 +V90-AA90 -> 0 | AG90: =P90 +W90-AB90 -> 0 | AH90: =Q90 +X90-AC90 -> 0 | AI90: =R90 -> 0 | AJ90: =S90 -> 0 | AK90: =SUM(AE90:AJ90) -> 0
D91: JR 12/18 | E91: NO SBITA | F91: 1045 | G91: 3288 | H91: =F91&G91 -> 10453288 | I91: =IF(ISNA(VLOOKUP(G91,GAAP02F[[#All],[Column1]:[FundHier1]],5,FALSE)),"Leases",(VLOOKUP(G91,GAAP02F[[#All],[Column1]:[FundHier1]],5,FALSE))) -> 200 | J91: =IF(ISNA(VLOOKUP(F91,Table_GAAP02A[[#All],[Agency]:[Hier1]],4,FALSE)),"Abolished Agency",(VLOOKUP(F91,Table_GAAP02A[[#All],[Agency]:[Hier1]],4,FALSE))) -> 0825 | K91: =IF(ISNA(VLOOKUP(F91,Table_GAAP02A[[#All],[Agency]:[Hier1]],2,FALSE)),"Abolished Agency",(VLOOKUP(F91,Table_GAAP02A[[#All],[Agency]:[Hier1]],2,FALSE))) -> BUS, CONSUMER SERV, HOUSING | L91: =IF(ISNA(VLOOKUP(F91,Table_GAAP02A[[#All],[Agency]:[Hier1]],3,FALSE)),"Abolished Agency",(VLOOKUP(F91,Table_GAAP02A[[#All],[Agency]:[Hier1]],3,FALSE))) -> CANNABIS CONTROL APPEALS PANEL | M91: =IF(ISNA(VLOOKUP(G91,GAAP02F[[#All],[Column1]:[FundName]],2,FALSE)),"Leases",(VLOOKUP(G91,GAAP02F[[#All],[Column1]:[FundName]],2,FALSE))) -> MEDICAL MARIJUANA REG & SAFETY | N91: 0 | O91: 1584188 | P91: 0 | Q91: 0 | R91: 0 | S91: 0 | T91: =SUM(N91:S91) -> 1584188 | U91: 0 | V91: 0 | W91: 0 | X91: 0 | Y91: =SUM(U91:X91) -> 0 | Z91: 0 | AA91: 0 | AB91: 0 | AC91: 0 | AD91: =SUM(Z91:AC91) -> 0 | AE91: =N91 +U91-Z91 -> 0 | AF91: =O91 +V91-AA91 -> 1584188 | AG91: =P91 +W91-AB91 -> 0 | AH91: =Q91 +X91-AC91 -> 0 | AI91: =R91 -> 0 | AJ91: =S91 -> 0 | AK91: =SUM(AE91:AJ91) -> 1584188
A92: 19 | C92: F | F92: 1111 | G92: 0069 | H92: =F92&G92 -> 11110069 | I92: =IF(ISNA(VLOOKUP(G92,GAAP02F[[#All],[Column1]:[FundHier1]],5,FALSE)),"Leases",(VLOOKUP(G92,GAAP02F[[#All],[Column1]:[FundHier1]],5,FALSE))) -> 200 | J92: =IF(ISNA(VLOOKUP(F92,Table_GAAP02A[[#All],[Agency]:[Hier1]],4,FALSE)),"Abolished Agency",(VLOOKUP(F92,Table_GAAP02A[[#All],[Agency]:[Hier1]],4,FALSE))) -> 0825 | K92: =IF(ISNA(VLOOKUP(F92,Table_GAAP02A[[#All],[Agency]:[Hier1]],2,FALSE)),"Abolished Agency",(VLOOKUP(F92,Table_GAAP02A[[#All],[Agency]:[Hier1]],2,FALSE))) -> BUS, CONSUMER SERV, HOUSING | L92: =IF(ISNA(VLOOKUP(F92,Table_GAAP02A[[#All],[Agency]:[Hier1]],3,FALSE)),"Abolished Agency",(VLOOKUP(F92,Table_GAAP02A[[#All],[Agency]:[Hier1]],3,FALSE))) -> DEPT OF CONSUMER AFFAIRS | M92: =IF(ISNA(VLOOKUP(G92,GAAP02F[[#All],[Column1]:[FundName]],2,FALSE)),"Leases",(VLOOKUP(G92,GAAP02F[[#All],[Column1]:[FundName]],2,FALSE))) -> BARBERING/COSMTLGY CONTINGENT | N92: 0 | O92: 0 | P92: 0 | Q92: 0 | R92: 0 | S92: 0 | T92: =SUM(N92:S92) -> 0 | U92: 0 | V92: 0 | W92: 0 | X92: 0 | Y92: =SUM(U92:X92) -> 0 | Z92: 0 | AA92: 0 | AB92: 0 | AC92: 0 | AD92: =SUM(Z92:AC92) -> 0 | AE92: =N92 +U92-Z92 -> 0 | AF92: =O92 +V92-AA92 -> 0 | AG92: =P92 +W92-AB92 -> 0 | AH92: =Q92 +X92-AC92 -> 0 | AI92: =R92 -> 0 | AJ92: =S92 -> 0 | AK92: =SUM(AE92:AJ92) -> 0
A93: 19 | C93: F | F93: 1111 | G93: 0108 | H93: =F93&G93 -> 11110108 | I93: =IF(ISNA(VLOOKUP(G93,GAAP02F[[#All],[Column1]:[FundHier1]],5,FALSE)),"Leases",(VLOOKUP(G93,GAAP02F[[#All],[Column1]:[FundHier1]],5,FALSE))) -> 200 | J93: =IF(ISNA(VLOOKUP(F93,Table_GAAP02A[[#All],[Agency]:[Hier1]],4,FALSE)),"Abolished Agency",(VLOOKUP(F93,Table_GAAP02A[[#All],[Agency]:[Hier1]],4,FALSE))) -> 0825 | K93: =IF(ISNA(VLOOKUP(F93,Table_GAAP02A[[#All],[Agency]:[Hier1]],2,FALSE)),"Abolished Agency",(VLOOKUP(F93,Table_GAAP02A[[#All],[Agency]:[Hier1]],2,FALSE))) -> BUS, CONSUMER SERV, HOUSING | L93: =IF(ISNA(VLOOKUP(F93,Table_GAAP02A[[#All],[Agency]:[Hier1]],3,FALSE)),"Abolished Agency",(VLOOKUP(F93,Table_GAAP02A[[#All],[Agency]:[Hier1]],3,FALSE))) -> DEPT OF CONSUMER AFFAIRS | M93: =IF(ISNA(VLOOKUP(G93,GAAP02F[[#All],[Column1]:[FundName]],2,FALSE)),"Leases",(VLOOKUP(G93,GAAP02F[[#All],[Column1]:[FundName]],2,FALSE))) -> ACUPUNCTURISTS FUND | N93: 0 | O93: 0 | P93: 0 | Q93: 0 | R93: 0 | S93: 0 | T93: =SUM(N93:S93) -> 0 | U93: 0 | V93: 0 | W93: 0 | X93: 0 | Y93: =SUM(U93:X93) -> 0 | Z93: 0 | AA93: 0 | AB93: 0 | AC93: 0 | AD93: =SUM(Z93:AC93) -> 0 | AE93: =N93 +U93-Z93 -> 0 | AF93: =O93 +V93-AA93 -> 0 | AG93: =P93 +W93-AB93 -> 0 | AH93: =Q93 +X93-AC93 -> 0 | AI93: =R93 -> 0 | AJ93: =S93 -> 0 | AK93: =SUM(AE93:AJ93) -> 0
A94: 19 | C94: F | F94: 1111 | G94: 0152 | H94: =F94&G94 -> 11110152 | I94: =IF(ISNA(VLOOKUP(G94,GAAP02F[[#All],[Column1]:[FundHier1]],5,FALSE)),"Leases",(VLOOKUP(G94,GAAP02F[[#All],[Column1]:[FundHier1]],5,FALSE))) -> 200 | J94: =IF(ISNA(VLOOKUP(F94,Table_GAAP02A[[#All],[Agency]:[Hier1]],4,FALSE)),"Abolished Agency",(VLOOKUP(F94,Table_GAAP02A[[#All],[Agency]:[Hier1]],4,FALSE))) -> 0825 | K94: =IF(ISNA(VLOOKUP(F94,Table_GAAP02A[[#All],[Agency]:[Hier1]],2,FALSE)),"Abolished Agency",(VLOOKUP(F94,Table_GAAP02A[[#All],[Agency]:[Hier1]],2,FALSE))) -> BUS, CONSUMER SERV, HOUSING | L94: =IF(ISNA(VLOOKUP(F94,Table_GAAP02A[[#All],[Agency]:[Hier1]],3,FALSE)),"Abolished Agency",(VLOOKUP(F94,Table_GAAP02A[[#All],[Agency]:[Hier1]],3,FALSE))) -> DEPT OF CONSUMER AFFAIRS | M94: =IF(ISNA(VLOOKUP(G94,GAAP02F[[#All],[Column1]:[FundName]],2,FALSE)),"Leases",(VLOOKUP(G94,GAAP02F[[#All],[Column1]:[FundName]],2,FALSE))) -> CHIROPRACTIC EXAMINERS' FUND | N94: 0 | O94: 0 | P94: 0 | Q94: 0 | R94: 0 | S94: 0 | T94: =SUM(N94:S94) -> 0 | U94: 0 | V94: 0 | W94: 0 | X94: 0 | Y94: =SUM(U94:X94) -> 0 | Z94: 0 | AA94: 0 | AB94: 0 | AC94: 0 | AD94: =SUM(Z94:AC94) -> 0 | AE94: =N94 +U94-Z94 -> 0 | AF94: =O94 +V94-AA94 -> 0 | AG94: =P94 +W94-AB94 -> 0 | AH94: =Q94 +X94-AC94 -> 0 | AI94: =R94 -> 0 | AJ94: =S94 -> 0 | AK94: =SUM(AE94:AJ94) -> 0
A95: 19 | C95: F | F95: 1111 | G95: 0166 | H95: =F95&G95 -> 11110166 | I95: =IF(ISNA(VLOOKUP(G95,GAAP02F[[#All],[Column1]:[FundHier1]],5,FALSE)),"Leases",(VLOOKUP(G95,GAAP02F[[#All],[Column1]:[FundHier1]],5,FALSE))) -> 200 | J95: =IF(ISNA(VLOOKUP(F95,Table_GAAP02A[[#All],[Agency]:[Hier1]],4,FALSE)),"Abolished Agency",(VLOOKUP(F95,Table_GAAP02A[[#All],[Agency]:[Hier1]],4,FALSE))) -> 0825 | K95: =IF(ISNA(VLOOKUP(F95,Table_GAAP02A[[#All],[Agency]:[Hier1]],2,FALSE)),"Abolished Agency",(VLOOKUP(F95,Table_GAAP02A[[#All],[Agency]:[Hier1]],2,FALSE))) -> BUS, CONSUMER SERV, HOUSING | L95: =IF(ISNA(VLOOKUP(F95,Table_GAAP02A[[#All],[Agency]:[Hier1]],3,FALSE)),"Abolished Agency",(VLOOKUP(F95,Table_GAAP02A[[#All],[Agency]:[Hier1]],3,FALSE))) -> DEPT OF CONSUMER AFFAIRS | M95: =IF(ISNA(VLOOKUP(G95,GAAP02F[[#All],[Column1]:[FundName]],2,FALSE)),"Leases",(VLOOKUP(G95,GAAP02F[[#All],[Column1]:[FundName]],2,FALSE))) -> CERTIFICATION ACCOUNT | N95: 0 | O95: 0 | P95: 0 | Q95: 0 | R95: 0 | S95: 0 | T95: =SUM(N95:S95) -> 0 | U95: 0 | V95: 0 | W95: 0 | X95: 0 | Y95: =SUM(U95:X95) -> 0 | Z95: 0 | AA95: 0 | AB95: 0 | AC95: 0 | AD95: =SUM(Z95:AC95) -> 0 | AE95: =N95 +U95-Z95 -> 0 | AF95: =O95 +V95-AA95 -> 0 | AG95: =P95 +W95-AB95 -> 0 | AH95: =Q95 +X95-AC95 -> 0 | AI95: =R95 -> 0 | AJ95: =S95 -> 0 | AK95: =SUM(AE95:AJ95) -> 0
A96: 19 | C96: F | F96: 1111 | G96: 0239 | H96: =F96&G96 -> 11110239 | I96: =IF(ISNA(VLOOKUP(G96,GAAP02F[[#All],[Column1]:[FundHier1]],5,FALSE)),"Leases",(VLOOKUP(G96,GAAP02F[[#All],[Column1]:[FundHier1]],5,FALSE))) -> 200 | J96: =IF(ISNA(VLOOKUP(F96,Table_GAAP02A[[#All],[Agency]:[Hier1]],4,FALSE)),"Abolished Agency",(VLOOKUP(F96,Table_GAAP02A[[#All],[Agency]:[Hier1]],4,FALSE))) -> 0825 | K96: =IF(ISNA(VLOOKUP(F96,Table_GAAP02A[[#All],[Agency]:[Hier1]],2,FALSE)),"Abolished Agency",(VLOOKUP(F96,Table_GAAP02A[[#All],[Agency]:[Hier1]],2,FALSE))) -> BUS, CONSUMER SERV, HOUSING | L96: =IF(ISNA(VLOOKUP(F96,Table_GAAP02A[[#All],[Agency]:[Hier1]],3,FALSE)),"Abolished Agency",(VLOOKUP(F96,Table_GAAP02A[[#All],[Agency]:[Hier1]],3,FALSE))) -> DEPT OF CONSUMER AFFAIRS | M96: =IF(ISNA(VLOOKUP(G96,GAAP02F[[#All],[Column1]:[FundName]],2,FALSE)),"Leases",(VLOOKUP(G96,GAAP02F[[#All],[Column1]:[FundName]],2,FALSE))) -> PRIVATE SECURITY SERVICES FUND | N96: 0 | O96: 0 | P96: 0 | Q96: 0 | R96: 0 | S96: 0 | T96: =SUM(N96:S96) -> 0 | U96: 0 | V96: 0 | W96: 0 | X96: 0 | Y96: =SUM(U96:X96) -> 0 | Z96: 0 | AA96: 0 | AB96: 0 | AC96: 0 | AD96: =SUM(Z96:AC96) -> 0 | AE96: =N96 +U96-Z96 -> 0 | AF96: =O96 +V96-AA96 -> 0 | AG96: =P96 +W96-AB96 -> 0 | AH96: =Q96 +X96-AC96 -> 0 | AI96: =R96 -> 0 | AJ96: =S96 -> 0 | AK96: =SUM(AE96:AJ96) -> 0
A97: 19 | C97: F | F97: 1111 | G97: 0264 | H97: =F97&G97 -> 11110264 | I97: =IF(ISNA(VLOOKUP(G97,GAAP02F[[#All],[Column1]:[FundHier1]],5,FALSE)),"Leases",(VLOOKUP(G97,GAAP02F[[#All],[Column1]:[FundHier1]],5,FALSE))) -> 200 | J97: =IF(ISNA(VLOOKUP(F97,Table_GAAP02A[[#All],[Agency]:[Hier1]],4,FALSE)),"Abolished Agency",(VLOOKUP(F97,Table_GAAP02A[[#All],[Agency]:[Hier1]],4,FALSE))) -> 0825 | K97: =IF(ISNA(VLOOKUP(F97,Table_GAAP02A[[#All],[Agency]:[Hier1]],2,FALSE)),"Abolished Agency",(VLOOKUP(F97,Table_GAAP02A[[#All],[Agency]:[Hier1]],2,FALSE))) -> BUS, CONSUMER SERV, HOUSING | L97: =IF(ISNA(VLOOKUP(F97,Table_GAAP02A[[#All],[Agency]:[Hier1]],3,FALSE)),"Abolished Agency",(VLOOKUP(F97,Table_GAAP02A[[#All],[Agency]:[Hier1]],3,FALSE))) -> DEPT OF CONSUMER AFFAIRS | M97: =IF(ISNA(VLOOKUP(G97,GAAP02F[[#All],[Column1]:[FundName]],2,FALSE)),"Leases",(VLOOKUP(G97,GAAP02F[[#All],[Column1]:[FundName]],2,FALSE))) -> OSTEOPATHIC EXAMINERS CONTING | N97: 0 | O97: 0 | P97: 0 | Q97: 0 | R97: 0 | S97: 0 | T97: =SUM(N97:S97) -> 0 | U97: 0 | V97: 0 | W97: 0 | X97: 0 | Y97: =SUM(U97:X97) -> 0 | Z97: 0 | AA97: 0 | AB97: 0 | AC97: 0 | AD97: =SUM(Z97:AC97) -> 0 | AE97: =N97 +U97-Z97 -> 0 | AF97: =O97 +V97-AA97 -> 0 | AG97: =P97 +W97-AB97 -> 0 | AH97: =Q97 +X97-AC97 -> 0 | AI97: =R97 -> 0 | AJ97: =S97 -> 0 | AK97: =SUM(AE97:AJ97) -> 0
A98: 19 | C98: F | F98: 1111 | G98: 0280 | H98: =F98&G98 -> 11110280 | I98: =IF(ISNA(VLOOKUP(G98,GAAP02F[[#All],[Column1]:[FundHier1]],5,FALSE)),"Leases",(VLOOKUP(G98,GAAP02F[[#All],[Column1]:[FundHier1]],5,FALSE))) -> 200 | J98: =IF(ISNA(VLOOKUP(F98,Table_GAAP02A[[#All],[Agency]:[Hier1]],4,FALSE)),"Abolished Agency",(VLOOKUP(F98,Table_GAAP02A[[#All],[Agency]:[Hier1]],4,FALSE))) -> 0825 | K98: =IF(ISNA(VLOOKUP(F98,Table_GAAP02A[[#All],[Agency]:[Hier1]],2,FALSE)),"Abolished Agency",(VLOOKUP(F98,Table_GAAP02A[[#All],[Agency]:[Hier1]],2,FALSE))) -> BUS, CONSUMER SERV, HOUSING | L98: =IF(ISNA(VLOOKUP(F98,Table_GAAP02A[[#All],[Agency]:[Hier1]],3,FALSE)),"Abolished Agency",(VLOOKUP(F98,Table_GAAP02A[[#All],[Agency]:[Hier1]],3,FALSE))) -> DEPT OF CONSUMER AFFAIRS | M98: =IF(ISNA(VLOOKUP(G98,GAAP02F[[#All],[Column1]:[FundName]],2,FALSE)),"Leases",(VLOOKUP(G98,GAAP02F[[#All],[Column1]:[FundName]],2,FALSE))) -> PHYSICIAN'S ASSISTANT | N98: 0 | O98: 0 | P98: 0 | Q98: 0 | R98: 0 | S98: 0 | T98: =SUM(N98:S98) -> 0 | U98: 0 | V98: 0 | W98: 0 | X98: 0 | Y98: =SUM(U98:X98) -> 0 | Z98: 0 | AA98: 0 | AB98: 0 | AC98: 0 | AD98: =SUM(Z98:AC98) -> 0 | AE98: =N98 +U98-Z98 -> 0 | AF98: =O98 +V98-AA98 -> 0 | AG98: =P98 +W98-AB98 -> 0 | AH98: =Q98 +X98-AC98 -> 0 | AI98: =R98 -> 0 | AJ98: =S98 -> 0 | AK98: =SUM(AE98:AJ98) -> 0
A99: 19 | C99: F | F99: 1111 | G99: 0295 | H99: =F99&G99 -> 11110295 | I99: =IF(ISNA(VLOOKUP(G99,GAAP02F[[#All],[Column1]:[FundHier1]],5,FALSE)),"Leases",(VLOOKUP(G99,GAAP02F[[#All],[Column1]:[FundHier1]],5,FALSE))) -> 200 | J99: =IF(ISNA(VLOOKUP(F99,Table_GAAP02A[[#All],[Agency]:[Hier1]],4,FALSE)),"Abolished Agency",(VLOOKUP(F99,Table_GAAP02A[[#All],[Agency]:[Hier1]],4,FALSE))) -> 0825 | K99: =IF(ISNA(VLOOKUP(F99,Table_GAAP02A[[#All],[Agency]:[Hier1]],2,FALSE)),"Abolished Agency",(VLOOKUP(F99,Table_GAAP02A[[#All],[Agency]:[Hier1]],2,FALSE))) -> BUS, CONSUMER SERV, HOUSING | L99: =IF(ISNA(VLOOKUP(F99,Table_GAAP02A[[#All],[Agency]:[Hier1]],3,FALSE)),"Abolished Agency",(VLOOKUP(F99,Table_GAAP02A[[#All],[Agency]:[Hier1]],3,FALSE))) -> DEPT OF CONSUMER AFFAIRS | M99: =IF(ISNA(VLOOKUP(G99,GAAP02F[[#All],[Column1]:[FundName]],2,FALSE)),"Leases",(VLOOKUP(G99,GAAP02F[[#All],[Column1]:[FundName]],2,FALSE))) -> BD OF PODIATRIC MEDICINE FUND | N99: 0 | O99: 0 | P99: 0 | Q99: 0 | R99: 0 | S99: 0 | T99: =SUM(N99:S99) -> 0 | U99: 0 | V99: 0 | W99: 0 | X99: 0 | Y99: =SUM(U99:X99) -> 0 | Z99: 0 | AA99: 0 | AB99: 0 | AC99: 0 | AD99: =SUM(Z99:AC99) -> 0 | AE99: =N99 +U99-Z99 -> 0 | AF99: =O99 +V99-AA99 -> 0 | AG99: =P99 +W99-AB99 -> 0 | AH99: =Q99 +X99-AC99 -> 0 | AI99: =R99 -> 0 | AJ99: =S99 -> 0 | AK99: =SUM(AE99:AJ99) -> 0
A100: 19 | C100: F | F100: 1111 | G100: 0305 | H100: =F100&G100 -> 11110305 | I100: =IF(ISNA(VLOOKUP(G100,GAAP02F[[#All],[Column1]:[FundHier1]],5,FALSE)),"Leases",(VLOOKUP(G100,GAAP02F[[#All],[Column1]:[FundHier1]],5,FALSE))) -> 200 | J100: =IF(ISNA(VLOOKUP(F100,Table_GAAP02A[[#All],[Agency]:[Hier1]],4,FALSE)),"Abolished Agency",(VLOOKUP(F100,Table_GAAP02A[[#All],[Agency]:[Hier1]],4,FALSE))) -> 0825 | K100: =IF(ISNA(VLOOKUP(F100,Table_GAAP02A[[#All],[Agency]:[Hier1]],2,FALSE)),"Abolished Agency",(VLOOKUP(F100,Table_GAAP02A[[#All],[Agency]:[Hier1]],2,FALSE))) -> BUS, CONSUMER SERV, HOUSING | L100: =IF(ISNA(VLOOKUP(F100,Table_GAAP02A[[#All],[Agency]:[Hier1]],3,FALSE)),"Abolished Agency",(VLOOKUP(F100,Table_GAAP02A[[#All],[Agency]:[Hier1]],3,FALSE))) -> DEPT OF CONSUMER AFFAIRS | M100: =IF(ISNA(VLOOKUP(G100,GAAP02F[[#All],[Column1]:[FundName]],2,FALSE)),"Leases",(VLOOKUP(G100,GAAP02F[[#All],[Column1]:[FundName]],2,FALSE))) -> PRIVATE POST SECONDARY ADMIN | N100: 0 | O100: 0 | P100: 0 | Q100: 0 | R100: 0 | S100: 0 | T100: =SUM(N100:S100) -> 0 | U100: 0 | V100: 0 | W100: 0 | X100: 0 | Y100: =SUM(U100:X100) -> 0 | Z100: 0 | AA100: 0 | AB100: 0 | AC100: 0 | AD100: =SUM(Z100:AC100) -> 0 | AE100: =N100 +U100-Z100 -> 0 | AF100: =O100 +V100-AA100 -> 0 | AG100: =P100 +W100-AB100 -> 0 | AH100: =Q100 +X100-AC100 -> 0 | AI100: =R100 -> 0 | AJ100: =S100 -> 0 | AK100: =SUM(AE100:AJ100) -> 0
A101: 19 | C101: F | F101: 1111 | G101: 0310 | H101: =F101&G101 -> 11110310 | I101: =IF(ISNA(VLOOKUP(G101,GAAP02F[[#All],[Column1]:[FundHier1]],5,FALSE)),"Leases",(VLOOKUP(G101,GAAP02F[[#All],[Column1]:[FundHier1]],5,FALSE))) -> 200 | J101: =IF(ISNA(VLOOKUP(F101,Table_GAAP02A[[#All],[Agency]:[Hier1]],4,FALSE)),"Abolished Agency",(VLOOKUP(F101,Table_GAAP02A[[#All],[Agency]:[Hier1]],4,FALSE))) -> 0825 | K101: =IF(ISNA(VLOOKUP(F101,Table_GAAP02A[[#All],[Agency]:[Hier1]],2,FALSE)),"Abolished Agency",(VLOOKUP(F101,Table_GAAP02A[[#All],[Agency]:[Hier1]],2,FALSE))) -> BUS, CONSUMER SERV, HOUSING | L101: =IF(ISNA(VLOOKUP(F101,Table_GAAP02A[[#All],[Agency]:[Hier1]],3,FALSE)),"Abolished Agency",(VLOOKUP(F101,Table_GAAP02A[[#All],[Agency]:[Hier1]],3,FALSE))) -> DEPT OF CONSUMER AFFAIRS | M101: =IF(ISNA(VLOOKUP(G101,GAAP02F[[#All],[Column1]:[FundName]],2,FALSE)),"Leases",(VLOOKUP(G101,GAAP02F[[#All],[Column1]:[FundName]],2,FALSE))) -> PSYCHOLOGY FUND | N101: 0 | O101: 0 | P101: 0 | Q101: 0 | R101: 0 | S101: 0 | T101: =SUM(N101:S101) -> 0 | U101: 0 | V101: 0 | W101: 0 | X101: 0 | Y101: =SUM(U101:X101) -> 0 | Z101: 0 | AA101: 0 | AB101: 0 | AC101: 0 | AD101: =SUM(Z101:AC101) -> 0 | AE101: =N101 +U101-Z101 -> 0 | AF101: =O101 +V101-AA101 -> 0 | AG101: =P101 +W101-AB101 -> 0 | AH101: =Q101 +X101-AC101 -> 0 | AI101: =R101 -> 0 | AJ101: =S101 -> 0 | AK101: =SUM(AE101:AJ101) -> 0
...

Sheet 2. Totals by Asset & Exp Code
A1: Capital Assets - Governmental Funds (Non-CSU) | D1: Source: | E1: Tab 1
A2: Assets by Type and Function | D2: Purpose: | E2: Consolidate tab 1 by major capital asset catergory and by function
A3: ='1. Rpt 18s (non-CSU)'!$A$3 -> as of June 30, 2024 | D3: Procedures: | E3: N/A-Spreadsheet is formula driven
A5: Land-0446 | H5: For input in Governmental Activities Workbook only
C6: (Restated) | H6: Amounts in thousands
A7: Expense Code | B7: Function | C7: Beginning Balance | D7: Additions | E7: Deductions | F7: Ending Balance | H7: Beginning Balance | I7: Additions | J7: Deductions | K7: Ending Balance
A8: 808 | B8: General Government | C8: =SUM(SUMIFS('1. Rpt 18s (non-CSU)'!R$9:R$555,'1. Rpt 18s (non-CSU)'!$J$9:$J$555,A8,'1. Rpt 18s (non-CSU)'!$I$9:$I$555,100),SUMIFS('1. Rpt 18s (non-CSU)'!R$9:R$555,'1. Rpt 18s (non-CSU)'!$J$9:$J$555,A8,'1. Rpt 18s (non-CSU)'!$I$9:$I$555,200),SUMIFS('1. Rpt 18s (non-CSU)'!R$9:R$555,'1. Rpt 18s (non-CSU)'!$J$9:$J$555,A8,'1. Rpt 18s (non-CSU)'!$I$9:$I$555,300)) -> 0 | D8: 0 | E8: 0 | F8: =+C8 +D8-E8 -> 0
A9: 810 | B9: Education | C9: =SUM(SUMIFS('1. Rpt 18s (non-CSU)'!R$9:R$555,'1. Rpt 18s (non-CSU)'!$J$9:$J$555,A9,'1. Rpt 18s (non-CSU)'!$I$9:$I$555,100),SUMIFS('1. Rpt 18s (non-CSU)'!R$9:R$555,'1. Rpt 18s (non-CSU)'!$J$9:$J$555,A9,'1. Rpt 18s (non-CSU)'!$I$9:$I$555,200),SUMIFS('1. Rpt 18s (non-CSU)'!R$9:R$555,'1. Rpt 18s (non-CSU)'!$J$9:$J$555,A9,'1. Rpt 18s (non-CSU)'!$I$9:$I$555,300)) -> 0 | D9: 0 | E9: 0 | F9: =+C9 +D9-E9 -> 0
A10: 815 | B10: Health & Human Services | C10: =SUM(SUMIFS('1. Rpt 18s (non-CSU)'!R$9:R$555,'1. Rpt 18s (non-CSU)'!$J$9:$J$555,A10,'1. Rpt 18s (non-CSU)'!$I$9:$I$555,100),SUMIFS('1. Rpt 18s (non-CSU)'!R$9:R$555,'1. Rpt 18s (non-CSU)'!$J$9:$J$555,A10,'1. Rpt 18s (non-CSU)'!$I$9:$I$555,200),SUMIFS('1. Rpt 18s (non-CSU)'!R$9:R$555,'1. Rpt 18s (non-CSU)'!$J$9:$J$555,A10,'1. Rpt 18s (non-CSU)'!$I$9:$I$555,300)) -> 0 | D10: 0 | E10: 0 | F10: =+C10 +D10-E10 -> 0
A11: 820 | B11: Natural Resources & Environmental Protection | C11: =SUM(SUMIFS('1. Rpt 18s (non-CSU)'!R$9:R$555,'1. Rpt 18s (non-CSU)'!$J$9:$J$555,A11,'1. Rpt 18s (non-CSU)'!$I$9:$I$555,100),SUMIFS('1. Rpt 18s (non-CSU)'!R$9:R$555,'1. Rpt 18s (non-CSU)'!$J$9:$J$555,A11,'1. Rpt 18s (non-CSU)'!$I$9:$I$555,200),SUMIFS('1. Rpt 18s (non-CSU)'!R$9:R$555,'1. Rpt 18s (non-CSU)'!$J$9:$J$555,A11,'1. Rpt 18s (non-CSU)'!$I$9:$I$555,300)) -> 0 | D11: 0 | E11: 0 | F11: =+C11 +D11-E11 -> 0
A12: 825 | B12: Business, Consumer Services, & Housing | C12: =SUM(SUMIFS('1. Rpt 18s (non-CSU)'!R$9:R$555,'1. Rpt 18s (non-CSU)'!$J$9:$J$555,A12,'1. Rpt 18s (non-CSU)'!$I$9:$I$555,100),SUMIFS('1. Rpt 18s (non-CSU)'!R$9:R$555,'1. Rpt 18s (non-CSU)'!$J$9:$J$555,A12,'1. Rpt 18s (non-CSU)'!$I$9:$I$555,200),SUMIFS('1. Rpt 18s (non-CSU)'!R$9:R$555,'1. Rpt 18s (non-CSU)'!$J$9:$J$555,A12,'1. Rpt 18s (non-CSU)'!$I$9:$I$555,300)) -> 0 | D12: 0 | E12: 0 | F12: =+C12 +D12-E12 -> 0
A13: 830 | B13: Transportation | C13: =SUM(SUMIFS('1. Rpt 18s (non-CSU)'!R$9:R$555,'1. Rpt 18s (non-CSU)'!$J$9:$J$555,A13,'1. Rpt 18s (non-CSU)'!$I$9:$I$555,100),SUMIFS('1. Rpt 18s (non-CSU)'!R$9:R$555,'1. Rpt 18s (non-CSU)'!$J$9:$J$555,A13,'1. Rpt 18s (non-CSU)'!$I$9:$I$555,200),SUMIFS('1. Rpt 18s (non-CSU)'!R$9:R$555,'1. Rpt 18s (non-CSU)'!$J$9:$J$555,A13,'1. Rpt 18s (non-CSU)'!$I$9:$I$555,300)) -> 0 | D13: 0 | E13: 0 | F13: =+C13 +D13-E13 -> 0
A14: 835 | B14: Corrections and Rehabilitation | C14: =SUM(SUMIFS('1. Rpt 18s (non-CSU)'!R$9:R$555,'1. Rpt 18s (non-CSU)'!$J$9:$J$555,A14,'1. Rpt 18s (non-CSU)'!$I$9:$I$555,100),SUMIFS('1. Rpt 18s (non-CSU)'!R$9:R$555,'1. Rpt 18s (non-CSU)'!$J$9:$J$555,A14,'1. Rpt 18s (non-CSU)'!$I$9:$I$555,200),SUMIFS('1. Rpt 18s (non-CSU)'!R$9:R$555,'1. Rpt 18s (non-CSU)'!$J$9:$J$555,A14,'1. Rpt 18s (non-CSU)'!$I$9:$I$555,300)) -> 0 | D14: 0 | E14: 0 | F14: =+C14 +D14-E14 -> 0
B15: Total | C15: =SUM(C8:C14) -> 0 | D15: =SUM(D8:D14) -> 0 | E15: =SUM(E8:E14) -> 0 | F15: =SUM(F8:F14) -> 0 | H15: =ROUND(C15,0)/1000 -> 0 | I15: =ROUND(D15,0)/1000 -> 0 | J15: =ROUND(E15,0)/1000 -> 0 | K15: =ROUND(F15,0)/1000 -> 0
A18: Building & Building Improvements-0448
A19: (Reported as Structures) | C19: (Restated)
A20: Expense Code | B20: Function | C20: Beginning Balance | D20: Additions | E20: Deductions | F20: Ending Balance
A21: 808 | B21: General Government | C21: =SUM(SUMIFS('1. Rpt 18s (non-CSU)'!S$9:S$555,'1. Rpt 18s (non-CSU)'!$J$9:$J$555,A21,'1. Rpt 18s (non-CSU)'!$I$9:$I$555,100),SUMIFS('1. Rpt 18s (non-CSU)'!S$9:S$555,'1. Rpt 18s (non-CSU)'!$J$9:$J$555,A21,'1. Rpt 18s (non-CSU)'!$I$9:$I$555,200),SUMIFS('1. Rpt 18s (non-CSU)'!S$9:S$555,'1. Rpt 18s (non-CSU)'!$J$9:$J$555,A21,'1. Rpt 18s (non-CSU)'!$I$9:$I$555,300)) -> 0 | D21: 0 | E21: 0 | F21: =+C21+D21-E21 -> 0
A22: 810 | B22: Education | C22: =SUM(SUMIFS('1. Rpt 18s (non-CSU)'!S$9:S$555,'1. Rpt 18s (non-CSU)'!$J$9:$J$555,A22,'1. Rpt 18s (non-CSU)'!$I$9:$I$555,100),SUMIFS('1. Rpt 18s (non-CSU)'!S$9:S$555,'1. Rpt 18s (non-CSU)'!$J$9:$J$555,A22,'1. Rpt 18s (non-CSU)'!$I$9:$I$555,200),SUMIFS('1. Rpt 18s (non-CSU)'!S$9:S$555,'1. Rpt 18s (non-CSU)'!$J$9:$J$555,A22,'1. Rpt 18s (non-CSU)'!$I$9:$I$555,300)) -> 0 | D22: 0 | E22: 0 | F22: =+C22+D22-E22 -> 0
A23: 815 | B23: Health & Human Services | C23: =SUM(SUMIFS('1. Rpt 18s (non-CSU)'!S$9:S$555,'1. Rpt 18s (non-CSU)'!$J$9:$J$555,A23,'1. Rpt 18s (non-CSU)'!$I$9:$I$555,100),SUMIFS('1. Rpt 18s (non-CSU)'!S$9:S$555,'1. Rpt 18s (non-CSU)'!$J$9:$J$555,A23,'1. Rpt 18s (non-CSU)'!$I$9:$I$555,200),SUMIFS('1. Rpt 18s (non-CSU)'!S$9:S$555,'1. Rpt 18s (non-CSU)'!$J$9:$J$555,A23,'1. Rpt 18s (non-CSU)'!$I$9:$I$555,300)) -> 0 | D23: 0 | E23: 0 | F23: =+C23+D23-E23 -> 0
A24: 820 | B24: Natural Resources & Environmental Protection | C24: =SUM(SUMIFS('1. Rpt 18s (non-CSU)'!S$9:S$555,'1. Rpt 18s (non-CSU)'!$J$9:$J$555,A24,'1. Rpt 18s (non-CSU)'!$I$9:$I$555,100),SUMIFS('1. Rpt 18s (non-CSU)'!S$9:S$555,'1. Rpt 18s (non-CSU)'!$J$9:$J$555,A24,'1. Rpt 18s (non-CSU)'!$I$9:$I$555,200),SUMIFS('1. Rpt 18s (non-CSU)'!S$9:S$555,'1. Rpt 18s (non-CSU)'!$J$9:$J$555,A24,'1. Rpt 18s (non-CSU)'!$I$9:$I$555,300)) -> 0 | D24: 0 | E24: 0 | F24: =+C24+D24-E24 -> 0
A25: 825 | B25: Business, Consumer Services, & Housing | C25: =SUM(SUMIFS('1. Rpt 18s (non-CSU)'!S$9:S$555,'1. Rpt 18s (non-CSU)'!$J$9:$J$555,A25,'1. Rpt 18s (non-CSU)'!$I$9:$I$555,100),SUMIFS('1. Rpt 18s (non-CSU)'!S$9:S$555,'1. Rpt 18s (non-CSU)'!$J$9:$J$555,A25,'1. Rpt 18s (non-CSU)'!$I$9:$I$555,200),SUMIFS('1. Rpt 18s (non-CSU)'!S$9:S$555,'1. Rpt 18s (non-CSU)'!$J$9:$J$555,A25,'1. Rpt 18s (non-CSU)'!$I$9:$I$555,300)) -> 0 | D25: 0 | E25: 0 | F25: =+C25+D25-E25 -> 0
A26: 830 | B26: Transportation | C26: =SUM(SUMIFS('1. Rpt 18s (non-CSU)'!S$9:S$555,'1. Rpt 18s (non-CSU)'!$J$9:$J$555,A26,'1. Rpt 18s (non-CSU)'!$I$9:$I$555,100),SUMIFS('1. Rpt 18s (non-CSU)'!S$9:S$555,'1. Rpt 18s (non-CSU)'!$J$9:$J$555,A26,'1. Rpt 18s (non-CSU)'!$I$9:$I$555,200),SUMIFS('1. Rpt 18s (non-CSU)'!S$9:S$555,'1. Rpt 18s (non-CSU)'!$J$9:$J$555,A26,'1. Rpt 18s (non-CSU)'!$I$9:$I$555,300)) -> 0 | D26: 0 | E26: 0 | F26: =+C26+D26-E26 -> 0
A27: 835 | B27: Corrections and Rehabilitation | C27: =SUM(SUMIFS('1. Rpt 18s (non-CSU)'!S$9:S$555,'1. Rpt 18s (non-CSU)'!$J$9:$J$555,A27,'1. Rpt 18s (non-CSU)'!$I$9:$I$555,100),SUMIFS('1. Rpt 18s (non-CSU)'!S$9:S$555,'1. Rpt 18s (non-CSU)'!$J$9:$J$555,A27,'1. Rpt 18s (non-CSU)'!$I$9:$I$555,200),SUMIFS('1. Rpt 18s (non-CSU)'!S$9:S$555,'1. Rpt 18s (non-CSU)'!$J$9:$J$555,A27,'1. Rpt 18s (non-CSU)'!$I$9:$I$555,300)) -> 0 | D27: 0 | E27: 0 | F27: =+C27+D27-E27 -> 0
B28: Total | C28: =SUM(C21:C27) -> 0 | D28: =SUM(D21:D27) -> 0 | E28: =SUM(E21:E27) -> 0 | F28: =SUM(F21:F27) -> 0 | H28: =ROUND(C28,0)/1000 -> 0 | I28: =ROUND(D28,0)/1000 -> 0 | J28: =ROUND(E28,0)/1000 -> 0 | K28: =ROUND(F28,0)/1000 -> 0
A31: Other Tangible Assets(Non-amortizable)-0447
A33: Expense Code | B33: Function | C33: Beginning Balance | D33: Additions | E33: Deductions | F33: Ending Balance
A34: 808 | B34: General Government | C34: =SUMIF('1. Rpt 18s (non-CSU)'!$J$9:$J$555,A34,'1. Rpt 18s (non-CSU)'!#REF!) -> #REF! | D34: =SUMIF('1. Rpt 18s (non-CSU)'!$J$9:$J$555,A34,'1. Rpt 18s (non-CSU)'!#REF!) -> #REF! | E34: =SUMIF('1. Rpt 18s (non-CSU)'!$J$9:$J$555,A34,'1. Rpt 18s (non-CSU)'!#REF!) -> #REF! | F34: =+C34 +D34-E34 -> #REF!
A35: 810 | B35: Education | C35: =SUMIF('1. Rpt 18s (non-CSU)'!$J$9:$J$555,A35,'1. Rpt 18s (non-CSU)'!#REF!) -> #REF! | D35: =SUMIF('1. Rpt 18s (non-CSU)'!$J$9:$J$555,A35,'1. Rpt 18s (non-CSU)'!#REF!) -> #REF! | E35: =SUMIF('1. Rpt 18s (non-CSU)'!$J$9:$J$555,A35,'1. Rpt 18s (non-CSU)'!#REF!) -> #REF! | F35: =+C35 +D35-E35 -> #REF!
A36: 815 | B36: Health & Human Services | C36: =SUMIF('1. Rpt 18s (non-CSU)'!$J$9:$J$555,A36,'1. Rpt 18s (non-CSU)'!#REF!) -> #REF! | D36: =SUMIF('1. Rpt 18s (non-CSU)'!$J$9:$J$555,A36,'1. Rpt 18s (non-CSU)'!#REF!) -> #REF! | E36: =SUMIF('1. Rpt 18s (non-CSU)'!$J$9:$J$555,A36,'1. Rpt 18s (non-CSU)'!#REF!) -> #REF! | F36: =+C36 +D36-E36 -> #REF!
A37: 820 | B37: Natural Resources & Environmental Protection | C37: =SUMIF('1. Rpt 18s (non-CSU)'!$J$9:$J$555,A37,'1. Rpt 18s (non-CSU)'!#REF!) -> #REF! | D37: =SUMIF('1. Rpt 18s (non-CSU)'!$J$9:$J$555,A37,'1. Rpt 18s (non-CSU)'!#REF!) -> #REF! | E37: =SUMIF('1. Rpt 18s (non-CSU)'!$J$9:$J$555,A37,'1. Rpt 18s (non-CSU)'!#REF!) -> #REF! | F37: =+C37 +D37-E37 -> #REF!
A38: 825 | B38: Business, Consumer Services, & Housing | C38: =SUMIF('1. Rpt 18s (non-CSU)'!$J$9:$J$555,A38,'1. Rpt 18s (non-CSU)'!#REF!) -> #REF! | D38: =SUMIF('1. Rpt 18s (non-CSU)'!$J$9:$J$555,A38,'1. Rpt 18s (non-CSU)'!#REF!) -> #REF! | E38: =SUMIF('1. Rpt 18s (non-CSU)'!$J$9:$J$555,A38,'1. Rpt 18s (non-CSU)'!#REF!) -> #REF! | F38: =+C38 +D38-E38 -> #REF!
A39: 830 | B39: Transportation | C39: =SUMIF('1. Rpt 18s (non-CSU)'!$J$9:$J$555,A39,'1. Rpt 18s (non-CSU)'!#REF!) -> #REF! | D39: =SUMIF('1. Rpt 18s (non-CSU)'!$J$9:$J$555,A39,'1. Rpt 18s (non-CSU)'!#REF!) -> #REF! | E39: =SUMIF('1. Rpt 18s (non-CSU)'!$J$9:$J$555,A39,'1. Rpt 18s (non-CSU)'!#REF!) -> #REF! | F39: =+C39 +D39-E39 -> #REF!
A40: 835 | B40: Corrections and Rehabilitation | C40: =SUMIF('1. Rpt 18s (non-CSU)'!$J$9:$J$555,A40,'1. Rpt 18s (non-CSU)'!#REF!) -> #REF! | D40: =SUMIF('1. Rpt 18s (non-CSU)'!$J$9:$J$555,A40,'1. Rpt 18s (non-CSU)'!#REF!) -> #REF! | E40: =SUMIF('1. Rpt 18s (non-CSU)'!$J$9:$J$555,A40,'1. Rpt 18s (non-CSU)'!#REF!) -> #REF! | F40: =+C40 +D40-E40 -> #REF!
B41: Total | C41: =SUM(C34:C40) -> #REF! | D41: =SUM(D34:D40) -> #REF! | E41: =SUM(E34:E40) -> #REF! | F41: =SUM(F34:F40) -> #REF! | H41: =ROUND(C41,0)/1000 -> #REF! | I41: =ROUND(D41,0)/1000 -> #REF! | J41: =ROUND(E41,0)/1000 -> #REF! | K41: =ROUND(F41,0)/1000 -> #REF!
C42: =IF(C41='1. Rpt 18s (non-CSU)'!#REF!,"OK","Formula Error") -> #REF! | D42: =IF(D41='1. Rpt 18s (non-CSU)'!#REF!,"OK","Formula Error") -> #REF! | E42: =IF(E41='1. Rpt 18s (non-CSU)'!#REF!,"OK","Formula Error") -> #REF! | F42: =IF(F41='1. Rpt 18s (non-CSU)'!#REF!,"OK","Formula Error") -> #REF!
A44: Improvements Other Than Buildings-0449
A45: (Reported as Structures) | C45: (Restated)
A46: Expense Code | B46: Function | C46: Beginning Balance | D46: Additions | E46: Deductions | F46: Ending Balance
A47: 808 | B47: General Government | C47: =SUMIF('1. Rpt 18s (non-CSU)'!$J$9:$J$555,A47,'1. Rpt 18s (non-CSU)'!#REF!) -> #REF! | D47: =SUMIF('1. Rpt 18s (non-CSU)'!$J$9:$J$555,A47,'1. Rpt 18s (non-CSU)'!#REF!) -> #REF! | E47: =SUMIF('1. Rpt 18s (non-CSU)'!$J$9:$J$555,A47,'1. Rpt 18s (non-CSU)'!#REF!) -> #REF! | F47: =+C47 +D47-E47 -> #REF!
A48: 810 | B48: Education | C48: =SUMIF('1. Rpt 18s (non-CSU)'!$J$9:$J$555,A48,'1. Rpt 18s (non-CSU)'!#REF!) -> #REF! | D48: =SUMIF('1. Rpt 18s (non-CSU)'!$J$9:$J$555,A48,'1. Rpt 18s (non-CSU)'!#REF!) -> #REF! | E48: =SUMIF('1. Rpt 18s (non-CSU)'!$J$9:$J$555,A48,'1. Rpt 18s (non-CSU)'!#REF!) -> #REF! | F48: =+C48 +D48-E48 -> #REF!
A49: 815 | B49: Health & Human Services | C49: =SUMIF('1. Rpt 18s (non-CSU)'!$J$9:$J$555,A49,'1. Rpt 18s (non-CSU)'!#REF!) -> #REF! | D49: =SUMIF('1. Rpt 18s (non-CSU)'!$J$9:$J$555,A49,'1. Rpt 18s (non-CSU)'!#REF!) -> #REF! | E49: =SUMIF('1. Rpt 18s (non-CSU)'!$J$9:$J$555,A49,'1. Rpt 18s (non-CSU)'!#REF!) -> #REF! | F49: =+C49 +D49-E49 -> #REF!
A50: 820 | B50: Natural Resources & Environmental Protection | C50: =SUMIF('1. Rpt 18s (non-CSU)'!$J$9:$J$555,A50,'1. Rpt 18s (non-CSU)'!#REF!) -> #REF! | D50: =SUMIF('1. Rpt 18s (non-CSU)'!$J$9:$J$555,A50,'1. Rpt 18s (non-CSU)'!#REF!) -> #REF! | E50: =SUMIF('1. Rpt 18s (non-CSU)'!$J$9:$J$555,A50,'1. Rpt 18s (non-CSU)'!#REF!) -> #REF! | F50: =+C50 +D50-E50 -> #REF!
A51: 825 | B51: Business, Consumer Services, & Housing | C51: =SUMIF('1. Rpt 18s (non-CSU)'!$J$9:$J$555,A51,'1. Rpt 18s (non-CSU)'!#REF!) -> #REF! | D51: =SUMIF('1. Rpt 18s (non-CSU)'!$J$9:$J$555,A51,'1. Rpt 18s (non-CSU)'!#REF!) -> #REF! | E51: =SUMIF('1. Rpt 18s (non-CSU)'!$J$9:$J$555,A51,'1. Rpt 18s (non-CSU)'!#REF!) -> #REF! | F51: =+C51 +D51-E51 -> #REF!
A52: 830 | B52: Transportation | C52: =SUMIF('1. Rpt 18s (non-CSU)'!$J$9:$J$555,A52,'1. Rpt 18s (non-CSU)'!#REF!) -> #REF! | D52: =SUMIF('1. Rpt 18s (non-CSU)'!$J$9:$J$555,A52,'1. Rpt 18s (non-CSU)'!#REF!) -> #REF! | E52: =SUMIF('1. Rpt 18s (non-CSU)'!$J$9:$J$555,A52,'1. Rpt 18s (non-CSU)'!#REF!) -> #REF! | F52: =+C52 +D52-E52 -> #REF!
A53: 835 | B53: Corrections and Rehabilitation | C53: =SUMIF('1. Rpt 18s (non-CSU)'!$J$9:$J$555,A53,'1. Rpt 18s (non-CSU)'!#REF!) -> #REF! | D53: =SUMIF('1. Rpt 18s (non-CSU)'!$J$9:$J$555,A53,'1. Rpt 18s (non-CSU)'!#REF!) -> #REF! | E53: =SUMIF('1. Rpt 18s (non-CSU)'!$J$9:$J$555,A53,'1. Rpt 18s (non-CSU)'!#REF!) -> #REF! | F53: =+C53 +D53-E53 -> #REF!
B54: Total | C54: =SUM(C47:C53) -> #REF! | D54: =SUM(D47:D53) -> #REF! | E54: =SUM(E47:E53) -> #REF! | F54: =SUM(F47:F53) -> #REF! | H54: =ROUND(C54,0)/1000 -> #REF! | I54: =ROUND(D54,0)/1000 -> #REF! | J54: =ROUND(E54,0)/1000 -> #REF! | K54: =ROUND(F54,0)/1000 -> #REF!
C55: =IF(C54='1. Rpt 18s (non-CSU)'!#REF!,"OK","Formula Error") -> #REF! | D55: =IF(D54='1. Rpt 18s (non-CSU)'!#REF!,"OK","Formula Error") -> #REF! | E55: =IF(E54='1. Rpt 18s (non-CSU)'!#REF!,"OK","Formula Error") -> #REF! | F55: =IF(F54='1. Rpt 18s (non-CSU)'!#REF!,"OK","Formula Error") -> #REF!
A57: Equipment-0450
C58: (Restated)
A59: Expense Code | B59: Function | C59: Beginning Balance | D59: Additions | E59: Deductions | F59: Ending Balance
A60: 808 | B60: General Government | C60: =SUMIF('1. Rpt 18s (non-CSU)'!$J$9:$J$555,A60,'1. Rpt 18s (non-CSU)'!#REF!) -> #REF! | D60: =SUMIF('1. Rpt 18s (non-CSU)'!$J$9:$J$555,A60,'1. Rpt 18s (non-CSU)'!#REF!) -> #REF! | E60: =SUMIF('1. Rpt 18s (non-CSU)'!$J$9:$J$555,A60,'1. Rpt 18s (non-CSU)'!#REF!) -> #REF! | F60: =+C60 +D60-E60 -> #REF!
A61: 810 | B61: Education | C61: =SUMIF('1. Rpt 18s (non-CSU)'!$J$9:$J$555,A61,'1. Rpt 18s (non-CSU)'!#REF!) -> #REF! | D61: =SUMIF('1. Rpt 18s (non-CSU)'!$J$9:$J$555,A61,'1. Rpt 18s (non-CSU)'!#REF!) -> #REF! | E61: =SUMIF('1. Rpt 18s (non-CSU)'!$J$9:$J$555,A61,'1. Rpt 18s (non-CSU)'!#REF!) -> #REF! | F61: =+C61 +D61-E61 -> #REF!
A62: 815 | B62: Health & Human Services | C62: =SUMIF('1. Rpt 18s (non-CSU)'!$J$9:$J$555,A62,'1. Rpt 18s (non-CSU)'!#REF!) -> #REF! | D62: =SUMIF('1. Rpt 18s (non-CSU)'!$J$9:$J$555,A62,'1. Rpt 18s (non-CSU)'!#REF!) -> #REF! | E62: =SUMIF('1. Rpt 18s (non-CSU)'!$J$9:$J$555,A62,'1. Rpt 18s (non-CSU)'!#REF!) -> #REF! | F62: =+C62 +D62-E62 -> #REF!
A63: 820 | B63: Natural Resources & Environmental Protection | C63: =SUMIF('1. Rpt 18s (non-CSU)'!$J$9:$J$555,A63,'1. Rpt 18s (non-CSU)'!#REF!) -> #REF! | D63: =SUMIF('1. Rpt 18s (non-CSU)'!$J$9:$J$555,A63,'1. Rpt 18s (non-CSU)'!#REF!) -> #REF! | E63: =SUMIF('1. Rpt 18s (non-CSU)'!$J$9:$J$555,A63,'1. Rpt 18s (non-CSU)'!#REF!) -> #REF! | F63: =+C63 +D63-E63 -> #REF!
A64: 825 | B64: Business, Consumer Services, & Housing | C64: =SUMIF('1. Rpt 18s (non-CSU)'!$J$9:$J$555,A64,'1. Rpt 18s (non-CSU)'!#REF!) -> #REF! | D64: =SUMIF('1. Rpt 18s (non-CSU)'!$J$9:$J$555,A64,'1. Rpt 18s (non-CSU)'!#REF!) -> #REF! | E64: =SUMIF('1. Rpt 18s (non-CSU)'!$J$9:$J$555,A64,'1. Rpt 18s (non-CSU)'!#REF!) -> #REF! | F64: =+C64 +D64-E64 -> #REF!
A65: 830 | B65: Transportation | C65: =SUMIF('1. Rpt 18s (non-CSU)'!$J$9:$J$555,A65,'1. Rpt 18s (non-CSU)'!#REF!) -> #REF! | D65: =SUMIF('1. Rpt 18s (non-CSU)'!$J$9:$J$555,A65,'1. Rpt 18s (non-CSU)'!#REF!) -> #REF! | E65: =SUMIF('1. Rpt 18s (non-CSU)'!$J$9:$J$555,A65,'1. Rpt 18s (non-CSU)'!#REF!) -> #REF! | F65: =+C65 +D65-E65 -> #REF!
A66: 835 | B66: Corrections and Rehabilitation | C66: =SUMIF('1. Rpt 18s (non-CSU)'!$J$9:$J$555,A66,'1. Rpt 18s (non-CSU)'!#REF!) -> #REF! | D66: =SUMIF('1. Rpt 18s (non-CSU)'!$J$9:$J$555,A66,'1. Rpt 18s (non-CSU)'!#REF!) -> #REF! | E66: =SUMIF('1. Rpt 18s (non-CSU)'!$J$9:$J$555,A66,'1. Rpt 18s (non-CSU)'!#REF!) -> #REF! | F66: =+C66 +D66-E66 -> #REF!
B67: Total | C67: =SUM(C60:C66) -> #REF! | D67: =SUM(D60:D66) -> #REF! | E67: =SUM(E60:E66) -> #REF! | F67: =SUM(F60:F66) -> #REF! | H67: =ROUND(C67,0)/1000 -> #REF! | I67: =ROUND(D67,0)/1000 -> #REF! | J67: =ROUND(E67,0)/1000 -> #REF! | K67: =ROUND(F67,0)/1000 -> #REF!
C68: =IF(C67='1. Rpt 18s (non-CSU)'!#REF!,"OK","Formula Error") -> #REF! | D68: =IF(D67='1. Rpt 18s (non-CSU)'!#REF!,"OK","Formula Error") -> #REF! | E68: =IF(E67='1. Rpt 18s (non-CSU)'!#REF!,"OK","Formula Error") -> #REF! | F68: =IF(F67='1. Rpt 18s (non-CSU)'!#REF!,"OK","Formula Error") -> #REF!
A70: Construction Work in Progress (CWIP)-0455
C71: (Restated)
A72: Expense Code | B72: Function | C72: Beginning Balance | D72: Additions | E72: Deductions | F72: Ending Balance
A73: 808 | B73: General Government | C73: =SUMIF('1. Rpt 18s (non-CSU)'!$J$9:$J$555,A73,'1. Rpt 18s (non-CSU)'!#REF!) -> #REF! | D73: =SUMIF('1. Rpt 18s (non-CSU)'!$J$9:$J$555,A73,'1. Rpt 18s (non-CSU)'!#REF!) -> #REF! | E73: =SUMIF('1. Rpt 18s (non-CSU)'!$J$9:$J$555,A73,'1. Rpt 18s (non-CSU)'!#REF!) -> #REF! | F73: =+C73 +D73-E73 -> #REF!
A74: 810 | B74: Education | C74: =SUMIF('1. Rpt 18s (non-CSU)'!$J$9:$J$555,A74,'1. Rpt 18s (non-CSU)'!#REF!) -> #REF! | D74: =SUMIF('1. Rpt 18s (non-CSU)'!$J$9:$J$555,A74,'1. Rpt 18s (non-CSU)'!#REF!) -> #REF! | E74: =SUMIF('1. Rpt 18s (non-CSU)'!$J$9:$J$555,A74,'1. Rpt 18s (non-CSU)'!#REF!) -> #REF! | F74: =+C74 +D74-E74 -> #REF!
A75: 815 | B75: Health & Human Services | C75: =SUMIF('1. Rpt 18s (non-CSU)'!$J$9:$J$555,A75,'1. Rpt 18s (non-CSU)'!#REF!) -> #REF! | D75: =SUMIF('1. Rpt 18s (non-CSU)'!$J$9:$J$555,A75,'1. Rpt 18s (non-CSU)'!#REF!) -> #REF! | E75: =SUMIF('1. Rpt 18s (non-CSU)'!$J$9:$J$555,A75,'1. Rpt 18s (non-CSU)'!#REF!) -> #REF! | F75: =+C75 +D75-E75 -> #REF!
A76: 820 | B76: Natural Resources & Environmental Protection | C76: =SUMIF('1. Rpt 18s (non-CSU)'!$J$9:$J$555,A76,'1. Rpt 18s (non-CSU)'!#REF!) -> #REF! | D76: =SUMIF('1. Rpt 18s (non-CSU)'!$J$9:$J$555,A76,'1. Rpt 18s (non-CSU)'!#REF!) -> #REF! | E76: =SUMIF('1. Rpt 18s (non-CSU)'!$J$9:$J$555,A76,'1. Rpt 18s (non-CSU)'!#REF!) -> #REF! | F76: =+C76 +D76-E76 -> #REF!
A77: 825 | B77: Business, Consumer Services, & Housing | C77: =SUMIF('1. Rpt 18s (non-CSU)'!$J$9:$J$555,A77,'1. Rpt 18s (non-CSU)'!#REF!) -> #REF! | D77: =SUMIF('1. Rpt 18s (non-CSU)'!$J$9:$J$555,A77,'1. Rpt 18s (non-CSU)'!#REF!) -> #REF! | E77: =SUMIF('1. Rpt 18s (non-CSU)'!$J$9:$J$555,A77,'1. Rpt 18s (non-CSU)'!#REF!) -> #REF! | F77: =+C77 +D77-E77 -> #REF!
A78: 830 | B78: Transportation | C78: =SUMIF('1. Rpt 18s (non-CSU)'!$J$9:$J$555,A78,'1. Rpt 18s (non-CSU)'!#REF!) -> #REF! | D78: =SUMIF('1. Rpt 18s (non-CSU)'!$J$9:$J$555,A78,'1. Rpt 18s (non-CSU)'!#REF!) -> #REF! | E78: =SUMIF('1. Rpt 18s (non-CSU)'!$J$9:$J$555,A78,'1. Rpt 18s (non-CSU)'!#REF!) -> #REF! | F78: =+C78 +D78-E78 -> #REF!
A79: 835 | B79: Corrections and Rehabilitation | C79: =SUMIF('1. Rpt 18s (non-CSU)'!$J$9:$J$555,A79,'1. Rpt 18s (non-CSU)'!#REF!) -> #REF! | D79: =SUMIF('1. Rpt 18s (non-CSU)'!$J$9:$J$555,A79,'1. Rpt 18s (non-CSU)'!#REF!) -> #REF! | E79: =SUMIF('1. Rpt 18s (non-CSU)'!$J$9:$J$555,A79,'1. Rpt 18s (non-CSU)'!#REF!) -> #REF! | F79: =+C79 +D79-E79 -> #REF!
B80: Total | C80: =SUM(C73:C79) -> #REF! | D80: =SUM(D73:D79) -> #REF! | E80: =SUM(E73:E79) -> #REF! | F80: =SUM(F73:F79) -> #REF! | H80: =ROUND(C80,0)/1000 -> #REF! | I80: =ROUND(D80,0)/1000 -> #REF! | J80: =ROUND(E80,0)/1000 -> #REF! | K80: =ROUND(F80,0)/1000 -> #REF!
C81: =IF(C80='1. Rpt 18s (non-CSU)'!#REF!,"OK","Formula Error") -> #REF! | D81: =IF(D80='1. Rpt 18s (non-CSU)'!#REF!,"OK","Formula Error") -> #REF! | E81: =IF(E80='1. Rpt 18s (non-CSU)'!#REF!,"OK","Formula Error") -> #REF! | F81: =IF(F80='1. Rpt 18s (non-CSU)'!#REF!,"OK","Formula Error") -> #REF!
A83: Infrastructure (Non-depreciable)-0452
A85: Expense Code | B85: Function | C85: Beginning Balance | D85: Additions | E85: Deductions | F85: Ending Balance
A86: 808 | B86: General Government | C86: =SUMIF('1. Rpt 18s (non-CSU)'!$J$9:$J$555,A86,'1. Rpt 18s (non-CSU)'!#REF!) -> #REF! | D86: =SUMIF('1. Rpt 18s (non-CSU)'!$J$9:$J$555,A86,'1. Rpt 18s (non-CSU)'!#REF!) -> #REF! | E86: =SUMIF('1. Rpt 18s (non-CSU)'!$J$9:$J$555,A86,'1. Rpt 18s (non-CSU)'!#REF!) -> #REF! | F86: =+C86 +D86-E86 -> #REF!
A87: 810 | B87: Education | C87: =SUMIF('1. Rpt 18s (non-CSU)'!$J$9:$J$555,A87,'1. Rpt 18s (non-CSU)'!#REF!) -> #REF! | D87: =SUMIF('1. Rpt 18s (non-CSU)'!$J$9:$J$555,A87,'1. Rpt 18s (non-CSU)'!#REF!) -> #REF! | E87: =SUMIF('1. Rpt 18s (non-CSU)'!$J$9:$J$555,A87,'1. Rpt 18s (non-CSU)'!#REF!) -> #REF! | F87: =+C87 +D87-E87 -> #REF!
A88: 815 | B88: Health & Human Services | C88: =SUMIF('1. Rpt 18s (non-CSU)'!$J$9:$J$555,A88,'1. Rpt 18s (non-CSU)'!#REF!) -> #REF! | D88: =SUMIF('1. Rpt 18s (non-CSU)'!$J$9:$J$555,A88,'1. Rpt 18s (non-CSU)'!#REF!) -> #REF! | E88: =SUMIF('1. Rpt 18s (non-CSU)'!$J$9:$J$555,A88,'1. Rpt 18s (non-CSU)'!#REF!) -> #REF! | F88: =+C88 +D88-E88 -> #REF!
A89: 820 | B89: Natural Resources & Environmental Protection | C89: =SUMIF('1. Rpt 18s (non-CSU)'!$J$9:$J$555,A89,'1. Rpt 18s (non-CSU)'!#REF!) -> #REF! | D89: =SUMIF('1. Rpt 18s (non-CSU)'!$J$9:$J$555,A89,'1. Rpt 18s (non-CSU)'!#REF!) -> #REF! | E89: =SUMIF('1. Rpt 18s (non-CSU)'!$J$9:$J$555,A89,'1. Rpt 18s (non-CSU)'!#REF!) -> #REF! | F89: =+C89 +D89-E89 -> #REF!
A90: 825 | B90: Business, Consumer Services, & Housing | C90: =SUMIF('1. Rpt 18s (non-CSU)'!$J$9:$J$555,A90,'1. Rpt 18s (non-CSU)'!#REF!) -> #REF! | D90: =SUMIF('1. Rpt 18s (non-CSU)'!$J$9:$J$555,A90,'1. Rpt 18s (non-CSU)'!#REF!) -> #REF! | E90: =SUMIF('1. Rpt 18s (non-CSU)'!$J$9:$J$555,A90,'1. Rpt 18s (non-CSU)'!#REF!) -> #REF! | F90: =+C90 +D90-E90 -> #REF!
A91: 830 | B91: Transportation | C91: =SUMIF('1. Rpt 18s (non-CSU)'!$J$9:$J$555,A91,'1. Rpt 18s (non-CSU)'!#REF!) -> #REF! | D91: =SUMIF('1. Rpt 18s (non-CSU)'!$J$9:$J$555,A91,'1. Rpt 18s (non-CSU)'!#REF!) -> #REF! | E91: =SUMIF('1. Rpt 18s (non-CSU)'!$J$9:$J$555,A91,'1. Rpt 18s (non-CSU)'!#REF!) -> #REF! | F91: =+C91 +D91-E91 -> #REF!
A92: 835 | B92: Corrections and Rehabilitation | C92: =SUMIF('1. Rpt 18s (non-CSU)'!$J$9:$J$555,A92,'1. Rpt 18s (non-CSU)'!#REF!) -> #REF! | D92: =SUMIF('1. Rpt 18s (non-CSU)'!$J$9:$J$555,A92,'1. Rpt 18s (non-CSU)'!#REF!) -> #REF! | E92: =SUMIF('1. Rpt 18s (non-CSU)'!$J$9:$J$555,A92,'1. Rpt 18s (non-CSU)'!#REF!) -> #REF! | F92: =+C92 +D92-E92 -> #REF!
B93: Total | C93: =SUM(C86:C92) -> #REF! | D93: =SUM(D86:D92) -> #REF! | E93: =SUM(E86:E92) -> #REF! | F93: =SUM(F86:F92) -> #REF! | H93: =ROUND(C93,0)/1000 -> #REF! | I93: =ROUND(D93,0)/1000 -> #REF! | J93: =ROUND(E93,0)/1000 -> #REF! | K93: =ROUND(F93,0)/1000 -> #REF!
C94: =IF(C93='1. Rpt 18s (non-CSU)'!#REF!,"OK","Formula Error") -> #REF! | D94: =IF(D93='1. Rpt 18s (non-CSU)'!#REF!,"OK","Formula Error") -> #REF! | E94: =IF(E93='1. Rpt 18s (non-CSU)'!#REF!,"OK","Formula Error") -> #REF! | F94: =IF(F93='1. Rpt 18s (non-CSU)'!#REF!,"OK","Formula Error") -> #REF!
A96: Infrastructure (Depreciable)-0451
A98: Expense Code | B98: Function | C98: Beginning Balance | D98: Additions | E98: Deductions | F98: Ending Balance
A99: 808 | B99: General Government | C99: =SUMIF('1. Rpt 18s (non-CSU)'!$J$9:$J$555,808,'1. Rpt 18s (non-CSU)'!#REF!) -> #REF! | D99: =SUMIF('1. Rpt 18s (non-CSU)'!$J$9:$J$555,808,'1. Rpt 18s (non-CSU)'!#REF!) -> #REF! | E99: =SUMIF('1. Rpt 18s (non-CSU)'!$J$9:$J$555,808,'1. Rpt 18s (non-CSU)'!#REF!) -> #REF! | F99: =+C99 +D99-E99 -> #REF!
A100: 810 | B100: Education | C100: =SUMIF('1. Rpt 18s (non-CSU)'!$J$9:$J$555,810,'1. Rpt 18s (non-CSU)'!#REF!) -> #REF! | D100: =SUMIF('1. Rpt 18s (non-CSU)'!$J$9:$J$555,810,'1. Rpt 18s (non-CSU)'!#REF!) -> #REF! | E100: =SUMIF('1. Rpt 18s (non-CSU)'!$J$9:$J$555,810,'1. Rpt 18s (non-CSU)'!#REF!) -> #REF! | F100: =+C100 +D100-E100 -> #REF!
A101: 815 | B101: Health & Human Services | C101: =SUMIF('1. Rpt 18s (non-CSU)'!$J$9:$J$555,815,'1. Rpt 18s (non-CSU)'!#REF!) -> #REF! | D101: =SUMIF('1. Rpt 18s (non-CSU)'!$J$9:$J$555,815,'1. Rpt 18s (non-CSU)'!#REF!) -> #REF! | E101: =SUMIF('1. Rpt 18s (non-CSU)'!$J$9:$J$555,815,'1. Rpt 18s (non-CSU)'!#REF!) -> #REF! | F101: =+C101 +D101-E101 -> #REF!
A102: 820 | B102: Natural Resources & Environmental Protection | C102: =SUMIF('1. Rpt 18s (non-CSU)'!$J$9:$J$555,820,'1. Rpt 18s (non-CSU)'!#REF!) -> #REF! | D102: =SUMIF('1. Rpt 18s (non-CSU)'!$J$9:$J$555,820,'1. Rpt 18s (non-CSU)'!#REF!) -> #REF! | E102: =SUMIF('1. Rpt 18s (non-CSU)'!$J$9:$J$555,820,'1. Rpt 18s (non-CSU)'!#REF!) -> #REF! | F102: =+C102 +D102-E102 -> #REF!
A103: 825 | B103: Business, Consumer Services, & Housing | C103: =SUMIF('1. Rpt 18s (non-CSU)'!$J$9:$J$555,825,'1. Rpt 18s (non-CSU)'!#REF!) -> #REF! | D103: =SUMIF('1. Rpt 18s (non-CSU)'!$J$9:$J$555,825,'1. Rpt 18s (non-CSU)'!#REF!) -> #REF! | E103: =SUMIF('1. Rpt 18s (non-CSU)'!$J$9:$J$555,825,'1. Rpt 18s (non-CSU)'!#REF!) -> #REF! | F103: =+C103 +D103-E103 -> #REF!
A104: 830 | B104: Transportation | C104: =SUMIF('1. Rpt 18s (non-CSU)'!$J$9:$J$555,830,'1. Rpt 18s (non-CSU)'!#REF!) -> #REF! | D104: =SUMIF('1. Rpt 18s (non-CSU)'!$J$9:$J$555,830,'1. Rpt 18s (non-CSU)'!#REF!) -> #REF! | E104: =SUMIF('1. Rpt 18s (non-CSU)'!$J$9:$J$555,830,'1. Rpt 18s (non-CSU)'!#REF!) -> #REF! | F104: =+C104 +D104-E104 -> #REF!
A105: 835 | B105: Corrections and Rehabilitation | C105: =SUMIF('1. Rpt 18s (non-CSU)'!$J$9:$J$555,835,'1. Rpt 18s (non-CSU)'!#REF!) -> #REF! | D105: =SUMIF('1. Rpt 18s (non-CSU)'!$J$9:$J$555,835,'1. Rpt 18s (non-CSU)'!#REF!) -> #REF! | E105: =SUMIF('1. Rpt 18s (non-CSU)'!$J$9:$J$555,835,'1. Rpt 18s (non-CSU)'!#REF!) -> #REF! | F105: =+C105 +D105-E105 -> #REF!
B106: Total | C106: =SUM(C99:C105) -> #REF! | D106: =SUM(D99:D105) -> #REF! | E106: =SUM(E99:E105) -> #REF! | F106: =SUM(F99:F105) -> #REF! | H106: =ROUND(C106,0)/1000 -> #REF! | I106: =ROUND(D106,0)/1000 -> #REF! | J106: =ROUND(E106,0)/1000 -> #REF! | K106: =ROUND(F106,0)/1000 -> #REF!
C107: =IF(C106='1. Rpt 18s (non-CSU)'!#REF!,"OK","Formula Error") -> #REF! | D107: =IF(D106='1. Rpt 18s (non-CSU)'!#REF!,"OK","Formula Error") -> #REF! | E107: =IF(E106='1. Rpt 18s (non-CSU)'!#REF!,"OK","Formula Error") -> #REF! | F107: =IF(F106='1. Rpt 18s (non-CSU)'!#REF!,"OK","Formula Error") -> #REF!
A109: Libraries, Collections, Works of Art & Historical Treasures (Non-depreciable)-0444
A111: Expense Code | B111: Function | C111: Beginning Balance | D111: Additions | E111: Deductions | F111: Ending Balance
A112: 808 | B112: General Government | C112: =SUMIF('1. Rpt 18s (non-CSU)'!$J$9:$J$555,808,'1. Rpt 18s (non-CSU)'!#REF!) -> #REF! | D112: =SUMIF('1. Rpt 18s (non-CSU)'!$J$9:$J$555,808,'1. Rpt 18s (non-CSU)'!#REF!) -> #REF! | E112: =SUMIF('1. Rpt 18s (non-CSU)'!$J$9:$J$555,808,'1. Rpt 18s (non-CSU)'!#REF!) -> #REF! | F112: =+C112 +D112-E112 -> #REF!
A113: 810 | B113: Education | C113: =SUMIF('1. Rpt 18s (non-CSU)'!$J$9:$J$555,810,'1. Rpt 18s (non-CSU)'!#REF!) -> #REF! | D113: =SUMIF('1. Rpt 18s (non-CSU)'!$J$9:$J$555,810,'1. Rpt 18s (non-CSU)'!#REF!) -> #REF! | E113: =SUMIF('1. Rpt 18s (non-CSU)'!$J$9:$J$555,810,'1. Rpt 18s (non-CSU)'!#REF!) -> #REF! | F113: =+C113 +D113-E113 -> #REF!
A114: 815 | B114: Health & Human Services | C114: =SUMIF('1. Rpt 18s (non-CSU)'!$J$9:$J$555,815,'1. Rpt 18s (non-CSU)'!#REF!) -> #REF! | D114: =SUMIF('1. Rpt 18s (non-CSU)'!$J$9:$J$555,815,'1. Rpt 18s (non-CSU)'!#REF!) -> #REF! | E114: =SUMIF('1. Rpt 18s (non-CSU)'!$J$9:$J$555,815,'1. Rpt 18s (non-CSU)'!#REF!) -> #REF! | F114: =+C114 +D114-E114 -> #REF!
A115: 820 | B115: Natural Resources & Environmental Protection | C115: =SUMIF('1. Rpt 18s (non-CSU)'!$J$9:$J$555,820,'1. Rpt 18s (non-CSU)'!#REF!) -> #REF! | D115: =SUMIF('1. Rpt 18s (non-CSU)'!$J$9:$J$555,820,'1. Rpt 18s (non-CSU)'!#REF!) -> #REF! | E115: =SUMIF('1. Rpt 18s (non-CSU)'!$J$9:$J$555,820,'1. Rpt 18s (non-CSU)'!#REF!) -> #REF! | F115: =+C115 +D115-E115 -> #REF!
...

Sheet 3. Restatement Reconciliation
A1: Beginning Balance Restatement Reconciliation | F1: Source: | G1: Tab 1 and 4
A2: =_xlfn.CONCAT("Ending Balances less Beginning Balances ",'1. Rpt 18s (non-CSU)'!A3) -> Ending Balances less Beginning Balances as of June 30, 2024 | F2: Purpose: | G2: To show by BU and fund capital asset categories that have a beginning balance restatement
A3: ='4. PY Ending Balances'!A4 -> FY 2023-24 | F3: Procedures: | G3: N/A - Spreadsheet is formula driven. If new funds are added to Tab 1, make sure to update Agency, Fund and Key columns.
A5: Restated
D7: Ending | E7: Ending | F7: Ending | G7: Ending | H7: Ending | I7: Ending | J7: Ending
D8: Right-to-Use Leased Land | E8: Right-to-Use Leased Buildings | F8: Right-to-Use Leased Equipment | G8: Right-to-Use SBITAs | H8: APA Land | I8: APA Buildings | J8: Total
A9: Agency | B9: Fund | C9: Key | D9: Amortizable | E9: Amortizable | F9: Amortizable | G9: Amortizable | I9: Depreciable
A10: 0160 | B10: 0001 | C10: 01600001 | D10: =IFERROR(VLOOKUP($C10,'4. PY Ending Balances'!$C:$J,2,FALSE),0)-IFERROR(VLOOKUP($C10,'1. Rpt 18s (non-CSU)'!$H:$T,7,FALSE),0) -> 0 | E10: =IFERROR(VLOOKUP($C10,'4. PY Ending Balances'!$C:$J,3,FALSE),0)-IFERROR(VLOOKUP($C10,'1. Rpt 18s (non-CSU)'!$H:$T,8,FALSE),0) -> 0 | F10: =IFERROR(VLOOKUP($C10,'4. PY Ending Balances'!$C:$J,4,FALSE),0)-IFERROR(VLOOKUP($C10,'1. Rpt 18s (non-CSU)'!$H:$T,9,FALSE),0) -> 0 | G10: =IFERROR(VLOOKUP($C10,'4. PY Ending Balances'!$C:$J,5,FALSE),0)-IFERROR(VLOOKUP($C10,'1. Rpt 18s (non-CSU)'!$H:$T,10,FALSE),0) -> 0 | H10: =IFERROR(VLOOKUP($C10,'4. PY Ending Balances'!$C:$J,6,FALSE),0)-IFERROR(VLOOKUP($C10,'1. Rpt 18s (non-CSU)'!$H:$T,11,FALSE),0) -> 0 | I10: =IFERROR(VLOOKUP($C10,'4. PY Ending Balances'!$C:$J,7,FALSE),0)-IFERROR(VLOOKUP($C10,'1. Rpt 18s (non-CSU)'!$H:$T,12,FALSE),0) -> 0 | J10: =IFERROR(VLOOKUP($C10,'4. PY Ending Balances'!$C:$J,8,FALSE),0)-IFERROR(VLOOKUP($C10,'1. Rpt 18s (non-CSU)'!$H:$T,13,FALSE),0) -> 0
A11: 0250 | B11: 0001 | C11: 02500001 | D11: =IFERROR(VLOOKUP($C11,'4. PY Ending Balances'!$C:$J,2,FALSE),0)-IFERROR(VLOOKUP($C11,'1. Rpt 18s (non-CSU)'!$H:$T,7,FALSE),0) -> 0 | E11: =IFERROR(VLOOKUP($C11,'4. PY Ending Balances'!$C:$J,3,FALSE),0)-IFERROR(VLOOKUP($C11,'1. Rpt 18s (non-CSU)'!$H:$T,8,FALSE),0) -> 0 | F11: =IFERROR(VLOOKUP($C11,'4. PY Ending Balances'!$C:$J,4,FALSE),0)-IFERROR(VLOOKUP($C11,'1. Rpt 18s (non-CSU)'!$H:$T,9,FALSE),0) -> 0 | G11: =IFERROR(VLOOKUP($C11,'4. PY Ending Balances'!$C:$J,5,FALSE),0)-IFERROR(VLOOKUP($C11,'1. Rpt 18s (non-CSU)'!$H:$T,10,FALSE),0) -> 0 | H11: =IFERROR(VLOOKUP($C11,'4. PY Ending Balances'!$C:$J,6,FALSE),0)-IFERROR(VLOOKUP($C11,'1. Rpt 18s (non-CSU)'!$H:$T,11,FALSE),0) -> 0 | I11: =IFERROR(VLOOKUP($C11,'4. PY Ending Balances'!$C:$J,7,FALSE),0)-IFERROR(VLOOKUP($C11,'1. Rpt 18s (non-CSU)'!$H:$T,12,FALSE),0) -> 0 | J11: =IFERROR(VLOOKUP($C11,'4. PY Ending Balances'!$C:$J,8,FALSE),0)-IFERROR(VLOOKUP($C11,'1. Rpt 18s (non-CSU)'!$H:$T,13,FALSE),0) -> 0
A12: 0250 | B12: 0159 | C12: 02500159 | D12: =IFERROR(VLOOKUP($C12,'4. PY Ending Balances'!$C:$J,2,FALSE),0)-IFERROR(VLOOKUP($C12,'1. Rpt 18s (non-CSU)'!$H:$T,7,FALSE),0) -> 0 | E12: =IFERROR(VLOOKUP($C12,'4. PY Ending Balances'!$C:$J,3,FALSE),0)-IFERROR(VLOOKUP($C12,'1. Rpt 18s (non-CSU)'!$H:$T,8,FALSE),0) -> 0 | F12: =IFERROR(VLOOKUP($C12,'4. PY Ending Balances'!$C:$J,4,FALSE),0)-IFERROR(VLOOKUP($C12,'1. Rpt 18s (non-CSU)'!$H:$T,9,FALSE),0) -> 0 | G12: =IFERROR(VLOOKUP($C12,'4. PY Ending Balances'!$C:$J,5,FALSE),0)-IFERROR(VLOOKUP($C12,'1. Rpt 18s (non-CSU)'!$H:$T,10,FALSE),0) -> 0 | H12: =IFERROR(VLOOKUP($C12,'4. PY Ending Balances'!$C:$J,6,FALSE),0)-IFERROR(VLOOKUP($C12,'1. Rpt 18s (non-CSU)'!$H:$T,11,FALSE),0) -> 0 | I12: =IFERROR(VLOOKUP($C12,'4. PY Ending Balances'!$C:$J,7,FALSE),0)-IFERROR(VLOOKUP($C12,'1. Rpt 18s (non-CSU)'!$H:$T,12,FALSE),0) -> 0 | J12: =IFERROR(VLOOKUP($C12,'4. PY Ending Balances'!$C:$J,8,FALSE),0)-IFERROR(VLOOKUP($C12,'1. Rpt 18s (non-CSU)'!$H:$T,13,FALSE),0) -> 0
A13: 0250 | B13: 0587 | C13: 02500587 | D13: =IFERROR(VLOOKUP($C13,'4. PY Ending Balances'!$C:$J,2,FALSE),0)-IFERROR(VLOOKUP($C13,'1. Rpt 18s (non-CSU)'!$H:$T,7,FALSE),0) -> 0 | E13: =IFERROR(VLOOKUP($C13,'4. PY Ending Balances'!$C:$J,3,FALSE),0)-IFERROR(VLOOKUP($C13,'1. Rpt 18s (non-CSU)'!$H:$T,8,FALSE),0) -> 0 | F13: =IFERROR(VLOOKUP($C13,'4. PY Ending Balances'!$C:$J,4,FALSE),0)-IFERROR(VLOOKUP($C13,'1. Rpt 18s (non-CSU)'!$H:$T,9,FALSE),0) -> 0 | G13: =IFERROR(VLOOKUP($C13,'4. PY Ending Balances'!$C:$J,5,FALSE),0)-IFERROR(VLOOKUP($C13,'1. Rpt 18s (non-CSU)'!$H:$T,10,FALSE),0) -> 0 | H13: =IFERROR(VLOOKUP($C13,'4. PY Ending Balances'!$C:$J,6,FALSE),0)-IFERROR(VLOOKUP($C13,'1. Rpt 18s (non-CSU)'!$H:$T,11,FALSE),0) -> 0 | I13: =IFERROR(VLOOKUP($C13,'4. PY Ending Balances'!$C:$J,7,FALSE),0)-IFERROR(VLOOKUP($C13,'1. Rpt 18s (non-CSU)'!$H:$T,12,FALSE),0) -> 0 | J13: =IFERROR(VLOOKUP($C13,'4. PY Ending Balances'!$C:$J,8,FALSE),0)-IFERROR(VLOOKUP($C13,'1. Rpt 18s (non-CSU)'!$H:$T,13,FALSE),0) -> 0
A14: 0250 | B14: 0890 | C14: 02500890 | D14: =IFERROR(VLOOKUP($C14,'4. PY Ending Balances'!$C:$J,2,FALSE),0)-IFERROR(VLOOKUP($C14,'1. Rpt 18s (non-CSU)'!$H:$T,7,FALSE),0) -> 0 | E14: =IFERROR(VLOOKUP($C14,'4. PY Ending Balances'!$C:$J,3,FALSE),0)-IFERROR(VLOOKUP($C14,'1. Rpt 18s (non-CSU)'!$H:$T,8,FALSE),0) -> 0 | F14: =IFERROR(VLOOKUP($C14,'4. PY Ending Balances'!$C:$J,4,FALSE),0)-IFERROR(VLOOKUP($C14,'1. Rpt 18s (non-CSU)'!$H:$T,9,FALSE),0) -> 0 | G14: =IFERROR(VLOOKUP($C14,'4. PY Ending Balances'!$C:$J,5,FALSE),0)-IFERROR(VLOOKUP($C14,'1. Rpt 18s (non-CSU)'!$H:$T,10,FALSE),0) -> 0 | H14: =IFERROR(VLOOKUP($C14,'4. PY Ending Balances'!$C:$J,6,FALSE),0)-IFERROR(VLOOKUP($C14,'1. Rpt 18s (non-CSU)'!$H:$T,11,FALSE),0) -> 0 | I14: =IFERROR(VLOOKUP($C14,'4. PY Ending Balances'!$C:$J,7,FALSE),0)-IFERROR(VLOOKUP($C14,'1. Rpt 18s (non-CSU)'!$H:$T,12,FALSE),0) -> 0 | J14: =IFERROR(VLOOKUP($C14,'4. PY Ending Balances'!$C:$J,8,FALSE),0)-IFERROR(VLOOKUP($C14,'1. Rpt 18s (non-CSU)'!$H:$T,13,FALSE),0) -> 0
A15: 0250 | B15: 0932 | C15: 02500932 | D15: =IFERROR(VLOOKUP($C15,'4. PY Ending Balances'!$C:$J,2,FALSE),0)-IFERROR(VLOOKUP($C15,'1. Rpt 18s (non-CSU)'!$H:$T,7,FALSE),0) -> 0 | E15: =IFERROR(VLOOKUP($C15,'4. PY Ending Balances'!$C:$J,3,FALSE),0)-IFERROR(VLOOKUP($C15,'1. Rpt 18s (non-CSU)'!$H:$T,8,FALSE),0) -> 0 | F15: =IFERROR(VLOOKUP($C15,'4. PY Ending Balances'!$C:$J,4,FALSE),0)-IFERROR(VLOOKUP($C15,'1. Rpt 18s (non-CSU)'!$H:$T,9,FALSE),0) -> 0 | G15: =IFERROR(VLOOKUP($C15,'4. PY Ending Balances'!$C:$J,5,FALSE),0)-IFERROR(VLOOKUP($C15,'1. Rpt 18s (non-CSU)'!$H:$T,10,FALSE),0) -> 0 | H15: =IFERROR(VLOOKUP($C15,'4. PY Ending Balances'!$C:$J,6,FALSE),0)-IFERROR(VLOOKUP($C15,'1. Rpt 18s (non-CSU)'!$H:$T,11,FALSE),0) -> 0 | I15: =IFERROR(VLOOKUP($C15,'4. PY Ending Balances'!$C:$J,7,FALSE),0)-IFERROR(VLOOKUP($C15,'1. Rpt 18s (non-CSU)'!$H:$T,12,FALSE),0) -> 0 | J15: =IFERROR(VLOOKUP($C15,'4. PY Ending Balances'!$C:$J,8,FALSE),0)-IFERROR(VLOOKUP($C15,'1. Rpt 18s (non-CSU)'!$H:$T,13,FALSE),0) -> 0
A16: 0250 | B16: 0991 | C16: 02500991 | D16: =IFERROR(VLOOKUP($C16,'4. PY Ending Balances'!$C:$J,2,FALSE),0)-IFERROR(VLOOKUP($C16,'1. Rpt 18s (non-CSU)'!$H:$T,7,FALSE),0) -> 0 | E16: =IFERROR(VLOOKUP($C16,'4. PY Ending Balances'!$C:$J,3,FALSE),0)-IFERROR(VLOOKUP($C16,'1. Rpt 18s (non-CSU)'!$H:$T,8,FALSE),0) -> 0 | F16: =IFERROR(VLOOKUP($C16,'4. PY Ending Balances'!$C:$J,4,FALSE),0)-IFERROR(VLOOKUP($C16,'1. Rpt 18s (non-CSU)'!$H:$T,9,FALSE),0) -> 0 | G16: =IFERROR(VLOOKUP($C16,'4. PY Ending Balances'!$C:$J,5,FALSE),0)-IFERROR(VLOOKUP($C16,'1. Rpt 18s (non-CSU)'!$H:$T,10,FALSE),0) -> 0 | H16: =IFERROR(VLOOKUP($C16,'4. PY Ending Balances'!$C:$J,6,FALSE),0)-IFERROR(VLOOKUP($C16,'1. Rpt 18s (non-CSU)'!$H:$T,11,FALSE),0) -> 0 | I16: =IFERROR(VLOOKUP($C16,'4. PY Ending Balances'!$C:$J,7,FALSE),0)-IFERROR(VLOOKUP($C16,'1. Rpt 18s (non-CSU)'!$H:$T,12,FALSE),0) -> 0 | J16: =IFERROR(VLOOKUP($C16,'4. PY Ending Balances'!$C:$J,8,FALSE),0)-IFERROR(VLOOKUP($C16,'1. Rpt 18s (non-CSU)'!$H:$T,13,FALSE),0) -> 0
A17: 0250 | B17: 3037 | C17: 02503037 | D17: =IFERROR(VLOOKUP($C17,'4. PY Ending Balances'!$C:$J,2,FALSE),0)-IFERROR(VLOOKUP($C17,'1. Rpt 18s (non-CSU)'!$H:$T,7,FALSE),0) -> 0 | E17: =IFERROR(VLOOKUP($C17,'4. PY Ending Balances'!$C:$J,3,FALSE),0)-IFERROR(VLOOKUP($C17,'1. Rpt 18s (non-CSU)'!$H:$T,8,FALSE),0) -> 0 | F17: =IFERROR(VLOOKUP($C17,'4. PY Ending Balances'!$C:$J,4,FALSE),0)-IFERROR(VLOOKUP($C17,'1. Rpt 18s (non-CSU)'!$H:$T,9,FALSE),0) -> 0 | G17: =IFERROR(VLOOKUP($C17,'4. PY Ending Balances'!$C:$J,5,FALSE),0)-IFERROR(VLOOKUP($C17,'1. Rpt 18s (non-CSU)'!$H:$T,10,FALSE),0) -> 0 | H17: =IFERROR(VLOOKUP($C17,'4. PY Ending Balances'!$C:$J,6,FALSE),0)-IFERROR(VLOOKUP($C17,'1. Rpt 18s (non-CSU)'!$H:$T,11,FALSE),0) -> 0 | I17: =IFERROR(VLOOKUP($C17,'4. PY Ending Balances'!$C:$J,7,FALSE),0)-IFERROR(VLOOKUP($C17,'1. Rpt 18s (non-CSU)'!$H:$T,12,FALSE),0) -> 0 | J17: =IFERROR(VLOOKUP($C17,'4. PY Ending Balances'!$C:$J,8,FALSE),0)-IFERROR(VLOOKUP($C17,'1. Rpt 18s (non-CSU)'!$H:$T,13,FALSE),0) -> 0
A18: 0250 | B18: 3060 | C18: 02503060 | D18: =IFERROR(VLOOKUP($C18,'4. PY Ending Balances'!$C:$J,2,FALSE),0)-IFERROR(VLOOKUP($C18,'1. Rpt 18s (non-CSU)'!$H:$T,7,FALSE),0) -> 0 | E18: =IFERROR(VLOOKUP($C18,'4. PY Ending Balances'!$C:$J,3,FALSE),0)-IFERROR(VLOOKUP($C18,'1. Rpt 18s (non-CSU)'!$H:$T,8,FALSE),0) -> 0 | F18: =IFERROR(VLOOKUP($C18,'4. PY Ending Balances'!$C:$J,4,FALSE),0)-IFERROR(VLOOKUP($C18,'1. Rpt 18s (non-CSU)'!$H:$T,9,FALSE),0) -> 0 | G18: =IFERROR(VLOOKUP($C18,'4. PY Ending Balances'!$C:$J,5,FALSE),0)-IFERROR(VLOOKUP($C18,'1. Rpt 18s (non-CSU)'!$H:$T,10,FALSE),0) -> 0 | H18: =IFERROR(VLOOKUP($C18,'4. PY Ending Balances'!$C:$J,6,FALSE),0)-IFERROR(VLOOKUP($C18,'1. Rpt 18s (non-CSU)'!$H:$T,11,FALSE),0) -> 0 | I18: =IFERROR(VLOOKUP($C18,'4. PY Ending Balances'!$C:$J,7,FALSE),0)-IFERROR(VLOOKUP($C18,'1. Rpt 18s (non-CSU)'!$H:$T,12,FALSE),0) -> 0 | J18: =IFERROR(VLOOKUP($C18,'4. PY Ending Balances'!$C:$J,8,FALSE),0)-IFERROR(VLOOKUP($C18,'1. Rpt 18s (non-CSU)'!$H:$T,13,FALSE),0) -> 0
A19: 0250 | B19: 3066 | C19: 02503066 | D19: =IFERROR(VLOOKUP($C19,'4. PY Ending Balances'!$C:$J,2,FALSE),0)-IFERROR(VLOOKUP($C19,'1. Rpt 18s (non-CSU)'!$H:$T,7,FALSE),0) -> 0 | E19: =IFERROR(VLOOKUP($C19,'4. PY Ending Balances'!$C:$J,3,FALSE),0)-IFERROR(VLOOKUP($C19,'1. Rpt 18s (non-CSU)'!$H:$T,8,FALSE),0) -> 0 | F19: =IFERROR(VLOOKUP($C19,'4. PY Ending Balances'!$C:$J,4,FALSE),0)-IFERROR(VLOOKUP($C19,'1. Rpt 18s (non-CSU)'!$H:$T,9,FALSE),0) -> 0 | G19: =IFERROR(VLOOKUP($C19,'4. PY Ending Balances'!$C:$J,5,FALSE),0)-IFERROR(VLOOKUP($C19,'1. Rpt 18s (non-CSU)'!$H:$T,10,FALSE),0) -> 0 | H19: =IFERROR(VLOOKUP($C19,'4. PY Ending Balances'!$C:$J,6,FALSE),0)-IFERROR(VLOOKUP($C19,'1. Rpt 18s (non-CSU)'!$H:$T,11,FALSE),0) -> 0 | I19: =IFERROR(VLOOKUP($C19,'4. PY Ending Balances'!$C:$J,7,FALSE),0)-IFERROR(VLOOKUP($C19,'1. Rpt 18s (non-CSU)'!$H:$T,12,FALSE),0) -> 0 | J19: =IFERROR(VLOOKUP($C19,'4. PY Ending Balances'!$C:$J,8,FALSE),0)-IFERROR(VLOOKUP($C19,'1. Rpt 18s (non-CSU)'!$H:$T,13,FALSE),0) -> 0
A20: 0250 | B20: 3085 | C20: 02503085 | D20: =IFERROR(VLOOKUP($C20,'4. PY Ending Balances'!$C:$J,2,FALSE),0)-IFERROR(VLOOKUP($C20,'1. Rpt 18s (non-CSU)'!$H:$T,7,FALSE),0) -> 0 | E20: =IFERROR(VLOOKUP($C20,'4. PY Ending Balances'!$C:$J,3,FALSE),0)-IFERROR(VLOOKUP($C20,'1. Rpt 18s (non-CSU)'!$H:$T,8,FALSE),0) -> 0 | F20: =IFERROR(VLOOKUP($C20,'4. PY Ending Balances'!$C:$J,4,FALSE),0)-IFERROR(VLOOKUP($C20,'1. Rpt 18s (non-CSU)'!$H:$T,9,FALSE),0) -> 0 | G20: =IFERROR(VLOOKUP($C20,'4. PY Ending Balances'!$C:$J,5,FALSE),0)-IFERROR(VLOOKUP($C20,'1. Rpt 18s (non-CSU)'!$H:$T,10,FALSE),0) -> 0 | H20: =IFERROR(VLOOKUP($C20,'4. PY Ending Balances'!$C:$J,6,FALSE),0)-IFERROR(VLOOKUP($C20,'1. Rpt 18s (non-CSU)'!$H:$T,11,FALSE),0) -> 0 | I20: =IFERROR(VLOOKUP($C20,'4. PY Ending Balances'!$C:$J,7,FALSE),0)-IFERROR(VLOOKUP($C20,'1. Rpt 18s (non-CSU)'!$H:$T,12,FALSE),0) -> 0 | J20: =IFERROR(VLOOKUP($C20,'4. PY Ending Balances'!$C:$J,8,FALSE),0)-IFERROR(VLOOKUP($C20,'1. Rpt 18s (non-CSU)'!$H:$T,13,FALSE),0) -> 0
A21: 0250 | B21: 3138 | C21: 02503138 | D21: =IFERROR(VLOOKUP($C21,'4. PY Ending Balances'!$C:$J,2,FALSE),0)-IFERROR(VLOOKUP($C21,'1. Rpt 18s (non-CSU)'!$H:$T,7,FALSE),0) -> 0 | E21: =IFERROR(VLOOKUP($C21,'4. PY Ending Balances'!$C:$J,3,FALSE),0)-IFERROR(VLOOKUP($C21,'1. Rpt 18s (non-CSU)'!$H:$T,8,FALSE),0) -> 0 | F21: =IFERROR(VLOOKUP($C21,'4. PY Ending Balances'!$C:$J,4,FALSE),0)-IFERROR(VLOOKUP($C21,'1. Rpt 18s (non-CSU)'!$H:$T,9,FALSE),0) -> 0 | G21: =IFERROR(VLOOKUP($C21,'4. PY Ending Balances'!$C:$J,5,FALSE),0)-IFERROR(VLOOKUP($C21,'1. Rpt 18s (non-CSU)'!$H:$T,10,FALSE),0) -> 0 | H21: =IFERROR(VLOOKUP($C21,'4. PY Ending Balances'!$C:$J,6,FALSE),0)-IFERROR(VLOOKUP($C21,'1. Rpt 18s (non-CSU)'!$H:$T,11,FALSE),0) -> 0 | I21: =IFERROR(VLOOKUP($C21,'4. PY Ending Balances'!$C:$J,7,FALSE),0)-IFERROR(VLOOKUP($C21,'1. Rpt 18s (non-CSU)'!$H:$T,12,FALSE),0) -> 0 | J21: =IFERROR(VLOOKUP($C21,'4. PY Ending Balances'!$C:$J,8,FALSE),0)-IFERROR(VLOOKUP($C21,'1. Rpt 18s (non-CSU)'!$H:$T,13,FALSE),0) -> 0
... A554: 8955 | B554: 3013 | C554: 89553013 | D554: =IFERROR(VLOOKUP($C554,'4. PY Ending Balances'!$C:$J,2,FALSE),0)-IFERROR(VLOOKUP($C554,'1. Rpt 18s (non-CSU)'!$H:$T,7,FALSE),0) -> 0 | E554: =IFERROR(VLOOKUP($C554,'4. PY Ending Balances'!$C:$J,3,FALSE),0)-IFERROR(VLOOKUP($C554,'1. Rpt 18s (non-CSU)'!$H:$T,8,FALSE),0) -> 0 | F554: =IFERROR(VLOOKUP($C554,'4. PY Ending Balances'!$C:$J,4,FALSE),0)-IFERROR(VLOOKUP($C554,'1. Rpt 18s (non-CSU)'!$H:$T,9,FALSE),0) -> 0 | G554: =IFERROR(VLOOKUP($C554,'4. PY Ending Balances'!$C:$J,5,FALSE),0)-IFERROR(VLOOKUP($C554,'1. Rpt 18s (non-CSU)'!$H:$T,10,FALSE),0) -> 0 | H554: =IFERROR(VLOOKUP($C554,'4. PY Ending Balances'!$C:$J,6,FALSE),0)-IFERROR(VLOOKUP($C554,'1. Rpt 18s (non-CSU)'!$H:$T,11,FALSE),0) -> 0 | I554: =IFERROR(VLOOKUP($C554,'4. PY Ending Balances'!$C:$J,7,FALSE),0)-IFERROR(VLOOKUP($C554,'1. Rpt 18s (non-CSU)'!$H:$T,12,FALSE),0) -> 0 | J554: =IFERROR(VLOOKUP($C554,'4. PY Ending Balances'!$C:$J,8,FALSE),0)-IFERROR(VLOOKUP($C554,'1. Rpt 18s (non-CSU)'!$H:$T,13,FALSE),0) -> 0
C555: TOTAL | D555: =SUM(D10:D554) -> -1953492.6 | E555: =SUM(E10:E554) -> -1.5939145e+08 | F555: =SUM(F10:F554) -> 0 | G555: =SUM(G10:G554) -> -6521419.2 | H555: =SUM(H10:H554) -> 0 | I555: =SUM(I10:I554) -> 0 | J555: =SUM(J10:J554) -> -1.6786636e+08

Sheet 4. PY Ending Balances
A1: Source | B1: Prior year's Non-CSU Governmental Excel file
A2: Purpose: | B2: Prior Year Beginning Balances to Identify Restatements
A3: Procedures: | B3: Copy and paste columns from prior year's Non-CSU Governmental Excel file
A4: FY 2023-24
D5: Ending | E5: Ending | F5: Ending | G5: Ending | H5: Ending | I5: Ending | J5: Ending
D6: Right-to-Use Leased Land | E6: Right-to-Use Leased Buildings | F6: Right-to-Use Leased Equipment | G6: Right-to-Use SBITAs | H6: APA Land | I6: APA Buildings | J6: Total
D7: Amortizable | E7: Amortizable | F7: Amortizable | G7: Amortizable | I7: Depreciable
A8: Agency | B8: Fund | C8: Agy&Fd
A9: 0160 | B9: 0001 | C9: =A9&B9 -> 01600001 | D9: 0 | E9: 0 | F9: 0 | G9: 0 | H9: 0 | I9: 0 | J9: =SUM(D9:I9) -> 0
A10: 0250 | B10: 0001 | C10: =A10&B10 -> 02500001 | D10: 0 | E10: 0 | F10: 0 | G10: 0 | H10: 0 | I10: 0 | J10: =SUM(D10:I10) -> 0
A11: 0250 | B11: 0159 | C11: =A11&B11 -> 02500159 | D11: 0 | E11: 0 | F11: 0 | G11: 0 | H11: 0 | I11: 0 | J11: =SUM(D11:I11) -> 0
A12: 0250 | B12: 0587 | C12: =A12&B12 -> 02500587 | D12: 0 | E12: 0 | F12: 0 | G12: 0 | H12: 0 | I12: 0 | J12: =SUM(D12:I12) -> 0
A13: 0250 | B13: 0890 | C13: =A13&B13 -> 02500890 | D13: 0 | E13: 0 | F13: 0 | G13: 0 | H13: 0 | I13: 0 | J13: =SUM(D13:I13) -> 0
A14: 0250 | B14: 0932 | C14: =A14&B14 -> 02500932 | D14: 0 | E14: 0 | F14: 0 | G14: 0 | H14: 0 | I14: 0 | J14: =SUM(D14:I14) -> 0
A15: 0250 | B15: 0991 | C15: =A15&B15 -> 02500991 | D15: 0 | E15: 0 | F15: 0 | G15: 0 | H15: 0 | I15: 0 | J15: =SUM(D15:I15) -> 0
A16: 0250 | B16: 3037 | C16: =A16&B16 -> 02503037 | D16: 0 | E16: 0 | F16: 0 | G16: 0 | H16: 0 | I16: 0 | J16: =SUM(D16:I16) -> 0
A17: 0250 | B17: 3060 | C17: =A17&B17 -> 02503060 | D17: 0 | E17: 0 | F17: 0 | G17: 0 | H17: 0 | I17: 0 | J17: =SUM(D17:I17) -> 0
A18: 0250 | B18: 3066 | C18: =A18&B18 -> 02503066 | D18: 0 | E18: 0 | F18: 0 | G18: 0 | H18: 0 | I18: 0 | J18: =SUM(D18:I18) -> 0
A19: 0250 | B19: 3085 | C19: =A19&B19 -> 02503085 | D19: 0 | E19: 0 | F19: 0 | G19: 0 | H19: 0 | I19: 0 | J19: =SUM(D19:I19) -> 0
A20: 0250 | B20: 3138 | C20: =A20&B20 -> 02503138 | D20: 0 | E20: 0 | F20: 0 | G20: 0 | H20: 0 | I20: 0 | J20: =SUM(D20:I20) -> 0
... A553: 8967 | B553: Leases | C553: =A553&B553 -> 8967Leases | D553: 0 | E553: 0 | F553: 0 | G553: 0 | H553: 0 | I553: 0 | J553: =SUM(D553:I553) -> 0
D554: =SUM(D9:D553) -> 0 | E554: =SUM(E9:E553) -> 0 | F554: =SUM(F9:F553) -> 0 | G554: =SUM(G9:G553) -> 0 | H554: =SUM(H9:H553) -> 0 | I554: =SUM(I9:I553) -> 0 | J554: =SUM(J9:J553) -> 0

Sheet GAAP 02F
A1: Source: | B1: GAAP System 02F Index Fund
A2: Purpose: | B2: To populate data in the Rpt18s (non-CSU) column K
A3: Procedures: | B3: Refresh table below
A4: Fund | B4: Column1 | C4: FundName | D4: RptCat | E4: GovWide | F4: FundHier1 | G4: MajorMinor | H4: FundHier2 | I4: AgencyFundHier1 | J4: AgencyFundHier2 | K4: Desc1 | L4: Desc2 | M4: Rev | N4: Exp | O4: Agency | P4: Delete | Q4: ProgGenRev | R4: NetAssetsRestricted | S4: EffDate | T4: FundBal | U4: EnablingLeg | V4: GW
A5: 0017000 | B5: =LEFT(GAAP02F[[#This Row],[Fund]],4) -> 0017 | C5: FINGERPRINT FEES ACCOUNT | D5: G | E5: 001 | F5: 200 | G5: 002 | H5: 950 | I5: 000 | J5: 000 | K5: SPECIAL REVENUE FUND | L5: BACKGROUND SCREENING | R5: 2 | S5: 06/26/2012 | T5: 9921 | U5: 9
A6: 0018000 | B6: =LEFT(GAAP02F[[#This Row],[Fund]],4) -> 0018 | C6: SITE REMEDIATION ACCOUNT | D6: G | E6: 001 | F6: 200 | G6: 001 | H6: 300 | I6: 000 | J6: 000 | K6: SPECIAL REVENUE FUND | L6: NAT RESOURES & ENVIRON PROTECT | M6: CH8 | N6: 52/ | O6: 92 | R6: 2 | S6: 10/28/2016 | T6: 9924 | U6: 9
A7: 0020000 | B7: =LEFT(GAAP02F[[#This Row],[Fund]],4) -> 0020 | C7: LAW LIBRARY SPEC ACCT CA STATE | D7: G | E7: 001 | F7: 200 | G7: 002 | H7: 950 | I7: 000 | J7: 000 | K7: SPECIAL REVENUE FUND | L7: MEMORIAL-STATE PROPERTY | M7: CH | N7: 114 | O7: 9/92 | R7: 3 | S7: 06/26/2012 | T7: 9943 | U7: 0
A8: 0021000 | B8: =LEFT(GAAP02F[[#This Row],[Fund]],4) -> 0021 | C8: STATE ENTERPRISE LOAN FUND | D8: N | E8: 001 | F8: 200 | G8: 002 | H8: 950 | I8: 000 | J8: 000 | K8: SPECIAL REVENUE FUND | L8: OTHER SPECIAL REVENUE PROGRAMS | M8: 775 | N8: 808 | O8: 0000 | P8: 0 | Q8: P | R8: 3 | S8: 12/19/2011 | T8: 9942 | U8: 0
A9: 0022000 | B9: =LEFT(GAAP02F[[#This Row],[Fund]],4) -> 0022 | C9: STATE EMERGENCY TEL NO ACCOUNT | D9: G | E9: 001 | F9: 200 | G9: 002 | H9: 950 | I9: 000 | J9: 000 | K9: SPECIAL REVENUE FUND | L9: TELECOMMUNICATIONS | R9: 2 | S9: 06/26/2012 | T9: 9921 | U9: 9
A10: 0023000 | B10: =LEFT(GAAP02F[[#This Row],[Fund]],4) -> 0023 | C10: FARMWORKER REMEDIAL ACCOUNT | D10: G | E10: 001 | F10: 200 | G10: 002 | H10: 950 | I10: 000 | J10: 000 | K10: SPECIAL REVENUE FUND | L10: RESTITUTION-CLAIMS | R10: 3 | S10: 06/26/2012 | T10: 9944 | U10: 0
A11: 0024000 | B11: =LEFT(GAAP02F[[#This Row],[Fund]],4) -> 0024 | C11: GUIDE DOGS FOR THE BLIND FUND | D11: G | E11: 001 | F11: 200 | G11: 002 | H11: 250 | I11: 000 | J11: 000 | K11: SPECIAL REVENUE FUND | L11: BUS & PROF REG & LIC FUND | M11: CH | N11: 149 | O11: /94 | R11: 2 | S11: 06/25/2012 | T11: 9925 | U11: 9
A12: 0025000 | B12: =LEFT(GAAP02F[[#This Row],[Fund]],4) -> 0025 | C12: LEAK UNDERGRND STORAG TANK CRF | D12: G | E12: 001 | F12: 200 | G12: 001 | H12: 300 | I12: 000 | J12: 000 | K12: SPECIAL REVENUE FUND | L12: NAT RESOURES & ENVIRON PROTECT | M12: 257 | N12: 32 | O12: PR | R12: 2 | S12: 10/28/2016 | T12: 9924 | U12: 9
A13: 0026000 | B13: =LEFT(GAAP02F[[#This Row],[Fund]],4) -> 0026 | C13: MOTOR VEHICLE INSURANCE ACCT | D13: G | E13: 001 | F13: 500 | G13: 002 | H13: 900 | I13: 000 | J13: 000 | K13: INTERNAL SERVICE FUND | L13: ALL OTHER INTERNAL SERVICE FD | M13: 755 | N13: 870 | O13: 5830 | P13: 0 | Q13: P | R13: 1 | S13: 10/28/2002 | T13: 0000 | U13: 0
A14: 0027000 | B14: =LEFT(GAAP02F[[#This Row],[Fund]],4) -> 0027 | C14: TAX RELIEF & REFUND ACCOUNT | D14: G | E14: 001 | F14: 850 | G14: 001 | H14: 000 | I14: 100 | J14: 100 | K14: INTERNAL AGENCY FUND | L14: GENERAL FUND | M14: 000 | N14: 000 | O14: 5620 | R14: 2 | S14: 02/06/2012 | T14: 9925 | U14: 0
A15: 0028000 | B15: =LEFT(GAAP02F[[#This Row],[Fund]],4) -> 0028 | C15: UNIFIED PROGRAM ACCOUNT | D15: G | E15: 001 | F15: 200 | G15: 001 | H15: 300 | I15: 000 | J15: 000 | K15: SPECIAL REVENUE FUND | L15: NAT RESOURES & ENVIRON PROTECT | M15: CH | N15: 418 | O15: /93 | R15: 2 | S15: 10/28/2016 | T15: 9921 | U15: 9
A16: 0029000 | B16: =LEFT(GAAP02F[[#This Row],[Fund]],4) -> 0029 | C16: NUCLEAR PLANNING ASSMT ACCOUNT | D16: G | E16: 001 | F16: 200 | G16: 001 | H16: 300 | I16: 000 | J16: 000 | K16: SPECIAL REVENUE FUND | L16: NAT RESOURES & ENVIRON PROTECT | M16: 000 | R16: 2 | S16: 10/28/2016 | T16: 9921 | U16: 9
A17: 0000000 | B17: =LEFT(GAAP02F[[#This Row],[Fund]],4) -> 0000 | C17: TREASURY ACCOUNTABILITY | S17: 07/01/1981 | T17: 0000 | U17: 0
A18: 0001000 | B18: =LEFT(GAAP02F[[#This Row],[Fund]],4) -> 0001 | C18: GENERAL FUND | D18: G | E18: 001 | F18: 100 | G18: 001 | H18: 100 | I18: 000 | J18: 000 | K18: GENERAL FUND | R18: 5 | S18: 09/09/2011 | T18: 0000 | U18: 0
A19: 0002000 | B19: =LEFT(GAAP02F[[#This Row],[Fund]],4) -> 0002 | C19: PROPERTY ACQUISITION LAW MONEY | D19: G | E19: 001 | F19: 200 | G19: 002 | H19: 950 | I19: 000 | J19: 000 | K19: SPECIAL REVENUE FUND | L19: MEMORIAL-STATE PROPERTY | R19: 3 | S19: 06/26/2012 | T19: 9946 | U19: 0
A20: 0003000 | B20: =LEFT(GAAP02F[[#This Row],[Fund]],4) -> 0003 | C20: MOTOR VEHICLE PARKING FAC A/C | D20: G | E20: 001 | F20: 200 | G20: 002 | H20: 950 | I20: 000 | J20: 000 | K20: SPECIAL REVENUE FUND | L20: MEMORIAL-STATE PROPERTY | R20: 2 | S20: 06/26/2012 | T20: 9925 | U20: 9
A21: 0004000 | B21: =LEFT(GAAP02F[[#This Row],[Fund]],4) -> 0004 | C21: BREAST CANCER FUND | D21: G | E21: 001 | F21: 200 | G21: 002 | H21: 550 | I21: 000 | J21: 000 | K21: SPECIAL REVENUE FUND | L21: CIGRTE TBCO & CNNBS TAX FUND | R21: 2 | S21: 09/13/2019 | T21: 9923 | U21: 9
A22: 0005000 | B22: =LEFT(GAAP02F[[#This Row],[Fund]],4) -> 0005 | C22: SAFE NEIGHBRHD PARK, CLEAN WAT | D22: B | E22: 001 | F22: 200 | G22: 001 | H22: 300 | I22: 000 | J22: 000 | K22: SPECIAL REVENUE FUND | L22: NAT RESOURCES & ENVIRON PROTEC | M22: 000 | R22: 2 | S22: 99/99/9999 | T22: 9924 | U22: 0
A23: 0006000 | B23: =LEFT(GAAP02F[[#This Row],[Fund]],4) -> 0006 | C23: DISABILITY ACCESS ACCOUNT | D23: G | E23: 001 | F23: 200 | G23: 002 | H23: 950 | I23: 000 | J23: 000 | K23: SPECIAL REVENUE FUND | L23: BUILDING REGULATIONS | R23: 3 | S23: 06/26/2012 | T23: 9946 | U23: 0
A24: 0007000 | B24: =LEFT(GAAP02F[[#This Row],[Fund]],4) -> 0007 | C24: BREAST CANCER RESEARCH ACCOUNT | D24: G | E24: 001 | F24: 200 | G24: 002 | H24: 550 | I24: 000 | J24: 000 | K24: SPECIAL REVENUE FUND | L24: CIGRTE TBCO & CNNBS TAX FUND | M24: CH | N24: 483 | O24: /94 | R24: 2 | S24: 09/13/2019 | T24: 9923 | U24: 9
A25: 0009000 | B25: =LEFT(GAAP02F[[#This Row],[Fund]],4) -> 0009 | C25: BREAST CANCER CONTROL ACCOUNT | D25: G | E25: 001 | F25: 200 | G25: 002 | H25: 550 | I25: 000 | J25: 000 | K25: SPECIAL REVENUE FUND | L25: CIGRTE TBCO & CNNBS TAX FUND | M25: CH | N25: 483 | O25: /94 | R25: 2 | S25: 09/13/2019 | T25: 9923 | U25: 9
A26: 0010000 | B26: =LEFT(GAAP02F[[#This Row],[Fund]],4) -> 0010 | C26: HAZARD MTRLS ENFORCE&TRNG ACCT | D26: G | E26: 001 | F26: 200 | G26: 001 | H26: 300 | I26: 000 | J26: 000 | K26: SPECIAL REVENUE FUND | L26: NAT RESOURES & ENVIRON PROTECT | R26: 1 | S26: 10/28/2016 | T26: 0000 | U26: 0
A27: 0012000 | B27: =LEFT(GAAP02F[[#This Row],[Fund]],4) -> 0012 | C27: ATTY GEN ANTITRUST ACCOUNT | D27: G | E27: 001 | F27: 200 | G27: 002 | H27: 950 | I27: 000 | J27: 000 | K27: SPECIAL REVENUE FUND | L27: OTHER - ANTITRUST | R27: 2 | S27: 01/08/2013 | T27: 9921 | U27: 9
A28: 0014000 | B28: =LEFT(GAAP02F[[#This Row],[Fund]],4) -> 0014 | C28: HAZARDOUS WASTE CONTROL ACCT | D28: G | E28: 001 | F28: 200 | G28: 001 | H28: 300 | I28: 000 | J28: 000 | K28: SPECIAL REVENUE FUND | L28: NAT RESOURES & ENVIRON PROTECT | M28: HAZ | N28: ARD | O28: OUS | P28: W | Q28: A | R28: 3 | S28: 10/28/2016 | T28: 9945 | U28: 0 | V28: S
A29: 0015000 | B29: =LEFT(GAAP02F[[#This Row],[Fund]],4) -> 0015 | C29: FIREARMS SAFETY TRNG FUND | D29: G | E29: 001 | F29: 200 | G29: 002 | H29: 950 | I29: 000 | J29: 000 | K29: SPECIAL REVENUE FUND | L29: OTHER SPECIAL REVENUE PROGRAMS | R29: 1 | S29: 08/31/2007 | T29: 0000 | U29: 0
A30: 0016000 | B30: =LEFT(GAAP02F[[#This Row],[Fund]],4) -> 0016 | C30: SUBSEQUENT INJURIES BNFT TRUST | D30: N | E30: 001 | F30: 200 | G30: 002 | H30: 950 | I30: 000 | J30: 000 | K30: SPECIAL REVENUE FUND | L30: WORKERS COMPENSATION-OCCUPATIO | M30: 775 | N30: 000 | O30: 0000 | P30: 0 | Q30: P | R30: 2 | S30: 06/26/2012 | T30: 9923 | U30: 9
A31: 0030000 | B31: =LEFT(GAAP02F[[#This Row],[Fund]],4) -> 0030 | C31: COUNTY SCHOOL SVC FD CONT ACCT | D31: G | E31: 001 | F31: 850 | G31: 001 | H31: 000 | I31: 100 | J31: 100 | K31: INTERNAL AGENCY FUND | L31: GENERAL FUND | M31: 000 | N31: 000 | O31: 5644 | R31: 3 | S31: 02/06/2012 | T31: 9943 | U31: 0
A32: 0032000 | B32: =LEFT(GAAP02F[[#This Row],[Fund]],4) -> 0032 | C32: FIREARM SAFETY ACCOUNT | D32: G | E32: 001 | F32: 200 | G32: 002 | H32: 250 | I32: 000 | J32: 000 | K32: SPECIAL REVENUE FUND | L32: BUS & PROF REG & LIC FUND | M32: CH2 | N32: 45/ | O32: 99 | R32: 2 | S32: 01/08/2013 | T32: 9921 | U32: 9
A33: 0033000 | B33: =LEFT(GAAP02F[[#This Row],[Fund]],4) -> 0033 | C33: STATE ENERGY CONSERV ASST ACCT | D33: G | E33: 001 | F33: 200 | G33: 001 | H33: 300 | I33: 000 | J33: 000 | K33: SPECIAL REVENUE FUND | L33: NAT RESOURCES & ENVIRON PROTEC | M33: 000 | N33: 000 | O33: 0000 | P33: 0 | R33: 2 | S33: 99/99/9999 | T33: 9924 | U33: 0
A34: 0034000 | B34: =LEFT(GAAP02F[[#This Row],[Fund]],4) -> 0034 | C34: Geothermal Resources Dev Acct | D34: G | E34: 001 | F34: 200 | G34: 001 | H34: 300 | I34: 000 | J34: 000 | K34: Special Revenue Fund | L34: Env. & Natural Resources Fund | M34: 732 | N34: 820 | O34: 0000 | P34: 0 | Q34: P | R34: 2 | S34: 08/30/2022 | T34: 9924 | U34: 0
A35: 0035000 | B35: =LEFT(GAAP02F[[#This Row],[Fund]],4) -> 0035 | C35: SURFACE MINING & RECLAMATION | D35: G | E35: 001 | F35: 850 | G35: 001 | H35: 000 | I35: 100 | J35: 100 | K35: INTERNAL AGENCY FUND | L35: GENERAL FUND | M35: 000 | N35: 000 | O35: 5644 | R35: 2 | S35: 02/06/2012 | T35: 9924 | U35: 0
A36: 0036000 | B36: =LEFT(GAAP02F[[#This Row],[Fund]],4) -> 0036 | C36: SPECIAL ACCOUNT FOR CAP OUTLAY | D36: G | E36: 001 | F36: 300 | G36: 002 | H36: 900 | I36: 000 | J36: 000 | K36: CAPITAL PROJECTS FUND | L36: OTHER CAPITAL PROJECTS FUND | R36: 3 | S36: 12/30/2014 | T36: 9943 | U36: 0
A37: 0041000 | B37: =LEFT(GAAP02F[[#This Row],[Fund]],4) -> 0041 | C37: AERONAUTICS ACCOUNT | D37: G | E37: 001 | F37: 200 | G37: 001 | H37: 150 | I37: 000 | J37: 000 | K37: SPECIAL REVENUE FUND | L37: TRANSPORTATION FUND | R37: 3 | S37: 12/19/2011 | T37: 9947 | U37: 1
A38: 0042000 | B38: =LEFT(GAAP02F[[#This Row],[Fund]],4) -> 0042 | C38: STATE HIGHWAY ACCOUNT | D38: G | E38: 001 | F38: 200 | G38: 001 | H38: 150 | I38: 000 | J38: 000 | K38: SPECIAL REVENUE | L38: TRANSPORTATION FUND | R38: 2 | S38: 02/01/2012 | T38: 9926 | U38: 1
A39: 0044000 | B39: =LEFT(GAAP02F[[#This Row],[Fund]],4) -> 0044 | C39: MOTOR VEHICLE ACCOUNT | D39: G | E39: 001 | F39: 200 | G39: 001 | H39: 150 | I39: 000 | J39: 000 | K39: SPECIAL REVENUE FUND | L39: TRANSPORTATION FUND | R39: 2 | S39: 02/01/2012 | T39: 9926 | U39: 1
A40: 0045000 | B40: =LEFT(GAAP02F[[#This Row],[Fund]],4) -> 0045 | C40: BICYCLE LANE ACCOUNT | D40: G | E40: 001 | F40: 200 | G40: 001 | H40: 150 | I40: 000 | J40: 000 | K40: SPECIAL REVENUE FUND | L40: TRANSPORTATION FUND | R40: 2 | S40: 12/19/2011 | T40: 9926 | U40: 1
A41: 0046000 | B41: =LEFT(GAAP02F[[#This Row],[Fund]],4) -> 0046 | C41: PUBLIC TRANSPORTATION ACCT STF | D41: G | E41: 001 | F41: 200 | G41: 001 | H41: 150 | I41: 000 | J41: 000 | K41: SPECIAL REVENUE | L41: TRANSPORTATION FUND | R41: 2 | S41: 12/19/2011 | T41: 9926 | U41: 1
A42: 0048000 | B42: =LEFT(GAAP02F[[#This Row],[Fund]],4) -> 0048 | C42: TRANSPORTATION REV ACCOUNT | D42: G | E42: 001 | F42: 850 | G42: 001 | H42: 000 | I42: 200 | J42: 150 | K42: INTERNAL AGENCY FUND | L42: TRANSPORTATION FUND | M42: 000 | N42: 000 | O42: 5678 | R42: 2 | S42: 02/06/2012 | T42: 9926 | U42: 1
A43: 0049000 | B43: =LEFT(GAAP02F[[#This Row],[Fund]],4) -> 0049 | C43: ABOLISHED IN 2004 - DO NOT USE | D43: G | E43: 002 | F43: 400 | G43: 002 | H43: 900 | I43: 000 | J43: 000 | K43: ENTERPRISE FUND | L43: ALL OTHER ENTERPRISE FUND | M43: 777 | N43: 870 | O43: 0000 | P43: D | Q43: P | R43: 2 | S43: 99/99/9999 | T43: 0000 | U43: 1
A44: 0050000 | B44: =LEFT(GAAP02F[[#This Row],[Fund]],4) -> 0050 | C44: COLORADO RIVER MGMT ACCOUNT | D44: G | E44: 001 | F44: 200 | G44: 001 | H44: 300 | I44: 000 | J44: 000 | K44: SPECIAL REVENUE FUND | L44: NAT RESOURES & ENVIRON PROTECT | M44: CH8 | N44: 13/ | O44: 98 | R44: 3 | S44: 10/28/2016 | T44: 9945 | U44: 0
A45: 0051000 | B45: =LEFT(GAAP02F[[#This Row],[Fund]],4) -> 0051 | C45: PROPANE SFTY INSP/ENF PRGM TRU | D45: N | E45: 001 | F45: 850 | G45: 002 | H45: 000 | I45: 200 | J45: 250 | K45: INTERNAL AGENCY FUND | L45: BUS & PROF REG & LIC FUND | M45: 000 | N45: 000 | O45: 5610 | R45: 2 | S45: 10/01/2014 | T45: 9921 | U45: 9
A46: 0052000 | B46: =LEFT(GAAP02F[[#This Row],[Fund]],4) -> 0052 | C46: LOCAL AIRPORT LOAN ACCOUNT | D46: G | E46: 001 | F46: 200 | G46: 001 | H46: 150 | I46: 000 | J46: 000 | K46: SPECIAL REVENUE FUND | L46: TRANSPORTATION FUND | M46: SEC | N46: 216 | O46: 02PU | P46: B | Q46: . | R46: 3 | S46: 02/01/2012 | T46: 9947 | U46: 0 | V46: U
A47: 0054000 | B47: =LEFT(GAAP02F[[#This Row],[Fund]],4) -> 0054 | C47: MOTOR V A/C-NEW MOTOR V BOARD | D47: G | E47: 001 | F47: 200 | G47: 002 | H47: 250 | I47: 000 | J47: 000 | K47: SPECIAL REVENUE FUND | L47: BUS & PROF REG & LIC FUND | R47: 3 | S47: 02/01/2012 | T47: 9947 | U47: 0
A48: 0055000 | B48: =LEFT(GAAP02F[[#This Row],[Fund]],4) -> 0055 | C48: MASS TRANSIT REVOLVING ACCOUNT | D48: G | E48: 001 | F48: 200 | G48: 001 | H48: 150 | I48: 000 | J48: 000 | K48: Special Revenue Fund | L48: TRANSPORTATION FUND | M48: 775 | N48: 830 | O48: 0000 | P48: 0 | Q48: P | R48: 2 | S48: 08/31/2022 | T48: 9926 | U48: 1
A49: 0056000 | B49: =LEFT(GAAP02F[[#This Row],[Fund]],4) -> 0056 | C49: SEISMIC SAFETY RETROFIT ACCT | D49: G | E49: 001 | F49: 200 | G49: 002 | H49: 950 | I49: 000 | J49: 000 | K49: SPECIAL REVENUE FUND | L49: OTHER SPECIAL REVENUE PROGRAMS | R49: 2 | S49: 08/31/2007 | T49: 0000 | U49: 0
A50: 0057000 | B50: =LEFT(GAAP02F[[#This Row],[Fund]],4) -> 0057 | C50: SS BATON RGE VICTORY MEM ACCT | D50: G | E50: 001 | F50: 200 | G50: 002 | H50: 950 | I50: 000 | J50: 000 | K50: SPECIAL REVENUE FUND | L50: OTHER SPECIAL REVENUE PROGRAMS | R50: 1 | S50: 09/17/2009 | T50: 0000 | U50: 0
A51: 0058000 | B51: =LEFT(GAAP02F[[#This Row],[Fund]],4) -> 0058 | C51: RAIL ACCIDENT PREV & RESP FUND | D51: G | E51: 001 | F51: 200 | G51: 001 | H51: 150 | I51: 000 | J51: 000 | K51: SPECIAL REVENUE FUND | L51: TRANSPORTATION FUND | M51: SEC | N51: .77 | O51: 13(A | P51: ) | Q51: P | R51: 3 | S51: 12/19/2011 | T51: 9945 | U51: 0 | V51: U
A52: 0059000 | B52: =LEFT(GAAP02F[[#This Row],[Fund]],4) -> 0059 | C52: HAZARDOUS SPILL PREVENTION ACC | D52: G | E52: 001 | F52: 200 | G52: 001 | H52: 150 | I52: 000 | J52: 000 | K52: SPECIAL REVENUE FUND | L52: TRANSPORTATION FUND | M52: SEC | N52: .77 | O52: 14(A | P52: ) | Q52: P | R52: 3 | S52: 12/19/2011 | T52: 9945 | U52: 0 | V52: U
A53: 0061000 | B53: =LEFT(GAAP02F[[#This Row],[Fund]],4) -> 0061 | C53: MOTOR VEHICLE FUEL ACCOUNT | D53: G | E53: 001 | F53: 850 | G53: 001 | H53: 000 | I53: 200 | J53: 150 | K53: INTERNAL AGENCY FUND | L53: TRANSPORTATION FUND | M53: 000 | N53: 000 | O53: 5610 | R53: 3 | S53: 12/19/2011 | T53: 9947 | U53: 1
A54: 0062000 | B54: =LEFT(GAAP02F[[#This Row],[Fund]],4) -> 0062 | C54: HIGHWAY USERS TAX ACCOUNT | D54: G | E54: 001 | F54: 200 | G54: 001 | H54: 150 | I54: 000 | J54: 000 | K54: SPECIAL REVENUE | L54: TRANSPORTATION FUND | M54: 000 | N54: 000 | O54: 0000 | P54: 0 | Q54: 0 | R54: 2 | S54: 03/06/2012 | T54: 9926 | U54: 0 | V54: 0
A55: 0063000 | B55: =LEFT(GAAP02F[[#This Row],[Fund]],4) -> 0063 | C55: MOTOR VEHICLE TRANS TAX ACCT | D55: G | E55: 001 | F55: 850 | G55: 001 | H55: 000 | I55: 200 | J55: 150 | K55: INTERNAL AGENCY FUND | L55: TRANSPORTATION FUND | M55: 000 | N55: 000 | O55: 5644 | R55: 2 | S55: 02/06/2012 | T55: 9921 | U55: 1
A56: 0064000 | B56: =LEFT(GAAP02F[[#This Row],[Fund]],4) -> 0064 | C56: MOTOR VEHICLE LIC FEE ACCOUNT | D56: G | E56: 001 | F56: 200 | G56: 001 | H56: 150 | I56: 000 | J56: 000 | K56: SPECIAL REVENUE FUND | L56: TRANSPORTATION FUND | M56: 000 | N56: 000 | O56: 0000 | P56: 0 | Q56: P | R56: 2 | S56: 12/28/2022 | T56: 9926 | U56: 1
A57: 0065000 | B57: =LEFT(GAAP02F[[#This Row],[Fund]],4) -> 0065 | C57: ILLEGAL DRUG LAB CLEANUP ACCT | D57: G | E57: 001 | F57: 200 | G57: 001 | H57: 300 | I57: 000 | J57: 000 | K57: SPECIAL REVENUE FUND | L57: NAT RESOURES & ENVIRON PROTECT | M57: CH | N57: 55/ | O57: 94 E | P57: X | Q57: T | R57: 3 | S57: 10/28/2016 | T57: 9945 | U57: 0 | V57: R
A58: 0066000 | B58: =LEFT(GAAP02F[[#This Row],[Fund]],4) -> 0066 | C58: SALE OF TOBACCO TO MINORS CTRL | D58: G | E58: 001 | F58: 200 | G58: 002 | H58: 950 | I58: 000 | J58: 000 | K58: SPECIAL REVENUE FUND | L58: HUMAN SERVICES-SUBSTANCE ABUSE | M58: CH | N58: 100 | O58: 9/94 | R58: 2 | S58: 06/26/2012 | T58: 9923 | U58: 9
A59: 0067000 | B59: =LEFT(GAAP02F[[#This Row],[Fund]],4) -> 0067 | C59: STATE CORPORATIONS FUND | D59: G | E59: 001 | F59: 200 | G59: 002 | H59: 250 | I59: 000 | J59: 000 | K59: SPECIAL REVENUE FUND | L59: BUS & PROF REG & LIC FUND | R59: 2 | S59: 09/07/2016 | T59: 9925 | U59: 9
A60: 0069000 | B60: =LEFT(GAAP02F[[#This Row],[Fund]],4) -> 0069 | C60: BARBERING/COSMTLGY CONTINGENT | D60: G | E60: 001 | F60: 200 | G60: 002 | H60: 250 | I60: 000 | J60: 000 | K60: SPECIAL REVENUE FUND | L60: BUS & PROF REG & LIC FUND | M60: 742 | N60: 2 B | O60: US & | Q60: P | R60: 2 | S60: 07/27/2012 | T60: 9925 | U60: 9 | V60: R
A61: 0070000 | B61: =LEFT(GAAP02F[[#This Row],[Fund]],4) -> 0070 | C61: OCCUPTNL LEAD POIS PREV ACCT | D61: G | E61: 001 | F61: 200 | G61: 001 | H61: 300 | I61: 000 | J61: 000 | K61: SPECIAL REVENUE FUND | L61: NAT RESOURES & ENVIRON PROTECT | M61: H&S | N61: 42 | O61: 9.14 | Q61: ( | R61: 2 | S61: 10/28/2016 | T61: 9923 | U61: 9 | V61: F
A62: 0071000 | B62: =LEFT(GAAP02F[[#This Row],[Fund]],4) -> 0071 | C62: YOSEMITE FOUNDATION ACCOUNT | D62: G | E62: 001 | F62: 200 | G62: 001 | H62: 300 | I62: 000 | J62: 000 | K62: SPECIAL REVENUE FUND | L62: NAT RESOURES & ENVIRON PROTECT | R62: 2 | S62: 10/28/2016 | T62: 9924 | U62: 9
A63: 0072000 | B63: =LEFT(GAAP02F[[#This Row],[Fund]],4) -> 0072 | C63: COLLEGIATE LICENSE PLATE FUND | D63: G | E63: 001 | F63: 200 | G63: 002 | H63: 950 | I63: 000 | J63: 000 | K63: SPECIAL REVENUE FUND | L63: SCHOLARSHIPS | M63: SEC | N63: 50 | O63: 24E | P63: V | Q63: E | R63: 2 | S63: 06/26/2012 | T63: 9926 | U63: 9 | V63: H
A64: 0073000 | B64: =LEFT(GAAP02F[[#This Row],[Fund]],4) -> 0073 | C64: RESOURCES LICENSE PLATE FUND | D64: G | E64: 001 | F64: 200 | G64: 001 | H64: 300 | I64: 000 | J64: 000 | K64: SPECIAL REVENUE FUND | L64: NAT RESOURES & ENVIRON PROTECT | M64: SEC | N64: 50 | O64: 24E | P64: V | Q64: E | R64: 2 | S64: 10/28/2016 | T64: 9926 | U64: 9 | V64: H
A65: 0074000 | B65: =LEFT(GAAP02F[[#This Row],[Fund]],4) -> 0074 | C65: MEDICAL WASTE MANAGEMENT FUND | D65: G | E65: 001 | F65: 200 | G65: 001 | H65: 300 | I65: 000 | J65: 000 | K65: SPECIAL REVENUE FUND | L65: NAT RESOURES & ENVIRON PROTECT | R65: 2 | S65: 10/28/2016 | T65: 9923 | U65: 9
A66: 0075000 | B66: =LEFT(GAAP02F[[#This Row],[Fund]],4) -> 0075 | C66: RADIATION CONTROL FUND | D66: G | E66: 001 | F66: 200 | G66: 002 | H66: 250 | I66: 000 | J66: 000 | K66: SPECIAL REVENUE FUND | L66: BUS & PROF REG & LIC FUND | R66: 2 | S66: 06/25/2012 | T66: 9923 | U66: 9
A67: 0076000 | B67: =LEFT(GAAP02F[[#This Row],[Fund]],4) -> 0076 | C67: TISSUE BANK LICENSE FUND | D67: G | E67: 001 | F67: 200 | G67: 002 | H67: 250 | I67: 000 | J67: 000 | K67: SPECIAL REVENUE FUND | L67: BUS & PROF REG & LIC FUND | M67: 163 | N67: 9.5 | O67: 5 H | P67: & | R67: 2 | S67: 06/25/2012 | T67: 9923 | U67: 9 | V67: S
A68: 0077000 | B68: =LEFT(GAAP02F[[#This Row],[Fund]],4) -> 0077 | C68: STATE EMPLOYEE SCHOLARSHIP FD | D68: G | E68: 001 | F68: 200 | G68: 002 | H68: 950 | I68: 000 | J68: 000 | K68: SPECIAL REVENUE FUND | L68: OTHER SPECIAL REVENUE PROGRAMS | M68: CH4 | N68: 46/ | O68: 99 | R68: 1 | S68: 08/31/2007 | T68: 0000 | U68: 0
A69: 0078000 | B69: =LEFT(GAAP02F[[#This Row],[Fund]],4) -> 0078 | C69: GRAPHIC DESIGN LIC PLATE ACCT | D69: G | E69: 001 | F69: 200 | G69: 002 | H69: 950 | I69: 000 | J69: 000 | K69: SPECIAL REVENUE FUND | L69: EDUCATION | M69: CH | N69: 128 | O69: 2/92 | R69: 2 | S69: 06/26/2012 | T69: 9921 | U69: 9
A70: 0079000 | B70: =LEFT(GAAP02F[[#This Row],[Fund]],4) -> 0079 | C70: INDUSTRIAL MEDICINE FUND | D70: G | E70: 001 | F70: 200 | G70: 002 | H70: 950 | I70: 000 | J70: 000 | K70: SPECIAL REVENUE FUND | L70: OTHER SPECIAL REVENUE PROGRAMS | R70: 1 | S70: 08/31/2007 | T70: 0000 | U70: 0
A71: 0080000 | B71: =LEFT(GAAP02F[[#This Row],[Fund]],4) -> 0080 | C71: CHILDHOOD LEAD POISONG PVTN FD | D71: G | E71: 001 | F71: 200 | G71: 001 | H71: 300 | I71: 000 | J71: 000 | K71: SPECIAL REVENUE FUND | L71: NAT RESOURES & ENVIRON PROTECT | M71: 372 | N71: .7( | O71: E) H | P71: & | Q71: S | R71: 2 | S71: 10/28/2016 | T71: 9923 | U71: 9
A72: 0081000 | B72: =LEFT(GAAP02F[[#This Row],[Fund]],4) -> 0081 | C72: ALCOHOL BEVERAGE CONTROL FUND | D72: G | E72: 001 | F72: 850 | G72: 001 | H72: 000 | I72: 100 | J72: 100 | K72: INTERNAL AGENCY FUND | L72: GENERAL FUND | M72: 000 | N72: 000 | O72: 5620 | P72: 0 | Q72: 0 | R72: 2 | S72: 99/99/9999 | T72: 9921 | U72: 0
A73: 0082000 | B73: =LEFT(GAAP02F[[#This Row],[Fund]],4) -> 0082 | C73: EXPORT DOCUMENT PROGRAM FUND | D73: G | E73: 001 | F73: 200 | G73: 002 | H73: 250 | I73: 000 | J73: 000 | K73: SPECIAL REVENUE FUND | L73: BUS & PROF REG & LIC FUND | R73: 2 | S73: 06/25/2012 | T73: 9923 | U73: 9
A74: 0083000 | B74: =LEFT(GAAP02F[[#This Row],[Fund]],4) -> 0083 | C74: VETERANS SERVICE OFFICE FUND | D74: G | E74: 001 | F74: 200 | G74: 002 | H74: 450 | I74: 000 | J74: 000 | K74: SPECIAL REVENUE FUND | L74: FINANCING TO LOCAL & PUBLIC | M74: CH | N74: 127 | O74: 5/92 | R74: 2 | S74: 06/25/2012 | T74: 9921 | U74: 9
A75: 0084000 | B75: =LEFT(GAAP02F[[#This Row],[Fund]],4) -> 0084 | C75: CORPORATION TAX FUND | D75: G | E75: 001 | F75: 850 | G75: 001 | H75: 000 | I75: 100 | J75: 100 | K75: INTERNAL AGENCY FUND | L75: GENERAL FUND | M75: 000 | N75: 000 | O75: 5620 | R75: 5 | S75: 02/06/2012 | T75: 0000 | U75: 0
A76: 0085000 | B76: =LEFT(GAAP02F[[#This Row],[Fund]],4) -> 0085 | C76: ESTATE TAX FUND | D76: G | E76: 001 | F76: 850 | G76: 001 | H76: 000 | I76: 100 | J76: 100 | K76: INTERNAL AGENCY FUND | L76: GENERAL FUND | M76: 000 | N76: 000 | O76: 5620 | R76: 5 | S76: 02/06/2012 | T76: 0000 | U76: 0
A77: 0086000 | B77: =LEFT(GAAP02F[[#This Row],[Fund]],4) -> 0086 | C77: CIGARETTE TAX FUND | D77: G | E77: 001 | F77: 850 | G77: 001 | H77: 000 | I77: 100 | J77: 100 | K77: INTERNAL AGENCY FUND | L77: GENERAL FUND | M77: 000 | N77: 000 | O77: 5620 | R77: 5 | S77: 02/06/2012 | T77: 0000 | U77: 0
A78: 0087000 | B78: =LEFT(GAAP02F[[#This Row],[Fund]],4) -> 0087 | C78: SCHOOL SAFETY ACCOUNT | D78: G | E78: 001 | F78: 200 | G78: 002 | H78: 450 | I78: 000 | J78: 000 | K78: SPECIAL REVENUE FUND | L78: FINANCING TO LOCAL & PUBLIC | M78: CH | N78: 102 | O78: 2/94 | R78: 1 | S78: 07/10/2002 | T78: 0000 | U78: 0
A79: 0088000 | B79: =LEFT(GAAP02F[[#This Row],[Fund]],4) -> 0088 | C79: GIFT TAX FUND | D79: G | E79: 001 | F79: 850 | G79: 001 | H79: 000 | I79: 100 | J79: 100 | K79: INTERNAL AGENCY FUND | L79: GENERAL FUND | M79: 000 | N79: 000 | O79: 5620 | R79: 5 | S79: 02/06/2012 | T79: 0000 | U79: 0
A80: 0089000 | B80: =LEFT(GAAP02F[[#This Row],[Fund]],4) -> 0089 | C80: INHERITANCE TAX FUND | D80: G | E80: 001 | F80: 850 | G80: 001 | H80: 000 | I80: 100 | J80: 100 | K80: INTERNAL AGENCY FUND | L80: GENERAL FUND | M80: 000 | N80: 000 | O80: 5620 | R80: 5 | S80: 02/06/2012 | T80: 0000 | U80: 0
A81: 0090000 | B81: =LEFT(GAAP02F[[#This Row],[Fund]],4) -> 0090 | C81: INSURANCE TAX FUND | D81: G | E81: 001 | F81: 850 | G81: 001 | H81: 000 | I81: 100 | J81: 100 | K81: INTERNAL AGENCY FUND | L81: GENERAL FUND | M81: 000 | N81: 000 | O81: 5620 | R81: 5 | S81: 02/06/2012 | T81: 0000 | U81: 0
A82: 0091000 | B82: =LEFT(GAAP02F[[#This Row],[Fund]],4) -> 0091 | C82: PERSONAL INCOME TAX | D82: G | E82: 001 | F82: 850 | G82: 001 | H82: 000 | I82: 100 | J82: 100 | K82: INTERNAL AGENCY FUND | L82: GENERAL FUND | M82: 000 | N82: 000 | O82: 5620 | R82: 5 | S82: 02/06/2012 | T82: 0000 | U82: 0
A83: 0093000 | B83: =LEFT(GAAP02F[[#This Row],[Fund]],4) -> 0093 | C83: CONSTRUCTION MGT ED ACCOUNT | D83: G | E83: 001 | F83: 200 | G83: 002 | H83: 250 | I83: 000 | J83: 000 | K83: SPECIAL REVENUE FUND | L83: BUS & PROF REG & LIC FUND | R83: 2 | S83: 06/25/2012 | T83: 9925 | U83: 9
A84: 0094000 | B84: =LEFT(GAAP02F[[#This Row],[Fund]],4) -> 0094 | C84: RETAIL SALES TAX FUND | D84: G | E84: 004 | F84: 850 | G84: 002 | H84: 000 | I84: 680 | J84: 100 | K84: INTERNAL AGENCY FUND | L84: CUSTODIAL FUND | M84: 000 | N84: 000 | O84: 5610 | P84: 0 | Q84: 0 | R84: 2 | S84: 99/99/9999 | T84: 9921 | U84: 0
A85: 0096000 | B85: =LEFT(GAAP02F[[#This Row],[Fund]],4) -> 0096 | C85: CAL-OSHA TARGET INSPCT/CONSULT | D85: G | E85: 001 | F85: 200 | G85: 002 | H85: 250 | I85: 000 | J85: 000 | K85: SPECIAL REVENUE FUND | L85: BUS & PROF REG & LIC FUND | M85: 000 | N85: 000 | R85: 2 | S85: 99/99/9999 | T85: 9923 | U85: 9
A86: 0097000 | B86: =LEFT(GAAP02F[[#This Row],[Fund]],4) -> 0097 | C86: HWY CARRIERS UNIF BUSN LIC TX | D86: G | E86: 001 | F86: 850 | G86: 001 | H86: 000 | I86: 100 | J86: 100 | K86: INTERNAL AGENCY FUND | L86: GENERAL FUND | M86: 000 | N86: 000 | O86: 5620 | R86: 5 | S86: 02/06/2012 | T86: 0000 | U86: 0
A87: 0098000 | B87: =LEFT(GAAP02F[[#This Row],[Fund]],4) -> 0098 | C87: CLINICAL LAB IMPROVEMENT FUND | D87: G | E87: 001 | F87: 200 | G87: 002 | H87: 250 | I87: 000 | J87: 000 | K87: SPECIAL REVENUE FUND | L87: BUS & PROF REG & LIC FUND | M87: CH | N87: 492 | O87: /94 | R87: 3 | S87: 12/19/2011 | T87: 9944 | U87: 0
A88: 0099000 | B88: =LEFT(GAAP02F[[#This Row],[Fund]],4) -> 0099 | C88: HEALTH STATISTICS SPECIAL FUND | D88: G | E88: 001 | F88: 200 | G88: 002 | H88: 950 | I88: 000 | J88: 000 | K88: SPECIAL REVENUE FUND | L88: REGISTRY-STATISTICS | M88: CH | N88: 492 | O88: /94 | R88: 2 | S88: 06/26/2012 | T88: 9923 | U88: 9
A89: 0100000 | B89: =LEFT(GAAP02F[[#This Row],[Fund]],4) -> 0100 | C89: CALIF USED OIL RECYCLING FUND | D89: G | E89: 001 | F89: 200 | G89: 001 | H89: 300 | I89: 000 | J89: 000 | K89: SPECIAL REVENUE FUND | L89: NAT RESOURES & ENVIRON PROTECT | M89: 000 | N89: 000 | R89: 2 | S89: 10/28/2016 | T89: 9924 | U89: 9
