Workbook
Name ActuaryCredentialsGASB: [1]DeveloperInfo!$D$19
Name ActuaryNameGASB: [1]DeveloperInfo!$D$17
Name ActuaryTitleGASB: [1]DeveloperInfo!$D$18
Name AdjCNSDate: [1]DeveloperInfo!$D$33
Name AdjCNSDate1: [1]DeveloperInfo!$E$33
Name AdjCNSDateTempEnable: [1]DeveloperInfo!$F$34
Name AgencyCode: #REF!
Name AgencyCode1: #REF!
Name AnalystGASB: [1]DeveloperInfo!$D$20
Name Annuity: #REF!
Name Annuity1: #REF!
Name AnnuityLY: #REF!
Name ASTABPF: [1]DeveloperInfo!$D$36
Name ASTABPF1: [1]DeveloperInfo!$D$37
Name ASTEBPF: [1]DeveloperInfo!$F$37
Name ClientShortGASB: [1]DeveloperInfo!$D$9
Name CLPOWERDisc: [1]Adjust!$H$199
Name CLPOWERDiscMinus1: [1]Adjust!$L$199
Name CLPOWERDiscPlus1: [1]Adjust!$K$199
Name CLPOWERExp: [1]Adjust!$G$199
Name CNSDateDisc: [1]DeveloperInfo!$D$32
Name CNSDateDisc1: [1]DeveloperInfo!$E$32
Name ColaRate: [1]DeveloperInfo!$D$40
Name ConsultantNameGASB: [1]DeveloperInfo!$D$22
Name ConsultantTitleGASB: [1]DeveloperInfo!$D$23
Name Disc1DELTACENSUS: [1]Adjust!$G$102
Name Disc1INTNDIV12: [1]Adjust!$H$195
Name Disc1SINTADJBOM: [1]Adjust!$I$197
Name Disc1SINTNDIV12: [1]Adjust!$I$195
Name DiscDELTACENSUS: [1]Adjust!$H$102
Name DiscINTADJBOM: [1]Adjust!$J$197
Name DiscINTNDIV12: [1]Adjust!$J$195
Name DiscMinusOneINTADJBOM: [1]Adjust!$L$197
Name DiscMinusOneINTNDIV12: [1]Adjust!$L$195
Name DiscPlusOneINTADJBOM: [1]Adjust!$K$197
Name DiscPlusOneINTNDIV12: [1]Adjust!$K$195
Name EmployerRates: #REF!
Name EmployerRates1: #REF!
Name EmployerRatesLEO: #REF!
Name EmployerRatesLEO1: #REF!
Name ERData: [1]ER_DATA!$B$16:$EN$318
Name ERID: [1]ER_NPLExpense!$L$8
Name ERInfo: [1]ER_Input!$B$16:$Y$318
Name Exp1INTADJBOM: [1]Adjust!$G$197
Name Exp1INTNDIV12: [1]Adjust!$G$195
Name FracYearProj: [1]TPL!$C$43
Name FundOfficeContactGASB: [1]DeveloperInfo!$D$10
Name FYrsGASB: [1]DeveloperInfo!$D$54
Name GainLoss: [1]ER_Allocation!$P$12
Name GASBDiscMinusOneINTADJBOM: [1]Adjust!$L$197
Name GASBDiscMinusOneINTNDIV12: [1]Adjust!$L$195
Name InflRate: [1]DeveloperInfo!$D$38
Name InflRate1: [1]DeveloperInfo!$E$38
Name IntDisc: [1]DeveloperInfo!$F$47
Name IntDisc1: [1]DeveloperInfo!$D$47
Name IntDisc1S: [1]DeveloperInfo!$E$47
Name INTDiscMinusOne: [1]DeveloperInfo!$H$47
Name INTDiscPlusOne: [1]DeveloperInfo!$G$47
Name IntExp1: [1]DeveloperInfo!$I$47
Name MeasureDate: [1]DeveloperInfo!$D$31

Sheet Fund 0001 Journal Entries
A1: GASB 96 - SBITA Contracts Fund-by-Fund Journal Entries Form (to be submitted to the SCO annually—one form per fund)
A2: Manually complete every yellow field in this worksheet—there are no automatically calculated data-entry cells in this worksheet.
A3: Fiscal year: | F3: 2023–2024
A4: Organization Name: | F4: Department of Justice
A5: Organization Code (Business Unit): | F5: 0820
A6: Fund Number: | F6: 1
A7: Fund Type: | F7: Governmental Fund
A8: Fund Classification: | F8: =IF(OR($F$7='Drop Down Menus'!B2,$F$7='Drop Down Menus'!$B$3),'Drop Down Menus'!$D$9,IFERROR(VLOOKUP($F$5,GAAP02Aindex!$A$2:$D$900,4,FALSE),"Unidentified")) -> GENERAL GOVERNMENT
A12: =IF($F$3="2022–2023","Establish Beginning Balances (SBITAs commenced on or before 07/01/2022)","Establish Beginning Balances (existing SBITAs only)") -> Establish Beginning Balances (existing SBITAs only)
A13: Entry #
A14: 0 | B14: =IF($F$3="2022–2023","To establish the beginning balance of SBITAs as of 07/01/2022.","Roll forward prior year right-to-use SBITAs to record opening balances.") -> Roll forward prior year right-to-use SBITAs to record opening balances. | M14: Department Beginning Balances | P14: From SCO BB List | S14: Difference
B15: Dr: Acct 0480 - RIGHT-TO-USE SBITA - AMORTIZABLE | J15: =ROUND(M15,0) -> 3655450 | M15: 3655450 | P15: 3655450 | S15: =M15-P15 -> 0 | T15: Report any "Differences" on the Report 18 Differential.
B16: Dr: Acct 0950 - BEGINNING FUND BALANCE | J16: =ROUND(P16,0) -> 0 | M16: 8892 | P16: =IF(SUM($Q$18:$Q$19)>$P$15,SUM($Q$18:$Q$19)-$P$15,0) -> 0 | S16: =M16-P16 -> 8892 | T16: No action required.
B17: Dr: Acct 0952 - BEG FB ADJ/PRIOR PERIOD ADJUSTMENT | J17: =ROUND(IF(SUM($K$18:$K$20)>SUM($J$15:$J$16),SUM($K$18:$K$20)-SUM($J$15:$J$16),0),0) -> 0 | S17: =M17-P17 -> 0 | T17: No action required.
C18: Cr. Acct 0475 - ACCUMULATED AMORTIZATION - RIGHT-TO-USE SBITA | K18: =ROUND(N18,0) -> 2247186 | N18: 2247186 | Q18: 2247186 | S18: =N18-Q18 -> 0 | T18: No action required.
C19: Cr: Acct 0674 - RIGHT-TO-USE SBITA LIABILITY | K19: =ROUND(N19,0) -> 968958 | N19: 968958 | Q19: 968958 | S19: =N19-Q19 -> 0 | T19: No action required.
C20: Cr: Acct 0950 - BEGINNING FUND BALANCE | K20: =ROUND(Q20,0) -> 439306 | N20: 448198 | Q20: =IF(SUM($Q$18:$Q$19)<$P$15,-SUM($Q$18:$Q$19)+$P$15,0) -> 439306 | S20: =N20-Q20 -> 8892 | T20: No action required.
C21: Cr: Acct 0952 - BEG FB ADJ/PRIOR PERIOD ADJUSTMENT | K21: =ROUND(IF(SUM($K$18:$K$20)<SUM($J$15:$J$16),-SUM($K$18:$K$20)+SUM($J$15:$J$16),0),0) -> 0 | S21: =N21-Q21 -> 0 | T21: No action required.
J22: =ROUND(SUM(J15:J17),0) -> 3655450 | K22: =ROUND(SUM(K18:K21),0) -> 3655450 | L22: =IF(J22=K22,"<- Debits and Credits equal each other.","<- Debits and Credits do not equal each other.") -> <- Debits and Credits equal each other.
B24: SBITA ASSET (Acct 0480) AMOUNT SHOULD BE REPORTED AS BEGINNING BALANCE ON REPORT 18.
A26: =IF($F$3="2022–2023","Record SBITAs Commenced on or after 07/02/2022","Record New SBITAs (new SBITAs only)") -> Record New SBITAs (new SBITAs only)
A27: 1 | B27: Record at inception of SBITA in accordance with Fund-Based accounting (Governmental Funds Only).
B28: Dr: Acct 0842 - CAPITAL OUTLAY | J28: 1083987
C29: Cr: Acct 0789 - LEASE AND OTHER FINANCING PROCEEDS | K29: 1083987
C30: =VLOOKUP($F$8,'Drop Down Menus'!$D$2:$G$10,4,FALSE) -> Cr: Acct 0808 - GENERAL GOV. (GAAP ADJ)
J31: =ROUND(SUM(J28:J30),2) -> 1083987 | K31: =ROUND(SUM(K28:K30),2) -> 1083987 | L31: =IF(J31=K31,"<- Debits and Credits equal each other.","<- Debits and Credits do not equal each other.") -> <- Debits and Credits equal each other.
A33: 2 | B33: Reverse the fund-based entry in #1 above, if any, and record an inception of SBITA in accordance with GAAP Govt Wide.
B34: Dr: Acct 0480 - RIGHT-TO-USE SBITA - AMORTIZABLE | J34: 1083987
B35: Dr: Acct 0789 - LEASE AND OTHER FINANCING PROCEEDS | J35: 1083987
C36: Cr: Acct 0842 - CAPITAL OUTLAY | K36: 1083987
C37: Cr: Acct 0674 - RIGHT-TO-USE SBITA LIABILITY | K37: 1083987
C38: =VLOOKUP($F$8,'Drop Down Menus'!$D$2:$G$10,4,FALSE) -> Cr: Acct 0808 - GENERAL GOV. (GAAP ADJ)
J39: =ROUND(SUM(J34:J35),2) -> 2167974 | K39: =ROUND(SUM(K36:K38),2) -> 2167974 | L39: =IF(J39=K39,"<- Debits and Credits equal each other.","<- Debits and Credits do not equal each other.") -> <- Debits and Credits equal each other.
B41: SBITA ASSET (Acct 0480) AMOUNT SHOULD BE INCLUDED AS "ADDITIONS" ON REPORT 18.
A43: Record Annual Activity (all SBITAs)
A44: 3 | B44: Record amortization of the SBITA asset for the year.
B45: Dr: Acct 0875 - DEPRECIATION/AMORTIZATION | J45: 882518
C46: Cr. Acct 0475 - ACCUMULATED AMORTIZATION - RIGHT-TO-USE SBITA | K46: =J45 -> 882518
J47: =ROUND(SUM(J45:J45),2) -> 882518 | K47: =ROUND(SUM(K46),2) -> 882518 | L47: =IF(J47=K47,"<- Debits and Credits equal each other.","<- Debits and Credits do not equal each other.") -> <- Debits and Credits equal each other.
A49: 4 | B49: Reclassify information technology subscription exp. to debt service principal and interest exp.
B50: Dr: Acct 0848 - DEBT SERVICE - PRINCIPAL LEASES | J50: 573282 | L50: =IF($J$50=$K$57,"","<- Accts 0848 must agree")
B51: =IF(OR($F$7="Proprietary - Internal Service Fund",$F$7="Proprietary - Enterprise Fund"),"Dr: Acct 0894 - INTEREST EXPENSE AND FISCAL CHARGES","Dr: Acct 0851 - DEBT SERVICE - INTEREST LEASES") -> Dr: Acct 0851 - DEBT SERVICE - INTEREST LEASES | J51: 16574
C52: =VLOOKUP($F$8,'Drop Down Menus'!$D$2:$G$10,4,FALSE) -> Cr: Acct 0808 - GENERAL GOV. (GAAP ADJ) | K52: =+J50+J51 -> 589856
J53: =ROUND(SUM(J50:J51),2) -> 589856 | K53: =ROUND(SUM(K52,),2) -> 589856 | L53: =IF(J53=K53,"<- Debits and Credits equal each other.","<- Debits and Credits do not equal each other.") -> <- Debits and Credits equal each other.
A55: 5 | B55: Reduce SBITA liability for total current year principal payments.
B56: Dr: Acct 0674 - RIGHT-TO-USE SBITA LIABILITY | J56: =K57 -> 573282
C57: Cr: Acct 0848 - DEBT SERVICE - PRINCIPAL LEASES | K57: =J50 -> 573282 | L57: =IF($J$50=$K$57,"","<- Accts 0848 must agree")
J58: =ROUND(SUM(J56:J56),2) -> 573282 | K58: =ROUND(SUM(K57),2) -> 573282 | L58: =IF(J58=K58,"<- Debits and Credits equal each other.","<- Debits and Credits do not equal each other.") -> <- Debits and Credits equal each other.
A60: 6 | B60: Reclassify the principal amount due in the next FY to the current liability.
B61: Dr: Acct 0674 - RIGHT-TO-USE SBITA LIABILITY | J61: 424220
C62: Cr. Acct 0651 - RIGHT-TO-USE SBITA LIABILITY (CURRENT PORTION LT) | K62: =J61 -> 424220
B63: NOTE: This is an annual accrual. The RTU SBITA Liability - Current portion will be added back to the RTU SBITA Liability in entry #0 when reestablishing the beginning balances next year. | J63: =ROUND(SUM(J61:J61),2) -> 424220 | K63: =ROUND(SUM(K62),2) -> 424220 | L63: =IF(J63=K63,"<- Debits and Credits equal each other.","<- Debits and Credits do not equal each other.") -> <- Debits and Credits equal each other.
A66: Remove SBITA Asset at the End of the Subscription Term (only at the end of the subscription term)
A67: 7 | B67: Record entry to write off the SBITA asset and accumulated amortization at the end of the subscription term.
B68: Dr: Acct 0475 - ACCUMULATED AMORTIZATION - RIGHT-TO-USE SBITA | J68: 2271149
C69: Cr: Acct 0480 - RIGHT-TO-USE SBITA - AMORTIZABLE | K69: 2271149
J70: =SUM(J68) -> 2271149 | K70: =SUM(K69) -> 2271149 | L70: =IF(J70=K70,"<- Debits and Credits equal each other.","<- Debits and Credits do not equal each other.") -> <- Debits and Credits equal each other.
B72: SBITA ASSET (Acct 0480) SHOULD BE INCLUDED AS "DEDUCTIONS" ON REPORT 18.
A74: Record SBITA Remeasurement and Modifications (only if a significant modification occurred during the fiscal year)
A75: 8 | B75: Record early termination of SBITA contract or SBITA modifications to decrease in the RTU SBITA asset.
B76: Dr: Acct 0674 - RIGHT-TO-USE SBITA LIABILITY | J76: 613984
B77: Dr: Acct 0475 - ACCUMULATED AMORTIZATION - RIGHT-TO-USE SBITA | J77: 523211
B78: =VLOOKUP($F$8,'Drop Down Menus'!$D$2:$G$10,3,FALSE) -> Dr: Acct 0808 - GENERAL GOV. (GAAP ADJ)
C79: Cr: Acct 0480 - RIGHT-TO-USE SBITA - AMORTIZABLE | K79: 1131150
C80: =VLOOKUP($F$8,'Drop Down Menus'!$D$2:$G$10,4,FALSE) -> Cr: Acct 0808 - GENERAL GOV. (GAAP ADJ) | K80: 6045
J81: =ROUND(SUM(J76:J78),2) -> 1137195 | K81: =ROUND(SUM(K79:K80),2) -> 1137195 | L81: =IF(J81=K81,"<- Debits and Credits equal each other.","<- Debits and Credits do not equal each other.") -> <- Debits and Credits equal each other.
A83: 9 | B83: Record SBITA modifications to increase in the RTU SBITA asset.
B84: Dr: Acct 0480 - RIGHT-TO-USE SBITA - AMORTIZABLE
C85: Cr: Acct 0674 - RIGHT-TO-USE SBITA LIABILITY
J86: =SUM(J84) -> 0 | K86: =SUM(K85) -> 0 | L86: =IF(J86=K86,"<- Debits and Credits equal each other.","<- Debits and Credits do not equal each other.") -> <- Debits and Credits equal each other.
B88: NOTE: Please check the instructions for remeasurement and modifications on the SCO website.
D92: Informational - Ending Balances of Assets and Liabilities
K93: Debit (Credit)
D94: Acct 0480 - RIGHT-TO-USE SBITA - AMORTIZABLE | K94: =+J15+J34-K69-K79+J84 -> 1337138
D95: Acct 0475 - ACCUMULATED AMORTIZATION - RIGHT-TO-USE SBITA | K95: =-K18-K46+J68+J77 -> -335344
D96: Acct 0674 - RIGHT-TO-USE SBITA LIABILITY | K96: =-K19-K37+J56+J61+J76-K85 -> -441459
D97: Acct 0651 - RIGHT-TO-USE SBITA LIABILITY (CURRENT PORTION LT) | K97: =-K62 -> -424220

Sheet Fund 0012 Journal Entries
A1: GASB 96 - SBITA Contracts Fund-by-Fund Journal Entries Form (to be submitted to the SCO annually—one form per fund)
A2: Manually complete every yellow field in this worksheet—there are no automatically calculated data-entry cells in this worksheet.
A3: Fiscal year: | F3: 2023–2024
A4: Organization Name: | F4: Department of Justice
A5: Organization Code (Business Unit): | F5: 0820
A6: Fund Number: | F6: 12
A7: Fund Type: | F7: Governmental Fund
A8: Fund Classification: | F8: =IF(OR($F$7='Drop Down Menus'!B2,$F$7='Drop Down Menus'!$B$3),'Drop Down Menus'!$D$9,IFERROR(VLOOKUP($F$5,GAAP02Aindex!$A$2:$D$900,4,FALSE),"Unidentified")) -> GENERAL GOVERNMENT
A12: =IF($F$3="2022–2023","Establish Beginning Balances (SBITAs commenced on or before 07/01/2022)","Establish Beginning Balances (existing SBITAs only)") -> Establish Beginning Balances (existing SBITAs only)
A13: Entry #
A14: 0 | B14: =IF($F$3="2022–2023","To establish the beginning balance of SBITAs as of 07/01/2022.","Roll forward prior year right-to-use SBITAs to record opening balances.") -> Roll forward prior year right-to-use SBITAs to record opening balances. | M14: Department Beginning Balances | P14: From SCO BB List | S14: Difference
B15: Dr: Acct 0480 - RIGHT-TO-USE SBITA - AMORTIZABLE | J15: =ROUND(M15,0) -> 717 | M15: 717 | P15: 717 | S15: =M15-P15 -> 0 | T15: Report any "Differences" on the Report 18 Differential.
B16: Dr: Acct 0950 - BEGINNING FUND BALANCE | J16: =ROUND(P16,0) -> 0 | M16: 4 | P16: =IF(SUM($Q$18:$Q$19)>$P$15,SUM($Q$18:$Q$19)-$P$15,0) -> 0 | S16: =M16-P16 -> 4 | T16: No action required.
B17: Dr: Acct 0952 - BEG FB ADJ/PRIOR PERIOD ADJUSTMENT | J17: =ROUND(IF(SUM($K$18:$K$20)>SUM($J$15:$J$16),SUM($K$18:$K$20)-SUM($J$15:$J$16),0),0) -> 0 | S17: =M17-P17 -> 0 | T17: No action required.
C18: Cr. Acct 0475 - ACCUMULATED AMORTIZATION - RIGHT-TO-USE SBITA | K18: =ROUND(N18,0) -> 295 | N18: 295 | Q18: 295 | S18: =N18-Q18 -> 0 | T18: No action required.
C19: Cr: Acct 0674 - RIGHT-TO-USE SBITA LIABILITY | K19: =ROUND(N19,0) -> 411 | N19: 411 | Q19: 411 | S19: =N19-Q19 -> 0 | T19: No action required.
C20: Cr: Acct 0950 - BEGINNING FUND BALANCE | K20: =ROUND(Q20,0) -> 11 | N20: 15 | Q20: =IF(SUM($Q$18:$Q$19)<$P$15,-SUM($Q$18:$Q$19)+$P$15,0) -> 11 | S20: =N20-Q20 -> 4 | T20: No action required.
C21: Cr: Acct 0952 - BEG FB ADJ/PRIOR PERIOD ADJUSTMENT | K21: =ROUND(IF(SUM($K$18:$K$20)<SUM($J$15:$J$16),-SUM($K$18:$K$20)+SUM($J$15:$J$16),0),0) -> 0 | S21: =N21-Q21 -> 0 | T21: No action required.
J22: =ROUND(SUM(J15:J17),0) -> 717 | K22: =ROUND(SUM(K18:K21),0) -> 717 | L22: =IF(J22=K22,"<- Debits and Credits equal each other.","<- Debits and Credits do not equal each other.") -> <- Debits and Credits equal each other.
B24: SBITA ASSET (Acct 0480) AMOUNT SHOULD BE REPORTED AS BEGINNING BALANCE ON REPORT 18.
A26: =IF($F$3="2022–2023","Record SBITAs Commenced on or after 07/02/2022","Record New SBITAs (new SBITAs only)") -> Record New SBITAs (new SBITAs only)
A27: 1 | B27: Record at inception of SBITA in accordance with Fund-Based accounting (Governmental Funds Only).
B28: Dr: Acct 0842 - CAPITAL OUTLAY | J28: 557
C29: Cr: Acct 0789 - LEASE AND OTHER FINANCING PROCEEDS | K29: 557
C30: =VLOOKUP($F$8,'Drop Down Menus'!$D$2:$G$10,4,FALSE) -> Cr: Acct 0808 - GENERAL GOV. (GAAP ADJ)
J31: =ROUND(SUM(J28:J30),2) -> 557 | K31: =ROUND(SUM(K28:K30),2) -> 557 | L31: =IF(J31=K31,"<- Debits and Credits equal each other.","<- Debits and Credits do not equal each other.") -> <- Debits and Credits equal each other.
A33: 2 | B33: Reverse the fund-based entry in #1 above, if any, and record an inception of SBITA in accordance with GAAP Govt Wide.
B34: Dr: Acct 0480 - RIGHT-TO-USE SBITA - AMORTIZABLE | J34: 557
B35: Dr: Acct 0789 - LEASE AND OTHER FINANCING PROCEEDS | J35: 557
C36: Cr: Acct 0842 - CAPITAL OUTLAY | K36: 557
C37: Cr: Acct 0674 - RIGHT-TO-USE SBITA LIABILITY | K37: 557
C38: =VLOOKUP($F$8,'Drop Down Menus'!$D$2:$G$10,4,FALSE) -> Cr: Acct 0808 - GENERAL GOV. (GAAP ADJ)
J39: =ROUND(SUM(J34:J35),2) -> 1114 | K39: =ROUND(SUM(K36:K38),2) -> 1114 | L39: =IF(J39=K39,"<- Debits and Credits equal each other.","<- Debits and Credits do not equal each other.") -> <- Debits and Credits equal each other.
B41: SBITA ASSET (Acct 0480) AMOUNT SHOULD BE INCLUDED AS "ADDITIONS" ON REPORT 18.
A43: Record Annual Activity (all SBITAs)
A44: 3 | B44: Record amortization of the SBITA asset for the year.
B45: Dr: Acct 0875 - DEPRECIATION/AMORTIZATION | J45: 161
C46: Cr. Acct 0475 - ACCUMULATED AMORTIZATION - RIGHT-TO-USE SBITA | K46: =J45 -> 161
J47: =ROUND(SUM(J45:J45),2) -> 161 | K47: =ROUND(SUM(K46),2) -> 161 | L47: =IF(J47=K47,"<- Debits and Credits equal each other.","<- Debits and Credits do not equal each other.") -> <- Debits and Credits equal each other.
A49: 4 | B49: Reclassify information technology subscription exp. to debt service principal and interest exp.
B50: Dr: Acct 0848 - DEBT SERVICE - PRINCIPAL LEASES | J50: 213 | L50: =IF($J$50=$K$57,"","<- Accts 0848 must agree")
B51: =IF(OR($F$7="Proprietary - Internal Service Fund",$F$7="Proprietary - Enterprise Fund"),"Dr: Acct 0894 - INTEREST EXPENSE AND FISCAL CHARGES","Dr: Acct 0851 - DEBT SERVICE - INTEREST LEASES") -> Dr: Acct 0851 - DEBT SERVICE - INTEREST LEASES | J51: 7
C52: =VLOOKUP($F$8,'Drop Down Menus'!$D$2:$G$10,4,FALSE) -> Cr: Acct 0808 - GENERAL GOV. (GAAP ADJ) | K52: =+J50+J51 -> 220
J53: =ROUND(SUM(J50:J51),2) -> 220 | K53: =ROUND(SUM(K52,),2) -> 220 | L53: =IF(J53=K53,"<- Debits and Credits equal each other.","<- Debits and Credits do not equal each other.") -> <- Debits and Credits equal each other.
A55: 5 | B55: Reduce SBITA liability for total current year principal payments.
B56: Dr: Acct 0674 - RIGHT-TO-USE SBITA LIABILITY | J56: =K57 -> 213
C57: Cr: Acct 0848 - DEBT SERVICE - PRINCIPAL LEASES | K57: =J50 -> 213 | L57: =IF($J$50=$K$57,"","<- Accts 0848 must agree")
J58: =ROUND(SUM(J56:J56),2) -> 213 | K58: =ROUND(SUM(K57),2) -> 213 | L58: =IF(J58=K58,"<- Debits and Credits equal each other.","<- Debits and Credits do not equal each other.") -> <- Debits and Credits equal each other.
A60: 6 | B60: Reclassify the principal amount due in the next FY to the current liability.
B61: Dr: Acct 0674 - RIGHT-TO-USE SBITA LIABILITY | J61: 199
C62: Cr. Acct 0651 - RIGHT-TO-USE SBITA LIABILITY (CURRENT PORTION LT) | K62: =J61 -> 199
B63: NOTE: This is an annual accrual. The RTU SBITA Liability - Current portion will be added back to the RTU SBITA Liability in entry #0 when reestablishing the beginning balances next year. | J63: =ROUND(SUM(J61:J61),2) -> 199 | K63: =ROUND(SUM(K62),2) -> 199 | L63: =IF(J63=K63,"<- Debits and Credits equal each other.","<- Debits and Credits do not equal each other.") -> <- Debits and Credits equal each other.
A66: Remove SBITA Asset at the End of the Subscription Term (only at the end of the subscription term)
A67: 7 | B67: Record entry to write off the SBITA asset and accumulated amortization at the end of the subscription term.
B68: Dr: Acct 0475 - ACCUMULATED AMORTIZATION - RIGHT-TO-USE SBITA | J68: 101
C69: Cr: Acct 0480 - RIGHT-TO-USE SBITA - AMORTIZABLE | K69: 101
J70: =SUM(J68) -> 101 | K70: =SUM(K69) -> 101 | L70: =IF(J70=K70,"<- Debits and Credits equal each other.","<- Debits and Credits do not equal each other.") -> <- Debits and Credits equal each other.
B72: SBITA ASSET (Acct 0480) SHOULD BE INCLUDED AS "DEDUCTIONS" ON REPORT 18.
A74: Record SBITA Remeasurement and Modifications (only if a significant modification occurred during the fiscal year)
A75: 8 | B75: Record early termination of SBITA contract or SBITA modifications to decrease in the RTU SBITA asset.
B76: Dr: Acct 0674 - RIGHT-TO-USE SBITA LIABILITY | J76: 327
B77: Dr: Acct 0475 - ACCUMULATED AMORTIZATION - RIGHT-TO-USE SBITA | J77: 214
B78: =VLOOKUP($F$8,'Drop Down Menus'!$D$2:$G$10,3,FALSE) -> Dr: Acct 0808 - GENERAL GOV. (GAAP ADJ)
C79: Cr: Acct 0480 - RIGHT-TO-USE SBITA - AMORTIZABLE | K79: 538
C80: =VLOOKUP($F$8,'Drop Down Menus'!$D$2:$G$10,4,FALSE) -> Cr: Acct 0808 - GENERAL GOV. (GAAP ADJ) | K80: 3
J81: =ROUND(SUM(J76:J78),2) -> 541 | K81: =ROUND(SUM(K79:K80),2) -> 541 | L81: =IF(J81=K81,"<- Debits and Credits equal each other.","<- Debits and Credits do not equal each other.") -> <- Debits and Credits equal each other.
A83: 9 | B83: Record SBITA modifications to increase in the RTU SBITA asset.
B84: Dr: Acct 0480 - RIGHT-TO-USE SBITA - AMORTIZABLE
C85: Cr: Acct 0674 - RIGHT-TO-USE SBITA LIABILITY
J86: =SUM(J84) -> 0 | K86: =SUM(K85) -> 0 | L86: =IF(J86=K86,"<- Debits and Credits equal each other.","<- Debits and Credits do not equal each other.") -> <- Debits and Credits equal each other.
B88: NOTE: Please check the instructions for remeasurement and modifications on the SCO website.
D92: Informational - Ending Balances of Assets and Liabilities
K93: Debit (Credit)
D94: Acct 0480 - RIGHT-TO-USE SBITA - AMORTIZABLE | K94: =+J15+J34-K69-K79+J84 -> 635
D95: Acct 0475 - ACCUMULATED AMORTIZATION - RIGHT-TO-USE SBITA | K95: =-K18-K46+J68+J77 -> -141
D96: Acct 0674 - RIGHT-TO-USE SBITA LIABILITY | K96: =-K19-K37+J56+J61+J76-K85 -> -229
D97: Acct 0651 - RIGHT-TO-USE SBITA LIABILITY (CURRENT PORTION LT) | K97: =-K62 -> -199

Sheet Fund 0017 Journal Entries
A1: GASB 96 - SBITA Contracts Fund-by-Fund Journal Entries Form (to be submitted to the SCO annually—one form per fund)
A2: Manually complete every yellow field in this worksheet—there are no automatically calculated data-entry cells in this worksheet.
A3: Fiscal year: | F3: 2023–2024
A4: Organization Name: | F4: Department of Justice
A5: Organization Code (Business Unit): | F5: 0820
A6: Fund Number: | F6: 17
A7: Fund Type: | F7: Governmental Fund
A8: Fund Classification: | F8: =IF(OR($F$7='Drop Down Menus'!B2,$F$7='Drop Down Menus'!$B$3),'Drop Down Menus'!$D$9,IFERROR(VLOOKUP($F$5,GAAP02Aindex!$A$2:$D$900,4,FALSE),"Unidentified")) -> GENERAL GOVERNMENT
A12: =IF($F$3="2022–2023","Establish Beginning Balances (SBITAs commenced on or before 07/01/2022)","Establish Beginning Balances (existing SBITAs only)") -> Establish Beginning Balances (existing SBITAs only)
A13: Entry #
A14: 0 | B14: =IF($F$3="2022–2023","To establish the beginning balance of SBITAs as of 07/01/2022.","Roll forward prior year right-to-use SBITAs to record opening balances.") -> Roll forward prior year right-to-use SBITAs to record opening balances. | M14: Department Beginning Balances | P14: From SCO BB List | S14: Difference
B15: Dr: Acct 0480 - RIGHT-TO-USE SBITA - AMORTIZABLE | J15: =ROUND(M15,0) -> 332868 | M15: 332868 | P15: 332868 | S15: =M15-P15 -> 0 | T15: Report any "Differences" on the Report 18 Differential.
B16: Dr: Acct 0950 - BEGINNING FUND BALANCE | J16: =ROUND(P16,0) -> 0 | M16: 1123 | P16: =IF(SUM($Q$18:$Q$19)>$P$15,SUM($Q$18:$Q$19)-$P$15,0) -> 0 | S16: =M16-P16 -> 1123 | T16: No action required.
B17: Dr: Acct 0952 - BEG FB ADJ/PRIOR PERIOD ADJUSTMENT | J17: =ROUND(IF(SUM($K$18:$K$20)>SUM($J$15:$J$16),SUM($K$18:$K$20)-SUM($J$15:$J$16),0),0) -> 0 | S17: =M17-P17 -> 0 | T17: No action required.
C18: Cr. Acct 0475 - ACCUMULATED AMORTIZATION - RIGHT-TO-USE SBITA | K18: =ROUND(N18,0) -> 186858 | N18: 186858 | Q18: 186858 | S18: =N18-Q18 -> 0 | T18: No action required.
C19: Cr: Acct 0674 - RIGHT-TO-USE SBITA LIABILITY | K19: =ROUND(N19,0) -> 124913 | N19: 124913 | Q19: 124913 | S19: =N19-Q19 -> 0 | T19: No action required.
C20: Cr: Acct 0950 - BEGINNING FUND BALANCE | K20: =ROUND(Q20,0) -> 21097 | N20: 22220 | Q20: =IF(SUM($Q$18:$Q$19)<$P$15,-SUM($Q$18:$Q$19)+$P$15,0) -> 21097 | S20: =N20-Q20 -> 1123 | T20: No action required.
C21: Cr: Acct 0952 - BEG FB ADJ/PRIOR PERIOD ADJUSTMENT | K21: =ROUND(IF(SUM($K$18:$K$20)<SUM($J$15:$J$16),-SUM($K$18:$K$20)+SUM($J$15:$J$16),0),0) -> 0 | S21: =N21-Q21 -> 0 | T21: No action required.
J22: =ROUND(SUM(J15:J17),0) -> 332868 | K22: =ROUND(SUM(K18:K21),0) -> 332868 | L22: =IF(J22=K22,"<- Debits and Credits equal each other.","<- Debits and Credits do not equal each other.") -> <- Debits and Credits equal each other.
B24: SBITA ASSET (Acct 0480) AMOUNT SHOULD BE REPORTED AS BEGINNING BALANCE ON REPORT 18.
A26: =IF($F$3="2022–2023","Record SBITAs Commenced on or after 07/02/2022","Record New SBITAs (new SBITAs only)") -> Record New SBITAs (new SBITAs only)
A27: 1 | B27: Record at inception of SBITA in accordance with Fund-Based accounting (Governmental Funds Only).
B28: Dr: Acct 0842 - CAPITAL OUTLAY | J28: 897953
C29: Cr: Acct 0789 - LEASE AND OTHER FINANCING PROCEEDS | K29: 897953
C30: =VLOOKUP($F$8,'Drop Down Menus'!$D$2:$G$10,4,FALSE) -> Cr: Acct 0808 - GENERAL GOV. (GAAP ADJ)
J31: =ROUND(SUM(J28:J30),2) -> 897953 | K31: =ROUND(SUM(K28:K30),2) -> 897953 | L31: =IF(J31=K31,"<- Debits and Credits equal each other.","<- Debits and Credits do not equal each other.") -> <- Debits and Credits equal each other.
A33: 2 | B33: Reverse the fund-based entry in #1 above, if any, and record an inception of SBITA in accordance with GAAP Govt Wide.
B34: Dr: Acct 0480 - RIGHT-TO-USE SBITA - AMORTIZABLE | J34: 897953
B35: Dr: Acct 0789 - LEASE AND OTHER FINANCING PROCEEDS | J35: 897953
C36: Cr: Acct 0842 - CAPITAL OUTLAY | K36: 897953
C37: Cr: Acct 0674 - RIGHT-TO-USE SBITA LIABILITY | K37: 897953
C38: =VLOOKUP($F$8,'Drop Down Menus'!$D$2:$G$10,4,FALSE) -> Cr: Acct 0808 - GENERAL GOV. (GAAP ADJ)
J39: =ROUND(SUM(J34:J35),2) -> 1795906 | K39: =ROUND(SUM(K36:K38),2) -> 1795906 | L39: =IF(J39=K39,"<- Debits and Credits equal each other.","<- Debits and Credits do not equal each other.") -> <- Debits and Credits equal each other.
B41: SBITA ASSET (Acct 0480) AMOUNT SHOULD BE INCLUDED AS "ADDITIONS" ON REPORT 18.
A43: Record Annual Activity (all SBITAs)
A44: 3 | B44: Record amortization of the SBITA asset for the year.
B45: Dr: Acct 0875 - DEPRECIATION/AMORTIZATION | J45: 234418
C46: Cr. Acct 0475 - ACCUMULATED AMORTIZATION - RIGHT-TO-USE SBITA | K46: =J45 -> 234418
J47: =ROUND(SUM(J45:J45),2) -> 234418 | K47: =ROUND(SUM(K46),2) -> 234418 | L47: =IF(J47=K47,"<- Debits and Credits equal each other.","<- Debits and Credits do not equal each other.") -> <- Debits and Credits equal each other.
A49: 4 | B49: Reclassify information technology subscription exp. to debt service principal and interest exp.
B50: Dr: Acct 0848 - DEBT SERVICE - PRINCIPAL LEASES | J50: 319827 | L50: =IF($J$50=$K$57,"","<- Accts 0848 must agree")
B51: =IF(OR($F$7="Proprietary - Internal Service Fund",$F$7="Proprietary - Enterprise Fund"),"Dr: Acct 0894 - INTEREST EXPENSE AND FISCAL CHARGES","Dr: Acct 0851 - DEBT SERVICE - INTEREST LEASES") -> Dr: Acct 0851 - DEBT SERVICE - INTEREST LEASES | J51: 10837
C52: =VLOOKUP($F$8,'Drop Down Menus'!$D$2:$G$10,4,FALSE) -> Cr: Acct 0808 - GENERAL GOV. (GAAP ADJ) | K52: =+J50+J51 -> 330664
J53: =ROUND(SUM(J50:J51),2) -> 330664 | K53: =ROUND(SUM(K52,),2) -> 330664 | L53: =IF(J53=K53,"<- Debits and Credits equal each other.","<- Debits and Credits do not equal each other.") -> <- Debits and Credits equal each other.
A55: 5 | B55: Reduce SBITA liability for total current year principal payments.
B56: Dr: Acct 0674 - RIGHT-TO-USE SBITA LIABILITY | J56: 319827
C57: Cr: Acct 0848 - DEBT SERVICE - PRINCIPAL LEASES | K57: =J50 -> 319827 | L57: =IF($J$50=$K$57,"","<- Accts 0848 must agree")
J58: =ROUND(SUM(J56:J56),2) -> 319827 | K58: =ROUND(SUM(K57),2) -> 319827 | L58: =IF(J58=K58,"<- Debits and Credits equal each other.","<- Debits and Credits do not equal each other.") -> <- Debits and Credits equal each other.
A60: 6 | B60: Reclassify the principal amount due in the next FY to the current liability.
B61: Dr: Acct 0674 - RIGHT-TO-USE SBITA LIABILITY | J61: 317873
C62: Cr. Acct 0651 - RIGHT-TO-USE SBITA LIABILITY (CURRENT PORTION LT) | K62: =J61 -> 317873
B63: NOTE: This is an annual accrual. The RTU SBITA Liability - Current portion will be added back to the RTU SBITA Liability in entry #0 when reestablishing the beginning balances next year. | J63: =ROUND(SUM(J61:J61),2) -> 317873 | K63: =ROUND(SUM(K62),2) -> 317873 | L63: =IF(J63=K63,"<- Debits and Credits equal each other.","<- Debits and Credits do not equal each other.") -> <- Debits and Credits equal each other.
A66: Remove SBITA Asset at the End of the Subscription Term (only at the end of the subscription term)
A67: 7 | B67: Record entry to write off the SBITA asset and accumulated amortization at the end of the subscription term.
B68: Dr: Acct 0475 - ACCUMULATED AMORTIZATION - RIGHT-TO-USE SBITA | J68: 111102
C69: Cr: Acct 0480 - RIGHT-TO-USE SBITA - AMORTIZABLE | K69: 111102
J70: =SUM(J68) -> 111102 | K70: =SUM(K69) -> 111102 | L70: =IF(J70=K70,"<- Debits and Credits equal each other.","<- Debits and Credits do not equal each other.") -> <- Debits and Credits equal each other.
B72: SBITA ASSET (Acct 0480) SHOULD BE INCLUDED AS "DEDUCTIONS" ON REPORT 18.
A74: Record SBITA Remeasurement and Modifications (only if a significant modification occurred during the fiscal year)
A75: 8 | B75: Record early termination of SBITA contract or SBITA modifications to decrease in the RTU SBITA asset.
B76: Dr: Acct 0674 - RIGHT-TO-USE SBITA LIABILITY | J76: 21874
B77: Dr: Acct 0475 - ACCUMULATED AMORTIZATION - RIGHT-TO-USE SBITA | J77: 86628
B78: =VLOOKUP($F$8,'Drop Down Menus'!$D$2:$G$10,3,FALSE) -> Dr: Acct 0808 - GENERAL GOV. (GAAP ADJ)
C79: Cr: Acct 0480 - RIGHT-TO-USE SBITA - AMORTIZABLE | K79: 108286
C80: =VLOOKUP($F$8,'Drop Down Menus'!$D$2:$G$10,4,FALSE) -> Cr: Acct 0808 - GENERAL GOV. (GAAP ADJ) | K80: 216
J81: =ROUND(SUM(J76:J78),2) -> 108502 | K81: =ROUND(SUM(K79:K80),2) -> 108502 | L81: =IF(J81=K81,"<- Debits and Credits equal each other.","<- Debits and Credits do not equal each other.") -> <- Debits and Credits equal each other.
A83: 9 | B83: Record SBITA modifications to increase in the RTU SBITA asset.
B84: Dr: Acct 0480 - RIGHT-TO-USE SBITA - AMORTIZABLE
C85: Cr: Acct 0674 - RIGHT-TO-USE SBITA LIABILITY
J86: =SUM(J84) -> 0 | K86: =SUM(K85) -> 0 | L86: =IF(J86=K86,"<- Debits and Credits equal each other.","<- Debits and Credits do not equal each other.") -> <- Debits and Credits equal each other.
B88: NOTE: Please check the instructions for remeasurement and modifications on the SCO website.
D92: Informational - Ending Balances of Assets and Liabilities
K93: Debit (Credit)
D94: Acct 0480 - RIGHT-TO-USE SBITA - AMORTIZABLE | K94: =+J15+J34-K69-K79+J84 -> 1011433
D95: Acct 0475 - ACCUMULATED AMORTIZATION - RIGHT-TO-USE SBITA | K95: =-K18-K46+J68+J77 -> -223546
D96: Acct 0674 - RIGHT-TO-USE SBITA LIABILITY | K96: =-K19-K37+J56+J61+J76-K85 -> -363292
D97: Acct 0651 - RIGHT-TO-USE SBITA LIABILITY (CURRENT PORTION LT) | K97: =-K62 -> -317873

Sheet Fund 0044 Journal Entries
A1: GASB 96 - SBITA Contracts Fund-by-Fund Journal Entries Form (to be submitted to the SCO annually—one form per fund)
A2: Manually complete every yellow field in this worksheet—there are no automatically calculated data-entry cells in this worksheet.
A3: Fiscal year: | F3: 2023–2024
A4: Organization Name: | F4: Department of Justice
A5: Organization Code (Business Unit): | F5: 0820
A6: Fund Number: | F6: 44
A7: Fund Type: | F7: Governmental Fund
A8: Fund Classification: | F8: =IF(OR($F$7='Drop Down Menus'!B2,$F$7='Drop Down Menus'!$B$3),'Drop Down Menus'!$D$9,IFERROR(VLOOKUP($F$5,GAAP02Aindex!$A$2:$D$900,4,FALSE),"Unidentified")) -> GENERAL GOVERNMENT
A12: =IF($F$3="2022–2023","Establish Beginning Balances (SBITAs commenced on or before 07/01/2022)","Establish Beginning Balances (existing SBITAs only)") -> Establish Beginning Balances (existing SBITAs only)
A13: Entry #
A14: 0 | B14: =IF($F$3="2022–2023","To establish the beginning balance of SBITAs as of 07/01/2022.","Roll forward prior year right-to-use SBITAs to record opening balances.") -> Roll forward prior year right-to-use SBITAs to record opening balances. | M14: Department Beginning Balances | P14: From SCO BB List | S14: Difference
B15: Dr: Acct 0480 - RIGHT-TO-USE SBITA - AMORTIZABLE | J15: =ROUND(M15,0) -> 436045 | M15: 436045 | P15: 436045 | S15: =M15-P15 -> 0 | T15: Report any "Differences" on the Report 18 Differential.
B16: Dr: Acct 0950 - BEGINNING FUND BALANCE | J16: =ROUND(P16,0) -> 0 | M16: 1472 | P16: =IF(SUM($Q$18:$Q$19)>$P$15,SUM($Q$18:$Q$19)-$P$15,0) -> 0 | S16: =M16-P16 -> 1472 | T16: No action required.
B17: Dr: Acct 0952 - BEG FB ADJ/PRIOR PERIOD ADJUSTMENT | J17: =ROUND(IF(SUM($K$18:$K$20)>SUM($J$15:$J$16),SUM($K$18:$K$20)-SUM($J$15:$J$16),0),0) -> 0 | S17: =M17-P17 -> 0 | T17: No action required.
C18: Cr. Acct 0475 - ACCUMULATED AMORTIZATION - RIGHT-TO-USE SBITA | K18: =ROUND(N18,0) -> 244778 | N18: 244778 | Q18: 244778 | S18: =N18-Q18 -> 0 | T18: No action required.
C19: Cr: Acct 0674 - RIGHT-TO-USE SBITA LIABILITY | K19: =ROUND(N19,0) -> 163631 | N19: 163631 | Q19: 163631 | S19: =N19-Q19 -> 0 | T19: No action required.
C20: Cr: Acct 0950 - BEGINNING FUND BALANCE | K20: =ROUND(Q20,0) -> 27636 | N20: 29108 | Q20: =IF(SUM($Q$18:$Q$19)<$P$15,-SUM($Q$18:$Q$19)+$P$15,0) -> 27636 | S20: =N20-Q20 -> 1472 | T20: No action required.
C21: Cr: Acct 0952 - BEG FB ADJ/PRIOR PERIOD ADJUSTMENT | K21: =ROUND(IF(SUM($K$18:$K$20)<SUM($J$15:$J$16),-SUM($K$18:$K$20)+SUM($J$15:$J$16),0),0) -> 0 | S21: =N21-Q21 -> 0 | T21: No action required.
J22: =ROUND(SUM(J15:J17),0) -> 436045 | K22: =ROUND(SUM(K18:K21),0) -> 436045 | L22: =IF(J22=K22,"<- Debits and Credits equal each other.","<- Debits and Credits do not equal each other.") -> <- Debits and Credits equal each other.
B24: SBITA ASSET (Acct 0480) AMOUNT SHOULD BE REPORTED AS BEGINNING BALANCE ON REPORT 18.
A26: =IF($F$3="2022–2023","Record SBITAs Commenced on or after 07/02/2022","Record New SBITAs (new SBITAs only)") -> Record New SBITAs (new SBITAs only)
A27: 1 | B27: Record at inception of SBITA in accordance with Fund-Based accounting (Governmental Funds Only).
B28: Dr: Acct 0842 - CAPITAL OUTLAY | J28: 1089435
C29: Cr: Acct 0789 - LEASE AND OTHER FINANCING PROCEEDS | K29: 1089435
C30: =VLOOKUP($F$8,'Drop Down Menus'!$D$2:$G$10,4,FALSE) -> Cr: Acct 0808 - GENERAL GOV. (GAAP ADJ)
J31: =ROUND(SUM(J28:J30),2) -> 1089435 | K31: =ROUND(SUM(K28:K30),2) -> 1089435 | L31: =IF(J31=K31,"<- Debits and Credits equal each other.","<- Debits and Credits do not equal each other.") -> <- Debits and Credits equal each other.
A33: 2 | B33: Reverse the fund-based entry in #1 above, if any, and record an inception of SBITA in accordance with GAAP Govt Wide.
B34: Dr: Acct 0480 - RIGHT-TO-USE SBITA - AMORTIZABLE | J34: 1089435
B35: Dr: Acct 0789 - LEASE AND OTHER FINANCING PROCEEDS | J35: 1089435
C36: Cr: Acct 0842 - CAPITAL OUTLAY | K36: 1089435
C37: Cr: Acct 0674 - RIGHT-TO-USE SBITA LIABILITY | K37: 1089435
C38: =VLOOKUP($F$8,'Drop Down Menus'!$D$2:$G$10,4,FALSE) -> Cr: Acct 0808 - GENERAL GOV. (GAAP ADJ)
J39: =ROUND(SUM(J34:J35),2) -> 2178870 | K39: =ROUND(SUM(K36:K38),2) -> 2178870 | L39: =IF(J39=K39,"<- Debits and Credits equal each other.","<- Debits and Credits do not equal each other.") -> <- Debits and Credits equal each other.
B41: SBITA ASSET (Acct 0480) AMOUNT SHOULD BE INCLUDED AS "ADDITIONS" ON REPORT 18.
A43: Record Annual Activity (all SBITAs)
A44: 3 | B44: Record amortization of the SBITA asset for the year.
B45: Dr: Acct 0875 - DEPRECIATION/AMORTIZATION | J45: 288751
C46: Cr. Acct 0475 - ACCUMULATED AMORTIZATION - RIGHT-TO-USE SBITA | K46: =J45 -> 288751
J47: =ROUND(SUM(J45:J45),2) -> 288751 | K47: =ROUND(SUM(K46),2) -> 288751 | L47: =IF(J47=K47,"<- Debits and Credits equal each other.","<- Debits and Credits do not equal each other.") -> <- Debits and Credits equal each other.
A49: 4 | B49: Reclassify information technology subscription exp. to debt service principal and interest exp.
B50: Dr: Acct 0848 - DEBT SERVICE - PRINCIPAL LEASES | J50: 390080 | L50: =IF($J$50=$K$57,"","<- Accts 0848 must agree")
B51: =IF(OR($F$7="Proprietary - Internal Service Fund",$F$7="Proprietary - Enterprise Fund"),"Dr: Acct 0894 - INTEREST EXPENSE AND FISCAL CHARGES","Dr: Acct 0851 - DEBT SERVICE - INTEREST LEASES") -> Dr: Acct 0851 - DEBT SERVICE - INTEREST LEASES | J51: 13365
C52: =VLOOKUP($F$8,'Drop Down Menus'!$D$2:$G$10,4,FALSE) -> Cr: Acct 0808 - GENERAL GOV. (GAAP ADJ) | K52: =+J50+J51 -> 403445
J53: =ROUND(SUM(J50:J51),2) -> 403445 | K53: =ROUND(SUM(K52,),2) -> 403445 | L53: =IF(J53=K53,"<- Debits and Credits equal each other.","<- Debits and Credits do not equal each other.") -> <- Debits and Credits equal each other.
A55: 5 | B55: Reduce SBITA liability for total current year principal payments.
B56: Dr: Acct 0674 - RIGHT-TO-USE SBITA LIABILITY | J56: 390080
C57: Cr: Acct 0848 - DEBT SERVICE - PRINCIPAL LEASES | K57: =J50 -> 390080 | L57: =IF($J$50=$K$57,"","<- Accts 0848 must agree")
J58: =ROUND(SUM(J56:J56),2) -> 390080 | K58: =ROUND(SUM(K57),2) -> 390080 | L58: =IF(J58=K58,"<- Debits and Credits equal each other.","<- Debits and Credits do not equal each other.") -> <- Debits and Credits equal each other.
A60: 6 | B60: Reclassify the principal amount due in the next FY to the current liability.
B61: Dr: Acct 0674 - RIGHT-TO-USE SBITA LIABILITY | J61: 387798
C62: Cr. Acct 0651 - RIGHT-TO-USE SBITA LIABILITY (CURRENT PORTION LT) | K62: =J61 -> 387798
B63: NOTE: This is an annual accrual. The RTU SBITA Liability - Current portion will be added back to the RTU SBITA Liability in entry #0 when reestablishing the beginning balances next year. | J63: =ROUND(SUM(J61:J61),2) -> 387798 | K63: =ROUND(SUM(K62),2) -> 387798 | L63: =IF(J63=K63,"<- Debits and Credits equal each other.","<- Debits and Credits do not equal each other.") -> <- Debits and Credits equal each other.
A66: Remove SBITA Asset at the End of the Subscription Term (only at the end of the subscription term)
A67: 7 | B67: Record entry to write off the SBITA asset and accumulated amortization at the end of the subscription term.
B68: Dr: Acct 0475 - ACCUMULATED AMORTIZATION - RIGHT-TO-USE SBITA | J68: 145540
C69: Cr: Acct 0480 - RIGHT-TO-USE SBITA - AMORTIZABLE | K69: 145540
J70: =SUM(J68) -> 145540 | K70: =SUM(K69) -> 145540 | L70: =IF(J70=K70,"<- Debits and Credits equal each other.","<- Debits and Credits do not equal each other.") -> <- Debits and Credits equal each other.
B72: SBITA ASSET (Acct 0480) SHOULD BE INCLUDED AS "DEDUCTIONS" ON REPORT 18.
A74: Record SBITA Remeasurement and Modifications (only if a significant modification occurred during the fiscal year)
A75: 8 | B75: Record early termination of SBITA contract or SBITA modifications to decrease in the RTU SBITA asset.
B76: Dr: Acct 0674 - RIGHT-TO-USE SBITA LIABILITY | J76: 28654
B77: Dr: Acct 0475 - ACCUMULATED AMORTIZATION - RIGHT-TO-USE SBITA | J77: 113480
B78: =VLOOKUP($F$8,'Drop Down Menus'!$D$2:$G$10,3,FALSE) -> Dr: Acct 0808 - GENERAL GOV. (GAAP ADJ)
C79: Cr: Acct 0480 - RIGHT-TO-USE SBITA - AMORTIZABLE | K79: 141850
C80: =VLOOKUP($F$8,'Drop Down Menus'!$D$2:$G$10,4,FALSE) -> Cr: Acct 0808 - GENERAL GOV. (GAAP ADJ) | K80: 284
J81: =ROUND(SUM(J76:J78),2) -> 142134 | K81: =ROUND(SUM(K79:K80),2) -> 142134 | L81: =IF(J81=K81,"<- Debits and Credits equal each other.","<- Debits and Credits do not equal each other.") -> <- Debits and Credits equal each other.
A83: 9 | B83: Record SBITA modifications to increase in the RTU SBITA asset.
B84: Dr: Acct 0480 - RIGHT-TO-USE SBITA - AMORTIZABLE
C85: Cr: Acct 0674 - RIGHT-TO-USE SBITA LIABILITY
J86: =SUM(J84) -> 0 | K86: =SUM(K85) -> 0 | L86: =IF(J86=K86,"<- Debits and Credits equal each other.","<- Debits and Credits do not equal each other.") -> <- Debits and Credits equal each other.
B88: NOTE: Please check the instructions for remeasurement and modifications on the SCO website.
D92: Informational - Ending Balances of Assets and Liabilities
K93: Debit (Credit)
D94: Acct 0480 - RIGHT-TO-USE SBITA - AMORTIZABLE | K94: =+J15+J34-K69-K79+J84 -> 1238090
D95: Acct 0475 - ACCUMULATED AMORTIZATION - RIGHT-TO-USE SBITA | K95: =-K18-K46+J68+J77 -> -274509
D96: Acct 0674 - RIGHT-TO-USE SBITA LIABILITY | K96: =-K19-K37+J56+J61+J76-K85 -> -446534
D97: Acct 0651 - RIGHT-TO-USE SBITA LIABILITY (CURRENT PORTION LT) | K97: =-K62 -> -387798

Sheet Fund 0158 Journal Entries
A1: GASB 96 - SBITA Contracts Fund-by-Fund Journal Entries Form (to be submitted to the SCO annually—one form per fund)
A2: Manually complete every yellow field in this worksheet—there are no automatically calculated data-entry cells in this worksheet.
A3: Fiscal year: | F3: 2023–2024
A4: Organization Name: | F4: Department of Justice
A5: Organization Code (Business Unit): | F5: 0820
A6: Fund Number: | F6: 158
A7: Fund Type: | F7: Governmental Fund
A8: Fund Classification: | F8: =IF(OR($F$7='Drop Down Menus'!B2,$F$7='Drop Down Menus'!$B$3),'Drop Down Menus'!$D$9,IFERROR(VLOOKUP($F$5,GAAP02Aindex!$A$2:$D$900,4,FALSE),"Unidentified")) -> GENERAL GOVERNMENT
A12: =IF($F$3="2022–2023","Establish Beginning Balances (SBITAs commenced on or before 07/01/2022)","Establish Beginning Balances (existing SBITAs only)") -> Establish Beginning Balances (existing SBITAs only)
A13: Entry #
A14: 0 | B14: =IF($F$3="2022–2023","To establish the beginning balance of SBITAs as of 07/01/2022.","Roll forward prior year right-to-use SBITAs to record opening balances.") -> Roll forward prior year right-to-use SBITAs to record opening balances. | M14: Department Beginning Balances | P14: From SCO BB List | S14: Difference
B15: Dr: Acct 0480 - RIGHT-TO-USE SBITA - AMORTIZABLE | J15: =ROUND(M15,0) -> 211 | M15: 211 | P15: 211 | S15: =M15-P15 -> 0 | T15: Report any "Differences" on the Report 18 Differential.
B16: Dr: Acct 0950 - BEGINNING FUND BALANCE | J16: =ROUND(P16,0) -> 0 | M16: 1 | P16: =IF(SUM($Q$18:$Q$19)>$P$15,SUM($Q$18:$Q$19)-$P$15,0) -> 0 | S16: =M16-P16 -> 1 | T16: No action required.
B17: Dr: Acct 0952 - BEG FB ADJ/PRIOR PERIOD ADJUSTMENT | J17: =ROUND(IF(SUM($K$18:$K$20)>SUM($J$15:$J$16),SUM($K$18:$K$20)-SUM($J$15:$J$16),0),0) -> 0 | S17: =M17-P17 -> 0 | T17: No action required.
C18: Cr. Acct 0475 - ACCUMULATED AMORTIZATION - RIGHT-TO-USE SBITA | K18: =ROUND(N18,0) -> 119 | N18: 119 | Q18: 119 | S18: =N18-Q18 -> 0 | T18: No action required.
C19: Cr: Acct 0674 - RIGHT-TO-USE SBITA LIABILITY | K19: =ROUND(N19,0) -> 79 | N19: 79 | Q19: 79 | S19: =N19-Q19 -> 0 | T19: No action required.
C20: Cr: Acct 0950 - BEGINNING FUND BALANCE | K20: =ROUND(Q20,0) -> 13 | N20: 14 | Q20: =IF(SUM($Q$18:$Q$19)<$P$15,-SUM($Q$18:$Q$19)+$P$15,0) -> 13 | S20: =N20-Q20 -> 1 | T20: No action required.
C21: Cr: Acct 0952 - BEG FB ADJ/PRIOR PERIOD ADJUSTMENT | K21: =ROUND(IF(SUM($K$18:$K$20)<SUM($J$15:$J$16),-SUM($K$18:$K$20)+SUM($J$15:$J$16),0),0) -> 0 | S21: =N21-Q21 -> 0 | T21: No action required.
J22: =ROUND(SUM(J15:J17),0) -> 211 | K22: =ROUND(SUM(K18:K21),0) -> 211 | L22: =IF(J22=K22,"<- Debits and Credits equal each other.","<- Debits and Credits do not equal each other.") -> <- Debits and Credits equal each other.
B24: SBITA ASSET (Acct 0480) AMOUNT SHOULD BE REPORTED AS BEGINNING BALANCE ON REPORT 18.
A26: =IF($F$3="2022–2023","Record SBITAs Commenced on or after 07/02/2022","Record New SBITAs (new SBITAs only)") -> Record New SBITAs (new SBITAs only)
A27: 1 | B27: Record at inception of SBITA in accordance with Fund-Based accounting (Governmental Funds Only).
B28: Dr: Acct 0842 - CAPITAL OUTLAY | J28: 517
C29: Cr: Acct 0789 - LEASE AND OTHER FINANCING PROCEEDS | K29: 517
C30: =VLOOKUP($F$8,'Drop Down Menus'!$D$2:$G$10,4,FALSE) -> Cr: Acct 0808 - GENERAL GOV. (GAAP ADJ)
J31: =ROUND(SUM(J28:J30),2) -> 517 | K31: =ROUND(SUM(K28:K30),2) -> 517 | L31: =IF(J31=K31,"<- Debits and Credits equal each other.","<- Debits and Credits do not equal each other.") -> <- Debits and Credits equal each other.
A33: 2 | B33: Reverse the fund-based entry in #1 above, if any, and record an inception of SBITA in accordance with GAAP Govt Wide.
B34: Dr: Acct 0480 - RIGHT-TO-USE SBITA - AMORTIZABLE | J34: 517
B35: Dr: Acct 0789 - LEASE AND OTHER FINANCING PROCEEDS | J35: 517
C36: Cr: Acct 0842 - CAPITAL OUTLAY | K36: 517
C37: Cr: Acct 0674 - RIGHT-TO-USE SBITA LIABILITY | K37: 517
C38: =VLOOKUP($F$8,'Drop Down Menus'!$D$2:$G$10,4,FALSE) -> Cr: Acct 0808 - GENERAL GOV. (GAAP ADJ)
J39: =ROUND(SUM(J34:J35),2) -> 1034 | K39: =ROUND(SUM(K36:K38),2) -> 1034 | L39: =IF(J39=K39,"<- Debits and Credits equal each other.","<- Debits and Credits do not equal each other.") -> <- Debits and Credits equal each other.
B41: SBITA ASSET (Acct 0480) AMOUNT SHOULD BE INCLUDED AS "ADDITIONS" ON REPORT 18.
A43: Record Annual Activity (all SBITAs)
A44: 3 | B44: Record amortization of the SBITA asset for the year.
B45: Dr: Acct 0875 - DEPRECIATION/AMORTIZATION | J45: 138
C46: Cr. Acct 0475 - ACCUMULATED AMORTIZATION - RIGHT-TO-USE SBITA | K46: =J45 -> 138
J47: =ROUND(SUM(J45:J45),2) -> 138 | K47: =ROUND(SUM(K46),2) -> 138 | L47: =IF(J47=K47,"<- Debits and Credits equal each other.","<- Debits and Credits do not equal each other.") -> <- Debits and Credits equal each other.
A49: 4 | B49: Reclassify information technology subscription exp. to debt service principal and interest exp.
B50: Dr: Acct 0848 - DEBT SERVICE - PRINCIPAL LEASES | J50: 185 | L50: =IF($J$50=$K$57,"","<- Accts 0848 must agree")
B51: =IF(OR($F$7="Proprietary - Internal Service Fund",$F$7="Proprietary - Enterprise Fund"),"Dr: Acct 0894 - INTEREST EXPENSE AND FISCAL CHARGES","Dr: Acct 0851 - DEBT SERVICE - INTEREST LEASES") -> Dr: Acct 0851 - DEBT SERVICE - INTEREST LEASES | J51: 6
C52: =VLOOKUP($F$8,'Drop Down Menus'!$D$2:$G$10,4,FALSE) -> Cr: Acct 0808 - GENERAL GOV. (GAAP ADJ) | K52: =+J50+J51 -> 191
J53: =ROUND(SUM(J50:J51),2) -> 191 | K53: =ROUND(SUM(K52,),2) -> 191 | L53: =IF(J53=K53,"<- Debits and Credits equal each other.","<- Debits and Credits do not equal each other.") -> <- Debits and Credits equal each other.
A55: 5 | B55: Reduce SBITA liability for total current year principal payments.
B56: Dr: Acct 0674 - RIGHT-TO-USE SBITA LIABILITY | J56: 185
C57: Cr: Acct 0848 - DEBT SERVICE - PRINCIPAL LEASES | K57: =J50 -> 185 | L57: =IF($J$50=$K$57,"","<- Accts 0848 must agree")
J58: =ROUND(SUM(J56:J56),2) -> 185 | K58: =ROUND(SUM(K57),2) -> 185 | L58: =IF(J58=K58,"<- Debits and Credits equal each other.","<- Debits and Credits do not equal each other.") -> <- Debits and Credits equal each other.
A60: 6 | B60: Reclassify the principal amount due in the next FY to the current liability.
B61: Dr: Acct 0674 - RIGHT-TO-USE SBITA LIABILITY | J61: 184
C62: Cr. Acct 0651 - RIGHT-TO-USE SBITA LIABILITY (CURRENT PORTION LT) | K62: =J61 -> 184
B63: NOTE: This is an annual accrual. The RTU SBITA Liability - Current portion will be added back to the RTU SBITA Liability in entry #0 when reestablishing the beginning balances next year. | J63: =ROUND(SUM(J61:J61),2) -> 184 | K63: =ROUND(SUM(K62),2) -> 184 | L63: =IF(J63=K63,"<- Debits and Credits equal each other.","<- Debits and Credits do not equal each other.") -> <- Debits and Credits equal each other.
A66: Remove SBITA Asset at the End of the Subscription Term (only at the end of the subscription term)
A67: 7 | B67: Record entry to write off the SBITA asset and accumulated amortization at the end of the subscription term.
B68: Dr: Acct 0475 - ACCUMULATED AMORTIZATION - RIGHT-TO-USE SBITA | J68: 71
C69: Cr: Acct 0480 - RIGHT-TO-USE SBITA - AMORTIZABLE | K69: 71
J70: =SUM(J68) -> 71 | K70: =SUM(K69) -> 71 | L70: =IF(J70=K70,"<- Debits and Credits equal each other.","<- Debits and Credits do not equal each other.") -> <- Debits and Credits equal each other.
B72: SBITA ASSET (Acct 0480) SHOULD BE INCLUDED AS "DEDUCTIONS" ON REPORT 18.
A74: Record SBITA Remeasurement and Modifications (only if a significant modification occurred during the fiscal year)
A75: 8 | B75: Record early termination of SBITA contract or SBITA modifications to decrease in the RTU SBITA asset.
B76: Dr: Acct 0674 - RIGHT-TO-USE SBITA LIABILITY | J76: 14
B77: Dr: Acct 0475 - ACCUMULATED AMORTIZATION - RIGHT-TO-USE SBITA | J77: 55
B78: =VLOOKUP($F$8,'Drop Down Menus'!$D$2:$G$10,3,FALSE) -> Dr: Acct 0808 - GENERAL GOV. (GAAP ADJ)
C79: Cr: Acct 0480 - RIGHT-TO-USE SBITA - AMORTIZABLE | K79: 69
C80: =VLOOKUP($F$8,'Drop Down Menus'!$D$2:$G$10,4,FALSE) -> Cr: Acct 0808 - GENERAL GOV. (GAAP ADJ)
J81: =ROUND(SUM(J76:J78),2) -> 69 | K81: =ROUND(SUM(K79:K80),2) -> 69 | L81: =IF(J81=K81,"<- Debits and Credits equal each other.","<- Debits and Credits do not equal each other.") -> <- Debits and Credits equal each other.
A83: 9 | B83: Record SBITA modifications to increase in the RTU SBITA asset.
B84: Dr: Acct 0480 - RIGHT-TO-USE SBITA - AMORTIZABLE
C85: Cr: Acct 0674 - RIGHT-TO-USE SBITA LIABILITY
J86: =SUM(J84) -> 0 | K86: =SUM(K85) -> 0 | L86: =IF(J86=K86,"<- Debits and Credits equal each other.","<- Debits and Credits do not equal each other.") -> <- Debits and Credits equal each other.
B88: NOTE: Please check the instructions for remeasurement and modifications on the SCO website.
D92: Informational - Ending Balances of Assets and Liabilities
K93: Debit (Credit)
D94: Acct 0480 - RIGHT-TO-USE SBITA - AMORTIZABLE | K94: =+J15+J34-K69-K79+J84 -> 588
D95: Acct 0475 - ACCUMULATED AMORTIZATION - RIGHT-TO-USE SBITA | K95: =-K18-K46+J68+J77 -> -131
D96: Acct 0674 - RIGHT-TO-USE SBITA LIABILITY | K96: =-K19-K37+J56+J61+J76-K85 -> -213
D97: Acct 0651 - RIGHT-TO-USE SBITA LIABILITY (CURRENT PORTION LT) | K97: =-K62 -> -184

Sheet Fund 0367 Journal Entries
A1: GASB 96 - SBITA Contracts Fund-by-Fund Journal Entries Form (to be submitted to the SCO annually—one form per fund)
A2: Manually complete every yellow field in this worksheet—there are no automatically calculated data-entry cells in this worksheet.
A3: Fiscal year: | F3: 2023–2024
A4: Organization Name: | F4: Department of Justice
A5: Organization Code (Business Unit): | F5: 0820
A6: Fund Number: | F6: 367
A7: Fund Type: | F7: Governmental Fund
A8: Fund Classification: | F8: =IF(OR($F$7='Drop Down Menus'!B2,$F$7='Drop Down Menus'!$B$3),'Drop Down Menus'!$D$9,IFERROR(VLOOKUP($F$5,GAAP02Aindex!$A$2:$D$900,4,FALSE),"Unidentified")) -> GENERAL GOVERNMENT
A12: =IF($F$3="2022–2023","Establish Beginning Balances (SBITAs commenced on or before 07/01/2022)","Establish Beginning Balances (existing SBITAs only)") -> Establish Beginning Balances (existing SBITAs only)
A13: Entry #
A14: 0 | B14: =IF($F$3="2022–2023","To establish the beginning balance of SBITAs as of 07/01/2022.","Roll forward prior year right-to-use SBITAs to record opening balances.") -> Roll forward prior year right-to-use SBITAs to record opening balances. | M14: Department Beginning Balances | P14: From SCO BB List | S14: Difference
B15: Dr: Acct 0480 - RIGHT-TO-USE SBITA - AMORTIZABLE | J15: =ROUND(M15,0) -> 287750 | M15: 287750 | P15: 287750 | S15: =M15-P15 -> 0 | T15: Report any "Differences" on the Report 18 Differential.
B16: Dr: Acct 0950 - BEGINNING FUND BALANCE | J16: =ROUND(P16,0) -> 1500 | M16: 1954 | P16: =IF(SUM($Q$18:$Q$19)>$P$15,SUM($Q$18:$Q$19)-$P$15,0) -> 1500 | S16: =M16-P16 -> 454 | T16: No action required.
B17: Dr: Acct 0952 - BEG FB ADJ/PRIOR PERIOD ADJUSTMENT | J17: =ROUND(IF(SUM($K$18:$K$20)>SUM($J$15:$J$16),SUM($K$18:$K$20)-SUM($J$15:$J$16),0),0) -> 0 | S17: =M17-P17 -> 0 | T17: No action required.
C18: Cr. Acct 0475 - ACCUMULATED AMORTIZATION - RIGHT-TO-USE SBITA | K18: =ROUND(N18,0) -> 99336 | N18: 99336 | Q18: 99336 | S18: =N18-Q18 -> 0 | T18: No action required.
C19: Cr: Acct 0674 - RIGHT-TO-USE SBITA LIABILITY | K19: =ROUND(N19,0) -> 189914 | N19: 189914 | Q19: 189914 | S19: =N19-Q19 -> 0 | T19: No action required.
C20: Cr: Acct 0950 - BEGINNING FUND BALANCE | K20: =ROUND(Q20,0) -> 0 | N20: 454 | Q20: =IF(SUM($Q$18:$Q$19)<$P$15,-SUM($Q$18:$Q$19)+$P$15,0) -> 0 | S20: =N20-Q20 -> 454 | T20: No action required.
C21: Cr: Acct 0952 - BEG FB ADJ/PRIOR PERIOD ADJUSTMENT | K21: =ROUND(IF(SUM($K$18:$K$20)<SUM($J$15:$J$16),-SUM($K$18:$K$20)+SUM($J$15:$J$16),0),0) -> 0 | S21: =N21-Q21 -> 0 | T21: No action required.
J22: =ROUND(SUM(J15:J17),0) -> 289250 | K22: =ROUND(SUM(K18:K21),0) -> 289250 | L22: =IF(J22=K22,"<- Debits and Credits equal each other.","<- Debits and Credits do not equal each other.") -> <- Debits and Credits equal each other.
B24: SBITA ASSET (Acct 0480) AMOUNT SHOULD BE REPORTED AS BEGINNING BALANCE ON REPORT 18.
A26: =IF($F$3="2022–2023","Record SBITAs Commenced on or after 07/02/2022","Record New SBITAs (new SBITAs only)") -> Record New SBITAs (new SBITAs only)
A27: 1 | B27: Record at inception of SBITA in accordance with Fund-Based accounting (Governmental Funds Only).
B28: Dr: Acct 0842 - CAPITAL OUTLAY | J28: 72854
C29: Cr: Acct 0789 - LEASE AND OTHER FINANCING PROCEEDS | K29: 72854
C30: =VLOOKUP($F$8,'Drop Down Menus'!$D$2:$G$10,4,FALSE) -> Cr: Acct 0808 - GENERAL GOV. (GAAP ADJ)
J31: =ROUND(SUM(J28:J30),2) -> 72854 | K31: =ROUND(SUM(K28:K30),2) -> 72854 | L31: =IF(J31=K31,"<- Debits and Credits equal each other.","<- Debits and Credits do not equal each other.") -> <- Debits and Credits equal each other.
A33: 2 | B33: Reverse the fund-based entry in #1 above, if any, and record an inception of SBITA in accordance with GAAP Govt Wide.
B34: Dr: Acct 0480 - RIGHT-TO-USE SBITA - AMORTIZABLE | J34: 72854
B35: Dr: Acct 0789 - LEASE AND OTHER FINANCING PROCEEDS | J35: 72854
C36: Cr: Acct 0842 - CAPITAL OUTLAY | K36: 72854
C37: Cr: Acct 0674 - RIGHT-TO-USE SBITA LIABILITY | K37: 72854
C38: =VLOOKUP($F$8,'Drop Down Menus'!$D$2:$G$10,4,FALSE) -> Cr: Acct 0808 - GENERAL GOV. (GAAP ADJ)
J39: =ROUND(SUM(J34:J35),2) -> 145708 | K39: =ROUND(SUM(K36:K38),2) -> 145708 | L39: =IF(J39=K39,"<- Debits and Credits equal each other.","<- Debits and Credits do not equal each other.") -> <- Debits and Credits equal each other.
B41: SBITA ASSET (Acct 0480) AMOUNT SHOULD BE INCLUDED AS "ADDITIONS" ON REPORT 18.
A43: Record Annual Activity (all SBITAs)
A44: 3 | B44: Record amortization of the SBITA asset for the year.
B45: Dr: Acct 0875 - DEPRECIATION/AMORTIZATION | J45: 21905
C46: Cr. Acct 0475 - ACCUMULATED AMORTIZATION - RIGHT-TO-USE SBITA | K46: =J45 -> 21905
J47: =ROUND(SUM(J45:J45),2) -> 21905 | K47: =ROUND(SUM(K46),2) -> 21905 | L47: =IF(J47=K47,"<- Debits and Credits equal each other.","<- Debits and Credits do not equal each other.") -> <- Debits and Credits equal each other.
A49: 4 | B49: Reclassify information technology subscription exp. to debt service principal and interest exp.
B50: Dr: Acct 0848 - DEBT SERVICE - PRINCIPAL LEASES | J50: 30422 | L50: =IF($J$50=$K$57,"","<- Accts 0848 must agree")
B51: =IF(OR($F$7="Proprietary - Internal Service Fund",$F$7="Proprietary - Enterprise Fund"),"Dr: Acct 0894 - INTEREST EXPENSE AND FISCAL CHARGES","Dr: Acct 0851 - DEBT SERVICE - INTEREST LEASES") -> Dr: Acct 0851 - DEBT SERVICE - INTEREST LEASES | J51: 883
C52: =VLOOKUP($F$8,'Drop Down Menus'!$D$2:$G$10,4,FALSE) -> Cr: Acct 0808 - GENERAL GOV. (GAAP ADJ) | K52: =+J50+J51 -> 31305
J53: =ROUND(SUM(J50:J51),2) -> 31305 | K53: =ROUND(SUM(K52,),2) -> 31305 | L53: =IF(J53=K53,"<- Debits and Credits equal each other.","<- Debits and Credits do not equal each other.") -> <- Debits and Credits equal each other.
A55: 5 | B55: Reduce SBITA liability for total current year principal payments.
B56: Dr: Acct 0674 - RIGHT-TO-USE SBITA LIABILITY | J56: 30422
C57: Cr: Acct 0848 - DEBT SERVICE - PRINCIPAL LEASES | K57: =J50 -> 30422 | L57: =IF($J$50=$K$57,"","<- Accts 0848 must agree")
J58: =ROUND(SUM(J56:J56),2) -> 30422 | K58: =ROUND(SUM(K57),2) -> 30422 | L58: =IF(J58=K58,"<- Debits and Credits equal each other.","<- Debits and Credits do not equal each other.") -> <- Debits and Credits equal each other.
A60: 6 | B60: Reclassify the principal amount due in the next FY to the current liability.
B61: Dr: Acct 0674 - RIGHT-TO-USE SBITA LIABILITY | J61: 24445
C62: Cr. Acct 0651 - RIGHT-TO-USE SBITA LIABILITY (CURRENT PORTION LT) | K62: =J61 -> 24445
B63: NOTE: This is an annual accrual. The RTU SBITA Liability - Current portion will be added back to the RTU SBITA Liability in entry #0 when reestablishing the beginning balances next year. | J63: =ROUND(SUM(J61:J61),2) -> 24445 | K63: =ROUND(SUM(K62),2) -> 24445 | L63: =IF(J63=K63,"<- Debits and Credits equal each other.","<- Debits and Credits do not equal each other.") -> <- Debits and Credits equal each other.
A66: Remove SBITA Asset at the End of the Subscription Term (only at the end of the subscription term)
A67: 7 | B67: Record entry to write off the SBITA asset and accumulated amortization at the end of the subscription term.
B68: Dr: Acct 0475 - ACCUMULATED AMORTIZATION - RIGHT-TO-USE SBITA | J68: 13494
C69: Cr: Acct 0480 - RIGHT-TO-USE SBITA - AMORTIZABLE | K69: 13494
J70: =SUM(J68) -> 13494 | K70: =SUM(K69) -> 13494 | L70: =IF(J70=K70,"<- Debits and Credits equal each other.","<- Debits and Credits do not equal each other.") -> <- Debits and Credits equal each other.
B72: SBITA ASSET (Acct 0480) SHOULD BE INCLUDED AS "DEDUCTIONS" ON REPORT 18.
A74: Record SBITA Remeasurement and Modifications (only if a significant modification occurred during the fiscal year)
A75: 8 | B75: Record early termination of SBITA contract or SBITA modifications to decrease in the RTU SBITA asset.
B76: Dr: Acct 0674 - RIGHT-TO-USE SBITA LIABILITY | J76: 182051
B77: Dr: Acct 0475 - ACCUMULATED AMORTIZATION - RIGHT-TO-USE SBITA | J77: 91678
B78: =VLOOKUP($F$8,'Drop Down Menus'!$D$2:$G$10,3,FALSE) -> Dr: Acct 0808 - GENERAL GOV. (GAAP ADJ)
C79: Cr: Acct 0480 - RIGHT-TO-USE SBITA - AMORTIZABLE | K79: 271940
C80: =VLOOKUP($F$8,'Drop Down Menus'!$D$2:$G$10,4,FALSE) -> Cr: Acct 0808 - GENERAL GOV. (GAAP ADJ) | K80: 1789
J81: =ROUND(SUM(J76:J78),2) -> 273729 | K81: =ROUND(SUM(K79:K80),2) -> 273729 | L81: =IF(J81=K81,"<- Debits and Credits equal each other.","<- Debits and Credits do not equal each other.") -> <- Debits and Credits equal each other.
A83: 9 | B83: Record SBITA modifications to increase in the RTU SBITA asset.
B84: Dr: Acct 0480 - RIGHT-TO-USE SBITA - AMORTIZABLE
C85: Cr: Acct 0674 - RIGHT-TO-USE SBITA LIABILITY
J86: =SUM(J84) -> 0 | K86: =SUM(K85) -> 0 | L86: =IF(J86=K86,"<- Debits and Credits equal each other.","<- Debits and Credits do not equal each other.") -> <- Debits and Credits equal each other.
B88: NOTE: Please check the instructions for remeasurement and modifications on the SCO website.
D92: Informational - Ending Balances of Assets and Liabilities
K93: Debit (Credit)
D94: Acct 0480 - RIGHT-TO-USE SBITA - AMORTIZABLE | K94: =+J15+J34-K69-K79+J84 -> 75170
D95: Acct 0475 - ACCUMULATED AMORTIZATION - RIGHT-TO-USE SBITA | K95: =-K18-K46+J68+J77 -> -16069
D96: Acct 0674 - RIGHT-TO-USE SBITA LIABILITY | K96: =-K19-K37+J56+J61+J76-K85 -> -25850
D97: Acct 0651 - RIGHT-TO-USE SBITA LIABILITY (CURRENT PORTION LT) | K97: =-K62 -> -24445

Sheet Fund 0378 Journal Entries
A1: GASB 96 - SBITA Contracts Fund-by-Fund Journal Entries Form (to be submitted to the SCO annually—one form per fund)
A2: Manually complete every yellow field in this worksheet—there are no automatically calculated data-entry cells in this worksheet.
A3: Fiscal year: | F3: 2023–2024
A4: Organization Name: | F4: Department of Justice
A5: Organization Code (Business Unit): | F5: 0820
A6: Fund Number: | F6: 378
A7: Fund Type: | F7: Governmental Fund
A8: Fund Classification: | F8: =IF(OR($F$7='Drop Down Menus'!B2,$F$7='Drop Down Menus'!$B$3),'Drop Down Menus'!$D$9,IFERROR(VLOOKUP($F$5,GAAP02Aindex!$A$2:$D$900,4,FALSE),"Unidentified")) -> GENERAL GOVERNMENT
A12: =IF($F$3="2022–2023","Establish Beginning Balances (SBITAs commenced on or before 07/01/2022)","Establish Beginning Balances (existing SBITAs only)") -> Establish Beginning Balances (existing SBITAs only)
A13: Entry #
A14: 0 | B14: =IF($F$3="2022–2023","To establish the beginning balance of SBITAs as of 07/01/2022.","Roll forward prior year right-to-use SBITAs to record opening balances.") -> Roll forward prior year right-to-use SBITAs to record opening balances. | M14: Department Beginning Balances | P14: From SCO BB List | S14: Difference
B15: Dr: Acct 0480 - RIGHT-TO-USE SBITA - AMORTIZABLE | J15: =ROUND(M15,0) -> 14455 | M15: 14455 | P15: 14455 | S15: =M15-P15 -> 0 | T15: Report any "Differences" on the Report 18 Differential.
B16: Dr: Acct 0950 - BEGINNING FUND BALANCE | J16: =ROUND(P16,0) -> 0 | M16: 88 | P16: =IF(SUM($Q$18:$Q$19)>$P$15,SUM($Q$18:$Q$19)-$P$15,0) -> 0 | S16: =M16-P16 -> 88 | T16: No action required.
B17: Dr: Acct 0952 - BEG FB ADJ/PRIOR PERIOD ADJUSTMENT | J17: =ROUND(IF(SUM($K$18:$K$20)>SUM($J$15:$J$16),SUM($K$18:$K$20)-SUM($J$15:$J$16),0),0) -> 0 | S17: =M17-P17 -> 0 | T17: No action required.
C18: Cr. Acct 0475 - ACCUMULATED AMORTIZATION - RIGHT-TO-USE SBITA | K18: =ROUND(N18,0) -> 7866 | N18: 7866 | Q18: 7866 | S18: =N18-Q18 -> 0 | T18: No action required.
C19: Cr: Acct 0674 - RIGHT-TO-USE SBITA LIABILITY | K19: =ROUND(N19,0) -> 5983 | N19: 5983 | Q19: 5983 | S19: =N19-Q19 -> 0 | T19: No action required.
C20: Cr: Acct 0950 - BEGINNING FUND BALANCE | K20: =ROUND(Q20,0) -> 606 | N20: 694 | Q20: =IF(SUM($Q$18:$Q$19)<$P$15,-SUM($Q$18:$Q$19)+$P$15,0) -> 606 | S20: =N20-Q20 -> 88 | T20: No action required.
C21: Cr: Acct 0952 - BEG FB ADJ/PRIOR PERIOD ADJUSTMENT | K21: =ROUND(IF(SUM($K$18:$K$20)<SUM($J$15:$J$16),-SUM($K$18:$K$20)+SUM($J$15:$J$16),0),0) -> 0 | S21: =N21-Q21 -> 0 | T21: No action required.
J22: =ROUND(SUM(J15:J17),0) -> 14455 | K22: =ROUND(SUM(K18:K21),0) -> 14455 | L22: =IF(J22=K22,"<- Debits and Credits equal each other.","<- Debits and Credits do not equal each other.") -> <- Debits and Credits equal each other.
B24: SBITA ASSET (Acct 0480) AMOUNT SHOULD BE REPORTED AS BEGINNING BALANCE ON REPORT 18.
A26: =IF($F$3="2022–2023","Record SBITAs Commenced on or after 07/02/2022","Record New SBITAs (new SBITAs only)") -> Record New SBITAs (new SBITAs only)
A27: 1 | B27: Record at inception of SBITA in accordance with Fund-Based accounting (Governmental Funds Only).
B28: Dr: Acct 0842 - CAPITAL OUTLAY | J28: 26207
C29: Cr: Acct 0789 - LEASE AND OTHER FINANCING PROCEEDS | K29: 26207
C30: =VLOOKUP($F$8,'Drop Down Menus'!$D$2:$G$10,4,FALSE) -> Cr: Acct 0808 - GENERAL GOV. (GAAP ADJ)
J31: =ROUND(SUM(J28:J30),2) -> 26207 | K31: =ROUND(SUM(K28:K30),2) -> 26207 | L31: =IF(J31=K31,"<- Debits and Credits equal each other.","<- Debits and Credits do not equal each other.") -> <- Debits and Credits equal each other.
A33: 2 | B33: Reverse the fund-based entry in #1 above, if any, and record an inception of SBITA in accordance with GAAP Govt Wide.
B34: Dr: Acct 0480 - RIGHT-TO-USE SBITA - AMORTIZABLE | J34: 26207
B35: Dr: Acct 0789 - LEASE AND OTHER FINANCING PROCEEDS | J35: 26207
C36: Cr: Acct 0842 - CAPITAL OUTLAY | K36: 26207
C37: Cr: Acct 0674 - RIGHT-TO-USE SBITA LIABILITY | K37: 26207
C38: =VLOOKUP($F$8,'Drop Down Menus'!$D$2:$G$10,4,FALSE) -> Cr: Acct 0808 - GENERAL GOV. (GAAP ADJ)
J39: =ROUND(SUM(J34:J35),2) -> 52414 | K39: =ROUND(SUM(K36:K38),2) -> 52414 | L39: =IF(J39=K39,"<- Debits and Credits equal each other.","<- Debits and Credits do not equal each other.") -> <- Debits and Credits equal each other.
B41: SBITA ASSET (Acct 0480) AMOUNT SHOULD BE INCLUDED AS "ADDITIONS" ON REPORT 18.
A43: Record Annual Activity (all SBITAs)
A44: 3 | B44: Record amortization of the SBITA asset for the year.
B45: Dr: Acct 0875 - DEPRECIATION/AMORTIZATION | J45: 8959
C46: Cr. Acct 0475 - ACCUMULATED AMORTIZATION - RIGHT-TO-USE SBITA | K46: =J45 -> 8959
J47: =ROUND(SUM(J45:J45),2) -> 8959 | K47: =ROUND(SUM(K46),2) -> 8959 | L47: =IF(J47=K47,"<- Debits and Credits equal each other.","<- Debits and Credits do not equal each other.") -> <- Debits and Credits equal each other.
A49: 4 | B49: Reclassify information technology subscription exp. to debt service principal and interest exp.
B50: Dr: Acct 0848 - DEBT SERVICE - PRINCIPAL LEASES | J50: 11456 | L50: =IF($J$50=$K$57,"","<- Accts 0848 must agree")
B51: =IF(OR($F$7="Proprietary - Internal Service Fund",$F$7="Proprietary - Enterprise Fund"),"Dr: Acct 0894 - INTEREST EXPENSE AND FISCAL CHARGES","Dr: Acct 0851 - DEBT SERVICE - INTEREST LEASES") -> Dr: Acct 0851 - DEBT SERVICE - INTEREST LEASES | J51: 371
C52: =VLOOKUP($F$8,'Drop Down Menus'!$D$2:$G$10,4,FALSE) -> Cr: Acct 0808 - GENERAL GOV. (GAAP ADJ) | K52: =+J50+J51 -> 11827
J53: =ROUND(SUM(J50:J51),2) -> 11827 | K53: =ROUND(SUM(K52,),2) -> 11827 | L53: =IF(J53=K53,"<- Debits and Credits equal each other.","<- Debits and Credits do not equal each other.") -> <- Debits and Credits equal each other.
A55: 5 | B55: Reduce SBITA liability for total current year principal payments.
B56: Dr: Acct 0674 - RIGHT-TO-USE SBITA LIABILITY | J56: 11456
C57: Cr: Acct 0848 - DEBT SERVICE - PRINCIPAL LEASES | K57: =J50 -> 11456 | L57: =IF($J$50=$K$57,"","<- Accts 0848 must agree")
J58: =ROUND(SUM(J56:J56),2) -> 11456 | K58: =ROUND(SUM(K57),2) -> 11456 | L58: =IF(J58=K58,"<- Debits and Credits equal each other.","<- Debits and Credits do not equal each other.") -> <- Debits and Credits equal each other.
A60: 6 | B60: Reclassify the principal amount due in the next FY to the current liability.
B61: Dr: Acct 0674 - RIGHT-TO-USE SBITA LIABILITY | J61: 9323
C62: Cr. Acct 0651 - RIGHT-TO-USE SBITA LIABILITY (CURRENT PORTION LT) | K62: =J61 -> 9323
B63: NOTE: This is an annual accrual. The RTU SBITA Liability - Current portion will be added back to the RTU SBITA Liability in entry #0 when reestablishing the beginning balances next year. | J63: =ROUND(SUM(J61:J61),2) -> 9323 | K63: =ROUND(SUM(K62),2) -> 9323 | L63: =IF(J63=K63,"<- Debits and Credits equal each other.","<- Debits and Credits do not equal each other.") -> <- Debits and Credits equal each other.
A66: Remove SBITA Asset at the End of the Subscription Term (only at the end of the subscription term)
A67: 7 | B67: Record entry to write off the SBITA asset and accumulated amortization at the end of the subscription term.
B68: Dr: Acct 0475 - ACCUMULATED AMORTIZATION - RIGHT-TO-USE SBITA | J68: 7522
C69: Cr: Acct 0480 - RIGHT-TO-USE SBITA - AMORTIZABLE | K69: 7522
J70: =SUM(J68) -> 7522 | K70: =SUM(K69) -> 7522 | L70: =IF(J70=K70,"<- Debits and Credits equal each other.","<- Debits and Credits do not equal each other.") -> <- Debits and Credits equal each other.
B72: SBITA ASSET (Acct 0480) SHOULD BE INCLUDED AS "DEDUCTIONS" ON REPORT 18.
A74: Record SBITA Remeasurement and Modifications (only if a significant modification occurred during the fiscal year)
A75: 8 | B75: Record early termination of SBITA contract or SBITA modifications to decrease in the RTU SBITA asset.
B76: Dr: Acct 0674 - RIGHT-TO-USE SBITA LIABILITY | J76: 684
B77: Dr: Acct 0475 - ACCUMULATED AMORTIZATION - RIGHT-TO-USE SBITA | J77: 2708
B78: =VLOOKUP($F$8,'Drop Down Menus'!$D$2:$G$10,3,FALSE) -> Dr: Acct 0808 - GENERAL GOV. (GAAP ADJ)
C79: Cr: Acct 0480 - RIGHT-TO-USE SBITA - AMORTIZABLE | K79: 3385
C80: =VLOOKUP($F$8,'Drop Down Menus'!$D$2:$G$10,4,FALSE) -> Cr: Acct 0808 - GENERAL GOV. (GAAP ADJ) | K80: 7
J81: =ROUND(SUM(J76:J78),2) -> 3392 | K81: =ROUND(SUM(K79:K80),2) -> 3392 | L81: =IF(J81=K81,"<- Debits and Credits equal each other.","<- Debits and Credits do not equal each other.") -> <- Debits and Credits equal each other.
A83: 9 | B83: Record SBITA modifications to increase in the RTU SBITA asset.
B84: Dr: Acct 0480 - RIGHT-TO-USE SBITA - AMORTIZABLE
C85: Cr: Acct 0674 - RIGHT-TO-USE SBITA LIABILITY
J86: =SUM(J84) -> 0 | K86: =SUM(K85) -> 0 | L86: =IF(J86=K86,"<- Debits and Credits equal each other.","<- Debits and Credits do not equal each other.") -> <- Debits and Credits equal each other.
B88: NOTE: Please check the instructions for remeasurement and modifications on the SCO website.
D92: Informational - Ending Balances of Assets and Liabilities
K93: Debit (Credit)
D94: Acct 0480 - RIGHT-TO-USE SBITA - AMORTIZABLE | K94: =+J15+J34-K69-K79+J84 -> 29755
D95: Acct 0475 - ACCUMULATED AMORTIZATION - RIGHT-TO-USE SBITA | K95: =-K18-K46+J68+J77 -> -6595
D96: Acct 0674 - RIGHT-TO-USE SBITA LIABILITY | K96: =-K19-K37+J56+J61+J76-K85 -> -10727
D97: Acct 0651 - RIGHT-TO-USE SBITA LIABILITY (CURRENT PORTION LT) | K97: =-K62 -> -9323

Sheet Fund 0460 Journal Entries
A1: GASB 96 - SBITA Contracts Fund-by-Fund Journal Entries Form (to be submitted to the SCO annually—one form per fund)
A2: Manually complete every yellow field in this worksheet—there are no automatically calculated data-entry cells in this worksheet.
A3: Fiscal year: | F3: 2023–2024
A4: Organization Name: | F4: Department of Justice
A5: Organization Code (Business Unit): | F5: 0820
A6: Fund Number: | F6: 460
A7: Fund Type: | F7: Governmental Fund
A8: Fund Classification: | F8: =IF(OR($F$7='Drop Down Menus'!B2,$F$7='Drop Down Menus'!$B$3),'Drop Down Menus'!$D$9,IFERROR(VLOOKUP($F$5,GAAP02Aindex!$A$2:$D$900,4,FALSE),"Unidentified")) -> GENERAL GOVERNMENT
A12: =IF($F$3="2022–2023","Establish Beginning Balances (SBITAs commenced on or before 07/01/2022)","Establish Beginning Balances (existing SBITAs only)") -> Establish Beginning Balances (existing SBITAs only)
A13: Entry #
A14: 0 | B14: =IF($F$3="2022–2023","To establish the beginning balance of SBITAs as of 07/01/2022.","Roll forward prior year right-to-use SBITAs to record opening balances.") -> Roll forward prior year right-to-use SBITAs to record opening balances. | M14: Department Beginning Balances | P14: From SCO BB List | S14: Difference
B15: Dr: Acct 0480 - RIGHT-TO-USE SBITA - AMORTIZABLE | J15: =ROUND(M15,0) -> 184476 | M15: 184476 | P15: 184476 | S15: =M15-P15 -> 0 | T15: Report any "Differences" on the Report 18 Differential.
B16: Dr: Acct 0950 - BEGINNING FUND BALANCE | J16: =ROUND(P16,0) -> 0 | M16: 627 | P16: =IF(SUM($Q$18:$Q$19)>$P$15,SUM($Q$18:$Q$19)-$P$15,0) -> 0 | S16: =M16-P16 -> 627 | T16: No action required.
B17: Dr: Acct 0952 - BEG FB ADJ/PRIOR PERIOD ADJUSTMENT | J17: =ROUND(IF(SUM($K$18:$K$20)>SUM($J$15:$J$16),SUM($K$18:$K$20)-SUM($J$15:$J$16),0),0) -> 0 | S17: =M17-P17 -> 0 | T17: No action required.
C18: Cr. Acct 0475 - ACCUMULATED AMORTIZATION - RIGHT-TO-USE SBITA | K18: =ROUND(N18,0) -> 103526 | N18: 103526 | Q18: 103526 | S18: =N18-Q18 -> 0 | T18: No action required.
C19: Cr: Acct 0674 - RIGHT-TO-USE SBITA LIABILITY | K19: =ROUND(N19,0) -> 69297 | N19: 69297 | Q19: 69297 | S19: =N19-Q19 -> 0 | T19: No action required.
C20: Cr: Acct 0950 - BEGINNING FUND BALANCE | K20: =ROUND(Q20,0) -> 11653 | N20: 12280 | Q20: =IF(SUM($Q$18:$Q$19)<$P$15,-SUM($Q$18:$Q$19)+$P$15,0) -> 11653 | S20: =N20-Q20 -> 627 | T20: No action required.
C21: Cr: Acct 0952 - BEG FB ADJ/PRIOR PERIOD ADJUSTMENT | K21: =ROUND(IF(SUM($K$18:$K$20)<SUM($J$15:$J$16),-SUM($K$18:$K$20)+SUM($J$15:$J$16),0),0) -> 0 | S21: =N21-Q21 -> 0 | T21: No action required.
J22: =ROUND(SUM(J15:J17),0) -> 184476 | K22: =ROUND(SUM(K18:K21),0) -> 184476 | L22: =IF(J22=K22,"<- Debits and Credits equal each other.","<- Debits and Credits do not equal each other.") -> <- Debits and Credits equal each other.
B24: SBITA ASSET (Acct 0480) AMOUNT SHOULD BE REPORTED AS BEGINNING BALANCE ON REPORT 18.
A26: =IF($F$3="2022–2023","Record SBITAs Commenced on or after 07/02/2022","Record New SBITAs (new SBITAs only)") -> Record New SBITAs (new SBITAs only)
A27: 1 | B27: Record at inception of SBITA in accordance with Fund-Based accounting (Governmental Funds Only).
B28: Dr: Acct 0842 - CAPITAL OUTLAY | J28: 385309
C29: Cr: Acct 0789 - LEASE AND OTHER FINANCING PROCEEDS | K29: 385309
C30: =VLOOKUP($F$8,'Drop Down Menus'!$D$2:$G$10,4,FALSE) -> Cr: Acct 0808 - GENERAL GOV. (GAAP ADJ)
J31: =ROUND(SUM(J28:J30),2) -> 385309 | K31: =ROUND(SUM(K28:K30),2) -> 385309 | L31: =IF(J31=K31,"<- Debits and Credits equal each other.","<- Debits and Credits do not equal each other.") -> <- Debits and Credits equal each other.
A33: 2 | B33: Reverse the fund-based entry in #1 above, if any, and record an inception of SBITA in accordance with GAAP Govt Wide.
B34: Dr: Acct 0480 - RIGHT-TO-USE SBITA - AMORTIZABLE | J34: 385309
B35: Dr: Acct 0789 - LEASE AND OTHER FINANCING PROCEEDS | J35: 385309
C36: Cr: Acct 0842 - CAPITAL OUTLAY | K36: 385309
C37: Cr: Acct 0674 - RIGHT-TO-USE SBITA LIABILITY | K37: 385309
C38: =VLOOKUP($F$8,'Drop Down Menus'!$D$2:$G$10,4,FALSE) -> Cr: Acct 0808 - GENERAL GOV. (GAAP ADJ)
J39: =ROUND(SUM(J34:J35),2) -> 770618 | K39: =ROUND(SUM(K36:K38),2) -> 770618 | L39: =IF(J39=K39,"<- Debits and Credits equal each other.","<- Debits and Credits do not equal each other.") -> <- Debits and Credits equal each other.
B41: SBITA ASSET (Acct 0480) AMOUNT SHOULD BE INCLUDED AS "ADDITIONS" ON REPORT 18.
A43: Record Annual Activity (all SBITAs)
A44: 3 | B44: Record amortization of the SBITA asset for the year.
B45: Dr: Acct 0875 - DEPRECIATION/AMORTIZATION | J45: 106395
C46: Cr. Acct 0475 - ACCUMULATED AMORTIZATION - RIGHT-TO-USE SBITA | K46: =J45 -> 106395
J47: =ROUND(SUM(J45:J45),2) -> 106395 | K47: =ROUND(SUM(K46),2) -> 106395 | L47: =IF(J47=K47,"<- Debits and Credits equal each other.","<- Debits and Credits do not equal each other.") -> <- Debits and Credits equal each other.
A49: 4 | B49: Reclassify information technology subscription exp. to debt service principal and interest exp.
B50: Dr: Acct 0848 - DEBT SERVICE - PRINCIPAL LEASES | J50: 140121 | L50: =IF($J$50=$K$57,"","<- Accts 0848 must agree")
B51: =IF(OR($F$7="Proprietary - Internal Service Fund",$F$7="Proprietary - Enterprise Fund"),"Dr: Acct 0894 - INTEREST EXPENSE AND FISCAL CHARGES","Dr: Acct 0851 - DEBT SERVICE - INTEREST LEASES") -> Dr: Acct 0851 - DEBT SERVICE - INTEREST LEASES | J51: 4933
C52: =VLOOKUP($F$8,'Drop Down Menus'!$D$2:$G$10,4,FALSE) -> Cr: Acct 0808 - GENERAL GOV. (GAAP ADJ) | K52: =+J50+J51 -> 145054
J53: =ROUND(SUM(J50:J51),2) -> 145054 | K53: =ROUND(SUM(K52,),2) -> 145054 | L53: =IF(J53=K53,"<- Debits and Credits equal each other.","<- Debits and Credits do not equal each other.") -> <- Debits and Credits equal each other.
A55: 5 | B55: Reduce SBITA liability for total current year principal payments.
B56: Dr: Acct 0674 - RIGHT-TO-USE SBITA LIABILITY | J56: 140121
C57: Cr: Acct 0848 - DEBT SERVICE - PRINCIPAL LEASES | K57: =J50 -> 140121 | L57: =IF($J$50=$K$57,"","<- Accts 0848 must agree")
J58: =ROUND(SUM(J56:J56),2) -> 140121 | K58: =ROUND(SUM(K57),2) -> 140121 | L58: =IF(J58=K58,"<- Debits and Credits equal each other.","<- Debits and Credits do not equal each other.") -> <- Debits and Credits equal each other.
A60: 6 | B60: Reclassify the principal amount due in the next FY to the current liability.
B61: Dr: Acct 0674 - RIGHT-TO-USE SBITA LIABILITY | J61: 139134
C62: Cr. Acct 0651 - RIGHT-TO-USE SBITA LIABILITY (CURRENT PORTION LT) | K62: =J61 -> 139134
B63: NOTE: This is an annual accrual. The RTU SBITA Liability - Current portion will be added back to the RTU SBITA Liability in entry #0 when reestablishing the beginning balances next year. | J63: =ROUND(SUM(J61:J61),2) -> 139134 | K63: =ROUND(SUM(K62),2) -> 139134 | L63: =IF(J63=K63,"<- Debits and Credits equal each other.","<- Debits and Credits do not equal each other.") -> <- Debits and Credits equal each other.
A66: Remove SBITA Asset at the End of the Subscription Term (only at the end of the subscription term)
A67: 7 | B67: Record entry to write off the SBITA asset and accumulated amortization at the end of the subscription term.
B68: Dr: Acct 0475 - ACCUMULATED AMORTIZATION - RIGHT-TO-USE SBITA | J68: 61915
C69: Cr: Acct 0480 - RIGHT-TO-USE SBITA - AMORTIZABLE | K69: 61915
J70: =SUM(J68) -> 61915 | K70: =SUM(K69) -> 61915 | L70: =IF(J70=K70,"<- Debits and Credits equal each other.","<- Debits and Credits do not equal each other.") -> <- Debits and Credits equal each other.
B72: SBITA ASSET (Acct 0480) SHOULD BE INCLUDED AS "DEDUCTIONS" ON REPORT 18.
A74: Record SBITA Remeasurement and Modifications (only if a significant modification occurred during the fiscal year)
A75: 8 | B75: Record early termination of SBITA contract or SBITA modifications to decrease in the RTU SBITA asset.
B76: Dr: Acct 0674 - RIGHT-TO-USE SBITA LIABILITY | J76: 12089
B77: Dr: Acct 0475 - ACCUMULATED AMORTIZATION - RIGHT-TO-USE SBITA | J77: 47876
B78: =VLOOKUP($F$8,'Drop Down Menus'!$D$2:$G$10,3,FALSE) -> Dr: Acct 0808 - GENERAL GOV. (GAAP ADJ)
C79: Cr: Acct 0480 - RIGHT-TO-USE SBITA - AMORTIZABLE | K79: 59846
C80: =VLOOKUP($F$8,'Drop Down Menus'!$D$2:$G$10,4,FALSE) -> Cr: Acct 0808 - GENERAL GOV. (GAAP ADJ) | K80: 119
J81: =ROUND(SUM(J76:J78),2) -> 59965 | K81: =ROUND(SUM(K79:K80),2) -> 59965 | L81: =IF(J81=K81,"<- Debits and Credits equal each other.","<- Debits and Credits do not equal each other.") -> <- Debits and Credits equal each other.
A83: 9 | B83: Record SBITA modifications to increase in the RTU SBITA asset.
B84: Dr: Acct 0480 - RIGHT-TO-USE SBITA - AMORTIZABLE
C85: Cr: Acct 0674 - RIGHT-TO-USE SBITA LIABILITY
J86: =SUM(J84) -> 0 | K86: =SUM(K85) -> 0 | L86: =IF(J86=K86,"<- Debits and Credits equal each other.","<- Debits and Credits do not equal each other.") -> <- Debits and Credits equal each other.
B88: NOTE: Please check the instructions for remeasurement and modifications on the SCO website.
D92: Informational - Ending Balances of Assets and Liabilities
K93: Debit (Credit)
D94: Acct 0480 - RIGHT-TO-USE SBITA - AMORTIZABLE | K94: =+J15+J34-K69-K79+J84 -> 448024
D95: Acct 0475 - ACCUMULATED AMORTIZATION - RIGHT-TO-USE SBITA | K95: =-K18-K46+J68+J77 -> -100130
D96: Acct 0674 - RIGHT-TO-USE SBITA LIABILITY | K96: =-K19-K37+J56+J61+J76-K85 -> -163262
D97: Acct 0651 - RIGHT-TO-USE SBITA LIABILITY (CURRENT PORTION LT) | K97: =-K62 -> -139134

Sheet Fund 0567 Journal Entries
A1: GASB 96 - SBITA Contracts Fund-by-Fund Journal Entries Form (to be submitted to the SCO annually—one form per fund)
A2: Manually complete every yellow field in this worksheet—there are no automatically calculated data-entry cells in this worksheet.
A3: Fiscal year: | F3: 2023–2024
A4: Organization Name: | F4: Department of Justice
A5: Organization Code (Business Unit): | F5: 0820
A6: Fund Number: | F6: 567
A7: Fund Type: | F7: Governmental Fund
A8: Fund Classification: | F8: =IF(OR($F$7='Drop Down Menus'!B2,$F$7='Drop Down Menus'!$B$3),'Drop Down Menus'!$D$9,IFERROR(VLOOKUP($F$5,GAAP02Aindex!$A$2:$D$900,4,FALSE),"Unidentified")) -> GENERAL GOVERNMENT
A12: =IF($F$3="2022–2023","Establish Beginning Balances (SBITAs commenced on or before 07/01/2022)","Establish Beginning Balances (existing SBITAs only)") -> Establish Beginning Balances (existing SBITAs only)
A13: Entry #
A14: 0 | B14: =IF($F$3="2022–2023","To establish the beginning balance of SBITAs as of 07/01/2022.","Roll forward prior year right-to-use SBITAs to record opening balances.") -> Roll forward prior year right-to-use SBITAs to record opening balances. | M14: Department Beginning Balances | P14: From SCO BB List | S14: Difference
B15: Dr: Acct 0480 - RIGHT-TO-USE SBITA - AMORTIZABLE | J15: =ROUND(M15,0) -> 145210 | M15: 145210 | P15: 145210 | S15: =M15-P15 -> 0 | T15: Report any "Differences" on the Report 18 Differential.
B16: Dr: Acct 0950 - BEGINNING FUND BALANCE | J16: =ROUND(P16,0) -> 1038 | M16: 1038 | P16: =IF(SUM($Q$18:$Q$19)>$P$15,SUM($Q$18:$Q$19)-$P$15,0) -> 1038 | S16: =M16-P16 -> 0 | T16: No action required.
B17: Dr: Acct 0952 - BEG FB ADJ/PRIOR PERIOD ADJUSTMENT | J17: =ROUND(IF(SUM($K$18:$K$20)>SUM($J$15:$J$16),SUM($K$18:$K$20)-SUM($J$15:$J$16),0),0) -> 0 | S17: =M17-P17 -> 0 | T17: No action required.
C18: Cr. Acct 0475 - ACCUMULATED AMORTIZATION - RIGHT-TO-USE SBITA | K18: =ROUND(N18,0) -> 50401 | N18: 50401 | Q18: 50401 | S18: =N18-Q18 -> 0 | T18: No action required.
C19: Cr: Acct 0674 - RIGHT-TO-USE SBITA LIABILITY | K19: =ROUND(N19,0) -> 95847 | N19: 95847 | Q19: 95847 | S19: =N19-Q19 -> 0 | T19: No action required.
C20: Cr: Acct 0950 - BEGINNING FUND BALANCE | K20: =ROUND(Q20,0) -> 0 | Q20: =IF(SUM($Q$18:$Q$19)<$P$15,-SUM($Q$18:$Q$19)+$P$15,0) -> 0 | S20: =N20-Q20 -> 0 | T20: No action required.
C21: Cr: Acct 0952 - BEG FB ADJ/PRIOR PERIOD ADJUSTMENT | K21: =ROUND(IF(SUM($K$18:$K$20)<SUM($J$15:$J$16),-SUM($K$18:$K$20)+SUM($J$15:$J$16),0),0) -> 0 | S21: =N21-Q21 -> 0 | T21: No action required.
J22: =ROUND(SUM(J15:J17),0) -> 146248 | K22: =ROUND(SUM(K18:K21),0) -> 146248 | L22: =IF(J22=K22,"<- Debits and Credits equal each other.","<- Debits and Credits do not equal each other.") -> <- Debits and Credits equal each other.
B24: SBITA ASSET (Acct 0480) AMOUNT SHOULD BE REPORTED AS BEGINNING BALANCE ON REPORT 18.
A26: =IF($F$3="2022–2023","Record SBITAs Commenced on or after 07/02/2022","Record New SBITAs (new SBITAs only)") -> Record New SBITAs (new SBITAs only)
A27: 1 | B27: Record at inception of SBITA in accordance with Fund-Based accounting (Governmental Funds Only).
B28: Dr: Acct 0842 - CAPITAL OUTLAY
C29: Cr: Acct 0789 - LEASE AND OTHER FINANCING PROCEEDS
C30: =VLOOKUP($F$8,'Drop Down Menus'!$D$2:$G$10,4,FALSE) -> Cr: Acct 0808 - GENERAL GOV. (GAAP ADJ)
J31: =ROUND(SUM(J28:J30),2) -> 0 | K31: =ROUND(SUM(K28:K30),2) -> 0 | L31: =IF(J31=K31,"<- Debits and Credits equal each other.","<- Debits and Credits do not equal each other.") -> <- Debits and Credits equal each other.
A33: 2 | B33: Reverse the fund-based entry in #1 above, if any, and record an inception of SBITA in accordance with GAAP Govt Wide.
B34: Dr: Acct 0480 - RIGHT-TO-USE SBITA - AMORTIZABLE
B35: Dr: Acct 0789 - LEASE AND OTHER FINANCING PROCEEDS
C36: Cr: Acct 0842 - CAPITAL OUTLAY
C37: Cr: Acct 0674 - RIGHT-TO-USE SBITA LIABILITY
C38: =VLOOKUP($F$8,'Drop Down Menus'!$D$2:$G$10,4,FALSE) -> Cr: Acct 0808 - GENERAL GOV. (GAAP ADJ)
J39: =ROUND(SUM(J34:J35),2) -> 0 | K39: =ROUND(SUM(K36:K38),2) -> 0 | L39: =IF(J39=K39,"<- Debits and Credits equal each other.","<- Debits and Credits do not equal each other.") -> <- Debits and Credits equal each other.
B41: SBITA ASSET (Acct 0480) AMOUNT SHOULD BE INCLUDED AS "ADDITIONS" ON REPORT 18.
A43: Record Annual Activity (all SBITAs)
A44: 3 | B44: Record amortization of the SBITA asset for the year.
B45: Dr: Acct 0875 - DEPRECIATION/AMORTIZATION | J45: 5993
C46: Cr. Acct 0475 - ACCUMULATED AMORTIZATION - RIGHT-TO-USE SBITA | K46: =J45 -> 5993
J47: =ROUND(SUM(J45:J45),2) -> 5993 | K47: =ROUND(SUM(K46),2) -> 5993 | L47: =IF(J47=K47,"<- Debits and Credits equal each other.","<- Debits and Credits do not equal each other.") -> <- Debits and Credits equal each other.
A49: 4 | B49: Reclassify information technology subscription exp. to debt service principal and interest exp.
B50: Dr: Acct 0848 - DEBT SERVICE - PRINCIPAL LEASES | J50: 6149 | L50: =IF($J$50=$K$57,"","<- Accts 0848 must agree")
B51: =IF(OR($F$7="Proprietary - Internal Service Fund",$F$7="Proprietary - Enterprise Fund"),"Dr: Acct 0894 - INTEREST EXPENSE AND FISCAL CHARGES","Dr: Acct 0851 - DEBT SERVICE - INTEREST LEASES") -> Dr: Acct 0851 - DEBT SERVICE - INTEREST LEASES | J51: 149
C52: =VLOOKUP($F$8,'Drop Down Menus'!$D$2:$G$10,4,FALSE) -> Cr: Acct 0808 - GENERAL GOV. (GAAP ADJ) | K52: 6298
J53: =ROUND(SUM(J50:J51),2) -> 6298 | K53: =ROUND(SUM(K52,),2) -> 6298 | L53: =IF(J53=K53,"<- Debits and Credits equal each other.","<- Debits and Credits do not equal each other.") -> <- Debits and Credits equal each other.
A55: 5 | B55: Reduce SBITA liability for total current year principal payments.
B56: Dr: Acct 0674 - RIGHT-TO-USE SBITA LIABILITY | J56: 6149
C57: Cr: Acct 0848 - DEBT SERVICE - PRINCIPAL LEASES | K57: =J50 -> 6149 | L57: =IF($J$50=$K$57,"","<- Accts 0848 must agree")
J58: =ROUND(SUM(J56:J56),2) -> 6149 | K58: =ROUND(SUM(K57),2) -> 6149 | L58: =IF(J58=K58,"<- Debits and Credits equal each other.","<- Debits and Credits do not equal each other.") -> <- Debits and Credits equal each other.
A60: 6 | B60: Reclassify the principal amount due in the next FY to the current liability.
B61: Dr: Acct 0674 - RIGHT-TO-USE SBITA LIABILITY
C62: Cr. Acct 0651 - RIGHT-TO-USE SBITA LIABILITY (CURRENT PORTION LT) | K62: =J61 -> 0
B63: NOTE: This is an annual accrual. The RTU SBITA Liability - Current portion will be added back to the RTU SBITA Liability in entry #0 when reestablishing the beginning balances next year. | J63: =ROUND(SUM(J61:J61),2) -> 0 | K63: =ROUND(SUM(K62),2) -> 0 | L63: =IF(J63=K63,"<- Debits and Credits equal each other.","<- Debits and Credits do not equal each other.") -> <- Debits and Credits equal each other.
A66: Remove SBITA Asset at the End of the Subscription Term (only at the end of the subscription term)
A67: 7 | B67: Record entry to write off the SBITA asset and accumulated amortization at the end of the subscription term.
B68: Dr: Acct 0475 - ACCUMULATED AMORTIZATION - RIGHT-TO-USE SBITA | J68: 11985
C69: Cr: Acct 0480 - RIGHT-TO-USE SBITA - AMORTIZABLE | K69: 11985
J70: =SUM(J68) -> 11985 | K70: =SUM(K69) -> 11985 | L70: =IF(J70=K70,"<- Debits and Credits equal each other.","<- Debits and Credits do not equal each other.") -> <- Debits and Credits equal each other.
B72: SBITA ASSET (Acct 0480) SHOULD BE INCLUDED AS "DEDUCTIONS" ON REPORT 18.
A74: Record SBITA Remeasurement and Modifications (only if a significant modification occurred during the fiscal year)
A75: 8 | B75: Record early termination of SBITA contract or SBITA modifications to decrease in the RTU SBITA asset.
B76: Dr: Acct 0674 - RIGHT-TO-USE SBITA LIABILITY | J76: 89698
B77: Dr: Acct 0475 - ACCUMULATED AMORTIZATION - RIGHT-TO-USE SBITA | J77: 44409
B78: =VLOOKUP($F$8,'Drop Down Menus'!$D$2:$G$10,3,FALSE) -> Dr: Acct 0808 - GENERAL GOV. (GAAP ADJ)
C79: Cr: Acct 0480 - RIGHT-TO-USE SBITA - AMORTIZABLE | K79: 133225
C80: =VLOOKUP($F$8,'Drop Down Menus'!$D$2:$G$10,4,FALSE) -> Cr: Acct 0808 - GENERAL GOV. (GAAP ADJ) | K80: 882
J81: =ROUND(SUM(J76:J78),2) -> 134107 | K81: =ROUND(SUM(K79:K80),2) -> 134107 | L81: =IF(J81=K81,"<- Debits and Credits equal each other.","<- Debits and Credits do not equal each other.") -> <- Debits and Credits equal each other.
A83: 9 | B83: Record SBITA modifications to increase in the RTU SBITA asset.
B84: Dr: Acct 0480 - RIGHT-TO-USE SBITA - AMORTIZABLE
C85: Cr: Acct 0674 - RIGHT-TO-USE SBITA LIABILITY
J86: =SUM(J84) -> 0 | K86: =SUM(K85) -> 0 | L86: =IF(J86=K86,"<- Debits and Credits equal each other.","<- Debits and Credits do not equal each other.") -> <- Debits and Credits equal each other.
B88: NOTE: Please check the instructions for remeasurement and modifications on the SCO website.
D92: Informational - Ending Balances of Assets and Liabilities
K93: Debit (Credit)
D94: Acct 0480 - RIGHT-TO-USE SBITA - AMORTIZABLE | K94: =+J15+J34-K69-K79+J84 -> 0
D95: Acct 0475 - ACCUMULATED AMORTIZATION - RIGHT-TO-USE SBITA | K95: =-K18-K46+J68+J77 -> 0
D96: Acct 0674 - RIGHT-TO-USE SBITA LIABILITY | K96: =-K19-K37+J56+J61+J76-K85 -> 0
D97: Acct 0651 - RIGHT-TO-USE SBITA LIABILITY (CURRENT PORTION LT) | K97: =-K62 -> 0

Sheet Fund 0569 Journal Entries
A1: GASB 96 - SBITA Contracts Fund-by-Fund Journal Entries Form (to be submitted to the SCO annually—one form per fund)
A2: Manually complete every yellow field in this worksheet—there are no automatically calculated data-entry cells in this worksheet.
A3: Fiscal year: | F3: 2023–2024
A4: Organization Name: | F4: Department of Justice
A5: Organization Code (Business Unit): | F5: 0820
A6: Fund Number: | F6: 569
A7: Fund Type: | F7: Governmental Fund
A8: Fund Classification: | F8: =IF(OR($F$7='Drop Down Menus'!B2,$F$7='Drop Down Menus'!$B$3),'Drop Down Menus'!$D$9,IFERROR(VLOOKUP($F$5,GAAP02Aindex!$A$2:$D$900,4,FALSE),"Unidentified")) -> GENERAL GOVERNMENT
A12: =IF($F$3="2022–2023","Establish Beginning Balances (SBITAs commenced on or before 07/01/2022)","Establish Beginning Balances (existing SBITAs only)") -> Establish Beginning Balances (existing SBITAs only)
A13: Entry #
A14: 0 | B14: =IF($F$3="2022–2023","To establish the beginning balance of SBITAs as of 07/01/2022.","Roll forward prior year right-to-use SBITAs to record opening balances.") -> Roll forward prior year right-to-use SBITAs to record opening balances. | M14: Department Beginning Balances | P14: From SCO BB List | S14: Difference
B15: Dr: Acct 0480 - RIGHT-TO-USE SBITA - AMORTIZABLE | J15: =ROUND(M15,0) -> 18449 | M15: 18449 | P15: 18449 | S15: =M15-P15 -> 0 | T15: Report any "Differences" on the Report 18 Differential.
B16: Dr: Acct 0950 - BEGINNING FUND BALANCE | J16: =ROUND(P16,0) -> 0 | M16: 71 | P16: =IF(SUM($Q$18:$Q$19)>$P$15,SUM($Q$18:$Q$19)-$P$15,0) -> 0 | S16: =M16-P16 -> 71 | T16: No action required.
B17: Dr: Acct 0952 - BEG FB ADJ/PRIOR PERIOD ADJUSTMENT | J17: =ROUND(IF(SUM($K$18:$K$20)>SUM($J$15:$J$16),SUM($K$18:$K$20)-SUM($J$15:$J$16),0),0) -> 0 | S17: =M17-P17 -> 0 | T17: No action required.
C18: Cr. Acct 0475 - ACCUMULATED AMORTIZATION - RIGHT-TO-USE SBITA | K18: =ROUND(N18,0) -> 9871 | N18: 9871 | Q18: 9871 | S18: =N18-Q18 -> 0 | T18: No action required.
C19: Cr: Acct 0674 - RIGHT-TO-USE SBITA LIABILITY | K19: =ROUND(N19,0) -> 7568 | N19: 7568 | Q19: 7568 | S19: =N19-Q19 -> 0 | T19: No action required.
C20: Cr: Acct 0950 - BEGINNING FUND BALANCE | K20: =ROUND(Q20,0) -> 1010 | N20: 1081 | Q20: =IF(SUM($Q$18:$Q$19)<$P$15,-SUM($Q$18:$Q$19)+$P$15,0) -> 1010 | S20: =N20-Q20 -> 71 | T20: No action required.
C21: Cr: Acct 0952 - BEG FB ADJ/PRIOR PERIOD ADJUSTMENT | K21: =ROUND(IF(SUM($K$18:$K$20)<SUM($J$15:$J$16),-SUM($K$18:$K$20)+SUM($J$15:$J$16),0),0) -> 0 | S21: =N21-Q21 -> 0 | T21: No action required.
J22: =ROUND(SUM(J15:J17),0) -> 18449 | K22: =ROUND(SUM(K18:K21),0) -> 18449 | L22: =IF(J22=K22,"<- Debits and Credits equal each other.","<- Debits and Credits do not equal each other.") -> <- Debits and Credits equal each other.
B24: SBITA ASSET (Acct 0480) AMOUNT SHOULD BE REPORTED AS BEGINNING BALANCE ON REPORT 18.
A26: =IF($F$3="2022–2023","Record SBITAs Commenced on or after 07/02/2022","Record New SBITAs (new SBITAs only)") -> Record New SBITAs (new SBITAs only)
A27: 1 | B27: Record at inception of SBITA in accordance with Fund-Based accounting (Governmental Funds Only).
B28: Dr: Acct 0842 - CAPITAL OUTLAY | J28: 64264
C29: Cr: Acct 0789 - LEASE AND OTHER FINANCING PROCEEDS | K29: 64264
C30: =VLOOKUP($F$8,'Drop Down Menus'!$D$2:$G$10,4,FALSE) -> Cr: Acct 0808 - GENERAL GOV. (GAAP ADJ)
J31: =ROUND(SUM(J28:J30),2) -> 64264 | K31: =ROUND(SUM(K28:K30),2) -> 64264 | L31: =IF(J31=K31,"<- Debits and Credits equal each other.","<- Debits and Credits do not equal each other.") -> <- Debits and Credits equal each other.
A33: 2 | B33: Reverse the fund-based entry in #1 above, if any, and record an inception of SBITA in accordance with GAAP Govt Wide.
B34: Dr: Acct 0480 - RIGHT-TO-USE SBITA - AMORTIZABLE | J34: 64264
B35: Dr: Acct 0789 - LEASE AND OTHER FINANCING PROCEEDS | J35: 64264
C36: Cr: Acct 0842 - CAPITAL OUTLAY | K36: 64264
C37: Cr: Acct 0674 - RIGHT-TO-USE SBITA LIABILITY | K37: 64264
C38: =VLOOKUP($F$8,'Drop Down Menus'!$D$2:$G$10,4,FALSE) -> Cr: Acct 0808 - GENERAL GOV. (GAAP ADJ)
J39: =ROUND(SUM(J34:J35),2) -> 128528 | K39: =ROUND(SUM(K36:K38),2) -> 128528 | L39: =IF(J39=K39,"<- Debits and Credits equal each other.","<- Debits and Credits do not equal each other.") -> <- Debits and Credits equal each other.
B41: SBITA ASSET (Acct 0480) AMOUNT SHOULD BE INCLUDED AS "ADDITIONS" ON REPORT 18.
A43: Record Annual Activity (all SBITAs)
A44: 3 | B44: Record amortization of the SBITA asset for the year.
B45: Dr: Acct 0875 - DEPRECIATION/AMORTIZATION | J45: 15837
C46: Cr. Acct 0475 - ACCUMULATED AMORTIZATION - RIGHT-TO-USE SBITA | K46: =J45 -> 15837
J47: =ROUND(SUM(J45:J45),2) -> 15837 | K47: =ROUND(SUM(K46),2) -> 15837 | L47: =IF(J47=K47,"<- Debits and Credits equal each other.","<- Debits and Credits do not equal each other.") -> <- Debits and Credits equal each other.
A49: 4 | B49: Reclassify information technology subscription exp. to debt service principal and interest exp.
B50: Dr: Acct 0848 - DEBT SERVICE - PRINCIPAL LEASES | J50: 22496 | L50: =IF($J$50=$K$57,"","<- Accts 0848 must agree")
B51: =IF(OR($F$7="Proprietary - Internal Service Fund",$F$7="Proprietary - Enterprise Fund"),"Dr: Acct 0894 - INTEREST EXPENSE AND FISCAL CHARGES","Dr: Acct 0851 - DEBT SERVICE - INTEREST LEASES") -> Dr: Acct 0851 - DEBT SERVICE - INTEREST LEASES | J51: 726
C52: =VLOOKUP($F$8,'Drop Down Menus'!$D$2:$G$10,4,FALSE) -> Cr: Acct 0808 - GENERAL GOV. (GAAP ADJ) | K52: =+J50+J51 -> 23222
J53: =ROUND(SUM(J50:J51),2) -> 23222 | K53: =ROUND(SUM(K52,),2) -> 23222 | L53: =IF(J53=K53,"<- Debits and Credits equal each other.","<- Debits and Credits do not equal each other.") -> <- Debits and Credits equal each other.
A55: 5 | B55: Reduce SBITA liability for total current year principal payments.
B56: Dr: Acct 0674 - RIGHT-TO-USE SBITA LIABILITY | J56: 22496
C57: Cr: Acct 0848 - DEBT SERVICE - PRINCIPAL LEASES | K57: =J50 -> 22496 | L57: =IF($J$50=$K$57,"","<- Accts 0848 must agree")
J58: =ROUND(SUM(J56:J56),2) -> 22496 | K58: =ROUND(SUM(K57),2) -> 22496 | L58: =IF(J58=K58,"<- Debits and Credits equal each other.","<- Debits and Credits do not equal each other.") -> <- Debits and Credits equal each other.
A60: 6 | B60: Reclassify the principal amount due in the next FY to the current liability.
B61: Dr: Acct 0674 - RIGHT-TO-USE SBITA LIABILITY | J61: 22242
C62: Cr. Acct 0651 - RIGHT-TO-USE SBITA LIABILITY (CURRENT PORTION LT) | K62: =J61 -> 22242
B63: NOTE: This is an annual accrual. The RTU SBITA Liability - Current portion will be added back to the RTU SBITA Liability in entry #0 when reestablishing the beginning balances next year. | J63: =ROUND(SUM(J61:J61),2) -> 22242 | K63: =ROUND(SUM(K62),2) -> 22242 | L63: =IF(J63=K63,"<- Debits and Credits equal each other.","<- Debits and Credits do not equal each other.") -> <- Debits and Credits equal each other.
A66: Remove SBITA Asset at the End of the Subscription Term (only at the end of the subscription term)
A67: 7 | B67: Record entry to write off the SBITA asset and accumulated amortization at the end of the subscription term.
B68: Dr: Acct 0475 - ACCUMULATED AMORTIZATION - RIGHT-TO-USE SBITA | J68: 5584
C69: Cr: Acct 0480 - RIGHT-TO-USE SBITA - AMORTIZABLE | K69: 5584
J70: =SUM(J68) -> 5584 | K70: =SUM(K69) -> 5584 | L70: =IF(J70=K70,"<- Debits and Credits equal each other.","<- Debits and Credits do not equal each other.") -> <- Debits and Credits equal each other.
B72: SBITA ASSET (Acct 0480) SHOULD BE INCLUDED AS "DEDUCTIONS" ON REPORT 18.
A74: Record SBITA Remeasurement and Modifications (only if a significant modification occurred during the fiscal year)
A75: 8 | B75: Record early termination of SBITA contract or SBITA modifications to decrease in the RTU SBITA asset.
B76: Dr: Acct 0674 - RIGHT-TO-USE SBITA LIABILITY | J76: 2465
B77: Dr: Acct 0475 - ACCUMULATED AMORTIZATION - RIGHT-TO-USE SBITA | J77: 4906
B78: =VLOOKUP($F$8,'Drop Down Menus'!$D$2:$G$10,3,FALSE) -> Dr: Acct 0808 - GENERAL GOV. (GAAP ADJ)
C79: Cr: Acct 0480 - RIGHT-TO-USE SBITA - AMORTIZABLE | K79: 7346
C80: =VLOOKUP($F$8,'Drop Down Menus'!$D$2:$G$10,4,FALSE) -> Cr: Acct 0808 - GENERAL GOV. (GAAP ADJ) | K80: 25
J81: =ROUND(SUM(J76:J78),2) -> 7371 | K81: =ROUND(SUM(K79:K80),2) -> 7371 | L81: =IF(J81=K81,"<- Debits and Credits equal each other.","<- Debits and Credits do not equal each other.") -> <- Debits and Credits equal each other.
A83: 9 | B83: Record SBITA modifications to increase in the RTU SBITA asset.
B84: Dr: Acct 0480 - RIGHT-TO-USE SBITA - AMORTIZABLE
C85: Cr: Acct 0674 - RIGHT-TO-USE SBITA LIABILITY
J86: =SUM(J84) -> 0 | K86: =SUM(K85) -> 0 | L86: =IF(J86=K86,"<- Debits and Credits equal each other.","<- Debits and Credits do not equal each other.") -> <- Debits and Credits equal each other.
B88: NOTE: Please check the instructions for remeasurement and modifications on the SCO website.
D92: Informational - Ending Balances of Assets and Liabilities
K93: Debit (Credit)
D94: Acct 0480 - RIGHT-TO-USE SBITA - AMORTIZABLE | K94: =+J15+J34-K69-K79+J84 -> 69783
D95: Acct 0475 - ACCUMULATED AMORTIZATION - RIGHT-TO-USE SBITA | K95: =-K18-K46+J68+J77 -> -15218
D96: Acct 0674 - RIGHT-TO-USE SBITA LIABILITY | K96: =-K19-K37+J56+J61+J76-K85 -> -24629
D97: Acct 0651 - RIGHT-TO-USE SBITA LIABILITY (CURRENT PORTION LT) | K97: =-K62 -> -22242

Sheet Fund 0890 Journal Entries
A1: GASB 96 - SBITA Contracts Fund-by-Fund Journal Entries Form (to be submitted to the SCO annually—one form per fund)
A2: Manually complete every yellow field in this worksheet—there are no automatically calculated data-entry cells in this worksheet.
A3: Fiscal year: | F3: 2023–2024
A4: Organization Name: | F4: Department of Justice
A5: Organization Code (Business Unit): | F5: 0820
A6: Fund Number: | F6: 890
A7: Fund Type: | F7: Governmental Fund
A8: Fund Classification: | F8: =IF(OR($F$7='Drop Down Menus'!B2,$F$7='Drop Down Menus'!$B$3),'Drop Down Menus'!$D$9,IFERROR(VLOOKUP($F$5,GAAP02Aindex!$A$2:$D$900,4,FALSE),"Unidentified")) -> GENERAL GOVERNMENT
A12: =IF($F$3="2022–2023","Establish Beginning Balances (SBITAs commenced on or before 07/01/2022)","Establish Beginning Balances (existing SBITAs only)") -> Establish Beginning Balances (existing SBITAs only)
A13: Entry #
A14: 0 | B14: =IF($F$3="2022–2023","To establish the beginning balance of SBITAs as of 07/01/2022.","Roll forward prior year right-to-use SBITAs to record opening balances.") -> Roll forward prior year right-to-use SBITAs to record opening balances. | M14: Department Beginning Balances | P14: From SCO BB List | S14: Difference
B15: Dr: Acct 0480 - RIGHT-TO-USE SBITA - AMORTIZABLE | J15: =ROUND(M15,0) -> 17865 | M15: 17865 | P15: 17865 | S15: =M15-P15 -> 0 | T15: Report any "Differences" on the Report 18 Differential.
B16: Dr: Acct 0950 - BEGINNING FUND BALANCE | J16: =ROUND(P16,0) -> 234 | M16: 234 | P16: =IF(SUM($Q$18:$Q$19)>$P$15,SUM($Q$18:$Q$19)-$P$15,0) -> 234 | S16: =M16-P16 -> 0 | T16: No action required.
B17: Dr: Acct 0952 - BEG FB ADJ/PRIOR PERIOD ADJUSTMENT | J17: =ROUND(IF(SUM($K$18:$K$20)>SUM($J$15:$J$16),SUM($K$18:$K$20)-SUM($J$15:$J$16),0),0) -> 0 | S17: =M17-P17 -> 0 | T17: No action required.
C18: Cr. Acct 0475 - ACCUMULATED AMORTIZATION - RIGHT-TO-USE SBITA | K18: =ROUND(N18,0) -> 8932 | N18: 8932 | Q18: 8932 | S18: =N18-Q18 -> 0 | T18: No action required.
C19: Cr: Acct 0674 - RIGHT-TO-USE SBITA LIABILITY | K19: =ROUND(N19,0) -> 9167 | N19: 9167 | Q19: 9167 | S19: =N19-Q19 -> 0 | T19: No action required.
C20: Cr: Acct 0950 - BEGINNING FUND BALANCE | K20: =ROUND(Q20,0) -> 0 | Q20: =IF(SUM($Q$18:$Q$19)<$P$15,-SUM($Q$18:$Q$19)+$P$15,0) -> 0 | S20: =N20-Q20 -> 0 | T20: No action required.
C21: Cr: Acct 0952 - BEG FB ADJ/PRIOR PERIOD ADJUSTMENT | K21: =ROUND(IF(SUM($K$18:$K$20)<SUM($J$15:$J$16),-SUM($K$18:$K$20)+SUM($J$15:$J$16),0),0) -> 0 | S21: =N21-Q21 -> 0 | T21: No action required.
J22: =ROUND(SUM(J15:J17),0) -> 18099 | K22: =ROUND(SUM(K18:K21),0) -> 18099 | L22: =IF(J22=K22,"<- Debits and Credits equal each other.","<- Debits and Credits do not equal each other.") -> <- Debits and Credits equal each other.
B24: SBITA ASSET (Acct 0480) AMOUNT SHOULD BE REPORTED AS BEGINNING BALANCE ON REPORT 18.
A26: =IF($F$3="2022–2023","Record SBITAs Commenced on or after 07/02/2022","Record New SBITAs (new SBITAs only)") -> Record New SBITAs (new SBITAs only)
A27: 1 | B27: Record at inception of SBITA in accordance with Fund-Based accounting (Governmental Funds Only).
B28: Dr: Acct 0842 - CAPITAL OUTLAY
C29: Cr: Acct 0789 - LEASE AND OTHER FINANCING PROCEEDS
C30: =VLOOKUP($F$8,'Drop Down Menus'!$D$2:$G$10,4,FALSE) -> Cr: Acct 0808 - GENERAL GOV. (GAAP ADJ)
J31: =ROUND(SUM(J28:J30),2) -> 0 | K31: =ROUND(SUM(K28:K30),2) -> 0 | L31: =IF(J31=K31,"<- Debits and Credits equal each other.","<- Debits and Credits do not equal each other.") -> <- Debits and Credits equal each other.
A33: 2 | B33: Reverse the fund-based entry in #1 above, if any, and record an inception of SBITA in accordance with GAAP Govt Wide.
B34: Dr: Acct 0480 - RIGHT-TO-USE SBITA - AMORTIZABLE
B35: Dr: Acct 0789 - LEASE AND OTHER FINANCING PROCEEDS
C36: Cr: Acct 0842 - CAPITAL OUTLAY
C37: Cr: Acct 0674 - RIGHT-TO-USE SBITA LIABILITY
C38: =VLOOKUP($F$8,'Drop Down Menus'!$D$2:$G$10,4,FALSE) -> Cr: Acct 0808 - GENERAL GOV. (GAAP ADJ)
J39: =ROUND(SUM(J34:J35),2) -> 0 | K39: =ROUND(SUM(K36:K38),2) -> 0 | L39: =IF(J39=K39,"<- Debits and Credits equal each other.","<- Debits and Credits do not equal each other.") -> <- Debits and Credits equal each other.
B41: SBITA ASSET (Acct 0480) AMOUNT SHOULD BE INCLUDED AS "ADDITIONS" ON REPORT 18.
A43: Record Annual Activity (all SBITAs)
A44: 3 | B44: Record amortization of the SBITA asset for the year.
B45: Dr: Acct 0875 - DEPRECIATION/AMORTIZATION | J45: 8933
C46: Cr. Acct 0475 - ACCUMULATED AMORTIZATION - RIGHT-TO-USE SBITA | K46: =J45 -> 8933
J47: =ROUND(SUM(J45:J45),2) -> 8933 | K47: =ROUND(SUM(K46),2) -> 8933 | L47: =IF(J47=K47,"<- Debits and Credits equal each other.","<- Debits and Credits do not equal each other.") -> <- Debits and Credits equal each other.
A49: 4 | B49: Reclassify information technology subscription exp. to debt service principal and interest exp.
B50: Dr: Acct 0848 - DEBT SERVICE - PRINCIPAL LEASES | J50: 9167 | L50: =IF($J$50=$K$57,"","<- Accts 0848 must agree")
B51: =IF(OR($F$7="Proprietary - Internal Service Fund",$F$7="Proprietary - Enterprise Fund"),"Dr: Acct 0894 - INTEREST EXPENSE AND FISCAL CHARGES","Dr: Acct 0851 - DEBT SERVICE - INTEREST LEASES") -> Dr: Acct 0851 - DEBT SERVICE - INTEREST LEASES | J51: 222
C52: =VLOOKUP($F$8,'Drop Down Menus'!$D$2:$G$10,4,FALSE) -> Cr: Acct 0808 - GENERAL GOV. (GAAP ADJ) | K52: 9389
J53: =ROUND(SUM(J50:J51),2) -> 9389 | K53: =ROUND(SUM(K52,),2) -> 9389 | L53: =IF(J53=K53,"<- Debits and Credits equal each other.","<- Debits and Credits do not equal each other.") -> <- Debits and Credits equal each other.
A55: 5 | B55: Reduce SBITA liability for total current year principal payments.
B56: Dr: Acct 0674 - RIGHT-TO-USE SBITA LIABILITY | J56: 9167
C57: Cr: Acct 0848 - DEBT SERVICE - PRINCIPAL LEASES | K57: 9167 | L57: =IF($J$50=$K$57,"","<- Accts 0848 must agree")
J58: =ROUND(SUM(J56:J56),2) -> 9167 | K58: =ROUND(SUM(K57),2) -> 9167 | L58: =IF(J58=K58,"<- Debits and Credits equal each other.","<- Debits and Credits do not equal each other.") -> <- Debits and Credits equal each other.
A60: 6 | B60: Reclassify the principal amount due in the next FY to the current liability.
B61: Dr: Acct 0674 - RIGHT-TO-USE SBITA LIABILITY
C62: Cr. Acct 0651 - RIGHT-TO-USE SBITA LIABILITY (CURRENT PORTION LT) | K62: =J61 -> 0
B63: NOTE: This is an annual accrual. The RTU SBITA Liability - Current portion will be added back to the RTU SBITA Liability in entry #0 when reestablishing the beginning balances next year. | J63: =ROUND(SUM(J61:J61),2) -> 0 | K63: =ROUND(SUM(K62),2) -> 0 | L63: =IF(J63=K63,"<- Debits and Credits equal each other.","<- Debits and Credits do not equal each other.") -> <- Debits and Credits equal each other.
A66: Remove SBITA Asset at the End of the Subscription Term (only at the end of the subscription term)
A67: 7 | B67: Record entry to write off the SBITA asset and accumulated amortization at the end of the subscription term.
B68: Dr: Acct 0475 - ACCUMULATED AMORTIZATION - RIGHT-TO-USE SBITA | J68: 17865
C69: Cr: Acct 0480 - RIGHT-TO-USE SBITA - AMORTIZABLE | K69: 17865
J70: =SUM(J68) -> 17865 | K70: =SUM(K69) -> 17865 | L70: =IF(J70=K70,"<- Debits and Credits equal each other.","<- Debits and Credits do not equal each other.") -> <- Debits and Credits equal each other.
B72: SBITA ASSET (Acct 0480) SHOULD BE INCLUDED AS "DEDUCTIONS" ON REPORT 18.
A74: Record SBITA Remeasurement and Modifications (only if a significant modification occurred during the fiscal year)
A75: 8 | B75: Record early termination of SBITA contract or SBITA modifications to decrease in the RTU SBITA asset.
B76: Dr: Acct 0674 - RIGHT-TO-USE SBITA LIABILITY
B77: Dr: Acct 0475 - ACCUMULATED AMORTIZATION - RIGHT-TO-USE SBITA
B78: =VLOOKUP($F$8,'Drop Down Menus'!$D$2:$G$10,3,FALSE) -> Dr: Acct 0808 - GENERAL GOV. (GAAP ADJ)
C79: Cr: Acct 0480 - RIGHT-TO-USE SBITA - AMORTIZABLE
C80: =VLOOKUP($F$8,'Drop Down Menus'!$D$2:$G$10,4,FALSE) -> Cr: Acct 0808 - GENERAL GOV. (GAAP ADJ)
J81: =ROUND(SUM(J76:J78),2) -> 0 | K81: =ROUND(SUM(K79:K80),2) -> 0 | L81: =IF(J81=K81,"<- Debits and Credits equal each other.","<- Debits and Credits do not equal each other.") -> <- Debits and Credits equal each other.
A83: 9 | B83: Record SBITA modifications to increase in the RTU SBITA asset.
B84: Dr: Acct 0480 - RIGHT-TO-USE SBITA - AMORTIZABLE
C85: Cr: Acct 0674 - RIGHT-TO-USE SBITA LIABILITY
J86: =SUM(J84) -> 0 | K86: =SUM(K85) -> 0 | L86: =IF(J86=K86,"<- Debits and Credits equal each other.","<- Debits and Credits do not equal each other.") -> <- Debits and Credits equal each other.
B88: NOTE: Please check the instructions for remeasurement and modifications on the SCO website.
D92: Informational - Ending Balances of Assets and Liabilities
K93: Debit (Credit)
D94: Acct 0480 - RIGHT-TO-USE SBITA - AMORTIZABLE | K94: =+J15+J34-K69-K79+J84 -> 0
D95: Acct 0475 - ACCUMULATED AMORTIZATION - RIGHT-TO-USE SBITA | K95: =-K18-K46+J68+J77 -> 0
D96: Acct 0674 - RIGHT-TO-USE SBITA LIABILITY | K96: =-K19-K37+J56+J61+J76-K85 -> 0
D97: Acct 0651 - RIGHT-TO-USE SBITA LIABILITY (CURRENT PORTION LT) | K97: =-K62 -> 0

Sheet Fund 1008 Journal Entries
A1: GASB 96 - SBITA Contracts Fund-by-Fund Journal Entries Form (to be submitted to the SCO annually—one form per fund)
A2: Manually complete every yellow field in this worksheet—there are no automatically calculated data-entry cells in this worksheet.
A3: Fiscal year: | F3: 2023–2024
A4: Organization Name: | F4: Department of Justice
A5: Organization Code (Business Unit): | F5: 0820
A6: Fund Number: | F6: 1008
A7: Fund Type: | F7: Governmental Fund
A8: Fund Classification: | F8: =IF(OR($F$7='Drop Down Menus'!B2,$F$7='Drop Down Menus'!$B$3),'Drop Down Menus'!$D$9,IFERROR(VLOOKUP($F$5,GAAP02Aindex!$A$2:$D$900,4,FALSE),"Unidentified")) -> GENERAL GOVERNMENT
A12: =IF($F$3="2022–2023","Establish Beginning Balances (SBITAs commenced on or before 07/01/2022)","Establish Beginning Balances (existing SBITAs only)") -> Establish Beginning Balances (existing SBITAs only)
A13: Entry #
A14: 0 | B14: =IF($F$3="2022–2023","To establish the beginning balance of SBITAs as of 07/01/2022.","Roll forward prior year right-to-use SBITAs to record opening balances.") -> Roll forward prior year right-to-use SBITAs to record opening balances. | M14: Department Beginning Balances | P14: From SCO BB List | S14: Difference
B15: Dr: Acct 0480 - RIGHT-TO-USE SBITA - AMORTIZABLE | J15: =ROUND(M15,0) -> 30776 | M15: 30776 | P15: 30776 | S15: =M15-P15 -> 0 | T15: Report any "Differences" on the Report 18 Differential.
B16: Dr: Acct 0950 - BEGINNING FUND BALANCE | J16: =ROUND(P16,0) -> 403 | M16: 403 | P16: =IF(SUM($Q$18:$Q$19)>$P$15,SUM($Q$18:$Q$19)-$P$15,0) -> 403 | S16: =M16-P16 -> 0 | T16: No action required.
B17: Dr: Acct 0952 - BEG FB ADJ/PRIOR PERIOD ADJUSTMENT | J17: =ROUND(IF(SUM($K$18:$K$20)>SUM($J$15:$J$16),SUM($K$18:$K$20)-SUM($J$15:$J$16),0),0) -> 0 | S17: =M17-P17 -> 0 | T17: No action required.
C18: Cr. Acct 0475 - ACCUMULATED AMORTIZATION - RIGHT-TO-USE SBITA | K18: =ROUND(N18,0) -> 15388 | N18: 15388 | Q18: 15388 | S18: =N18-Q18 -> 0 | T18: No action required.
C19: Cr: Acct 0674 - RIGHT-TO-USE SBITA LIABILITY | K19: =ROUND(N19,0) -> 15791 | N19: 15791 | Q19: 15791 | S19: =N19-Q19 -> 0 | T19: No action required.
C20: Cr: Acct 0950 - BEGINNING FUND BALANCE | K20: =ROUND(Q20,0) -> 0 | Q20: =IF(SUM($Q$18:$Q$19)<$P$15,-SUM($Q$18:$Q$19)+$P$15,0) -> 0 | S20: =N20-Q20 -> 0 | T20: No action required.
C21: Cr: Acct 0952 - BEG FB ADJ/PRIOR PERIOD ADJUSTMENT | K21: =ROUND(IF(SUM($K$18:$K$20)<SUM($J$15:$J$16),-SUM($K$18:$K$20)+SUM($J$15:$J$16),0),0) -> 0 | S21: =N21-Q21 -> 0 | T21: No action required.
J22: =ROUND(SUM(J15:J17),0) -> 31179 | K22: =ROUND(SUM(K18:K21),0) -> 31179 | L22: =IF(J22=K22,"<- Debits and Credits equal each other.","<- Debits and Credits do not equal each other.") -> <- Debits and Credits equal each other.
B24: SBITA ASSET (Acct 0480) AMOUNT SHOULD BE REPORTED AS BEGINNING BALANCE ON REPORT 18.
A26: =IF($F$3="2022–2023","Record SBITAs Commenced on or after 07/02/2022","Record New SBITAs (new SBITAs only)") -> Record New SBITAs (new SBITAs only)
A27: 1 | B27: Record at inception of SBITA in accordance with Fund-Based accounting (Governmental Funds Only).
B28: Dr: Acct 0842 - CAPITAL OUTLAY
C29: Cr: Acct 0789 - LEASE AND OTHER FINANCING PROCEEDS
C30: =VLOOKUP($F$8,'Drop Down Menus'!$D$2:$G$10,4,FALSE) -> Cr: Acct 0808 - GENERAL GOV. (GAAP ADJ)
J31: =ROUND(SUM(J28:J30),2) -> 0 | K31: =ROUND(SUM(K28:K30),2) -> 0 | L31: =IF(J31=K31,"<- Debits and Credits equal each other.","<- Debits and Credits do not equal each other.") -> <- Debits and Credits equal each other.
A33: 2 | B33: Reverse the fund-based entry in #1 above, if any, and record an inception of SBITA in accordance with GAAP Govt Wide.
B34: Dr: Acct 0480 - RIGHT-TO-USE SBITA - AMORTIZABLE
B35: Dr: Acct 0789 - LEASE AND OTHER FINANCING PROCEEDS
C36: Cr: Acct 0842 - CAPITAL OUTLAY
C37: Cr: Acct 0674 - RIGHT-TO-USE SBITA LIABILITY
C38: =VLOOKUP($F$8,'Drop Down Menus'!$D$2:$G$10,4,FALSE) -> Cr: Acct 0808 - GENERAL GOV. (GAAP ADJ)
J39: =ROUND(SUM(J34:J35),2) -> 0 | K39: =ROUND(SUM(K36:K38),2) -> 0 | L39: =IF(J39=K39,"<- Debits and Credits equal each other.","<- Debits and Credits do not equal each other.") -> <- Debits and Credits equal each other.
B41: SBITA ASSET (Acct 0480) AMOUNT SHOULD BE INCLUDED AS "ADDITIONS" ON REPORT 18.
A43: Record Annual Activity (all SBITAs)
A44: 3 | B44: Record amortization of the SBITA asset for the year.
B45: Dr: Acct 0875 - DEPRECIATION/AMORTIZATION | J45: 15388
C46: Cr. Acct 0475 - ACCUMULATED AMORTIZATION - RIGHT-TO-USE SBITA | K46: =J45 -> 15388
J47: =ROUND(SUM(J45:J45),2) -> 15388 | K47: =ROUND(SUM(K46),2) -> 15388 | L47: =IF(J47=K47,"<- Debits and Credits equal each other.","<- Debits and Credits do not equal each other.") -> <- Debits and Credits equal each other.
A49: 4 | B49: Reclassify information technology subscription exp. to debt service principal and interest exp.
B50: Dr: Acct 0848 - DEBT SERVICE - PRINCIPAL LEASES | J50: 15791 | L50: =IF($J$50=$K$57,"","<- Accts 0848 must agree")
B51: =IF(OR($F$7="Proprietary - Internal Service Fund",$F$7="Proprietary - Enterprise Fund"),"Dr: Acct 0894 - INTEREST EXPENSE AND FISCAL CHARGES","Dr: Acct 0851 - DEBT SERVICE - INTEREST LEASES") -> Dr: Acct 0851 - DEBT SERVICE - INTEREST LEASES | J51: 383
C52: =VLOOKUP($F$8,'Drop Down Menus'!$D$2:$G$10,4,FALSE) -> Cr: Acct 0808 - GENERAL GOV. (GAAP ADJ) | K52: =+J50+J51 -> 16174
J53: =ROUND(SUM(J50:J51),2) -> 16174 | K53: =ROUND(SUM(K52,),2) -> 16174 | L53: =IF(J53=K53,"<- Debits and Credits equal each other.","<- Debits and Credits do not equal each other.") -> <- Debits and Credits equal each other.
A55: 5 | B55: Reduce SBITA liability for total current year principal payments.
B56: Dr: Acct 0674 - RIGHT-TO-USE SBITA LIABILITY | J56: 15791
C57: Cr: Acct 0848 - DEBT SERVICE - PRINCIPAL LEASES | K57: =J50 -> 15791 | L57: =IF($J$50=$K$57,"","<- Accts 0848 must agree")
J58: =ROUND(SUM(J56:J56),2) -> 15791 | K58: =ROUND(SUM(K57),2) -> 15791 | L58: =IF(J58=K58,"<- Debits and Credits equal each other.","<- Debits and Credits do not equal each other.") -> <- Debits and Credits equal each other.
A60: 6 | B60: Reclassify the principal amount due in the next FY to the current liability.
B61: Dr: Acct 0674 - RIGHT-TO-USE SBITA LIABILITY
C62: Cr. Acct 0651 - RIGHT-TO-USE SBITA LIABILITY (CURRENT PORTION LT) | K62: =J61 -> 0
B63: NOTE: This is an annual accrual. The RTU SBITA Liability - Current portion will be added back to the RTU SBITA Liability in entry #0 when reestablishing the beginning balances next year. | J63: =ROUND(SUM(J61:J61),2) -> 0 | K63: =ROUND(SUM(K62),2) -> 0 | L63: =IF(J63=K63,"<- Debits and Credits equal each other.","<- Debits and Credits do not equal each other.") -> <- Debits and Credits equal each other.
A66: Remove SBITA Asset at the End of the Subscription Term (only at the end of the subscription term)
A67: 7 | B67: Record entry to write off the SBITA asset and accumulated amortization at the end of the subscription term.
B68: Dr: Acct 0475 - ACCUMULATED AMORTIZATION - RIGHT-TO-USE SBITA | J68: 30776
C69: Cr: Acct 0480 - RIGHT-TO-USE SBITA - AMORTIZABLE | K69: 30776
J70: =SUM(J68) -> 30776 | K70: =SUM(K69) -> 30776 | L70: =IF(J70=K70,"<- Debits and Credits equal each other.","<- Debits and Credits do not equal each other.") -> <- Debits and Credits equal each other.
B72: SBITA ASSET (Acct 0480) SHOULD BE INCLUDED AS "DEDUCTIONS" ON REPORT 18.
A74: Record SBITA Remeasurement and Modifications (only if a significant modification occurred during the fiscal year)
A75: 8 | B75: Record early termination of SBITA contract or SBITA modifications to decrease in the RTU SBITA asset.
B76: Dr: Acct 0674 - RIGHT-TO-USE SBITA LIABILITY
B77: Dr: Acct 0475 - ACCUMULATED AMORTIZATION - RIGHT-TO-USE SBITA
B78: =VLOOKUP($F$8,'Drop Down Menus'!$D$2:$G$10,3,FALSE) -> Dr: Acct 0808 - GENERAL GOV. (GAAP ADJ)
C79: Cr: Acct 0480 - RIGHT-TO-USE SBITA - AMORTIZABLE
C80: =VLOOKUP($F$8,'Drop Down Menus'!$D$2:$G$10,4,FALSE) -> Cr: Acct 0808 - GENERAL GOV. (GAAP ADJ)
J81: =ROUND(SUM(J76:J78),2) -> 0 | K81: =ROUND(SUM(K79:K80),2) -> 0 | L81: =IF(J81=K81,"<- Debits and Credits equal each other.","<- Debits and Credits do not equal each other.") -> <- Debits and Credits equal each other.
A83: 9 | B83: Record SBITA modifications to increase in the RTU SBITA asset.
B84: Dr: Acct 0480 - RIGHT-TO-USE SBITA - AMORTIZABLE
C85: Cr: Acct 0674 - RIGHT-TO-USE SBITA LIABILITY
J86: =SUM(J84) -> 0 | K86: =SUM(K85) -> 0 | L86: =IF(J86=K86,"<- Debits and Credits equal each other.","<- Debits and Credits do not equal each other.") -> <- Debits and Credits equal each other.
B88: NOTE: Please check the instructions for remeasurement and modifications on the SCO website.
D92: Informational - Ending Balances of Assets and Liabilities
K93: Debit (Credit)
D94: Acct 0480 - RIGHT-TO-USE SBITA - AMORTIZABLE | K94: =+J15+J34-K69-K79+J84 -> 0
D95: Acct 0475 - ACCUMULATED AMORTIZATION - RIGHT-TO-USE SBITA | K95: =-K18-K46+J68+J77 -> 0
D96: Acct 0674 - RIGHT-TO-USE SBITA LIABILITY | K96: =-K19-K37+J56+J61+J76-K85 -> 0
D97: Acct 0651 - RIGHT-TO-USE SBITA LIABILITY (CURRENT PORTION LT) | K97: =-K62 -> 0

Sheet Fund 3053 Journal Entries
A1: GASB 96 - SBITA Contracts Fund-by-Fund Journal Entries Form (to be submitted to the SCO annually—one form per fund)
A2: Manually complete every yellow field in this worksheet—there are no automatically calculated data-entry cells in this worksheet.
A3: Fiscal year: | F3: 2023–2024
A4: Organization Name: | F4: Department of Justice
A5: Organization Code (Business Unit): | F5: 0820
A6: Fund Number: | F6: 3053
A7: Fund Type: | F7: Governmental Fund
A8: Fund Classification: | F8: =IF(OR($F$7='Drop Down Menus'!B2,$F$7='Drop Down Menus'!$B$3),'Drop Down Menus'!$D$9,IFERROR(VLOOKUP($F$5,GAAP02Aindex!$A$2:$D$900,4,FALSE),"Unidentified")) -> GENERAL GOVERNMENT
A12: =IF($F$3="2022–2023","Establish Beginning Balances (SBITAs commenced on or before 07/01/2022)","Establish Beginning Balances (existing SBITAs only)") -> Establish Beginning Balances (existing SBITAs only)
A13: Entry #
A14: 0 | B14: =IF($F$3="2022–2023","To establish the beginning balance of SBITAs as of 07/01/2022.","Roll forward prior year right-to-use SBITAs to record opening balances.") -> Roll forward prior year right-to-use SBITAs to record opening balances. | M14: Department Beginning Balances | P14: From SCO BB List | S14: Difference
B15: Dr: Acct 0480 - RIGHT-TO-USE SBITA - AMORTIZABLE | J15: =ROUND(M15,0) -> 1671 | M15: 1671 | P15: 1671 | S15: =M15-P15 -> 0 | T15: Report any "Differences" on the Report 18 Differential.
B16: Dr: Acct 0950 - BEGINNING FUND BALANCE | J16: =ROUND(P16,0) -> 8 | M16: 8 | P16: =IF(SUM($Q$18:$Q$19)>$P$15,SUM($Q$18:$Q$19)-$P$15,0) -> 8 | S16: =M16-P16 -> 0 | T16: No action required.
B17: Dr: Acct 0952 - BEG FB ADJ/PRIOR PERIOD ADJUSTMENT | J17: =ROUND(IF(SUM($K$18:$K$20)>SUM($J$15:$J$16),SUM($K$18:$K$20)-SUM($J$15:$J$16),0),0) -> 0 | S17: =M17-P17 -> 0 | T17: No action required.
C18: Cr. Acct 0475 - ACCUMULATED AMORTIZATION - RIGHT-TO-USE SBITA | K18: =ROUND(N18,0) -> 835 | N18: 835 | Q18: 835 | S18: =N18-Q18 -> 0 | T18: No action required.
C19: Cr: Acct 0674 - RIGHT-TO-USE SBITA LIABILITY | K19: =ROUND(N19,0) -> 844 | N19: 844 | Q19: 844 | S19: =N19-Q19 -> 0 | T19: No action required.
C20: Cr: Acct 0950 - BEGINNING FUND BALANCE | K20: =ROUND(Q20,0) -> 0 | Q20: =IF(SUM($Q$18:$Q$19)<$P$15,-SUM($Q$18:$Q$19)+$P$15,0) -> 0 | S20: =N20-Q20 -> 0 | T20: No action required.
C21: Cr: Acct 0952 - BEG FB ADJ/PRIOR PERIOD ADJUSTMENT | K21: =ROUND(IF(SUM($K$18:$K$20)<SUM($J$15:$J$16),-SUM($K$18:$K$20)+SUM($J$15:$J$16),0),0) -> 0 | S21: =N21-Q21 -> 0 | T21: No action required.
J22: =ROUND(SUM(J15:J17),0) -> 1679 | K22: =ROUND(SUM(K18:K21),0) -> 1679 | L22: =IF(J22=K22,"<- Debits and Credits equal each other.","<- Debits and Credits do not equal each other.") -> <- Debits and Credits equal each other.
B24: SBITA ASSET (Acct 0480) AMOUNT SHOULD BE REPORTED AS BEGINNING BALANCE ON REPORT 18.
A26: =IF($F$3="2022–2023","Record SBITAs Commenced on or after 07/02/2022","Record New SBITAs (new SBITAs only)") -> Record New SBITAs (new SBITAs only)
A27: 1 | B27: Record at inception of SBITA in accordance with Fund-Based accounting (Governmental Funds Only).
B28: Dr: Acct 0842 - CAPITAL OUTLAY
C29: Cr: Acct 0789 - LEASE AND OTHER FINANCING PROCEEDS
C30: =VLOOKUP($F$8,'Drop Down Menus'!$D$2:$G$10,4,FALSE) -> Cr: Acct 0808 - GENERAL GOV. (GAAP ADJ)
J31: =ROUND(SUM(J28:J30),2) -> 0 | K31: =ROUND(SUM(K28:K30),2) -> 0 | L31: =IF(J31=K31,"<- Debits and Credits equal each other.","<- Debits and Credits do not equal each other.") -> <- Debits and Credits equal each other.
A33: 2 | B33: Reverse the fund-based entry in #1 above, if any, and record an inception of SBITA in accordance with GAAP Govt Wide.
B34: Dr: Acct 0480 - RIGHT-TO-USE SBITA - AMORTIZABLE
B35: Dr: Acct 0789 - LEASE AND OTHER FINANCING PROCEEDS
C36: Cr: Acct 0842 - CAPITAL OUTLAY
C37: Cr: Acct 0674 - RIGHT-TO-USE SBITA LIABILITY
C38: =VLOOKUP($F$8,'Drop Down Menus'!$D$2:$G$10,4,FALSE) -> Cr: Acct 0808 - GENERAL GOV. (GAAP ADJ)
J39: =ROUND(SUM(J34:J35),2) -> 0 | K39: =ROUND(SUM(K36:K38),2) -> 0 | L39: =IF(J39=K39,"<- Debits and Credits equal each other.","<- Debits and Credits do not equal each other.") -> <- Debits and Credits equal each other.
B41: SBITA ASSET (Acct 0480) AMOUNT SHOULD BE INCLUDED AS "ADDITIONS" ON REPORT 18.
A43: Record Annual Activity (all SBITAs)
A44: 3 | B44: Record amortization of the SBITA asset for the year.
B45: Dr: Acct 0875 - DEPRECIATION/AMORTIZATION
C46: Cr. Acct 0475 - ACCUMULATED AMORTIZATION - RIGHT-TO-USE SBITA | K46: =J45 -> 0
J47: =ROUND(SUM(J45:J45),2) -> 0 | K47: =ROUND(SUM(K46),2) -> 0 | L47: =IF(J47=K47,"<- Debits and Credits equal each other.","<- Debits and Credits do not equal each other.") -> <- Debits and Credits equal each other.
A49: 4 | B49: Reclassify information technology subscription exp. to debt service principal and interest exp.
B50: Dr: Acct 0848 - DEBT SERVICE - PRINCIPAL LEASES | L50: =IF($J$50=$K$57,"","<- Accts 0848 must agree")
B51: =IF(OR($F$7="Proprietary - Internal Service Fund",$F$7="Proprietary - Enterprise Fund"),"Dr: Acct 0894 - INTEREST EXPENSE AND FISCAL CHARGES","Dr: Acct 0851 - DEBT SERVICE - INTEREST LEASES") -> Dr: Acct 0851 - DEBT SERVICE - INTEREST LEASES
C52: =VLOOKUP($F$8,'Drop Down Menus'!$D$2:$G$10,4,FALSE) -> Cr: Acct 0808 - GENERAL GOV. (GAAP ADJ) | K52: =+J50+J51 -> 0
J53: =ROUND(SUM(J50:J51),2) -> 0 | K53: =ROUND(SUM(K52,),2) -> 0 | L53: =IF(J53=K53,"<- Debits and Credits equal each other.","<- Debits and Credits do not equal each other.") -> <- Debits and Credits equal each other.
A55: 5 | B55: Reduce SBITA liability for total current year principal payments.
B56: Dr: Acct 0674 - RIGHT-TO-USE SBITA LIABILITY
C57: Cr: Acct 0848 - DEBT SERVICE - PRINCIPAL LEASES | K57: =J50 -> 0 | L57: =IF($J$50=$K$57,"","<- Accts 0848 must agree")
J58: =ROUND(SUM(J56:J56),2) -> 0 | K58: =ROUND(SUM(K57),2) -> 0 | L58: =IF(J58=K58,"<- Debits and Credits equal each other.","<- Debits and Credits do not equal each other.") -> <- Debits and Credits equal each other.
A60: 6 | B60: Reclassify the principal amount due in the next FY to the current liability.
B61: Dr: Acct 0674 - RIGHT-TO-USE SBITA LIABILITY
C62: Cr. Acct 0651 - RIGHT-TO-USE SBITA LIABILITY (CURRENT PORTION LT) | K62: =J61 -> 0
B63: NOTE: This is an annual accrual. The RTU SBITA Liability - Current portion will be added back to the RTU SBITA Liability in entry #0 when reestablishing the beginning balances next year. | J63: =ROUND(SUM(J61:J61),2) -> 0 | K63: =ROUND(SUM(K62),2) -> 0 | L63: =IF(J63=K63,"<- Debits and Credits equal each other.","<- Debits and Credits do not equal each other.") -> <- Debits and Credits equal each other.
A66: Remove SBITA Asset at the End of the Subscription Term (only at the end of the subscription term)
A67: 7 | B67: Record entry to write off the SBITA asset and accumulated amortization at the end of the subscription term.
B68: Dr: Acct 0475 - ACCUMULATED AMORTIZATION - RIGHT-TO-USE SBITA
C69: Cr: Acct 0480 - RIGHT-TO-USE SBITA - AMORTIZABLE
J70: =SUM(J68) -> 0 | K70: =SUM(K69) -> 0 | L70: =IF(J70=K70,"<- Debits and Credits equal each other.","<- Debits and Credits do not equal each other.") -> <- Debits and Credits equal each other.
B72: SBITA ASSET (Acct 0480) SHOULD BE INCLUDED AS "DEDUCTIONS" ON REPORT 18.
A74: Record SBITA Remeasurement and Modifications (only if a significant modification occurred during the fiscal year)
A75: 8 | B75: Record early termination of SBITA contract or SBITA modifications to decrease in the RTU SBITA asset.
B76: Dr: Acct 0674 - RIGHT-TO-USE SBITA LIABILITY | J76: 844
B77: Dr: Acct 0475 - ACCUMULATED AMORTIZATION - RIGHT-TO-USE SBITA | J77: 835
B78: =VLOOKUP($F$8,'Drop Down Menus'!$D$2:$G$10,3,FALSE) -> Dr: Acct 0808 - GENERAL GOV. (GAAP ADJ)
C79: Cr: Acct 0480 - RIGHT-TO-USE SBITA - AMORTIZABLE | K79: 1671
C80: =VLOOKUP($F$8,'Drop Down Menus'!$D$2:$G$10,4,FALSE) -> Cr: Acct 0808 - GENERAL GOV. (GAAP ADJ) | K80: 8
J81: =ROUND(SUM(J76:J78),2) -> 1679 | K81: =ROUND(SUM(K79:K80),2) -> 1679 | L81: =IF(J81=K81,"<- Debits and Credits equal each other.","<- Debits and Credits do not equal each other.") -> <- Debits and Credits equal each other.
A83: 9 | B83: Record SBITA modifications to increase in the RTU SBITA asset.
B84: Dr: Acct 0480 - RIGHT-TO-USE SBITA - AMORTIZABLE
C85: Cr: Acct 0674 - RIGHT-TO-USE SBITA LIABILITY
J86: =SUM(J84) -> 0 | K86: =SUM(K85) -> 0 | L86: =IF(J86=K86,"<- Debits and Credits equal each other.","<- Debits and Credits do not equal each other.") -> <- Debits and Credits equal each other.
B88: NOTE: Please check the instructions for remeasurement and modifications on the SCO website.
D92: Informational - Ending Balances of Assets and Liabilities
K93: Debit (Credit)
D94: Acct 0480 - RIGHT-TO-USE SBITA - AMORTIZABLE | K94: =+J15+J34-K69-K79+J84 -> 0
D95: Acct 0475 - ACCUMULATED AMORTIZATION - RIGHT-TO-USE SBITA | K95: =-K18-K46+J68+J77 -> 0
D96: Acct 0674 - RIGHT-TO-USE SBITA LIABILITY | K96: =-K19-K37+J56+J61+J76-K85 -> 0
D97: Acct 0651 - RIGHT-TO-USE SBITA LIABILITY (CURRENT PORTION LT) | K97: =-K62 -> 0

Sheet Fund 3086 Journal Entries
A1: GASB 96 - SBITA Contracts Fund-by-Fund Journal Entries Form (to be submitted to the SCO annually—one form per fund)
A2: Manually complete every yellow field in this worksheet—there are no automatically calculated data-entry cells in this worksheet.
A3: Fiscal year: | F3: 2023–2024
A4: Organization Name: | F4: Department of Justice
A5: Organization Code (Business Unit): | F5: 0820
A6: Fund Number: | F6: 3086
A7: Fund Type: | F7: Governmental Fund
A8: Fund Classification: | F8: =IF(OR($F$7='Drop Down Menus'!B2,$F$7='Drop Down Menus'!$B$3),'Drop Down Menus'!$D$9,IFERROR(VLOOKUP($F$5,GAAP02Aindex!$A$2:$D$900,4,FALSE),"Unidentified")) -> GENERAL GOVERNMENT
A12: =IF($F$3="2022–2023","Establish Beginning Balances (SBITAs commenced on or before 07/01/2022)","Establish Beginning Balances (existing SBITAs only)") -> Establish Beginning Balances (existing SBITAs only)
A13: Entry #
A14: 0 | B14: =IF($F$3="2022–2023","To establish the beginning balance of SBITAs as of 07/01/2022.","Roll forward prior year right-to-use SBITAs to record opening balances.") -> Roll forward prior year right-to-use SBITAs to record opening balances. | M14: Department Beginning Balances | P14: From SCO BB List | S14: Difference
B15: Dr: Acct 0480 - RIGHT-TO-USE SBITA - AMORTIZABLE | J15: =ROUND(M15,0) -> 54222 | M15: 54222 | P15: 54222 | S15: =M15-P15 -> 0 | T15: Report any "Differences" on the Report 18 Differential.
B16: Dr: Acct 0950 - BEGINNING FUND BALANCE | J16: =ROUND(P16,0) -> 0 | M16: 457 | P16: =IF(SUM($Q$18:$Q$19)>$P$15,SUM($Q$18:$Q$19)-$P$15,0) -> 0 | S16: =M16-P16 -> 457 | T16: No action required.
B17: Dr: Acct 0952 - BEG FB ADJ/PRIOR PERIOD ADJUSTMENT | J17: =ROUND(IF(SUM($K$18:$K$20)>SUM($J$15:$J$16),SUM($K$18:$K$20)-SUM($J$15:$J$16),0),0) -> 0 | S17: =M17-P17 -> 0 | T17: No action required.
C18: Cr. Acct 0475 - ACCUMULATED AMORTIZATION - RIGHT-TO-USE SBITA | K18: =ROUND(N18,0) -> 32913 | N18: 32913 | Q18: 32913 | S18: =N18-Q18 -> 0 | T18: No action required.
C19: Cr: Acct 0674 - RIGHT-TO-USE SBITA LIABILITY | K19: =ROUND(N19,0) -> 17898 | N19: 17898 | Q19: 17898 | S19: =N19-Q19 -> 0 | T19: No action required.
C20: Cr: Acct 0950 - BEGINNING FUND BALANCE | K20: =ROUND(Q20,0) -> 3411 | N20: 3868 | Q20: =IF(SUM($Q$18:$Q$19)<$P$15,-SUM($Q$18:$Q$19)+$P$15,0) -> 3411 | S20: =N20-Q20 -> 457 | T20: No action required.
C21: Cr: Acct 0952 - BEG FB ADJ/PRIOR PERIOD ADJUSTMENT | K21: =ROUND(IF(SUM($K$18:$K$20)<SUM($J$15:$J$16),-SUM($K$18:$K$20)+SUM($J$15:$J$16),0),0) -> 0 | S21: =N21-Q21 -> 0 | T21: No action required.
J22: =ROUND(SUM(J15:J17),0) -> 54222 | K22: =ROUND(SUM(K18:K21),0) -> 54222 | L22: =IF(J22=K22,"<- Debits and Credits equal each other.","<- Debits and Credits do not equal each other.") -> <- Debits and Credits equal each other.
B24: SBITA ASSET (Acct 0480) AMOUNT SHOULD BE REPORTED AS BEGINNING BALANCE ON REPORT 18.
A26: =IF($F$3="2022–2023","Record SBITAs Commenced on or after 07/02/2022","Record New SBITAs (new SBITAs only)") -> Record New SBITAs (new SBITAs only)
A27: 1 | B27: Record at inception of SBITA in accordance with Fund-Based accounting (Governmental Funds Only).
B28: Dr: Acct 0842 - CAPITAL OUTLAY | J28: 1300314
C29: Cr: Acct 0789 - LEASE AND OTHER FINANCING PROCEEDS | K29: 1300314
C30: =VLOOKUP($F$8,'Drop Down Menus'!$D$2:$G$10,4,FALSE) -> Cr: Acct 0808 - GENERAL GOV. (GAAP ADJ)
J31: =ROUND(SUM(J28:J30),2) -> 1300314 | K31: =ROUND(SUM(K28:K30),2) -> 1300314 | L31: =IF(J31=K31,"<- Debits and Credits equal each other.","<- Debits and Credits do not equal each other.") -> <- Debits and Credits equal each other.
A33: 2 | B33: Reverse the fund-based entry in #1 above, if any, and record an inception of SBITA in accordance with GAAP Govt Wide.
B34: Dr: Acct 0480 - RIGHT-TO-USE SBITA - AMORTIZABLE | J34: 1300314
B35: Dr: Acct 0789 - LEASE AND OTHER FINANCING PROCEEDS | J35: 1300314
C36: Cr: Acct 0842 - CAPITAL OUTLAY | K36: 1300314
C37: Cr: Acct 0674 - RIGHT-TO-USE SBITA LIABILITY | K37: 1300314
C38: =VLOOKUP($F$8,'Drop Down Menus'!$D$2:$G$10,4,FALSE) -> Cr: Acct 0808 - GENERAL GOV. (GAAP ADJ)
J39: =ROUND(SUM(J34:J35),2) -> 2600628 | K39: =ROUND(SUM(K36:K38),2) -> 2600628 | L39: =IF(J39=K39,"<- Debits and Credits equal each other.","<- Debits and Credits do not equal each other.") -> <- Debits and Credits equal each other.
B41: SBITA ASSET (Acct 0480) AMOUNT SHOULD BE INCLUDED AS "ADDITIONS" ON REPORT 18.
A43: Record Annual Activity (all SBITAs)
A44: 3 | B44: Record amortization of the SBITA asset for the year.
B45: Dr: Acct 0875 - DEPRECIATION/AMORTIZATION | J45: 310268
C46: Cr. Acct 0475 - ACCUMULATED AMORTIZATION - RIGHT-TO-USE SBITA | K46: =J45 -> 310268
J47: =ROUND(SUM(J45:J45),2) -> 310268 | K47: =ROUND(SUM(K46),2) -> 310268 | L47: =IF(J47=K47,"<- Debits and Credits equal each other.","<- Debits and Credits do not equal each other.") -> <- Debits and Credits equal each other.
A49: 4 | B49: Reclassify information technology subscription exp. to debt service principal and interest exp.
B50: Dr: Acct 0848 - DEBT SERVICE - PRINCIPAL LEASES | J50: 449561 | L50: =IF($J$50=$K$57,"","<- Accts 0848 must agree")
B51: =IF(OR($F$7="Proprietary - Internal Service Fund",$F$7="Proprietary - Enterprise Fund"),"Dr: Acct 0894 - INTEREST EXPENSE AND FISCAL CHARGES","Dr: Acct 0851 - DEBT SERVICE - INTEREST LEASES") -> Dr: Acct 0851 - DEBT SERVICE - INTEREST LEASES | J51: 13645
C52: =VLOOKUP($F$8,'Drop Down Menus'!$D$2:$G$10,4,FALSE) -> Cr: Acct 0808 - GENERAL GOV. (GAAP ADJ) | K52: =+J50+J51 -> 463206
J53: =ROUND(SUM(J50:J51),2) -> 463206 | K53: =ROUND(SUM(K52,),2) -> 463206 | L53: =IF(J53=K53,"<- Debits and Credits equal each other.","<- Debits and Credits do not equal each other.") -> <- Debits and Credits equal each other.
A55: 5 | B55: Reduce SBITA liability for total current year principal payments.
B56: Dr: Acct 0674 - RIGHT-TO-USE SBITA LIABILITY | J56: 449561
C57: Cr: Acct 0848 - DEBT SERVICE - PRINCIPAL LEASES | K57: =J50 -> 449561 | L57: =IF($J$50=$K$57,"","<- Accts 0848 must agree")
J58: =ROUND(SUM(J56:J56),2) -> 449561 | K58: =ROUND(SUM(K57),2) -> 449561 | L58: =IF(J58=K58,"<- Debits and Credits equal each other.","<- Debits and Credits do not equal each other.") -> <- Debits and Credits equal each other.
A60: 6 | B60: Reclassify the principal amount due in the next FY to the current liability.
B61: Dr: Acct 0674 - RIGHT-TO-USE SBITA LIABILITY | J61: 428621
C62: Cr. Acct 0651 - RIGHT-TO-USE SBITA LIABILITY (CURRENT PORTION LT) | K62: =J61 -> 428621
B63: NOTE: This is an annual accrual. The RTU SBITA Liability - Current portion will be added back to the RTU SBITA Liability in entry #0 when reestablishing the beginning balances next year. | J63: =ROUND(SUM(J61:J61),2) -> 428621 | K63: =ROUND(SUM(K62),2) -> 428621 | L63: =IF(J63=K63,"<- Debits and Credits equal each other.","<- Debits and Credits do not equal each other.") -> <- Debits and Credits equal each other.
A66: Remove SBITA Asset at the End of the Subscription Term (only at the end of the subscription term)
A67: 7 | B67: Record entry to write off the SBITA asset and accumulated amortization at the end of the subscription term.
B68: Dr: Acct 0475 - ACCUMULATED AMORTIZATION - RIGHT-TO-USE SBITA | J68: 54222
C69: Cr: Acct 0480 - RIGHT-TO-USE SBITA - AMORTIZABLE | K69: 54222
J70: =SUM(J68) -> 54222 | K70: =SUM(K69) -> 54222 | L70: =IF(J70=K70,"<- Debits and Credits equal each other.","<- Debits and Credits do not equal each other.") -> <- Debits and Credits equal each other.
B72: SBITA ASSET (Acct 0480) SHOULD BE INCLUDED AS "DEDUCTIONS" ON REPORT 18.
A74: Record SBITA Remeasurement and Modifications (only if a significant modification occurred during the fiscal year)
A75: 8 | B75: Record early termination of SBITA contract or SBITA modifications to decrease in the RTU SBITA asset.
B76: Dr: Acct 0674 - RIGHT-TO-USE SBITA LIABILITY
B77: Dr: Acct 0475 - ACCUMULATED AMORTIZATION - RIGHT-TO-USE SBITA
B78: =VLOOKUP($F$8,'Drop Down Menus'!$D$2:$G$10,3,FALSE) -> Dr: Acct 0808 - GENERAL GOV. (GAAP ADJ)
C79: Cr: Acct 0480 - RIGHT-TO-USE SBITA - AMORTIZABLE
C80: =VLOOKUP($F$8,'Drop Down Menus'!$D$2:$G$10,4,FALSE) -> Cr: Acct 0808 - GENERAL GOV. (GAAP ADJ)
J81: =ROUND(SUM(J76:J78),2) -> 0 | K81: =ROUND(SUM(K79:K80),2) -> 0 | L81: =IF(J81=K81,"<- Debits and Credits equal each other.","<- Debits and Credits do not equal each other.") -> <- Debits and Credits equal each other.
A83: 9 | B83: Record SBITA modifications to increase in the RTU SBITA asset.
B84: Dr: Acct 0480 - RIGHT-TO-USE SBITA - AMORTIZABLE
C85: Cr: Acct 0674 - RIGHT-TO-USE SBITA LIABILITY
J86: =SUM(J84) -> 0 | K86: =SUM(K85) -> 0 | L86: =IF(J86=K86,"<- Debits and Credits equal each other.","<- Debits and Credits do not equal each other.") -> <- Debits and Credits equal each other.
B88: NOTE: Please check the instructions for remeasurement and modifications on the SCO website.
D92: Informational - Ending Balances of Assets and Liabilities
K93: Debit (Credit)
D94: Acct 0480 - RIGHT-TO-USE SBITA - AMORTIZABLE | K94: =+J15+J34-K69-K79+J84 -> 1300314
D95: Acct 0475 - ACCUMULATED AMORTIZATION - RIGHT-TO-USE SBITA | K95: =-K18-K46+J68+J77 -> -288959
D96: Acct 0674 - RIGHT-TO-USE SBITA LIABILITY | K96: =-K19-K37+J56+J61+J76-K85 -> -440030
D97: Acct 0651 - RIGHT-TO-USE SBITA LIABILITY (CURRENT PORTION LT) | K97: =-K62 -> -428621

Sheet Fund 3088 Journal Entries
A1: GASB 96 - SBITA Contracts Fund-by-Fund Journal Entries Form (to be submitted to the SCO annually—one form per fund)
A2: Manually complete every yellow field in this worksheet—there are no automatically calculated data-entry cells in this worksheet.
A3: Fiscal year: | F3: 2023–2024
A4: Organization Name: | F4: Department of Justice
A5: Organization Code (Business Unit): | F5: 0820
A6: Fund Number: | F6: 3088
A7: Fund Type: | F7: Governmental Fund
A8: Fund Classification: | F8: =IF(OR($F$7='Drop Down Menus'!B2,$F$7='Drop Down Menus'!$B$3),'Drop Down Menus'!$D$9,IFERROR(VLOOKUP($F$5,GAAP02Aindex!$A$2:$D$900,4,FALSE),"Unidentified")) -> GENERAL GOVERNMENT
A12: =IF($F$3="2022–2023","Establish Beginning Balances (SBITAs commenced on or before 07/01/2022)","Establish Beginning Balances (existing SBITAs only)") -> Establish Beginning Balances (existing SBITAs only)
A13: Entry #
A14: 0 | B14: =IF($F$3="2022–2023","To establish the beginning balance of SBITAs as of 07/01/2022.","Roll forward prior year right-to-use SBITAs to record opening balances.") -> Roll forward prior year right-to-use SBITAs to record opening balances. | M14: Department Beginning Balances | P14: From SCO BB List | S14: Difference
B15: Dr: Acct 0480 - RIGHT-TO-USE SBITA - AMORTIZABLE | J15: =ROUND(M15,0) -> 6156 | M15: 6156 | P15: 6156 | S15: =M15-P15 -> 0 | T15: Report any "Differences" on the Report 18 Differential.
B16: Dr: Acct 0950 - BEGINNING FUND BALANCE | J16: =ROUND(P16,0) -> 0 | M16: 20 | P16: =IF(SUM($Q$18:$Q$19)>$P$15,SUM($Q$18:$Q$19)-$P$15,0) -> 0 | S16: =M16-P16 -> 20 | T16: No action required.
B17: Dr: Acct 0952 - BEG FB ADJ/PRIOR PERIOD ADJUSTMENT | J17: =ROUND(IF(SUM($K$18:$K$20)>SUM($J$15:$J$16),SUM($K$18:$K$20)-SUM($J$15:$J$16),0),0) -> 0 | S17: =M17-P17 -> 0 | T17: No action required.
C18: Cr. Acct 0475 - ACCUMULATED AMORTIZATION - RIGHT-TO-USE SBITA | K18: =ROUND(N18,0) -> 3455 | N18: 3455 | Q18: 3455 | S18: =N18-Q18 -> 0 | T18: No action required.
C19: Cr: Acct 0674 - RIGHT-TO-USE SBITA LIABILITY | K19: =ROUND(N19,0) -> 2310 | N19: 2310 | Q19: 2310 | S19: =N19-Q19 -> 0 | T19: No action required.
C20: Cr: Acct 0950 - BEGINNING FUND BALANCE | K20: =ROUND(Q20,0) -> 391 | N20: 411 | Q20: =IF(SUM($Q$18:$Q$19)<$P$15,-SUM($Q$18:$Q$19)+$P$15,0) -> 391 | S20: =N20-Q20 -> 20 | T20: No action required.
C21: Cr: Acct 0952 - BEG FB ADJ/PRIOR PERIOD ADJUSTMENT | K21: =ROUND(IF(SUM($K$18:$K$20)<SUM($J$15:$J$16),-SUM($K$18:$K$20)+SUM($J$15:$J$16),0),0) -> 0 | S21: =N21-Q21 -> 0 | T21: No action required.
J22: =ROUND(SUM(J15:J17),0) -> 6156 | K22: =ROUND(SUM(K18:K21),0) -> 6156 | L22: =IF(J22=K22,"<- Debits and Credits equal each other.","<- Debits and Credits do not equal each other.") -> <- Debits and Credits equal each other.
B24: SBITA ASSET (Acct 0480) AMOUNT SHOULD BE REPORTED AS BEGINNING BALANCE ON REPORT 18.
A26: =IF($F$3="2022–2023","Record SBITAs Commenced on or after 07/02/2022","Record New SBITAs (new SBITAs only)") -> Record New SBITAs (new SBITAs only)
A27: 1 | B27: Record at inception of SBITA in accordance with Fund-Based accounting (Governmental Funds Only).
B28: Dr: Acct 0842 - CAPITAL OUTLAY | J28: 15430
C29: Cr: Acct 0789 - LEASE AND OTHER FINANCING PROCEEDS | K29: 15430
C30: =VLOOKUP($F$8,'Drop Down Menus'!$D$2:$G$10,4,FALSE) -> Cr: Acct 0808 - GENERAL GOV. (GAAP ADJ)
J31: =ROUND(SUM(J28:J30),2) -> 15430 | K31: =ROUND(SUM(K28:K30),2) -> 15430 | L31: =IF(J31=K31,"<- Debits and Credits equal each other.","<- Debits and Credits do not equal each other.") -> <- Debits and Credits equal each other.
A33: 2 | B33: Reverse the fund-based entry in #1 above, if any, and record an inception of SBITA in accordance with GAAP Govt Wide.
B34: Dr: Acct 0480 - RIGHT-TO-USE SBITA - AMORTIZABLE | J34: 15430
B35: Dr: Acct 0789 - LEASE AND OTHER FINANCING PROCEEDS | J35: 15430
C36: Cr: Acct 0842 - CAPITAL OUTLAY | K36: 15430
C37: Cr: Acct 0674 - RIGHT-TO-USE SBITA LIABILITY | K37: 15430
C38: =VLOOKUP($F$8,'Drop Down Menus'!$D$2:$G$10,4,FALSE) -> Cr: Acct 0808 - GENERAL GOV. (GAAP ADJ)
J39: =ROUND(SUM(J34:J35),2) -> 30860 | K39: =ROUND(SUM(K36:K38),2) -> 30860 | L39: =IF(J39=K39,"<- Debits and Credits equal each other.","<- Debits and Credits do not equal each other.") -> <- Debits and Credits equal each other.
B41: SBITA ASSET (Acct 0480) AMOUNT SHOULD BE INCLUDED AS "ADDITIONS" ON REPORT 18.
A43: Record Annual Activity (all SBITAs)
A44: 3 | B44: Record amortization of the SBITA asset for the year.
B45: Dr: Acct 0875 - DEPRECIATION/AMORTIZATION | J45: 4087
C46: Cr. Acct 0475 - ACCUMULATED AMORTIZATION - RIGHT-TO-USE SBITA | K46: =J45 -> 4087
J47: =ROUND(SUM(J45:J45),2) -> 4087 | K47: =ROUND(SUM(K46),2) -> 4087 | L47: =IF(J47=K47,"<- Debits and Credits equal each other.","<- Debits and Credits do not equal each other.") -> <- Debits and Credits equal each other.
A49: 4 | B49: Reclassify information technology subscription exp. to debt service principal and interest exp.
B50: Dr: Acct 0848 - DEBT SERVICE - PRINCIPAL LEASES | J50: 5523 | L50: =IF($J$50=$K$57,"","<- Accts 0848 must agree")
B51: =IF(OR($F$7="Proprietary - Internal Service Fund",$F$7="Proprietary - Enterprise Fund"),"Dr: Acct 0894 - INTEREST EXPENSE AND FISCAL CHARGES","Dr: Acct 0851 - DEBT SERVICE - INTEREST LEASES") -> Dr: Acct 0851 - DEBT SERVICE - INTEREST LEASES | J51: 189
C52: =VLOOKUP($F$8,'Drop Down Menus'!$D$2:$G$10,4,FALSE) -> Cr: Acct 0808 - GENERAL GOV. (GAAP ADJ) | K52: =+J50+J51 -> 5712
J53: =ROUND(SUM(J50:J51),2) -> 5712 | K53: =ROUND(SUM(K52,),2) -> 5712 | L53: =IF(J53=K53,"<- Debits and Credits equal each other.","<- Debits and Credits do not equal each other.") -> <- Debits and Credits equal each other.
A55: 5 | B55: Reduce SBITA liability for total current year principal payments.
B56: Dr: Acct 0674 - RIGHT-TO-USE SBITA LIABILITY | J56: 5523
C57: Cr: Acct 0848 - DEBT SERVICE - PRINCIPAL LEASES | K57: =J50 -> 5523 | L57: =IF($J$50=$K$57,"","<- Accts 0848 must agree")
J58: =ROUND(SUM(J56:J56),2) -> 5523 | K58: =ROUND(SUM(K57),2) -> 5523 | L58: =IF(J58=K58,"<- Debits and Credits equal each other.","<- Debits and Credits do not equal each other.") -> <- Debits and Credits equal each other.
A60: 6 | B60: Reclassify the principal amount due in the next FY to the current liability.
B61: Dr: Acct 0674 - RIGHT-TO-USE SBITA LIABILITY | J61: 5491
C62: Cr. Acct 0651 - RIGHT-TO-USE SBITA LIABILITY (CURRENT PORTION LT) | K62: =J61 -> 5491
B63: NOTE: This is an annual accrual. The RTU SBITA Liability - Current portion will be added back to the RTU SBITA Liability in entry #0 when reestablishing the beginning balances next year. | J63: =ROUND(SUM(J61:J61),2) -> 5491 | K63: =ROUND(SUM(K62),2) -> 5491 | L63: =IF(J63=K63,"<- Debits and Credits equal each other.","<- Debits and Credits do not equal each other.") -> <- Debits and Credits equal each other.
A66: Remove SBITA Asset at the End of the Subscription Term (only at the end of the subscription term)
A67: 7 | B67: Record entry to write off the SBITA asset and accumulated amortization at the end of the subscription term.
B68: Dr: Acct 0475 - ACCUMULATED AMORTIZATION - RIGHT-TO-USE SBITA | J68: 2055
C69: Cr: Acct 0480 - RIGHT-TO-USE SBITA - AMORTIZABLE | K69: 2055
J70: =SUM(J68) -> 2055 | K70: =SUM(K69) -> 2055 | L70: =IF(J70=K70,"<- Debits and Credits equal each other.","<- Debits and Credits do not equal each other.") -> <- Debits and Credits equal each other.
B72: SBITA ASSET (Acct 0480) SHOULD BE INCLUDED AS "DEDUCTIONS" ON REPORT 18.
A74: Record SBITA Remeasurement and Modifications (only if a significant modification occurred during the fiscal year)
A75: 8 | B75: Record early termination of SBITA contract or SBITA modifications to decrease in the RTU SBITA asset.
B76: Dr: Acct 0674 - RIGHT-TO-USE SBITA LIABILITY | J76: 404
B77: Dr: Acct 0475 - ACCUMULATED AMORTIZATION - RIGHT-TO-USE SBITA | J77: 1602
B78: =VLOOKUP($F$8,'Drop Down Menus'!$D$2:$G$10,3,FALSE) -> Dr: Acct 0808 - GENERAL GOV. (GAAP ADJ)
C79: Cr: Acct 0480 - RIGHT-TO-USE SBITA - AMORTIZABLE | K79: 2002
C80: =VLOOKUP($F$8,'Drop Down Menus'!$D$2:$G$10,4,FALSE) -> Cr: Acct 0808 - GENERAL GOV. (GAAP ADJ) | K80: 4
J81: =ROUND(SUM(J76:J78),2) -> 2006 | K81: =ROUND(SUM(K79:K80),2) -> 2006 | L81: =IF(J81=K81,"<- Debits and Credits equal each other.","<- Debits and Credits do not equal each other.") -> <- Debits and Credits equal each other.
A83: 9 | B83: Record SBITA modifications to increase in the RTU SBITA asset.
B84: Dr: Acct 0480 - RIGHT-TO-USE SBITA - AMORTIZABLE
C85: Cr: Acct 0674 - RIGHT-TO-USE SBITA LIABILITY
J86: =SUM(J84) -> 0 | K86: =SUM(K85) -> 0 | L86: =IF(J86=K86,"<- Debits and Credits equal each other.","<- Debits and Credits do not equal each other.") -> <- Debits and Credits equal each other.
B88: NOTE: Please check the instructions for remeasurement and modifications on the SCO website.
D92: Informational - Ending Balances of Assets and Liabilities
K93: Debit (Credit)
D94: Acct 0480 - RIGHT-TO-USE SBITA - AMORTIZABLE | K94: =+J15+J34-K69-K79+J84 -> 17529
D95: Acct 0475 - ACCUMULATED AMORTIZATION - RIGHT-TO-USE SBITA | K95: =-K18-K46+J68+J77 -> -3885
D96: Acct 0674 - RIGHT-TO-USE SBITA LIABILITY | K96: =-K19-K37+J56+J61+J76-K85 -> -6322
D97: Acct 0651 - RIGHT-TO-USE SBITA LIABILITY (CURRENT PORTION LT) | K97: =-K62 -> -5491

Sheet Fund 3297 Journal Entries
A1: GASB 96 - SBITA Contracts Fund-by-Fund Journal Entries Form (to be submitted to the SCO annually—one form per fund)
A2: Manually complete every yellow field in this worksheet—there are no automatically calculated data-entry cells in this worksheet.
A3: Fiscal year: | F3: 2023–2024
A4: Organization Name: | F4: Department of Justice
A5: Organization Code (Business Unit): | F5: 0820
A6: Fund Number: | F6: 3297
A7: Fund Type: | F7: Governmental Fund
A8: Fund Classification: | F8: =IF(OR($F$7='Drop Down Menus'!B2,$F$7='Drop Down Menus'!$B$3),'Drop Down Menus'!$D$9,IFERROR(VLOOKUP($F$5,GAAP02Aindex!$A$2:$D$900,4,FALSE),"Unidentified")) -> GENERAL GOVERNMENT
A12: =IF($F$3="2022–2023","Establish Beginning Balances (SBITAs commenced on or before 07/01/2022)","Establish Beginning Balances (existing SBITAs only)") -> Establish Beginning Balances (existing SBITAs only)
A13: Entry #
A14: 0 | B14: =IF($F$3="2022–2023","To establish the beginning balance of SBITAs as of 07/01/2022.","Roll forward prior year right-to-use SBITAs to record opening balances.") -> Roll forward prior year right-to-use SBITAs to record opening balances. | M14: Department Beginning Balances | P14: From SCO BB List | S14: Difference
B15: Dr: Acct 0480 - RIGHT-TO-USE SBITA - AMORTIZABLE | J15: =ROUND(M15,0) -> 395 | M15: 395 | P15: 395 | S15: =M15-P15 -> 0 | T15: Report any "Differences" on the Report 18 Differential.
B16: Dr: Acct 0950 - BEGINNING FUND BALANCE | J16: =ROUND(P16,0) -> 5 | M16: 5 | P16: =IF(SUM($Q$18:$Q$19)>$P$15,SUM($Q$18:$Q$19)-$P$15,0) -> 5 | S16: =M16-P16 -> 0 | T16: No action required.
B17: Dr: Acct 0952 - BEG FB ADJ/PRIOR PERIOD ADJUSTMENT | J17: =ROUND(IF(SUM($K$18:$K$20)>SUM($J$15:$J$16),SUM($K$18:$K$20)-SUM($J$15:$J$16),0),0) -> 0 | S17: =M17-P17 -> 0 | T17: No action required.
C18: Cr. Acct 0475 - ACCUMULATED AMORTIZATION - RIGHT-TO-USE SBITA | K18: =ROUND(N18,0) -> 197 | N18: 197 | Q18: 197 | S18: =N18-Q18 -> 0 | T18: No action required.
C19: Cr: Acct 0674 - RIGHT-TO-USE SBITA LIABILITY | K19: =ROUND(N19,0) -> 203 | N19: 203 | Q19: 203 | S19: =N19-Q19 -> 0 | T19: No action required.
C20: Cr: Acct 0950 - BEGINNING FUND BALANCE | K20: =ROUND(Q20,0) -> 0 | Q20: =IF(SUM($Q$18:$Q$19)<$P$15,-SUM($Q$18:$Q$19)+$P$15,0) -> 0 | S20: =N20-Q20 -> 0 | T20: No action required.
C21: Cr: Acct 0952 - BEG FB ADJ/PRIOR PERIOD ADJUSTMENT | K21: =ROUND(IF(SUM($K$18:$K$20)<SUM($J$15:$J$16),-SUM($K$18:$K$20)+SUM($J$15:$J$16),0),0) -> 0 | S21: =N21-Q21 -> 0 | T21: No action required.
J22: =ROUND(SUM(J15:J17),0) -> 400 | K22: =ROUND(SUM(K18:K21),0) -> 400 | L22: =IF(J22=K22,"<- Debits and Credits equal each other.","<- Debits and Credits do not equal each other.") -> <- Debits and Credits equal each other.
B24: SBITA ASSET (Acct 0480) AMOUNT SHOULD BE REPORTED AS BEGINNING BALANCE ON REPORT 18.
A26: =IF($F$3="2022–2023","Record SBITAs Commenced on or after 07/02/2022","Record New SBITAs (new SBITAs only)") -> Record New SBITAs (new SBITAs only)
A27: 1 | B27: Record at inception of SBITA in accordance with Fund-Based accounting (Governmental Funds Only).
B28: Dr: Acct 0842 - CAPITAL OUTLAY
C29: Cr: Acct 0789 - LEASE AND OTHER FINANCING PROCEEDS
C30: =VLOOKUP($F$8,'Drop Down Menus'!$D$2:$G$10,4,FALSE) -> Cr: Acct 0808 - GENERAL GOV. (GAAP ADJ)
J31: =ROUND(SUM(J28:J30),2) -> 0 | K31: =ROUND(SUM(K28:K30),2) -> 0 | L31: =IF(J31=K31,"<- Debits and Credits equal each other.","<- Debits and Credits do not equal each other.") -> <- Debits and Credits equal each other.
A33: 2 | B33: Reverse the fund-based entry in #1 above, if any, and record an inception of SBITA in accordance with GAAP Govt Wide.
B34: Dr: Acct 0480 - RIGHT-TO-USE SBITA - AMORTIZABLE
B35: Dr: Acct 0789 - LEASE AND OTHER FINANCING PROCEEDS
C36: Cr: Acct 0842 - CAPITAL OUTLAY
C37: Cr: Acct 0674 - RIGHT-TO-USE SBITA LIABILITY
C38: =VLOOKUP($F$8,'Drop Down Menus'!$D$2:$G$10,4,FALSE) -> Cr: Acct 0808 - GENERAL GOV. (GAAP ADJ)
J39: =ROUND(SUM(J34:J35),2) -> 0 | K39: =ROUND(SUM(K36:K38),2) -> 0 | L39: =IF(J39=K39,"<- Debits and Credits equal each other.","<- Debits and Credits do not equal each other.") -> <- Debits and Credits equal each other.
B41: SBITA ASSET (Acct 0480) AMOUNT SHOULD BE INCLUDED AS "ADDITIONS" ON REPORT 18.
A43: Record Annual Activity (all SBITAs)
A44: 3 | B44: Record amortization of the SBITA asset for the year.
B45: Dr: Acct 0875 - DEPRECIATION/AMORTIZATION | J45: 198
C46: Cr. Acct 0475 - ACCUMULATED AMORTIZATION - RIGHT-TO-USE SBITA | K46: 198
J47: =ROUND(SUM(J45:J45),2) -> 198 | K47: =ROUND(SUM(K46),2) -> 198 | L47: =IF(J47=K47,"<- Debits and Credits equal each other.","<- Debits and Credits do not equal each other.") -> <- Debits and Credits equal each other.
A49: 4 | B49: Reclassify information technology subscription exp. to debt service principal and interest exp.
B50: Dr: Acct 0848 - DEBT SERVICE - PRINCIPAL LEASES | J50: 203 | L50: =IF($J$50=$K$57,"","<- Accts 0848 must agree")
B51: =IF(OR($F$7="Proprietary - Internal Service Fund",$F$7="Proprietary - Enterprise Fund"),"Dr: Acct 0894 - INTEREST EXPENSE AND FISCAL CHARGES","Dr: Acct 0851 - DEBT SERVICE - INTEREST LEASES") -> Dr: Acct 0851 - DEBT SERVICE - INTEREST LEASES | J51: 5
C52: =VLOOKUP($F$8,'Drop Down Menus'!$D$2:$G$10,4,FALSE) -> Cr: Acct 0808 - GENERAL GOV. (GAAP ADJ) | K52: =+J50+J51 -> 208
J53: =ROUND(SUM(J50:J51),2) -> 208 | K53: =ROUND(SUM(K52,),2) -> 208 | L53: =IF(J53=K53,"<- Debits and Credits equal each other.","<- Debits and Credits do not equal each other.") -> <- Debits and Credits equal each other.
A55: 5 | B55: Reduce SBITA liability for total current year principal payments.
B56: Dr: Acct 0674 - RIGHT-TO-USE SBITA LIABILITY | J56: 203
C57: Cr: Acct 0848 - DEBT SERVICE - PRINCIPAL LEASES | K57: =J50 -> 203 | L57: =IF($J$50=$K$57,"","<- Accts 0848 must agree")
J58: =ROUND(SUM(J56:J56),2) -> 203 | K58: =ROUND(SUM(K57),2) -> 203 | L58: =IF(J58=K58,"<- Debits and Credits equal each other.","<- Debits and Credits do not equal each other.") -> <- Debits and Credits equal each other.
A60: 6 | B60: Reclassify the principal amount due in the next FY to the current liability.
B61: Dr: Acct 0674 - RIGHT-TO-USE SBITA LIABILITY
C62: Cr. Acct 0651 - RIGHT-TO-USE SBITA LIABILITY (CURRENT PORTION LT) | K62: =J61 -> 0
B63: NOTE: This is an annual accrual. The RTU SBITA Liability - Current portion will be added back to the RTU SBITA Liability in entry #0 when reestablishing the beginning balances next year. | J63: =ROUND(SUM(J61:J61),2) -> 0 | K63: =ROUND(SUM(K62),2) -> 0 | L63: =IF(J63=K63,"<- Debits and Credits equal each other.","<- Debits and Credits do not equal each other.") -> <- Debits and Credits equal each other.
A66: Remove SBITA Asset at the End of the Subscription Term (only at the end of the subscription term)
A67: 7 | B67: Record entry to write off the SBITA asset and accumulated amortization at the end of the subscription term.
B68: Dr: Acct 0475 - ACCUMULATED AMORTIZATION - RIGHT-TO-USE SBITA | J68: 395
C69: Cr: Acct 0480 - RIGHT-TO-USE SBITA - AMORTIZABLE | K69: 395
J70: =SUM(J68) -> 395 | K70: =SUM(K69) -> 395 | L70: =IF(J70=K70,"<- Debits and Credits equal each other.","<- Debits and Credits do not equal each other.") -> <- Debits and Credits equal each other.
B72: SBITA ASSET (Acct 0480) SHOULD BE INCLUDED AS "DEDUCTIONS" ON REPORT 18.
A74: Record SBITA Remeasurement and Modifications (only if a significant modification occurred during the fiscal year)
A75: 8 | B75: Record early termination of SBITA contract or SBITA modifications to decrease in the RTU SBITA asset.
B76: Dr: Acct 0674 - RIGHT-TO-USE SBITA LIABILITY
B77: Dr: Acct 0475 - ACCUMULATED AMORTIZATION - RIGHT-TO-USE SBITA
B78: =VLOOKUP($F$8,'Drop Down Menus'!$D$2:$G$10,3,FALSE) -> Dr: Acct 0808 - GENERAL GOV. (GAAP ADJ)
C79: Cr: Acct 0480 - RIGHT-TO-USE SBITA - AMORTIZABLE
C80: =VLOOKUP($F$8,'Drop Down Menus'!$D$2:$G$10,4,FALSE) -> Cr: Acct 0808 - GENERAL GOV. (GAAP ADJ)
J81: =ROUND(SUM(J76:J78),2) -> 0 | K81: =ROUND(SUM(K79:K80),2) -> 0 | L81: =IF(J81=K81,"<- Debits and Credits equal each other.","<- Debits and Credits do not equal each other.") -> <- Debits and Credits equal each other.
A83: 9 | B83: Record SBITA modifications to increase in the RTU SBITA asset.
B84: Dr: Acct 0480 - RIGHT-TO-USE SBITA - AMORTIZABLE
C85: Cr: Acct 0674 - RIGHT-TO-USE SBITA LIABILITY
J86: =SUM(J84) -> 0 | K86: =SUM(K85) -> 0 | L86: =IF(J86=K86,"<- Debits and Credits equal each other.","<- Debits and Credits do not equal each other.") -> <- Debits and Credits equal each other.
B88: NOTE: Please check the instructions for remeasurement and modifications on the SCO website.
D92: Informational - Ending Balances of Assets and Liabilities
K93: Debit (Credit)
D94: Acct 0480 - RIGHT-TO-USE SBITA - AMORTIZABLE | K94: =+J15+J34-K69-K79+J84 -> 0
D95: Acct 0475 - ACCUMULATED AMORTIZATION - RIGHT-TO-USE SBITA | K95: =-K18-K46+J68+J77 -> 0
D96: Acct 0674 - RIGHT-TO-USE SBITA LIABILITY | K96: =-K19-K37+J56+J61+J76-K85 -> 0
D97: Acct 0651 - RIGHT-TO-USE SBITA LIABILITY (CURRENT PORTION LT) | K97: =-K62 -> 0

Sheet Fund 3320 Journal Entries
A1: GASB 96 - SBITA Contracts Fund-by-Fund Journal Entries Form (to be submitted to the SCO annually—one form per fund)
A2: Manually complete every yellow field in this worksheet—there are no automatically calculated data-entry cells in this worksheet.
A3: Fiscal year: | F3: 2023–2024
A4: Organization Name: | F4: Department of Justice
A5: Organization Code (Business Unit): | F5: 0820
A6: Fund Number: | F6: 3320
A7: Fund Type: | F7: Governmental Fund
A8: Fund Classification: | F8: =IF(OR($F$7='Drop Down Menus'!B2,$F$7='Drop Down Menus'!$B$3),'Drop Down Menus'!$D$9,IFERROR(VLOOKUP($F$5,GAAP02Aindex!$A$2:$D$900,4,FALSE),"Unidentified")) -> GENERAL GOVERNMENT
A12: =IF($F$3="2022–2023","Establish Beginning Balances (SBITAs commenced on or before 07/01/2022)","Establish Beginning Balances (existing SBITAs only)") -> Establish Beginning Balances (existing SBITAs only)
A13: Entry #
A14: 0 | B14: =IF($F$3="2022–2023","To establish the beginning balance of SBITAs as of 07/01/2022.","Roll forward prior year right-to-use SBITAs to record opening balances.") -> Roll forward prior year right-to-use SBITAs to record opening balances. | M14: Department Beginning Balances | P14: From SCO BB List | S14: Difference
B15: Dr: Acct 0480 - RIGHT-TO-USE SBITA - AMORTIZABLE | J15: =ROUND(M15,0) -> 616020 | M15: 616020 | P15: 616020 | S15: =M15-P15 -> 0 | T15: Report any "Differences" on the Report 18 Differential.
B16: Dr: Acct 0950 - BEGINNING FUND BALANCE | J16: =ROUND(P16,0) -> 3072 | M16: 3072 | P16: =IF(SUM($Q$18:$Q$19)>$P$15,SUM($Q$18:$Q$19)-$P$15,0) -> 3072 | S16: =M16-P16 -> 0 | T16: No action required.
B17: Dr: Acct 0952 - BEG FB ADJ/PRIOR PERIOD ADJUSTMENT | J17: =ROUND(IF(SUM($K$18:$K$20)>SUM($J$15:$J$16),SUM($K$18:$K$20)-SUM($J$15:$J$16),0),0) -> 0 | S17: =M17-P17 -> 0 | T17: No action required.
C18: Cr. Acct 0475 - ACCUMULATED AMORTIZATION - RIGHT-TO-USE SBITA | K18: =ROUND(N18,0) -> 308010 | N18: 308010 | Q18: 308010 | S18: =N18-Q18 -> 0 | T18: No action required.
C19: Cr: Acct 0674 - RIGHT-TO-USE SBITA LIABILITY | K19: =ROUND(N19,0) -> 311082 | N19: 311082 | Q19: 311082 | S19: =N19-Q19 -> 0 | T19: No action required.
C20: Cr: Acct 0950 - BEGINNING FUND BALANCE | K20: =ROUND(Q20,0) -> 0 | Q20: =IF(SUM($Q$18:$Q$19)<$P$15,-SUM($Q$18:$Q$19)+$P$15,0) -> 0 | S20: =N20-Q20 -> 0 | T20: No action required.
C21: Cr: Acct 0952 - BEG FB ADJ/PRIOR PERIOD ADJUSTMENT | K21: =ROUND(IF(SUM($K$18:$K$20)<SUM($J$15:$J$16),-SUM($K$18:$K$20)+SUM($J$15:$J$16),0),0) -> 0 | S21: =N21-Q21 -> 0 | T21: No action required.
J22: =ROUND(SUM(J15:J17),0) -> 619092 | K22: =ROUND(SUM(K18:K21),0) -> 619092 | L22: =IF(J22=K22,"<- Debits and Credits equal each other.","<- Debits and Credits do not equal each other.") -> <- Debits and Credits equal each other.
B24: SBITA ASSET (Acct 0480) AMOUNT SHOULD BE REPORTED AS BEGINNING BALANCE ON REPORT 18.
A26: =IF($F$3="2022–2023","Record SBITAs Commenced on or after 07/02/2022","Record New SBITAs (new SBITAs only)") -> Record New SBITAs (new SBITAs only)
A27: 1 | B27: Record at inception of SBITA in accordance with Fund-Based accounting (Governmental Funds Only).
B28: Dr: Acct 0842 - CAPITAL OUTLAY
C29: Cr: Acct 0789 - LEASE AND OTHER FINANCING PROCEEDS
C30: =VLOOKUP($F$8,'Drop Down Menus'!$D$2:$G$10,4,FALSE) -> Cr: Acct 0808 - GENERAL GOV. (GAAP ADJ)
J31: =ROUND(SUM(J28:J30),2) -> 0 | K31: =ROUND(SUM(K28:K30),2) -> 0 | L31: =IF(J31=K31,"<- Debits and Credits equal each other.","<- Debits and Credits do not equal each other.") -> <- Debits and Credits equal each other.
A33: 2 | B33: Reverse the fund-based entry in #1 above, if any, and record an inception of SBITA in accordance with GAAP Govt Wide.
B34: Dr: Acct 0480 - RIGHT-TO-USE SBITA - AMORTIZABLE
B35: Dr: Acct 0789 - LEASE AND OTHER FINANCING PROCEEDS
C36: Cr: Acct 0842 - CAPITAL OUTLAY
C37: Cr: Acct 0674 - RIGHT-TO-USE SBITA LIABILITY
C38: =VLOOKUP($F$8,'Drop Down Menus'!$D$2:$G$10,4,FALSE) -> Cr: Acct 0808 - GENERAL GOV. (GAAP ADJ)
J39: =ROUND(SUM(J34:J35),2) -> 0 | K39: =ROUND(SUM(K36:K38),2) -> 0 | L39: =IF(J39=K39,"<- Debits and Credits equal each other.","<- Debits and Credits do not equal each other.") -> <- Debits and Credits equal each other.
B41: SBITA ASSET (Acct 0480) AMOUNT SHOULD BE INCLUDED AS "ADDITIONS" ON REPORT 18.
A43: Record Annual Activity (all SBITAs)
A44: 3 | B44: Record amortization of the SBITA asset for the year.
B45: Dr: Acct 0875 - DEPRECIATION/AMORTIZATION | J45: 308010
C46: Cr. Acct 0475 - ACCUMULATED AMORTIZATION - RIGHT-TO-USE SBITA | K46: =J45 -> 308010
J47: =ROUND(SUM(J45:J45),2) -> 308010 | K47: =ROUND(SUM(K46),2) -> 308010 | L47: =IF(J47=K47,"<- Debits and Credits equal each other.","<- Debits and Credits do not equal each other.") -> <- Debits and Credits equal each other.
A49: 4 | B49: Reclassify information technology subscription exp. to debt service principal and interest exp.
B50: Dr: Acct 0848 - DEBT SERVICE - PRINCIPAL LEASES | J50: 311082 | L50: =IF($J$50=$K$57,"","<- Accts 0848 must agree")
B51: =IF(OR($F$7="Proprietary - Internal Service Fund",$F$7="Proprietary - Enterprise Fund"),"Dr: Acct 0894 - INTEREST EXPENSE AND FISCAL CHARGES","Dr: Acct 0851 - DEBT SERVICE - INTEREST LEASES") -> Dr: Acct 0851 - DEBT SERVICE - INTEREST LEASES | J51: 4061
C52: =VLOOKUP($F$8,'Drop Down Menus'!$D$2:$G$10,4,FALSE) -> Cr: Acct 0808 - GENERAL GOV. (GAAP ADJ) | K52: =+J50+J51 -> 315143
J53: =ROUND(SUM(J50:J51),2) -> 315143 | K53: =ROUND(SUM(K52,),2) -> 315143 | L53: =IF(J53=K53,"<- Debits and Credits equal each other.","<- Debits and Credits do not equal each other.") -> <- Debits and Credits equal each other.
A55: 5 | B55: Reduce SBITA liability for total current year principal payments.
B56: Dr: Acct 0674 - RIGHT-TO-USE SBITA LIABILITY | J56: 311082
C57: Cr: Acct 0848 - DEBT SERVICE - PRINCIPAL LEASES | K57: =J50 -> 311082 | L57: =IF($J$50=$K$57,"","<- Accts 0848 must agree")
J58: =ROUND(SUM(J56:J56),2) -> 311082 | K58: =ROUND(SUM(K57),2) -> 311082 | L58: =IF(J58=K58,"<- Debits and Credits equal each other.","<- Debits and Credits do not equal each other.") -> <- Debits and Credits equal each other.
A60: 6 | B60: Reclassify the principal amount due in the next FY to the current liability.
B61: Dr: Acct 0674 - RIGHT-TO-USE SBITA LIABILITY
C62: Cr. Acct 0651 - RIGHT-TO-USE SBITA LIABILITY (CURRENT PORTION LT) | K62: =J61 -> 0
B63: NOTE: This is an annual accrual. The RTU SBITA Liability - Current portion will be added back to the RTU SBITA Liability in entry #0 when reestablishing the beginning balances next year. | J63: =ROUND(SUM(J61:J61),2) -> 0 | K63: =ROUND(SUM(K62),2) -> 0 | L63: =IF(J63=K63,"<- Debits and Credits equal each other.","<- Debits and Credits do not equal each other.") -> <- Debits and Credits equal each other.
A66: Remove SBITA Asset at the End of the Subscription Term (only at the end of the subscription term)
A67: 7 | B67: Record entry to write off the SBITA asset and accumulated amortization at the end of the subscription term.
B68: Dr: Acct 0475 - ACCUMULATED AMORTIZATION - RIGHT-TO-USE SBITA | J68: 616020
C69: Cr: Acct 0480 - RIGHT-TO-USE SBITA - AMORTIZABLE | K69: 616020
J70: =SUM(J68) -> 616020 | K70: =SUM(K69) -> 616020 | L70: =IF(J70=K70,"<- Debits and Credits equal each other.","<- Debits and Credits do not equal each other.") -> <- Debits and Credits equal each other.
B72: SBITA ASSET (Acct 0480) SHOULD BE INCLUDED AS "DEDUCTIONS" ON REPORT 18.
A74: Record SBITA Remeasurement and Modifications (only if a significant modification occurred during the fiscal year)
A75: 8 | B75: Record early termination of SBITA contract or SBITA modifications to decrease in the RTU SBITA asset.
B76: Dr: Acct 0674 - RIGHT-TO-USE SBITA LIABILITY
B77: Dr: Acct 0475 - ACCUMULATED AMORTIZATION - RIGHT-TO-USE SBITA
B78: =VLOOKUP($F$8,'Drop Down Menus'!$D$2:$G$10,3,FALSE) -> Dr: Acct 0808 - GENERAL GOV. (GAAP ADJ)
C79: Cr: Acct 0480 - RIGHT-TO-USE SBITA - AMORTIZABLE
C80: =VLOOKUP($F$8,'Drop Down Menus'!$D$2:$G$10,4,FALSE) -> Cr: Acct 0808 - GENERAL GOV. (GAAP ADJ)
J81: =ROUND(SUM(J76:J78),2) -> 0 | K81: =ROUND(SUM(K79:K80),2) -> 0 | L81: =IF(J81=K81,"<- Debits and Credits equal each other.","<- Debits and Credits do not equal each other.") -> <- Debits and Credits equal each other.
A83: 9 | B83: Record SBITA modifications to increase in the RTU SBITA asset.
B84: Dr: Acct 0480 - RIGHT-TO-USE SBITA - AMORTIZABLE
C85: Cr: Acct 0674 - RIGHT-TO-USE SBITA LIABILITY
J86: =SUM(J84) -> 0 | K86: =SUM(K85) -> 0 | L86: =IF(J86=K86,"<- Debits and Credits equal each other.","<- Debits and Credits do not equal each other.") -> <- Debits and Credits equal each other.
B88: NOTE: Please check the instructions for remeasurement and modifications on the SCO website.
D92: Informational - Ending Balances of Assets and Liabilities
K93: Debit (Credit)
D94: Acct 0480 - RIGHT-TO-USE SBITA - AMORTIZABLE | K94: =+J15+J34-K69-K79+J84 -> 0
D95: Acct 0475 - ACCUMULATED AMORTIZATION - RIGHT-TO-USE SBITA | K95: =-K18-K46+J68+J77 -> 0
D96: Acct 0674 - RIGHT-TO-USE SBITA LIABILITY | K96: =-K19-K37+J56+J61+J76-K85 -> 0
D97: Acct 0651 - RIGHT-TO-USE SBITA LIABILITY (CURRENT PORTION LT) | K97: =-K62 -> 0

Sheet Fund 9731 Journal Entries
A1: GASB 96 - SBITA Contracts Fund-by-Fund Journal Entries Form (to be submitted to the SCO annually—one form per fund)
A2: Manually complete every yellow field in this worksheet—there are no automatically calculated data-entry cells in this worksheet.
A3: Fiscal year: | F3: 2023–2024
A4: Organization Name: | F4: Department of Justice
A5: Organization Code (Business Unit): | F5: 0820
A6: Fund Number: | F6: 9731
A7: Fund Type: | F7: Proprietary - Internal Service Fund
A8: Fund Classification: | F8: =IF(OR($F$7='Drop Down Menus'!B2,$F$7='Drop Down Menus'!$B$3),'Drop Down Menus'!$D$9,IFERROR(VLOOKUP($F$5,GAAP02Aindex!$A$2:$D$900,4,FALSE),"Unidentified")) -> PROPRIETARY FUND
A12: =IF($F$3="2022–2023","Establish Beginning Balances (SBITAs commenced on or before 07/01/2022)","Establish Beginning Balances (existing SBITAs only)") -> Establish Beginning Balances (existing SBITAs only)
A13: Entry #
A14: 0 | B14: =IF($F$3="2022–2023","To establish the beginning balance of SBITAs as of 07/01/2022.","Roll forward prior year right-to-use SBITAs to record opening balances.") -> Roll forward prior year right-to-use SBITAs to record opening balances. | M14: Department Beginning Balances | P14: From SCO BB List | S14: Difference
B15: Dr: Acct 0480 - RIGHT-TO-USE SBITA - AMORTIZABLE | J15: =ROUND(M15,0) -> 525859 | M15: 525859 | P15: 525859 | S15: =M15-P15 -> 0 | T15: Report any "Differences" on the Report 18 Differential.
B16: Dr: Acct 0950 - BEGINNING FUND BALANCE | J16: =ROUND(P16,0) -> 1348 | M16: 1348 | P16: =IF(SUM($Q$18:$Q$19)>$P$15,SUM($Q$18:$Q$19)-$P$15,0) -> 1348 | S16: =M16-P16 -> 0 | T16: No action required.
B17: Dr: Acct 0952 - BEG FB ADJ/PRIOR PERIOD ADJUSTMENT | J17: =ROUND(IF(SUM($K$18:$K$20)>SUM($J$15:$J$16),SUM($K$18:$K$20)-SUM($J$15:$J$16),0),0) -> 0 | S17: =M17-P17 -> 0 | T17: No action required.
C18: Cr. Acct 0475 - ACCUMULATED AMORTIZATION - RIGHT-TO-USE SBITA | K18: =ROUND(N18,0) -> 395262 | N18: 395262 | Q18: 395262 | S18: =N18-Q18 -> 0 | T18: No action required.
C19: Cr: Acct 0674 - RIGHT-TO-USE SBITA LIABILITY | K19: =ROUND(N19,0) -> 131945 | N19: 131945 | Q19: 131945 | S19: =N19-Q19 -> 0 | T19: No action required.
C20: Cr: Acct 0950 - BEGINNING FUND BALANCE | K20: =ROUND(Q20,0) -> 0 | Q20: =IF(SUM($Q$18:$Q$19)<$P$15,-SUM($Q$18:$Q$19)+$P$15,0) -> 0 | S20: =N20-Q20 -> 0 | T20: No action required.
C21: Cr: Acct 0952 - BEG FB ADJ/PRIOR PERIOD ADJUSTMENT | K21: =ROUND(IF(SUM($K$18:$K$20)<SUM($J$15:$J$16),-SUM($K$18:$K$20)+SUM($J$15:$J$16),0),0) -> 0 | S21: =N21-Q21 -> 0 | T21: No action required.
J22: =ROUND(SUM(J15:J17),0) -> 527207 | K22: =ROUND(SUM(K18:K21),0) -> 527207 | L22: =IF(J22=K22,"<- Debits and Credits equal each other.","<- Debits and Credits do not equal each other.") -> <- Debits and Credits equal each other.
B24: SBITA ASSET (Acct 0480) AMOUNT SHOULD BE REPORTED AS BEGINNING BALANCE ON REPORT 18.
A26: =IF($F$3="2022–2023","Record SBITAs Commenced on or after 07/02/2022","Record New SBITAs (new SBITAs only)") -> Record New SBITAs (new SBITAs only)
A27: 1 | B27: Record at inception of SBITA in accordance with Fund-Based accounting (Governmental Funds Only).
B28: Dr: Acct 0842 - CAPITAL OUTLAY | J28: 0
C29: Cr: Acct 0789 - LEASE AND OTHER FINANCING PROCEEDS | K29: 0
C30: =VLOOKUP($F$8,'Drop Down Menus'!$D$2:$G$10,4,FALSE) -> Cr: Acct 0870 - SERVICES & CHARGES (MG ADJ) | K30: 0
J31: =ROUND(SUM(J28:J30),2) -> 0 | K31: =ROUND(SUM(K28:K30),2) -> 0 | L31: =IF(J31=K31,"<- Debits and Credits equal each other.","<- Debits and Credits do not equal each other.") -> <- Debits and Credits equal each other.
A33: 2 | B33: Reverse the fund-based entry in #1 above, if any, and record an inception of SBITA in accordance with GAAP Govt Wide.
B34: Dr: Acct 0480 - RIGHT-TO-USE SBITA - AMORTIZABLE | J34: 0
B35: Dr: Acct 0789 - LEASE AND OTHER FINANCING PROCEEDS | J35: 0
C36: Cr: Acct 0842 - CAPITAL OUTLAY | K36: 0
C37: Cr: Acct 0674 - RIGHT-TO-USE SBITA LIABILITY | K37: 0
C38: =VLOOKUP($F$8,'Drop Down Menus'!$D$2:$G$10,4,FALSE) -> Cr: Acct 0870 - SERVICES & CHARGES (MG ADJ) | K38: 0
J39: =ROUND(SUM(J34:J35),2) -> 0 | K39: =ROUND(SUM(K36:K38),2) -> 0 | L39: =IF(J39=K39,"<- Debits and Credits equal each other.","<- Debits and Credits do not equal each other.") -> <- Debits and Credits equal each other.
B41: SBITA ASSET (Acct 0480) AMOUNT SHOULD BE INCLUDED AS "ADDITIONS" ON REPORT 18.
A43: Record Annual Activity (all SBITAs)
A44: 3 | B44: Record amortization of the SBITA asset for the year.
B45: Dr: Acct 0875 - DEPRECIATION/AMORTIZATION | J45: 62623
C46: Cr. Acct 0475 - ACCUMULATED AMORTIZATION - RIGHT-TO-USE SBITA | K46: =J45 -> 62623
J47: =ROUND(SUM(J45:J45),2) -> 62623 | K47: =ROUND(SUM(K46),2) -> 62623 | L47: =IF(J47=K47,"<- Debits and Credits equal each other.","<- Debits and Credits do not equal each other.") -> <- Debits and Credits equal each other.
A49: 4 | B49: Reclassify information technology subscription exp. to debt service principal and interest exp.
B50: Dr: Acct 0848 - DEBT SERVICE - PRINCIPAL LEASES | J50: 63297 | L50: =IF($J$50=$K$57,"","<- Accts 0848 must agree")
B51: =IF(OR($F$7="Proprietary - Internal Service Fund",$F$7="Proprietary - Enterprise Fund"),"Dr: Acct 0894 - INTEREST EXPENSE AND FISCAL CHARGES","Dr: Acct 0851 - DEBT SERVICE - INTEREST LEASES") -> Dr: Acct 0894 - INTEREST EXPENSE AND FISCAL CHARGES | J51: 253
C52: =VLOOKUP($F$8,'Drop Down Menus'!$D$2:$G$10,4,FALSE) -> Cr: Acct 0870 - SERVICES & CHARGES (MG ADJ) | K52: =+J50+J51 -> 63550
J53: =ROUND(SUM(J50:J51),2) -> 63550 | K53: =ROUND(SUM(K52,),2) -> 63550 | L53: =IF(J53=K53,"<- Debits and Credits equal each other.","<- Debits and Credits do not equal each other.") -> <- Debits and Credits equal each other.
A55: 5 | B55: Reduce SBITA liability for total current year principal payments.
B56: Dr: Acct 0674 - RIGHT-TO-USE SBITA LIABILITY | J56: 63297
C57: Cr: Acct 0848 - DEBT SERVICE - PRINCIPAL LEASES | K57: =J50 -> 63297 | L57: =IF($J$50=$K$57,"","<- Accts 0848 must agree")
J58: =ROUND(SUM(J56:J56),2) -> 63297 | K58: =ROUND(SUM(K57),2) -> 63297 | L58: =IF(J58=K58,"<- Debits and Credits equal each other.","<- Debits and Credits do not equal each other.") -> <- Debits and Credits equal each other.
A60: 6 | B60: Reclassify the principal amount due in the next FY to the current liability.
B61: Dr: Acct 0674 - RIGHT-TO-USE SBITA LIABILITY | J61: 0
C62: Cr. Acct 0651 - RIGHT-TO-USE SBITA LIABILITY (CURRENT PORTION LT) | K62: =J61 -> 0
B63: NOTE: This is an annual accrual. The RTU SBITA Liability - Current portion will be added back to the RTU SBITA Liability in entry #0 when reestablishing the beginning balances next year. | J63: =ROUND(SUM(J61:J61),2) -> 0 | K63: =ROUND(SUM(K62),2) -> 0 | L63: =IF(J63=K63,"<- Debits and Credits equal each other.","<- Debits and Credits do not equal each other.") -> <- Debits and Credits equal each other.
A66: Remove SBITA Asset at the End of the Subscription Term (only at the end of the subscription term)
A67: 7 | B67: Record entry to write off the SBITA asset and accumulated amortization at the end of the subscription term.
B68: Dr: Acct 0475 - ACCUMULATED AMORTIZATION - RIGHT-TO-USE SBITA | J68: 423898
C69: Cr: Acct 0480 - RIGHT-TO-USE SBITA - AMORTIZABLE | K69: 423898
J70: =SUM(J68) -> 423898 | K70: =SUM(K69) -> 423898 | L70: =IF(J70=K70,"<- Debits and Credits equal each other.","<- Debits and Credits do not equal each other.") -> <- Debits and Credits equal each other.
B72: SBITA ASSET (Acct 0480) SHOULD BE INCLUDED AS "DEDUCTIONS" ON REPORT 18.
A74: Record SBITA Remeasurement and Modifications (only if a significant modification occurred during the fiscal year)
A75: 8 | B75: Record early termination of SBITA contract or SBITA modifications to decrease in the RTU SBITA asset.
B76: Dr: Acct 0674 - RIGHT-TO-USE SBITA LIABILITY | J76: 68648
B77: Dr: Acct 0475 - ACCUMULATED AMORTIZATION - RIGHT-TO-USE SBITA | J77: 33987
B78: =VLOOKUP($F$8,'Drop Down Menus'!$D$2:$G$10,3,FALSE) -> Dr: Acct 0875 - DEPRECIATION/AMORTIZATION (MG ADJ)
C79: Cr: Acct 0480 - RIGHT-TO-USE SBITA - AMORTIZABLE | K79: 101961
C80: =VLOOKUP($F$8,'Drop Down Menus'!$D$2:$G$10,4,FALSE) -> Cr: Acct 0870 - SERVICES & CHARGES (MG ADJ) | K80: 674
J81: =ROUND(SUM(J76:J78),2) -> 102635 | K81: =ROUND(SUM(K79:K80),2) -> 102635 | L81: =IF(J81=K81,"<- Debits and Credits equal each other.","<- Debits and Credits do not equal each other.") -> <- Debits and Credits equal each other.
A83: 9 | B83: Record SBITA modifications to increase in the RTU SBITA asset.
B84: Dr: Acct 0480 - RIGHT-TO-USE SBITA - AMORTIZABLE
C85: Cr: Acct 0674 - RIGHT-TO-USE SBITA LIABILITY
J86: =SUM(J84) -> 0 | K86: =SUM(K85) -> 0 | L86: =IF(J86=K86,"<- Debits and Credits equal each other.","<- Debits and Credits do not equal each other.") -> <- Debits and Credits equal each other.
B88: NOTE: Please check the instructions for remeasurement and modifications on the SCO website.
D92: Informational - Ending Balances of Assets and Liabilities
K93: Debit (Credit)
D94: Acct 0480 - RIGHT-TO-USE SBITA - AMORTIZABLE | K94: =+J15+J34-K69-K79+J84 -> 0
D95: Acct 0475 - ACCUMULATED AMORTIZATION - RIGHT-TO-USE SBITA | K95: =-K18-K46+J68+J77 -> 0
D96: Acct 0674 - RIGHT-TO-USE SBITA LIABILITY | K96: =-K19-K37+J56+J61+J76-K85 -> 0
D97: Acct 0651 - RIGHT-TO-USE SBITA LIABILITY (CURRENT PORTION LT) | K97: =-K62 -> 0

Sheet Fund 9740 Journal Entries
A1: GASB 96 - SBITA Contracts Fund-by-Fund Journal Entries Form (to be submitted to the SCO annually—one form per fund)
A2: Manually complete every yellow field in this worksheet—there are no automatically calculated data-entry cells in this worksheet.
A3: Fiscal year: | F3: 2023–2024
A4: Organization Name: | F4: Department of Justice
A5: Organization Code (Business Unit): | F5: 0820
A6: Fund Number: | F6: 9740
A7: Fund Type: | F7: Proprietary - Internal Service Fund
A8: Fund Classification: | F8: =IF(OR($F$7='Drop Down Menus'!B2,$F$7='Drop Down Menus'!$B$3),'Drop Down Menus'!$D$9,IFERROR(VLOOKUP($F$5,GAAP02Aindex!$A$2:$D$900,4,FALSE),"Unidentified")) -> PROPRIETARY FUND
A12: =IF($F$3="2022–2023","Establish Beginning Balances (SBITAs commenced on or before 07/01/2022)","Establish Beginning Balances (existing SBITAs only)") -> Establish Beginning Balances (existing SBITAs only)
A13: Entry #
A14: 0 | B14: =IF($F$3="2022–2023","To establish the beginning balance of SBITAs as of 07/01/2022.","Roll forward prior year right-to-use SBITAs to record opening balances.") -> Roll forward prior year right-to-use SBITAs to record opening balances. | M14: Department Beginning Balances | P14: From SCO BB List | S14: Difference
B15: Dr: Acct 0480 - RIGHT-TO-USE SBITA - AMORTIZABLE | J15: =ROUND(M15,0) -> 14973 | M15: 14973 | P15: 14973 | S15: =M15-P15 -> 0 | T15: Report any "Differences" on the Report 18 Differential.
B16: Dr: Acct 0950 - BEGINNING FUND BALANCE | J16: =ROUND(P16,0) -> 34 | M16: 34 | P16: =IF(SUM($Q$18:$Q$19)>$P$15,SUM($Q$18:$Q$19)-$P$15,0) -> 34 | S16: =M16-P16 -> 0 | T16: No action required.
B17: Dr: Acct 0952 - BEG FB ADJ/PRIOR PERIOD ADJUSTMENT | J17: =ROUND(IF(SUM($K$18:$K$20)>SUM($J$15:$J$16),SUM($K$18:$K$20)-SUM($J$15:$J$16),0),0) -> 0 | S17: =M17-P17 -> 0 | T17: No action required.
C18: Cr. Acct 0475 - ACCUMULATED AMORTIZATION - RIGHT-TO-USE SBITA | K18: =ROUND(N18,0) -> 11495 | N18: 11495 | Q18: 11495 | S18: =N18-Q18 -> 0 | T18: No action required.
C19: Cr: Acct 0674 - RIGHT-TO-USE SBITA LIABILITY | K19: =ROUND(N19,0) -> 3512 | N19: 3512 | Q19: 3512 | S19: =N19-Q19 -> 0 | T19: No action required.
C20: Cr: Acct 0950 - BEGINNING FUND BALANCE | K20: =ROUND(Q20,0) -> 0 | Q20: =IF(SUM($Q$18:$Q$19)<$P$15,-SUM($Q$18:$Q$19)+$P$15,0) -> 0 | S20: =N20-Q20 -> 0 | T20: No action required.
C21: Cr: Acct 0952 - BEG FB ADJ/PRIOR PERIOD ADJUSTMENT | K21: =ROUND(IF(SUM($K$18:$K$20)<SUM($J$15:$J$16),-SUM($K$18:$K$20)+SUM($J$15:$J$16),0),0) -> 0 | S21: =N21-Q21 -> 0 | T21: No action required.
J22: =ROUND(SUM(J15:J17),0) -> 15007 | K22: =ROUND(SUM(K18:K21),0) -> 15007 | L22: =IF(J22=K22,"<- Debits and Credits equal each other.","<- Debits and Credits do not equal each other.") -> <- Debits and Credits equal each other.
B24: SBITA ASSET (Acct 0480) AMOUNT SHOULD BE REPORTED AS BEGINNING BALANCE ON REPORT 18.
A26: =IF($F$3="2022–2023","Record SBITAs Commenced on or after 07/02/2022","Record New SBITAs (new SBITAs only)") -> Record New SBITAs (new SBITAs only)
A27: 1 | B27: Record at inception of SBITA in accordance with Fund-Based accounting (Governmental Funds Only).
B28: Dr: Acct 0842 - CAPITAL OUTLAY
C29: Cr: Acct 0789 - LEASE AND OTHER FINANCING PROCEEDS
C30: =VLOOKUP($F$8,'Drop Down Menus'!$D$2:$G$10,4,FALSE) -> Cr: Acct 0870 - SERVICES & CHARGES (MG ADJ)
J31: =ROUND(SUM(J28:J30),2) -> 0 | K31: =ROUND(SUM(K28:K30),2) -> 0 | L31: =IF(J31=K31,"<- Debits and Credits equal each other.","<- Debits and Credits do not equal each other.") -> <- Debits and Credits equal each other.
A33: 2 | B33: Reverse the fund-based entry in #1 above, if any, and record an inception of SBITA in accordance with GAAP Govt Wide.
B34: Dr: Acct 0480 - RIGHT-TO-USE SBITA - AMORTIZABLE
B35: Dr: Acct 0789 - LEASE AND OTHER FINANCING PROCEEDS
C36: Cr: Acct 0842 - CAPITAL OUTLAY
C37: Cr: Acct 0674 - RIGHT-TO-USE SBITA LIABILITY
C38: =VLOOKUP($F$8,'Drop Down Menus'!$D$2:$G$10,4,FALSE) -> Cr: Acct 0870 - SERVICES & CHARGES (MG ADJ)
J39: =ROUND(SUM(J34:J35),2) -> 0 | K39: =ROUND(SUM(K36:K38),2) -> 0 | L39: =IF(J39=K39,"<- Debits and Credits equal each other.","<- Debits and Credits do not equal each other.") -> <- Debits and Credits equal each other.
B41: SBITA ASSET (Acct 0480) AMOUNT SHOULD BE INCLUDED AS "ADDITIONS" ON REPORT 18.
A43: Record Annual Activity (all SBITAs)
A44: 3 | B44: Record amortization of the SBITA asset for the year.
B45: Dr: Acct 0875 - DEPRECIATION/AMORTIZATION | J45: 3478
C46: Cr. Acct 0475 - ACCUMULATED AMORTIZATION - RIGHT-TO-USE SBITA | K46: =J45 -> 3478
J47: =ROUND(SUM(J45:J45),2) -> 3478 | K47: =ROUND(SUM(K46),2) -> 3478 | L47: =IF(J47=K47,"<- Debits and Credits equal each other.","<- Debits and Credits do not equal each other.") -> <- Debits and Credits equal each other.
A49: 4 | B49: Reclassify information technology subscription exp. to debt service principal and interest exp.
B50: Dr: Acct 0848 - DEBT SERVICE - PRINCIPAL LEASES | J50: 3512 | L50: =IF($J$50=$K$57,"","<- Accts 0848 must agree")
B51: =IF(OR($F$7="Proprietary - Internal Service Fund",$F$7="Proprietary - Enterprise Fund"),"Dr: Acct 0894 - INTEREST EXPENSE AND FISCAL CHARGES","Dr: Acct 0851 - DEBT SERVICE - INTEREST LEASES") -> Dr: Acct 0894 - INTEREST EXPENSE AND FISCAL CHARGES | J51: 30
C52: =VLOOKUP($F$8,'Drop Down Menus'!$D$2:$G$10,4,FALSE) -> Cr: Acct 0870 - SERVICES & CHARGES (MG ADJ) | K52: =+J50+J51 -> 3542
J53: =ROUND(SUM(J50:J51),2) -> 3542 | K53: =ROUND(SUM(K52,),2) -> 3542 | L53: =IF(J53=K53,"<- Debits and Credits equal each other.","<- Debits and Credits do not equal each other.") -> <- Debits and Credits equal each other.
A55: 5 | B55: Reduce SBITA liability for total current year principal payments.
B56: Dr: Acct 0674 - RIGHT-TO-USE SBITA LIABILITY | J56: 3512
C57: Cr: Acct 0848 - DEBT SERVICE - PRINCIPAL LEASES | K57: =J50 -> 3512 | L57: =IF($J$50=$K$57,"","<- Accts 0848 must agree")
J58: =ROUND(SUM(J56:J56),2) -> 3512 | K58: =ROUND(SUM(K57),2) -> 3512 | L58: =IF(J58=K58,"<- Debits and Credits equal each other.","<- Debits and Credits do not equal each other.") -> <- Debits and Credits equal each other.
A60: 6 | B60: Reclassify the principal amount due in the next FY to the current liability.
B61: Dr: Acct 0674 - RIGHT-TO-USE SBITA LIABILITY
C62: Cr. Acct 0651 - RIGHT-TO-USE SBITA LIABILITY (CURRENT PORTION LT) | K62: =J61 -> 0
B63: NOTE: This is an annual accrual. The RTU SBITA Liability - Current portion will be added back to the RTU SBITA Liability in entry #0 when reestablishing the beginning balances next year. | J63: =ROUND(SUM(J61:J61),2) -> 0 | K63: =ROUND(SUM(K62),2) -> 0 | L63: =IF(J63=K63,"<- Debits and Credits equal each other.","<- Debits and Credits do not equal each other.") -> <- Debits and Credits equal each other.
A66: Remove SBITA Asset at the End of the Subscription Term (only at the end of the subscription term)
A67: 7 | B67: Record entry to write off the SBITA asset and accumulated amortization at the end of the subscription term.
B68: Dr: Acct 0475 - ACCUMULATED AMORTIZATION - RIGHT-TO-USE SBITA | J68: 14973
C69: Cr: Acct 0480 - RIGHT-TO-USE SBITA - AMORTIZABLE | K69: 14973
J70: =SUM(J68) -> 14973 | K70: =SUM(K69) -> 14973 | L70: =IF(J70=K70,"<- Debits and Credits equal each other.","<- Debits and Credits do not equal each other.") -> <- Debits and Credits equal each other.
B72: SBITA ASSET (Acct 0480) SHOULD BE INCLUDED AS "DEDUCTIONS" ON REPORT 18.
A74: Record SBITA Remeasurement and Modifications (only if a significant modification occurred during the fiscal year)
A75: 8 | B75: Record early termination of SBITA contract or SBITA modifications to decrease in the RTU SBITA asset.
B76: Dr: Acct 0674 - RIGHT-TO-USE SBITA LIABILITY
B77: Dr: Acct 0475 - ACCUMULATED AMORTIZATION - RIGHT-TO-USE SBITA
B78: =VLOOKUP($F$8,'Drop Down Menus'!$D$2:$G$10,3,FALSE) -> Dr: Acct 0875 - DEPRECIATION/AMORTIZATION (MG ADJ)
C79: Cr: Acct 0480 - RIGHT-TO-USE SBITA - AMORTIZABLE
C80: =VLOOKUP($F$8,'Drop Down Menus'!$D$2:$G$10,4,FALSE) -> Cr: Acct 0870 - SERVICES & CHARGES (MG ADJ)
J81: =ROUND(SUM(J76:J78),2) -> 0 | K81: =ROUND(SUM(K79:K80),2) -> 0 | L81: =IF(J81=K81,"<- Debits and Credits equal each other.","<- Debits and Credits do not equal each other.") -> <- Debits and Credits equal each other.
A83: 9 | B83: Record SBITA modifications to increase in the RTU SBITA asset.
B84: Dr: Acct 0480 - RIGHT-TO-USE SBITA - AMORTIZABLE
C85: Cr: Acct 0674 - RIGHT-TO-USE SBITA LIABILITY
J86: =SUM(J84) -> 0 | K86: =SUM(K85) -> 0 | L86: =IF(J86=K86,"<- Debits and Credits equal each other.","<- Debits and Credits do not equal each other.") -> <- Debits and Credits equal each other.
B88: NOTE: Please check the instructions for remeasurement and modifications on the SCO website.
D92: Informational - Ending Balances of Assets and Liabilities
K93: Debit (Credit)
D94: Acct 0480 - RIGHT-TO-USE SBITA - AMORTIZABLE | K94: =+J15+J34-K69-K79+J84 -> 0
D95: Acct 0475 - ACCUMULATED AMORTIZATION - RIGHT-TO-USE SBITA | K95: =-K18-K46+J68+J77 -> 0
D96: Acct 0674 - RIGHT-TO-USE SBITA LIABILITY | K96: =-K19-K37+J56+J61+J76-K85 -> 0
D97: Acct 0651 - RIGHT-TO-USE SBITA LIABILITY (CURRENT PORTION LT) | K97: =-K62 -> 0

Sheet Department Note Disclosure
A1: GASB 96 - SBITA Note Disclosure Form ( Submit one form for the department to the SCO annually)
A3: Note: There are three tables of note disclosures on this form —1) governmental funds, 2) proprietary - internal service funds, and 3) proprietary - enterprise funds. Complete all applicable tables before submitting to the SCO.
A4: Manually complete every yellow field in this worksheet—there are no automatically calculated cells in this worksheet.
A5: Complete the fields below using aggregated and summarized information from all of your department's completed contract template forms.
A7: The fields in this worksheet should contain the sums of the department's contracts' corresponding information in their note disclosure worksheets.
A10: I. Governmental Funds
A11: Fiscal Year: | B11: 2023–2024
A12: Org Code/Business Unit: | B12: 820
A13: Reporting Department Name: | B13: Department of Justice
A14: The below information must be entered manually. DO NOT ENTER DECIMALS. PLEASE ROUND TO THE NEAREST DOLLAR.
B15: Principal Payments | C15: Interest Payments | D15: ="All of the below questions are for Fiscal Year "&$B$11&":" -> All of the below questions are for Fiscal Year 2023–2024:
A16: =RIGHT(B11,4)&"–"&RIGHT(B11,4)+1 -> 2024–2025 | B16: =1759529+1 -> 1759530 | C16: 70929 | D16: 1. Did your SBITAs have any variable payments which ARE NOT included in the measurement of the subscription liability?
A17: =LEFT(A16,4)+1&"–"&RIGHT(A16,4)+1 -> 2025–2026 | B17: =1767484-1 -> 1767483 | C17: 24466
A18: =LEFT(A17,4)+1&"–"&RIGHT(A17,4)+1 -> 2026–2027 | B18: =102140-1 -> 102139 | C18: 2603 | D18: No
A19: =LEFT(A18,4)+1&"–"&RIGHT(A18,4)+1 -> 2027–2028 | B19: =52928-3 -> 52925 | C19: 371 | D19: ="If yes, record the dollar amount of variable payments below for fiscal year "&$B$11&":" -> If yes, record the dollar amount of variable payments below for fiscal year 2023–2024:
A20: =LEFT(A19,4)+1&"–"&RIGHT(A19,4)+1 -> 2028–2029 | D20: 0
A21: =LEFT(A20,4)+1&"–"&RIGHT(A20,4)+5 -> 2029–2034 | D21: ="2. Record the dollar amount of any other payments for your SBITAs, such as termination penalties, not previously recorded in the payment schedule for fiscal year "&$B$11&":" -> 2. Record the dollar amount of any other payments for your SBITAs, such as termination penalties, not previously recorded in the payment schedule for fiscal year 2023–2024:
A22: =LEFT(A21,4)+5&"–"&RIGHT(A21,4)+5 -> 2034–2039
A23: =LEFT(A22,4)+5&"–"&RIGHT(A22,4)+5 -> 2039–2044 | D23: N/A
A24: =LEFT(A23,4)+5&"–"&RIGHT(A23,4)+5 -> 2044–2049 | D24: ="3. Did you receive any SBITA incentives from the SBITA vendor (not already included in the SBITA measurement) during fiscal year "&$B$11&"? If so, record the amount below:" -> 3. Did you receive any SBITA incentives from the SBITA vendor (not already included in the SBITA measurement) during fiscal year 2023–2024? If so, record the amount below:
A25: =LEFT(A24,4)+5&"–"&RIGHT(A24,4)+5 -> 2049–2054
A26: =LEFT(A25,4)+5&"–"&RIGHT(A25,4)+5 -> 2054–2059 | D26: N/A
A27: =LEFT(A26,4)+5&"–"&RIGHT(A26,4)+5 -> 2059–2064 | D27: ="4. Are there any SBITA commitments known that have yet to commence as of June 30, "&RIGHT($B$11,4)&"?" -> 4. Are there any SBITA commitments known that have yet to commence as of June 30, 2024?
A28: =LEFT(A27,4)+5&"–"&RIGHT(A27,4)+5 -> 2064–2069
A29: =LEFT(A28,4)+5&"–"&RIGHT(A28,4)+5 -> 2069–2074 | D29: N/A
A30: =LEFT(A29,4)+5&"–"&RIGHT(A29,4)+5 -> 2074–2079 | D30: ="If yes, record the dollar amount of any SBITA commitments not commenced below for fiscal year "&$A$16&":" -> If yes, record the dollar amount of any SBITA commitments not commenced below for fiscal year 2024–2025:
A31: =LEFT(A30,4)+5&"–"&RIGHT(A30,4)+5 -> 2079–2084
A32: =LEFT(A31,4)+5&"–"&RIGHT(A31,4)+5 -> 2084–2089 | D32: 0
A33: =LEFT(A32,4)+5&"–"&RIGHT(A32,4)+5 -> 2089–2094
A34: =LEFT(A33,4)+5&"–"&RIGHT(A33,4)+5 -> 2094–2099
A35: =LEFT(A34,4)+5&"–"&RIGHT(A34,4)+5 -> 2099–2104
A36: =LEFT(A35,4)+5&"–"&RIGHT(A35,4)+5 -> 2104–2109
A37: =LEFT(A36,4)+5&"–"&RIGHT(A36,4)+5 -> 2109–2114
A38: =LEFT(A37,4)+5&"–"&RIGHT(A37,4)+5 -> 2114–2119
A39: =LEFT(A38,4)+5&"–"&RIGHT(A38,4)+5 -> 2119–2124
A41: II. Proprietary - Internal Service Funds
A42: Fiscal Year: | B42: =B11 -> 2023–2024
A43: Org Code/Business Unit: | B43: =B12 -> 820
A44: Reporting Department Name: | B44: =B13 -> Department of Justice
A45: The below information must be entered manually. DO NOT ENTER DECIMALS. PLEASE ROUND TO THE NEAREST DOLLAR.
B46: Principal Payments | C46: Interest Payments | D46: ="All of the below questions are for Fiscal Year "&$B$11&":" -> All of the below questions are for Fiscal Year 2023–2024:
A47: =RIGHT(B42,4)&"–"&RIGHT(B42,4)+1 -> 2024–2025 | D47: 1. Did your SBITAs have any variable payments which ARE NOT included in the measurement of the subscription liability?
A48: =LEFT(A47,4)+1&"–"&RIGHT(A47,4)+1 -> 2025–2026
A49: =LEFT(A48,4)+1&"–"&RIGHT(A48,4)+1 -> 2026–2027 | D49: No
A50: =LEFT(A49,4)+1&"–"&RIGHT(A49,4)+1 -> 2027–2028 | D50: ="If yes, record the dollar amount of variable payments below for fiscal year "&$B$11&":" -> If yes, record the dollar amount of variable payments below for fiscal year 2023–2024:
A51: =LEFT(A50,4)+1&"–"&RIGHT(A50,4)+1 -> 2028–2029 | D51: 0
A52: =LEFT(A51,4)+1&"–"&RIGHT(A51,4)+5 -> 2029–2034 | D52: ="2. Record the dollar amount of any other payments for your SBITAs, such as termination penalties, not previously recorded in the payment schedule for fiscal year "&$B$11&":" -> 2. Record the dollar amount of any other payments for your SBITAs, such as termination penalties, not previously recorded in the payment schedule for fiscal year 2023–2024:
A53: =LEFT(A52,4)+5&"–"&RIGHT(A52,4)+5 -> 2034–2039
A54: =LEFT(A53,4)+5&"–"&RIGHT(A53,4)+5 -> 2039–2044 | D54: No
A55: =LEFT(A54,4)+5&"–"&RIGHT(A54,4)+5 -> 2044–2049 | D55: ="3. Did you receive any SBITA incentives from the SBITA vendor (not already included in the SBITA measurement) during fiscal year "&$B$11&"? If so, record the amount below:" -> 3. Did you receive any SBITA incentives from the SBITA vendor (not already included in the SBITA measurement) during fiscal year 2023–2024? If so, record the amount below:
A56: =LEFT(A55,4)+5&"–"&RIGHT(A55,4)+5 -> 2049–2054
A57: =LEFT(A56,4)+5&"–"&RIGHT(A56,4)+5 -> 2054–2059 | D57: No
A58: =LEFT(A57,4)+5&"–"&RIGHT(A57,4)+5 -> 2059–2064 | D58: ="4. Are there any SBITA commitments known that have yet to commence as of June 30, "&RIGHT($B$11,4)&"?" -> 4. Are there any SBITA commitments known that have yet to commence as of June 30, 2024?
A59: =LEFT(A58,4)+5&"–"&RIGHT(A58,4)+5 -> 2064–2069
A60: =LEFT(A59,4)+5&"–"&RIGHT(A59,4)+5 -> 2069–2074 | D60: No
A61: =LEFT(A60,4)+5&"–"&RIGHT(A60,4)+5 -> 2074–2079 | D61: ="If yes, record the dollar amount of any SBITA commitments not commenced below for fiscal year "&$A$16&":" -> If yes, record the dollar amount of any SBITA commitments not commenced below for fiscal year 2024–2025:
A62: =LEFT(A61,4)+5&"–"&RIGHT(A61,4)+5 -> 2079–2084
A63: =LEFT(A62,4)+5&"–"&RIGHT(A62,4)+5 -> 2084–2089 | D63: N/A
A64: =LEFT(A63,4)+5&"–"&RIGHT(A63,4)+5 -> 2089–2094
A65: =LEFT(A64,4)+5&"–"&RIGHT(A64,4)+5 -> 2094–2099
A66: =LEFT(A65,4)+5&"–"&RIGHT(A65,4)+5 -> 2099–2104
A67: =LEFT(A66,4)+5&"–"&RIGHT(A66,4)+5 -> 2104–2109
A68: =LEFT(A67,4)+5&"–"&RIGHT(A67,4)+5 -> 2109–2114
A69: =LEFT(A68,4)+5&"–"&RIGHT(A68,4)+5 -> 2114–2119
A70: =LEFT(A69,4)+5&"–"&RIGHT(A69,4)+5 -> 2119–2124
A72: III. Proprietary - Enterprise Funds
A73: Fiscal Year: | B73: =B11 -> 2023–2024
A74: Org Code/Business Unit: | B74: =B12 -> 820
A75: Reporting Department Name: | B75: =B13 -> Department of Justice
A76: The below information must be entered manually. DO NOT ENTER DECIMALS. PLEASE ROUND TO THE NEAREST DOLLAR.
B77: Principal Payments | C77: Interest Payments | D77: ="All of the below questions are for Fiscal Year "&$B$11&":" -> All of the below questions are for Fiscal Year 2023–2024:
A78: =RIGHT(B73,4)&"–"&RIGHT(B73,4)+1 -> 2024–2025 | D78: 1. Did your SBITAs have any variable payments which ARE NOT included in the measurement of the subscription liability?
A79: =LEFT(A78,4)+1&"–"&RIGHT(A78,4)+1 -> 2025–2026
A80: =LEFT(A79,4)+1&"–"&RIGHT(A79,4)+1 -> 2026–2027
A81: =LEFT(A80,4)+1&"–"&RIGHT(A80,4)+1 -> 2027–2028 | D81: ="If yes, record the dollar amount of variable payments below for fiscal year "&$B$11&":" -> If yes, record the dollar amount of variable payments below for fiscal year 2023–2024:
A82: =LEFT(A81,4)+1&"–"&RIGHT(A81,4)+1 -> 2028–2029
A83: =LEFT(A82,4)+1&"–"&RIGHT(A82,4)+5 -> 2029–2034 | D83: ="2. Record the dollar amount of any other payments for your SBITAs, such as termination penalties, not previously recorded in the payment schedule for fiscal year "&$B$11&":" -> 2. Record the dollar amount of any other payments for your SBITAs, such as termination penalties, not previously recorded in the payment schedule for fiscal year 2023–2024:
A84: =LEFT(A83,4)+5&"–"&RIGHT(A83,4)+5 -> 2034–2039
A85: =LEFT(A84,4)+5&"–"&RIGHT(A84,4)+5 -> 2039–2044
A86: =LEFT(A85,4)+5&"–"&RIGHT(A85,4)+5 -> 2044–2049 | D86: ="3. Did you receive any SBITA incentives from the SBITA vendor (not already included in the SBITA measurement) during fiscal year "&$B$11&"? If so, record the amount below:" -> 3. Did you receive any SBITA incentives from the SBITA vendor (not already included in the SBITA measurement) during fiscal year 2023–2024? If so, record the amount below:
A87: =LEFT(A86,4)+5&"–"&RIGHT(A86,4)+5 -> 2049–2054
A88: =LEFT(A87,4)+5&"–"&RIGHT(A87,4)+5 -> 2054–2059
A89: =LEFT(A88,4)+5&"–"&RIGHT(A88,4)+5 -> 2059–2064 | D89: ="4. Are there any SBITA commitments known that have yet to commence as of June 30, "&RIGHT($B$11,4)&"?" -> 4. Are there any SBITA commitments known that have yet to commence as of June 30, 2024?
A90: =LEFT(A89,4)+5&"–"&RIGHT(A89,4)+5 -> 2064–2069
A91: =LEFT(A90,4)+5&"–"&RIGHT(A90,4)+5 -> 2069–2074
A92: =LEFT(A91,4)+5&"–"&RIGHT(A91,4)+5 -> 2074–2079 | D92: ="If yes, record the dollar amount of any SBITA commitments not commenced below for fiscal year "&$A$16&":" -> If yes, record the dollar amount of any SBITA commitments not commenced below for fiscal year 2024–2025:
A93: =LEFT(A92,4)+5&"–"&RIGHT(A92,4)+5 -> 2079–2084
A94: =LEFT(A93,4)+5&"–"&RIGHT(A93,4)+5 -> 2084–2089
A95: =LEFT(A94,4)+5&"–"&RIGHT(A94,4)+5 -> 2089–2094
A96: =LEFT(A95,4)+5&"–"&RIGHT(A95,4)+5 -> 2094–2099
A97: =LEFT(A96,4)+5&"–"&RIGHT(A96,4)+5 -> 2099–2104
A98: =LEFT(A97,4)+5&"–"&RIGHT(A97,4)+5 -> 2104–2109
A99: =LEFT(A98,4)+5&"–"&RIGHT(A98,4)+5 -> 2109–2114
A100: =LEFT(A99,4)+5&"–"&RIGHT(A99,4)+5 -> 2114–2119
A101: =LEFT(A100,4)+5&"–"&RIGHT(A100,4)+5 -> 2119–2124

Sheet SBITA Liabilities
C3: Schedule of Changes in SBITA Liabilities
C4: ="FY "&'Department Note Disclosure'!$B$11 -> FY 2023–2024
C5: ="Business Unit " &'Fund 0012 Journal Entries'!$F$5&" "&'Fund 0012 Journal Entries'!$F$4 -> Business Unit 0820 Department of Justice
F7: ="Balance July 1, "&LEFT('Fund 0012 Journal Entries'!$F$3,4) -> Balance July 1, 2023 | H7: Additions | J7: Deductions | L7: ="Balance June 30, "&RIGHT('Fund 0012 Journal Entries'!$F$3,4) -> Balance June 30, 2024 | N7: Due Within One Year | P7: Noncurrent Liabilities
F8: (Entry #0) | H8: (Entry #2 & 9) | J8: (Entry #5 & 8) | N8: (Entry #6)
C9: Governmental Funds
D10: SBITA Liability | F10: ='Fund 0001 Journal Entries'!K19+'Fund 0012 Journal Entries'!K19+'Fund 0017 Journal Entries'!K19+'Fund 0044 Journal Entries'!K19+'Fund 0158 Journal Entries'!K19+'Fund 0367 Journal Entries'!K19+'Fund 0378 Journal Entries'!K19+'Fund 0460 Journal Entries'!K19+'Fund 0567 Journal Entries'!K19+'Fund 0569 Journal Entries'!K19+'Fund 0890 Journal Entries'!K19+'Fund 1008 Journal Entries'!K19+'Fund 3053 Journal Entries'!K19+'Fund 3086 Journal Entries'!K19+'Fund 3088 Journal Entries'!K19+'Fund 3297 Journal Entries'!K19+'Fund 3320 Journal Entries'!K19 -> 1983896 | H10: ='Fund 0001 Journal Entries'!K37+'Fund 0012 Journal Entries'!K37+'Fund 0017 Journal Entries'!K37+'Fund 0044 Journal Entries'!K37+'Fund 0158 Journal Entries'!K37+'Fund 0367 Journal Entries'!K37+'Fund 0378 Journal Entries'!K37+'Fund 0460 Journal Entries'!K37+'Fund 0567 Journal Entries'!K37+'Fund 0569 Journal Entries'!K37+'Fund 0890 Journal Entries'!K37+'Fund 1008 Journal Entries'!K37+'Fund 3053 Journal Entries'!K37+'Fund 3086 Journal Entries'!K37+'Fund 3088 Journal Entries'!K37+'Fund 3297 Journal Entries'!K37+'Fund 3320 Journal Entries'!K37+'Fund 0001 Journal Entries'!K85+'Fund 0012 Journal Entries'!K85+'Fund 0017 Journal Entries'!K85+'Fund 0044 Journal Entries'!K85+'Fund 0158 Journal Entries'!K85+'Fund 0367 Journal Entries'!K85+'Fund 0378 Journal Entries'!K85+'Fund 0460 Journal Entries'!K85+'Fund 0567 Journal Entries'!K85+'Fund 0569 Journal Entries'!K85+'Fund 0890 Journal Entries'!K85+'Fund 1008 Journal Entries'!K85+'Fund 3053 Journal Entries'!K85+'Fund 3086 Journal Entries'!K85+'Fund 3088 Journal Entries'!K85+'Fund 3297 Journal Entries'!K85+'Fund 3320 Journal Entries'!K85 -> 4936827 | J10: ='Fund 0001 Journal Entries'!J56+'Fund 0012 Journal Entries'!J56+'Fund 0017 Journal Entries'!J56+'Fund 0044 Journal Entries'!J56+'Fund 0158 Journal Entries'!J56+'Fund 0367 Journal Entries'!J56+'Fund 0378 Journal Entries'!J56+'Fund 0460 Journal Entries'!J56+'Fund 0567 Journal Entries'!J56+'Fund 0569 Journal Entries'!J56+'Fund 0890 Journal Entries'!J56+'Fund 1008 Journal Entries'!J56+'Fund 3053 Journal Entries'!J56+'Fund 3086 Journal Entries'!J56+'Fund 3088 Journal Entries'!J56+'Fund 3297 Journal Entries'!J56+'Fund 3320 Journal Entries'!J56+'Fund 0001 Journal Entries'!J76+'Fund 0012 Journal Entries'!J76+'Fund 0017 Journal Entries'!J76+'Fund 0044 Journal Entries'!J76+'Fund 0158 Journal Entries'!J76+'Fund 0367 Journal Entries'!J76+'Fund 0378 Journal Entries'!J76+'Fund 0460 Journal Entries'!J76+'Fund 0567 Journal Entries'!J76+'Fund 0569 Journal Entries'!J76+'Fund 0890 Journal Entries'!J76+'Fund 1008 Journal Entries'!J76+'Fund 3053 Journal Entries'!J76+'Fund 3086 Journal Entries'!J76+'Fund 3088 Journal Entries'!J76+'Fund 3297 Journal Entries'!J76+'Fund 3320 Journal Entries'!J76 -> 3238646 | L10: =SUM(F10+H10-J10) -> 3682077 | N10: ='Fund 0001 Journal Entries'!K62+'Fund 0012 Journal Entries'!K62+'Fund 0017 Journal Entries'!K62+'Fund 0044 Journal Entries'!K62+'Fund 0158 Journal Entries'!K62+'Fund 0367 Journal Entries'!K62+'Fund 0378 Journal Entries'!K62+'Fund 0460 Journal Entries'!K62+'Fund 0567 Journal Entries'!K62+'Fund 0569 Journal Entries'!K62+'Fund 0890 Journal Entries'!K62+'Fund 1008 Journal Entries'!K62+'Fund 3053 Journal Entries'!K62+'Fund 3086 Journal Entries'!K62+'Fund 3088 Journal Entries'!K62+'Fund 3297 Journal Entries'!K62+'Fund 3320 Journal Entries'!K62 -> 1759530 | P10: =L10-N10 -> 1922547
C11: Total Governmental Funds | F11: =SUM(F10:F10) -> 1983896 | H11: =SUM(H10:H10) -> 4936827 | J11: =SUM(J10:J10) -> 3238646 | L11: =SUM(L10:L10) -> 3682077 | N11: =SUM(N10:N10) -> 1759530 | P11: =SUM(P10:P10) -> 1922547
C13: Proprietary - Internal Service Funds
D14: SBITA Liability | F14: 135457 | H14: =IF('Fund 0012 Journal Entries'!$F$7="Proprietary - Internal Service Fund",SUM('Fund 0012 Journal Entries'!$K$37,'Fund 0012 Journal Entries'!$K$85),0) -> 0 | J14: =66809+68648 -> 135457 | L14: =SUM(F14+H14-J14) -> 0 | N14: =IF('Fund 0012 Journal Entries'!$F$7="Proprietary - Internal Service Fund",'Fund 0012 Journal Entries'!$J$61,0) -> 0 | P14: =L14-N14 -> 0
C15: Total Proprietary - Internal Service Funds | F15: =SUM(F14:F14) -> 135457 | H15: =SUM(H14:H14) -> 0 | J15: =SUM(J14:J14) -> 135457 | L15: =SUM(L14:L14) -> 0 | N15: =SUM(N14:N14) -> 0 | P15: =SUM(P14:P14) -> 0
C17: Proprietary - Enterprise Funds
D18: SBITA Liability | F18: =IF('Fund 0012 Journal Entries'!$F$7="Proprietary - Enterprise Fund",'Fund 0012 Journal Entries'!$K$19,0) -> 0 | H18: =IF('Fund 0012 Journal Entries'!$F$7="Proprietary - Enterprise Fund",SUM('Fund 0012 Journal Entries'!$K$37,'Fund 0012 Journal Entries'!$K$85),0) -> 0 | J18: =IF('Fund 0012 Journal Entries'!$F$7="Proprietary - Enterprise Fund",SUM('Fund 0012 Journal Entries'!$J$56,'Fund 0012 Journal Entries'!$J$76),0) -> 0 | L18: =SUM(F18+H18-J18) -> 0 | N18: =IF('Fund 0012 Journal Entries'!$F$7="Proprietary - Enterprise Fund",'Fund 0012 Journal Entries'!$J$61,0) -> 0 | P18: =L18-N18 -> 0
C19: Total Proprietary - Enterprise Funds | F19: =SUM(F18:F18) -> 0 | H19: =SUM(H18:H18) -> 0 | J19: =SUM(J18:J18) -> 0 | L19: =SUM(L18:L18) -> 0 | N19: =SUM(N18:N18) -> 0 | P19: =SUM(P18:P18) -> 0
B22: THIS SCHEDULE IS FOR THE CHANGE IN SBITA LIABILITY (ACCOUNT 0674) ONLY. THESE AMOUNTS WILL DIFFER FROM THE REPORT 18 (ASSETS).
B23: NOTE: If multiple funds are included in this workbook, manually complete every yellow field by consolidating the entries by fund type (Governmental, Proprietary ISF, and Proprietary EF).

Sheet Check Figures 
A1: GASB Statement No. 96 Subscription-Based Information Technology Arrangements
A2: Check Figures
A4: Purpose:
A5: The purpose of this workbook is to check the figures entered in the journal entries reconcile to the future principal payments disclosed and the changes in the schedule of the SBITA liabilities.
A8: NOTE: The yellow highlighted fields have formulas embedded to generate the amounts automatically based on inputs in the journal entries tab. If multiple funds are included in this Workbook, manually complete every yellow field by consolidating the entries by fund type (Governmental Fund, Proprietary - Internal Service Fund, and Proprietary - Enterprise Fund).
A11: 1. To reconcile the journal entries of RTU SBITA Liability with the principal payments in Note Disclosure.
A12: a) Governmental Funds
B14: Journal Entries (Acct 0674 - RIGHT-TO-USE SBITA LIABILITY) | N14: Department Note Disclosure
B15: Beginning Balance | D15: Additions | F15: Deductions | H15: Deductions (Mod) | J15: Additions (Mod) | L15: Total
B16: Entry #0 | C16: + | D16: Entry #2 | E16: - | F16: Entry #5 | G16: - | H16: Entry #8 | I16: + | J16: Entry #9 | N16: Sum Principal Payments | P16: Variance
B17: ='Fund 0001 Journal Entries'!K19+'Fund 0012 Journal Entries'!K19+'Fund 0017 Journal Entries'!K19+'Fund 0044 Journal Entries'!K19+'Fund 0158 Journal Entries'!K19+'Fund 0367 Journal Entries'!K19+'Fund 0378 Journal Entries'!K19+'Fund 0460 Journal Entries'!K19+'Fund 0567 Journal Entries'!K19+'Fund 0569 Journal Entries'!K19+'Fund 0890 Journal Entries'!K19+'Fund 1008 Journal Entries'!K19+'Fund 3053 Journal Entries'!K19+'Fund 3086 Journal Entries'!K19+'Fund 3088 Journal Entries'!K19+'Fund 3297 Journal Entries'!K19+'Fund 3320 Journal Entries'!K19 -> 1983896 | C17: + | D17: ='Fund 0001 Journal Entries'!K37+'Fund 0012 Journal Entries'!K37+'Fund 0017 Journal Entries'!K37+'Fund 0044 Journal Entries'!K37+'Fund 0158 Journal Entries'!K37+'Fund 0367 Journal Entries'!K37+'Fund 0378 Journal Entries'!K37+'Fund 0460 Journal Entries'!K37+'Fund 0567 Journal Entries'!K37+'Fund 0569 Journal Entries'!K37+'Fund 0890 Journal Entries'!K37+'Fund 1008 Journal Entries'!K37+'Fund 3053 Journal Entries'!K37+'Fund 3086 Journal Entries'!K37+'Fund 3088 Journal Entries'!K37+'Fund 3297 Journal Entries'!K37+'Fund 3320 Journal Entries'!K37 -> 4936827 | E17: - | F17: ='Fund 0001 Journal Entries'!J56+'Fund 0012 Journal Entries'!J56+'Fund 0017 Journal Entries'!J56+'Fund 0044 Journal Entries'!J56+'Fund 0158 Journal Entries'!J56+'Fund 0367 Journal Entries'!J56+'Fund 0378 Journal Entries'!J56+'Fund 0460 Journal Entries'!J56+'Fund 0567 Journal Entries'!J56+'Fund 0569 Journal Entries'!J56+'Fund 0890 Journal Entries'!J56+'Fund 1008 Journal Entries'!J56+'Fund 3053 Journal Entries'!J56+'Fund 3086 Journal Entries'!J56+'Fund 3088 Journal Entries'!J56+'Fund 3297 Journal Entries'!J56+'Fund 3320 Journal Entries'!J56 -> 2285558 | G17: - | H17: ='Fund 0001 Journal Entries'!J76+'Fund 0012 Journal Entries'!J76+'Fund 0017 Journal Entries'!J76+'Fund 0044 Journal Entries'!J76+'Fund 0158 Journal Entries'!J76+'Fund 0367 Journal Entries'!J76+'Fund 0378 Journal Entries'!J76+'Fund 0460 Journal Entries'!J76+'Fund 0567 Journal Entries'!J76+'Fund 0569 Journal Entries'!J76+'Fund 0890 Journal Entries'!J76+'Fund 1008 Journal Entries'!J76+'Fund 3053 Journal Entries'!J76+'Fund 3086 Journal Entries'!J76+'Fund 3088 Journal Entries'!J76+'Fund 3297 Journal Entries'!J76+'Fund 3320 Journal Entries'!J76 -> 953088 | I17: + | J17: ='Fund 0001 Journal Entries'!K85+'Fund 0012 Journal Entries'!K85+'Fund 0017 Journal Entries'!K85+'Fund 0044 Journal Entries'!K85+'Fund 0158 Journal Entries'!K85+'Fund 0367 Journal Entries'!K85+'Fund 0378 Journal Entries'!K85+'Fund 0460 Journal Entries'!K85+'Fund 0567 Journal Entries'!K85+'Fund 0569 Journal Entries'!K85+'Fund 0890 Journal Entries'!K85+'Fund 1008 Journal Entries'!K85+'Fund 3053 Journal Entries'!K85+'Fund 3086 Journal Entries'!K85+'Fund 3088 Journal Entries'!K85+'Fund 3297 Journal Entries'!K85+'Fund 3320 Journal Entries'!K85 -> 0 | K17: = | L17: =+B17+D17-F17-H17+J17 -> 3682077 | N17: =ROUND(SUM('Department Note Disclosure'!$B$16:$B$39),0) -> 3682077 | P17: =L17-N17 -> 0
D18: =IF(OR(P17>0.99, (P17<(-0.99))), "Please review and correct the variance.","")
A20: b) Proprietary - Internal Service Funds
B22: Journal Entries (Acct 0674 - RIGHT-TO-USE SBITA LIABILITY) | N22: Department Note Disclosure
B23: Beginning Balance | D23: Additions | F23: Deductions | H23: Deductions (Mod) | J23: Additions (Mod) | L23: Total
B24: Entry #0 | C24: + | D24: Entry #2 | E24: - | F24: Entry #5 | G24: - | H24: Entry #8 | I24: + | J24: Entry #9 | N24: Sum Principal Payments | P24: Variance
