Workbook
Name ActuaryCredentialsGASB: [1]DeveloperInfo!$D$19
Name ActuaryNameGASB: [1]DeveloperInfo!$D$17
Name ActuaryTitleGASB: [1]DeveloperInfo!$D$18
Name AdjCNSDate: [1]DeveloperInfo!$D$33
Name AdjCNSDate1: [1]DeveloperInfo!$E$33
Name AdjCNSDateTempEnable: [1]DeveloperInfo!$F$34
Name AgencyCode: #REF!
Name AgencyCode: #REF!
Name AgencyCode: #REF!
Name AgencyCode: #REF!
Name AgencyCode: #REF!
Name AgencyCode: #REF!
Name AgencyCode: #REF!
Name AgencyCode: #REF!
Name AgencyCode1: #REF!
Name AgencyCode1: #REF!
Name AgencyCode1: #REF!
Name AgencyCode1: #REF!
Name AgencyCode1: #REF!
Name AgencyCode1: #REF!
Name AgencyCode1: #REF!
Name AgencyCode1: #REF!
Name AnalystGASB: [1]DeveloperInfo!$D$20
Name Annuity: #REF!
Name Annuity: #REF!
Name Annuity: #REF!
Name Annuity: #REF!
Name Annuity: #REF!
Name Annuity: #REF!
Name Annuity: #REF!
Name Annuity: #REF!
Name Annuity1: #REF!
Name Annuity1: #REF!
Name Annuity1: #REF!
Name Annuity1: #REF!
Name Annuity1: #REF!
Name Annuity1: #REF!
Name Annuity1: #REF!
Name Annuity1: #REF!
Name AnnuityLY: #REF!
Name AnnuityLY: #REF!
Name AnnuityLY: #REF!
Name AnnuityLY: #REF!
Name AnnuityLY: #REF!
Name AnnuityLY: #REF!
Name AnnuityLY: #REF!
Name AnnuityLY: #REF!
Name ASTABPF: [1]DeveloperInfo!$D$36
Name ASTABPF1: [1]DeveloperInfo!$D$37
Name ASTEBPF: [1]DeveloperInfo!$F$37
Name ClientShortGASB: [1]DeveloperInfo!$D$9
Name CLPOWERDisc: [1]Adjust!$H$199
Name CLPOWERDiscMinus1: [1]Adjust!$L$199
Name CLPOWERDiscPlus1: [1]Adjust!$K$199
Name CLPOWERExp: [1]Adjust!$G$199
Name CNSDateDisc: [1]DeveloperInfo!$D$32
Name CNSDateDisc1: [1]DeveloperInfo!$E$32
Name ColaRate: [1]DeveloperInfo!$D$40
Name ConsultantNameGASB: [1]DeveloperInfo!$D$22
Name ConsultantTitleGASB: [1]DeveloperInfo!$D$23

Sheet Drop Down Menus
A1: 2021–2022 | B1: Governmental | C1: FI$Cal | D1: Yes | E1: Governmental Fund | G1: Please select fund type above.
A2: 2022–2023 | B2: Proprietary | C2: Non-FI$Cal | D2: No | E2: Proprietary - Internal Service Fund | F2: General government | G2: Cr: Acct 0808 - GENERAL GOV. (GAAP ADJ) | H2: Dr: Acct 0808 - GENERAL GOV. (GAAP ADJ)
A3: 2023–2024 | E3: Proprietary - Enterprise Fund | F3: Education | G3: Cr: Acct 0810 - EDUCATION EXP (GAAP ADJ) | H3: Dr: Acct 0810 - EDUCATION EXP (GAAP ADJ)
A4: 2024–2025 | F4: Health and human services | G4: Cr: Acct 0815 - HLTH&HUM SV SV.LAB(GAAP ADJ) | H4: Dr: Acct 0815 - HLTH&HUM SV SV.LAB(GAAP ADJ)
A5: 2025–2026 | F5: Resources | G5: Cr: Acct 0820 - NAT RES & ENVIRON (GAAP ADJ) | H5: Dr: Acct 0820 - NAT RES & ENVIRON (GAAP ADJ)
A6: 2026–2027 | F6: BUS, CONSUMER SERV, HOUSING | G6: Cr: Acct 0825 - BUS, CONSUMER SERV, HOUSING | H6: Dr: Acct 0825 - BUS, CONSUMER SERV, HOUSING
A7: 2027–2028 | F7: Transportation | G7: Cr: Acct 0830 - TRANSPORTATION (GAAP ADJ) | H7: Dr: Acct 0830 - TRANSPORTATION (GAAP ADJ)
A8: 2028–2029 | F8: CORRECTIONS AND REHABILITATION | G8: Cr: Acct 0835 - CORRECTIONS AND REHABILITATION | H8: Dr: Acct 0835 - CORRECTIONS AND REHABILITATION
A9: 2029–2030 | F9: Proprietary fund | G9: Cr: Acct 0870 - SERVICES & CHARGES (MG ADJ) | H9: Dr: Acct 0870 - SERVICES & CHARGES (MG ADJ)
A10: 2030–2031 | F10: Unidentified | G10: Cr: Acct 0XXX - FUNCTIONAL EXPENSE | H10: Dr: Acct 0XXX - FUNCTIONAL EXPENSE
A11: 2031–2032
A12: 2032–2033
A13: 2033–2034
A14: 2034–2035
A15: 2035–2036
A16: 2036–2037
A17: 2037–2038
A18: 2038–2039
A19: 2039–2040
A20: 2040–2041
A21: 2041–2042
A22: 2042–2043
... A101: 2121–2122

Sheet qryIndex02a
A1: Agency | B1: Title | C1: Hier1 | D1: Desc1 | E1: Desc2 | F1: Hier2 | G1: Hier3 | H1: Hier4 | I1: Hier5 | J1: EffectiveDate | K1: CancelDate
A2: 0000 | B2: BOND INTEREST AND REDEMPTION | C2: 9000 | D2: BOND INTEREST AND REDEMPTION | F2: 9030 | G2: 9600 | H2: 0000 | I2: 0000 | J2: 04/04/1984 | K2: 00/00/0000
A3: 0010 | B3: LEGISLATIVE, JUDICIAL AND EXEC | C3: 0808 | D3: GENERAL GOVERNMENT | F3: 0000 | G3: 0000 | H3: 0000 | I3: 0000 | J3: 07/11/2006 | K3: 00/00/0000
A4: 0015 | B4: ADD AGENCY TEST | C4: 0808 | D4: GENERAL GOVERNMENT | F4: 0000 | G4: 0000 | H4: 0000 | I4: 0000 | J4: 99/99/9999 | K4: 00/00/0000
A5: 0020 | B5: LEGISLATIVE | C5: 0808 | D5: GENERAL GOVERNMENT | F5: 0000 | G5: 0000 | H5: 0000 | I5: 0000 | J5: 99/99/9999 | K5: 00/00/0000
A6: 0100 | B6: LEGISLATURE | C6: 0808 | D6: GENERAL GOVERNMENT | F6: 0000 | G6: 0000 | H6: 0000 | I6: 0000 | J6: 99/99/9999 | K6: 00/00/0000
A7: 0110 | B7: SENATE | C7: 0808 | D7: GENERAL GOVERNMENT | F7: 0000 | G7: 0000 | H7: 0000 | I7: 0000 | J7: 06/26/1985 | K7: 00/00/0000
A8: 0120 | B8: ASSEMBLY | C8: 0808 | D8: GENERAL GOVERNMENT | F8: 0000 | G8: 0000 | H8: 0000 | I8: 0000 | J8: 06/26/1985 | K8: 00/00/0000
A9: 0130 | B9: LEGISLATIVE JOINT EXPENSES | C9: 0808 | D9: GENERAL GOVERNMENT | F9: 0000 | G9: 0000 | H9: 0000 | I9: 0000 | J9: 06/26/1985 | K9: 00/00/0000
A10: 0150 | B10: CONTRIB TO LEGIS RETIRE FUND | C10: 0808 | D10: GENERAL GOVERNMENT | F10: 0000 | G10: 0000 | H10: 0000 | I10: 0000 | J10: 07/11/2006 | K10: 00/00/0000
A11: 0155 | B11: AUDITOR GENERAL OFFICE | C11: 0808 | D11: GENERAL GOVERNMENT | F11: 0000 | G11: 0000 | H11: 0000 | I11: 0000 | J11: 99/99/9999 | K11: 00/00/0000
A12: 0160 | B12: LEGISLATIVE COUNSEL BUREAU | C12: 0808 | D12: GENERAL GOVERNMENT | F12: 0000 | G12: 0000 | H12: 0000 | I12: 0000 | J12: 04/04/1984 | K12: 00/00/0000
A13: 0170 | B13: CA LAW REVISION COMMISSION | C13: 0808 | D13: GENERAL GOVERNMENT | F13: 0000 | G13: 0000 | H13: 0000 | I13: 0000 | J13: 99/99/9999 | K13: 07/01/1985
... A190: 2140 | B190: STATE BANKING DEPARTMENT | C190: 0825 | D190: BUS, CONSUMER SERV, HOUSING | F190: 0000 | G190: 0000 | H190: 0000 | I190: 0000 | J190: 12/21/2016 | K190: 00/00/0000
A191: 2150 | B191: FINANCIAL INSTITUTIONS | C191: 0825 | D191: ADD BACK TO POST PY REVERSAL | E191: DELETE 16/17 | F191: 0000 | G191: 0000 | H191: 0000 | I191: 0000 | J191: 08/18/2016 | K191: 00/00/0000
A192: 2180 | B192: DEPART OF CORPORATIONS | C192: 0825 | D192: ADD BACK TO POST PY REVERSAL | E192: DELETE 16/17 | F192: 0000 | G192: 0000 | H192: 0000 | I192: 0000 | J192: 08/24/2016 | K192: 00/00/0000
A193: 2190 | B193: MAJOR MEDICAL INSURANCE BOARD | C193: 0825 | D193: BUS, CONSUMER SERV, HOUSING | F193: 0000 | G193: 0000 | H193: 0000 | I193: 0000 | J193: 12/21/2016 | K193: 00/00/0000
A194: 2200 | B194: DEPARTMENT OF COMMERCE | C194: 0825 | D194: BUS, CONSUMER SERV, HOUSING | F194: 0000 | G194: 0000 | H194: 0000 | I194: 0000 | J194: 12/21/2016 | K194: 00/00/0000
A195: 2220 | B195: OFFICE OF SMALL BUSINESS DEVEL | C195: 0825 | D195: BUS, CONSUMER SERV, HOUSING | F195: 0000 | G195: 0000 | H195: 0000 | I195: 0000 | J195: 12/21/2016 | K195: 00/00/0000
A196: 2222 | B196: ST ASST FD FOR ENTERPRISE | C196: 0825 | D196: BUS, CONSUMER SERV, HOUSING | F196: 0000 | G196: 0000 | H196: 0000 | I196: 0000 | J196: 12/21/2016 | K196: 00/00/0000
A197: 2225 | B197: UNITARY FUND PROGRAMS | C197: 0825 | D197: BUS, CONSUMER SERV, HOUSING | F197: 0000 | G197: 0000 | H197: 0000 | I197: 0000 | J197: 12/21/2016 | K197: 00/00/0000
A198: 2230 | B198: CA INDTRL DEV FINCL ADVRY COMM | C198: 0825 | D198: BUS, CONSUMER SERV, HOUSING | F198: 0000 | G198: 0000 | H198: 0000 | I198: 0000 | J198: 12/21/2016 | K198: 07/01/1985
A199: 2235 | B199: CA HOME LOAN MORTGAGE ASSN | C199: 0825 | D199: BUS, CONSUMER SERV, HOUSING | F199: 0000 | G199: 0000 | H199: 0000 | I199: 0000 | J199: 12/21/2016 | K199: 00/00/0000
A200: 2240 | B200: DEPT-HOUSING/COMMUNITY DEVEL | C200: 0825 | D200: BUS, CONSUMER SERV, HOUSING | F200: 0000 | G200: 0000 | H200: 0000 | I200: 0000 | J200: 12/12/2016 | K200: 00/00/1999
A201: 2245 | B201: CALIFORNIA HOUSING FINANCE AGY | C201: 0825 | D201: BUS, CONSUMER SERV, HOUSING | F201: 0000 | G201: 0000 | H201: 0000 | I201: 0000 | J201: 08/19/2016 | K201: 00/00/0000
A202: 2265 | B202: CALIFORNIA HOUSING INSURANCE | C202: 0825 | D202: BUS, CONSUMER SERV, HOUSING | F202: 0000 | G202: 0000 | H202: 0000 | I202: 0000 | J202: 12/21/2016 | K202: 00/00/0000
A203: 2270 | B203: MORTGAGE BOND ALLOC COMMITTEE | C203: 0825 | D203: BUS, CONSUMER SERV, HOUSING | F203: 0000 | G203: 0000 | H203: 0000 | I203: 0000 | J203: 12/21/2016 | K203: 07/01/1985
A204: 2290 | B204: DEPARTMENT OF INSURANCE | C204: 0825 | D204: BUS, CONSUMER SERV, HOUSING | F204: 0000 | G204: 0000 | H204: 0000 | I204: 0000 | J204: 12/21/2016 | K204: 00/00/1999
... A214: 2670 | B214: BD OF PILOT COMMISSIONERS-SF | C214: 0830 | D214: TRANSPORTATION | F214: 0000 | G214: 0000 | H214: 0000 | I214: 0000 | J214: 08/03/2017 | K214: 00/00/0000
A215: 2700 | B215: OFFICE OF TRAFFIC SAFETY | C215: 0830 | D215: TRANSPORTATION | E215: MERGED W/0521-ADD 4 PY ACCR RV | F215: 0000 | G215: 0000 | H215: 0000 | I215: 0000 | J215: 09/28/2016 | K215: 00/00/0000
A216: 2720 | B216: DEPT OF CAL HIGHWAY PATROL | C216: 0830 | D216: TRANSPORTATION | F216: 0000 | G216: 0000 | H216: 0000 | I216: 0000 | J216: 10/28/2016 | K216: 00/00/1999
A217: 2740 | B217: DEPARTMENT OF MOTOR VEHICLES | C217: 0830 | D217: TRANSPORTATION | F217: 0000 | G217: 0000 | H217: 0000 | I217: 0000 | J217: 10/28/2016 | K217: 00/00/0000
A218: 2780 | B218: STEPHEN P TEALE DATA CENTER | C218: 0825 | D218: BUS, CONSUMER SERV, HOUSING | F218: 0000 | G218: 0000 | H218: 0000 | I218: 0000 | J218: 12/21/2016 | K218: 00/00/0000
A219: 2900 | B219: TRADE AND COMMERCE | C219: 0825 | D219: BUS, CONSUMER SERV, HOUSING | F219: 0000 | G219: 0000 | H219: 0000 | I219: 0000 | J219: 12/21/2016 | K219: 00/00/0000
A220: 2920 | B220: TECHNOLOGY TRADE & COMMERCE AG | C220: 0825 | D220: BUS, CONSUMER SERV, HOUSING | F220: 0000 | G220: 0000 | H220: 0000 | I220: 0000 | J220: 12/21/2016 | K220: 00/00/0000
A221: 3000 | B221: NATURAL RESOURCES | C221: 0820 | D221: RESOURCES | F221: 0000 | G221: 0000 | H221: 0000 | I221: 0000 | J221: 08/25/2010 | K221: 00/00/0000
A222: 3100 | B222: EXPOSITION PARK | C222: 0820 | D222: RESOURCES | F222: 0000 | G222: 0000 | H222: 0000 | I222: 0000 | J222: 10/17/2018 | K222: 00/00/0000
A223: 3105 | B223: CALIFORNIA AFRO-AMERICAN MUSEU | C223: 0820 | D223: RESOURCES | F223: 0000 | G223: 0000 | H223: 0000 | I223: 0000 | J223: 09/05/2014 | K223: 00/00/0000
A224: 3110 | B224: SPECIAL RESOURCES PROGRAMS | C224: 0820 | D224: RESOURCES | F224: 0000 | G224: 0000 | H224: 0000 | I224: 0000 | J224: 07/11/2006 | K224: 00/00/1999
A225: 3125 | B225: CALIF TAHOE CONSERVANCY | C225: 0820 | D225: RESOURCES | F225: 0000 | G225: 0000 | H225: 0000 | I225: 0000 | J225: 04/18/1988 | K225: 00/00/1999
A226: 3130 | B226: WATERWAYS MANAGEMENT PLANNING | C226: 0820 | D226: RESOURCES | F226: 0000 | G226: 0000 | H226: 0000 | I226: 0000 | J226: 99/99/9999 | K226: 00/00/0000
A227: 3140 | B227: SEA GRANT PROGRAM | C227: 0820 | D227: RESOURCES | F227: 0000 | G227: 0000 | H227: 0000 | I227: 0000 | J227: 99/99/9999 | K227: 00/00/0000
... A278: 4140 | B278: OFFICE OF HEALTH PLAN & DEV | C278: 0815 | D278: HEALTH AND HUMAN SERVICES | F278: 0000 | G278: 0000 | H278: 0000 | I278: 0000 | J278: 10/28/2016 | K278: 00/00/0000
A279: 4150 | B279: DEPT OF MANAGED HEALTH CARE | C279: 0815 | D279: HEALTH AND HUMAN SERVICES | E279: RENUMBERED FROM 2400 | F279: 0000 | G279: 0000 | H279: 0000 | I279: 0000 | J279: 10/28/2016 | K279: 00/00/0000
A280: 4170 | B280: DEPARTMENT OF AGING | C280: 0815 | D280: HEALTH AND HUMAN SERVICES | F280: 0000 | G280: 0000 | H280: 0000 | I280: 0000 | J280: 10/28/2016 | K280: 00/00/1999
A281: 4180 | B281: COMMISSION ON AGING | C281: 0815 | D281: HEALTH AND HUMAN SERVICES | F281: 0000 | G281: 0000 | H281: 0000 | I281: 0000 | J281: 10/28/2016 | K281: 00/00/1999
A282: 4185 | B282: CALIFORNIA SENIOR LEGISLATURE | C282: 0815 | D282: HEALTH AND HUMAN SERVICES | F282: 0000 | G282: 0000 | H282: 0000 | I282: 0000 | J282: 10/28/2016 | K282: 00/00/0000
A283: 4210 | B283: GOV COUNCIL DRUG/ALCOHOL ABUSE | C283: 0815 | D283: HEALTH AND HUMAN SERVICES | F283: 0000 | G283: 0000 | H283: 0000 | I283: 0000 | J283: 10/28/2016 | K283: 00/00/0000
A284: 4220 | B284: GOV ADV COM CHILD DEVEL PROG | C284: 0815 | D284: HEALTH AND HUMAN SERVICES | F284: 0000 | G284: 0000 | H284: 0000 | I284: 0000 | J284: 10/28/2016 | K284: 00/00/0000
A285: 4250 | B285: CA. CHILDREN AND FAMILIES COMM | C285: 0815 | D285: HEALTH AND HUMAN SERVICES | F285: 0000 | G285: 0000 | H285: 0000 | I285: 0000 | J285: 10/28/2016 | K285: 00/00/0000
A286: 4260 | B286: DEPARTMENT OF HEALTH CARE SVCS | C286: 0815 | D286: HEALTH AND HUMAN SERVICES | F286: 0000 | G286: 0000 | H286: 0000 | I286: 0000 | J286: 10/28/2016 | K286: 00/00/0000
A287: 4265 | B287: DEPARTMENT OF PUBLIC HEALTH | C287: 0815 | D287: HEALTH AND HUMAN SERVICES | F287: 0000 | G287: 0000 | H287: 0000 | I287: 0000 | J287: 10/28/2016 | K287: 00/00/0000
A288: 4270 | B288: CAL MED ASSISTANCE COMMISSION | C288: 0815 | D288: HEALTH AND HUMAN SERVICES | F288: 0000 | G288: 0000 | H288: 0000 | I288: 0000 | J288: 10/28/2016 | K288: 00/00/1999
A289: 4280 | B289: MANAGED RISK MED INSUR BD. | C289: 0815 | D289: HEALTH AND HUMAN SERVICES | F289: 0000 | G289: 0000 | H289: 0000 | I289: 0000 | J289: 10/28/2016 | K289: 00/00/0000
A290: 4300 | B290: DEPT. DEVELOPMENTAL SVCS | C290: 0815 | D290: HEALTH AND HUMAN SERVICES | F290: 0000 | G290: 0000 | H290: 0000 | I290: 0000 | J290: 10/28/2016 | K290: 00/00/0000
A291: 4310 | B291: DO NOT USE AGENCY MERGED WITH | C291: 0815 | F291: 0000 | G291: 0000 | H291: 0000 | I291: 0000 | J291: 09/07/2018 | K291: 00/00/0000
A292: 4320 | B292: STATE HOSPITALS | C292: 0815 | D292: HEALTH AND HUMAN SERVICES | F292: 0000 | G292: 0000 | H292: 0000 | I292: 0000 | J292: 10/28/2016 | K292: 00/00/0000
A293: 4350 | B293: DO NOT USE AGENCY MERGED WITH | C293: 0815 | F293: 0000 | G293: 0000 | H293: 0000 | I293: 0000 | J293: 09/07/2018 | K293: 00/00/0000
A294: 4370 | B294: DO NOT USE AGENCY MERGED WITH | C294: 0815 | F294: 0000 | G294: 0000 | H294: 0000 | I294: 0000 | J294: 09/07/2018 | K294: 00/00/0000
A295: 4390 | B295: DO NOT USE AGENCY MERGED WITH | C295: 0815 | F295: 0000 | G295: 0000 | H295: 0000 | I295: 0000 | J295: 09/07/2018 | K295: 00/00/0000
A296: 4400 | B296: DO NOT USE AGENCY MERGED WITH | C296: 0815 | F296: 0000 | G296: 0000 | H296: 0000 | I296: 0000 | J296: 09/07/2018 | K296: 00/00/0000
A297: 4430 | B297: DO NOT USE AGENCY MERGED WITH | C297: 0815 | F297: 0000 | G297: 0000 | H297: 0000 | I297: 0000 | J297: 09/07/2018 | K297: 00/00/0000
A298: 4440 | B298: DEPT. OF STATE HOSPITAL | C298: 0815 | D298: HEALTH AND HUMAN SERVICES | F298: 0000 | G298: 0000 | H298: 0000 | I298: 0000 | J298: 10/28/2016 | K298: 00/00/0000
A299: 4450 | B299: SACRAMENTO STATE HOSPITAL | C299: 0815 | D299: HEALTH AND HUMAN SERVICES | F299: 0000 | G299: 0000 | H299: 0000 | I299: 0000 | J299: 10/28/2016 | K299: 00/00/1999
A300: 4460 | B300: STATE HOSPITALS | C300: 0815 | D300: HEALTH AND HUMAN SERVICES | F300: 0000 | G300: 0000 | H300: 0000 | I300: 0000 | J300: 10/28/2016 | K300: 00/00/0000
A301: 4470 | B301: ATASCADERO STATE HOSPITAL | C301: 0815 | D301: HEALTH AND HUMAN SERVICES | F301: 0000 | G301: 0000 | H301: 0000 | I301: 0000 | J301: 10/28/2016 | K301: 00/00/1999
A302: 4490 | B302: METROPOLITAN STATE HOSPITAL | C302: 0815 | D302: HEALTH AND HUMAN SERVICES | F302: 0000 | G302: 0000 | H302: 0000 | I302: 0000 | J302: 10/28/2016 | K302: 00/00/1999
A303: 4500 | B303: NAPA STATE HOSPITAL | C303: 0815 | D303: HEALTH AND HUMAN SERVICES | F303: 0000 | G303: 0000 | H303: 0000 | I303: 0000 | J303: 10/28/2016 | K303: 00/00/1999
A304: 4510 | B304: PATTON STATE HOSPITAL | C304: 0815 | D304: HEALTH AND HUMAN SERVICES | F304: 0000 | G304: 0000 | H304: 0000 | I304: 0000 | J304: 10/28/2016 | K304: 00/00/1999
A305: 4520 | B305: STOCKTON STATE HOSPITAL-DMH | C305: 0815 | D305: HEALTH AND HUMAN SERVICES | F305: 0000 | G305: 0000 | H305: 0000 | I305: 0000 | J305: 10/28/2016 | K305: 00/00/1999
A306: 4530 | B306: VACAVILLE STATE HOSPITAL | C306: 0815 | D306: HEALTH AND HUMAN SERVICES | F306: 0000 | G306: 0000 | H306: 0000 | I306: 0000 | J306: 10/28/2016 | K306: 00/00/0000
A307: 4540 | B307: COALINGA STATE HOSPITAL | C307: 0815 | D307: HEALTH AND HUMAN SERVICES | F307: 0000 | G307: 0000 | H307: 0000 | I307: 0000 | J307: 10/28/2016 | K307: 00/00/0000
A308: 4550 | B308: SALINAS STATE HOSPITAL | C308: 0815 | D308: HEALTH AND HUMAN SERVICES | F308: 0000 | G308: 0000 | H308: 0000 | I308: 0000 | J308: 10/28/2016 | K308: 00/00/0000
A309: 4560 | B309: MENTAL HEALTH SVCS OVERSIGHT | C309: 0815 | D309: HEALTH AND HUMAN SERVICES | F309: 0000 | G309: 0000 | H309: 0000 | I309: 0000 | J309: 10/28/2016 | K309: 00/00/0000
... A597: 9610 | B597: LEASE-REV NOTES & BONDS | C597: 9000 | D597: DEBT SERVICE INT & FISCAL CHGS | F597: 9030 | G597: 9610 | H597: 0000 | I597: 0000 | J597: 08/19/2016 | K597: 00/00/0000
A598: 9612 | B598: ENHN TOBAC ASSET-BACKED BND | C598: 0847 | D598: BOND INTEREST AND REDEMPTION | E598: WHEN TOBACCO REVENUE IS SHORT | F598: 0000 | G598: 0000 | H598: 0000 | I598: 0000 | J598: 08/19/2016 | K598: 00/00/0000
A599: 9613 | B599: UNENHANCED TOBACCO BD PROCEEDS | C599: 0808 | D599: GENERAL GOVERNMENT | F599: 0000 | G599: 0000 | H599: 0000 | I599: 0000 | J599: 02/26/2008 | K599: 00/00/0000
A600: 9618 | B600: ECONOMIC RECOVERY FINANCE COMM | C600: 0808 | D600: GENERAL GOVERNMENT | F600: 0000 | G600: 0000 | H600: 0000 | I600: 0000 | J600: 10/28/2005 | K600: 00/00/0000
A601: 9620 | B601: CASH MGMT & BUDGETARY LOANS | C601: 0850 | D601: DEBT SERVICE INT & FISCAL CHGS | F601: 0000 | G601: 0000 | H601: 0000 | I601: 0000 | J601: 08/19/2016 | K601: 00/00/0000
A602: 9625 | B602: INT PYMTS TO FEDERAL GOVT | C602: 0846 | D602: DEBT SERVICE INT & FISCAL CHGS | F602: 0000 | G602: 0000 | H602: 0000 | I602: 0000 | J602: 08/19/2016 | K602: 00/00/0000
A603: 9632 | B603: STATE MANDATED LOCAL COSTS | C603: 0808 | D603: GENERAL GOVERNMENT | F603: 0000 | G603: 0000 | H603: 0000 | I603: 0000 | J603: 99/99/9999 | K603: 00/00/0000
A604: 9634 | B604: GENERAL OBLIGATION BONDS | C604: 9000 | D604: GENERAL OBLIGATION BONDS | F604: 9030 | G604: 9634 | H604: 0000 | I604: 0000 | J604: 06/13/1988 | K604: 00/00/0000
A605: 9636 | B605: MISCELLANEOUS ADJUSTMENTS | C605: 9000 | D605: MISCELLANEOUS ADJUSTMENTS | F605: 9030 | G605: 9636 | H605: 0000 | I605: 0000 | J605: 06/13/1988 | K605: 00/00/0000
A606: 9650 | B606: HEALTH BENEFITS FOR ANNUITANTS | C606: 0808 | D606: GENERAL GOVERNMENT | F606: 0000 | G606: 0000 | H606: 0000 | I606: 0000 | J606: 04/04/1984 | K606: 00/00/0000
A607: 9651 | B607: PREFUND HEALTH & DENTAL BEN | C607: 0808 | D607: GENERAL GOVERNMENT | F607: 0000 | G607: 0000 | H607: 0000 | I607: 0000 | J607: 08/25/2010 | K607: 00/00/0000
A608: 9658 | B608: BUDGET STABILIZATION ACCOUNT | C608: 0808 | D608: GENERAL GOVERNMENT | F608: 0000 | G608: 0000 | H608: 0000 | I608: 0000 | J608: 07/11/2006 | K608: 00/00/0000
A609: 9670 | B609: LEGISLATIVE CLAIMS | C609: 0808 | D609: GENERAL GOVERNMENT | F609: 0000 | G609: 0000 | H609: 0000 | I609: 0000 | J609: 04/04/1984 | K609: 00/00/0000
A610: 9671 | B610: EQUITY CLAIMS OF BD OF CONTROL | C610: 0808 | D610: GENERAL GOVERNMENT | F610: 0000 | G610: 0000 | H610: 0000 | I610: 0000 | J610: 03/30/1994 | K610: 00/00/0000
... A635: 9885 | B635: RESERVE FOR ENCUMBRANCE | C635: 0808 | D635: GENERAL GOVERNMENT | F635: 0000 | G635: 0000 | H635: 0000 | I635: 0000 | J635: 01/23/1991 | K635: 00/00/0000
A636: 9889 | B636: PUBLIC SCHOOL SYSTEM STABILIZA | C636: 0810 | D636: PUBLIC SCHOOL SYSTEM | E636: STABILIZATION ACCOUNT | F636: 0000 | G636: 0000 | H636: 0000 | I636: 0000 | J636: 04/01/2020 | K636: 00/00/0000
A637: 9890 | B637: RES FOR ECONOMIC UNCERTAINTIES | C637: 0808 | D637: GENERAL GOVERNMENT | F637: 0000 | G637: 0000 | H637: 0000 | I637: 0000 | J637: 07/11/2006 | K637: 00/00/0000
A638: 9891 | B638: DEPT OF HEALTH HUMAN SERVICES | C638: 0815 | D638: HEALTH AND HUMAN SERVICES | F638: 0000 | G638: 0000 | H638: 0000 | I638: 0000 | J638: 10/28/2016 | K638: 00/00/0000
A639: 9892 | B639: SUPPLEMENTAL PENSION PAYMENTS | C639: 0843 | D639: INT. ON INTERFUND LOANS | F639: 0000 | G639: 0000 | H639: 0000 | I639: 0000 | J639: 11/22/2019 | K639: 00/00/0000
A640: 9895 | B640: PETROLEUM VIOLATION ESCROW PRO | C640: 0808 | D640: GENERAL GOVERNMENT | F640: 0000 | G640: 0000 | H640: 0000 | I640: 0000 | J640: 07/11/2006 | K640: 00/00/0000
A641: 9896 | B641: OUTER CONT SHELF LAND ACT | C641: 0808 | D641: GENERAL GOVERNMENT | F641: 0000 | G641: 0000 | H641: 0000 | I641: 0000 | J641: 07/11/2006 | K641: 00/00/0000
A642: 9898 | B642: PERS GENERAL FUND PAYMENT | C642: 0808 | D642: GENERAL GOVERNMENT | F642: 0000 | G642: 0000 | H642: 0000 | I642: 0000 | J642: 11/04/1998 | K642: 00/00/0000
A643: 9900 | B643: GEN FD CREDITS FROM SPEC FUNDS | C643: 0808 | D643: GENERAL GOVERNMENT | F643: 0000 | G643: 0000 | H643: 0000 | I643: 0000 | J643: 07/11/2006 | K643: 00/00/0000
A644: 9901 | B644: STATEWIDE GEN ADM EXP (PR) | C644: 0808 | D644: GENERAL GOVERNMENT | F644: 0000 | G644: 0000 | H644: 0000 | I644: 0000 | J644: 07/11/2006 | K644: 00/00/0000
A645: 9909 | B645: HLTH INS PORTABLTY ACCTABLTY | C645: 0815 | D645: HEALTH AND HUMAN SERVICES | F645: 0000 | G645: 0000 | H645: 0000 | I645: 0000 | J645: 10/28/2016 | K645: 00/00/0000
A646: 9910 | B646: GEN FD CREDITS FROM FED FUNDS | C646: 0808 | D646: GENERAL GOVERNMENT | F646: 0000 | G646: 0000 | H646: 0000 | I646: 0000 | J646: 07/11/2006 | K646: 00/00/0000
...

Sheet LS-Fund #### JE
A1: Lessee-Type Contracts Fund-by-Fund Journal Entries Form (to be submitted to the SCO annually—one form per fund)
A2: Manually complete every yellow field in this worksheet—there are no automatically calculated data-entry cells in this worksheet.
A3: Fiscal Year: | F3: 2023–2024
A4: Organization Name:
A5: Organization Code (4-Digits):
A6: Fund Number (4-Digits):
A7: Fund Classification:
A8: Fund Type:
A9: Functional Expense: | F9: =IFERROR(IF(F7="Proprietary","Proprietary Fund",VLOOKUP(F5,qryIndex02a!$A$2:$K$654,4,FALSE)),"Unidentified") -> Unidentified
A12: Establish Beginning Balances (existing leases only)
A13: Entry #
A14: 0 | B14: Roll forward prior year right-to-use leases to record opening balances. | M14: Combined Lessee Templates | P14: From SCO BB List | S14: Difference
A15: *Rpt 18 | B15: Dr: Acct 0476 - RIGHT-TO-USE LEASED LAND - AMORTIZABLE | J15: =M15 -> 0 | S15: =P15-M15 -> 0 | T15: Report any "Differences" on the Report 18 Differential.
A16: *Rpt 18 | B16: Dr: Acct 0478 - RIGHT-TO-USE LEASED EQUIPMENT - AMORTIZABLE | J16: =M16 -> 0 | S16: =P16-M16 -> 0 | T16: Report any "Differences" on the Report 18 Differential.
A17: *Rpt 18 | B17: Dr: Acct 0477 - RIGHT-TO-USE LEASED BUILDINGS - AMORTIZABLE | J17: =M17 -> 0 | S17: =P17-M17 -> 0 | T17: Report any "Differences" on the Report 18 Differential.
B18: Dr: Acct 0950 - BEGINNING FUND BALANCE | J18: =P18 -> 0 | P18: =IF(SUM($Q$20:$Q$23)>SUM($P$15:$P$17),SUM($Q$20:$Q$23)-SUM($P$15:$P$17),0) -> 0 | S18: =P18-M18 -> 0 | T18: No action required.
B19: Dr: Acct 0952 - BEGINNING FUND ADJUSTMENT/PRIOR PERIOD ADJUSTMENT | J19: =IF(SUM($K$20:$K$24)>SUM($J$15:$J$18),SUM($K$20:$K$24)-SUM($J$15:$J$18),0) -> 0 | S19: =P19-M19 -> 0 | T19: No action required.
C20: Cr: Acct 0485 - ACCUMULATED AMORTIZATION - RIGHT-TO-USE LEASED LAND | K20: =N20 -> 0 | S20: =Q20-N20 -> 0 | T20: No action required.
C21: Cr: Acct 0479 - ACCUMULATED AMORTIZATION - RIGHT-TO-USE LEASED EQUIPMENT | K21: =N21 -> 0 | S21: =Q21-N21 -> 0 | T21: No action required.
C22: Cr: Acct 0486 - ACCUMULATED AMORTIZATION - RIGHT-TO-USE LEASED BUILDINGS | K22: =N22 -> 0 | S22: =Q22-N22 -> 0 | T22: No action required.
A23: **LS LL/CF | C23: Cr: Acct 0691 - RIGHT-TO-USE LEASE LIABILITY | K23: =N23 -> 0 | S23: =Q23-N23 -> 0 | T23: No action required.
C24: Cr: Acct 0950 - BEGINNING FUND BALANCE | K24: =Q24 -> 0 | Q24: =IF(SUM($Q$20:$Q$23)<SUM($P$15:$P$17),-SUM($Q$20:$Q$23)+SUM($P$15:$P$17),0) -> 0 | S24: =Q24-N24 -> 0 | T24: No action required.
C25: Cr: Acct 0952 - BEGINNING FUND ADJUSTMENT/PRIOR PERIOD ADJUSTMENT | K25: =IF(SUM($K$20:$K$24)<SUM($J$15:$J$18),-SUM($K$20:$K$24)+SUM($J$15:$J$18),0) -> 0 | S25: =Q25-N25 -> 0 | T25: No action required.
J26: =SUM(J15:J25) -> 0 | K26: =SUM(K15:K25) -> 0 | L26: =IF(J26=K26,"<- Debits and Credits equal each other.","<- Debits and Credits do not equal each other.") -> <- Debits and Credits equal each other.
B27: * THESE ASSET AMOUNTS SHOULD BE REPORTED AS BEGINNING BALANCES ON REPORT 18.
B28: ** This amount should be included in the beginning balance column on the LS-Lease Liability and LS-Check Figures Tabs.
A31: Record New Leases (new leases only)
A32: 1 | B32: Record lease contract commencement (fund-based entries only)
B33: Dr: Acct 0842 - CAPITAL OUTLAY
C34: Cr: Acct 0789 - LEASE AND OTHER FINANCING PROCEEDS
C35: =IF($F$7="Proprietary","Cr: Acct 0870 - SERVICES & CHARGES (MG ADJ)",VLOOKUP($F$9,'Drop Down Menus'!$F$2:$G$10,2,FALSE)) -> Cr: Acct 0XXX - FUNCTIONAL EXPENSE
J36: =SUM(J33:J35) -> 0 | K36: =SUM(K33:K35) -> 0 | L36: =IF(J36=K36,"<- Debits and Credits equal each other.","<- Debits and Credits do not equal each other.") -> <- Debits and Credits equal each other.
A38: 2 | B38: Record leased assets.
A39: *Rpt 18 | B39: Dr: Acct 0476 - RIGHT-TO-USE LEASED LAND - AMORTIZABLE
A40: *Rpt 18 | B40: Dr: Acct 0478 - RIGHT-TO-USE LEASED EQUIPMENT - AMORTIZABLE
A41: *Rpt 18 | B41: Dr: Acct 0477 - RIGHT-TO-USE LEASED BUILDINGS - AMORTIZABLE
C42: Cr: Acct 0842 - CAPITAL OUTLAY
B43: * THESE AMOUNTS SHOULD BE INCLUDED AS "ADDITIONS" ON REPORT 18. | J43: =SUM(J39:J42) -> 0 | K43: =SUM(K39:K42) -> 0 | L43: =IF(J43=K43,"<- Debits and Credits equal each other.","<- Debits and Credits do not equal each other.") -> <- Debits and Credits equal each other.
A46: 3 | B46: Replace proceeds from leases with right-to-use lease liability.
B47: Dr: Acct 0789 - LEASE AND OTHER FINANCING PROCEEDS
A48: **LS LL/CF | C48: Cr: Acct 0691 - RIGHT-TO-USE LEASE LIABILITY
J49: =SUM(J47:J48) -> 0 | K49: =SUM(K47:K48) -> 0 | L49: =IF(J49=K49,"<- Debits and Credits equal each other.","<- Debits and Credits do not equal each other.") -> <- Debits and Credits equal each other.
B50: ** This amount should be included in the additions column on the LS-Lease Liability and LS-Check Figures Tabs.
A53: Record Annual Activity (all leases)
A54: 4 | B54: Record amortization of the leased assets for the year.
B55: Dr: Acct 0875 - DEPRECIATION/AMORTIZATION
C56: Cr: Acct 0485 - ACCUMULATED AMORTIZATION - RIGHT-TO-USE LEASED LAND
C57: Cr: Acct 0479 - ACCUMULATED AMORTIZATION - RIGHT-TO-USE LEASED EQUIPMENT
C58: Cr: Acct 0486 - ACCUMULATED AMORTIZATION - RIGHT-TO-USE LEASED BUILDINGS
J59: =SUM(J55:J58) -> 0 | K59: =SUM(K55:K58) -> 0 | L59: =IF(J59=K59,"<- Debits and Credits equal each other.","<- Debits and Credits do not equal each other.") -> <- Debits and Credits equal each other.
A61: 5 | B61: Reclassify rents and leases exp. to lease contract principal and interest exp.
B62: Dr: Acct 0848 - DEBT SERVICE - PRINCIPAL LEASES | L62: =IF($J$62=$K$69,"","<- Accts 0848 must agree")
B63: =IF($F$7="Governmental","Dr: Acct 0851 - DEBT SERVICE - INTEREST LEASES","Dr: Acct 0894 - INTEREST EXPENSE AND FISCAL CHARGES") -> Dr: Acct 0894 - INTEREST EXPENSE AND FISCAL CHARGES
C64: =IF($F$7="Proprietary","Cr: Acct 0870 - SERVICES & CHARGES (MG ADJ)",VLOOKUP($F$9,'Drop Down Menus'!$F$2:$G$10,2,FALSE)) -> Cr: Acct 0XXX - FUNCTIONAL EXPENSE
J65: =SUM(J62:J64) -> 0 | K65: =SUM(K62:K64) -> 0 | L65: =IF(J65=K65,"<- Debits and Credits equal each other.","<- Debits and Credits do not equal each other.") -> <- Debits and Credits equal each other.
A67: 6 | B67: Reduce lease contracts liability for total current year principal payments.
A68: **LS LL/CF | B68: Dr: Acct 0691 - RIGHT-TO-USE LEASE LIABILITY
C69: Cr: Acct 0848 - DEBT SERVICE - PRINCIPAL LEASES | L69: =IF($J$62=$K$69,"","<- Accts 0848 must agree")
J70: =SUM(J68:J69) -> 0 | K70: =SUM(K68:K69) -> 0 | L70: =IF(J70=K70,"<- Debits and Credits equal each other.","<- Debits and Credits do not equal each other.") -> <- Debits and Credits equal each other.
B71: ** This amount should be included in the deductions column on the LS-Lease Liability and LS-Check Figures Tabs.
A74: 7 | B74: Reclassify the principal amount due in the next FY to the current liability.
A75: **LS LL/CF | B75: Dr: Acct 0691 - RIGHT-TO-USE LEASE LIABILITY
C76: Cr: Acct 0649 - RIGHT-TO-USE LEASE LIABILITY (CURRENT PORTION LT)
B77: NOTE: This is an annual accrual. It is to be reversed at the start of the next fiscal year. SCO combines the current and non current amount in Entry #0 to reestablish the beginning balances. No action required. | J77: =SUM(J75:J76) -> 0 | K77: =SUM(K75:K76) -> 0 | L77: =IF(J77=K77,"<- Debits and Credits equal each other.","<- Debits and Credits do not equal each other.") -> <- Debits and Credits equal each other.
B80: ** This amount should be included in the due in one year column on the LS-Lease Liability and LS-Check Figures Tabs.
A83: Remove Lease Asset at the End of the Lease Term (only at the end of the lease term)
A84: 8 | B84: Record entry to write off the lease asset and accumulated amortization at the end of the lease term.
B85: Dr: Acct 0485 - ACCUMULATED AMORTIZATION - RIGHT-TO-USE LEASED LAND
B86: Dr: Acct 0479 - ACCUMULATED AMORTIZATION - RIGHT-TO-USE LEASED EQUIPMENT
B87: Dr: Acct 0486 - ACCUMULATED AMORTIZATION - RIGHT-TO-USE LEASED BUILDINGS
A88: *Rpt 18 | C88: Cr: Acct 0476 - RIGHT-TO-USE LEASED LAND - AMORTIZABLE
A89: *Rpt 18 | C89: Cr: Acct 0478 - RIGHT-TO-USE LEASED EQUIPMENT - AMORTIZABLE
A90: *Rpt 18 | C90: Cr: Acct 0477 - RIGHT-TO-USE LEASED BUILDINGS - AMORTIZABLE
B91: * THESE AMOUNTS SHOULD BE INCLUDED AS "DEDUCTIONS" ON REPORT 18. | J91: =SUM(J85:J90) -> 0 | K91: =SUM(K85:K90) -> 0 | L91: =IF(J91=K91,"<- Debits and Credits equal each other.","<- Debits and Credits do not equal each other.") -> <- Debits and Credits equal each other.
A94: Lease Remeasurement and Modifications (only if a significant modification occurred during the fiscal year)
A95: 9 | B95: Record early termination or lease modifications to decrease in the RTU leased asset.
A96: **LS LL/CF | B96: Dr: Acct 0691 - RIGHT-TO-USE LEASE LIABILITY
B97: Dr: Acct 0485 - ACCUMULATED AMORTIZATION - RIGHT-TO-USE LEASED LAND
B98: Dr: Acct 0479 - ACCUMULATED AMORTIZATION - RIGHT-TO-USE LEASED EQUIPMENT
B99: Dr: Acct 0486 - ACCUMULATED AMORTIZATION - RIGHT-TO-USE LEASED BUILDINGS
B100: =IF($F$7="Proprietary","Dr: Acct 0870 - SERVICES & CHARGES (MG ADJ)",VLOOKUP($F$9,'Drop Down Menus'!$F$2:$H$10,3,FALSE)) -> Dr: Acct 0XXX - FUNCTIONAL EXPENSE
A101: *Rpt 18 | C101: Cr: Acct 0476 - RIGHT-TO-USE LEASED LAND - AMORTIZABLE
A102: *Rpt 18 | C102: Cr: Acct 0478 - RIGHT-TO-USE LEASED EQUIPMENT - AMORTIZABLE
A103: *Rpt 18 | C103: Cr: Acct 0477 - RIGHT-TO-USE LEASED BUILDINGS - AMORTIZABLE
C104: =IF($F$7="Proprietary","Dr: Acct 0870 - SERVICES & CHARGES (MG ADJ)",VLOOKUP($F$9,'Drop Down Menus'!$F$2:$G$10,2,FALSE)) -> Cr: Acct 0XXX - FUNCTIONAL EXPENSE
B105: * THESE AMOUNTS SHOULD BE INCLUDED AS "DEDUCTIONS" ON REPORT 18. | J105: =SUM(J96:J104) -> 0 | K105: =SUM(K96:K104) -> 0 | L105: =IF(J105=K105,"<- Debits and Credits equal each other.","<- Debits and Credits do not equal each other.") -> <- Debits and Credits equal each other.
B106: ** This amount should be included in the deductions column on the LS-Lease Liability and LS-Check Figures Tabs.
A109: 10 | B109: Record lease modifications to increase in the RTU leased asset.
A110: *Rpt 18 | B110: Dr: Acct 0476 - RIGHT-TO-USE LEASED LAND - AMORTIZABLE
A111: *Rpt 18 | B111: Dr: Acct 0478 - RIGHT-TO-USE LEASED EQUIPMENT - AMORTIZABLE
A112: *Rpt 18 | B112: Dr: Acct 0477 - RIGHT-TO-USE LEASED BUILDINGS - AMORTIZABLE
A113: **LS LL/CF | C113: Cr: Acct 0691 - RIGHT-TO-USE LEASE LIABILITY
B114: * THESE AMOUNTS SHOULD BE INCLUDED AS "ADDITIONS" ON REPORT 18. | J114: =SUM(J110:J113) -> 0 | K114: =SUM(K110:K113) -> 0 | L114: =IF(J114=K114,"<- Debits and Credits equal each other.","<- Debits and Credits do not equal each other.") -> <- Debits and Credits equal each other.
B115: ** This amount should be included in the additions column on the LS-Lease Liability and LS-Check Figures Tabs.
D120: Informational - Ending Balances of Assets and Liabilities
K121: Debit (Credit)
D122: Acct 0476 - RIGHT-TO-USE LEASED LAND - AMORTIZABLE | K122: =J15+J39-K88-K101+J110 -> 0
D123: Acct 0478 - RIGHT-TO-USE LEASED EQUIPMENT - AMORTIZABLE | K123: =J16+J40-K89-K102+J111 -> 0
D124: Acct 0477 - RIGHT-TO-USE LEASED BUILDINGS - AMORTIZABLE | K124: =J17+J41-K90-K103+J112 -> 0
D125: Acct 0485 - ACCUMULATED AMORTIZATION - RIGHT-TO-USE LEASED LAND | K125: =-K20-K56+J85+J97 -> 0
...

Sheet LS-Fund 0001 Journal Entries
A1: Lessee-Type Contracts Fund-by-Fund Journal Entries Form (to be submitted to the SCO annually—one form per fund)
A2: Manually complete every yellow field in this worksheet—there are no automatically calculated data-entry cells in this worksheet.
A3: Fiscal Year: | F3: 2023–2024
A4: Organization Name: | F4: Department of Justice
A5: Organization Code (4-Digits): | F5: 0820
A6: Fund Number (4-Digits): | F6: 1
A7: Fund Classification: | F7: Governmental
A8: Fund Type: | F8: Governmental Fund
A9: Functional Expense: | F9: =IFERROR(IF(F7="Proprietary","Proprietary Fund",VLOOKUP(F5,qryIndex02a!$A$2:$K$654,4,FALSE)),"Unidentified") -> GENERAL GOVERNMENT
A12: Establish Beginning Balances (existing leases only)
A13: Entry #
A14: 0 | B14: Roll forward prior year right-to-use leases to record opening balances. | M14: Combined Lessee Templates | P14: From SCO BB List | S14: Difference
A15: *Rpt 18 | B15: Dr: Acct 0476 - RIGHT-TO-USE LEASED LAND - AMORTIZABLE | J15: =M15 -> 0 | M15: 0 | P15: 0 | S15: =P15-M15 -> 0 | T15: Report any "Differences" on the Report 18 Differential.
A16: *Rpt 18 | B16: Dr: Acct 0478 - RIGHT-TO-USE LEASED EQUIPMENT - AMORTIZABLE | J16: =M16 -> 54341.588 | M16: 54341.588 | P16: 54342 | S16: =P16-M16 -> 0.411964 | T16: Report any "Differences" on the Report 18 Differential.
A17: *Rpt 18 | B17: Dr: Acct 0477 - RIGHT-TO-USE LEASED BUILDINGS - AMORTIZABLE | J17: =M17 -> 56311884 | M17: 56311884 | P17: 57141192 | S17: =P17-M17 -> 829308.46 | T17: Report any "Differences" on the Report 18 Differential.
B18: Dr: Acct 0950 - BEGINNING FUND BALANCE | J18: =P18 -> 788510 | M18: 1039549.5 | P18: =IF(SUM($Q$20:$Q$23)>SUM($P$15:$P$17),SUM($Q$20:$Q$23)-SUM($P$15:$P$17),0) -> 788510 | S18: =P18-M18 -> -251039.48 | T18: No action required.
B19: Dr: Acct 0952 - BEGINNING FUND ADJUSTMENT/PRIOR PERIOD ADJUSTMENT | J19: =IF(SUM($K$20:$K$24)>SUM($J$15:$J$18),SUM($K$20:$K$24)-SUM($J$15:$J$18),0) -> 23371.789 | M19: 0 | S19: =P19-M19 -> 0 | T19: No action required.
C20: Cr: Acct 0485 - ACCUMULATED AMORTIZATION - RIGHT-TO-USE LEASED LAND | K20: =N20 -> 0 | N20: 0 | S20: =Q20-N20 -> 0 | T20: No action required.
C21: Cr: Acct 0479 - ACCUMULATED AMORTIZATION - RIGHT-TO-USE LEASED EQUIPMENT | K21: =N21 -> 21736.547 | N21: 21736.547 | Q21: 21736 | S21: =Q21-N21 -> -0.5466005 | T21: No action required.
C22: Cr: Acct 0486 - ACCUMULATED AMORTIZATION - RIGHT-TO-USE LEASED BUILDINGS | K22: =N22 -> 16828663 | N22: 16828663 | Q22: 17411023 | S22: =Q22-N22 -> 582359.65 | T22: No action required.
A23: **LS LL/CF | C23: Cr: Acct 0691 - RIGHT-TO-USE LEASE LIABILITY | K23: =N23 -> 40327707 | N23: 40327707 | Q23: 40551285 | S23: =Q23-N23 -> 223577.97 | T23: No action required.
C24: Cr: Acct 0950 - BEGINNING FUND BALANCE | K24: =Q24 -> 0 | N24: 227664.01 | Q24: =IF(SUM($Q$20:$Q$23)<SUM($P$15:$P$17),-SUM($Q$20:$Q$23)+SUM($P$15:$P$17),0) -> 0 | S24: =Q24-N24 -> -227664.01 | T24: No action required.
C25: Cr: Acct 0952 - BEGINNING FUND ADJUSTMENT/PRIOR PERIOD ADJUSTMENT | K25: =IF(SUM($K$20:$K$24)<SUM($J$15:$J$18),-SUM($K$20:$K$24)+SUM($J$15:$J$18),0) -> 0 | N25: 0 | S25: =Q25-N25 -> 0 | T25: No action required.
J26: =SUM(J15:J25) -> 57178107 | K26: =SUM(K15:K25) -> 57178107 | L26: =IF(J26=K26,"<- Debits and Credits equal each other.","<- Debits and Credits do not equal each other.") -> <- Debits and Credits equal each other.
B27: * THESE ASSET AMOUNTS SHOULD BE REPORTED AS BEGINNING BALANCES ON REPORT 18.
B28: ** This amount should be included in the beginning balance column on the LS-Lease Liability and LS-Check Figures Tabs.
A31: Record New Leases (new leases only)
A32: 1 | B32: Record lease contract commencement (fund-based entries only)
B33: Dr: Acct 0842 - CAPITAL OUTLAY | J33: 117572
C34: Cr: Acct 0789 - LEASE AND OTHER FINANCING PROCEEDS | K34: 117572
C35: =IF($F$7="Proprietary","Cr: Acct 0870 - SERVICES & CHARGES (MG ADJ)",VLOOKUP($F$9,'Drop Down Menus'!$F$2:$G$10,2,FALSE)) -> Cr: Acct 0808 - GENERAL GOV. (GAAP ADJ)
J36: =SUM(J33:J35) -> 117572 | K36: =SUM(K33:K35) -> 117572 | L36: =IF(J36=K36,"<- Debits and Credits equal each other.","<- Debits and Credits do not equal each other.") -> <- Debits and Credits equal each other.
A38: 2 | B38: Record leased assets.
A39: *Rpt 18 | B39: Dr: Acct 0476 - RIGHT-TO-USE LEASED LAND - AMORTIZABLE | J39: 0
A40: *Rpt 18 | B40: Dr: Acct 0478 - RIGHT-TO-USE LEASED EQUIPMENT - AMORTIZABLE | J40: 0
A41: *Rpt 18 | B41: Dr: Acct 0477 - RIGHT-TO-USE LEASED BUILDINGS - AMORTIZABLE | J41: 117572
C42: Cr: Acct 0842 - CAPITAL OUTLAY | K42: 117572
B43: * THESE AMOUNTS SHOULD BE INCLUDED AS "ADDITIONS" ON REPORT 18. | J43: =SUM(J39:J42) -> 117572 | K43: =SUM(K39:K42) -> 117572 | L43: =IF(J43=K43,"<- Debits and Credits equal each other.","<- Debits and Credits do not equal each other.") -> <- Debits and Credits equal each other.
A46: 3 | B46: Replace proceeds from leases with right-to-use lease liability.
B47: Dr: Acct 0789 - LEASE AND OTHER FINANCING PROCEEDS | J47: 117572
A48: **LS LL/CF | C48: Cr: Acct 0691 - RIGHT-TO-USE LEASE LIABILITY | K48: 117572
J49: =SUM(J47:J48) -> 117572 | K49: =SUM(K47:K48) -> 117572 | L49: =IF(J49=K49,"<- Debits and Credits equal each other.","<- Debits and Credits do not equal each other.") -> <- Debits and Credits equal each other.
B50: ** This amount should be included in the additions column on the LS-Lease Liability and LS-Check Figures Tabs.
A53: Record Annual Activity (all leases)
A54: 4 | B54: Record amortization of the leased assets for the year.
B55: Dr: Acct 0875 - DEPRECIATION/AMORTIZATION | J55: 8544992.3
C56: Cr: Acct 0485 - ACCUMULATED AMORTIZATION - RIGHT-TO-USE LEASED LAND | K56: 0
C57: Cr: Acct 0479 - ACCUMULATED AMORTIZATION - RIGHT-TO-USE LEASED EQUIPMENT | K57: 10868.406
C58: Cr: Acct 0486 - ACCUMULATED AMORTIZATION - RIGHT-TO-USE LEASED BUILDINGS | K58: 8534123.9
J59: =SUM(J55:J58) -> 8544992.3 | K59: =SUM(K55:K58) -> 8544992.3 | L59: =IF(J59=K59,"<- Debits and Credits equal each other.","<- Debits and Credits do not equal each other.") -> <- Debits and Credits equal each other.
A61: 5 | B61: Reclassify rents and leases exp. to lease contract principal and interest exp.
B62: Dr: Acct 0848 - DEBT SERVICE - PRINCIPAL LEASES | J62: 8225414 | L62: =IF($J$62=$K$69,"","<- Accts 0848 must agree")
B63: =IF($F$7="Governmental","Dr: Acct 0851 - DEBT SERVICE - INTEREST LEASES","Dr: Acct 0894 - INTEREST EXPENSE AND FISCAL CHARGES") -> Dr: Acct 0851 - DEBT SERVICE - INTEREST LEASES | J63: 502504
C64: =IF($F$7="Proprietary","Cr: Acct 0870 - SERVICES & CHARGES (MG ADJ)",VLOOKUP($F$9,'Drop Down Menus'!$F$2:$G$10,2,FALSE)) -> Cr: Acct 0808 - GENERAL GOV. (GAAP ADJ) | K64: 8727918
J65: =SUM(J62:J64) -> 8727918 | K65: =SUM(K62:K64) -> 8727918 | L65: =IF(J65=K65,"<- Debits and Credits equal each other.","<- Debits and Credits do not equal each other.") -> <- Debits and Credits equal each other.
A67: 6 | B67: Reduce lease contracts liability for total current year principal payments.
A68: **LS LL/CF | B68: Dr: Acct 0691 - RIGHT-TO-USE LEASE LIABILITY | J68: 8225414
C69: Cr: Acct 0848 - DEBT SERVICE - PRINCIPAL LEASES | K69: 8225414 | L69: =IF($J$62=$K$69,"","<- Accts 0848 must agree")
J70: =SUM(J68:J69) -> 8225414 | K70: =SUM(K68:K69) -> 8225414 | L70: =IF(J70=K70,"<- Debits and Credits equal each other.","<- Debits and Credits do not equal each other.") -> <- Debits and Credits equal each other.
B71: ** This amount should be included in the deductions column on the LS-Lease Liability and LS-Check Figures Tabs.
A74: 7 | B74: Reclassify the principal amount due in the next FY to the current liability.
A75: **LS LL/CF | B75: Dr: Acct 0691 - RIGHT-TO-USE LEASE LIABILITY | J75: 6914823.9
C76: Cr: Acct 0649 - RIGHT-TO-USE LEASE LIABILITY (CURRENT PORTION LT) | K76: 6914823.9
B77: NOTE: This is an annual accrual. It is to be reversed at the start of the next fiscal year. SCO combines the current and non current amount in Entry #0 to reestablish the beginning balances. No action required. | J77: =SUM(J75:J76) -> 6914823.9 | K77: =SUM(K75:K76) -> 6914823.9 | L77: =IF(J77=K77,"<- Debits and Credits equal each other.","<- Debits and Credits do not equal each other.") -> <- Debits and Credits equal each other.
B80: ** This amount should be included in the due in one year column on the LS-Lease Liability and LS-Check Figures Tabs.
A83: Remove Lease Asset at the End of the Lease Term (only at the end of the lease term)
A84: 8 | B84: Record entry to write off the lease asset and accumulated amortization at the end of the lease term.
B85: Dr: Acct 0485 - ACCUMULATED AMORTIZATION - RIGHT-TO-USE LEASED LAND | J85: 0
B86: Dr: Acct 0479 - ACCUMULATED AMORTIZATION - RIGHT-TO-USE LEASED EQUIPMENT | J86: 0
B87: Dr: Acct 0486 - ACCUMULATED AMORTIZATION - RIGHT-TO-USE LEASED BUILDINGS | J87: 4989182
A88: *Rpt 18 | C88: Cr: Acct 0476 - RIGHT-TO-USE LEASED LAND - AMORTIZABLE | K88: 0
A89: *Rpt 18 | C89: Cr: Acct 0478 - RIGHT-TO-USE LEASED EQUIPMENT - AMORTIZABLE | K89: 0
A90: *Rpt 18 | C90: Cr: Acct 0477 - RIGHT-TO-USE LEASED BUILDINGS - AMORTIZABLE | K90: 4989182
B91: * THESE AMOUNTS SHOULD BE INCLUDED AS "DEDUCTIONS" ON REPORT 18. | J91: =SUM(J85:J90) -> 4989182 | K91: =SUM(K85:K90) -> 4989182 | L91: =IF(J91=K91,"<- Debits and Credits equal each other.","<- Debits and Credits do not equal each other.") -> <- Debits and Credits equal each other.
A94: Lease Remeasurement and Modifications (only if a significant modification occurred during the fiscal year)
A95: 9 | B95: Record early termination or lease modifications to decrease in the RTU leased asset.
A96: **LS LL/CF | B96: Dr: Acct 0691 - RIGHT-TO-USE LEASE LIABILITY
B97: Dr: Acct 0485 - ACCUMULATED AMORTIZATION - RIGHT-TO-USE LEASED LAND
B98: Dr: Acct 0479 - ACCUMULATED AMORTIZATION - RIGHT-TO-USE LEASED EQUIPMENT
B99: Dr: Acct 0486 - ACCUMULATED AMORTIZATION - RIGHT-TO-USE LEASED BUILDINGS
B100: =IF($F$7="Proprietary","Dr: Acct 0870 - SERVICES & CHARGES (MG ADJ)",VLOOKUP($F$9,'Drop Down Menus'!$F$2:$H$10,3,FALSE)) -> Dr: Acct 0808 - GENERAL GOV. (GAAP ADJ)
A101: *Rpt 18 | C101: Cr: Acct 0476 - RIGHT-TO-USE LEASED LAND - AMORTIZABLE
A102: *Rpt 18 | C102: Cr: Acct 0478 - RIGHT-TO-USE LEASED EQUIPMENT - AMORTIZABLE
A103: *Rpt 18 | C103: Cr: Acct 0477 - RIGHT-TO-USE LEASED BUILDINGS - AMORTIZABLE
C104: =IF($F$7="Proprietary","Dr: Acct 0870 - SERVICES & CHARGES (MG ADJ)",VLOOKUP($F$9,'Drop Down Menus'!$F$2:$G$10,2,FALSE)) -> Cr: Acct 0808 - GENERAL GOV. (GAAP ADJ)
B105: * THESE AMOUNTS SHOULD BE INCLUDED AS "DEDUCTIONS" ON REPORT 18. | J105: =SUM(J96:J104) -> 0 | K105: =SUM(K96:K104) -> 0 | L105: =IF(J105=K105,"<- Debits and Credits equal each other.","<- Debits and Credits do not equal each other.") -> <- Debits and Credits equal each other.
B106: ** This amount should be included in the deductions column on the LS-Lease Liability and LS-Check Figures Tabs.
A109: 10 | B109: Record lease modifications to increase in the RTU leased asset.
A110: *Rpt 18 | B110: Dr: Acct 0476 - RIGHT-TO-USE LEASED LAND - AMORTIZABLE | J110: 0
A111: *Rpt 18 | B111: Dr: Acct 0478 - RIGHT-TO-USE LEASED EQUIPMENT - AMORTIZABLE | J111: 0
A112: *Rpt 18 | B112: Dr: Acct 0477 - RIGHT-TO-USE LEASED BUILDINGS - AMORTIZABLE | J112: 2498265.1
A113: **LS LL/CF | C113: Cr: Acct 0691 - RIGHT-TO-USE LEASE LIABILITY | K113: 2498265.1
B114: * THESE AMOUNTS SHOULD BE INCLUDED AS "ADDITIONS" ON REPORT 18. | J114: =SUM(J110:J113) -> 2498265.1 | K114: =SUM(K110:K113) -> 2498265.1 | L114: =IF(J114=K114,"<- Debits and Credits equal each other.","<- Debits and Credits do not equal each other.") -> <- Debits and Credits equal each other.
B115: ** This amount should be included in the additions column on the LS-Lease Liability and LS-Check Figures Tabs.
D120: Informational - Ending Balances of Assets and Liabilities
K121: Debit (Credit)
D122: Acct 0476 - RIGHT-TO-USE LEASED LAND - AMORTIZABLE | K122: =J15+J39-K88-K101+J110 -> 0
D123: Acct 0478 - RIGHT-TO-USE LEASED EQUIPMENT - AMORTIZABLE | K123: =J16+J40-K89-K102+J111 -> 54341.588
D124: Acct 0477 - RIGHT-TO-USE LEASED BUILDINGS - AMORTIZABLE | K124: =J17+J41-K90-K103+J112 -> 53938539
D125: Acct 0485 - ACCUMULATED AMORTIZATION - RIGHT-TO-USE LEASED LAND | K125: =-K20-K56+J85+J97 -> 0
...

Sheet LS-Fund 0012 Journal Entries
A1: Lessee-Type Contracts Fund-by-Fund Journal Entries Form (to be submitted to the SCO annually—one form per fund)
A2: Manually complete every yellow field in this worksheet—there are no automatically calculated data-entry cells in this worksheet.
A3: Fiscal Year: | F3: 2023–2024
A4: Organization Name: | F4: Department of Justice
A5: Organization Code (4-Digits): | F5: 0820
A6: Fund Number (4-Digits): | F6: 12
A7: Fund Classification: | F7: Governmental
A8: Fund Type: | F8: Governmental Fund
A9: Functional Expense: | F9: =IFERROR(IF(F7="Proprietary","Proprietary Fund",VLOOKUP(F5,qryIndex02a!$A$2:$K$654,4,FALSE)),"Unidentified") -> GENERAL GOVERNMENT
A12: Establish Beginning Balances (existing leases only)
A13: Entry #
A14: 0 | B14: Roll forward prior year right-to-use leases to record opening balances. | M14: Combined Lessee Templates | P14: From SCO BB List | S14: Difference
A15: *Rpt 18 | B15: Dr: Acct 0476 - RIGHT-TO-USE LEASED LAND - AMORTIZABLE | J15: =M15 -> 0 | M15: 0 | P15: 0 | S15: =P15-M15 -> 0 | T15: Report any "Differences" on the Report 18 Differential.
A16: *Rpt 18 | B16: Dr: Acct 0478 - RIGHT-TO-USE LEASED EQUIPMENT - AMORTIZABLE | J16: =M16 -> 0 | M16: 0 | P16: 0 | S16: =P16-M16 -> 0 | T16: Report any "Differences" on the Report 18 Differential.
A17: *Rpt 18 | B17: Dr: Acct 0477 - RIGHT-TO-USE LEASED BUILDINGS - AMORTIZABLE | J17: =M17 -> 33272.218 | M17: 33272.218 | P17: 33418 | S17: =P17-M17 -> 145.78157 | T17: Report any "Differences" on the Report 18 Differential.
B18: Dr: Acct 0950 - BEGINNING FUND BALANCE | J18: =P18 -> 271 | M18: 539.09894 | P18: =IF(SUM($Q$20:$Q$23)>SUM($P$15:$P$17),SUM($Q$20:$Q$23)-SUM($P$15:$P$17),0) -> 271 | S18: =P18-M18 -> -268.09894 | T18: No action required.
B19: Dr: Acct 0952 - BEGINNING FUND ADJUSTMENT/PRIOR PERIOD ADJUSTMENT | J19: =IF(SUM($K$20:$K$24)>SUM($J$15:$J$18),SUM($K$20:$K$24)-SUM($J$15:$J$18),0) -> 12.406176 | M19: 0 | S19: =P19-M19 -> 0 | T19: No action required.
C20: Cr: Acct 0485 - ACCUMULATED AMORTIZATION - RIGHT-TO-USE LEASED LAND | K20: =N20 -> 0 | N20: 0 | Q20: 0 | S20: =Q20-N20 -> 0 | T20: No action required.
C21: Cr: Acct 0479 - ACCUMULATED AMORTIZATION - RIGHT-TO-USE LEASED EQUIPMENT | K21: =N21 -> 0 | N21: 0 | Q21: 0 | S21: =Q21-N21 -> 0 | T21: No action required.
C22: Cr: Acct 0486 - ACCUMULATED AMORTIZATION - RIGHT-TO-USE LEASED BUILDINGS | K22: =N22 -> 10644.368 | N22: 10644.368 | Q22: 10660 | S22: =Q22-N22 -> 15.632194 | T22: No action required.
A23: **LS LL/CF | C23: Cr: Acct 0691 - RIGHT-TO-USE LEASE LIABILITY | K23: =N23 -> 22911.257 | N23: 22911.257 | Q23: 23029 | S23: =Q23-N23 -> 117.7432 | T23: No action required.
C24: Cr: Acct 0950 - BEGINNING FUND BALANCE | K24: =Q24 -> 0 | N24: 255.69234 | Q24: =IF(SUM($Q$20:$Q$23)<SUM($P$15:$P$17),-SUM($Q$20:$Q$23)+SUM($P$15:$P$17),0) -> 0 | S24: =Q24-N24 -> -255.69234 | T24: No action required.
C25: Cr: Acct 0952 - BEGINNING FUND ADJUSTMENT/PRIOR PERIOD ADJUSTMENT | K25: =IF(SUM($K$20:$K$24)<SUM($J$15:$J$18),-SUM($K$20:$K$24)+SUM($J$15:$J$18),0) -> 0 | N25: 0 | S25: =Q25-N25 -> 0 | T25: No action required.
J26: =SUM(J15:J25) -> 33555.625 | K26: =SUM(K15:K25) -> 33555.625 | L26: =IF(J26=K26,"<- Debits and Credits equal each other.","<- Debits and Credits do not equal each other.") -> <- Debits and Credits equal each other.
B27: * THESE ASSET AMOUNTS SHOULD BE REPORTED AS BEGINNING BALANCES ON REPORT 18.
B28: ** This amount should be included in the beginning balance column on the LS-Lease Liability and LS-Check Figures Tabs.
A31: Record New Leases (new leases only)
A32: 1 | B32: Record lease contract commencement (fund-based entries only)
B33: Dr: Acct 0842 - CAPITAL OUTLAY
C34: Cr: Acct 0789 - LEASE AND OTHER FINANCING PROCEEDS
C35: =IF($F$7="Proprietary","Cr: Acct 0870 - SERVICES & CHARGES (MG ADJ)",VLOOKUP($F$9,'Drop Down Menus'!$F$2:$G$10,2,FALSE)) -> Cr: Acct 0808 - GENERAL GOV. (GAAP ADJ)
J36: =SUM(J33:J35) -> 0 | K36: =SUM(K33:K35) -> 0 | L36: =IF(J36=K36,"<- Debits and Credits equal each other.","<- Debits and Credits do not equal each other.") -> <- Debits and Credits equal each other.
A38: 2 | B38: Record leased assets.
A39: *Rpt 18 | B39: Dr: Acct 0476 - RIGHT-TO-USE LEASED LAND - AMORTIZABLE
A40: *Rpt 18 | B40: Dr: Acct 0478 - RIGHT-TO-USE LEASED EQUIPMENT - AMORTIZABLE
A41: *Rpt 18 | B41: Dr: Acct 0477 - RIGHT-TO-USE LEASED BUILDINGS - AMORTIZABLE
C42: Cr: Acct 0842 - CAPITAL OUTLAY
B43: * THESE AMOUNTS SHOULD BE INCLUDED AS "ADDITIONS" ON REPORT 18. | J43: =SUM(J39:J42) -> 0 | K43: =SUM(K39:K42) -> 0 | L43: =IF(J43=K43,"<- Debits and Credits equal each other.","<- Debits and Credits do not equal each other.") -> <- Debits and Credits equal each other.
A46: 3 | B46: Replace proceeds from leases with right-to-use lease liability.
B47: Dr: Acct 0789 - LEASE AND OTHER FINANCING PROCEEDS
A48: **LS LL/CF | C48: Cr: Acct 0691 - RIGHT-TO-USE LEASE LIABILITY
J49: =SUM(J47:J48) -> 0 | K49: =SUM(K47:K48) -> 0 | L49: =IF(J49=K49,"<- Debits and Credits equal each other.","<- Debits and Credits do not equal each other.") -> <- Debits and Credits equal each other.
B50: ** This amount should be included in the additions column on the LS-Lease Liability and LS-Check Figures Tabs.
A53: Record Annual Activity (all leases)
A54: 4 | B54: Record amortization of the leased assets for the year.
B55: Dr: Acct 0875 - DEPRECIATION/AMORTIZATION | J55: 5455.3238
C56: Cr: Acct 0485 - ACCUMULATED AMORTIZATION - RIGHT-TO-USE LEASED LAND | K56: 0
C57: Cr: Acct 0479 - ACCUMULATED AMORTIZATION - RIGHT-TO-USE LEASED EQUIPMENT | K57: 0
C58: Cr: Acct 0486 - ACCUMULATED AMORTIZATION - RIGHT-TO-USE LEASED BUILDINGS | K58: 5455.3238
J59: =SUM(J55:J58) -> 5455.3238 | K59: =SUM(K55:K58) -> 5455.3238 | L59: =IF(J59=K59,"<- Debits and Credits equal each other.","<- Debits and Credits do not equal each other.") -> <- Debits and Credits equal each other.
A61: 5 | B61: Reclassify rents and leases exp. to lease contract principal and interest exp.
B62: Dr: Acct 0848 - DEBT SERVICE - PRINCIPAL LEASES | J62: 5414 | L62: =IF($J$62=$K$69,"","<- Accts 0848 must agree")
B63: =IF($F$7="Governmental","Dr: Acct 0851 - DEBT SERVICE - INTEREST LEASES","Dr: Acct 0894 - INTEREST EXPENSE AND FISCAL CHARGES") -> Dr: Acct 0851 - DEBT SERVICE - INTEREST LEASES | J63: 177
C64: =IF($F$7="Proprietary","Cr: Acct 0870 - SERVICES & CHARGES (MG ADJ)",VLOOKUP($F$9,'Drop Down Menus'!$F$2:$G$10,2,FALSE)) -> Cr: Acct 0808 - GENERAL GOV. (GAAP ADJ) | K64: 5591
J65: =SUM(J62:J64) -> 5591 | K65: =SUM(K62:K64) -> 5591 | L65: =IF(J65=K65,"<- Debits and Credits equal each other.","<- Debits and Credits do not equal each other.") -> <- Debits and Credits equal each other.
A67: 6 | B67: Reduce lease contracts liability for total current year principal payments.
A68: **LS LL/CF | B68: Dr: Acct 0691 - RIGHT-TO-USE LEASE LIABILITY | J68: 5414
C69: Cr: Acct 0848 - DEBT SERVICE - PRINCIPAL LEASES | K69: 5414 | L69: =IF($J$62=$K$69,"","<- Accts 0848 must agree")
J70: =SUM(J68:J69) -> 5414 | K70: =SUM(K68:K69) -> 5414 | L70: =IF(J70=K70,"<- Debits and Credits equal each other.","<- Debits and Credits do not equal each other.") -> <- Debits and Credits equal each other.
B71: ** This amount should be included in the deductions column on the LS-Lease Liability and LS-Check Figures Tabs.
A74: 7 | B74: Reclassify the principal amount due in the next FY to the current liability.
A75: **LS LL/CF | B75: Dr: Acct 0691 - RIGHT-TO-USE LEASE LIABILITY | J75: 5314.8612
C76: Cr: Acct 0649 - RIGHT-TO-USE LEASE LIABILITY (CURRENT PORTION LT) | K76: 5314.8612
B77: NOTE: This is an annual accrual. It is to be reversed at the start of the next fiscal year. SCO combines the current and non current amount in Entry #0 to reestablish the beginning balances. No action required. | J77: =SUM(J75:J76) -> 5314.8612 | K77: =SUM(K75:K76) -> 5314.8612 | L77: =IF(J77=K77,"<- Debits and Credits equal each other.","<- Debits and Credits do not equal each other.") -> <- Debits and Credits equal each other.
B80: ** This amount should be included in the due in one year column on the LS-Lease Liability and LS-Check Figures Tabs.
A83: Remove Lease Asset at the End of the Lease Term (only at the end of the lease term)
A84: 8 | B84: Record entry to write off the lease asset and accumulated amortization at the end of the lease term.
B85: Dr: Acct 0485 - ACCUMULATED AMORTIZATION - RIGHT-TO-USE LEASED LAND
B86: Dr: Acct 0479 - ACCUMULATED AMORTIZATION - RIGHT-TO-USE LEASED EQUIPMENT
B87: Dr: Acct 0486 - ACCUMULATED AMORTIZATION - RIGHT-TO-USE LEASED BUILDINGS | J87: 499.68834
A88: *Rpt 18 | C88: Cr: Acct 0476 - RIGHT-TO-USE LEASED LAND - AMORTIZABLE
A89: *Rpt 18 | C89: Cr: Acct 0478 - RIGHT-TO-USE LEASED EQUIPMENT - AMORTIZABLE
A90: *Rpt 18 | C90: Cr: Acct 0477 - RIGHT-TO-USE LEASED BUILDINGS - AMORTIZABLE | K90: 499.68834
B91: * THESE AMOUNTS SHOULD BE INCLUDED AS "DEDUCTIONS" ON REPORT 18. | J91: =SUM(J85:J90) -> 499.68834 | K91: =SUM(K85:K90) -> 499.68834 | L91: =IF(J91=K91,"<- Debits and Credits equal each other.","<- Debits and Credits do not equal each other.") -> <- Debits and Credits equal each other.
A94: Lease Remeasurement and Modifications (only if a significant modification occurred during the fiscal year)
A95: 9 | B95: Record early termination or lease modifications to decrease in the RTU leased asset.
A96: **LS LL/CF | B96: Dr: Acct 0691 - RIGHT-TO-USE LEASE LIABILITY
B97: Dr: Acct 0485 - ACCUMULATED AMORTIZATION - RIGHT-TO-USE LEASED LAND
B98: Dr: Acct 0479 - ACCUMULATED AMORTIZATION - RIGHT-TO-USE LEASED EQUIPMENT
B99: Dr: Acct 0486 - ACCUMULATED AMORTIZATION - RIGHT-TO-USE LEASED BUILDINGS
B100: =IF($F$7="Proprietary","Dr: Acct 0870 - SERVICES & CHARGES (MG ADJ)",VLOOKUP($F$9,'Drop Down Menus'!$F$2:$H$10,3,FALSE)) -> Dr: Acct 0808 - GENERAL GOV. (GAAP ADJ)
A101: *Rpt 18 | C101: Cr: Acct 0476 - RIGHT-TO-USE LEASED LAND - AMORTIZABLE
A102: *Rpt 18 | C102: Cr: Acct 0478 - RIGHT-TO-USE LEASED EQUIPMENT - AMORTIZABLE
A103: *Rpt 18 | C103: Cr: Acct 0477 - RIGHT-TO-USE LEASED BUILDINGS - AMORTIZABLE
C104: =IF($F$7="Proprietary","Dr: Acct 0870 - SERVICES & CHARGES (MG ADJ)",VLOOKUP($F$9,'Drop Down Menus'!$F$2:$G$10,2,FALSE)) -> Cr: Acct 0808 - GENERAL GOV. (GAAP ADJ)
B105: * THESE AMOUNTS SHOULD BE INCLUDED AS "DEDUCTIONS" ON REPORT 18. | J105: =SUM(J96:J104) -> 0 | K105: =SUM(K96:K104) -> 0 | L105: =IF(J105=K105,"<- Debits and Credits equal each other.","<- Debits and Credits do not equal each other.") -> <- Debits and Credits equal each other.
B106: ** This amount should be included in the deductions column on the LS-Lease Liability and LS-Check Figures Tabs.
A109: 10 | B109: Record lease modifications to increase in the RTU leased asset.
A110: *Rpt 18 | B110: Dr: Acct 0476 - RIGHT-TO-USE LEASED LAND - AMORTIZABLE
A111: *Rpt 18 | B111: Dr: Acct 0478 - RIGHT-TO-USE LEASED EQUIPMENT - AMORTIZABLE
A112: *Rpt 18 | B112: Dr: Acct 0477 - RIGHT-TO-USE LEASED BUILDINGS - AMORTIZABLE
A113: **LS LL/CF | C113: Cr: Acct 0691 - RIGHT-TO-USE LEASE LIABILITY
B114: * THESE AMOUNTS SHOULD BE INCLUDED AS "ADDITIONS" ON REPORT 18. | J114: =SUM(J110:J113) -> 0 | K114: =SUM(K110:K113) -> 0 | L114: =IF(J114=K114,"<- Debits and Credits equal each other.","<- Debits and Credits do not equal each other.") -> <- Debits and Credits equal each other.
B115: ** This amount should be included in the additions column on the LS-Lease Liability and LS-Check Figures Tabs.
D120: Informational - Ending Balances of Assets and Liabilities
K121: Debit (Credit)
D122: Acct 0476 - RIGHT-TO-USE LEASED LAND - AMORTIZABLE | K122: =J15+J39-K88-K101+J110 -> 0
D123: Acct 0478 - RIGHT-TO-USE LEASED EQUIPMENT - AMORTIZABLE | K123: =J16+J40-K89-K102+J111 -> 0
D124: Acct 0477 - RIGHT-TO-USE LEASED BUILDINGS - AMORTIZABLE | K124: =J17+J41-K90-K103+J112 -> 32772.53
D125: Acct 0485 - ACCUMULATED AMORTIZATION - RIGHT-TO-USE LEASED LAND | K125: =-K20-K56+J85+J97 -> 0
...

Sheet LS-Fund 0017 Journal Entries
A1: Lessee-Type Contracts Fund-by-Fund Journal Entries Form (to be submitted to the SCO annually—one form per fund)
A2: Manually complete every yellow field in this worksheet—there are no automatically calculated data-entry cells in this worksheet.
A3: Fiscal Year: | F3: 2023–2024
A4: Organization Name: | F4: Department of Justice
A5: Organization Code (4-Digits): | F5: 0820
A6: Fund Number (4-Digits): | F6: 17
A7: Fund Classification: | F7: Governmental
A8: Fund Type: | F8: Governmental Fund
A9: Functional Expense: | F9: =IFERROR(IF(F7="Proprietary","Proprietary Fund",VLOOKUP(F5,qryIndex02a!$A$2:$K$654,4,FALSE)),"Unidentified") -> GENERAL GOVERNMENT
A12: Establish Beginning Balances (existing leases only)
A13: Entry #
A14: 0 | B14: Roll forward prior year right-to-use leases to record opening balances. | M14: Combined Lessee Templates | P14: From SCO BB List | S14: Difference
A15: *Rpt 18 | B15: Dr: Acct 0476 - RIGHT-TO-USE LEASED LAND - AMORTIZABLE | J15: =M15 -> 0 | M15: 0 | P15: 0 | S15: =P15-M15 -> 0 | T15: Report any "Differences" on the Report 18 Differential.
A16: *Rpt 18 | B16: Dr: Acct 0478 - RIGHT-TO-USE LEASED EQUIPMENT - AMORTIZABLE | J16: =M16 -> 0 | M16: 0 | P16: 0 | S16: =P16-M16 -> 0 | T16: Report any "Differences" on the Report 18 Differential.
A17: *Rpt 18 | B17: Dr: Acct 0477 - RIGHT-TO-USE LEASED BUILDINGS - AMORTIZABLE | J17: =M17 -> 9284225.2 | M17: 9284225.2 | P17: 9284225 | S17: =P17-M17 -> -0.23263196 | T17: Report any "Differences" on the Report 18 Differential.
B18: Dr: Acct 0950 - BEGINNING FUND BALANCE | J18: =P18 -> 246109 | M18: 246109.1 | P18: =IF(SUM($Q$20:$Q$23)>SUM($P$15:$P$17),SUM($Q$20:$Q$23)-SUM($P$15:$P$17),0) -> 246109 | S18: =P18-M18 -> -0.099523548 | T18: No action required.
B19: Dr: Acct 0952 - BEGINNING FUND ADJUSTMENT/PRIOR PERIOD ADJUSTMENT | J19: =IF(SUM($K$20:$K$24)>SUM($J$15:$J$18),SUM($K$20:$K$24)-SUM($J$15:$J$18),0) -> 0 | S19: =P19-M19 -> 0 | T19: No action required.
C20: Cr: Acct 0485 - ACCUMULATED AMORTIZATION - RIGHT-TO-USE LEASED LAND | K20: =N20 -> 0 | N20: 0 | Q20: 0 | S20: =Q20-N20 -> 0 | T20: No action required.
C21: Cr: Acct 0479 - ACCUMULATED AMORTIZATION - RIGHT-TO-USE LEASED EQUIPMENT | K21: =N21 -> 0 | N21: 0 | Q21: 0 | S21: =Q21-N21 -> 0 | T21: No action required.
C22: Cr: Acct 0486 - ACCUMULATED AMORTIZATION - RIGHT-TO-USE LEASED BUILDINGS | K22: =N22 -> 1848937.7 | N22: 1848937.7 | Q22: 1848938 | S22: =Q22-N22 -> 0.2876353 | T22: No action required.
A23: **LS LL/CF | C23: Cr: Acct 0691 - RIGHT-TO-USE LEASE LIABILITY | K23: =N23 -> 7681396.3 | N23: 7681396.3 | Q23: 7681396 | S23: =Q23-N23 -> -0.31720241 | T23: No action required.
C24: Cr: Acct 0950 - BEGINNING FUND BALANCE | K24: =Q24 -> 0 | N24: 0 | Q24: =IF(SUM($Q$20:$Q$23)<SUM($P$15:$P$17),-SUM($Q$20:$Q$23)+SUM($P$15:$P$17),0) -> 0 | S24: =Q24-N24 -> 0 | T24: No action required.
C25: Cr: Acct 0952 - BEGINNING FUND ADJUSTMENT/PRIOR PERIOD ADJUSTMENT | K25: =IF(SUM($K$20:$K$24)<SUM($J$15:$J$18),-SUM($K$20:$K$24)+SUM($J$15:$J$18),0) -> 0.20306485 | N25: 0 | S25: =Q25-N25 -> 0 | T25: No action required.
J26: =SUM(J15:J25) -> 9530334.2 | K26: =SUM(K15:K25) -> 9530334.2 | L26: =IF(J26=K26,"<- Debits and Credits equal each other.","<- Debits and Credits do not equal each other.") -> <- Debits and Credits equal each other.
B27: * THESE ASSET AMOUNTS SHOULD BE REPORTED AS BEGINNING BALANCES ON REPORT 18.
B28: ** This amount should be included in the beginning balance column on the LS-Lease Liability and LS-Check Figures Tabs.
A31: Record New Leases (new leases only)
A32: 1 | B32: Record lease contract commencement (fund-based entries only)
B33: Dr: Acct 0842 - CAPITAL OUTLAY
C34: Cr: Acct 0789 - LEASE AND OTHER FINANCING PROCEEDS
C35: =IF($F$7="Proprietary","Cr: Acct 0870 - SERVICES & CHARGES (MG ADJ)",VLOOKUP($F$9,'Drop Down Menus'!$F$2:$G$10,2,FALSE)) -> Cr: Acct 0808 - GENERAL GOV. (GAAP ADJ)
J36: =SUM(J33:J35) -> 0 | K36: =SUM(K33:K35) -> 0 | L36: =IF(J36=K36,"<- Debits and Credits equal each other.","<- Debits and Credits do not equal each other.") -> <- Debits and Credits equal each other.
A38: 2 | B38: Record leased assets.
A39: *Rpt 18 | B39: Dr: Acct 0476 - RIGHT-TO-USE LEASED LAND - AMORTIZABLE
A40: *Rpt 18 | B40: Dr: Acct 0478 - RIGHT-TO-USE LEASED EQUIPMENT - AMORTIZABLE
A41: *Rpt 18 | B41: Dr: Acct 0477 - RIGHT-TO-USE LEASED BUILDINGS - AMORTIZABLE
C42: Cr: Acct 0842 - CAPITAL OUTLAY
B43: * THESE AMOUNTS SHOULD BE INCLUDED AS "ADDITIONS" ON REPORT 18. | J43: =SUM(J39:J42) -> 0 | K43: =SUM(K39:K42) -> 0 | L43: =IF(J43=K43,"<- Debits and Credits equal each other.","<- Debits and Credits do not equal each other.") -> <- Debits and Credits equal each other.
A46: 3 | B46: Replace proceeds from leases with right-to-use lease liability.
B47: Dr: Acct 0789 - LEASE AND OTHER FINANCING PROCEEDS
A48: **LS LL/CF | C48: Cr: Acct 0691 - RIGHT-TO-USE LEASE LIABILITY
J49: =SUM(J47:J48) -> 0 | K49: =SUM(K47:K48) -> 0 | L49: =IF(J49=K49,"<- Debits and Credits equal each other.","<- Debits and Credits do not equal each other.") -> <- Debits and Credits equal each other.
B50: ** This amount should be included in the additions column on the LS-Lease Liability and LS-Check Figures Tabs.
A53: Record Annual Activity (all leases)
A54: 4 | B54: Record amortization of the leased assets for the year.
B55: Dr: Acct 0875 - DEPRECIATION/AMORTIZATION | J55: 924468.71
C56: Cr: Acct 0485 - ACCUMULATED AMORTIZATION - RIGHT-TO-USE LEASED LAND | K56: 0
C57: Cr: Acct 0479 - ACCUMULATED AMORTIZATION - RIGHT-TO-USE LEASED EQUIPMENT | K57: 0
C58: Cr: Acct 0486 - ACCUMULATED AMORTIZATION - RIGHT-TO-USE LEASED BUILDINGS | K58: 924468.71
J59: =SUM(J55:J58) -> 924468.71 | K59: =SUM(K55:K58) -> 924468.71 | L59: =IF(J59=K59,"<- Debits and Credits equal each other.","<- Debits and Credits do not equal each other.") -> <- Debits and Credits equal each other.
A61: 5 | B61: Reclassify rents and leases exp. to lease contract principal and interest exp.
B62: Dr: Acct 0848 - DEBT SERVICE - PRINCIPAL LEASES | J62: 843781.7 | L62: =IF($J$62=$K$69,"","<- Accts 0848 must agree")
B63: =IF($F$7="Governmental","Dr: Acct 0851 - DEBT SERVICE - INTEREST LEASES","Dr: Acct 0894 - INTEREST EXPENSE AND FISCAL CHARGES") -> Dr: Acct 0851 - DEBT SERVICE - INTEREST LEASES | J63: 107923.59
C64: =IF($F$7="Proprietary","Cr: Acct 0870 - SERVICES & CHARGES (MG ADJ)",VLOOKUP($F$9,'Drop Down Menus'!$F$2:$G$10,2,FALSE)) -> Cr: Acct 0808 - GENERAL GOV. (GAAP ADJ) | K64: 951705.3
J65: =SUM(J62:J64) -> 951705.3 | K65: =SUM(K62:K64) -> 951705.3 | L65: =IF(J65=K65,"<- Debits and Credits equal each other.","<- Debits and Credits do not equal each other.") -> <- Debits and Credits equal each other.
A67: 6 | B67: Reduce lease contracts liability for total current year principal payments.
A68: **LS LL/CF | B68: Dr: Acct 0691 - RIGHT-TO-USE LEASE LIABILITY | J68: 843781.7
C69: Cr: Acct 0848 - DEBT SERVICE - PRINCIPAL LEASES | K69: 843781.7 | L69: =IF($J$62=$K$69,"","<- Accts 0848 must agree")
J70: =SUM(J68:J69) -> 843781.7 | K70: =SUM(K68:K69) -> 843781.7 | L70: =IF(J70=K70,"<- Debits and Credits equal each other.","<- Debits and Credits do not equal each other.") -> <- Debits and Credits equal each other.
B71: ** This amount should be included in the deductions column on the LS-Lease Liability and LS-Check Figures Tabs.
A74: 7 | B74: Reclassify the principal amount due in the next FY to the current liability.
A75: **LS LL/CF | B75: Dr: Acct 0691 - RIGHT-TO-USE LEASE LIABILITY | J75: 873444.15
C76: Cr: Acct 0649 - RIGHT-TO-USE LEASE LIABILITY (CURRENT PORTION LT) | K76: 873444.15
B77: NOTE: This is an annual accrual. It is to be reversed at the start of the next fiscal year. SCO combines the current and non current amount in Entry #0 to reestablish the beginning balances. No action required. | J77: =SUM(J75:J76) -> 873444.15 | K77: =SUM(K75:K76) -> 873444.15 | L77: =IF(J77=K77,"<- Debits and Credits equal each other.","<- Debits and Credits do not equal each other.") -> <- Debits and Credits equal each other.
B80: ** This amount should be included in the due in one year column on the LS-Lease Liability and LS-Check Figures Tabs.
A83: Remove Lease Asset at the End of the Lease Term (only at the end of the lease term)
A84: 8 | B84: Record entry to write off the lease asset and accumulated amortization at the end of the lease term.
B85: Dr: Acct 0485 - ACCUMULATED AMORTIZATION - RIGHT-TO-USE LEASED LAND
B86: Dr: Acct 0479 - ACCUMULATED AMORTIZATION - RIGHT-TO-USE LEASED EQUIPMENT
B87: Dr: Acct 0486 - ACCUMULATED AMORTIZATION - RIGHT-TO-USE LEASED BUILDINGS
A88: *Rpt 18 | C88: Cr: Acct 0476 - RIGHT-TO-USE LEASED LAND - AMORTIZABLE
A89: *Rpt 18 | C89: Cr: Acct 0478 - RIGHT-TO-USE LEASED EQUIPMENT - AMORTIZABLE
A90: *Rpt 18 | C90: Cr: Acct 0477 - RIGHT-TO-USE LEASED BUILDINGS - AMORTIZABLE
B91: * THESE AMOUNTS SHOULD BE INCLUDED AS "DEDUCTIONS" ON REPORT 18. | J91: =SUM(J85:J90) -> 0 | K91: =SUM(K85:K90) -> 0 | L91: =IF(J91=K91,"<- Debits and Credits equal each other.","<- Debits and Credits do not equal each other.") -> <- Debits and Credits equal each other.
A94: Lease Remeasurement and Modifications (only if a significant modification occurred during the fiscal year)
A95: 9 | B95: Record early termination or lease modifications to decrease in the RTU leased asset.
A96: **LS LL/CF | B96: Dr: Acct 0691 - RIGHT-TO-USE LEASE LIABILITY
B97: Dr: Acct 0485 - ACCUMULATED AMORTIZATION - RIGHT-TO-USE LEASED LAND
B98: Dr: Acct 0479 - ACCUMULATED AMORTIZATION - RIGHT-TO-USE LEASED EQUIPMENT
B99: Dr: Acct 0486 - ACCUMULATED AMORTIZATION - RIGHT-TO-USE LEASED BUILDINGS
B100: =IF($F$7="Proprietary","Dr: Acct 0870 - SERVICES & CHARGES (MG ADJ)",VLOOKUP($F$9,'Drop Down Menus'!$F$2:$H$10,3,FALSE)) -> Dr: Acct 0808 - GENERAL GOV. (GAAP ADJ)
A101: *Rpt 18 | C101: Cr: Acct 0476 - RIGHT-TO-USE LEASED LAND - AMORTIZABLE
A102: *Rpt 18 | C102: Cr: Acct 0478 - RIGHT-TO-USE LEASED EQUIPMENT - AMORTIZABLE
A103: *Rpt 18 | C103: Cr: Acct 0477 - RIGHT-TO-USE LEASED BUILDINGS - AMORTIZABLE
C104: =IF($F$7="Proprietary","Dr: Acct 0870 - SERVICES & CHARGES (MG ADJ)",VLOOKUP($F$9,'Drop Down Menus'!$F$2:$G$10,2,FALSE)) -> Cr: Acct 0808 - GENERAL GOV. (GAAP ADJ)
B105: * THESE AMOUNTS SHOULD BE INCLUDED AS "DEDUCTIONS" ON REPORT 18. | J105: =SUM(J96:J104) -> 0 | K105: =SUM(K96:K104) -> 0 | L105: =IF(J105=K105,"<- Debits and Credits equal each other.","<- Debits and Credits do not equal each other.") -> <- Debits and Credits equal each other.
B106: ** This amount should be included in the deductions column on the LS-Lease Liability and LS-Check Figures Tabs.
A109: 10 | B109: Record lease modifications to increase in the RTU leased asset.
A110: *Rpt 18 | B110: Dr: Acct 0476 - RIGHT-TO-USE LEASED LAND - AMORTIZABLE
A111: *Rpt 18 | B111: Dr: Acct 0478 - RIGHT-TO-USE LEASED EQUIPMENT - AMORTIZABLE
A112: *Rpt 18 | B112: Dr: Acct 0477 - RIGHT-TO-USE LEASED BUILDINGS - AMORTIZABLE
A113: **LS LL/CF | C113: Cr: Acct 0691 - RIGHT-TO-USE LEASE LIABILITY
B114: * THESE AMOUNTS SHOULD BE INCLUDED AS "ADDITIONS" ON REPORT 18. | J114: =SUM(J110:J113) -> 0 | K114: =SUM(K110:K113) -> 0 | L114: =IF(J114=K114,"<- Debits and Credits equal each other.","<- Debits and Credits do not equal each other.") -> <- Debits and Credits equal each other.
B115: ** This amount should be included in the additions column on the LS-Lease Liability and LS-Check Figures Tabs.
D120: Informational - Ending Balances of Assets and Liabilities
K121: Debit (Credit)
D122: Acct 0476 - RIGHT-TO-USE LEASED LAND - AMORTIZABLE | K122: =J15+J39-K88-K101+J110 -> 0
D123: Acct 0478 - RIGHT-TO-USE LEASED EQUIPMENT - AMORTIZABLE | K123: =J16+J40-K89-K102+J111 -> 0
D124: Acct 0477 - RIGHT-TO-USE LEASED BUILDINGS - AMORTIZABLE | K124: =J17+J41-K90-K103+J112 -> 9284225.2
D125: Acct 0485 - ACCUMULATED AMORTIZATION - RIGHT-TO-USE LEASED LAND | K125: =-K20-K56+J85+J97 -> 0
...

Sheet LS-Fund 0044 Journal Entries
A1: Lessee-Type Contracts Fund-by-Fund Journal Entries Form (to be submitted to the SCO annually—one form per fund)
A2: Manually complete every yellow field in this worksheet—there are no automatically calculated data-entry cells in this worksheet.
A3: Fiscal Year: | F3: 2023–2024
A4: Organization Name: | F4: Department of Justice
A5: Organization Code (4-Digits): | F5: 0820
A6: Fund Number (4-Digits): | F6: 44
A7: Fund Classification: | F7: Governmental
A8: Fund Type: | F8: Governmental Fund
A9: Functional Expense: | F9: =IFERROR(IF(F7="Proprietary","Proprietary Fund",VLOOKUP(F5,qryIndex02a!$A$2:$K$654,4,FALSE)),"Unidentified") -> GENERAL GOVERNMENT
A12: Establish Beginning Balances (existing leases only)
A13: Entry #
A14: 0 | B14: Roll forward prior year right-to-use leases to record opening balances. | M14: Combined Lessee Templates | P14: From SCO BB List | S14: Difference
A15: *Rpt 18 | B15: Dr: Acct 0476 - RIGHT-TO-USE LEASED LAND - AMORTIZABLE | J15: =M15 -> 0 | M15: 0 | P15: 0 | S15: =P15-M15 -> 0 | T15: Report any "Differences" on the Report 18 Differential.
A16: *Rpt 18 | B16: Dr: Acct 0478 - RIGHT-TO-USE LEASED EQUIPMENT - AMORTIZABLE | J16: =M16 -> 0 | M16: 0 | P16: 0 | S16: =P16-M16 -> 0 | T16: Report any "Differences" on the Report 18 Differential.
A17: *Rpt 18 | B17: Dr: Acct 0477 - RIGHT-TO-USE LEASED BUILDINGS - AMORTIZABLE | J17: =M17 -> 4099348.2 | M17: 4099348.2 | P17: 4099348 | S17: =P17-M17 -> -0.15252568 | T17: Report any "Differences" on the Report 18 Differential.
B18: Dr: Acct 0950 - BEGINNING FUND BALANCE | J18: =P18 -> 108667 | M18: 108666.78 | P18: =IF(SUM($Q$20:$Q$23)>SUM($P$15:$P$17),SUM($Q$20:$Q$23)-SUM($P$15:$P$17),0) -> 108667 | S18: =P18-M18 -> 0.21767059 | T18: No action required.
B19: Dr: Acct 0952 - BEGINNING FUND ADJUSTMENT/PRIOR PERIOD ADJUSTMENT | J19: =IF(SUM($K$20:$K$24)>SUM($J$15:$J$18),SUM($K$20:$K$24)-SUM($J$15:$J$18),0) -> 0 | S19: =P19-M19 -> 0 | T19: No action required.
C20: Cr: Acct 0485 - ACCUMULATED AMORTIZATION - RIGHT-TO-USE LEASED LAND | K20: =N20 -> 0 | N20: 0 | Q20: 0 | S20: =Q20-N20 -> 0 | T20: No action required.
C21: Cr: Acct 0479 - ACCUMULATED AMORTIZATION - RIGHT-TO-USE LEASED EQUIPMENT | K21: =N21 -> 0 | N21: 0 | Q21: 0 | S21: =Q21-N21 -> 0 | T21: No action required.
C22: Cr: Acct 0486 - ACCUMULATED AMORTIZATION - RIGHT-TO-USE LEASED BUILDINGS | K22: =N22 -> 816378.23 | N22: 816378.23 | Q22: 816378 | S22: =Q22-N22 -> -0.23355225 | T22: No action required.
A23: **LS LL/CF | C23: Cr: Acct 0691 - RIGHT-TO-USE LEASE LIABILITY | K23: =N23 -> 3391636.6 | N23: 3391636.6 | Q23: 3391637 | S23: =Q23-N23 -> 0.43230176 | T23: No action required.
C24: Cr: Acct 0950 - BEGINNING FUND BALANCE | K24: =Q24 -> 0 | Q24: =IF(SUM($Q$20:$Q$23)<SUM($P$15:$P$17),-SUM($Q$20:$Q$23)+SUM($P$15:$P$17),0) -> 0 | S24: =Q24-N24 -> 0 | T24: No action required.
C25: Cr: Acct 0952 - BEGINNING FUND ADJUSTMENT/PRIOR PERIOD ADJUSTMENT | K25: =IF(SUM($K$20:$K$24)<SUM($J$15:$J$18),-SUM($K$20:$K$24)+SUM($J$15:$J$18),0) -> 0.35127519 | S25: =Q25-N25 -> 0 | T25: No action required.
J26: =SUM(J15:J25) -> 4208015.2 | K26: =SUM(K15:K25) -> 4208015.2 | L26: =IF(J26=K26,"<- Debits and Credits equal each other.","<- Debits and Credits do not equal each other.") -> <- Debits and Credits equal each other.
B27: * THESE ASSET AMOUNTS SHOULD BE REPORTED AS BEGINNING BALANCES ON REPORT 18.
B28: ** This amount should be included in the beginning balance column on the LS-Lease Liability and LS-Check Figures Tabs.
A31: Record New Leases (new leases only)
A32: 1 | B32: Record lease contract commencement (fund-based entries only)
B33: Dr: Acct 0842 - CAPITAL OUTLAY
C34: Cr: Acct 0789 - LEASE AND OTHER FINANCING PROCEEDS
C35: =IF($F$7="Proprietary","Cr: Acct 0870 - SERVICES & CHARGES (MG ADJ)",VLOOKUP($F$9,'Drop Down Menus'!$F$2:$G$10,2,FALSE)) -> Cr: Acct 0808 - GENERAL GOV. (GAAP ADJ)
J36: =SUM(J33:J35) -> 0 | K36: =SUM(K33:K35) -> 0 | L36: =IF(J36=K36,"<- Debits and Credits equal each other.","<- Debits and Credits do not equal each other.") -> <- Debits and Credits equal each other.
A38: 2 | B38: Record leased assets.
A39: *Rpt 18 | B39: Dr: Acct 0476 - RIGHT-TO-USE LEASED LAND - AMORTIZABLE
A40: *Rpt 18 | B40: Dr: Acct 0478 - RIGHT-TO-USE LEASED EQUIPMENT - AMORTIZABLE
A41: *Rpt 18 | B41: Dr: Acct 0477 - RIGHT-TO-USE LEASED BUILDINGS - AMORTIZABLE
C42: Cr: Acct 0842 - CAPITAL OUTLAY
B43: * THESE AMOUNTS SHOULD BE INCLUDED AS "ADDITIONS" ON REPORT 18. | J43: =SUM(J39:J42) -> 0 | K43: =SUM(K39:K42) -> 0 | L43: =IF(J43=K43,"<- Debits and Credits equal each other.","<- Debits and Credits do not equal each other.") -> <- Debits and Credits equal each other.
A46: 3 | B46: Replace proceeds from leases with right-to-use lease liability.
B47: Dr: Acct 0789 - LEASE AND OTHER FINANCING PROCEEDS
A48: **LS LL/CF | C48: Cr: Acct 0691 - RIGHT-TO-USE LEASE LIABILITY
J49: =SUM(J47:J48) -> 0 | K49: =SUM(K47:K48) -> 0 | L49: =IF(J49=K49,"<- Debits and Credits equal each other.","<- Debits and Credits do not equal each other.") -> <- Debits and Credits equal each other.
B50: ** This amount should be included in the additions column on the LS-Lease Liability and LS-Check Figures Tabs.
A53: Record Annual Activity (all leases)
A54: 4 | B54: Record amortization of the leased assets for the year.
B55: Dr: Acct 0875 - DEPRECIATION/AMORTIZATION | J55: 408189.05
C56: Cr: Acct 0485 - ACCUMULATED AMORTIZATION - RIGHT-TO-USE LEASED LAND | K56: 0
C57: Cr: Acct 0479 - ACCUMULATED AMORTIZATION - RIGHT-TO-USE LEASED EQUIPMENT | K57: 0
C58: Cr: Acct 0486 - ACCUMULATED AMORTIZATION - RIGHT-TO-USE LEASED BUILDINGS | K58: 408189.05
J59: =SUM(J55:J58) -> 408189.05 | K59: =SUM(K55:K58) -> 408189.05 | L59: =IF(J59=K59,"<- Debits and Credits equal each other.","<- Debits and Credits do not equal each other.") -> <- Debits and Credits equal each other.
A61: 5 | B61: Reclassify rents and leases exp. to lease contract principal and interest exp.
B62: Dr: Acct 0848 - DEBT SERVICE - PRINCIPAL LEASES | J62: 372562.59 | L62: =IF($J$62=$K$69,"","<- Accts 0848 must agree")
B63: =IF($F$7="Governmental","Dr: Acct 0851 - DEBT SERVICE - INTEREST LEASES","Dr: Acct 0894 - INTEREST EXPENSE AND FISCAL CHARGES") -> Dr: Acct 0851 - DEBT SERVICE - INTEREST LEASES | J63: 47652.482
C64: =IF($F$7="Proprietary","Cr: Acct 0870 - SERVICES & CHARGES (MG ADJ)",VLOOKUP($F$9,'Drop Down Menus'!$F$2:$G$10,2,FALSE)) -> Cr: Acct 0808 - GENERAL GOV. (GAAP ADJ) | K64: 420215.07
J65: =SUM(J62:J64) -> 420215.07 | K65: =SUM(K62:K64) -> 420215.07 | L65: =IF(J65=K65,"<- Debits and Credits equal each other.","<- Debits and Credits do not equal each other.") -> <- Debits and Credits equal each other.
A67: 6 | B67: Reduce lease contracts liability for total current year principal payments.
A68: **LS LL/CF | B68: Dr: Acct 0691 - RIGHT-TO-USE LEASE LIABILITY | J68: 372562.59
C69: Cr: Acct 0848 - DEBT SERVICE - PRINCIPAL LEASES | K69: 372562.59 | L69: =IF($J$62=$K$69,"","<- Accts 0848 must agree")
J70: =SUM(J68:J69) -> 372562.59 | K70: =SUM(K68:K69) -> 372562.59 | L70: =IF(J70=K70,"<- Debits and Credits equal each other.","<- Debits and Credits do not equal each other.") -> <- Debits and Credits equal each other.
B71: ** This amount should be included in the deductions column on the LS-Lease Liability and LS-Check Figures Tabs.
A74: 7 | B74: Reclassify the principal amount due in the next FY to the current liability.
A75: **LS LL/CF | B75: Dr: Acct 0691 - RIGHT-TO-USE LEASE LIABILITY | J75: 385659.72
C76: Cr: Acct 0649 - RIGHT-TO-USE LEASE LIABILITY (CURRENT PORTION LT) | K76: 385659.72
B77: NOTE: This is an annual accrual. It is to be reversed at the start of the next fiscal year. SCO combines the current and non current amount in Entry #0 to reestablish the beginning balances. No action required. | J77: =SUM(J75:J76) -> 385659.72 | K77: =SUM(K75:K76) -> 385659.72 | L77: =IF(J77=K77,"<- Debits and Credits equal each other.","<- Debits and Credits do not equal each other.") -> <- Debits and Credits equal each other.
B80: ** This amount should be included in the due in one year column on the LS-Lease Liability and LS-Check Figures Tabs.
A83: Remove Lease Asset at the End of the Lease Term (only at the end of the lease term)
A84: 8 | B84: Record entry to write off the lease asset and accumulated amortization at the end of the lease term.
B85: Dr: Acct 0485 - ACCUMULATED AMORTIZATION - RIGHT-TO-USE LEASED LAND
B86: Dr: Acct 0479 - ACCUMULATED AMORTIZATION - RIGHT-TO-USE LEASED EQUIPMENT
B87: Dr: Acct 0486 - ACCUMULATED AMORTIZATION - RIGHT-TO-USE LEASED BUILDINGS
A88: *Rpt 18 | C88: Cr: Acct 0476 - RIGHT-TO-USE LEASED LAND - AMORTIZABLE
A89: *Rpt 18 | C89: Cr: Acct 0478 - RIGHT-TO-USE LEASED EQUIPMENT - AMORTIZABLE
A90: *Rpt 18 | C90: Cr: Acct 0477 - RIGHT-TO-USE LEASED BUILDINGS - AMORTIZABLE
B91: * THESE AMOUNTS SHOULD BE INCLUDED AS "DEDUCTIONS" ON REPORT 18. | J91: =SUM(J85:J90) -> 0 | K91: =SUM(K85:K90) -> 0 | L91: =IF(J91=K91,"<- Debits and Credits equal each other.","<- Debits and Credits do not equal each other.") -> <- Debits and Credits equal each other.
A94: Lease Remeasurement and Modifications (only if a significant modification occurred during the fiscal year)
A95: 9 | B95: Record early termination or lease modifications to decrease in the RTU leased asset.
A96: **LS LL/CF | B96: Dr: Acct 0691 - RIGHT-TO-USE LEASE LIABILITY
B97: Dr: Acct 0485 - ACCUMULATED AMORTIZATION - RIGHT-TO-USE LEASED LAND
B98: Dr: Acct 0479 - ACCUMULATED AMORTIZATION - RIGHT-TO-USE LEASED EQUIPMENT
B99: Dr: Acct 0486 - ACCUMULATED AMORTIZATION - RIGHT-TO-USE LEASED BUILDINGS
B100: =IF($F$7="Proprietary","Dr: Acct 0870 - SERVICES & CHARGES (MG ADJ)",VLOOKUP($F$9,'Drop Down Menus'!$F$2:$H$10,3,FALSE)) -> Dr: Acct 0808 - GENERAL GOV. (GAAP ADJ)
A101: *Rpt 18 | C101: Cr: Acct 0476 - RIGHT-TO-USE LEASED LAND - AMORTIZABLE
A102: *Rpt 18 | C102: Cr: Acct 0478 - RIGHT-TO-USE LEASED EQUIPMENT - AMORTIZABLE
A103: *Rpt 18 | C103: Cr: Acct 0477 - RIGHT-TO-USE LEASED BUILDINGS - AMORTIZABLE
C104: =IF($F$7="Proprietary","Dr: Acct 0870 - SERVICES & CHARGES (MG ADJ)",VLOOKUP($F$9,'Drop Down Menus'!$F$2:$G$10,2,FALSE)) -> Cr: Acct 0808 - GENERAL GOV. (GAAP ADJ)
B105: * THESE AMOUNTS SHOULD BE INCLUDED AS "DEDUCTIONS" ON REPORT 18. | J105: =SUM(J96:J104) -> 0 | K105: =SUM(K96:K104) -> 0 | L105: =IF(J105=K105,"<- Debits and Credits equal each other.","<- Debits and Credits do not equal each other.") -> <- Debits and Credits equal each other.
B106: ** This amount should be included in the deductions column on the LS-Lease Liability and LS-Check Figures Tabs.
A109: 10 | B109: Record lease modifications to increase in the RTU leased asset.
A110: *Rpt 18 | B110: Dr: Acct 0476 - RIGHT-TO-USE LEASED LAND - AMORTIZABLE
A111: *Rpt 18 | B111: Dr: Acct 0478 - RIGHT-TO-USE LEASED EQUIPMENT - AMORTIZABLE
A112: *Rpt 18 | B112: Dr: Acct 0477 - RIGHT-TO-USE LEASED BUILDINGS - AMORTIZABLE
A113: **LS LL/CF | C113: Cr: Acct 0691 - RIGHT-TO-USE LEASE LIABILITY
B114: * THESE AMOUNTS SHOULD BE INCLUDED AS "ADDITIONS" ON REPORT 18. | J114: =SUM(J110:J113) -> 0 | K114: =SUM(K110:K113) -> 0 | L114: =IF(J114=K114,"<- Debits and Credits equal each other.","<- Debits and Credits do not equal each other.") -> <- Debits and Credits equal each other.
B115: ** This amount should be included in the additions column on the LS-Lease Liability and LS-Check Figures Tabs.
D120: Informational - Ending Balances of Assets and Liabilities
K121: Debit (Credit)
D122: Acct 0476 - RIGHT-TO-USE LEASED LAND - AMORTIZABLE | K122: =J15+J39-K88-K101+J110 -> 0
D123: Acct 0478 - RIGHT-TO-USE LEASED EQUIPMENT - AMORTIZABLE | K123: =J16+J40-K89-K102+J111 -> 0
D124: Acct 0477 - RIGHT-TO-USE LEASED BUILDINGS - AMORTIZABLE | K124: =J17+J41-K90-K103+J112 -> 4099348.2
D125: Acct 0485 - ACCUMULATED AMORTIZATION - RIGHT-TO-USE LEASED LAND | K125: =-K20-K56+J85+J97 -> 0
...

Sheet LS-Fund 0142 Journal Entries
A1: Lessee-Type Contracts Fund-by-Fund Journal Entries Form (to be submitted to the SCO annually—one form per fund)
A2: Manually complete every yellow field in this worksheet—there are no automatically calculated data-entry cells in this worksheet.
A3: Fiscal Year: | F3: 2023–2024
A4: Organization Name: | F4: Department of Justice
A5: Organization Code (4-Digits): | F5: 0820
A6: Fund Number (4-Digits): | F6: 142
A7: Fund Classification: | F7: Governmental
A8: Fund Type: | F8: Governmental Fund
A9: Functional Expense: | F9: =IFERROR(IF(F7="Proprietary","Proprietary Fund",VLOOKUP(F5,qryIndex02a!$A$2:$K$654,4,FALSE)),"Unidentified") -> GENERAL GOVERNMENT
A12: Establish Beginning Balances (existing leases only)
A13: Entry #
A14: 0 | B14: Roll forward prior year right-to-use leases to record opening balances. | M14: Combined Lessee Templates | P14: From SCO BB List | S14: Difference
A15: *Rpt 18 | B15: Dr: Acct 0476 - RIGHT-TO-USE LEASED LAND - AMORTIZABLE | J15: =M15 -> 0 | M15: 0 | P15: 0 | S15: =P15-M15 -> 0 | T15: Report any "Differences" on the Report 18 Differential.
A16: *Rpt 18 | B16: Dr: Acct 0478 - RIGHT-TO-USE LEASED EQUIPMENT - AMORTIZABLE | J16: =M16 -> 0 | M16: 0 | P16: 0 | S16: =P16-M16 -> 0 | T16: Report any "Differences" on the Report 18 Differential.
A17: *Rpt 18 | B17: Dr: Acct 0477 - RIGHT-TO-USE LEASED BUILDINGS - AMORTIZABLE | J17: =M17 -> 409242.61 | M17: 409242.61 | P17: 409243 | S17: =P17-M17 -> 0.38617104 | T17: Report any "Differences" on the Report 18 Differential.
B18: Dr: Acct 0950 - BEGINNING FUND BALANCE | J18: =P18 -> 10848 | M18: 10848.329 | P18: =IF(SUM($Q$20:$Q$23)>SUM($P$15:$P$17),SUM($Q$20:$Q$23)-SUM($P$15:$P$17),0) -> 10848 | S18: =P18-M18 -> -0.32914459 | T18: No action required.
B19: Dr: Acct 0952 - BEGINNING FUND ADJUSTMENT/PRIOR PERIOD ADJUSTMENT | J19: =IF(SUM($K$20:$K$24)>SUM($J$15:$J$18),SUM($K$20:$K$24)-SUM($J$15:$J$18),0) -> 0.31580669 | S19: =P19-M19 -> 0 | T19: No action required.
C20: Cr: Acct 0485 - ACCUMULATED AMORTIZATION - RIGHT-TO-USE LEASED LAND | K20: =N20 -> 0 | N20: 0 | Q20: 0 | S20: =Q20-N20 -> 0 | T20: No action required.
C21: Cr: Acct 0479 - ACCUMULATED AMORTIZATION - RIGHT-TO-USE LEASED EQUIPMENT | K21: =N21 -> 0 | N21: 0 | Q21: 0 | S21: =Q21-N21 -> 0 | T21: No action required.
C22: Cr: Acct 0486 - ACCUMULATED AMORTIZATION - RIGHT-TO-USE LEASED BUILDINGS | K22: =N22 -> 81499.973 | N22: 81499.973 | Q22: 81500 | S22: =Q22-N22 -> 0.027384562 | T22: No action required.
A23: **LS LL/CF | C23: Cr: Acct 0691 - RIGHT-TO-USE LEASE LIABILITY | K23: =N23 -> 338590.96 | N23: 338590.96 | Q23: 338591 | S23: =Q23-N23 -> 0.04297979 | T23: No action required.
C24: Cr: Acct 0950 - BEGINNING FUND BALANCE | K24: =Q24 -> 0 | Q24: =IF(SUM($Q$20:$Q$23)<SUM($P$15:$P$17),-SUM($Q$20:$Q$23)+SUM($P$15:$P$17),0) -> 0 | S24: =Q24-N24 -> 0 | T24: No action required.
C25: Cr: Acct 0952 - BEGINNING FUND ADJUSTMENT/PRIOR PERIOD ADJUSTMENT | K25: =IF(SUM($K$20:$K$24)<SUM($J$15:$J$18),-SUM($K$20:$K$24)+SUM($J$15:$J$18),0) -> 0 | S25: =Q25-N25 -> 0 | T25: No action required.
J26: =SUM(J15:J25) -> 420090.93 | K26: =SUM(K15:K25) -> 420090.93 | L26: =IF(J26=K26,"<- Debits and Credits equal each other.","<- Debits and Credits do not equal each other.") -> <- Debits and Credits equal each other.
B27: * THESE ASSET AMOUNTS SHOULD BE REPORTED AS BEGINNING BALANCES ON REPORT 18.
B28: ** This amount should be included in the beginning balance column on the LS-Lease Liability and LS-Check Figures Tabs.
A31: Record New Leases (new leases only)
A32: 1 | B32: Record lease contract commencement (fund-based entries only)
B33: Dr: Acct 0842 - CAPITAL OUTLAY
C34: Cr: Acct 0789 - LEASE AND OTHER FINANCING PROCEEDS
C35: =IF($F$7="Proprietary","Cr: Acct 0870 - SERVICES & CHARGES (MG ADJ)",VLOOKUP($F$9,'Drop Down Menus'!$F$2:$G$10,2,FALSE)) -> Cr: Acct 0808 - GENERAL GOV. (GAAP ADJ)
J36: =SUM(J33:J35) -> 0 | K36: =SUM(K33:K35) -> 0 | L36: =IF(J36=K36,"<- Debits and Credits equal each other.","<- Debits and Credits do not equal each other.") -> <- Debits and Credits equal each other.
A38: 2 | B38: Record leased assets.
A39: *Rpt 18 | B39: Dr: Acct 0476 - RIGHT-TO-USE LEASED LAND - AMORTIZABLE
A40: *Rpt 18 | B40: Dr: Acct 0478 - RIGHT-TO-USE LEASED EQUIPMENT - AMORTIZABLE
A41: *Rpt 18 | B41: Dr: Acct 0477 - RIGHT-TO-USE LEASED BUILDINGS - AMORTIZABLE
C42: Cr: Acct 0842 - CAPITAL OUTLAY
B43: * THESE AMOUNTS SHOULD BE INCLUDED AS "ADDITIONS" ON REPORT 18. | J43: =SUM(J39:J42) -> 0 | K43: =SUM(K39:K42) -> 0 | L43: =IF(J43=K43,"<- Debits and Credits equal each other.","<- Debits and Credits do not equal each other.") -> <- Debits and Credits equal each other.
A46: 3 | B46: Replace proceeds from leases with right-to-use lease liability.
B47: Dr: Acct 0789 - LEASE AND OTHER FINANCING PROCEEDS
A48: **LS LL/CF | C48: Cr: Acct 0691 - RIGHT-TO-USE LEASE LIABILITY
J49: =SUM(J47:J48) -> 0 | K49: =SUM(K47:K48) -> 0 | L49: =IF(J49=K49,"<- Debits and Credits equal each other.","<- Debits and Credits do not equal each other.") -> <- Debits and Credits equal each other.
B50: ** This amount should be included in the additions column on the LS-Lease Liability and LS-Check Figures Tabs.
A53: Record Annual Activity (all leases)
A54: 4 | B54: Record amortization of the leased assets for the year.
B55: Dr: Acct 0875 - DEPRECIATION/AMORTIZATION | J55: 40749.98
C56: Cr: Acct 0485 - ACCUMULATED AMORTIZATION - RIGHT-TO-USE LEASED LAND | K56: 0
C57: Cr: Acct 0479 - ACCUMULATED AMORTIZATION - RIGHT-TO-USE LEASED EQUIPMENT | K57: 0
C58: Cr: Acct 0486 - ACCUMULATED AMORTIZATION - RIGHT-TO-USE LEASED BUILDINGS | K58: 40749.98
J59: =SUM(J55:J58) -> 40749.98 | K59: =SUM(K55:K58) -> 40749.98 | L59: =IF(J59=K59,"<- Debits and Credits equal each other.","<- Debits and Credits do not equal each other.") -> <- Debits and Credits equal each other.
A61: 5 | B61: Reclassify rents and leases exp. to lease contract principal and interest exp.
B62: Dr: Acct 0848 - DEBT SERVICE - PRINCIPAL LEASES | J62: 37193.349 | L62: =IF($J$62=$K$69,"","<- Accts 0848 must agree")
B63: =IF($F$7="Governmental","Dr: Acct 0851 - DEBT SERVICE - INTEREST LEASES","Dr: Acct 0894 - INTEREST EXPENSE AND FISCAL CHARGES") -> Dr: Acct 0851 - DEBT SERVICE - INTEREST LEASES | J63: 4757.2018
C64: =IF($F$7="Proprietary","Cr: Acct 0870 - SERVICES & CHARGES (MG ADJ)",VLOOKUP($F$9,'Drop Down Menus'!$F$2:$G$10,2,FALSE)) -> Cr: Acct 0808 - GENERAL GOV. (GAAP ADJ) | K64: 41950.551
J65: =SUM(J62:J64) -> 41950.551 | K65: =SUM(K62:K64) -> 41950.551 | L65: =IF(J65=K65,"<- Debits and Credits equal each other.","<- Debits and Credits do not equal each other.") -> <- Debits and Credits equal each other.
A67: 6 | B67: Reduce lease contracts liability for total current year principal payments.
A68: **LS LL/CF | B68: Dr: Acct 0691 - RIGHT-TO-USE LEASE LIABILITY | J68: 37193.349
C69: Cr: Acct 0848 - DEBT SERVICE - PRINCIPAL LEASES | K69: 37193.349 | L69: =IF($J$62=$K$69,"","<- Accts 0848 must agree")
J70: =SUM(J68:J69) -> 37193.349 | K70: =SUM(K68:K69) -> 37193.349 | L70: =IF(J70=K70,"<- Debits and Credits equal each other.","<- Debits and Credits do not equal each other.") -> <- Debits and Credits equal each other.
B71: ** This amount should be included in the deductions column on the LS-Lease Liability and LS-Check Figures Tabs.
A74: 7 | B74: Reclassify the principal amount due in the next FY to the current liability.
A75: **LS LL/CF | B75: Dr: Acct 0691 - RIGHT-TO-USE LEASE LIABILITY | J75: 38500.851
C76: Cr: Acct 0649 - RIGHT-TO-USE LEASE LIABILITY (CURRENT PORTION LT) | K76: 38500.851
B77: NOTE: This is an annual accrual. It is to be reversed at the start of the next fiscal year. SCO combines the current and non current amount in Entry #0 to reestablish the beginning balances. No action required. | J77: =SUM(J75:J76) -> 38500.851 | K77: =SUM(K75:K76) -> 38500.851 | L77: =IF(J77=K77,"<- Debits and Credits equal each other.","<- Debits and Credits do not equal each other.") -> <- Debits and Credits equal each other.
B80: ** This amount should be included in the due in one year column on the LS-Lease Liability and LS-Check Figures Tabs.
A83: Remove Lease Asset at the End of the Lease Term (only at the end of the lease term)
A84: 8 | B84: Record entry to write off the lease asset and accumulated amortization at the end of the lease term.
B85: Dr: Acct 0485 - ACCUMULATED AMORTIZATION - RIGHT-TO-USE LEASED LAND
B86: Dr: Acct 0479 - ACCUMULATED AMORTIZATION - RIGHT-TO-USE LEASED EQUIPMENT
B87: Dr: Acct 0486 - ACCUMULATED AMORTIZATION - RIGHT-TO-USE LEASED BUILDINGS
A88: *Rpt 18 | C88: Cr: Acct 0476 - RIGHT-TO-USE LEASED LAND - AMORTIZABLE
A89: *Rpt 18 | C89: Cr: Acct 0478 - RIGHT-TO-USE LEASED EQUIPMENT - AMORTIZABLE
A90: *Rpt 18 | C90: Cr: Acct 0477 - RIGHT-TO-USE LEASED BUILDINGS - AMORTIZABLE
B91: * THESE AMOUNTS SHOULD BE INCLUDED AS "DEDUCTIONS" ON REPORT 18. | J91: =SUM(J85:J90) -> 0 | K91: =SUM(K85:K90) -> 0 | L91: =IF(J91=K91,"<- Debits and Credits equal each other.","<- Debits and Credits do not equal each other.") -> <- Debits and Credits equal each other.
A94: Lease Remeasurement and Modifications (only if a significant modification occurred during the fiscal year)
A95: 9 | B95: Record early termination or lease modifications to decrease in the RTU leased asset.
A96: **LS LL/CF | B96: Dr: Acct 0691 - RIGHT-TO-USE LEASE LIABILITY
B97: Dr: Acct 0485 - ACCUMULATED AMORTIZATION - RIGHT-TO-USE LEASED LAND
B98: Dr: Acct 0479 - ACCUMULATED AMORTIZATION - RIGHT-TO-USE LEASED EQUIPMENT
B99: Dr: Acct 0486 - ACCUMULATED AMORTIZATION - RIGHT-TO-USE LEASED BUILDINGS
B100: =IF($F$7="Proprietary","Dr: Acct 0870 - SERVICES & CHARGES (MG ADJ)",VLOOKUP($F$9,'Drop Down Menus'!$F$2:$H$10,3,FALSE)) -> Dr: Acct 0808 - GENERAL GOV. (GAAP ADJ)
A101: *Rpt 18 | C101: Cr: Acct 0476 - RIGHT-TO-USE LEASED LAND - AMORTIZABLE
A102: *Rpt 18 | C102: Cr: Acct 0478 - RIGHT-TO-USE LEASED EQUIPMENT - AMORTIZABLE
A103: *Rpt 18 | C103: Cr: Acct 0477 - RIGHT-TO-USE LEASED BUILDINGS - AMORTIZABLE
C104: =IF($F$7="Proprietary","Dr: Acct 0870 - SERVICES & CHARGES (MG ADJ)",VLOOKUP($F$9,'Drop Down Menus'!$F$2:$G$10,2,FALSE)) -> Cr: Acct 0808 - GENERAL GOV. (GAAP ADJ)
B105: * THESE AMOUNTS SHOULD BE INCLUDED AS "DEDUCTIONS" ON REPORT 18. | J105: =SUM(J96:J104) -> 0 | K105: =SUM(K96:K104) -> 0 | L105: =IF(J105=K105,"<- Debits and Credits equal each other.","<- Debits and Credits do not equal each other.") -> <- Debits and Credits equal each other.
B106: ** This amount should be included in the deductions column on the LS-Lease Liability and LS-Check Figures Tabs.
A109: 10 | B109: Record lease modifications to increase in the RTU leased asset.
A110: *Rpt 18 | B110: Dr: Acct 0476 - RIGHT-TO-USE LEASED LAND - AMORTIZABLE
A111: *Rpt 18 | B111: Dr: Acct 0478 - RIGHT-TO-USE LEASED EQUIPMENT - AMORTIZABLE
A112: *Rpt 18 | B112: Dr: Acct 0477 - RIGHT-TO-USE LEASED BUILDINGS - AMORTIZABLE
A113: **LS LL/CF | C113: Cr: Acct 0691 - RIGHT-TO-USE LEASE LIABILITY
B114: * THESE AMOUNTS SHOULD BE INCLUDED AS "ADDITIONS" ON REPORT 18. | J114: =SUM(J110:J113) -> 0 | K114: =SUM(K110:K113) -> 0 | L114: =IF(J114=K114,"<- Debits and Credits equal each other.","<- Debits and Credits do not equal each other.") -> <- Debits and Credits equal each other.
B115: ** This amount should be included in the additions column on the LS-Lease Liability and LS-Check Figures Tabs.
D120: Informational - Ending Balances of Assets and Liabilities
K121: Debit (Credit)
D122: Acct 0476 - RIGHT-TO-USE LEASED LAND - AMORTIZABLE | K122: =J15+J39-K88-K101+J110 -> 0
D123: Acct 0478 - RIGHT-TO-USE LEASED EQUIPMENT - AMORTIZABLE | K123: =J16+J40-K89-K102+J111 -> 0
D124: Acct 0477 - RIGHT-TO-USE LEASED BUILDINGS - AMORTIZABLE | K124: =J17+J41-K90-K103+J112 -> 409242.61
D125: Acct 0485 - ACCUMULATED AMORTIZATION - RIGHT-TO-USE LEASED LAND | K125: =-K20-K56+J85+J97 -> 0
...

Sheet LS-Fund 0256 Journal Entries
A1: Lessee-Type Contracts Fund-by-Fund Journal Entries Form (to be submitted to the SCO annually—one form per fund)
A2: Manually complete every yellow field in this worksheet—there are no automatically calculated data-entry cells in this worksheet.
A3: Fiscal Year: | F3: 2023–2024
A4: Organization Name: | F4: Department of Justice
A5: Organization Code (4-Digits): | F5: 0820
A6: Fund Number (4-Digits): | F6: 256
A7: Fund Classification: | F7: Governmental
A8: Fund Type: | F8: Governmental Fund
A9: Functional Expense: | F9: =IFERROR(IF(F7="Proprietary","Proprietary Fund",VLOOKUP(F5,qryIndex02a!$A$2:$K$654,4,FALSE)),"Unidentified") -> GENERAL GOVERNMENT
A12: Establish Beginning Balances (existing leases only)
A13: Entry #
A14: 0 | B14: Roll forward prior year right-to-use leases to record opening balances. | M14: Combined Lessee Templates | P14: From SCO BB List | S14: Difference
A15: *Rpt 18 | B15: Dr: Acct 0476 - RIGHT-TO-USE LEASED LAND - AMORTIZABLE | J15: =M15 -> 0 | M15: 0 | P15: 0 | S15: =P15-M15 -> 0 | T15: Report any "Differences" on the Report 18 Differential.
A16: *Rpt 18 | B16: Dr: Acct 0478 - RIGHT-TO-USE LEASED EQUIPMENT - AMORTIZABLE | J16: =M16 -> 0 | M16: 0 | P16: 0 | S16: =P16-M16 -> 0 | T16: Report any "Differences" on the Report 18 Differential.
A17: *Rpt 18 | B17: Dr: Acct 0477 - RIGHT-TO-USE LEASED BUILDINGS - AMORTIZABLE | J17: =M17 -> 69364.351 | M17: 69364.351 | P17: 69364 | S17: =P17-M17 -> -0.35099102 | T17: Report any "Differences" on the Report 18 Differential.
B18: Dr: Acct 0950 - BEGINNING FUND BALANCE | J18: =P18 -> 1840 | M18: 1838.7316 | P18: =IF(SUM($Q$20:$Q$23)>SUM($P$15:$P$17),SUM($Q$20:$Q$23)-SUM($P$15:$P$17),0) -> 1840 | S18: =P18-M18 -> 1.2684383 | T18: No action required.
B19: Dr: Acct 0952 - BEGINNING FUND ADJUSTMENT/PRIOR PERIOD ADJUSTMENT | J19: =IF(SUM($K$20:$K$24)>SUM($J$15:$J$18),SUM($K$20:$K$24)-SUM($J$15:$J$18),0) -> 0 | S19: =P19-M19 -> 0 | T19: No action required.
C20: Cr: Acct 0485 - ACCUMULATED AMORTIZATION - RIGHT-TO-USE LEASED LAND | K20: =N20 -> 0 | N20: 0 | Q20: 0 | S20: =Q20-N20 -> 0 | T20: No action required.
C21: Cr: Acct 0479 - ACCUMULATED AMORTIZATION - RIGHT-TO-USE LEASED EQUIPMENT | K21: =N21 -> 0 | N21: 0 | Q21: 0 | S21: =Q21-N21 -> 0 | T21: No action required.
C22: Cr: Acct 0486 - ACCUMULATED AMORTIZATION - RIGHT-TO-USE LEASED BUILDINGS | K22: =N22 -> 13813.793 | N22: 13813.793 | Q22: 13814 | S22: =Q22-N22 -> 0.20711718 | T22: No action required.
A23: **LS LL/CF | C23: Cr: Acct 0691 - RIGHT-TO-USE LEASE LIABILITY | K23: =N23 -> 57389.287 | N23: 57389.287 | Q23: 57390 | S23: =Q23-N23 -> 0.71259077 | T23: No action required.
C24: Cr: Acct 0950 - BEGINNING FUND BALANCE | K24: =Q24 -> 0 | Q24: =IF(SUM($Q$20:$Q$23)<SUM($P$15:$P$17),-SUM($Q$20:$Q$23)+SUM($P$15:$P$17),0) -> 0 | S24: =Q24-N24 -> 0 | T24: No action required.
C25: Cr: Acct 0952 - BEGINNING FUND ADJUSTMENT/PRIOR PERIOD ADJUSTMENT | K25: =IF(SUM($K$20:$K$24)<SUM($J$15:$J$18),-SUM($K$20:$K$24)+SUM($J$15:$J$18),0) -> 1.270699 | S25: =Q25-N25 -> 0 | T25: No action required.
J26: =SUM(J15:J25) -> 71204.351 | K26: =SUM(K15:K25) -> 71204.351 | L26: =IF(J26=K26,"<- Debits and Credits equal each other.","<- Debits and Credits do not equal each other.") -> <- Debits and Credits equal each other.
B27: * THESE ASSET AMOUNTS SHOULD BE REPORTED AS BEGINNING BALANCES ON REPORT 18.
B28: ** This amount should be included in the beginning balance column on the LS-Lease Liability and LS-Check Figures Tabs.
A31: Record New Leases (new leases only)
A32: 1 | B32: Record lease contract commencement (fund-based entries only)
B33: Dr: Acct 0842 - CAPITAL OUTLAY
C34: Cr: Acct 0789 - LEASE AND OTHER FINANCING PROCEEDS
C35: =IF($F$7="Proprietary","Cr: Acct 0870 - SERVICES & CHARGES (MG ADJ)",VLOOKUP($F$9,'Drop Down Menus'!$F$2:$G$10,2,FALSE)) -> Cr: Acct 0808 - GENERAL GOV. (GAAP ADJ)
J36: =SUM(J33:J35) -> 0 | K36: =SUM(K33:K35) -> 0 | L36: =IF(J36=K36,"<- Debits and Credits equal each other.","<- Debits and Credits do not equal each other.") -> <- Debits and Credits equal each other.
A38: 2 | B38: Record leased assets.
A39: *Rpt 18 | B39: Dr: Acct 0476 - RIGHT-TO-USE LEASED LAND - AMORTIZABLE
A40: *Rpt 18 | B40: Dr: Acct 0478 - RIGHT-TO-USE LEASED EQUIPMENT - AMORTIZABLE
A41: *Rpt 18 | B41: Dr: Acct 0477 - RIGHT-TO-USE LEASED BUILDINGS - AMORTIZABLE
C42: Cr: Acct 0842 - CAPITAL OUTLAY
B43: * THESE AMOUNTS SHOULD BE INCLUDED AS "ADDITIONS" ON REPORT 18. | J43: =SUM(J39:J42) -> 0 | K43: =SUM(K39:K42) -> 0 | L43: =IF(J43=K43,"<- Debits and Credits equal each other.","<- Debits and Credits do not equal each other.") -> <- Debits and Credits equal each other.
A46: 3 | B46: Replace proceeds from leases with right-to-use lease liability.
B47: Dr: Acct 0789 - LEASE AND OTHER FINANCING PROCEEDS
A48: **LS LL/CF | C48: Cr: Acct 0691 - RIGHT-TO-USE LEASE LIABILITY
J49: =SUM(J47:J48) -> 0 | K49: =SUM(K47:K48) -> 0 | L49: =IF(J49=K49,"<- Debits and Credits equal each other.","<- Debits and Credits do not equal each other.") -> <- Debits and Credits equal each other.
B50: ** This amount should be included in the additions column on the LS-Lease Liability and LS-Check Figures Tabs.
A53: Record Annual Activity (all leases)
A54: 4 | B54: Record amortization of the leased assets for the year.
B55: Dr: Acct 0875 - DEPRECIATION/AMORTIZATION | J55: 6906.8953
C56: Cr: Acct 0485 - ACCUMULATED AMORTIZATION - RIGHT-TO-USE LEASED LAND | K56: 0
C57: Cr: Acct 0479 - ACCUMULATED AMORTIZATION - RIGHT-TO-USE LEASED EQUIPMENT | K57: 0
C58: Cr: Acct 0486 - ACCUMULATED AMORTIZATION - RIGHT-TO-USE LEASED BUILDINGS | K58: 6906.8953
J59: =SUM(J55:J58) -> 6906.8953 | K59: =SUM(K55:K58) -> 6906.8953 | L59: =IF(J59=K59,"<- Debits and Credits equal each other.","<- Debits and Credits do not equal each other.") -> <- Debits and Credits equal each other.
A61: 5 | B61: Reclassify rents and leases exp. to lease contract principal and interest exp.
B62: Dr: Acct 0848 - DEBT SERVICE - PRINCIPAL LEASES | J62: 6304.0662 | L62: =IF($J$62=$K$69,"","<- Accts 0848 must agree")
B63: =IF($F$7="Governmental","Dr: Acct 0851 - DEBT SERVICE - INTEREST LEASES","Dr: Acct 0894 - INTEREST EXPENSE AND FISCAL CHARGES") -> Dr: Acct 0851 - DEBT SERVICE - INTEREST LEASES | J63: 806.31929
C64: =IF($F$7="Proprietary","Cr: Acct 0870 - SERVICES & CHARGES (MG ADJ)",VLOOKUP($F$9,'Drop Down Menus'!$F$2:$G$10,2,FALSE)) -> Cr: Acct 0808 - GENERAL GOV. (GAAP ADJ) | K64: 7110.3855
J65: =SUM(J62:J64) -> 7110.3855 | K65: =SUM(K62:K64) -> 7110.3855 | L65: =IF(J65=K65,"<- Debits and Credits equal each other.","<- Debits and Credits do not equal each other.") -> <- Debits and Credits equal each other.
A67: 6 | B67: Reduce lease contracts liability for total current year principal payments.
A68: **LS LL/CF | B68: Dr: Acct 0691 - RIGHT-TO-USE LEASE LIABILITY | J68: 6304.0662
C69: Cr: Acct 0848 - DEBT SERVICE - PRINCIPAL LEASES | K69: 6304.0662 | L69: =IF($J$62=$K$69,"","<- Accts 0848 must agree")
J70: =SUM(J68:J69) -> 6304.0662 | K70: =SUM(K68:K69) -> 6304.0662 | L70: =IF(J70=K70,"<- Debits and Credits equal each other.","<- Debits and Credits do not equal each other.") -> <- Debits and Credits equal each other.
B71: ** This amount should be included in the deductions column on the LS-Lease Liability and LS-Check Figures Tabs.
A74: 7 | B74: Reclassify the principal amount due in the next FY to the current liability.
A75: **LS LL/CF | B75: Dr: Acct 0691 - RIGHT-TO-USE LEASE LIABILITY | J75: 6525.6804
C76: Cr: Acct 0649 - RIGHT-TO-USE LEASE LIABILITY (CURRENT PORTION LT) | K76: 6525.6804
B77: NOTE: This is an annual accrual. It is to be reversed at the start of the next fiscal year. SCO combines the current and non current amount in Entry #0 to reestablish the beginning balances. No action required. | J77: =SUM(J75:J76) -> 6525.6804 | K77: =SUM(K75:K76) -> 6525.6804 | L77: =IF(J77=K77,"<- Debits and Credits equal each other.","<- Debits and Credits do not equal each other.") -> <- Debits and Credits equal each other.
B80: ** This amount should be included in the due in one year column on the LS-Lease Liability and LS-Check Figures Tabs.
A83: Remove Lease Asset at the End of the Lease Term (only at the end of the lease term)
A84: 8 | B84: Record entry to write off the lease asset and accumulated amortization at the end of the lease term.
B85: Dr: Acct 0485 - ACCUMULATED AMORTIZATION - RIGHT-TO-USE LEASED LAND
B86: Dr: Acct 0479 - ACCUMULATED AMORTIZATION - RIGHT-TO-USE LEASED EQUIPMENT
B87: Dr: Acct 0486 - ACCUMULATED AMORTIZATION - RIGHT-TO-USE LEASED BUILDINGS
A88: *Rpt 18 | C88: Cr: Acct 0476 - RIGHT-TO-USE LEASED LAND - AMORTIZABLE
A89: *Rpt 18 | C89: Cr: Acct 0478 - RIGHT-TO-USE LEASED EQUIPMENT - AMORTIZABLE
A90: *Rpt 18 | C90: Cr: Acct 0477 - RIGHT-TO-USE LEASED BUILDINGS - AMORTIZABLE
B91: * THESE AMOUNTS SHOULD BE INCLUDED AS "DEDUCTIONS" ON REPORT 18. | J91: =SUM(J85:J90) -> 0 | K91: =SUM(K85:K90) -> 0 | L91: =IF(J91=K91,"<- Debits and Credits equal each other.","<- Debits and Credits do not equal each other.") -> <- Debits and Credits equal each other.
A94: Lease Remeasurement and Modifications (only if a significant modification occurred during the fiscal year)
A95: 9 | B95: Record early termination or lease modifications to decrease in the RTU leased asset.
A96: **LS LL/CF | B96: Dr: Acct 0691 - RIGHT-TO-USE LEASE LIABILITY
B97: Dr: Acct 0485 - ACCUMULATED AMORTIZATION - RIGHT-TO-USE LEASED LAND
B98: Dr: Acct 0479 - ACCUMULATED AMORTIZATION - RIGHT-TO-USE LEASED EQUIPMENT
B99: Dr: Acct 0486 - ACCUMULATED AMORTIZATION - RIGHT-TO-USE LEASED BUILDINGS
B100: =IF($F$7="Proprietary","Dr: Acct 0870 - SERVICES & CHARGES (MG ADJ)",VLOOKUP($F$9,'Drop Down Menus'!$F$2:$H$10,3,FALSE)) -> Dr: Acct 0808 - GENERAL GOV. (GAAP ADJ)
A101: *Rpt 18 | C101: Cr: Acct 0476 - RIGHT-TO-USE LEASED LAND - AMORTIZABLE
A102: *Rpt 18 | C102: Cr: Acct 0478 - RIGHT-TO-USE LEASED EQUIPMENT - AMORTIZABLE
A103: *Rpt 18 | C103: Cr: Acct 0477 - RIGHT-TO-USE LEASED BUILDINGS - AMORTIZABLE
C104: =IF($F$7="Proprietary","Dr: Acct 0870 - SERVICES & CHARGES (MG ADJ)",VLOOKUP($F$9,'Drop Down Menus'!$F$2:$G$10,2,FALSE)) -> Cr: Acct 0808 - GENERAL GOV. (GAAP ADJ)
B105: * THESE AMOUNTS SHOULD BE INCLUDED AS "DEDUCTIONS" ON REPORT 18. | J105: =SUM(J96:J104) -> 0 | K105: =SUM(K96:K104) -> 0 | L105: =IF(J105=K105,"<- Debits and Credits equal each other.","<- Debits and Credits do not equal each other.") -> <- Debits and Credits equal each other.
B106: ** This amount should be included in the deductions column on the LS-Lease Liability and LS-Check Figures Tabs.
A109: 10 | B109: Record lease modifications to increase in the RTU leased asset.
A110: *Rpt 18 | B110: Dr: Acct 0476 - RIGHT-TO-USE LEASED LAND - AMORTIZABLE
A111: *Rpt 18 | B111: Dr: Acct 0478 - RIGHT-TO-USE LEASED EQUIPMENT - AMORTIZABLE
A112: *Rpt 18 | B112: Dr: Acct 0477 - RIGHT-TO-USE LEASED BUILDINGS - AMORTIZABLE
A113: **LS LL/CF | C113: Cr: Acct 0691 - RIGHT-TO-USE LEASE LIABILITY
B114: * THESE AMOUNTS SHOULD BE INCLUDED AS "ADDITIONS" ON REPORT 18. | J114: =SUM(J110:J113) -> 0 | K114: =SUM(K110:K113) -> 0 | L114: =IF(J114=K114,"<- Debits and Credits equal each other.","<- Debits and Credits do not equal each other.") -> <- Debits and Credits equal each other.
B115: ** This amount should be included in the additions column on the LS-Lease Liability and LS-Check Figures Tabs.
D120: Informational - Ending Balances of Assets and Liabilities
K121: Debit (Credit)
D122: Acct 0476 - RIGHT-TO-USE LEASED LAND - AMORTIZABLE | K122: =J15+J39-K88-K101+J110 -> 0
D123: Acct 0478 - RIGHT-TO-USE LEASED EQUIPMENT - AMORTIZABLE | K123: =J16+J40-K89-K102+J111 -> 0
D124: Acct 0477 - RIGHT-TO-USE LEASED BUILDINGS - AMORTIZABLE | K124: =J17+J41-K90-K103+J112 -> 69364.351
D125: Acct 0485 - ACCUMULATED AMORTIZATION - RIGHT-TO-USE LEASED LAND | K125: =-K20-K56+J85+J97 -> 0
...

Sheet LS-Fund 0367 Journal Entries
A1: Lessee-Type Contracts Fund-by-Fund Journal Entries Form (to be submitted to the SCO annually—one form per fund)
A2: Manually complete every yellow field in this worksheet—there are no automatically calculated data-entry cells in this worksheet.
A3: Fiscal Year: | F3: 2023–2024
A4: Organization Name: | F4: Department of Justice
A5: Organization Code (4-Digits): | F5: 0820
A6: Fund Number (4-Digits): | F6: 367
A7: Fund Classification: | F7: Governmental
A8: Fund Type: | F8: Governmental Fund
A9: Functional Expense: | F9: =IFERROR(IF(F7="Proprietary","Proprietary Fund",VLOOKUP(F5,qryIndex02a!$A$2:$K$654,4,FALSE)),"Unidentified") -> GENERAL GOVERNMENT
A12: Establish Beginning Balances (existing leases only)
A13: Entry #
A14: 0 | B14: Roll forward prior year right-to-use leases to record opening balances. | M14: Combined Lessee Templates | P14: From SCO BB List | S14: Difference
A15: *Rpt 18 | B15: Dr: Acct 0476 - RIGHT-TO-USE LEASED LAND - AMORTIZABLE | J15: =M15 -> 0 | M15: 0 | P15: 0 | S15: =P15-M15 -> 0 | T15: Report any "Differences" on the Report 18 Differential.
A16: *Rpt 18 | B16: Dr: Acct 0478 - RIGHT-TO-USE LEASED EQUIPMENT - AMORTIZABLE | J16: =M16 -> 56597.33 | M16: 56597.33 | P16: 56597 | S16: =P16-M16 -> -0.330052 | T16: Report any "Differences" on the Report 18 Differential.
A17: *Rpt 18 | B17: Dr: Acct 0477 - RIGHT-TO-USE LEASED BUILDINGS - AMORTIZABLE | J17: =M17 -> 4852660.4 | M17: 4852660.4 | P17: 4890682 | S17: =P17-M17 -> 38021.59 | T17: Report any "Differences" on the Report 18 Differential.
B18: Dr: Acct 0950 - BEGINNING FUND BALANCE | J18: =P18 -> 29157 | M18: 82493.478 | P18: =IF(SUM($Q$20:$Q$23)>SUM($P$15:$P$17),SUM($Q$20:$Q$23)-SUM($P$15:$P$17),0) -> 29157 | S18: =P18-M18 -> -53336.478 | T18: No action required.
B19: Dr: Acct 0952 - BEGINNING FUND ADJUSTMENT/PRIOR PERIOD ADJUSTMENT | J19: =IF(SUM($K$20:$K$24)>SUM($J$15:$J$18),SUM($K$20:$K$24)-SUM($J$15:$J$18),0) -> 3207.936 | S19: =P19-M19 -> 0 | T19: No action required.
C20: Cr: Acct 0485 - ACCUMULATED AMORTIZATION - RIGHT-TO-USE LEASED LAND | K20: =N20 -> 0 | N20: 0 | Q20: 0 | S20: =Q20-N20 -> 0 | T20: No action required.
C21: Cr: Acct 0479 - ACCUMULATED AMORTIZATION - RIGHT-TO-USE LEASED EQUIPMENT | K21: =N21 -> 22638.84 | N21: 22638.84 | Q21: 22640 | S21: =Q21-N21 -> 1.1602715 | T21: No action required.
C22: Cr: Acct 0486 - ACCUMULATED AMORTIZATION - RIGHT-TO-USE LEASED BUILDINGS | K22: =N22 -> 1773889.2 | N22: 1773889.2 | Q22: 1778008 | S22: =Q22-N22 -> 4118.7758 | T22: No action required.
A23: **LS LL/CF | C23: Cr: Acct 0691 - RIGHT-TO-USE LEASE LIABILITY | K23: =N23 -> 3145094.6 | N23: 3145094.6 | Q23: 3175788 | S23: =Q23-N23 -> 30693.388 | T23: No action required.
C24: Cr: Acct 0950 - BEGINNING FUND BALANCE | K24: =Q24 -> 0 | N24: 50127.749 | Q24: =IF(SUM($Q$20:$Q$23)<SUM($P$15:$P$17),-SUM($Q$20:$Q$23)+SUM($P$15:$P$17),0) -> 0 | S24: =Q24-N24 -> -50127.749 | T24: No action required.
C25: Cr: Acct 0952 - BEGINNING FUND ADJUSTMENT/PRIOR PERIOD ADJUSTMENT | K25: =IF(SUM($K$20:$K$24)<SUM($J$15:$J$18),-SUM($K$20:$K$24)+SUM($J$15:$J$18),0) -> 0 | S25: =Q25-N25 -> 0 | T25: No action required.
J26: =SUM(J15:J25) -> 4941622.7 | K26: =SUM(K15:K25) -> 4941622.7 | L26: =IF(J26=K26,"<- Debits and Credits equal each other.","<- Debits and Credits do not equal each other.") -> <- Debits and Credits equal each other.
B27: * THESE ASSET AMOUNTS SHOULD BE REPORTED AS BEGINNING BALANCES ON REPORT 18.
B28: ** This amount should be included in the beginning balance column on the LS-Lease Liability and LS-Check Figures Tabs.
A31: Record New Leases (new leases only)
A32: 1 | B32: Record lease contract commencement (fund-based entries only)
B33: Dr: Acct 0842 - CAPITAL OUTLAY
C34: Cr: Acct 0789 - LEASE AND OTHER FINANCING PROCEEDS
C35: =IF($F$7="Proprietary","Cr: Acct 0870 - SERVICES & CHARGES (MG ADJ)",VLOOKUP($F$9,'Drop Down Menus'!$F$2:$G$10,2,FALSE)) -> Cr: Acct 0808 - GENERAL GOV. (GAAP ADJ)
J36: =SUM(J33:J35) -> 0 | K36: =SUM(K33:K35) -> 0 | L36: =IF(J36=K36,"<- Debits and Credits equal each other.","<- Debits and Credits do not equal each other.") -> <- Debits and Credits equal each other.
A38: 2 | B38: Record leased assets.
A39: *Rpt 18 | B39: Dr: Acct 0476 - RIGHT-TO-USE LEASED LAND - AMORTIZABLE
A40: *Rpt 18 | B40: Dr: Acct 0478 - RIGHT-TO-USE LEASED EQUIPMENT - AMORTIZABLE
A41: *Rpt 18 | B41: Dr: Acct 0477 - RIGHT-TO-USE LEASED BUILDINGS - AMORTIZABLE
C42: Cr: Acct 0842 - CAPITAL OUTLAY
B43: * THESE AMOUNTS SHOULD BE INCLUDED AS "ADDITIONS" ON REPORT 18. | J43: =SUM(J39:J42) -> 0 | K43: =SUM(K39:K42) -> 0 | L43: =IF(J43=K43,"<- Debits and Credits equal each other.","<- Debits and Credits do not equal each other.") -> <- Debits and Credits equal each other.
A46: 3 | B46: Replace proceeds from leases with right-to-use lease liability.
B47: Dr: Acct 0789 - LEASE AND OTHER FINANCING PROCEEDS
A48: **LS LL/CF | C48: Cr: Acct 0691 - RIGHT-TO-USE LEASE LIABILITY
J49: =SUM(J47:J48) -> 0 | K49: =SUM(K47:K48) -> 0 | L49: =IF(J49=K49,"<- Debits and Credits equal each other.","<- Debits and Credits do not equal each other.") -> <- Debits and Credits equal each other.
B50: ** This amount should be included in the additions column on the LS-Lease Liability and LS-Check Figures Tabs.
A53: Record Annual Activity (all leases)
A54: 4 | B54: Record amortization of the leased assets for the year.
B55: Dr: Acct 0875 - DEPRECIATION/AMORTIZATION | J55: 930258
C56: Cr: Acct 0485 - ACCUMULATED AMORTIZATION - RIGHT-TO-USE LEASED LAND | K56: 0
C57: Cr: Acct 0479 - ACCUMULATED AMORTIZATION - RIGHT-TO-USE LEASED EQUIPMENT | K57: 11320
C58: Cr: Acct 0486 - ACCUMULATED AMORTIZATION - RIGHT-TO-USE LEASED BUILDINGS | K58: 918938
J59: =SUM(J55:J58) -> 930258 | K59: =SUM(K55:K58) -> 930258 | L59: =IF(J59=K59,"<- Debits and Credits equal each other.","<- Debits and Credits do not equal each other.") -> <- Debits and Credits equal each other.
A61: 5 | B61: Reclassify rents and leases exp. to lease contract principal and interest exp.
B62: Dr: Acct 0848 - DEBT SERVICE - PRINCIPAL LEASES | J62: 925344 | L62: =IF($J$62=$K$69,"","<- Accts 0848 must agree")
B63: =IF($F$7="Governmental","Dr: Acct 0851 - DEBT SERVICE - INTEREST LEASES","Dr: Acct 0894 - INTEREST EXPENSE AND FISCAL CHARGES") -> Dr: Acct 0851 - DEBT SERVICE - INTEREST LEASES | J63: 22874
C64: =IF($F$7="Proprietary","Cr: Acct 0870 - SERVICES & CHARGES (MG ADJ)",VLOOKUP($F$9,'Drop Down Menus'!$F$2:$G$10,2,FALSE)) -> Cr: Acct 0808 - GENERAL GOV. (GAAP ADJ) | K64: 948218
J65: =SUM(J62:J64) -> 948218 | K65: =SUM(K62:K64) -> 948218 | L65: =IF(J65=K65,"<- Debits and Credits equal each other.","<- Debits and Credits do not equal each other.") -> <- Debits and Credits equal each other.
A67: 6 | B67: Reduce lease contracts liability for total current year principal payments.
A68: **LS LL/CF | B68: Dr: Acct 0691 - RIGHT-TO-USE LEASE LIABILITY | J68: 925344
C69: Cr: Acct 0848 - DEBT SERVICE - PRINCIPAL LEASES | K69: 925344 | L69: =IF($J$62=$K$69,"","<- Accts 0848 must agree")
J70: =SUM(J68:J69) -> 925344 | K70: =SUM(K68:K69) -> 925344 | L70: =IF(J70=K70,"<- Debits and Credits equal each other.","<- Debits and Credits do not equal each other.") -> <- Debits and Credits equal each other.
B71: ** This amount should be included in the deductions column on the LS-Lease Liability and LS-Check Figures Tabs.
A74: 7 | B74: Reclassify the principal amount due in the next FY to the current liability.
A75: **LS LL/CF | B75: Dr: Acct 0691 - RIGHT-TO-USE LEASE LIABILITY | J75: 862768.4
C76: Cr: Acct 0649 - RIGHT-TO-USE LEASE LIABILITY (CURRENT PORTION LT) | K76: 862768.4
B77: NOTE: This is an annual accrual. It is to be reversed at the start of the next fiscal year. SCO combines the current and non current amount in Entry #0 to reestablish the beginning balances. No action required. | J77: =SUM(J75:J76) -> 862768.4 | K77: =SUM(K75:K76) -> 862768.4 | L77: =IF(J77=K77,"<- Debits and Credits equal each other.","<- Debits and Credits do not equal each other.") -> <- Debits and Credits equal each other.
B80: ** This amount should be included in the due in one year column on the LS-Lease Liability and LS-Check Figures Tabs.
A83: Remove Lease Asset at the End of the Lease Term (only at the end of the lease term)
A84: 8 | B84: Record entry to write off the lease asset and accumulated amortization at the end of the lease term.
B85: Dr: Acct 0485 - ACCUMULATED AMORTIZATION - RIGHT-TO-USE LEASED LAND | J85: 0
B86: Dr: Acct 0479 - ACCUMULATED AMORTIZATION - RIGHT-TO-USE LEASED EQUIPMENT | J86: 0
B87: Dr: Acct 0486 - ACCUMULATED AMORTIZATION - RIGHT-TO-USE LEASED BUILDINGS | J87: 215272.96
A88: *Rpt 18 | C88: Cr: Acct 0476 - RIGHT-TO-USE LEASED LAND - AMORTIZABLE | K88: 0
A89: *Rpt 18 | C89: Cr: Acct 0478 - RIGHT-TO-USE LEASED EQUIPMENT - AMORTIZABLE | K89: 0
A90: *Rpt 18 | C90: Cr: Acct 0477 - RIGHT-TO-USE LEASED BUILDINGS - AMORTIZABLE | K90: 215272.96
B91: * THESE AMOUNTS SHOULD BE INCLUDED AS "DEDUCTIONS" ON REPORT 18. | J91: =SUM(J85:J90) -> 215272.96 | K91: =SUM(K85:K90) -> 215272.96 | L91: =IF(J91=K91,"<- Debits and Credits equal each other.","<- Debits and Credits do not equal each other.") -> <- Debits and Credits equal each other.
A94: Lease Remeasurement and Modifications (only if a significant modification occurred during the fiscal year)
A95: 9 | B95: Record early termination or lease modifications to decrease in the RTU leased asset.
A96: **LS LL/CF | B96: Dr: Acct 0691 - RIGHT-TO-USE LEASE LIABILITY
B97: Dr: Acct 0485 - ACCUMULATED AMORTIZATION - RIGHT-TO-USE LEASED LAND
B98: Dr: Acct 0479 - ACCUMULATED AMORTIZATION - RIGHT-TO-USE LEASED EQUIPMENT
B99: Dr: Acct 0486 - ACCUMULATED AMORTIZATION - RIGHT-TO-USE LEASED BUILDINGS
B100: =IF($F$7="Proprietary","Dr: Acct 0870 - SERVICES & CHARGES (MG ADJ)",VLOOKUP($F$9,'Drop Down Menus'!$F$2:$H$10,3,FALSE)) -> Dr: Acct 0808 - GENERAL GOV. (GAAP ADJ)
A101: *Rpt 18 | C101: Cr: Acct 0476 - RIGHT-TO-USE LEASED LAND - AMORTIZABLE
A102: *Rpt 18 | C102: Cr: Acct 0478 - RIGHT-TO-USE LEASED EQUIPMENT - AMORTIZABLE
A103: *Rpt 18 | C103: Cr: Acct 0477 - RIGHT-TO-USE LEASED BUILDINGS - AMORTIZABLE
C104: =IF($F$7="Proprietary","Dr: Acct 0870 - SERVICES & CHARGES (MG ADJ)",VLOOKUP($F$9,'Drop Down Menus'!$F$2:$G$10,2,FALSE)) -> Cr: Acct 0808 - GENERAL GOV. (GAAP ADJ)
B105: * THESE AMOUNTS SHOULD BE INCLUDED AS "DEDUCTIONS" ON REPORT 18. | J105: =SUM(J96:J104) -> 0 | K105: =SUM(K96:K104) -> 0 | L105: =IF(J105=K105,"<- Debits and Credits equal each other.","<- Debits and Credits do not equal each other.") -> <- Debits and Credits equal each other.
B106: ** This amount should be included in the deductions column on the LS-Lease Liability and LS-Check Figures Tabs.
A109: 10 | B109: Record lease modifications to increase in the RTU leased asset.
A110: *Rpt 18 | B110: Dr: Acct 0476 - RIGHT-TO-USE LEASED LAND - AMORTIZABLE | J110: 0
A111: *Rpt 18 | B111: Dr: Acct 0478 - RIGHT-TO-USE LEASED EQUIPMENT - AMORTIZABLE | J111: 0
A112: *Rpt 18 | B112: Dr: Acct 0477 - RIGHT-TO-USE LEASED BUILDINGS - AMORTIZABLE | J112: 360213.84
A113: **LS LL/CF | C113: Cr: Acct 0691 - RIGHT-TO-USE LEASE LIABILITY | K113: 360213.84
B114: * THESE AMOUNTS SHOULD BE INCLUDED AS "ADDITIONS" ON REPORT 18. | J114: =SUM(J110:J113) -> 360213.84 | K114: =SUM(K110:K113) -> 360213.84 | L114: =IF(J114=K114,"<- Debits and Credits equal each other.","<- Debits and Credits do not equal each other.") -> <- Debits and Credits equal each other.
B115: ** This amount should be included in the additions column on the LS-Lease Liability and LS-Check Figures Tabs.
D120: Informational - Ending Balances of Assets and Liabilities
K121: Debit (Credit)
D122: Acct 0476 - RIGHT-TO-USE LEASED LAND - AMORTIZABLE | K122: =J15+J39-K88-K101+J110 -> 0
D123: Acct 0478 - RIGHT-TO-USE LEASED EQUIPMENT - AMORTIZABLE | K123: =J16+J40-K89-K102+J111 -> 56597.33
D124: Acct 0477 - RIGHT-TO-USE LEASED BUILDINGS - AMORTIZABLE | K124: =J17+J41-K90-K103+J112 -> 4997601.3
D125: Acct 0485 - ACCUMULATED AMORTIZATION - RIGHT-TO-USE LEASED LAND | K125: =-K20-K56+J85+J97 -> 0
...

Sheet LS-Fund 0378 Journal Entries
A1: Lessee-Type Contracts Fund-by-Fund Journal Entries Form (to be submitted to the SCO annually—one form per fund)
A2: Manually complete every yellow field in this worksheet—there are no automatically calculated data-entry cells in this worksheet.
A3: Fiscal Year: | F3: 2023–2024
A4: Organization Name: | F4: Department of Justice
A5: Organization Code (4-Digits): | F5: 0820
A6: Fund Number (4-Digits): | F6: 378
A7: Fund Classification: | F7: Governmental
A8: Fund Type: | F8: Governmental Fund
A9: Functional Expense: | F9: =IFERROR(IF(F7="Proprietary","Proprietary Fund",VLOOKUP(F5,qryIndex02a!$A$2:$K$654,4,FALSE)),"Unidentified") -> GENERAL GOVERNMENT
A12: Establish Beginning Balances (existing leases only)
A13: Entry #
A14: 0 | B14: Roll forward prior year right-to-use leases to record opening balances. | M14: Combined Lessee Templates | P14: From SCO BB List | S14: Difference
A15: *Rpt 18 | B15: Dr: Acct 0476 - RIGHT-TO-USE LEASED LAND - AMORTIZABLE | J15: =M15 -> 0 | M15: 0 | P15: 0 | S15: =P15-M15 -> 0 | T15: Report any "Differences" on the Report 18 Differential.
A16: *Rpt 18 | B16: Dr: Acct 0478 - RIGHT-TO-USE LEASED EQUIPMENT - AMORTIZABLE | J16: =M16 -> 0 | M16: 0 | P16: 0 | S16: =P16-M16 -> 0 | T16: Report any "Differences" on the Report 18 Differential.
A17: *Rpt 18 | B17: Dr: Acct 0477 - RIGHT-TO-USE LEASED BUILDINGS - AMORTIZABLE | J17: =M17 -> 2654035.9 | M17: 2654035.9 | P17: 2654036 | S17: =P17-M17 -> 0.060843223 | T17: Report any "Differences" on the Report 18 Differential.
B18: Dr: Acct 0950 - BEGINNING FUND BALANCE | J18: =P18 -> 561 | M18: 26913.548 | P18: =IF(SUM($Q$20:$Q$23)>SUM($P$15:$P$17),SUM($Q$20:$Q$23)-SUM($P$15:$P$17),0) -> 561 | S18: =P18-M18 -> -26352.548 | T18: No action required.
B19: Dr: Acct 0952 - BEGINNING FUND ADJUSTMENT/PRIOR PERIOD ADJUSTMENT | J19: =IF(SUM($K$20:$K$24)>SUM($J$15:$J$18),SUM($K$20:$K$24)-SUM($J$15:$J$18),0) -> 0 | S19: =P19-M19 -> 0 | T19: No action required.
C20: Cr: Acct 0485 - ACCUMULATED AMORTIZATION - RIGHT-TO-USE LEASED LAND | K20: =N20 -> 0 | N20: 0 | Q20: 0 | S20: =Q20-N20 -> 0 | T20: No action required.
C21: Cr: Acct 0479 - ACCUMULATED AMORTIZATION - RIGHT-TO-USE LEASED EQUIPMENT | K21: =N21 -> 0 | N21: 0 | Q21: 0 | S21: =Q21-N21 -> 0 | T21: No action required.
C22: Cr: Acct 0486 - ACCUMULATED AMORTIZATION - RIGHT-TO-USE LEASED BUILDINGS | K22: =N22 -> 1013281.5 | N22: 1013281.5 | Q22: 1013282 | S22: =Q22-N22 -> 0.52044999 | T22: No action required.
A23: **LS LL/CF | C23: Cr: Acct 0691 - RIGHT-TO-USE LEASE LIABILITY | K23: =N23 -> 1641314.8 | N23: 1641314.8 | Q23: 1641315 | S23: =Q23-N23 -> 0.20999757 | T23: No action required.
C24: Cr: Acct 0950 - BEGINNING FUND BALANCE | K24: =Q24 -> 0 | N24: 26353.048 | Q24: =IF(SUM($Q$20:$Q$23)<SUM($P$15:$P$17),-SUM($Q$20:$Q$23)+SUM($P$15:$P$17),0) -> 0 | S24: =Q24-N24 -> -26353.048 | T24: No action required.
C25: Cr: Acct 0952 - BEGINNING FUND ADJUSTMENT/PRIOR PERIOD ADJUSTMENT | K25: =IF(SUM($K$20:$K$24)<SUM($J$15:$J$18),-SUM($K$20:$K$24)+SUM($J$15:$J$18),0) -> 0.66960434 | S25: =Q25-N25 -> 0 | T25: No action required.
J26: =SUM(J15:J25) -> 2654596.9 | K26: =SUM(K15:K25) -> 2654596.9 | L26: =IF(J26=K26,"<- Debits and Credits equal each other.","<- Debits and Credits do not equal each other.") -> <- Debits and Credits equal each other.
B27: * THESE ASSET AMOUNTS SHOULD BE REPORTED AS BEGINNING BALANCES ON REPORT 18.
B28: ** This amount should be included in the beginning balance column on the LS-Lease Liability and LS-Check Figures Tabs.
A31: Record New Leases (new leases only)
A32: 1 | B32: Record lease contract commencement (fund-based entries only)
B33: Dr: Acct 0842 - CAPITAL OUTLAY
C34: Cr: Acct 0789 - LEASE AND OTHER FINANCING PROCEEDS
C35: =IF($F$7="Proprietary","Cr: Acct 0870 - SERVICES & CHARGES (MG ADJ)",VLOOKUP($F$9,'Drop Down Menus'!$F$2:$G$10,2,FALSE)) -> Cr: Acct 0808 - GENERAL GOV. (GAAP ADJ)
J36: =SUM(J33:J35) -> 0 | K36: =SUM(K33:K35) -> 0 | L36: =IF(J36=K36,"<- Debits and Credits equal each other.","<- Debits and Credits do not equal each other.") -> <- Debits and Credits equal each other.
A38: 2 | B38: Record leased assets.
A39: *Rpt 18 | B39: Dr: Acct 0476 - RIGHT-TO-USE LEASED LAND - AMORTIZABLE
A40: *Rpt 18 | B40: Dr: Acct 0478 - RIGHT-TO-USE LEASED EQUIPMENT - AMORTIZABLE
A41: *Rpt 18 | B41: Dr: Acct 0477 - RIGHT-TO-USE LEASED BUILDINGS - AMORTIZABLE
C42: Cr: Acct 0842 - CAPITAL OUTLAY
B43: * THESE AMOUNTS SHOULD BE INCLUDED AS "ADDITIONS" ON REPORT 18. | J43: =SUM(J39:J42) -> 0 | K43: =SUM(K39:K42) -> 0 | L43: =IF(J43=K43,"<- Debits and Credits equal each other.","<- Debits and Credits do not equal each other.") -> <- Debits and Credits equal each other.
A46: 3 | B46: Replace proceeds from leases with right-to-use lease liability.
B47: Dr: Acct 0789 - LEASE AND OTHER FINANCING PROCEEDS
A48: **LS LL/CF | C48: Cr: Acct 0691 - RIGHT-TO-USE LEASE LIABILITY
J49: =SUM(J47:J48) -> 0 | K49: =SUM(K47:K48) -> 0 | L49: =IF(J49=K49,"<- Debits and Credits equal each other.","<- Debits and Credits do not equal each other.") -> <- Debits and Credits equal each other.
B50: ** This amount should be included in the additions column on the LS-Lease Liability and LS-Check Figures Tabs.
A53: Record Annual Activity (all leases)
A54: 4 | B54: Record amortization of the leased assets for the year.
B55: Dr: Acct 0875 - DEPRECIATION/AMORTIZATION | J55: 509752.76
C56: Cr: Acct 0485 - ACCUMULATED AMORTIZATION - RIGHT-TO-USE LEASED LAND | K56: 0
C57: Cr: Acct 0479 - ACCUMULATED AMORTIZATION - RIGHT-TO-USE LEASED EQUIPMENT | K57: 0
C58: Cr: Acct 0486 - ACCUMULATED AMORTIZATION - RIGHT-TO-USE LEASED BUILDINGS | K58: 509752.76
J59: =SUM(J55:J58) -> 509752.76 | K59: =SUM(K55:K58) -> 509752.76 | L59: =IF(J59=K59,"<- Debits and Credits equal each other.","<- Debits and Credits do not equal each other.") -> <- Debits and Credits equal each other.
A61: 5 | B61: Reclassify rents and leases exp. to lease contract principal and interest exp.
B62: Dr: Acct 0848 - DEBT SERVICE - PRINCIPAL LEASES | J62: 518200 | L62: =IF($J$62=$K$69,"","<- Accts 0848 must agree")
B63: =IF($F$7="Governmental","Dr: Acct 0851 - DEBT SERVICE - INTEREST LEASES","Dr: Acct 0894 - INTEREST EXPENSE AND FISCAL CHARGES") -> Dr: Acct 0851 - DEBT SERVICE - INTEREST LEASES | J63: 14849
C64: =IF($F$7="Proprietary","Cr: Acct 0870 - SERVICES & CHARGES (MG ADJ)",VLOOKUP($F$9,'Drop Down Menus'!$F$2:$G$10,2,FALSE)) -> Cr: Acct 0808 - GENERAL GOV. (GAAP ADJ) | K64: 533049
J65: =SUM(J62:J64) -> 533049 | K65: =SUM(K62:K64) -> 533049 | L65: =IF(J65=K65,"<- Debits and Credits equal each other.","<- Debits and Credits do not equal each other.") -> <- Debits and Credits equal each other.
A67: 6 | B67: Reduce lease contracts liability for total current year principal payments.
A68: **LS LL/CF | B68: Dr: Acct 0691 - RIGHT-TO-USE LEASE LIABILITY | J68: 518200
C69: Cr: Acct 0848 - DEBT SERVICE - PRINCIPAL LEASES | K69: 518200 | L69: =IF($J$62=$K$69,"","<- Accts 0848 must agree")
J70: =SUM(J68:J69) -> 518200 | K70: =SUM(K68:K69) -> 518200 | L70: =IF(J70=K70,"<- Debits and Credits equal each other.","<- Debits and Credits do not equal each other.") -> <- Debits and Credits equal each other.
B71: ** This amount should be included in the deductions column on the LS-Lease Liability and LS-Check Figures Tabs.
A74: 7 | B74: Reclassify the principal amount due in the next FY to the current liability.
A75: **LS LL/CF | B75: Dr: Acct 0691 - RIGHT-TO-USE LEASE LIABILITY | J75: 463864.55
C76: Cr: Acct 0649 - RIGHT-TO-USE LEASE LIABILITY (CURRENT PORTION LT) | K76: 463864.55
B77: NOTE: This is an annual accrual. It is to be reversed at the start of the next fiscal year. SCO combines the current and non current amount in Entry #0 to reestablish the beginning balances. No action required. | J77: =SUM(J75:J76) -> 463864.55 | K77: =SUM(K75:K76) -> 463864.55 | L77: =IF(J77=K77,"<- Debits and Credits equal each other.","<- Debits and Credits do not equal each other.") -> <- Debits and Credits equal each other.
B80: ** This amount should be included in the due in one year column on the LS-Lease Liability and LS-Check Figures Tabs.
A83: Remove Lease Asset at the End of the Lease Term (only at the end of the lease term)
A84: 8 | B84: Record entry to write off the lease asset and accumulated amortization at the end of the lease term.
B85: Dr: Acct 0485 - ACCUMULATED AMORTIZATION - RIGHT-TO-USE LEASED LAND
B86: Dr: Acct 0479 - ACCUMULATED AMORTIZATION - RIGHT-TO-USE LEASED EQUIPMENT
B87: Dr: Acct 0486 - ACCUMULATED AMORTIZATION - RIGHT-TO-USE LEASED BUILDINGS
A88: *Rpt 18 | C88: Cr: Acct 0476 - RIGHT-TO-USE LEASED LAND - AMORTIZABLE
A89: *Rpt 18 | C89: Cr: Acct 0478 - RIGHT-TO-USE LEASED EQUIPMENT - AMORTIZABLE
A90: *Rpt 18 | C90: Cr: Acct 0477 - RIGHT-TO-USE LEASED BUILDINGS - AMORTIZABLE
B91: * THESE AMOUNTS SHOULD BE INCLUDED AS "DEDUCTIONS" ON REPORT 18. | J91: =SUM(J85:J90) -> 0 | K91: =SUM(K85:K90) -> 0 | L91: =IF(J91=K91,"<- Debits and Credits equal each other.","<- Debits and Credits do not equal each other.") -> <- Debits and Credits equal each other.
A94: Lease Remeasurement and Modifications (only if a significant modification occurred during the fiscal year)
A95: 9 | B95: Record early termination or lease modifications to decrease in the RTU leased asset.
A96: **LS LL/CF | B96: Dr: Acct 0691 - RIGHT-TO-USE LEASE LIABILITY
B97: Dr: Acct 0485 - ACCUMULATED AMORTIZATION - RIGHT-TO-USE LEASED LAND
B98: Dr: Acct 0479 - ACCUMULATED AMORTIZATION - RIGHT-TO-USE LEASED EQUIPMENT
B99: Dr: Acct 0486 - ACCUMULATED AMORTIZATION - RIGHT-TO-USE LEASED BUILDINGS
B100: =IF($F$7="Proprietary","Dr: Acct 0870 - SERVICES & CHARGES (MG ADJ)",VLOOKUP($F$9,'Drop Down Menus'!$F$2:$H$10,3,FALSE)) -> Dr: Acct 0808 - GENERAL GOV. (GAAP ADJ)
A101: *Rpt 18 | C101: Cr: Acct 0476 - RIGHT-TO-USE LEASED LAND - AMORTIZABLE
A102: *Rpt 18 | C102: Cr: Acct 0478 - RIGHT-TO-USE LEASED EQUIPMENT - AMORTIZABLE
A103: *Rpt 18 | C103: Cr: Acct 0477 - RIGHT-TO-USE LEASED BUILDINGS - AMORTIZABLE
C104: =IF($F$7="Proprietary","Dr: Acct 0870 - SERVICES & CHARGES (MG ADJ)",VLOOKUP($F$9,'Drop Down Menus'!$F$2:$G$10,2,FALSE)) -> Cr: Acct 0808 - GENERAL GOV. (GAAP ADJ)
B105: * THESE AMOUNTS SHOULD BE INCLUDED AS "DEDUCTIONS" ON REPORT 18. | J105: =SUM(J96:J104) -> 0 | K105: =SUM(K96:K104) -> 0 | L105: =IF(J105=K105,"<- Debits and Credits equal each other.","<- Debits and Credits do not equal each other.") -> <- Debits and Credits equal each other.
B106: ** This amount should be included in the deductions column on the LS-Lease Liability and LS-Check Figures Tabs.
A109: 10 | B109: Record lease modifications to increase in the RTU leased asset.
A110: *Rpt 18 | B110: Dr: Acct 0476 - RIGHT-TO-USE LEASED LAND - AMORTIZABLE | J110: 0
A111: *Rpt 18 | B111: Dr: Acct 0478 - RIGHT-TO-USE LEASED EQUIPMENT - AMORTIZABLE | J111: 0
A112: *Rpt 18 | B112: Dr: Acct 0477 - RIGHT-TO-USE LEASED BUILDINGS - AMORTIZABLE | J112: 150603
A113: **LS LL/CF | C113: Cr: Acct 0691 - RIGHT-TO-USE LEASE LIABILITY | K113: 150603
B114: * THESE AMOUNTS SHOULD BE INCLUDED AS "ADDITIONS" ON REPORT 18. | J114: =SUM(J110:J113) -> 150603 | K114: =SUM(K110:K113) -> 150603 | L114: =IF(J114=K114,"<- Debits and Credits equal each other.","<- Debits and Credits do not equal each other.") -> <- Debits and Credits equal each other.
B115: ** This amount should be included in the additions column on the LS-Lease Liability and LS-Check Figures Tabs.
D120: Informational - Ending Balances of Assets and Liabilities
K121: Debit (Credit)
D122: Acct 0476 - RIGHT-TO-USE LEASED LAND - AMORTIZABLE | K122: =J15+J39-K88-K101+J110 -> 0
D123: Acct 0478 - RIGHT-TO-USE LEASED EQUIPMENT - AMORTIZABLE | K123: =J16+J40-K89-K102+J111 -> 0
D124: Acct 0477 - RIGHT-TO-USE LEASED BUILDINGS - AMORTIZABLE | K124: =J17+J41-K90-K103+J112 -> 2804638.9
D125: Acct 0485 - ACCUMULATED AMORTIZATION - RIGHT-TO-USE LEASED LAND | K125: =-K20-K56+J85+J97 -> 0
...

Sheet LS-Fund 0460 Journal Entries
A1: Lessee-Type Contracts Fund-by-Fund Journal Entries Form (to be submitted to the SCO annually—one form per fund)
A2: Manually complete every yellow field in this worksheet—there are no automatically calculated data-entry cells in this worksheet.
A3: Fiscal Year: | F3: 2023–2024
A4: Organization Name: | F4: Department of Justice
A5: Organization Code (4-Digits): | F5: 0820
A6: Fund Number (4-Digits): | F6: 460
A7: Fund Classification: | F7: Governmental
A8: Fund Type: | F8: Governmental Fund
A9: Functional Expense: | F9: =IFERROR(IF(F7="Proprietary","Proprietary Fund",VLOOKUP(F5,qryIndex02a!$A$2:$K$654,4,FALSE)),"Unidentified") -> GENERAL GOVERNMENT
A12: Establish Beginning Balances (existing leases only)
A13: Entry #
A14: 0 | B14: Roll forward prior year right-to-use leases to record opening balances. | M14: Combined Lessee Templates | P14: From SCO BB List | S14: Difference
A15: *Rpt 18 | B15: Dr: Acct 0476 - RIGHT-TO-USE LEASED LAND - AMORTIZABLE | J15: =M15 -> 0 | M15: 0 | P15: 0 | S15: =P15-M15 -> 0 | T15: Report any "Differences" on the Report 18 Differential.
A16: *Rpt 18 | B16: Dr: Acct 0478 - RIGHT-TO-USE LEASED EQUIPMENT - AMORTIZABLE | J16: =M16 -> 93098.479 | M16: 93098.479 | P16: 93098 | S16: =P16-M16 -> -0.478684 | T16: Report any "Differences" on the Report 18 Differential.
A17: *Rpt 18 | B17: Dr: Acct 0477 - RIGHT-TO-USE LEASED BUILDINGS - AMORTIZABLE | J17: =M17 -> 687570.27 | M17: 687570.27 | P17: 687570 | S17: =P17-M17 -> -0.26699823 | T17: Report any "Differences" on the Report 18 Differential.
B18: Dr: Acct 0950 - BEGINNING FUND BALANCE | J18: =P18 -> 0 | M18: 34280.994 | P18: =IF(SUM($Q$20:$Q$23)>SUM($P$15:$P$17),SUM($Q$20:$Q$23)-SUM($P$15:$P$17),0) -> 0 | S18: =P18-M18 -> -34280.994 | T18: No action required.
B19: Dr: Acct 0952 - BEGINNING FUND ADJUSTMENT/PRIOR PERIOD ADJUSTMENT | J19: =IF(SUM($K$20:$K$24)>SUM($J$15:$J$18),SUM($K$20:$K$24)-SUM($J$15:$J$18),0) -> 0 | S19: =P19-M19 -> 0 | T19: No action required.
C20: Cr: Acct 0485 - ACCUMULATED AMORTIZATION - RIGHT-TO-USE LEASED LAND | K20: =N20 -> 0 | N20: 0 | Q20: 0 | S20: =Q20-N20 -> 0 | T20: No action required.
C21: Cr: Acct 0479 - ACCUMULATED AMORTIZATION - RIGHT-TO-USE LEASED EQUIPMENT | K21: =N21 -> 37239.24 | N21: 37239.24 | Q21: 37240 | S21: =Q21-N21 -> 0.7603405 | T21: No action required.
C22: Cr: Acct 0486 - ACCUMULATED AMORTIZATION - RIGHT-TO-USE LEASED BUILDINGS | K22: =N22 -> 208813.98 | N22: 208813.98 | Q22: 208814 | S22: =Q22-N22 -> 0.022490287 | T22: No action required.
A23: **LS LL/CF | C23: Cr: Acct 0691 - RIGHT-TO-USE LEASE LIABILITY | K23: =N23 -> 532293.11 | N23: 532293.11 | Q23: 532293 | S23: =Q23-N23 -> -0.10980036 | T23: No action required.
C24: Cr: Acct 0950 - BEGINNING FUND BALANCE | K24: =Q24 -> 2321 | N24: 36602.945 | Q24: =IF(SUM($Q$20:$Q$23)<SUM($P$15:$P$17),-SUM($Q$20:$Q$23)+SUM($P$15:$P$17),0) -> 2321 | S24: =Q24-N24 -> -34281.945 | T24: No action required.
C25: Cr: Acct 0952 - BEGINNING FUND ADJUSTMENT/PRIOR PERIOD ADJUSTMENT | K25: =IF(SUM($K$20:$K$24)<SUM($J$15:$J$18),-SUM($K$20:$K$24)+SUM($J$15:$J$18),0) -> 1.4187127 | S25: =Q25-N25 -> 0 | T25: No action required.
J26: =SUM(J15:J25) -> 780668.75 | K26: =SUM(K15:K25) -> 780668.75 | L26: =IF(J26=K26,"<- Debits and Credits equal each other.","<- Debits and Credits do not equal each other.") -> <- Debits and Credits equal each other.
B27: * THESE ASSET AMOUNTS SHOULD BE REPORTED AS BEGINNING BALANCES ON REPORT 18.
B28: ** This amount should be included in the beginning balance column on the LS-Lease Liability and LS-Check Figures Tabs.
A31: Record New Leases (new leases only)
A32: 1 | B32: Record lease contract commencement (fund-based entries only)
B33: Dr: Acct 0842 - CAPITAL OUTLAY
C34: Cr: Acct 0789 - LEASE AND OTHER FINANCING PROCEEDS
C35: =IF($F$7="Proprietary","Cr: Acct 0870 - SERVICES & CHARGES (MG ADJ)",VLOOKUP($F$9,'Drop Down Menus'!$F$2:$G$10,2,FALSE)) -> Cr: Acct 0808 - GENERAL GOV. (GAAP ADJ)
J36: =SUM(J33:J35) -> 0 | K36: =SUM(K33:K35) -> 0 | L36: =IF(J36=K36,"<- Debits and Credits equal each other.","<- Debits and Credits do not equal each other.") -> <- Debits and Credits equal each other.
A38: 2 | B38: Record leased assets.
A39: *Rpt 18 | B39: Dr: Acct 0476 - RIGHT-TO-USE LEASED LAND - AMORTIZABLE
A40: *Rpt 18 | B40: Dr: Acct 0478 - RIGHT-TO-USE LEASED EQUIPMENT - AMORTIZABLE
A41: *Rpt 18 | B41: Dr: Acct 0477 - RIGHT-TO-USE LEASED BUILDINGS - AMORTIZABLE
C42: Cr: Acct 0842 - CAPITAL OUTLAY
B43: * THESE AMOUNTS SHOULD BE INCLUDED AS "ADDITIONS" ON REPORT 18. | J43: =SUM(J39:J42) -> 0 | K43: =SUM(K39:K42) -> 0 | L43: =IF(J43=K43,"<- Debits and Credits equal each other.","<- Debits and Credits do not equal each other.") -> <- Debits and Credits equal each other.
A46: 3 | B46: Replace proceeds from leases with right-to-use lease liability.
B47: Dr: Acct 0789 - LEASE AND OTHER FINANCING PROCEEDS
A48: **LS LL/CF | C48: Cr: Acct 0691 - RIGHT-TO-USE LEASE LIABILITY
J49: =SUM(J47:J48) -> 0 | K49: =SUM(K47:K48) -> 0 | L49: =IF(J49=K49,"<- Debits and Credits equal each other.","<- Debits and Credits do not equal each other.") -> <- Debits and Credits equal each other.
B50: ** This amount should be included in the additions column on the LS-Lease Liability and LS-Check Figures Tabs.
A53: Record Annual Activity (all leases)
A54: 4 | B54: Record amortization of the leased assets for the year.
B55: Dr: Acct 0875 - DEPRECIATION/AMORTIZATION | J55: 118469.63
C56: Cr: Acct 0485 - ACCUMULATED AMORTIZATION - RIGHT-TO-USE LEASED LAND | K56: 0
C57: Cr: Acct 0479 - ACCUMULATED AMORTIZATION - RIGHT-TO-USE LEASED EQUIPMENT | K57: 18619.848
C58: Cr: Acct 0486 - ACCUMULATED AMORTIZATION - RIGHT-TO-USE LEASED BUILDINGS | K58: 99849.785
J59: =SUM(J55:J58) -> 118469.63 | K59: =SUM(K55:K58) -> 118469.63 | L59: =IF(J59=K59,"<- Debits and Credits equal each other.","<- Debits and Credits do not equal each other.") -> <- Debits and Credits equal each other.
A61: 5 | B61: Reclassify rents and leases exp. to lease contract principal and interest exp.
B62: Dr: Acct 0848 - DEBT SERVICE - PRINCIPAL LEASES | J62: 120714 | L62: =IF($J$62=$K$69,"","<- Accts 0848 must agree")
B63: =IF($F$7="Governmental","Dr: Acct 0851 - DEBT SERVICE - INTEREST LEASES","Dr: Acct 0894 - INTEREST EXPENSE AND FISCAL CHARGES") -> Dr: Acct 0851 - DEBT SERVICE - INTEREST LEASES | J63: 4762
C64: =IF($F$7="Proprietary","Cr: Acct 0870 - SERVICES & CHARGES (MG ADJ)",VLOOKUP($F$9,'Drop Down Menus'!$F$2:$G$10,2,FALSE)) -> Cr: Acct 0808 - GENERAL GOV. (GAAP ADJ) | K64: 125476
J65: =SUM(J62:J64) -> 125476 | K65: =SUM(K62:K64) -> 125476 | L65: =IF(J65=K65,"<- Debits and Credits equal each other.","<- Debits and Credits do not equal each other.") -> <- Debits and Credits equal each other.
A67: 6 | B67: Reduce lease contracts liability for total current year principal payments.
A68: **LS LL/CF | B68: Dr: Acct 0691 - RIGHT-TO-USE LEASE LIABILITY | J68: 120714
C69: Cr: Acct 0848 - DEBT SERVICE - PRINCIPAL LEASES | K69: 120714 | L69: =IF($J$62=$K$69,"","<- Accts 0848 must agree")
J70: =SUM(J68:J69) -> 120714 | K70: =SUM(K68:K69) -> 120714 | L70: =IF(J70=K70,"<- Debits and Credits equal each other.","<- Debits and Credits do not equal each other.") -> <- Debits and Credits equal each other.
B71: ** This amount should be included in the deductions column on the LS-Lease Liability and LS-Check Figures Tabs.
A74: 7 | B74: Reclassify the principal amount due in the next FY to the current liability.
A75: **LS LL/CF | B75: Dr: Acct 0691 - RIGHT-TO-USE LEASE LIABILITY | J75: 87085.008
C76: Cr: Acct 0649 - RIGHT-TO-USE LEASE LIABILITY (CURRENT PORTION LT) | K76: 87085.008
B77: NOTE: This is an annual accrual. It is to be reversed at the start of the next fiscal year. SCO combines the current and non current amount in Entry #0 to reestablish the beginning balances. No action required. | J77: =SUM(J75:J76) -> 87085.008 | K77: =SUM(K75:K76) -> 87085.008 | L77: =IF(J77=K77,"<- Debits and Credits equal each other.","<- Debits and Credits do not equal each other.") -> <- Debits and Credits equal each other.
B80: ** This amount should be included in the due in one year column on the LS-Lease Liability and LS-Check Figures Tabs.
A83: Remove Lease Asset at the End of the Lease Term (only at the end of the lease term)
A84: 8 | B84: Record entry to write off the lease asset and accumulated amortization at the end of the lease term.
B85: Dr: Acct 0485 - ACCUMULATED AMORTIZATION - RIGHT-TO-USE LEASED LAND | J85: 0
B86: Dr: Acct 0479 - ACCUMULATED AMORTIZATION - RIGHT-TO-USE LEASED EQUIPMENT | J86: 0
B87: Dr: Acct 0486 - ACCUMULATED AMORTIZATION - RIGHT-TO-USE LEASED BUILDINGS | J87: 50129.301
A88: *Rpt 18 | C88: Cr: Acct 0476 - RIGHT-TO-USE LEASED LAND - AMORTIZABLE | K88: 0
A89: *Rpt 18 | C89: Cr: Acct 0478 - RIGHT-TO-USE LEASED EQUIPMENT - AMORTIZABLE | K89: 0
A90: *Rpt 18 | C90: Cr: Acct 0477 - RIGHT-TO-USE LEASED BUILDINGS - AMORTIZABLE | K90: 50129.301
B91: * THESE AMOUNTS SHOULD BE INCLUDED AS "DEDUCTIONS" ON REPORT 18. | J91: =SUM(J85:J90) -> 50129.301 | K91: =SUM(K85:K90) -> 50129.301 | L91: =IF(J91=K91,"<- Debits and Credits equal each other.","<- Debits and Credits do not equal each other.") -> <- Debits and Credits equal each other.
A94: Lease Remeasurement and Modifications (only if a significant modification occurred during the fiscal year)
A95: 9 | B95: Record early termination or lease modifications to decrease in the RTU leased asset.
A96: **LS LL/CF | B96: Dr: Acct 0691 - RIGHT-TO-USE LEASE LIABILITY
B97: Dr: Acct 0485 - ACCUMULATED AMORTIZATION - RIGHT-TO-USE LEASED LAND
B98: Dr: Acct 0479 - ACCUMULATED AMORTIZATION - RIGHT-TO-USE LEASED EQUIPMENT
B99: Dr: Acct 0486 - ACCUMULATED AMORTIZATION - RIGHT-TO-USE LEASED BUILDINGS
B100: =IF($F$7="Proprietary","Dr: Acct 0870 - SERVICES & CHARGES (MG ADJ)",VLOOKUP($F$9,'Drop Down Menus'!$F$2:$H$10,3,FALSE)) -> Dr: Acct 0808 - GENERAL GOV. (GAAP ADJ)
A101: *Rpt 18 | C101: Cr: Acct 0476 - RIGHT-TO-USE LEASED LAND - AMORTIZABLE
A102: *Rpt 18 | C102: Cr: Acct 0478 - RIGHT-TO-USE LEASED EQUIPMENT - AMORTIZABLE
A103: *Rpt 18 | C103: Cr: Acct 0477 - RIGHT-TO-USE LEASED BUILDINGS - AMORTIZABLE
C104: =IF($F$7="Proprietary","Dr: Acct 0870 - SERVICES & CHARGES (MG ADJ)",VLOOKUP($F$9,'Drop Down Menus'!$F$2:$G$10,2,FALSE)) -> Cr: Acct 0808 - GENERAL GOV. (GAAP ADJ)
B105: * THESE AMOUNTS SHOULD BE INCLUDED AS "DEDUCTIONS" ON REPORT 18. | J105: =SUM(J96:J104) -> 0 | K105: =SUM(K96:K104) -> 0 | L105: =IF(J105=K105,"<- Debits and Credits equal each other.","<- Debits and Credits do not equal each other.") -> <- Debits and Credits equal each other.
B106: ** This amount should be included in the deductions column on the LS-Lease Liability and LS-Check Figures Tabs.
A109: 10 | B109: Record lease modifications to increase in the RTU leased asset.
A110: *Rpt 18 | B110: Dr: Acct 0476 - RIGHT-TO-USE LEASED LAND - AMORTIZABLE
A111: *Rpt 18 | B111: Dr: Acct 0478 - RIGHT-TO-USE LEASED EQUIPMENT - AMORTIZABLE
A112: *Rpt 18 | B112: Dr: Acct 0477 - RIGHT-TO-USE LEASED BUILDINGS - AMORTIZABLE
A113: **LS LL/CF | C113: Cr: Acct 0691 - RIGHT-TO-USE LEASE LIABILITY
B114: * THESE AMOUNTS SHOULD BE INCLUDED AS "ADDITIONS" ON REPORT 18. | J114: =SUM(J110:J113) -> 0 | K114: =SUM(K110:K113) -> 0 | L114: =IF(J114=K114,"<- Debits and Credits equal each other.","<- Debits and Credits do not equal each other.") -> <- Debits and Credits equal each other.
B115: ** This amount should be included in the additions column on the LS-Lease Liability and LS-Check Figures Tabs.
D120: Informational - Ending Balances of Assets and Liabilities
K121: Debit (Credit)
D122: Acct 0476 - RIGHT-TO-USE LEASED LAND - AMORTIZABLE | K122: =J15+J39-K88-K101+J110 -> 0
D123: Acct 0478 - RIGHT-TO-USE LEASED EQUIPMENT - AMORTIZABLE | K123: =J16+J40-K89-K102+J111 -> 93098.479
D124: Acct 0477 - RIGHT-TO-USE LEASED BUILDINGS - AMORTIZABLE | K124: =J17+J41-K90-K103+J112 -> 637440.97
D125: Acct 0485 - ACCUMULATED AMORTIZATION - RIGHT-TO-USE LEASED LAND | K125: =-K20-K56+J85+J97 -> 0
...

Sheet LS-Fund 0566 Journal Entries
A1: Lessee-Type Contracts Fund-by-Fund Journal Entries Form (to be submitted to the SCO annually—one form per fund)
A2: Manually complete every yellow field in this worksheet—there are no automatically calculated data-entry cells in this worksheet.
A3: Fiscal Year: | F3: 2023–2024
A4: Organization Name: | F4: Department of Justice
A5: Organization Code (4-Digits): | F5: 0820
A6: Fund Number (4-Digits): | F6: 566
A7: Fund Classification: | F7: Governmental
A8: Fund Type: | F8: Governmental Fund
A9: Functional Expense: | F9: =IFERROR(IF(F7="Proprietary","Proprietary Fund",VLOOKUP(F5,qryIndex02a!$A$2:$K$654,4,FALSE)),"Unidentified") -> GENERAL GOVERNMENT
A12: Establish Beginning Balances (existing leases only)
A13: Entry #
A14: 0 | B14: Roll forward prior year right-to-use leases to record opening balances. | M14: Combined Lessee Templates | P14: From SCO BB List | S14: Difference
A15: *Rpt 18 | B15: Dr: Acct 0476 - RIGHT-TO-USE LEASED LAND - AMORTIZABLE | J15: =M15 -> 0 | M15: 0 | P15: 0 | S15: =P15-M15 -> 0 | T15: Report any "Differences" on the Report 18 Differential.
A16: *Rpt 18 | B16: Dr: Acct 0478 - RIGHT-TO-USE LEASED EQUIPMENT - AMORTIZABLE | J16: =M16 -> 0 | M16: 0 | P16: 0 | S16: =P16-M16 -> 0 | T16: Report any "Differences" on the Report 18 Differential.
A17: *Rpt 18 | B17: Dr: Acct 0477 - RIGHT-TO-USE LEASED BUILDINGS - AMORTIZABLE | J17: =M17 -> 27746.354 | M17: 27746.354 | P17: 27746 | S17: =P17-M17 -> -0.35405015 | T17: Report any "Differences" on the Report 18 Differential.
B18: Dr: Acct 0950 - BEGINNING FUND BALANCE | J18: =P18 -> 736 | M18: 735.50889 | P18: =IF(SUM($Q$20:$Q$23)>SUM($P$15:$P$17),SUM($Q$20:$Q$23)-SUM($P$15:$P$17),0) -> 736 | S18: =P18-M18 -> 0.49110839 | T18: No action required.
B19: Dr: Acct 0952 - BEGINNING FUND ADJUSTMENT/PRIOR PERIOD ADJUSTMENT | J19: =IF(SUM($K$20:$K$24)>SUM($J$15:$J$18),SUM($K$20:$K$24)-SUM($J$15:$J$18),0) -> 0 | S19: =P19-M19 -> 0 | T19: No action required.
C20: Cr: Acct 0485 - ACCUMULATED AMORTIZATION - RIGHT-TO-USE LEASED LAND | K20: =N20 -> 0 | N20: 0 | Q20: 0 | S20: =Q20-N20 -> 0 | T20: No action required.
C21: Cr: Acct 0479 - ACCUMULATED AMORTIZATION - RIGHT-TO-USE LEASED EQUIPMENT | K21: =N21 -> 0 | N21: 0 | Q21: 0 | S21: =Q21-N21 -> 0 | T21: No action required.
C22: Cr: Acct 0486 - ACCUMULATED AMORTIZATION - RIGHT-TO-USE LEASED BUILDINGS | K22: =N22 -> 5525.6394 | N22: 5525.6394 | Q22: 5526 | S22: =Q22-N22 -> 0.36063877 | T22: No action required.
A23: **LS LL/CF | C23: Cr: Acct 0691 - RIGHT-TO-USE LEASE LIABILITY | K23: =N23 -> 22956.223 | N23: 22956.223 | Q23: 22956 | S23: =Q23-N23 -> -0.22267624 | T23: No action required.
C24: Cr: Acct 0950 - BEGINNING FUND BALANCE | K24: =Q24 -> 0 | Q24: =IF(SUM($Q$20:$Q$23)<SUM($P$15:$P$17),-SUM($Q$20:$Q$23)+SUM($P$15:$P$17),0) -> 0 | S24: =Q24-N24 -> 0 | T24: No action required.
C25: Cr: Acct 0952 - BEGINNING FUND ADJUSTMENT/PRIOR PERIOD ADJUSTMENT | K25: =IF(SUM($K$20:$K$24)<SUM($J$15:$J$18),-SUM($K$20:$K$24)+SUM($J$15:$J$18),0) -> 0.49201269 | S25: =Q25-N25 -> 0 | T25: No action required.
J26: =SUM(J15:J25) -> 28482.354 | K26: =SUM(K15:K25) -> 28482.354 | L26: =IF(J26=K26,"<- Debits and Credits equal each other.","<- Debits and Credits do not equal each other.") -> <- Debits and Credits equal each other.
B27: * THESE ASSET AMOUNTS SHOULD BE REPORTED AS BEGINNING BALANCES ON REPORT 18.
B28: ** This amount should be included in the beginning balance column on the LS-Lease Liability and LS-Check Figures Tabs.
A31: Record New Leases (new leases only)
A32: 1 | B32: Record lease contract commencement (fund-based entries only)
B33: Dr: Acct 0842 - CAPITAL OUTLAY
C34: Cr: Acct 0789 - LEASE AND OTHER FINANCING PROCEEDS
C35: =IF($F$7="Proprietary","Cr: Acct 0870 - SERVICES & CHARGES (MG ADJ)",VLOOKUP($F$9,'Drop Down Menus'!$F$2:$G$10,2,FALSE)) -> Cr: Acct 0808 - GENERAL GOV. (GAAP ADJ)
J36: =SUM(J33:J35) -> 0 | K36: =SUM(K33:K35) -> 0 | L36: =IF(J36=K36,"<- Debits and Credits equal each other.","<- Debits and Credits do not equal each other.") -> <- Debits and Credits equal each other.
A38: 2 | B38: Record leased assets.
A39: *Rpt 18 | B39: Dr: Acct 0476 - RIGHT-TO-USE LEASED LAND - AMORTIZABLE
A40: *Rpt 18 | B40: Dr: Acct 0478 - RIGHT-TO-USE LEASED EQUIPMENT - AMORTIZABLE
A41: *Rpt 18 | B41: Dr: Acct 0477 - RIGHT-TO-USE LEASED BUILDINGS - AMORTIZABLE
C42: Cr: Acct 0842 - CAPITAL OUTLAY
B43: * THESE AMOUNTS SHOULD BE INCLUDED AS "ADDITIONS" ON REPORT 18. | J43: =SUM(J39:J42) -> 0 | K43: =SUM(K39:K42) -> 0 | L43: =IF(J43=K43,"<- Debits and Credits equal each other.","<- Debits and Credits do not equal each other.") -> <- Debits and Credits equal each other.
A46: 3 | B46: Replace proceeds from leases with right-to-use lease liability.
B47: Dr: Acct 0789 - LEASE AND OTHER FINANCING PROCEEDS
A48: **LS LL/CF | C48: Cr: Acct 0691 - RIGHT-TO-USE LEASE LIABILITY
J49: =SUM(J47:J48) -> 0 | K49: =SUM(K47:K48) -> 0 | L49: =IF(J49=K49,"<- Debits and Credits equal each other.","<- Debits and Credits do not equal each other.") -> <- Debits and Credits equal each other.
B50: ** This amount should be included in the additions column on the LS-Lease Liability and LS-Check Figures Tabs.
A53: Record Annual Activity (all leases)
A54: 4 | B54: Record amortization of the leased assets for the year.
B55: Dr: Acct 0875 - DEPRECIATION/AMORTIZATION | J55: 2762.8192
C56: Cr: Acct 0485 - ACCUMULATED AMORTIZATION - RIGHT-TO-USE LEASED LAND | K56: 0
C57: Cr: Acct 0479 - ACCUMULATED AMORTIZATION - RIGHT-TO-USE LEASED EQUIPMENT | K57: 0
C58: Cr: Acct 0486 - ACCUMULATED AMORTIZATION - RIGHT-TO-USE LEASED BUILDINGS | K58: 2762.8192
J59: =SUM(J55:J58) -> 2762.8192 | K59: =SUM(K55:K58) -> 2762.8192 | L59: =IF(J59=K59,"<- Debits and Credits equal each other.","<- Debits and Credits do not equal each other.") -> <- Debits and Credits equal each other.
A61: 5 | B61: Reclassify rents and leases exp. to lease contract principal and interest exp.
B62: Dr: Acct 0848 - DEBT SERVICE - PRINCIPAL LEASES | J62: 2521.6822 | L62: =IF($J$62=$K$69,"","<- Accts 0848 must agree")
B63: =IF($F$7="Governmental","Dr: Acct 0851 - DEBT SERVICE - INTEREST LEASES","Dr: Acct 0894 - INTEREST EXPENSE AND FISCAL CHARGES") -> Dr: Acct 0851 - DEBT SERVICE - INTEREST LEASES | J63: 322.53485
C64: =IF($F$7="Proprietary","Cr: Acct 0870 - SERVICES & CHARGES (MG ADJ)",VLOOKUP($F$9,'Drop Down Menus'!$F$2:$G$10,2,FALSE)) -> Cr: Acct 0808 - GENERAL GOV. (GAAP ADJ) | K64: 2844.2171
J65: =SUM(J62:J64) -> 2844.2171 | K65: =SUM(K62:K64) -> 2844.2171 | L65: =IF(J65=K65,"<- Debits and Credits equal each other.","<- Debits and Credits do not equal each other.") -> <- Debits and Credits equal each other.
A67: 6 | B67: Reduce lease contracts liability for total current year principal payments.
A68: **LS LL/CF | B68: Dr: Acct 0691 - RIGHT-TO-USE LEASE LIABILITY | J68: 2521.6822
C69: Cr: Acct 0848 - DEBT SERVICE - PRINCIPAL LEASES | K69: 2521.6822 | L69: =IF($J$62=$K$69,"","<- Accts 0848 must agree")
J70: =SUM(J68:J69) -> 2521.6822 | K70: =SUM(K68:K69) -> 2521.6822 | L70: =IF(J70=K70,"<- Debits and Credits equal each other.","<- Debits and Credits do not equal each other.") -> <- Debits and Credits equal each other.
B71: ** This amount should be included in the deductions column on the LS-Lease Liability and LS-Check Figures Tabs.
A74: 7 | B74: Reclassify the principal amount due in the next FY to the current liability.
A75: **LS LL/CF | B75: Dr: Acct 0691 - RIGHT-TO-USE LEASE LIABILITY | J75: 2610.3299
C76: Cr: Acct 0649 - RIGHT-TO-USE LEASE LIABILITY (CURRENT PORTION LT) | K76: 2610.3299
B77: NOTE: This is an annual accrual. It is to be reversed at the start of the next fiscal year. SCO combines the current and non current amount in Entry #0 to reestablish the beginning balances. No action required. | J77: =SUM(J75:J76) -> 2610.3299 | K77: =SUM(K75:K76) -> 2610.3299 | L77: =IF(J77=K77,"<- Debits and Credits equal each other.","<- Debits and Credits do not equal each other.") -> <- Debits and Credits equal each other.
B80: ** This amount should be included in the due in one year column on the LS-Lease Liability and LS-Check Figures Tabs.
A83: Remove Lease Asset at the End of the Lease Term (only at the end of the lease term)
A84: 8 | B84: Record entry to write off the lease asset and accumulated amortization at the end of the lease term.
B85: Dr: Acct 0485 - ACCUMULATED AMORTIZATION - RIGHT-TO-USE LEASED LAND
B86: Dr: Acct 0479 - ACCUMULATED AMORTIZATION - RIGHT-TO-USE LEASED EQUIPMENT
B87: Dr: Acct 0486 - ACCUMULATED AMORTIZATION - RIGHT-TO-USE LEASED BUILDINGS
A88: *Rpt 18 | C88: Cr: Acct 0476 - RIGHT-TO-USE LEASED LAND - AMORTIZABLE
A89: *Rpt 18 | C89: Cr: Acct 0478 - RIGHT-TO-USE LEASED EQUIPMENT - AMORTIZABLE
A90: *Rpt 18 | C90: Cr: Acct 0477 - RIGHT-TO-USE LEASED BUILDINGS - AMORTIZABLE
B91: * THESE AMOUNTS SHOULD BE INCLUDED AS "DEDUCTIONS" ON REPORT 18. | J91: =SUM(J85:J90) -> 0 | K91: =SUM(K85:K90) -> 0 | L91: =IF(J91=K91,"<- Debits and Credits equal each other.","<- Debits and Credits do not equal each other.") -> <- Debits and Credits equal each other.
A94: Lease Remeasurement and Modifications (only if a significant modification occurred during the fiscal year)
A95: 9 | B95: Record early termination or lease modifications to decrease in the RTU leased asset.
A96: **LS LL/CF | B96: Dr: Acct 0691 - RIGHT-TO-USE LEASE LIABILITY
B97: Dr: Acct 0485 - ACCUMULATED AMORTIZATION - RIGHT-TO-USE LEASED LAND
B98: Dr: Acct 0479 - ACCUMULATED AMORTIZATION - RIGHT-TO-USE LEASED EQUIPMENT
B99: Dr: Acct 0486 - ACCUMULATED AMORTIZATION - RIGHT-TO-USE LEASED BUILDINGS
B100: =IF($F$7="Proprietary","Dr: Acct 0870 - SERVICES & CHARGES (MG ADJ)",VLOOKUP($F$9,'Drop Down Menus'!$F$2:$H$10,3,FALSE)) -> Dr: Acct 0808 - GENERAL GOV. (GAAP ADJ)
A101: *Rpt 18 | C101: Cr: Acct 0476 - RIGHT-TO-USE LEASED LAND - AMORTIZABLE
A102: *Rpt 18 | C102: Cr: Acct 0478 - RIGHT-TO-USE LEASED EQUIPMENT - AMORTIZABLE
A103: *Rpt 18 | C103: Cr: Acct 0477 - RIGHT-TO-USE LEASED BUILDINGS - AMORTIZABLE
C104: =IF($F$7="Proprietary","Dr: Acct 0870 - SERVICES & CHARGES (MG ADJ)",VLOOKUP($F$9,'Drop Down Menus'!$F$2:$G$10,2,FALSE)) -> Cr: Acct 0808 - GENERAL GOV. (GAAP ADJ)
B105: * THESE AMOUNTS SHOULD BE INCLUDED AS "DEDUCTIONS" ON REPORT 18. | J105: =SUM(J96:J104) -> 0 | K105: =SUM(K96:K104) -> 0 | L105: =IF(J105=K105,"<- Debits and Credits equal each other.","<- Debits and Credits do not equal each other.") -> <- Debits and Credits equal each other.
B106: ** This amount should be included in the deductions column on the LS-Lease Liability and LS-Check Figures Tabs.
A109: 10 | B109: Record lease modifications to increase in the RTU leased asset.
A110: *Rpt 18 | B110: Dr: Acct 0476 - RIGHT-TO-USE LEASED LAND - AMORTIZABLE
A111: *Rpt 18 | B111: Dr: Acct 0478 - RIGHT-TO-USE LEASED EQUIPMENT - AMORTIZABLE
A112: *Rpt 18 | B112: Dr: Acct 0477 - RIGHT-TO-USE LEASED BUILDINGS - AMORTIZABLE
A113: **LS LL/CF | C113: Cr: Acct 0691 - RIGHT-TO-USE LEASE LIABILITY
B114: * THESE AMOUNTS SHOULD BE INCLUDED AS "ADDITIONS" ON REPORT 18. | J114: =SUM(J110:J113) -> 0 | K114: =SUM(K110:K113) -> 0 | L114: =IF(J114=K114,"<- Debits and Credits equal each other.","<- Debits and Credits do not equal each other.") -> <- Debits and Credits equal each other.
B115: ** This amount should be included in the additions column on the LS-Lease Liability and LS-Check Figures Tabs.
D120: Informational - Ending Balances of Assets and Liabilities
K121: Debit (Credit)
D122: Acct 0476 - RIGHT-TO-USE LEASED LAND - AMORTIZABLE | K122: =J15+J39-K88-K101+J110 -> 0
D123: Acct 0478 - RIGHT-TO-USE LEASED EQUIPMENT - AMORTIZABLE | K123: =J16+J40-K89-K102+J111 -> 0
D124: Acct 0477 - RIGHT-TO-USE LEASED BUILDINGS - AMORTIZABLE | K124: =J17+J41-K90-K103+J112 -> 27746.354
D125: Acct 0485 - ACCUMULATED AMORTIZATION - RIGHT-TO-USE LEASED LAND | K125: =-K20-K56+J85+J97 -> 0
...

Sheet LS-Fund 0567 Journal Entries
A1: Lessee-Type Contracts Fund-by-Fund Journal Entries Form (to be submitted to the SCO annually—one form per fund)
A2: Manually complete every yellow field in this worksheet—there are no automatically calculated data-entry cells in this worksheet.
A3: Fiscal Year: | F3: 2023–2024
A4: Organization Name: | F4: Department of Justice
A5: Organization Code (4-Digits): | F5: 0820
A6: Fund Number (4-Digits): | F6: 567
A7: Fund Classification: | F7: Governmental
A8: Fund Type: | F8: Governmental Fund
A9: Functional Expense: | F9: =IFERROR(IF(F7="Proprietary","Proprietary Fund",VLOOKUP(F5,[2]qryIndex02a!$A$2:$K$654,4,FALSE)),"Unidentified") -> GENERAL GOVERNMENT
A12: Establish Beginning Balances (existing leases only)
A13: Entry #
A14: 0 | B14: Roll forward prior year right-to-use leases to record opening balances. | M14: Combined Lessee Templates | P14: From SCO BB List | S14: Difference
A15: *Rpt 18 | B15: Dr: Acct 0476 - RIGHT-TO-USE LEASED LAND - AMORTIZABLE | J15: =M15 -> 0 | S15: =P15-M15 -> 0
A16: *Rpt 18 | B16: Dr: Acct 0478 - RIGHT-TO-USE LEASED EQUIPMENT - AMORTIZABLE | J16: =M16 -> 65210 | M16: 65210 | P16: 65210 | S16: =P16-M16 -> 0
A17: *Rpt 18 | B17: Dr: Acct 0477 - RIGHT-TO-USE LEASED BUILDINGS - AMORTIZABLE | J17: =M17 -> 4543472 | M17: 4543472 | P17: 4584022 | S17: =P17-M17 -> 40550
B18: Dr: Acct 0950 - BEGINNING FUND BALANCE | J18: =P18 -> 21684 | M18: 78588 | P18: =IF(SUM($Q$20:$Q$23)>SUM($P$15:$P$17),SUM($Q$20:$Q$23)-SUM($P$15:$P$17),0) -> 21684 | S18: =P18-M18 -> -56904
B19: Dr: Acct 0952 - BEGINNING FUND ADJUSTMENT/PRIOR PERIOD ADJUSTMENT | J19: =IF(SUM($K$20:$K$24)>SUM($J$15:$J$18),SUM($K$20:$K$24)-SUM($J$15:$J$18),0) -> 3423 | S19: =P19-M19 -> 0
C20: Cr: Acct 0485 - ACCUMULATED AMORTIZATION - RIGHT-TO-USE LEASED LAND | K20: =N20 -> 0 | S20: =P20-M20 -> 0
C21: Cr: Acct 0479 - ACCUMULATED AMORTIZATION - RIGHT-TO-USE LEASED EQUIPMENT | K21: =N21 -> 26084 | N21: 26084 | Q21: 26084 | S21: =Q21-N21 -> 0
C22: Cr: Acct 0486 - ACCUMULATED AMORTIZATION - RIGHT-TO-USE LEASED BUILDINGS | K22: =N22 -> 1628392 | N22: 1628392 | Q22: 1632785 | S22: =Q22-N22 -> 4393
A23: **LS LL/CF | C23: Cr: Acct 0691 - RIGHT-TO-USE LEASE LIABILITY | K23: =N23 -> 2979313 | N23: 2979313 | Q23: 3012047 | S23: =Q23-N23 -> 32734
C24: Cr: Acct 0950 - BEGINNING FUND BALANCE | K24: =Q24 -> 0 | N24: 53480 | Q24: =IF(SUM($Q$20:$Q$23)<SUM($P$15:$P$17),-SUM($Q$20:$Q$23)+SUM($P$15:$P$17),0) -> 0 | S24: =Q24-N24 -> -53480
C25: Cr: Acct 0952 - BEGINNING FUND ADJUSTMENT/PRIOR PERIOD ADJUSTMENT | K25: =IF(SUM($K$20:$K$24)<SUM($J$15:$J$18),-SUM($K$20:$K$24)+SUM($J$15:$J$18),0) -> 0 | S25: =Q25-N25 -> 0
J26: =SUM(J15:J25) -> 4633789 | K26: =SUM(K15:K25) -> 4633789 | L26: =IF(J26=K26,"<- Debits and Credits equal each other.","<- Debits and Credits do not equal each other.") -> <- Debits and Credits equal each other.
B27: * THESE ASSET AMOUNTS SHOULD BE REPORTED AS BEGINNING BALANCES ON REPORT 18.
B28: ** This amount should be included in the beginning balance column on the LS-Lease Liability and LS-Check Figures Tabs.
A31: Record New Leases (new leases only)
A32: 1 | B32: Record lease contract commencement (fund-based entries only)
B33: Dr: Acct 0842 - CAPITAL OUTLAY
C34: Cr: Acct 0789 - LEASE AND OTHER FINANCING PROCEEDS
C35: =IF($F$7="Proprietary","Cr: Acct 0870 - SERVICES & CHARGES (MG ADJ)",VLOOKUP($F$9,'[2]Drop Down Menus'!$F$2:$G$10,2,FALSE)) -> Cr: Acct 0808 - GENERAL GOV. (GAAP ADJ)
J36: =SUM(J33:J35) -> 0 | K36: =SUM(K33:K35) -> 0 | L36: =IF(J36=K36,"<- Debits and Credits equal each other.","<- Debits and Credits do not equal each other.") -> <- Debits and Credits equal each other.
A38: 2 | B38: Record leased assets.
A39: *Rpt 18 | B39: Dr: Acct 0476 - RIGHT-TO-USE LEASED LAND - AMORTIZABLE
A40: *Rpt 18 | B40: Dr: Acct 0478 - RIGHT-TO-USE LEASED EQUIPMENT - AMORTIZABLE
A41: *Rpt 18 | B41: Dr: Acct 0477 - RIGHT-TO-USE LEASED BUILDINGS - AMORTIZABLE
C42: Cr: Acct 0842 - CAPITAL OUTLAY
B43: * THESE AMOUNTS SHOULD BE INCLUDED AS "ADDITIONS" ON REPORT 18. | J43: =SUM(J39:J42) -> 0 | K43: =SUM(K39:K42) -> 0 | L43: =IF(J43=K43,"<- Debits and Credits equal each other.","<- Debits and Credits do not equal each other.") -> <- Debits and Credits equal each other.
A46: 3 | B46: Replace proceeds from leases with right-to-use lease liability.
B47: Dr: Acct 0789 - LEASE AND OTHER FINANCING PROCEEDS
A48: **LS LL/CF | C48: Cr: Acct 0691 - RIGHT-TO-USE LEASE LIABILITY
J49: =SUM(J47:J48) -> 0 | K49: =SUM(K47:K48) -> 0 | L49: =IF(J49=K49,"<- Debits and Credits equal each other.","<- Debits and Credits do not equal each other.") -> <- Debits and Credits equal each other.
B50: ** This amount should be included in the additions column on the LS-Lease Liability and LS-Check Figures Tabs.
A53: Record Annual Activity (all leases)
A54: 4 | B54: Record amortization of the leased assets for the year.
B55: Dr: Acct 0875 - DEPRECIATION/AMORTIZATION | J55: 861160
C56: Cr: Acct 0485 - ACCUMULATED AMORTIZATION - RIGHT-TO-USE LEASED LAND
C57: Cr: Acct 0479 - ACCUMULATED AMORTIZATION - RIGHT-TO-USE LEASED EQUIPMENT | K57: 13042
C58: Cr: Acct 0486 - ACCUMULATED AMORTIZATION - RIGHT-TO-USE LEASED BUILDINGS | K58: 848118
J59: =SUM(J55:J58) -> 861160 | K59: =SUM(K55:K58) -> 861160 | L59: =IF(J59=K59,"<- Debits and Credits equal each other.","<- Debits and Credits do not equal each other.") -> <- Debits and Credits equal each other.
A61: 5 | B61: Reclassify rents and leases exp. to lease contract principal and interest exp.
B62: Dr: Acct 0848 - DEBT SERVICE - PRINCIPAL LEASES | J62: 865531
B63: =IF(F7="Governmental","Dr: Acct 0851 - DEBT SERVICE - INTEREST LEASES","Dr: Acct 0894 - INTEREST EXPENSE AND FISCAL CHARGES") -> Dr: Acct 0851 - DEBT SERVICE - INTEREST LEASES | J63: 17107
C64: =IF($F$7="Proprietary","Cr: Acct 0870 - SERVICES & CHARGES (MG ADJ)",VLOOKUP($F$9,'[2]Drop Down Menus'!$F$2:$G$10,2,FALSE)) -> Cr: Acct 0808 - GENERAL GOV. (GAAP ADJ) | K64: 882638
J65: =SUM(J62:J64) -> 882638 | K65: =SUM(K62:K64) -> 882638 | L65: =IF(J65=K65,"<- Debits and Credits equal each other.","<- Debits and Credits do not equal each other.") -> <- Debits and Credits equal each other.
A67: 6 | B67: Reduce lease contracts liability for total current year principal payments.
A68: **LS LL/CF | B68: Dr: Acct 0691 - RIGHT-TO-USE LEASE LIABILITY | J68: 865531
C69: Cr: Acct 0848 - DEBT SERVICE - PRINCIPAL LEASES | K69: 865531
J70: =SUM(J68:J69) -> 865531 | K70: =SUM(K68:K69) -> 865531 | L70: =IF(J70=K70,"<- Debits and Credits equal each other.","<- Debits and Credits do not equal each other.") -> <- Debits and Credits equal each other.
B71: ** This amount should be included in the deductions column on the LS-Lease Liability and LS-Check Figures Tabs.
A74: 7 | B74: Reclassify the principal amount due in the next FY to the current liability.
A75: **LS LL/CF | B75: Dr: Acct 0691 - RIGHT-TO-USE LEASE LIABILITY | J75: 805559
C76: Cr: Acct 0649 - RIGHT-TO-USE LEASE LIABILITY (CURRENT PORTION LT) | K76: 805559
B77: NOTE: This is an annual accrual. It is to be reversed at the start of the next fiscal year. SCO combines the current and non current amount in Entry #0 to reestablish the beginning balances. No action required. | J77: =SUM(J75:J76) -> 805559 | K77: =SUM(K75:K76) -> 805559 | L77: =IF(J77=K77,"<- Debits and Credits equal each other.","<- Debits and Credits do not equal each other.") -> <- Debits and Credits equal each other.
B80: ** This amount should be included in the due in one year column on the LS-Lease Liability and LS-Check Figures Tabs.
A83: Remove Lease Asset at the End of the Lease Term (only at the end of the lease term)
A84: 8 | B84: Record entry to write off the lease asset and accumulated amortization at the end of the lease term.
B85: Dr: Acct 0485 - ACCUMULATED AMORTIZATION - RIGHT-TO-USE LEASED LAND
B86: Dr: Acct 0479 - ACCUMULATED AMORTIZATION - RIGHT-TO-USE LEASED EQUIPMENT
B87: Dr: Acct 0486 - ACCUMULATED AMORTIZATION - RIGHT-TO-USE LEASED BUILDINGS | J87: 175215
A88: *Rpt 18 | C88: Cr: Acct 0476 - RIGHT-TO-USE LEASED LAND - AMORTIZABLE
A89: *Rpt 18 | C89: Cr: Acct 0478 - RIGHT-TO-USE LEASED EQUIPMENT - AMORTIZABLE
A90: *Rpt 18 | C90: Cr: Acct 0477 - RIGHT-TO-USE LEASED BUILDINGS - AMORTIZABLE | K90: 175215
B91: * THESE AMOUNTS SHOULD BE INCLUDED AS "DEDUCTIONS" ON REPORT 18. | J91: =SUM(J85:J90) -> 175215 | K91: =SUM(K85:K90) -> 175215 | L91: =IF(J91=K91,"<- Debits and Credits equal each other.","<- Debits and Credits do not equal each other.") -> <- Debits and Credits equal each other.
A94: Lease Remeasurement and Modifications (only if a significant modification occurred during the fiscal year)
A95: 9 | B95: Record early termination or lease modifications to decrease in the RTU leased asset.
A96: **LS LL/CF | B96: Dr: Acct 0691 - RIGHT-TO-USE LEASE LIABILITY
B97: Dr: Acct 0485 - ACCUMULATED AMORTIZATION - RIGHT-TO-USE LEASED LAND
B98: Dr: Acct 0479 - ACCUMULATED AMORTIZATION - RIGHT-TO-USE LEASED EQUIPMENT
B99: Dr: Acct 0486 - ACCUMULATED AMORTIZATION - RIGHT-TO-USE LEASED BUILDINGS
B100: =IF($F$7="Proprietary","Dr: Acct 0870 - SERVICES & CHARGES (MG ADJ)",VLOOKUP($F$9,'[2]Drop Down Menus'!$F$2:$H$10,3,FALSE)) -> Dr: Acct 0808 - GENERAL GOV. (GAAP ADJ)
A101: *Rpt 18 | C101: Cr: Acct 0476 - RIGHT-TO-USE LEASED LAND - AMORTIZABLE
A102: *Rpt 18 | C102: Cr: Acct 0478 - RIGHT-TO-USE LEASED EQUIPMENT - AMORTIZABLE
A103: *Rpt 18 | C103: Cr: Acct 0477 - RIGHT-TO-USE LEASED BUILDINGS - AMORTIZABLE
C104: =IF($F$7="Proprietary","Dr: Acct 0870 - SERVICES & CHARGES (MG ADJ)",VLOOKUP($F$9,'[2]Drop Down Menus'!$F$2:$G$10,2,FALSE)) -> Cr: Acct 0808 - GENERAL GOV. (GAAP ADJ)
B105: * THESE AMOUNTS SHOULD BE INCLUDED AS "DEDUCTIONS" ON REPORT 18. | J105: =SUM(J96:J104) -> 0 | K105: =SUM(K96:K104) -> 0 | L105: =IF(J105=K105,"<- Debits and Credits equal each other.","<- Debits and Credits do not equal each other.") -> <- Debits and Credits equal each other.
B106: ** This amount should be included in the deductions column on the LS-Lease Liability and LS-Check Figures Tabs.
A109: 10 | B109: Record lease modifications to increase in the RTU leased asset.
A110: *Rpt 18 | B110: Dr: Acct 0476 - RIGHT-TO-USE LEASED LAND - AMORTIZABLE
A111: *Rpt 18 | B111: Dr: Acct 0478 - RIGHT-TO-USE LEASED EQUIPMENT - AMORTIZABLE
A112: *Rpt 18 | B112: Dr: Acct 0477 - RIGHT-TO-USE LEASED BUILDINGS - AMORTIZABLE | J112: 5626
A113: **LS LL/CF | C113: Cr: Acct 0691 - RIGHT-TO-USE LEASE LIABILITY | K113: 5626
B114: * THESE AMOUNTS SHOULD BE INCLUDED AS "ADDITIONS" ON REPORT 18. | J114: =SUM(J110:J113) -> 5626 | K114: =SUM(K110:K113) -> 5626 | L114: =IF(J114=K114,"<- Debits and Credits equal each other.","<- Debits and Credits do not equal each other.") -> <- Debits and Credits equal each other.
B115: ** This amount should be included in the additions column on the LS-Lease Liability and LS-Check Figures Tabs.
D120: Informational - Ending Balances of Assets and Liabilities
K121: Debit (Credit)
D122: Acct 0476 - RIGHT-TO-USE LEASED LAND - AMORTIZABLE | K122: =J15+J39-K88-K101+J110 -> 0
D123: Acct 0478 - RIGHT-TO-USE LEASED EQUIPMENT - AMORTIZABLE | K123: =J16+J40-K89-K102+J111 -> 65210
D124: Acct 0477 - RIGHT-TO-USE LEASED BUILDINGS - AMORTIZABLE | K124: =J17+J41-K90-K103+J112 -> 4373883
D125: Acct 0485 - ACCUMULATED AMORTIZATION - RIGHT-TO-USE LEASED LAND | K125: =-K20-K56+J85+J97 -> 0
...

Sheet LS-Fund 0569 Journal Entries
A1: Lessee-Type Contracts Fund-by-Fund Journal Entries Form (to be submitted to the SCO annually—one form per fund)
A2: Manually complete every yellow field in this worksheet—there are no automatically calculated data-entry cells in this worksheet.
A3: Fiscal Year: | F3: 2023–2024
A4: Organization Name: | F4: Department of Justice
A5: Organization Code (4-Digits): | F5: 0820
A6: Fund Number (4-Digits): | F6: 569
A7: Fund Classification: | F7: Governmental
A8: Fund Type: | F8: Governmental Fund
A9: Functional Expense: | F9: =IFERROR(IF(F7="Proprietary","Proprietary Fund",VLOOKUP(F5,[2]qryIndex02a!$A$2:$K$654,4,FALSE)),"Unidentified") -> GENERAL GOVERNMENT
A12: Establish Beginning Balances (existing leases only)
A13: Entry #
A14: 0 | B14: Roll forward prior year right-to-use leases to record opening balances. | M14: Combined Lessee Templates | P14: From SCO BB List | S14: Difference
A15: *Rpt 18 | B15: Dr: Acct 0476 - RIGHT-TO-USE LEASED LAND - AMORTIZABLE | J15: =M15 -> 0 | S15: =P15-M15 -> 0
A16: *Rpt 18 | B16: Dr: Acct 0478 - RIGHT-TO-USE LEASED EQUIPMENT - AMORTIZABLE | J16: =M16 -> 0 | S16: =P16-M16 -> 0
A17: *Rpt 18 | B17: Dr: Acct 0477 - RIGHT-TO-USE LEASED BUILDINGS - AMORTIZABLE | J17: =M17 -> 223874 | M17: 223874 | P17: 223874 | S17: =P17-M17 -> 0
B18: Dr: Acct 0950 - BEGINNING FUND BALANCE | J18: =P18 -> 522 | M18: 1410 | P18: =IF(SUM($Q$20:$Q$23)>SUM($P$15:$P$17),SUM($Q$20:$Q$23)-SUM($P$15:$P$17),0) -> 522 | S18: =P18-M18 -> -888
B19: Dr: Acct 0952 - BEGINNING FUND ADJUSTMENT/PRIOR PERIOD ADJUSTMENT | J19: =IF(SUM($K$20:$K$24)>SUM($J$15:$J$18),SUM($K$20:$K$24)-SUM($J$15:$J$18),0) -> 0 | S19: =P19-M19 -> 0
C20: Cr: Acct 0485 - ACCUMULATED AMORTIZATION - RIGHT-TO-USE LEASED LAND | K20: =N20 -> 0 | S20: =P20-M20 -> 0
C21: Cr: Acct 0479 - ACCUMULATED AMORTIZATION - RIGHT-TO-USE LEASED EQUIPMENT | K21: =N21 -> 0 | S21: =Q21-N21 -> 0
C22: Cr: Acct 0486 - ACCUMULATED AMORTIZATION - RIGHT-TO-USE LEASED BUILDINGS | K22: =N22 -> 147834 | N22: 147834 | Q22: 147903 | S22: =Q22-N22 -> 69
A23: **LS LL/CF | C23: Cr: Acct 0691 - RIGHT-TO-USE LEASE LIABILITY | K23: =N23 -> 75981 | N23: 75981 | Q23: 76493 | S23: =Q23-N23 -> 512
C24: Cr: Acct 0950 - BEGINNING FUND BALANCE | K24: =Q24 -> 0 | N24: 835 | Q24: =IF(SUM($Q$20:$Q$23)<SUM($P$15:$P$17),-SUM($Q$20:$Q$23)+SUM($P$15:$P$17),0) -> 0 | S24: =Q24-N24 -> -835
C25: Cr: Acct 0952 - BEGINNING FUND ADJUSTMENT/PRIOR PERIOD ADJUSTMENT | K25: =IF(SUM($K$20:$K$24)<SUM($J$15:$J$18),-SUM($K$20:$K$24)+SUM($J$15:$J$18),0) -> 581 | S25: =Q25-N25 -> 0
J26: =SUM(J15:J25) -> 224396 | K26: =SUM(K15:K25) -> 224396 | L26: =IF(J26=K26,"<- Debits and Credits equal each other.","<- Debits and Credits do not equal each other.") -> <- Debits and Credits equal each other.
B27: * THESE ASSET AMOUNTS SHOULD BE REPORTED AS BEGINNING BALANCES ON REPORT 18.
B28: ** This amount should be included in the beginning balance column on the LS-Lease Liability and LS-Check Figures Tabs.
A31: Record New Leases (new leases only)
A32: 1 | B32: Record lease contract commencement (fund-based entries only)
B33: Dr: Acct 0842 - CAPITAL OUTLAY
C34: Cr: Acct 0789 - LEASE AND OTHER FINANCING PROCEEDS
C35: =IF($F$7="Proprietary","Cr: Acct 0870 - SERVICES & CHARGES (MG ADJ)",VLOOKUP($F$9,'[2]Drop Down Menus'!$F$2:$G$10,2,FALSE)) -> Cr: Acct 0808 - GENERAL GOV. (GAAP ADJ)
J36: =SUM(J33:J35) -> 0 | K36: =SUM(K33:K35) -> 0 | L36: =IF(J36=K36,"<- Debits and Credits equal each other.","<- Debits and Credits do not equal each other.") -> <- Debits and Credits equal each other.
A38: 2 | B38: Record leased assets.
A39: *Rpt 18 | B39: Dr: Acct 0476 - RIGHT-TO-USE LEASED LAND - AMORTIZABLE
A40: *Rpt 18 | B40: Dr: Acct 0478 - RIGHT-TO-USE LEASED EQUIPMENT - AMORTIZABLE
A41: *Rpt 18 | B41: Dr: Acct 0477 - RIGHT-TO-USE LEASED BUILDINGS - AMORTIZABLE
C42: Cr: Acct 0842 - CAPITAL OUTLAY
B43: * THESE AMOUNTS SHOULD BE INCLUDED AS "ADDITIONS" ON REPORT 18. | J43: =SUM(J39:J42) -> 0 | K43: =SUM(K39:K42) -> 0 | L43: =IF(J43=K43,"<- Debits and Credits equal each other.","<- Debits and Credits do not equal each other.") -> <- Debits and Credits equal each other.
A46: 3 | B46: Replace proceeds from leases with right-to-use lease liability.
B47: Dr: Acct 0789 - LEASE AND OTHER FINANCING PROCEEDS
A48: **LS LL/CF | C48: Cr: Acct 0691 - RIGHT-TO-USE LEASE LIABILITY
J49: =SUM(J47:J48) -> 0 | K49: =SUM(K47:K48) -> 0 | L49: =IF(J49=K49,"<- Debits and Credits equal each other.","<- Debits and Credits do not equal each other.") -> <- Debits and Credits equal each other.
B50: ** This amount should be included in the additions column on the LS-Lease Liability and LS-Check Figures Tabs.
A53: Record Annual Activity (all leases)
A54: 4 | B54: Record amortization of the leased assets for the year.
B55: Dr: Acct 0875 - DEPRECIATION/AMORTIZATION | J55: 83680
C56: Cr: Acct 0485 - ACCUMULATED AMORTIZATION - RIGHT-TO-USE LEASED LAND
C57: Cr: Acct 0479 - ACCUMULATED AMORTIZATION - RIGHT-TO-USE LEASED EQUIPMENT
C58: Cr: Acct 0486 - ACCUMULATED AMORTIZATION - RIGHT-TO-USE LEASED BUILDINGS | K58: 83680
J59: =SUM(J55:J58) -> 83680 | K59: =SUM(K55:K58) -> 83680 | L59: =IF(J59=K59,"<- Debits and Credits equal each other.","<- Debits and Credits do not equal each other.") -> <- Debits and Credits equal each other.
A61: 5 | B61: Reclassify rents and leases exp. to lease contract principal and interest exp.
B62: Dr: Acct 0848 - DEBT SERVICE - PRINCIPAL LEASES | J62: 69572
B63: =IF(F7="Governmental","Dr: Acct 0851 - DEBT SERVICE - INTEREST LEASES","Dr: Acct 0894 - INTEREST EXPENSE AND FISCAL CHARGES") -> Dr: Acct 0851 - DEBT SERVICE - INTEREST LEASES | J63: 8357
C64: =IF($F$7="Proprietary","Cr: Acct 0870 - SERVICES & CHARGES (MG ADJ)",VLOOKUP($F$9,'[2]Drop Down Menus'!$F$2:$G$10,2,FALSE)) -> Cr: Acct 0808 - GENERAL GOV. (GAAP ADJ) | K64: 77929
J65: =SUM(J62:J64) -> 77929 | K65: =SUM(K62:K64) -> 77929 | L65: =IF(J65=K65,"<- Debits and Credits equal each other.","<- Debits and Credits do not equal each other.") -> <- Debits and Credits equal each other.
A67: 6 | B67: Reduce lease contracts liability for total current year principal payments.
A68: **LS LL/CF | B68: Dr: Acct 0691 - RIGHT-TO-USE LEASE LIABILITY | J68: 69572
C69: Cr: Acct 0848 - DEBT SERVICE - PRINCIPAL LEASES | K69: 69572
J70: =SUM(J68:J69) -> 69572 | K70: =SUM(K68:K69) -> 69572 | L70: =IF(J70=K70,"<- Debits and Credits equal each other.","<- Debits and Credits do not equal each other.") -> <- Debits and Credits equal each other.
B71: ** This amount should be included in the deductions column on the LS-Lease Liability and LS-Check Figures Tabs.
A74: 7 | B74: Reclassify the principal amount due in the next FY to the current liability.
A75: **LS LL/CF | B75: Dr: Acct 0691 - RIGHT-TO-USE LEASE LIABILITY | J75: 78487
C76: Cr: Acct 0649 - RIGHT-TO-USE LEASE LIABILITY (CURRENT PORTION LT) | K76: 78487
B77: NOTE: This is an annual accrual. It is to be reversed at the start of the next fiscal year. SCO combines the current and non current amount in Entry #0 to reestablish the beginning balances. No action required. | J77: =SUM(J75:J76) -> 78487 | K77: =SUM(K75:K76) -> 78487 | L77: =IF(J77=K77,"<- Debits and Credits equal each other.","<- Debits and Credits do not equal each other.") -> <- Debits and Credits equal each other.
B80: ** This amount should be included in the due in one year column on the LS-Lease Liability and LS-Check Figures Tabs.
A83: Remove Lease Asset at the End of the Lease Term (only at the end of the lease term)
A84: 8 | B84: Record entry to write off the lease asset and accumulated amortization at the end of the lease term.
B85: Dr: Acct 0485 - ACCUMULATED AMORTIZATION - RIGHT-TO-USE LEASED LAND
B86: Dr: Acct 0479 - ACCUMULATED AMORTIZATION - RIGHT-TO-USE LEASED EQUIPMENT
B87: Dr: Acct 0486 - ACCUMULATED AMORTIZATION - RIGHT-TO-USE LEASED BUILDINGS | J87: 2651
A88: *Rpt 18 | C88: Cr: Acct 0476 - RIGHT-TO-USE LEASED LAND - AMORTIZABLE
A89: *Rpt 18 | C89: Cr: Acct 0478 - RIGHT-TO-USE LEASED EQUIPMENT - AMORTIZABLE
A90: *Rpt 18 | C90: Cr: Acct 0477 - RIGHT-TO-USE LEASED BUILDINGS - AMORTIZABLE | K90: 2651
B91: * THESE AMOUNTS SHOULD BE INCLUDED AS "DEDUCTIONS" ON REPORT 18. | J91: =SUM(J85:J90) -> 2651 | K91: =SUM(K85:K90) -> 2651 | L91: =IF(J91=K91,"<- Debits and Credits equal each other.","<- Debits and Credits do not equal each other.") -> <- Debits and Credits equal each other.
A94: Lease Remeasurement and Modifications (only if a significant modification occurred during the fiscal year)
A95: 9 | B95: Record early termination or lease modifications to decrease in the RTU leased asset.
A96: **LS LL/CF | B96: Dr: Acct 0691 - RIGHT-TO-USE LEASE LIABILITY
B97: Dr: Acct 0485 - ACCUMULATED AMORTIZATION - RIGHT-TO-USE LEASED LAND
B98: Dr: Acct 0479 - ACCUMULATED AMORTIZATION - RIGHT-TO-USE LEASED EQUIPMENT
B99: Dr: Acct 0486 - ACCUMULATED AMORTIZATION - RIGHT-TO-USE LEASED BUILDINGS
B100: =IF($F$7="Proprietary","Dr: Acct 0870 - SERVICES & CHARGES (MG ADJ)",VLOOKUP($F$9,'[2]Drop Down Menus'!$F$2:$H$10,3,FALSE)) -> Dr: Acct 0808 - GENERAL GOV. (GAAP ADJ)
A101: *Rpt 18 | C101: Cr: Acct 0476 - RIGHT-TO-USE LEASED LAND - AMORTIZABLE
A102: *Rpt 18 | C102: Cr: Acct 0478 - RIGHT-TO-USE LEASED EQUIPMENT - AMORTIZABLE
A103: *Rpt 18 | C103: Cr: Acct 0477 - RIGHT-TO-USE LEASED BUILDINGS - AMORTIZABLE
C104: =IF($F$7="Proprietary","Dr: Acct 0870 - SERVICES & CHARGES (MG ADJ)",VLOOKUP($F$9,'[2]Drop Down Menus'!$F$2:$G$10,2,FALSE)) -> Cr: Acct 0808 - GENERAL GOV. (GAAP ADJ)
B105: * THESE AMOUNTS SHOULD BE INCLUDED AS "DEDUCTIONS" ON REPORT 18. | J105: =SUM(J96:J104) -> 0 | K105: =SUM(K96:K104) -> 0 | L105: =IF(J105=K105,"<- Debits and Credits equal each other.","<- Debits and Credits do not equal each other.") -> <- Debits and Credits equal each other.
B106: ** This amount should be included in the deductions column on the LS-Lease Liability and LS-Check Figures Tabs.
A109: 10 | B109: Record lease modifications to increase in the RTU leased asset.
A110: *Rpt 18 | B110: Dr: Acct 0476 - RIGHT-TO-USE LEASED LAND - AMORTIZABLE
A111: *Rpt 18 | B111: Dr: Acct 0478 - RIGHT-TO-USE LEASED EQUIPMENT - AMORTIZABLE
A112: *Rpt 18 | B112: Dr: Acct 0477 - RIGHT-TO-USE LEASED BUILDINGS - AMORTIZABLE | J112: 679206
A113: **LS LL/CF | C113: Cr: Acct 0691 - RIGHT-TO-USE LEASE LIABILITY | K113: 679206
B114: * THESE AMOUNTS SHOULD BE INCLUDED AS "ADDITIONS" ON REPORT 18. | J114: =SUM(J110:J113) -> 679206 | K114: =SUM(K110:K113) -> 679206 | L114: =IF(J114=K114,"<- Debits and Credits equal each other.","<- Debits and Credits do not equal each other.") -> <- Debits and Credits equal each other.
B115: ** This amount should be included in the additions column on the LS-Lease Liability and LS-Check Figures Tabs.
D120: Informational - Ending Balances of Assets and Liabilities
K121: Debit (Credit)
D122: Acct 0476 - RIGHT-TO-USE LEASED LAND - AMORTIZABLE | K122: =J15+J39-K88-K101+J110 -> 0
D123: Acct 0478 - RIGHT-TO-USE LEASED EQUIPMENT - AMORTIZABLE | K123: =J16+J40-K89-K102+J111 -> 0
D124: Acct 0477 - RIGHT-TO-USE LEASED BUILDINGS - AMORTIZABLE | K124: =J17+J41-K90-K103+J112 -> 900429
D125: Acct 0485 - ACCUMULATED AMORTIZATION - RIGHT-TO-USE LEASED LAND | K125: =-K20-K56+J85+J97 -> 0
...

Sheet LS-Fund 0890 Journal Entries
A1: Lessee-Type Contracts Fund-by-Fund Journal Entries Form (to be submitted to the SCO annually—one form per fund)
A2: Manually complete every yellow field in this worksheet—there are no automatically calculated data-entry cells in this worksheet.
A3: Fiscal Year: | F3: 2023–2024
A4: Organization Name: | F4: Department of Justice
A5: Organization Code (4-Digits): | F5: 0820
A6: Fund Number (4-Digits): | F6: 890
A7: Fund Classification: | F7: Governmental
A8: Fund Type: | F8: Governmental Fund
A9: Functional Expense: | F9: =IFERROR(IF(F7="Proprietary","Proprietary Fund",VLOOKUP(F5,[2]qryIndex02a!$A$2:$K$654,4,FALSE)),"Unidentified") -> GENERAL GOVERNMENT
A12: Establish Beginning Balances (existing leases only)
A13: Entry #
A14: 0 | B14: Roll forward prior year right-to-use leases to record opening balances. | M14: Combined Lessee Templates | P14: From SCO BB List | S14: Difference
A15: *Rpt 18 | B15: Dr: Acct 0476 - RIGHT-TO-USE LEASED LAND - AMORTIZABLE | J15: =M15 -> 0 | S15: =P15-M15 -> 0
A16: *Rpt 18 | B16: Dr: Acct 0478 - RIGHT-TO-USE LEASED EQUIPMENT - AMORTIZABLE | J16: =M16 -> 0 | S16: =P16-M16 -> 0
A17: *Rpt 18 | B17: Dr: Acct 0477 - RIGHT-TO-USE LEASED BUILDINGS - AMORTIZABLE | J17: =M17 -> 12062144 | M17: 12062144 | P17: 12075331 | S17: =P17-M17 -> 13187
B18: Dr: Acct 0950 - BEGINNING FUND BALANCE | J18: =P18 -> 7852 | M18: 125228 | P18: =IF(SUM($Q$20:$Q$23)>SUM($P$15:$P$17),SUM($Q$20:$Q$23)-SUM($P$15:$P$17),0) -> 7852 | S18: =P18-M18 -> -117376
B19: Dr: Acct 0952 - BEGINNING FUND ADJUSTMENT/PRIOR PERIOD ADJUSTMENT | J19: =IF(SUM($K$20:$K$24)>SUM($J$15:$J$18),SUM($K$20:$K$24)-SUM($J$15:$J$18),0) -> 1112 | S19: =P19-M19 -> 0
C20: Cr: Acct 0485 - ACCUMULATED AMORTIZATION - RIGHT-TO-USE LEASED LAND | K20: =N20 -> 0 | S20: =P20-M20 -> 0
C21: Cr: Acct 0479 - ACCUMULATED AMORTIZATION - RIGHT-TO-USE LEASED EQUIPMENT | K21: =N21 -> 0 | S21: =Q21-N21 -> 0
C22: Cr: Acct 0486 - ACCUMULATED AMORTIZATION - RIGHT-TO-USE LEASED BUILDINGS | K22: =N22 -> 4508619 | N22: 4508619 | Q22: 4510048 | S22: =Q22-N22 -> 1429
A23: **LS LL/CF | C23: Cr: Acct 0691 - RIGHT-TO-USE LEASE LIABILITY | K23: =N23 -> 7562489 | N23: 7562489 | Q23: 7573135 | S23: =Q23-N23 -> 10646
C24: Cr: Acct 0950 - BEGINNING FUND BALANCE | K24: =Q24 -> 0 | N24: 116263 | Q24: =IF(SUM($Q$20:$Q$23)<SUM($P$15:$P$17),-SUM($Q$20:$Q$23)+SUM($P$15:$P$17),0) -> 0 | S24: =Q24-N24 -> -116263
C25: Cr: Acct 0952 - BEGINNING FUND ADJUSTMENT/PRIOR PERIOD ADJUSTMENT | K25: =IF(SUM($K$20:$K$24)<SUM($J$15:$J$18),-SUM($K$20:$K$24)+SUM($J$15:$J$18),0) -> 0 | S25: =Q25-N25 -> 0
J26: =SUM(J15:J25) -> 12071108 | K26: =SUM(K15:K25) -> 12071108 | L26: =IF(J26=K26,"<- Debits and Credits equal each other.","<- Debits and Credits do not equal each other.") -> <- Debits and Credits equal each other.
B27: * THESE ASSET AMOUNTS SHOULD BE REPORTED AS BEGINNING BALANCES ON REPORT 18.
B28: ** This amount should be included in the beginning balance column on the LS-Lease Liability and LS-Check Figures Tabs.
A31: Record New Leases (new leases only)
A32: 1 | B32: Record lease contract commencement (fund-based entries only)
B33: Dr: Acct 0842 - CAPITAL OUTLAY
C34: Cr: Acct 0789 - LEASE AND OTHER FINANCING PROCEEDS
C35: =IF($F$7="Proprietary","Cr: Acct 0870 - SERVICES & CHARGES (MG ADJ)",VLOOKUP($F$9,'[2]Drop Down Menus'!$F$2:$G$10,2,FALSE)) -> Cr: Acct 0808 - GENERAL GOV. (GAAP ADJ)
J36: =SUM(J33:J35) -> 0 | K36: =SUM(K33:K35) -> 0 | L36: =IF(J36=K36,"<- Debits and Credits equal each other.","<- Debits and Credits do not equal each other.") -> <- Debits and Credits equal each other.
A38: 2 | B38: Record leased assets.
A39: *Rpt 18 | B39: Dr: Acct 0476 - RIGHT-TO-USE LEASED LAND - AMORTIZABLE
A40: *Rpt 18 | B40: Dr: Acct 0478 - RIGHT-TO-USE LEASED EQUIPMENT - AMORTIZABLE
A41: *Rpt 18 | B41: Dr: Acct 0477 - RIGHT-TO-USE LEASED BUILDINGS - AMORTIZABLE
C42: Cr: Acct 0842 - CAPITAL OUTLAY
B43: * THESE AMOUNTS SHOULD BE INCLUDED AS "ADDITIONS" ON REPORT 18. | J43: =SUM(J39:J42) -> 0 | K43: =SUM(K39:K42) -> 0 | L43: =IF(J43=K43,"<- Debits and Credits equal each other.","<- Debits and Credits do not equal each other.") -> <- Debits and Credits equal each other.
A46: 3 | B46: Replace proceeds from leases with right-to-use lease liability.
B47: Dr: Acct 0789 - LEASE AND OTHER FINANCING PROCEEDS
A48: **LS LL/CF | C48: Cr: Acct 0691 - RIGHT-TO-USE LEASE LIABILITY
J49: =SUM(J47:J48) -> 0 | K49: =SUM(K47:K48) -> 0 | L49: =IF(J49=K49,"<- Debits and Credits equal each other.","<- Debits and Credits do not equal each other.") -> <- Debits and Credits equal each other.
B50: ** This amount should be included in the additions column on the LS-Lease Liability and LS-Check Figures Tabs.
A53: Record Annual Activity (all leases)
A54: 4 | B54: Record amortization of the leased assets for the year.
B55: Dr: Acct 0875 - DEPRECIATION/AMORTIZATION | J55: 2284225
C56: Cr: Acct 0485 - ACCUMULATED AMORTIZATION - RIGHT-TO-USE LEASED LAND
C57: Cr: Acct 0479 - ACCUMULATED AMORTIZATION - RIGHT-TO-USE LEASED EQUIPMENT
C58: Cr: Acct 0486 - ACCUMULATED AMORTIZATION - RIGHT-TO-USE LEASED BUILDINGS | K58: 2284225
J59: =SUM(J55:J58) -> 2284225 | K59: =SUM(K55:K58) -> 2284225 | L59: =IF(J59=K59,"<- Debits and Credits equal each other.","<- Debits and Credits do not equal each other.") -> <- Debits and Credits equal each other.
A61: 5 | B61: Reclassify rents and leases exp. to lease contract principal and interest exp.
B62: Dr: Acct 0848 - DEBT SERVICE - PRINCIPAL LEASES | J62: 2316758
B63: =IF(F7="Governmental","Dr: Acct 0851 - DEBT SERVICE - INTEREST LEASES","Dr: Acct 0894 - INTEREST EXPENSE AND FISCAL CHARGES") -> Dr: Acct 0851 - DEBT SERVICE - INTEREST LEASES | J63: 68275
C64: =IF($F$7="Proprietary","Cr: Acct 0870 - SERVICES & CHARGES (MG ADJ)",VLOOKUP($F$9,'[2]Drop Down Menus'!$F$2:$G$10,2,FALSE)) -> Cr: Acct 0808 - GENERAL GOV. (GAAP ADJ) | K64: 2385033
J65: =SUM(J62:J64) -> 2385033 | K65: =SUM(K62:K64) -> 2385033 | L65: =IF(J65=K65,"<- Debits and Credits equal each other.","<- Debits and Credits do not equal each other.") -> <- Debits and Credits equal each other.
A67: 6 | B67: Reduce lease contracts liability for total current year principal payments.
A68: **LS LL/CF | B68: Dr: Acct 0691 - RIGHT-TO-USE LEASE LIABILITY | J68: 2316758
C69: Cr: Acct 0848 - DEBT SERVICE - PRINCIPAL LEASES | K69: 2316758
J70: =SUM(J68:J69) -> 2316758 | K70: =SUM(K68:K69) -> 2316758 | L70: =IF(J70=K70,"<- Debits and Credits equal each other.","<- Debits and Credits do not equal each other.") -> <- Debits and Credits equal each other.
B71: ** This amount should be included in the deductions column on the LS-Lease Liability and LS-Check Figures Tabs.
A74: 7 | B74: Reclassify the principal amount due in the next FY to the current liability.
A75: **LS LL/CF | B75: Dr: Acct 0691 - RIGHT-TO-USE LEASE LIABILITY | J75: 2078323
C76: Cr: Acct 0649 - RIGHT-TO-USE LEASE LIABILITY (CURRENT PORTION LT) | K76: 2078323
B77: NOTE: This is an annual accrual. It is to be reversed at the start of the next fiscal year. SCO combines the current and non current amount in Entry #0 to reestablish the beginning balances. No action required. | J77: =SUM(J75:J76) -> 2078323 | K77: =SUM(K75:K76) -> 2078323 | L77: =IF(J77=K77,"<- Debits and Credits equal each other.","<- Debits and Credits do not equal each other.") -> <- Debits and Credits equal each other.
B80: ** This amount should be included in the due in one year column on the LS-Lease Liability and LS-Check Figures Tabs.
A83: Remove Lease Asset at the End of the Lease Term (only at the end of the lease term)
A84: 8 | B84: Record entry to write off the lease asset and accumulated amortization at the end of the lease term.
B85: Dr: Acct 0485 - ACCUMULATED AMORTIZATION - RIGHT-TO-USE LEASED LAND
B86: Dr: Acct 0479 - ACCUMULATED AMORTIZATION - RIGHT-TO-USE LEASED EQUIPMENT
B87: Dr: Acct 0486 - ACCUMULATED AMORTIZATION - RIGHT-TO-USE LEASED BUILDINGS
A88: *Rpt 18 | C88: Cr: Acct 0476 - RIGHT-TO-USE LEASED LAND - AMORTIZABLE
A89: *Rpt 18 | C89: Cr: Acct 0478 - RIGHT-TO-USE LEASED EQUIPMENT - AMORTIZABLE
A90: *Rpt 18 | C90: Cr: Acct 0477 - RIGHT-TO-USE LEASED BUILDINGS - AMORTIZABLE
B91: * THESE AMOUNTS SHOULD BE INCLUDED AS "DEDUCTIONS" ON REPORT 18. | J91: =SUM(J85:J90) -> 0 | K91: =SUM(K85:K90) -> 0 | L91: =IF(J91=K91,"<- Debits and Credits equal each other.","<- Debits and Credits do not equal each other.") -> <- Debits and Credits equal each other.
A94: Lease Remeasurement and Modifications (only if a significant modification occurred during the fiscal year)
A95: 9 | B95: Record early termination or lease modifications to decrease in the RTU leased asset.
A96: **LS LL/CF | B96: Dr: Acct 0691 - RIGHT-TO-USE LEASE LIABILITY
B97: Dr: Acct 0485 - ACCUMULATED AMORTIZATION - RIGHT-TO-USE LEASED LAND
B98: Dr: Acct 0479 - ACCUMULATED AMORTIZATION - RIGHT-TO-USE LEASED EQUIPMENT
B99: Dr: Acct 0486 - ACCUMULATED AMORTIZATION - RIGHT-TO-USE LEASED BUILDINGS
B100: =IF($F$7="Proprietary","Dr: Acct 0870 - SERVICES & CHARGES (MG ADJ)",VLOOKUP($F$9,'[2]Drop Down Menus'!$F$2:$H$10,3,FALSE)) -> Dr: Acct 0808 - GENERAL GOV. (GAAP ADJ)
A101: *Rpt 18 | C101: Cr: Acct 0476 - RIGHT-TO-USE LEASED LAND - AMORTIZABLE
A102: *Rpt 18 | C102: Cr: Acct 0478 - RIGHT-TO-USE LEASED EQUIPMENT - AMORTIZABLE
A103: *Rpt 18 | C103: Cr: Acct 0477 - RIGHT-TO-USE LEASED BUILDINGS - AMORTIZABLE
C104: =IF($F$7="Proprietary","Dr: Acct 0870 - SERVICES & CHARGES (MG ADJ)",VLOOKUP($F$9,'[2]Drop Down Menus'!$F$2:$G$10,2,FALSE)) -> Cr: Acct 0808 - GENERAL GOV. (GAAP ADJ)
B105: * THESE AMOUNTS SHOULD BE INCLUDED AS "DEDUCTIONS" ON REPORT 18. | J105: =SUM(J96:J104) -> 0 | K105: =SUM(K96:K104) -> 0 | L105: =IF(J105=K105,"<- Debits and Credits equal each other.","<- Debits and Credits do not equal each other.") -> <- Debits and Credits equal each other.
B106: ** This amount should be included in the deductions column on the LS-Lease Liability and LS-Check Figures Tabs.
A109: 10 | B109: Record lease modifications to increase in the RTU leased asset.
A110: *Rpt 18 | B110: Dr: Acct 0476 - RIGHT-TO-USE LEASED LAND - AMORTIZABLE
A111: *Rpt 18 | B111: Dr: Acct 0478 - RIGHT-TO-USE LEASED EQUIPMENT - AMORTIZABLE
A112: *Rpt 18 | B112: Dr: Acct 0477 - RIGHT-TO-USE LEASED BUILDINGS - AMORTIZABLE | J112: 664425
A113: **LS LL/CF | C113: Cr: Acct 0691 - RIGHT-TO-USE LEASE LIABILITY | K113: 664425
B114: * THESE AMOUNTS SHOULD BE INCLUDED AS "ADDITIONS" ON REPORT 18. | J114: =SUM(J110:J113) -> 664425 | K114: =SUM(K110:K113) -> 664425 | L114: =IF(J114=K114,"<- Debits and Credits equal each other.","<- Debits and Credits do not equal each other.") -> <- Debits and Credits equal each other.
B115: ** This amount should be included in the additions column on the LS-Lease Liability and LS-Check Figures Tabs.
D120: Informational - Ending Balances of Assets and Liabilities
K121: Debit (Credit)
D122: Acct 0476 - RIGHT-TO-USE LEASED LAND - AMORTIZABLE | K122: =J15+J39-K88-K101+J110 -> 0
D123: Acct 0478 - RIGHT-TO-USE LEASED EQUIPMENT - AMORTIZABLE | K123: =J16+J40-K89-K102+J111 -> 0
D124: Acct 0477 - RIGHT-TO-USE LEASED BUILDINGS - AMORTIZABLE | K124: =J17+J41-K90-K103+J112 -> 12726569
D125: Acct 0485 - ACCUMULATED AMORTIZATION - RIGHT-TO-USE LEASED LAND | K125: =-K20-K56+J85+J97 -> 0
...

Sheet LS-Fund 1008 Journal Entries
A1: Lessee-Type Contracts Fund-by-Fund Journal Entries Form (to be submitted to the SCO annually—one form per fund)
A2: Manually complete every yellow field in this worksheet—there are no automatically calculated data-entry cells in this worksheet.
A3: Fiscal Year: | F3: 2023–2024
A4: Organization Name: | F4: Department of Justice
A5: Organization Code (4-Digits): | F5: 0820
A6: Fund Number (4-Digits): | F6: 1008
A7: Fund Classification: | F7: Governmental
A8: Fund Type: | F8: Governmental Fund
A9: Functional Expense: | F9: =IFERROR(IF(F7="Proprietary","Proprietary Fund",VLOOKUP(F5,[2]qryIndex02a!$A$2:$K$654,4,FALSE)),"Unidentified") -> GENERAL GOVERNMENT
A12: Establish Beginning Balances (existing leases only)
A13: Entry #
A14: 0 | B14: Roll forward prior year right-to-use leases to record opening balances. | M14: Combined Lessee Templates | P14: From SCO BB List | S14: Difference
A15: *Rpt 18 | B15: Dr: Acct 0476 - RIGHT-TO-USE LEASED LAND - AMORTIZABLE | J15: =M15 -> 0 | S15: =P15-M15 -> 0
A16: *Rpt 18 | B16: Dr: Acct 0478 - RIGHT-TO-USE LEASED EQUIPMENT - AMORTIZABLE | J16: =M16 -> 0 | S16: =P16-M16 -> 0
A17: *Rpt 18 | B17: Dr: Acct 0477 - RIGHT-TO-USE LEASED BUILDINGS - AMORTIZABLE | J17: =M17 -> 1437205 | M17: 1437205 | P17: 1451723 | S17: =P17-M17 -> 14518
B18: Dr: Acct 0950 - BEGINNING FUND BALANCE | J18: =P18 -> 0 | M18: 8836 | P18: =IF(SUM($Q$20:$Q$23)>SUM($P$15:$P$17),SUM($Q$20:$Q$23)-SUM($P$15:$P$17),0) -> 0 | S18: =P18-M18 -> -8836
B19: Dr: Acct 0952 - BEGINNING FUND ADJUSTMENT/PRIOR PERIOD ADJUSTMENT | J19: =IF(SUM($K$20:$K$24)>SUM($J$15:$J$18),SUM($K$20:$K$24)-SUM($J$15:$J$18),0) -> 1226 | S19: =P19-M19 -> 0
C20: Cr: Acct 0485 - ACCUMULATED AMORTIZATION - RIGHT-TO-USE LEASED LAND | K20: =N20 -> 0 | S20: =P20-M20 -> 0
C21: Cr: Acct 0479 - ACCUMULATED AMORTIZATION - RIGHT-TO-USE LEASED EQUIPMENT | K21: =N21 -> 0 | S21: =Q21-N21 -> 0
C22: Cr: Acct 0486 - ACCUMULATED AMORTIZATION - RIGHT-TO-USE LEASED BUILDINGS | K22: =N22 -> 360202 | N22: 360202 | Q22: 361774 | S22: =Q22-N22 -> 1572
A23: **LS LL/CF | C23: Cr: Acct 0691 - RIGHT-TO-USE LEASE LIABILITY | K23: =N23 -> 997062 | N23: 997062 | Q23: 1008782 | S23: =Q23-N23 -> 11720
C24: Cr: Acct 0950 - BEGINNING FUND BALANCE | K24: =Q24 -> 81167 | N24: 88777 | Q24: =IF(SUM($Q$20:$Q$23)<SUM($P$15:$P$17),-SUM($Q$20:$Q$23)+SUM($P$15:$P$17),0) -> 81167 | S24: =Q24-N24 -> -7610
C25: Cr: Acct 0952 - BEGINNING FUND ADJUSTMENT/PRIOR PERIOD ADJUSTMENT | K25: =IF(SUM($K$20:$K$24)<SUM($J$15:$J$18),-SUM($K$20:$K$24)+SUM($J$15:$J$18),0) -> 0 | S25: =Q25-N25 -> 0
J26: =SUM(J15:J25) -> 1438431 | K26: =SUM(K15:K25) -> 1438431 | L26: =IF(J26=K26,"<- Debits and Credits equal each other.","<- Debits and Credits do not equal each other.") -> <- Debits and Credits equal each other.
B27: * THESE ASSET AMOUNTS SHOULD BE REPORTED AS BEGINNING BALANCES ON REPORT 18.
B28: ** This amount should be included in the beginning balance column on the LS-Lease Liability and LS-Check Figures Tabs.
A31: Record New Leases (new leases only)
A32: 1 | B32: Record lease contract commencement (fund-based entries only)
B33: Dr: Acct 0842 - CAPITAL OUTLAY
C34: Cr: Acct 0789 - LEASE AND OTHER FINANCING PROCEEDS
C35: =IF($F$7="Proprietary","Cr: Acct 0870 - SERVICES & CHARGES (MG ADJ)",VLOOKUP($F$9,'[2]Drop Down Menus'!$F$2:$G$10,2,FALSE)) -> Cr: Acct 0808 - GENERAL GOV. (GAAP ADJ)
J36: =SUM(J33:J35) -> 0 | K36: =SUM(K33:K35) -> 0 | L36: =IF(J36=K36,"<- Debits and Credits equal each other.","<- Debits and Credits do not equal each other.") -> <- Debits and Credits equal each other.
A38: 2 | B38: Record leased assets.
A39: *Rpt 18 | B39: Dr: Acct 0476 - RIGHT-TO-USE LEASED LAND - AMORTIZABLE
A40: *Rpt 18 | B40: Dr: Acct 0478 - RIGHT-TO-USE LEASED EQUIPMENT - AMORTIZABLE
A41: *Rpt 18 | B41: Dr: Acct 0477 - RIGHT-TO-USE LEASED BUILDINGS - AMORTIZABLE
C42: Cr: Acct 0842 - CAPITAL OUTLAY
B43: * THESE AMOUNTS SHOULD BE INCLUDED AS "ADDITIONS" ON REPORT 18. | J43: =SUM(J39:J42) -> 0 | K43: =SUM(K39:K42) -> 0 | L43: =IF(J43=K43,"<- Debits and Credits equal each other.","<- Debits and Credits do not equal each other.") -> <- Debits and Credits equal each other.
A46: 3 | B46: Replace proceeds from leases with right-to-use lease liability.
B47: Dr: Acct 0789 - LEASE AND OTHER FINANCING PROCEEDS
A48: **LS LL/CF | C48: Cr: Acct 0691 - RIGHT-TO-USE LEASE LIABILITY
J49: =SUM(J47:J48) -> 0 | K49: =SUM(K47:K48) -> 0 | L49: =IF(J49=K49,"<- Debits and Credits equal each other.","<- Debits and Credits do not equal each other.") -> <- Debits and Credits equal each other.
B50: ** This amount should be included in the additions column on the LS-Lease Liability and LS-Check Figures Tabs.
A53: Record Annual Activity (all leases)
A54: 4 | B54: Record amortization of the leased assets for the year.
B55: Dr: Acct 0875 - DEPRECIATION/AMORTIZATION | J55: 194300
C56: Cr: Acct 0485 - ACCUMULATED AMORTIZATION - RIGHT-TO-USE LEASED LAND
C57: Cr: Acct 0479 - ACCUMULATED AMORTIZATION - RIGHT-TO-USE LEASED EQUIPMENT
C58: Cr: Acct 0486 - ACCUMULATED AMORTIZATION - RIGHT-TO-USE LEASED BUILDINGS | K58: 194300
J59: =SUM(J55:J58) -> 194300 | K59: =SUM(K55:K58) -> 194300 | L59: =IF(J59=K59,"<- Debits and Credits equal each other.","<- Debits and Credits do not equal each other.") -> <- Debits and Credits equal each other.
A61: 5 | B61: Reclassify rents and leases exp. to lease contract principal and interest exp.
B62: Dr: Acct 0848 - DEBT SERVICE - PRINCIPAL LEASES | J62: 231356
B63: =IF(F7="Governmental","Dr: Acct 0851 - DEBT SERVICE - INTEREST LEASES","Dr: Acct 0894 - INTEREST EXPENSE AND FISCAL CHARGES") -> Dr: Acct 0851 - DEBT SERVICE - INTEREST LEASES | J63: 7610
C64: =IF($F$7="Proprietary","Cr: Acct 0870 - SERVICES & CHARGES (MG ADJ)",VLOOKUP($F$9,'[2]Drop Down Menus'!$F$2:$G$10,2,FALSE)) -> Cr: Acct 0808 - GENERAL GOV. (GAAP ADJ) | K64: 238966
J65: =SUM(J62:J64) -> 238966 | K65: =SUM(K62:K64) -> 238966 | L65: =IF(J65=K65,"<- Debits and Credits equal each other.","<- Debits and Credits do not equal each other.") -> <- Debits and Credits equal each other.
A67: 6 | B67: Reduce lease contracts liability for total current year principal payments.
A68: **LS LL/CF | B68: Dr: Acct 0691 - RIGHT-TO-USE LEASE LIABILITY | J68: 231356
C69: Cr: Acct 0848 - DEBT SERVICE - PRINCIPAL LEASES | K69: 231356
J70: =SUM(J68:J69) -> 231356 | K70: =SUM(K68:K69) -> 231356 | L70: =IF(J70=K70,"<- Debits and Credits equal each other.","<- Debits and Credits do not equal each other.") -> <- Debits and Credits equal each other.
B71: ** This amount should be included in the deductions column on the LS-Lease Liability and LS-Check Figures Tabs.
A74: 7 | B74: Reclassify the principal amount due in the next FY to the current liability.
A75: **LS LL/CF | B75: Dr: Acct 0691 - RIGHT-TO-USE LEASE LIABILITY | J75: 171433
C76: Cr: Acct 0649 - RIGHT-TO-USE LEASE LIABILITY (CURRENT PORTION LT) | K76: 171433
B77: NOTE: This is an annual accrual. It is to be reversed at the start of the next fiscal year. SCO combines the current and non current amount in Entry #0 to reestablish the beginning balances. No action required. | J77: =SUM(J75:J76) -> 171433 | K77: =SUM(K75:K76) -> 171433 | L77: =IF(J77=K77,"<- Debits and Credits equal each other.","<- Debits and Credits do not equal each other.") -> <- Debits and Credits equal each other.
B80: ** This amount should be included in the due in one year column on the LS-Lease Liability and LS-Check Figures Tabs.
A83: Remove Lease Asset at the End of the Lease Term (only at the end of the lease term)
A84: 8 | B84: Record entry to write off the lease asset and accumulated amortization at the end of the lease term.
B85: Dr: Acct 0485 - ACCUMULATED AMORTIZATION - RIGHT-TO-USE LEASED LAND
B86: Dr: Acct 0479 - ACCUMULATED AMORTIZATION - RIGHT-TO-USE LEASED EQUIPMENT
B87: Dr: Acct 0486 - ACCUMULATED AMORTIZATION - RIGHT-TO-USE LEASED BUILDINGS | J87: 39836
A88: *Rpt 18 | C88: Cr: Acct 0476 - RIGHT-TO-USE LEASED LAND - AMORTIZABLE
A89: *Rpt 18 | C89: Cr: Acct 0478 - RIGHT-TO-USE LEASED EQUIPMENT - AMORTIZABLE
A90: *Rpt 18 | C90: Cr: Acct 0477 - RIGHT-TO-USE LEASED BUILDINGS - AMORTIZABLE | K90: 39836
B91: * THESE AMOUNTS SHOULD BE INCLUDED AS "DEDUCTIONS" ON REPORT 18. | J91: =SUM(J85:J90) -> 39836 | K91: =SUM(K85:K90) -> 39836 | L91: =IF(J91=K91,"<- Debits and Credits equal each other.","<- Debits and Credits do not equal each other.") -> <- Debits and Credits equal each other.
A94: Lease Remeasurement and Modifications (only if a significant modification occurred during the fiscal year)
A95: 9 | B95: Record early termination or lease modifications to decrease in the RTU leased asset.
A96: **LS LL/CF | B96: Dr: Acct 0691 - RIGHT-TO-USE LEASE LIABILITY
B97: Dr: Acct 0485 - ACCUMULATED AMORTIZATION - RIGHT-TO-USE LEASED LAND
B98: Dr: Acct 0479 - ACCUMULATED AMORTIZATION - RIGHT-TO-USE LEASED EQUIPMENT
B99: Dr: Acct 0486 - ACCUMULATED AMORTIZATION - RIGHT-TO-USE LEASED BUILDINGS
B100: =IF($F$7="Proprietary","Dr: Acct 0870 - SERVICES & CHARGES (MG ADJ)",VLOOKUP($F$9,'[2]Drop Down Menus'!$F$2:$H$10,3,FALSE)) -> Dr: Acct 0808 - GENERAL GOV. (GAAP ADJ)
A101: *Rpt 18 | C101: Cr: Acct 0476 - RIGHT-TO-USE LEASED LAND - AMORTIZABLE
A102: *Rpt 18 | C102: Cr: Acct 0478 - RIGHT-TO-USE LEASED EQUIPMENT - AMORTIZABLE
A103: *Rpt 18 | C103: Cr: Acct 0477 - RIGHT-TO-USE LEASED BUILDINGS - AMORTIZABLE
C104: =IF($F$7="Proprietary","Dr: Acct 0870 - SERVICES & CHARGES (MG ADJ)",VLOOKUP($F$9,'[2]Drop Down Menus'!$F$2:$G$10,2,FALSE)) -> Cr: Acct 0808 - GENERAL GOV. (GAAP ADJ)
B105: * THESE AMOUNTS SHOULD BE INCLUDED AS "DEDUCTIONS" ON REPORT 18. | J105: =SUM(J96:J104) -> 0 | K105: =SUM(K96:K104) -> 0 | L105: =IF(J105=K105,"<- Debits and Credits equal each other.","<- Debits and Credits do not equal each other.") -> <- Debits and Credits equal each other.
B106: ** This amount should be included in the deductions column on the LS-Lease Liability and LS-Check Figures Tabs.
A109: 10 | B109: Record lease modifications to increase in the RTU leased asset.
A110: *Rpt 18 | B110: Dr: Acct 0476 - RIGHT-TO-USE LEASED LAND - AMORTIZABLE
A111: *Rpt 18 | B111: Dr: Acct 0478 - RIGHT-TO-USE LEASED EQUIPMENT - AMORTIZABLE
A112: *Rpt 18 | B112: Dr: Acct 0477 - RIGHT-TO-USE LEASED BUILDINGS - AMORTIZABLE
A113: **LS LL/CF | C113: Cr: Acct 0691 - RIGHT-TO-USE LEASE LIABILITY
B114: * THESE AMOUNTS SHOULD BE INCLUDED AS "ADDITIONS" ON REPORT 18. | J114: =SUM(J110:J113) -> 0 | K114: =SUM(K110:K113) -> 0 | L114: =IF(J114=K114,"<- Debits and Credits equal each other.","<- Debits and Credits do not equal each other.") -> <- Debits and Credits equal each other.
B115: ** This amount should be included in the additions column on the LS-Lease Liability and LS-Check Figures Tabs.
D120: Informational - Ending Balances of Assets and Liabilities
K121: Debit (Credit)
D122: Acct 0476 - RIGHT-TO-USE LEASED LAND - AMORTIZABLE | K122: =J15+J39-K88-K101+J110 -> 0
D123: Acct 0478 - RIGHT-TO-USE LEASED EQUIPMENT - AMORTIZABLE | K123: =J16+J40-K89-K102+J111 -> 0
D124: Acct 0477 - RIGHT-TO-USE LEASED BUILDINGS - AMORTIZABLE | K124: =J17+J41-K90-K103+J112 -> 1397369
D125: Acct 0485 - ACCUMULATED AMORTIZATION - RIGHT-TO-USE LEASED LAND | K125: =-K20-K56+J85+J97 -> 0
...

Sheet LS-Fund 3016 Journal Entries
A1: Lessee-Type Contracts Fund-by-Fund Journal Entries Form (to be submitted to the SCO annually—one form per fund)
A2: Manually complete every yellow field in this worksheet—there are no automatically calculated data-entry cells in this worksheet.
A3: Fiscal Year: | F3: 2023–2024
A4: Organization Name: | F4: Department of Justice
A5: Organization Code (4-Digits): | F5: 0820
A6: Fund Number (4-Digits): | F6: 3016
A7: Fund Classification: | F7: Governmental
A8: Fund Type: | F8: Governmental Fund
A9: Functional Expense: | F9: =IFERROR(IF(F7="Proprietary","Proprietary Fund",VLOOKUP(F5,[3]qryIndex02a!$A$2:$K$654,4,FALSE)),"Unidentified") -> GENERAL GOVERNMENT
A12: Establish Beginning Balances (existing leases only)
A13: Entry #
A14: 0 | B14: Roll forward prior year right-to-use leases to record opening balances. | M14: Combined Lessee Templates | P14: From SCO BB List | S14: Difference
A15: *Rpt 18 | B15: Dr: Acct 0476 - RIGHT-TO-USE LEASED LAND - AMORTIZABLE | J15: =M15 -> 0 | S15: =P15-M15 -> 0
A16: *Rpt 18 | B16: Dr: Acct 0478 - RIGHT-TO-USE LEASED EQUIPMENT - AMORTIZABLE | J16: =M16 -> 0 | S16: =P16-M16 -> 0
A17: *Rpt 18 | B17: Dr: Acct 0477 - RIGHT-TO-USE LEASED BUILDINGS - AMORTIZABLE | J17: =M17 -> 1010026 | M17: 1010026 | P17: 1010026 | S17: =P17-M17 -> 0
B18: Dr: Acct 0950 - BEGINNING FUND BALANCE | J18: =P18 -> 5469 | M18: 5469 | P18: =IF(SUM($Q$20:$Q$23)>SUM($P$15:$P$17),SUM($Q$20:$Q$23)-SUM($P$15:$P$17),0) -> 5469 | S18: =P18-M18 -> 0
B19: Dr: Acct 0952 - BEGINNING FUND ADJUSTMENT/PRIOR PERIOD ADJUSTMENT | J19: =IF(SUM($K$20:$K$24)>SUM($J$15:$J$18),SUM($K$20:$K$24)-SUM($J$15:$J$18),0) -> 0 | S19: =P19-M19 -> 0
C20: Cr: Acct 0485 - ACCUMULATED AMORTIZATION - RIGHT-TO-USE LEASED LAND | K20: =N20 -> 0 | S20: =P20-M20 -> 0
C21: Cr: Acct 0479 - ACCUMULATED AMORTIZATION - RIGHT-TO-USE LEASED EQUIPMENT | K21: =N21 -> 0 | S21: =Q21-N21 -> 0
C22: Cr: Acct 0486 - ACCUMULATED AMORTIZATION - RIGHT-TO-USE LEASED BUILDINGS | K22: =N22 -> 734564 | N22: 734564 | Q22: 734564 | S22: =Q22-N22 -> 0
A23: **LS LL/CF | C23: Cr: Acct 0691 - RIGHT-TO-USE LEASE LIABILITY | K23: =N23 -> 280931 | N23: 280931 | Q23: 280931 | S23: =Q23-N23 -> 0
C24: Cr: Acct 0950 - BEGINNING FUND BALANCE | K24: =Q24 -> 0 | Q24: =IF(SUM($Q$20:$Q$23)<SUM($P$15:$P$17),-SUM($Q$20:$Q$23)+SUM($P$15:$P$17),0) -> 0 | S24: =Q24-N24 -> 0
C25: Cr: Acct 0952 - BEGINNING FUND ADJUSTMENT/PRIOR PERIOD ADJUSTMENT | K25: =IF(SUM($K$20:$K$24)<SUM($J$15:$J$18),-SUM($K$20:$K$24)+SUM($J$15:$J$18),0) -> 0 | S25: =Q25-N25 -> 0
J26: =SUM(J15:J25) -> 1015495 | K26: =SUM(K15:K25) -> 1015495 | L26: =IF(J26=K26,"<- Debits and Credits equal each other.","<- Debits and Credits do not equal each other.") -> <- Debits and Credits equal each other.
B27: * THESE ASSET AMOUNTS SHOULD BE REPORTED AS BEGINNING BALANCES ON REPORT 18.
B28: ** This amount should be included in the beginning balance column on the LS-Lease Liability and LS-Check Figures Tabs.
A31: Record New Leases (new leases only)
A32: 1 | B32: Record lease contract commencement (fund-based entries only)
B33: Dr: Acct 0842 - CAPITAL OUTLAY
C34: Cr: Acct 0789 - LEASE AND OTHER FINANCING PROCEEDS
