Workbook
Name ActuaryCredentialsGASB: [1]DeveloperInfo!$D$19
Name ActuaryNameGASB: [1]DeveloperInfo!$D$17
Name ActuaryTitleGASB: [1]DeveloperInfo!$D$18
Name AdjCNSDate: [1]DeveloperInfo!$D$33
Name AdjCNSDate1: [1]DeveloperInfo!$E$33
Name AdjCNSDateTempEnable: [1]DeveloperInfo!$F$34
Name AgencyCode: #REF!
Name AgencyCode: #REF!
Name AgencyCode: #REF!
Name AgencyCode: #REF!
Name AgencyCode: #REF!
Name AgencyCode: #REF!
Name AgencyCode: #REF!
Name AgencyCode: #REF!
Name AgencyCode: #REF!
Name AgencyCode: #REF!
Name AgencyCode: #REF!
Name AgencyCode: #REF!
Name AgencyCode: #REF!
Name AgencyCode: #REF!
Name AgencyCode: #REF!
Name AgencyCode: #REF!
Name AgencyCode: #REF!
Name AgencyCode: #REF!
Name AgencyCode: #REF!
Name AgencyCode: #REF!
Name AgencyCode1: #REF!
Name AgencyCode1: #REF!
Name AgencyCode1: #REF!
Name AgencyCode1: #REF!
Name AgencyCode1: #REF!
Name AgencyCode1: #REF!
Name AgencyCode1: #REF!
Name AgencyCode1: #REF!
Name AgencyCode1: #REF!
Name AgencyCode1: #REF!
Name AgencyCode1: #REF!
Name AgencyCode1: #REF!
Name AgencyCode1: #REF!
Name AgencyCode1: #REF!
Name AgencyCode1: #REF!
Name AgencyCode1: #REF!
Name AgencyCode1: #REF!
Name AgencyCode1: #REF!
Name AgencyCode1: #REF!
Name AgencyCode1: #REF!
Name AnalystGASB: [1]DeveloperInfo!$D$20
Name Annuity: #REF!
Name Annuity: #REF!
Name Annuity: #REF!
Name Annuity: #REF!
Name Annuity: #REF!
Name Annuity: #REF!
Name Annuity: #REF!
Name Annuity: #REF!
Name Annuity: #REF!
Name Annuity: #REF!
Name Annuity: #REF!
Name Annuity: #REF!
Name Annuity: #REF!

Sheet LS-Version Changes
A1: This sheet details the changes made between version 2 and version 3 of the GASB 87 Lessee Annual Reporting Submission Workbook. Familiarize yourself with the changes in the table below and follow the instructions for updating data from template version 2 to version 3.
A4: Version 2 | B4: Published on SCO website in March 2024 for use for reporting periods 2022-2023 and afterwards.
A5: Version 3 | B5: Published on SCO website in October 2024 for use for reporting periods 2023-2024 and afterwards.
A7: The GASB 87 Annual Reporting Submission Workbook is required to be updated and submitted every year. See below for the summary of changes between versions.
A9: Summary of Changes
A10: Sheet | B10: Feature | C10: Location V2 | D10: Location V3 | E10: Description | F10: Required Action
A11: LS-Fund #### Journal Entries | B11: "Difference" Guidance | C11: N/A | D11: T15-T25 | E11: Wording was added in column T to describe what type of action needs to be taken for the "Differences" in Entry #0. | F11: Clarification only. Follow the guidance in column T.
A12: LS-Fund #### Journal Entries | B12: Highlighted Errors | C12: Multiple | D12: Multiple | E12: Errors such as "Debits and Credits do not equal each other" and "Accts 0848 must agree" will populate in bold and be highlighted to assist with the identification of errors. | F12: Clarification only. Resolve all errors before submitting.
A13: LS-Department Note Disclosure | B13: Reminder - No Decimals. | C13: A11, A42, A73 | D13: A11, A42, A73 | E13: Added additional wording to remind users not to enter decimals into the payment and interest table. | F13: Clarification only. Do not enter decimals.
A14: LS-Department Note Disclosure | B14: Question 4 | C14: D29, D60, D91 | D14: D29, D60, D91 | E14: Removed dropdown menu to allow amounts to be entered in the cells in response to Question 4. | F14: Clarification only.
A15: LS-Lease Liabilities | B15: Reminder - Acct 0691 Only | C15: N/A | D15: B22 | E15: Added additional wording to remind users that the Schedule of Changes in Lease Liabilities is for Account 0691 only, and therefore will differ from the Report 18. | F15: Clarification only.
A16: LS-Lease Liabilities | B16: Linked Values | C16: Multiple | D16: Multiple | E16: Linked values to the LS-Fund #### Journal Entries worksheet. Per line 23, if multiple funds are present in the workbook, the department will need to override the formulas in yellow to capture the activity in all funds. | F16: No action required if the workbook only contains one fund. If the workbook contains multiple funds, override the formulas in yellow.

Sheet LS-Fund 0069 Journal Entries
A1: Lessee-Type Contracts Fund-by-Fund Journal Entries Form (to be submitted to the SCO annually—one form per fund)
A2: Manually complete every yellow field in this worksheet—there are no automatically calculated data-entry cells in this worksheet.
A3: Fiscal Year: | F3: 2023–2024
A4: Organization Name: | F4: Department of Consumer Affairs
A5: Organization Code (4-Digits): | F5: 1111
A6: Fund Number (4-Digits): | F6: 69
A7: Fund Classification: | F7: Governmental
A8: Fund Type: | F8: Governmental Fund
A9: Functional Expense: | F9: =IFERROR(IF(F7="Proprietary","Proprietary Fund",VLOOKUP(F5,[2]qryIndex02a!$A$2:$K$654,4,FALSE)),"Unidentified") -> BUS, CONSUMER SERV, HOUSING
A12: Establish Beginning Balances (existing leases only)
A13: Entry #
A14: 0 | B14: Roll forward prior year right-to-use leases to record opening balances. | M14: Combined Lessee Templates | P14: From SCO BB List | S14: Difference
A15: *Rpt 18 | B15: Dr: Acct 0476 - RIGHT-TO-USE LEASED LAND - AMORTIZABLE | J15: =M15 -> 0 | S15: =P15-M15 -> 0 | T15: Report any "Differences" on the Report 18 Differential.
A16: *Rpt 18 | B16: Dr: Acct 0478 - RIGHT-TO-USE LEASED EQUIPMENT - AMORTIZABLE | J16: =M16 -> 0 | S16: =P16-M16 -> 0 | T16: Report any "Differences" on the Report 18 Differential.
A17: *Rpt 18 | B17: Dr: Acct 0477 - RIGHT-TO-USE LEASED BUILDINGS - AMORTIZABLE | J17: =M17 -> 3651728 | M17: 3651728 | P17: 3651728 | S17: =P17-M17 -> 0 | T17: Report any "Differences" on the Report 18 Differential.
B18: Dr: Acct 0950 - BEGINNING FUND BALANCE | J18: =P18 -> 11814 | M18: 11814 | P18: =IF(SUM($Q$20:$Q$23)>SUM($P$15:$P$17),SUM($Q$20:$Q$23)-SUM($P$15:$P$17),0) -> 11814 | S18: =P18-M18 -> 0 | T18: No action required.
B19: Dr: Acct 0952 - BEGINNING FUND ADJUSTMENT/PRIOR PERIOD ADJUSTMENT | J19: =IF(SUM($K$20:$K$24)>SUM($J$15:$J$18),SUM($K$20:$K$24)-SUM($J$15:$J$18),0) -> 0 | S19: =P19-M19 -> 0 | T19: No action required.
C20: Cr: Acct 0485 - ACCUMULATED AMORTIZATION - RIGHT-TO-USE LEASED LAND | K20: =N20 -> 0 | S20: =Q20-N20 -> 0 | T20: No action required.
C21: Cr: Acct 0479 - ACCUMULATED AMORTIZATION - RIGHT-TO-USE LEASED EQUIPMENT | K21: =N21 -> 0 | S21: =Q21-N21 -> 0 | T21: No action required.
C22: Cr: Acct 0486 - ACCUMULATED AMORTIZATION - RIGHT-TO-USE LEASED BUILDINGS | K22: =N22 -> 3119228 | N22: 3119228 | Q22: 3119228 | S22: =Q22-N22 -> 0 | T22: No action required.
A23: **LS LL/CF | C23: Cr: Acct 0691 - RIGHT-TO-USE LEASE LIABILITY | K23: =N23 -> 544314 | N23: 544314 | Q23: 544314 | S23: =Q23-N23 -> 0 | T23: No action required.
C24: Cr: Acct 0950 - BEGINNING FUND BALANCE | K24: =Q24 -> 0 | Q24: =IF(SUM($Q$20:$Q$23)<SUM($P$15:$P$17),-SUM($Q$20:$Q$23)+SUM($P$15:$P$17),0) -> 0 | S24: =Q24-N24 -> 0 | T24: No action required.
C25: Cr: Acct 0952 - BEGINNING FUND ADJUSTMENT/PRIOR PERIOD ADJUSTMENT | K25: =IF(SUM($K$20:$K$24)<SUM($J$15:$J$18),-SUM($K$20:$K$24)+SUM($J$15:$J$18),0) -> 0 | S25: =Q25-N25 -> 0 | T25: No action required.
J26: =SUM(J15:J25) -> 3663542 | K26: =SUM(K15:K25) -> 3663542 | L26: =IF(J26=K26,"<- Debits and Credits equal each other.","<- Debits and Credits do not equal each other.") -> <- Debits and Credits equal each other.
B27: * THESE ASSET AMOUNTS SHOULD BE REPORTED AS BEGINNING BALANCES ON REPORT 18.
B28: ** This amount should be included in the beginning balance column on the LS-Lease Liability and LS-Check Figures Tabs.
A31: Record New Leases (new leases only)
A32: 1 | B32: Record lease contract commencement (fund-based entries only)
B33: Dr: Acct 0842 - CAPITAL OUTLAY
C34: Cr: Acct 0789 - LEASE AND OTHER FINANCING PROCEEDS
C35: =IF($F$7="Proprietary","Cr: Acct 0870 - SERVICES & CHARGES (MG ADJ)",VLOOKUP($F$9,'[2]Drop Down Menus'!$F$2:$G$10,2,FALSE)) -> Cr: Acct 0825 - BUS, CONSUMER SERV, HOUSING
J36: =SUM(J33:J35) -> 0 | K36: =SUM(K33:K35) -> 0 | L36: =IF(J36=K36,"<- Debits and Credits equal each other.","<- Debits and Credits do not equal each other.") -> <- Debits and Credits equal each other.
A38: 2 | B38: Record leased assets.
A39: *Rpt 18 | B39: Dr: Acct 0476 - RIGHT-TO-USE LEASED LAND - AMORTIZABLE
A40: *Rpt 18 | B40: Dr: Acct 0478 - RIGHT-TO-USE LEASED EQUIPMENT - AMORTIZABLE
A41: *Rpt 18 | B41: Dr: Acct 0477 - RIGHT-TO-USE LEASED BUILDINGS - AMORTIZABLE
C42: Cr: Acct 0842 - CAPITAL OUTLAY
B43: * THESE AMOUNTS SHOULD BE INCLUDED AS "ADDITIONS" ON REPORT 18. | J43: =SUM(J39:J42) -> 0 | K43: =SUM(K39:K42) -> 0 | L43: =IF(J43=K43,"<- Debits and Credits equal each other.","<- Debits and Credits do not equal each other.") -> <- Debits and Credits equal each other.
A46: 3 | B46: Replace proceeds from leases with right-to-use lease liability.
B47: Dr: Acct 0789 - LEASE AND OTHER FINANCING PROCEEDS
A48: **LS LL/CF | C48: Cr: Acct 0691 - RIGHT-TO-USE LEASE LIABILITY
J49: =SUM(J47:J48) -> 0 | K49: =SUM(K47:K48) -> 0 | L49: =IF(J49=K49,"<- Debits and Credits equal each other.","<- Debits and Credits do not equal each other.") -> <- Debits and Credits equal each other.
B50: ** This amount should be included in the additions column on the LS-Lease Liability and LS-Check Figures Tabs.
A53: Record Annual Activity (all leases)
A54: 4 | B54: Record amortization of the leased assets for the year.
B55: Dr: Acct 0875 - DEPRECIATION/AMORTIZATION | J55: 532500
C56: Cr: Acct 0485 - ACCUMULATED AMORTIZATION - RIGHT-TO-USE LEASED LAND
C57: Cr: Acct 0479 - ACCUMULATED AMORTIZATION - RIGHT-TO-USE LEASED EQUIPMENT
C58: Cr: Acct 0486 - ACCUMULATED AMORTIZATION - RIGHT-TO-USE LEASED BUILDINGS | K58: 532500
J59: =SUM(J55:J58) -> 532500 | K59: =SUM(K55:K58) -> 532500 | L59: =IF(J59=K59,"<- Debits and Credits equal each other.","<- Debits and Credits do not equal each other.") -> <- Debits and Credits equal each other.
A61: 5 | B61: Reclassify rents and leases exp. to lease contract principal and interest exp.
B62: Dr: Acct 0848 - DEBT SERVICE - PRINCIPAL LEASES | J62: 544314 | L62: =IF($J$62=$K$69,"","<- Accts 0848 must agree")
B63: =IF(F7="Governmental","Dr: Acct 0851 - DEBT SERVICE - INTEREST LEASES","Dr: Acct 0894 - INTEREST EXPENSE AND FISCAL CHARGES") -> Dr: Acct 0851 - DEBT SERVICE - INTEREST LEASES | J63: 252
C64: =IF($F$7="Proprietary","Cr: Acct 0870 - SERVICES & CHARGES (MG ADJ)",VLOOKUP($F$9,'[2]Drop Down Menus'!$F$2:$G$10,2,FALSE)) -> Cr: Acct 0825 - BUS, CONSUMER SERV, HOUSING | K64: 544566
J65: =SUM(J62:J64) -> 544566 | K65: =SUM(K62:K64) -> 544566 | L65: =IF(J65=K65,"<- Debits and Credits equal each other.","<- Debits and Credits do not equal each other.") -> <- Debits and Credits equal each other.
A67: 6 | B67: Reduce lease contracts liability for total current year principal payments.
A68: **LS LL/CF | B68: Dr: Acct 0691 - RIGHT-TO-USE LEASE LIABILITY | J68: 544314
C69: Cr: Acct 0848 - DEBT SERVICE - PRINCIPAL LEASES | K69: 544314 | L69: =IF($J$62=$K$69,"","<- Accts 0848 must agree")
J70: =SUM(J68:J69) -> 544314 | K70: =SUM(K68:K69) -> 544314 | L70: =IF(J70=K70,"<- Debits and Credits equal each other.","<- Debits and Credits do not equal each other.") -> <- Debits and Credits equal each other.
B71: ** This amount should be included in the deductions column on the LS-Lease Liability and LS-Check Figures Tabs.
A74: 7 | B74: Reclassify the principal amount due in the next FY to the current liability.
A75: **LS LL/CF | B75: Dr: Acct 0691 - RIGHT-TO-USE LEASE LIABILITY
C76: Cr: Acct 0649 - RIGHT-TO-USE LEASE LIABILITY (CURRENT PORTION LT)
B77: NOTE: This is an annual accrual. It is to be reversed at the start of the next fiscal year. SCO combines the current and non current amount in Entry #0 to reestablish the beginning balances. No action required. | J77: =SUM(J75:J76) -> 0 | K77: =SUM(K75:K76) -> 0 | L77: =IF(J77=K77,"<- Debits and Credits equal each other.","<- Debits and Credits do not equal each other.") -> <- Debits and Credits equal each other.
B80: ** This amount should be included in the due in one year column on the LS-Lease Liability and LS-Check Figures Tabs.
A83: Remove Lease Asset at the End of the Lease Term (only at the end of the lease term)
A84: 8 | B84: Record entry to write off the lease asset and accumulated amortization at the end of the lease term.
B85: Dr: Acct 0485 - ACCUMULATED AMORTIZATION - RIGHT-TO-USE LEASED LAND
B86: Dr: Acct 0479 - ACCUMULATED AMORTIZATION - RIGHT-TO-USE LEASED EQUIPMENT
B87: Dr: Acct 0486 - ACCUMULATED AMORTIZATION - RIGHT-TO-USE LEASED BUILDINGS | J87: 3651728
A88: *Rpt 18 | C88: Cr: Acct 0476 - RIGHT-TO-USE LEASED LAND - AMORTIZABLE
A89: *Rpt 18 | C89: Cr: Acct 0478 - RIGHT-TO-USE LEASED EQUIPMENT - AMORTIZABLE
A90: *Rpt 18 | C90: Cr: Acct 0477 - RIGHT-TO-USE LEASED BUILDINGS - AMORTIZABLE | K90: 3651728
B91: * THESE AMOUNTS SHOULD BE INCLUDED AS "DEDUCTIONS" ON REPORT 18. | J91: =SUM(J85:J90) -> 3651728 | K91: =SUM(K85:K90) -> 3651728 | L91: =IF(J91=K91,"<- Debits and Credits equal each other.","<- Debits and Credits do not equal each other.") -> <- Debits and Credits equal each other.
A94: Lease Remeasurement and Modifications (only if a significant modification occurred during the fiscal year)
A95: 9 | B95: Record early termination or lease modifications to decrease in the RTU leased asset.
A96: **LS LL/CF | B96: Dr: Acct 0691 - RIGHT-TO-USE LEASE LIABILITY
B97: Dr: Acct 0485 - ACCUMULATED AMORTIZATION - RIGHT-TO-USE LEASED LAND
B98: Dr: Acct 0479 - ACCUMULATED AMORTIZATION - RIGHT-TO-USE LEASED EQUIPMENT
B99: Dr: Acct 0486 - ACCUMULATED AMORTIZATION - RIGHT-TO-USE LEASED BUILDINGS
B100: =IF($F$7="Proprietary","Dr: Acct 0870 - SERVICES & CHARGES (MG ADJ)",VLOOKUP($F$9,'[2]Drop Down Menus'!$F$2:$H$10,3,FALSE)) -> Dr: Acct 0825 - BUS, CONSUMER SERV, HOUSING
A101: *Rpt 18 | C101: Cr: Acct 0476 - RIGHT-TO-USE LEASED LAND - AMORTIZABLE
A102: *Rpt 18 | C102: Cr: Acct 0478 - RIGHT-TO-USE LEASED EQUIPMENT - AMORTIZABLE
A103: *Rpt 18 | C103: Cr: Acct 0477 - RIGHT-TO-USE LEASED BUILDINGS - AMORTIZABLE
C104: =IF($F$7="Proprietary","Dr: Acct 0870 - SERVICES & CHARGES (MG ADJ)",VLOOKUP($F$9,'[2]Drop Down Menus'!$F$2:$G$10,2,FALSE)) -> Cr: Acct 0825 - BUS, CONSUMER SERV, HOUSING
B105: * THESE AMOUNTS SHOULD BE INCLUDED AS "DEDUCTIONS" ON REPORT 18. | J105: =SUM(J96:J104) -> 0 | K105: =SUM(K96:K104) -> 0 | L105: =IF(J105=K105,"<- Debits and Credits equal each other.","<- Debits and Credits do not equal each other.") -> <- Debits and Credits equal each other.
B106: ** This amount should be included in the deductions column on the LS-Lease Liability and LS-Check Figures Tabs.
A109: 10 | B109: Record lease modifications to increase in the RTU leased asset.
A110: *Rpt 18 | B110: Dr: Acct 0476 - RIGHT-TO-USE LEASED LAND - AMORTIZABLE
A111: *Rpt 18 | B111: Dr: Acct 0478 - RIGHT-TO-USE LEASED EQUIPMENT - AMORTIZABLE
A112: *Rpt 18 | B112: Dr: Acct 0477 - RIGHT-TO-USE LEASED BUILDINGS - AMORTIZABLE
A113: **LS LL/CF | C113: Cr: Acct 0691 - RIGHT-TO-USE LEASE LIABILITY
B114: * THESE AMOUNTS SHOULD BE INCLUDED AS "ADDITIONS" ON REPORT 18. | J114: =SUM(J110:J113) -> 0 | K114: =SUM(K110:K113) -> 0 | L114: =IF(J114=K114,"<- Debits and Credits equal each other.","<- Debits and Credits do not equal each other.") -> <- Debits and Credits equal each other.
B115: ** This amount should be included in the additions column on the LS-Lease Liability and LS-Check Figures Tabs.
D120: Informational - Ending Balances of Assets and Liabilities
K121: Debit (Credit)
D122: Acct 0476 - RIGHT-TO-USE LEASED LAND - AMORTIZABLE | K122: =J15+J39-K88-K101+J110 -> 0
D123: Acct 0478 - RIGHT-TO-USE LEASED EQUIPMENT - AMORTIZABLE | K123: =J16+J40-K89-K102+J111 -> 0
D124: Acct 0477 - RIGHT-TO-USE LEASED BUILDINGS - AMORTIZABLE | K124: =J17+J41-K90-K103+J112 -> 0
D125: Acct 0485 - ACCUMULATED AMORTIZATION - RIGHT-TO-USE LEASED LAND | K125: =-K20-K56+J85+J97 -> 0
...

Sheet LS-Fund 0239 Journal Entries
A1: Lessee-Type Contracts Fund-by-Fund Journal Entries Form (to be submitted to the SCO annually—one form per fund)
A2: Manually complete every yellow field in this worksheet—there are no automatically calculated data-entry cells in this worksheet.
A3: Fiscal Year: | F3: 2023–2024
A4: Organization Name: | F4: Department of Consumer Affairs
A5: Organization Code (4-Digits): | F5: 1111
A6: Fund Number (4-Digits): | F6: 239
A7: Fund Classification: | F7: Governmental
A8: Fund Type: | F8: Governmental Fund
A9: Functional Expense: | F9: =IFERROR(IF(F7="Proprietary","Proprietary Fund",VLOOKUP(F5,[3]qryIndex02a!$A$2:$K$654,4,FALSE)),"Unidentified") -> BUS, CONSUMER SERV, HOUSING
A12: Establish Beginning Balances (existing leases only)
A13: Entry #
A14: 0 | B14: Roll forward prior year right-to-use leases to record opening balances. | M14: Combined Lessee Templates | P14: From SCO BB List | S14: Difference
A15: *Rpt 18 | B15: Dr: Acct 0476 - RIGHT-TO-USE LEASED LAND - AMORTIZABLE | J15: =M15 -> 0 | S15: =P15-M15 -> 0 | T15: Report any "Differences" on the Report 18 Differential.
A16: *Rpt 18 | B16: Dr: Acct 0478 - RIGHT-TO-USE LEASED EQUIPMENT - AMORTIZABLE | J16: =M16 -> 0 | S16: =P16-M16 -> 0 | T16: Report any "Differences" on the Report 18 Differential.
A17: *Rpt 18 | B17: Dr: Acct 0477 - RIGHT-TO-USE LEASED BUILDINGS - AMORTIZABLE | J17: =M17 -> 0 | S17: =P17-M17 -> 0 | T17: Report any "Differences" on the Report 18 Differential.
B18: Dr: Acct 0950 - BEGINNING FUND BALANCE | J18: =P18 -> 0 | P18: =IF(SUM($Q$20:$Q$23)>SUM($P$15:$P$17),SUM($Q$20:$Q$23)-SUM($P$15:$P$17),0) -> 0 | S18: =P18-M18 -> 0 | T18: No action required.
B19: Dr: Acct 0952 - BEGINNING FUND ADJUSTMENT/PRIOR PERIOD ADJUSTMENT | J19: =IF(SUM($K$20:$K$24)>SUM($J$15:$J$18),SUM($K$20:$K$24)-SUM($J$15:$J$18),0) -> 0 | S19: =P19-M19 -> 0 | T19: No action required.
C20: Cr: Acct 0485 - ACCUMULATED AMORTIZATION - RIGHT-TO-USE LEASED LAND | K20: =N20 -> 0 | S20: =Q20-N20 -> 0 | T20: No action required.
C21: Cr: Acct 0479 - ACCUMULATED AMORTIZATION - RIGHT-TO-USE LEASED EQUIPMENT | K21: =N21 -> 0 | S21: =Q21-N21 -> 0 | T21: No action required.
C22: Cr: Acct 0486 - ACCUMULATED AMORTIZATION - RIGHT-TO-USE LEASED BUILDINGS | K22: =N22 -> 0 | S22: =Q22-N22 -> 0 | T22: No action required.
A23: **LS LL/CF | C23: Cr: Acct 0691 - RIGHT-TO-USE LEASE LIABILITY | K23: =N23 -> 0 | S23: =Q23-N23 -> 0 | T23: No action required.
C24: Cr: Acct 0950 - BEGINNING FUND BALANCE | K24: =Q24 -> 0 | Q24: =IF(SUM($Q$20:$Q$23)<SUM($P$15:$P$17),-SUM($Q$20:$Q$23)+SUM($P$15:$P$17),0) -> 0 | S24: =Q24-N24 -> 0 | T24: No action required.
C25: Cr: Acct 0952 - BEGINNING FUND ADJUSTMENT/PRIOR PERIOD ADJUSTMENT | K25: =IF(SUM($K$20:$K$24)<SUM($J$15:$J$18),-SUM($K$20:$K$24)+SUM($J$15:$J$18),0) -> 0 | S25: =Q25-N25 -> 0 | T25: No action required.
J26: =SUM(J15:J25) -> 0 | K26: =SUM(K15:K25) -> 0 | L26: =IF(J26=K26,"<- Debits and Credits equal each other.","<- Debits and Credits do not equal each other.") -> <- Debits and Credits equal each other.
B27: * THESE ASSET AMOUNTS SHOULD BE REPORTED AS BEGINNING BALANCES ON REPORT 18.
B28: ** This amount should be included in the beginning balance column on the LS-Lease Liability and LS-Check Figures Tabs.
A31: Record New Leases (new leases only)
A32: 1 | B32: Record lease contract commencement (fund-based entries only)
B33: Dr: Acct 0842 - CAPITAL OUTLAY | J33: 2789016
C34: Cr: Acct 0789 - LEASE AND OTHER FINANCING PROCEEDS | K34: 2789016
C35: =IF($F$7="Proprietary","Cr: Acct 0870 - SERVICES & CHARGES (MG ADJ)",VLOOKUP($F$9,'[3]Drop Down Menus'!$F$2:$G$10,2,FALSE)) -> Cr: Acct 0825 - BUS, CONSUMER SERV, HOUSING
J36: =SUM(J33:J35) -> 2789016 | K36: =SUM(K33:K35) -> 2789016 | L36: =IF(J36=K36,"<- Debits and Credits equal each other.","<- Debits and Credits do not equal each other.") -> <- Debits and Credits equal each other.
A38: 2 | B38: Record leased assets.
A39: *Rpt 18 | B39: Dr: Acct 0476 - RIGHT-TO-USE LEASED LAND - AMORTIZABLE
A40: *Rpt 18 | B40: Dr: Acct 0478 - RIGHT-TO-USE LEASED EQUIPMENT - AMORTIZABLE
A41: *Rpt 18 | B41: Dr: Acct 0477 - RIGHT-TO-USE LEASED BUILDINGS - AMORTIZABLE | J41: 2789016
C42: Cr: Acct 0842 - CAPITAL OUTLAY | K42: 2789016
B43: * THESE AMOUNTS SHOULD BE INCLUDED AS "ADDITIONS" ON REPORT 18. | J43: =SUM(J39:J42) -> 2789016 | K43: =SUM(K39:K42) -> 2789016 | L43: =IF(J43=K43,"<- Debits and Credits equal each other.","<- Debits and Credits do not equal each other.") -> <- Debits and Credits equal each other.
A46: 3 | B46: Replace proceeds from leases with right-to-use lease liability.
B47: Dr: Acct 0789 - LEASE AND OTHER FINANCING PROCEEDS | J47: 2789016
A48: **LS LL/CF | C48: Cr: Acct 0691 - RIGHT-TO-USE LEASE LIABILITY | K48: 2789016
J49: =SUM(J47:J48) -> 2789016 | K49: =SUM(K47:K48) -> 2789016 | L49: =IF(J49=K49,"<- Debits and Credits equal each other.","<- Debits and Credits do not equal each other.") -> <- Debits and Credits equal each other.
B50: ** This amount should be included in the additions column on the LS-Lease Liability and LS-Check Figures Tabs.
A53: Record Annual Activity (all leases)
A54: 4 | B54: Record amortization of the leased assets for the year.
B55: Dr: Acct 0875 - DEPRECIATION/AMORTIZATION | J55: 174313
C56: Cr: Acct 0485 - ACCUMULATED AMORTIZATION - RIGHT-TO-USE LEASED LAND
C57: Cr: Acct 0479 - ACCUMULATED AMORTIZATION - RIGHT-TO-USE LEASED EQUIPMENT
C58: Cr: Acct 0486 - ACCUMULATED AMORTIZATION - RIGHT-TO-USE LEASED BUILDINGS | K58: 174313
J59: =SUM(J55:J58) -> 174313 | K59: =SUM(K55:K58) -> 174313 | L59: =IF(J59=K59,"<- Debits and Credits equal each other.","<- Debits and Credits do not equal each other.") -> <- Debits and Credits equal each other.
A61: 5 | B61: Reclassify rents and leases exp. to lease contract principal and interest exp.
B62: Dr: Acct 0848 - DEBT SERVICE - PRINCIPAL LEASES | J62: 47897 | L62: =IF($J$62=$K$69,"","<- Accts 0848 must agree")
B63: =IF(F7="Governmental","Dr: Acct 0851 - DEBT SERVICE - INTEREST LEASES","Dr: Acct 0894 - INTEREST EXPENSE AND FISCAL CHARGES") -> Dr: Acct 0851 - DEBT SERVICE - INTEREST LEASES | J63: 18362
C64: =IF($F$7="Proprietary","Cr: Acct 0870 - SERVICES & CHARGES (MG ADJ)",VLOOKUP($F$9,'[3]Drop Down Menus'!$F$2:$G$10,2,FALSE)) -> Cr: Acct 0825 - BUS, CONSUMER SERV, HOUSING | K64: 66259
J65: =SUM(J62:J64) -> 66259 | K65: =SUM(K62:K64) -> 66259 | L65: =IF(J65=K65,"<- Debits and Credits equal each other.","<- Debits and Credits do not equal each other.") -> <- Debits and Credits equal each other.
A67: 6 | B67: Reduce lease contracts liability for total current year principal payments.
A68: **LS LL/CF | B68: Dr: Acct 0691 - RIGHT-TO-USE LEASE LIABILITY | J68: 47897
C69: Cr: Acct 0848 - DEBT SERVICE - PRINCIPAL LEASES | K69: 47897 | L69: =IF($J$62=$K$69,"","<- Accts 0848 must agree")
J70: =SUM(J68:J69) -> 47897 | K70: =SUM(K68:K69) -> 47897 | L70: =IF(J70=K70,"<- Debits and Credits equal each other.","<- Debits and Credits do not equal each other.") -> <- Debits and Credits equal each other.
B71: ** This amount should be included in the deductions column on the LS-Lease Liability and LS-Check Figures Tabs.
A74: 7 | B74: Reclassify the principal amount due in the next FY to the current liability.
A75: **LS LL/CF | B75: Dr: Acct 0691 - RIGHT-TO-USE LEASE LIABILITY | J75: 678608
C76: Cr: Acct 0649 - RIGHT-TO-USE LEASE LIABILITY (CURRENT PORTION LT) | K76: 678608
B77: NOTE: This is an annual accrual. It is to be reversed at the start of the next fiscal year. SCO combines the current and non current amount in Entry #0 to reestablish the beginning balances. No action required. | J77: =SUM(J75:J76) -> 678608 | K77: =SUM(K75:K76) -> 678608 | L77: =IF(J77=K77,"<- Debits and Credits equal each other.","<- Debits and Credits do not equal each other.") -> <- Debits and Credits equal each other.
B80: ** This amount should be included in the due in one year column on the LS-Lease Liability and LS-Check Figures Tabs.
A83: Remove Lease Asset at the End of the Lease Term (only at the end of the lease term)
A84: 8 | B84: Record entry to write off the lease asset and accumulated amortization at the end of the lease term.
B85: Dr: Acct 0485 - ACCUMULATED AMORTIZATION - RIGHT-TO-USE LEASED LAND
B86: Dr: Acct 0479 - ACCUMULATED AMORTIZATION - RIGHT-TO-USE LEASED EQUIPMENT
B87: Dr: Acct 0486 - ACCUMULATED AMORTIZATION - RIGHT-TO-USE LEASED BUILDINGS
A88: *Rpt 18 | C88: Cr: Acct 0476 - RIGHT-TO-USE LEASED LAND - AMORTIZABLE
A89: *Rpt 18 | C89: Cr: Acct 0478 - RIGHT-TO-USE LEASED EQUIPMENT - AMORTIZABLE
A90: *Rpt 18 | C90: Cr: Acct 0477 - RIGHT-TO-USE LEASED BUILDINGS - AMORTIZABLE
B91: * THESE AMOUNTS SHOULD BE INCLUDED AS "DEDUCTIONS" ON REPORT 18. | J91: =SUM(J85:J90) -> 0 | K91: =SUM(K85:K90) -> 0 | L91: =IF(J91=K91,"<- Debits and Credits equal each other.","<- Debits and Credits do not equal each other.") -> <- Debits and Credits equal each other.
A94: Lease Remeasurement and Modifications (only if a significant modification occurred during the fiscal year)
A95: 9 | B95: Record early termination or lease modifications to decrease in the RTU leased asset.
A96: **LS LL/CF | B96: Dr: Acct 0691 - RIGHT-TO-USE LEASE LIABILITY
B97: Dr: Acct 0485 - ACCUMULATED AMORTIZATION - RIGHT-TO-USE LEASED LAND
B98: Dr: Acct 0479 - ACCUMULATED AMORTIZATION - RIGHT-TO-USE LEASED EQUIPMENT
B99: Dr: Acct 0486 - ACCUMULATED AMORTIZATION - RIGHT-TO-USE LEASED BUILDINGS
B100: =IF($F$7="Proprietary","Dr: Acct 0870 - SERVICES & CHARGES (MG ADJ)",VLOOKUP($F$9,'[3]Drop Down Menus'!$F$2:$H$10,3,FALSE)) -> Dr: Acct 0825 - BUS, CONSUMER SERV, HOUSING
A101: *Rpt 18 | C101: Cr: Acct 0476 - RIGHT-TO-USE LEASED LAND - AMORTIZABLE
A102: *Rpt 18 | C102: Cr: Acct 0478 - RIGHT-TO-USE LEASED EQUIPMENT - AMORTIZABLE
A103: *Rpt 18 | C103: Cr: Acct 0477 - RIGHT-TO-USE LEASED BUILDINGS - AMORTIZABLE
C104: =IF($F$7="Proprietary","Dr: Acct 0870 - SERVICES & CHARGES (MG ADJ)",VLOOKUP($F$9,'[3]Drop Down Menus'!$F$2:$G$10,2,FALSE)) -> Cr: Acct 0825 - BUS, CONSUMER SERV, HOUSING
B105: * THESE AMOUNTS SHOULD BE INCLUDED AS "DEDUCTIONS" ON REPORT 18. | J105: =SUM(J96:J104) -> 0 | K105: =SUM(K96:K104) -> 0 | L105: =IF(J105=K105,"<- Debits and Credits equal each other.","<- Debits and Credits do not equal each other.") -> <- Debits and Credits equal each other.
B106: ** This amount should be included in the deductions column on the LS-Lease Liability and LS-Check Figures Tabs.
A109: 10 | B109: Record lease modifications to increase in the RTU leased asset.
A110: *Rpt 18 | B110: Dr: Acct 0476 - RIGHT-TO-USE LEASED LAND - AMORTIZABLE
A111: *Rpt 18 | B111: Dr: Acct 0478 - RIGHT-TO-USE LEASED EQUIPMENT - AMORTIZABLE
A112: *Rpt 18 | B112: Dr: Acct 0477 - RIGHT-TO-USE LEASED BUILDINGS - AMORTIZABLE
A113: **LS LL/CF | C113: Cr: Acct 0691 - RIGHT-TO-USE LEASE LIABILITY
B114: * THESE AMOUNTS SHOULD BE INCLUDED AS "ADDITIONS" ON REPORT 18. | J114: =SUM(J110:J113) -> 0 | K114: =SUM(K110:K113) -> 0 | L114: =IF(J114=K114,"<- Debits and Credits equal each other.","<- Debits and Credits do not equal each other.") -> <- Debits and Credits equal each other.
B115: ** This amount should be included in the additions column on the LS-Lease Liability and LS-Check Figures Tabs.
D120: Informational - Ending Balances of Assets and Liabilities
K121: Debit (Credit)
D122: Acct 0476 - RIGHT-TO-USE LEASED LAND - AMORTIZABLE | K122: =J15+J39-K88-K101+J110 -> 0
D123: Acct 0478 - RIGHT-TO-USE LEASED EQUIPMENT - AMORTIZABLE | K123: =J16+J40-K89-K102+J111 -> 0
D124: Acct 0477 - RIGHT-TO-USE LEASED BUILDINGS - AMORTIZABLE | K124: =J17+J41-K90-K103+J112 -> 2789016
D125: Acct 0485 - ACCUMULATED AMORTIZATION - RIGHT-TO-USE LEASED LAND | K125: =-K20-K56+J85+J97 -> 0
...

Sheet LS-Fund 0305 Journal Entries
A1: Lessee-Type Contracts Fund-by-Fund Journal Entries Form (to be submitted to the SCO annually—one form per fund)
A2: Manually complete every yellow field in this worksheet—there are no automatically calculated data-entry cells in this worksheet.
A3: Fiscal Year: | F3: 2023–2024
A4: Organization Name: | F4: Department of Consumer Affairs
A5: Organization Code (4-Digits): | F5: 1111
A6: Fund Number (4-Digits): | F6: 305
A7: Fund Classification: | F7: Governmental
A8: Fund Type: | F8: Governmental Fund
A9: Functional Expense: | F9: =IFERROR(IF(F7="Proprietary","Proprietary Fund",VLOOKUP(F5,[4]qryIndex02a!$A$2:$K$654,4,FALSE)),"Unidentified") -> BUS, CONSUMER SERV, HOUSING
A12: Establish Beginning Balances (existing leases only)
A13: Entry #
A14: 0 | B14: Roll forward prior year right-to-use leases to record opening balances. | M14: Combined Lessee Templates | P14: From SCO BB List | S14: Difference
A15: *Rpt 18 | B15: Dr: Acct 0476 - RIGHT-TO-USE LEASED LAND - AMORTIZABLE | J15: =M15 -> 0 | S15: =P15-M15 -> 0 | T15: Report any "Differences" on the Report 18 Differential.
A16: *Rpt 18 | B16: Dr: Acct 0478 - RIGHT-TO-USE LEASED EQUIPMENT - AMORTIZABLE | J16: =M16 -> 0 | S16: =P16-M16 -> 0 | T16: Report any "Differences" on the Report 18 Differential.
A17: *Rpt 18 | B17: Dr: Acct 0477 - RIGHT-TO-USE LEASED BUILDINGS - AMORTIZABLE | J17: =M17 -> 1346693 | M17: 1346693 | P17: 1346693 | S17: =P17-M17 -> 0 | T17: Report any "Differences" on the Report 18 Differential.
B18: Dr: Acct 0950 - BEGINNING FUND BALANCE | J18: =P18 -> 7839 | M18: 7839 | P18: =IF(SUM($Q$20:$Q$23)>SUM($P$15:$P$17),SUM($Q$20:$Q$23)-SUM($P$15:$P$17),0) -> 7839 | S18: =P18-M18 -> 0 | T18: No action required.
B19: Dr: Acct 0952 - BEGINNING FUND ADJUSTMENT/PRIOR PERIOD ADJUSTMENT | J19: =IF(SUM($K$20:$K$24)>SUM($J$15:$J$18),SUM($K$20:$K$24)-SUM($J$15:$J$18),0) -> 0 | S19: =P19-M19 -> 0 | T19: No action required.
C20: Cr: Acct 0485 - ACCUMULATED AMORTIZATION - RIGHT-TO-USE LEASED LAND | K20: =N20 -> 0 | S20: =Q20-N20 -> 0 | T20: No action required.
C21: Cr: Acct 0479 - ACCUMULATED AMORTIZATION - RIGHT-TO-USE LEASED EQUIPMENT | K21: =N21 -> 0 | S21: =Q21-N21 -> 0 | T21: No action required.
C22: Cr: Acct 0486 - ACCUMULATED AMORTIZATION - RIGHT-TO-USE LEASED BUILDINGS | K22: =N22 -> 979414 | N22: 979414 | Q22: 979414 | S22: =Q22-N22 -> 0 | T22: No action required.
A23: **LS LL/CF | C23: Cr: Acct 0691 - RIGHT-TO-USE LEASE LIABILITY | K23: =N23 -> 375118 | N23: 375118 | Q23: 375118 | S23: =Q23-N23 -> 0 | T23: No action required.
C24: Cr: Acct 0950 - BEGINNING FUND BALANCE | K24: =Q24 -> 0 | Q24: =IF(SUM($Q$20:$Q$23)<SUM($P$15:$P$17),-SUM($Q$20:$Q$23)+SUM($P$15:$P$17),0) -> 0 | S24: =Q24-N24 -> 0 | T24: No action required.
C25: Cr: Acct 0952 - BEGINNING FUND ADJUSTMENT/PRIOR PERIOD ADJUSTMENT | K25: =IF(SUM($K$20:$K$24)<SUM($J$15:$J$18),-SUM($K$20:$K$24)+SUM($J$15:$J$18),0) -> 0 | S25: =Q25-N25 -> 0 | T25: No action required.
J26: =SUM(J15:J25) -> 1354532 | K26: =SUM(K15:K25) -> 1354532 | L26: =IF(J26=K26,"<- Debits and Credits equal each other.","<- Debits and Credits do not equal each other.") -> <- Debits and Credits equal each other.
B27: * THESE ASSET AMOUNTS SHOULD BE REPORTED AS BEGINNING BALANCES ON REPORT 18.
B28: ** This amount should be included in the beginning balance column on the LS-Lease Liability and LS-Check Figures Tabs.
A31: Record New Leases (new leases only)
A32: 1 | B32: Record lease contract commencement (fund-based entries only)
B33: Dr: Acct 0842 - CAPITAL OUTLAY
C34: Cr: Acct 0789 - LEASE AND OTHER FINANCING PROCEEDS
C35: =IF($F$7="Proprietary","Cr: Acct 0870 - SERVICES & CHARGES (MG ADJ)",VLOOKUP($F$9,'[4]Drop Down Menus'!$F$2:$G$10,2,FALSE)) -> Cr: Acct 0825 - BUS, CONSUMER SERV, HOUSING
J36: =SUM(J33:J35) -> 0 | K36: =SUM(K33:K35) -> 0 | L36: =IF(J36=K36,"<- Debits and Credits equal each other.","<- Debits and Credits do not equal each other.") -> <- Debits and Credits equal each other.
A38: 2 | B38: Record leased assets.
A39: *Rpt 18 | B39: Dr: Acct 0476 - RIGHT-TO-USE LEASED LAND - AMORTIZABLE
A40: *Rpt 18 | B40: Dr: Acct 0478 - RIGHT-TO-USE LEASED EQUIPMENT - AMORTIZABLE
A41: *Rpt 18 | B41: Dr: Acct 0477 - RIGHT-TO-USE LEASED BUILDINGS - AMORTIZABLE
C42: Cr: Acct 0842 - CAPITAL OUTLAY
B43: * THESE AMOUNTS SHOULD BE INCLUDED AS "ADDITIONS" ON REPORT 18. | J43: =SUM(J39:J42) -> 0 | K43: =SUM(K39:K42) -> 0 | L43: =IF(J43=K43,"<- Debits and Credits equal each other.","<- Debits and Credits do not equal each other.") -> <- Debits and Credits equal each other.
A46: 3 | B46: Replace proceeds from leases with right-to-use lease liability.
B47: Dr: Acct 0789 - LEASE AND OTHER FINANCING PROCEEDS
A48: **LS LL/CF | C48: Cr: Acct 0691 - RIGHT-TO-USE LEASE LIABILITY
J49: =SUM(J47:J48) -> 0 | K49: =SUM(K47:K48) -> 0 | L49: =IF(J49=K49,"<- Debits and Credits equal each other.","<- Debits and Credits do not equal each other.") -> <- Debits and Credits equal each other.
B50: ** This amount should be included in the additions column on the LS-Lease Liability and LS-Check Figures Tabs.
A53: Record Annual Activity (all leases)
A54: 4 | B54: Record amortization of the leased assets for the year.
B55: Dr: Acct 0875 - DEPRECIATION/AMORTIZATION | J55: 367279
C56: Cr: Acct 0485 - ACCUMULATED AMORTIZATION - RIGHT-TO-USE LEASED LAND
C57: Cr: Acct 0479 - ACCUMULATED AMORTIZATION - RIGHT-TO-USE LEASED EQUIPMENT
C58: Cr: Acct 0486 - ACCUMULATED AMORTIZATION - RIGHT-TO-USE LEASED BUILDINGS | K58: 367279
J59: =SUM(J55:J58) -> 367279 | K59: =SUM(K55:K58) -> 367279 | L59: =IF(J59=K59,"<- Debits and Credits equal each other.","<- Debits and Credits do not equal each other.") -> <- Debits and Credits equal each other.
A61: 5 | B61: Reclassify rents and leases exp. to lease contract principal and interest exp.
B62: Dr: Acct 0848 - DEBT SERVICE - PRINCIPAL LEASES | J62: 375118 | L62: =IF($J$62=$K$69,"","<- Accts 0848 must agree")
B63: =IF(F7="Governmental","Dr: Acct 0851 - DEBT SERVICE - INTEREST LEASES","Dr: Acct 0894 - INTEREST EXPENSE AND FISCAL CHARGES") -> Dr: Acct 0851 - DEBT SERVICE - INTEREST LEASES | J63: 314
C64: =IF($F$7="Proprietary","Cr: Acct 0870 - SERVICES & CHARGES (MG ADJ)",VLOOKUP($F$9,'[4]Drop Down Menus'!$F$2:$G$10,2,FALSE)) -> Cr: Acct 0825 - BUS, CONSUMER SERV, HOUSING | K64: 375432
J65: =SUM(J62:J64) -> 375432 | K65: =SUM(K62:K64) -> 375432 | L65: =IF(J65=K65,"<- Debits and Credits equal each other.","<- Debits and Credits do not equal each other.") -> <- Debits and Credits equal each other.
A67: 6 | B67: Reduce lease contracts liability for total current year principal payments.
A68: **LS LL/CF | B68: Dr: Acct 0691 - RIGHT-TO-USE LEASE LIABILITY | J68: 375118
C69: Cr: Acct 0848 - DEBT SERVICE - PRINCIPAL LEASES | K69: 375118 | L69: =IF($J$62=$K$69,"","<- Accts 0848 must agree")
J70: =SUM(J68:J69) -> 375118 | K70: =SUM(K68:K69) -> 375118 | L70: =IF(J70=K70,"<- Debits and Credits equal each other.","<- Debits and Credits do not equal each other.") -> <- Debits and Credits equal each other.
B71: ** This amount should be included in the deductions column on the LS-Lease Liability and LS-Check Figures Tabs.
A74: 7 | B74: Reclassify the principal amount due in the next FY to the current liability.
A75: **LS LL/CF | B75: Dr: Acct 0691 - RIGHT-TO-USE LEASE LIABILITY
C76: Cr: Acct 0649 - RIGHT-TO-USE LEASE LIABILITY (CURRENT PORTION LT)
B77: NOTE: This is an annual accrual. It is to be reversed at the start of the next fiscal year. SCO combines the current and non current amount in Entry #0 to reestablish the beginning balances. No action required. | J77: =SUM(J75:J76) -> 0 | K77: =SUM(K75:K76) -> 0 | L77: =IF(J77=K77,"<- Debits and Credits equal each other.","<- Debits and Credits do not equal each other.") -> <- Debits and Credits equal each other.
B80: ** This amount should be included in the due in one year column on the LS-Lease Liability and LS-Check Figures Tabs.
A83: Remove Lease Asset at the End of the Lease Term (only at the end of the lease term)
A84: 8 | B84: Record entry to write off the lease asset and accumulated amortization at the end of the lease term.
B85: Dr: Acct 0485 - ACCUMULATED AMORTIZATION - RIGHT-TO-USE LEASED LAND
B86: Dr: Acct 0479 - ACCUMULATED AMORTIZATION - RIGHT-TO-USE LEASED EQUIPMENT
B87: Dr: Acct 0486 - ACCUMULATED AMORTIZATION - RIGHT-TO-USE LEASED BUILDINGS | J87: 1346693
A88: *Rpt 18 | C88: Cr: Acct 0476 - RIGHT-TO-USE LEASED LAND - AMORTIZABLE
A89: *Rpt 18 | C89: Cr: Acct 0478 - RIGHT-TO-USE LEASED EQUIPMENT - AMORTIZABLE
A90: *Rpt 18 | C90: Cr: Acct 0477 - RIGHT-TO-USE LEASED BUILDINGS - AMORTIZABLE | K90: 1346693
B91: * THESE AMOUNTS SHOULD BE INCLUDED AS "DEDUCTIONS" ON REPORT 18. | J91: =SUM(J85:J90) -> 1346693 | K91: =SUM(K85:K90) -> 1346693 | L91: =IF(J91=K91,"<- Debits and Credits equal each other.","<- Debits and Credits do not equal each other.") -> <- Debits and Credits equal each other.
A94: Lease Remeasurement and Modifications (only if a significant modification occurred during the fiscal year)
A95: 9 | B95: Record early termination or lease modifications to decrease in the RTU leased asset.
A96: **LS LL/CF | B96: Dr: Acct 0691 - RIGHT-TO-USE LEASE LIABILITY
B97: Dr: Acct 0485 - ACCUMULATED AMORTIZATION - RIGHT-TO-USE LEASED LAND
B98: Dr: Acct 0479 - ACCUMULATED AMORTIZATION - RIGHT-TO-USE LEASED EQUIPMENT
B99: Dr: Acct 0486 - ACCUMULATED AMORTIZATION - RIGHT-TO-USE LEASED BUILDINGS
B100: =IF($F$7="Proprietary","Dr: Acct 0870 - SERVICES & CHARGES (MG ADJ)",VLOOKUP($F$9,'[4]Drop Down Menus'!$F$2:$H$10,3,FALSE)) -> Dr: Acct 0825 - BUS, CONSUMER SERV, HOUSING
A101: *Rpt 18 | C101: Cr: Acct 0476 - RIGHT-TO-USE LEASED LAND - AMORTIZABLE
A102: *Rpt 18 | C102: Cr: Acct 0478 - RIGHT-TO-USE LEASED EQUIPMENT - AMORTIZABLE
A103: *Rpt 18 | C103: Cr: Acct 0477 - RIGHT-TO-USE LEASED BUILDINGS - AMORTIZABLE
C104: =IF($F$7="Proprietary","Dr: Acct 0870 - SERVICES & CHARGES (MG ADJ)",VLOOKUP($F$9,'[4]Drop Down Menus'!$F$2:$G$10,2,FALSE)) -> Cr: Acct 0825 - BUS, CONSUMER SERV, HOUSING
B105: * THESE AMOUNTS SHOULD BE INCLUDED AS "DEDUCTIONS" ON REPORT 18. | J105: =SUM(J96:J104) -> 0 | K105: =SUM(K96:K104) -> 0 | L105: =IF(J105=K105,"<- Debits and Credits equal each other.","<- Debits and Credits do not equal each other.") -> <- Debits and Credits equal each other.
B106: ** This amount should be included in the deductions column on the LS-Lease Liability and LS-Check Figures Tabs.
A109: 10 | B109: Record lease modifications to increase in the RTU leased asset.
A110: *Rpt 18 | B110: Dr: Acct 0476 - RIGHT-TO-USE LEASED LAND - AMORTIZABLE
A111: *Rpt 18 | B111: Dr: Acct 0478 - RIGHT-TO-USE LEASED EQUIPMENT - AMORTIZABLE
A112: *Rpt 18 | B112: Dr: Acct 0477 - RIGHT-TO-USE LEASED BUILDINGS - AMORTIZABLE
A113: **LS LL/CF | C113: Cr: Acct 0691 - RIGHT-TO-USE LEASE LIABILITY
B114: * THESE AMOUNTS SHOULD BE INCLUDED AS "ADDITIONS" ON REPORT 18. | J114: =SUM(J110:J113) -> 0 | K114: =SUM(K110:K113) -> 0 | L114: =IF(J114=K114,"<- Debits and Credits equal each other.","<- Debits and Credits do not equal each other.") -> <- Debits and Credits equal each other.
B115: ** This amount should be included in the additions column on the LS-Lease Liability and LS-Check Figures Tabs.
D120: Informational - Ending Balances of Assets and Liabilities
K121: Debit (Credit)
D122: Acct 0476 - RIGHT-TO-USE LEASED LAND - AMORTIZABLE | K122: =J15+J39-K88-K101+J110 -> 0
D123: Acct 0478 - RIGHT-TO-USE LEASED EQUIPMENT - AMORTIZABLE | K123: =J16+J40-K89-K102+J111 -> 0
D124: Acct 0477 - RIGHT-TO-USE LEASED BUILDINGS - AMORTIZABLE | K124: =J17+J41-K90-K103+J112 -> 0
D125: Acct 0485 - ACCUMULATED AMORTIZATION - RIGHT-TO-USE LEASED LAND | K125: =-K20-K56+J85+J97 -> 0
...

Sheet LS-Fund 0376 Journal Entries
A1: Lessee-Type Contracts Fund-by-Fund Journal Entries Form (to be submitted to the SCO annually—one form per fund)
A2: Manually complete every yellow field in this worksheet—there are no automatically calculated data-entry cells in this worksheet.
A3: Fiscal Year: | F3: 2023–2024
A4: Organization Name: | F4: Department of Consumer Affairs
A5: Organization Code (4-Digits): | F5: 1111
A6: Fund Number (4-Digits): | F6: 376
A7: Fund Classification: | F7: Governmental
A8: Fund Type: | F8: Governmental Fund
A9: Functional Expense: | F9: =IFERROR(IF(F7="Proprietary","Proprietary Fund",VLOOKUP(F5,[5]qryIndex02a!$A$2:$K$654,4,FALSE)),"Unidentified") -> BUS, CONSUMER SERV, HOUSING
A12: Establish Beginning Balances (existing leases only)
A13: Entry #
A14: 0 | B14: Roll forward prior year right-to-use leases to record opening balances. | M14: Combined Lessee Templates | P14: From SCO BB List | S14: Difference
A15: *Rpt 18 | B15: Dr: Acct 0476 - RIGHT-TO-USE LEASED LAND - AMORTIZABLE | J15: =M15 -> 0 | S15: =P15-M15 -> 0 | T15: Report any "Differences" on the Report 18 Differential.
A16: *Rpt 18 | B16: Dr: Acct 0478 - RIGHT-TO-USE LEASED EQUIPMENT - AMORTIZABLE | J16: =M16 -> 0 | S16: =P16-M16 -> 0 | T16: Report any "Differences" on the Report 18 Differential.
A17: *Rpt 18 | B17: Dr: Acct 0477 - RIGHT-TO-USE LEASED BUILDINGS - AMORTIZABLE | J17: =M17 -> 510190 | M17: 510190 | P17: 510190 | S17: =P17-M17 -> 0 | T17: Report any "Differences" on the Report 18 Differential.
B18: Dr: Acct 0950 - BEGINNING FUND BALANCE | J18: =P18 -> 5494 | M18: 5494 | P18: =IF(SUM($Q$20:$Q$23)>SUM($P$15:$P$17),SUM($Q$20:$Q$23)-SUM($P$15:$P$17),0) -> 5494 | S18: =P18-M18 -> 0 | T18: No action required.
B19: Dr: Acct 0952 - BEGINNING FUND ADJUSTMENT/PRIOR PERIOD ADJUSTMENT | J19: =IF(SUM($K$20:$K$24)>SUM($J$15:$J$18),SUM($K$20:$K$24)-SUM($J$15:$J$18),0) -> 0 | S19: =P19-M19 -> 0 | T19: No action required.
C20: Cr: Acct 0485 - ACCUMULATED AMORTIZATION - RIGHT-TO-USE LEASED LAND | K20: =N20 -> 0 | S20: =Q20-N20 -> 0 | T20: No action required.
C21: Cr: Acct 0479 - ACCUMULATED AMORTIZATION - RIGHT-TO-USE LEASED EQUIPMENT | K21: =N21 -> 0 | S21: =Q21-N21 -> 0 | T21: No action required.
C22: Cr: Acct 0486 - ACCUMULATED AMORTIZATION - RIGHT-TO-USE LEASED BUILDINGS | K22: =N22 -> 266186 | N22: 266186 | Q22: 266186 | S22: =Q22-N22 -> 0 | T22: No action required.
A23: **LS LL/CF | C23: Cr: Acct 0691 - RIGHT-TO-USE LEASE LIABILITY | K23: =N23 -> 249498 | N23: 249498 | Q23: 249498 | S23: =Q23-N23 -> 0 | T23: No action required.
C24: Cr: Acct 0950 - BEGINNING FUND BALANCE | K24: =Q24 -> 0 | Q24: =IF(SUM($Q$20:$Q$23)<SUM($P$15:$P$17),-SUM($Q$20:$Q$23)+SUM($P$15:$P$17),0) -> 0 | S24: =Q24-N24 -> 0 | T24: No action required.
C25: Cr: Acct 0952 - BEGINNING FUND ADJUSTMENT/PRIOR PERIOD ADJUSTMENT | K25: =IF(SUM($K$20:$K$24)<SUM($J$15:$J$18),-SUM($K$20:$K$24)+SUM($J$15:$J$18),0) -> 0 | S25: =Q25-N25 -> 0 | T25: No action required.
J26: =SUM(J15:J25) -> 515684 | K26: =SUM(K15:K25) -> 515684 | L26: =IF(J26=K26,"<- Debits and Credits equal each other.","<- Debits and Credits do not equal each other.") -> <- Debits and Credits equal each other.
B27: * THESE ASSET AMOUNTS SHOULD BE REPORTED AS BEGINNING BALANCES ON REPORT 18.
B28: ** This amount should be included in the beginning balance column on the LS-Lease Liability and LS-Check Figures Tabs.
A31: Record New Leases (new leases only)
A32: 1 | B32: Record lease contract commencement (fund-based entries only)
B33: Dr: Acct 0842 - CAPITAL OUTLAY
C34: Cr: Acct 0789 - LEASE AND OTHER FINANCING PROCEEDS
C35: =IF($F$7="Proprietary","Cr: Acct 0870 - SERVICES & CHARGES (MG ADJ)",VLOOKUP($F$9,'[5]Drop Down Menus'!$F$2:$G$10,2,FALSE)) -> Cr: Acct 0825 - BUS, CONSUMER SERV, HOUSING
J36: =SUM(J33:J35) -> 0 | K36: =SUM(K33:K35) -> 0 | L36: =IF(J36=K36,"<- Debits and Credits equal each other.","<- Debits and Credits do not equal each other.") -> <- Debits and Credits equal each other.
A38: 2 | B38: Record leased assets.
A39: *Rpt 18 | B39: Dr: Acct 0476 - RIGHT-TO-USE LEASED LAND - AMORTIZABLE
A40: *Rpt 18 | B40: Dr: Acct 0478 - RIGHT-TO-USE LEASED EQUIPMENT - AMORTIZABLE
A41: *Rpt 18 | B41: Dr: Acct 0477 - RIGHT-TO-USE LEASED BUILDINGS - AMORTIZABLE
C42: Cr: Acct 0842 - CAPITAL OUTLAY
B43: * THESE AMOUNTS SHOULD BE INCLUDED AS "ADDITIONS" ON REPORT 18. | J43: =SUM(J39:J42) -> 0 | K43: =SUM(K39:K42) -> 0 | L43: =IF(J43=K43,"<- Debits and Credits equal each other.","<- Debits and Credits do not equal each other.") -> <- Debits and Credits equal each other.
A46: 3 | B46: Replace proceeds from leases with right-to-use lease liability.
B47: Dr: Acct 0789 - LEASE AND OTHER FINANCING PROCEEDS
A48: **LS LL/CF | C48: Cr: Acct 0691 - RIGHT-TO-USE LEASE LIABILITY
J49: =SUM(J47:J48) -> 0 | K49: =SUM(K47:K48) -> 0 | L49: =IF(J49=K49,"<- Debits and Credits equal each other.","<- Debits and Credits do not equal each other.") -> <- Debits and Credits equal each other.
B50: ** This amount should be included in the additions column on the LS-Lease Liability and LS-Check Figures Tabs.
A53: Record Annual Activity (all leases)
A54: 4 | B54: Record amortization of the leased assets for the year.
B55: Dr: Acct 0875 - DEPRECIATION/AMORTIZATION | J55: 133093
C56: Cr: Acct 0485 - ACCUMULATED AMORTIZATION - RIGHT-TO-USE LEASED LAND
C57: Cr: Acct 0479 - ACCUMULATED AMORTIZATION - RIGHT-TO-USE LEASED EQUIPMENT
C58: Cr: Acct 0486 - ACCUMULATED AMORTIZATION - RIGHT-TO-USE LEASED BUILDINGS | K58: 133093
J59: =SUM(J55:J58) -> 133093 | K59: =SUM(K55:K58) -> 133093 | L59: =IF(J59=K59,"<- Debits and Credits equal each other.","<- Debits and Credits do not equal each other.") -> <- Debits and Credits equal each other.
A61: 5 | B61: Reclassify rents and leases exp. to lease contract principal and interest exp.
B62: Dr: Acct 0848 - DEBT SERVICE - PRINCIPAL LEASES | J62: 134921 | L62: =IF($J$62=$K$69,"","<- Accts 0848 must agree")
B63: =IF(F7="Governmental","Dr: Acct 0851 - DEBT SERVICE - INTEREST LEASES","Dr: Acct 0894 - INTEREST EXPENSE AND FISCAL CHARGES") -> Dr: Acct 0851 - DEBT SERVICE - INTEREST LEASES | J63: 376
C64: =IF($F$7="Proprietary","Cr: Acct 0870 - SERVICES & CHARGES (MG ADJ)",VLOOKUP($F$9,'[5]Drop Down Menus'!$F$2:$G$10,2,FALSE)) -> Cr: Acct 0825 - BUS, CONSUMER SERV, HOUSING | K64: 135297
J65: =SUM(J62:J64) -> 135297 | K65: =SUM(K62:K64) -> 135297 | L65: =IF(J65=K65,"<- Debits and Credits equal each other.","<- Debits and Credits do not equal each other.") -> <- Debits and Credits equal each other.
A67: 6 | B67: Reduce lease contracts liability for total current year principal payments.
A68: **LS LL/CF | B68: Dr: Acct 0691 - RIGHT-TO-USE LEASE LIABILITY | J68: 134921
C69: Cr: Acct 0848 - DEBT SERVICE - PRINCIPAL LEASES | K69: 134921 | L69: =IF($J$62=$K$69,"","<- Accts 0848 must agree")
J70: =SUM(J68:J69) -> 134921 | K70: =SUM(K68:K69) -> 134921 | L70: =IF(J70=K70,"<- Debits and Credits equal each other.","<- Debits and Credits do not equal each other.") -> <- Debits and Credits equal each other.
B71: ** This amount should be included in the deductions column on the LS-Lease Liability and LS-Check Figures Tabs.
A74: 7 | B74: Reclassify the principal amount due in the next FY to the current liability.
A75: **LS LL/CF | B75: Dr: Acct 0691 - RIGHT-TO-USE LEASE LIABILITY | J75: 114577
C76: Cr: Acct 0649 - RIGHT-TO-USE LEASE LIABILITY (CURRENT PORTION LT) | K76: 114577
B77: NOTE: This is an annual accrual. It is to be reversed at the start of the next fiscal year. SCO combines the current and non current amount in Entry #0 to reestablish the beginning balances. No action required. | J77: =SUM(J75:J76) -> 114577 | K77: =SUM(K75:K76) -> 114577 | L77: =IF(J77=K77,"<- Debits and Credits equal each other.","<- Debits and Credits do not equal each other.") -> <- Debits and Credits equal each other.
B80: ** This amount should be included in the due in one year column on the LS-Lease Liability and LS-Check Figures Tabs.
A83: Remove Lease Asset at the End of the Lease Term (only at the end of the lease term)
A84: 8 | B84: Record entry to write off the lease asset and accumulated amortization at the end of the lease term.
B85: Dr: Acct 0485 - ACCUMULATED AMORTIZATION - RIGHT-TO-USE LEASED LAND
B86: Dr: Acct 0479 - ACCUMULATED AMORTIZATION - RIGHT-TO-USE LEASED EQUIPMENT
B87: Dr: Acct 0486 - ACCUMULATED AMORTIZATION - RIGHT-TO-USE LEASED BUILDINGS
A88: *Rpt 18 | C88: Cr: Acct 0476 - RIGHT-TO-USE LEASED LAND - AMORTIZABLE
A89: *Rpt 18 | C89: Cr: Acct 0478 - RIGHT-TO-USE LEASED EQUIPMENT - AMORTIZABLE
A90: *Rpt 18 | C90: Cr: Acct 0477 - RIGHT-TO-USE LEASED BUILDINGS - AMORTIZABLE
B91: * THESE AMOUNTS SHOULD BE INCLUDED AS "DEDUCTIONS" ON REPORT 18. | J91: =SUM(J85:J90) -> 0 | K91: =SUM(K85:K90) -> 0 | L91: =IF(J91=K91,"<- Debits and Credits equal each other.","<- Debits and Credits do not equal each other.") -> <- Debits and Credits equal each other.
A94: Lease Remeasurement and Modifications (only if a significant modification occurred during the fiscal year)
A95: 9 | B95: Record early termination or lease modifications to decrease in the RTU leased asset.
A96: **LS LL/CF | B96: Dr: Acct 0691 - RIGHT-TO-USE LEASE LIABILITY
B97: Dr: Acct 0485 - ACCUMULATED AMORTIZATION - RIGHT-TO-USE LEASED LAND
B98: Dr: Acct 0479 - ACCUMULATED AMORTIZATION - RIGHT-TO-USE LEASED EQUIPMENT
B99: Dr: Acct 0486 - ACCUMULATED AMORTIZATION - RIGHT-TO-USE LEASED BUILDINGS
B100: =IF($F$7="Proprietary","Dr: Acct 0870 - SERVICES & CHARGES (MG ADJ)",VLOOKUP($F$9,'[5]Drop Down Menus'!$F$2:$H$10,3,FALSE)) -> Dr: Acct 0825 - BUS, CONSUMER SERV, HOUSING
A101: *Rpt 18 | C101: Cr: Acct 0476 - RIGHT-TO-USE LEASED LAND - AMORTIZABLE
A102: *Rpt 18 | C102: Cr: Acct 0478 - RIGHT-TO-USE LEASED EQUIPMENT - AMORTIZABLE
A103: *Rpt 18 | C103: Cr: Acct 0477 - RIGHT-TO-USE LEASED BUILDINGS - AMORTIZABLE
C104: =IF($F$7="Proprietary","Dr: Acct 0870 - SERVICES & CHARGES (MG ADJ)",VLOOKUP($F$9,'[5]Drop Down Menus'!$F$2:$G$10,2,FALSE)) -> Cr: Acct 0825 - BUS, CONSUMER SERV, HOUSING
B105: * THESE AMOUNTS SHOULD BE INCLUDED AS "DEDUCTIONS" ON REPORT 18. | J105: =SUM(J96:J104) -> 0 | K105: =SUM(K96:K104) -> 0 | L105: =IF(J105=K105,"<- Debits and Credits equal each other.","<- Debits and Credits do not equal each other.") -> <- Debits and Credits equal each other.
B106: ** This amount should be included in the deductions column on the LS-Lease Liability and LS-Check Figures Tabs.
A109: 10 | B109: Record lease modifications to increase in the RTU leased asset.
A110: *Rpt 18 | B110: Dr: Acct 0476 - RIGHT-TO-USE LEASED LAND - AMORTIZABLE
A111: *Rpt 18 | B111: Dr: Acct 0478 - RIGHT-TO-USE LEASED EQUIPMENT - AMORTIZABLE
A112: *Rpt 18 | B112: Dr: Acct 0477 - RIGHT-TO-USE LEASED BUILDINGS - AMORTIZABLE
A113: **LS LL/CF | C113: Cr: Acct 0691 - RIGHT-TO-USE LEASE LIABILITY
B114: * THESE AMOUNTS SHOULD BE INCLUDED AS "ADDITIONS" ON REPORT 18. | J114: =SUM(J110:J113) -> 0 | K114: =SUM(K110:K113) -> 0 | L114: =IF(J114=K114,"<- Debits and Credits equal each other.","<- Debits and Credits do not equal each other.") -> <- Debits and Credits equal each other.
B115: ** This amount should be included in the additions column on the LS-Lease Liability and LS-Check Figures Tabs.
D120: Informational - Ending Balances of Assets and Liabilities
K121: Debit (Credit)
D122: Acct 0476 - RIGHT-TO-USE LEASED LAND - AMORTIZABLE | K122: =J15+J39-K88-K101+J110 -> 0
D123: Acct 0478 - RIGHT-TO-USE LEASED EQUIPMENT - AMORTIZABLE | K123: =J16+J40-K89-K102+J111 -> 0
D124: Acct 0477 - RIGHT-TO-USE LEASED BUILDINGS - AMORTIZABLE | K124: =J17+J41-K90-K103+J112 -> 510190
D125: Acct 0485 - ACCUMULATED AMORTIZATION - RIGHT-TO-USE LEASED LAND | K125: =-K20-K56+J85+J97 -> 0
...

Sheet LS-Fund 0421 Journal Entries
A1: Lessee-Type Contracts Fund-by-Fund Journal Entries Form (to be submitted to the SCO annually—one form per fund)
A2: Manually complete every yellow field in this worksheet—there are no automatically calculated data-entry cells in this worksheet.
A3: Fiscal Year: | F3: 2023–2024
A4: Organization Name: | F4: Department of Consumer Affairs
A5: Organization Code (4-Digits): | F5: 1111
A6: Fund Number (4-Digits): | F6: 421
A7: Fund Classification: | F7: Governmental
A8: Fund Type: | F8: Governmental Fund
A9: Functional Expense: | F9: =IFERROR(IF(F7="Proprietary","Proprietary Fund",VLOOKUP(F5,[6]qryIndex02a!$A$2:$K$654,4,FALSE)),"Unidentified") -> BUS, CONSUMER SERV, HOUSING
A12: Establish Beginning Balances (existing leases only)
A13: Entry #
A14: 0 | B14: Roll forward prior year right-to-use leases to record opening balances. | M14: Combined Lessee Templates | P14: From SCO BB List | S14: Difference
A15: *Rpt 18 | B15: Dr: Acct 0476 - RIGHT-TO-USE LEASED LAND - AMORTIZABLE | J15: =M15 -> 0 | S15: =P15-M15 -> 0 | T15: Report any "Differences" on the Report 18 Differential.
A16: *Rpt 18 | B16: Dr: Acct 0478 - RIGHT-TO-USE LEASED EQUIPMENT - AMORTIZABLE | J16: =M16 -> 0 | S16: =P16-M16 -> 0 | T16: Report any "Differences" on the Report 18 Differential.
A17: *Rpt 18 | B17: Dr: Acct 0477 - RIGHT-TO-USE LEASED BUILDINGS - AMORTIZABLE | J17: =M17 -> 11507652 | M17: 11507652 | P17: 11507652 | S17: =P17-M17 -> 0 | T17: Report any "Differences" on the Report 18 Differential.
B18: Dr: Acct 0950 - BEGINNING FUND BALANCE | J18: =P18 -> 176118 | M18: 176118 | P18: =IF(SUM($Q$20:$Q$23)>SUM($P$15:$P$17),SUM($Q$20:$Q$23)-SUM($P$15:$P$17),0) -> 176118 | S18: =P18-M18 -> 0 | T18: No action required.
B19: Dr: Acct 0952 - BEGINNING FUND ADJUSTMENT/PRIOR PERIOD ADJUSTMENT | J19: =IF(SUM($K$20:$K$24)>SUM($J$15:$J$18),SUM($K$20:$K$24)-SUM($J$15:$J$18),0) -> 0 | S19: =P19-M19 -> 0 | T19: No action required.
C20: Cr: Acct 0485 - ACCUMULATED AMORTIZATION - RIGHT-TO-USE LEASED LAND | K20: =N20 -> 0 | S20: =Q20-N20 -> 0 | T20: No action required.
C21: Cr: Acct 0479 - ACCUMULATED AMORTIZATION - RIGHT-TO-USE LEASED EQUIPMENT | K21: =N21 -> 0 | S21: =Q21-N21 -> 0 | T21: No action required.
C22: Cr: Acct 0486 - ACCUMULATED AMORTIZATION - RIGHT-TO-USE LEASED BUILDINGS | K22: =N22 -> 3673329 | N22: 3673329 | Q22: 3673329 | S22: =Q22-N22 -> 0 | T22: No action required.
A23: **LS LL/CF | C23: Cr: Acct 0691 - RIGHT-TO-USE LEASE LIABILITY | K23: =N23 -> 8010441 | N23: 8010441 | Q23: 8010441 | S23: =Q23-N23 -> 0 | T23: No action required.
C24: Cr: Acct 0950 - BEGINNING FUND BALANCE | K24: =Q24 -> 0 | Q24: =IF(SUM($Q$20:$Q$23)<SUM($P$15:$P$17),-SUM($Q$20:$Q$23)+SUM($P$15:$P$17),0) -> 0 | S24: =Q24-N24 -> 0 | T24: No action required.
C25: Cr: Acct 0952 - BEGINNING FUND ADJUSTMENT/PRIOR PERIOD ADJUSTMENT | K25: =IF(SUM($K$20:$K$24)<SUM($J$15:$J$18),-SUM($K$20:$K$24)+SUM($J$15:$J$18),0) -> 0 | S25: =Q25-N25 -> 0 | T25: No action required.
J26: =SUM(J15:J25) -> 11683770 | K26: =SUM(K15:K25) -> 11683770 | L26: =IF(J26=K26,"<- Debits and Credits equal each other.","<- Debits and Credits do not equal each other.") -> <- Debits and Credits equal each other.
B27: * THESE ASSET AMOUNTS SHOULD BE REPORTED AS BEGINNING BALANCES ON REPORT 18.
B28: ** This amount should be included in the beginning balance column on the LS-Lease Liability and LS-Check Figures Tabs.
A31: Record New Leases (new leases only)
A32: 1 | B32: Record lease contract commencement (fund-based entries only)
B33: Dr: Acct 0842 - CAPITAL OUTLAY | J33: 1840711
C34: Cr: Acct 0789 - LEASE AND OTHER FINANCING PROCEEDS | K34: 1840711
C35: =IF($F$7="Proprietary","Cr: Acct 0870 - SERVICES & CHARGES (MG ADJ)",VLOOKUP($F$9,'[6]Drop Down Menus'!$F$2:$G$10,2,FALSE)) -> Cr: Acct 0825 - BUS, CONSUMER SERV, HOUSING
J36: =SUM(J33:J35) -> 1840711 | K36: =SUM(K33:K35) -> 1840711 | L36: =IF(J36=K36,"<- Debits and Credits equal each other.","<- Debits and Credits do not equal each other.") -> <- Debits and Credits equal each other.
A38: 2 | B38: Record leased assets.
A39: *Rpt 18 | B39: Dr: Acct 0476 - RIGHT-TO-USE LEASED LAND - AMORTIZABLE
A40: *Rpt 18 | B40: Dr: Acct 0478 - RIGHT-TO-USE LEASED EQUIPMENT - AMORTIZABLE
A41: *Rpt 18 | B41: Dr: Acct 0477 - RIGHT-TO-USE LEASED BUILDINGS - AMORTIZABLE | J41: 1840711
C42: Cr: Acct 0842 - CAPITAL OUTLAY | K42: 1840711
B43: * THESE AMOUNTS SHOULD BE INCLUDED AS "ADDITIONS" ON REPORT 18. | J43: =SUM(J39:J42) -> 1840711 | K43: =SUM(K39:K42) -> 1840711 | L43: =IF(J43=K43,"<- Debits and Credits equal each other.","<- Debits and Credits do not equal each other.") -> <- Debits and Credits equal each other.
A46: 3 | B46: Replace proceeds from leases with right-to-use lease liability.
B47: Dr: Acct 0789 - LEASE AND OTHER FINANCING PROCEEDS | J47: 1840711
A48: **LS LL/CF | C48: Cr: Acct 0691 - RIGHT-TO-USE LEASE LIABILITY | K48: 1840711
J49: =SUM(J47:J48) -> 1840711 | K49: =SUM(K47:K48) -> 1840711 | L49: =IF(J49=K49,"<- Debits and Credits equal each other.","<- Debits and Credits do not equal each other.") -> <- Debits and Credits equal each other.
B50: ** This amount should be included in the additions column on the LS-Lease Liability and LS-Check Figures Tabs.
A53: Record Annual Activity (all leases)
A54: 4 | B54: Record amortization of the leased assets for the year.
B55: Dr: Acct 0875 - DEPRECIATION/AMORTIZATION | J55: 2814633
C56: Cr: Acct 0485 - ACCUMULATED AMORTIZATION - RIGHT-TO-USE LEASED LAND
C57: Cr: Acct 0479 - ACCUMULATED AMORTIZATION - RIGHT-TO-USE LEASED EQUIPMENT
C58: Cr: Acct 0486 - ACCUMULATED AMORTIZATION - RIGHT-TO-USE LEASED BUILDINGS | K58: 2814633
J59: =SUM(J55:J58) -> 2814633 | K59: =SUM(K55:K58) -> 2814633 | L59: =IF(J59=K59,"<- Debits and Credits equal each other.","<- Debits and Credits do not equal each other.") -> <- Debits and Credits equal each other.
A61: 5 | B61: Reclassify rents and leases exp. to lease contract principal and interest exp.
B62: Dr: Acct 0848 - DEBT SERVICE - PRINCIPAL LEASES | J62: 2764127 | L62: =IF($J$62=$K$69,"","<- Accts 0848 must agree")
B63: =IF(F7="Governmental","Dr: Acct 0851 - DEBT SERVICE - INTEREST LEASES","Dr: Acct 0894 - INTEREST EXPENSE AND FISCAL CHARGES") -> Dr: Acct 0851 - DEBT SERVICE - INTEREST LEASES | J63: 105407
C64: =IF($F$7="Proprietary","Cr: Acct 0870 - SERVICES & CHARGES (MG ADJ)",VLOOKUP($F$9,'[6]Drop Down Menus'!$F$2:$G$10,2,FALSE)) -> Cr: Acct 0825 - BUS, CONSUMER SERV, HOUSING | K64: 2869534
J65: =SUM(J62:J64) -> 2869534 | K65: =SUM(K62:K64) -> 2869534 | L65: =IF(J65=K65,"<- Debits and Credits equal each other.","<- Debits and Credits do not equal each other.") -> <- Debits and Credits equal each other.
A67: 6 | B67: Reduce lease contracts liability for total current year principal payments.
A68: **LS LL/CF | B68: Dr: Acct 0691 - RIGHT-TO-USE LEASE LIABILITY | J68: 2764127
C69: Cr: Acct 0848 - DEBT SERVICE - PRINCIPAL LEASES | K69: 2764127 | L69: =IF($J$62=$K$69,"","<- Accts 0848 must agree")
J70: =SUM(J68:J69) -> 2764127 | K70: =SUM(K68:K69) -> 2764127 | L70: =IF(J70=K70,"<- Debits and Credits equal each other.","<- Debits and Credits do not equal each other.") -> <- Debits and Credits equal each other.
B71: ** This amount should be included in the deductions column on the LS-Lease Liability and LS-Check Figures Tabs.
A74: 7 | B74: Reclassify the principal amount due in the next FY to the current liability.
A75: **LS LL/CF | B75: Dr: Acct 0691 - RIGHT-TO-USE LEASE LIABILITY | J75: 2700639
C76: Cr: Acct 0649 - RIGHT-TO-USE LEASE LIABILITY (CURRENT PORTION LT) | K76: 2700639
B77: NOTE: This is an annual accrual. It is to be reversed at the start of the next fiscal year. SCO combines the current and non current amount in Entry #0 to reestablish the beginning balances. No action required. | J77: =SUM(J75:J76) -> 2700639 | K77: =SUM(K75:K76) -> 2700639 | L77: =IF(J77=K77,"<- Debits and Credits equal each other.","<- Debits and Credits do not equal each other.") -> <- Debits and Credits equal each other.
B80: ** This amount should be included in the due in one year column on the LS-Lease Liability and LS-Check Figures Tabs.
A83: Remove Lease Asset at the End of the Lease Term (only at the end of the lease term)
A84: 8 | B84: Record entry to write off the lease asset and accumulated amortization at the end of the lease term.
B85: Dr: Acct 0485 - ACCUMULATED AMORTIZATION - RIGHT-TO-USE LEASED LAND
B86: Dr: Acct 0479 - ACCUMULATED AMORTIZATION - RIGHT-TO-USE LEASED EQUIPMENT
B87: Dr: Acct 0486 - ACCUMULATED AMORTIZATION - RIGHT-TO-USE LEASED BUILDINGS | J87: 872242
A88: *Rpt 18 | C88: Cr: Acct 0476 - RIGHT-TO-USE LEASED LAND - AMORTIZABLE
A89: *Rpt 18 | C89: Cr: Acct 0478 - RIGHT-TO-USE LEASED EQUIPMENT - AMORTIZABLE
A90: *Rpt 18 | C90: Cr: Acct 0477 - RIGHT-TO-USE LEASED BUILDINGS - AMORTIZABLE | K90: 872242
B91: * THESE AMOUNTS SHOULD BE INCLUDED AS "DEDUCTIONS" ON REPORT 18. | J91: =SUM(J85:J90) -> 872242 | K91: =SUM(K85:K90) -> 872242 | L91: =IF(J91=K91,"<- Debits and Credits equal each other.","<- Debits and Credits do not equal each other.") -> <- Debits and Credits equal each other.
A94: Lease Remeasurement and Modifications (only if a significant modification occurred during the fiscal year)
A95: 9 | B95: Record early termination or lease modifications to decrease in the RTU leased asset.
A96: **LS LL/CF | B96: Dr: Acct 0691 - RIGHT-TO-USE LEASE LIABILITY
B97: Dr: Acct 0485 - ACCUMULATED AMORTIZATION - RIGHT-TO-USE LEASED LAND
B98: Dr: Acct 0479 - ACCUMULATED AMORTIZATION - RIGHT-TO-USE LEASED EQUIPMENT
B99: Dr: Acct 0486 - ACCUMULATED AMORTIZATION - RIGHT-TO-USE LEASED BUILDINGS
B100: =IF($F$7="Proprietary","Dr: Acct 0870 - SERVICES & CHARGES (MG ADJ)",VLOOKUP($F$9,'[6]Drop Down Menus'!$F$2:$H$10,3,FALSE)) -> Dr: Acct 0825 - BUS, CONSUMER SERV, HOUSING
A101: *Rpt 18 | C101: Cr: Acct 0476 - RIGHT-TO-USE LEASED LAND - AMORTIZABLE
A102: *Rpt 18 | C102: Cr: Acct 0478 - RIGHT-TO-USE LEASED EQUIPMENT - AMORTIZABLE
A103: *Rpt 18 | C103: Cr: Acct 0477 - RIGHT-TO-USE LEASED BUILDINGS - AMORTIZABLE
C104: =IF($F$7="Proprietary","Dr: Acct 0870 - SERVICES & CHARGES (MG ADJ)",VLOOKUP($F$9,'[6]Drop Down Menus'!$F$2:$G$10,2,FALSE)) -> Cr: Acct 0825 - BUS, CONSUMER SERV, HOUSING
B105: * THESE AMOUNTS SHOULD BE INCLUDED AS "DEDUCTIONS" ON REPORT 18. | J105: =SUM(J96:J104) -> 0 | K105: =SUM(K96:K104) -> 0 | L105: =IF(J105=K105,"<- Debits and Credits equal each other.","<- Debits and Credits do not equal each other.") -> <- Debits and Credits equal each other.
B106: ** This amount should be included in the deductions column on the LS-Lease Liability and LS-Check Figures Tabs.
A109: 10 | B109: Record lease modifications to increase in the RTU leased asset.
A110: *Rpt 18 | B110: Dr: Acct 0476 - RIGHT-TO-USE LEASED LAND - AMORTIZABLE
A111: *Rpt 18 | B111: Dr: Acct 0478 - RIGHT-TO-USE LEASED EQUIPMENT - AMORTIZABLE
A112: *Rpt 18 | B112: Dr: Acct 0477 - RIGHT-TO-USE LEASED BUILDINGS - AMORTIZABLE
A113: **LS LL/CF | C113: Cr: Acct 0691 - RIGHT-TO-USE LEASE LIABILITY
B114: * THESE AMOUNTS SHOULD BE INCLUDED AS "ADDITIONS" ON REPORT 18. | J114: =SUM(J110:J113) -> 0 | K114: =SUM(K110:K113) -> 0 | L114: =IF(J114=K114,"<- Debits and Credits equal each other.","<- Debits and Credits do not equal each other.") -> <- Debits and Credits equal each other.
B115: ** This amount should be included in the additions column on the LS-Lease Liability and LS-Check Figures Tabs.
D120: Informational - Ending Balances of Assets and Liabilities
K121: Debit (Credit)
D122: Acct 0476 - RIGHT-TO-USE LEASED LAND - AMORTIZABLE | K122: =J15+J39-K88-K101+J110 -> 0
D123: Acct 0478 - RIGHT-TO-USE LEASED EQUIPMENT - AMORTIZABLE | K123: =J16+J40-K89-K102+J111 -> 0
D124: Acct 0477 - RIGHT-TO-USE LEASED BUILDINGS - AMORTIZABLE | K124: =J17+J41-K90-K103+J112 -> 12476121
D125: Acct 0485 - ACCUMULATED AMORTIZATION - RIGHT-TO-USE LEASED LAND | K125: =-K20-K56+J85+J97 -> 0
...

Sheet LS-Fund 0702 Journal Entries
A1: Lessee-Type Contracts Fund-by-Fund Journal Entries Form (to be submitted to the SCO annually—one form per fund)
A2: Manually complete every yellow field in this worksheet—there are no automatically calculated data-entry cells in this worksheet.
A3: Fiscal Year: | F3: 2023–2024
A4: Organization Name: | F4: Department of Consumer Affairs
A5: Organization Code (4-Digits): | F5: 1111
A6: Fund Number (4-Digits): | F6: 702
A7: Fund Classification: | F7: Governmental
A8: Fund Type: | F8: Governmental Fund
A9: Functional Expense: | F9: =IFERROR(IF(F7="Proprietary","Proprietary Fund",VLOOKUP(F5,[7]qryIndex02a!$A$2:$K$654,4,FALSE)),"Unidentified") -> BUS, CONSUMER SERV, HOUSING
A12: Establish Beginning Balances (existing leases only)
A13: Entry #
A14: 0 | B14: Roll forward prior year right-to-use leases to record opening balances. | M14: Combined Lessee Templates | P14: From SCO BB List | S14: Difference
A15: *Rpt 18 | B15: Dr: Acct 0476 - RIGHT-TO-USE LEASED LAND - AMORTIZABLE | J15: =M15 -> 0 | S15: =P15-M15 -> 0 | T15: Report any "Differences" on the Report 18 Differential.
A16: *Rpt 18 | B16: Dr: Acct 0478 - RIGHT-TO-USE LEASED EQUIPMENT - AMORTIZABLE | J16: =M16 -> 0 | S16: =P16-M16 -> 0 | T16: Report any "Differences" on the Report 18 Differential.
A17: *Rpt 18 | B17: Dr: Acct 0477 - RIGHT-TO-USE LEASED BUILDINGS - AMORTIZABLE | J17: =M17 -> 15877802 | M17: 15877802 | P17: 15877802 | S17: =P17-M17 -> 0 | T17: Report any "Differences" on the Report 18 Differential.
B18: Dr: Acct 0950 - BEGINNING FUND BALANCE | J18: =P18 -> 92340 | M18: 92340 | P18: =IF(SUM($Q$20:$Q$23)>SUM($P$15:$P$17),SUM($Q$20:$Q$23)-SUM($P$15:$P$17),0) -> 92340 | S18: =P18-M18 -> 0 | T18: No action required.
B19: Dr: Acct 0952 - BEGINNING FUND ADJUSTMENT/PRIOR PERIOD ADJUSTMENT | J19: =IF(SUM($K$20:$K$24)>SUM($J$15:$J$18),SUM($K$20:$K$24)-SUM($J$15:$J$18),0) -> 0 | S19: =P19-M19 -> 0 | T19: No action required.
C20: Cr: Acct 0485 - ACCUMULATED AMORTIZATION - RIGHT-TO-USE LEASED LAND | K20: =N20 -> 0 | S20: =Q20-N20 -> 0 | T20: No action required.
C21: Cr: Acct 0479 - ACCUMULATED AMORTIZATION - RIGHT-TO-USE LEASED EQUIPMENT | K21: =N21 -> 0 | S21: =Q21-N21 -> 0 | T21: No action required.
C22: Cr: Acct 0486 - ACCUMULATED AMORTIZATION - RIGHT-TO-USE LEASED BUILDINGS | K22: =N22 -> 9681819 | N22: 9681819 | Q22: 9681819 | S22: =Q22-N22 -> 0 | T22: No action required.
A23: **LS LL/CF | C23: Cr: Acct 0691 - RIGHT-TO-USE LEASE LIABILITY | K23: =N23 -> 6288323 | N23: 6288323 | Q23: 6288323 | S23: =Q23-N23 -> 0 | T23: No action required.
C24: Cr: Acct 0950 - BEGINNING FUND BALANCE | K24: =Q24 -> 0 | Q24: =IF(SUM($Q$20:$Q$23)<SUM($P$15:$P$17),-SUM($Q$20:$Q$23)+SUM($P$15:$P$17),0) -> 0 | S24: =Q24-N24 -> 0 | T24: No action required.
C25: Cr: Acct 0952 - BEGINNING FUND ADJUSTMENT/PRIOR PERIOD ADJUSTMENT | K25: =IF(SUM($K$20:$K$24)<SUM($J$15:$J$18),-SUM($K$20:$K$24)+SUM($J$15:$J$18),0) -> 0 | S25: =Q25-N25 -> 0 | T25: No action required.
J26: =SUM(J15:J25) -> 15970142 | K26: =SUM(K15:K25) -> 15970142 | L26: =IF(J26=K26,"<- Debits and Credits equal each other.","<- Debits and Credits do not equal each other.") -> <- Debits and Credits equal each other.
B27: * THESE ASSET AMOUNTS SHOULD BE REPORTED AS BEGINNING BALANCES ON REPORT 18.
B28: ** This amount should be included in the beginning balance column on the LS-Lease Liability and LS-Check Figures Tabs.
A31: Record New Leases (new leases only)
A32: 1 | B32: Record lease contract commencement (fund-based entries only)
B33: Dr: Acct 0842 - CAPITAL OUTLAY | J33: 1361026
C34: Cr: Acct 0789 - LEASE AND OTHER FINANCING PROCEEDS | K34: 1361026
C35: =IF($F$7="Proprietary","Cr: Acct 0870 - SERVICES & CHARGES (MG ADJ)",VLOOKUP($F$9,'[7]Drop Down Menus'!$F$2:$G$10,2,FALSE)) -> Cr: Acct 0825 - BUS, CONSUMER SERV, HOUSING
J36: =SUM(J33:J35) -> 1361026 | K36: =SUM(K33:K35) -> 1361026 | L36: =IF(J36=K36,"<- Debits and Credits equal each other.","<- Debits and Credits do not equal each other.") -> <- Debits and Credits equal each other.
A38: 2 | B38: Record leased assets.
A39: *Rpt 18 | B39: Dr: Acct 0476 - RIGHT-TO-USE LEASED LAND - AMORTIZABLE
A40: *Rpt 18 | B40: Dr: Acct 0478 - RIGHT-TO-USE LEASED EQUIPMENT - AMORTIZABLE
A41: *Rpt 18 | B41: Dr: Acct 0477 - RIGHT-TO-USE LEASED BUILDINGS - AMORTIZABLE | J41: 1361026
C42: Cr: Acct 0842 - CAPITAL OUTLAY | K42: 1361026
B43: * THESE AMOUNTS SHOULD BE INCLUDED AS "ADDITIONS" ON REPORT 18. | J43: =SUM(J39:J42) -> 1361026 | K43: =SUM(K39:K42) -> 1361026 | L43: =IF(J43=K43,"<- Debits and Credits equal each other.","<- Debits and Credits do not equal each other.") -> <- Debits and Credits equal each other.
A46: 3 | B46: Replace proceeds from leases with right-to-use lease liability.
B47: Dr: Acct 0789 - LEASE AND OTHER FINANCING PROCEEDS | J47: 1361026
A48: **LS LL/CF | C48: Cr: Acct 0691 - RIGHT-TO-USE LEASE LIABILITY | K48: 1361026
J49: =SUM(J47:J48) -> 1361026 | K49: =SUM(K47:K48) -> 1361026 | L49: =IF(J49=K49,"<- Debits and Credits equal each other.","<- Debits and Credits do not equal each other.") -> <- Debits and Credits equal each other.
B50: ** This amount should be included in the additions column on the LS-Lease Liability and LS-Check Figures Tabs.
A53: Record Annual Activity (all leases)
A54: 4 | B54: Record amortization of the leased assets for the year.
B55: Dr: Acct 0875 - DEPRECIATION/AMORTIZATION | J55: 5078387
C56: Cr: Acct 0485 - ACCUMULATED AMORTIZATION - RIGHT-TO-USE LEASED LAND
C57: Cr: Acct 0479 - ACCUMULATED AMORTIZATION - RIGHT-TO-USE LEASED EQUIPMENT
C58: Cr: Acct 0486 - ACCUMULATED AMORTIZATION - RIGHT-TO-USE LEASED BUILDINGS | K58: 5078387
J59: =SUM(J55:J58) -> 5078387 | K59: =SUM(K55:K58) -> 5078387 | L59: =IF(J59=K59,"<- Debits and Credits equal each other.","<- Debits and Credits do not equal each other.") -> <- Debits and Credits equal each other.
A61: 5 | B61: Reclassify rents and leases exp. to lease contract principal and interest exp.
B62: Dr: Acct 0848 - DEBT SERVICE - PRINCIPAL LEASES | J62: 5118817 | L62: =IF($J$62=$K$69,"","<- Accts 0848 must agree")
B63: =IF(F7="Governmental","Dr: Acct 0851 - DEBT SERVICE - INTEREST LEASES","Dr: Acct 0894 - INTEREST EXPENSE AND FISCAL CHARGES") -> Dr: Acct 0851 - DEBT SERVICE - INTEREST LEASES | J63: 42262
C64: =IF($F$7="Proprietary","Cr: Acct 0870 - SERVICES & CHARGES (MG ADJ)",VLOOKUP($F$9,'[7]Drop Down Menus'!$F$2:$G$10,2,FALSE)) -> Cr: Acct 0825 - BUS, CONSUMER SERV, HOUSING | K64: 5161079
J65: =SUM(J62:J64) -> 5161079 | K65: =SUM(K62:K64) -> 5161079 | L65: =IF(J65=K65,"<- Debits and Credits equal each other.","<- Debits and Credits do not equal each other.") -> <- Debits and Credits equal each other.
A67: 6 | B67: Reduce lease contracts liability for total current year principal payments.
A68: **LS LL/CF | B68: Dr: Acct 0691 - RIGHT-TO-USE LEASE LIABILITY | J68: 5118817
C69: Cr: Acct 0848 - DEBT SERVICE - PRINCIPAL LEASES | K69: 5118817 | L69: =IF($J$62=$K$69,"","<- Accts 0848 must agree")
J70: =SUM(J68:J69) -> 5118817 | K70: =SUM(K68:K69) -> 5118817 | L70: =IF(J70=K70,"<- Debits and Credits equal each other.","<- Debits and Credits do not equal each other.") -> <- Debits and Credits equal each other.
B71: ** This amount should be included in the deductions column on the LS-Lease Liability and LS-Check Figures Tabs.
A74: 7 | B74: Reclassify the principal amount due in the next FY to the current liability.
A75: **LS LL/CF | B75: Dr: Acct 0691 - RIGHT-TO-USE LEASE LIABILITY | J75: 1267632
C76: Cr: Acct 0649 - RIGHT-TO-USE LEASE LIABILITY (CURRENT PORTION LT) | K76: 1267632
B77: NOTE: This is an annual accrual. It is to be reversed at the start of the next fiscal year. SCO combines the current and non current amount in Entry #0 to reestablish the beginning balances. No action required. | J77: =SUM(J75:J76) -> 1267632 | K77: =SUM(K75:K76) -> 1267632 | L77: =IF(J77=K77,"<- Debits and Credits equal each other.","<- Debits and Credits do not equal each other.") -> <- Debits and Credits equal each other.
B80: ** This amount should be included in the due in one year column on the LS-Lease Liability and LS-Check Figures Tabs.
A83: Remove Lease Asset at the End of the Lease Term (only at the end of the lease term)
A84: 8 | B84: Record entry to write off the lease asset and accumulated amortization at the end of the lease term.
B85: Dr: Acct 0485 - ACCUMULATED AMORTIZATION - RIGHT-TO-USE LEASED LAND
B86: Dr: Acct 0479 - ACCUMULATED AMORTIZATION - RIGHT-TO-USE LEASED EQUIPMENT
B87: Dr: Acct 0486 - ACCUMULATED AMORTIZATION - RIGHT-TO-USE LEASED BUILDINGS | J87: 358191
A88: *Rpt 18 | C88: Cr: Acct 0476 - RIGHT-TO-USE LEASED LAND - AMORTIZABLE
A89: *Rpt 18 | C89: Cr: Acct 0478 - RIGHT-TO-USE LEASED EQUIPMENT - AMORTIZABLE
A90: *Rpt 18 | C90: Cr: Acct 0477 - RIGHT-TO-USE LEASED BUILDINGS - AMORTIZABLE | K90: 358191
B91: * THESE AMOUNTS SHOULD BE INCLUDED AS "DEDUCTIONS" ON REPORT 18. | J91: =SUM(J85:J90) -> 358191 | K91: =SUM(K85:K90) -> 358191 | L91: =IF(J91=K91,"<- Debits and Credits equal each other.","<- Debits and Credits do not equal each other.") -> <- Debits and Credits equal each other.
A94: Lease Remeasurement and Modifications (only if a significant modification occurred during the fiscal year)
A95: 9 | B95: Record early termination or lease modifications to decrease in the RTU leased asset.
A96: **LS LL/CF | B96: Dr: Acct 0691 - RIGHT-TO-USE LEASE LIABILITY
B97: Dr: Acct 0485 - ACCUMULATED AMORTIZATION - RIGHT-TO-USE LEASED LAND
B98: Dr: Acct 0479 - ACCUMULATED AMORTIZATION - RIGHT-TO-USE LEASED EQUIPMENT
B99: Dr: Acct 0486 - ACCUMULATED AMORTIZATION - RIGHT-TO-USE LEASED BUILDINGS
B100: =IF($F$7="Proprietary","Dr: Acct 0870 - SERVICES & CHARGES (MG ADJ)",VLOOKUP($F$9,'[7]Drop Down Menus'!$F$2:$H$10,3,FALSE)) -> Dr: Acct 0825 - BUS, CONSUMER SERV, HOUSING
A101: *Rpt 18 | C101: Cr: Acct 0476 - RIGHT-TO-USE LEASED LAND - AMORTIZABLE
A102: *Rpt 18 | C102: Cr: Acct 0478 - RIGHT-TO-USE LEASED EQUIPMENT - AMORTIZABLE
A103: *Rpt 18 | C103: Cr: Acct 0477 - RIGHT-TO-USE LEASED BUILDINGS - AMORTIZABLE
C104: =IF($F$7="Proprietary","Dr: Acct 0870 - SERVICES & CHARGES (MG ADJ)",VLOOKUP($F$9,'[7]Drop Down Menus'!$F$2:$G$10,2,FALSE)) -> Cr: Acct 0825 - BUS, CONSUMER SERV, HOUSING
B105: * THESE AMOUNTS SHOULD BE INCLUDED AS "DEDUCTIONS" ON REPORT 18. | J105: =SUM(J96:J104) -> 0 | K105: =SUM(K96:K104) -> 0 | L105: =IF(J105=K105,"<- Debits and Credits equal each other.","<- Debits and Credits do not equal each other.") -> <- Debits and Credits equal each other.
B106: ** This amount should be included in the deductions column on the LS-Lease Liability and LS-Check Figures Tabs.
A109: 10 | B109: Record lease modifications to increase in the RTU leased asset.
A110: *Rpt 18 | B110: Dr: Acct 0476 - RIGHT-TO-USE LEASED LAND - AMORTIZABLE
A111: *Rpt 18 | B111: Dr: Acct 0478 - RIGHT-TO-USE LEASED EQUIPMENT - AMORTIZABLE
A112: *Rpt 18 | B112: Dr: Acct 0477 - RIGHT-TO-USE LEASED BUILDINGS - AMORTIZABLE
A113: **LS LL/CF | C113: Cr: Acct 0691 - RIGHT-TO-USE LEASE LIABILITY
B114: * THESE AMOUNTS SHOULD BE INCLUDED AS "ADDITIONS" ON REPORT 18. | J114: =SUM(J110:J113) -> 0 | K114: =SUM(K110:K113) -> 0 | L114: =IF(J114=K114,"<- Debits and Credits equal each other.","<- Debits and Credits do not equal each other.") -> <- Debits and Credits equal each other.
B115: ** This amount should be included in the additions column on the LS-Lease Liability and LS-Check Figures Tabs.
D120: Informational - Ending Balances of Assets and Liabilities
K121: Debit (Credit)
D122: Acct 0476 - RIGHT-TO-USE LEASED LAND - AMORTIZABLE | K122: =J15+J39-K88-K101+J110 -> 0
D123: Acct 0478 - RIGHT-TO-USE LEASED EQUIPMENT - AMORTIZABLE | K123: =J16+J40-K89-K102+J111 -> 0
D124: Acct 0477 - RIGHT-TO-USE LEASED BUILDINGS - AMORTIZABLE | K124: =J17+J41-K90-K103+J112 -> 16880637
D125: Acct 0485 - ACCUMULATED AMORTIZATION - RIGHT-TO-USE LEASED LAND | K125: =-K20-K56+J85+J97 -> 0
...

Sheet LS-Fund 0735 Journal Entries
A1: Lessee-Type Contracts Fund-by-Fund Journal Entries Form (to be submitted to the SCO annually—one form per fund)
A2: Manually complete every yellow field in this worksheet—there are no automatically calculated data-entry cells in this worksheet.
A3: Fiscal Year: | F3: 2023–2024
A4: Organization Name: | F4: Department of Consumer Affairs
A5: Organization Code (4-Digits): | F5: 1111
A6: Fund Number (4-Digits): | F6: 735
A7: Fund Classification: | F7: Governmental
A8: Fund Type: | F8: Governmental Fund
A9: Functional Expense: | F9: =IFERROR(IF(F7="Proprietary","Proprietary Fund",VLOOKUP(F5,[8]qryIndex02a!$A$2:$K$654,4,FALSE)),"Unidentified") -> BUS, CONSUMER SERV, HOUSING
A12: Establish Beginning Balances (existing leases only)
A13: Entry #
A14: 0 | B14: Roll forward prior year right-to-use leases to record opening balances. | M14: Combined Lessee Templates | P14: From SCO BB List | S14: Difference
A15: *Rpt 18 | B15: Dr: Acct 0476 - RIGHT-TO-USE LEASED LAND - AMORTIZABLE | J15: =M15 -> 0 | S15: =P15-M15 -> 0 | T15: Report any "Differences" on the Report 18 Differential.
A16: *Rpt 18 | B16: Dr: Acct 0478 - RIGHT-TO-USE LEASED EQUIPMENT - AMORTIZABLE | J16: =M16 -> 0 | S16: =P16-M16 -> 0 | T16: Report any "Differences" on the Report 18 Differential.
A17: *Rpt 18 | B17: Dr: Acct 0477 - RIGHT-TO-USE LEASED BUILDINGS - AMORTIZABLE | J17: =M17 -> 1423813 | M17: 1423813 | P17: 1423813 | S17: =P17-M17 -> 0 | T17: Report any "Differences" on the Report 18 Differential.
B18: Dr: Acct 0950 - BEGINNING FUND BALANCE | J18: =P18 -> 16941 | M18: 16941 | P18: =IF(SUM($Q$20:$Q$23)>SUM($P$15:$P$17),SUM($Q$20:$Q$23)-SUM($P$15:$P$17),0) -> 16941 | S18: =P18-M18 -> 0 | T18: No action required.
B19: Dr: Acct 0952 - BEGINNING FUND ADJUSTMENT/PRIOR PERIOD ADJUSTMENT | J19: =IF(SUM($K$20:$K$24)>SUM($J$15:$J$18),SUM($K$20:$K$24)-SUM($J$15:$J$18),0) -> 0 | S19: =P19-M19 -> 0 | T19: No action required.
C20: Cr: Acct 0485 - ACCUMULATED AMORTIZATION - RIGHT-TO-USE LEASED LAND | K20: =N20 -> 0 | S20: =Q20-N20 -> 0 | T20: No action required.
C21: Cr: Acct 0479 - ACCUMULATED AMORTIZATION - RIGHT-TO-USE LEASED EQUIPMENT | K21: =N21 -> 0 | S21: =Q21-N21 -> 0 | T21: No action required.
C22: Cr: Acct 0486 - ACCUMULATED AMORTIZATION - RIGHT-TO-USE LEASED BUILDINGS | K22: =N22 -> 814279 | N22: 814279 | Q22: 814279 | S22: =Q22-N22 -> 0 | T22: No action required.
A23: **LS LL/CF | C23: Cr: Acct 0691 - RIGHT-TO-USE LEASE LIABILITY | K23: =N23 -> 626475 | N23: 626475 | Q23: 626475 | S23: =Q23-N23 -> 0 | T23: No action required.
C24: Cr: Acct 0950 - BEGINNING FUND BALANCE | K24: =Q24 -> 0 | Q24: =IF(SUM($Q$20:$Q$23)<SUM($P$15:$P$17),-SUM($Q$20:$Q$23)+SUM($P$15:$P$17),0) -> 0 | S24: =Q24-N24 -> 0 | T24: No action required.
C25: Cr: Acct 0952 - BEGINNING FUND ADJUSTMENT/PRIOR PERIOD ADJUSTMENT | K25: =IF(SUM($K$20:$K$24)<SUM($J$15:$J$18),-SUM($K$20:$K$24)+SUM($J$15:$J$18),0) -> 0 | S25: =Q25-N25 -> 0 | T25: No action required.
J26: =SUM(J15:J25) -> 1440754 | K26: =SUM(K15:K25) -> 1440754 | L26: =IF(J26=K26,"<- Debits and Credits equal each other.","<- Debits and Credits do not equal each other.") -> <- Debits and Credits equal each other.
B27: * THESE ASSET AMOUNTS SHOULD BE REPORTED AS BEGINNING BALANCES ON REPORT 18.
B28: ** This amount should be included in the beginning balance column on the LS-Lease Liability and LS-Check Figures Tabs.
A31: Record New Leases (new leases only)
A32: 1 | B32: Record lease contract commencement (fund-based entries only)
B33: Dr: Acct 0842 - CAPITAL OUTLAY | J33: 11108176
C34: Cr: Acct 0789 - LEASE AND OTHER FINANCING PROCEEDS | K34: 11108176
C35: =IF($F$7="Proprietary","Cr: Acct 0870 - SERVICES & CHARGES (MG ADJ)",VLOOKUP($F$9,'[8]Drop Down Menus'!$F$2:$G$10,2,FALSE)) -> Cr: Acct 0825 - BUS, CONSUMER SERV, HOUSING
J36: =SUM(J33:J35) -> 11108176 | K36: =SUM(K33:K35) -> 11108176 | L36: =IF(J36=K36,"<- Debits and Credits equal each other.","<- Debits and Credits do not equal each other.") -> <- Debits and Credits equal each other.
A38: 2 | B38: Record leased assets.
A39: *Rpt 18 | B39: Dr: Acct 0476 - RIGHT-TO-USE LEASED LAND - AMORTIZABLE
A40: *Rpt 18 | B40: Dr: Acct 0478 - RIGHT-TO-USE LEASED EQUIPMENT - AMORTIZABLE
A41: *Rpt 18 | B41: Dr: Acct 0477 - RIGHT-TO-USE LEASED BUILDINGS - AMORTIZABLE | J41: 11108176
C42: Cr: Acct 0842 - CAPITAL OUTLAY | K42: 11108176
B43: * THESE AMOUNTS SHOULD BE INCLUDED AS "ADDITIONS" ON REPORT 18. | J43: =SUM(J39:J42) -> 11108176 | K43: =SUM(K39:K42) -> 11108176 | L43: =IF(J43=K43,"<- Debits and Credits equal each other.","<- Debits and Credits do not equal each other.") -> <- Debits and Credits equal each other.
A46: 3 | B46: Replace proceeds from leases with right-to-use lease liability.
B47: Dr: Acct 0789 - LEASE AND OTHER FINANCING PROCEEDS | J47: 11108176
A48: **LS LL/CF | C48: Cr: Acct 0691 - RIGHT-TO-USE LEASE LIABILITY | K48: 11108176
J49: =SUM(J47:J48) -> 11108176 | K49: =SUM(K47:K48) -> 11108176 | L49: =IF(J49=K49,"<- Debits and Credits equal each other.","<- Debits and Credits do not equal each other.") -> <- Debits and Credits equal each other.
B50: ** This amount should be included in the additions column on the LS-Lease Liability and LS-Check Figures Tabs.
A53: Record Annual Activity (all leases)
A54: 4 | B54: Record amortization of the leased assets for the year.
B55: Dr: Acct 0875 - DEPRECIATION/AMORTIZATION | J55: 589240
C56: Cr: Acct 0485 - ACCUMULATED AMORTIZATION - RIGHT-TO-USE LEASED LAND
C57: Cr: Acct 0479 - ACCUMULATED AMORTIZATION - RIGHT-TO-USE LEASED EQUIPMENT
C58: Cr: Acct 0486 - ACCUMULATED AMORTIZATION - RIGHT-TO-USE LEASED BUILDINGS | K58: 589240
J59: =SUM(J55:J58) -> 589240 | K59: =SUM(K55:K58) -> 589240 | L59: =IF(J59=K59,"<- Debits and Credits equal each other.","<- Debits and Credits do not equal each other.") -> <- Debits and Credits equal each other.
A61: 5 | B61: Reclassify rents and leases exp. to lease contract principal and interest exp.
B62: Dr: Acct 0848 - DEBT SERVICE - PRINCIPAL LEASES | J62: 393355 | L62: =IF($J$62=$K$69,"","<- Accts 0848 must agree")
B63: =IF(F7="Governmental","Dr: Acct 0851 - DEBT SERVICE - INTEREST LEASES","Dr: Acct 0894 - INTEREST EXPENSE AND FISCAL CHARGES") -> Dr: Acct 0851 - DEBT SERVICE - INTEREST LEASES | J63: 23275
C64: =IF($F$7="Proprietary","Cr: Acct 0870 - SERVICES & CHARGES (MG ADJ)",VLOOKUP($F$9,'[8]Drop Down Menus'!$F$2:$G$10,2,FALSE)) -> Cr: Acct 0825 - BUS, CONSUMER SERV, HOUSING | K64: 416630
J65: =SUM(J62:J64) -> 416630 | K65: =SUM(K62:K64) -> 416630 | L65: =IF(J65=K65,"<- Debits and Credits equal each other.","<- Debits and Credits do not equal each other.") -> <- Debits and Credits equal each other.
A67: 6 | B67: Reduce lease contracts liability for total current year principal payments.
A68: **LS LL/CF | B68: Dr: Acct 0691 - RIGHT-TO-USE LEASE LIABILITY | J68: 393355
C69: Cr: Acct 0848 - DEBT SERVICE - PRINCIPAL LEASES | K69: 393355 | L69: =IF($J$62=$K$69,"","<- Accts 0848 must agree")
J70: =SUM(J68:J69) -> 393355 | K70: =SUM(K68:K69) -> 393355 | L70: =IF(J70=K70,"<- Debits and Credits equal each other.","<- Debits and Credits do not equal each other.") -> <- Debits and Credits equal each other.
B71: ** This amount should be included in the deductions column on the LS-Lease Liability and LS-Check Figures Tabs.
A74: 7 | B74: Reclassify the principal amount due in the next FY to the current liability.
A75: **LS LL/CF | B75: Dr: Acct 0691 - RIGHT-TO-USE LEASE LIABILITY | J75: 2216583
C76: Cr: Acct 0649 - RIGHT-TO-USE LEASE LIABILITY (CURRENT PORTION LT) | K76: 2216583
B77: NOTE: This is an annual accrual. It is to be reversed at the start of the next fiscal year. SCO combines the current and non current amount in Entry #0 to reestablish the beginning balances. No action required. | J77: =SUM(J75:J76) -> 2216583 | K77: =SUM(K75:K76) -> 2216583 | L77: =IF(J77=K77,"<- Debits and Credits equal each other.","<- Debits and Credits do not equal each other.") -> <- Debits and Credits equal each other.
B80: ** This amount should be included in the due in one year column on the LS-Lease Liability and LS-Check Figures Tabs.
A83: Remove Lease Asset at the End of the Lease Term (only at the end of the lease term)
A84: 8 | B84: Record entry to write off the lease asset and accumulated amortization at the end of the lease term.
B85: Dr: Acct 0485 - ACCUMULATED AMORTIZATION - RIGHT-TO-USE LEASED LAND
B86: Dr: Acct 0479 - ACCUMULATED AMORTIZATION - RIGHT-TO-USE LEASED EQUIPMENT
B87: Dr: Acct 0486 - ACCUMULATED AMORTIZATION - RIGHT-TO-USE LEASED BUILDINGS
A88: *Rpt 18 | C88: Cr: Acct 0476 - RIGHT-TO-USE LEASED LAND - AMORTIZABLE
A89: *Rpt 18 | C89: Cr: Acct 0478 - RIGHT-TO-USE LEASED EQUIPMENT - AMORTIZABLE
A90: *Rpt 18 | C90: Cr: Acct 0477 - RIGHT-TO-USE LEASED BUILDINGS - AMORTIZABLE
B91: * THESE AMOUNTS SHOULD BE INCLUDED AS "DEDUCTIONS" ON REPORT 18. | J91: =SUM(J85:J90) -> 0 | K91: =SUM(K85:K90) -> 0 | L91: =IF(J91=K91,"<- Debits and Credits equal each other.","<- Debits and Credits do not equal each other.") -> <- Debits and Credits equal each other.
A94: Lease Remeasurement and Modifications (only if a significant modification occurred during the fiscal year)
A95: 9 | B95: Record early termination or lease modifications to decrease in the RTU leased asset.
A96: **LS LL/CF | B96: Dr: Acct 0691 - RIGHT-TO-USE LEASE LIABILITY
B97: Dr: Acct 0485 - ACCUMULATED AMORTIZATION - RIGHT-TO-USE LEASED LAND
B98: Dr: Acct 0479 - ACCUMULATED AMORTIZATION - RIGHT-TO-USE LEASED EQUIPMENT
B99: Dr: Acct 0486 - ACCUMULATED AMORTIZATION - RIGHT-TO-USE LEASED BUILDINGS
B100: =IF($F$7="Proprietary","Dr: Acct 0870 - SERVICES & CHARGES (MG ADJ)",VLOOKUP($F$9,'[8]Drop Down Menus'!$F$2:$H$10,3,FALSE)) -> Dr: Acct 0825 - BUS, CONSUMER SERV, HOUSING
A101: *Rpt 18 | C101: Cr: Acct 0476 - RIGHT-TO-USE LEASED LAND - AMORTIZABLE
A102: *Rpt 18 | C102: Cr: Acct 0478 - RIGHT-TO-USE LEASED EQUIPMENT - AMORTIZABLE
A103: *Rpt 18 | C103: Cr: Acct 0477 - RIGHT-TO-USE LEASED BUILDINGS - AMORTIZABLE
C104: =IF($F$7="Proprietary","Dr: Acct 0870 - SERVICES & CHARGES (MG ADJ)",VLOOKUP($F$9,'[8]Drop Down Menus'!$F$2:$G$10,2,FALSE)) -> Cr: Acct 0825 - BUS, CONSUMER SERV, HOUSING
B105: * THESE AMOUNTS SHOULD BE INCLUDED AS "DEDUCTIONS" ON REPORT 18. | J105: =SUM(J96:J104) -> 0 | K105: =SUM(K96:K104) -> 0 | L105: =IF(J105=K105,"<- Debits and Credits equal each other.","<- Debits and Credits do not equal each other.") -> <- Debits and Credits equal each other.
B106: ** This amount should be included in the deductions column on the LS-Lease Liability and LS-Check Figures Tabs.
A109: 10 | B109: Record lease modifications to increase in the RTU leased asset.
A110: *Rpt 18 | B110: Dr: Acct 0476 - RIGHT-TO-USE LEASED LAND - AMORTIZABLE
A111: *Rpt 18 | B111: Dr: Acct 0478 - RIGHT-TO-USE LEASED EQUIPMENT - AMORTIZABLE
A112: *Rpt 18 | B112: Dr: Acct 0477 - RIGHT-TO-USE LEASED BUILDINGS - AMORTIZABLE
A113: **LS LL/CF | C113: Cr: Acct 0691 - RIGHT-TO-USE LEASE LIABILITY
B114: * THESE AMOUNTS SHOULD BE INCLUDED AS "ADDITIONS" ON REPORT 18. | J114: =SUM(J110:J113) -> 0 | K114: =SUM(K110:K113) -> 0 | L114: =IF(J114=K114,"<- Debits and Credits equal each other.","<- Debits and Credits do not equal each other.") -> <- Debits and Credits equal each other.
B115: ** This amount should be included in the additions column on the LS-Lease Liability and LS-Check Figures Tabs.
D120: Informational - Ending Balances of Assets and Liabilities
K121: Debit (Credit)
D122: Acct 0476 - RIGHT-TO-USE LEASED LAND - AMORTIZABLE | K122: =J15+J39-K88-K101+J110 -> 0
D123: Acct 0478 - RIGHT-TO-USE LEASED EQUIPMENT - AMORTIZABLE | K123: =J16+J40-K89-K102+J111 -> 0
D124: Acct 0477 - RIGHT-TO-USE LEASED BUILDINGS - AMORTIZABLE | K124: =J17+J41-K90-K103+J112 -> 12531989
D125: Acct 0485 - ACCUMULATED AMORTIZATION - RIGHT-TO-USE LEASED LAND | K125: =-K20-K56+J85+J97 -> 0
...

Sheet LS-Fund 0758 Journal Entries
A1: Lessee-Type Contracts Fund-by-Fund Journal Entries Form (to be submitted to the SCO annually—one form per fund)
A2: Manually complete every yellow field in this worksheet—there are no automatically calculated data-entry cells in this worksheet.
A3: Fiscal Year: | F3: 2023–2024
A4: Organization Name: | F4: Department of Consumer Affairs
A5: Organization Code (4-Digits): | F5: 1111
A6: Fund Number (4-Digits): | F6: 758
A7: Fund Classification: | F7: Governmental
A8: Fund Type: | F8: Governmental Fund
A9: Functional Expense: | F9: =IFERROR(IF(F7="Proprietary","Proprietary Fund",VLOOKUP(F5,[9]qryIndex02a!$A$2:$K$654,4,FALSE)),"Unidentified") -> BUS, CONSUMER SERV, HOUSING
A12: Establish Beginning Balances (existing leases only)
A13: Entry #
A14: 0 | B14: Roll forward prior year right-to-use leases to record opening balances. | M14: Combined Lessee Templates | P14: From SCO BB List | S14: Difference
A15: *Rpt 18 | B15: Dr: Acct 0476 - RIGHT-TO-USE LEASED LAND - AMORTIZABLE | J15: =M15 -> 0 | S15: =P15-M15 -> 0 | T15: Report any "Differences" on the Report 18 Differential.
A16: *Rpt 18 | B16: Dr: Acct 0478 - RIGHT-TO-USE LEASED EQUIPMENT - AMORTIZABLE | J16: =M16 -> 0 | S16: =P16-M16 -> 0 | T16: Report any "Differences" on the Report 18 Differential.
A17: *Rpt 18 | B17: Dr: Acct 0477 - RIGHT-TO-USE LEASED BUILDINGS - AMORTIZABLE | J17: =M17 -> 9256185 | M17: 9256185 | P17: 9256185 | S17: =P17-M17 -> 0 | T17: Report any "Differences" on the Report 18 Differential.
B18: Dr: Acct 0950 - BEGINNING FUND BALANCE | J18: =P18 -> 119134 | M18: 119134 | P18: =IF(SUM($Q$20:$Q$23)>SUM($P$15:$P$17),SUM($Q$20:$Q$23)-SUM($P$15:$P$17),0) -> 119134 | S18: =P18-M18 -> 0 | T18: No action required.
B19: Dr: Acct 0952 - BEGINNING FUND ADJUSTMENT/PRIOR PERIOD ADJUSTMENT | J19: =IF(SUM($K$20:$K$24)>SUM($J$15:$J$18),SUM($K$20:$K$24)-SUM($J$15:$J$18),0) -> 0 | S19: =P19-M19 -> 0 | T19: No action required.
C20: Cr: Acct 0485 - ACCUMULATED AMORTIZATION - RIGHT-TO-USE LEASED LAND | K20: =N20 -> 0 | S20: =Q20-N20 -> 0 | T20: No action required.
C21: Cr: Acct 0479 - ACCUMULATED AMORTIZATION - RIGHT-TO-USE LEASED EQUIPMENT | K21: =N21 -> 0 | S21: =Q21-N21 -> 0 | T21: No action required.
C22: Cr: Acct 0486 - ACCUMULATED AMORTIZATION - RIGHT-TO-USE LEASED BUILDINGS | K22: =N22 -> 4726562 | N22: 4726562 | Q22: 4726562 | S22: =Q22-N22 -> 0 | T22: No action required.
A23: **LS LL/CF | C23: Cr: Acct 0691 - RIGHT-TO-USE LEASE LIABILITY | K23: =N23 -> 4648757 | N23: 4648757 | Q23: 4648757 | S23: =Q23-N23 -> 0 | T23: No action required.
C24: Cr: Acct 0950 - BEGINNING FUND BALANCE | K24: =Q24 -> 0 | Q24: =IF(SUM($Q$20:$Q$23)<SUM($P$15:$P$17),-SUM($Q$20:$Q$23)+SUM($P$15:$P$17),0) -> 0 | S24: =Q24-N24 -> 0 | T24: No action required.
C25: Cr: Acct 0952 - BEGINNING FUND ADJUSTMENT/PRIOR PERIOD ADJUSTMENT | K25: =IF(SUM($K$20:$K$24)<SUM($J$15:$J$18),-SUM($K$20:$K$24)+SUM($J$15:$J$18),0) -> 0 | S25: =Q25-N25 -> 0 | T25: No action required.
J26: =SUM(J15:J25) -> 9375319 | K26: =SUM(K15:K25) -> 9375319 | L26: =IF(J26=K26,"<- Debits and Credits equal each other.","<- Debits and Credits do not equal each other.") -> <- Debits and Credits equal each other.
B27: * THESE ASSET AMOUNTS SHOULD BE REPORTED AS BEGINNING BALANCES ON REPORT 18.
B28: ** This amount should be included in the beginning balance column on the LS-Lease Liability and LS-Check Figures Tabs.
A31: Record New Leases (new leases only)
A32: 1 | B32: Record lease contract commencement (fund-based entries only)
B33: Dr: Acct 0842 - CAPITAL OUTLAY
C34: Cr: Acct 0789 - LEASE AND OTHER FINANCING PROCEEDS
C35: =IF($F$7="Proprietary","Cr: Acct 0870 - SERVICES & CHARGES (MG ADJ)",VLOOKUP($F$9,'[9]Drop Down Menus'!$F$2:$G$10,2,FALSE)) -> Cr: Acct 0825 - BUS, CONSUMER SERV, HOUSING
J36: =SUM(J33:J35) -> 0 | K36: =SUM(K33:K35) -> 0 | L36: =IF(J36=K36,"<- Debits and Credits equal each other.","<- Debits and Credits do not equal each other.") -> <- Debits and Credits equal each other.
A38: 2 | B38: Record leased assets.
A39: *Rpt 18 | B39: Dr: Acct 0476 - RIGHT-TO-USE LEASED LAND - AMORTIZABLE
A40: *Rpt 18 | B40: Dr: Acct 0478 - RIGHT-TO-USE LEASED EQUIPMENT - AMORTIZABLE
A41: *Rpt 18 | B41: Dr: Acct 0477 - RIGHT-TO-USE LEASED BUILDINGS - AMORTIZABLE
C42: Cr: Acct 0842 - CAPITAL OUTLAY
B43: * THESE AMOUNTS SHOULD BE INCLUDED AS "ADDITIONS" ON REPORT 18. | J43: =SUM(J39:J42) -> 0 | K43: =SUM(K39:K42) -> 0 | L43: =IF(J43=K43,"<- Debits and Credits equal each other.","<- Debits and Credits do not equal each other.") -> <- Debits and Credits equal each other.
A46: 3 | B46: Replace proceeds from leases with right-to-use lease liability.
B47: Dr: Acct 0789 - LEASE AND OTHER FINANCING PROCEEDS
A48: **LS LL/CF | C48: Cr: Acct 0691 - RIGHT-TO-USE LEASE LIABILITY
J49: =SUM(J47:J48) -> 0 | K49: =SUM(K47:K48) -> 0 | L49: =IF(J49=K49,"<- Debits and Credits equal each other.","<- Debits and Credits do not equal each other.") -> <- Debits and Credits equal each other.
B50: ** This amount should be included in the additions column on the LS-Lease Liability and LS-Check Figures Tabs.
A53: Record Annual Activity (all leases)
A54: 4 | B54: Record amortization of the leased assets for the year.
B55: Dr: Acct 0875 - DEPRECIATION/AMORTIZATION | J55: 2363281
C56: Cr: Acct 0485 - ACCUMULATED AMORTIZATION - RIGHT-TO-USE LEASED LAND
C57: Cr: Acct 0479 - ACCUMULATED AMORTIZATION - RIGHT-TO-USE LEASED EQUIPMENT
C58: Cr: Acct 0486 - ACCUMULATED AMORTIZATION - RIGHT-TO-USE LEASED BUILDINGS | K58: 2363281
J59: =SUM(J55:J58) -> 2363281 | K59: =SUM(K55:K58) -> 2363281 | L59: =IF(J59=K59,"<- Debits and Credits equal each other.","<- Debits and Credits do not equal each other.") -> <- Debits and Credits equal each other.
A61: 5 | B61: Reclassify rents and leases exp. to lease contract principal and interest exp.
B62: Dr: Acct 0848 - DEBT SERVICE - PRINCIPAL LEASES | J62: 2396955 | L62: =IF($J$62=$K$69,"","<- Accts 0848 must agree")
B63: =IF(F7="Governmental","Dr: Acct 0851 - DEBT SERVICE - INTEREST LEASES","Dr: Acct 0894 - INTEREST EXPENSE AND FISCAL CHARGES") -> Dr: Acct 0851 - DEBT SERVICE - INTEREST LEASES | J63: 7115
C64: =IF($F$7="Proprietary","Cr: Acct 0870 - SERVICES & CHARGES (MG ADJ)",VLOOKUP($F$9,'[9]Drop Down Menus'!$F$2:$G$10,2,FALSE)) -> Cr: Acct 0825 - BUS, CONSUMER SERV, HOUSING | K64: 2404070
J65: =SUM(J62:J64) -> 2404070 | K65: =SUM(K62:K64) -> 2404070 | L65: =IF(J65=K65,"<- Debits and Credits equal each other.","<- Debits and Credits do not equal each other.") -> <- Debits and Credits equal each other.
A67: 6 | B67: Reduce lease contracts liability for total current year principal payments.
A68: **LS LL/CF | B68: Dr: Acct 0691 - RIGHT-TO-USE LEASE LIABILITY | J68: 2396955
C69: Cr: Acct 0848 - DEBT SERVICE - PRINCIPAL LEASES | K69: 2396955 | L69: =IF($J$62=$K$69,"","<- Accts 0848 must agree")
J70: =SUM(J68:J69) -> 2396955 | K70: =SUM(K68:K69) -> 2396955 | L70: =IF(J70=K70,"<- Debits and Credits equal each other.","<- Debits and Credits do not equal each other.") -> <- Debits and Credits equal each other.
B71: ** This amount should be included in the deductions column on the LS-Lease Liability and LS-Check Figures Tabs.
A74: 7 | B74: Reclassify the principal amount due in the next FY to the current liability.
A75: **LS LL/CF | B75: Dr: Acct 0691 - RIGHT-TO-USE LEASE LIABILITY | J75: 2251802
C76: Cr: Acct 0649 - RIGHT-TO-USE LEASE LIABILITY (CURRENT PORTION LT) | K76: 2251802
B77: NOTE: This is an annual accrual. It is to be reversed at the start of the next fiscal year. SCO combines the current and non current amount in Entry #0 to reestablish the beginning balances. No action required. | J77: =SUM(J75:J76) -> 2251802 | K77: =SUM(K75:K76) -> 2251802 | L77: =IF(J77=K77,"<- Debits and Credits equal each other.","<- Debits and Credits do not equal each other.") -> <- Debits and Credits equal each other.
B80: ** This amount should be included in the due in one year column on the LS-Lease Liability and LS-Check Figures Tabs.
A83: Remove Lease Asset at the End of the Lease Term (only at the end of the lease term)
A84: 8 | B84: Record entry to write off the lease asset and accumulated amortization at the end of the lease term.
B85: Dr: Acct 0485 - ACCUMULATED AMORTIZATION - RIGHT-TO-USE LEASED LAND
B86: Dr: Acct 0479 - ACCUMULATED AMORTIZATION - RIGHT-TO-USE LEASED EQUIPMENT
B87: Dr: Acct 0486 - ACCUMULATED AMORTIZATION - RIGHT-TO-USE LEASED BUILDINGS
A88: *Rpt 18 | C88: Cr: Acct 0476 - RIGHT-TO-USE LEASED LAND - AMORTIZABLE
A89: *Rpt 18 | C89: Cr: Acct 0478 - RIGHT-TO-USE LEASED EQUIPMENT - AMORTIZABLE
A90: *Rpt 18 | C90: Cr: Acct 0477 - RIGHT-TO-USE LEASED BUILDINGS - AMORTIZABLE
B91: * THESE AMOUNTS SHOULD BE INCLUDED AS "DEDUCTIONS" ON REPORT 18. | J91: =SUM(J85:J90) -> 0 | K91: =SUM(K85:K90) -> 0 | L91: =IF(J91=K91,"<- Debits and Credits equal each other.","<- Debits and Credits do not equal each other.") -> <- Debits and Credits equal each other.
A94: Lease Remeasurement and Modifications (only if a significant modification occurred during the fiscal year)
A95: 9 | B95: Record early termination or lease modifications to decrease in the RTU leased asset.
A96: **LS LL/CF | B96: Dr: Acct 0691 - RIGHT-TO-USE LEASE LIABILITY
B97: Dr: Acct 0485 - ACCUMULATED AMORTIZATION - RIGHT-TO-USE LEASED LAND
B98: Dr: Acct 0479 - ACCUMULATED AMORTIZATION - RIGHT-TO-USE LEASED EQUIPMENT
B99: Dr: Acct 0486 - ACCUMULATED AMORTIZATION - RIGHT-TO-USE LEASED BUILDINGS
B100: =IF($F$7="Proprietary","Dr: Acct 0870 - SERVICES & CHARGES (MG ADJ)",VLOOKUP($F$9,'[9]Drop Down Menus'!$F$2:$H$10,3,FALSE)) -> Dr: Acct 0825 - BUS, CONSUMER SERV, HOUSING
A101: *Rpt 18 | C101: Cr: Acct 0476 - RIGHT-TO-USE LEASED LAND - AMORTIZABLE
A102: *Rpt 18 | C102: Cr: Acct 0478 - RIGHT-TO-USE LEASED EQUIPMENT - AMORTIZABLE
A103: *Rpt 18 | C103: Cr: Acct 0477 - RIGHT-TO-USE LEASED BUILDINGS - AMORTIZABLE
C104: =IF($F$7="Proprietary","Dr: Acct 0870 - SERVICES & CHARGES (MG ADJ)",VLOOKUP($F$9,'[9]Drop Down Menus'!$F$2:$G$10,2,FALSE)) -> Cr: Acct 0825 - BUS, CONSUMER SERV, HOUSING
B105: * THESE AMOUNTS SHOULD BE INCLUDED AS "DEDUCTIONS" ON REPORT 18. | J105: =SUM(J96:J104) -> 0 | K105: =SUM(K96:K104) -> 0 | L105: =IF(J105=K105,"<- Debits and Credits equal each other.","<- Debits and Credits do not equal each other.") -> <- Debits and Credits equal each other.
B106: ** This amount should be included in the deductions column on the LS-Lease Liability and LS-Check Figures Tabs.
A109: 10 | B109: Record lease modifications to increase in the RTU leased asset.
A110: *Rpt 18 | B110: Dr: Acct 0476 - RIGHT-TO-USE LEASED LAND - AMORTIZABLE
A111: *Rpt 18 | B111: Dr: Acct 0478 - RIGHT-TO-USE LEASED EQUIPMENT - AMORTIZABLE
A112: *Rpt 18 | B112: Dr: Acct 0477 - RIGHT-TO-USE LEASED BUILDINGS - AMORTIZABLE
A113: **LS LL/CF | C113: Cr: Acct 0691 - RIGHT-TO-USE LEASE LIABILITY
B114: * THESE AMOUNTS SHOULD BE INCLUDED AS "ADDITIONS" ON REPORT 18. | J114: =SUM(J110:J113) -> 0 | K114: =SUM(K110:K113) -> 0 | L114: =IF(J114=K114,"<- Debits and Credits equal each other.","<- Debits and Credits do not equal each other.") -> <- Debits and Credits equal each other.
B115: ** This amount should be included in the additions column on the LS-Lease Liability and LS-Check Figures Tabs.
D120: Informational - Ending Balances of Assets and Liabilities
K121: Debit (Credit)
D122: Acct 0476 - RIGHT-TO-USE LEASED LAND - AMORTIZABLE | K122: =J15+J39-K88-K101+J110 -> 0
D123: Acct 0478 - RIGHT-TO-USE LEASED EQUIPMENT - AMORTIZABLE | K123: =J16+J40-K89-K102+J111 -> 0
D124: Acct 0477 - RIGHT-TO-USE LEASED BUILDINGS - AMORTIZABLE | K124: =J17+J41-K90-K103+J112 -> 9256185
D125: Acct 0485 - ACCUMULATED AMORTIZATION - RIGHT-TO-USE LEASED LAND | K125: =-K20-K56+J85+J97 -> 0
...

Sheet LS-Fund 0761 Journal Entries
A1: Lessee-Type Contracts Fund-by-Fund Journal Entries Form (to be submitted to the SCO annually—one form per fund)
A2: Manually complete every yellow field in this worksheet—there are no automatically calculated data-entry cells in this worksheet.
A3: Fiscal Year: | F3: 2023–2024
A4: Organization Name: | F4: Department of Consumer Affairs
A5: Organization Code (4-Digits): | F5: 1111
A6: Fund Number (4-Digits): | F6: 761
A7: Fund Classification: | F7: Governmental
A8: Fund Type: | F8: Governmental Fund
A9: Functional Expense: | F9: =IFERROR(IF(F7="Proprietary","Proprietary Fund",VLOOKUP(F5,[10]qryIndex02a!$A$2:$K$654,4,FALSE)),"Unidentified") -> BUS, CONSUMER SERV, HOUSING
A12: Establish Beginning Balances (existing leases only)
A13: Entry #
A14: 0 | B14: Roll forward prior year right-to-use leases to record opening balances. | M14: Combined Lessee Templates | P14: From SCO BB List | S14: Difference
A15: *Rpt 18 | B15: Dr: Acct 0476 - RIGHT-TO-USE LEASED LAND - AMORTIZABLE | J15: =M15 -> 0 | S15: =P15-M15 -> 0 | T15: Report any "Differences" on the Report 18 Differential.
A16: *Rpt 18 | B16: Dr: Acct 0478 - RIGHT-TO-USE LEASED EQUIPMENT - AMORTIZABLE | J16: =M16 -> 0 | S16: =P16-M16 -> 0 | T16: Report any "Differences" on the Report 18 Differential.
A17: *Rpt 18 | B17: Dr: Acct 0477 - RIGHT-TO-USE LEASED BUILDINGS - AMORTIZABLE | J17: =M17 -> 8845233 | M17: 8845233 | P17: 8845233 | S17: =P17-M17 -> 0 | T17: Report any "Differences" on the Report 18 Differential.
B18: Dr: Acct 0950 - BEGINNING FUND BALANCE | J18: =P18 -> 123171 | M18: 123171 | P18: =IF(SUM($Q$20:$Q$23)>SUM($P$15:$P$17),SUM($Q$20:$Q$23)-SUM($P$15:$P$17),0) -> 123171 | S18: =P18-M18 -> 0 | T18: No action required.
B19: Dr: Acct 0952 - BEGINNING FUND ADJUSTMENT/PRIOR PERIOD ADJUSTMENT | J19: =IF(SUM($K$20:$K$24)>SUM($J$15:$J$18),SUM($K$20:$K$24)-SUM($J$15:$J$18),0) -> 0 | S19: =P19-M19 -> 0 | T19: No action required.
C20: Cr: Acct 0485 - ACCUMULATED AMORTIZATION - RIGHT-TO-USE LEASED LAND | K20: =N20 -> 0 | S20: =Q20-N20 -> 0 | T20: No action required.
C21: Cr: Acct 0479 - ACCUMULATED AMORTIZATION - RIGHT-TO-USE LEASED EQUIPMENT | K21: =N21 -> 0 | S21: =Q21-N21 -> 0 | T21: No action required.
C22: Cr: Acct 0486 - ACCUMULATED AMORTIZATION - RIGHT-TO-USE LEASED BUILDINGS | K22: =N22 -> 4245710 | N22: 4245710 | Q22: 4245710 | S22: =Q22-N22 -> 0 | T22: No action required.
A23: **LS LL/CF | C23: Cr: Acct 0691 - RIGHT-TO-USE LEASE LIABILITY | K23: =N23 -> 4722694 | N23: 4722694 | Q23: 4722694 | S23: =Q23-N23 -> 0 | T23: No action required.
C24: Cr: Acct 0950 - BEGINNING FUND BALANCE | K24: =Q24 -> 0 | Q24: =IF(SUM($Q$20:$Q$23)<SUM($P$15:$P$17),-SUM($Q$20:$Q$23)+SUM($P$15:$P$17),0) -> 0 | S24: =Q24-N24 -> 0 | T24: No action required.
C25: Cr: Acct 0952 - BEGINNING FUND ADJUSTMENT/PRIOR PERIOD ADJUSTMENT | K25: =IF(SUM($K$20:$K$24)<SUM($J$15:$J$18),-SUM($K$20:$K$24)+SUM($J$15:$J$18),0) -> 0 | S25: =Q25-N25 -> 0 | T25: No action required.
J26: =SUM(J15:J25) -> 8968404 | K26: =SUM(K15:K25) -> 8968404 | L26: =IF(J26=K26,"<- Debits and Credits equal each other.","<- Debits and Credits do not equal each other.") -> <- Debits and Credits equal each other.
B27: * THESE ASSET AMOUNTS SHOULD BE REPORTED AS BEGINNING BALANCES ON REPORT 18.
B28: ** This amount should be included in the beginning balance column on the LS-Lease Liability and LS-Check Figures Tabs.
A31: Record New Leases (new leases only)
A32: 1 | B32: Record lease contract commencement (fund-based entries only)
B33: Dr: Acct 0842 - CAPITAL OUTLAY
C34: Cr: Acct 0789 - LEASE AND OTHER FINANCING PROCEEDS
C35: =IF($F$7="Proprietary","Cr: Acct 0870 - SERVICES & CHARGES (MG ADJ)",VLOOKUP($F$9,'[10]Drop Down Menus'!$F$2:$G$10,2,FALSE)) -> Cr: Acct 0825 - BUS, CONSUMER SERV, HOUSING
J36: =SUM(J33:J35) -> 0 | K36: =SUM(K33:K35) -> 0 | L36: =IF(J36=K36,"<- Debits and Credits equal each other.","<- Debits and Credits do not equal each other.") -> <- Debits and Credits equal each other.
A38: 2 | B38: Record leased assets.
A39: *Rpt 18 | B39: Dr: Acct 0476 - RIGHT-TO-USE LEASED LAND - AMORTIZABLE
A40: *Rpt 18 | B40: Dr: Acct 0478 - RIGHT-TO-USE LEASED EQUIPMENT - AMORTIZABLE
A41: *Rpt 18 | B41: Dr: Acct 0477 - RIGHT-TO-USE LEASED BUILDINGS - AMORTIZABLE
C42: Cr: Acct 0842 - CAPITAL OUTLAY
B43: * THESE AMOUNTS SHOULD BE INCLUDED AS "ADDITIONS" ON REPORT 18. | J43: =SUM(J39:J42) -> 0 | K43: =SUM(K39:K42) -> 0 | L43: =IF(J43=K43,"<- Debits and Credits equal each other.","<- Debits and Credits do not equal each other.") -> <- Debits and Credits equal each other.
A46: 3 | B46: Replace proceeds from leases with right-to-use lease liability.
B47: Dr: Acct 0789 - LEASE AND OTHER FINANCING PROCEEDS
A48: **LS LL/CF | C48: Cr: Acct 0691 - RIGHT-TO-USE LEASE LIABILITY
J49: =SUM(J47:J48) -> 0 | K49: =SUM(K47:K48) -> 0 | L49: =IF(J49=K49,"<- Debits and Credits equal each other.","<- Debits and Credits do not equal each other.") -> <- Debits and Credits equal each other.
B50: ** This amount should be included in the additions column on the LS-Lease Liability and LS-Check Figures Tabs.
A53: Record Annual Activity (all leases)
A54: 4 | B54: Record amortization of the leased assets for the year.
B55: Dr: Acct 0875 - DEPRECIATION/AMORTIZATION | J55: 2122855
C56: Cr: Acct 0485 - ACCUMULATED AMORTIZATION - RIGHT-TO-USE LEASED LAND
C57: Cr: Acct 0479 - ACCUMULATED AMORTIZATION - RIGHT-TO-USE LEASED EQUIPMENT
C58: Cr: Acct 0486 - ACCUMULATED AMORTIZATION - RIGHT-TO-USE LEASED BUILDINGS | K58: 2122855
J59: =SUM(J55:J58) -> 2122855 | K59: =SUM(K55:K58) -> 2122855 | L59: =IF(J59=K59,"<- Debits and Credits equal each other.","<- Debits and Credits do not equal each other.") -> <- Debits and Credits equal each other.
A61: 5 | B61: Reclassify rents and leases exp. to lease contract principal and interest exp.
B62: Dr: Acct 0848 - DEBT SERVICE - PRINCIPAL LEASES | J62: 2149835 | L62: =IF($J$62=$K$69,"","<- Accts 0848 must agree")
B63: =IF(F7="Governmental","Dr: Acct 0851 - DEBT SERVICE - INTEREST LEASES","Dr: Acct 0894 - INTEREST EXPENSE AND FISCAL CHARGES") -> Dr: Acct 0851 - DEBT SERVICE - INTEREST LEASES | J63: 7486
C64: =IF($F$7="Proprietary","Cr: Acct 0870 - SERVICES & CHARGES (MG ADJ)",VLOOKUP($F$9,'[10]Drop Down Menus'!$F$2:$G$10,2,FALSE)) -> Cr: Acct 0825 - BUS, CONSUMER SERV, HOUSING | K64: 2157321
J65: =SUM(J62:J64) -> 2157321 | K65: =SUM(K62:K64) -> 2157321 | L65: =IF(J65=K65,"<- Debits and Credits equal each other.","<- Debits and Credits do not equal each other.") -> <- Debits and Credits equal each other.
A67: 6 | B67: Reduce lease contracts liability for total current year principal payments.
A68: **LS LL/CF | B68: Dr: Acct 0691 - RIGHT-TO-USE LEASE LIABILITY | J68: 2149835
C69: Cr: Acct 0848 - DEBT SERVICE - PRINCIPAL LEASES | K69: 2149835 | L69: =IF($J$62=$K$69,"","<- Accts 0848 must agree")
J70: =SUM(J68:J69) -> 2149835 | K70: =SUM(K68:K69) -> 2149835 | L70: =IF(J70=K70,"<- Debits and Credits equal each other.","<- Debits and Credits do not equal each other.") -> <- Debits and Credits equal each other.
B71: ** This amount should be included in the deductions column on the LS-Lease Liability and LS-Check Figures Tabs.
A74: 7 | B74: Reclassify the principal amount due in the next FY to the current liability.
A75: **LS LL/CF | B75: Dr: Acct 0691 - RIGHT-TO-USE LEASE LIABILITY | J75: 2200517
C76: Cr: Acct 0649 - RIGHT-TO-USE LEASE LIABILITY (CURRENT PORTION LT) | K76: 2200517
B77: NOTE: This is an annual accrual. It is to be reversed at the start of the next fiscal year. SCO combines the current and non current amount in Entry #0 to reestablish the beginning balances. No action required. | J77: =SUM(J75:J76) -> 2200517 | K77: =SUM(K75:K76) -> 2200517 | L77: =IF(J77=K77,"<- Debits and Credits equal each other.","<- Debits and Credits do not equal each other.") -> <- Debits and Credits equal each other.
B80: ** This amount should be included in the due in one year column on the LS-Lease Liability and LS-Check Figures Tabs.
A83: Remove Lease Asset at the End of the Lease Term (only at the end of the lease term)
A84: 8 | B84: Record entry to write off the lease asset and accumulated amortization at the end of the lease term.
B85: Dr: Acct 0485 - ACCUMULATED AMORTIZATION - RIGHT-TO-USE LEASED LAND
B86: Dr: Acct 0479 - ACCUMULATED AMORTIZATION - RIGHT-TO-USE LEASED EQUIPMENT
B87: Dr: Acct 0486 - ACCUMULATED AMORTIZATION - RIGHT-TO-USE LEASED BUILDINGS
A88: *Rpt 18 | C88: Cr: Acct 0476 - RIGHT-TO-USE LEASED LAND - AMORTIZABLE
A89: *Rpt 18 | C89: Cr: Acct 0478 - RIGHT-TO-USE LEASED EQUIPMENT - AMORTIZABLE
A90: *Rpt 18 | C90: Cr: Acct 0477 - RIGHT-TO-USE LEASED BUILDINGS - AMORTIZABLE
B91: * THESE AMOUNTS SHOULD BE INCLUDED AS "DEDUCTIONS" ON REPORT 18. | J91: =SUM(J85:J90) -> 0 | K91: =SUM(K85:K90) -> 0 | L91: =IF(J91=K91,"<- Debits and Credits equal each other.","<- Debits and Credits do not equal each other.") -> <- Debits and Credits equal each other.
A94: Lease Remeasurement and Modifications (only if a significant modification occurred during the fiscal year)
A95: 9 | B95: Record early termination or lease modifications to decrease in the RTU leased asset.
A96: **LS LL/CF | B96: Dr: Acct 0691 - RIGHT-TO-USE LEASE LIABILITY
B97: Dr: Acct 0485 - ACCUMULATED AMORTIZATION - RIGHT-TO-USE LEASED LAND
B98: Dr: Acct 0479 - ACCUMULATED AMORTIZATION - RIGHT-TO-USE LEASED EQUIPMENT
B99: Dr: Acct 0486 - ACCUMULATED AMORTIZATION - RIGHT-TO-USE LEASED BUILDINGS
B100: =IF($F$7="Proprietary","Dr: Acct 0870 - SERVICES & CHARGES (MG ADJ)",VLOOKUP($F$9,'[10]Drop Down Menus'!$F$2:$H$10,3,FALSE)) -> Dr: Acct 0825 - BUS, CONSUMER SERV, HOUSING
A101: *Rpt 18 | C101: Cr: Acct 0476 - RIGHT-TO-USE LEASED LAND - AMORTIZABLE
A102: *Rpt 18 | C102: Cr: Acct 0478 - RIGHT-TO-USE LEASED EQUIPMENT - AMORTIZABLE
A103: *Rpt 18 | C103: Cr: Acct 0477 - RIGHT-TO-USE LEASED BUILDINGS - AMORTIZABLE
C104: =IF($F$7="Proprietary","Dr: Acct 0870 - SERVICES & CHARGES (MG ADJ)",VLOOKUP($F$9,'[10]Drop Down Menus'!$F$2:$G$10,2,FALSE)) -> Cr: Acct 0825 - BUS, CONSUMER SERV, HOUSING
B105: * THESE AMOUNTS SHOULD BE INCLUDED AS "DEDUCTIONS" ON REPORT 18. | J105: =SUM(J96:J104) -> 0 | K105: =SUM(K96:K104) -> 0 | L105: =IF(J105=K105,"<- Debits and Credits equal each other.","<- Debits and Credits do not equal each other.") -> <- Debits and Credits equal each other.
B106: ** This amount should be included in the deductions column on the LS-Lease Liability and LS-Check Figures Tabs.
A109: 10 | B109: Record lease modifications to increase in the RTU leased asset.
A110: *Rpt 18 | B110: Dr: Acct 0476 - RIGHT-TO-USE LEASED LAND - AMORTIZABLE
A111: *Rpt 18 | B111: Dr: Acct 0478 - RIGHT-TO-USE LEASED EQUIPMENT - AMORTIZABLE
A112: *Rpt 18 | B112: Dr: Acct 0477 - RIGHT-TO-USE LEASED BUILDINGS - AMORTIZABLE
A113: **LS LL/CF | C113: Cr: Acct 0691 - RIGHT-TO-USE LEASE LIABILITY
B114: * THESE AMOUNTS SHOULD BE INCLUDED AS "ADDITIONS" ON REPORT 18. | J114: =SUM(J110:J113) -> 0 | K114: =SUM(K110:K113) -> 0 | L114: =IF(J114=K114,"<- Debits and Credits equal each other.","<- Debits and Credits do not equal each other.") -> <- Debits and Credits equal each other.
B115: ** This amount should be included in the additions column on the LS-Lease Liability and LS-Check Figures Tabs.
D120: Informational - Ending Balances of Assets and Liabilities
K121: Debit (Credit)
D122: Acct 0476 - RIGHT-TO-USE LEASED LAND - AMORTIZABLE | K122: =J15+J39-K88-K101+J110 -> 0
D123: Acct 0478 - RIGHT-TO-USE LEASED EQUIPMENT - AMORTIZABLE | K123: =J16+J40-K89-K102+J111 -> 0
D124: Acct 0477 - RIGHT-TO-USE LEASED BUILDINGS - AMORTIZABLE | K124: =J17+J41-K90-K103+J112 -> 8845233
D125: Acct 0485 - ACCUMULATED AMORTIZATION - RIGHT-TO-USE LEASED LAND | K125: =-K20-K56+J85+J97 -> 0
...

Sheet LS-Fund 0763 Journal Entries
A1: Lessee-Type Contracts Fund-by-Fund Journal Entries Form (to be submitted to the SCO annually—one form per fund)
A2: Manually complete every yellow field in this worksheet—there are no automatically calculated data-entry cells in this worksheet.
A3: Fiscal Year: | F3: 2023–2024
A4: Organization Name: | F4: Department of Consumer Affairs
A5: Organization Code (4-Digits): | F5: 1111
A6: Fund Number (4-Digits): | F6: 763
A7: Fund Classification: | F7: Governmental
A8: Fund Type: | F8: Governmental Fund
A9: Functional Expense: | F9: =IFERROR(IF(F7="Proprietary","Proprietary Fund",VLOOKUP(F5,[11]qryIndex02a!$A$2:$K$654,4,FALSE)),"Unidentified") -> BUS, CONSUMER SERV, HOUSING
A12: Establish Beginning Balances (existing leases only)
A13: Entry #
A14: 0 | B14: Roll forward prior year right-to-use leases to record opening balances. | M14: Combined Lessee Templates | P14: From SCO BB List | S14: Difference
A15: *Rpt 18 | B15: Dr: Acct 0476 - RIGHT-TO-USE LEASED LAND - AMORTIZABLE | J15: =M15 -> 0 | S15: =P15-M15 -> 0 | T15: Report any "Differences" on the Report 18 Differential.
A16: *Rpt 18 | B16: Dr: Acct 0478 - RIGHT-TO-USE LEASED EQUIPMENT - AMORTIZABLE | J16: =M16 -> 0 | S16: =P16-M16 -> 0 | T16: Report any "Differences" on the Report 18 Differential.
A17: *Rpt 18 | B17: Dr: Acct 0477 - RIGHT-TO-USE LEASED BUILDINGS - AMORTIZABLE | J17: =M17 -> 204719 | M17: 204719 | P17: 204719 | S17: =P17-M17 -> 0 | T17: Report any "Differences" on the Report 18 Differential.
B18: Dr: Acct 0950 - BEGINNING FUND BALANCE | J18: =P18 -> 1942 | M18: 1942 | P18: =IF(SUM($Q$20:$Q$23)>SUM($P$15:$P$17),SUM($Q$20:$Q$23)-SUM($P$15:$P$17),0) -> 1942 | S18: =P18-M18 -> 0 | T18: No action required.
B19: Dr: Acct 0952 - BEGINNING FUND ADJUSTMENT/PRIOR PERIOD ADJUSTMENT | J19: =IF(SUM($K$20:$K$24)>SUM($J$15:$J$18),SUM($K$20:$K$24)-SUM($J$15:$J$18),0) -> 0 | S19: =P19-M19 -> 0 | T19: No action required.
C20: Cr: Acct 0485 - ACCUMULATED AMORTIZATION - RIGHT-TO-USE LEASED LAND | K20: =N20 -> 0 | S20: =Q20-N20 -> 0 | T20: No action required.
C21: Cr: Acct 0479 - ACCUMULATED AMORTIZATION - RIGHT-TO-USE LEASED EQUIPMENT | K21: =N21 -> 0 | S21: =Q21-N21 -> 0 | T21: No action required.
C22: Cr: Acct 0486 - ACCUMULATED AMORTIZATION - RIGHT-TO-USE LEASED BUILDINGS | K22: =N22 -> 169422 | N22: 169422 | Q22: 169422 | S22: =Q22-N22 -> 0 | T22: No action required.
A23: **LS LL/CF | C23: Cr: Acct 0691 - RIGHT-TO-USE LEASE LIABILITY | K23: =N23 -> 37239 | N23: 37239 | Q23: 37239 | S23: =Q23-N23 -> 0 | T23: No action required.
C24: Cr: Acct 0950 - BEGINNING FUND BALANCE | K24: =Q24 -> 0 | Q24: =IF(SUM($Q$20:$Q$23)<SUM($P$15:$P$17),-SUM($Q$20:$Q$23)+SUM($P$15:$P$17),0) -> 0 | S24: =Q24-N24 -> 0 | T24: No action required.
C25: Cr: Acct 0952 - BEGINNING FUND ADJUSTMENT/PRIOR PERIOD ADJUSTMENT | K25: =IF(SUM($K$20:$K$24)<SUM($J$15:$J$18),-SUM($K$20:$K$24)+SUM($J$15:$J$18),0) -> 0 | S25: =Q25-N25 -> 0 | T25: No action required.
J26: =SUM(J15:J25) -> 206661 | K26: =SUM(K15:K25) -> 206661 | L26: =IF(J26=K26,"<- Debits and Credits equal each other.","<- Debits and Credits do not equal each other.") -> <- Debits and Credits equal each other.
B27: * THESE ASSET AMOUNTS SHOULD BE REPORTED AS BEGINNING BALANCES ON REPORT 18.
B28: ** This amount should be included in the beginning balance column on the LS-Lease Liability and LS-Check Figures Tabs.
A31: Record New Leases (new leases only)
A32: 1 | B32: Record lease contract commencement (fund-based entries only)
B33: Dr: Acct 0842 - CAPITAL OUTLAY
C34: Cr: Acct 0789 - LEASE AND OTHER FINANCING PROCEEDS
C35: =IF($F$7="Proprietary","Cr: Acct 0870 - SERVICES & CHARGES (MG ADJ)",VLOOKUP($F$9,'[11]Drop Down Menus'!$F$2:$G$10,2,FALSE)) -> Cr: Acct 0825 - BUS, CONSUMER SERV, HOUSING
J36: =SUM(J33:J35) -> 0 | K36: =SUM(K33:K35) -> 0 | L36: =IF(J36=K36,"<- Debits and Credits equal each other.","<- Debits and Credits do not equal each other.") -> <- Debits and Credits equal each other.
A38: 2 | B38: Record leased assets.
A39: *Rpt 18 | B39: Dr: Acct 0476 - RIGHT-TO-USE LEASED LAND - AMORTIZABLE
A40: *Rpt 18 | B40: Dr: Acct 0478 - RIGHT-TO-USE LEASED EQUIPMENT - AMORTIZABLE
A41: *Rpt 18 | B41: Dr: Acct 0477 - RIGHT-TO-USE LEASED BUILDINGS - AMORTIZABLE
C42: Cr: Acct 0842 - CAPITAL OUTLAY
B43: * THESE AMOUNTS SHOULD BE INCLUDED AS "ADDITIONS" ON REPORT 18. | J43: =SUM(J39:J42) -> 0 | K43: =SUM(K39:K42) -> 0 | L43: =IF(J43=K43,"<- Debits and Credits equal each other.","<- Debits and Credits do not equal each other.") -> <- Debits and Credits equal each other.
A46: 3 | B46: Replace proceeds from leases with right-to-use lease liability.
B47: Dr: Acct 0789 - LEASE AND OTHER FINANCING PROCEEDS
A48: **LS LL/CF | C48: Cr: Acct 0691 - RIGHT-TO-USE LEASE LIABILITY
J49: =SUM(J47:J48) -> 0 | K49: =SUM(K47:K48) -> 0 | L49: =IF(J49=K49,"<- Debits and Credits equal each other.","<- Debits and Credits do not equal each other.") -> <- Debits and Credits equal each other.
B50: ** This amount should be included in the additions column on the LS-Lease Liability and LS-Check Figures Tabs.
A53: Record Annual Activity (all leases)
A54: 4 | B54: Record amortization of the leased assets for the year.
B55: Dr: Acct 0875 - DEPRECIATION/AMORTIZATION | J55: 35297
C56: Cr: Acct 0485 - ACCUMULATED AMORTIZATION - RIGHT-TO-USE LEASED LAND
C57: Cr: Acct 0479 - ACCUMULATED AMORTIZATION - RIGHT-TO-USE LEASED EQUIPMENT
C58: Cr: Acct 0486 - ACCUMULATED AMORTIZATION - RIGHT-TO-USE LEASED BUILDINGS | K58: 35297
J59: =SUM(J55:J58) -> 35297 | K59: =SUM(K55:K58) -> 35297 | L59: =IF(J59=K59,"<- Debits and Credits equal each other.","<- Debits and Credits do not equal each other.") -> <- Debits and Credits equal each other.
A61: 5 | B61: Reclassify rents and leases exp. to lease contract principal and interest exp.
B62: Dr: Acct 0848 - DEBT SERVICE - PRINCIPAL LEASES | J62: 37239 | L62: =IF($J$62=$K$69,"","<- Accts 0848 must agree")
B63: =IF(F7="Governmental","Dr: Acct 0851 - DEBT SERVICE - INTEREST LEASES","Dr: Acct 0894 - INTEREST EXPENSE AND FISCAL CHARGES") -> Dr: Acct 0851 - DEBT SERVICE - INTEREST LEASES | J63: 18
C64: =IF($F$7="Proprietary","Cr: Acct 0870 - SERVICES & CHARGES (MG ADJ)",VLOOKUP($F$9,'[11]Drop Down Menus'!$F$2:$G$10,2,FALSE)) -> Cr: Acct 0825 - BUS, CONSUMER SERV, HOUSING | K64: 37257
J65: =SUM(J62:J64) -> 37257 | K65: =SUM(K62:K64) -> 37257 | L65: =IF(J65=K65,"<- Debits and Credits equal each other.","<- Debits and Credits do not equal each other.") -> <- Debits and Credits equal each other.
A67: 6 | B67: Reduce lease contracts liability for total current year principal payments.
A68: **LS LL/CF | B68: Dr: Acct 0691 - RIGHT-TO-USE LEASE LIABILITY | J68: 37239
C69: Cr: Acct 0848 - DEBT SERVICE - PRINCIPAL LEASES | K69: 37239 | L69: =IF($J$62=$K$69,"","<- Accts 0848 must agree")
J70: =SUM(J68:J69) -> 37239 | K70: =SUM(K68:K69) -> 37239 | L70: =IF(J70=K70,"<- Debits and Credits equal each other.","<- Debits and Credits do not equal each other.") -> <- Debits and Credits equal each other.
B71: ** This amount should be included in the deductions column on the LS-Lease Liability and LS-Check Figures Tabs.
A74: 7 | B74: Reclassify the principal amount due in the next FY to the current liability.
A75: **LS LL/CF | B75: Dr: Acct 0691 - RIGHT-TO-USE LEASE LIABILITY
C76: Cr: Acct 0649 - RIGHT-TO-USE LEASE LIABILITY (CURRENT PORTION LT)
B77: NOTE: This is an annual accrual. It is to be reversed at the start of the next fiscal year. SCO combines the current and non current amount in Entry #0 to reestablish the beginning balances. No action required. | J77: =SUM(J75:J76) -> 0 | K77: =SUM(K75:K76) -> 0 | L77: =IF(J77=K77,"<- Debits and Credits equal each other.","<- Debits and Credits do not equal each other.") -> <- Debits and Credits equal each other.
B80: ** This amount should be included in the due in one year column on the LS-Lease Liability and LS-Check Figures Tabs.
A83: Remove Lease Asset at the End of the Lease Term (only at the end of the lease term)
A84: 8 | B84: Record entry to write off the lease asset and accumulated amortization at the end of the lease term.
B85: Dr: Acct 0485 - ACCUMULATED AMORTIZATION - RIGHT-TO-USE LEASED LAND
B86: Dr: Acct 0479 - ACCUMULATED AMORTIZATION - RIGHT-TO-USE LEASED EQUIPMENT
B87: Dr: Acct 0486 - ACCUMULATED AMORTIZATION - RIGHT-TO-USE LEASED BUILDINGS | J87: 204719
A88: *Rpt 18 | C88: Cr: Acct 0476 - RIGHT-TO-USE LEASED LAND - AMORTIZABLE
A89: *Rpt 18 | C89: Cr: Acct 0478 - RIGHT-TO-USE LEASED EQUIPMENT - AMORTIZABLE
A90: *Rpt 18 | C90: Cr: Acct 0477 - RIGHT-TO-USE LEASED BUILDINGS - AMORTIZABLE | K90: 204719
B91: * THESE AMOUNTS SHOULD BE INCLUDED AS "DEDUCTIONS" ON REPORT 18. | J91: =SUM(J85:J90) -> 204719 | K91: =SUM(K85:K90) -> 204719 | L91: =IF(J91=K91,"<- Debits and Credits equal each other.","<- Debits and Credits do not equal each other.") -> <- Debits and Credits equal each other.
A94: Lease Remeasurement and Modifications (only if a significant modification occurred during the fiscal year)
A95: 9 | B95: Record early termination or lease modifications to decrease in the RTU leased asset.
A96: **LS LL/CF | B96: Dr: Acct 0691 - RIGHT-TO-USE LEASE LIABILITY
B97: Dr: Acct 0485 - ACCUMULATED AMORTIZATION - RIGHT-TO-USE LEASED LAND
B98: Dr: Acct 0479 - ACCUMULATED AMORTIZATION - RIGHT-TO-USE LEASED EQUIPMENT
B99: Dr: Acct 0486 - ACCUMULATED AMORTIZATION - RIGHT-TO-USE LEASED BUILDINGS
B100: =IF($F$7="Proprietary","Dr: Acct 0870 - SERVICES & CHARGES (MG ADJ)",VLOOKUP($F$9,'[11]Drop Down Menus'!$F$2:$H$10,3,FALSE)) -> Dr: Acct 0825 - BUS, CONSUMER SERV, HOUSING
A101: *Rpt 18 | C101: Cr: Acct 0476 - RIGHT-TO-USE LEASED LAND - AMORTIZABLE
A102: *Rpt 18 | C102: Cr: Acct 0478 - RIGHT-TO-USE LEASED EQUIPMENT - AMORTIZABLE
A103: *Rpt 18 | C103: Cr: Acct 0477 - RIGHT-TO-USE LEASED BUILDINGS - AMORTIZABLE
C104: =IF($F$7="Proprietary","Dr: Acct 0870 - SERVICES & CHARGES (MG ADJ)",VLOOKUP($F$9,'[11]Drop Down Menus'!$F$2:$G$10,2,FALSE)) -> Cr: Acct 0825 - BUS, CONSUMER SERV, HOUSING
B105: * THESE AMOUNTS SHOULD BE INCLUDED AS "DEDUCTIONS" ON REPORT 18. | J105: =SUM(J96:J104) -> 0 | K105: =SUM(K96:K104) -> 0 | L105: =IF(J105=K105,"<- Debits and Credits equal each other.","<- Debits and Credits do not equal each other.") -> <- Debits and Credits equal each other.
B106: ** This amount should be included in the deductions column on the LS-Lease Liability and LS-Check Figures Tabs.
A109: 10 | B109: Record lease modifications to increase in the RTU leased asset.
A110: *Rpt 18 | B110: Dr: Acct 0476 - RIGHT-TO-USE LEASED LAND - AMORTIZABLE
A111: *Rpt 18 | B111: Dr: Acct 0478 - RIGHT-TO-USE LEASED EQUIPMENT - AMORTIZABLE
A112: *Rpt 18 | B112: Dr: Acct 0477 - RIGHT-TO-USE LEASED BUILDINGS - AMORTIZABLE
A113: **LS LL/CF | C113: Cr: Acct 0691 - RIGHT-TO-USE LEASE LIABILITY
B114: * THESE AMOUNTS SHOULD BE INCLUDED AS "ADDITIONS" ON REPORT 18. | J114: =SUM(J110:J113) -> 0 | K114: =SUM(K110:K113) -> 0 | L114: =IF(J114=K114,"<- Debits and Credits equal each other.","<- Debits and Credits do not equal each other.") -> <- Debits and Credits equal each other.
B115: ** This amount should be included in the additions column on the LS-Lease Liability and LS-Check Figures Tabs.
D120: Informational - Ending Balances of Assets and Liabilities
K121: Debit (Credit)
D122: Acct 0476 - RIGHT-TO-USE LEASED LAND - AMORTIZABLE | K122: =J15+J39-K88-K101+J110 -> 0
D123: Acct 0478 - RIGHT-TO-USE LEASED EQUIPMENT - AMORTIZABLE | K123: =J16+J40-K89-K102+J111 -> 0
D124: Acct 0477 - RIGHT-TO-USE LEASED BUILDINGS - AMORTIZABLE | K124: =J17+J41-K90-K103+J112 -> 0
D125: Acct 0485 - ACCUMULATED AMORTIZATION - RIGHT-TO-USE LEASED LAND | K125: =-K20-K56+J85+J97 -> 0
...

Sheet LS-Fund 0767 Journal Entries
A1: Lessee-Type Contracts Fund-by-Fund Journal Entries Form (to be submitted to the SCO annually—one form per fund)
A2: Manually complete every yellow field in this worksheet—there are no automatically calculated data-entry cells in this worksheet.
A3: Fiscal Year: | F3: 2023–2024
A4: Organization Name: | F4: Department of Consumer Affairs
A5: Organization Code (4-Digits): | F5: 1111
A6: Fund Number (4-Digits): | F6: 767
A7: Fund Classification: | F7: Governmental
A8: Fund Type: | F8: Governmental Fund
A9: Functional Expense: | F9: =IFERROR(IF(F7="Proprietary","Proprietary Fund",VLOOKUP(F5,[12]qryIndex02a!$A$2:$K$654,4,FALSE)),"Unidentified") -> BUS, CONSUMER SERV, HOUSING
A12: Establish Beginning Balances (existing leases only)
A13: Entry #
A14: 0 | B14: Roll forward prior year right-to-use leases to record opening balances. | M14: Combined Lessee Templates | P14: From SCO BB List | S14: Difference
A15: *Rpt 18 | B15: Dr: Acct 0476 - RIGHT-TO-USE LEASED LAND - AMORTIZABLE | J15: =M15 -> 0 | S15: =P15-M15 -> 0 | T15: Report any "Differences" on the Report 18 Differential.
A16: *Rpt 18 | B16: Dr: Acct 0478 - RIGHT-TO-USE LEASED EQUIPMENT - AMORTIZABLE | J16: =M16 -> 0 | S16: =P16-M16 -> 0 | T16: Report any "Differences" on the Report 18 Differential.
A17: *Rpt 18 | B17: Dr: Acct 0477 - RIGHT-TO-USE LEASED BUILDINGS - AMORTIZABLE | J17: =M17 -> 3221650 | M17: 3221650 | P17: 3221650 | S17: =P17-M17 -> 0 | T17: Report any "Differences" on the Report 18 Differential.
B18: Dr: Acct 0950 - BEGINNING FUND BALANCE | J18: =P18 -> 14708 | M18: 14708 | P18: =IF(SUM($Q$20:$Q$23)>SUM($P$15:$P$17),SUM($Q$20:$Q$23)-SUM($P$15:$P$17),0) -> 14708 | S18: =P18-M18 -> 0 | T18: No action required.
B19: Dr: Acct 0952 - BEGINNING FUND ADJUSTMENT/PRIOR PERIOD ADJUSTMENT | J19: =IF(SUM($K$20:$K$24)>SUM($J$15:$J$18),SUM($K$20:$K$24)-SUM($J$15:$J$18),0) -> 0 | S19: =P19-M19 -> 0 | T19: No action required.
C20: Cr: Acct 0485 - ACCUMULATED AMORTIZATION - RIGHT-TO-USE LEASED LAND | K20: =N20 -> 0 | S20: =Q20-N20 -> 0 | T20: No action required.
C21: Cr: Acct 0479 - ACCUMULATED AMORTIZATION - RIGHT-TO-USE LEASED EQUIPMENT | K21: =N21 -> 0 | S21: =Q21-N21 -> 0 | T21: No action required.
C22: Cr: Acct 0486 - ACCUMULATED AMORTIZATION - RIGHT-TO-USE LEASED BUILDINGS | K22: =N22 -> 1196341 | N22: 1196341 | Q22: 1196341 | S22: =Q22-N22 -> 0 | T22: No action required.
A23: **LS LL/CF | C23: Cr: Acct 0691 - RIGHT-TO-USE LEASE LIABILITY | K23: =N23 -> 2040017 | N23: 2040017 | Q23: 2040017 | S23: =Q23-N23 -> 0 | T23: No action required.
C24: Cr: Acct 0950 - BEGINNING FUND BALANCE | K24: =Q24 -> 0 | Q24: =IF(SUM($Q$20:$Q$23)<SUM($P$15:$P$17),-SUM($Q$20:$Q$23)+SUM($P$15:$P$17),0) -> 0 | S24: =Q24-N24 -> 0 | T24: No action required.
C25: Cr: Acct 0952 - BEGINNING FUND ADJUSTMENT/PRIOR PERIOD ADJUSTMENT | K25: =IF(SUM($K$20:$K$24)<SUM($J$15:$J$18),-SUM($K$20:$K$24)+SUM($J$15:$J$18),0) -> 0 | S25: =Q25-N25 -> 0 | T25: No action required.
J26: =SUM(J15:J25) -> 3236358 | K26: =SUM(K15:K25) -> 3236358 | L26: =IF(J26=K26,"<- Debits and Credits equal each other.","<- Debits and Credits do not equal each other.") -> <- Debits and Credits equal each other.
B27: * THESE ASSET AMOUNTS SHOULD BE REPORTED AS BEGINNING BALANCES ON REPORT 18.
B28: ** This amount should be included in the beginning balance column on the LS-Lease Liability and LS-Check Figures Tabs.
A31: Record New Leases (new leases only)
A32: 1 | B32: Record lease contract commencement (fund-based entries only)
B33: Dr: Acct 0842 - CAPITAL OUTLAY
C34: Cr: Acct 0789 - LEASE AND OTHER FINANCING PROCEEDS
C35: =IF($F$7="Proprietary","Cr: Acct 0870 - SERVICES & CHARGES (MG ADJ)",VLOOKUP($F$9,'[12]Drop Down Menus'!$F$2:$G$10,2,FALSE)) -> Cr: Acct 0825 - BUS, CONSUMER SERV, HOUSING
J36: =SUM(J33:J35) -> 0 | K36: =SUM(K33:K35) -> 0 | L36: =IF(J36=K36,"<- Debits and Credits equal each other.","<- Debits and Credits do not equal each other.") -> <- Debits and Credits equal each other.
A38: 2 | B38: Record leased assets.
A39: *Rpt 18 | B39: Dr: Acct 0476 - RIGHT-TO-USE LEASED LAND - AMORTIZABLE
A40: *Rpt 18 | B40: Dr: Acct 0478 - RIGHT-TO-USE LEASED EQUIPMENT - AMORTIZABLE
A41: *Rpt 18 | B41: Dr: Acct 0477 - RIGHT-TO-USE LEASED BUILDINGS - AMORTIZABLE
C42: Cr: Acct 0842 - CAPITAL OUTLAY
B43: * THESE AMOUNTS SHOULD BE INCLUDED AS "ADDITIONS" ON REPORT 18. | J43: =SUM(J39:J42) -> 0 | K43: =SUM(K39:K42) -> 0 | L43: =IF(J43=K43,"<- Debits and Credits equal each other.","<- Debits and Credits do not equal each other.") -> <- Debits and Credits equal each other.
A46: 3 | B46: Replace proceeds from leases with right-to-use lease liability.
B47: Dr: Acct 0789 - LEASE AND OTHER FINANCING PROCEEDS
A48: **LS LL/CF | C48: Cr: Acct 0691 - RIGHT-TO-USE LEASE LIABILITY
J49: =SUM(J47:J48) -> 0 | K49: =SUM(K47:K48) -> 0 | L49: =IF(J49=K49,"<- Debits and Credits equal each other.","<- Debits and Credits do not equal each other.") -> <- Debits and Credits equal each other.
B50: ** This amount should be included in the additions column on the LS-Lease Liability and LS-Check Figures Tabs.
A53: Record Annual Activity (all leases)
A54: 4 | B54: Record amortization of the leased assets for the year.
B55: Dr: Acct 0875 - DEPRECIATION/AMORTIZATION | J55: 589495
C56: Cr: Acct 0485 - ACCUMULATED AMORTIZATION - RIGHT-TO-USE LEASED LAND
C57: Cr: Acct 0479 - ACCUMULATED AMORTIZATION - RIGHT-TO-USE LEASED EQUIPMENT
C58: Cr: Acct 0486 - ACCUMULATED AMORTIZATION - RIGHT-TO-USE LEASED BUILDINGS | K58: 589495
J59: =SUM(J55:J58) -> 589495 | K59: =SUM(K55:K58) -> 589495 | L59: =IF(J59=K59,"<- Debits and Credits equal each other.","<- Debits and Credits do not equal each other.") -> <- Debits and Credits equal each other.
A61: 5 | B61: Reclassify rents and leases exp. to lease contract principal and interest exp.
B62: Dr: Acct 0848 - DEBT SERVICE - PRINCIPAL LEASES | J62: 551760 | L62: =IF($J$62=$K$69,"","<- Accts 0848 must agree")
B63: =IF(F7="Governmental","Dr: Acct 0851 - DEBT SERVICE - INTEREST LEASES","Dr: Acct 0894 - INTEREST EXPENSE AND FISCAL CHARGES") -> Dr: Acct 0851 - DEBT SERVICE - INTEREST LEASES | J63: 3578
C64: =IF($F$7="Proprietary","Cr: Acct 0870 - SERVICES & CHARGES (MG ADJ)",VLOOKUP($F$9,'[12]Drop Down Menus'!$F$2:$G$10,2,FALSE)) -> Cr: Acct 0825 - BUS, CONSUMER SERV, HOUSING | K64: 555338
J65: =SUM(J62:J64) -> 555338 | K65: =SUM(K62:K64) -> 555338 | L65: =IF(J65=K65,"<- Debits and Credits equal each other.","<- Debits and Credits do not equal each other.") -> <- Debits and Credits equal each other.
A67: 6 | B67: Reduce lease contracts liability for total current year principal payments.
A68: **LS LL/CF | B68: Dr: Acct 0691 - RIGHT-TO-USE LEASE LIABILITY | J68: 551760
C69: Cr: Acct 0848 - DEBT SERVICE - PRINCIPAL LEASES | K69: 551760 | L69: =IF($J$62=$K$69,"","<- Accts 0848 must agree")
J70: =SUM(J68:J69) -> 551760 | K70: =SUM(K68:K69) -> 551760 | L70: =IF(J70=K70,"<- Debits and Credits equal each other.","<- Debits and Credits do not equal each other.") -> <- Debits and Credits equal each other.
B71: ** This amount should be included in the deductions column on the LS-Lease Liability and LS-Check Figures Tabs.
A74: 7 | B74: Reclassify the principal amount due in the next FY to the current liability.
A75: **LS LL/CF | B75: Dr: Acct 0691 - RIGHT-TO-USE LEASE LIABILITY | J75: 565669
C76: Cr: Acct 0649 - RIGHT-TO-USE LEASE LIABILITY (CURRENT PORTION LT) | K76: 565669
B77: NOTE: This is an annual accrual. It is to be reversed at the start of the next fiscal year. SCO combines the current and non current amount in Entry #0 to reestablish the beginning balances. No action required. | J77: =SUM(J75:J76) -> 565669 | K77: =SUM(K75:K76) -> 565669 | L77: =IF(J77=K77,"<- Debits and Credits equal each other.","<- Debits and Credits do not equal each other.") -> <- Debits and Credits equal each other.
B80: ** This amount should be included in the due in one year column on the LS-Lease Liability and LS-Check Figures Tabs.
A83: Remove Lease Asset at the End of the Lease Term (only at the end of the lease term)
A84: 8 | B84: Record entry to write off the lease asset and accumulated amortization at the end of the lease term.
B85: Dr: Acct 0485 - ACCUMULATED AMORTIZATION - RIGHT-TO-USE LEASED LAND
B86: Dr: Acct 0479 - ACCUMULATED AMORTIZATION - RIGHT-TO-USE LEASED EQUIPMENT
B87: Dr: Acct 0486 - ACCUMULATED AMORTIZATION - RIGHT-TO-USE LEASED BUILDINGS
A88: *Rpt 18 | C88: Cr: Acct 0476 - RIGHT-TO-USE LEASED LAND - AMORTIZABLE
A89: *Rpt 18 | C89: Cr: Acct 0478 - RIGHT-TO-USE LEASED EQUIPMENT - AMORTIZABLE
A90: *Rpt 18 | C90: Cr: Acct 0477 - RIGHT-TO-USE LEASED BUILDINGS - AMORTIZABLE
B91: * THESE AMOUNTS SHOULD BE INCLUDED AS "DEDUCTIONS" ON REPORT 18. | J91: =SUM(J85:J90) -> 0 | K91: =SUM(K85:K90) -> 0 | L91: =IF(J91=K91,"<- Debits and Credits equal each other.","<- Debits and Credits do not equal each other.") -> <- Debits and Credits equal each other.
A94: Lease Remeasurement and Modifications (only if a significant modification occurred during the fiscal year)
A95: 9 | B95: Record early termination or lease modifications to decrease in the RTU leased asset.
A96: **LS LL/CF | B96: Dr: Acct 0691 - RIGHT-TO-USE LEASE LIABILITY
B97: Dr: Acct 0485 - ACCUMULATED AMORTIZATION - RIGHT-TO-USE LEASED LAND
B98: Dr: Acct 0479 - ACCUMULATED AMORTIZATION - RIGHT-TO-USE LEASED EQUIPMENT
B99: Dr: Acct 0486 - ACCUMULATED AMORTIZATION - RIGHT-TO-USE LEASED BUILDINGS
B100: =IF($F$7="Proprietary","Dr: Acct 0870 - SERVICES & CHARGES (MG ADJ)",VLOOKUP($F$9,'[12]Drop Down Menus'!$F$2:$H$10,3,FALSE)) -> Dr: Acct 0825 - BUS, CONSUMER SERV, HOUSING
A101: *Rpt 18 | C101: Cr: Acct 0476 - RIGHT-TO-USE LEASED LAND - AMORTIZABLE
A102: *Rpt 18 | C102: Cr: Acct 0478 - RIGHT-TO-USE LEASED EQUIPMENT - AMORTIZABLE
A103: *Rpt 18 | C103: Cr: Acct 0477 - RIGHT-TO-USE LEASED BUILDINGS - AMORTIZABLE
C104: =IF($F$7="Proprietary","Dr: Acct 0870 - SERVICES & CHARGES (MG ADJ)",VLOOKUP($F$9,'[12]Drop Down Menus'!$F$2:$G$10,2,FALSE)) -> Cr: Acct 0825 - BUS, CONSUMER SERV, HOUSING
B105: * THESE AMOUNTS SHOULD BE INCLUDED AS "DEDUCTIONS" ON REPORT 18. | J105: =SUM(J96:J104) -> 0 | K105: =SUM(K96:K104) -> 0 | L105: =IF(J105=K105,"<- Debits and Credits equal each other.","<- Debits and Credits do not equal each other.") -> <- Debits and Credits equal each other.
B106: ** This amount should be included in the deductions column on the LS-Lease Liability and LS-Check Figures Tabs.
A109: 10 | B109: Record lease modifications to increase in the RTU leased asset.
A110: *Rpt 18 | B110: Dr: Acct 0476 - RIGHT-TO-USE LEASED LAND - AMORTIZABLE
A111: *Rpt 18 | B111: Dr: Acct 0478 - RIGHT-TO-USE LEASED EQUIPMENT - AMORTIZABLE
A112: *Rpt 18 | B112: Dr: Acct 0477 - RIGHT-TO-USE LEASED BUILDINGS - AMORTIZABLE
A113: **LS LL/CF | C113: Cr: Acct 0691 - RIGHT-TO-USE LEASE LIABILITY
B114: * THESE AMOUNTS SHOULD BE INCLUDED AS "ADDITIONS" ON REPORT 18. | J114: =SUM(J110:J113) -> 0 | K114: =SUM(K110:K113) -> 0 | L114: =IF(J114=K114,"<- Debits and Credits equal each other.","<- Debits and Credits do not equal each other.") -> <- Debits and Credits equal each other.
B115: ** This amount should be included in the additions column on the LS-Lease Liability and LS-Check Figures Tabs.
D120: Informational - Ending Balances of Assets and Liabilities
K121: Debit (Credit)
D122: Acct 0476 - RIGHT-TO-USE LEASED LAND - AMORTIZABLE | K122: =J15+J39-K88-K101+J110 -> 0
D123: Acct 0478 - RIGHT-TO-USE LEASED EQUIPMENT - AMORTIZABLE | K123: =J16+J40-K89-K102+J111 -> 0
D124: Acct 0477 - RIGHT-TO-USE LEASED BUILDINGS - AMORTIZABLE | K124: =J17+J41-K90-K103+J112 -> 3221650
D125: Acct 0485 - ACCUMULATED AMORTIZATION - RIGHT-TO-USE LEASED LAND | K125: =-K20-K56+J85+J97 -> 0
...

Sheet LS-Fund 0770 Journal Entries
A1: Lessee-Type Contracts Fund-by-Fund Journal Entries Form (to be submitted to the SCO annually—one form per fund)
A2: Manually complete every yellow field in this worksheet—there are no automatically calculated data-entry cells in this worksheet.
A3: Fiscal Year: | F3: 2023–2024
A4: Organization Name: | F4: Department of Consumer Affairs
A5: Organization Code (4-Digits): | F5: 1111
A6: Fund Number (4-Digits): | F6: 770
A7: Fund Classification: | F7: Governmental
A8: Fund Type: | F8: Governmental Fund
A9: Functional Expense: | F9: =IFERROR(IF(F7="Proprietary","Proprietary Fund",VLOOKUP(F5,[13]qryIndex02a!$A$2:$K$654,4,FALSE)),"Unidentified") -> BUS, CONSUMER SERV, HOUSING
A12: Establish Beginning Balances (existing leases only)
A13: Entry #
A14: 0 | B14: Roll forward prior year right-to-use leases to record opening balances. | M14: Combined Lessee Templates | P14: From SCO BB List | S14: Difference
A15: *Rpt 18 | B15: Dr: Acct 0476 - RIGHT-TO-USE LEASED LAND - AMORTIZABLE | J15: =M15 -> 0 | S15: =P15-M15 -> 0 | T15: Report any "Differences" on the Report 18 Differential.
A16: *Rpt 18 | B16: Dr: Acct 0478 - RIGHT-TO-USE LEASED EQUIPMENT - AMORTIZABLE | J16: =M16 -> 0 | S16: =P16-M16 -> 0 | T16: Report any "Differences" on the Report 18 Differential.
A17: *Rpt 18 | B17: Dr: Acct 0477 - RIGHT-TO-USE LEASED BUILDINGS - AMORTIZABLE | J17: =M17 -> 1176061 | M17: 1176061 | P17: 1176061 | S17: =P17-M17 -> 0 | T17: Report any "Differences" on the Report 18 Differential.
B18: Dr: Acct 0950 - BEGINNING FUND BALANCE | J18: =P18 -> 4266 | M18: 4266 | P18: =IF(SUM($Q$20:$Q$23)>SUM($P$15:$P$17),SUM($Q$20:$Q$23)-SUM($P$15:$P$17),0) -> 4266 | S18: =P18-M18 -> 0 | T18: No action required.
B19: Dr: Acct 0952 - BEGINNING FUND ADJUSTMENT/PRIOR PERIOD ADJUSTMENT | J19: =IF(SUM($K$20:$K$24)>SUM($J$15:$J$18),SUM($K$20:$K$24)-SUM($J$15:$J$18),0) -> 0 | S19: =P19-M19 -> 0 | T19: No action required.
C20: Cr: Acct 0485 - ACCUMULATED AMORTIZATION - RIGHT-TO-USE LEASED LAND | K20: =N20 -> 0 | S20: =Q20-N20 -> 0 | T20: No action required.
C21: Cr: Acct 0479 - ACCUMULATED AMORTIZATION - RIGHT-TO-USE LEASED EQUIPMENT | K21: =N21 -> 0 | S21: =Q21-N21 -> 0 | T21: No action required.
C22: Cr: Acct 0486 - ACCUMULATED AMORTIZATION - RIGHT-TO-USE LEASED BUILDINGS | K22: =N22 -> 855316 | N22: 855316 | Q22: 855316 | S22: =Q22-N22 -> 0 | T22: No action required.
A23: **LS LL/CF | C23: Cr: Acct 0691 - RIGHT-TO-USE LEASE LIABILITY | K23: =N23 -> 325011 | N23: 325011 | Q23: 325011 | S23: =Q23-N23 -> 0 | T23: No action required.
C24: Cr: Acct 0950 - BEGINNING FUND BALANCE | K24: =Q24 -> 0 | Q24: =IF(SUM($Q$20:$Q$23)<SUM($P$15:$P$17),-SUM($Q$20:$Q$23)+SUM($P$15:$P$17),0) -> 0 | S24: =Q24-N24 -> 0 | T24: No action required.
C25: Cr: Acct 0952 - BEGINNING FUND ADJUSTMENT/PRIOR PERIOD ADJUSTMENT | K25: =IF(SUM($K$20:$K$24)<SUM($J$15:$J$18),-SUM($K$20:$K$24)+SUM($J$15:$J$18),0) -> 0 | S25: =Q25-N25 -> 0 | T25: No action required.
J26: =SUM(J15:J25) -> 1180327 | K26: =SUM(K15:K25) -> 1180327 | L26: =IF(J26=K26,"<- Debits and Credits equal each other.","<- Debits and Credits do not equal each other.") -> <- Debits and Credits equal each other.
B27: * THESE ASSET AMOUNTS SHOULD BE REPORTED AS BEGINNING BALANCES ON REPORT 18.
B28: ** This amount should be included in the beginning balance column on the LS-Lease Liability and LS-Check Figures Tabs.
A31: Record New Leases (new leases only)
A32: 1 | B32: Record lease contract commencement (fund-based entries only)
B33: Dr: Acct 0842 - CAPITAL OUTLAY
C34: Cr: Acct 0789 - LEASE AND OTHER FINANCING PROCEEDS
C35: =IF($F$7="Proprietary","Cr: Acct 0870 - SERVICES & CHARGES (MG ADJ)",VLOOKUP($F$9,'[13]Drop Down Menus'!$F$2:$G$10,2,FALSE)) -> Cr: Acct 0825 - BUS, CONSUMER SERV, HOUSING
J36: =SUM(J33:J35) -> 0 | K36: =SUM(K33:K35) -> 0 | L36: =IF(J36=K36,"<- Debits and Credits equal each other.","<- Debits and Credits do not equal each other.") -> <- Debits and Credits equal each other.
A38: 2 | B38: Record leased assets.
A39: *Rpt 18 | B39: Dr: Acct 0476 - RIGHT-TO-USE LEASED LAND - AMORTIZABLE
A40: *Rpt 18 | B40: Dr: Acct 0478 - RIGHT-TO-USE LEASED EQUIPMENT - AMORTIZABLE
A41: *Rpt 18 | B41: Dr: Acct 0477 - RIGHT-TO-USE LEASED BUILDINGS - AMORTIZABLE
C42: Cr: Acct 0842 - CAPITAL OUTLAY
B43: * THESE AMOUNTS SHOULD BE INCLUDED AS "ADDITIONS" ON REPORT 18. | J43: =SUM(J39:J42) -> 0 | K43: =SUM(K39:K42) -> 0 | L43: =IF(J43=K43,"<- Debits and Credits equal each other.","<- Debits and Credits do not equal each other.") -> <- Debits and Credits equal each other.
A46: 3 | B46: Replace proceeds from leases with right-to-use lease liability.
B47: Dr: Acct 0789 - LEASE AND OTHER FINANCING PROCEEDS
A48: **LS LL/CF | C48: Cr: Acct 0691 - RIGHT-TO-USE LEASE LIABILITY
J49: =SUM(J47:J48) -> 0 | K49: =SUM(K47:K48) -> 0 | L49: =IF(J49=K49,"<- Debits and Credits equal each other.","<- Debits and Credits do not equal each other.") -> <- Debits and Credits equal each other.
B50: ** This amount should be included in the additions column on the LS-Lease Liability and LS-Check Figures Tabs.
A53: Record Annual Activity (all leases)
A54: 4 | B54: Record amortization of the leased assets for the year.
B55: Dr: Acct 0875 - DEPRECIATION/AMORTIZATION | J55: 320745
C56: Cr: Acct 0485 - ACCUMULATED AMORTIZATION - RIGHT-TO-USE LEASED LAND
C57: Cr: Acct 0479 - ACCUMULATED AMORTIZATION - RIGHT-TO-USE LEASED EQUIPMENT
C58: Cr: Acct 0486 - ACCUMULATED AMORTIZATION - RIGHT-TO-USE LEASED BUILDINGS | K58: 320745
J59: =SUM(J55:J58) -> 320745 | K59: =SUM(K55:K58) -> 320745 | L59: =IF(J59=K59,"<- Debits and Credits equal each other.","<- Debits and Credits do not equal each other.") -> <- Debits and Credits equal each other.
A61: 5 | B61: Reclassify rents and leases exp. to lease contract principal and interest exp.
B62: Dr: Acct 0848 - DEBT SERVICE - PRINCIPAL LEASES | J62: 325011 | L62: =IF($J$62=$K$69,"","<- Accts 0848 must agree")
B63: =IF(F7="Governmental","Dr: Acct 0851 - DEBT SERVICE - INTEREST LEASES","Dr: Acct 0894 - INTEREST EXPENSE AND FISCAL CHARGES") -> Dr: Acct 0851 - DEBT SERVICE - INTEREST LEASES | J63: 271
C64: =IF($F$7="Proprietary","Cr: Acct 0870 - SERVICES & CHARGES (MG ADJ)",VLOOKUP($F$9,'[13]Drop Down Menus'!$F$2:$G$10,2,FALSE)) -> Cr: Acct 0825 - BUS, CONSUMER SERV, HOUSING | K64: 325282
J65: =SUM(J62:J64) -> 325282 | K65: =SUM(K62:K64) -> 325282 | L65: =IF(J65=K65,"<- Debits and Credits equal each other.","<- Debits and Credits do not equal each other.") -> <- Debits and Credits equal each other.
A67: 6 | B67: Reduce lease contracts liability for total current year principal payments.
A68: **LS LL/CF | B68: Dr: Acct 0691 - RIGHT-TO-USE LEASE LIABILITY | J68: 325011
C69: Cr: Acct 0848 - DEBT SERVICE - PRINCIPAL LEASES | K69: 325011 | L69: =IF($J$62=$K$69,"","<- Accts 0848 must agree")
J70: =SUM(J68:J69) -> 325011 | K70: =SUM(K68:K69) -> 325011 | L70: =IF(J70=K70,"<- Debits and Credits equal each other.","<- Debits and Credits do not equal each other.") -> <- Debits and Credits equal each other.
B71: ** This amount should be included in the deductions column on the LS-Lease Liability and LS-Check Figures Tabs.
A74: 7 | B74: Reclassify the principal amount due in the next FY to the current liability.
A75: **LS LL/CF | B75: Dr: Acct 0691 - RIGHT-TO-USE LEASE LIABILITY
C76: Cr: Acct 0649 - RIGHT-TO-USE LEASE LIABILITY (CURRENT PORTION LT)
B77: NOTE: This is an annual accrual. It is to be reversed at the start of the next fiscal year. SCO combines the current and non current amount in Entry #0 to reestablish the beginning balances. No action required. | J77: =SUM(J75:J76) -> 0 | K77: =SUM(K75:K76) -> 0 | L77: =IF(J77=K77,"<- Debits and Credits equal each other.","<- Debits and Credits do not equal each other.") -> <- Debits and Credits equal each other.
B80: ** This amount should be included in the due in one year column on the LS-Lease Liability and LS-Check Figures Tabs.
A83: Remove Lease Asset at the End of the Lease Term (only at the end of the lease term)
A84: 8 | B84: Record entry to write off the lease asset and accumulated amortization at the end of the lease term.
B85: Dr: Acct 0485 - ACCUMULATED AMORTIZATION - RIGHT-TO-USE LEASED LAND
B86: Dr: Acct 0479 - ACCUMULATED AMORTIZATION - RIGHT-TO-USE LEASED EQUIPMENT
B87: Dr: Acct 0486 - ACCUMULATED AMORTIZATION - RIGHT-TO-USE LEASED BUILDINGS | J87: 1176061
A88: *Rpt 18 | C88: Cr: Acct 0476 - RIGHT-TO-USE LEASED LAND - AMORTIZABLE
A89: *Rpt 18 | C89: Cr: Acct 0478 - RIGHT-TO-USE LEASED EQUIPMENT - AMORTIZABLE
A90: *Rpt 18 | C90: Cr: Acct 0477 - RIGHT-TO-USE LEASED BUILDINGS - AMORTIZABLE | K90: 1176061
B91: * THESE AMOUNTS SHOULD BE INCLUDED AS "DEDUCTIONS" ON REPORT 18. | J91: =SUM(J85:J90) -> 1176061 | K91: =SUM(K85:K90) -> 1176061 | L91: =IF(J91=K91,"<- Debits and Credits equal each other.","<- Debits and Credits do not equal each other.") -> <- Debits and Credits equal each other.
A94: Lease Remeasurement and Modifications (only if a significant modification occurred during the fiscal year)
A95: 9 | B95: Record early termination or lease modifications to decrease in the RTU leased asset.
A96: **LS LL/CF | B96: Dr: Acct 0691 - RIGHT-TO-USE LEASE LIABILITY
B97: Dr: Acct 0485 - ACCUMULATED AMORTIZATION - RIGHT-TO-USE LEASED LAND
B98: Dr: Acct 0479 - ACCUMULATED AMORTIZATION - RIGHT-TO-USE LEASED EQUIPMENT
B99: Dr: Acct 0486 - ACCUMULATED AMORTIZATION - RIGHT-TO-USE LEASED BUILDINGS
B100: =IF($F$7="Proprietary","Dr: Acct 0870 - SERVICES & CHARGES (MG ADJ)",VLOOKUP($F$9,'[13]Drop Down Menus'!$F$2:$H$10,3,FALSE)) -> Dr: Acct 0825 - BUS, CONSUMER SERV, HOUSING
A101: *Rpt 18 | C101: Cr: Acct 0476 - RIGHT-TO-USE LEASED LAND - AMORTIZABLE
A102: *Rpt 18 | C102: Cr: Acct 0478 - RIGHT-TO-USE LEASED EQUIPMENT - AMORTIZABLE
A103: *Rpt 18 | C103: Cr: Acct 0477 - RIGHT-TO-USE LEASED BUILDINGS - AMORTIZABLE
C104: =IF($F$7="Proprietary","Dr: Acct 0870 - SERVICES & CHARGES (MG ADJ)",VLOOKUP($F$9,'[13]Drop Down Menus'!$F$2:$G$10,2,FALSE)) -> Cr: Acct 0825 - BUS, CONSUMER SERV, HOUSING
B105: * THESE AMOUNTS SHOULD BE INCLUDED AS "DEDUCTIONS" ON REPORT 18. | J105: =SUM(J96:J104) -> 0 | K105: =SUM(K96:K104) -> 0 | L105: =IF(J105=K105,"<- Debits and Credits equal each other.","<- Debits and Credits do not equal each other.") -> <- Debits and Credits equal each other.
B106: ** This amount should be included in the deductions column on the LS-Lease Liability and LS-Check Figures Tabs.
A109: 10 | B109: Record lease modifications to increase in the RTU leased asset.
A110: *Rpt 18 | B110: Dr: Acct 0476 - RIGHT-TO-USE LEASED LAND - AMORTIZABLE
A111: *Rpt 18 | B111: Dr: Acct 0478 - RIGHT-TO-USE LEASED EQUIPMENT - AMORTIZABLE
A112: *Rpt 18 | B112: Dr: Acct 0477 - RIGHT-TO-USE LEASED BUILDINGS - AMORTIZABLE
A113: **LS LL/CF | C113: Cr: Acct 0691 - RIGHT-TO-USE LEASE LIABILITY
B114: * THESE AMOUNTS SHOULD BE INCLUDED AS "ADDITIONS" ON REPORT 18. | J114: =SUM(J110:J113) -> 0 | K114: =SUM(K110:K113) -> 0 | L114: =IF(J114=K114,"<- Debits and Credits equal each other.","<- Debits and Credits do not equal each other.") -> <- Debits and Credits equal each other.
B115: ** This amount should be included in the additions column on the LS-Lease Liability and LS-Check Figures Tabs.
D120: Informational - Ending Balances of Assets and Liabilities
K121: Debit (Credit)
D122: Acct 0476 - RIGHT-TO-USE LEASED LAND - AMORTIZABLE | K122: =J15+J39-K88-K101+J110 -> 0
D123: Acct 0478 - RIGHT-TO-USE LEASED EQUIPMENT - AMORTIZABLE | K123: =J16+J40-K89-K102+J111 -> 0
D124: Acct 0477 - RIGHT-TO-USE LEASED BUILDINGS - AMORTIZABLE | K124: =J17+J41-K90-K103+J112 -> 0
D125: Acct 0485 - ACCUMULATED AMORTIZATION - RIGHT-TO-USE LEASED LAND | K125: =-K20-K56+J85+J97 -> 0
...

Sheet LS-Fund 0771 Journal Entries
A1: Lessee-Type Contracts Fund-by-Fund Journal Entries Form (to be submitted to the SCO annually—one form per fund)
A2: Manually complete every yellow field in this worksheet—there are no automatically calculated data-entry cells in this worksheet.
A3: Fiscal Year: | F3: 2023–2024
A4: Organization Name: | F4: Department of Consumer Affairs
A5: Organization Code (4-Digits): | F5: 1111
A6: Fund Number (4-Digits): | F6: 771
A7: Fund Classification: | F7: Governmental
A8: Fund Type: | F8: Governmental Fund
A9: Functional Expense: | F9: =IFERROR(IF(F7="Proprietary","Proprietary Fund",VLOOKUP(F5,[14]qryIndex02a!$A$2:$K$654,4,FALSE)),"Unidentified") -> BUS, CONSUMER SERV, HOUSING
A12: Establish Beginning Balances (existing leases only)
A13: Entry #
A14: 0 | B14: Roll forward prior year right-to-use leases to record opening balances. | M14: Combined Lessee Templates | P14: From SCO BB List | S14: Difference
A15: *Rpt 18 | B15: Dr: Acct 0476 - RIGHT-TO-USE LEASED LAND - AMORTIZABLE | J15: =M15 -> 0 | S15: =P15-M15 -> 0 | T15: Report any "Differences" on the Report 18 Differential.
A16: *Rpt 18 | B16: Dr: Acct 0478 - RIGHT-TO-USE LEASED EQUIPMENT - AMORTIZABLE | J16: =M16 -> 0 | S16: =P16-M16 -> 0 | T16: Report any "Differences" on the Report 18 Differential.
A17: *Rpt 18 | B17: Dr: Acct 0477 - RIGHT-TO-USE LEASED BUILDINGS - AMORTIZABLE | J17: =M17 -> 119249 | M17: 119249 | P17: 119249 | S17: =P17-M17 -> 0 | T17: Report any "Differences" on the Report 18 Differential.
B18: Dr: Acct 0950 - BEGINNING FUND BALANCE | J18: =P18 -> 184 | M18: 184 | P18: =IF(SUM($Q$20:$Q$23)>SUM($P$15:$P$17),SUM($Q$20:$Q$23)-SUM($P$15:$P$17),0) -> 184 | S18: =P18-M18 -> 0 | T18: No action required.
B19: Dr: Acct 0952 - BEGINNING FUND ADJUSTMENT/PRIOR PERIOD ADJUSTMENT | J19: =IF(SUM($K$20:$K$24)>SUM($J$15:$J$18),SUM($K$20:$K$24)-SUM($J$15:$J$18),0) -> 0 | S19: =P19-M19 -> 0 | T19: No action required.
C20: Cr: Acct 0485 - ACCUMULATED AMORTIZATION - RIGHT-TO-USE LEASED LAND | K20: =N20 -> 0 | S20: =Q20-N20 -> 0 | T20: No action required.
C21: Cr: Acct 0479 - ACCUMULATED AMORTIZATION - RIGHT-TO-USE LEASED EQUIPMENT | K21: =N21 -> 0 | S21: =Q21-N21 -> 0 | T21: No action required.
C22: Cr: Acct 0486 - ACCUMULATED AMORTIZATION - RIGHT-TO-USE LEASED BUILDINGS | K22: =N22 -> 102214 | N22: 102214 | Q22: 102214 | S22: =Q22-N22 -> 0 | T22: No action required.
A23: **LS LL/CF | C23: Cr: Acct 0691 - RIGHT-TO-USE LEASE LIABILITY | K23: =N23 -> 17219 | N23: 17219 | Q23: 17219 | S23: =Q23-N23 -> 0 | T23: No action required.
C24: Cr: Acct 0950 - BEGINNING FUND BALANCE | K24: =Q24 -> 0 | Q24: =IF(SUM($Q$20:$Q$23)<SUM($P$15:$P$17),-SUM($Q$20:$Q$23)+SUM($P$15:$P$17),0) -> 0 | S24: =Q24-N24 -> 0 | T24: No action required.
C25: Cr: Acct 0952 - BEGINNING FUND ADJUSTMENT/PRIOR PERIOD ADJUSTMENT | K25: =IF(SUM($K$20:$K$24)<SUM($J$15:$J$18),-SUM($K$20:$K$24)+SUM($J$15:$J$18),0) -> 0 | S25: =Q25-N25 -> 0 | T25: No action required.
J26: =SUM(J15:J25) -> 119433 | K26: =SUM(K15:K25) -> 119433 | L26: =IF(J26=K26,"<- Debits and Credits equal each other.","<- Debits and Credits do not equal each other.") -> <- Debits and Credits equal each other.
B27: * THESE ASSET AMOUNTS SHOULD BE REPORTED AS BEGINNING BALANCES ON REPORT 18.
B28: ** This amount should be included in the beginning balance column on the LS-Lease Liability and LS-Check Figures Tabs.
A31: Record New Leases (new leases only)
A32: 1 | B32: Record lease contract commencement (fund-based entries only)
B33: Dr: Acct 0842 - CAPITAL OUTLAY
C34: Cr: Acct 0789 - LEASE AND OTHER FINANCING PROCEEDS
C35: =IF($F$7="Proprietary","Cr: Acct 0870 - SERVICES & CHARGES (MG ADJ)",VLOOKUP($F$9,'[14]Drop Down Menus'!$F$2:$G$10,2,FALSE)) -> Cr: Acct 0825 - BUS, CONSUMER SERV, HOUSING
J36: =SUM(J33:J35) -> 0 | K36: =SUM(K33:K35) -> 0 | L36: =IF(J36=K36,"<- Debits and Credits equal each other.","<- Debits and Credits do not equal each other.") -> <- Debits and Credits equal each other.
A38: 2 | B38: Record leased assets.
A39: *Rpt 18 | B39: Dr: Acct 0476 - RIGHT-TO-USE LEASED LAND - AMORTIZABLE
A40: *Rpt 18 | B40: Dr: Acct 0478 - RIGHT-TO-USE LEASED EQUIPMENT - AMORTIZABLE
A41: *Rpt 18 | B41: Dr: Acct 0477 - RIGHT-TO-USE LEASED BUILDINGS - AMORTIZABLE
C42: Cr: Acct 0842 - CAPITAL OUTLAY
B43: * THESE AMOUNTS SHOULD BE INCLUDED AS "ADDITIONS" ON REPORT 18. | J43: =SUM(J39:J42) -> 0 | K43: =SUM(K39:K42) -> 0 | L43: =IF(J43=K43,"<- Debits and Credits equal each other.","<- Debits and Credits do not equal each other.") -> <- Debits and Credits equal each other.
A46: 3 | B46: Replace proceeds from leases with right-to-use lease liability.
B47: Dr: Acct 0789 - LEASE AND OTHER FINANCING PROCEEDS
A48: **LS LL/CF | C48: Cr: Acct 0691 - RIGHT-TO-USE LEASE LIABILITY
J49: =SUM(J47:J48) -> 0 | K49: =SUM(K47:K48) -> 0 | L49: =IF(J49=K49,"<- Debits and Credits equal each other.","<- Debits and Credits do not equal each other.") -> <- Debits and Credits equal each other.
B50: ** This amount should be included in the additions column on the LS-Lease Liability and LS-Check Figures Tabs.
A53: Record Annual Activity (all leases)
A54: 4 | B54: Record amortization of the leased assets for the year.
B55: Dr: Acct 0875 - DEPRECIATION/AMORTIZATION | J55: 17035
C56: Cr: Acct 0485 - ACCUMULATED AMORTIZATION - RIGHT-TO-USE LEASED LAND
C57: Cr: Acct 0479 - ACCUMULATED AMORTIZATION - RIGHT-TO-USE LEASED EQUIPMENT
C58: Cr: Acct 0486 - ACCUMULATED AMORTIZATION - RIGHT-TO-USE LEASED BUILDINGS | K58: 17035
J59: =SUM(J55:J58) -> 17035 | K59: =SUM(K55:K58) -> 17035 | L59: =IF(J59=K59,"<- Debits and Credits equal each other.","<- Debits and Credits do not equal each other.") -> <- Debits and Credits equal each other.
A61: 5 | B61: Reclassify rents and leases exp. to lease contract principal and interest exp.
B62: Dr: Acct 0848 - DEBT SERVICE - PRINCIPAL LEASES | J62: 17219 | L62: =IF($J$62=$K$69,"","<- Accts 0848 must agree")
B63: =IF(F7="Governmental","Dr: Acct 0851 - DEBT SERVICE - INTEREST LEASES","Dr: Acct 0894 - INTEREST EXPENSE AND FISCAL CHARGES") -> Dr: Acct 0851 - DEBT SERVICE - INTEREST LEASES | J63: 7
C64: =IF($F$7="Proprietary","Cr: Acct 0870 - SERVICES & CHARGES (MG ADJ)",VLOOKUP($F$9,'[14]Drop Down Menus'!$F$2:$G$10,2,FALSE)) -> Cr: Acct 0825 - BUS, CONSUMER SERV, HOUSING | K64: 17226
J65: =SUM(J62:J64) -> 17226 | K65: =SUM(K62:K64) -> 17226 | L65: =IF(J65=K65,"<- Debits and Credits equal each other.","<- Debits and Credits do not equal each other.") -> <- Debits and Credits equal each other.
A67: 6 | B67: Reduce lease contracts liability for total current year principal payments.
A68: **LS LL/CF | B68: Dr: Acct 0691 - RIGHT-TO-USE LEASE LIABILITY | J68: 17219
C69: Cr: Acct 0848 - DEBT SERVICE - PRINCIPAL LEASES | K69: 17219 | L69: =IF($J$62=$K$69,"","<- Accts 0848 must agree")
J70: =SUM(J68:J69) -> 17219 | K70: =SUM(K68:K69) -> 17219 | L70: =IF(J70=K70,"<- Debits and Credits equal each other.","<- Debits and Credits do not equal each other.") -> <- Debits and Credits equal each other.
B71: ** This amount should be included in the deductions column on the LS-Lease Liability and LS-Check Figures Tabs.
A74: 7 | B74: Reclassify the principal amount due in the next FY to the current liability.
A75: **LS LL/CF | B75: Dr: Acct 0691 - RIGHT-TO-USE LEASE LIABILITY
C76: Cr: Acct 0649 - RIGHT-TO-USE LEASE LIABILITY (CURRENT PORTION LT)
B77: NOTE: This is an annual accrual. It is to be reversed at the start of the next fiscal year. SCO combines the current and non current amount in Entry #0 to reestablish the beginning balances. No action required. | J77: =SUM(J75:J76) -> 0 | K77: =SUM(K75:K76) -> 0 | L77: =IF(J77=K77,"<- Debits and Credits equal each other.","<- Debits and Credits do not equal each other.") -> <- Debits and Credits equal each other.
B80: ** This amount should be included in the due in one year column on the LS-Lease Liability and LS-Check Figures Tabs.
A83: Remove Lease Asset at the End of the Lease Term (only at the end of the lease term)
A84: 8 | B84: Record entry to write off the lease asset and accumulated amortization at the end of the lease term.
B85: Dr: Acct 0485 - ACCUMULATED AMORTIZATION - RIGHT-TO-USE LEASED LAND
B86: Dr: Acct 0479 - ACCUMULATED AMORTIZATION - RIGHT-TO-USE LEASED EQUIPMENT
B87: Dr: Acct 0486 - ACCUMULATED AMORTIZATION - RIGHT-TO-USE LEASED BUILDINGS | J87: 119249
A88: *Rpt 18 | C88: Cr: Acct 0476 - RIGHT-TO-USE LEASED LAND - AMORTIZABLE
A89: *Rpt 18 | C89: Cr: Acct 0478 - RIGHT-TO-USE LEASED EQUIPMENT - AMORTIZABLE
A90: *Rpt 18 | C90: Cr: Acct 0477 - RIGHT-TO-USE LEASED BUILDINGS - AMORTIZABLE | K90: 119249
B91: * THESE AMOUNTS SHOULD BE INCLUDED AS "DEDUCTIONS" ON REPORT 18. | J91: =SUM(J85:J90) -> 119249 | K91: =SUM(K85:K90) -> 119249 | L91: =IF(J91=K91,"<- Debits and Credits equal each other.","<- Debits and Credits do not equal each other.") -> <- Debits and Credits equal each other.
A94: Lease Remeasurement and Modifications (only if a significant modification occurred during the fiscal year)
A95: 9 | B95: Record early termination or lease modifications to decrease in the RTU leased asset.
A96: **LS LL/CF | B96: Dr: Acct 0691 - RIGHT-TO-USE LEASE LIABILITY
B97: Dr: Acct 0485 - ACCUMULATED AMORTIZATION - RIGHT-TO-USE LEASED LAND
B98: Dr: Acct 0479 - ACCUMULATED AMORTIZATION - RIGHT-TO-USE LEASED EQUIPMENT
B99: Dr: Acct 0486 - ACCUMULATED AMORTIZATION - RIGHT-TO-USE LEASED BUILDINGS
B100: =IF($F$7="Proprietary","Dr: Acct 0870 - SERVICES & CHARGES (MG ADJ)",VLOOKUP($F$9,'[14]Drop Down Menus'!$F$2:$H$10,3,FALSE)) -> Dr: Acct 0825 - BUS, CONSUMER SERV, HOUSING
A101: *Rpt 18 | C101: Cr: Acct 0476 - RIGHT-TO-USE LEASED LAND - AMORTIZABLE
A102: *Rpt 18 | C102: Cr: Acct 0478 - RIGHT-TO-USE LEASED EQUIPMENT - AMORTIZABLE
A103: *Rpt 18 | C103: Cr: Acct 0477 - RIGHT-TO-USE LEASED BUILDINGS - AMORTIZABLE
C104: =IF($F$7="Proprietary","Dr: Acct 0870 - SERVICES & CHARGES (MG ADJ)",VLOOKUP($F$9,'[14]Drop Down Menus'!$F$2:$G$10,2,FALSE)) -> Cr: Acct 0825 - BUS, CONSUMER SERV, HOUSING
B105: * THESE AMOUNTS SHOULD BE INCLUDED AS "DEDUCTIONS" ON REPORT 18. | J105: =SUM(J96:J104) -> 0 | K105: =SUM(K96:K104) -> 0 | L105: =IF(J105=K105,"<- Debits and Credits equal each other.","<- Debits and Credits do not equal each other.") -> <- Debits and Credits equal each other.
B106: ** This amount should be included in the deductions column on the LS-Lease Liability and LS-Check Figures Tabs.
A109: 10 | B109: Record lease modifications to increase in the RTU leased asset.
A110: *Rpt 18 | B110: Dr: Acct 0476 - RIGHT-TO-USE LEASED LAND - AMORTIZABLE
A111: *Rpt 18 | B111: Dr: Acct 0478 - RIGHT-TO-USE LEASED EQUIPMENT - AMORTIZABLE
A112: *Rpt 18 | B112: Dr: Acct 0477 - RIGHT-TO-USE LEASED BUILDINGS - AMORTIZABLE
A113: **LS LL/CF | C113: Cr: Acct 0691 - RIGHT-TO-USE LEASE LIABILITY
B114: * THESE AMOUNTS SHOULD BE INCLUDED AS "ADDITIONS" ON REPORT 18. | J114: =SUM(J110:J113) -> 0 | K114: =SUM(K110:K113) -> 0 | L114: =IF(J114=K114,"<- Debits and Credits equal each other.","<- Debits and Credits do not equal each other.") -> <- Debits and Credits equal each other.
B115: ** This amount should be included in the additions column on the LS-Lease Liability and LS-Check Figures Tabs.
D120: Informational - Ending Balances of Assets and Liabilities
K121: Debit (Credit)
D122: Acct 0476 - RIGHT-TO-USE LEASED LAND - AMORTIZABLE | K122: =J15+J39-K88-K101+J110 -> 0
D123: Acct 0478 - RIGHT-TO-USE LEASED EQUIPMENT - AMORTIZABLE | K123: =J16+J40-K89-K102+J111 -> 0
D124: Acct 0477 - RIGHT-TO-USE LEASED BUILDINGS - AMORTIZABLE | K124: =J17+J41-K90-K103+J112 -> 0
D125: Acct 0485 - ACCUMULATED AMORTIZATION - RIGHT-TO-USE LEASED LAND | K125: =-K20-K56+J85+J97 -> 0
...

Sheet LS-Fund 0777 Journal Entries
A1: Lessee-Type Contracts Fund-by-Fund Journal Entries Form (to be submitted to the SCO annually—one form per fund)
A2: Manually complete every yellow field in this worksheet—there are no automatically calculated data-entry cells in this worksheet.
A3: Fiscal Year: | F3: 2023–2024
A4: Organization Name: | F4: Department of Consumer Affairs
A5: Organization Code (4-Digits): | F5: 1111
A6: Fund Number (4-Digits): | F6: 777
A7: Fund Classification: | F7: Governmental
A8: Fund Type: | F8: Governmental Fund
A9: Functional Expense: | F9: =IFERROR(IF(F7="Proprietary","Proprietary Fund",VLOOKUP(F5,[15]qryIndex02a!$A$2:$K$654,4,FALSE)),"Unidentified") -> BUS, CONSUMER SERV, HOUSING
A12: Establish Beginning Balances (existing leases only)
A13: Entry #
A14: 0 | B14: Roll forward prior year right-to-use leases to record opening balances. | M14: Combined Lessee Templates | P14: From SCO BB List | S14: Difference
A15: *Rpt 18 | B15: Dr: Acct 0476 - RIGHT-TO-USE LEASED LAND - AMORTIZABLE | J15: =M15 -> 0 | S15: =P15-M15 -> 0 | T15: Report any "Differences" on the Report 18 Differential.
A16: *Rpt 18 | B16: Dr: Acct 0478 - RIGHT-TO-USE LEASED EQUIPMENT - AMORTIZABLE | J16: =M16 -> 0 | S16: =P16-M16 -> 0 | T16: Report any "Differences" on the Report 18 Differential.
A17: *Rpt 18 | B17: Dr: Acct 0477 - RIGHT-TO-USE LEASED BUILDINGS - AMORTIZABLE | J17: =M17 -> 581401 | M17: 581401 | P17: 581401 | S17: =P17-M17 -> 0 | T17: Report any "Differences" on the Report 18 Differential.
B18: Dr: Acct 0950 - BEGINNING FUND BALANCE | J18: =P18 -> 7093 | M18: 7093 | P18: =IF(SUM($Q$20:$Q$23)>SUM($P$15:$P$17),SUM($Q$20:$Q$23)-SUM($P$15:$P$17),0) -> 7093 | S18: =P18-M18 -> 0 | T18: No action required.
B19: Dr: Acct 0952 - BEGINNING FUND ADJUSTMENT/PRIOR PERIOD ADJUSTMENT | J19: =IF(SUM($K$20:$K$24)>SUM($J$15:$J$18),SUM($K$20:$K$24)-SUM($J$15:$J$18),0) -> 0 | S19: =P19-M19 -> 0 | T19: No action required.
C20: Cr: Acct 0485 - ACCUMULATED AMORTIZATION - RIGHT-TO-USE LEASED LAND | K20: =N20 -> 0 | S20: =Q20-N20 -> 0 | T20: No action required.
C21: Cr: Acct 0479 - ACCUMULATED AMORTIZATION - RIGHT-TO-USE LEASED EQUIPMENT | K21: =N21 -> 0 | S21: =Q21-N21 -> 0 | T21: No action required.
C22: Cr: Acct 0486 - ACCUMULATED AMORTIZATION - RIGHT-TO-USE LEASED BUILDINGS | K22: =N22 -> 279072 | N22: 279072 | Q22: 279072 | S22: =Q22-N22 -> 0 | T22: No action required.
A23: **LS LL/CF | C23: Cr: Acct 0691 - RIGHT-TO-USE LEASE LIABILITY | K23: =N23 -> 309422 | N23: 309422 | Q23: 309422 | S23: =Q23-N23 -> 0 | T23: No action required.
C24: Cr: Acct 0950 - BEGINNING FUND BALANCE | K24: =Q24 -> 0 | Q24: =IF(SUM($Q$20:$Q$23)<SUM($P$15:$P$17),-SUM($Q$20:$Q$23)+SUM($P$15:$P$17),0) -> 0 | S24: =Q24-N24 -> 0 | T24: No action required.
C25: Cr: Acct 0952 - BEGINNING FUND ADJUSTMENT/PRIOR PERIOD ADJUSTMENT | K25: =IF(SUM($K$20:$K$24)<SUM($J$15:$J$18),-SUM($K$20:$K$24)+SUM($J$15:$J$18),0) -> 0 | S25: =Q25-N25 -> 0 | T25: No action required.
J26: =SUM(J15:J25) -> 588494 | K26: =SUM(K15:K25) -> 588494 | L26: =IF(J26=K26,"<- Debits and Credits equal each other.","<- Debits and Credits do not equal each other.") -> <- Debits and Credits equal each other.
B27: * THESE ASSET AMOUNTS SHOULD BE REPORTED AS BEGINNING BALANCES ON REPORT 18.
B28: ** This amount should be included in the beginning balance column on the LS-Lease Liability and LS-Check Figures Tabs.
A31: Record New Leases (new leases only)
A32: 1 | B32: Record lease contract commencement (fund-based entries only)
B33: Dr: Acct 0842 - CAPITAL OUTLAY
C34: Cr: Acct 0789 - LEASE AND OTHER FINANCING PROCEEDS
C35: =IF($F$7="Proprietary","Cr: Acct 0870 - SERVICES & CHARGES (MG ADJ)",VLOOKUP($F$9,'[15]Drop Down Menus'!$F$2:$G$10,2,FALSE)) -> Cr: Acct 0825 - BUS, CONSUMER SERV, HOUSING
J36: =SUM(J33:J35) -> 0 | K36: =SUM(K33:K35) -> 0 | L36: =IF(J36=K36,"<- Debits and Credits equal each other.","<- Debits and Credits do not equal each other.") -> <- Debits and Credits equal each other.
A38: 2 | B38: Record leased assets.
A39: *Rpt 18 | B39: Dr: Acct 0476 - RIGHT-TO-USE LEASED LAND - AMORTIZABLE
A40: *Rpt 18 | B40: Dr: Acct 0478 - RIGHT-TO-USE LEASED EQUIPMENT - AMORTIZABLE
A41: *Rpt 18 | B41: Dr: Acct 0477 - RIGHT-TO-USE LEASED BUILDINGS - AMORTIZABLE
C42: Cr: Acct 0842 - CAPITAL OUTLAY
B43: * THESE AMOUNTS SHOULD BE INCLUDED AS "ADDITIONS" ON REPORT 18. | J43: =SUM(J39:J42) -> 0 | K43: =SUM(K39:K42) -> 0 | L43: =IF(J43=K43,"<- Debits and Credits equal each other.","<- Debits and Credits do not equal each other.") -> <- Debits and Credits equal each other.
A46: 3 | B46: Replace proceeds from leases with right-to-use lease liability.
B47: Dr: Acct 0789 - LEASE AND OTHER FINANCING PROCEEDS
A48: **LS LL/CF | C48: Cr: Acct 0691 - RIGHT-TO-USE LEASE LIABILITY
J49: =SUM(J47:J48) -> 0 | K49: =SUM(K47:K48) -> 0 | L49: =IF(J49=K49,"<- Debits and Credits equal each other.","<- Debits and Credits do not equal each other.") -> <- Debits and Credits equal each other.
B50: ** This amount should be included in the additions column on the LS-Lease Liability and LS-Check Figures Tabs.
A53: Record Annual Activity (all leases)
A54: 4 | B54: Record amortization of the leased assets for the year.
B55: Dr: Acct 0875 - DEPRECIATION/AMORTIZATION | J55: 139536
C56: Cr: Acct 0485 - ACCUMULATED AMORTIZATION - RIGHT-TO-USE LEASED LAND
C57: Cr: Acct 0479 - ACCUMULATED AMORTIZATION - RIGHT-TO-USE LEASED EQUIPMENT
C58: Cr: Acct 0486 - ACCUMULATED AMORTIZATION - RIGHT-TO-USE LEASED BUILDINGS | K58: 139536
J59: =SUM(J55:J58) -> 139536 | K59: =SUM(K55:K58) -> 139536 | L59: =IF(J59=K59,"<- Debits and Credits equal each other.","<- Debits and Credits do not equal each other.") -> <- Debits and Credits equal each other.
A61: 5 | B61: Reclassify rents and leases exp. to lease contract principal and interest exp.
B62: Dr: Acct 0848 - DEBT SERVICE - PRINCIPAL LEASES | J62: 140882 | L62: =IF($J$62=$K$69,"","<- Accts 0848 must agree")
B63: =IF(F7="Governmental","Dr: Acct 0851 - DEBT SERVICE - INTEREST LEASES","Dr: Acct 0894 - INTEREST EXPENSE AND FISCAL CHARGES") -> Dr: Acct 0851 - DEBT SERVICE - INTEREST LEASES | J63: 490
C64: =IF($F$7="Proprietary","Cr: Acct 0870 - SERVICES & CHARGES (MG ADJ)",VLOOKUP($F$9,'[15]Drop Down Menus'!$F$2:$G$10,2,FALSE)) -> Cr: Acct 0825 - BUS, CONSUMER SERV, HOUSING | K64: 141372
J65: =SUM(J62:J64) -> 141372 | K65: =SUM(K62:K64) -> 141372 | L65: =IF(J65=K65,"<- Debits and Credits equal each other.","<- Debits and Credits do not equal each other.") -> <- Debits and Credits equal each other.
A67: 6 | B67: Reduce lease contracts liability for total current year principal payments.
A68: **LS LL/CF | B68: Dr: Acct 0691 - RIGHT-TO-USE LEASE LIABILITY | J68: 140882
C69: Cr: Acct 0848 - DEBT SERVICE - PRINCIPAL LEASES | K69: 140882 | L69: =IF($J$62=$K$69,"","<- Accts 0848 must agree")
J70: =SUM(J68:J69) -> 140882 | K70: =SUM(K68:K69) -> 140882 | L70: =IF(J70=K70,"<- Debits and Credits equal each other.","<- Debits and Credits do not equal each other.") -> <- Debits and Credits equal each other.
B71: ** This amount should be included in the deductions column on the LS-Lease Liability and LS-Check Figures Tabs.
A74: 7 | B74: Reclassify the principal amount due in the next FY to the current liability.
A75: **LS LL/CF | B75: Dr: Acct 0691 - RIGHT-TO-USE LEASE LIABILITY | J75: 144154
C76: Cr: Acct 0649 - RIGHT-TO-USE LEASE LIABILITY (CURRENT PORTION LT) | K76: 144154
B77: NOTE: This is an annual accrual. It is to be reversed at the start of the next fiscal year. SCO combines the current and non current amount in Entry #0 to reestablish the beginning balances. No action required. | J77: =SUM(J75:J76) -> 144154 | K77: =SUM(K75:K76) -> 144154 | L77: =IF(J77=K77,"<- Debits and Credits equal each other.","<- Debits and Credits do not equal each other.") -> <- Debits and Credits equal each other.
B80: ** This amount should be included in the due in one year column on the LS-Lease Liability and LS-Check Figures Tabs.
A83: Remove Lease Asset at the End of the Lease Term (only at the end of the lease term)
A84: 8 | B84: Record entry to write off the lease asset and accumulated amortization at the end of the lease term.
B85: Dr: Acct 0485 - ACCUMULATED AMORTIZATION - RIGHT-TO-USE LEASED LAND
B86: Dr: Acct 0479 - ACCUMULATED AMORTIZATION - RIGHT-TO-USE LEASED EQUIPMENT
B87: Dr: Acct 0486 - ACCUMULATED AMORTIZATION - RIGHT-TO-USE LEASED BUILDINGS
A88: *Rpt 18 | C88: Cr: Acct 0476 - RIGHT-TO-USE LEASED LAND - AMORTIZABLE
A89: *Rpt 18 | C89: Cr: Acct 0478 - RIGHT-TO-USE LEASED EQUIPMENT - AMORTIZABLE
A90: *Rpt 18 | C90: Cr: Acct 0477 - RIGHT-TO-USE LEASED BUILDINGS - AMORTIZABLE
B91: * THESE AMOUNTS SHOULD BE INCLUDED AS "DEDUCTIONS" ON REPORT 18. | J91: =SUM(J85:J90) -> 0 | K91: =SUM(K85:K90) -> 0 | L91: =IF(J91=K91,"<- Debits and Credits equal each other.","<- Debits and Credits do not equal each other.") -> <- Debits and Credits equal each other.
A94: Lease Remeasurement and Modifications (only if a significant modification occurred during the fiscal year)
A95: 9 | B95: Record early termination or lease modifications to decrease in the RTU leased asset.
A96: **LS LL/CF | B96: Dr: Acct 0691 - RIGHT-TO-USE LEASE LIABILITY
B97: Dr: Acct 0485 - ACCUMULATED AMORTIZATION - RIGHT-TO-USE LEASED LAND
B98: Dr: Acct 0479 - ACCUMULATED AMORTIZATION - RIGHT-TO-USE LEASED EQUIPMENT
B99: Dr: Acct 0486 - ACCUMULATED AMORTIZATION - RIGHT-TO-USE LEASED BUILDINGS
B100: =IF($F$7="Proprietary","Dr: Acct 0870 - SERVICES & CHARGES (MG ADJ)",VLOOKUP($F$9,'[15]Drop Down Menus'!$F$2:$H$10,3,FALSE)) -> Dr: Acct 0825 - BUS, CONSUMER SERV, HOUSING
A101: *Rpt 18 | C101: Cr: Acct 0476 - RIGHT-TO-USE LEASED LAND - AMORTIZABLE
A102: *Rpt 18 | C102: Cr: Acct 0478 - RIGHT-TO-USE LEASED EQUIPMENT - AMORTIZABLE
A103: *Rpt 18 | C103: Cr: Acct 0477 - RIGHT-TO-USE LEASED BUILDINGS - AMORTIZABLE
C104: =IF($F$7="Proprietary","Dr: Acct 0870 - SERVICES & CHARGES (MG ADJ)",VLOOKUP($F$9,'[15]Drop Down Menus'!$F$2:$G$10,2,FALSE)) -> Cr: Acct 0825 - BUS, CONSUMER SERV, HOUSING
B105: * THESE AMOUNTS SHOULD BE INCLUDED AS "DEDUCTIONS" ON REPORT 18. | J105: =SUM(J96:J104) -> 0 | K105: =SUM(K96:K104) -> 0 | L105: =IF(J105=K105,"<- Debits and Credits equal each other.","<- Debits and Credits do not equal each other.") -> <- Debits and Credits equal each other.
B106: ** This amount should be included in the deductions column on the LS-Lease Liability and LS-Check Figures Tabs.
A109: 10 | B109: Record lease modifications to increase in the RTU leased asset.
A110: *Rpt 18 | B110: Dr: Acct 0476 - RIGHT-TO-USE LEASED LAND - AMORTIZABLE
A111: *Rpt 18 | B111: Dr: Acct 0478 - RIGHT-TO-USE LEASED EQUIPMENT - AMORTIZABLE
A112: *Rpt 18 | B112: Dr: Acct 0477 - RIGHT-TO-USE LEASED BUILDINGS - AMORTIZABLE
A113: **LS LL/CF | C113: Cr: Acct 0691 - RIGHT-TO-USE LEASE LIABILITY
B114: * THESE AMOUNTS SHOULD BE INCLUDED AS "ADDITIONS" ON REPORT 18. | J114: =SUM(J110:J113) -> 0 | K114: =SUM(K110:K113) -> 0 | L114: =IF(J114=K114,"<- Debits and Credits equal each other.","<- Debits and Credits do not equal each other.") -> <- Debits and Credits equal each other.
B115: ** This amount should be included in the additions column on the LS-Lease Liability and LS-Check Figures Tabs.
D120: Informational - Ending Balances of Assets and Liabilities
K121: Debit (Credit)
D122: Acct 0476 - RIGHT-TO-USE LEASED LAND - AMORTIZABLE | K122: =J15+J39-K88-K101+J110 -> 0
D123: Acct 0478 - RIGHT-TO-USE LEASED EQUIPMENT - AMORTIZABLE | K123: =J16+J40-K89-K102+J111 -> 0
D124: Acct 0477 - RIGHT-TO-USE LEASED BUILDINGS - AMORTIZABLE | K124: =J17+J41-K90-K103+J112 -> 581401
D125: Acct 0485 - ACCUMULATED AMORTIZATION - RIGHT-TO-USE LEASED LAND | K125: =-K20-K56+J85+J97 -> 0
...

Sheet LS-Fund 0779 Journal Entries
A1: Lessee-Type Contracts Fund-by-Fund Journal Entries Form (to be submitted to the SCO annually—one form per fund)
A2: Manually complete every yellow field in this worksheet—there are no automatically calculated data-entry cells in this worksheet.
A3: Fiscal Year: | F3: 2023–2024
A4: Organization Name: | F4: Department of Consumer Affairs
A5: Organization Code (4-Digits): | F5: 1111
A6: Fund Number (4-Digits): | F6: 779
A7: Fund Classification: | F7: Governmental
A8: Fund Type: | F8: Governmental Fund
A9: Functional Expense: | F9: =IFERROR(IF(F7="Proprietary","Proprietary Fund",VLOOKUP(F5,[16]qryIndex02a!$A$2:$K$654,4,FALSE)),"Unidentified") -> BUS, CONSUMER SERV, HOUSING
A12: Establish Beginning Balances (existing leases only)
A13: Entry #
A14: 0 | B14: Roll forward prior year right-to-use leases to record opening balances. | M14: Combined Lessee Templates | P14: From SCO BB List | S14: Difference
A15: *Rpt 18 | B15: Dr: Acct 0476 - RIGHT-TO-USE LEASED LAND - AMORTIZABLE | J15: =M15 -> 0 | S15: =P15-M15 -> 0 | T15: Report any "Differences" on the Report 18 Differential.
A16: *Rpt 18 | B16: Dr: Acct 0478 - RIGHT-TO-USE LEASED EQUIPMENT - AMORTIZABLE | J16: =M16 -> 0 | S16: =P16-M16 -> 0 | T16: Report any "Differences" on the Report 18 Differential.
A17: *Rpt 18 | B17: Dr: Acct 0477 - RIGHT-TO-USE LEASED BUILDINGS - AMORTIZABLE | J17: =M17 -> 1541948 | M17: 1541948 | P17: 1541948 | S17: =P17-M17 -> 0 | T17: Report any "Differences" on the Report 18 Differential.
B18: Dr: Acct 0950 - BEGINNING FUND BALANCE | J18: =P18 -> 8724 | M18: 8724 | P18: =IF(SUM($Q$20:$Q$23)>SUM($P$15:$P$17),SUM($Q$20:$Q$23)-SUM($P$15:$P$17),0) -> 8724 | S18: =P18-M18 -> 0 | T18: No action required.
B19: Dr: Acct 0952 - BEGINNING FUND ADJUSTMENT/PRIOR PERIOD ADJUSTMENT | J19: =IF(SUM($K$20:$K$24)>SUM($J$15:$J$18),SUM($K$20:$K$24)-SUM($J$15:$J$18),0) -> 0 | S19: =P19-M19 -> 0 | T19: No action required.
C20: Cr: Acct 0485 - ACCUMULATED AMORTIZATION - RIGHT-TO-USE LEASED LAND | K20: =N20 -> 0 | S20: =Q20-N20 -> 0 | T20: No action required.
C21: Cr: Acct 0479 - ACCUMULATED AMORTIZATION - RIGHT-TO-USE LEASED EQUIPMENT | K21: =N21 -> 0 | S21: =Q21-N21 -> 0 | T21: No action required.
C22: Cr: Acct 0486 - ACCUMULATED AMORTIZATION - RIGHT-TO-USE LEASED BUILDINGS | K22: =N22 -> 1027966 | N22: 1027966 | Q22: 1027966 | S22: =Q22-N22 -> 0 | T22: No action required.
A23: **LS LL/CF | C23: Cr: Acct 0691 - RIGHT-TO-USE LEASE LIABILITY | K23: =N23 -> 522706 | N23: 522706 | Q23: 522706 | S23: =Q23-N23 -> 0 | T23: No action required.
C24: Cr: Acct 0950 - BEGINNING FUND BALANCE | K24: =Q24 -> 0 | Q24: =IF(SUM($Q$20:$Q$23)<SUM($P$15:$P$17),-SUM($Q$20:$Q$23)+SUM($P$15:$P$17),0) -> 0 | S24: =Q24-N24 -> 0 | T24: No action required.
C25: Cr: Acct 0952 - BEGINNING FUND ADJUSTMENT/PRIOR PERIOD ADJUSTMENT | K25: =IF(SUM($K$20:$K$24)<SUM($J$15:$J$18),-SUM($K$20:$K$24)+SUM($J$15:$J$18),0) -> 0 | S25: =Q25-N25 -> 0 | T25: No action required.
J26: =SUM(J15:J25) -> 1550672 | K26: =SUM(K15:K25) -> 1550672 | L26: =IF(J26=K26,"<- Debits and Credits equal each other.","<- Debits and Credits do not equal each other.") -> <- Debits and Credits equal each other.
B27: * THESE ASSET AMOUNTS SHOULD BE REPORTED AS BEGINNING BALANCES ON REPORT 18.
B28: ** This amount should be included in the beginning balance column on the LS-Lease Liability and LS-Check Figures Tabs.
A31: Record New Leases (new leases only)
A32: 1 | B32: Record lease contract commencement (fund-based entries only)
B33: Dr: Acct 0842 - CAPITAL OUTLAY
C34: Cr: Acct 0789 - LEASE AND OTHER FINANCING PROCEEDS
C35: =IF($F$7="Proprietary","Cr: Acct 0870 - SERVICES & CHARGES (MG ADJ)",VLOOKUP($F$9,'[16]Drop Down Menus'!$F$2:$G$10,2,FALSE)) -> Cr: Acct 0825 - BUS, CONSUMER SERV, HOUSING
J36: =SUM(J33:J35) -> 0 | K36: =SUM(K33:K35) -> 0 | L36: =IF(J36=K36,"<- Debits and Credits equal each other.","<- Debits and Credits do not equal each other.") -> <- Debits and Credits equal each other.
A38: 2 | B38: Record leased assets.
A39: *Rpt 18 | B39: Dr: Acct 0476 - RIGHT-TO-USE LEASED LAND - AMORTIZABLE
A40: *Rpt 18 | B40: Dr: Acct 0478 - RIGHT-TO-USE LEASED EQUIPMENT - AMORTIZABLE
A41: *Rpt 18 | B41: Dr: Acct 0477 - RIGHT-TO-USE LEASED BUILDINGS - AMORTIZABLE
C42: Cr: Acct 0842 - CAPITAL OUTLAY
B43: * THESE AMOUNTS SHOULD BE INCLUDED AS "ADDITIONS" ON REPORT 18. | J43: =SUM(J39:J42) -> 0 | K43: =SUM(K39:K42) -> 0 | L43: =IF(J43=K43,"<- Debits and Credits equal each other.","<- Debits and Credits do not equal each other.") -> <- Debits and Credits equal each other.
A46: 3 | B46: Replace proceeds from leases with right-to-use lease liability.
B47: Dr: Acct 0789 - LEASE AND OTHER FINANCING PROCEEDS
A48: **LS LL/CF | C48: Cr: Acct 0691 - RIGHT-TO-USE LEASE LIABILITY
J49: =SUM(J47:J48) -> 0 | K49: =SUM(K47:K48) -> 0 | L49: =IF(J49=K49,"<- Debits and Credits equal each other.","<- Debits and Credits do not equal each other.") -> <- Debits and Credits equal each other.
B50: ** This amount should be included in the additions column on the LS-Lease Liability and LS-Check Figures Tabs.
A53: Record Annual Activity (all leases)
A54: 4 | B54: Record amortization of the leased assets for the year.
B55: Dr: Acct 0875 - DEPRECIATION/AMORTIZATION | J55: 513982
C56: Cr: Acct 0485 - ACCUMULATED AMORTIZATION - RIGHT-TO-USE LEASED LAND
C57: Cr: Acct 0479 - ACCUMULATED AMORTIZATION - RIGHT-TO-USE LEASED EQUIPMENT
C58: Cr: Acct 0486 - ACCUMULATED AMORTIZATION - RIGHT-TO-USE LEASED BUILDINGS | K58: 513982
J59: =SUM(J55:J58) -> 513982 | K59: =SUM(K55:K58) -> 513982 | L59: =IF(J59=K59,"<- Debits and Credits equal each other.","<- Debits and Credits do not equal each other.") -> <- Debits and Credits equal each other.
A61: 5 | B61: Reclassify rents and leases exp. to lease contract principal and interest exp.
B62: Dr: Acct 0848 - DEBT SERVICE - PRINCIPAL LEASES | J62: 522706 | L62: =IF($J$62=$K$69,"","<- Accts 0848 must agree")
B63: =IF(F7="Governmental","Dr: Acct 0851 - DEBT SERVICE - INTEREST LEASES","Dr: Acct 0894 - INTEREST EXPENSE AND FISCAL CHARGES") -> Dr: Acct 0851 - DEBT SERVICE - INTEREST LEASES | J63: 568
C64: =IF($F$7="Proprietary","Cr: Acct 0870 - SERVICES & CHARGES (MG ADJ)",VLOOKUP($F$9,'[16]Drop Down Menus'!$F$2:$G$10,2,FALSE)) -> Cr: Acct 0825 - BUS, CONSUMER SERV, HOUSING | K64: 523274
J65: =SUM(J62:J64) -> 523274 | K65: =SUM(K62:K64) -> 523274 | L65: =IF(J65=K65,"<- Debits and Credits equal each other.","<- Debits and Credits do not equal each other.") -> <- Debits and Credits equal each other.
A67: 6 | B67: Reduce lease contracts liability for total current year principal payments.
A68: **LS LL/CF | B68: Dr: Acct 0691 - RIGHT-TO-USE LEASE LIABILITY | J68: 522706
C69: Cr: Acct 0848 - DEBT SERVICE - PRINCIPAL LEASES | K69: 522706 | L69: =IF($J$62=$K$69,"","<- Accts 0848 must agree")
J70: =SUM(J68:J69) -> 522706 | K70: =SUM(K68:K69) -> 522706 | L70: =IF(J70=K70,"<- Debits and Credits equal each other.","<- Debits and Credits do not equal each other.") -> <- Debits and Credits equal each other.
B71: ** This amount should be included in the deductions column on the LS-Lease Liability and LS-Check Figures Tabs.
A74: 7 | B74: Reclassify the principal amount due in the next FY to the current liability.
A75: **LS LL/CF | B75: Dr: Acct 0691 - RIGHT-TO-USE LEASE LIABILITY
C76: Cr: Acct 0649 - RIGHT-TO-USE LEASE LIABILITY (CURRENT PORTION LT)
B77: NOTE: This is an annual accrual. It is to be reversed at the start of the next fiscal year. SCO combines the current and non current amount in Entry #0 to reestablish the beginning balances. No action required. | J77: =SUM(J75:J76) -> 0 | K77: =SUM(K75:K76) -> 0 | L77: =IF(J77=K77,"<- Debits and Credits equal each other.","<- Debits and Credits do not equal each other.") -> <- Debits and Credits equal each other.
B80: ** This amount should be included in the due in one year column on the LS-Lease Liability and LS-Check Figures Tabs.
A83: Remove Lease Asset at the End of the Lease Term (only at the end of the lease term)
A84: 8 | B84: Record entry to write off the lease asset and accumulated amortization at the end of the lease term.
B85: Dr: Acct 0485 - ACCUMULATED AMORTIZATION - RIGHT-TO-USE LEASED LAND
B86: Dr: Acct 0479 - ACCUMULATED AMORTIZATION - RIGHT-TO-USE LEASED EQUIPMENT
B87: Dr: Acct 0486 - ACCUMULATED AMORTIZATION - RIGHT-TO-USE LEASED BUILDINGS | J87: 1541948
A88: *Rpt 18 | C88: Cr: Acct 0476 - RIGHT-TO-USE LEASED LAND - AMORTIZABLE
A89: *Rpt 18 | C89: Cr: Acct 0478 - RIGHT-TO-USE LEASED EQUIPMENT - AMORTIZABLE
A90: *Rpt 18 | C90: Cr: Acct 0477 - RIGHT-TO-USE LEASED BUILDINGS - AMORTIZABLE | K90: 1541948
B91: * THESE AMOUNTS SHOULD BE INCLUDED AS "DEDUCTIONS" ON REPORT 18. | J91: =SUM(J85:J90) -> 1541948 | K91: =SUM(K85:K90) -> 1541948 | L91: =IF(J91=K91,"<- Debits and Credits equal each other.","<- Debits and Credits do not equal each other.") -> <- Debits and Credits equal each other.
A94: Lease Remeasurement and Modifications (only if a significant modification occurred during the fiscal year)
A95: 9 | B95: Record early termination or lease modifications to decrease in the RTU leased asset.
A96: **LS LL/CF | B96: Dr: Acct 0691 - RIGHT-TO-USE LEASE LIABILITY
B97: Dr: Acct 0485 - ACCUMULATED AMORTIZATION - RIGHT-TO-USE LEASED LAND
B98: Dr: Acct 0479 - ACCUMULATED AMORTIZATION - RIGHT-TO-USE LEASED EQUIPMENT
B99: Dr: Acct 0486 - ACCUMULATED AMORTIZATION - RIGHT-TO-USE LEASED BUILDINGS
B100: =IF($F$7="Proprietary","Dr: Acct 0870 - SERVICES & CHARGES (MG ADJ)",VLOOKUP($F$9,'[16]Drop Down Menus'!$F$2:$H$10,3,FALSE)) -> Dr: Acct 0825 - BUS, CONSUMER SERV, HOUSING
A101: *Rpt 18 | C101: Cr: Acct 0476 - RIGHT-TO-USE LEASED LAND - AMORTIZABLE
A102: *Rpt 18 | C102: Cr: Acct 0478 - RIGHT-TO-USE LEASED EQUIPMENT - AMORTIZABLE
A103: *Rpt 18 | C103: Cr: Acct 0477 - RIGHT-TO-USE LEASED BUILDINGS - AMORTIZABLE
C104: =IF($F$7="Proprietary","Dr: Acct 0870 - SERVICES & CHARGES (MG ADJ)",VLOOKUP($F$9,'[16]Drop Down Menus'!$F$2:$G$10,2,FALSE)) -> Cr: Acct 0825 - BUS, CONSUMER SERV, HOUSING
B105: * THESE AMOUNTS SHOULD BE INCLUDED AS "DEDUCTIONS" ON REPORT 18. | J105: =SUM(J96:J104) -> 0 | K105: =SUM(K96:K104) -> 0 | L105: =IF(J105=K105,"<- Debits and Credits equal each other.","<- Debits and Credits do not equal each other.") -> <- Debits and Credits equal each other.
B106: ** This amount should be included in the deductions column on the LS-Lease Liability and LS-Check Figures Tabs.
A109: 10 | B109: Record lease modifications to increase in the RTU leased asset.
A110: *Rpt 18 | B110: Dr: Acct 0476 - RIGHT-TO-USE LEASED LAND - AMORTIZABLE
A111: *Rpt 18 | B111: Dr: Acct 0478 - RIGHT-TO-USE LEASED EQUIPMENT - AMORTIZABLE
A112: *Rpt 18 | B112: Dr: Acct 0477 - RIGHT-TO-USE LEASED BUILDINGS - AMORTIZABLE
A113: **LS LL/CF | C113: Cr: Acct 0691 - RIGHT-TO-USE LEASE LIABILITY
B114: * THESE AMOUNTS SHOULD BE INCLUDED AS "ADDITIONS" ON REPORT 18. | J114: =SUM(J110:J113) -> 0 | K114: =SUM(K110:K113) -> 0 | L114: =IF(J114=K114,"<- Debits and Credits equal each other.","<- Debits and Credits do not equal each other.") -> <- Debits and Credits equal each other.
B115: ** This amount should be included in the additions column on the LS-Lease Liability and LS-Check Figures Tabs.
D120: Informational - Ending Balances of Assets and Liabilities
K121: Debit (Credit)
D122: Acct 0476 - RIGHT-TO-USE LEASED LAND - AMORTIZABLE | K122: =J15+J39-K88-K101+J110 -> 0
D123: Acct 0478 - RIGHT-TO-USE LEASED EQUIPMENT - AMORTIZABLE | K123: =J16+J40-K89-K102+J111 -> 0
D124: Acct 0477 - RIGHT-TO-USE LEASED BUILDINGS - AMORTIZABLE | K124: =J17+J41-K90-K103+J112 -> 0
D125: Acct 0485 - ACCUMULATED AMORTIZATION - RIGHT-TO-USE LEASED LAND | K125: =-K20-K56+J85+J97 -> 0
...

Sheet LS-Fund 3017 Journal Entries
A1: Lessee-Type Contracts Fund-by-Fund Journal Entries Form (to be submitted to the SCO annually—one form per fund)
A2: Manually complete every yellow field in this worksheet—there are no automatically calculated data-entry cells in this worksheet.
A3: Fiscal Year: | F3: 2023–2024
A4: Organization Name: | F4: Department of Consumer Affairs
A5: Organization Code (4-Digits): | F5: 1111
A6: Fund Number (4-Digits): | F6: 3017
A7: Fund Classification: | F7: Governmental
A8: Fund Type: | F8: Governmental Fund
A9: Functional Expense: | F9: =IFERROR(IF(F7="Proprietary","Proprietary Fund",VLOOKUP(F5,[17]qryIndex02a!$A$2:$K$654,4,FALSE)),"Unidentified") -> BUS, CONSUMER SERV, HOUSING
A12: Establish Beginning Balances (existing leases only)
A13: Entry #
A14: 0 | B14: Roll forward prior year right-to-use leases to record opening balances. | M14: Combined Lessee Templates | P14: From SCO BB List | S14: Difference
A15: *Rpt 18 | B15: Dr: Acct 0476 - RIGHT-TO-USE LEASED LAND - AMORTIZABLE | J15: =M15 -> 0 | S15: =P15-M15 -> 0 | T15: Report any "Differences" on the Report 18 Differential.
A16: *Rpt 18 | B16: Dr: Acct 0478 - RIGHT-TO-USE LEASED EQUIPMENT - AMORTIZABLE | J16: =M16 -> 0 | S16: =P16-M16 -> 0 | T16: Report any "Differences" on the Report 18 Differential.
A17: *Rpt 18 | B17: Dr: Acct 0477 - RIGHT-TO-USE LEASED BUILDINGS - AMORTIZABLE | J17: =M17 -> 331372 | M17: 331372 | P17: 331372 | S17: =P17-M17 -> 0 | T17: Report any "Differences" on the Report 18 Differential.
B18: Dr: Acct 0950 - BEGINNING FUND BALANCE | J18: =P18 -> 1677 | M18: 1677 | P18: =IF(SUM($Q$20:$Q$23)>SUM($P$15:$P$17),SUM($Q$20:$Q$23)-SUM($P$15:$P$17),0) -> 1677 | S18: =P18-M18 -> 0 | T18: No action required.
B19: Dr: Acct 0952 - BEGINNING FUND ADJUSTMENT/PRIOR PERIOD ADJUSTMENT | J19: =IF(SUM($K$20:$K$24)>SUM($J$15:$J$18),SUM($K$20:$K$24)-SUM($J$15:$J$18),0) -> 0 | S19: =P19-M19 -> 0 | T19: No action required.
C20: Cr: Acct 0485 - ACCUMULATED AMORTIZATION - RIGHT-TO-USE LEASED LAND | K20: =N20 -> 0 | S20: =Q20-N20 -> 0 | T20: No action required.
C21: Cr: Acct 0479 - ACCUMULATED AMORTIZATION - RIGHT-TO-USE LEASED EQUIPMENT | K21: =N21 -> 0 | S21: =Q21-N21 -> 0 | T21: No action required.
C22: Cr: Acct 0486 - ACCUMULATED AMORTIZATION - RIGHT-TO-USE LEASED BUILDINGS | K22: =N22 -> 265098 | N22: 265098 | Q22: 265098 | S22: =Q22-N22 -> 0 | T22: No action required.
A23: **LS LL/CF | C23: Cr: Acct 0691 - RIGHT-TO-USE LEASE LIABILITY | K23: =N23 -> 67951 | N23: 67951 | Q23: 67951 | S23: =Q23-N23 -> 0 | T23: No action required.
C24: Cr: Acct 0950 - BEGINNING FUND BALANCE | K24: =Q24 -> 0 | Q24: =IF(SUM($Q$20:$Q$23)<SUM($P$15:$P$17),-SUM($Q$20:$Q$23)+SUM($P$15:$P$17),0) -> 0 | S24: =Q24-N24 -> 0 | T24: No action required.
C25: Cr: Acct 0952 - BEGINNING FUND ADJUSTMENT/PRIOR PERIOD ADJUSTMENT | K25: =IF(SUM($K$20:$K$24)<SUM($J$15:$J$18),-SUM($K$20:$K$24)+SUM($J$15:$J$18),0) -> 0 | S25: =Q25-N25 -> 0 | T25: No action required.
J26: =SUM(J15:J25) -> 333049 | K26: =SUM(K15:K25) -> 333049 | L26: =IF(J26=K26,"<- Debits and Credits equal each other.","<- Debits and Credits do not equal each other.") -> <- Debits and Credits equal each other.
B27: * THESE ASSET AMOUNTS SHOULD BE REPORTED AS BEGINNING BALANCES ON REPORT 18.
B28: ** This amount should be included in the beginning balance column on the LS-Lease Liability and LS-Check Figures Tabs.
A31: Record New Leases (new leases only)
A32: 1 | B32: Record lease contract commencement (fund-based entries only)
B33: Dr: Acct 0842 - CAPITAL OUTLAY
C34: Cr: Acct 0789 - LEASE AND OTHER FINANCING PROCEEDS
C35: =IF($F$7="Proprietary","Cr: Acct 0870 - SERVICES & CHARGES (MG ADJ)",VLOOKUP($F$9,'[17]Drop Down Menus'!$F$2:$G$10,2,FALSE)) -> Cr: Acct 0825 - BUS, CONSUMER SERV, HOUSING
J36: =SUM(J33:J35) -> 0 | K36: =SUM(K33:K35) -> 0 | L36: =IF(J36=K36,"<- Debits and Credits equal each other.","<- Debits and Credits do not equal each other.") -> <- Debits and Credits equal each other.
A38: 2 | B38: Record leased assets.
A39: *Rpt 18 | B39: Dr: Acct 0476 - RIGHT-TO-USE LEASED LAND - AMORTIZABLE
A40: *Rpt 18 | B40: Dr: Acct 0478 - RIGHT-TO-USE LEASED EQUIPMENT - AMORTIZABLE
A41: *Rpt 18 | B41: Dr: Acct 0477 - RIGHT-TO-USE LEASED BUILDINGS - AMORTIZABLE
C42: Cr: Acct 0842 - CAPITAL OUTLAY
B43: * THESE AMOUNTS SHOULD BE INCLUDED AS "ADDITIONS" ON REPORT 18. | J43: =SUM(J39:J42) -> 0 | K43: =SUM(K39:K42) -> 0 | L43: =IF(J43=K43,"<- Debits and Credits equal each other.","<- Debits and Credits do not equal each other.") -> <- Debits and Credits equal each other.
A46: 3 | B46: Replace proceeds from leases with right-to-use lease liability.
B47: Dr: Acct 0789 - LEASE AND OTHER FINANCING PROCEEDS
A48: **LS LL/CF | C48: Cr: Acct 0691 - RIGHT-TO-USE LEASE LIABILITY
J49: =SUM(J47:J48) -> 0 | K49: =SUM(K47:K48) -> 0 | L49: =IF(J49=K49,"<- Debits and Credits equal each other.","<- Debits and Credits do not equal each other.") -> <- Debits and Credits equal each other.
B50: ** This amount should be included in the additions column on the LS-Lease Liability and LS-Check Figures Tabs.
A53: Record Annual Activity (all leases)
A54: 4 | B54: Record amortization of the leased assets for the year.
B55: Dr: Acct 0875 - DEPRECIATION/AMORTIZATION | J55: 66274
C56: Cr: Acct 0485 - ACCUMULATED AMORTIZATION - RIGHT-TO-USE LEASED LAND
C57: Cr: Acct 0479 - ACCUMULATED AMORTIZATION - RIGHT-TO-USE LEASED EQUIPMENT
C58: Cr: Acct 0486 - ACCUMULATED AMORTIZATION - RIGHT-TO-USE LEASED BUILDINGS | K58: 66274
J59: =SUM(J55:J58) -> 66274 | K59: =SUM(K55:K58) -> 66274 | L59: =IF(J59=K59,"<- Debits and Credits equal each other.","<- Debits and Credits do not equal each other.") -> <- Debits and Credits equal each other.
A61: 5 | B61: Reclassify rents and leases exp. to lease contract principal and interest exp.
B62: Dr: Acct 0848 - DEBT SERVICE - PRINCIPAL LEASES | J62: 67951 | L62: =IF($J$62=$K$69,"","<- Accts 0848 must agree")
B63: =IF(F7="Governmental","Dr: Acct 0851 - DEBT SERVICE - INTEREST LEASES","Dr: Acct 0894 - INTEREST EXPENSE AND FISCAL CHARGES") -> Dr: Acct 0851 - DEBT SERVICE - INTEREST LEASES | J63: 40
C64: =IF($F$7="Proprietary","Cr: Acct 0870 - SERVICES & CHARGES (MG ADJ)",VLOOKUP($F$9,'[17]Drop Down Menus'!$F$2:$G$10,2,FALSE)) -> Cr: Acct 0825 - BUS, CONSUMER SERV, HOUSING | K64: 67991
J65: =SUM(J62:J64) -> 67991 | K65: =SUM(K62:K64) -> 67991 | L65: =IF(J65=K65,"<- Debits and Credits equal each other.","<- Debits and Credits do not equal each other.") -> <- Debits and Credits equal each other.
A67: 6 | B67: Reduce lease contracts liability for total current year principal payments.
A68: **LS LL/CF | B68: Dr: Acct 0691 - RIGHT-TO-USE LEASE LIABILITY | J68: 67951
C69: Cr: Acct 0848 - DEBT SERVICE - PRINCIPAL LEASES | K69: 67951 | L69: =IF($J$62=$K$69,"","<- Accts 0848 must agree")
J70: =SUM(J68:J69) -> 67951 | K70: =SUM(K68:K69) -> 67951 | L70: =IF(J70=K70,"<- Debits and Credits equal each other.","<- Debits and Credits do not equal each other.") -> <- Debits and Credits equal each other.
B71: ** This amount should be included in the deductions column on the LS-Lease Liability and LS-Check Figures Tabs.
A74: 7 | B74: Reclassify the principal amount due in the next FY to the current liability.
A75: **LS LL/CF | B75: Dr: Acct 0691 - RIGHT-TO-USE LEASE LIABILITY
C76: Cr: Acct 0649 - RIGHT-TO-USE LEASE LIABILITY (CURRENT PORTION LT)
B77: NOTE: This is an annual accrual. It is to be reversed at the start of the next fiscal year. SCO combines the current and non current amount in Entry #0 to reestablish the beginning balances. No action required. | J77: =SUM(J75:J76) -> 0 | K77: =SUM(K75:K76) -> 0 | L77: =IF(J77=K77,"<- Debits and Credits equal each other.","<- Debits and Credits do not equal each other.") -> <- Debits and Credits equal each other.
B80: ** This amount should be included in the due in one year column on the LS-Lease Liability and LS-Check Figures Tabs.
A83: Remove Lease Asset at the End of the Lease Term (only at the end of the lease term)
A84: 8 | B84: Record entry to write off the lease asset and accumulated amortization at the end of the lease term.
B85: Dr: Acct 0485 - ACCUMULATED AMORTIZATION - RIGHT-TO-USE LEASED LAND
B86: Dr: Acct 0479 - ACCUMULATED AMORTIZATION - RIGHT-TO-USE LEASED EQUIPMENT
B87: Dr: Acct 0486 - ACCUMULATED AMORTIZATION - RIGHT-TO-USE LEASED BUILDINGS | J87: 331372
A88: *Rpt 18 | C88: Cr: Acct 0476 - RIGHT-TO-USE LEASED LAND - AMORTIZABLE
A89: *Rpt 18 | C89: Cr: Acct 0478 - RIGHT-TO-USE LEASED EQUIPMENT - AMORTIZABLE
A90: *Rpt 18 | C90: Cr: Acct 0477 - RIGHT-TO-USE LEASED BUILDINGS - AMORTIZABLE | K90: 331372
B91: * THESE AMOUNTS SHOULD BE INCLUDED AS "DEDUCTIONS" ON REPORT 18. | J91: =SUM(J85:J90) -> 331372 | K91: =SUM(K85:K90) -> 331372 | L91: =IF(J91=K91,"<- Debits and Credits equal each other.","<- Debits and Credits do not equal each other.") -> <- Debits and Credits equal each other.
A94: Lease Remeasurement and Modifications (only if a significant modification occurred during the fiscal year)
A95: 9 | B95: Record early termination or lease modifications to decrease in the RTU leased asset.
A96: **LS LL/CF | B96: Dr: Acct 0691 - RIGHT-TO-USE LEASE LIABILITY
B97: Dr: Acct 0485 - ACCUMULATED AMORTIZATION - RIGHT-TO-USE LEASED LAND
B98: Dr: Acct 0479 - ACCUMULATED AMORTIZATION - RIGHT-TO-USE LEASED EQUIPMENT
B99: Dr: Acct 0486 - ACCUMULATED AMORTIZATION - RIGHT-TO-USE LEASED BUILDINGS
B100: =IF($F$7="Proprietary","Dr: Acct 0870 - SERVICES & CHARGES (MG ADJ)",VLOOKUP($F$9,'[17]Drop Down Menus'!$F$2:$H$10,3,FALSE)) -> Dr: Acct 0825 - BUS, CONSUMER SERV, HOUSING
A101: *Rpt 18 | C101: Cr: Acct 0476 - RIGHT-TO-USE LEASED LAND - AMORTIZABLE
A102: *Rpt 18 | C102: Cr: Acct 0478 - RIGHT-TO-USE LEASED EQUIPMENT - AMORTIZABLE
A103: *Rpt 18 | C103: Cr: Acct 0477 - RIGHT-TO-USE LEASED BUILDINGS - AMORTIZABLE
C104: =IF($F$7="Proprietary","Dr: Acct 0870 - SERVICES & CHARGES (MG ADJ)",VLOOKUP($F$9,'[17]Drop Down Menus'!$F$2:$G$10,2,FALSE)) -> Cr: Acct 0825 - BUS, CONSUMER SERV, HOUSING
B105: * THESE AMOUNTS SHOULD BE INCLUDED AS "DEDUCTIONS" ON REPORT 18. | J105: =SUM(J96:J104) -> 0 | K105: =SUM(K96:K104) -> 0 | L105: =IF(J105=K105,"<- Debits and Credits equal each other.","<- Debits and Credits do not equal each other.") -> <- Debits and Credits equal each other.
B106: ** This amount should be included in the deductions column on the LS-Lease Liability and LS-Check Figures Tabs.
A109: 10 | B109: Record lease modifications to increase in the RTU leased asset.
A110: *Rpt 18 | B110: Dr: Acct 0476 - RIGHT-TO-USE LEASED LAND - AMORTIZABLE
A111: *Rpt 18 | B111: Dr: Acct 0478 - RIGHT-TO-USE LEASED EQUIPMENT - AMORTIZABLE
A112: *Rpt 18 | B112: Dr: Acct 0477 - RIGHT-TO-USE LEASED BUILDINGS - AMORTIZABLE
A113: **LS LL/CF | C113: Cr: Acct 0691 - RIGHT-TO-USE LEASE LIABILITY
B114: * THESE AMOUNTS SHOULD BE INCLUDED AS "ADDITIONS" ON REPORT 18. | J114: =SUM(J110:J113) -> 0 | K114: =SUM(K110:K113) -> 0 | L114: =IF(J114=K114,"<- Debits and Credits equal each other.","<- Debits and Credits do not equal each other.") -> <- Debits and Credits equal each other.
B115: ** This amount should be included in the additions column on the LS-Lease Liability and LS-Check Figures Tabs.
D120: Informational - Ending Balances of Assets and Liabilities
K121: Debit (Credit)
D122: Acct 0476 - RIGHT-TO-USE LEASED LAND - AMORTIZABLE | K122: =J15+J39-K88-K101+J110 -> 0
D123: Acct 0478 - RIGHT-TO-USE LEASED EQUIPMENT - AMORTIZABLE | K123: =J16+J40-K89-K102+J111 -> 0
D124: Acct 0477 - RIGHT-TO-USE LEASED BUILDINGS - AMORTIZABLE | K124: =J17+J41-K90-K103+J112 -> 0
D125: Acct 0485 - ACCUMULATED AMORTIZATION - RIGHT-TO-USE LEASED LAND | K125: =-K20-K56+J85+J97 -> 0
...

Sheet LS-Lease Liabilities
J3: Schedule of Changes in Lease Liabilities
J4: =CONCATENATE("FY ",'[18]LS-Fund xxxx Journal Entries'!F3) -> FY 2023–2024
J5: =CONCATENATE("Business Unit ",'[18]LS-Department Note Disclosure'!B9," - ",'[18]LS-Department Note Disclosure'!B10) -> Business Unit 1111 - Department of Consumer Affairs
F7: =CONCATENATE("Balance July 1, ",MID(J4,4,4)) -> Balance July 1, 2023 | H7: Additions | J7: Deductions | L7: =CONCATENATE("Balance June 30, ",RIGHT(J4,4)) -> Balance June 30, 2024 | N7: Due Within One Year | P7: Noncurrent Liabilities
F8: (Entry #0) | H8: (Entry #3 & 10) | J8: (Entry #6 & 9) | N8: (Entry #7)
C9: Governmental Funds
D10: Lease Liability | F10: 28785185 | H10: 17098929 | J10: 15588107 | L10: =SUM(F10+H10-J10) -> 30296007 | N10: 12140181 | P10: =L10-N10 -> 18155826
C11: Total Governmental Funds | F11: =SUM(F10:F10) -> 28785185 | H11: =SUM(H10:H10) -> 17098929 | J11: =SUM(J10:J10) -> 15588107 | L11: =SUM(L10:L10) -> 30296007 | N11: =SUM(N10:N10) -> 12140181 | P11: =SUM(P10:P10) -> 18155826
C13: Proprietary - Internal Service Funds
D14: Lease Liability | L14: =SUM(F14+H14-J14) -> 0 | P14: =L14-N14 -> 0
C15: Total Proprietary - Internal Service Funds | F15: =SUM(F14:F14) -> 0 | H15: =SUM(H14:H14) -> 0 | J15: =SUM(J14:J14) -> 0 | L15: =SUM(L14:L14) -> 0 | N15: =SUM(N14:N14) -> 0 | P15: =SUM(P14:P14) -> 0
C17: Proprietary - Enterprise Funds
D18: Lease Liability | L18: =SUM(F18+H18-J18) -> 0 | P18: =L18-N18 -> 0
C19: Total Proprietary - Enterprise Funds | F19: =SUM(F18:F18) -> 0 | H19: =SUM(H18:H18) -> 0 | J19: =SUM(J18:J18) -> 0 | L19: =SUM(L18:L18) -> 0 | N19: =SUM(N18:N18) -> 0 | P19: =SUM(P18:P18) -> 0
B22: THIS SCHEDULE IS FOR THE CHANGE IN LEASE LIABILITY (ACCOUNT 0691) ONLY. THESE AMOUNTS WILL DIFFER FROM THE REPORT 18 (ASSETS).
B23: NOTE: If multiple funds are included in this workbook, manually complete every yellow field by consolidating the entries by fund type (Governmental, Proprietary ISF, and Proprietary EF).

Sheet LS-Department Note Disclosure
A1: Submit one form for the department to the SCO annually.
A2: Note: There are three tables of note disclosures on this form —1) governmental funds, 2) proprietary - internal service funds, and 3) proprietary - enterprise funds. Complete all applicable tables before submitting to the SCO.
A3: Manually complete every yellow field in this worksheet—there are no automatically calculated cells in this worksheet.
A4: Complete the fields below using aggregated and summarized information from all of your department's completed contract template forms.
A5: The fields in this worksheet should contain the sums of the department's contracts' corresponding information in their note disclosure worksheets.
A7: I. Governmental funds
A8: Fiscal Year: | B8: 2023–2024
A9: Organization Code: | B9: 1111
A10: Organization Name: | B10: Department of Consumer Affairs
A11: The below information must be entered manually. DO NOT ENTER DECIMALS. PLEASE ROUND TO THE NEAREST DOLLAR.
B12: Principal Payments | C12: Interest Payments | D12: ="All of the below questions are for Fiscal Year "&$B$8&":" -> All of the below questions are for Fiscal Year 2023–2024:
A13: =RIGHT(B8,4)&"–"&RIGHT(B8,4)+1 -> 2024–2025 | B13: 12140181 | C13: 445433 | D13: 1. Did your leasing arrangements have any variable payments which ARE NOT included in the measurement of the lease liability?
A14: =LEFT(A13,4)+1&"–"&RIGHT(A13,4)+1 -> 2025–2026 | B14: 6729986 | C14: 323366
A15: =LEFT(A14,4)+1&"–"&RIGHT(A14,4)+1 -> 2026–2027 | B15: 4911462 | C15: 210051 | D15: No
A16: =LEFT(A15,4)+1&"–"&RIGHT(A15,4)+1 -> 2027–2028 | B16: 3592236 | C16: 114549 | D16: ="If yes, record the dollar amount of variable payments below for fiscal year "&$B$8&":" -> If yes, record the dollar amount of variable payments below for fiscal year 2023–2024:
A17: =LEFT(A16,4)+1&"–"&RIGHT(A16,4)+1 -> 2028–2029 | B17: 2646336 | C17: 41556
A18: =LEFT(A17,4)+1&"–"&RIGHT(A17,4)+5 -> 2029–2034 | B18: 275806 | C18: 5391 | D18: 2. Do your leasing arrangements have any residual value guarantees provided by YOU which ARE NOT included in the measurement of the lease liability?
A19: =LEFT(A18,4)+5&"–"&RIGHT(A18,4)+5 -> 2034–2039
A20: =LEFT(A19,4)+5&"–"&RIGHT(A19,4)+5 -> 2039–2044 | D20: No
A21: =LEFT(A20,4)+5&"–"&RIGHT(A20,4)+5 -> 2044–2049 | D21: ="If yes, record the dollar amount of any payments made for residual value guarantees below for fiscal year "&$B$8&":" -> If yes, record the dollar amount of any payments made for residual value guarantees below for fiscal year 2023–2024:
A22: =LEFT(A21,4)+5&"–"&RIGHT(A21,4)+5 -> 2049–2054
A23: =LEFT(A22,4)+5&"–"&RIGHT(A22,4)+5 -> 2054–2059
A24: =LEFT(A23,4)+5&"–"&RIGHT(A23,4)+5 -> 2059–2064 | D24: ="3. Record the dollar amount of any other payments for this lease, such as termination penalties, not previously recorded in the payment schedule for fiscal year "&$B$8&":" -> 3. Record the dollar amount of any other payments for this lease, such as termination penalties, not previously recorded in the payment schedule for fiscal year 2023–2024:
A25: =LEFT(A24,4)+5&"–"&RIGHT(A24,4)+5 -> 2064–2069
A26: =LEFT(A25,4)+5&"–"&RIGHT(A25,4)+5 -> 2069–2074
A27: =LEFT(A26,4)+5&"–"&RIGHT(A26,4)+5 -> 2074–2079 | D27: ="4. Did you receive any lease incentives from the lessor (not already included in the lease measurment) during fiscal year "&$B$8&"? If so, record the amount below:" -> 4. Did you receive any lease incentives from the lessor (not already included in the lease measurment) during fiscal year 2023–2024? If so, record the amount below:
A28: =LEFT(A27,4)+5&"–"&RIGHT(A27,4)+5 -> 2079–2084
A29: =LEFT(A28,4)+5&"–"&RIGHT(A28,4)+5 -> 2084–2089
A30: =LEFT(A29,4)+5&"–"&RIGHT(A29,4)+5 -> 2089–2094 | D30: =CONCATENATE("5. Are there any lease commitments known that have yet to commence as of June 30, ",RIGHT(B8,4),"?") -> 5. Are there any lease commitments known that have yet to commence as of June 30, 2024?
A31: =LEFT(A30,4)+5&"–"&RIGHT(A30,4)+5 -> 2094–2099 | D31: No
A32: =LEFT(A31,4)+5&"–"&RIGHT(A31,4)+5 -> 2099–2104 | D32: ="If yes, record the dollar amount of any lease commitments not commenced below for fiscal year "&A13&"." -> If yes, record the dollar amount of any lease commitments not commenced below for fiscal year 2024–2025.
A33: =LEFT(A32,4)+5&"–"&RIGHT(A32,4)+5 -> 2104–2109
A34: =LEFT(A33,4)+5&"–"&RIGHT(A33,4)+5 -> 2109–2114
A35: =LEFT(A34,4)+5&"–"&RIGHT(A34,4)+5 -> 2114–2119
A36: =LEFT(A35,4)+5&"–"&RIGHT(A35,4)+5 -> 2119–2124
A38: II. Proprietary - INTERNAL SERVICE FUNDS
A39: Fiscal Year: | B39: =B8 -> 2023–2024
A40: Organization Code: | B40: =B9 -> 1111
A41: Organization Name: | B41: =B10 -> Department of Consumer Affairs
A42: The below information must be entered manually. DO NOT ENTER DECIMALS. PLEASE ROUND TO THE NEAREST DOLLAR.
B43: Principal Payments | C43: Interest Payments | D43: ="All of the below questions are for Fiscal Year "&$B$8&":" -> All of the below questions are for Fiscal Year 2023–2024:
A44: =RIGHT(B39,4)&"–"&RIGHT(B39,4)+1 -> 2024–2025 | D44: 1. Did your leasing arrangements have any variable payments which ARE NOT included in the measurement of the lease liability?
A45: =LEFT(A44,4)+1&"–"&RIGHT(A44,4)+1 -> 2025–2026
A46: =LEFT(A45,4)+1&"–"&RIGHT(A45,4)+1 -> 2026–2027
A47: =LEFT(A46,4)+1&"–"&RIGHT(A46,4)+1 -> 2027–2028 | D47: ="If yes, record the dollar amount of variable payments below for fiscal year "&$B$8&":" -> If yes, record the dollar amount of variable payments below for fiscal year 2023–2024:
A48: =LEFT(A47,4)+1&"–"&RIGHT(A47,4)+1 -> 2028–2029
A49: =LEFT(A48,4)+1&"–"&RIGHT(A48,4)+5 -> 2029–2034 | D49: 2. Do your leasing arrangements have any residual value guarantees provided by YOU which ARE NOT included in the measurement of the lease liability?
A50: =LEFT(A49,4)+5&"–"&RIGHT(A49,4)+5 -> 2034–2039
A51: =LEFT(A50,4)+5&"–"&RIGHT(A50,4)+5 -> 2039–2044
A52: =LEFT(A51,4)+5&"–"&RIGHT(A51,4)+5 -> 2044–2049 | D52: ="If yes, record the dollar amount of any payments made for residual value guarantees below for fiscal year "&$B$8&":" -> If yes, record the dollar amount of any payments made for residual value guarantees below for fiscal year 2023–2024:
A53: =LEFT(A52,4)+5&"–"&RIGHT(A52,4)+5 -> 2049–2054
A54: =LEFT(A53,4)+5&"–"&RIGHT(A53,4)+5 -> 2054–2059
