Workbook
Name ActuaryCredentialsGASB: [1]DeveloperInfo!$D$19
Name ActuaryNameGASB: [1]DeveloperInfo!$D$17
Name ActuaryTitleGASB: [1]DeveloperInfo!$D$18
Name AdjCNSDate: [1]DeveloperInfo!$D$33
Name AdjCNSDate1: [1]DeveloperInfo!$E$33
Name AdjCNSDateTempEnable: [1]DeveloperInfo!$F$34
Name AgencyCode: #REF!
Name AgencyCode: #REF!
Name AgencyCode: #REF!
Name AgencyCode: #REF!
Name AgencyCode1: #REF!
Name AgencyCode1: #REF!
Name AgencyCode1: #REF!
Name AgencyCode1: #REF!
Name AnalystGASB: [1]DeveloperInfo!$D$20
Name Annuity: #REF!
Name Annuity: #REF!
Name Annuity: #REF!
Name Annuity: #REF!
Name Annuity1: #REF!
Name Annuity1: #REF!
Name Annuity1: #REF!
Name Annuity1: #REF!
Name AnnuityLY: #REF!
Name AnnuityLY: #REF!
Name AnnuityLY: #REF!
Name AnnuityLY: #REF!
Name ASTABPF: [1]DeveloperInfo!$D$36
Name ASTABPF1: [1]DeveloperInfo!$D$37
Name ASTEBPF: [1]DeveloperInfo!$F$37
Name ClientShortGASB: [1]DeveloperInfo!$D$9
Name CLPOWERDisc: [1]Adjust!$H$199
Name CLPOWERDiscMinus1: [1]Adjust!$L$199
Name CLPOWERDiscPlus1: [1]Adjust!$K$199
Name CLPOWERExp: [1]Adjust!$G$199
Name CNSDateDisc: [1]DeveloperInfo!$D$32
Name CNSDateDisc1: [1]DeveloperInfo!$E$32
Name ColaRate: [1]DeveloperInfo!$D$40
Name ConsultantNameGASB: [1]DeveloperInfo!$D$22
Name ConsultantTitleGASB: [1]DeveloperInfo!$D$23
Name Disc1DELTACENSUS: [1]Adjust!$G$102
Name Disc1INTNDIV12: [1]Adjust!$H$195
Name Disc1SINTADJBOM: [1]Adjust!$I$197
Name Disc1SINTNDIV12: [1]Adjust!$I$195
Name DiscDELTACENSUS: [1]Adjust!$H$102
Name DiscINTADJBOM: [1]Adjust!$J$197
Name DiscINTNDIV12: [1]Adjust!$J$195
Name DiscMinusOneINTADJBOM: [1]Adjust!$L$197
Name DiscMinusOneINTNDIV12: [1]Adjust!$L$195
Name DiscPlusOneINTADJBOM: [1]Adjust!$K$197
Name DiscPlusOneINTNDIV12: [1]Adjust!$K$195
Name EmployerRates: #REF!
Name EmployerRates: #REF!
Name EmployerRates: #REF!
Name EmployerRates: #REF!
Name EmployerRates1: #REF!
Name EmployerRates1: #REF!
Name EmployerRates1: #REF!
Name EmployerRates1: #REF!
Name EmployerRatesLEO: #REF!

Sheet Drop Down Menus
A1: 2021–2022 | B1: Governmental | C1: FI$Cal | D1: Yes | E1: Governmental Fund | G1: Please select fund type above.
A2: 2022–2023 | B2: Proprietary | C2: Non-FI$Cal | D2: No | E2: Proprietary - Internal Service Fund | F2: General government | G2: Cr: Acct 0808 - GENERAL GOV. (GAAP ADJ) | H2: Dr: Acct 0808 - GENERAL GOV. (GAAP ADJ)
A3: 2023–2024 | E3: Proprietary - Enterprise Fund | F3: Education | G3: Cr: Acct 0810 - EDUCATION EXP (GAAP ADJ) | H3: Dr: Acct 0810 - EDUCATION EXP (GAAP ADJ)
A4: 2024–2025 | F4: Health and human services | G4: Cr: Acct 0815 - HLTH&HUM SV SV.LAB(GAAP ADJ) | H4: Dr: Acct 0815 - HLTH&HUM SV SV.LAB(GAAP ADJ)
A5: 2025–2026 | F5: Resources | G5: Cr: Acct 0820 - NAT RES & ENVIRON (GAAP ADJ) | H5: Dr: Acct 0820 - NAT RES & ENVIRON (GAAP ADJ)
A6: 2026–2027 | F6: BUS, CONSUMER SERV, HOUSING | G6: Cr: Acct 0825 - BUS, CONSUMER SERV, HOUSING | H6: Dr: Acct 0825 - BUS, CONSUMER SERV, HOUSING
A7: 2027–2028 | F7: Transportation | G7: Cr: Acct 0830 - TRANSPORTATION (GAAP ADJ) | H7: Dr: Acct 0830 - TRANSPORTATION (GAAP ADJ)
A8: 2028–2029 | F8: CORRECTIONS AND REHABILITATION | G8: Cr: Acct 0835 - CORRECTIONS AND REHABILITATION | H8: Dr: Acct 0835 - CORRECTIONS AND REHABILITATION
A9: 2029–2030 | F9: Proprietary fund | G9: Cr: Acct 0870 - SERVICES & CHARGES (MG ADJ) | H9: Dr: Acct 0870 - SERVICES & CHARGES (MG ADJ)
A10: 2030–2031 | F10: Unidentified | G10: Cr: Acct 0XXX - FUNCTIONAL EXPENSE | H10: Dr: Acct 0XXX - FUNCTIONAL EXPENSE
A11: 2031–2032
A12: 2032–2033
A13: 2033–2034
A14: 2034–2035
A15: 2035–2036
A16: 2036–2037
A17: 2037–2038
A18: 2038–2039
A19: 2039–2040
A20: 2040–2041
A21: 2041–2042
A22: 2042–2043
... A101: 2121–2122

Sheet qryIndex02a
A1: Agency | B1: Title | C1: Hier1 | D1: Desc1 | E1: Desc2 | F1: Hier2 | G1: Hier3 | H1: Hier4 | I1: Hier5 | J1: EffectiveDate | K1: CancelDate
A2: 0000 | B2: BOND INTEREST AND REDEMPTION | C2: 9000 | D2: BOND INTEREST AND REDEMPTION | F2: 9030 | G2: 9600 | H2: 0000 | I2: 0000 | J2: 04/04/1984 | K2: 00/00/0000
A3: 0010 | B3: LEGISLATIVE, JUDICIAL AND EXEC | C3: 0808 | D3: GENERAL GOVERNMENT | F3: 0000 | G3: 0000 | H3: 0000 | I3: 0000 | J3: 07/11/2006 | K3: 00/00/0000
A4: 0015 | B4: ADD AGENCY TEST | C4: 0808 | D4: GENERAL GOVERNMENT | F4: 0000 | G4: 0000 | H4: 0000 | I4: 0000 | J4: 99/99/9999 | K4: 00/00/0000
A5: 0020 | B5: LEGISLATIVE | C5: 0808 | D5: GENERAL GOVERNMENT | F5: 0000 | G5: 0000 | H5: 0000 | I5: 0000 | J5: 99/99/9999 | K5: 00/00/0000
A6: 0100 | B6: LEGISLATURE | C6: 0808 | D6: GENERAL GOVERNMENT | F6: 0000 | G6: 0000 | H6: 0000 | I6: 0000 | J6: 99/99/9999 | K6: 00/00/0000
A7: 0110 | B7: SENATE | C7: 0808 | D7: GENERAL GOVERNMENT | F7: 0000 | G7: 0000 | H7: 0000 | I7: 0000 | J7: 06/26/1985 | K7: 00/00/0000
A8: 0120 | B8: ASSEMBLY | C8: 0808 | D8: GENERAL GOVERNMENT | F8: 0000 | G8: 0000 | H8: 0000 | I8: 0000 | J8: 06/26/1985 | K8: 00/00/0000
A9: 0130 | B9: LEGISLATIVE JOINT EXPENSES | C9: 0808 | D9: GENERAL GOVERNMENT | F9: 0000 | G9: 0000 | H9: 0000 | I9: 0000 | J9: 06/26/1985 | K9: 00/00/0000
A10: 0150 | B10: CONTRIB TO LEGIS RETIRE FUND | C10: 0808 | D10: GENERAL GOVERNMENT | F10: 0000 | G10: 0000 | H10: 0000 | I10: 0000 | J10: 07/11/2006 | K10: 00/00/0000
A11: 0155 | B11: AUDITOR GENERAL OFFICE | C11: 0808 | D11: GENERAL GOVERNMENT | F11: 0000 | G11: 0000 | H11: 0000 | I11: 0000 | J11: 99/99/9999 | K11: 00/00/0000
A12: 0160 | B12: LEGISLATIVE COUNSEL BUREAU | C12: 0808 | D12: GENERAL GOVERNMENT | F12: 0000 | G12: 0000 | H12: 0000 | I12: 0000 | J12: 04/04/1984 | K12: 00/00/0000
A13: 0170 | B13: CA LAW REVISION COMMISSION | C13: 0808 | D13: GENERAL GOVERNMENT | F13: 0000 | G13: 0000 | H13: 0000 | I13: 0000 | J13: 99/99/9999 | K13: 07/01/1985
... A190: 2140 | B190: STATE BANKING DEPARTMENT | C190: 0825 | D190: BUS, CONSUMER SERV, HOUSING | F190: 0000 | G190: 0000 | H190: 0000 | I190: 0000 | J190: 12/21/2016 | K190: 00/00/0000
A191: 2150 | B191: FINANCIAL INSTITUTIONS | C191: 0825 | D191: ADD BACK TO POST PY REVERSAL | E191: DELETE 16/17 | F191: 0000 | G191: 0000 | H191: 0000 | I191: 0000 | J191: 08/18/2016 | K191: 00/00/0000
A192: 2180 | B192: DEPART OF CORPORATIONS | C192: 0825 | D192: ADD BACK TO POST PY REVERSAL | E192: DELETE 16/17 | F192: 0000 | G192: 0000 | H192: 0000 | I192: 0000 | J192: 08/24/2016 | K192: 00/00/0000
A193: 2190 | B193: MAJOR MEDICAL INSURANCE BOARD | C193: 0825 | D193: BUS, CONSUMER SERV, HOUSING | F193: 0000 | G193: 0000 | H193: 0000 | I193: 0000 | J193: 12/21/2016 | K193: 00/00/0000
A194: 2200 | B194: DEPARTMENT OF COMMERCE | C194: 0825 | D194: BUS, CONSUMER SERV, HOUSING | F194: 0000 | G194: 0000 | H194: 0000 | I194: 0000 | J194: 12/21/2016 | K194: 00/00/0000
A195: 2220 | B195: OFFICE OF SMALL BUSINESS DEVEL | C195: 0825 | D195: BUS, CONSUMER SERV, HOUSING | F195: 0000 | G195: 0000 | H195: 0000 | I195: 0000 | J195: 12/21/2016 | K195: 00/00/0000
A196: 2222 | B196: ST ASST FD FOR ENTERPRISE | C196: 0825 | D196: BUS, CONSUMER SERV, HOUSING | F196: 0000 | G196: 0000 | H196: 0000 | I196: 0000 | J196: 12/21/2016 | K196: 00/00/0000
A197: 2225 | B197: UNITARY FUND PROGRAMS | C197: 0825 | D197: BUS, CONSUMER SERV, HOUSING | F197: 0000 | G197: 0000 | H197: 0000 | I197: 0000 | J197: 12/21/2016 | K197: 00/00/0000
A198: 2230 | B198: CA INDTRL DEV FINCL ADVRY COMM | C198: 0825 | D198: BUS, CONSUMER SERV, HOUSING | F198: 0000 | G198: 0000 | H198: 0000 | I198: 0000 | J198: 12/21/2016 | K198: 07/01/1985
A199: 2235 | B199: CA HOME LOAN MORTGAGE ASSN | C199: 0825 | D199: BUS, CONSUMER SERV, HOUSING | F199: 0000 | G199: 0000 | H199: 0000 | I199: 0000 | J199: 12/21/2016 | K199: 00/00/0000
A200: 2240 | B200: DEPT-HOUSING/COMMUNITY DEVEL | C200: 0825 | D200: BUS, CONSUMER SERV, HOUSING | F200: 0000 | G200: 0000 | H200: 0000 | I200: 0000 | J200: 12/12/2016 | K200: 00/00/1999
A201: 2245 | B201: CALIFORNIA HOUSING FINANCE AGY | C201: 0825 | D201: BUS, CONSUMER SERV, HOUSING | F201: 0000 | G201: 0000 | H201: 0000 | I201: 0000 | J201: 08/19/2016 | K201: 00/00/0000
A202: 2265 | B202: CALIFORNIA HOUSING INSURANCE | C202: 0825 | D202: BUS, CONSUMER SERV, HOUSING | F202: 0000 | G202: 0000 | H202: 0000 | I202: 0000 | J202: 12/21/2016 | K202: 00/00/0000
A203: 2270 | B203: MORTGAGE BOND ALLOC COMMITTEE | C203: 0825 | D203: BUS, CONSUMER SERV, HOUSING | F203: 0000 | G203: 0000 | H203: 0000 | I203: 0000 | J203: 12/21/2016 | K203: 07/01/1985
A204: 2290 | B204: DEPARTMENT OF INSURANCE | C204: 0825 | D204: BUS, CONSUMER SERV, HOUSING | F204: 0000 | G204: 0000 | H204: 0000 | I204: 0000 | J204: 12/21/2016 | K204: 00/00/1999
... A214: 2670 | B214: BD OF PILOT COMMISSIONERS-SF | C214: 0830 | D214: TRANSPORTATION | F214: 0000 | G214: 0000 | H214: 0000 | I214: 0000 | J214: 08/03/2017 | K214: 00/00/0000
A215: 2700 | B215: OFFICE OF TRAFFIC SAFETY | C215: 0830 | D215: TRANSPORTATION | E215: MERGED W/0521-ADD 4 PY ACCR RV | F215: 0000 | G215: 0000 | H215: 0000 | I215: 0000 | J215: 09/28/2016 | K215: 00/00/0000
A216: 2720 | B216: DEPT OF CAL HIGHWAY PATROL | C216: 0830 | D216: TRANSPORTATION | F216: 0000 | G216: 0000 | H216: 0000 | I216: 0000 | J216: 10/28/2016 | K216: 00/00/1999
A217: 2740 | B217: DEPARTMENT OF MOTOR VEHICLES | C217: 0830 | D217: TRANSPORTATION | F217: 0000 | G217: 0000 | H217: 0000 | I217: 0000 | J217: 10/28/2016 | K217: 00/00/0000
A218: 2780 | B218: STEPHEN P TEALE DATA CENTER | C218: 0825 | D218: BUS, CONSUMER SERV, HOUSING | F218: 0000 | G218: 0000 | H218: 0000 | I218: 0000 | J218: 12/21/2016 | K218: 00/00/0000
A219: 2900 | B219: TRADE AND COMMERCE | C219: 0825 | D219: BUS, CONSUMER SERV, HOUSING | F219: 0000 | G219: 0000 | H219: 0000 | I219: 0000 | J219: 12/21/2016 | K219: 00/00/0000
A220: 2920 | B220: TECHNOLOGY TRADE & COMMERCE AG | C220: 0825 | D220: BUS, CONSUMER SERV, HOUSING | F220: 0000 | G220: 0000 | H220: 0000 | I220: 0000 | J220: 12/21/2016 | K220: 00/00/0000
A221: 3000 | B221: NATURAL RESOURCES | C221: 0820 | D221: RESOURCES | F221: 0000 | G221: 0000 | H221: 0000 | I221: 0000 | J221: 08/25/2010 | K221: 00/00/0000
A222: 3100 | B222: EXPOSITION PARK | C222: 0820 | D222: RESOURCES | F222: 0000 | G222: 0000 | H222: 0000 | I222: 0000 | J222: 10/17/2018 | K222: 00/00/0000
A223: 3105 | B223: CALIFORNIA AFRO-AMERICAN MUSEU | C223: 0820 | D223: RESOURCES | F223: 0000 | G223: 0000 | H223: 0000 | I223: 0000 | J223: 09/05/2014 | K223: 00/00/0000
A224: 3110 | B224: SPECIAL RESOURCES PROGRAMS | C224: 0820 | D224: RESOURCES | F224: 0000 | G224: 0000 | H224: 0000 | I224: 0000 | J224: 07/11/2006 | K224: 00/00/1999
A225: 3125 | B225: CALIF TAHOE CONSERVANCY | C225: 0820 | D225: RESOURCES | F225: 0000 | G225: 0000 | H225: 0000 | I225: 0000 | J225: 04/18/1988 | K225: 00/00/1999
A226: 3130 | B226: WATERWAYS MANAGEMENT PLANNING | C226: 0820 | D226: RESOURCES | F226: 0000 | G226: 0000 | H226: 0000 | I226: 0000 | J226: 99/99/9999 | K226: 00/00/0000
A227: 3140 | B227: SEA GRANT PROGRAM | C227: 0820 | D227: RESOURCES | F227: 0000 | G227: 0000 | H227: 0000 | I227: 0000 | J227: 99/99/9999 | K227: 00/00/0000
... A278: 4140 | B278: OFFICE OF HEALTH PLAN & DEV | C278: 0815 | D278: HEALTH AND HUMAN SERVICES | F278: 0000 | G278: 0000 | H278: 0000 | I278: 0000 | J278: 10/28/2016 | K278: 00/00/0000
A279: 4150 | B279: DEPT OF MANAGED HEALTH CARE | C279: 0815 | D279: HEALTH AND HUMAN SERVICES | E279: RENUMBERED FROM 2400 | F279: 0000 | G279: 0000 | H279: 0000 | I279: 0000 | J279: 10/28/2016 | K279: 00/00/0000
A280: 4170 | B280: DEPARTMENT OF AGING | C280: 0815 | D280: HEALTH AND HUMAN SERVICES | F280: 0000 | G280: 0000 | H280: 0000 | I280: 0000 | J280: 10/28/2016 | K280: 00/00/1999
A281: 4180 | B281: COMMISSION ON AGING | C281: 0815 | D281: HEALTH AND HUMAN SERVICES | F281: 0000 | G281: 0000 | H281: 0000 | I281: 0000 | J281: 10/28/2016 | K281: 00/00/1999
A282: 4185 | B282: CALIFORNIA SENIOR LEGISLATURE | C282: 0815 | D282: HEALTH AND HUMAN SERVICES | F282: 0000 | G282: 0000 | H282: 0000 | I282: 0000 | J282: 10/28/2016 | K282: 00/00/0000
A283: 4210 | B283: GOV COUNCIL DRUG/ALCOHOL ABUSE | C283: 0815 | D283: HEALTH AND HUMAN SERVICES | F283: 0000 | G283: 0000 | H283: 0000 | I283: 0000 | J283: 10/28/2016 | K283: 00/00/0000
A284: 4220 | B284: GOV ADV COM CHILD DEVEL PROG | C284: 0815 | D284: HEALTH AND HUMAN SERVICES | F284: 0000 | G284: 0000 | H284: 0000 | I284: 0000 | J284: 10/28/2016 | K284: 00/00/0000
A285: 4250 | B285: CA. CHILDREN AND FAMILIES COMM | C285: 0815 | D285: HEALTH AND HUMAN SERVICES | F285: 0000 | G285: 0000 | H285: 0000 | I285: 0000 | J285: 10/28/2016 | K285: 00/00/0000
A286: 4260 | B286: DEPARTMENT OF HEALTH CARE SVCS | C286: 0815 | D286: HEALTH AND HUMAN SERVICES | F286: 0000 | G286: 0000 | H286: 0000 | I286: 0000 | J286: 10/28/2016 | K286: 00/00/0000
A287: 4265 | B287: DEPARTMENT OF PUBLIC HEALTH | C287: 0815 | D287: HEALTH AND HUMAN SERVICES | F287: 0000 | G287: 0000 | H287: 0000 | I287: 0000 | J287: 10/28/2016 | K287: 00/00/0000
A288: 4270 | B288: CAL MED ASSISTANCE COMMISSION | C288: 0815 | D288: HEALTH AND HUMAN SERVICES | F288: 0000 | G288: 0000 | H288: 0000 | I288: 0000 | J288: 10/28/2016 | K288: 00/00/1999
A289: 4280 | B289: MANAGED RISK MED INSUR BD. | C289: 0815 | D289: HEALTH AND HUMAN SERVICES | F289: 0000 | G289: 0000 | H289: 0000 | I289: 0000 | J289: 10/28/2016 | K289: 00/00/0000
A290: 4300 | B290: DEPT. DEVELOPMENTAL SVCS | C290: 0815 | D290: HEALTH AND HUMAN SERVICES | F290: 0000 | G290: 0000 | H290: 0000 | I290: 0000 | J290: 10/28/2016 | K290: 00/00/0000
A291: 4310 | B291: DO NOT USE AGENCY MERGED WITH | C291: 0815 | F291: 0000 | G291: 0000 | H291: 0000 | I291: 0000 | J291: 09/07/2018 | K291: 00/00/0000
A292: 4320 | B292: STATE HOSPITALS | C292: 0815 | D292: HEALTH AND HUMAN SERVICES | F292: 0000 | G292: 0000 | H292: 0000 | I292: 0000 | J292: 10/28/2016 | K292: 00/00/0000
A293: 4350 | B293: DO NOT USE AGENCY MERGED WITH | C293: 0815 | F293: 0000 | G293: 0000 | H293: 0000 | I293: 0000 | J293: 09/07/2018 | K293: 00/00/0000
A294: 4370 | B294: DO NOT USE AGENCY MERGED WITH | C294: 0815 | F294: 0000 | G294: 0000 | H294: 0000 | I294: 0000 | J294: 09/07/2018 | K294: 00/00/0000
A295: 4390 | B295: DO NOT USE AGENCY MERGED WITH | C295: 0815 | F295: 0000 | G295: 0000 | H295: 0000 | I295: 0000 | J295: 09/07/2018 | K295: 00/00/0000
A296: 4400 | B296: DO NOT USE AGENCY MERGED WITH | C296: 0815 | F296: 0000 | G296: 0000 | H296: 0000 | I296: 0000 | J296: 09/07/2018 | K296: 00/00/0000
A297: 4430 | B297: DO NOT USE AGENCY MERGED WITH | C297: 0815 | F297: 0000 | G297: 0000 | H297: 0000 | I297: 0000 | J297: 09/07/2018 | K297: 00/00/0000
A298: 4440 | B298: DEPT. OF STATE HOSPITAL | C298: 0815 | D298: HEALTH AND HUMAN SERVICES | F298: 0000 | G298: 0000 | H298: 0000 | I298: 0000 | J298: 10/28/2016 | K298: 00/00/0000
A299: 4450 | B299: SACRAMENTO STATE HOSPITAL | C299: 0815 | D299: HEALTH AND HUMAN SERVICES | F299: 0000 | G299: 0000 | H299: 0000 | I299: 0000 | J299: 10/28/2016 | K299: 00/00/1999
A300: 4460 | B300: STATE HOSPITALS | C300: 0815 | D300: HEALTH AND HUMAN SERVICES | F300: 0000 | G300: 0000 | H300: 0000 | I300: 0000 | J300: 10/28/2016 | K300: 00/00/0000
A301: 4470 | B301: ATASCADERO STATE HOSPITAL | C301: 0815 | D301: HEALTH AND HUMAN SERVICES | F301: 0000 | G301: 0000 | H301: 0000 | I301: 0000 | J301: 10/28/2016 | K301: 00/00/1999
A302: 4490 | B302: METROPOLITAN STATE HOSPITAL | C302: 0815 | D302: HEALTH AND HUMAN SERVICES | F302: 0000 | G302: 0000 | H302: 0000 | I302: 0000 | J302: 10/28/2016 | K302: 00/00/1999
A303: 4500 | B303: NAPA STATE HOSPITAL | C303: 0815 | D303: HEALTH AND HUMAN SERVICES | F303: 0000 | G303: 0000 | H303: 0000 | I303: 0000 | J303: 10/28/2016 | K303: 00/00/1999
A304: 4510 | B304: PATTON STATE HOSPITAL | C304: 0815 | D304: HEALTH AND HUMAN SERVICES | F304: 0000 | G304: 0000 | H304: 0000 | I304: 0000 | J304: 10/28/2016 | K304: 00/00/1999
A305: 4520 | B305: STOCKTON STATE HOSPITAL-DMH | C305: 0815 | D305: HEALTH AND HUMAN SERVICES | F305: 0000 | G305: 0000 | H305: 0000 | I305: 0000 | J305: 10/28/2016 | K305: 00/00/1999
A306: 4530 | B306: VACAVILLE STATE HOSPITAL | C306: 0815 | D306: HEALTH AND HUMAN SERVICES | F306: 0000 | G306: 0000 | H306: 0000 | I306: 0000 | J306: 10/28/2016 | K306: 00/00/0000
A307: 4540 | B307: COALINGA STATE HOSPITAL | C307: 0815 | D307: HEALTH AND HUMAN SERVICES | F307: 0000 | G307: 0000 | H307: 0000 | I307: 0000 | J307: 10/28/2016 | K307: 00/00/0000
A308: 4550 | B308: SALINAS STATE HOSPITAL | C308: 0815 | D308: HEALTH AND HUMAN SERVICES | F308: 0000 | G308: 0000 | H308: 0000 | I308: 0000 | J308: 10/28/2016 | K308: 00/00/0000
A309: 4560 | B309: MENTAL HEALTH SVCS OVERSIGHT | C309: 0815 | D309: HEALTH AND HUMAN SERVICES | F309: 0000 | G309: 0000 | H309: 0000 | I309: 0000 | J309: 10/28/2016 | K309: 00/00/0000
... A597: 9610 | B597: LEASE-REV NOTES & BONDS | C597: 9000 | D597: DEBT SERVICE INT & FISCAL CHGS | F597: 9030 | G597: 9610 | H597: 0000 | I597: 0000 | J597: 08/19/2016 | K597: 00/00/0000
A598: 9612 | B598: ENHN TOBAC ASSET-BACKED BND | C598: 0847 | D598: BOND INTEREST AND REDEMPTION | E598: WHEN TOBACCO REVENUE IS SHORT | F598: 0000 | G598: 0000 | H598: 0000 | I598: 0000 | J598: 08/19/2016 | K598: 00/00/0000
A599: 9613 | B599: UNENHANCED TOBACCO BD PROCEEDS | C599: 0808 | D599: GENERAL GOVERNMENT | F599: 0000 | G599: 0000 | H599: 0000 | I599: 0000 | J599: 02/26/2008 | K599: 00/00/0000
A600: 9618 | B600: ECONOMIC RECOVERY FINANCE COMM | C600: 0808 | D600: GENERAL GOVERNMENT | F600: 0000 | G600: 0000 | H600: 0000 | I600: 0000 | J600: 10/28/2005 | K600: 00/00/0000
A601: 9620 | B601: CASH MGMT & BUDGETARY LOANS | C601: 0850 | D601: DEBT SERVICE INT & FISCAL CHGS | F601: 0000 | G601: 0000 | H601: 0000 | I601: 0000 | J601: 08/19/2016 | K601: 00/00/0000
A602: 9625 | B602: INT PYMTS TO FEDERAL GOVT | C602: 0846 | D602: DEBT SERVICE INT & FISCAL CHGS | F602: 0000 | G602: 0000 | H602: 0000 | I602: 0000 | J602: 08/19/2016 | K602: 00/00/0000
A603: 9632 | B603: STATE MANDATED LOCAL COSTS | C603: 0808 | D603: GENERAL GOVERNMENT | F603: 0000 | G603: 0000 | H603: 0000 | I603: 0000 | J603: 99/99/9999 | K603: 00/00/0000
A604: 9634 | B604: GENERAL OBLIGATION BONDS | C604: 9000 | D604: GENERAL OBLIGATION BONDS | F604: 9030 | G604: 9634 | H604: 0000 | I604: 0000 | J604: 06/13/1988 | K604: 00/00/0000
A605: 9636 | B605: MISCELLANEOUS ADJUSTMENTS | C605: 9000 | D605: MISCELLANEOUS ADJUSTMENTS | F605: 9030 | G605: 9636 | H605: 0000 | I605: 0000 | J605: 06/13/1988 | K605: 00/00/0000
A606: 9650 | B606: HEALTH BENEFITS FOR ANNUITANTS | C606: 0808 | D606: GENERAL GOVERNMENT | F606: 0000 | G606: 0000 | H606: 0000 | I606: 0000 | J606: 04/04/1984 | K606: 00/00/0000
A607: 9651 | B607: PREFUND HEALTH & DENTAL BEN | C607: 0808 | D607: GENERAL GOVERNMENT | F607: 0000 | G607: 0000 | H607: 0000 | I607: 0000 | J607: 08/25/2010 | K607: 00/00/0000
A608: 9658 | B608: BUDGET STABILIZATION ACCOUNT | C608: 0808 | D608: GENERAL GOVERNMENT | F608: 0000 | G608: 0000 | H608: 0000 | I608: 0000 | J608: 07/11/2006 | K608: 00/00/0000
A609: 9670 | B609: LEGISLATIVE CLAIMS | C609: 0808 | D609: GENERAL GOVERNMENT | F609: 0000 | G609: 0000 | H609: 0000 | I609: 0000 | J609: 04/04/1984 | K609: 00/00/0000
A610: 9671 | B610: EQUITY CLAIMS OF BD OF CONTROL | C610: 0808 | D610: GENERAL GOVERNMENT | F610: 0000 | G610: 0000 | H610: 0000 | I610: 0000 | J610: 03/30/1994 | K610: 00/00/0000
... A635: 9885 | B635: RESERVE FOR ENCUMBRANCE | C635: 0808 | D635: GENERAL GOVERNMENT | F635: 0000 | G635: 0000 | H635: 0000 | I635: 0000 | J635: 01/23/1991 | K635: 00/00/0000
A636: 9889 | B636: PUBLIC SCHOOL SYSTEM STABILIZA | C636: 0810 | D636: PUBLIC SCHOOL SYSTEM | E636: STABILIZATION ACCOUNT | F636: 0000 | G636: 0000 | H636: 0000 | I636: 0000 | J636: 04/01/2020 | K636: 00/00/0000
A637: 9890 | B637: RES FOR ECONOMIC UNCERTAINTIES | C637: 0808 | D637: GENERAL GOVERNMENT | F637: 0000 | G637: 0000 | H637: 0000 | I637: 0000 | J637: 07/11/2006 | K637: 00/00/0000
A638: 9891 | B638: DEPT OF HEALTH HUMAN SERVICES | C638: 0815 | D638: HEALTH AND HUMAN SERVICES | F638: 0000 | G638: 0000 | H638: 0000 | I638: 0000 | J638: 10/28/2016 | K638: 00/00/0000
A639: 9892 | B639: SUPPLEMENTAL PENSION PAYMENTS | C639: 0843 | D639: INT. ON INTERFUND LOANS | F639: 0000 | G639: 0000 | H639: 0000 | I639: 0000 | J639: 11/22/2019 | K639: 00/00/0000
A640: 9895 | B640: PETROLEUM VIOLATION ESCROW PRO | C640: 0808 | D640: GENERAL GOVERNMENT | F640: 0000 | G640: 0000 | H640: 0000 | I640: 0000 | J640: 07/11/2006 | K640: 00/00/0000
A641: 9896 | B641: OUTER CONT SHELF LAND ACT | C641: 0808 | D641: GENERAL GOVERNMENT | F641: 0000 | G641: 0000 | H641: 0000 | I641: 0000 | J641: 07/11/2006 | K641: 00/00/0000
A642: 9898 | B642: PERS GENERAL FUND PAYMENT | C642: 0808 | D642: GENERAL GOVERNMENT | F642: 0000 | G642: 0000 | H642: 0000 | I642: 0000 | J642: 11/04/1998 | K642: 00/00/0000
A643: 9900 | B643: GEN FD CREDITS FROM SPEC FUNDS | C643: 0808 | D643: GENERAL GOVERNMENT | F643: 0000 | G643: 0000 | H643: 0000 | I643: 0000 | J643: 07/11/2006 | K643: 00/00/0000
A644: 9901 | B644: STATEWIDE GEN ADM EXP (PR) | C644: 0808 | D644: GENERAL GOVERNMENT | F644: 0000 | G644: 0000 | H644: 0000 | I644: 0000 | J644: 07/11/2006 | K644: 00/00/0000
A645: 9909 | B645: HLTH INS PORTABLTY ACCTABLTY | C645: 0815 | D645: HEALTH AND HUMAN SERVICES | F645: 0000 | G645: 0000 | H645: 0000 | I645: 0000 | J645: 10/28/2016 | K645: 00/00/0000
A646: 9910 | B646: GEN FD CREDITS FROM FED FUNDS | C646: 0808 | D646: GENERAL GOVERNMENT | F646: 0000 | G646: 0000 | H646: 0000 | I646: 0000 | J646: 07/11/2006 | K646: 00/00/0000
...

Sheet LS-Fund 0001 Journal Entries
A1: Lessee-Type Contracts Fund-by-Fund Journal Entries Form (to be submitted to the SCO annually—one form per fund)
A2: Manually complete every yellow field in this worksheet—there are no automatically calculated data-entry cells in this worksheet.
A3: Fiscal Year: | F3: 2023–2024
A4: Organization Name: | F4: Department of Water Resources
A5: Organization Code (4-Digits): | F5: 3860
A6: Fund Number (4-Digits): | F6: 1
A7: Fund Classification: | F7: Governmental
A8: Fund Type: | F8: Governmental Fund
A9: Functional Expense: | F9: =IFERROR(IF(F7="Proprietary","Proprietary Fund",VLOOKUP(F5,qryIndex02a!$A$2:$K$654,4,FALSE)),"Unidentified") -> RESOURCES
A12: Establish Beginning Balances (existing leases only)
A13: Entry #
A14: 0 | B14: Roll forward prior year right-to-use leases to record opening balances. | M14: Combined Lessee Templates | P14: From SCO BB List | S14: Difference
A15: *Rpt 18 | B15: Dr: Acct 0476 - RIGHT-TO-USE LEASED LAND - AMORTIZABLE | J15: =M15 -> 0 | S15: =P15-M15 -> 0
A16: *Rpt 18 | B16: Dr: Acct 0478 - RIGHT-TO-USE LEASED EQUIPMENT - AMORTIZABLE | J16: =M16 -> 0 | S16: =P16-M16 -> 0
A17: *Rpt 18 | B17: Dr: Acct 0477 - RIGHT-TO-USE LEASED BUILDINGS - AMORTIZABLE | J17: =M17 -> 17257410 | M17: 17257410 | P17: 15686432 | S17: =P17-M17 -> -1570978
B18: Dr: Acct 0950 - BEGINNING FUND BALANCE | J18: =P18 -> 335074 | M18: 384939 | P18: =IF(SUM($Q$20:$Q$23)>SUM($P$15:$P$17),SUM($Q$20:$Q$23)-SUM($P$15:$P$17),0) -> 335074 | S18: =P18-M18 -> -49865
B19: Dr: Acct 0952 - BEGINNING FUND ADJUSTMENT/PRIOR PERIOD ADJUSTMENT | J19: =IF(SUM($K$20:$K$24)>SUM($J$15:$J$18),SUM($K$20:$K$24)-SUM($J$15:$J$18),0) -> 33564 | M19: 0 | S19: =P19-M19 -> 0
C20: Cr: Acct 0485 - ACCUMULATED AMORTIZATION - RIGHT-TO-USE LEASED LAND | K20: =N20 -> 0 | S20: =P20-M20 -> 0
C21: Cr: Acct 0479 - ACCUMULATED AMORTIZATION - RIGHT-TO-USE LEASED EQUIPMENT | K21: =N21 -> 0 | S21: =Q21-N21 -> 0
C22: Cr: Acct 0486 - ACCUMULATED AMORTIZATION - RIGHT-TO-USE LEASED BUILDINGS | K22: =N22 -> 4886519 | N22: 4886519 | Q22: 4441687 | S22: =Q22-N22 -> -444832
A23: **LS LL/CF | C23: Cr: Acct 0691 - RIGHT-TO-USE LEASE LIABILITY | K23: =N23 -> 12739529 | N23: 12739529 | Q23: 11579819 | S23: =Q23-N23 -> -1159710
C24: Cr: Acct 0950 - BEGINNING FUND BALANCE | K24: =Q24 -> 0 | N24: 16308 | Q24: =IF(SUM($Q$20:$Q$23)<SUM($P$15:$P$17),-SUM($Q$20:$Q$23)+SUM($P$15:$P$17),0) -> 0 | S24: =Q24-N24 -> -16308
C25: Cr: Acct 0952 - BEGINNING FUND ADJUSTMENT/PRIOR PERIOD ADJUSTMENT | K25: =IF(SUM($K$20:$K$24)<SUM($J$15:$J$18),-SUM($K$20:$K$24)+SUM($J$15:$J$18),0) -> 0 | N25: 0 | S25: =Q25-N25 -> 0
J26: =SUM(J15:J25) -> 17626048 | K26: =SUM(K15:K25) -> 17626048 | L26: =IF(J26=K26,"<- Debits and Credits equal each other.","<- Debits and Credits do not equal each other.") -> <- Debits and Credits equal each other.
B27: * THESE ASSET AMOUNTS SHOULD BE REPORTED AS BEGINNING BALANCES ON REPORT 18.
B28: ** This amount should be included in the beginning balance column on the LS-Lease Liability and LS-Check Figures Tabs.
A31: Record New Leases (new leases only)
A32: 1 | B32: Record lease contract commencement (fund-based entries only)
B33: Dr: Acct 0842 - CAPITAL OUTLAY | J33: 3997116
C34: Cr: Acct 0789 - LEASE AND OTHER FINANCING PROCEEDS | K34: 3997116
C35: =IF($F$7="Proprietary","Cr: Acct 0870 - SERVICES & CHARGES (MG ADJ)",VLOOKUP($F$9,'Drop Down Menus'!$F$2:$G$10,2,FALSE)) -> Cr: Acct 0820 - NAT RES & ENVIRON (GAAP ADJ)
J36: =SUM(J33:J35) -> 3997116 | K36: =SUM(K33:K35) -> 3997116 | L36: =IF(J36=K36,"<- Debits and Credits equal each other.","<- Debits and Credits do not equal each other.") -> <- Debits and Credits equal each other.
A38: 2 | B38: Record leased assets.
A39: *Rpt 18 | B39: Dr: Acct 0476 - RIGHT-TO-USE LEASED LAND - AMORTIZABLE
A40: *Rpt 18 | B40: Dr: Acct 0478 - RIGHT-TO-USE LEASED EQUIPMENT - AMORTIZABLE
A41: *Rpt 18 | B41: Dr: Acct 0477 - RIGHT-TO-USE LEASED BUILDINGS - AMORTIZABLE | J41: 3997116
C42: Cr: Acct 0842 - CAPITAL OUTLAY | K42: 3997116
B43: * THESE AMOUNTS SHOULD BE INCLUDED AS "ADDITIONS" ON REPORT 18. | J43: =SUM(J39:J42) -> 3997116 | K43: =SUM(K39:K42) -> 3997116 | L43: =IF(J43=K43,"<- Debits and Credits equal each other.","<- Debits and Credits do not equal each other.") -> <- Debits and Credits equal each other.
A46: 3 | B46: Replace proceeds from leases with right-to-use lease liability.
B47: Dr: Acct 0789 - LEASE AND OTHER FINANCING PROCEEDS | J47: 3997116
A48: **LS LL/CF | C48: Cr: Acct 0691 - RIGHT-TO-USE LEASE LIABILITY | K48: 3997116
J49: =SUM(J47:J48) -> 3997116 | K49: =SUM(K47:K48) -> 3997116 | L49: =IF(J49=K49,"<- Debits and Credits equal each other.","<- Debits and Credits do not equal each other.") -> <- Debits and Credits equal each other.
B50: ** This amount should be included in the additions column on the LS-Lease Liability and LS-Check Figures Tabs.
A53: Record Annual Activity (all leases)
A54: 4 | B54: Record amortization of the leased assets for the year.
B55: Dr: Acct 0875 - DEPRECIATION/AMORTIZATION | J55: 2616779
C56: Cr: Acct 0485 - ACCUMULATED AMORTIZATION - RIGHT-TO-USE LEASED LAND
C57: Cr: Acct 0479 - ACCUMULATED AMORTIZATION - RIGHT-TO-USE LEASED EQUIPMENT
C58: Cr: Acct 0486 - ACCUMULATED AMORTIZATION - RIGHT-TO-USE LEASED BUILDINGS | K58: 2616779
J59: =SUM(J55:J58) -> 2616779 | K59: =SUM(K55:K58) -> 2616779 | L59: =IF(J59=K59,"<- Debits and Credits equal each other.","<- Debits and Credits do not equal each other.") -> <- Debits and Credits equal each other.
A61: 5 | B61: Reclassify rents and leases exp. to lease contract principal and interest exp.
B62: Dr: Acct 0848 - DEBT SERVICE - PRINCIPAL LEASES | J62: 2379010
B63: =IF(F7="Governmental","Dr: Acct 0851 - DEBT SERVICE - INTEREST LEASES","Dr: Acct 0894 - INTEREST EXPENSE AND FISCAL CHARGES") -> Dr: Acct 0851 - DEBT SERVICE - INTEREST LEASES | J63: 292371
C64: =IF($F$7="Proprietary","Cr: Acct 0870 - SERVICES & CHARGES (MG ADJ)",VLOOKUP($F$9,'Drop Down Menus'!$F$2:$G$10,2,FALSE)) -> Cr: Acct 0820 - NAT RES & ENVIRON (GAAP ADJ) | K64: 2671381
J65: =SUM(J62:J64) -> 2671381 | K65: =SUM(K62:K64) -> 2671381 | L65: =IF(J65=K65,"<- Debits and Credits equal each other.","<- Debits and Credits do not equal each other.") -> <- Debits and Credits equal each other.
A67: 6 | B67: Reduce lease contracts liability for total current year principal payments.
A68: **LS LL/CF | B68: Dr: Acct 0691 - RIGHT-TO-USE LEASE LIABILITY | J68: 2379010
C69: Cr: Acct 0848 - DEBT SERVICE - PRINCIPAL LEASES | K69: 2379010
J70: =SUM(J68:J69) -> 2379010 | K70: =SUM(K68:K69) -> 2379010 | L70: =IF(J70=K70,"<- Debits and Credits equal each other.","<- Debits and Credits do not equal each other.") -> <- Debits and Credits equal each other.
B71: ** This amount should be included in the deductions column on the LS-Lease Liability and LS-Check Figures Tabs.
A74: 7 | B74: Reclassify the principal amount due in the next FY to the current liability.
A75: **LS LL/CF | B75: Dr: Acct 0691 - RIGHT-TO-USE LEASE LIABILITY | J75: 2435021
C76: Cr: Acct 0649 - RIGHT-TO-USE LEASE LIABILITY (CURRENT PORTION LT) | K76: 2435021
B77: NOTE: This is an annual accrual. It is to be reversed at the start of the next fiscal year. SCO combines the current and non current amount in Entry #0 to reestablish the beginning balances. No action required. | J77: =SUM(J75:J76) -> 2435021 | K77: =SUM(K75:K76) -> 2435021 | L77: =IF(J77=K77,"<- Debits and Credits equal each other.","<- Debits and Credits do not equal each other.") -> <- Debits and Credits equal each other.
B80: ** This amount should be included in the due in one year column on the LS-Lease Liability and LS-Check Figures Tabs.
A83: Remove Lease Asset at the End of the Lease Term (only at the end of the lease term)
A84: 8 | B84: Record entry to write off the lease asset and accumulated amortization at the end of the lease term.
B85: Dr: Acct 0485 - ACCUMULATED AMORTIZATION - RIGHT-TO-USE LEASED LAND
B86: Dr: Acct 0479 - ACCUMULATED AMORTIZATION - RIGHT-TO-USE LEASED EQUIPMENT
B87: Dr: Acct 0486 - ACCUMULATED AMORTIZATION - RIGHT-TO-USE LEASED BUILDINGS | J87: 955675
A88: *Rpt 18 | C88: Cr: Acct 0476 - RIGHT-TO-USE LEASED LAND - AMORTIZABLE
A89: *Rpt 18 | C89: Cr: Acct 0478 - RIGHT-TO-USE LEASED EQUIPMENT - AMORTIZABLE
A90: *Rpt 18 | C90: Cr: Acct 0477 - RIGHT-TO-USE LEASED BUILDINGS - AMORTIZABLE | K90: 955675
B91: * THESE AMOUNTS SHOULD BE INCLUDED AS "DEDUCTIONS" ON REPORT 18. | J91: =SUM(J85:J90) -> 955675 | K91: =SUM(K85:K90) -> 955675 | L91: =IF(J91=K91,"<- Debits and Credits equal each other.","<- Debits and Credits do not equal each other.") -> <- Debits and Credits equal each other.
A94: Lease Remeasurement and Modifications (only if a significant modification occurred during the fiscal year)
A95: 9 | B95: Record early termination or lease modifications to decrease in the RTU leased asset.
A96: **LS LL/CF | B96: Dr: Acct 0691 - RIGHT-TO-USE LEASE LIABILITY
B97: Dr: Acct 0485 - ACCUMULATED AMORTIZATION - RIGHT-TO-USE LEASED LAND
B98: Dr: Acct 0479 - ACCUMULATED AMORTIZATION - RIGHT-TO-USE LEASED EQUIPMENT
B99: Dr: Acct 0486 - ACCUMULATED AMORTIZATION - RIGHT-TO-USE LEASED BUILDINGS
B100: =IF($F$7="Proprietary","Dr: Acct 0870 - SERVICES & CHARGES (MG ADJ)",VLOOKUP($F$9,'Drop Down Menus'!$F$2:$H$10,3,FALSE)) -> Dr: Acct 0820 - NAT RES & ENVIRON (GAAP ADJ)
A101: *Rpt 18 | C101: Cr: Acct 0476 - RIGHT-TO-USE LEASED LAND - AMORTIZABLE
A102: *Rpt 18 | C102: Cr: Acct 0478 - RIGHT-TO-USE LEASED EQUIPMENT - AMORTIZABLE
A103: *Rpt 18 | C103: Cr: Acct 0477 - RIGHT-TO-USE LEASED BUILDINGS - AMORTIZABLE
C104: =IF($F$7="Proprietary","Dr: Acct 0870 - SERVICES & CHARGES (MG ADJ)",VLOOKUP($F$9,'Drop Down Menus'!$F$2:$G$10,2,FALSE)) -> Cr: Acct 0820 - NAT RES & ENVIRON (GAAP ADJ)
B105: * THESE AMOUNTS SHOULD BE INCLUDED AS "DEDUCTIONS" ON REPORT 18. | J105: =SUM(J96:J104) -> 0 | K105: =SUM(K96:K104) -> 0 | L105: =IF(J105=K105,"<- Debits and Credits equal each other.","<- Debits and Credits do not equal each other.") -> <- Debits and Credits equal each other.
B106: ** This amount should be included in the deductions column on the LS-Lease Liability and LS-Check Figures Tabs.
A109: 10 | B109: Record lease modifications to increase in the RTU leased asset.
A110: *Rpt 18 | B110: Dr: Acct 0476 - RIGHT-TO-USE LEASED LAND - AMORTIZABLE
A111: *Rpt 18 | B111: Dr: Acct 0478 - RIGHT-TO-USE LEASED EQUIPMENT - AMORTIZABLE
A112: *Rpt 18 | B112: Dr: Acct 0477 - RIGHT-TO-USE LEASED BUILDINGS - AMORTIZABLE
A113: **LS LL/CF | C113: Cr: Acct 0691 - RIGHT-TO-USE LEASE LIABILITY
B114: * THESE AMOUNTS SHOULD BE INCLUDED AS "ADDITIONS" ON REPORT 18. | J114: =SUM(J110:J113) -> 0 | K114: =SUM(K110:K113) -> 0 | L114: =IF(J114=K114,"<- Debits and Credits equal each other.","<- Debits and Credits do not equal each other.") -> <- Debits and Credits equal each other.
B115: ** This amount should be included in the additions column on the LS-Lease Liability and LS-Check Figures Tabs.
D120: Informational - Ending Balances of Assets and Liabilities
K121: Debit (Credit)
D122: Acct 0476 - RIGHT-TO-USE LEASED LAND - AMORTIZABLE | K122: =J15+J39-K88-K101+J110 -> 0
D123: Acct 0478 - RIGHT-TO-USE LEASED EQUIPMENT - AMORTIZABLE | K123: =J16+J40-K89-K102+J111 -> 0
D124: Acct 0477 - RIGHT-TO-USE LEASED BUILDINGS - AMORTIZABLE | K124: =J17+J41-K90-K103+J112 -> 20298851
D125: Acct 0485 - ACCUMULATED AMORTIZATION - RIGHT-TO-USE LEASED LAND | K125: =-K20-K56+J85+J97 -> 0
...

Sheet LS-Fund 0140 Journal Entries
A1: Lessee-Type Contracts Fund-by-Fund Journal Entries Form (to be submitted to the SCO annually—one form per fund)
A2: Manually complete every yellow field in this worksheet—there are no automatically calculated data-entry cells in this worksheet.
A3: Fiscal Year: | F3: 2023–2024
A4: Organization Name: | F4: Department of Water Resources
A5: Organization Code (4-Digits): | F5: 3860
A6: Fund Number (4-Digits): | F6: 140
A7: Fund Classification: | F7: Governmental
A8: Fund Type: | F8: Governmental Fund
A9: Functional Expense: | F9: =IFERROR(IF(F7="Proprietary","Proprietary Fund",VLOOKUP(F5,qryIndex02a!$A$2:$K$654,4,FALSE)),"Unidentified") -> RESOURCES
A12: Establish Beginning Balances (existing leases only)
A13: Entry #
A14: 0 | B14: Roll forward prior year right-to-use leases to record opening balances. | M14: Combined Lessee Templates | P14: From SCO BB List | S14: Difference
A15: *Rpt 18 | B15: Dr: Acct 0476 - RIGHT-TO-USE LEASED LAND - AMORTIZABLE | J15: =M15 -> 0 | S15: =P15-M15 -> 0
A16: *Rpt 18 | B16: Dr: Acct 0478 - RIGHT-TO-USE LEASED EQUIPMENT - AMORTIZABLE | J16: =M16 -> 0 | S16: =P16-M16 -> 0
A17: *Rpt 18 | B17: Dr: Acct 0477 - RIGHT-TO-USE LEASED BUILDINGS - AMORTIZABLE | J17: =M17 -> 178425 | M17: 178425 | P17: 214084 | S17: =P17-M17 -> 35659
B18: Dr: Acct 0950 - BEGINNING FUND BALANCE | J18: =P18 -> 4572 | M18: 3980 | P18: =IF(SUM($Q$20:$Q$23)>SUM($P$15:$P$17),SUM($Q$20:$Q$23)-SUM($P$15:$P$17),0) -> 4572 | S18: =P18-M18 -> 592
B19: Dr: Acct 0952 - BEGINNING FUND ADJUSTMENT/PRIOR PERIOD ADJUSTMENT | J19: =IF(SUM($K$20:$K$24)>SUM($J$15:$J$18),SUM($K$20:$K$24)-SUM($J$15:$J$18),0) -> 0 | M19: 0 | S19: =P19-M19 -> 0
C20: Cr: Acct 0485 - ACCUMULATED AMORTIZATION - RIGHT-TO-USE LEASED LAND | K20: =N20 -> 0 | S20: =P20-M20 -> 0
C21: Cr: Acct 0479 - ACCUMULATED AMORTIZATION - RIGHT-TO-USE LEASED EQUIPMENT | K21: =N21 -> 0 | S21: =Q21-N21 -> 0
C22: Cr: Acct 0486 - ACCUMULATED AMORTIZATION - RIGHT-TO-USE LEASED BUILDINGS | K22: =N22 -> 50522 | N22: 50522 | Q22: 60619 | S22: =Q22-N22 -> 10097
A23: **LS LL/CF | C23: Cr: Acct 0691 - RIGHT-TO-USE LEASE LIABILITY | K23: =N23 -> 131714 | N23: 131714 | Q23: 158037 | S23: =Q23-N23 -> 26323
C24: Cr: Acct 0950 - BEGINNING FUND BALANCE | K24: =Q24 -> 0 | N24: 169 | Q24: =IF(SUM($Q$20:$Q$23)<SUM($P$15:$P$17),-SUM($Q$20:$Q$23)+SUM($P$15:$P$17),0) -> 0 | S24: =Q24-N24 -> -169
C25: Cr: Acct 0952 - BEGINNING FUND ADJUSTMENT/PRIOR PERIOD ADJUSTMENT | K25: =IF(SUM($K$20:$K$24)<SUM($J$15:$J$18),-SUM($K$20:$K$24)+SUM($J$15:$J$18),0) -> 761 | N25: 0 | S25: =Q25-N25 -> 0
J26: =SUM(J15:J25) -> 182997 | K26: =SUM(K15:K25) -> 182997 | L26: =IF(J26=K26,"<- Debits and Credits equal each other.","<- Debits and Credits do not equal each other.") -> <- Debits and Credits equal each other.
B27: * THESE ASSET AMOUNTS SHOULD BE REPORTED AS BEGINNING BALANCES ON REPORT 18.
B28: ** This amount should be included in the beginning balance column on the LS-Lease Liability and LS-Check Figures Tabs.
A31: Record New Leases (new leases only)
A32: 1 | B32: Record lease contract commencement (fund-based entries only)
B33: Dr: Acct 0842 - CAPITAL OUTLAY | J33: 41326
C34: Cr: Acct 0789 - LEASE AND OTHER FINANCING PROCEEDS | K34: 41326
C35: =IF($F$7="Proprietary","Cr: Acct 0870 - SERVICES & CHARGES (MG ADJ)",VLOOKUP($F$9,'Drop Down Menus'!$F$2:$G$10,2,FALSE)) -> Cr: Acct 0820 - NAT RES & ENVIRON (GAAP ADJ)
J36: =SUM(J33:J35) -> 41326 | K36: =SUM(K33:K35) -> 41326 | L36: =IF(J36=K36,"<- Debits and Credits equal each other.","<- Debits and Credits do not equal each other.") -> <- Debits and Credits equal each other.
A38: 2 | B38: Record leased assets.
A39: *Rpt 18 | B39: Dr: Acct 0476 - RIGHT-TO-USE LEASED LAND - AMORTIZABLE
A40: *Rpt 18 | B40: Dr: Acct 0478 - RIGHT-TO-USE LEASED EQUIPMENT - AMORTIZABLE
A41: *Rpt 18 | B41: Dr: Acct 0477 - RIGHT-TO-USE LEASED BUILDINGS - AMORTIZABLE | J41: 41326
C42: Cr: Acct 0842 - CAPITAL OUTLAY | K42: 41326
B43: * THESE AMOUNTS SHOULD BE INCLUDED AS "ADDITIONS" ON REPORT 18. | J43: =SUM(J39:J42) -> 41326 | K43: =SUM(K39:K42) -> 41326 | L43: =IF(J43=K43,"<- Debits and Credits equal each other.","<- Debits and Credits do not equal each other.") -> <- Debits and Credits equal each other.
A46: 3 | B46: Replace proceeds from leases with right-to-use lease liability.
B47: Dr: Acct 0789 - LEASE AND OTHER FINANCING PROCEEDS | J47: 41326
A48: **LS LL/CF | C48: Cr: Acct 0691 - RIGHT-TO-USE LEASE LIABILITY | K48: 41326
J49: =SUM(J47:J48) -> 41326 | K49: =SUM(K47:K48) -> 41326 | L49: =IF(J49=K49,"<- Debits and Credits equal each other.","<- Debits and Credits do not equal each other.") -> <- Debits and Credits equal each other.
B50: ** This amount should be included in the additions column on the LS-Lease Liability and LS-Check Figures Tabs.
A53: Record Annual Activity (all leases)
A54: 4 | B54: Record amortization of the leased assets for the year.
B55: Dr: Acct 0875 - DEPRECIATION/AMORTIZATION | J55: 27055
C56: Cr: Acct 0485 - ACCUMULATED AMORTIZATION - RIGHT-TO-USE LEASED LAND
C57: Cr: Acct 0479 - ACCUMULATED AMORTIZATION - RIGHT-TO-USE LEASED EQUIPMENT
C58: Cr: Acct 0486 - ACCUMULATED AMORTIZATION - RIGHT-TO-USE LEASED BUILDINGS | K58: 27055
J59: =SUM(J55:J58) -> 27055 | K59: =SUM(K55:K58) -> 27055 | L59: =IF(J59=K59,"<- Debits and Credits equal each other.","<- Debits and Credits do not equal each other.") -> <- Debits and Credits equal each other.
A61: 5 | B61: Reclassify rents and leases exp. to lease contract principal and interest exp.
B62: Dr: Acct 0848 - DEBT SERVICE - PRINCIPAL LEASES | J62: 24596.65
B63: =IF(F7="Governmental","Dr: Acct 0851 - DEBT SERVICE - INTEREST LEASES","Dr: Acct 0894 - INTEREST EXPENSE AND FISCAL CHARGES") -> Dr: Acct 0851 - DEBT SERVICE - INTEREST LEASES | J63: 3022.83
C64: =IF($F$7="Proprietary","Cr: Acct 0870 - SERVICES & CHARGES (MG ADJ)",VLOOKUP($F$9,'Drop Down Menus'!$F$2:$G$10,2,FALSE)) -> Cr: Acct 0820 - NAT RES & ENVIRON (GAAP ADJ) | K64: 27619
J65: =SUM(J62:J64) -> 27619.48 | K65: =SUM(K62:K64) -> 27619 | L65: =IF(J65=K65,"<- Debits and Credits equal each other.","<- Debits and Credits do not equal each other.") -> <- Debits and Credits do not equal each other.
A67: 6 | B67: Reduce lease contracts liability for total current year principal payments.
A68: **LS LL/CF | B68: Dr: Acct 0691 - RIGHT-TO-USE LEASE LIABILITY | J68: 24597
C69: Cr: Acct 0848 - DEBT SERVICE - PRINCIPAL LEASES | K69: 24597
J70: =SUM(J68:J69) -> 24597 | K70: =SUM(K68:K69) -> 24597 | L70: =IF(J70=K70,"<- Debits and Credits equal each other.","<- Debits and Credits do not equal each other.") -> <- Debits and Credits equal each other.
B71: ** This amount should be included in the deductions column on the LS-Lease Liability and LS-Check Figures Tabs.
A74: 7 | B74: Reclassify the principal amount due in the next FY to the current liability.
A75: **LS LL/CF | B75: Dr: Acct 0691 - RIGHT-TO-USE LEASE LIABILITY | J75: 25176
C76: Cr: Acct 0649 - RIGHT-TO-USE LEASE LIABILITY (CURRENT PORTION LT) | K76: 25176
B77: NOTE: This is an annual accrual. It is to be reversed at the start of the next fiscal year. SCO combines the current and non current amount in Entry #0 to reestablish the beginning balances. No action required. | J77: =SUM(J75:J76) -> 25176 | K77: =SUM(K75:K76) -> 25176 | L77: =IF(J77=K77,"<- Debits and Credits equal each other.","<- Debits and Credits do not equal each other.") -> <- Debits and Credits equal each other.
B80: ** This amount should be included in the due in one year column on the LS-Lease Liability and LS-Check Figures Tabs.
A83: Remove Lease Asset at the End of the Lease Term (only at the end of the lease term)
A84: 8 | B84: Record entry to write off the lease asset and accumulated amortization at the end of the lease term.
B85: Dr: Acct 0485 - ACCUMULATED AMORTIZATION - RIGHT-TO-USE LEASED LAND
B86: Dr: Acct 0479 - ACCUMULATED AMORTIZATION - RIGHT-TO-USE LEASED EQUIPMENT
B87: Dr: Acct 0486 - ACCUMULATED AMORTIZATION - RIGHT-TO-USE LEASED BUILDINGS | J87: 9881
A88: *Rpt 18 | C88: Cr: Acct 0476 - RIGHT-TO-USE LEASED LAND - AMORTIZABLE
A89: *Rpt 18 | C89: Cr: Acct 0478 - RIGHT-TO-USE LEASED EQUIPMENT - AMORTIZABLE
A90: *Rpt 18 | C90: Cr: Acct 0477 - RIGHT-TO-USE LEASED BUILDINGS - AMORTIZABLE | K90: 9881
B91: * THESE AMOUNTS SHOULD BE INCLUDED AS "DEDUCTIONS" ON REPORT 18. | J91: =SUM(J85:J90) -> 9881 | K91: =SUM(K85:K90) -> 9881 | L91: =IF(J91=K91,"<- Debits and Credits equal each other.","<- Debits and Credits do not equal each other.") -> <- Debits and Credits equal each other.
A94: Lease Remeasurement and Modifications (only if a significant modification occurred during the fiscal year)
A95: 9 | B95: Record early termination or lease modifications to decrease in the RTU leased asset.
A96: **LS LL/CF | B96: Dr: Acct 0691 - RIGHT-TO-USE LEASE LIABILITY
B97: Dr: Acct 0485 - ACCUMULATED AMORTIZATION - RIGHT-TO-USE LEASED LAND
B98: Dr: Acct 0479 - ACCUMULATED AMORTIZATION - RIGHT-TO-USE LEASED EQUIPMENT
B99: Dr: Acct 0486 - ACCUMULATED AMORTIZATION - RIGHT-TO-USE LEASED BUILDINGS
B100: =IF($F$7="Proprietary","Dr: Acct 0870 - SERVICES & CHARGES (MG ADJ)",VLOOKUP($F$9,'Drop Down Menus'!$F$2:$H$10,3,FALSE)) -> Dr: Acct 0820 - NAT RES & ENVIRON (GAAP ADJ)
A101: *Rpt 18 | C101: Cr: Acct 0476 - RIGHT-TO-USE LEASED LAND - AMORTIZABLE
A102: *Rpt 18 | C102: Cr: Acct 0478 - RIGHT-TO-USE LEASED EQUIPMENT - AMORTIZABLE
A103: *Rpt 18 | C103: Cr: Acct 0477 - RIGHT-TO-USE LEASED BUILDINGS - AMORTIZABLE
C104: =IF($F$7="Proprietary","Dr: Acct 0870 - SERVICES & CHARGES (MG ADJ)",VLOOKUP($F$9,'Drop Down Menus'!$F$2:$G$10,2,FALSE)) -> Cr: Acct 0820 - NAT RES & ENVIRON (GAAP ADJ)
B105: * THESE AMOUNTS SHOULD BE INCLUDED AS "DEDUCTIONS" ON REPORT 18. | J105: =SUM(J96:J104) -> 0 | K105: =SUM(K96:K104) -> 0 | L105: =IF(J105=K105,"<- Debits and Credits equal each other.","<- Debits and Credits do not equal each other.") -> <- Debits and Credits equal each other.
B106: ** This amount should be included in the deductions column on the LS-Lease Liability and LS-Check Figures Tabs.
A109: 10 | B109: Record lease modifications to increase in the RTU leased asset.
A110: *Rpt 18 | B110: Dr: Acct 0476 - RIGHT-TO-USE LEASED LAND - AMORTIZABLE
A111: *Rpt 18 | B111: Dr: Acct 0478 - RIGHT-TO-USE LEASED EQUIPMENT - AMORTIZABLE
A112: *Rpt 18 | B112: Dr: Acct 0477 - RIGHT-TO-USE LEASED BUILDINGS - AMORTIZABLE
A113: **LS LL/CF | C113: Cr: Acct 0691 - RIGHT-TO-USE LEASE LIABILITY
B114: * THESE AMOUNTS SHOULD BE INCLUDED AS "ADDITIONS" ON REPORT 18. | J114: =SUM(J110:J113) -> 0 | K114: =SUM(K110:K113) -> 0 | L114: =IF(J114=K114,"<- Debits and Credits equal each other.","<- Debits and Credits do not equal each other.") -> <- Debits and Credits equal each other.
B115: ** This amount should be included in the additions column on the LS-Lease Liability and LS-Check Figures Tabs.
D120: Informational - Ending Balances of Assets and Liabilities
K121: Debit (Credit)
D122: Acct 0476 - RIGHT-TO-USE LEASED LAND - AMORTIZABLE | K122: =J15+J39-K88-K101+J110 -> 0
D123: Acct 0478 - RIGHT-TO-USE LEASED EQUIPMENT - AMORTIZABLE | K123: =J16+J40-K89-K102+J111 -> 0
D124: Acct 0477 - RIGHT-TO-USE LEASED BUILDINGS - AMORTIZABLE | K124: =J17+J41-K90-K103+J112 -> 209870
D125: Acct 0485 - ACCUMULATED AMORTIZATION - RIGHT-TO-USE LEASED LAND | K125: =-K20-K56+J85+J97 -> 0
...

Sheet LS-Fund 0465 Journal Entries
A1: Lessee-Type Contracts Fund-by-Fund Journal Entries Form (to be submitted to the SCO annually—one form per fund)
A2: Manually complete every yellow field in this worksheet—there are no automatically calculated data-entry cells in this worksheet.
A3: Fiscal Year: | F3: 2023–2024
A4: Organization Name: | F4: Department of Water Resources
A5: Organization Code (4-Digits): | F5: 3860
A6: Fund Number (4-Digits): | F6: 465
A7: Fund Classification: | F7: Governmental
A8: Fund Type: | F8: Governmental Fund
A9: Functional Expense: | F9: =IFERROR(IF(F7="Proprietary","Proprietary Fund",VLOOKUP(F5,qryIndex02a!$A$2:$K$654,4,FALSE)),"Unidentified") -> RESOURCES
A12: Establish Beginning Balances (existing leases only)
A13: Entry #
A14: 0 | B14: Roll forward prior year right-to-use leases to record opening balances. | M14: Combined Lessee Templates | P14: From SCO BB List | S14: Difference
A15: *Rpt 18 | B15: Dr: Acct 0476 - RIGHT-TO-USE LEASED LAND - AMORTIZABLE | J15: =M15 -> 0 | S15: =P15-M15 -> 0
A16: *Rpt 18 | B16: Dr: Acct 0478 - RIGHT-TO-USE LEASED EQUIPMENT - AMORTIZABLE | J16: =M16 -> 0 | S16: =P16-M16 -> 0
A17: *Rpt 18 | B17: Dr: Acct 0477 - RIGHT-TO-USE LEASED BUILDINGS - AMORTIZABLE | J17: =M17 -> 337883 | M17: 337883 | P17: 408703 | S17: =P17-M17 -> 70820
B18: Dr: Acct 0950 - BEGINNING FUND BALANCE | J18: =P18 -> 8731 | M18: 7537 | P18: =IF(SUM($Q$20:$Q$23)>SUM($P$15:$P$17),SUM($Q$20:$Q$23)-SUM($P$15:$P$17),0) -> 8731 | S18: =P18-M18 -> 1194
B19: Dr: Acct 0952 - BEGINNING FUND ADJUSTMENT/PRIOR PERIOD ADJUSTMENT | J19: =IF(SUM($K$20:$K$24)>SUM($J$15:$J$18),SUM($K$20:$K$24)-SUM($J$15:$J$18),0) -> 0 | M19: 0 | S19: =P19-M19 -> 0
C20: Cr: Acct 0485 - ACCUMULATED AMORTIZATION - RIGHT-TO-USE LEASED LAND | K20: =N20 -> 0 | S20: =P20-M20 -> 0
C21: Cr: Acct 0479 - ACCUMULATED AMORTIZATION - RIGHT-TO-USE LEASED EQUIPMENT | K21: =N21 -> 0 | S21: =Q21-N21 -> 0
C22: Cr: Acct 0486 - ACCUMULATED AMORTIZATION - RIGHT-TO-USE LEASED BUILDINGS | K22: =N22 -> 95673 | N22: 95673 | Q22: 115727 | S22: =Q22-N22 -> 20054
A23: **LS LL/CF | C23: Cr: Acct 0691 - RIGHT-TO-USE LEASE LIABILITY | K23: =N23 -> 249427 | N23: 249427 | Q23: 301707 | S23: =Q23-N23 -> 52280
C24: Cr: Acct 0950 - BEGINNING FUND BALANCE | K24: =Q24 -> 0 | N24: 319 | Q24: =IF(SUM($Q$20:$Q$23)<SUM($P$15:$P$17),-SUM($Q$20:$Q$23)+SUM($P$15:$P$17),0) -> 0 | S24: =Q24-N24 -> -319
C25: Cr: Acct 0952 - BEGINNING FUND ADJUSTMENT/PRIOR PERIOD ADJUSTMENT | K25: =IF(SUM($K$20:$K$24)<SUM($J$15:$J$18),-SUM($K$20:$K$24)+SUM($J$15:$J$18),0) -> 1514 | N25: 0 | S25: =Q25-N25 -> 0
J26: =SUM(J15:J25) -> 346614 | K26: =SUM(K15:K25) -> 346614 | L26: =IF(J26=K26,"<- Debits and Credits equal each other.","<- Debits and Credits do not equal each other.") -> <- Debits and Credits equal each other.
B27: * THESE ASSET AMOUNTS SHOULD BE REPORTED AS BEGINNING BALANCES ON REPORT 18.
B28: ** This amount should be included in the beginning balance column on the LS-Lease Liability and LS-Check Figures Tabs.
A31: Record New Leases (new leases only)
A32: 1 | B32: Record lease contract commencement (fund-based entries only)
B33: Dr: Acct 0842 - CAPITAL OUTLAY | J33: 78260
C34: Cr: Acct 0789 - LEASE AND OTHER FINANCING PROCEEDS | K34: 78260
C35: =IF($F$7="Proprietary","Cr: Acct 0870 - SERVICES & CHARGES (MG ADJ)",VLOOKUP($F$9,'Drop Down Menus'!$F$2:$G$10,2,FALSE)) -> Cr: Acct 0820 - NAT RES & ENVIRON (GAAP ADJ)
J36: =SUM(J33:J35) -> 78260 | K36: =SUM(K33:K35) -> 78260 | L36: =IF(J36=K36,"<- Debits and Credits equal each other.","<- Debits and Credits do not equal each other.") -> <- Debits and Credits equal each other.
A38: 2 | B38: Record leased assets.
A39: *Rpt 18 | B39: Dr: Acct 0476 - RIGHT-TO-USE LEASED LAND - AMORTIZABLE
A40: *Rpt 18 | B40: Dr: Acct 0478 - RIGHT-TO-USE LEASED EQUIPMENT - AMORTIZABLE
A41: *Rpt 18 | B41: Dr: Acct 0477 - RIGHT-TO-USE LEASED BUILDINGS - AMORTIZABLE | J41: 78260
C42: Cr: Acct 0842 - CAPITAL OUTLAY | K42: 78260
B43: * THESE AMOUNTS SHOULD BE INCLUDED AS "ADDITIONS" ON REPORT 18. | J43: =SUM(J39:J42) -> 78260 | K43: =SUM(K39:K42) -> 78260 | L43: =IF(J43=K43,"<- Debits and Credits equal each other.","<- Debits and Credits do not equal each other.") -> <- Debits and Credits equal each other.
A46: 3 | B46: Replace proceeds from leases with right-to-use lease liability.
B47: Dr: Acct 0789 - LEASE AND OTHER FINANCING PROCEEDS | J47: 78260
A48: **LS LL/CF | C48: Cr: Acct 0691 - RIGHT-TO-USE LEASE LIABILITY | K48: 78260
J49: =SUM(J47:J48) -> 78260 | K49: =SUM(K47:K48) -> 78260 | L49: =IF(J49=K49,"<- Debits and Credits equal each other.","<- Debits and Credits do not equal each other.") -> <- Debits and Credits equal each other.
B50: ** This amount should be included in the additions column on the LS-Lease Liability and LS-Check Figures Tabs.
A53: Record Annual Activity (all leases)
A54: 4 | B54: Record amortization of the leased assets for the year.
B55: Dr: Acct 0875 - DEPRECIATION/AMORTIZATION | J55: 51234
C56: Cr: Acct 0485 - ACCUMULATED AMORTIZATION - RIGHT-TO-USE LEASED LAND
C57: Cr: Acct 0479 - ACCUMULATED AMORTIZATION - RIGHT-TO-USE LEASED EQUIPMENT
C58: Cr: Acct 0486 - ACCUMULATED AMORTIZATION - RIGHT-TO-USE LEASED BUILDINGS | K58: 51234
J59: =SUM(J55:J58) -> 51234 | K59: =SUM(K55:K58) -> 51234 | L59: =IF(J59=K59,"<- Debits and Credits equal each other.","<- Debits and Credits do not equal each other.") -> <- Debits and Credits equal each other.
A61: 5 | B61: Reclassify rents and leases exp. to lease contract principal and interest exp.
B62: Dr: Acct 0848 - DEBT SERVICE - PRINCIPAL LEASES | J62: 46578.69
B63: =IF(F7="Governmental","Dr: Acct 0851 - DEBT SERVICE - INTEREST LEASES","Dr: Acct 0894 - INTEREST EXPENSE AND FISCAL CHARGES") -> Dr: Acct 0851 - DEBT SERVICE - INTEREST LEASES | J63: 5724.33
C64: =IF($F$7="Proprietary","Cr: Acct 0870 - SERVICES & CHARGES (MG ADJ)",VLOOKUP($F$9,'Drop Down Menus'!$F$2:$G$10,2,FALSE)) -> Cr: Acct 0820 - NAT RES & ENVIRON (GAAP ADJ) | K64: 52303
J65: =SUM(J62:J64) -> 52303.02 | K65: =SUM(K62:K64) -> 52303 | L65: =IF(J65=K65,"<- Debits and Credits equal each other.","<- Debits and Credits do not equal each other.") -> <- Debits and Credits do not equal each other.
A67: 6 | B67: Reduce lease contracts liability for total current year principal payments.
A68: **LS LL/CF | B68: Dr: Acct 0691 - RIGHT-TO-USE LEASE LIABILITY | J68: 46579
C69: Cr: Acct 0848 - DEBT SERVICE - PRINCIPAL LEASES | K69: 46579
J70: =SUM(J68:J69) -> 46579 | K70: =SUM(K68:K69) -> 46579 | L70: =IF(J70=K70,"<- Debits and Credits equal each other.","<- Debits and Credits do not equal each other.") -> <- Debits and Credits equal each other.
B71: ** This amount should be included in the deductions column on the LS-Lease Liability and LS-Check Figures Tabs.
A74: 7 | B74: Reclassify the principal amount due in the next FY to the current liability.
A75: **LS LL/CF | B75: Dr: Acct 0691 - RIGHT-TO-USE LEASE LIABILITY | J75: 47675
C76: Cr: Acct 0649 - RIGHT-TO-USE LEASE LIABILITY (CURRENT PORTION LT) | K76: 47675
B77: NOTE: This is an annual accrual. It is to be reversed at the start of the next fiscal year. SCO combines the current and non current amount in Entry #0 to reestablish the beginning balances. No action required. | J77: =SUM(J75:J76) -> 47675 | K77: =SUM(K75:K76) -> 47675 | L77: =IF(J77=K77,"<- Debits and Credits equal each other.","<- Debits and Credits do not equal each other.") -> <- Debits and Credits equal each other.
B80: ** This amount should be included in the due in one year column on the LS-Lease Liability and LS-Check Figures Tabs.
A83: Remove Lease Asset at the End of the Lease Term (only at the end of the lease term)
A84: 8 | B84: Record entry to write off the lease asset and accumulated amortization at the end of the lease term.
B85: Dr: Acct 0485 - ACCUMULATED AMORTIZATION - RIGHT-TO-USE LEASED LAND
B86: Dr: Acct 0479 - ACCUMULATED AMORTIZATION - RIGHT-TO-USE LEASED EQUIPMENT
B87: Dr: Acct 0486 - ACCUMULATED AMORTIZATION - RIGHT-TO-USE LEASED BUILDINGS | J87: 18711
A88: *Rpt 18 | C88: Cr: Acct 0476 - RIGHT-TO-USE LEASED LAND - AMORTIZABLE
A89: *Rpt 18 | C89: Cr: Acct 0478 - RIGHT-TO-USE LEASED EQUIPMENT - AMORTIZABLE
A90: *Rpt 18 | C90: Cr: Acct 0477 - RIGHT-TO-USE LEASED BUILDINGS - AMORTIZABLE | K90: 18711
B91: * THESE AMOUNTS SHOULD BE INCLUDED AS "DEDUCTIONS" ON REPORT 18. | J91: =SUM(J85:J90) -> 18711 | K91: =SUM(K85:K90) -> 18711 | L91: =IF(J91=K91,"<- Debits and Credits equal each other.","<- Debits and Credits do not equal each other.") -> <- Debits and Credits equal each other.
A94: Lease Remeasurement and Modifications (only if a significant modification occurred during the fiscal year)
A95: 9 | B95: Record early termination or lease modifications to decrease in the RTU leased asset.
A96: **LS LL/CF | B96: Dr: Acct 0691 - RIGHT-TO-USE LEASE LIABILITY
B97: Dr: Acct 0485 - ACCUMULATED AMORTIZATION - RIGHT-TO-USE LEASED LAND
B98: Dr: Acct 0479 - ACCUMULATED AMORTIZATION - RIGHT-TO-USE LEASED EQUIPMENT
B99: Dr: Acct 0486 - ACCUMULATED AMORTIZATION - RIGHT-TO-USE LEASED BUILDINGS
B100: =IF($F$7="Proprietary","Dr: Acct 0870 - SERVICES & CHARGES (MG ADJ)",VLOOKUP($F$9,'Drop Down Menus'!$F$2:$H$10,3,FALSE)) -> Dr: Acct 0820 - NAT RES & ENVIRON (GAAP ADJ)
A101: *Rpt 18 | C101: Cr: Acct 0476 - RIGHT-TO-USE LEASED LAND - AMORTIZABLE
A102: *Rpt 18 | C102: Cr: Acct 0478 - RIGHT-TO-USE LEASED EQUIPMENT - AMORTIZABLE
A103: *Rpt 18 | C103: Cr: Acct 0477 - RIGHT-TO-USE LEASED BUILDINGS - AMORTIZABLE
C104: =IF($F$7="Proprietary","Dr: Acct 0870 - SERVICES & CHARGES (MG ADJ)",VLOOKUP($F$9,'Drop Down Menus'!$F$2:$G$10,2,FALSE)) -> Cr: Acct 0820 - NAT RES & ENVIRON (GAAP ADJ)
B105: * THESE AMOUNTS SHOULD BE INCLUDED AS "DEDUCTIONS" ON REPORT 18. | J105: =SUM(J96:J104) -> 0 | K105: =SUM(K96:K104) -> 0 | L105: =IF(J105=K105,"<- Debits and Credits equal each other.","<- Debits and Credits do not equal each other.") -> <- Debits and Credits equal each other.
B106: ** This amount should be included in the deductions column on the LS-Lease Liability and LS-Check Figures Tabs.
A109: 10 | B109: Record lease modifications to increase in the RTU leased asset.
A110: *Rpt 18 | B110: Dr: Acct 0476 - RIGHT-TO-USE LEASED LAND - AMORTIZABLE
A111: *Rpt 18 | B111: Dr: Acct 0478 - RIGHT-TO-USE LEASED EQUIPMENT - AMORTIZABLE
A112: *Rpt 18 | B112: Dr: Acct 0477 - RIGHT-TO-USE LEASED BUILDINGS - AMORTIZABLE
A113: **LS LL/CF | C113: Cr: Acct 0691 - RIGHT-TO-USE LEASE LIABILITY
B114: * THESE AMOUNTS SHOULD BE INCLUDED AS "ADDITIONS" ON REPORT 18. | J114: =SUM(J110:J113) -> 0 | K114: =SUM(K110:K113) -> 0 | L114: =IF(J114=K114,"<- Debits and Credits equal each other.","<- Debits and Credits do not equal each other.") -> <- Debits and Credits equal each other.
B115: ** This amount should be included in the additions column on the LS-Lease Liability and LS-Check Figures Tabs.
D120: Informational - Ending Balances of Assets and Liabilities
K121: Debit (Credit)
D122: Acct 0476 - RIGHT-TO-USE LEASED LAND - AMORTIZABLE | K122: =J15+J39-K88-K101+J110 -> 0
D123: Acct 0478 - RIGHT-TO-USE LEASED EQUIPMENT - AMORTIZABLE | K123: =J16+J40-K89-K102+J111 -> 0
D124: Acct 0477 - RIGHT-TO-USE LEASED BUILDINGS - AMORTIZABLE | K124: =J17+J41-K90-K103+J112 -> 397432
D125: Acct 0485 - ACCUMULATED AMORTIZATION - RIGHT-TO-USE LEASED LAND | K125: =-K20-K56+J85+J97 -> 0
...

Sheet LS-Fund 0545 Journal Entries
A1: Lessee-Type Contracts Fund-by-Fund Journal Entries Form (to be submitted to the SCO annually—one form per fund)
A2: Manually complete every yellow field in this worksheet—there are no automatically calculated data-entry cells in this worksheet.
A3: Fiscal Year: | F3: 2023–2024
A4: Organization Name: | F4: Department of Water Resources
A5: Organization Code (4-Digits): | F5: 3860
A6: Fund Number (4-Digits): | F6: 545
A7: Fund Classification: | F7: Governmental
A8: Fund Type: | F8: Governmental Fund
A9: Functional Expense: | F9: =IFERROR(IF(F7="Proprietary","Proprietary Fund",VLOOKUP(F5,qryIndex02a!$A$2:$K$654,4,FALSE)),"Unidentified") -> RESOURCES
A12: Establish Beginning Balances (existing leases only)
A13: Entry #
A14: 0 | B14: Roll forward prior year right-to-use leases to record opening balances. | M14: Combined Lessee Templates | P14: From SCO BB List | S14: Difference
A15: *Rpt 18 | B15: Dr: Acct 0476 - RIGHT-TO-USE LEASED LAND - AMORTIZABLE | J15: =M15 -> 0 | S15: =P15-M15 -> 0
A16: *Rpt 18 | B16: Dr: Acct 0478 - RIGHT-TO-USE LEASED EQUIPMENT - AMORTIZABLE | J16: =M16 -> 0 | S16: =P16-M16 -> 0
A17: *Rpt 18 | B17: Dr: Acct 0477 - RIGHT-TO-USE LEASED BUILDINGS - AMORTIZABLE | J17: =M17 -> 12862 | M17: 12862 | P17: 0 | S17: =P17-M17 -> -12862
B18: Dr: Acct 0950 - BEGINNING FUND BALANCE | J18: =P18 -> 0 | M18: 287 | P18: =IF(SUM($Q$20:$Q$23)>SUM($P$15:$P$17),SUM($Q$20:$Q$23)-SUM($P$15:$P$17),0) -> 0 | S18: =P18-M18 -> -287
B19: Dr: Acct 0952 - BEGINNING FUND ADJUSTMENT/PRIOR PERIOD ADJUSTMENT | J19: =IF(SUM($K$20:$K$24)>SUM($J$15:$J$18),SUM($K$20:$K$24)-SUM($J$15:$J$18),0) -> 275 | M19: 0 | S19: =P19-M19 -> 0
C20: Cr: Acct 0485 - ACCUMULATED AMORTIZATION - RIGHT-TO-USE LEASED LAND | K20: =N20 -> 0 | S20: =P20-M20 -> 0
C21: Cr: Acct 0479 - ACCUMULATED AMORTIZATION - RIGHT-TO-USE LEASED EQUIPMENT | K21: =N21 -> 0 | S21: =Q21-N21 -> 0
C22: Cr: Acct 0486 - ACCUMULATED AMORTIZATION - RIGHT-TO-USE LEASED BUILDINGS | K22: =N22 -> 3642 | N22: 3642 | Q22: 0 | S22: =Q22-N22 -> -3642
A23: **LS LL/CF | C23: Cr: Acct 0691 - RIGHT-TO-USE LEASE LIABILITY | K23: =N23 -> 9495 | N23: 9495 | Q23: 0 | S23: =Q23-N23 -> -9495
C24: Cr: Acct 0950 - BEGINNING FUND BALANCE | K24: =Q24 -> 0 | N24: 12 | Q24: =IF(SUM($Q$20:$Q$23)<SUM($P$15:$P$17),-SUM($Q$20:$Q$23)+SUM($P$15:$P$17),0) -> 0 | S24: =Q24-N24 -> -12
C25: Cr: Acct 0952 - BEGINNING FUND ADJUSTMENT/PRIOR PERIOD ADJUSTMENT | K25: =IF(SUM($K$20:$K$24)<SUM($J$15:$J$18),-SUM($K$20:$K$24)+SUM($J$15:$J$18),0) -> 0 | N25: 0 | S25: =Q25-N25 -> 0
J26: =SUM(J15:J25) -> 13137 | K26: =SUM(K15:K25) -> 13137 | L26: =IF(J26=K26,"<- Debits and Credits equal each other.","<- Debits and Credits do not equal each other.") -> <- Debits and Credits equal each other.
B27: * THESE ASSET AMOUNTS SHOULD BE REPORTED AS BEGINNING BALANCES ON REPORT 18.
B28: ** This amount should be included in the beginning balance column on the LS-Lease Liability and LS-Check Figures Tabs.
A31: Record New Leases (new leases only)
A32: 1 | B32: Record lease contract commencement (fund-based entries only)
B33: Dr: Acct 0842 - CAPITAL OUTLAY | J33: 2979
C34: Cr: Acct 0789 - LEASE AND OTHER FINANCING PROCEEDS | K34: 2979
C35: =IF($F$7="Proprietary","Cr: Acct 0870 - SERVICES & CHARGES (MG ADJ)",VLOOKUP($F$9,'Drop Down Menus'!$F$2:$G$10,2,FALSE)) -> Cr: Acct 0820 - NAT RES & ENVIRON (GAAP ADJ)
J36: =SUM(J33:J35) -> 2979 | K36: =SUM(K33:K35) -> 2979 | L36: =IF(J36=K36,"<- Debits and Credits equal each other.","<- Debits and Credits do not equal each other.") -> <- Debits and Credits equal each other.
A38: 2 | B38: Record leased assets.
A39: *Rpt 18 | B39: Dr: Acct 0476 - RIGHT-TO-USE LEASED LAND - AMORTIZABLE
A40: *Rpt 18 | B40: Dr: Acct 0478 - RIGHT-TO-USE LEASED EQUIPMENT - AMORTIZABLE
A41: *Rpt 18 | B41: Dr: Acct 0477 - RIGHT-TO-USE LEASED BUILDINGS - AMORTIZABLE | J41: 2979
C42: Cr: Acct 0842 - CAPITAL OUTLAY | K42: 2979
B43: * THESE AMOUNTS SHOULD BE INCLUDED AS "ADDITIONS" ON REPORT 18. | J43: =SUM(J39:J42) -> 2979 | K43: =SUM(K39:K42) -> 2979 | L43: =IF(J43=K43,"<- Debits and Credits equal each other.","<- Debits and Credits do not equal each other.") -> <- Debits and Credits equal each other.
A46: 3 | B46: Replace proceeds from leases with right-to-use lease liability.
B47: Dr: Acct 0789 - LEASE AND OTHER FINANCING PROCEEDS | J47: 2979
A48: **LS LL/CF | C48: Cr: Acct 0691 - RIGHT-TO-USE LEASE LIABILITY | K48: 2979
J49: =SUM(J47:J48) -> 2979 | K49: =SUM(K47:K48) -> 2979 | L49: =IF(J49=K49,"<- Debits and Credits equal each other.","<- Debits and Credits do not equal each other.") -> <- Debits and Credits equal each other.
B50: ** This amount should be included in the additions column on the LS-Lease Liability and LS-Check Figures Tabs.
A53: Record Annual Activity (all leases)
A54: 4 | B54: Record amortization of the leased assets for the year.
B55: Dr: Acct 0875 - DEPRECIATION/AMORTIZATION | J55: 1950
C56: Cr: Acct 0485 - ACCUMULATED AMORTIZATION - RIGHT-TO-USE LEASED LAND
C57: Cr: Acct 0479 - ACCUMULATED AMORTIZATION - RIGHT-TO-USE LEASED EQUIPMENT
C58: Cr: Acct 0486 - ACCUMULATED AMORTIZATION - RIGHT-TO-USE LEASED BUILDINGS | K58: 1950
J59: =SUM(J55:J58) -> 1950 | K59: =SUM(K55:K58) -> 1950 | L59: =IF(J59=K59,"<- Debits and Credits equal each other.","<- Debits and Credits do not equal each other.") -> <- Debits and Credits equal each other.
A61: 5 | B61: Reclassify rents and leases exp. to lease contract principal and interest exp.
B62: Dr: Acct 0848 - DEBT SERVICE - PRINCIPAL LEASES | J62: 1773
B63: =IF(F7="Governmental","Dr: Acct 0851 - DEBT SERVICE - INTEREST LEASES","Dr: Acct 0894 - INTEREST EXPENSE AND FISCAL CHARGES") -> Dr: Acct 0851 - DEBT SERVICE - INTEREST LEASES | J63: 218
C64: =IF($F$7="Proprietary","Cr: Acct 0870 - SERVICES & CHARGES (MG ADJ)",VLOOKUP($F$9,'Drop Down Menus'!$F$2:$G$10,2,FALSE)) -> Cr: Acct 0820 - NAT RES & ENVIRON (GAAP ADJ) | K64: 1991
J65: =SUM(J62:J64) -> 1991 | K65: =SUM(K62:K64) -> 1991 | L65: =IF(J65=K65,"<- Debits and Credits equal each other.","<- Debits and Credits do not equal each other.") -> <- Debits and Credits equal each other.
A67: 6 | B67: Reduce lease contracts liability for total current year principal payments.
A68: **LS LL/CF | B68: Dr: Acct 0691 - RIGHT-TO-USE LEASE LIABILITY | J68: 1773
C69: Cr: Acct 0848 - DEBT SERVICE - PRINCIPAL LEASES | K69: 1773
J70: =SUM(J68:J69) -> 1773 | K70: =SUM(K68:K69) -> 1773 | L70: =IF(J70=K70,"<- Debits and Credits equal each other.","<- Debits and Credits do not equal each other.") -> <- Debits and Credits equal each other.
B71: ** This amount should be included in the deductions column on the LS-Lease Liability and LS-Check Figures Tabs.
A74: 7 | B74: Reclassify the principal amount due in the next FY to the current liability.
A75: **LS LL/CF | B75: Dr: Acct 0691 - RIGHT-TO-USE LEASE LIABILITY | J75: 1815
C76: Cr: Acct 0649 - RIGHT-TO-USE LEASE LIABILITY (CURRENT PORTION LT) | K76: 1815
B77: NOTE: This is an annual accrual. It is to be reversed at the start of the next fiscal year. SCO combines the current and non current amount in Entry #0 to reestablish the beginning balances. No action required. | J77: =SUM(J75:J76) -> 1815 | K77: =SUM(K75:K76) -> 1815 | L77: =IF(J77=K77,"<- Debits and Credits equal each other.","<- Debits and Credits do not equal each other.") -> <- Debits and Credits equal each other.
B80: ** This amount should be included in the due in one year column on the LS-Lease Liability and LS-Check Figures Tabs.
A83: Remove Lease Asset at the End of the Lease Term (only at the end of the lease term)
A84: 8 | B84: Record entry to write off the lease asset and accumulated amortization at the end of the lease term.
B85: Dr: Acct 0485 - ACCUMULATED AMORTIZATION - RIGHT-TO-USE LEASED LAND
B86: Dr: Acct 0479 - ACCUMULATED AMORTIZATION - RIGHT-TO-USE LEASED EQUIPMENT
B87: Dr: Acct 0486 - ACCUMULATED AMORTIZATION - RIGHT-TO-USE LEASED BUILDINGS | J87: 712
A88: *Rpt 18 | C88: Cr: Acct 0476 - RIGHT-TO-USE LEASED LAND - AMORTIZABLE
A89: *Rpt 18 | C89: Cr: Acct 0478 - RIGHT-TO-USE LEASED EQUIPMENT - AMORTIZABLE
A90: *Rpt 18 | C90: Cr: Acct 0477 - RIGHT-TO-USE LEASED BUILDINGS - AMORTIZABLE | K90: 712
B91: * THESE AMOUNTS SHOULD BE INCLUDED AS "DEDUCTIONS" ON REPORT 18. | J91: =SUM(J85:J90) -> 712 | K91: =SUM(K85:K90) -> 712 | L91: =IF(J91=K91,"<- Debits and Credits equal each other.","<- Debits and Credits do not equal each other.") -> <- Debits and Credits equal each other.
A94: Lease Remeasurement and Modifications (only if a significant modification occurred during the fiscal year)
A95: 9 | B95: Record early termination or lease modifications to decrease in the RTU leased asset.
A96: **LS LL/CF | B96: Dr: Acct 0691 - RIGHT-TO-USE LEASE LIABILITY
B97: Dr: Acct 0485 - ACCUMULATED AMORTIZATION - RIGHT-TO-USE LEASED LAND
B98: Dr: Acct 0479 - ACCUMULATED AMORTIZATION - RIGHT-TO-USE LEASED EQUIPMENT
B99: Dr: Acct 0486 - ACCUMULATED AMORTIZATION - RIGHT-TO-USE LEASED BUILDINGS
B100: =IF($F$7="Proprietary","Dr: Acct 0870 - SERVICES & CHARGES (MG ADJ)",VLOOKUP($F$9,'Drop Down Menus'!$F$2:$H$10,3,FALSE)) -> Dr: Acct 0820 - NAT RES & ENVIRON (GAAP ADJ)
A101: *Rpt 18 | C101: Cr: Acct 0476 - RIGHT-TO-USE LEASED LAND - AMORTIZABLE
A102: *Rpt 18 | C102: Cr: Acct 0478 - RIGHT-TO-USE LEASED EQUIPMENT - AMORTIZABLE
A103: *Rpt 18 | C103: Cr: Acct 0477 - RIGHT-TO-USE LEASED BUILDINGS - AMORTIZABLE
C104: =IF($F$7="Proprietary","Dr: Acct 0870 - SERVICES & CHARGES (MG ADJ)",VLOOKUP($F$9,'Drop Down Menus'!$F$2:$G$10,2,FALSE)) -> Cr: Acct 0820 - NAT RES & ENVIRON (GAAP ADJ)
B105: * THESE AMOUNTS SHOULD BE INCLUDED AS "DEDUCTIONS" ON REPORT 18. | J105: =SUM(J96:J104) -> 0 | K105: =SUM(K96:K104) -> 0 | L105: =IF(J105=K105,"<- Debits and Credits equal each other.","<- Debits and Credits do not equal each other.") -> <- Debits and Credits equal each other.
B106: ** This amount should be included in the deductions column on the LS-Lease Liability and LS-Check Figures Tabs.
A109: 10 | B109: Record lease modifications to increase in the RTU leased asset.
A110: *Rpt 18 | B110: Dr: Acct 0476 - RIGHT-TO-USE LEASED LAND - AMORTIZABLE
A111: *Rpt 18 | B111: Dr: Acct 0478 - RIGHT-TO-USE LEASED EQUIPMENT - AMORTIZABLE
A112: *Rpt 18 | B112: Dr: Acct 0477 - RIGHT-TO-USE LEASED BUILDINGS - AMORTIZABLE
A113: **LS LL/CF | C113: Cr: Acct 0691 - RIGHT-TO-USE LEASE LIABILITY
B114: * THESE AMOUNTS SHOULD BE INCLUDED AS "ADDITIONS" ON REPORT 18. | J114: =SUM(J110:J113) -> 0 | K114: =SUM(K110:K113) -> 0 | L114: =IF(J114=K114,"<- Debits and Credits equal each other.","<- Debits and Credits do not equal each other.") -> <- Debits and Credits equal each other.
B115: ** This amount should be included in the additions column on the LS-Lease Liability and LS-Check Figures Tabs.
D120: Informational - Ending Balances of Assets and Liabilities
K121: Debit (Credit)
D122: Acct 0476 - RIGHT-TO-USE LEASED LAND - AMORTIZABLE | K122: =J15+J39-K88-K101+J110 -> 0
D123: Acct 0478 - RIGHT-TO-USE LEASED EQUIPMENT - AMORTIZABLE | K123: =J16+J40-K89-K102+J111 -> 0
D124: Acct 0477 - RIGHT-TO-USE LEASED BUILDINGS - AMORTIZABLE | K124: =J17+J41-K90-K103+J112 -> 15129
D125: Acct 0485 - ACCUMULATED AMORTIZATION - RIGHT-TO-USE LEASED LAND | K125: =-K20-K56+J85+J97 -> 0
...

Sheet LS-Fund 0890 Journal Entries
A1: Lessee-Type Contracts Fund-by-Fund Journal Entries Form (to be submitted to the SCO annually—one form per fund)
A2: Manually complete every yellow field in this worksheet—there are no automatically calculated data-entry cells in this worksheet.
A3: Fiscal Year: | F3: 2023–2024
A4: Organization Name: | F4: Department of Water Resources
A5: Organization Code (4-Digits): | F5: 3860
A6: Fund Number (4-Digits): | F6: 890
A7: Fund Classification: | F7: Governmental
A8: Fund Type: | F8: Governmental Fund
A9: Functional Expense: | F9: =IFERROR(IF(F7="Proprietary","Proprietary Fund",VLOOKUP(F5,qryIndex02a!$A$2:$K$654,4,FALSE)),"Unidentified") -> RESOURCES
A12: Establish Beginning Balances (existing leases only)
A13: Entry #
A14: 0 | B14: Roll forward prior year right-to-use leases to record opening balances. | M14: Combined Lessee Templates | P14: From SCO BB List | S14: Difference
A15: *Rpt 18 | B15: Dr: Acct 0476 - RIGHT-TO-USE LEASED LAND - AMORTIZABLE | J15: =M15 -> 0 | S15: =P15-M15 -> 0
A16: *Rpt 18 | B16: Dr: Acct 0478 - RIGHT-TO-USE LEASED EQUIPMENT - AMORTIZABLE | J16: =M16 -> 0 | S16: =P16-M16 -> 0
A17: *Rpt 18 | B17: Dr: Acct 0477 - RIGHT-TO-USE LEASED BUILDINGS - AMORTIZABLE | J17: =M17 -> 105593 | M17: 105593 | P17: 291931 | S17: =P17-M17 -> 186338
B18: Dr: Acct 0950 - BEGINNING FUND BALANCE | J18: =P18 -> 6235 | M18: 2355 | P18: =IF(SUM($Q$20:$Q$23)>SUM($P$15:$P$17),SUM($Q$20:$Q$23)-SUM($P$15:$P$17),0) -> 6235 | S18: =P18-M18 -> 3880
B19: Dr: Acct 0952 - BEGINNING FUND ADJUSTMENT/PRIOR PERIOD ADJUSTMENT | J19: =IF(SUM($K$20:$K$24)>SUM($J$15:$J$18),SUM($K$20:$K$24)-SUM($J$15:$J$18),0) -> 0 | M19: 0 | S19: =P19-M19 -> 0
C20: Cr: Acct 0485 - ACCUMULATED AMORTIZATION - RIGHT-TO-USE LEASED LAND | K20: =N20 -> 0 | S20: =P20-M20 -> 0
C21: Cr: Acct 0479 - ACCUMULATED AMORTIZATION - RIGHT-TO-USE LEASED EQUIPMENT | K21: =N21 -> 0 | S21: =Q21-N21 -> 0
C22: Cr: Acct 0486 - ACCUMULATED AMORTIZATION - RIGHT-TO-USE LEASED BUILDINGS | K22: =N22 -> 29899 | N22: 29899 | Q22: 82662 | S22: =Q22-N22 -> 52763
A23: **LS LL/CF | C23: Cr: Acct 0691 - RIGHT-TO-USE LEASE LIABILITY | K23: =N23 -> 77949 | N23: 77949 | Q23: 215504 | S23: =Q23-N23 -> 137555
C24: Cr: Acct 0950 - BEGINNING FUND BALANCE | K24: =Q24 -> 0 | N24: 100 | Q24: =IF(SUM($Q$20:$Q$23)<SUM($P$15:$P$17),-SUM($Q$20:$Q$23)+SUM($P$15:$P$17),0) -> 0 | S24: =Q24-N24 -> -100
C25: Cr: Acct 0952 - BEGINNING FUND ADJUSTMENT/PRIOR PERIOD ADJUSTMENT | K25: =IF(SUM($K$20:$K$24)<SUM($J$15:$J$18),-SUM($K$20:$K$24)+SUM($J$15:$J$18),0) -> 3980 | N25: 0 | S25: =Q25-N25 -> 0
J26: =SUM(J15:J25) -> 111828 | K26: =SUM(K15:K25) -> 111828 | L26: =IF(J26=K26,"<- Debits and Credits equal each other.","<- Debits and Credits do not equal each other.") -> <- Debits and Credits equal each other.
B27: * THESE ASSET AMOUNTS SHOULD BE REPORTED AS BEGINNING BALANCES ON REPORT 18.
B28: ** This amount should be included in the beginning balance column on the LS-Lease Liability and LS-Check Figures Tabs.
A31: Record New Leases (new leases only)
A32: 1 | B32: Record lease contract commencement (fund-based entries only)
B33: Dr: Acct 0842 - CAPITAL OUTLAY | J33: 24457
C34: Cr: Acct 0789 - LEASE AND OTHER FINANCING PROCEEDS | K34: 24457
C35: =IF($F$7="Proprietary","Cr: Acct 0870 - SERVICES & CHARGES (MG ADJ)",VLOOKUP($F$9,'Drop Down Menus'!$F$2:$G$10,2,FALSE)) -> Cr: Acct 0820 - NAT RES & ENVIRON (GAAP ADJ)
J36: =SUM(J33:J35) -> 24457 | K36: =SUM(K33:K35) -> 24457 | L36: =IF(J36=K36,"<- Debits and Credits equal each other.","<- Debits and Credits do not equal each other.") -> <- Debits and Credits equal each other.
A38: 2 | B38: Record leased assets.
A39: *Rpt 18 | B39: Dr: Acct 0476 - RIGHT-TO-USE LEASED LAND - AMORTIZABLE
A40: *Rpt 18 | B40: Dr: Acct 0478 - RIGHT-TO-USE LEASED EQUIPMENT - AMORTIZABLE
A41: *Rpt 18 | B41: Dr: Acct 0477 - RIGHT-TO-USE LEASED BUILDINGS - AMORTIZABLE | J41: 24457
C42: Cr: Acct 0842 - CAPITAL OUTLAY | K42: 24457
B43: * THESE AMOUNTS SHOULD BE INCLUDED AS "ADDITIONS" ON REPORT 18. | J43: =SUM(J39:J42) -> 24457 | K43: =SUM(K39:K42) -> 24457 | L43: =IF(J43=K43,"<- Debits and Credits equal each other.","<- Debits and Credits do not equal each other.") -> <- Debits and Credits equal each other.
A46: 3 | B46: Replace proceeds from leases with right-to-use lease liability.
B47: Dr: Acct 0789 - LEASE AND OTHER FINANCING PROCEEDS | J47: 24457
A48: **LS LL/CF | C48: Cr: Acct 0691 - RIGHT-TO-USE LEASE LIABILITY | K48: 24457
J49: =SUM(J47:J48) -> 24457 | K49: =SUM(K47:K48) -> 24457 | L49: =IF(J49=K49,"<- Debits and Credits equal each other.","<- Debits and Credits do not equal each other.") -> <- Debits and Credits equal each other.
B50: ** This amount should be included in the additions column on the LS-Lease Liability and LS-Check Figures Tabs.
A53: Record Annual Activity (all leases)
A54: 4 | B54: Record amortization of the leased assets for the year.
B55: Dr: Acct 0875 - DEPRECIATION/AMORTIZATION | J55: 16011
C56: Cr: Acct 0485 - ACCUMULATED AMORTIZATION - RIGHT-TO-USE LEASED LAND
C57: Cr: Acct 0479 - ACCUMULATED AMORTIZATION - RIGHT-TO-USE LEASED EQUIPMENT
C58: Cr: Acct 0486 - ACCUMULATED AMORTIZATION - RIGHT-TO-USE LEASED BUILDINGS | K58: 16011
J59: =SUM(J55:J58) -> 16011 | K59: =SUM(K55:K58) -> 16011 | L59: =IF(J59=K59,"<- Debits and Credits equal each other.","<- Debits and Credits do not equal each other.") -> <- Debits and Credits equal each other.
A61: 5 | B61: Reclassify rents and leases exp. to lease contract principal and interest exp.
B62: Dr: Acct 0848 - DEBT SERVICE - PRINCIPAL LEASES | J62: 14556
B63: =IF(F7="Governmental","Dr: Acct 0851 - DEBT SERVICE - INTEREST LEASES","Dr: Acct 0894 - INTEREST EXPENSE AND FISCAL CHARGES") -> Dr: Acct 0851 - DEBT SERVICE - INTEREST LEASES | J63: 1789
C64: =IF($F$7="Proprietary","Cr: Acct 0870 - SERVICES & CHARGES (MG ADJ)",VLOOKUP($F$9,'Drop Down Menus'!$F$2:$G$10,2,FALSE)) -> Cr: Acct 0820 - NAT RES & ENVIRON (GAAP ADJ) | K64: 16345
J65: =SUM(J62:J64) -> 16345 | K65: =SUM(K62:K64) -> 16345 | L65: =IF(J65=K65,"<- Debits and Credits equal each other.","<- Debits and Credits do not equal each other.") -> <- Debits and Credits equal each other.
A67: 6 | B67: Reduce lease contracts liability for total current year principal payments.
A68: **LS LL/CF | B68: Dr: Acct 0691 - RIGHT-TO-USE LEASE LIABILITY | J68: 14556
C69: Cr: Acct 0848 - DEBT SERVICE - PRINCIPAL LEASES | K69: 14556
J70: =SUM(J68:J69) -> 14556 | K70: =SUM(K68:K69) -> 14556 | L70: =IF(J70=K70,"<- Debits and Credits equal each other.","<- Debits and Credits do not equal each other.") -> <- Debits and Credits equal each other.
B71: ** This amount should be included in the deductions column on the LS-Lease Liability and LS-Check Figures Tabs.
A74: 7 | B74: Reclassify the principal amount due in the next FY to the current liability.
A75: **LS LL/CF | B75: Dr: Acct 0691 - RIGHT-TO-USE LEASE LIABILITY | J75: 14899
C76: Cr: Acct 0649 - RIGHT-TO-USE LEASE LIABILITY (CURRENT PORTION LT) | K76: 14899
B77: NOTE: This is an annual accrual. It is to be reversed at the start of the next fiscal year. SCO combines the current and non current amount in Entry #0 to reestablish the beginning balances. No action required. | J77: =SUM(J75:J76) -> 14899 | K77: =SUM(K75:K76) -> 14899 | L77: =IF(J77=K77,"<- Debits and Credits equal each other.","<- Debits and Credits do not equal each other.") -> <- Debits and Credits equal each other.
B80: ** This amount should be included in the due in one year column on the LS-Lease Liability and LS-Check Figures Tabs.
A83: Remove Lease Asset at the End of the Lease Term (only at the end of the lease term)
A84: 8 | B84: Record entry to write off the lease asset and accumulated amortization at the end of the lease term.
B85: Dr: Acct 0485 - ACCUMULATED AMORTIZATION - RIGHT-TO-USE LEASED LAND
B86: Dr: Acct 0479 - ACCUMULATED AMORTIZATION - RIGHT-TO-USE LEASED EQUIPMENT
B87: Dr: Acct 0486 - ACCUMULATED AMORTIZATION - RIGHT-TO-USE LEASED BUILDINGS | J87: 5847
A88: *Rpt 18 | C88: Cr: Acct 0476 - RIGHT-TO-USE LEASED LAND - AMORTIZABLE
A89: *Rpt 18 | C89: Cr: Acct 0478 - RIGHT-TO-USE LEASED EQUIPMENT - AMORTIZABLE
A90: *Rpt 18 | C90: Cr: Acct 0477 - RIGHT-TO-USE LEASED BUILDINGS - AMORTIZABLE | K90: 5847
B91: * THESE AMOUNTS SHOULD BE INCLUDED AS "DEDUCTIONS" ON REPORT 18. | J91: =SUM(J85:J90) -> 5847 | K91: =SUM(K85:K90) -> 5847 | L91: =IF(J91=K91,"<- Debits and Credits equal each other.","<- Debits and Credits do not equal each other.") -> <- Debits and Credits equal each other.
A94: Lease Remeasurement and Modifications (only if a significant modification occurred during the fiscal year)
A95: 9 | B95: Record early termination or lease modifications to decrease in the RTU leased asset.
A96: **LS LL/CF | B96: Dr: Acct 0691 - RIGHT-TO-USE LEASE LIABILITY
B97: Dr: Acct 0485 - ACCUMULATED AMORTIZATION - RIGHT-TO-USE LEASED LAND
B98: Dr: Acct 0479 - ACCUMULATED AMORTIZATION - RIGHT-TO-USE LEASED EQUIPMENT
B99: Dr: Acct 0486 - ACCUMULATED AMORTIZATION - RIGHT-TO-USE LEASED BUILDINGS
B100: =IF($F$7="Proprietary","Dr: Acct 0870 - SERVICES & CHARGES (MG ADJ)",VLOOKUP($F$9,'Drop Down Menus'!$F$2:$H$10,3,FALSE)) -> Dr: Acct 0820 - NAT RES & ENVIRON (GAAP ADJ)
A101: *Rpt 18 | C101: Cr: Acct 0476 - RIGHT-TO-USE LEASED LAND - AMORTIZABLE
A102: *Rpt 18 | C102: Cr: Acct 0478 - RIGHT-TO-USE LEASED EQUIPMENT - AMORTIZABLE
A103: *Rpt 18 | C103: Cr: Acct 0477 - RIGHT-TO-USE LEASED BUILDINGS - AMORTIZABLE
C104: =IF($F$7="Proprietary","Dr: Acct 0870 - SERVICES & CHARGES (MG ADJ)",VLOOKUP($F$9,'Drop Down Menus'!$F$2:$G$10,2,FALSE)) -> Cr: Acct 0820 - NAT RES & ENVIRON (GAAP ADJ)
B105: * THESE AMOUNTS SHOULD BE INCLUDED AS "DEDUCTIONS" ON REPORT 18. | J105: =SUM(J96:J104) -> 0 | K105: =SUM(K96:K104) -> 0 | L105: =IF(J105=K105,"<- Debits and Credits equal each other.","<- Debits and Credits do not equal each other.") -> <- Debits and Credits equal each other.
B106: ** This amount should be included in the deductions column on the LS-Lease Liability and LS-Check Figures Tabs.
A109: 10 | B109: Record lease modifications to increase in the RTU leased asset.
A110: *Rpt 18 | B110: Dr: Acct 0476 - RIGHT-TO-USE LEASED LAND - AMORTIZABLE
A111: *Rpt 18 | B111: Dr: Acct 0478 - RIGHT-TO-USE LEASED EQUIPMENT - AMORTIZABLE
A112: *Rpt 18 | B112: Dr: Acct 0477 - RIGHT-TO-USE LEASED BUILDINGS - AMORTIZABLE
A113: **LS LL/CF | C113: Cr: Acct 0691 - RIGHT-TO-USE LEASE LIABILITY
B114: * THESE AMOUNTS SHOULD BE INCLUDED AS "ADDITIONS" ON REPORT 18. | J114: =SUM(J110:J113) -> 0 | K114: =SUM(K110:K113) -> 0 | L114: =IF(J114=K114,"<- Debits and Credits equal each other.","<- Debits and Credits do not equal each other.") -> <- Debits and Credits equal each other.
B115: ** This amount should be included in the additions column on the LS-Lease Liability and LS-Check Figures Tabs.
D120: Informational - Ending Balances of Assets and Liabilities
K121: Debit (Credit)
D122: Acct 0476 - RIGHT-TO-USE LEASED LAND - AMORTIZABLE | K122: =J15+J39-K88-K101+J110 -> 0
D123: Acct 0478 - RIGHT-TO-USE LEASED EQUIPMENT - AMORTIZABLE | K123: =J16+J40-K89-K102+J111 -> 0
D124: Acct 0477 - RIGHT-TO-USE LEASED BUILDINGS - AMORTIZABLE | K124: =J17+J41-K90-K103+J112 -> 124203
D125: Acct 0485 - ACCUMULATED AMORTIZATION - RIGHT-TO-USE LEASED LAND | K125: =-K20-K56+J85+J97 -> 0
...

Sheet LS-Fund 3057 Journal Entries
A1: Lessee-Type Contracts Fund-by-Fund Journal Entries Form (to be submitted to the SCO annually—one form per fund)
A2: Manually complete every yellow field in this worksheet—there are no automatically calculated data-entry cells in this worksheet.
A3: Fiscal Year: | F3: 2023–2024
A4: Organization Name: | F4: Department of Water Resources
A5: Organization Code (4-Digits): | F5: 3860
A6: Fund Number (4-Digits): | F6: 3057
A7: Fund Classification: | F7: Governmental
A8: Fund Type: | F8: Governmental Fund
A9: Functional Expense: | F9: =IFERROR(IF(F7="Proprietary","Proprietary Fund",VLOOKUP(F5,qryIndex02a!$A$2:$K$654,4,FALSE)),"Unidentified") -> RESOURCES
A12: Establish Beginning Balances (existing leases only)
A13: Entry #
A14: 0 | B14: Roll forward prior year right-to-use leases to record opening balances. | M14: Combined Lessee Templates | P14: From SCO BB List | S14: Difference
A15: *Rpt 18 | B15: Dr: Acct 0476 - RIGHT-TO-USE LEASED LAND - AMORTIZABLE | J15: =M15 -> 0 | S15: =P15-M15 -> 0
A16: *Rpt 18 | B16: Dr: Acct 0478 - RIGHT-TO-USE LEASED EQUIPMENT - AMORTIZABLE | J16: =M16 -> 0 | S16: =P16-M16 -> 0
A17: *Rpt 18 | B17: Dr: Acct 0477 - RIGHT-TO-USE LEASED BUILDINGS - AMORTIZABLE | J17: =M17 -> 1763529 | M17: 1763529 | P17: 1816458 | S17: =P17-M17 -> 52929
B18: Dr: Acct 0950 - BEGINNING FUND BALANCE | J18: =P18 -> 38801 | M18: 39337 | P18: =IF(SUM($Q$20:$Q$23)>SUM($P$15:$P$17),SUM($Q$20:$Q$23)-SUM($P$15:$P$17),0) -> 38801 | S18: =P18-M18 -> -536
B19: Dr: Acct 0952 - BEGINNING FUND ADJUSTMENT/PRIOR PERIOD ADJUSTMENT | J19: =IF(SUM($K$20:$K$24)>SUM($J$15:$J$18),SUM($K$20:$K$24)-SUM($J$15:$J$18),0) -> 0 | M19: 0 | S19: =P19-M19 -> 0
C20: Cr: Acct 0485 - ACCUMULATED AMORTIZATION - RIGHT-TO-USE LEASED LAND | K20: =N20 -> 0 | S20: =P20-M20 -> 0
C21: Cr: Acct 0479 - ACCUMULATED AMORTIZATION - RIGHT-TO-USE LEASED EQUIPMENT | K21: =N21 -> 0 | S21: =Q21-N21 -> 0
C22: Cr: Acct 0486 - ACCUMULATED AMORTIZATION - RIGHT-TO-USE LEASED BUILDINGS | K22: =N22 -> 499352 | N22: 499352 | Q22: 514338 | S22: =Q22-N22 -> 14986
A23: **LS LL/CF | C23: Cr: Acct 0691 - RIGHT-TO-USE LEASE LIABILITY | K23: =N23 -> 1301848 | N23: 1301848 | Q23: 1340921 | S23: =Q23-N23 -> 39073
C24: Cr: Acct 0950 - BEGINNING FUND BALANCE | K24: =Q24 -> 0 | N24: 1666 | Q24: =IF(SUM($Q$20:$Q$23)<SUM($P$15:$P$17),-SUM($Q$20:$Q$23)+SUM($P$15:$P$17),0) -> 0 | S24: =Q24-N24 -> -1666
C25: Cr: Acct 0952 - BEGINNING FUND ADJUSTMENT/PRIOR PERIOD ADJUSTMENT | K25: =IF(SUM($K$20:$K$24)<SUM($J$15:$J$18),-SUM($K$20:$K$24)+SUM($J$15:$J$18),0) -> 1130 | N25: 0 | S25: =Q25-N25 -> 0
J26: =SUM(J15:J25) -> 1802330 | K26: =SUM(K15:K25) -> 1802330 | L26: =IF(J26=K26,"<- Debits and Credits equal each other.","<- Debits and Credits do not equal each other.") -> <- Debits and Credits equal each other.
B27: * THESE ASSET AMOUNTS SHOULD BE REPORTED AS BEGINNING BALANCES ON REPORT 18.
B28: ** This amount should be included in the beginning balance column on the LS-Lease Liability and LS-Check Figures Tabs.
A31: Record New Leases (new leases only)
A32: 1 | B32: Record lease contract commencement (fund-based entries only)
B33: Dr: Acct 0842 - CAPITAL OUTLAY | J33: 408464
C34: Cr: Acct 0789 - LEASE AND OTHER FINANCING PROCEEDS | K34: 408464
C35: =IF($F$7="Proprietary","Cr: Acct 0870 - SERVICES & CHARGES (MG ADJ)",VLOOKUP($F$9,'Drop Down Menus'!$F$2:$G$10,2,FALSE)) -> Cr: Acct 0820 - NAT RES & ENVIRON (GAAP ADJ)
J36: =SUM(J33:J35) -> 408464 | K36: =SUM(K33:K35) -> 408464 | L36: =IF(J36=K36,"<- Debits and Credits equal each other.","<- Debits and Credits do not equal each other.") -> <- Debits and Credits equal each other.
A38: 2 | B38: Record leased assets.
A39: *Rpt 18 | B39: Dr: Acct 0476 - RIGHT-TO-USE LEASED LAND - AMORTIZABLE
A40: *Rpt 18 | B40: Dr: Acct 0478 - RIGHT-TO-USE LEASED EQUIPMENT - AMORTIZABLE
A41: *Rpt 18 | B41: Dr: Acct 0477 - RIGHT-TO-USE LEASED BUILDINGS - AMORTIZABLE | J41: 408464
C42: Cr: Acct 0842 - CAPITAL OUTLAY | K42: 408464
B43: * THESE AMOUNTS SHOULD BE INCLUDED AS "ADDITIONS" ON REPORT 18. | J43: =SUM(J39:J42) -> 408464 | K43: =SUM(K39:K42) -> 408464 | L43: =IF(J43=K43,"<- Debits and Credits equal each other.","<- Debits and Credits do not equal each other.") -> <- Debits and Credits equal each other.
A46: 3 | B46: Replace proceeds from leases with right-to-use lease liability.
B47: Dr: Acct 0789 - LEASE AND OTHER FINANCING PROCEEDS | J47: 408464
A48: **LS LL/CF | C48: Cr: Acct 0691 - RIGHT-TO-USE LEASE LIABILITY | K48: 408464
J49: =SUM(J47:J48) -> 408464 | K49: =SUM(K47:K48) -> 408464 | L49: =IF(J49=K49,"<- Debits and Credits equal each other.","<- Debits and Credits do not equal each other.") -> <- Debits and Credits equal each other.
B50: ** This amount should be included in the additions column on the LS-Lease Liability and LS-Check Figures Tabs.
A53: Record Annual Activity (all leases)
A54: 4 | B54: Record amortization of the leased assets for the year.
B55: Dr: Acct 0875 - DEPRECIATION/AMORTIZATION | J55: 267408
C56: Cr: Acct 0485 - ACCUMULATED AMORTIZATION - RIGHT-TO-USE LEASED LAND
C57: Cr: Acct 0479 - ACCUMULATED AMORTIZATION - RIGHT-TO-USE LEASED EQUIPMENT
C58: Cr: Acct 0486 - ACCUMULATED AMORTIZATION - RIGHT-TO-USE LEASED BUILDINGS | K58: 267408
J59: =SUM(J55:J58) -> 267408 | K59: =SUM(K55:K58) -> 267408 | L59: =IF(J59=K59,"<- Debits and Credits equal each other.","<- Debits and Credits do not equal each other.") -> <- Debits and Credits equal each other.
A61: 5 | B61: Reclassify rents and leases exp. to lease contract principal and interest exp.
B62: Dr: Acct 0848 - DEBT SERVICE - PRINCIPAL LEASES | J62: 243110
B63: =IF(F7="Governmental","Dr: Acct 0851 - DEBT SERVICE - INTEREST LEASES","Dr: Acct 0894 - INTEREST EXPENSE AND FISCAL CHARGES") -> Dr: Acct 0851 - DEBT SERVICE - INTEREST LEASES | J63: 29877
C64: =IF($F$7="Proprietary","Cr: Acct 0870 - SERVICES & CHARGES (MG ADJ)",VLOOKUP($F$9,'Drop Down Menus'!$F$2:$G$10,2,FALSE)) -> Cr: Acct 0820 - NAT RES & ENVIRON (GAAP ADJ) | K64: 272988
J65: =SUM(J62:J64) -> 272987 | K65: =SUM(K62:K64) -> 272988 | L65: =IF(J65=K65,"<- Debits and Credits equal each other.","<- Debits and Credits do not equal each other.") -> <- Debits and Credits do not equal each other.
A67: 6 | B67: Reduce lease contracts liability for total current year principal payments.
A68: **LS LL/CF | B68: Dr: Acct 0691 - RIGHT-TO-USE LEASE LIABILITY | J68: 243110
C69: Cr: Acct 0848 - DEBT SERVICE - PRINCIPAL LEASES | K69: 243110
J70: =SUM(J68:J69) -> 243110 | K70: =SUM(K68:K69) -> 243110 | L70: =IF(J70=K70,"<- Debits and Credits equal each other.","<- Debits and Credits do not equal each other.") -> <- Debits and Credits equal each other.
B71: ** This amount should be included in the deductions column on the LS-Lease Liability and LS-Check Figures Tabs.
A74: 7 | B74: Reclassify the principal amount due in the next FY to the current liability.
A75: **LS LL/CF | B75: Dr: Acct 0691 - RIGHT-TO-USE LEASE LIABILITY | J75: 248834
C76: Cr: Acct 0649 - RIGHT-TO-USE LEASE LIABILITY (CURRENT PORTION LT) | K76: 248834
B77: NOTE: This is an annual accrual. It is to be reversed at the start of the next fiscal year. SCO combines the current and non current amount in Entry #0 to reestablish the beginning balances. No action required. | J77: =SUM(J75:J76) -> 248834 | K77: =SUM(K75:K76) -> 248834 | L77: =IF(J77=K77,"<- Debits and Credits equal each other.","<- Debits and Credits do not equal each other.") -> <- Debits and Credits equal each other.
B80: ** This amount should be included in the due in one year column on the LS-Lease Liability and LS-Check Figures Tabs.
A83: Remove Lease Asset at the End of the Lease Term (only at the end of the lease term)
A84: 8 | B84: Record entry to write off the lease asset and accumulated amortization at the end of the lease term.
B85: Dr: Acct 0485 - ACCUMULATED AMORTIZATION - RIGHT-TO-USE LEASED LAND
B86: Dr: Acct 0479 - ACCUMULATED AMORTIZATION - RIGHT-TO-USE LEASED EQUIPMENT
B87: Dr: Acct 0486 - ACCUMULATED AMORTIZATION - RIGHT-TO-USE LEASED BUILDINGS | J87: 97660
A88: *Rpt 18 | C88: Cr: Acct 0476 - RIGHT-TO-USE LEASED LAND - AMORTIZABLE
A89: *Rpt 18 | C89: Cr: Acct 0478 - RIGHT-TO-USE LEASED EQUIPMENT - AMORTIZABLE
A90: *Rpt 18 | C90: Cr: Acct 0477 - RIGHT-TO-USE LEASED BUILDINGS - AMORTIZABLE | K90: 97660
B91: * THESE AMOUNTS SHOULD BE INCLUDED AS "DEDUCTIONS" ON REPORT 18. | J91: =SUM(J85:J90) -> 97660 | K91: =SUM(K85:K90) -> 97660 | L91: =IF(J91=K91,"<- Debits and Credits equal each other.","<- Debits and Credits do not equal each other.") -> <- Debits and Credits equal each other.
A94: Lease Remeasurement and Modifications (only if a significant modification occurred during the fiscal year)
A95: 9 | B95: Record early termination or lease modifications to decrease in the RTU leased asset.
A96: **LS LL/CF | B96: Dr: Acct 0691 - RIGHT-TO-USE LEASE LIABILITY
B97: Dr: Acct 0485 - ACCUMULATED AMORTIZATION - RIGHT-TO-USE LEASED LAND
B98: Dr: Acct 0479 - ACCUMULATED AMORTIZATION - RIGHT-TO-USE LEASED EQUIPMENT
B99: Dr: Acct 0486 - ACCUMULATED AMORTIZATION - RIGHT-TO-USE LEASED BUILDINGS
B100: =IF($F$7="Proprietary","Dr: Acct 0870 - SERVICES & CHARGES (MG ADJ)",VLOOKUP($F$9,'Drop Down Menus'!$F$2:$H$10,3,FALSE)) -> Dr: Acct 0820 - NAT RES & ENVIRON (GAAP ADJ)
A101: *Rpt 18 | C101: Cr: Acct 0476 - RIGHT-TO-USE LEASED LAND - AMORTIZABLE
A102: *Rpt 18 | C102: Cr: Acct 0478 - RIGHT-TO-USE LEASED EQUIPMENT - AMORTIZABLE
A103: *Rpt 18 | C103: Cr: Acct 0477 - RIGHT-TO-USE LEASED BUILDINGS - AMORTIZABLE
C104: =IF($F$7="Proprietary","Dr: Acct 0870 - SERVICES & CHARGES (MG ADJ)",VLOOKUP($F$9,'Drop Down Menus'!$F$2:$G$10,2,FALSE)) -> Cr: Acct 0820 - NAT RES & ENVIRON (GAAP ADJ)
B105: * THESE AMOUNTS SHOULD BE INCLUDED AS "DEDUCTIONS" ON REPORT 18. | J105: =SUM(J96:J104) -> 0 | K105: =SUM(K96:K104) -> 0 | L105: =IF(J105=K105,"<- Debits and Credits equal each other.","<- Debits and Credits do not equal each other.") -> <- Debits and Credits equal each other.
B106: ** This amount should be included in the deductions column on the LS-Lease Liability and LS-Check Figures Tabs.
A109: 10 | B109: Record lease modifications to increase in the RTU leased asset.
A110: *Rpt 18 | B110: Dr: Acct 0476 - RIGHT-TO-USE LEASED LAND - AMORTIZABLE
A111: *Rpt 18 | B111: Dr: Acct 0478 - RIGHT-TO-USE LEASED EQUIPMENT - AMORTIZABLE
A112: *Rpt 18 | B112: Dr: Acct 0477 - RIGHT-TO-USE LEASED BUILDINGS - AMORTIZABLE
A113: **LS LL/CF | C113: Cr: Acct 0691 - RIGHT-TO-USE LEASE LIABILITY
B114: * THESE AMOUNTS SHOULD BE INCLUDED AS "ADDITIONS" ON REPORT 18. | J114: =SUM(J110:J113) -> 0 | K114: =SUM(K110:K113) -> 0 | L114: =IF(J114=K114,"<- Debits and Credits equal each other.","<- Debits and Credits do not equal each other.") -> <- Debits and Credits equal each other.
B115: ** This amount should be included in the additions column on the LS-Lease Liability and LS-Check Figures Tabs.
D120: Informational - Ending Balances of Assets and Liabilities
K121: Debit (Credit)
D122: Acct 0476 - RIGHT-TO-USE LEASED LAND - AMORTIZABLE | K122: =J15+J39-K88-K101+J110 -> 0
D123: Acct 0478 - RIGHT-TO-USE LEASED EQUIPMENT - AMORTIZABLE | K123: =J16+J40-K89-K102+J111 -> 0
D124: Acct 0477 - RIGHT-TO-USE LEASED BUILDINGS - AMORTIZABLE | K124: =J17+J41-K90-K103+J112 -> 2074333
D125: Acct 0485 - ACCUMULATED AMORTIZATION - RIGHT-TO-USE LEASED LAND | K125: =-K20-K56+J85+J97 -> 0
...

Sheet LS-Fund 3237 Journal Entries
A1: Lessee-Type Contracts Fund-by-Fund Journal Entries Form (to be submitted to the SCO annually—one form per fund)
A2: Manually complete every yellow field in this worksheet—there are no automatically calculated data-entry cells in this worksheet.
A3: Fiscal Year: | F3: 2023–2024
A4: Organization Name: | F4: Department of Water Resources
A5: Organization Code (4-Digits): | F5: 3860
A6: Fund Number (4-Digits): | F6: 3237
A7: Fund Classification: | F7: Governmental
A8: Fund Type: | F8: Governmental Fund
A9: Functional Expense: | F9: =IFERROR(IF(F7="Proprietary","Proprietary Fund",VLOOKUP(F5,qryIndex02a!$A$2:$K$654,4,FALSE)),"Unidentified") -> RESOURCES
A12: Establish Beginning Balances (existing leases only)
A13: Entry #
A14: 0 | B14: Roll forward prior year right-to-use leases to record opening balances. | M14: Combined Lessee Templates | P14: From SCO BB List | S14: Difference
A15: *Rpt 18 | B15: Dr: Acct 0476 - RIGHT-TO-USE LEASED LAND - AMORTIZABLE | J15: =M15 -> 0 | S15: =P15-M15 -> 0
A16: *Rpt 18 | B16: Dr: Acct 0478 - RIGHT-TO-USE LEASED EQUIPMENT - AMORTIZABLE | J16: =M16 -> 0 | S16: =P16-M16 -> 0
A17: *Rpt 18 | B17: Dr: Acct 0477 - RIGHT-TO-USE LEASED BUILDINGS - AMORTIZABLE | J17: =M17 -> 14633 | M17: 14633 | P17: 12976 | S17: =P17-M17 -> -1657
B18: Dr: Acct 0950 - BEGINNING FUND BALANCE | J18: =P18 -> 276 | M18: 326 | P18: =IF(SUM($Q$20:$Q$23)>SUM($P$15:$P$17),SUM($Q$20:$Q$23)-SUM($P$15:$P$17),0) -> 276 | S18: =P18-M18 -> -50
B19: Dr: Acct 0952 - BEGINNING FUND ADJUSTMENT/PRIOR PERIOD ADJUSTMENT | J19: =IF(SUM($K$20:$K$24)>SUM($J$15:$J$18),SUM($K$20:$K$24)-SUM($J$15:$J$18),0) -> 36 | M19: 0 | S19: =P19-M19 -> 0
C20: Cr: Acct 0485 - ACCUMULATED AMORTIZATION - RIGHT-TO-USE LEASED LAND | K20: =N20 -> 0 | S20: =P20-M20 -> 0
C21: Cr: Acct 0479 - ACCUMULATED AMORTIZATION - RIGHT-TO-USE LEASED EQUIPMENT | K21: =N21 -> 0 | S21: =Q21-N21 -> 0
C22: Cr: Acct 0486 - ACCUMULATED AMORTIZATION - RIGHT-TO-USE LEASED BUILDINGS | K22: =N22 -> 4143 | N22: 4143 | Q22: 3674 | S22: =Q22-N22 -> -469
A23: **LS LL/CF | C23: Cr: Acct 0691 - RIGHT-TO-USE LEASE LIABILITY | K23: =N23 -> 10802 | N23: 10802 | Q23: 9578 | S23: =Q23-N23 -> -1224
C24: Cr: Acct 0950 - BEGINNING FUND BALANCE | K24: =Q24 -> 0 | N24: 14 | Q24: =IF(SUM($Q$20:$Q$23)<SUM($P$15:$P$17),-SUM($Q$20:$Q$23)+SUM($P$15:$P$17),0) -> 0 | S24: =Q24-N24 -> -14
C25: Cr: Acct 0952 - BEGINNING FUND ADJUSTMENT/PRIOR PERIOD ADJUSTMENT | K25: =IF(SUM($K$20:$K$24)<SUM($J$15:$J$18),-SUM($K$20:$K$24)+SUM($J$15:$J$18),0) -> 0 | N25: 0 | S25: =Q25-N25 -> 0
J26: =SUM(J15:J25) -> 14945 | K26: =SUM(K15:K25) -> 14945 | L26: =IF(J26=K26,"<- Debits and Credits equal each other.","<- Debits and Credits do not equal each other.") -> <- Debits and Credits equal each other.
B27: * THESE ASSET AMOUNTS SHOULD BE REPORTED AS BEGINNING BALANCES ON REPORT 18.
B28: ** This amount should be included in the beginning balance column on the LS-Lease Liability and LS-Check Figures Tabs.
A31: Record New Leases (new leases only)
A32: 1 | B32: Record lease contract commencement (fund-based entries only)
B33: Dr: Acct 0842 - CAPITAL OUTLAY | J33: 3389
C34: Cr: Acct 0789 - LEASE AND OTHER FINANCING PROCEEDS | K34: 3389
C35: =IF($F$7="Proprietary","Cr: Acct 0870 - SERVICES & CHARGES (MG ADJ)",VLOOKUP($F$9,'Drop Down Menus'!$F$2:$G$10,2,FALSE)) -> Cr: Acct 0820 - NAT RES & ENVIRON (GAAP ADJ)
J36: =SUM(J33:J35) -> 3389 | K36: =SUM(K33:K35) -> 3389 | L36: =IF(J36=K36,"<- Debits and Credits equal each other.","<- Debits and Credits do not equal each other.") -> <- Debits and Credits equal each other.
A38: 2 | B38: Record leased assets.
A39: *Rpt 18 | B39: Dr: Acct 0476 - RIGHT-TO-USE LEASED LAND - AMORTIZABLE
A40: *Rpt 18 | B40: Dr: Acct 0478 - RIGHT-TO-USE LEASED EQUIPMENT - AMORTIZABLE
A41: *Rpt 18 | B41: Dr: Acct 0477 - RIGHT-TO-USE LEASED BUILDINGS - AMORTIZABLE | J41: 3389
C42: Cr: Acct 0842 - CAPITAL OUTLAY | K42: 3389
B43: * THESE AMOUNTS SHOULD BE INCLUDED AS "ADDITIONS" ON REPORT 18. | J43: =SUM(J39:J42) -> 3389 | K43: =SUM(K39:K42) -> 3389 | L43: =IF(J43=K43,"<- Debits and Credits equal each other.","<- Debits and Credits do not equal each other.") -> <- Debits and Credits equal each other.
A46: 3 | B46: Replace proceeds from leases with right-to-use lease liability.
B47: Dr: Acct 0789 - LEASE AND OTHER FINANCING PROCEEDS | J47: 3389
A48: **LS LL/CF | C48: Cr: Acct 0691 - RIGHT-TO-USE LEASE LIABILITY | K48: 3389
J49: =SUM(J47:J48) -> 3389 | K49: =SUM(K47:K48) -> 3389 | L49: =IF(J49=K49,"<- Debits and Credits equal each other.","<- Debits and Credits do not equal each other.") -> <- Debits and Credits equal each other.
B50: ** This amount should be included in the additions column on the LS-Lease Liability and LS-Check Figures Tabs.
A53: Record Annual Activity (all leases)
A54: 4 | B54: Record amortization of the leased assets for the year.
B55: Dr: Acct 0875 - DEPRECIATION/AMORTIZATION | J55: 2219
C56: Cr: Acct 0485 - ACCUMULATED AMORTIZATION - RIGHT-TO-USE LEASED LAND
C57: Cr: Acct 0479 - ACCUMULATED AMORTIZATION - RIGHT-TO-USE LEASED EQUIPMENT
C58: Cr: Acct 0486 - ACCUMULATED AMORTIZATION - RIGHT-TO-USE LEASED BUILDINGS | K58: 2219
J59: =SUM(J55:J58) -> 2219 | K59: =SUM(K55:K58) -> 2219 | L59: =IF(J59=K59,"<- Debits and Credits equal each other.","<- Debits and Credits do not equal each other.") -> <- Debits and Credits equal each other.
A61: 5 | B61: Reclassify rents and leases exp. to lease contract principal and interest exp.
B62: Dr: Acct 0848 - DEBT SERVICE - PRINCIPAL LEASES | J62: 2017
B63: =IF(F7="Governmental","Dr: Acct 0851 - DEBT SERVICE - INTEREST LEASES","Dr: Acct 0894 - INTEREST EXPENSE AND FISCAL CHARGES") -> Dr: Acct 0851 - DEBT SERVICE - INTEREST LEASES | J63: 248
C64: =IF($F$7="Proprietary","Cr: Acct 0870 - SERVICES & CHARGES (MG ADJ)",VLOOKUP($F$9,'Drop Down Menus'!$F$2:$G$10,2,FALSE)) -> Cr: Acct 0820 - NAT RES & ENVIRON (GAAP ADJ) | K64: 2265
J65: =SUM(J62:J64) -> 2265 | K65: =SUM(K62:K64) -> 2265 | L65: =IF(J65=K65,"<- Debits and Credits equal each other.","<- Debits and Credits do not equal each other.") -> <- Debits and Credits equal each other.
A67: 6 | B67: Reduce lease contracts liability for total current year principal payments.
A68: **LS LL/CF | B68: Dr: Acct 0691 - RIGHT-TO-USE LEASE LIABILITY | J68: 2017
C69: Cr: Acct 0848 - DEBT SERVICE - PRINCIPAL LEASES | K69: 2017
J70: =SUM(J68:J69) -> 2017 | K70: =SUM(K68:K69) -> 2017 | L70: =IF(J70=K70,"<- Debits and Credits equal each other.","<- Debits and Credits do not equal each other.") -> <- Debits and Credits equal each other.
B71: ** This amount should be included in the deductions column on the LS-Lease Liability and LS-Check Figures Tabs.
A74: 7 | B74: Reclassify the principal amount due in the next FY to the current liability.
A75: **LS LL/CF | B75: Dr: Acct 0691 - RIGHT-TO-USE LEASE LIABILITY | J75: 2065
C76: Cr: Acct 0649 - RIGHT-TO-USE LEASE LIABILITY (CURRENT PORTION LT) | K76: 2065
B77: NOTE: This is an annual accrual. It is to be reversed at the start of the next fiscal year. SCO combines the current and non current amount in Entry #0 to reestablish the beginning balances. No action required. | J77: =SUM(J75:J76) -> 2065 | K77: =SUM(K75:K76) -> 2065 | L77: =IF(J77=K77,"<- Debits and Credits equal each other.","<- Debits and Credits do not equal each other.") -> <- Debits and Credits equal each other.
B80: ** This amount should be included in the due in one year column on the LS-Lease Liability and LS-Check Figures Tabs.
A83: Remove Lease Asset at the End of the Lease Term (only at the end of the lease term)
A84: 8 | B84: Record entry to write off the lease asset and accumulated amortization at the end of the lease term.
B85: Dr: Acct 0485 - ACCUMULATED AMORTIZATION - RIGHT-TO-USE LEASED LAND
B86: Dr: Acct 0479 - ACCUMULATED AMORTIZATION - RIGHT-TO-USE LEASED EQUIPMENT
B87: Dr: Acct 0486 - ACCUMULATED AMORTIZATION - RIGHT-TO-USE LEASED BUILDINGS | J87: 810
A88: *Rpt 18 | C88: Cr: Acct 0476 - RIGHT-TO-USE LEASED LAND - AMORTIZABLE
A89: *Rpt 18 | C89: Cr: Acct 0478 - RIGHT-TO-USE LEASED EQUIPMENT - AMORTIZABLE
A90: *Rpt 18 | C90: Cr: Acct 0477 - RIGHT-TO-USE LEASED BUILDINGS - AMORTIZABLE | K90: 810
B91: * THESE AMOUNTS SHOULD BE INCLUDED AS "DEDUCTIONS" ON REPORT 18. | J91: =SUM(J85:J90) -> 810 | K91: =SUM(K85:K90) -> 810 | L91: =IF(J91=K91,"<- Debits and Credits equal each other.","<- Debits and Credits do not equal each other.") -> <- Debits and Credits equal each other.
A94: Lease Remeasurement and Modifications (only if a significant modification occurred during the fiscal year)
A95: 9 | B95: Record early termination or lease modifications to decrease in the RTU leased asset.
A96: **LS LL/CF | B96: Dr: Acct 0691 - RIGHT-TO-USE LEASE LIABILITY
B97: Dr: Acct 0485 - ACCUMULATED AMORTIZATION - RIGHT-TO-USE LEASED LAND
B98: Dr: Acct 0479 - ACCUMULATED AMORTIZATION - RIGHT-TO-USE LEASED EQUIPMENT
B99: Dr: Acct 0486 - ACCUMULATED AMORTIZATION - RIGHT-TO-USE LEASED BUILDINGS
B100: =IF($F$7="Proprietary","Dr: Acct 0870 - SERVICES & CHARGES (MG ADJ)",VLOOKUP($F$9,'Drop Down Menus'!$F$2:$H$10,3,FALSE)) -> Dr: Acct 0820 - NAT RES & ENVIRON (GAAP ADJ)
A101: *Rpt 18 | C101: Cr: Acct 0476 - RIGHT-TO-USE LEASED LAND - AMORTIZABLE
A102: *Rpt 18 | C102: Cr: Acct 0478 - RIGHT-TO-USE LEASED EQUIPMENT - AMORTIZABLE
A103: *Rpt 18 | C103: Cr: Acct 0477 - RIGHT-TO-USE LEASED BUILDINGS - AMORTIZABLE
C104: =IF($F$7="Proprietary","Dr: Acct 0870 - SERVICES & CHARGES (MG ADJ)",VLOOKUP($F$9,'Drop Down Menus'!$F$2:$G$10,2,FALSE)) -> Cr: Acct 0820 - NAT RES & ENVIRON (GAAP ADJ)
B105: * THESE AMOUNTS SHOULD BE INCLUDED AS "DEDUCTIONS" ON REPORT 18. | J105: =SUM(J96:J104) -> 0 | K105: =SUM(K96:K104) -> 0 | L105: =IF(J105=K105,"<- Debits and Credits equal each other.","<- Debits and Credits do not equal each other.") -> <- Debits and Credits equal each other.
B106: ** This amount should be included in the deductions column on the LS-Lease Liability and LS-Check Figures Tabs.
A109: 10 | B109: Record lease modifications to increase in the RTU leased asset.
A110: *Rpt 18 | B110: Dr: Acct 0476 - RIGHT-TO-USE LEASED LAND - AMORTIZABLE
A111: *Rpt 18 | B111: Dr: Acct 0478 - RIGHT-TO-USE LEASED EQUIPMENT - AMORTIZABLE
A112: *Rpt 18 | B112: Dr: Acct 0477 - RIGHT-TO-USE LEASED BUILDINGS - AMORTIZABLE
A113: **LS LL/CF | C113: Cr: Acct 0691 - RIGHT-TO-USE LEASE LIABILITY
B114: * THESE AMOUNTS SHOULD BE INCLUDED AS "ADDITIONS" ON REPORT 18. | J114: =SUM(J110:J113) -> 0 | K114: =SUM(K110:K113) -> 0 | L114: =IF(J114=K114,"<- Debits and Credits equal each other.","<- Debits and Credits do not equal each other.") -> <- Debits and Credits equal each other.
B115: ** This amount should be included in the additions column on the LS-Lease Liability and LS-Check Figures Tabs.
D120: Informational - Ending Balances of Assets and Liabilities
K121: Debit (Credit)
D122: Acct 0476 - RIGHT-TO-USE LEASED LAND - AMORTIZABLE | K122: =J15+J39-K88-K101+J110 -> 0
D123: Acct 0478 - RIGHT-TO-USE LEASED EQUIPMENT - AMORTIZABLE | K123: =J16+J40-K89-K102+J111 -> 0
D124: Acct 0477 - RIGHT-TO-USE LEASED BUILDINGS - AMORTIZABLE | K124: =J17+J41-K90-K103+J112 -> 17212
D125: Acct 0485 - ACCUMULATED AMORTIZATION - RIGHT-TO-USE LEASED LAND | K125: =-K20-K56+J85+J97 -> 0
...

Sheet LS-Fund 3398 Journal Entries
A1: Lessee-Type Contracts Fund-by-Fund Journal Entries Form (to be submitted to the SCO annually—one form per fund)
A2: Manually complete every yellow field in this worksheet—there are no automatically calculated data-entry cells in this worksheet.
A3: Fiscal Year: | F3: 2023–2024
A4: Organization Name: | F4: Department of Water Resources
A5: Organization Code (4-Digits): | F5: 3860
A6: Fund Number (4-Digits): | F6: 3398
A7: Fund Classification: | F7: Governmental
A8: Fund Type: | F8: Governmental Fund
A9: Functional Expense: | F9: =IFERROR(IF(F7="Proprietary","Proprietary Fund",VLOOKUP(F5,qryIndex02a!$A$2:$K$654,4,FALSE)),"Unidentified") -> RESOURCES
A12: Establish Beginning Balances (existing leases only)
A13: Entry #
A14: 0 | B14: Roll forward prior year right-to-use leases to record opening balances. | M14: Combined Lessee Templates | P14: From SCO BB List | S14: Difference
A15: *Rpt 18 | B15: Dr: Acct 0476 - RIGHT-TO-USE LEASED LAND - AMORTIZABLE | J15: =M15 -> 0 | S15: =P15-M15 -> 0
A16: *Rpt 18 | B16: Dr: Acct 0478 - RIGHT-TO-USE LEASED EQUIPMENT - AMORTIZABLE | J16: =M16 -> 0 | S16: =P16-M16 -> 0
A17: *Rpt 18 | B17: Dr: Acct 0477 - RIGHT-TO-USE LEASED BUILDINGS - AMORTIZABLE | J17: =M17 -> 242977 | M17: 242977 | P17: 142721 | S17: =P17-M17 -> -100256
B18: Dr: Acct 0950 - BEGINNING FUND BALANCE | J18: =P18 -> 3049 | M18: 5420 | P18: =IF(SUM($Q$20:$Q$23)>SUM($P$15:$P$17),SUM($Q$20:$Q$23)-SUM($P$15:$P$17),0) -> 3049 | S18: =P18-M18 -> -2371
B19: Dr: Acct 0952 - BEGINNING FUND ADJUSTMENT/PRIOR PERIOD ADJUSTMENT | J19: =IF(SUM($K$20:$K$24)>SUM($J$15:$J$18),SUM($K$20:$K$24)-SUM($J$15:$J$18),0) -> 2141 | M19: 0 | S19: =P19-M19 -> 0
C20: Cr: Acct 0485 - ACCUMULATED AMORTIZATION - RIGHT-TO-USE LEASED LAND | K20: =N20 -> 0 | S20: =P20-M20 -> 0
C21: Cr: Acct 0479 - ACCUMULATED AMORTIZATION - RIGHT-TO-USE LEASED EQUIPMENT | K21: =N21 -> 0 | S21: =Q21-N21 -> 0
C22: Cr: Acct 0486 - ACCUMULATED AMORTIZATION - RIGHT-TO-USE LEASED BUILDINGS | K22: =N22 -> 68800 | N22: 68800 | Q22: 40412 | S22: =Q22-N22 -> -28388
A23: **LS LL/CF | C23: Cr: Acct 0691 - RIGHT-TO-USE LEASE LIABILITY | K23: =N23 -> 179367 | N23: 179367 | Q23: 105358 | S23: =Q23-N23 -> -74009
C24: Cr: Acct 0950 - BEGINNING FUND BALANCE | K24: =Q24 -> 0 | N24: 230 | Q24: =IF(SUM($Q$20:$Q$23)<SUM($P$15:$P$17),-SUM($Q$20:$Q$23)+SUM($P$15:$P$17),0) -> 0 | S24: =Q24-N24 -> -230
C25: Cr: Acct 0952 - BEGINNING FUND ADJUSTMENT/PRIOR PERIOD ADJUSTMENT | K25: =IF(SUM($K$20:$K$24)<SUM($J$15:$J$18),-SUM($K$20:$K$24)+SUM($J$15:$J$18),0) -> 0 | N25: 0 | S25: =Q25-N25 -> 0
J26: =SUM(J15:J25) -> 248167 | K26: =SUM(K15:K25) -> 248167 | L26: =IF(J26=K26,"<- Debits and Credits equal each other.","<- Debits and Credits do not equal each other.") -> <- Debits and Credits equal each other.
B27: * THESE ASSET AMOUNTS SHOULD BE REPORTED AS BEGINNING BALANCES ON REPORT 18.
B28: ** This amount should be included in the beginning balance column on the LS-Lease Liability and LS-Check Figures Tabs.
A31: Record New Leases (new leases only)
A32: 1 | B32: Record lease contract commencement (fund-based entries only)
B33: Dr: Acct 0842 - CAPITAL OUTLAY | J33: 56278
C34: Cr: Acct 0789 - LEASE AND OTHER FINANCING PROCEEDS | K34: 56278
C35: =IF($F$7="Proprietary","Cr: Acct 0870 - SERVICES & CHARGES (MG ADJ)",VLOOKUP($F$9,'Drop Down Menus'!$F$2:$G$10,2,FALSE)) -> Cr: Acct 0820 - NAT RES & ENVIRON (GAAP ADJ)
J36: =SUM(J33:J35) -> 56278 | K36: =SUM(K33:K35) -> 56278 | L36: =IF(J36=K36,"<- Debits and Credits equal each other.","<- Debits and Credits do not equal each other.") -> <- Debits and Credits equal each other.
A38: 2 | B38: Record leased assets.
A39: *Rpt 18 | B39: Dr: Acct 0476 - RIGHT-TO-USE LEASED LAND - AMORTIZABLE
A40: *Rpt 18 | B40: Dr: Acct 0478 - RIGHT-TO-USE LEASED EQUIPMENT - AMORTIZABLE
A41: *Rpt 18 | B41: Dr: Acct 0477 - RIGHT-TO-USE LEASED BUILDINGS - AMORTIZABLE | J41: 56278
C42: Cr: Acct 0842 - CAPITAL OUTLAY | K42: 56278
B43: * THESE AMOUNTS SHOULD BE INCLUDED AS "ADDITIONS" ON REPORT 18. | J43: =SUM(J39:J42) -> 56278 | K43: =SUM(K39:K42) -> 56278 | L43: =IF(J43=K43,"<- Debits and Credits equal each other.","<- Debits and Credits do not equal each other.") -> <- Debits and Credits equal each other.
A46: 3 | B46: Replace proceeds from leases with right-to-use lease liability.
B47: Dr: Acct 0789 - LEASE AND OTHER FINANCING PROCEEDS | J47: 56278
A48: **LS LL/CF | C48: Cr: Acct 0691 - RIGHT-TO-USE LEASE LIABILITY | K48: 56278
J49: =SUM(J47:J48) -> 56278 | K49: =SUM(K47:K48) -> 56278 | L49: =IF(J49=K49,"<- Debits and Credits equal each other.","<- Debits and Credits do not equal each other.") -> <- Debits and Credits equal each other.
B50: ** This amount should be included in the additions column on the LS-Lease Liability and LS-Check Figures Tabs.
A53: Record Annual Activity (all leases)
A54: 4 | B54: Record amortization of the leased assets for the year.
B55: Dr: Acct 0875 - DEPRECIATION/AMORTIZATION | J55: 36843
C56: Cr: Acct 0485 - ACCUMULATED AMORTIZATION - RIGHT-TO-USE LEASED LAND
C57: Cr: Acct 0479 - ACCUMULATED AMORTIZATION - RIGHT-TO-USE LEASED EQUIPMENT
C58: Cr: Acct 0486 - ACCUMULATED AMORTIZATION - RIGHT-TO-USE LEASED BUILDINGS | K58: 36843
J59: =SUM(J55:J58) -> 36843 | K59: =SUM(K55:K58) -> 36843 | L59: =IF(J59=K59,"<- Debits and Credits equal each other.","<- Debits and Credits do not equal each other.") -> <- Debits and Credits equal each other.
A61: 5 | B61: Reclassify rents and leases exp. to lease contract principal and interest exp.
B62: Dr: Acct 0848 - DEBT SERVICE - PRINCIPAL LEASES | J62: 33495
B63: =IF(F7="Governmental","Dr: Acct 0851 - DEBT SERVICE - INTEREST LEASES","Dr: Acct 0894 - INTEREST EXPENSE AND FISCAL CHARGES") -> Dr: Acct 0851 - DEBT SERVICE - INTEREST LEASES | J63: 4116
C64: =IF($F$7="Proprietary","Cr: Acct 0870 - SERVICES & CHARGES (MG ADJ)",VLOOKUP($F$9,'Drop Down Menus'!$F$2:$G$10,2,FALSE)) -> Cr: Acct 0820 - NAT RES & ENVIRON (GAAP ADJ) | K64: 37612
J65: =SUM(J62:J64) -> 37611 | K65: =SUM(K62:K64) -> 37612 | L65: =IF(J65=K65,"<- Debits and Credits equal each other.","<- Debits and Credits do not equal each other.") -> <- Debits and Credits do not equal each other.
A67: 6 | B67: Reduce lease contracts liability for total current year principal payments.
A68: **LS LL/CF | B68: Dr: Acct 0691 - RIGHT-TO-USE LEASE LIABILITY | J68: 33495
C69: Cr: Acct 0848 - DEBT SERVICE - PRINCIPAL LEASES | K69: 33495
J70: =SUM(J68:J69) -> 33495 | K70: =SUM(K68:K69) -> 33495 | L70: =IF(J70=K70,"<- Debits and Credits equal each other.","<- Debits and Credits do not equal each other.") -> <- Debits and Credits equal each other.
B71: ** This amount should be included in the deductions column on the LS-Lease Liability and LS-Check Figures Tabs.
A74: 7 | B74: Reclassify the principal amount due in the next FY to the current liability.
A75: **LS LL/CF | B75: Dr: Acct 0691 - RIGHT-TO-USE LEASE LIABILITY | J75: 34284
C76: Cr: Acct 0649 - RIGHT-TO-USE LEASE LIABILITY (CURRENT PORTION LT) | K76: 34284
B77: NOTE: This is an annual accrual. It is to be reversed at the start of the next fiscal year. SCO combines the current and non current amount in Entry #0 to reestablish the beginning balances. No action required. | J77: =SUM(J75:J76) -> 34284 | K77: =SUM(K75:K76) -> 34284 | L77: =IF(J77=K77,"<- Debits and Credits equal each other.","<- Debits and Credits do not equal each other.") -> <- Debits and Credits equal each other.
B80: ** This amount should be included in the due in one year column on the LS-Lease Liability and LS-Check Figures Tabs.
A83: Remove Lease Asset at the End of the Lease Term (only at the end of the lease term)
A84: 8 | B84: Record entry to write off the lease asset and accumulated amortization at the end of the lease term.
B85: Dr: Acct 0485 - ACCUMULATED AMORTIZATION - RIGHT-TO-USE LEASED LAND
B86: Dr: Acct 0479 - ACCUMULATED AMORTIZATION - RIGHT-TO-USE LEASED EQUIPMENT
B87: Dr: Acct 0486 - ACCUMULATED AMORTIZATION - RIGHT-TO-USE LEASED BUILDINGS | J87: 13455
A88: *Rpt 18 | C88: Cr: Acct 0476 - RIGHT-TO-USE LEASED LAND - AMORTIZABLE
A89: *Rpt 18 | C89: Cr: Acct 0478 - RIGHT-TO-USE LEASED EQUIPMENT - AMORTIZABLE
A90: *Rpt 18 | C90: Cr: Acct 0477 - RIGHT-TO-USE LEASED BUILDINGS - AMORTIZABLE | K90: 13455
B91: * THESE AMOUNTS SHOULD BE INCLUDED AS "DEDUCTIONS" ON REPORT 18. | J91: =SUM(J85:J90) -> 13455 | K91: =SUM(K85:K90) -> 13455 | L91: =IF(J91=K91,"<- Debits and Credits equal each other.","<- Debits and Credits do not equal each other.") -> <- Debits and Credits equal each other.
A94: Lease Remeasurement and Modifications (only if a significant modification occurred during the fiscal year)
A95: 9 | B95: Record early termination or lease modifications to decrease in the RTU leased asset.
A96: **LS LL/CF | B96: Dr: Acct 0691 - RIGHT-TO-USE LEASE LIABILITY
B97: Dr: Acct 0485 - ACCUMULATED AMORTIZATION - RIGHT-TO-USE LEASED LAND
B98: Dr: Acct 0479 - ACCUMULATED AMORTIZATION - RIGHT-TO-USE LEASED EQUIPMENT
B99: Dr: Acct 0486 - ACCUMULATED AMORTIZATION - RIGHT-TO-USE LEASED BUILDINGS
B100: =IF($F$7="Proprietary","Dr: Acct 0870 - SERVICES & CHARGES (MG ADJ)",VLOOKUP($F$9,'Drop Down Menus'!$F$2:$H$10,3,FALSE)) -> Dr: Acct 0820 - NAT RES & ENVIRON (GAAP ADJ)
A101: *Rpt 18 | C101: Cr: Acct 0476 - RIGHT-TO-USE LEASED LAND - AMORTIZABLE
A102: *Rpt 18 | C102: Cr: Acct 0478 - RIGHT-TO-USE LEASED EQUIPMENT - AMORTIZABLE
A103: *Rpt 18 | C103: Cr: Acct 0477 - RIGHT-TO-USE LEASED BUILDINGS - AMORTIZABLE
C104: =IF($F$7="Proprietary","Dr: Acct 0870 - SERVICES & CHARGES (MG ADJ)",VLOOKUP($F$9,'Drop Down Menus'!$F$2:$G$10,2,FALSE)) -> Cr: Acct 0820 - NAT RES & ENVIRON (GAAP ADJ)
B105: * THESE AMOUNTS SHOULD BE INCLUDED AS "DEDUCTIONS" ON REPORT 18. | J105: =SUM(J96:J104) -> 0 | K105: =SUM(K96:K104) -> 0 | L105: =IF(J105=K105,"<- Debits and Credits equal each other.","<- Debits and Credits do not equal each other.") -> <- Debits and Credits equal each other.
B106: ** This amount should be included in the deductions column on the LS-Lease Liability and LS-Check Figures Tabs.
A109: 10 | B109: Record lease modifications to increase in the RTU leased asset.
A110: *Rpt 18 | B110: Dr: Acct 0476 - RIGHT-TO-USE LEASED LAND - AMORTIZABLE
A111: *Rpt 18 | B111: Dr: Acct 0478 - RIGHT-TO-USE LEASED EQUIPMENT - AMORTIZABLE
A112: *Rpt 18 | B112: Dr: Acct 0477 - RIGHT-TO-USE LEASED BUILDINGS - AMORTIZABLE
A113: **LS LL/CF | C113: Cr: Acct 0691 - RIGHT-TO-USE LEASE LIABILITY
B114: * THESE AMOUNTS SHOULD BE INCLUDED AS "ADDITIONS" ON REPORT 18. | J114: =SUM(J110:J113) -> 0 | K114: =SUM(K110:K113) -> 0 | L114: =IF(J114=K114,"<- Debits and Credits equal each other.","<- Debits and Credits do not equal each other.") -> <- Debits and Credits equal each other.
B115: ** This amount should be included in the additions column on the LS-Lease Liability and LS-Check Figures Tabs.
D120: Informational - Ending Balances of Assets and Liabilities
K121: Debit (Credit)
D122: Acct 0476 - RIGHT-TO-USE LEASED LAND - AMORTIZABLE | K122: =J15+J39-K88-K101+J110 -> 0
D123: Acct 0478 - RIGHT-TO-USE LEASED EQUIPMENT - AMORTIZABLE | K123: =J16+J40-K89-K102+J111 -> 0
D124: Acct 0477 - RIGHT-TO-USE LEASED BUILDINGS - AMORTIZABLE | K124: =J17+J41-K90-K103+J112 -> 285800
D125: Acct 0485 - ACCUMULATED AMORTIZATION - RIGHT-TO-USE LEASED LAND | K125: =-K20-K56+J85+J97 -> 0
...

Sheet LS-Fund 3413 Journal Entries
A1: Lessee-Type Contracts Fund-by-Fund Journal Entries Form (to be submitted to the SCO annually—one form per fund)
A2: Manually complete every yellow field in this worksheet—there are no automatically calculated data-entry cells in this worksheet.
A3: Fiscal Year: | F3: 2023–2024
A4: Organization Name: | F4: Department of Water Resources
A5: Organization Code (4-Digits): | F5: 3860
A6: Fund Number (4-Digits): | F6: 3413
A7: Fund Classification: | F7: Governmental
A8: Fund Type: | F8: Governmental Fund
A9: Functional Expense: | F9: =IFERROR(IF(F7="Proprietary","Proprietary Fund",VLOOKUP(F5,qryIndex02a!$A$2:$K$654,4,FALSE)),"Unidentified") -> RESOURCES
A12: Establish Beginning Balances (existing leases only)
A13: Entry #
A14: 0 | B14: Roll forward prior year right-to-use leases to record opening balances. | M14: Combined Lessee Templates | P14: From SCO BB List | S14: Difference
A15: *Rpt 18 | B15: Dr: Acct 0476 - RIGHT-TO-USE LEASED LAND - AMORTIZABLE | J15: =M15 -> 0 | S15: =P15-M15 -> 0
A16: *Rpt 18 | B16: Dr: Acct 0478 - RIGHT-TO-USE LEASED EQUIPMENT - AMORTIZABLE | J16: =M16 -> 0 | S16: =P16-M16 -> 0
A17: *Rpt 18 | B17: Dr: Acct 0477 - RIGHT-TO-USE LEASED BUILDINGS - AMORTIZABLE | J17: =M17 -> 76804 | M17: 76804 | S17: =P17-M17 -> -76804
B18: Dr: Acct 0950 - BEGINNING FUND BALANCE | J18: =P18 -> 0 | M18: 1713 | P18: =IF(SUM($Q$20:$Q$23)>SUM($P$15:$P$17),SUM($Q$20:$Q$23)-SUM($P$15:$P$17),0) -> 0 | S18: =P18-M18 -> -1713
B19: Dr: Acct 0952 - BEGINNING FUND ADJUSTMENT/PRIOR PERIOD ADJUSTMENT | J19: =IF(SUM($K$20:$K$24)>SUM($J$15:$J$18),SUM($K$20:$K$24)-SUM($J$15:$J$18),0) -> 1640 | M19: 0 | S19: =P19-M19 -> 0
C20: Cr: Acct 0485 - ACCUMULATED AMORTIZATION - RIGHT-TO-USE LEASED LAND | K20: =N20 -> 0 | S20: =P20-M20 -> 0
C21: Cr: Acct 0479 - ACCUMULATED AMORTIZATION - RIGHT-TO-USE LEASED EQUIPMENT | K21: =N21 -> 0 | S21: =Q21-N21 -> 0
C22: Cr: Acct 0486 - ACCUMULATED AMORTIZATION - RIGHT-TO-USE LEASED BUILDINGS | K22: =N22 -> 21747 | N22: 21747 | S22: =Q22-N22 -> -21747
A23: **LS LL/CF | C23: Cr: Acct 0691 - RIGHT-TO-USE LEASE LIABILITY | K23: =N23 -> 56697 | N23: 56697 | S23: =Q23-N23 -> -56697
C24: Cr: Acct 0950 - BEGINNING FUND BALANCE | K24: =Q24 -> 0 | N24: 73 | Q24: =IF(SUM($Q$20:$Q$23)<SUM($P$15:$P$17),-SUM($Q$20:$Q$23)+SUM($P$15:$P$17),0) -> 0 | S24: =Q24-N24 -> -73
C25: Cr: Acct 0952 - BEGINNING FUND ADJUSTMENT/PRIOR PERIOD ADJUSTMENT | K25: =IF(SUM($K$20:$K$24)<SUM($J$15:$J$18),-SUM($K$20:$K$24)+SUM($J$15:$J$18),0) -> 0 | N25: 0 | S25: =Q25-N25 -> 0
J26: =SUM(J15:J25) -> 78444 | K26: =SUM(K15:K25) -> 78444 | L26: =IF(J26=K26,"<- Debits and Credits equal each other.","<- Debits and Credits do not equal each other.") -> <- Debits and Credits equal each other.
B27: * THESE ASSET AMOUNTS SHOULD BE REPORTED AS BEGINNING BALANCES ON REPORT 18.
B28: ** This amount should be included in the beginning balance column on the LS-Lease Liability and LS-Check Figures Tabs.
A31: Record New Leases (new leases only)
A32: 1 | B32: Record lease contract commencement (fund-based entries only)
B33: Dr: Acct 0842 - CAPITAL OUTLAY | J33: 17789
C34: Cr: Acct 0789 - LEASE AND OTHER FINANCING PROCEEDS | K34: 17789
C35: =IF($F$7="Proprietary","Cr: Acct 0870 - SERVICES & CHARGES (MG ADJ)",VLOOKUP($F$9,'Drop Down Menus'!$F$2:$G$10,2,FALSE)) -> Cr: Acct 0820 - NAT RES & ENVIRON (GAAP ADJ)
J36: =SUM(J33:J35) -> 17789 | K36: =SUM(K33:K35) -> 17789 | L36: =IF(J36=K36,"<- Debits and Credits equal each other.","<- Debits and Credits do not equal each other.") -> <- Debits and Credits equal each other.
A38: 2 | B38: Record leased assets.
A39: *Rpt 18 | B39: Dr: Acct 0476 - RIGHT-TO-USE LEASED LAND - AMORTIZABLE
A40: *Rpt 18 | B40: Dr: Acct 0478 - RIGHT-TO-USE LEASED EQUIPMENT - AMORTIZABLE
A41: *Rpt 18 | B41: Dr: Acct 0477 - RIGHT-TO-USE LEASED BUILDINGS - AMORTIZABLE | J41: 17789
C42: Cr: Acct 0842 - CAPITAL OUTLAY | K42: 17789
B43: * THESE AMOUNTS SHOULD BE INCLUDED AS "ADDITIONS" ON REPORT 18. | J43: =SUM(J39:J42) -> 17789 | K43: =SUM(K39:K42) -> 17789 | L43: =IF(J43=K43,"<- Debits and Credits equal each other.","<- Debits and Credits do not equal each other.") -> <- Debits and Credits equal each other.
A46: 3 | B46: Replace proceeds from leases with right-to-use lease liability.
B47: Dr: Acct 0789 - LEASE AND OTHER FINANCING PROCEEDS | J47: 17789
A48: **LS LL/CF | C48: Cr: Acct 0691 - RIGHT-TO-USE LEASE LIABILITY | K48: 17789
J49: =SUM(J47:J48) -> 17789 | K49: =SUM(K47:K48) -> 17789 | L49: =IF(J49=K49,"<- Debits and Credits equal each other.","<- Debits and Credits do not equal each other.") -> <- Debits and Credits equal each other.
B50: ** This amount should be included in the additions column on the LS-Lease Liability and LS-Check Figures Tabs.
A53: Record Annual Activity (all leases)
A54: 4 | B54: Record amortization of the leased assets for the year.
B55: Dr: Acct 0875 - DEPRECIATION/AMORTIZATION | J55: 11646
C56: Cr: Acct 0485 - ACCUMULATED AMORTIZATION - RIGHT-TO-USE LEASED LAND
C57: Cr: Acct 0479 - ACCUMULATED AMORTIZATION - RIGHT-TO-USE LEASED EQUIPMENT
C58: Cr: Acct 0486 - ACCUMULATED AMORTIZATION - RIGHT-TO-USE LEASED BUILDINGS | K58: 11646
J59: =SUM(J55:J58) -> 11646 | K59: =SUM(K55:K58) -> 11646 | L59: =IF(J59=K59,"<- Debits and Credits equal each other.","<- Debits and Credits do not equal each other.") -> <- Debits and Credits equal each other.
A61: 5 | B61: Reclassify rents and leases exp. to lease contract principal and interest exp.
B62: Dr: Acct 0848 - DEBT SERVICE - PRINCIPAL LEASES | J62: 11933
B63: =IF(F7="Governmental","Dr: Acct 0851 - DEBT SERVICE - INTEREST LEASES","Dr: Acct 0894 - INTEREST EXPENSE AND FISCAL CHARGES") -> Dr: Acct 0851 - DEBT SERVICE - INTEREST LEASES | J63: 1301
C64: =IF($F$7="Proprietary","Cr: Acct 0870 - SERVICES & CHARGES (MG ADJ)",VLOOKUP($F$9,'Drop Down Menus'!$F$2:$G$10,2,FALSE)) -> Cr: Acct 0820 - NAT RES & ENVIRON (GAAP ADJ) | K64: 13234
J65: =SUM(J62:J64) -> 13234 | K65: =SUM(K62:K64) -> 13234 | L65: =IF(J65=K65,"<- Debits and Credits equal each other.","<- Debits and Credits do not equal each other.") -> <- Debits and Credits equal each other.
A67: 6 | B67: Reduce lease contracts liability for total current year principal payments.
A68: **LS LL/CF | B68: Dr: Acct 0691 - RIGHT-TO-USE LEASE LIABILITY | J68: 11933
C69: Cr: Acct 0848 - DEBT SERVICE - PRINCIPAL LEASES | K69: 11933
J70: =SUM(J68:J69) -> 11933 | K70: =SUM(K68:K69) -> 11933 | L70: =IF(J70=K70,"<- Debits and Credits equal each other.","<- Debits and Credits do not equal each other.") -> <- Debits and Credits equal each other.
B71: ** This amount should be included in the deductions column on the LS-Lease Liability and LS-Check Figures Tabs.
A74: 7 | B74: Reclassify the principal amount due in the next FY to the current liability.
A75: **LS LL/CF | B75: Dr: Acct 0691 - RIGHT-TO-USE LEASE LIABILITY | J75: 10837
C76: Cr: Acct 0649 - RIGHT-TO-USE LEASE LIABILITY (CURRENT PORTION LT) | K76: 10837
B77: NOTE: This is an annual accrual. It is to be reversed at the start of the next fiscal year. SCO combines the current and non current amount in Entry #0 to reestablish the beginning balances. No action required. | J77: =SUM(J75:J76) -> 10837 | K77: =SUM(K75:K76) -> 10837 | L77: =IF(J77=K77,"<- Debits and Credits equal each other.","<- Debits and Credits do not equal each other.") -> <- Debits and Credits equal each other.
B80: ** This amount should be included in the due in one year column on the LS-Lease Liability and LS-Check Figures Tabs.
A83: Remove Lease Asset at the End of the Lease Term (only at the end of the lease term)
A84: 8 | B84: Record entry to write off the lease asset and accumulated amortization at the end of the lease term.
B85: Dr: Acct 0485 - ACCUMULATED AMORTIZATION - RIGHT-TO-USE LEASED LAND
B86: Dr: Acct 0479 - ACCUMULATED AMORTIZATION - RIGHT-TO-USE LEASED EQUIPMENT
B87: Dr: Acct 0486 - ACCUMULATED AMORTIZATION - RIGHT-TO-USE LEASED BUILDINGS | J87: 4253
A88: *Rpt 18 | C88: Cr: Acct 0476 - RIGHT-TO-USE LEASED LAND - AMORTIZABLE
A89: *Rpt 18 | C89: Cr: Acct 0478 - RIGHT-TO-USE LEASED EQUIPMENT - AMORTIZABLE
A90: *Rpt 18 | C90: Cr: Acct 0477 - RIGHT-TO-USE LEASED BUILDINGS - AMORTIZABLE | K90: 4253
B91: * THESE AMOUNTS SHOULD BE INCLUDED AS "DEDUCTIONS" ON REPORT 18. | J91: =SUM(J85:J90) -> 4253 | K91: =SUM(K85:K90) -> 4253 | L91: =IF(J91=K91,"<- Debits and Credits equal each other.","<- Debits and Credits do not equal each other.") -> <- Debits and Credits equal each other.
A94: Lease Remeasurement and Modifications (only if a significant modification occurred during the fiscal year)
A95: 9 | B95: Record early termination or lease modifications to decrease in the RTU leased asset.
A96: **LS LL/CF | B96: Dr: Acct 0691 - RIGHT-TO-USE LEASE LIABILITY
B97: Dr: Acct 0485 - ACCUMULATED AMORTIZATION - RIGHT-TO-USE LEASED LAND
B98: Dr: Acct 0479 - ACCUMULATED AMORTIZATION - RIGHT-TO-USE LEASED EQUIPMENT
B99: Dr: Acct 0486 - ACCUMULATED AMORTIZATION - RIGHT-TO-USE LEASED BUILDINGS
B100: =IF($F$7="Proprietary","Dr: Acct 0870 - SERVICES & CHARGES (MG ADJ)",VLOOKUP($F$9,'Drop Down Menus'!$F$2:$H$10,3,FALSE)) -> Dr: Acct 0820 - NAT RES & ENVIRON (GAAP ADJ)
A101: *Rpt 18 | C101: Cr: Acct 0476 - RIGHT-TO-USE LEASED LAND - AMORTIZABLE
A102: *Rpt 18 | C102: Cr: Acct 0478 - RIGHT-TO-USE LEASED EQUIPMENT - AMORTIZABLE
A103: *Rpt 18 | C103: Cr: Acct 0477 - RIGHT-TO-USE LEASED BUILDINGS - AMORTIZABLE
C104: =IF($F$7="Proprietary","Dr: Acct 0870 - SERVICES & CHARGES (MG ADJ)",VLOOKUP($F$9,'Drop Down Menus'!$F$2:$G$10,2,FALSE)) -> Cr: Acct 0820 - NAT RES & ENVIRON (GAAP ADJ)
B105: * THESE AMOUNTS SHOULD BE INCLUDED AS "DEDUCTIONS" ON REPORT 18. | J105: =SUM(J96:J104) -> 0 | K105: =SUM(K96:K104) -> 0 | L105: =IF(J105=K105,"<- Debits and Credits equal each other.","<- Debits and Credits do not equal each other.") -> <- Debits and Credits equal each other.
B106: ** This amount should be included in the deductions column on the LS-Lease Liability and LS-Check Figures Tabs.
A109: 10 | B109: Record lease modifications to increase in the RTU leased asset.
A110: *Rpt 18 | B110: Dr: Acct 0476 - RIGHT-TO-USE LEASED LAND - AMORTIZABLE
A111: *Rpt 18 | B111: Dr: Acct 0478 - RIGHT-TO-USE LEASED EQUIPMENT - AMORTIZABLE
A112: *Rpt 18 | B112: Dr: Acct 0477 - RIGHT-TO-USE LEASED BUILDINGS - AMORTIZABLE
A113: **LS LL/CF | C113: Cr: Acct 0691 - RIGHT-TO-USE LEASE LIABILITY
B114: * THESE AMOUNTS SHOULD BE INCLUDED AS "ADDITIONS" ON REPORT 18. | J114: =SUM(J110:J113) -> 0 | K114: =SUM(K110:K113) -> 0 | L114: =IF(J114=K114,"<- Debits and Credits equal each other.","<- Debits and Credits do not equal each other.") -> <- Debits and Credits equal each other.
B115: ** This amount should be included in the additions column on the LS-Lease Liability and LS-Check Figures Tabs.
D120: Informational - Ending Balances of Assets and Liabilities
K121: Debit (Credit)
D122: Acct 0476 - RIGHT-TO-USE LEASED LAND - AMORTIZABLE | K122: =J15+J39-K88-K101+J110 -> 0
D123: Acct 0478 - RIGHT-TO-USE LEASED EQUIPMENT - AMORTIZABLE | K123: =J16+J40-K89-K102+J111 -> 0
D124: Acct 0477 - RIGHT-TO-USE LEASED BUILDINGS - AMORTIZABLE | K124: =J17+J41-K90-K103+J112 -> 90340
D125: Acct 0485 - ACCUMULATED AMORTIZATION - RIGHT-TO-USE LEASED LAND | K125: =-K20-K56+J85+J97 -> 0
...

Sheet LS-Fund 6001 Journal Entries
A1: Lessee-Type Contracts Fund-by-Fund Journal Entries Form (to be submitted to the SCO annually—one form per fund)
A2: Manually complete every yellow field in this worksheet—there are no automatically calculated data-entry cells in this worksheet.
A3: Fiscal Year: | F3: 2023–2024
A4: Organization Name: | F4: Department of Water Resources
A5: Organization Code (4-Digits): | F5: 3860
A6: Fund Number (4-Digits): | F6: 6001
A7: Fund Classification: | F7: Governmental
A8: Fund Type: | F8: Governmental Fund
A9: Functional Expense: | F9: =IFERROR(IF(F7="Proprietary","Proprietary Fund",VLOOKUP(F5,qryIndex02a!$A$2:$K$654,4,FALSE)),"Unidentified") -> RESOURCES
A12: Establish Beginning Balances (existing leases only)
A13: Entry #
A14: 0 | B14: Roll forward prior year right-to-use leases to record opening balances. | M14: Combined Lessee Templates | P14: From SCO BB List | S14: Difference
A15: *Rpt 18 | B15: Dr: Acct 0476 - RIGHT-TO-USE LEASED LAND - AMORTIZABLE | J15: =M15 -> 0 | S15: =P15-M15 -> 0
A16: *Rpt 18 | B16: Dr: Acct 0478 - RIGHT-TO-USE LEASED EQUIPMENT - AMORTIZABLE | J16: =M16 -> 0 | S16: =P16-M16 -> 0
A17: *Rpt 18 | B17: Dr: Acct 0477 - RIGHT-TO-USE LEASED BUILDINGS - AMORTIZABLE | J17: =M17 -> 0 | P17: 45411 | S17: =P17-M17 -> 45411
B18: Dr: Acct 0950 - BEGINNING FUND BALANCE | J18: =P18 -> 970 | P18: =IF(SUM($Q$20:$Q$23)>SUM($P$15:$P$17),SUM($Q$20:$Q$23)-SUM($P$15:$P$17),0) -> 970 | S18: =P18-M18 -> 970
B19: Dr: Acct 0952 - BEGINNING FUND ADJUSTMENT/PRIOR PERIOD ADJUSTMENT | J19: =IF(SUM($K$20:$K$24)>SUM($J$15:$J$18),SUM($K$20:$K$24)-SUM($J$15:$J$18),0) -> 0 | S19: =P19-M19 -> 0
C20: Cr: Acct 0485 - ACCUMULATED AMORTIZATION - RIGHT-TO-USE LEASED LAND | K20: =N20 -> 0 | S20: =P20-M20 -> 0
C21: Cr: Acct 0479 - ACCUMULATED AMORTIZATION - RIGHT-TO-USE LEASED EQUIPMENT | K21: =N21 -> 0 | S21: =Q21-N21 -> 0
C22: Cr: Acct 0486 - ACCUMULATED AMORTIZATION - RIGHT-TO-USE LEASED BUILDINGS | K22: =N22 -> 0 | Q22: 12858 | S22: =Q22-N22 -> 12858
A23: **LS LL/CF | C23: Cr: Acct 0691 - RIGHT-TO-USE LEASE LIABILITY | K23: =N23 -> 0 | Q23: 33523 | S23: =Q23-N23 -> 33523
C24: Cr: Acct 0950 - BEGINNING FUND BALANCE | K24: =Q24 -> 0 | Q24: =IF(SUM($Q$20:$Q$23)<SUM($P$15:$P$17),-SUM($Q$20:$Q$23)+SUM($P$15:$P$17),0) -> 0 | S24: =Q24-N24 -> 0
C25: Cr: Acct 0952 - BEGINNING FUND ADJUSTMENT/PRIOR PERIOD ADJUSTMENT | K25: =IF(SUM($K$20:$K$24)<SUM($J$15:$J$18),-SUM($K$20:$K$24)+SUM($J$15:$J$18),0) -> 970 | S25: =Q25-N25 -> 0
J26: =SUM(J15:J25) -> 970 | K26: =SUM(K15:K25) -> 970 | L26: =IF(J26=K26,"<- Debits and Credits equal each other.","<- Debits and Credits do not equal each other.") -> <- Debits and Credits equal each other.
B27: * THESE ASSET AMOUNTS SHOULD BE REPORTED AS BEGINNING BALANCES ON REPORT 18.
B28: ** This amount should be included in the beginning balance column on the LS-Lease Liability and LS-Check Figures Tabs.
A31: Record New Leases (new leases only)
A32: 1 | B32: Record lease contract commencement (fund-based entries only)
B33: Dr: Acct 0842 - CAPITAL OUTLAY
C34: Cr: Acct 0789 - LEASE AND OTHER FINANCING PROCEEDS
C35: =IF($F$7="Proprietary","Cr: Acct 0870 - SERVICES & CHARGES (MG ADJ)",VLOOKUP($F$9,'Drop Down Menus'!$F$2:$G$10,2,FALSE)) -> Cr: Acct 0820 - NAT RES & ENVIRON (GAAP ADJ)
J36: =SUM(J33:J35) -> 0 | K36: =SUM(K33:K35) -> 0 | L36: =IF(J36=K36,"<- Debits and Credits equal each other.","<- Debits and Credits do not equal each other.") -> <- Debits and Credits equal each other.
A38: 2 | B38: Record leased assets.
A39: *Rpt 18 | B39: Dr: Acct 0476 - RIGHT-TO-USE LEASED LAND - AMORTIZABLE
A40: *Rpt 18 | B40: Dr: Acct 0478 - RIGHT-TO-USE LEASED EQUIPMENT - AMORTIZABLE
A41: *Rpt 18 | B41: Dr: Acct 0477 - RIGHT-TO-USE LEASED BUILDINGS - AMORTIZABLE
C42: Cr: Acct 0842 - CAPITAL OUTLAY
B43: * THESE AMOUNTS SHOULD BE INCLUDED AS "ADDITIONS" ON REPORT 18. | J43: =SUM(J39:J42) -> 0 | K43: =SUM(K39:K42) -> 0 | L43: =IF(J43=K43,"<- Debits and Credits equal each other.","<- Debits and Credits do not equal each other.") -> <- Debits and Credits equal each other.
A46: 3 | B46: Replace proceeds from leases with right-to-use lease liability.
B47: Dr: Acct 0789 - LEASE AND OTHER FINANCING PROCEEDS
A48: **LS LL/CF | C48: Cr: Acct 0691 - RIGHT-TO-USE LEASE LIABILITY
J49: =SUM(J47:J48) -> 0 | K49: =SUM(K47:K48) -> 0 | L49: =IF(J49=K49,"<- Debits and Credits equal each other.","<- Debits and Credits do not equal each other.") -> <- Debits and Credits equal each other.
B50: ** This amount should be included in the additions column on the LS-Lease Liability and LS-Check Figures Tabs.
A53: Record Annual Activity (all leases)
A54: 4 | B54: Record amortization of the leased assets for the year.
B55: Dr: Acct 0875 - DEPRECIATION/AMORTIZATION
C56: Cr: Acct 0485 - ACCUMULATED AMORTIZATION - RIGHT-TO-USE LEASED LAND
C57: Cr: Acct 0479 - ACCUMULATED AMORTIZATION - RIGHT-TO-USE LEASED EQUIPMENT
C58: Cr: Acct 0486 - ACCUMULATED AMORTIZATION - RIGHT-TO-USE LEASED BUILDINGS
J59: =SUM(J55:J58) -> 0 | K59: =SUM(K55:K58) -> 0 | L59: =IF(J59=K59,"<- Debits and Credits equal each other.","<- Debits and Credits do not equal each other.") -> <- Debits and Credits equal each other.
A61: 5 | B61: Reclassify rents and leases exp. to lease contract principal and interest exp.
B62: Dr: Acct 0848 - DEBT SERVICE - PRINCIPAL LEASES
B63: =IF(F7="Governmental","Dr: Acct 0851 - DEBT SERVICE - INTEREST LEASES","Dr: Acct 0894 - INTEREST EXPENSE AND FISCAL CHARGES") -> Dr: Acct 0851 - DEBT SERVICE - INTEREST LEASES
C64: =IF($F$7="Proprietary","Cr: Acct 0870 - SERVICES & CHARGES (MG ADJ)",VLOOKUP($F$9,'Drop Down Menus'!$F$2:$G$10,2,FALSE)) -> Cr: Acct 0820 - NAT RES & ENVIRON (GAAP ADJ)
J65: =SUM(J62:J64) -> 0 | K65: =SUM(K62:K64) -> 0 | L65: =IF(J65=K65,"<- Debits and Credits equal each other.","<- Debits and Credits do not equal each other.") -> <- Debits and Credits equal each other.
A67: 6 | B67: Reduce lease contracts liability for total current year principal payments.
A68: **LS LL/CF | B68: Dr: Acct 0691 - RIGHT-TO-USE LEASE LIABILITY
C69: Cr: Acct 0848 - DEBT SERVICE - PRINCIPAL LEASES
J70: =SUM(J68:J69) -> 0 | K70: =SUM(K68:K69) -> 0 | L70: =IF(J70=K70,"<- Debits and Credits equal each other.","<- Debits and Credits do not equal each other.") -> <- Debits and Credits equal each other.
B71: ** This amount should be included in the deductions column on the LS-Lease Liability and LS-Check Figures Tabs.
A74: 7 | B74: Reclassify the principal amount due in the next FY to the current liability.
A75: **LS LL/CF | B75: Dr: Acct 0691 - RIGHT-TO-USE LEASE LIABILITY
C76: Cr: Acct 0649 - RIGHT-TO-USE LEASE LIABILITY (CURRENT PORTION LT)
B77: NOTE: This is an annual accrual. It is to be reversed at the start of the next fiscal year. SCO combines the current and non current amount in Entry #0 to reestablish the beginning balances. No action required. | J77: =SUM(J75:J76) -> 0 | K77: =SUM(K75:K76) -> 0 | L77: =IF(J77=K77,"<- Debits and Credits equal each other.","<- Debits and Credits do not equal each other.") -> <- Debits and Credits equal each other.
B80: ** This amount should be included in the due in one year column on the LS-Lease Liability and LS-Check Figures Tabs.
A83: Remove Lease Asset at the End of the Lease Term (only at the end of the lease term)
A84: 8 | B84: Record entry to write off the lease asset and accumulated amortization at the end of the lease term.
B85: Dr: Acct 0485 - ACCUMULATED AMORTIZATION - RIGHT-TO-USE LEASED LAND
B86: Dr: Acct 0479 - ACCUMULATED AMORTIZATION - RIGHT-TO-USE LEASED EQUIPMENT
B87: Dr: Acct 0486 - ACCUMULATED AMORTIZATION - RIGHT-TO-USE LEASED BUILDINGS
A88: *Rpt 18 | C88: Cr: Acct 0476 - RIGHT-TO-USE LEASED LAND - AMORTIZABLE
A89: *Rpt 18 | C89: Cr: Acct 0478 - RIGHT-TO-USE LEASED EQUIPMENT - AMORTIZABLE
A90: *Rpt 18 | C90: Cr: Acct 0477 - RIGHT-TO-USE LEASED BUILDINGS - AMORTIZABLE
B91: * THESE AMOUNTS SHOULD BE INCLUDED AS "DEDUCTIONS" ON REPORT 18. | J91: =SUM(J85:J90) -> 0 | K91: =SUM(K85:K90) -> 0 | L91: =IF(J91=K91,"<- Debits and Credits equal each other.","<- Debits and Credits do not equal each other.") -> <- Debits and Credits equal each other.
A94: Lease Remeasurement and Modifications (only if a significant modification occurred during the fiscal year)
A95: 9 | B95: Record early termination or lease modifications to decrease in the RTU leased asset.
A96: **LS LL/CF | B96: Dr: Acct 0691 - RIGHT-TO-USE LEASE LIABILITY
B97: Dr: Acct 0485 - ACCUMULATED AMORTIZATION - RIGHT-TO-USE LEASED LAND
B98: Dr: Acct 0479 - ACCUMULATED AMORTIZATION - RIGHT-TO-USE LEASED EQUIPMENT
B99: Dr: Acct 0486 - ACCUMULATED AMORTIZATION - RIGHT-TO-USE LEASED BUILDINGS
B100: =IF($F$7="Proprietary","Dr: Acct 0870 - SERVICES & CHARGES (MG ADJ)",VLOOKUP($F$9,'Drop Down Menus'!$F$2:$H$10,3,FALSE)) -> Dr: Acct 0820 - NAT RES & ENVIRON (GAAP ADJ)
A101: *Rpt 18 | C101: Cr: Acct 0476 - RIGHT-TO-USE LEASED LAND - AMORTIZABLE
A102: *Rpt 18 | C102: Cr: Acct 0478 - RIGHT-TO-USE LEASED EQUIPMENT - AMORTIZABLE
A103: *Rpt 18 | C103: Cr: Acct 0477 - RIGHT-TO-USE LEASED BUILDINGS - AMORTIZABLE
C104: =IF($F$7="Proprietary","Dr: Acct 0870 - SERVICES & CHARGES (MG ADJ)",VLOOKUP($F$9,'Drop Down Menus'!$F$2:$G$10,2,FALSE)) -> Cr: Acct 0820 - NAT RES & ENVIRON (GAAP ADJ)
B105: * THESE AMOUNTS SHOULD BE INCLUDED AS "DEDUCTIONS" ON REPORT 18. | J105: =SUM(J96:J104) -> 0 | K105: =SUM(K96:K104) -> 0 | L105: =IF(J105=K105,"<- Debits and Credits equal each other.","<- Debits and Credits do not equal each other.") -> <- Debits and Credits equal each other.
B106: ** This amount should be included in the deductions column on the LS-Lease Liability and LS-Check Figures Tabs.
A109: 10 | B109: Record lease modifications to increase in the RTU leased asset.
A110: *Rpt 18 | B110: Dr: Acct 0476 - RIGHT-TO-USE LEASED LAND - AMORTIZABLE
A111: *Rpt 18 | B111: Dr: Acct 0478 - RIGHT-TO-USE LEASED EQUIPMENT - AMORTIZABLE
A112: *Rpt 18 | B112: Dr: Acct 0477 - RIGHT-TO-USE LEASED BUILDINGS - AMORTIZABLE
A113: **LS LL/CF | C113: Cr: Acct 0691 - RIGHT-TO-USE LEASE LIABILITY
B114: * THESE AMOUNTS SHOULD BE INCLUDED AS "ADDITIONS" ON REPORT 18. | J114: =SUM(J110:J113) -> 0 | K114: =SUM(K110:K113) -> 0 | L114: =IF(J114=K114,"<- Debits and Credits equal each other.","<- Debits and Credits do not equal each other.") -> <- Debits and Credits equal each other.
B115: ** This amount should be included in the additions column on the LS-Lease Liability and LS-Check Figures Tabs.
D120: Informational - Ending Balances of Assets and Liabilities
K121: Debit (Credit)
D122: Acct 0476 - RIGHT-TO-USE LEASED LAND - AMORTIZABLE | K122: =J15+J39-K88-K101+J110 -> 0
D123: Acct 0478 - RIGHT-TO-USE LEASED EQUIPMENT - AMORTIZABLE | K123: =J16+J40-K89-K102+J111 -> 0
D124: Acct 0477 - RIGHT-TO-USE LEASED BUILDINGS - AMORTIZABLE | K124: =J17+J41-K90-K103+J112 -> 0
D125: Acct 0485 - ACCUMULATED AMORTIZATION - RIGHT-TO-USE LEASED LAND | K125: =-K20-K56+J85+J97 -> 0
...

Sheet LS-Fund 6005 Journal Entries
A1: Lessee-Type Contracts Fund-by-Fund Journal Entries Form (to be submitted to the SCO annually—one form per fund)
A2: Manually complete every yellow field in this worksheet—there are no automatically calculated data-entry cells in this worksheet.
A3: Fiscal Year: | F3: 2023–2024
A4: Organization Name: | F4: Department of Water Resources
A5: Organization Code (4-Digits): | F5: 3860
A6: Fund Number (4-Digits): | F6: 6005
A7: Fund Classification: | F7: Governmental
A8: Fund Type: | F8: Governmental Fund
A9: Functional Expense: | F9: =IFERROR(IF(F7="Proprietary","Proprietary Fund",VLOOKUP(F5,qryIndex02a!$A$2:$K$654,4,FALSE)),"Unidentified") -> RESOURCES
A12: Establish Beginning Balances (existing leases only)
A13: Entry #
A14: 0 | B14: Roll forward prior year right-to-use leases to record opening balances. | M14: Combined Lessee Templates | P14: From SCO BB List | S14: Difference
A15: *Rpt 18 | B15: Dr: Acct 0476 - RIGHT-TO-USE LEASED LAND - AMORTIZABLE | J15: =M15 -> 0 | S15: =P15-M15 -> 0
A16: *Rpt 18 | B16: Dr: Acct 0478 - RIGHT-TO-USE LEASED EQUIPMENT - AMORTIZABLE | J16: =M16 -> 0 | S16: =P16-M16 -> 0
A17: *Rpt 18 | B17: Dr: Acct 0477 - RIGHT-TO-USE LEASED BUILDINGS - AMORTIZABLE | J17: =M17 -> 397 | M17: 397 | P17: 12976 | S17: =P17-M17 -> 12579
B18: Dr: Acct 0950 - BEGINNING FUND BALANCE | J18: =P18 -> 276 | M18: 9 | P18: =IF(SUM($Q$20:$Q$23)>SUM($P$15:$P$17),SUM($Q$20:$Q$23)-SUM($P$15:$P$17),0) -> 276 | S18: =P18-M18 -> 267
B19: Dr: Acct 0952 - BEGINNING FUND ADJUSTMENT/PRIOR PERIOD ADJUSTMENT | J19: =IF(SUM($K$20:$K$24)>SUM($J$15:$J$18),SUM($K$20:$K$24)-SUM($J$15:$J$18),0) -> 0 | M19: 0 | S19: =P19-M19 -> 0
C20: Cr: Acct 0485 - ACCUMULATED AMORTIZATION - RIGHT-TO-USE LEASED LAND | K20: =N20 -> 0 | S20: =P20-M20 -> 0
C21: Cr: Acct 0479 - ACCUMULATED AMORTIZATION - RIGHT-TO-USE LEASED EQUIPMENT | K21: =N21 -> 0 | S21: =Q21-N21 -> 0
C22: Cr: Acct 0486 - ACCUMULATED AMORTIZATION - RIGHT-TO-USE LEASED BUILDINGS | K22: =N22 -> 113 | N22: 113 | Q22: 3674 | S22: =Q22-N22 -> 3561
A23: **LS LL/CF | C23: Cr: Acct 0691 - RIGHT-TO-USE LEASE LIABILITY | K23: =N23 -> 293 | N23: 293 | Q23: 9578 | S23: =Q23-N23 -> 9285
C24: Cr: Acct 0950 - BEGINNING FUND BALANCE | K24: =Q24 -> 0 | N24: 0 | Q24: =IF(SUM($Q$20:$Q$23)<SUM($P$15:$P$17),-SUM($Q$20:$Q$23)+SUM($P$15:$P$17),0) -> 0 | S24: =Q24-N24 -> 0
C25: Cr: Acct 0952 - BEGINNING FUND ADJUSTMENT/PRIOR PERIOD ADJUSTMENT | K25: =IF(SUM($K$20:$K$24)<SUM($J$15:$J$18),-SUM($K$20:$K$24)+SUM($J$15:$J$18),0) -> 267 | N25: 0 | S25: =Q25-N25 -> 0
J26: =SUM(J15:J25) -> 673 | K26: =SUM(K15:K25) -> 673 | L26: =IF(J26=K26,"<- Debits and Credits equal each other.","<- Debits and Credits do not equal each other.") -> <- Debits and Credits equal each other.
B27: * THESE ASSET AMOUNTS SHOULD BE REPORTED AS BEGINNING BALANCES ON REPORT 18.
B28: ** This amount should be included in the beginning balance column on the LS-Lease Liability and LS-Check Figures Tabs.
A31: Record New Leases (new leases only)
A32: 1 | B32: Record lease contract commencement (fund-based entries only)
B33: Dr: Acct 0842 - CAPITAL OUTLAY | J33: 92
C34: Cr: Acct 0789 - LEASE AND OTHER FINANCING PROCEEDS | K34: 92
C35: =IF($F$7="Proprietary","Cr: Acct 0870 - SERVICES & CHARGES (MG ADJ)",VLOOKUP($F$9,'Drop Down Menus'!$F$2:$G$10,2,FALSE)) -> Cr: Acct 0820 - NAT RES & ENVIRON (GAAP ADJ)
J36: =SUM(J33:J35) -> 92 | K36: =SUM(K33:K35) -> 92 | L36: =IF(J36=K36,"<- Debits and Credits equal each other.","<- Debits and Credits do not equal each other.") -> <- Debits and Credits equal each other.
A38: 2 | B38: Record leased assets.
A39: *Rpt 18 | B39: Dr: Acct 0476 - RIGHT-TO-USE LEASED LAND - AMORTIZABLE
A40: *Rpt 18 | B40: Dr: Acct 0478 - RIGHT-TO-USE LEASED EQUIPMENT - AMORTIZABLE
A41: *Rpt 18 | B41: Dr: Acct 0477 - RIGHT-TO-USE LEASED BUILDINGS - AMORTIZABLE | J41: 92
C42: Cr: Acct 0842 - CAPITAL OUTLAY | K42: 92
B43: * THESE AMOUNTS SHOULD BE INCLUDED AS "ADDITIONS" ON REPORT 18. | J43: =SUM(J39:J42) -> 92 | K43: =SUM(K39:K42) -> 92 | L43: =IF(J43=K43,"<- Debits and Credits equal each other.","<- Debits and Credits do not equal each other.") -> <- Debits and Credits equal each other.
A46: 3 | B46: Replace proceeds from leases with right-to-use lease liability.
B47: Dr: Acct 0789 - LEASE AND OTHER FINANCING PROCEEDS | J47: 92
A48: **LS LL/CF | C48: Cr: Acct 0691 - RIGHT-TO-USE LEASE LIABILITY | K48: 92
J49: =SUM(J47:J48) -> 92 | K49: =SUM(K47:K48) -> 92 | L49: =IF(J49=K49,"<- Debits and Credits equal each other.","<- Debits and Credits do not equal each other.") -> <- Debits and Credits equal each other.
B50: ** This amount should be included in the additions column on the LS-Lease Liability and LS-Check Figures Tabs.
A53: Record Annual Activity (all leases)
A54: 4 | B54: Record amortization of the leased assets for the year.
B55: Dr: Acct 0875 - DEPRECIATION/AMORTIZATION | J55: 60
C56: Cr: Acct 0485 - ACCUMULATED AMORTIZATION - RIGHT-TO-USE LEASED LAND
C57: Cr: Acct 0479 - ACCUMULATED AMORTIZATION - RIGHT-TO-USE LEASED EQUIPMENT
C58: Cr: Acct 0486 - ACCUMULATED AMORTIZATION - RIGHT-TO-USE LEASED BUILDINGS | K58: 60
J59: =SUM(J55:J58) -> 60 | K59: =SUM(K55:K58) -> 60 | L59: =IF(J59=K59,"<- Debits and Credits equal each other.","<- Debits and Credits do not equal each other.") -> <- Debits and Credits equal each other.
A61: 5 | B61: Reclassify rents and leases exp. to lease contract principal and interest exp.
B62: Dr: Acct 0848 - DEBT SERVICE - PRINCIPAL LEASES | J62: 55
B63: =IF(F7="Governmental","Dr: Acct 0851 - DEBT SERVICE - INTEREST LEASES","Dr: Acct 0894 - INTEREST EXPENSE AND FISCAL CHARGES") -> Dr: Acct 0851 - DEBT SERVICE - INTEREST LEASES | J63: 7
C64: =IF($F$7="Proprietary","Cr: Acct 0870 - SERVICES & CHARGES (MG ADJ)",VLOOKUP($F$9,'Drop Down Menus'!$F$2:$G$10,2,FALSE)) -> Cr: Acct 0820 - NAT RES & ENVIRON (GAAP ADJ) | K64: 62
J65: =SUM(J62:J64) -> 62 | K65: =SUM(K62:K64) -> 62 | L65: =IF(J65=K65,"<- Debits and Credits equal each other.","<- Debits and Credits do not equal each other.") -> <- Debits and Credits equal each other.
A67: 6 | B67: Reduce lease contracts liability for total current year principal payments.
A68: **LS LL/CF | B68: Dr: Acct 0691 - RIGHT-TO-USE LEASE LIABILITY | J68: 55
C69: Cr: Acct 0848 - DEBT SERVICE - PRINCIPAL LEASES | K69: 55
J70: =SUM(J68:J69) -> 55 | K70: =SUM(K68:K69) -> 55 | L70: =IF(J70=K70,"<- Debits and Credits equal each other.","<- Debits and Credits do not equal each other.") -> <- Debits and Credits equal each other.
B71: ** This amount should be included in the deductions column on the LS-Lease Liability and LS-Check Figures Tabs.
A74: 7 | B74: Reclassify the principal amount due in the next FY to the current liability.
A75: **LS LL/CF | B75: Dr: Acct 0691 - RIGHT-TO-USE LEASE LIABILITY | J75: 56
C76: Cr: Acct 0649 - RIGHT-TO-USE LEASE LIABILITY (CURRENT PORTION LT) | K76: 56
B77: NOTE: This is an annual accrual. It is to be reversed at the start of the next fiscal year. SCO combines the current and non current amount in Entry #0 to reestablish the beginning balances. No action required. | J77: =SUM(J75:J76) -> 56 | K77: =SUM(K75:K76) -> 56 | L77: =IF(J77=K77,"<- Debits and Credits equal each other.","<- Debits and Credits do not equal each other.") -> <- Debits and Credits equal each other.
B80: ** This amount should be included in the due in one year column on the LS-Lease Liability and LS-Check Figures Tabs.
A83: Remove Lease Asset at the End of the Lease Term (only at the end of the lease term)
A84: 8 | B84: Record entry to write off the lease asset and accumulated amortization at the end of the lease term.
B85: Dr: Acct 0485 - ACCUMULATED AMORTIZATION - RIGHT-TO-USE LEASED LAND
B86: Dr: Acct 0479 - ACCUMULATED AMORTIZATION - RIGHT-TO-USE LEASED EQUIPMENT
B87: Dr: Acct 0486 - ACCUMULATED AMORTIZATION - RIGHT-TO-USE LEASED BUILDINGS | J87: 22
A88: *Rpt 18 | C88: Cr: Acct 0476 - RIGHT-TO-USE LEASED LAND - AMORTIZABLE
A89: *Rpt 18 | C89: Cr: Acct 0478 - RIGHT-TO-USE LEASED EQUIPMENT - AMORTIZABLE
A90: *Rpt 18 | C90: Cr: Acct 0477 - RIGHT-TO-USE LEASED BUILDINGS - AMORTIZABLE | K90: 22
B91: * THESE AMOUNTS SHOULD BE INCLUDED AS "DEDUCTIONS" ON REPORT 18. | J91: =SUM(J85:J90) -> 22 | K91: =SUM(K85:K90) -> 22 | L91: =IF(J91=K91,"<- Debits and Credits equal each other.","<- Debits and Credits do not equal each other.") -> <- Debits and Credits equal each other.
A94: Lease Remeasurement and Modifications (only if a significant modification occurred during the fiscal year)
A95: 9 | B95: Record early termination or lease modifications to decrease in the RTU leased asset.
A96: **LS LL/CF | B96: Dr: Acct 0691 - RIGHT-TO-USE LEASE LIABILITY
B97: Dr: Acct 0485 - ACCUMULATED AMORTIZATION - RIGHT-TO-USE LEASED LAND
B98: Dr: Acct 0479 - ACCUMULATED AMORTIZATION - RIGHT-TO-USE LEASED EQUIPMENT
B99: Dr: Acct 0486 - ACCUMULATED AMORTIZATION - RIGHT-TO-USE LEASED BUILDINGS
B100: =IF($F$7="Proprietary","Dr: Acct 0870 - SERVICES & CHARGES (MG ADJ)",VLOOKUP($F$9,'Drop Down Menus'!$F$2:$H$10,3,FALSE)) -> Dr: Acct 0820 - NAT RES & ENVIRON (GAAP ADJ)
A101: *Rpt 18 | C101: Cr: Acct 0476 - RIGHT-TO-USE LEASED LAND - AMORTIZABLE
A102: *Rpt 18 | C102: Cr: Acct 0478 - RIGHT-TO-USE LEASED EQUIPMENT - AMORTIZABLE
A103: *Rpt 18 | C103: Cr: Acct 0477 - RIGHT-TO-USE LEASED BUILDINGS - AMORTIZABLE
C104: =IF($F$7="Proprietary","Dr: Acct 0870 - SERVICES & CHARGES (MG ADJ)",VLOOKUP($F$9,'Drop Down Menus'!$F$2:$G$10,2,FALSE)) -> Cr: Acct 0820 - NAT RES & ENVIRON (GAAP ADJ)
B105: * THESE AMOUNTS SHOULD BE INCLUDED AS "DEDUCTIONS" ON REPORT 18. | J105: =SUM(J96:J104) -> 0 | K105: =SUM(K96:K104) -> 0 | L105: =IF(J105=K105,"<- Debits and Credits equal each other.","<- Debits and Credits do not equal each other.") -> <- Debits and Credits equal each other.
B106: ** This amount should be included in the deductions column on the LS-Lease Liability and LS-Check Figures Tabs.
A109: 10 | B109: Record lease modifications to increase in the RTU leased asset.
A110: *Rpt 18 | B110: Dr: Acct 0476 - RIGHT-TO-USE LEASED LAND - AMORTIZABLE
A111: *Rpt 18 | B111: Dr: Acct 0478 - RIGHT-TO-USE LEASED EQUIPMENT - AMORTIZABLE
A112: *Rpt 18 | B112: Dr: Acct 0477 - RIGHT-TO-USE LEASED BUILDINGS - AMORTIZABLE
A113: **LS LL/CF | C113: Cr: Acct 0691 - RIGHT-TO-USE LEASE LIABILITY
B114: * THESE AMOUNTS SHOULD BE INCLUDED AS "ADDITIONS" ON REPORT 18. | J114: =SUM(J110:J113) -> 0 | K114: =SUM(K110:K113) -> 0 | L114: =IF(J114=K114,"<- Debits and Credits equal each other.","<- Debits and Credits do not equal each other.") -> <- Debits and Credits equal each other.
B115: ** This amount should be included in the additions column on the LS-Lease Liability and LS-Check Figures Tabs.
D120: Informational - Ending Balances of Assets and Liabilities
K121: Debit (Credit)
D122: Acct 0476 - RIGHT-TO-USE LEASED LAND - AMORTIZABLE | K122: =J15+J39-K88-K101+J110 -> 0
D123: Acct 0478 - RIGHT-TO-USE LEASED EQUIPMENT - AMORTIZABLE | K123: =J16+J40-K89-K102+J111 -> 0
D124: Acct 0477 - RIGHT-TO-USE LEASED BUILDINGS - AMORTIZABLE | K124: =J17+J41-K90-K103+J112 -> 467
D125: Acct 0485 - ACCUMULATED AMORTIZATION - RIGHT-TO-USE LEASED LAND | K125: =-K20-K56+J85+J97 -> 0
...

Sheet LS-Fund 6026 Journal Entries
A1: Lessee-Type Contracts Fund-by-Fund Journal Entries Form (to be submitted to the SCO annually—one form per fund)
A2: Manually complete every yellow field in this worksheet—there are no automatically calculated data-entry cells in this worksheet.
A3: Fiscal Year: | F3: 2023–2024
A4: Organization Name: | F4: Department of Water Resources
A5: Organization Code (4-Digits): | F5: 3860
A6: Fund Number (4-Digits): | F6: 6026
A7: Fund Classification: | F7: Governmental
A8: Fund Type: | F8: Governmental Fund
A9: Functional Expense: | F9: =IFERROR(IF(F7="Proprietary","Proprietary Fund",VLOOKUP(F5,qryIndex02a!$A$2:$K$654,4,FALSE)),"Unidentified") -> RESOURCES
A12: Establish Beginning Balances (existing leases only)
A13: Entry #
A14: 0 | B14: Roll forward prior year right-to-use leases to record opening balances. | M14: Combined Lessee Templates | P14: From SCO BB List | S14: Difference
A15: *Rpt 18 | B15: Dr: Acct 0476 - RIGHT-TO-USE LEASED LAND - AMORTIZABLE | J15: =M15 -> 0 | S15: =P15-M15 -> 0
A16: *Rpt 18 | B16: Dr: Acct 0478 - RIGHT-TO-USE LEASED EQUIPMENT - AMORTIZABLE | J16: =M16 -> 0 | S16: =P16-M16 -> 0
A17: *Rpt 18 | B17: Dr: Acct 0477 - RIGHT-TO-USE LEASED BUILDINGS - AMORTIZABLE | J17: =M17 -> 20000 | M17: 20000 | S17: =P17-M17 -> -20000
B18: Dr: Acct 0950 - BEGINNING FUND BALANCE | J18: =P18 -> 0 | M18: 446 | P18: =IF(SUM($Q$20:$Q$23)>SUM($P$15:$P$17),SUM($Q$20:$Q$23)-SUM($P$15:$P$17),0) -> 0 | S18: =P18-M18 -> -446
B19: Dr: Acct 0952 - BEGINNING FUND ADJUSTMENT/PRIOR PERIOD ADJUSTMENT | J19: =IF(SUM($K$20:$K$24)>SUM($J$15:$J$18),SUM($K$20:$K$24)-SUM($J$15:$J$18),0) -> 427 | M19: 0 | S19: =P19-M19 -> 0
C20: Cr: Acct 0485 - ACCUMULATED AMORTIZATION - RIGHT-TO-USE LEASED LAND | K20: =N20 -> 0 | S20: =P20-M20 -> 0
C21: Cr: Acct 0479 - ACCUMULATED AMORTIZATION - RIGHT-TO-USE LEASED EQUIPMENT | K21: =N21 -> 0 | S21: =Q21-N21 -> 0
C22: Cr: Acct 0486 - ACCUMULATED AMORTIZATION - RIGHT-TO-USE LEASED BUILDINGS | K22: =N22 -> 5663 | N22: 5663 | S22: =Q22-N22 -> -5663
A23: **LS LL/CF | C23: Cr: Acct 0691 - RIGHT-TO-USE LEASE LIABILITY | K23: =N23 -> 14764 | N23: 14764 | S23: =Q23-N23 -> -14764
C24: Cr: Acct 0950 - BEGINNING FUND BALANCE | K24: =Q24 -> 0 | N24: 19 | Q24: =IF(SUM($Q$20:$Q$23)<SUM($P$15:$P$17),-SUM($Q$20:$Q$23)+SUM($P$15:$P$17),0) -> 0 | S24: =Q24-N24 -> -19
C25: Cr: Acct 0952 - BEGINNING FUND ADJUSTMENT/PRIOR PERIOD ADJUSTMENT | K25: =IF(SUM($K$20:$K$24)<SUM($J$15:$J$18),-SUM($K$20:$K$24)+SUM($J$15:$J$18),0) -> 0 | N25: 0 | S25: =Q25-N25 -> 0
J26: =SUM(J15:J25) -> 20427 | K26: =SUM(K15:K25) -> 20427 | L26: =IF(J26=K26,"<- Debits and Credits equal each other.","<- Debits and Credits do not equal each other.") -> <- Debits and Credits equal each other.
B27: * THESE ASSET AMOUNTS SHOULD BE REPORTED AS BEGINNING BALANCES ON REPORT 18.
B28: ** This amount should be included in the beginning balance column on the LS-Lease Liability and LS-Check Figures Tabs.
A31: Record New Leases (new leases only)
A32: 1 | B32: Record lease contract commencement (fund-based entries only)
B33: Dr: Acct 0842 - CAPITAL OUTLAY | J33: 4632
C34: Cr: Acct 0789 - LEASE AND OTHER FINANCING PROCEEDS | K34: 4632
C35: =IF($F$7="Proprietary","Cr: Acct 0870 - SERVICES & CHARGES (MG ADJ)",VLOOKUP($F$9,'Drop Down Menus'!$F$2:$G$10,2,FALSE)) -> Cr: Acct 0820 - NAT RES & ENVIRON (GAAP ADJ)
J36: =SUM(J33:J35) -> 4632 | K36: =SUM(K33:K35) -> 4632 | L36: =IF(J36=K36,"<- Debits and Credits equal each other.","<- Debits and Credits do not equal each other.") -> <- Debits and Credits equal each other.
A38: 2 | B38: Record leased assets.
A39: *Rpt 18 | B39: Dr: Acct 0476 - RIGHT-TO-USE LEASED LAND - AMORTIZABLE
A40: *Rpt 18 | B40: Dr: Acct 0478 - RIGHT-TO-USE LEASED EQUIPMENT - AMORTIZABLE
A41: *Rpt 18 | B41: Dr: Acct 0477 - RIGHT-TO-USE LEASED BUILDINGS - AMORTIZABLE | J41: 4632
C42: Cr: Acct 0842 - CAPITAL OUTLAY | K42: 4632
B43: * THESE AMOUNTS SHOULD BE INCLUDED AS "ADDITIONS" ON REPORT 18. | J43: =SUM(J39:J42) -> 4632 | K43: =SUM(K39:K42) -> 4632 | L43: =IF(J43=K43,"<- Debits and Credits equal each other.","<- Debits and Credits do not equal each other.") -> <- Debits and Credits equal each other.
A46: 3 | B46: Replace proceeds from leases with right-to-use lease liability.
B47: Dr: Acct 0789 - LEASE AND OTHER FINANCING PROCEEDS | J47: 4632
A48: **LS LL/CF | C48: Cr: Acct 0691 - RIGHT-TO-USE LEASE LIABILITY | K48: 4632
J49: =SUM(J47:J48) -> 4632 | K49: =SUM(K47:K48) -> 4632 | L49: =IF(J49=K49,"<- Debits and Credits equal each other.","<- Debits and Credits do not equal each other.") -> <- Debits and Credits equal each other.
B50: ** This amount should be included in the additions column on the LS-Lease Liability and LS-Check Figures Tabs.
A53: Record Annual Activity (all leases)
A54: 4 | B54: Record amortization of the leased assets for the year.
B55: Dr: Acct 0875 - DEPRECIATION/AMORTIZATION | J55: 3033
C56: Cr: Acct 0485 - ACCUMULATED AMORTIZATION - RIGHT-TO-USE LEASED LAND
C57: Cr: Acct 0479 - ACCUMULATED AMORTIZATION - RIGHT-TO-USE LEASED EQUIPMENT
C58: Cr: Acct 0486 - ACCUMULATED AMORTIZATION - RIGHT-TO-USE LEASED BUILDINGS | K58: 3033
J59: =SUM(J55:J58) -> 3033 | K59: =SUM(K55:K58) -> 3033 | L59: =IF(J59=K59,"<- Debits and Credits equal each other.","<- Debits and Credits do not equal each other.") -> <- Debits and Credits equal each other.
A61: 5 | B61: Reclassify rents and leases exp. to lease contract principal and interest exp.
B62: Dr: Acct 0848 - DEBT SERVICE - PRINCIPAL LEASES | J62: 2757
B63: =IF(F7="Governmental","Dr: Acct 0851 - DEBT SERVICE - INTEREST LEASES","Dr: Acct 0894 - INTEREST EXPENSE AND FISCAL CHARGES") -> Dr: Acct 0851 - DEBT SERVICE - INTEREST LEASES | J63: 339
C64: =IF($F$7="Proprietary","Cr: Acct 0870 - SERVICES & CHARGES (MG ADJ)",VLOOKUP($F$9,'Drop Down Menus'!$F$2:$G$10,2,FALSE)) -> Cr: Acct 0820 - NAT RES & ENVIRON (GAAP ADJ) | K64: 3096
J65: =SUM(J62:J64) -> 3096 | K65: =SUM(K62:K64) -> 3096 | L65: =IF(J65=K65,"<- Debits and Credits equal each other.","<- Debits and Credits do not equal each other.") -> <- Debits and Credits equal each other.
A67: 6 | B67: Reduce lease contracts liability for total current year principal payments.
A68: **LS LL/CF | B68: Dr: Acct 0691 - RIGHT-TO-USE LEASE LIABILITY | J68: 2757
C69: Cr: Acct 0848 - DEBT SERVICE - PRINCIPAL LEASES | K69: 2757
J70: =SUM(J68:J69) -> 2757 | K70: =SUM(K68:K69) -> 2757 | L70: =IF(J70=K70,"<- Debits and Credits equal each other.","<- Debits and Credits do not equal each other.") -> <- Debits and Credits equal each other.
B71: ** This amount should be included in the deductions column on the LS-Lease Liability and LS-Check Figures Tabs.
A74: 7 | B74: Reclassify the principal amount due in the next FY to the current liability.
A75: **LS LL/CF | B75: Dr: Acct 0691 - RIGHT-TO-USE LEASE LIABILITY | J75: 2822
C76: Cr: Acct 0649 - RIGHT-TO-USE LEASE LIABILITY (CURRENT PORTION LT) | K76: 2822
B77: NOTE: This is an annual accrual. It is to be reversed at the start of the next fiscal year. SCO combines the current and non current amount in Entry #0 to reestablish the beginning balances. No action required. | J77: =SUM(J75:J76) -> 2822 | K77: =SUM(K75:K76) -> 2822 | L77: =IF(J77=K77,"<- Debits and Credits equal each other.","<- Debits and Credits do not equal each other.") -> <- Debits and Credits equal each other.
B80: ** This amount should be included in the due in one year column on the LS-Lease Liability and LS-Check Figures Tabs.
A83: Remove Lease Asset at the End of the Lease Term (only at the end of the lease term)
A84: 8 | B84: Record entry to write off the lease asset and accumulated amortization at the end of the lease term.
B85: Dr: Acct 0485 - ACCUMULATED AMORTIZATION - RIGHT-TO-USE LEASED LAND
B86: Dr: Acct 0479 - ACCUMULATED AMORTIZATION - RIGHT-TO-USE LEASED EQUIPMENT
B87: Dr: Acct 0486 - ACCUMULATED AMORTIZATION - RIGHT-TO-USE LEASED BUILDINGS | J87: 1108
A88: *Rpt 18 | C88: Cr: Acct 0476 - RIGHT-TO-USE LEASED LAND - AMORTIZABLE
A89: *Rpt 18 | C89: Cr: Acct 0478 - RIGHT-TO-USE LEASED EQUIPMENT - AMORTIZABLE
A90: *Rpt 18 | C90: Cr: Acct 0477 - RIGHT-TO-USE LEASED BUILDINGS - AMORTIZABLE | K90: 1108
B91: * THESE AMOUNTS SHOULD BE INCLUDED AS "DEDUCTIONS" ON REPORT 18. | J91: =SUM(J85:J90) -> 1108 | K91: =SUM(K85:K90) -> 1108 | L91: =IF(J91=K91,"<- Debits and Credits equal each other.","<- Debits and Credits do not equal each other.") -> <- Debits and Credits equal each other.
A94: Lease Remeasurement and Modifications (only if a significant modification occurred during the fiscal year)
A95: 9 | B95: Record early termination or lease modifications to decrease in the RTU leased asset.
A96: **LS LL/CF | B96: Dr: Acct 0691 - RIGHT-TO-USE LEASE LIABILITY
B97: Dr: Acct 0485 - ACCUMULATED AMORTIZATION - RIGHT-TO-USE LEASED LAND
B98: Dr: Acct 0479 - ACCUMULATED AMORTIZATION - RIGHT-TO-USE LEASED EQUIPMENT
B99: Dr: Acct 0486 - ACCUMULATED AMORTIZATION - RIGHT-TO-USE LEASED BUILDINGS
B100: =IF($F$7="Proprietary","Dr: Acct 0870 - SERVICES & CHARGES (MG ADJ)",VLOOKUP($F$9,'Drop Down Menus'!$F$2:$H$10,3,FALSE)) -> Dr: Acct 0820 - NAT RES & ENVIRON (GAAP ADJ)
A101: *Rpt 18 | C101: Cr: Acct 0476 - RIGHT-TO-USE LEASED LAND - AMORTIZABLE
A102: *Rpt 18 | C102: Cr: Acct 0478 - RIGHT-TO-USE LEASED EQUIPMENT - AMORTIZABLE
A103: *Rpt 18 | C103: Cr: Acct 0477 - RIGHT-TO-USE LEASED BUILDINGS - AMORTIZABLE
C104: =IF($F$7="Proprietary","Dr: Acct 0870 - SERVICES & CHARGES (MG ADJ)",VLOOKUP($F$9,'Drop Down Menus'!$F$2:$G$10,2,FALSE)) -> Cr: Acct 0820 - NAT RES & ENVIRON (GAAP ADJ)
B105: * THESE AMOUNTS SHOULD BE INCLUDED AS "DEDUCTIONS" ON REPORT 18. | J105: =SUM(J96:J104) -> 0 | K105: =SUM(K96:K104) -> 0 | L105: =IF(J105=K105,"<- Debits and Credits equal each other.","<- Debits and Credits do not equal each other.") -> <- Debits and Credits equal each other.
B106: ** This amount should be included in the deductions column on the LS-Lease Liability and LS-Check Figures Tabs.
A109: 10 | B109: Record lease modifications to increase in the RTU leased asset.
A110: *Rpt 18 | B110: Dr: Acct 0476 - RIGHT-TO-USE LEASED LAND - AMORTIZABLE
A111: *Rpt 18 | B111: Dr: Acct 0478 - RIGHT-TO-USE LEASED EQUIPMENT - AMORTIZABLE
A112: *Rpt 18 | B112: Dr: Acct 0477 - RIGHT-TO-USE LEASED BUILDINGS - AMORTIZABLE
A113: **LS LL/CF | C113: Cr: Acct 0691 - RIGHT-TO-USE LEASE LIABILITY
B114: * THESE AMOUNTS SHOULD BE INCLUDED AS "ADDITIONS" ON REPORT 18. | J114: =SUM(J110:J113) -> 0 | K114: =SUM(K110:K113) -> 0 | L114: =IF(J114=K114,"<- Debits and Credits equal each other.","<- Debits and Credits do not equal each other.") -> <- Debits and Credits equal each other.
B115: ** This amount should be included in the additions column on the LS-Lease Liability and LS-Check Figures Tabs.
D120: Informational - Ending Balances of Assets and Liabilities
K121: Debit (Credit)
D122: Acct 0476 - RIGHT-TO-USE LEASED LAND - AMORTIZABLE | K122: =J15+J39-K88-K101+J110 -> 0
D123: Acct 0478 - RIGHT-TO-USE LEASED EQUIPMENT - AMORTIZABLE | K123: =J16+J40-K89-K102+J111 -> 0
D124: Acct 0477 - RIGHT-TO-USE LEASED BUILDINGS - AMORTIZABLE | K124: =J17+J41-K90-K103+J112 -> 23524
D125: Acct 0485 - ACCUMULATED AMORTIZATION - RIGHT-TO-USE LEASED LAND | K125: =-K20-K56+J85+J97 -> 0
...

Sheet LS-Fund 6027 Journal Entries
A1: Lessee-Type Contracts Fund-by-Fund Journal Entries Form (to be submitted to the SCO annually—one form per fund)
A2: Manually complete every yellow field in this worksheet—there are no automatically calculated data-entry cells in this worksheet.
A3: Fiscal Year: | F3: 2023–2024
A4: Organization Name: | F4: Department of Water Resources
A5: Organization Code (4-Digits): | F5: 3860
A6: Fund Number (4-Digits): | F6: 6027
A7: Fund Classification: | F7: Governmental
A8: Fund Type: | F8: Governmental Fund
A9: Functional Expense: | F9: =IFERROR(IF(F7="Proprietary","Proprietary Fund",VLOOKUP(F5,qryIndex02a!$A$2:$K$654,4,FALSE)),"Unidentified") -> RESOURCES
A12: Establish Beginning Balances (existing leases only)
A13: Entry #
A14: 0 | B14: Roll forward prior year right-to-use leases to record opening balances. | M14: Combined Lessee Templates | P14: From SCO BB List | S14: Difference
A15: *Rpt 18 | B15: Dr: Acct 0476 - RIGHT-TO-USE LEASED LAND - AMORTIZABLE | J15: =M15 -> 0 | S15: =P15-M15 -> 0
A16: *Rpt 18 | B16: Dr: Acct 0478 - RIGHT-TO-USE LEASED EQUIPMENT - AMORTIZABLE | J16: =M16 -> 0 | S16: =P16-M16 -> 0
A17: *Rpt 18 | B17: Dr: Acct 0477 - RIGHT-TO-USE LEASED BUILDINGS - AMORTIZABLE | J17: =M17 -> 2718 | M17: 2718 | S17: =P17-M17 -> -2718
B18: Dr: Acct 0950 - BEGINNING FUND BALANCE | J18: =P18 -> 0 | M18: 61 | P18: =IF(SUM($Q$20:$Q$23)>SUM($P$15:$P$17),SUM($Q$20:$Q$23)-SUM($P$15:$P$17),0) -> 0 | S18: =P18-M18 -> -61
B19: Dr: Acct 0952 - BEGINNING FUND ADJUSTMENT/PRIOR PERIOD ADJUSTMENT | J19: =IF(SUM($K$20:$K$24)>SUM($J$15:$J$18),SUM($K$20:$K$24)-SUM($J$15:$J$18),0) -> 59 | M19: 0 | S19: =P19-M19 -> 0
C20: Cr: Acct 0485 - ACCUMULATED AMORTIZATION - RIGHT-TO-USE LEASED LAND | K20: =N20 -> 0 | S20: =P20-M20 -> 0
C21: Cr: Acct 0479 - ACCUMULATED AMORTIZATION - RIGHT-TO-USE LEASED EQUIPMENT | K21: =N21 -> 0 | S21: =Q21-N21 -> 0
C22: Cr: Acct 0486 - ACCUMULATED AMORTIZATION - RIGHT-TO-USE LEASED BUILDINGS | K22: =N22 -> 770 | N22: 770 | S22: =Q22-N22 -> -770
A23: **LS LL/CF | C23: Cr: Acct 0691 - RIGHT-TO-USE LEASE LIABILITY | K23: =N23 -> 2007 | N23: 2007 | S23: =Q23-N23 -> -2007
C24: Cr: Acct 0950 - BEGINNING FUND BALANCE | K24: =Q24 -> 0 | N24: 3 | Q24: =IF(SUM($Q$20:$Q$23)<SUM($P$15:$P$17),-SUM($Q$20:$Q$23)+SUM($P$15:$P$17),0) -> 0 | S24: =Q24-N24 -> -3
C25: Cr: Acct 0952 - BEGINNING FUND ADJUSTMENT/PRIOR PERIOD ADJUSTMENT | K25: =IF(SUM($K$20:$K$24)<SUM($J$15:$J$18),-SUM($K$20:$K$24)+SUM($J$15:$J$18),0) -> 0 | N25: 0 | S25: =Q25-N25 -> 0
J26: =SUM(J15:J25) -> 2777 | K26: =SUM(K15:K25) -> 2777 | L26: =IF(J26=K26,"<- Debits and Credits equal each other.","<- Debits and Credits do not equal each other.") -> <- Debits and Credits equal each other.
B27: * THESE ASSET AMOUNTS SHOULD BE REPORTED AS BEGINNING BALANCES ON REPORT 18.
B28: ** This amount should be included in the beginning balance column on the LS-Lease Liability and LS-Check Figures Tabs.
A31: Record New Leases (new leases only)
A32: 1 | B32: Record lease contract commencement (fund-based entries only)
B33: Dr: Acct 0842 - CAPITAL OUTLAY | J33: 630
C34: Cr: Acct 0789 - LEASE AND OTHER FINANCING PROCEEDS | K34: 630
C35: =IF($F$7="Proprietary","Cr: Acct 0870 - SERVICES & CHARGES (MG ADJ)",VLOOKUP($F$9,'Drop Down Menus'!$F$2:$G$10,2,FALSE)) -> Cr: Acct 0820 - NAT RES & ENVIRON (GAAP ADJ)
J36: =SUM(J33:J35) -> 630 | K36: =SUM(K33:K35) -> 630 | L36: =IF(J36=K36,"<- Debits and Credits equal each other.","<- Debits and Credits do not equal each other.") -> <- Debits and Credits equal each other.
A38: 2 | B38: Record leased assets.
A39: *Rpt 18 | B39: Dr: Acct 0476 - RIGHT-TO-USE LEASED LAND - AMORTIZABLE
A40: *Rpt 18 | B40: Dr: Acct 0478 - RIGHT-TO-USE LEASED EQUIPMENT - AMORTIZABLE
A41: *Rpt 18 | B41: Dr: Acct 0477 - RIGHT-TO-USE LEASED BUILDINGS - AMORTIZABLE | J41: 630
C42: Cr: Acct 0842 - CAPITAL OUTLAY | K42: 630
B43: * THESE AMOUNTS SHOULD BE INCLUDED AS "ADDITIONS" ON REPORT 18. | J43: =SUM(J39:J42) -> 630 | K43: =SUM(K39:K42) -> 630 | L43: =IF(J43=K43,"<- Debits and Credits equal each other.","<- Debits and Credits do not equal each other.") -> <- Debits and Credits equal each other.
A46: 3 | B46: Replace proceeds from leases with right-to-use lease liability.
B47: Dr: Acct 0789 - LEASE AND OTHER FINANCING PROCEEDS | J47: 630
A48: **LS LL/CF | C48: Cr: Acct 0691 - RIGHT-TO-USE LEASE LIABILITY | K48: 630
J49: =SUM(J47:J48) -> 630 | K49: =SUM(K47:K48) -> 630 | L49: =IF(J49=K49,"<- Debits and Credits equal each other.","<- Debits and Credits do not equal each other.") -> <- Debits and Credits equal each other.
B50: ** This amount should be included in the additions column on the LS-Lease Liability and LS-Check Figures Tabs.
A53: Record Annual Activity (all leases)
A54: 4 | B54: Record amortization of the leased assets for the year.
B55: Dr: Acct 0875 - DEPRECIATION/AMORTIZATION | J55: 412
C56: Cr: Acct 0485 - ACCUMULATED AMORTIZATION - RIGHT-TO-USE LEASED LAND
C57: Cr: Acct 0479 - ACCUMULATED AMORTIZATION - RIGHT-TO-USE LEASED EQUIPMENT
C58: Cr: Acct 0486 - ACCUMULATED AMORTIZATION - RIGHT-TO-USE LEASED BUILDINGS | K58: 412
J59: =SUM(J55:J58) -> 412 | K59: =SUM(K55:K58) -> 412 | L59: =IF(J59=K59,"<- Debits and Credits equal each other.","<- Debits and Credits do not equal each other.") -> <- Debits and Credits equal each other.
A61: 5 | B61: Reclassify rents and leases exp. to lease contract principal and interest exp.
B62: Dr: Acct 0848 - DEBT SERVICE - PRINCIPAL LEASES | J62: 375
B63: =IF(F7="Governmental","Dr: Acct 0851 - DEBT SERVICE - INTEREST LEASES","Dr: Acct 0894 - INTEREST EXPENSE AND FISCAL CHARGES") -> Dr: Acct 0851 - DEBT SERVICE - INTEREST LEASES | J63: 46
C64: =IF($F$7="Proprietary","Cr: Acct 0870 - SERVICES & CHARGES (MG ADJ)",VLOOKUP($F$9,'Drop Down Menus'!$F$2:$G$10,2,FALSE)) -> Cr: Acct 0820 - NAT RES & ENVIRON (GAAP ADJ) | K64: 421
J65: =SUM(J62:J64) -> 421 | K65: =SUM(K62:K64) -> 421 | L65: =IF(J65=K65,"<- Debits and Credits equal each other.","<- Debits and Credits do not equal each other.") -> <- Debits and Credits equal each other.
A67: 6 | B67: Reduce lease contracts liability for total current year principal payments.
A68: **LS LL/CF | B68: Dr: Acct 0691 - RIGHT-TO-USE LEASE LIABILITY | J68: 375
C69: Cr: Acct 0848 - DEBT SERVICE - PRINCIPAL LEASES | K69: 375
J70: =SUM(J68:J69) -> 375 | K70: =SUM(K68:K69) -> 375 | L70: =IF(J70=K70,"<- Debits and Credits equal each other.","<- Debits and Credits do not equal each other.") -> <- Debits and Credits equal each other.
B71: ** This amount should be included in the deductions column on the LS-Lease Liability and LS-Check Figures Tabs.
A74: 7 | B74: Reclassify the principal amount due in the next FY to the current liability.
A75: **LS LL/CF | B75: Dr: Acct 0691 - RIGHT-TO-USE LEASE LIABILITY | J75: 384
C76: Cr: Acct 0649 - RIGHT-TO-USE LEASE LIABILITY (CURRENT PORTION LT) | K76: 384
B77: NOTE: This is an annual accrual. It is to be reversed at the start of the next fiscal year. SCO combines the current and non current amount in Entry #0 to reestablish the beginning balances. No action required. | J77: =SUM(J75:J76) -> 384 | K77: =SUM(K75:K76) -> 384 | L77: =IF(J77=K77,"<- Debits and Credits equal each other.","<- Debits and Credits do not equal each other.") -> <- Debits and Credits equal each other.
B80: ** This amount should be included in the due in one year column on the LS-Lease Liability and LS-Check Figures Tabs.
A83: Remove Lease Asset at the End of the Lease Term (only at the end of the lease term)
A84: 8 | B84: Record entry to write off the lease asset and accumulated amortization at the end of the lease term.
B85: Dr: Acct 0485 - ACCUMULATED AMORTIZATION - RIGHT-TO-USE LEASED LAND
B86: Dr: Acct 0479 - ACCUMULATED AMORTIZATION - RIGHT-TO-USE LEASED EQUIPMENT
B87: Dr: Acct 0486 - ACCUMULATED AMORTIZATION - RIGHT-TO-USE LEASED BUILDINGS | J87: 151
A88: *Rpt 18 | C88: Cr: Acct 0476 - RIGHT-TO-USE LEASED LAND - AMORTIZABLE
A89: *Rpt 18 | C89: Cr: Acct 0478 - RIGHT-TO-USE LEASED EQUIPMENT - AMORTIZABLE
A90: *Rpt 18 | C90: Cr: Acct 0477 - RIGHT-TO-USE LEASED BUILDINGS - AMORTIZABLE | K90: 151
B91: * THESE AMOUNTS SHOULD BE INCLUDED AS "DEDUCTIONS" ON REPORT 18. | J91: =SUM(J85:J90) -> 151 | K91: =SUM(K85:K90) -> 151 | L91: =IF(J91=K91,"<- Debits and Credits equal each other.","<- Debits and Credits do not equal each other.") -> <- Debits and Credits equal each other.
A94: Lease Remeasurement and Modifications (only if a significant modification occurred during the fiscal year)
A95: 9 | B95: Record early termination or lease modifications to decrease in the RTU leased asset.
A96: **LS LL/CF | B96: Dr: Acct 0691 - RIGHT-TO-USE LEASE LIABILITY
B97: Dr: Acct 0485 - ACCUMULATED AMORTIZATION - RIGHT-TO-USE LEASED LAND
B98: Dr: Acct 0479 - ACCUMULATED AMORTIZATION - RIGHT-TO-USE LEASED EQUIPMENT
B99: Dr: Acct 0486 - ACCUMULATED AMORTIZATION - RIGHT-TO-USE LEASED BUILDINGS
B100: =IF($F$7="Proprietary","Dr: Acct 0870 - SERVICES & CHARGES (MG ADJ)",VLOOKUP($F$9,'Drop Down Menus'!$F$2:$H$10,3,FALSE)) -> Dr: Acct 0820 - NAT RES & ENVIRON (GAAP ADJ)
A101: *Rpt 18 | C101: Cr: Acct 0476 - RIGHT-TO-USE LEASED LAND - AMORTIZABLE
A102: *Rpt 18 | C102: Cr: Acct 0478 - RIGHT-TO-USE LEASED EQUIPMENT - AMORTIZABLE
A103: *Rpt 18 | C103: Cr: Acct 0477 - RIGHT-TO-USE LEASED BUILDINGS - AMORTIZABLE
C104: =IF($F$7="Proprietary","Dr: Acct 0870 - SERVICES & CHARGES (MG ADJ)",VLOOKUP($F$9,'Drop Down Menus'!$F$2:$G$10,2,FALSE)) -> Cr: Acct 0820 - NAT RES & ENVIRON (GAAP ADJ)
B105: * THESE AMOUNTS SHOULD BE INCLUDED AS "DEDUCTIONS" ON REPORT 18. | J105: =SUM(J96:J104) -> 0 | K105: =SUM(K96:K104) -> 0 | L105: =IF(J105=K105,"<- Debits and Credits equal each other.","<- Debits and Credits do not equal each other.") -> <- Debits and Credits equal each other.
B106: ** This amount should be included in the deductions column on the LS-Lease Liability and LS-Check Figures Tabs.
A109: 10 | B109: Record lease modifications to increase in the RTU leased asset.
A110: *Rpt 18 | B110: Dr: Acct 0476 - RIGHT-TO-USE LEASED LAND - AMORTIZABLE
A111: *Rpt 18 | B111: Dr: Acct 0478 - RIGHT-TO-USE LEASED EQUIPMENT - AMORTIZABLE
A112: *Rpt 18 | B112: Dr: Acct 0477 - RIGHT-TO-USE LEASED BUILDINGS - AMORTIZABLE
A113: **LS LL/CF | C113: Cr: Acct 0691 - RIGHT-TO-USE LEASE LIABILITY
B114: * THESE AMOUNTS SHOULD BE INCLUDED AS "ADDITIONS" ON REPORT 18. | J114: =SUM(J110:J113) -> 0 | K114: =SUM(K110:K113) -> 0 | L114: =IF(J114=K114,"<- Debits and Credits equal each other.","<- Debits and Credits do not equal each other.") -> <- Debits and Credits equal each other.
B115: ** This amount should be included in the additions column on the LS-Lease Liability and LS-Check Figures Tabs.
D120: Informational - Ending Balances of Assets and Liabilities
K121: Debit (Credit)
D122: Acct 0476 - RIGHT-TO-USE LEASED LAND - AMORTIZABLE | K122: =J15+J39-K88-K101+J110 -> 0
D123: Acct 0478 - RIGHT-TO-USE LEASED EQUIPMENT - AMORTIZABLE | K123: =J16+J40-K89-K102+J111 -> 0
D124: Acct 0477 - RIGHT-TO-USE LEASED BUILDINGS - AMORTIZABLE | K124: =J17+J41-K90-K103+J112 -> 3197
D125: Acct 0485 - ACCUMULATED AMORTIZATION - RIGHT-TO-USE LEASED LAND | K125: =-K20-K56+J85+J97 -> 0
...

Sheet LS-Fund 6031 Journal Entries
A1: Lessee-Type Contracts Fund-by-Fund Journal Entries Form (to be submitted to the SCO annually—one form per fund)
A2: Manually complete every yellow field in this worksheet—there are no automatically calculated data-entry cells in this worksheet.
A3: Fiscal Year: | F3: 2023–2024
A4: Organization Name: | F4: Department of Water Resources
A5: Organization Code (4-Digits): | F5: 3860
A6: Fund Number (4-Digits): | F6: 6031
A7: Fund Classification: | F7: Governmental
A8: Fund Type: | F8: Governmental Fund
A9: Functional Expense: | F9: =IFERROR(IF(F7="Proprietary","Proprietary Fund",VLOOKUP(F5,qryIndex02a!$A$2:$K$654,4,FALSE)),"Unidentified") -> RESOURCES
A12: Establish Beginning Balances (existing leases only)
A13: Entry #
A14: 0 | B14: Roll forward prior year right-to-use leases to record opening balances. | M14: Combined Lessee Templates | P14: From SCO BB List | S14: Difference
A15: *Rpt 18 | B15: Dr: Acct 0476 - RIGHT-TO-USE LEASED LAND - AMORTIZABLE | J15: =M15 -> 0 | S15: =P15-M15 -> 0
A16: *Rpt 18 | B16: Dr: Acct 0478 - RIGHT-TO-USE LEASED EQUIPMENT - AMORTIZABLE | J16: =M16 -> 0 | S16: =P16-M16 -> 0
A17: *Rpt 18 | B17: Dr: Acct 0477 - RIGHT-TO-USE LEASED BUILDINGS - AMORTIZABLE | J17: =M17 -> 295582 | M17: 295582 | P17: 58385 | S17: =P17-M17 -> -237197
B18: Dr: Acct 0950 - BEGINNING FUND BALANCE | J18: =P18 -> 1248 | M18: 6593 | P18: =IF(SUM($Q$20:$Q$23)>SUM($P$15:$P$17),SUM($Q$20:$Q$23)-SUM($P$15:$P$17),0) -> 1248 | S18: =P18-M18 -> -5345
B19: Dr: Acct 0952 - BEGINNING FUND ADJUSTMENT/PRIOR PERIOD ADJUSTMENT | J19: =IF(SUM($K$20:$K$24)>SUM($J$15:$J$18),SUM($K$20:$K$24)-SUM($J$15:$J$18),0) -> 5065 | M19: 0 | S19: =P19-M19 -> 0
C20: Cr: Acct 0485 - ACCUMULATED AMORTIZATION - RIGHT-TO-USE LEASED LAND | K20: =N20 -> 0 | S20: =P20-M20 -> 0
C21: Cr: Acct 0479 - ACCUMULATED AMORTIZATION - RIGHT-TO-USE LEASED EQUIPMENT | K21: =N21 -> 0 | S21: =Q21-N21 -> 0
C22: Cr: Acct 0486 - ACCUMULATED AMORTIZATION - RIGHT-TO-USE LEASED BUILDINGS | K22: =N22 -> 83695 | N22: 83695 | Q22: 16532 | S22: =Q22-N22 -> -67163
A23: **LS LL/CF | C23: Cr: Acct 0691 - RIGHT-TO-USE LEASE LIABILITY | K23: =N23 -> 218200 | N23: 218200 | Q23: 43101 | S23: =Q23-N23 -> -175099
C24: Cr: Acct 0950 - BEGINNING FUND BALANCE | K24: =Q24 -> 0 | N24: 279 | Q24: =IF(SUM($Q$20:$Q$23)<SUM($P$15:$P$17),-SUM($Q$20:$Q$23)+SUM($P$15:$P$17),0) -> 0 | S24: =Q24-N24 -> -279
C25: Cr: Acct 0952 - BEGINNING FUND ADJUSTMENT/PRIOR PERIOD ADJUSTMENT | K25: =IF(SUM($K$20:$K$24)<SUM($J$15:$J$18),-SUM($K$20:$K$24)+SUM($J$15:$J$18),0) -> 0 | N25: 0 | S25: =Q25-N25 -> 0
J26: =SUM(J15:J25) -> 301895 | K26: =SUM(K15:K25) -> 301895 | L26: =IF(J26=K26,"<- Debits and Credits equal each other.","<- Debits and Credits do not equal each other.") -> <- Debits and Credits equal each other.
B27: * THESE ASSET AMOUNTS SHOULD BE REPORTED AS BEGINNING BALANCES ON REPORT 18.
B28: ** This amount should be included in the beginning balance column on the LS-Lease Liability and LS-Check Figures Tabs.
A31: Record New Leases (new leases only)
A32: 1 | B32: Record lease contract commencement (fund-based entries only)
B33: Dr: Acct 0842 - CAPITAL OUTLAY | J33: 68462
C34: Cr: Acct 0789 - LEASE AND OTHER FINANCING PROCEEDS | K34: 68462
C35: =IF($F$7="Proprietary","Cr: Acct 0870 - SERVICES & CHARGES (MG ADJ)",VLOOKUP($F$9,'Drop Down Menus'!$F$2:$G$10,2,FALSE)) -> Cr: Acct 0820 - NAT RES & ENVIRON (GAAP ADJ)
J36: =SUM(J33:J35) -> 68462 | K36: =SUM(K33:K35) -> 68462 | L36: =IF(J36=K36,"<- Debits and Credits equal each other.","<- Debits and Credits do not equal each other.") -> <- Debits and Credits equal each other.
A38: 2 | B38: Record leased assets.
A39: *Rpt 18 | B39: Dr: Acct 0476 - RIGHT-TO-USE LEASED LAND - AMORTIZABLE
A40: *Rpt 18 | B40: Dr: Acct 0478 - RIGHT-TO-USE LEASED EQUIPMENT - AMORTIZABLE
A41: *Rpt 18 | B41: Dr: Acct 0477 - RIGHT-TO-USE LEASED BUILDINGS - AMORTIZABLE | J41: 68462
C42: Cr: Acct 0842 - CAPITAL OUTLAY | K42: 68462
B43: * THESE AMOUNTS SHOULD BE INCLUDED AS "ADDITIONS" ON REPORT 18. | J43: =SUM(J39:J42) -> 68462 | K43: =SUM(K39:K42) -> 68462 | L43: =IF(J43=K43,"<- Debits and Credits equal each other.","<- Debits and Credits do not equal each other.") -> <- Debits and Credits equal each other.
A46: 3 | B46: Replace proceeds from leases with right-to-use lease liability.
B47: Dr: Acct 0789 - LEASE AND OTHER FINANCING PROCEEDS | J47: 68462
A48: **LS LL/CF | C48: Cr: Acct 0691 - RIGHT-TO-USE LEASE LIABILITY | K48: 68462
J49: =SUM(J47:J48) -> 68462 | K49: =SUM(K47:K48) -> 68462 | L49: =IF(J49=K49,"<- Debits and Credits equal each other.","<- Debits and Credits do not equal each other.") -> <- Debits and Credits equal each other.
B50: ** This amount should be included in the additions column on the LS-Lease Liability and LS-Check Figures Tabs.
A53: Record Annual Activity (all leases)
A54: 4 | B54: Record amortization of the leased assets for the year.
B55: Dr: Acct 0875 - DEPRECIATION/AMORTIZATION | J55: 44820
C56: Cr: Acct 0485 - ACCUMULATED AMORTIZATION - RIGHT-TO-USE LEASED LAND
C57: Cr: Acct 0479 - ACCUMULATED AMORTIZATION - RIGHT-TO-USE LEASED EQUIPMENT
C58: Cr: Acct 0486 - ACCUMULATED AMORTIZATION - RIGHT-TO-USE LEASED BUILDINGS | K58: 44820
J59: =SUM(J55:J58) -> 44820 | K59: =SUM(K55:K58) -> 44820 | L59: =IF(J59=K59,"<- Debits and Credits equal each other.","<- Debits and Credits do not equal each other.") -> <- Debits and Credits equal each other.
A61: 5 | B61: Reclassify rents and leases exp. to lease contract principal and interest exp.
B62: Dr: Acct 0848 - DEBT SERVICE - PRINCIPAL LEASES | J62: 40747.24
B63: =IF(F7="Governmental","Dr: Acct 0851 - DEBT SERVICE - INTEREST LEASES","Dr: Acct 0894 - INTEREST EXPENSE AND FISCAL CHARGES") -> Dr: Acct 0851 - DEBT SERVICE - INTEREST LEASES | J63: 5008.67
C64: =IF($F$7="Proprietary","Cr: Acct 0870 - SERVICES & CHARGES (MG ADJ)",VLOOKUP($F$9,'Drop Down Menus'!$F$2:$G$10,2,FALSE)) -> Cr: Acct 0820 - NAT RES & ENVIRON (GAAP ADJ) | K64: 45755
J65: =SUM(J62:J64) -> 45755.91 | K65: =SUM(K62:K64) -> 45755 | L65: =IF(J65=K65,"<- Debits and Credits equal each other.","<- Debits and Credits do not equal each other.") -> <- Debits and Credits do not equal each other.
A67: 6 | B67: Reduce lease contracts liability for total current year principal payments.
A68: **LS LL/CF | B68: Dr: Acct 0691 - RIGHT-TO-USE LEASE LIABILITY | J68: 40747
C69: Cr: Acct 0848 - DEBT SERVICE - PRINCIPAL LEASES | K69: 40747
J70: =SUM(J68:J69) -> 40747 | K70: =SUM(K68:K69) -> 40747 | L70: =IF(J70=K70,"<- Debits and Credits equal each other.","<- Debits and Credits do not equal each other.") -> <- Debits and Credits equal each other.
B71: ** This amount should be included in the deductions column on the LS-Lease Liability and LS-Check Figures Tabs.
A74: 7 | B74: Reclassify the principal amount due in the next FY to the current liability.
A75: **LS LL/CF | B75: Dr: Acct 0691 - RIGHT-TO-USE LEASE LIABILITY | J75: 41707
C76: Cr: Acct 0649 - RIGHT-TO-USE LEASE LIABILITY (CURRENT PORTION LT) | K76: 41707
B77: NOTE: This is an annual accrual. It is to be reversed at the start of the next fiscal year. SCO combines the current and non current amount in Entry #0 to reestablish the beginning balances. No action required. | J77: =SUM(J75:J76) -> 41707 | K77: =SUM(K75:K76) -> 41707 | L77: =IF(J77=K77,"<- Debits and Credits equal each other.","<- Debits and Credits do not equal each other.") -> <- Debits and Credits equal each other.
B80: ** This amount should be included in the due in one year column on the LS-Lease Liability and LS-Check Figures Tabs.
A83: Remove Lease Asset at the End of the Lease Term (only at the end of the lease term)
A84: 8 | B84: Record entry to write off the lease asset and accumulated amortization at the end of the lease term.
B85: Dr: Acct 0485 - ACCUMULATED AMORTIZATION - RIGHT-TO-USE LEASED LAND
B86: Dr: Acct 0479 - ACCUMULATED AMORTIZATION - RIGHT-TO-USE LEASED EQUIPMENT
B87: Dr: Acct 0486 - ACCUMULATED AMORTIZATION - RIGHT-TO-USE LEASED BUILDINGS | J87: 16369
A88: *Rpt 18 | C88: Cr: Acct 0476 - RIGHT-TO-USE LEASED LAND - AMORTIZABLE
A89: *Rpt 18 | C89: Cr: Acct 0478 - RIGHT-TO-USE LEASED EQUIPMENT - AMORTIZABLE
A90: *Rpt 18 | C90: Cr: Acct 0477 - RIGHT-TO-USE LEASED BUILDINGS - AMORTIZABLE | K90: 16369
B91: * THESE AMOUNTS SHOULD BE INCLUDED AS "DEDUCTIONS" ON REPORT 18. | J91: =SUM(J85:J90) -> 16369 | K91: =SUM(K85:K90) -> 16369 | L91: =IF(J91=K91,"<- Debits and Credits equal each other.","<- Debits and Credits do not equal each other.") -> <- Debits and Credits equal each other.
A94: Lease Remeasurement and Modifications (only if a significant modification occurred during the fiscal year)
A95: 9 | B95: Record early termination or lease modifications to decrease in the RTU leased asset.
A96: **LS LL/CF | B96: Dr: Acct 0691 - RIGHT-TO-USE LEASE LIABILITY
B97: Dr: Acct 0485 - ACCUMULATED AMORTIZATION - RIGHT-TO-USE LEASED LAND
B98: Dr: Acct 0479 - ACCUMULATED AMORTIZATION - RIGHT-TO-USE LEASED EQUIPMENT
B99: Dr: Acct 0486 - ACCUMULATED AMORTIZATION - RIGHT-TO-USE LEASED BUILDINGS
B100: =IF($F$7="Proprietary","Dr: Acct 0870 - SERVICES & CHARGES (MG ADJ)",VLOOKUP($F$9,'Drop Down Menus'!$F$2:$H$10,3,FALSE)) -> Dr: Acct 0820 - NAT RES & ENVIRON (GAAP ADJ)
A101: *Rpt 18 | C101: Cr: Acct 0476 - RIGHT-TO-USE LEASED LAND - AMORTIZABLE
A102: *Rpt 18 | C102: Cr: Acct 0478 - RIGHT-TO-USE LEASED EQUIPMENT - AMORTIZABLE
A103: *Rpt 18 | C103: Cr: Acct 0477 - RIGHT-TO-USE LEASED BUILDINGS - AMORTIZABLE
C104: =IF($F$7="Proprietary","Dr: Acct 0870 - SERVICES & CHARGES (MG ADJ)",VLOOKUP($F$9,'Drop Down Menus'!$F$2:$G$10,2,FALSE)) -> Cr: Acct 0820 - NAT RES & ENVIRON (GAAP ADJ)
B105: * THESE AMOUNTS SHOULD BE INCLUDED AS "DEDUCTIONS" ON REPORT 18. | J105: =SUM(J96:J104) -> 0 | K105: =SUM(K96:K104) -> 0 | L105: =IF(J105=K105,"<- Debits and Credits equal each other.","<- Debits and Credits do not equal each other.") -> <- Debits and Credits equal each other.
B106: ** This amount should be included in the deductions column on the LS-Lease Liability and LS-Check Figures Tabs.
A109: 10 | B109: Record lease modifications to increase in the RTU leased asset.
A110: *Rpt 18 | B110: Dr: Acct 0476 - RIGHT-TO-USE LEASED LAND - AMORTIZABLE
A111: *Rpt 18 | B111: Dr: Acct 0478 - RIGHT-TO-USE LEASED EQUIPMENT - AMORTIZABLE
A112: *Rpt 18 | B112: Dr: Acct 0477 - RIGHT-TO-USE LEASED BUILDINGS - AMORTIZABLE
A113: **LS LL/CF | C113: Cr: Acct 0691 - RIGHT-TO-USE LEASE LIABILITY
B114: * THESE AMOUNTS SHOULD BE INCLUDED AS "ADDITIONS" ON REPORT 18. | J114: =SUM(J110:J113) -> 0 | K114: =SUM(K110:K113) -> 0 | L114: =IF(J114=K114,"<- Debits and Credits equal each other.","<- Debits and Credits do not equal each other.") -> <- Debits and Credits equal each other.
B115: ** This amount should be included in the additions column on the LS-Lease Liability and LS-Check Figures Tabs.
D120: Informational - Ending Balances of Assets and Liabilities
K121: Debit (Credit)
D122: Acct 0476 - RIGHT-TO-USE LEASED LAND - AMORTIZABLE | K122: =J15+J39-K88-K101+J110 -> 0
D123: Acct 0478 - RIGHT-TO-USE LEASED EQUIPMENT - AMORTIZABLE | K123: =J16+J40-K89-K102+J111 -> 0
D124: Acct 0477 - RIGHT-TO-USE LEASED BUILDINGS - AMORTIZABLE | K124: =J17+J41-K90-K103+J112 -> 347675
D125: Acct 0485 - ACCUMULATED AMORTIZATION - RIGHT-TO-USE LEASED LAND | K125: =-K20-K56+J85+J97 -> 0
...

Sheet LS-Fund 6051 Journal Entries
A1: Lessee-Type Contracts Fund-by-Fund Journal Entries Form (to be submitted to the SCO annually—one form per fund)
A2: Manually complete every yellow field in this worksheet—there are no automatically calculated data-entry cells in this worksheet.
A3: Fiscal Year: | F3: 2023–2024
A4: Organization Name: | F4: Department of Water Resources
A5: Organization Code (4-Digits): | F5: 3860
A6: Fund Number (4-Digits): | F6: 6051
A7: Fund Classification: | F7: Governmental
A8: Fund Type: | F8: Governmental Fund
A9: Functional Expense: | F9: =IFERROR(IF(F7="Proprietary","Proprietary Fund",VLOOKUP(F5,qryIndex02a!$A$2:$K$654,4,FALSE)),"Unidentified") -> RESOURCES
A12: Establish Beginning Balances (existing leases only)
A13: Entry #
A14: 0 | B14: Roll forward prior year right-to-use leases to record opening balances. | M14: Combined Lessee Templates | P14: From SCO BB List | S14: Difference
A15: *Rpt 18 | B15: Dr: Acct 0476 - RIGHT-TO-USE LEASED LAND - AMORTIZABLE | J15: =M15 -> 0 | S15: =P15-M15 -> 0
A16: *Rpt 18 | B16: Dr: Acct 0478 - RIGHT-TO-USE LEASED EQUIPMENT - AMORTIZABLE | J16: =M16 -> 0 | S16: =P16-M16 -> 0
A17: *Rpt 18 | B17: Dr: Acct 0477 - RIGHT-TO-USE LEASED BUILDINGS - AMORTIZABLE | J17: =M17 -> 209450 | M17: 209450 | P17: 395727 | S17: =P17-M17 -> 186277
B18: Dr: Acct 0950 - BEGINNING FUND BALANCE | J18: =P18 -> 8454 | M18: 4672 | P18: =IF(SUM($Q$20:$Q$23)>SUM($P$15:$P$17),SUM($Q$20:$Q$23)-SUM($P$15:$P$17),0) -> 8454 | S18: =P18-M18 -> 3782
B19: Dr: Acct 0952 - BEGINNING FUND ADJUSTMENT/PRIOR PERIOD ADJUSTMENT | J19: =IF(SUM($K$20:$K$24)>SUM($J$15:$J$18),SUM($K$20:$K$24)-SUM($J$15:$J$18),0) -> 0 | M19: 0 | S19: =P19-M19 -> 0
C20: Cr: Acct 0485 - ACCUMULATED AMORTIZATION - RIGHT-TO-USE LEASED LAND | K20: =N20 -> 0 | S20: =P20-M20 -> 0
C21: Cr: Acct 0479 - ACCUMULATED AMORTIZATION - RIGHT-TO-USE LEASED EQUIPMENT | K21: =N21 -> 0 | S21: =Q21-N21 -> 0
C22: Cr: Acct 0486 - ACCUMULATED AMORTIZATION - RIGHT-TO-USE LEASED BUILDINGS | K22: =N22 -> 59307 | N22: 59307 | Q22: 112052 | S22: =Q22-N22 -> 52745
A23: **LS LL/CF | C23: Cr: Acct 0691 - RIGHT-TO-USE LEASE LIABILITY | K23: =N23 -> 154617 | N23: 154617 | Q23: 292129 | S23: =Q23-N23 -> 137512
C24: Cr: Acct 0950 - BEGINNING FUND BALANCE | K24: =Q24 -> 0 | N24: 198 | Q24: =IF(SUM($Q$20:$Q$23)<SUM($P$15:$P$17),-SUM($Q$20:$Q$23)+SUM($P$15:$P$17),0) -> 0 | S24: =Q24-N24 -> -198
C25: Cr: Acct 0952 - BEGINNING FUND ADJUSTMENT/PRIOR PERIOD ADJUSTMENT | K25: =IF(SUM($K$20:$K$24)<SUM($J$15:$J$18),-SUM($K$20:$K$24)+SUM($J$15:$J$18),0) -> 3980 | N25: 0 | S25: =Q25-N25 -> 0
J26: =SUM(J15:J25) -> 217904 | K26: =SUM(K15:K25) -> 217904 | L26: =IF(J26=K26,"<- Debits and Credits equal each other.","<- Debits and Credits do not equal each other.") -> <- Debits and Credits equal each other.
B27: * THESE ASSET AMOUNTS SHOULD BE REPORTED AS BEGINNING BALANCES ON REPORT 18.
B28: ** This amount should be included in the beginning balance column on the LS-Lease Liability and LS-Check Figures Tabs.
A31: Record New Leases (new leases only)
A32: 1 | B32: Record lease contract commencement (fund-based entries only)
B33: Dr: Acct 0842 - CAPITAL OUTLAY | J33: 48512
C34: Cr: Acct 0789 - LEASE AND OTHER FINANCING PROCEEDS | K34: 48512
C35: =IF($F$7="Proprietary","Cr: Acct 0870 - SERVICES & CHARGES (MG ADJ)",VLOOKUP($F$9,'Drop Down Menus'!$F$2:$G$10,2,FALSE)) -> Cr: Acct 0820 - NAT RES & ENVIRON (GAAP ADJ)
J36: =SUM(J33:J35) -> 48512 | K36: =SUM(K33:K35) -> 48512 | L36: =IF(J36=K36,"<- Debits and Credits equal each other.","<- Debits and Credits do not equal each other.") -> <- Debits and Credits equal each other.
A38: 2 | B38: Record leased assets.
A39: *Rpt 18 | B39: Dr: Acct 0476 - RIGHT-TO-USE LEASED LAND - AMORTIZABLE
A40: *Rpt 18 | B40: Dr: Acct 0478 - RIGHT-TO-USE LEASED EQUIPMENT - AMORTIZABLE
A41: *Rpt 18 | B41: Dr: Acct 0477 - RIGHT-TO-USE LEASED BUILDINGS - AMORTIZABLE | J41: 48512
C42: Cr: Acct 0842 - CAPITAL OUTLAY | K42: 48512
B43: * THESE AMOUNTS SHOULD BE INCLUDED AS "ADDITIONS" ON REPORT 18. | J43: =SUM(J39:J42) -> 48512 | K43: =SUM(K39:K42) -> 48512 | L43: =IF(J43=K43,"<- Debits and Credits equal each other.","<- Debits and Credits do not equal each other.") -> <- Debits and Credits equal each other.
A46: 3 | B46: Replace proceeds from leases with right-to-use lease liability.
B47: Dr: Acct 0789 - LEASE AND OTHER FINANCING PROCEEDS | J47: 48512
A48: **LS LL/CF | C48: Cr: Acct 0691 - RIGHT-TO-USE LEASE LIABILITY | K48: 48512
J49: =SUM(J47:J48) -> 48512 | K49: =SUM(K47:K48) -> 48512 | L49: =IF(J49=K49,"<- Debits and Credits equal each other.","<- Debits and Credits do not equal each other.") -> <- Debits and Credits equal each other.
B50: ** This amount should be included in the additions column on the LS-Lease Liability and LS-Check Figures Tabs.
A53: Record Annual Activity (all leases)
A54: 4 | B54: Record amortization of the leased assets for the year.
B55: Dr: Acct 0875 - DEPRECIATION/AMORTIZATION | J55: 31759
C56: Cr: Acct 0485 - ACCUMULATED AMORTIZATION - RIGHT-TO-USE LEASED LAND
C57: Cr: Acct 0479 - ACCUMULATED AMORTIZATION - RIGHT-TO-USE LEASED EQUIPMENT
C58: Cr: Acct 0486 - ACCUMULATED AMORTIZATION - RIGHT-TO-USE LEASED BUILDINGS | K58: 31759
J59: =SUM(J55:J58) -> 31759 | K59: =SUM(K55:K58) -> 31759 | L59: =IF(J59=K59,"<- Debits and Credits equal each other.","<- Debits and Credits do not equal each other.") -> <- Debits and Credits equal each other.
A61: 5 | B61: Reclassify rents and leases exp. to lease contract principal and interest exp.
B62: Dr: Acct 0848 - DEBT SERVICE - PRINCIPAL LEASES | J62: 28874
B63: =IF(F7="Governmental","Dr: Acct 0851 - DEBT SERVICE - INTEREST LEASES","Dr: Acct 0894 - INTEREST EXPENSE AND FISCAL CHARGES") -> Dr: Acct 0851 - DEBT SERVICE - INTEREST LEASES | J63: 3548
C64: =IF($F$7="Proprietary","Cr: Acct 0870 - SERVICES & CHARGES (MG ADJ)",VLOOKUP($F$9,'Drop Down Menus'!$F$2:$G$10,2,FALSE)) -> Cr: Acct 0820 - NAT RES & ENVIRON (GAAP ADJ) | K64: 32422
J65: =SUM(J62:J64) -> 32422 | K65: =SUM(K62:K64) -> 32422 | L65: =IF(J65=K65,"<- Debits and Credits equal each other.","<- Debits and Credits do not equal each other.") -> <- Debits and Credits equal each other.
A67: 6 | B67: Reduce lease contracts liability for total current year principal payments.
A68: **LS LL/CF | B68: Dr: Acct 0691 - RIGHT-TO-USE LEASE LIABILITY | J68: 28874
C69: Cr: Acct 0848 - DEBT SERVICE - PRINCIPAL LEASES | K69: 28874
J70: =SUM(J68:J69) -> 28874 | K70: =SUM(K68:K69) -> 28874 | L70: =IF(J70=K70,"<- Debits and Credits equal each other.","<- Debits and Credits do not equal each other.") -> <- Debits and Credits equal each other.
B71: ** This amount should be included in the deductions column on the LS-Lease Liability and LS-Check Figures Tabs.
A74: 7 | B74: Reclassify the principal amount due in the next FY to the current liability.
A75: **LS LL/CF | B75: Dr: Acct 0691 - RIGHT-TO-USE LEASE LIABILITY | J75: 29553
C76: Cr: Acct 0649 - RIGHT-TO-USE LEASE LIABILITY (CURRENT PORTION LT) | K76: 29553
B77: NOTE: This is an annual accrual. It is to be reversed at the start of the next fiscal year. SCO combines the current and non current amount in Entry #0 to reestablish the beginning balances. No action required. | J77: =SUM(J75:J76) -> 29553 | K77: =SUM(K75:K76) -> 29553 | L77: =IF(J77=K77,"<- Debits and Credits equal each other.","<- Debits and Credits do not equal each other.") -> <- Debits and Credits equal each other.
B80: ** This amount should be included in the due in one year column on the LS-Lease Liability and LS-Check Figures Tabs.
A83: Remove Lease Asset at the End of the Lease Term (only at the end of the lease term)
A84: 8 | B84: Record entry to write off the lease asset and accumulated amortization at the end of the lease term.
B85: Dr: Acct 0485 - ACCUMULATED AMORTIZATION - RIGHT-TO-USE LEASED LAND
B86: Dr: Acct 0479 - ACCUMULATED AMORTIZATION - RIGHT-TO-USE LEASED EQUIPMENT
B87: Dr: Acct 0486 - ACCUMULATED AMORTIZATION - RIGHT-TO-USE LEASED BUILDINGS | J87: 11599
A88: *Rpt 18 | C88: Cr: Acct 0476 - RIGHT-TO-USE LEASED LAND - AMORTIZABLE
A89: *Rpt 18 | C89: Cr: Acct 0478 - RIGHT-TO-USE LEASED EQUIPMENT - AMORTIZABLE
A90: *Rpt 18 | C90: Cr: Acct 0477 - RIGHT-TO-USE LEASED BUILDINGS - AMORTIZABLE | K90: 11599
B91: * THESE AMOUNTS SHOULD BE INCLUDED AS "DEDUCTIONS" ON REPORT 18. | J91: =SUM(J85:J90) -> 11599 | K91: =SUM(K85:K90) -> 11599 | L91: =IF(J91=K91,"<- Debits and Credits equal each other.","<- Debits and Credits do not equal each other.") -> <- Debits and Credits equal each other.
A94: Lease Remeasurement and Modifications (only if a significant modification occurred during the fiscal year)
A95: 9 | B95: Record early termination or lease modifications to decrease in the RTU leased asset.
A96: **LS LL/CF | B96: Dr: Acct 0691 - RIGHT-TO-USE LEASE LIABILITY
B97: Dr: Acct 0485 - ACCUMULATED AMORTIZATION - RIGHT-TO-USE LEASED LAND
B98: Dr: Acct 0479 - ACCUMULATED AMORTIZATION - RIGHT-TO-USE LEASED EQUIPMENT
B99: Dr: Acct 0486 - ACCUMULATED AMORTIZATION - RIGHT-TO-USE LEASED BUILDINGS
B100: =IF($F$7="Proprietary","Dr: Acct 0870 - SERVICES & CHARGES (MG ADJ)",VLOOKUP($F$9,'Drop Down Menus'!$F$2:$H$10,3,FALSE)) -> Dr: Acct 0820 - NAT RES & ENVIRON (GAAP ADJ)
A101: *Rpt 18 | C101: Cr: Acct 0476 - RIGHT-TO-USE LEASED LAND - AMORTIZABLE
A102: *Rpt 18 | C102: Cr: Acct 0478 - RIGHT-TO-USE LEASED EQUIPMENT - AMORTIZABLE
A103: *Rpt 18 | C103: Cr: Acct 0477 - RIGHT-TO-USE LEASED BUILDINGS - AMORTIZABLE
C104: =IF($F$7="Proprietary","Dr: Acct 0870 - SERVICES & CHARGES (MG ADJ)",VLOOKUP($F$9,'Drop Down Menus'!$F$2:$G$10,2,FALSE)) -> Cr: Acct 0820 - NAT RES & ENVIRON (GAAP ADJ)
B105: * THESE AMOUNTS SHOULD BE INCLUDED AS "DEDUCTIONS" ON REPORT 18. | J105: =SUM(J96:J104) -> 0 | K105: =SUM(K96:K104) -> 0 | L105: =IF(J105=K105,"<- Debits and Credits equal each other.","<- Debits and Credits do not equal each other.") -> <- Debits and Credits equal each other.
B106: ** This amount should be included in the deductions column on the LS-Lease Liability and LS-Check Figures Tabs.
A109: 10 | B109: Record lease modifications to increase in the RTU leased asset.
A110: *Rpt 18 | B110: Dr: Acct 0476 - RIGHT-TO-USE LEASED LAND - AMORTIZABLE
A111: *Rpt 18 | B111: Dr: Acct 0478 - RIGHT-TO-USE LEASED EQUIPMENT - AMORTIZABLE
A112: *Rpt 18 | B112: Dr: Acct 0477 - RIGHT-TO-USE LEASED BUILDINGS - AMORTIZABLE
A113: **LS LL/CF | C113: Cr: Acct 0691 - RIGHT-TO-USE LEASE LIABILITY
B114: * THESE AMOUNTS SHOULD BE INCLUDED AS "ADDITIONS" ON REPORT 18. | J114: =SUM(J110:J113) -> 0 | K114: =SUM(K110:K113) -> 0 | L114: =IF(J114=K114,"<- Debits and Credits equal each other.","<- Debits and Credits do not equal each other.") -> <- Debits and Credits equal each other.
B115: ** This amount should be included in the additions column on the LS-Lease Liability and LS-Check Figures Tabs.
D120: Informational - Ending Balances of Assets and Liabilities
K121: Debit (Credit)
D122: Acct 0476 - RIGHT-TO-USE LEASED LAND - AMORTIZABLE | K122: =J15+J39-K88-K101+J110 -> 0
D123: Acct 0478 - RIGHT-TO-USE LEASED EQUIPMENT - AMORTIZABLE | K123: =J16+J40-K89-K102+J111 -> 0
D124: Acct 0477 - RIGHT-TO-USE LEASED BUILDINGS - AMORTIZABLE | K124: =J17+J41-K90-K103+J112 -> 246363
D125: Acct 0485 - ACCUMULATED AMORTIZATION - RIGHT-TO-USE LEASED LAND | K125: =-K20-K56+J85+J97 -> 0
...

Sheet LS-Fund 6083 Journal Entries
A1: Lessee-Type Contracts Fund-by-Fund Journal Entries Form (to be submitted to the SCO annually—one form per fund)
A2: Manually complete every yellow field in this worksheet—there are no automatically calculated data-entry cells in this worksheet.
A3: Fiscal Year: | F3: 2023–2024
A4: Organization Name: | F4: Department of Water Resources
A5: Organization Code (4-Digits): | F5: 3860
A6: Fund Number (4-Digits): | F6: 6083
A7: Fund Classification: | F7: Governmental
A8: Fund Type: | F8: Governmental Fund
A9: Functional Expense: | F9: =IFERROR(IF(F7="Proprietary","Proprietary Fund",VLOOKUP(F5,qryIndex02a!$A$2:$K$654,4,FALSE)),"Unidentified") -> RESOURCES
A12: Establish Beginning Balances (existing leases only)
A13: Entry #
A14: 0 | B14: Roll forward prior year right-to-use leases to record opening balances. | M14: Combined Lessee Templates | P14: From SCO BB List | S14: Difference
A15: *Rpt 18 | B15: Dr: Acct 0476 - RIGHT-TO-USE LEASED LAND - AMORTIZABLE | J15: =M15 -> 0 | S15: =P15-M15 -> 0
A16: *Rpt 18 | B16: Dr: Acct 0478 - RIGHT-TO-USE LEASED EQUIPMENT - AMORTIZABLE | J16: =M16 -> 0 | S16: =P16-M16 -> 0
A17: *Rpt 18 | B17: Dr: Acct 0477 - RIGHT-TO-USE LEASED BUILDINGS - AMORTIZABLE | J17: =M17 -> 743071 | M17: 743071 | P17: 1349370 | S17: =P17-M17 -> 606299
B18: Dr: Acct 0950 - BEGINNING FUND BALANCE | J18: =P18 -> 28824 | M18: 16575 | P18: =IF(SUM($Q$20:$Q$23)>SUM($P$15:$P$17),SUM($Q$20:$Q$23)-SUM($P$15:$P$17),0) -> 28824 | S18: =P18-M18 -> 12249
B19: Dr: Acct 0952 - BEGINNING FUND ADJUSTMENT/PRIOR PERIOD ADJUSTMENT | J19: =IF(SUM($K$20:$K$24)>SUM($J$15:$J$18),SUM($K$20:$K$24)-SUM($J$15:$J$18),0) -> 0 | M19: 0 | S19: =P19-M19 -> 0
C20: Cr: Acct 0485 - ACCUMULATED AMORTIZATION - RIGHT-TO-USE LEASED LAND | K20: =N20 -> 0 | S20: =P20-M20 -> 0
C21: Cr: Acct 0479 - ACCUMULATED AMORTIZATION - RIGHT-TO-USE LEASED EQUIPMENT | K21: =N21 -> 0 | S21: =Q21-N21 -> 0
C22: Cr: Acct 0486 - ACCUMULATED AMORTIZATION - RIGHT-TO-USE LEASED BUILDINGS | K22: =N22 -> 210404 | N22: 210404 | Q22: 382081 | S22: =Q22-N22 -> 171677
A23: **LS LL/CF | C23: Cr: Acct 0691 - RIGHT-TO-USE LEASE LIABILITY | K23: =N23 -> 548539 | N23: 548539 | Q23: 996113 | S23: =Q23-N23 -> 447574
C24: Cr: Acct 0950 - BEGINNING FUND BALANCE | K24: =Q24 -> 0 | N24: 702 | Q24: =IF(SUM($Q$20:$Q$23)<SUM($P$15:$P$17),-SUM($Q$20:$Q$23)+SUM($P$15:$P$17),0) -> 0 | S24: =Q24-N24 -> -702
C25: Cr: Acct 0952 - BEGINNING FUND ADJUSTMENT/PRIOR PERIOD ADJUSTMENT | K25: =IF(SUM($K$20:$K$24)<SUM($J$15:$J$18),-SUM($K$20:$K$24)+SUM($J$15:$J$18),0) -> 12952 | N25: 0 | S25: =Q25-N25 -> 0
J26: =SUM(J15:J25) -> 771895 | K26: =SUM(K15:K25) -> 771895 | L26: =IF(J26=K26,"<- Debits and Credits equal each other.","<- Debits and Credits do not equal each other.") -> <- Debits and Credits equal each other.
B27: * THESE ASSET AMOUNTS SHOULD BE REPORTED AS BEGINNING BALANCES ON REPORT 18.
B28: ** This amount should be included in the beginning balance column on the LS-Lease Liability and LS-Check Figures Tabs.
A31: Record New Leases (new leases only)
A32: 1 | B32: Record lease contract commencement (fund-based entries only)
B33: Dr: Acct 0842 - CAPITAL OUTLAY | J33: 172108
C34: Cr: Acct 0789 - LEASE AND OTHER FINANCING PROCEEDS | K34: 172108
C35: =IF($F$7="Proprietary","Cr: Acct 0870 - SERVICES & CHARGES (MG ADJ)",VLOOKUP($F$9,'Drop Down Menus'!$F$2:$G$10,2,FALSE)) -> Cr: Acct 0820 - NAT RES & ENVIRON (GAAP ADJ)
J36: =SUM(J33:J35) -> 172108 | K36: =SUM(K33:K35) -> 172108 | L36: =IF(J36=K36,"<- Debits and Credits equal each other.","<- Debits and Credits do not equal each other.") -> <- Debits and Credits equal each other.
A38: 2 | B38: Record leased assets.
A39: *Rpt 18 | B39: Dr: Acct 0476 - RIGHT-TO-USE LEASED LAND - AMORTIZABLE
A40: *Rpt 18 | B40: Dr: Acct 0478 - RIGHT-TO-USE LEASED EQUIPMENT - AMORTIZABLE
A41: *Rpt 18 | B41: Dr: Acct 0477 - RIGHT-TO-USE LEASED BUILDINGS - AMORTIZABLE | J41: 172108
C42: Cr: Acct 0842 - CAPITAL OUTLAY | K42: 172108
B43: * THESE AMOUNTS SHOULD BE INCLUDED AS "ADDITIONS" ON REPORT 18. | J43: =SUM(J39:J42) -> 172108 | K43: =SUM(K39:K42) -> 172108 | L43: =IF(J43=K43,"<- Debits and Credits equal each other.","<- Debits and Credits do not equal each other.") -> <- Debits and Credits equal each other.
A46: 3 | B46: Replace proceeds from leases with right-to-use lease liability.
B47: Dr: Acct 0789 - LEASE AND OTHER FINANCING PROCEEDS | J47: 172108
A48: **LS LL/CF | C48: Cr: Acct 0691 - RIGHT-TO-USE LEASE LIABILITY | K48: 172108
J49: =SUM(J47:J48) -> 172108 | K49: =SUM(K47:K48) -> 172108 | L49: =IF(J49=K49,"<- Debits and Credits equal each other.","<- Debits and Credits do not equal each other.") -> <- Debits and Credits equal each other.
B50: ** This amount should be included in the additions column on the LS-Lease Liability and LS-Check Figures Tabs.
A53: Record Annual Activity (all leases)
A54: 4 | B54: Record amortization of the leased assets for the year.
B55: Dr: Acct 0875 - DEPRECIATION/AMORTIZATION | J55: 112673
C56: Cr: Acct 0485 - ACCUMULATED AMORTIZATION - RIGHT-TO-USE LEASED LAND
C57: Cr: Acct 0479 - ACCUMULATED AMORTIZATION - RIGHT-TO-USE LEASED EQUIPMENT
C58: Cr: Acct 0486 - ACCUMULATED AMORTIZATION - RIGHT-TO-USE LEASED BUILDINGS | K58: 112673
J59: =SUM(J55:J58) -> 112673 | K59: =SUM(K55:K58) -> 112673 | L59: =IF(J59=K59,"<- Debits and Credits equal each other.","<- Debits and Credits do not equal each other.") -> <- Debits and Credits equal each other.
A61: 5 | B61: Reclassify rents and leases exp. to lease contract principal and interest exp.
B62: Dr: Acct 0848 - DEBT SERVICE - PRINCIPAL LEASES | J62: 102436
B63: =IF(F7="Governmental","Dr: Acct 0851 - DEBT SERVICE - INTEREST LEASES","Dr: Acct 0894 - INTEREST EXPENSE AND FISCAL CHARGES") -> Dr: Acct 0851 - DEBT SERVICE - INTEREST LEASES | J63: 12589
C64: =IF($F$7="Proprietary","Cr: Acct 0870 - SERVICES & CHARGES (MG ADJ)",VLOOKUP($F$9,'Drop Down Menus'!$F$2:$G$10,2,FALSE)) -> Cr: Acct 0820 - NAT RES & ENVIRON (GAAP ADJ) | K64: 115024
J65: =SUM(J62:J64) -> 115025 | K65: =SUM(K62:K64) -> 115024 | L65: =IF(J65=K65,"<- Debits and Credits equal each other.","<- Debits and Credits do not equal each other.") -> <- Debits and Credits do not equal each other.
A67: 6 | B67: Reduce lease contracts liability for total current year principal payments.
A68: **LS LL/CF | B68: Dr: Acct 0691 - RIGHT-TO-USE LEASE LIABILITY | J68: 102436
C69: Cr: Acct 0848 - DEBT SERVICE - PRINCIPAL LEASES | K69: 102436
J70: =SUM(J68:J69) -> 102436 | K70: =SUM(K68:K69) -> 102436 | L70: =IF(J70=K70,"<- Debits and Credits equal each other.","<- Debits and Credits do not equal each other.") -> <- Debits and Credits equal each other.
B71: ** This amount should be included in the deductions column on the LS-Lease Liability and LS-Check Figures Tabs.
A74: 7 | B74: Reclassify the principal amount due in the next FY to the current liability.
A75: **LS LL/CF | B75: Dr: Acct 0691 - RIGHT-TO-USE LEASE LIABILITY | J75: 104847
C76: Cr: Acct 0649 - RIGHT-TO-USE LEASE LIABILITY (CURRENT PORTION LT) | K76: 104847
B77: NOTE: This is an annual accrual. It is to be reversed at the start of the next fiscal year. SCO combines the current and non current amount in Entry #0 to reestablish the beginning balances. No action required. | J77: =SUM(J75:J76) -> 104847 | K77: =SUM(K75:K76) -> 104847 | L77: =IF(J77=K77,"<- Debits and Credits equal each other.","<- Debits and Credits do not equal each other.") -> <- Debits and Credits equal each other.
B80: ** This amount should be included in the due in one year column on the LS-Lease Liability and LS-Check Figures Tabs.
A83: Remove Lease Asset at the End of the Lease Term (only at the end of the lease term)
A84: 8 | B84: Record entry to write off the lease asset and accumulated amortization at the end of the lease term.
B85: Dr: Acct 0485 - ACCUMULATED AMORTIZATION - RIGHT-TO-USE LEASED LAND
B86: Dr: Acct 0479 - ACCUMULATED AMORTIZATION - RIGHT-TO-USE LEASED EQUIPMENT
B87: Dr: Acct 0486 - ACCUMULATED AMORTIZATION - RIGHT-TO-USE LEASED BUILDINGS | J87: 41150
A88: *Rpt 18 | C88: Cr: Acct 0476 - RIGHT-TO-USE LEASED LAND - AMORTIZABLE
A89: *Rpt 18 | C89: Cr: Acct 0478 - RIGHT-TO-USE LEASED EQUIPMENT - AMORTIZABLE
A90: *Rpt 18 | C90: Cr: Acct 0477 - RIGHT-TO-USE LEASED BUILDINGS - AMORTIZABLE | K90: 41150
B91: * THESE AMOUNTS SHOULD BE INCLUDED AS "DEDUCTIONS" ON REPORT 18. | J91: =SUM(J85:J90) -> 41150 | K91: =SUM(K85:K90) -> 41150 | L91: =IF(J91=K91,"<- Debits and Credits equal each other.","<- Debits and Credits do not equal each other.") -> <- Debits and Credits equal each other.
A94: Lease Remeasurement and Modifications (only if a significant modification occurred during the fiscal year)
A95: 9 | B95: Record early termination or lease modifications to decrease in the RTU leased asset.
A96: **LS LL/CF | B96: Dr: Acct 0691 - RIGHT-TO-USE LEASE LIABILITY
B97: Dr: Acct 0485 - ACCUMULATED AMORTIZATION - RIGHT-TO-USE LEASED LAND
B98: Dr: Acct 0479 - ACCUMULATED AMORTIZATION - RIGHT-TO-USE LEASED EQUIPMENT
B99: Dr: Acct 0486 - ACCUMULATED AMORTIZATION - RIGHT-TO-USE LEASED BUILDINGS
B100: =IF($F$7="Proprietary","Dr: Acct 0870 - SERVICES & CHARGES (MG ADJ)",VLOOKUP($F$9,'Drop Down Menus'!$F$2:$H$10,3,FALSE)) -> Dr: Acct 0820 - NAT RES & ENVIRON (GAAP ADJ)
A101: *Rpt 18 | C101: Cr: Acct 0476 - RIGHT-TO-USE LEASED LAND - AMORTIZABLE
A102: *Rpt 18 | C102: Cr: Acct 0478 - RIGHT-TO-USE LEASED EQUIPMENT - AMORTIZABLE
A103: *Rpt 18 | C103: Cr: Acct 0477 - RIGHT-TO-USE LEASED BUILDINGS - AMORTIZABLE
C104: =IF($F$7="Proprietary","Dr: Acct 0870 - SERVICES & CHARGES (MG ADJ)",VLOOKUP($F$9,'Drop Down Menus'!$F$2:$G$10,2,FALSE)) -> Cr: Acct 0820 - NAT RES & ENVIRON (GAAP ADJ)
