Workbook
Name ActuaryCredentialsGASB: [1]DeveloperInfo!$D$19
Name ActuaryNameGASB: [1]DeveloperInfo!$D$17
Name ActuaryTitleGASB: [1]DeveloperInfo!$D$18
Name AdjCNSDate: [1]DeveloperInfo!$D$33
Name AdjCNSDate1: [1]DeveloperInfo!$E$33
Name AdjCNSDateTempEnable: [1]DeveloperInfo!$F$34
Name AgencyCode: #REF!
Name AgencyCode: #REF!
Name AgencyCode1: #REF!
Name AgencyCode1: #REF!
Name AnalystGASB: [1]DeveloperInfo!$D$20
Name Annuity: #REF!
Name Annuity: #REF!
Name Annuity1: #REF!
Name Annuity1: #REF!
Name AnnuityLY: #REF!
Name AnnuityLY: #REF!
Name AssetClasses: '[2]Drop-down menus'!#REF!
Name ASTABPF: [1]DeveloperInfo!$D$36
Name ASTABPF1: [1]DeveloperInfo!$D$37
Name ASTEBPF: [1]DeveloperInfo!$F$37
Name ClientShortGASB: [1]DeveloperInfo!$D$9
Name CLPOWERDisc: [1]Adjust!$H$199
Name CLPOWERDiscMinus1: [1]Adjust!$L$199
Name CLPOWERDiscPlus1: [1]Adjust!$K$199
Name CLPOWERExp: [1]Adjust!$G$199
Name CNSDateDisc: [1]DeveloperInfo!$D$32
Name CNSDateDisc1: [1]DeveloperInfo!$E$32
Name ColaRate: [1]DeveloperInfo!$D$40
Name ConsultantNameGASB: [1]DeveloperInfo!$D$22
Name ConsultantTitleGASB: [1]DeveloperInfo!$D$23
Name Disc1DELTACENSUS: [1]Adjust!$G$102
Name Disc1INTNDIV12: [1]Adjust!$H$195
Name Disc1SINTADJBOM: [1]Adjust!$I$197
Name Disc1SINTNDIV12: [1]Adjust!$I$195
Name DiscDELTACENSUS: [1]Adjust!$H$102
Name DiscINTADJBOM: [1]Adjust!$J$197
Name DiscINTNDIV12: [1]Adjust!$J$195
Name DiscMinusOneINTADJBOM: [1]Adjust!$L$197
Name DiscMinusOneINTNDIV12: [1]Adjust!$L$195
Name DiscPlusOneINTADJBOM: [1]Adjust!$K$197
Name DiscPlusOneINTNDIV12: [1]Adjust!$K$195
Name EmployerRates: #REF!
Name EmployerRates: #REF!
Name EmployerRates1: #REF!
Name EmployerRates1: #REF!
Name EmployerRatesLEO: #REF!
Name EmployerRatesLEO: #REF!
Name EmployerRatesLEO1: #REF!
Name EmployerRatesLEO1: #REF!
Name ERData: [1]ER_DATA!$B$16:$EN$318
Name ERID: [1]ER_NPLExpense!$L$8
Name ERInfo: [1]ER_Input!$B$16:$Y$318
Name Exp1INTADJBOM: [1]Adjust!$G$197
Name Exp1INTNDIV12: [1]Adjust!$G$195
Name FracYearProj: [1]TPL!$C$43
Name FundOfficeContactGASB: [1]DeveloperInfo!$D$10
Name FYrsGASB: [1]DeveloperInfo!$D$54
Name GainLoss: [1]ER_Allocation!$P$12
Name GASBDiscMinusOneINTADJBOM: [1]Adjust!$L$197

Sheet Drop Down Menus
A1: 2021–2022 | B1: Governmental | C1: FI$Cal | D1: Yes | E1: Governmental Fund | G1: Please select fund type above.
A2: 2022–2023 | B2: Proprietary | C2: Non-FI$Cal | D2: No | E2: Proprietary - Internal Service Fund | F2: General government | G2: Cr: Acct 0808 - GENERAL GOV. (GAAP ADJ) | H2: Dr: Acct 0808 - GENERAL GOV. (GAAP ADJ)
A3: 2023–2024 | E3: Proprietary - Enterprise Fund | F3: Education | G3: Cr: Acct 0810 - EDUCATION EXP (GAAP ADJ) | H3: Dr: Acct 0810 - EDUCATION EXP (GAAP ADJ)
A4: 2024–2025 | F4: Health and human services | G4: Cr: Acct 0815 - HLTH&HUM SV SV.LAB(GAAP ADJ) | H4: Dr: Acct 0815 - HLTH&HUM SV SV.LAB(GAAP ADJ)
A5: 2025–2026 | F5: Resources | G5: Cr: Acct 0820 - NAT RES & ENVIRON (GAAP ADJ) | H5: Dr: Acct 0820 - NAT RES & ENVIRON (GAAP ADJ)
A6: 2026–2027 | F6: BUS, CONSUMER SERV, HOUSING | G6: Cr: Acct 0825 - BUS, CONSUMER SERV, HOUSING | H6: Dr: Acct 0825 - BUS, CONSUMER SERV, HOUSING
A7: 2027–2028 | F7: Transportation | G7: Cr: Acct 0830 - TRANSPORTATION (GAAP ADJ) | H7: Dr: Acct 0830 - TRANSPORTATION (GAAP ADJ)
A8: 2028–2029 | F8: CORRECTIONS AND REHABILITATION | G8: Cr: Acct 0835 - CORRECTIONS AND REHABILITATION | H8: Dr: Acct 0835 - CORRECTIONS AND REHABILITATION
A9: 2029–2030 | F9: Proprietary fund | G9: Cr: Acct 0870 - SERVICES & CHARGES (MG ADJ) | H9: Dr: Acct 0870 - SERVICES & CHARGES (MG ADJ)
A10: 2030–2031 | F10: Unidentified | G10: Cr: Acct 0XXX - FUNCTIONAL EXPENSE | H10: Dr: Acct 0XXX - FUNCTIONAL EXPENSE
A11: 2031–2032
A12: 2032–2033
A13: 2033–2034
A14: 2034–2035
A15: 2035–2036
A16: 2036–2037
A17: 2037–2038
A18: 2038–2039
A19: 2039–2040
A20: 2040–2041
A21: 2041–2042
A22: 2042–2043
... A101: 2121–2122

Sheet qryIndex02a
A1: Agency | B1: Title | C1: Hier1 | D1: Desc1 | E1: Desc2 | F1: Hier2 | G1: Hier3 | H1: Hier4 | I1: Hier5 | J1: EffectiveDate | K1: CancelDate
A2: 0000 | B2: BOND INTEREST AND REDEMPTION | C2: 9000 | D2: BOND INTEREST AND REDEMPTION | F2: 9030 | G2: 9600 | H2: 0000 | I2: 0000 | J2: 04/04/1984 | K2: 00/00/0000
A3: 0010 | B3: LEGISLATIVE, JUDICIAL AND EXEC | C3: 0808 | D3: GENERAL GOVERNMENT | F3: 0000 | G3: 0000 | H3: 0000 | I3: 0000 | J3: 07/11/2006 | K3: 00/00/0000
A4: 0015 | B4: ADD AGENCY TEST | C4: 0808 | D4: GENERAL GOVERNMENT | F4: 0000 | G4: 0000 | H4: 0000 | I4: 0000 | J4: 99/99/9999 | K4: 00/00/0000
A5: 0020 | B5: LEGISLATIVE | C5: 0808 | D5: GENERAL GOVERNMENT | F5: 0000 | G5: 0000 | H5: 0000 | I5: 0000 | J5: 99/99/9999 | K5: 00/00/0000
A6: 0100 | B6: LEGISLATURE | C6: 0808 | D6: GENERAL GOVERNMENT | F6: 0000 | G6: 0000 | H6: 0000 | I6: 0000 | J6: 99/99/9999 | K6: 00/00/0000
A7: 0110 | B7: SENATE | C7: 0808 | D7: GENERAL GOVERNMENT | F7: 0000 | G7: 0000 | H7: 0000 | I7: 0000 | J7: 06/26/1985 | K7: 00/00/0000
A8: 0120 | B8: ASSEMBLY | C8: 0808 | D8: GENERAL GOVERNMENT | F8: 0000 | G8: 0000 | H8: 0000 | I8: 0000 | J8: 06/26/1985 | K8: 00/00/0000
A9: 0130 | B9: LEGISLATIVE JOINT EXPENSES | C9: 0808 | D9: GENERAL GOVERNMENT | F9: 0000 | G9: 0000 | H9: 0000 | I9: 0000 | J9: 06/26/1985 | K9: 00/00/0000
A10: 0150 | B10: CONTRIB TO LEGIS RETIRE FUND | C10: 0808 | D10: GENERAL GOVERNMENT | F10: 0000 | G10: 0000 | H10: 0000 | I10: 0000 | J10: 07/11/2006 | K10: 00/00/0000
A11: 0155 | B11: AUDITOR GENERAL OFFICE | C11: 0808 | D11: GENERAL GOVERNMENT | F11: 0000 | G11: 0000 | H11: 0000 | I11: 0000 | J11: 99/99/9999 | K11: 00/00/0000
A12: 0160 | B12: LEGISLATIVE COUNSEL BUREAU | C12: 0808 | D12: GENERAL GOVERNMENT | F12: 0000 | G12: 0000 | H12: 0000 | I12: 0000 | J12: 04/04/1984 | K12: 00/00/0000
A13: 0170 | B13: CA LAW REVISION COMMISSION | C13: 0808 | D13: GENERAL GOVERNMENT | F13: 0000 | G13: 0000 | H13: 0000 | I13: 0000 | J13: 99/99/9999 | K13: 07/01/1985
... A190: 2140 | B190: STATE BANKING DEPARTMENT | C190: 0825 | D190: BUS, CONSUMER SERV, HOUSING | F190: 0000 | G190: 0000 | H190: 0000 | I190: 0000 | J190: 12/21/2016 | K190: 00/00/0000
A191: 2150 | B191: FINANCIAL INSTITUTIONS | C191: 0825 | D191: ADD BACK TO POST PY REVERSAL | E191: DELETE 16/17 | F191: 0000 | G191: 0000 | H191: 0000 | I191: 0000 | J191: 08/18/2016 | K191: 00/00/0000
A192: 2180 | B192: DEPART OF CORPORATIONS | C192: 0825 | D192: ADD BACK TO POST PY REVERSAL | E192: DELETE 16/17 | F192: 0000 | G192: 0000 | H192: 0000 | I192: 0000 | J192: 08/24/2016 | K192: 00/00/0000
A193: 2190 | B193: MAJOR MEDICAL INSURANCE BOARD | C193: 0825 | D193: BUS, CONSUMER SERV, HOUSING | F193: 0000 | G193: 0000 | H193: 0000 | I193: 0000 | J193: 12/21/2016 | K193: 00/00/0000
A194: 2200 | B194: DEPARTMENT OF COMMERCE | C194: 0825 | D194: BUS, CONSUMER SERV, HOUSING | F194: 0000 | G194: 0000 | H194: 0000 | I194: 0000 | J194: 12/21/2016 | K194: 00/00/0000
A195: 2220 | B195: OFFICE OF SMALL BUSINESS DEVEL | C195: 0825 | D195: BUS, CONSUMER SERV, HOUSING | F195: 0000 | G195: 0000 | H195: 0000 | I195: 0000 | J195: 12/21/2016 | K195: 00/00/0000
A196: 2222 | B196: ST ASST FD FOR ENTERPRISE | C196: 0825 | D196: BUS, CONSUMER SERV, HOUSING | F196: 0000 | G196: 0000 | H196: 0000 | I196: 0000 | J196: 12/21/2016 | K196: 00/00/0000
A197: 2225 | B197: UNITARY FUND PROGRAMS | C197: 0825 | D197: BUS, CONSUMER SERV, HOUSING | F197: 0000 | G197: 0000 | H197: 0000 | I197: 0000 | J197: 12/21/2016 | K197: 00/00/0000
A198: 2230 | B198: CA INDTRL DEV FINCL ADVRY COMM | C198: 0825 | D198: BUS, CONSUMER SERV, HOUSING | F198: 0000 | G198: 0000 | H198: 0000 | I198: 0000 | J198: 12/21/2016 | K198: 07/01/1985
A199: 2235 | B199: CA HOME LOAN MORTGAGE ASSN | C199: 0825 | D199: BUS, CONSUMER SERV, HOUSING | F199: 0000 | G199: 0000 | H199: 0000 | I199: 0000 | J199: 12/21/2016 | K199: 00/00/0000
A200: 2240 | B200: DEPT-HOUSING/COMMUNITY DEVEL | C200: 0825 | D200: BUS, CONSUMER SERV, HOUSING | F200: 0000 | G200: 0000 | H200: 0000 | I200: 0000 | J200: 12/12/2016 | K200: 00/00/1999
A201: 2245 | B201: CALIFORNIA HOUSING FINANCE AGY | C201: 0825 | D201: BUS, CONSUMER SERV, HOUSING | F201: 0000 | G201: 0000 | H201: 0000 | I201: 0000 | J201: 08/19/2016 | K201: 00/00/0000
A202: 2265 | B202: CALIFORNIA HOUSING INSURANCE | C202: 0825 | D202: BUS, CONSUMER SERV, HOUSING | F202: 0000 | G202: 0000 | H202: 0000 | I202: 0000 | J202: 12/21/2016 | K202: 00/00/0000
A203: 2270 | B203: MORTGAGE BOND ALLOC COMMITTEE | C203: 0825 | D203: BUS, CONSUMER SERV, HOUSING | F203: 0000 | G203: 0000 | H203: 0000 | I203: 0000 | J203: 12/21/2016 | K203: 07/01/1985
A204: 2290 | B204: DEPARTMENT OF INSURANCE | C204: 0825 | D204: BUS, CONSUMER SERV, HOUSING | F204: 0000 | G204: 0000 | H204: 0000 | I204: 0000 | J204: 12/21/2016 | K204: 00/00/1999
... A214: 2670 | B214: BD OF PILOT COMMISSIONERS-SF | C214: 0830 | D214: TRANSPORTATION | F214: 0000 | G214: 0000 | H214: 0000 | I214: 0000 | J214: 08/03/2017 | K214: 00/00/0000
A215: 2700 | B215: OFFICE OF TRAFFIC SAFETY | C215: 0830 | D215: TRANSPORTATION | E215: MERGED W/0521-ADD 4 PY ACCR RV | F215: 0000 | G215: 0000 | H215: 0000 | I215: 0000 | J215: 09/28/2016 | K215: 00/00/0000
A216: 2720 | B216: DEPT OF CAL HIGHWAY PATROL | C216: 0830 | D216: TRANSPORTATION | F216: 0000 | G216: 0000 | H216: 0000 | I216: 0000 | J216: 10/28/2016 | K216: 00/00/1999
A217: 2740 | B217: DEPARTMENT OF MOTOR VEHICLES | C217: 0830 | D217: TRANSPORTATION | F217: 0000 | G217: 0000 | H217: 0000 | I217: 0000 | J217: 10/28/2016 | K217: 00/00/0000
A218: 2780 | B218: STEPHEN P TEALE DATA CENTER | C218: 0825 | D218: BUS, CONSUMER SERV, HOUSING | F218: 0000 | G218: 0000 | H218: 0000 | I218: 0000 | J218: 12/21/2016 | K218: 00/00/0000
A219: 2900 | B219: TRADE AND COMMERCE | C219: 0825 | D219: BUS, CONSUMER SERV, HOUSING | F219: 0000 | G219: 0000 | H219: 0000 | I219: 0000 | J219: 12/21/2016 | K219: 00/00/0000
A220: 2920 | B220: TECHNOLOGY TRADE & COMMERCE AG | C220: 0825 | D220: BUS, CONSUMER SERV, HOUSING | F220: 0000 | G220: 0000 | H220: 0000 | I220: 0000 | J220: 12/21/2016 | K220: 00/00/0000
A221: 3000 | B221: NATURAL RESOURCES | C221: 0820 | D221: RESOURCES | F221: 0000 | G221: 0000 | H221: 0000 | I221: 0000 | J221: 08/25/2010 | K221: 00/00/0000
A222: 3100 | B222: EXPOSITION PARK | C222: 0820 | D222: RESOURCES | F222: 0000 | G222: 0000 | H222: 0000 | I222: 0000 | J222: 10/17/2018 | K222: 00/00/0000
A223: 3105 | B223: CALIFORNIA AFRO-AMERICAN MUSEU | C223: 0820 | D223: RESOURCES | F223: 0000 | G223: 0000 | H223: 0000 | I223: 0000 | J223: 09/05/2014 | K223: 00/00/0000
A224: 3110 | B224: SPECIAL RESOURCES PROGRAMS | C224: 0820 | D224: RESOURCES | F224: 0000 | G224: 0000 | H224: 0000 | I224: 0000 | J224: 07/11/2006 | K224: 00/00/1999
A225: 3125 | B225: CALIF TAHOE CONSERVANCY | C225: 0820 | D225: RESOURCES | F225: 0000 | G225: 0000 | H225: 0000 | I225: 0000 | J225: 04/18/1988 | K225: 00/00/1999
A226: 3130 | B226: WATERWAYS MANAGEMENT PLANNING | C226: 0820 | D226: RESOURCES | F226: 0000 | G226: 0000 | H226: 0000 | I226: 0000 | J226: 99/99/9999 | K226: 00/00/0000
A227: 3140 | B227: SEA GRANT PROGRAM | C227: 0820 | D227: RESOURCES | F227: 0000 | G227: 0000 | H227: 0000 | I227: 0000 | J227: 99/99/9999 | K227: 00/00/0000
... A278: 4140 | B278: OFFICE OF HEALTH PLAN & DEV | C278: 0815 | D278: HEALTH AND HUMAN SERVICES | F278: 0000 | G278: 0000 | H278: 0000 | I278: 0000 | J278: 10/28/2016 | K278: 00/00/0000
A279: 4150 | B279: DEPT OF MANAGED HEALTH CARE | C279: 0815 | D279: HEALTH AND HUMAN SERVICES | E279: RENUMBERED FROM 2400 | F279: 0000 | G279: 0000 | H279: 0000 | I279: 0000 | J279: 10/28/2016 | K279: 00/00/0000
A280: 4170 | B280: DEPARTMENT OF AGING | C280: 0815 | D280: HEALTH AND HUMAN SERVICES | F280: 0000 | G280: 0000 | H280: 0000 | I280: 0000 | J280: 10/28/2016 | K280: 00/00/1999
A281: 4180 | B281: COMMISSION ON AGING | C281: 0815 | D281: HEALTH AND HUMAN SERVICES | F281: 0000 | G281: 0000 | H281: 0000 | I281: 0000 | J281: 10/28/2016 | K281: 00/00/1999
A282: 4185 | B282: CALIFORNIA SENIOR LEGISLATURE | C282: 0815 | D282: HEALTH AND HUMAN SERVICES | F282: 0000 | G282: 0000 | H282: 0000 | I282: 0000 | J282: 10/28/2016 | K282: 00/00/0000
A283: 4210 | B283: GOV COUNCIL DRUG/ALCOHOL ABUSE | C283: 0815 | D283: HEALTH AND HUMAN SERVICES | F283: 0000 | G283: 0000 | H283: 0000 | I283: 0000 | J283: 10/28/2016 | K283: 00/00/0000
A284: 4220 | B284: GOV ADV COM CHILD DEVEL PROG | C284: 0815 | D284: HEALTH AND HUMAN SERVICES | F284: 0000 | G284: 0000 | H284: 0000 | I284: 0000 | J284: 10/28/2016 | K284: 00/00/0000
A285: 4250 | B285: CA. CHILDREN AND FAMILIES COMM | C285: 0815 | D285: HEALTH AND HUMAN SERVICES | F285: 0000 | G285: 0000 | H285: 0000 | I285: 0000 | J285: 10/28/2016 | K285: 00/00/0000
A286: 4260 | B286: DEPARTMENT OF HEALTH CARE SVCS | C286: 0815 | D286: HEALTH AND HUMAN SERVICES | F286: 0000 | G286: 0000 | H286: 0000 | I286: 0000 | J286: 10/28/2016 | K286: 00/00/0000
A287: 4265 | B287: DEPARTMENT OF PUBLIC HEALTH | C287: 0815 | D287: HEALTH AND HUMAN SERVICES | F287: 0000 | G287: 0000 | H287: 0000 | I287: 0000 | J287: 10/28/2016 | K287: 00/00/0000
A288: 4270 | B288: CAL MED ASSISTANCE COMMISSION | C288: 0815 | D288: HEALTH AND HUMAN SERVICES | F288: 0000 | G288: 0000 | H288: 0000 | I288: 0000 | J288: 10/28/2016 | K288: 00/00/1999
A289: 4280 | B289: MANAGED RISK MED INSUR BD. | C289: 0815 | D289: HEALTH AND HUMAN SERVICES | F289: 0000 | G289: 0000 | H289: 0000 | I289: 0000 | J289: 10/28/2016 | K289: 00/00/0000
A290: 4300 | B290: DEPT. DEVELOPMENTAL SVCS | C290: 0815 | D290: HEALTH AND HUMAN SERVICES | F290: 0000 | G290: 0000 | H290: 0000 | I290: 0000 | J290: 10/28/2016 | K290: 00/00/0000
A291: 4310 | B291: DO NOT USE AGENCY MERGED WITH | C291: 0815 | F291: 0000 | G291: 0000 | H291: 0000 | I291: 0000 | J291: 09/07/2018 | K291: 00/00/0000
A292: 4320 | B292: STATE HOSPITALS | C292: 0815 | D292: HEALTH AND HUMAN SERVICES | F292: 0000 | G292: 0000 | H292: 0000 | I292: 0000 | J292: 10/28/2016 | K292: 00/00/0000
A293: 4350 | B293: DO NOT USE AGENCY MERGED WITH | C293: 0815 | F293: 0000 | G293: 0000 | H293: 0000 | I293: 0000 | J293: 09/07/2018 | K293: 00/00/0000
A294: 4370 | B294: DO NOT USE AGENCY MERGED WITH | C294: 0815 | F294: 0000 | G294: 0000 | H294: 0000 | I294: 0000 | J294: 09/07/2018 | K294: 00/00/0000
A295: 4390 | B295: DO NOT USE AGENCY MERGED WITH | C295: 0815 | F295: 0000 | G295: 0000 | H295: 0000 | I295: 0000 | J295: 09/07/2018 | K295: 00/00/0000
A296: 4400 | B296: DO NOT USE AGENCY MERGED WITH | C296: 0815 | F296: 0000 | G296: 0000 | H296: 0000 | I296: 0000 | J296: 09/07/2018 | K296: 00/00/0000
A297: 4430 | B297: DO NOT USE AGENCY MERGED WITH | C297: 0815 | F297: 0000 | G297: 0000 | H297: 0000 | I297: 0000 | J297: 09/07/2018 | K297: 00/00/0000
A298: 4440 | B298: DEPT. OF STATE HOSPITAL | C298: 0815 | D298: HEALTH AND HUMAN SERVICES | F298: 0000 | G298: 0000 | H298: 0000 | I298: 0000 | J298: 10/28/2016 | K298: 00/00/0000
A299: 4450 | B299: SACRAMENTO STATE HOSPITAL | C299: 0815 | D299: HEALTH AND HUMAN SERVICES | F299: 0000 | G299: 0000 | H299: 0000 | I299: 0000 | J299: 10/28/2016 | K299: 00/00/1999
A300: 4460 | B300: STATE HOSPITALS | C300: 0815 | D300: HEALTH AND HUMAN SERVICES | F300: 0000 | G300: 0000 | H300: 0000 | I300: 0000 | J300: 10/28/2016 | K300: 00/00/0000
A301: 4470 | B301: ATASCADERO STATE HOSPITAL | C301: 0815 | D301: HEALTH AND HUMAN SERVICES | F301: 0000 | G301: 0000 | H301: 0000 | I301: 0000 | J301: 10/28/2016 | K301: 00/00/1999
A302: 4490 | B302: METROPOLITAN STATE HOSPITAL | C302: 0815 | D302: HEALTH AND HUMAN SERVICES | F302: 0000 | G302: 0000 | H302: 0000 | I302: 0000 | J302: 10/28/2016 | K302: 00/00/1999
A303: 4500 | B303: NAPA STATE HOSPITAL | C303: 0815 | D303: HEALTH AND HUMAN SERVICES | F303: 0000 | G303: 0000 | H303: 0000 | I303: 0000 | J303: 10/28/2016 | K303: 00/00/1999
A304: 4510 | B304: PATTON STATE HOSPITAL | C304: 0815 | D304: HEALTH AND HUMAN SERVICES | F304: 0000 | G304: 0000 | H304: 0000 | I304: 0000 | J304: 10/28/2016 | K304: 00/00/1999
A305: 4520 | B305: STOCKTON STATE HOSPITAL-DMH | C305: 0815 | D305: HEALTH AND HUMAN SERVICES | F305: 0000 | G305: 0000 | H305: 0000 | I305: 0000 | J305: 10/28/2016 | K305: 00/00/1999
A306: 4530 | B306: VACAVILLE STATE HOSPITAL | C306: 0815 | D306: HEALTH AND HUMAN SERVICES | F306: 0000 | G306: 0000 | H306: 0000 | I306: 0000 | J306: 10/28/2016 | K306: 00/00/0000
A307: 4540 | B307: COALINGA STATE HOSPITAL | C307: 0815 | D307: HEALTH AND HUMAN SERVICES | F307: 0000 | G307: 0000 | H307: 0000 | I307: 0000 | J307: 10/28/2016 | K307: 00/00/0000
A308: 4550 | B308: SALINAS STATE HOSPITAL | C308: 0815 | D308: HEALTH AND HUMAN SERVICES | F308: 0000 | G308: 0000 | H308: 0000 | I308: 0000 | J308: 10/28/2016 | K308: 00/00/0000
A309: 4560 | B309: MENTAL HEALTH SVCS OVERSIGHT | C309: 0815 | D309: HEALTH AND HUMAN SERVICES | F309: 0000 | G309: 0000 | H309: 0000 | I309: 0000 | J309: 10/28/2016 | K309: 00/00/0000
... A597: 9610 | B597: LEASE-REV NOTES & BONDS | C597: 9000 | D597: DEBT SERVICE INT & FISCAL CHGS | F597: 9030 | G597: 9610 | H597: 0000 | I597: 0000 | J597: 08/19/2016 | K597: 00/00/0000
A598: 9612 | B598: ENHN TOBAC ASSET-BACKED BND | C598: 0847 | D598: BOND INTEREST AND REDEMPTION | E598: WHEN TOBACCO REVENUE IS SHORT | F598: 0000 | G598: 0000 | H598: 0000 | I598: 0000 | J598: 08/19/2016 | K598: 00/00/0000
A599: 9613 | B599: UNENHANCED TOBACCO BD PROCEEDS | C599: 0808 | D599: GENERAL GOVERNMENT | F599: 0000 | G599: 0000 | H599: 0000 | I599: 0000 | J599: 02/26/2008 | K599: 00/00/0000
A600: 9618 | B600: ECONOMIC RECOVERY FINANCE COMM | C600: 0808 | D600: GENERAL GOVERNMENT | F600: 0000 | G600: 0000 | H600: 0000 | I600: 0000 | J600: 10/28/2005 | K600: 00/00/0000
A601: 9620 | B601: CASH MGMT & BUDGETARY LOANS | C601: 0850 | D601: DEBT SERVICE INT & FISCAL CHGS | F601: 0000 | G601: 0000 | H601: 0000 | I601: 0000 | J601: 08/19/2016 | K601: 00/00/0000
A602: 9625 | B602: INT PYMTS TO FEDERAL GOVT | C602: 0846 | D602: DEBT SERVICE INT & FISCAL CHGS | F602: 0000 | G602: 0000 | H602: 0000 | I602: 0000 | J602: 08/19/2016 | K602: 00/00/0000
A603: 9632 | B603: STATE MANDATED LOCAL COSTS | C603: 0808 | D603: GENERAL GOVERNMENT | F603: 0000 | G603: 0000 | H603: 0000 | I603: 0000 | J603: 99/99/9999 | K603: 00/00/0000
A604: 9634 | B604: GENERAL OBLIGATION BONDS | C604: 9000 | D604: GENERAL OBLIGATION BONDS | F604: 9030 | G604: 9634 | H604: 0000 | I604: 0000 | J604: 06/13/1988 | K604: 00/00/0000
A605: 9636 | B605: MISCELLANEOUS ADJUSTMENTS | C605: 9000 | D605: MISCELLANEOUS ADJUSTMENTS | F605: 9030 | G605: 9636 | H605: 0000 | I605: 0000 | J605: 06/13/1988 | K605: 00/00/0000
A606: 9650 | B606: HEALTH BENEFITS FOR ANNUITANTS | C606: 0808 | D606: GENERAL GOVERNMENT | F606: 0000 | G606: 0000 | H606: 0000 | I606: 0000 | J606: 04/04/1984 | K606: 00/00/0000
A607: 9651 | B607: PREFUND HEALTH & DENTAL BEN | C607: 0808 | D607: GENERAL GOVERNMENT | F607: 0000 | G607: 0000 | H607: 0000 | I607: 0000 | J607: 08/25/2010 | K607: 00/00/0000
A608: 9658 | B608: BUDGET STABILIZATION ACCOUNT | C608: 0808 | D608: GENERAL GOVERNMENT | F608: 0000 | G608: 0000 | H608: 0000 | I608: 0000 | J608: 07/11/2006 | K608: 00/00/0000
A609: 9670 | B609: LEGISLATIVE CLAIMS | C609: 0808 | D609: GENERAL GOVERNMENT | F609: 0000 | G609: 0000 | H609: 0000 | I609: 0000 | J609: 04/04/1984 | K609: 00/00/0000
A610: 9671 | B610: EQUITY CLAIMS OF BD OF CONTROL | C610: 0808 | D610: GENERAL GOVERNMENT | F610: 0000 | G610: 0000 | H610: 0000 | I610: 0000 | J610: 03/30/1994 | K610: 00/00/0000
... A635: 9885 | B635: RESERVE FOR ENCUMBRANCE | C635: 0808 | D635: GENERAL GOVERNMENT | F635: 0000 | G635: 0000 | H635: 0000 | I635: 0000 | J635: 01/23/1991 | K635: 00/00/0000
A636: 9889 | B636: PUBLIC SCHOOL SYSTEM STABILIZA | C636: 0810 | D636: PUBLIC SCHOOL SYSTEM | E636: STABILIZATION ACCOUNT | F636: 0000 | G636: 0000 | H636: 0000 | I636: 0000 | J636: 04/01/2020 | K636: 00/00/0000
A637: 9890 | B637: RES FOR ECONOMIC UNCERTAINTIES | C637: 0808 | D637: GENERAL GOVERNMENT | F637: 0000 | G637: 0000 | H637: 0000 | I637: 0000 | J637: 07/11/2006 | K637: 00/00/0000
A638: 9891 | B638: DEPT OF HEALTH HUMAN SERVICES | C638: 0815 | D638: HEALTH AND HUMAN SERVICES | F638: 0000 | G638: 0000 | H638: 0000 | I638: 0000 | J638: 10/28/2016 | K638: 00/00/0000
A639: 9892 | B639: SUPPLEMENTAL PENSION PAYMENTS | C639: 0843 | D639: INT. ON INTERFUND LOANS | F639: 0000 | G639: 0000 | H639: 0000 | I639: 0000 | J639: 11/22/2019 | K639: 00/00/0000
A640: 9895 | B640: PETROLEUM VIOLATION ESCROW PRO | C640: 0808 | D640: GENERAL GOVERNMENT | F640: 0000 | G640: 0000 | H640: 0000 | I640: 0000 | J640: 07/11/2006 | K640: 00/00/0000
A641: 9896 | B641: OUTER CONT SHELF LAND ACT | C641: 0808 | D641: GENERAL GOVERNMENT | F641: 0000 | G641: 0000 | H641: 0000 | I641: 0000 | J641: 07/11/2006 | K641: 00/00/0000
A642: 9898 | B642: PERS GENERAL FUND PAYMENT | C642: 0808 | D642: GENERAL GOVERNMENT | F642: 0000 | G642: 0000 | H642: 0000 | I642: 0000 | J642: 11/04/1998 | K642: 00/00/0000
A643: 9900 | B643: GEN FD CREDITS FROM SPEC FUNDS | C643: 0808 | D643: GENERAL GOVERNMENT | F643: 0000 | G643: 0000 | H643: 0000 | I643: 0000 | J643: 07/11/2006 | K643: 00/00/0000
A644: 9901 | B644: STATEWIDE GEN ADM EXP (PR) | C644: 0808 | D644: GENERAL GOVERNMENT | F644: 0000 | G644: 0000 | H644: 0000 | I644: 0000 | J644: 07/11/2006 | K644: 00/00/0000
A645: 9909 | B645: HLTH INS PORTABLTY ACCTABLTY | C645: 0815 | D645: HEALTH AND HUMAN SERVICES | F645: 0000 | G645: 0000 | H645: 0000 | I645: 0000 | J645: 10/28/2016 | K645: 00/00/0000
A646: 9910 | B646: GEN FD CREDITS FROM FED FUNDS | C646: 0808 | D646: GENERAL GOVERNMENT | F646: 0000 | G646: 0000 | H646: 0000 | I646: 0000 | J646: 07/11/2006 | K646: 00/00/0000
...

Sheet FP-Version Changes
A1: This sheet details the changes made between version 1 and version 2 of the GASB 87 Lessee Financed Purchase Annual Reporting Submission Workbook. Familiarize yourself with the changes in the table below and follow the instructions for updating data from template version 1 to version 2.
A4: Version 1 | B4: Published on SCO website from August 2023 to March 2024 for use for the 2021-2022 reporting period.
A5: Version 2 | B5: Published on SCO website in March 2024 for use for reporting periods 2022-2023 and afterwards.
A7: The GASB 87 Annual Reporting Submission Workbook is required to be updated and submitted every year. See below for the summary of changes between versions.
A9: Summary of Changes
A10: Sheet | B10: Feature | C10: Location V1 | D10: Location V2 | E10: Description | F10: Required Action
A11: FP-Fund #### Journal Entries | B11: Revised - Instructions | C11: Row 1 | D11: Row 1 | E11: Non-transferring leases were removed from the worksheet. This worksheet is now isolated to just leases that do transfer ownership. There is a separate worksheet, "LS-Fund #### Journal Entries" to use if your fund has leases that do not transfer ownership. | F11: Only use this worksheet for leases that do transfer ownership.
A12: FP-Fund #### Journal Entries | B12: Added - Organization Name | C12: N/A | D12: Row 4 | E12: Added a row to type in the organization name. | F12: Type organization name.
A13: FP-Fund #### Journal Entries | B13: Removed - Fi$Cal or Non-Fi$Cal Departments | C13: Row 7 | D13: N/A | E13: The default is now non-Fi$Cal account numbers. A crosswalk between SCO GAAP and Fi$Cal account numbers can be found on the SCO Website under the heading "GASB 87 Supplemental Materials". https://sco.ca.gov/sard_gasb_87_reporting_instructions.html | F13: No action required.
A14: FP-Fund #### Journal Entries | B14: Added - Fund Type | C14: N/A | D14: Row 8 | E14: Select if the fund type is Governmental, Proprietary ISF, or Proprietary EF. This assists in the SCO's preparation of disclosures for the ACFR. | F14: Select one fund type.
A15: FP-Fund #### Journal Entries | B15: Added - Functional Expense | C15: N/A | D15: Row 9 | E15: Added a lookup of SCO GAAP functional expense based on organization code entered into row 5. This functional expense will automatically populate in Entry #1, 5, and M1. | F15: No action required.
A16: FP-Fund #### Journal Entries | B16: Added - Headers | C16: N/A | D16: Rows 12, 29, and 48 | E16: Added journal entry headers to help clarify when each set of entries are applicable. Informative only. | F16: No action required.
A17: FP-Fund #### Journal Entries | B17: Revised - Entry #0 | C17: Row 10 | D17: Row 14 | E17: Entry #0, rolling the prior fiscal year ending balance for the current year opening balance, was revised to add "Acct 0950 - Beginning Fund Balances". This entry will remain blank if the fund did not have any leases in the prior year. | F17: No change in action required. Continue to populate Entry #0 based on amounts populated on the Lessee FP Template(s) for this fund.
A18: FP-Fund #### Journal Entries | B18: Revised - Entries #5 and #6, Account Numbers | C18: Rows 67-81 | D18: Rows 55-63 | E18: "Acct: 0845 - Debt Service - Principal" was updated to "Acct: 0848 - Debt Service - Principal Leases". "Acct: 0850 - Debt Service - Interest " was updated to "Acct: 0851 - Debt Service - Interest Leases" if a Governmental fund, and updated to "Acct: 0894 - Interest Expense and Fiscal Charges" if a Proprietary (ISF or EF) fund. | F18: No action required.
A19: FP-Fund #### Journal Entries | B19: Revised - Entry #7 Account Number | C19: Row 87 | D19: Row 68 | E19: "Acct: 0645 - Contracts and Notes Payable" was updated to "Acct: 0677 - Current Portion of Other Long-Term Liabilites". | F19: No action required.
A20: FP-Fund #### Journal Entries | B20: Added - Informational - Ending Balances | C20: N/A | D20: Row 75 | E20: Added a calculation of ending balances for all financed purchase assets and liabilities. | F20: No action required.
A21: FP-Lease Liabilities | B21: Revised - Column D | C21: Column D | D21: Column D | E21: The row headers is column D were modified for two results. Firstly, Lease Liability (leases that do not transfer ownership) were removed from worksheet. Leases Liability and Installment Contracts Payable (Financed Purchase) are now on separate worksheets. Secondly, the Proprietary Funds sections was split into Proprietary - ISF and Proprietary - EF in version 2. | F21: When compiling information from the lessee templates, distinguish between Proprietary ISF and Proprietary EF funds.
A22: FP-Lease Liabilities | B22: Added - Journal Entry References | C22: N/A | D22: Row 8 | E22: Added a reference (journal entry number) under each column header to help identify where to find the necessary information on the FP-Fund #### Journal Entry tab. | F22: No action required.

Sheet FP-Fund 5225 Journal Entries
A1: Financed Purchase-Type Contracts Fund-by-Fund Journal Entries Form (to be submitted to the SCO annually—one form per fund)
A2: Manually complete every yellow field in this worksheet—there are no automatically calculated data-entry cells in this worksheet.
A3: Fiscal Year: | F3: 2022–2023
A4: Organization Name: | F4: Department of Corrections and Rehabilitation
A5: Organization Code (4-Digits): | F5: 5225
A6: Fund Number: | F6: 1
A7: Fund Classification: | F7: Governmental
A8: Fund Type: | F8: Governmental Fund
A9: Functional Expense: | F9: =IFERROR(IF(F7="Proprietary","Proprietary Fund",VLOOKUP(F5,[3]qryIndex02a!$A$2:$K$654,4,FALSE)),"Unidentified") -> CORRECTIONS AND REHABILITATION
A12: Establish Beginning Balances (existing financed purchases only)
A13: Entry #
A14: 0 | B14: Roll prior year to record opening balances of financed purchase assets and liabilities. | M14: Combined FP Templates | P14: From SCO BB List | S14: Difference
B15: Dr: Acct 0446 - LAND AND LAND IMPROVEMENTS | J15: =M15 -> 0 | S15: =P15-M15 -> 0
B16: Dr: Acct 0448 - BUILDINGS AND BUILDING IMPROVEMENTS | J16: =M16 -> 2768185 | M16: 2768185 | P16: 2768185 | S16: =P16-M16 -> 0
B17: Dr: Acct 0450 - EQUIPMENT | J17: =M17 -> 0 | S17: =P17-M17 -> 0
B18: Dr: Acct 0950 - BEGINNING FUND BALANCE | J18: =P18 -> 0 | P18: =IF(SUM($Q$21:$Q$23)>SUM($P$15:$P$17),SUM($Q$21:$Q$23)-SUM($P$15:$P$17),0) -> 0 | S18: =P18-M18 -> 0
B19: Dr: Acct 0952 - BEGINNING FUND ADJUSTMENT/PRIOR PERIOD ADJUSTMENT | J19: =IF(SUM($K$21:$K$24)>SUM($J$15:$J$18),SUM($K$21:$K$24)-SUM($J$15:$J$18),0) -> 37377 | S19: =P19-M19 -> 0
C20: Land is not depreciable
C21: Cr: Acct 0462 - ACCUMULATED DEPRECIATION - EQUIPMENT | K21: =N21 -> 0 | S21: =Q21-N21 -> 0
C22: Cr: Acct 0458 - ACCUMULATED DEPRECIATION - BUILDINGS AND BUILDING IMPROVEMENTS | K22: =N22 -> 69205 | N22: 69205 | Q22: 31828 | S22: =Q22-N22 -> -37377
C23: Cr: Acct 0695 - OTHER NONCURRENT LIABILITIES | K23: =N23 -> 971518 | N23: 971518 | Q23: 971518 | S23: =Q23-N23 -> 0
C24: Cr: Acct 0950 - BEGINNING FUND BALANCE | K24: =Q24 -> 1764839 | N24: 1727462 | Q24: =IF(SUM($Q$21:$Q$23)<SUM($P$15:$P$17),-SUM($Q$21:$Q$23)+SUM($P$15:$P$17),0) -> 1764839 | S24: =Q24-N24 -> 37377
C25: Cr: Acct 0952 - BEGINNING FUND ADJUSTMENT/PRIOR PERIOD ADJUSTMENT | K25: =IF(SUM($K$21:$K$24)<SUM($J$15:$J$18),-SUM($K$21:$K$24)+SUM($J$15:$J$18),0) -> 0 | S25: =Q25-N25 -> 0
J26: =SUM(J15:J25) -> 2805562 | K26: =SUM(K15:K25) -> 2805562 | L26: =IF(J26=K26,"<- Debits and Credits equal each other.","<- Debits and Credits do not equal each other.") -> <- Debits and Credits equal each other.
A29: Record New Financed Purchases (new financed purchases only)
A30: 1 | B30: Record financed purchase contract commencement (fund-based entries only)
B31: Dr: Acct 0842 - CAPITAL OUTLAY
C32: Cr: Acct 0789 - LEASE AND OTHER FINANCING PROCEEDS
C33: =IF($F$7="Proprietary","Cr: Acct 0870 - SERVICES & CHARGES (MG ADJ)",VLOOKUP($F$9,'[3]Drop Down Menus'!$F$2:$G$10,2,FALSE)) -> Cr: Acct 0835 - CORRECTIONS AND REHABILITATION
J34: =SUM(J31:J33) -> 0 | K34: =SUM(K31:K33) -> 0 | L34: =IF(J34=K34,"<- Debits and Credits equal each other.","<- Debits and Credits do not equal each other.") -> <- Debits and Credits equal each other.
A36: 2 | B36: Record financed purchase assets. These amounts should be included in the Report 18.
B37: Dr: Acct 0446 - LAND AND LAND IMPROVEMENTS
B38: Dr: Acct 0448 - BUILDINGS AND BUILDING IMPROVEMENTS
B39: Dr: Acct 0450 - EQUIPMENT
C40: Cr: Acct 0842 - CAPITAL OUTLAY
J41: =SUM(J37:J40) -> 0 | K41: =SUM(K37:K40) -> 0 | L41: =IF(J41=K41,"<- Debits and Credits equal each other.","<- Debits and Credits do not equal each other.") -> <- Debits and Credits equal each other.
A43: 3 | B43: Replace proceeds from leases with other noncurrent liabilities.
B44: Dr: Acct 0789 - LEASE AND OTHER FINANCING PROCEEDS
C45: Cr: Acct 0695 - OTHER NONCURRENT LIABILITIES
J46: =SUM(J44:J45) -> 0 | K46: =SUM(K44:K45) -> 0 | L46: =IF(J46=K46,"<- Debits and Credits equal each other.","<- Debits and Credits do not equal each other.") -> <- Debits and Credits equal each other.
A48: Record Annual Activity (all financed purchases)
A49: 4 | B49: Record depreciation of the financed purchase assets for the year.
B50: Dr: Acct 0875 - DEPRECIATION/AMORTIZATION | J50: 69205
C51: Cr: Acct 0458 - ACCUMULATED DEPRECIATION - BUILDINGS AND BUILDING IMPROVEMENTS | K51: 69205
C52: Cr: Acct 0462 - ACCUMULATED DEPRECIATION - EQUIPMENT
J53: =SUM(J50:J52) -> 69205 | K53: =SUM(K50:K52) -> 69205 | L53: =IF(J53=K53,"<- Debits and Credits equal each other.","<- Debits and Credits do not equal each other.") -> <- Debits and Credits equal each other.
A55: 5 | B55: Reclassify rents and leases exp. to financed purchase contract principal and interest exp.
B56: Dr: Acct 0848 - DEBT SERVICE - PRINCIPAL LEASES | J56: 342081
B57: =IF(F6="Governmental","Dr: Acct 0851 - DEBT SERVICE - INTEREST LEASES","Dr: Acct 0894 - INTEREST EXPENSE AND FISCAL CHARGES") -> Dr: Acct 0894 - INTEREST EXPENSE AND FISCAL CHARGES | J57: 78433
C58: =IF($F$7="Proprietary","Cr: Acct 0870 - SERVICES & CHARGES (MG ADJ)",VLOOKUP($F$9,'[3]Drop Down Menus'!$F$2:$G$10,2,FALSE)) -> Cr: Acct 0835 - CORRECTIONS AND REHABILITATION | K58: 420514
J59: =SUM(J56:J58) -> 420514 | K59: =SUM(K56:K58) -> 420514 | L59: =IF(J59=K59,"<- Debits and Credits equal each other.","<- Debits and Credits do not equal each other.") -> <- Debits and Credits equal each other.
A61: 6 | B61: Reduce financed purchase contracts liability for total current year principal payments.
B62: Dr: Acct 0695 - OTHER NONCURRENT LIABILITIES | J62: 342081
C63: Cr: Acct 0848 - DEBT SERVICE - PRINCIPAL LEASES | K63: 342081
J64: =SUM(J62:J63) -> 342081 | K64: =SUM(K62:K63) -> 342081 | L64: =IF(J64=K64,"<- Debits and Credits equal each other.","<- Debits and Credits do not equal each other.") -> <- Debits and Credits equal each other.
A66: 7 | B66: Reclassify the principal amount due in the next FY to the current liability.
B67: Dr: Acct 0695 - OTHER NONCURRENT LIABILITIES | J67: 255669
C68: Cr: Acct 0677 - CURRENT PORTION OF OTHER LONG-TERM LIABILITIES | K68: 255669
B69: NOTE: This is an annual accrual. It is to be reversed at the start of the next fiscal year. SCO combines the current and non current amount in Entry #0 to reestablish the beginning balances. No action required. | J69: =SUM(J67:J68) -> 255669 | K69: =SUM(K67:K68) -> 255669 | L69: =IF(J69=K69,"<- Debits and Credits equal each other.","<- Debits and Credits do not equal each other.") -> <- Debits and Credits equal each other.
D75: Informational - Ending Balances of Assets and Liabilities
K76: Debit (Credit)
D77: Acct 0446 - LAND AND LAND IMPROVEMENTS | K77: =J15+J37 -> 0
D78: Acct 0448 - BUILDINGS AND BUILDING IMPROVEMENTS | K78: =J16+J38 -> 2768185
D79: Acct 0450 - EQUIPMENT | K79: =J17+J39 -> 0
D80: Acct 0462 - ACCUMULATED DEPRECIATION - EQUIPMENT | K80: =-K21-K52 -> 0
D81: Acct 0458 - ACCUMULATED DEPRECIATION - BUILDINGS AND BUILDING IMPROVEMENTS | K81: =-K22-K51 -> -138410
D82: Acct 0695 - OTHER NONCURRENT LIABILITIES | K82: =-K23-K45+J62+J67 -> -373768
D83: Acct 0677 - CURRENT PORTION OF OTHER LONG-TERM LIABILITIES | K83: =-K68 -> -255669

Sheet FP-Lease Liabilities
J3: Schedule of Changes in Lease Liabilities
J4: =CONCATENATE("FY ",'FP-Fund 5225 Journal Entries'!F3) -> FY 2022–2023
J5: =CONCATENATE("Business Unit ",'FP-Fund 5225 Journal Entries'!F5," - ",'FP-Fund 5225 Journal Entries'!F4) -> Business Unit 5225 - Department of Corrections and Rehabilitation
F7: =CONCATENATE("Balance July 1, ",MID(J4,4,4)) -> Balance July 1, 2022 | H7: Additions | J7: Deductions | L7: =CONCATENATE("Balance June 30, ",RIGHT(J4,4)) -> Balance June 30, 2023 | N7: Due Within One Year | P7: Noncurrent Liabilities
F8: (Entry #0) | H8: (Entry #3) | J8: (Entry #6) | N8: (Entry #7)
C9: Governmental Funds
D10: Installment Contracts Payable (Financed Purchase) | F10: ='FP-Fund 5225 Journal Entries'!N23 -> 971518 | H10: ='FP-Fund 5225 Journal Entries'!J44 -> 0 | J10: ='FP-Fund 5225 Journal Entries'!J62 -> 342081 | L10: =SUM(F10+H10-J10) -> 629437 | N10: ='FP-Fund 5225 Journal Entries'!K68 -> 255669 | P10: =L10-N10 -> 373768
C11: Total Governmental Funds | F11: =SUM(F10:F10) -> 971518 | H11: =SUM(H10:H10) -> 0 | J11: =SUM(J10:J10) -> 342081 | L11: =SUM(L10:L10) -> 629437 | N11: =SUM(N10:N10) -> 255669 | P11: =SUM(P10:P10) -> 373768
C13: Proprietary - Internal Service Funds
D14: Installment Contracts Payable (Financed Purchase) | L14: =SUM(F14+H14-J14) -> 0 | P14: =L14-N14 -> 0
C15: Total Proprietary - Internal Service Funds | F15: =SUM(F14:F14) -> 0 | H15: =SUM(H14:H14) -> 0 | J15: =SUM(J14:J14) -> 0 | L15: =SUM(L14:L14) -> 0 | N15: =SUM(N14:N14) -> 0 | P15: =SUM(P14:P14) -> 0
C17: Proprietary - Enterprise Funds
D18: Installment Contracts Payable (Financed Purchase) | L18: =SUM(F18+H18-J18) -> 0 | P18: =L18-N18 -> 0
C19: Total Proprietary - Enterprise Funds | F19: =SUM(F18:F18) -> 0 | H19: =SUM(H18:H18) -> 0 | J19: =SUM(J18:J18) -> 0 | L19: =SUM(L18:L18) -> 0 | N19: =SUM(N18:N18) -> 0 | P19: =SUM(P18:P18) -> 0
