Workbook
Name \Z: #REF!
Name \Z: #REF!
Name \Z: #REF!
Name \Z: #REF!
Name \Z: #REF!
Name Table26: '4. Non Current Liab'!$H$1:$P$11
Name Table26: '5. Gov Wide Entries Fund 9142'!$J$1:$R$6
Name Table26: '1. Summary 2324'!$I$1:$Q$12
Name WC_LiabilityAllocation: '4. Non Current Liab'!$A$1:$E$50
Name WC_LiabilityAllocation: '5. Gov Wide Entries Fund 9142'!$A$1:$F$61
Name WC_LiabilityAllocation: '1. Summary 2324'!$A$1:$G$91

Sheet 1. Summary 2324
A1: Workers' Compensation Liability | C1: ref | E1: ref | K1: Identifies as cell reference in this tab
A2: June 30, 2024 | D2: Prior Yr.% from | F2: Short-term | G2: % of Total
B3: KO717 Total | D3: SCIF letter | F3: Liability | G3: Outstanding
B4: (Total billed) | D4: (related to py) | F4: B5*C5 | G4: S-T %
A5: Total paid | B5: ='8. K0717_2024_Jun '!B332 -> 6.8659103e+08 | C5: tab 8 | D5: 0.0093 | E5: A | F5: =B5*D5 -> 6385296.6 | G5: =+F5/'2. K0215-June 30, 2024'!R11 -> 0.0015716524
A6: Add Claim Pmts from audit | B6: =-L21*1000 -> 1820000 | C6: L21
A7: Subtract the Proprietary Funds | B7: Total O/S | D7: % of Total O/S | J7: Primary Government - Gov. Activities & Enterprise fund (amounts in thousands) | M7: ref | O7: ref
A8: Enterprise Funds (Hier 400) | B8: =+'2. K0215-June 30, 2024'!Q418 -> 9909595.4 | C8: tab 2 | D8: =ROUND($G$5,3) -> 0.002 | F8: =-(B8*D8) -> -19819.191 | K8: 2024 | N8: 2023
A9: Internal Services Funds (Hier 500) | B9: =+'2. K0215-June 30, 2024'!Q455 -> 36058778 | C9: tab 2 | D9: =ROUND($G$5,3) -> 0.002 | F9: =-(B9*D9) -> -72117.555 | J9: Liabilities Beg. Bal. | K9: =N12 -> 0 | O9: G1
A10: Allocated to GF & SR | F10: =SUM(F5:F9) -> 6293359.8 | G10: * | J10: Incurred claims | K10: =+K12-K9-K11 -> 688411.03 | O10: G2
J11: Claim payments | K11: =((B5+B6)/1000*-1) -> -688411.03 | O11: G3
B12: Total | F12: Short-term | J12: Liabilities End. Bal. | K12: =N22 -> 0 | N12: =SUM(N9:N11) -> 0 | O12: G4
B13: Outstanding* | D13: Percentage* | F13: Allocation* | N13: =IF(N12=N19,"OK","ERROR") -> OK
A14: General Fund (Hier 100) | B14: =+'2. K0215-June 30, 2024'!Q293 -> 3.0321371e+09 | C14: B14 must match D30 | D14: =B14/B17 -> 0.75492242 | F14: =D14*$F$10 -> 4750998.4 | N14: Check to ensure cells N19 and N12 match
A15: Special Revenue Funds (Hier 200) | B15: =+'2. K0215-June 30, 2024'!Q414 -> 9.8435126e+08 | C15: B15 must match D67 | D15: =B15/B17 -> 0.24507758 | F15: =D15*$F$10 -> 1542361.4 | G15: GF Total
A16: SUBTOTAL - K0215 (w/o Hiers 400, 500, or 900) | B16: =+B14+B15 -> 4.0164883e+09 | F16: =+F14+F15 -> 6293359.8 | G16: =+F14 -> 4750998.4
B17: =+B16 -> 4.0164883e+09 | D17: =SUM(D14:D16) -> 1 | F17: =+F16 -> 6293359.8 | J17: Breakdown of Primary Government (amounts in thousands) | U17: (PY GAAP system) | V17: (CY-PY)
K18: Gov. Activities | L18: Enterprise | M18: ref | N18: Total Primary Gov. | S18: Fund | T18: CY | U18: PY | V18: Change
A19: Breakdown of Workers' Compensation by Exp Code | J19: Beginning | K19: =N12-L19 -> -14535 | L19: =U21 -> 14535 | M19: U21 | N19: =SUM(K19:L19) -> 0 | S19: F0562 | T19: 8337 | U19: 9791 | V19: =T19-U19 -> -1454 | W19: CY amouts see L attachment
A20: General Fund | B20: Expend. Code | D20: Outstanding | F20: Percentage * | G20: Current WC Allocation* | J20: Addition | K20: =K22-K19-K21 -> 688411.03 | L20: 0 | N20: =SUM(K20:L20) -> 688411.03 | S20: F0917 | T20: 4378 | U20: 4744 | V20: =T20-U20 -> -366 | W20: CY amouts see J attachment
B21: 808 | D21: =+'2. K0215-June 30, 2024'!Q45 -> 77954501 | E21: tab 2 | F21: =D21/$D$30 -> 0.025709425 | G21: =F21*$F$14 -> 122145.44 | J21: Deduction | K21: =K11-L21 -> -686591.03 | L21: =V21 -> -1820 | M21: V21 | N21: =SUM(K21:L21) -> -688411.03 | T21: =SUM(T19:T20) -> 12715 | U21: =SUM(U19:U20) -> 14535 | V21: =SUM(V19:V20) -> -1820
B22: 810 | D22: =+'2. K0215-June 30, 2024'!R62 -> 6511365 | F22: =D22/$D$30 -> 0.0021474507 | G22: =F22*$F$14 -> 10202.535 | J22: Ending Balance | K22: =ROUND(J112-L22,0) -> -12715 | L22: =SUM(L19:L21) -> 12715 | N22: =SUM(K22:L22) -> 0
A23: Fund 1031 | B23: 810 | D23: ='2. K0215-June 30, 2024'!R59 -> 0 | F23: =D23/$D$30 -> 0 | G23: =F23*$F$14 -> 0 | J23: Current | K23: =ROUND((+G30+G67+D84)/1000,0) -> 6293 | L23: =+D74/1000 -> 0 | N23: =SUM(K23:L23) -> 6293 | T23: PY EB, wp - tab "Summary 2021", cell L22 | U23: 14535
B24: 815 | D24: =SUM('2. K0215-June 30, 2024'!Q70:Q110)+SUM('2. K0215-June 30, 2024'!Q64:Q65) -> 3.8494123e+08 | F24: =D24/$D$30 -> 0.12695377 | G24: =F24*$F$14 -> 603157.16 | J24: NonCurrent | K24: =SUM(K22-K23) -> -19008 | L24: =SUM(L22-L23) -> 12715 | N24: =SUM(K24:L24) -> -6293 | T24: PY variance check | U24: =U21-U23 -> 0
A25: Fund 0870 | B25: 815 | D25: =SUM('2. K0215-June 30, 2024'!Q66:Q69) -> 74005124 | F25: =D25/$D$30 -> 0.024406919 | G25: =F25*$F$14 -> 115957.23 | K25: is a round entry needed | L25: =IF((L22=G74/1000),"OK","ERROR") -> OK | N25: =IF((N24=(ROUND(G89,-3))/1000),"OK","ERROR") -> OK
B26: 820 | D26: =+'2. K0215-June 30, 2024'!Q132 -> 2.9721834e+08 | F26: =D26/$D$30 -> 0.098022726 | G26: =F26*$F$14 -> 465705.82 | L26: check to ensure cells L22 and G74 match | N26: Check to ensure cells N24 and G89 match
B27: 825 | D27: =+'2. K0215-June 30, 2024'!Q135 -> 732131.7 | F27: =D27/$D$30 -> 0.00024145732 | G27: =F27*$F$14 -> 1147.1634
B28: 830 | D28: 0 | F28: =D28/$D$30 -> 0 | G28: =F28*$F$14 -> 0
B29: 835 | D29: =+'2. K0215-June 30, 2024'!Q291 -> 2.1907744e+09 | F29: =D29/$D$30 -> 0.72251825 | G29: =F29*$F$14 -> 3432683.1
A30: Total General Fund | C30: =IF(B14=D30,"OK","ERROR") -> OK | D30: =SUM(D21:D29) -> 3.0321371e+09 | F30: =SUM(F21:F29) -> 1 | G30: =SUM(G21:G29) -> 4750998.4
A32: Special Revenue Funds
A33: 200-100 | B33: #808 - fund 0890 | D33: =+'2. K0215-June 30, 2024'!Q296 -> 12606027 | F33: =D33/$D$67 -> 0.012806431 | G33: =F33*$F$15 -> 19752.146
A34: 200-100 | B34: #810 - fund 0890 | D34: =+'2. K0215-June 30, 2024'!Q307 -> 5447668.2 | F34: =D34/$D$67 -> 0.0055342726 | G34: =F34*$F$15 -> 8535.8487
A35: 200-100 | B35: #815 - fund 0890 | D35: =+'2. K0215-June 30, 2024'!Q306 -> 35360538 | F35: =D35/$D$67 -> 0.035922683 | G35: =F35*$F$15 -> 55405.76
A36: 200-100 | B36: #820 - fund 0890 | D36: =+'2. K0215-June 30, 2024'!Q308 -> 3146933.7 | F36: =D36/$D$67 -> 0.0031969622 | G36: =F36*$F$15 -> 4930.8711
A37: 200-100 | B37: #825 - fund 0890 | D37: =+'2. K0215-June 30, 2024'!Q309 -> 74358.362 | F37: =D37/$D$67 -> 7.5540475e-05 | G37: =F37*$F$15 -> 116.51072
A38: 200-100 | B38: #835 - fund 0890 | D38: =+'2. K0215-June 30, 2024'!Q310 -> 410860.28 | F38: =D38/$D$67 -> 0.00041739194 | G38: =F38*$F$15 -> 643.76922
A39: 200-150 | B39: #820 - fund 0044 | D39: ='2. K0215-June 30, 2024'!Q312 -> 3291027.8 | F39: =D39/$D$67 -> 0.0033433469 | G39: =F39*$F$15 -> 5156.6493 | K39: Information for Note 17 Risk Management
A40: 200-150 | B40: #830 - fund 0042 | D40: =SUM('2. K0215-June 30, 2024'!$Q$314:Q341) -> 2.0736529e+08 | F40: =D40/$D$67 -> 0.21066188 | G40: =F40*$F$15 -> 324916.76
A41: 200-150 | B41: #830 - fund 0044 | D41: =SUM('2. K0215-June 30, 2024'!Q344:Q348) -> 5.0800893e+08 | F41: =D41/$D$67 -> 0.51608502 | G41: =F41*$F$15 -> 795989.62 | J41: Current: | K41: =G30 -> 4750998.4 | L41: General Fund
A42: 200-150 | B42: #830 - fund 0064 | D42: =+'2. K0215-June 30, 2024'!Q342 -> 1.0051609e+08 | F42: =D42/$D$67 -> 0.10211404 | G42: =F42*$F$15 -> 157496.76 | K42: =G67 -> 1542361.4 | L42: Special Revenue Funds
A43: 200-250 | B43: #808 - fund 0111 | D43: =+'2. K0215-June 30, 2024'!Q352 -> 6666335.1 | F43: =D43/$D$67 -> 0.0067723133 | G43: =F43*$F$15 -> 10445.355 | K43: =D86 -> 0 | L43: Proprietary funds (Internal Service & Enterprise)
A44: 200-250 | B44: #808 - fund 0217 | D44: =+'2. K0215-June 30, 2024'!Q351 -> 6843951.4 | F44: =D44/$D$67 -> 0.0069527532 | G44: =F44*$F$15 -> 10723.658 | K44: =SUM(K41:K43) -> 6293359.8 | L44: Total Current
A45: 200-250 | B45: #808 - fund 0567 | D45: =+'2. K0215-June 30, 2024'!Q353 -> 0 | F45: =D45/$D$67 -> 0 | G45: =F45*$F$15 -> 0
A46: 200-250 | B46: #808 - fund 0462 | D46: ='2. K0215-June 30, 2024'!Q354 -> 1597976 | F46: =D46/$D$67 -> 0.0016233798 | G46: =F46*$F$15 -> 2503.8384 | J46: Noncurrent: | K46: =G89 -> -6293359.8
A47: 200-250 | B47: #810 - fund 0407 | D47: =+'2. K0215-June 30, 2024'!Q358 -> 0 | F47: =D47/$D$67 -> 0 | G47: =F47*$F$15 -> 0 | K47: =SUM(K44:K46) -> 0
A48: 200-250 | B48: #815 - fund 0933 | D48: ='2. K0215-June 30, 2024'!Q359 -> 258637.63 | F48: =D48/$D$67 -> 0.00026274933 | G48: =F48*$F$15 -> 405.25443
A49: 200-250 | B49: #825 - fund 0067 | D49: =+'2. K0215-June 30, 2024'!Q363+'2. K0215-June 30, 2024'!Q364+'2. K0215-June 30, 2024'!Q365 -> 1608120.2 | F49: =D49/$D$67 -> 0.0016336853 | G49: =F49*$F$15 -> 2519.7332
A50: 200-250 | B50: #825 - fund 0317 | D50: =+'2. K0215-June 30, 2024'!Q366 -> 309527.02 | F50: =D50/$D$67 -> 0.00031444773 | G50: =F50*$F$15 -> 484.99205
A51: 200-250 | B51: #825 - fund 3153 | D51: ='2. K0215-June 30, 2024'!Q369 -> 51658.01 | F51: =D51/$D$67 -> 5.2479244e-05 | G51: =F51*$F$15 -> 80.941962
A52: 200-250 | B52: #825 - fund 0702 | D52: ='2. K0215-June 30, 2024'!Q367+'2. K0215-June 30, 2024'!Q368 -> 8069555.8 | F52: =D52/$D$67 -> 0.0081978417 | G52: =F52*$F$15 -> 12644.035
A53: 200-250 | B53: #825 - fund 3036 | D53: =+'2. K0215-June 30, 2024'!Q370+'2. K0215-June 30, 2024'!Q371 -> 2627389.4 | F53: =D53/$D$67 -> 0.0026691584 | G53: =F53*$F$15 -> 4116.8069
A54: 200-300 | B54: #820 - fund 0014 | D54: =+'2. K0215-June 30, 2024'!Q389 -> 3562884.2 | F54: =D54/$D$67 -> 0.0036195252 | G54: =F54*$F$15 -> 5582.616
A55: 200-300 | B55: #820 - fund 3046 | D55: =+'2. K0215-June 30, 2024'!Q379 -> 595331.86 | F55: =D55/$D$67 -> 0.00060479616 | G55: =F55*$F$15 -> 932.81427
A56: 200-300 | B56: #820 - fund 0140 | D56: ='2. K0215-June 30, 2024'!Q376+'2. K0215-June 30, 2024'!Q382+'2. K0215-June 30, 2024'!Q383+'2. K0215-June 30, 2024'!Q384 -> 71272.74 | F56: =D56/$D$67 -> 7.24058e-05 | G56: =F56*$F$15 -> 111.67591
A57: 200-300 | B57: #820 - fund 0200 | D57: =+'2. K0215-June 30, 2024'!Q380+'2. K0215-June 30, 2024'!Q381 -> 16534332 | F57: =D57/$D$67 -> 0.016797187 | G57: =F57*$F$15 -> 25907.333
A58: 200-300 | B58: #820 - fund 3211 | D58: =+'2. K0215-June 30, 2024'!Q377+'2. K0215-June 30, 2024'!Q378 -> 292687.24 | F58: =D58/$D$67 -> 0.00029734024 | G58: =F58*$F$15 -> 458.60612
A59: 200-300 | B59: #820 - fund 0387 | D59: =+'2. K0215-June 30, 2024'!Q385 -> 1831475 | F59: =D59/$D$67 -> 0.0018605909 | G59: =F59*$F$15 -> 2869.7036
A60: 200-300 | B60: #820 - fund 0439 | D60: =+'2. K0215-June 30, 2024'!Q386+'2. K0215-June 30, 2024'!Q388+'2. K0215-June 30, 2024'!Q387 -> 2662317 | F60: =D60/$D$67 -> 0.0027046413 | G60: =F60*$F$15 -> 4171.5344
A61: 200-450 | B61: #820 - fund 0565 | D61: =+'2. K0215-June 30, 2024'!Q397 -> 0 | F61: =D61/$D$67 -> 0 | G61: =F61*$F$15 -> 0
A62: 200-450 | B62: #825 - fund 0929 | D62: =+'2. K0215-June 30, 2024'!Q400 -> 826879.56 | F62: =D62/$D$67 -> 0.00084002489 | G62: =F62*$F$15 -> 1295.622
A63: 200-550 | B63: #815 - fund 0639 | D63: =+'2. K0215-June 30, 2024'!Q402 -> 0 | F63: =D63/$D$67 -> 0 | G63: =F63*$F$15 -> 0
A64: 200-950 | B64: #815 - fund 0121 | D64: =+'2. K0215-June 30, 2024'!Q407 -> 496412.41 | F64: =D64/$D$67 -> 0.00050430414 | G64: =F64*$F$15 -> 777.81924
A65: 200-950 | B65: #815 - fund 0223 | D65: ='2. K0215-June 30, 2024'!$Q$408 -> 36861087 | F65: =D65/$D$67 -> 0.037447087 | G65: =F65*$F$15 -> 57756.943
A66: 200-950 | B66: #820 - fund 0318 | D66: =+'2. K0215-June 30, 2024'!Q412 -> 16355706 | F66: =D66/$D$67 -> 0.016615721 | G66: =F66*$F$15 -> 25627.447
A67: Total Special Revenue Funds | C67: =IF(B15=D67,"OK","ERROR") -> OK | D67: =SUM(D33:D66) -> 9.8435126e+08 | F67: =SUM(F33:F66) -> 1 | G67: =SUM(G33:G66) -> 1542361.4
A69: Current/Non-Current Workers' Comp Liab for Enterprise and Internal Service Funds from Audit Reports/Agency Submitted Adjustments | J69: Noncurrent
D70: Current Liability | F70: Non-Current Liability | G70: Total Liability | J70: =G89 -> -6293359.8 | K70: Total
A71: Enterprise Funds
A72: 0562000 | B72: #808 - (400.600) | D72: =IFERROR(VLOOKUP('1. Summary 2324'!A72&"06550000000",Table_CY_GAAP[[#All],[Fund&Glccount]:[Amount]],2,FALSE),0) -> 0 | E72: L | F72: =-(IFERROR(VLOOKUP('1. Summary 2324'!A72&"06920000000",Table_CY_GAAP[[#All],[Fund&Glccount]:[Amount]],2,FALSE),0)) -> 8337000 | G72: =+F72+D72 -> 8337000 | J72: =-F86 -> -42479487 | K72: Less Proprietary
A73: 0917000 | B73: #808 - (400.900) | D73: =IFERROR(VLOOKUP('1. Summary 2324'!A73&"06550000000",Table_CY_GAAP[[#All],[Fund&Glccount]:[Amount]],2,FALSE),0) -> 0 | E73: J | F73: =-(IFERROR(VLOOKUP('1. Summary 2324'!A73&"06920000000",Table_CY_GAAP[[#All],[Fund&Glccount]:[Amount]],2,FALSE),0)) -> 4378000 | G73: =+F73+D73 -> 4378000 | J73: =SUM(J70:J72) -> -48772847 | K73: Gov Wide Adj
A74: Total Enterprise Funds | D74: =SUM(D72:D73) -> 0 | F74: =SUM(F72:F73) -> 12715000 | G74: =SUM(G72:G73) -> 12715000
G75: matches cell L22
A76: Internal Service Funds | J76: Current
A77: 0666000 | B77: #825 - (500.100) | D77: =IFERROR(VLOOKUP('1. Summary 2324'!A77&"06550000000",Table_CY_GAAP[[#All],[Fund&Glccount]:[Amount]],2,FALSE),0) -> 0 | E77: M | F77: =-(IFERROR(VLOOKUP('1. Summary 2324'!A77&"06920000000",Table_CY_GAAP[[#All],[Fund&Glccount]:[Amount]],2,FALSE),0)) -> 28118000 | G77: =+F77+D77 -> 28118000 | J77: =G91-G89 -> 6293359.8 | K77: Total
A78: 9730000 | B78: #830 - (500.600) | D78: =IFERROR(VLOOKUP('1. Summary 2324'!A78&"06550000000",Table_CY_GAAP[[#All],[Fund&Glccount]:[Amount]],2,FALSE),0) -> 0 | E78: N | F78: =-(IFERROR(VLOOKUP('1. Summary 2324'!A78&"06920000000",Table_CY_GAAP[[#All],[Fund&Glccount]:[Amount]],2,FALSE),0)) -> 136487 | G78: =+F78+D78 -> 136487 | J78: =-D86 -> 0 | K78: Less Proprietary
A79: 0678000 | B79: #835 - (500.200) | C79: O | G79: =+F79+D79 -> 0 | J79: =SUM(J77:J78) -> 6293359.8 | K79: Gov Wide Adj
A80: 0602000 | B80: #808 - (500.500) | D80: =IFERROR(VLOOKUP('1. Summary 2324'!A80&"06550000000",Table_CY_GAAP[[#All],[Fund&Glccount]:[Amount]],2,FALSE),0) -> 0 | E80: P | F80: =-(IFERROR(VLOOKUP('1. Summary 2324'!A80&"06920000000",Table_CY_GAAP[[#All],[Fund&Glccount]:[Amount]],2,FALSE),0)) -> 290000 | G80: =+F80+D80 -> 290000
A81: 9751000 | B81: #808 - (500.900) | D81: =IFERROR(VLOOKUP('1. Summary 2324'!A81&"06550000000",Table_CY_GAAP[[#All],[Fund&Glccount]:[Amount]],2,FALSE),0) -> 0 | E81: Q | F81: =-(IFERROR(VLOOKUP('1. Summary 2324'!A81&"06920000000",Table_CY_GAAP[[#All],[Fund&Glccount]:[Amount]],2,FALSE),0)) -> 1210000 | G81: =+F81+D81 -> 1210000
A82: 9746000 | B82: #808 - (500.900) | D82: =IFERROR(VLOOKUP('1. Summary 2324'!A82&"06550000000",Table_CY_GAAP[[#All],[Fund&Glccount]:[Amount]],2,FALSE),0) -> 0 | E82: R | F82: =-(IFERROR(VLOOKUP('1. Summary 2324'!A82&"06920000000",Table_CY_GAAP[[#All],[Fund&Glccount]:[Amount]],2,FALSE),0)) -> 3000 | G82: =+F82+D82 -> 3000
A83: 0026000 | B83: #808 - (500.900) | D83: =IFERROR(VLOOKUP('1. Summary 2324'!A83&"06550000000",Table_CY_GAAP[[#All],[Fund&Glccount]:[Amount]],2,FALSE),0) -> 0 | E83: S | F83: =-(IFERROR(VLOOKUP('1. Summary 2324'!A83&"06920000000",Table_CY_GAAP[[#All],[Fund&Glccount]:[Amount]],2,FALSE),0)) -> 7000 | G83: =+F83+D83 -> 7000
A84: Total Internal Service Funds | D84: =SUM(D77:D80) -> 0 | F84: =SUM(F77:F83) -> 29764487 | G84: =SUM(G77:G83) -> 29764487 | J84: Totals
J85: =J70+J77 -> 0 | K85: Total
A86: Total Proprietary Funds | D86: =+D84+D74 -> 0 | F86: =+F84+F74 -> 42479487 | G86: =+G74+G84 -> 42479487 | J86: =J72+J78 -> -42479487 | K86: Less Proprietary
J87: =J73+J79 -> -42479487 | K87: Gov Wide Adj
A89: Non Curr. WC Benefits Payable (Grand Total less Current W/C Allocation -GF-SR-PF)* | G89: =+G91-G30-G67-D86 -> -6293359.8
G90: cell G89 matches N24
A91: Grand Total | G91: =+J112*1000 -> 0
D94: Total Outstanding Workers' Compensation Liability | F94: =+J106*1000 -> 0
B95: Workers' Compensation Discount Amount | D95: =-F95/F94 -> #DIV/0! | F95: =-F94+J112*1000 -> 0
D96: Discounted Liability Workers' Compensation Liability | F96: =SUM(F94:F95) -> 0
D99: State of California's Self-Insured Employee Workers' Compensation Program (SCIF) Actuarial Review as of June 30, 2023 (amounts in thousands)
K101: WC Liability | L101: Workers' Comp
K102: Discounts | L102: Discounted Liability
H103: Actuarial Review | I103: F | K103: =+J103-L103 -> 0 | N103: F
I104: tab 6 | K104: =+J104-L104 -> 0 | L104: =J110 -> 0
H106: Total Estimated Outstanding Workers' Compensation Liability | J106: =+J103+J104 -> 0 | K106: =+J106-L106 -> 0 | L106: =+L103+L104 -> 0
N108: Discount %
G109: SCIF Discounted Workers' Compensation Liability | H109: =N109 -> #DIV/0! | J109: =L103 -> 0 | N109: =+K103/J103 -> #DIV/0!
H110: CSUS Discounted WC Liability | J110: 0 | N110: =+K104/J104 -> #DIV/0!
...

Sheet 2. K0215-June 30, 2024
A1: Chap-Agy # | B1: AGENCY | C1: Agency ID | D1: Exp Code | E1: Fund# | F1: Hier1 | G1: Hier2 | H1: O/S COMP | I1: O/S MED | J1: TOTAL | K1: General Fund (in thousands) | L1: Federal Funds (in thousands) | M1: % Reimb by (or to) Fed. Trust Fund [L/(K+L)] | N1: Federal Trust Fund (200-100) Amount (J*M) | O1: General Fund or Applicable Fund Total (J-N) | P1: To Balance | Q1: Total By Fund Hierarchy | R1: ='3. K0215-REFERENCE'!E287 -> 3.9863007e+09 | S1: Total from K0215 Report tab 3
A2: 30-000 | B2: ATTN: ACCOUNTING OFFICER | C2: 0001 | D2: 808 | E2: 0001 | F2: 100 | G2: 100 | J2: =SUM(H2+I2) -> 0 | K2: 0 | L2: 0 | M2: =IFERROR(+L2/(L2+K2),0) -> 0 | N2: =+J2*M2 -> 0 | O2: =+J2-N2 -> 0 | P2: =ROUND(((O2/$R$1)*$R$2),2) -> 0 | Q2: =+O2+P2 -> 0 | R2: =+R11-R1 -> 76491269 | S2: Balance
A3: 99-999 | B3: UNMATCHED RECS | C3: 0001 | D3: 808 | E3: 0001 | F3: 100 | G3: 100 | J3: =SUM(H3+I3) -> 0 | K3: 0 | L3: 0 | M3: =IFERROR(+L3/(L3+K3),0) -> 0 | N3: =+J3*M3 -> 0 | O3: =+J3-N3 -> 0 | P3: =ROUND(((O3/$R$1)*$R$2),2) -> 0 | Q3: =+O3+P3 -> 0
A4: 03-002 | B4: STATE SENATE EMPLOYEE | C4: 0110 | D4: 808 | E4: 0001 | F4: 100 | G4: 100 | H4: =VLOOKUP(A4,'3. K0215-REFERENCE'!A:D,3,FALSE) -> 48431.85 | I4: =VLOOKUP(A4,'3. K0215-REFERENCE'!A:D,4,FALSE) -> 351671.68 | J4: =SUM(H4+I4) -> 400103.53 | K4: 177325 | L4: 0 | M4: =IFERROR(+L4/(L4+K4),0) -> 0 | N4: =+J4*M4 -> 0 | O4: =+J4-N4 -> 400103.53 | P4: =ROUND(((O4/$R$1)*$R$2),2) -> 7677.4 | Q4: =+O4+P4 -> 407780.93
A5: 03-001 | B5: STATE ASSEMBLY ASSEMBLY MEMBERS-ONLY | C5: 0120 | D5: 808 | E5: 0001 | F5: 100 | G5: 100 | J5: =SUM(H5+I5) -> 0 | K5: 233648 | L5: 0 | M5: =IFERROR(+L5/(L5+K5),0) -> 0 | N5: =+J5*M5 -> 0 | O5: =+J5-N5 -> 0 | P5: =ROUND(((O5/$R$1)*$R$2),2) -> 0 | Q5: =+O5+P5 -> 0
A6: 03-004 | B6: STATE ASSEMBLY | C6: 0120 | D6: 808 | E6: 0001 | F6: 100 | G6: 100 | H6: =VLOOKUP(A6,'3. K0215-REFERENCE'!A:D,3,FALSE) -> 145094.09 | I6: =VLOOKUP(A6,'3. K0215-REFERENCE'!A:D,4,FALSE) -> 787574.88 | J6: =SUM(H6+I6) -> 932668.97 | K6: 233648 | L6: 0 | M6: =IFERROR(+L6/(L6+K6),0) -> 0 | N6: =+J6*M6 -> 0 | O6: =+J6-N6 -> 932668.97 | P6: =ROUND(((O6/$R$1)*$R$2),2) -> 17896.55 | Q6: =+O6+P6 -> 950565.52
A7: 03-007 | B7: STATE SENATE EMPLOYEE | C7: 0110 | D7: 808 | E7: 0001 | F7: 100 | G7: 100 | J7: =SUM(H7+I7) -> 0 | K7: 177325 | L7: 0 | M7: =IFERROR(+L7/(L7+K7),0) -> 0 | N7: =+J7*M7 -> 0 | O7: =+J7-N7 -> 0 | P7: =ROUND(((O7/$R$1)*$R$2),2) -> 0 | Q7: =+O7+P7 -> 0
A8: 03-008 | B8: LEGISLATIVE BUDGET COMMITTEE | C8: 0160 | D8: 808 | E8: 0001 | F8: 100 | G8: 100 | J8: =SUM(H8+I8) -> 0 | K8: 177027 | L8: 0 | M8: =IFERROR(+L8/(L8+K8),0) -> 0 | N8: =+J8*M8 -> 0 | O8: =+J8-N8 -> 0 | P8: =ROUND(((O8/$R$1)*$R$2),2) -> 0 | Q8: =+O8+P8 -> 0
A9: 03-430 | B9: LEGISLATIVE COUNSEL BUREAU | C9: 0160 | D9: 808 | E9: 0001 | F9: 100 | G9: 100 | H9: =VLOOKUP(A9,'3. K0215-REFERENCE'!A:D,3,FALSE) -> 56303.53 | I9: =VLOOKUP(A9,'3. K0215-REFERENCE'!A:D,4,FALSE) -> 545184.56 | J9: =SUM(H9+I9) -> 601488.09 | K9: 177027 | L9: 0 | M9: =IFERROR(+L9/(L9+K9),0) -> 0 | N9: =+J9*M9 -> 0 | O9: =+J9-N9 -> 601488.09 | P9: =ROUND(((O9/$R$1)*$R$2),2) -> 11541.68 | Q9: =+O9+P9 -> 613029.77
A10: 03-368 | B10: GOV OFFC PLANNING/RESEARCH | C10: 0500 | D10: 808 | E10: 0001 | F10: 100 | G10: 100 | J10: =SUM(H10+I10) -> 0 | K10: 26617 | L10: 0 | M10: =IFERROR(+L10/(L10+K10),0) -> 0 | N10: =+J10*M10 -> 0 | O10: =+J10-N10 -> 0 | P10: =ROUND(((O10/$R$1)*$R$2),2) -> 0 | Q10: =+O10+P10 -> 0
A11: 03-370 | B11: GOVERNOR'S OFFICE | C11: 0500 | D11: 808 | E11: 0001 | F11: 100 | G11: 100 | J11: =SUM(H11+I11) -> 0 | K11: 26617 | L11: 0 | M11: =IFERROR(+L11/(L11+K11),0) -> 0 | N11: =+J11*M11 -> 0 | O11: =+J11-N11 -> 0 | P11: =ROUND(((O11/$R$1)*$R$2),2) -> 0 | Q11: =+O11+P11 -> 0 | R11: 4.062792e+09 | S11: B
A12: 03-297 | B12: OFFC OF THE INSPECTOR GENERAL | C12: 0552 | D12: 808 | E12: 0001 | F12: 100 | G12: 100 | H12: =VLOOKUP(A12,'3. K0215-REFERENCE'!A:D,3,FALSE) -> 62263.34 | I12: =VLOOKUP(A12,'3. K0215-REFERENCE'!A:D,4,FALSE) -> 142282.46 | J12: =SUM(H12+I12) -> 204545.8 | K12: 39601 | L12: 0 | M12: =IFERROR(+L12/(L12+K12),0) -> 0 | N12: =+J12*M12 -> 0 | O12: =+J12-N12 -> 204545.8 | P12: =ROUND(((O12/$R$1)*$R$2),2) -> 3924.93 | Q12: =+O12+P12 -> 208470.73 | S12: Total from SCIF Letter to SARD
A13: 03-329 | B13: COMMISSION STATUS OF WOMEN | C13: 8820 | D13: 808 | E13: 0001 | F13: 100 | G13: 100 | J13: =SUM(H13+I13) -> 0 | K13: 1471 | L13: 0 | M13: =IFERROR(+L13/(L13+K13),0) -> 0 | N13: =+J13*M13 -> 0 | O13: =+J13-N13 -> 0 | P13: =ROUND(((O13/$R$1)*$R$2),2) -> 0 | Q13: =+O13+P13 -> 0 | S13: Labeled DOF Package
A14: 03-163 | B14: OFFICE EMERGENCY SERVICES | C14: 0690 | D14: 808 | E14: 0001 | F14: 100 | G14: 100 | H14: =VLOOKUP(A14,'3. K0215-REFERENCE'!A:D,3,FALSE) -> 2266882.4 | I14: =VLOOKUP(A14,'3. K0215-REFERENCE'!A:D,4,FALSE) -> 3908668.5 | J14: =SUM(H14+I14) -> 6175550.9 | K14: 215558 | L14: 2607520 | M14: =+L14/(L14+K14) -> 0.92364433 | N14: =+J14*M14 -> 5704012.6 | O14: =+J14-N14 -> 471538.3 | P14: =ROUND(((O14/$R$1)*$R$2),2) -> 9048.13 | Q14: =+O14+P14 -> 480586.43 | S14: Subject: Workers' Compensation Costs
A15: 30-419 | B15: DOJ-LAW ENFORCEMENT | C15: 0820 | D15: 808 | E15: 0001 | F15: 100 | G15: 100 | H15: =VLOOKUP(A15,'3. K0215-REFERENCE'!A:D,3,FALSE) -> 6005897.5 | I15: =VLOOKUP(A15,'3. K0215-REFERENCE'!A:D,4,FALSE) -> 12956128 | J15: =SUM(H15+I15) -> 18962026 | K15: 486805 | L15: 59756 | M15: =+L15/(L15+K15) -> 0.10933089 | N15: =+J15*M15 -> 2073135.2 | O15: =+J15-N15 -> 16888891 | P15: =ROUND(((O15/$R$1)*$R$2),2) -> 324073.07 | Q15: =+O15+P15 -> 17212964
A16: 30-420 | B16: DEPT OF JUSTICE | C16: 0820 | D16: 808 | E16: 0001 | F16: 100 | G16: 100 | H16: =VLOOKUP(A16,'3. K0215-REFERENCE'!A:D,3,FALSE) -> 2366682.8 | I16: =VLOOKUP(A16,'3. K0215-REFERENCE'!A:D,4,FALSE) -> 5838937 | J16: =SUM(H16+I16) -> 8205619.8 | K16: 486805 | L16: 59756 | M16: =+L16/(L16+K16) -> 0.10933089 | N16: =+J16*M16 -> 897127.71 | O16: =+J16-N16 -> 7308492.1 | P16: =ROUND(((O16/$R$1)*$R$2),2) -> 140239.25 | Q16: =+O16+P16 -> 7448731.3
A17: 30-423 | B17: DOJ-FEDERAL GRANTS | C17: 0820 | D17: 808 | E17: 0001 | F17: 100 | G17: 100 | H17: =VLOOKUP(A17,'3. K0215-REFERENCE'!A:D,3,FALSE) -> 462699.35 | I17: =VLOOKUP(A17,'3. K0215-REFERENCE'!A:D,4,FALSE) -> 445177.89 | J17: =SUM(H17+I17) -> 907877.24 | K17: 486805 | L17: 59756 | M17: =+L17/(L17+K17) -> 0.10933089 | N17: =+J17*M17 -> 99259.026 | O17: =+J17-N17 -> 808618.21 | P17: =ROUND(((O17/$R$1)*$R$2),2) -> 15516.2 | Q17: =+O17+P17 -> 824134.41
A18: 11-051 | B18: STATE CONTROLLER'S OFFICE | C18: 0840 | D18: 808 | E18: 0001 | F18: 100 | G18: 100 | H18: =VLOOKUP(A18,'3. K0215-REFERENCE'!A:D,3,FALSE) -> 101038.58 | I18: =VLOOKUP(A18,'3. K0215-REFERENCE'!A:D,4,FALSE) -> 619570.53 | J18: =SUM(H18+I18) -> 720609.11 | K18: 123122 | L18: 1320 | M18: =+L18/(L18+K18) -> 0.010607351 | N18: =+J18*M18 -> 7643.7539 | O18: =+J18-N18 -> 712965.36 | P18: =ROUND(((O18/$R$1)*$R$2),2) -> 13680.76 | Q18: =+O18+P18 -> 726646.12
A19: 33-333 | B19: STATE CONTROLLER'S OFFICE-FI$CAL | C19: 8880 | D19: 808 | E19: 0001 | F19: 100 | G19: 100 | J19: =SUM(H19+I19) -> 0 | K19: 72904 | L19: 0 | M19: =IFERROR(+L19/(L19+K19),0) -> 0 | N19: =+J19*M19 -> 0 | O19: =+J19-N19 -> 0 | P19: =ROUND(((O19/$R$1)*$R$2),2) -> 0 | Q19: =+O19+P19 -> 0
A20: 21-290 | B20: STATE BRD OF EQUALIZATION | C20: 0860 | D20: 808 | E20: 0001 | F20: 100 | G20: 100 | H20: =VLOOKUP(A20,'3. K0215-REFERENCE'!A:D,3,FALSE) -> 18995 | I20: =VLOOKUP(A20,'3. K0215-REFERENCE'!A:D,4,FALSE) -> 15801.57 | J20: =SUM(H20+I20) -> 34796.57 | K20: 26934 | L20: 0 | M20: =IFERROR(+L20/(L20+K20),0) -> 0 | N20: =+J20*M20 -> 0 | O20: =+J20-N20 -> 34796.57 | P20: =ROUND(((O20/$R$1)*$R$2),2) -> 667.7 | Q20: =+O20+P20 -> 35464.27
A21: 21-291 | B21: CA DEPT. OF TAX AND FEE | C21: 7600 | D21: 808 | E21: 0001 | F21: 100 | G21: 100 | H21: =VLOOKUP(A21,'3. K0215-REFERENCE'!A:D,3,FALSE) -> 4903844.1 | I21: =VLOOKUP(A21,'3. K0215-REFERENCE'!A:D,4,FALSE) -> 7984474.2 | J21: =SUM(H21+I21) -> 12888318 | K21: 494836 | L21: 154 | M21: =+L21/(L21+K21) -> 0.0003111174 | N21: =+J21*M21 -> 4009.78 | O21: =+J21-N21 -> 12884308 | P21: =ROUND(((O21/$R$1)*$R$2),2) -> 247231 | Q21: =+O21+P21 -> 13131539
A22: 03-426 | B22: STATE PUBLIC DEFENDER | C22: 8140 | D22: 808 | E22: 0001 | F22: 100 | G22: 100 | J22: =SUM(H22+I22) -> 0 | K22: 21697 | L22: 0 | M22: =IFERROR(+L22/(L22+K22),0) -> 0 | N22: =+J22*M22 -> 0 | O22: =+J22-N22 -> 0 | P22: =ROUND(((O22/$R$1)*$R$2),2) -> 0 | Q22: =+O22+P22 -> 0
A23: 03-352 | B23: CALIFORNIA ARTS COUNCIL | C23: 8260 | D23: 808 | E23: 0001 | F23: 100 | G23: 100 | H23: =VLOOKUP(A23,'3. K0215-REFERENCE'!A:D,3,FALSE) -> 477.9 | I23: =VLOOKUP(A23,'3. K0215-REFERENCE'!A:D,4,FALSE) -> 11712.77 | J23: =SUM(H23+I23) -> 12190.67 | K23: 11525 | L23: 1180 | M23: =IFERROR(+L23/(L23+K23),0) -> 0.09287682 | N23: =+J23*M23 -> 1132.2307 | O23: =+J23-N23 -> 11058.439 | P23: =ROUND(((O23/$R$1)*$R$2),2) -> 212.2 | Q23: =+O23+P23 -> 11270.639
A24: 03-363 | B24: CA DEPT OF HUMAN RESOURCES | C24: 7501 | D24: 808 | E24: 0001 | F24: 100 | G24: 100 | H24: =VLOOKUP(A24,'3. K0215-REFERENCE'!A:D,3,FALSE) -> 456946.58 | I24: =VLOOKUP(A24,'3. K0215-REFERENCE'!A:D,4,FALSE) -> 379220.01 | J24: =SUM(H24+I24) -> 836166.59 | K24: 30450 | L24: 0 | M24: =IFERROR(+L24/(L24+K24),0) -> 0 | N24: =+J24*M24 -> 0 | O24: =+J24-N24 -> 836166.59 | P24: =ROUND(((O24/$R$1)*$R$2),2) -> 16044.81 | Q24: =+O24+P24 -> 852211.4
A25: 03-325 | B25: FAIR POLITICAL PRACT COMM | C25: 8620 | D25: 808 | E25: 0001 | F25: 100 | G25: 100 | H25: =VLOOKUP(A25,'3. K0215-REFERENCE'!A:D,3,FALSE) -> 4500 | I25: =VLOOKUP(A25,'3. K0215-REFERENCE'!A:D,4,FALSE) -> 45411.22 | J25: =SUM(H25+I25) -> 49911.22 | K25: 18308 | L25: 0 | M25: =IFERROR(+L25/(L25+K25),0) -> 0 | N25: =+J25*M25 -> 0 | O25: =+J25-N25 -> 49911.22 | P25: =ROUND(((O25/$R$1)*$R$2),2) -> 957.72 | Q25: =+O25+P25 -> 50868.94
A26: 99-292 | B26: OFFICE OF TAX APPEALS | C26: 0870 | D26: 808 | E26: 0001 | F26: 100 | G26: 100 | J26: =SUM(H26+I26) -> 0 | K26: 24194 | L26: 0 | M26: =IFERROR(+L26/(L26+K26),0) -> 0 | N26: =+J26*M26 -> 0 | O26: =+J26-N26 -> 0 | P26: =ROUND(((O26/$R$1)*$R$2),2) -> 0 | Q26: =+O26+P26 -> 0
A27: 99-356 | B27: COMMISSION ON STATE MANDATES | C27: 8885 | D27: 808 | E27: 0001 | F27: 100 | G27: 100 | H27: =VLOOKUP(A27,'3. K0215-REFERENCE'!A:D,3,FALSE) -> 0 | I27: =VLOOKUP(A27,'3. K0215-REFERENCE'!A:D,4,FALSE) -> 9304.2 | J27: =SUM(H27+I27) -> 9304.2 | K27: 3117 | L27: 0 | M27: =IFERROR(+L27/(L27+K27),0) -> 0 | N27: =+J27*M27 -> 0 | O27: =+J27-N27 -> 9304.2 | P27: =ROUND(((O27/$R$1)*$R$2),2) -> 178.53 | Q27: =+O27+P27 -> 9482.73
A28: 57-573 | B28: DVA-VETERANS' HOME OF CA | C28: 8955 | D28: 808 | E28: 0001 | F28: 100 | G28: 100 | H28: =VLOOKUP(A28,'3. K0215-REFERENCE'!A:D,3,FALSE) -> 3790118 | I28: =VLOOKUP(A28,'3. K0215-REFERENCE'!A:D,4,FALSE) -> 4888208.6 | J28: =SUM(H28+I28) -> 8678326.6 | K28: 537853 | L28: 0 | M28: =+L28/(L28+K28) -> 0 | N28: =+J28*M28 -> 0 | O28: =+J28-N28 -> 8678326.6 | P28: =ROUND(((O28/$R$1)*$R$2),2) -> 166524.37 | Q28: =+O28+P28 -> 8844850.9
A29: 57-574 | B29: DVA-BARSTOW VETERANS HOME | C29: 8955 | D29: 808 | E29: 0001 | F29: 100 | G29: 100 | H29: =VLOOKUP(A29,'3. K0215-REFERENCE'!A:D,3,FALSE) -> 70915.36 | I29: =VLOOKUP(A29,'3. K0215-REFERENCE'!A:D,4,FALSE) -> 894968.77 | J29: =SUM(H29+I29) -> 965884.13 | K29: 537853 | L29: 0 | M29: =+L29/(L29+K29) -> 0 | N29: =+J29*M29 -> 0 | O29: =+J29-N29 -> 965884.13 | P29: =ROUND(((O29/$R$1)*$R$2),2) -> 18533.9 | Q29: =+O29+P29 -> 984418.03
A30: 57-575 | B30: DVA-CHULA VISTA VETERANS | C30: 8955 | D30: 808 | E30: 0001 | F30: 100 | G30: 100 | H30: =VLOOKUP(A30,'3. K0215-REFERENCE'!A:D,3,FALSE) -> 388607.87 | I30: =VLOOKUP(A30,'3. K0215-REFERENCE'!A:D,4,FALSE) -> 2347917.4 | J30: =SUM(H30+I30) -> 2736525.2 | K30: 537853 | L30: 0 | M30: =+L30/(L30+K30) -> 0 | N30: =+J30*M30 -> 0 | O30: =+J30-N30 -> 2736525.2 | P30: =ROUND(((O30/$R$1)*$R$2),2) -> 52509.91 | Q30: =+O30+P30 -> 2789035.1
A31: 57-576 | B31: DVA-GLAVC | C31: 8955 | D31: 808 | E31: 0001 | F31: 100 | G31: 100 | H31: =VLOOKUP(A31,'3. K0215-REFERENCE'!A:D,3,FALSE) -> 1123946.2 | I31: =VLOOKUP(A31,'3. K0215-REFERENCE'!A:D,4,FALSE) -> 4783625.2 | J31: =SUM(H31+I31) -> 5907571.4 | K31: 537853 | L31: 0 | M31: =+L31/(L31+K31) -> 0 | N31: =+J31*M31 -> 0 | O31: =+J31-N31 -> 5907571.4 | P31: =ROUND(((O31/$R$1)*$R$2),2) -> 113357.64 | Q31: =+O31+P31 -> 6020929
A32: 57-577 | B32: DVA-FRESNO VETERANS HOME | C32: 8955 | D32: 808 | E32: 0001 | F32: 100 | G32: 100 | H32: =VLOOKUP(A32,'3. K0215-REFERENCE'!A:D,3,FALSE) -> 262570.98 | I32: =VLOOKUP(A32,'3. K0215-REFERENCE'!A:D,4,FALSE) -> 1881971.2 | J32: =SUM(H32+I32) -> 2144542.2 | K32: 537853 | L32: 0 | M32: =+L32/(L32+K32) -> 0 | N32: =+J32*M32 -> 0 | O32: =+J32-N32 -> 2144542.2 | P32: =ROUND(((O32/$R$1)*$R$2),2) -> 41150.62 | Q32: =+O32+P32 -> 2185692.9
A33: 57-578 | B33: DVA-REDDING VETERANS HOME | C33: 8955 | D33: 808 | E33: 0001 | F33: 100 | G33: 100 | H33: =VLOOKUP(A33,'3. K0215-REFERENCE'!A:D,3,FALSE) -> 272343.99 | I33: =VLOOKUP(A33,'3. K0215-REFERENCE'!A:D,4,FALSE) -> 1666427.5 | J33: =SUM(H33+I33) -> 1938771.5 | K33: 537853 | L33: 0 | M33: =+L33/(L33+K33) -> 0 | N33: =+J33*M33 -> 0 | O33: =+J33-N33 -> 1938771.5 | P33: =ROUND(((O33/$R$1)*$R$2),2) -> 37202.18 | Q33: =+O33+P33 -> 1975973.7
A34: 57-831 | B34: CA DEPT OF VETERAN'S AFFAIRS - HOME AND FARM | C34: 8955 | D34: 808 | E34: 0001 | F34: 100 | G34: 100 | H34: =VLOOKUP(A34,'3. K0215-REFERENCE'!A:D,3,FALSE) -> 0.5 | I34: =VLOOKUP(A34,'3. K0215-REFERENCE'!A:D,4,FALSE) -> 15167.13 | J34: =SUM(H34+I34) -> 15167.63 | K34: 537853 | L34: 0 | M34: =+L34/(L34+K34) -> 0 | N34: =+J34*M34 -> 0 | O34: =+J34-N34 -> 15167.63 | P34: =ROUND(((O34/$R$1)*$R$2),2) -> 291.04 | Q34: =+O34+P34 -> 15458.67
A35: 57-830 | B35: DEPT OF VETERANS AFFAIRS | C35: 8955 | D35: 808 | E35: 0001 | F35: 100 | G35: 100 | H35: =VLOOKUP(A35,'3. K0215-REFERENCE'!A:D,3,FALSE) -> 2420.76 | I35: =VLOOKUP(A35,'3. K0215-REFERENCE'!A:D,4,FALSE) -> 393689.25 | J35: =SUM(H35+I35) -> 396110.01 | K35: 537853 | L35: 0 | M35: =+L35/(L35+K35) -> 0 | N35: =+J35*M35 -> 0 | O35: =+J35-N35 -> 396110.01 | P35: =ROUND(((O35/$R$1)*$R$2),2) -> 7600.77 | Q35: =+O35+P35 -> 403710.78
A36: 42-564 | B36: FRANCHISE TAX BOARD | C36: 7730 | D36: 808 | E36: 0001 | F36: 100 | G36: 100 | H36: =VLOOKUP(A36,'3. K0215-REFERENCE'!A:D,3,FALSE) -> 939583.82 | I36: =VLOOKUP(A36,'3. K0215-REFERENCE'!A:D,4,FALSE) -> 4686414.8 | J36: =SUM(H36+I36) -> 5625998.6 | K36: 722099 | L36: 0 | M36: =+L36/(L36+K36) -> 0 | N36: =+J36*M36 -> 0 | O36: =+J36-N36 -> 5625998.6 | P36: =ROUND(((O36/$R$1)*$R$2),2) -> 107954.67 | Q36: =+O36+P36 -> 5733953.3
A37: 03-040 | B37: VICTIM COMP & GOV CLMS BD | C37: 7870 | D37: 808 | E37: 0001 | F37: 100 | G37: 100 | H37: =VLOOKUP(A37,'3. K0215-REFERENCE'!A:D,3,FALSE) -> 19.52 | I37: =VLOOKUP(A37,'3. K0215-REFERENCE'!A:D,4,FALSE) -> 172597.25 | J37: =SUM(H37+I37) -> 172616.77 | K37: 808 | L37: 657 | M37: =+L37/(L37+K37) -> 0.44846416 | N37: =+J37*M37 -> 77412.435 | O37: =+J37-N37 -> 95204.335 | P37: =ROUND(((O37/$R$1)*$R$2),2) -> 1826.83 | Q37: =+O37+P37 -> 97031.165
A38: 03-333 | B38: FI$CAL | C38: 8880 | D38: 808 | E38: 0001 | F38: 100 | G38: 100 | H38: =VLOOKUP(A38,'3. K0215-REFERENCE'!A:D,3,FALSE) -> 72183.8 | I38: =VLOOKUP(A38,'3. K0215-REFERENCE'!A:D,4,FALSE) -> 71128.05 | J38: =SUM(H38+I38) -> 143311.85 | K38: 72904 | L38: 0 | M38: =+L38/(L38+K38) -> 0 | N38: =+J38*M38 -> 0 | O38: =+J38-N38 -> 143311.85 | P38: =ROUND(((O38/$R$1)*$R$2),2) -> 2749.94 | Q38: =+O38+P38 -> 146061.79
A39: 03-590 | B39: STATE PERSONNEL BOARD | C39: 7503 | D39: 808 | E39: 0001 | F39: 100 | G39: 100 | H39: =VLOOKUP(A39,'3. K0215-REFERENCE'!A:D,3,FALSE) -> 1562466.5 | I39: =VLOOKUP(A39,'3. K0215-REFERENCE'!A:D,4,FALSE) -> 332405.75 | J39: =SUM(H39+I39) -> 1894872.2 | K39: 2519 | L39: 0 | M39: =+L39/(L39+K39) -> 0 | N39: =+J39*M39 -> 0 | O39: =+J39-N39 -> 1894872.2 | P39: =ROUND(((O39/$R$1)*$R$2),2) -> 36359.82 | Q39: =+O39+P39 -> 1931232.1
A40: 99-275 | B40: CALPERS | C40: 7900 | D40: 808 | E40: 0001 | F40: 100 | G40: 100 | H40: =VLOOKUP(A40,'3. K0215-REFERENCE'!A:D,3,FALSE) -> 1872848.1 | I40: =VLOOKUP(A40,'3. K0215-REFERENCE'!A:D,4,FALSE) -> 1347131.5 | J40: =SUM(H40+I40) -> 3219979.6 | K40: 1657000 | L40: 0 | M40: =+L40/(L40+K40) -> 0 | N40: =+J40*M40 -> 0 | O40: =+J40-N40 -> 3219979.6 | P40: =ROUND(((O40/$R$1)*$R$2),2) -> 61786.69 | Q40: =+O40+P40 -> 3281766.3
A41: 03-815 | B41: CA STATE TEACHER'S RETIREMENT SYSTEM | C41: 7920 | D41: 808 | E41: 0001 | F41: 100 | G41: 100 | H41: =VLOOKUP(A41,'3. K0215-REFERENCE'!A:D,3,FALSE) -> 143999.08 | I41: =VLOOKUP(A41,'3. K0215-REFERENCE'!A:D,4,FALSE) -> 316965.6 | J41: =SUM(H41+I41) -> 460964.68 | K41: 0 | L41: 0 | M41: 0 | N41: =+J41*M41 -> 0 | O41: =+J41-N41 -> 460964.68 | P41: =ROUND(((O41/$R$1)*$R$2),2) -> 8845.24 | Q41: =+O41+P41 -> 469809.92
A42: 24-300 | B42: DEPARTMENT OF FINANCE | C42: 8860 | D42: 808 | E42: 0001 | F42: 100 | G42: 100 | H42: =VLOOKUP(A42,'3. K0215-REFERENCE'!A:D,3,FALSE) -> 1174.51 | I42: =VLOOKUP(A42,'3. K0215-REFERENCE'!A:D,4,FALSE) -> 107569.41 | J42: =SUM(H42+I42) -> 108743.92 | K42: 43554 | L42: 0 | M42: =+L42/(L42+K42) -> 0 | N42: =+J42*M42 -> 0 | O42: =+J42-N42 -> 108743.92 | P42: =ROUND(((O42/$R$1)*$R$2),2) -> 2086.64 | Q42: =+O42+P42 -> 110830.56
A43: 03-009 | B43: CA STATE AUDITOR'S OFFICE | C43: 8855 | D43: 808 | E43: 0001 | F43: 100 | G43: 100 | J43: =SUM(H43+I43) -> 0 | K43: 21606 | L43: 0 | M43: =+L43/(L43+K43) -> 0 | N43: =+J43*M43 -> 0 | O43: =+J43-N43 -> 0 | P43: =ROUND(((O43/$R$1)*$R$2),2) -> 0 | Q43: =+O43+P43 -> 0
A44: 03-305 | B44: OFFICE OF ADMINISTRATION LAW | C44: 7910 | D44: 808 | E44: 0001 | F44: 100 | G44: 100 | J44: =SUM(H44+I44) -> 0 | K44: 3032 | L44: 0 | M44: =IFERROR(+L44/(L44+K44),0) -> 0 | N44: =+J44*M44 -> 0 | O44: =+J44-N44 -> 0 | P44: =ROUND(((O44/$R$1)*$R$2),2) -> 0 | Q44: =+O44+P44 -> 0
D45: 808 Total | H45: =SUBTOTAL(9,H2:H44) -> 27403256 | I45: =SUBTOTAL(9,I2:I44) -> 57947307 | J45: =SUBTOTAL(9,J2:J44) -> 85350563 | K45: =SUBTOTAL(9,K2:K44) -> 10599712 | L45: =SUBTOTAL(9,L2:L44) -> 2790099 | M45: =SUBTOTAL(9,M2:M44) -> 1.8038965 | N45: =SUBTOTAL(9,N2:N44) -> 8863732.7 | O45: =SUBTOTAL(9,O2:O44) -> 76486831 | ... Q45: =SUBTOTAL(9,Q2:Q44) -> 77954501 | R45: TO TAB 1
A46: 18-174 | B46: DEPT OF EDUCATION | C46: 6100 | D46: 810 | E46: 0001 | F46: 100 | G46: 100 | H46: =VLOOKUP(A46,'3. K0215-REFERENCE'!A:D,3,FALSE) -> 582837.31 | I46: =VLOOKUP(A46,'3. K0215-REFERENCE'!A:D,4,FALSE) -> 1521469.2 | J46: =SUM(H46+I46) -> 2104306.5 | K46: 185843 | L46: 160713 | M46: =+L46/(L46+K46) -> 0.46374323 | N46: =+J46*M46 -> 975857.9 | O46: =+J46-N46 -> 1128448.6 | P46: =ROUND(((O46/$R$1)*$R$2),2) -> 21653.28 | Q46: =+O46+P46 -> 1150101.9
A47: 18-184 | B47: DOE-SCHOOL FOR THE BLIND | C47: 6100 | D47: 810 | E47: 0001 | F47: 100 | G47: 100 | H47: =VLOOKUP(A47,'3. K0215-REFERENCE'!A:D,3,FALSE) -> 59823.29 | I47: =VLOOKUP(A47,'3. K0215-REFERENCE'!A:D,4,FALSE) -> 481975.96 | J47: =SUM(H47+I47) -> 541799.25 | K47: 185843 | L47: 160713 | M47: =+L47/(L47+K47) -> 0.46374323 | N47: =+J47*M47 -> 251255.74 | O47: =+J47-N47 -> 290543.51 | P47: =ROUND(((O47/$R$1)*$R$2),2) -> 5575.1 | Q47: =+O47+P47 -> 296118.61
A48: 18-193 | B48: DOE-CENTRAL CA DIAGNOSTIC | C48: 6100 | D48: 810 | E48: 0001 | F48: 100 | G48: 100 | H48: =VLOOKUP(A48,'3. K0215-REFERENCE'!A:D,3,FALSE) -> 99163.72 | I48: =VLOOKUP(A48,'3. K0215-REFERENCE'!A:D,4,FALSE) -> 89203.17 | J48: =SUM(H48+I48) -> 188366.89 | K48: 185843 | L48: 160713 | M48: =+L48/(L48+K48) -> 0.46374323 | N48: =+J48*M48 -> 87353.871 | O48: =+J48-N48 -> 101013.02 | P48: =ROUND(((O48/$R$1)*$R$2),2) -> 1938.29 | Q48: =+O48+P48 -> 102951.31
A49: 18-199 | B49: DOE-NORTHERN CA DIAGNOSTIC | C49: 6100 | D49: 810 | E49: 0001 | F49: 100 | G49: 100 | H49: =VLOOKUP(A49,'3. K0215-REFERENCE'!A:D,3,FALSE) -> 0 | I49: =VLOOKUP(A49,'3. K0215-REFERENCE'!A:D,4,FALSE) -> 51637.75 | J49: =SUM(H49+I49) -> 51637.75 | K49: 185843 | L49: 160713 | M49: =+L49/(L49+K49) -> 0.46374323 | N49: =+J49*M49 -> 23946.657 | O49: =+J49-N49 -> 27691.093 | P49: =ROUND(((O49/$R$1)*$R$2),2) -> 531.35 | Q49: =+O49+P49 -> 28222.443
A50: 18-202 | B50: DIAGNOSTIC SCHOOL FOR NHC | C50: 6100 | D50: 810 | E50: 0001 | F50: 100 | G50: 100 | H50: =VLOOKUP(A50,'3. K0215-REFERENCE'!A:D,3,FALSE) -> 7044.08 | I50: =VLOOKUP(A50,'3. K0215-REFERENCE'!A:D,4,FALSE) -> 63375.16 | J50: =SUM(H50+I50) -> 70419.24 | K50: 185843 | L50: 160713 | M50: =+L50/(L50+K50) -> 0.46374323 | N50: =+J50*M50 -> 32656.446 | O50: =+J50-N50 -> 37762.794 | P50: =ROUND(((O50/$R$1)*$R$2),2) -> 724.61 | Q50: =+O50+P50 -> 38487.404
A51: 18-204 | B51: DOE-FREMONT DEAF SCHOOL | C51: 6100 | D51: 810 | E51: 0001 | F51: 100 | G51: 100 | H51: =VLOOKUP(A51,'3. K0215-REFERENCE'!A:D,3,FALSE) -> 88099.54 | I51: =VLOOKUP(A51,'3. K0215-REFERENCE'!A:D,4,FALSE) -> 426659.05 | J51: =SUM(H51+I51) -> 514758.59 | K51: 185843 | L51: 160713 | M51: =+L51/(L51+K51) -> 0.46374323 | N51: =+J51*M51 -> 238715.81 | O51: =+J51-N51 -> 276042.78 | P51: =ROUND(((O51/$R$1)*$R$2),2) -> 5296.86 | Q51: =+O51+P51 -> 281339.64
A52: 18-205 | B52: DOE-RIVERSIDE DEAF SCHOOL | C52: 6100 | D52: 810 | E52: 0001 | F52: 100 | G52: 100 | H52: =VLOOKUP(A52,'3. K0215-REFERENCE'!A:D,3,FALSE) -> 1905710.9 | I52: =VLOOKUP(A52,'3. K0215-REFERENCE'!A:D,4,FALSE) -> 6139760.2 | J52: =SUM(H52+I52) -> 8045471.1 | K52: 185843 | L52: 160713 | M52: =+L52/(L52+K52) -> 0.46374323 | N52: =+J52*M52 -> 3731032.8 | O52: =+J52-N52 -> 4314438.3 | P52: =ROUND(((O52/$R$1)*$R$2),2) -> 82787.75 | Q52: =+O52+P52 -> 4397226.1
A53: 56-650 | B53: CSU, CHANCELLOR'S OFFICE | C53: 6610 | D53: 810 | E53: 0001 | F53: 100 | G53: 100 | J53: =SUM(H53+I53) -> 0 | K53: 5024184 | L53: 0 | M53: =IFERROR(+L53/(L53+K53),0) -> 0 | N53: =+J53*M53 -> 0 | O53: =+J53-N53 -> 0 | P53: =ROUND(((O53/$R$1)*$R$2),2) -> 0 | Q53: =+O53+P53 -> 0
A54: 55-240 | B54: CSU,CALIF MARITIME ACADEMY | C54: 6752 | D54: 810 | E54: 0001 | F54: 100 | G54: 100 | J54: =SUM(H54+I54) -> 0 | K54: 0 | L54: 0 | M54: =IFERROR(+L54/(L54+K54),0) -> 0 | N54: =+J54*M54 -> 0 | O54: =+J54-N54 -> 0 | P54: =ROUND(((O54/$R$1)*$R$2),2) -> 0 | Q54: =+O54+P54 -> 0
A55: 55-253 | B55: CSU, NORTHRIDGE | C55: 6760 | D55: 810 | E55: 0001 | F55: 100 | G55: 100 | J55: =SUM(H55+I55) -> 0 | K55: 0 | L55: 0 | M55: =IFERROR(+L55/(L55+K55),0) -> 0 | N55: =+J55*M55 -> 0 | O55: =+J55-N55 -> 0 | P55: =ROUND(((O55/$R$1)*$R$2),2) -> 0 | Q55: =+O55+P55 -> 0
A56: 56-653 | B56: CSU, LONG BEACH | C56: 6740 | D56: 810 | E56: 0001 | F56: 100 | G56: 100 | J56: =SUM(H56+I56) -> 0 | K56: 0 | L56: 0 | M56: =IFERROR(+L56/(L56+K56),0) -> 0 | N56: =+J56*M56 -> 0 | O56: =+J56-N56 -> 0 | P56: =ROUND(((O56/$R$1)*$R$2),2) -> 0 | Q56: =+O56+P56 -> 0
A57: 55-196 | B57: POMONA STATE POLY UNIVERSITY | C57: 6770 | D57: 810 | E57: 0001 | F57: 100 | G57: 100 | J57: =SUM(H57+I57) -> 0 | K57: 0 | L57: 0 | M57: =IFERROR(+L57/(L57+K57),0) -> 0 | N57: =+J57*M57 -> 0 | O57: =+J57-N57 -> 0 | P57: =ROUND(((O57/$R$1)*$R$2),2) -> 0 | Q57: =+O57+P57 -> 0
A58: 33-670 | B58: CSU SAN MARCOS | C58: 6840 | D58: 810 | E58: 0001 | F58: 100 | G58: 100 | J58: =SUM(H58+I58) -> 0 | K58: 0 | L58: 0 | M58: =IFERROR(+L58/(L58+K58),0) -> 0 | N58: =+J58*M58 -> 0 | O58: =+J58-N58 -> 0 | P58: =ROUND(((O58/$R$1)*$R$2),2) -> 0 | Q58: =+O58+P58 -> 0 | R58: Sum of Exp 810 - Fund 1031
A59: 99-162 | B59: CA INST FOR REGENERATIVE MEDICINE | C59: 6445 | D59: 810 | E59: 1031 | F59: 100 | G59: 100 | J59: =SUM(H59+I59) -> 0 | K59: 0 | L59: 0 | M59: =IFERROR(+L59/(L59+K59),0) -> 0 | N59: =+J59*M59 -> 0 | O59: =+J59-N59 -> 0 | P59: =ROUND(((O59/$R$1)*$R$2),2) -> 0 | Q59: =+O59+P59 -> 0 | R59: =SUMIF($E$46:$E$62,"1031",$Q$46:$Q$62) -> 0 | S59: TO TAB 1
A60: 99-175 | B60: CALIFORNIA STATE LIBRARY | C60: 6120 | D60: 810 | E60: 0001 | F60: 100 | G60: 100 | H60: =VLOOKUP(A60,'3. K0215-REFERENCE'!A:D,3,FALSE) -> 0 | I60: =VLOOKUP(A60,'3. K0215-REFERENCE'!A:D,4,FALSE) -> 30705.54 | J60: =SUM(H60+I60) -> 30705.54 | K60: 31951 | L60: 5181 | M60: =+L60/(L60+K60) -> 0.13952925 | N60: =+J60*M60 -> 4284.3209 | O60: =+J60-N60 -> 26421.219 | P60: =ROUND(((O60/$R$1)*$R$2),2) -> 506.98 | Q60: =+O60+P60 -> 26928.199
A61: 03-364 | B61: BOARD GOV CA COMM COLLEGE | C61: 6870 | D61: 810 | E61: 0001 | F61: 100 | G61: 100 | H61: =VLOOKUP(A61,'3. K0215-REFERENCE'!A:D,3,FALSE) -> 0 | I61: =VLOOKUP(A61,'3. K0215-REFERENCE'!A:D,4,FALSE) -> 7923.52 | J61: =SUM(H61+I61) -> 7923.52 | K61: 77594 | L61: 0 | M61: =+L61/(L61+K61) -> 0 | N61: =+J61*M61 -> 0 | O61: =+J61-N61 -> 7923.52 | P61: =ROUND(((O61/$R$1)*$R$2),2) -> 152.04 | Q61: =+O61+P61 -> 8075.56 | R61: Sum of Exp 810 - Fund 0001
A62: 03-270 | B62: CA STUDENT AID COMMISSION | C62: 6980 | D62: 810 | E62: 0001 | F62: 100 | G62: 100 | H62: =VLOOKUP(A62,'3. K0215-REFERENCE'!A:D,3,FALSE) -> 28178.01 | I62: =VLOOKUP(A62,'3. K0215-REFERENCE'!A:D,4,FALSE) -> 150310.88 | J62: =SUM(H62+I62) -> 178488.89 | K62: 24360 | L62: 0 | M62: =+L62/(L62+K62) -> 0 | N62: =+J62*M62 -> 0 | O62: =+J62-N62 -> 178488.89 | P62: =ROUND(((O62/$R$1)*$R$2),2) -> 3424.94 | Q62: =+O62+P62 -> 181913.83 | R62: =SUMIF($E$46:$E$62,"0001",$Q$46:$Q$62) -> 6511365 | S62: TO TAB 1
D63: 810 Total | H63: =SUBTOTAL(9,H46:H62) -> 2770856.8 | I63: =SUBTOTAL(9,I46:I62) -> 8963020.4 | J63: =SUBTOTAL(9,J46:J62) -> 11733877 | K63: =SUBTOTAL(9,K46:K62) -> 6458990 | L63: =SUBTOTAL(9,L46:L62) -> 1130172 | M63: =SUBTOTAL(9,M46:M62) -> 3.3857319 | N63: =SUBTOTAL(9,N46:N62) -> 5345103.5 | O63: =SUBTOTAL(9,O46:O62) -> 6388773.8 | ... Q63: =SUBTOTAL(9,Q46:Q62) -> 6511365
A64: 03-797 | B64: DEPARTMENT OF AGING | C64: 4170 | D64: 815 | E64: 0001 | F64: 100 | G64: 100 | H64: =VLOOKUP(A64,'3. K0215-REFERENCE'!A:D,3,FALSE) -> 66159.9 | I64: =VLOOKUP(A64,'3. K0215-REFERENCE'!A:D,4,FALSE) -> 153022.47 | J64: =SUM(H64:I64) -> 219182.37 | K64: 40215 | L64: 18945 | M64: =+L64/(L64+K64) -> 0.32023327 | N64: =+J64*M64 -> 70189.486 | O64: =+J64-N64 -> 148992.88 | P64: =ROUND(((O64/$R$1)*$R$2),2) -> 2858.96 | Q64: =+O64+P64 -> 151851.84
A65: 03-397 | B65: LABOR & WORKFORCE DEV AGY | C65: 0559 | D65: 815 | E65: 0001 | F65: 100 | G65: 100 | H65: =VLOOKUP(A65,'3. K0215-REFERENCE'!A:D,3,FALSE) -> 1531.66 | I65: =VLOOKUP(A65,'3. K0215-REFERENCE'!A:D,4,FALSE) -> 66845.09 | J65: =SUM(H65:I65) -> 68376.75 | K65: 3729 | L65: 0 | M65: =+L65/(L65+K65) -> 0 | N65: =+J65*M65 -> 0 | O65: =+J65-N65 -> 68376.75 | P65: =ROUND(((O65/$R$1)*$R$2),2) -> 1312.05 | Q65: =+O65+P65 -> 69688.8
A66: 99-795 | B66: GOVERNOR'S COMMITTEE ON EMPOYMENT OF PEOPLE WITH DISABILITIES | C66: 7100 | D66: 815 | E66: 0870 | F66: 100 | G66: 100 | J66: =SUM(H66:I66) -> 0 | K66: 0 | L66: 0 | M66: =IFERROR(+L66/(L66+K66),0) -> 0 | N66: =+J66*M66 -> 0 | O66: =+J66-N66 -> 0 | P66: =ROUND(((O66/$R$1)*$R$2),2) -> 0 | Q66: =+O66+P66 -> 0
A67: 03-279 | B67: UNEMPLOYMENT INS APPS BD | C67: 7100 | D67: 815 | E67: 0870 | F67: 100 | G67: 100 | H67: =VLOOKUP(A67,'3. K0215-REFERENCE'!A:D,3,FALSE) -> 677732.25 | I67: =VLOOKUP(A67,'3. K0215-REFERENCE'!A:D,4,FALSE) -> 1606791.8 | J67: =SUM(H67:I67) -> 2284524 | K67: 0 | L67: 0 | M67: =IF((L67+K67)=0, 0, L67/(L67+K67)) -> 0 | N67: =+J67*M67 -> 0 | O67: =+J67-N67 -> 2284524 | P67: =ROUND(((O67/$R$1)*$R$2),2) -> 43836.67 | Q67: =+O67+P67 -> 2328360.7
A68: 74-280 | B68: EMPLOYMENT DEVELOPMENT | C68: 7100 | D68: 815 | E68: 0870 | F68: 100 | G68: 100 | H68: =VLOOKUP(A68,'3. K0215-REFERENCE'!A:D,3,FALSE) -> 20758144 | I68: =VLOOKUP(A68,'3. K0215-REFERENCE'!A:D,4,FALSE) -> 49517617 | J68: =SUM(H68:I68) -> 70275762 | K68: 0 | L68: 0 | M68: =IF((L68+K68)=0, 0, L68/(L68+K68)) -> 0 | N68: =+J68*M68 -> 0 | O68: =+J68-N68 -> 70275762 | P68: =ROUND(((O68/$R$1)*$R$2),2) -> 1348488.9 | Q68: =+O68+P68 -> 71624250 | R68: Sum of Exp 815 - Fund 0870
A69: 74-281 | B69: EDD-EMPYMT TRAINING PANEL | C69: 7100 | D69: 815 | E69: 0870 | F69: 100 | G69: 100 | H69: =VLOOKUP(A69,'3. K0215-REFERENCE'!A:D,3,FALSE) -> 0 | I69: =VLOOKUP(A69,'3. K0215-REFERENCE'!A:D,4,FALSE) -> 51523.98 | J69: =SUM(H69:I69) -> 51523.98 | K69: 0 | L69: 0 | M69: =IF((L69+K69)=0, 0, L69/(L69+K69)) -> 0 | N69: =+J69*M69 -> 0 | O69: =+J69-N69 -> 51523.98 | P69: =ROUND(((O69/$R$1)*$R$2),2) -> 988.67 | Q69: =+O69+P69 -> 52512.65 | R69: =SUM(Q66:Q69) -> 74005124 | S69: TO TAB 1
A70: 03-315 | B70: PUBLIC EMPLMT RELATION BD | C70: 7320 | D70: 815 | E70: 0001 | F70: 100 | G70: 100 | H70: =VLOOKUP(A70,'3. K0215-REFERENCE'!A:D,3,FALSE) -> 0 | I70: =VLOOKUP(A70,'3. K0215-REFERENCE'!A:D,4,FALSE) -> 7914.61 | J70: =SUM(H70:I70) -> 7914.61 | K70: 17712 | L70: 0 | M70: =IF((L70+K70)=0, 0, L70/(L70+K70)) -> 0 | N70: =+J70*M70 -> 0 | O70: =+J70-N70 -> 7914.61 | P70: =ROUND(((O70/$R$1)*$R$2),2) -> 151.87 | Q70: =+O70+P70 -> 8066.48
A71: 52-580 | B71: CA DEPT OF PUBLIC HEALTH | C71: 4265 | D71: 815 | E71: 0001 | F71: 100 | G71: 100 | H71: =VLOOKUP(A71,'3. K0215-REFERENCE'!A:D,3,FALSE) -> 2343117.8 | I71: =VLOOKUP(A71,'3. K0215-REFERENCE'!A:D,4,FALSE) -> 11600029 | J71: =SUM(H71:I71) -> 13943147 | K71: 717149 | L71: 408790 | M71: =+L71/(L71+K71) -> 0.36306585 | N71: =+J71*M71 -> 5062280.6 | O71: =+J71-N71 -> 8880866.6 | P71: =ROUND(((O71/$R$1)*$R$2),2) -> 170410.82 | Q71: =+O71+P71 -> 9051277.5
A72: 52-581 | B72: CA DEPT OF PUBLIC HEALTH | C72: 4265 | D72: 815 | E72: 0001 | F72: 100 | G72: 100 | J72: =SUM(H72:I72) -> 0 | K72: 717149 | L72: 408790 | M72: =+L72/(L72+K72) -> 0.36306585 | N72: =+J72*M72 -> 0 | O72: =+J72-N72 -> 0 | P72: =ROUND(((O72/$R$1)*$R$2),2) -> 0 | Q72: =+O72+P72 -> 0
A73: 03-475 | B73: MHSOAC | C73: 4560 | D73: 815 | E73: 0001 | F73: 100 | G73: 100 | J73: =SUM(H73:I73) -> 0 | K73: 0 | L73: 0 | M73: =IFERROR(+L73/(L73+K73),0) -> 0 | N73: =+J73*M73 -> 0 | O73: =+J73-N73 -> 0 | P73: =ROUND(((O73/$R$1)*$R$2),2) -> 0 | Q73: =+O73+P73 -> 0
A74: 03-799 | B74: CA HEALTH & HUMAN SVCS | C74: 0530 | D74: 815 | E74: 0001 | F74: 100 | G74: 100 | H74: =VLOOKUP(A74,'3. K0215-REFERENCE'!A:D,3,FALSE) -> 0 | I74: =VLOOKUP(A74,'3. K0215-REFERENCE'!A:D,4,FALSE) -> 33538.36 | J74: =SUM(H74:I74) -> 33538.36 | K74: 64583 | L74: 6931 | M74: =IFERROR(+L74/(L74+K74),0) -> 0.096918086 | N74: =+J74*M74 -> 3250.4737 | O74: =+J74-N74 -> 30287.886 | P74: =ROUND(((O74/$R$1)*$R$2),2) -> 581.18 | Q74: =+O74+P74 -> 30869.066
A75: 34-802 | B75: DEPT OF HEALTH CARE SVCS | C75: 4260 | D75: 815 | E75: 0001 | F75: 100 | G75: 100 | H75: =VLOOKUP(A75,'3. K0215-REFERENCE'!A:D,3,FALSE) -> 314645 | I75: =VLOOKUP(A75,'3. K0215-REFERENCE'!A:D,4,FALSE) -> 193322.46 | J75: =SUM(H75:I75) -> 507967.46 | K75: 421416 | L75: 548422 | M75: =+L75/(L75+K75) -> 0.56547795 | N75: =+J75*M75 -> 287244.4 | O75: =+J75-N75 -> 220723.06 | P75: =ROUND(((O75/$R$1)*$R$2),2) -> 4235.35 | Q75: =+O75+P75 -> 224958.41
A76: 34-803 | B76: DEPT OF HEALTH CARE SVCS | C76: 4260 | D76: 815 | E76: 0001 | F76: 100 | G76: 100 | J76: =SUM(H76:I76) -> 0 | K76: 421416 | L76: 548422 | M76: 0 | N76: =+J76*M76 -> 0 | O76: =+J76-N76 -> 0 | P76: =ROUND(((O76/$R$1)*$R$2),2) -> 0 | Q76: =+O76+P76 -> 0
A77: 34-804 | B77: DEPT OF HEALTH CARE SVCS | C77: 4260 | D77: 815 | E77: 0001 | F77: 100 | G77: 100 | J77: =SUM(H77:I77) -> 0 | K77: 421416 | L77: 548422 | M77: =IFERROR(+L77/(L77+K77),0) -> 0.56547795 | N77: =+J77*M77 -> 0 | O77: =+J77-N77 -> 0 | P77: =ROUND(((O77/$R$1)*$R$2),2) -> 0 | Q77: =+O77+P77 -> 0
A78: 34-805 | B78: DEPT OF HEALTH CARE SVCS | C78: 4260 | D78: 815 | E78: 0001 | F78: 100 | G78: 100 | H78: =VLOOKUP(A78,'3. K0215-REFERENCE'!A:D,3,FALSE) -> 297101.2 | I78: =VLOOKUP(A78,'3. K0215-REFERENCE'!A:D,4,FALSE) -> 1391561.6 | J78: =SUM(H78:I78) -> 1688662.8 | K78: 421416 | L78: 548422 | M78: =+L78/(L78+K78) -> 0.56547795 | N78: =+J78*M78 -> 954901.55 | O78: =+J78-N78 -> 733761.22 | P78: =ROUND(((O78/$R$1)*$R$2),2) -> 14079.8 | Q78: =+O78+P78 -> 747841.02
A79: 34-806 | B79: DEPT OF HEALTH CARE SVCS | C79: 4260 | D79: 815 | E79: 0001 | F79: 100 | G79: 100 | H79: =VLOOKUP(A79,'3. K0215-REFERENCE'!A:D,3,FALSE) -> 1284096.9 | I79: =VLOOKUP(A79,'3. K0215-REFERENCE'!A:D,4,FALSE) -> 1623771.3 | J79: =SUM(H79:I79) -> 2907868.2 | K79: 421416 | L79: 548422 | M79: =+L79/(L79+K79) -> 0.56547795 | N79: =+J79*M79 -> 1644335.3 | O79: =+J79-N79 -> 1263532.8 | P79: =ROUND(((O79/$R$1)*$R$2),2) -> 24245.34 | Q79: =+O79+P79 -> 1287778.2
A80: 34-807 | B80: DEPT OF HEALTH CARE SVCS | C80: 4260 | D80: 815 | E80: 0001 | F80: 100 | G80: 100 | J80: =SUM(H80:I80) -> 0 | K80: 421416 | L80: 548422 | M80: =IFERROR(+L80/(L80+K80),0) -> 0.56547795 | N80: =+J80*M80 -> 0 | O80: =+J80-N80 -> 0 | P80: =ROUND(((O80/$R$1)*$R$2),2) -> 0 | Q80: =+O80+P80 -> 0
A81: 34-808 | B81: DEPT OF HEALTH CARE SVCS | C81: 4260 | D81: 815 | E81: 0001 | F81: 100 | G81: 100 | H81: =VLOOKUP(A81,'3. K0215-REFERENCE'!A:D,3,FALSE) -> 202667.79 | I81: =VLOOKUP(A81,'3. K0215-REFERENCE'!A:D,4,FALSE) -> 485794.34 | J81: =SUM(H81:I81) -> 688462.13 | K81: 421416 | L81: 548422 | M81: =+L81/(L81+K81) -> 0.56547795 | N81: =+J81*M81 -> 389310.15 | O81: =+J81-N81 -> 299151.98 | P81: =ROUND(((O81/$R$1)*$R$2),2) -> 5740.29 | Q81: =+O81+P81 -> 304892.27
A82: 34-809 | B82: DEPT OF HEALTH CARE SVCS | C82: 4260 | D82: 815 | E82: 0001 | F82: 100 | G82: 100 | J82: =SUM(H82:I82) -> 0 | K82: 421416 | L82: 548422 | M82: =IFERROR(+L82/(L82+K82),0) -> 0.56547795 | N82: =+J82*M82 -> 0 | O82: =+J82-N82 -> 0 | P82: =ROUND(((O82/$R$1)*$R$2),2) -> 0 | Q82: =+O82+P82 -> 0
A83: 33-505 | B83: DDS-SIERRA VISTA | C83: 4300 | D83: 815 | E83: 0001 | F83: 100 | G83: 100 | H83: =VLOOKUP(A83,'3. K0215-REFERENCE'!A:D,3,FALSE) -> 8219.74 | I83: =VLOOKUP(A83,'3. K0215-REFERENCE'!A:D,4,FALSE) -> 197518.63 | J83: =SUM(H83:I83) -> 205738.37 | K83: 354587 | L83: 2777 | M83: =+L83/(L83+K83) -> 0.0077707883 | N83: =+J83*M83 -> 1598.7493 | O83: =+J83-N83 -> 204139.62 | P83: =ROUND(((O83/$R$1)*$R$2),2) -> 3917.14 | Q83: =+O83+P83 -> 208056.76
A84: 33-468 | B84: DEPT DEV'T SERVICE | C84: 4300 | D84: 815 | E84: 0001 | F84: 100 | G84: 100 | J84: =SUM(H84:I84) -> 0 | K84: 354587 | L84: 2777 | M84: =IFERROR(+L84/(L84+K84),0) -> 0.0077707883 | N84: =+J84*M84 -> 0 | O84: =+J84-N84 -> 0 | P84: =ROUND(((O84/$R$1)*$R$2),2) -> 0 | Q84: =+O84+P84 -> 0
A85: 33-473 | B85: DDS-ADMINISTRATION | C85: 4300 | D85: 815 | E85: 0001 | F85: 100 | G85: 100 | H85: =VLOOKUP(A85,'3. K0215-REFERENCE'!A:D,3,FALSE) -> 664548.47 | I85: =VLOOKUP(A85,'3. K0215-REFERENCE'!A:D,4,FALSE) -> 1845850.4 | J85: =SUM(H85:I85) -> 2510398.9 | K85: 354587 | L85: 2777 | M85: =+L85/(L85+K85) -> 0.0077707883 | N85: =+J85*M85 -> 19507.778 | O85: =+J85-N85 -> 2490891.1 | P85: =ROUND(((O85/$R$1)*$R$2),2) -> 47796.55 | Q85: =+O85+P85 -> 2538687.7
A86: 33-453 | B86: DDS-AGNEWS | C86: 4300 | D86: 815 | E86: 0001 | F86: 100 | G86: 100 | H86: =VLOOKUP(A86,'3. K0215-REFERENCE'!A:D,3,FALSE) -> 1097315.3 | I86: =VLOOKUP(A86,'3. K0215-REFERENCE'!A:D,4,FALSE) -> 514906.49 | J86: =SUM(H86:I86) -> 1612221.8 | K86: 354587 | L86: 2777 | M86: =+L86/(L86+K86) -> 0.0077707883 | N86: =+J86*M86 -> 12528.235 | O86: =+J86-N86 -> 1599693.6 | P86: =ROUND(((O86/$R$1)*$R$2),2) -> 30695.78 | Q86: =+O86+P86 -> 1630389.4
A87: 33-518 | B87: DDS-FAIRVIEW | C87: 4300 | D87: 815 | E87: 0001 | F87: 100 | G87: 100 | H87: =VLOOKUP(A87,'3. K0215-REFERENCE'!A:D,3,FALSE) -> 5424086.2 | I87: =VLOOKUP(A87,'3. K0215-REFERENCE'!A:D,4,FALSE) -> 15985552 | J87: =SUM(H87:I87) -> 21409638 | K87: 354587 | L87: 2777 | M87: =+L87/(L87+K87) -> 0.0077707883 | N87: =+J87*M87 -> 166369.77 | O87: =+J87-N87 -> 21243268 | P87: =ROUND(((O87/$R$1)*$R$2),2) -> 407627.19 | Q87: =+O87+P87 -> 21650895
A88: 33-497 | B88: DDS-LANTERMAN | C88: 4300 | D88: 815 | E88: 0001 | F88: 100 | G88: 100 | H88: =VLOOKUP(A88,'3. K0215-REFERENCE'!A:D,3,FALSE) -> 1650440.5 | I88: =VLOOKUP(A88,'3. K0215-REFERENCE'!A:D,4,FALSE) -> 3847833.8 | J88: =SUM(H88:I88) -> 5498274.2 | K88: 354587 | L88: 2777 | M88: =+L88/(L88+K88) -> 0.0077707883 | N88: =+J88*M88 -> 42725.925 | O88: =+J88-N88 -> 5455548.3 | P88: =ROUND(((O88/$R$1)*$R$2),2) -> 104683.98 | Q88: =+O88+P88 -> 5560232.3
A89: 33-504 | B89: DDS-CANYON SPRINGS | C89: 4300 | D89: 815 | E89: 0001 | F89: 100 | G89: 100 | H89: =VLOOKUP(A89,'3. K0215-REFERENCE'!A:D,3,FALSE) -> 504429.09 | I89: =VLOOKUP(A89,'3. K0215-REFERENCE'!A:D,4,FALSE) -> 1741235.2 | J89: =SUM(H89:I89) -> 2245664.2 | K89: 354587 | L89: 2777 | M89: =+L89/(L89+K89) -> 0.0077707883 | N89: =+J89*M89 -> 17450.582 | O89: =+J89-N89 -> 2228213.7 | P89: =ROUND(((O89/$R$1)*$R$2),2) -> 42756.16 | Q89: =+O89+P89 -> 2270969.8
A90: 33-515 | B90: DDS-PORTERVILLE | C90: 4300 | D90: 815 | E90: 0001 | F90: 100 | G90: 100 | H90: =VLOOKUP(A90,'3. K0215-REFERENCE'!A:D,3,FALSE) -> 4582984.8 | I90: =VLOOKUP(A90,'3. K0215-REFERENCE'!A:D,4,FALSE) -> 18827127 | J90: =SUM(H90:I90) -> 23410112 | K90: 354587 | L90: 2777 | M90: =+L90/(L90+K90) -> 0.0077707883 | N90: =+J90*M90 -> 181915.02 | O90: =+J90-N90 -> 23228197 | P90: =ROUND(((O90/$R$1)*$R$2),2) -> 445715.06 | Q90: =+O90+P90 -> 23673912
A91: 32-437 | B91: DSH-COALINGA | C91: 4440 | D91: 815 | E91: 0001 | F91: 100 | G91: 100 | H91: =VLOOKUP(A91,'3. K0215-REFERENCE'!A:D,3,FALSE) -> 12914272 | I91: =VLOOKUP(A91,'3. K0215-REFERENCE'!A:D,4,FALSE) -> 31057257 | J91: =SUM(H91:I91) -> 43971529 | K91: 3197474 | L91: 0 | M91: =+L91/(L91+K91) -> 0 | N91: =+J91*M91 -> 0 | O91: =+J91-N91 -> 43971529 | P91: =ROUND(((O91/$R$1)*$R$2),2) -> 843749.21 | Q91: =+O91+P91 -> 44815278
A92: 33-506 | B92: SONOMA DEVELOPMENTAL CTR | C92: 4300 | D92: 815 | E92: 0001 | F92: 100 | G92: 100 | J92: =SUM(H92:I92) -> 0 | K92: 354587 | L92: 2777 | M92: =IFERROR(+L92/(L92+K92),0) -> 0.0077707883 | N92: =+J92*M92 -> 0 | O92: =+J92-N92 -> 0 | P92: =ROUND(((O92/$R$1)*$R$2),2) -> 0 | Q92: =+O92+P92 -> 0
A93: 33-507 | B93: DDS-SONOMA | C93: 4300 | D93: 815 | E93: 0001 | F93: 100 | G93: 100 | H93: =VLOOKUP(A93,'3. K0215-REFERENCE'!A:D,3,FALSE) -> 5196560.2 | I93: =VLOOKUP(A93,'3. K0215-REFERENCE'!A:D,4,FALSE) -> 4775677.3 | J93: =SUM(H93:I93) -> 9972237.4 | K93: 354587 | L93: 2777 | M93: =+L93/(L93+K93) -> 0.0077707883 | N93: =+J93*M93 -> 77492.146 | O93: =+J93-N93 -> 9894745.3 | P93: =ROUND(((O93/$R$1)*$R$2),2) -> 189865.66 | Q93: =+O93+P93 -> 10084611
A94: 32-461 | B94: DSH-SACRAMENTO | C94: 4440 | D94: 815 | E94: 0001 | F94: 100 | G94: 100 | H94: =VLOOKUP(A94,'3. K0215-REFERENCE'!A:D,3,FALSE) -> 350126.79 | I94: =VLOOKUP(A94,'3. K0215-REFERENCE'!A:D,4,FALSE) -> 650067.05 | J94: =SUM(H94:I94) -> 1000193.8 | K94: 3197474 | L94: 0 | M94: =+L94/(L94+K94) -> 0 | N94: =+J94*M94 -> 0 | O94: =+J94-N94 -> 1000193.8 | P94: =ROUND(((O94/$R$1)*$R$2),2) -> 19192.25 | Q94: =+O94+P94 -> 1019386.1
A95: 32-463 | B95: DEPT STATE HOSPITAL - STOCKTON | C95: 4440 | D95: 815 | E95: 0001 | F95: 100 | G95: 100 | J95: =SUM(H95:I95) -> 0 | K95: 3197474 | L95: 0 | M95: =IFERROR(+L95/(L95+K95),0) -> 0 | N95: =+J95*M95 -> 0 | O95: =+J95-N95 -> 0 | P95: =ROUND(((O95/$R$1)*$R$2),2) -> 0 | Q95: =+O95+P95 -> 0
A96: 32-455 | B96: DSH-ATASCADERO | C96: 4440 | D96: 815 | E96: 0001 | F96: 100 | G96: 100 | H96: =VLOOKUP(A96,'3. K0215-REFERENCE'!A:D,3,FALSE) -> 22185220 | I96: =VLOOKUP(A96,'3. K0215-REFERENCE'!A:D,4,FALSE) -> 31923085 | J96: =SUM(H96:I96) -> 54108305 | K96: 3197474 | L96: 0 | M96: =+L96/(L96+K96) -> 0 | N96: =+J96*M96 -> 0 | O96: =+J96-N96 -> 54108305 | P96: =ROUND(((O96/$R$1)*$R$2),2) -> 1038259.1 | Q96: =+O96+P96 -> 55146564
A97: 33-457 | B97: DDS-CAMARILLO | C97: 4440 | D97: 815 | E97: 0001 | F97: 100 | G97: 100 | H97: =VLOOKUP(A97,'3. K0215-REFERENCE'!A:D,3,FALSE) -> 1000254.8 | I97: =VLOOKUP(A97,'3. K0215-REFERENCE'!A:D,4,FALSE) -> 2389072.8 | J97: =SUM(H97:I97) -> 3389327.6 | K97: 3197474 | L97: 0 | M97: =+L97/(L97+K97) -> 0 | N97: =+J97*M97 -> 0 | O97: =+J97-N97 -> 3389327.6 | P97: =ROUND(((O97/$R$1)*$R$2),2) -> 65036.23 | Q97: =+O97+P97 -> 3454363.9
A98: 32-487 | B98: DSH-METROPOLITAN | C98: 4440 | D98: 815 | E98: 0001 | F98: 100 | G98: 100 | H98: =VLOOKUP(A98,'3. K0215-REFERENCE'!A:D,3,FALSE) -> 8620581.2 | I98: =VLOOKUP(A98,'3. K0215-REFERENCE'!A:D,4,FALSE) -> 24767468 | J98: =SUM(H98:I98) -> 33388050 | K98: 3197474 | L98: 0 | M98: =+L98/(L98+K98) -> 0 | N98: =+J98*M98 -> 0 | O98: =+J98-N98 -> 33388050 | P98: =ROUND(((O98/$R$1)*$R$2),2) -> 640667.75 | Q98: =+O98+P98 -> 34028717
A99: 32-480 | B99: DSH-NAPA | C99: 4440 | D99: 815 | E99: 0001 | F99: 100 | G99: 100 | H99: =VLOOKUP(A99,'3. K0215-REFERENCE'!A:D,3,FALSE) -> 15793064 | I99: =VLOOKUP(A99,'3. K0215-REFERENCE'!A:D,4,FALSE) -> 21254122 | J99: =SUM(H99:I99) -> 37047186 | K99: 3197474 | L99: 0 | M99: =+L99/(L99+K99) -> 0 | N99: =+J99*M99 -> 0 | O99: =+J99-N99 -> 37047186 | P99: =ROUND(((O99/$R$1)*$R$2),2) -> 710881.21 | Q99: =+O99+P99 -> 37758067
A100: 32-482 | B100: ACCOUNTING | C100: 4440 | D100: 815 | E100: 0001 | F100: 100 | G100: 100 | J100: =SUM(H100:I100) -> 0 | K100: 3197474 | L100: 0 | M100: =IFERROR(+L100/(L100+K100),0) -> 0 | N100: =+J100*M100 -> 0 | O100: =+J100-N100 -> 0 | P100: =ROUND(((O100/$R$1)*$R$2),2) -> 0 | Q100: =+O100+P100 -> 0
...

Sheet 3. K0215-REFERENCE
A1: AGENCY # | B1: Agency Name | C1: O/S COMP | D1: O/S MED | E1: TOTAL | G1: C
A2: 03-002 | B2: STATE SENATE EMPLOYEE | C2: 48431.85 | D2: 351671.68 | E2: =SUM(C2:D2) -> 400103.53 | G2: Source | H2: SCIF
A3: 03-004 | B3: STATE ASSEMBLY | C3: 145094.09 | D3: 787574.88 | E3: =SUM(C3:D3) -> 932668.97 | H3: WC Monthly list of State Contract Open Disability Claims Report as of 6/30/24
A4: 03-016 | B4: DEPT COMMUNITY SVCS & DEV | C4: 100 | D4: 55847.14 | E4: =SUM(C4:D4) -> 55947.14
A5: 03-037 | B5: CDCR-BOARD OF PRISON TERMS | C5: 10007.97 | D5: 234868.94 | E5: =SUM(C5:D5) -> 244876.91
A6: 03-040 | B6: VICTIM COMP & GOV CLMS BD | C6: 19.52 | D6: 172597.25 | E6: =SUM(C6:D6) -> 172616.77
A7: 03-163 | B7: OFFICE EMERGENCY SERVICES | C7: 2266882.4 | D7: 3908668.5 | E7: =SUM(C7:D7) -> 6175550.9
A8: 03-270 | B8: CA STUDENT AID COMMISSION | C8: 28178.01 | D8: 150310.88 | E8: =SUM(C8:D8) -> 178488.89
A9: 03-279 | B9: UNEMPLOYMENT INS APPS BD | C9: 677732.25 | D9: 1606791.8 | E9: =SUM(C9:D9) -> 2284524
A10: 03-297 | B10: OFFC OF THE INSPECTOR GENERAL | C10: 62263.34 | D10: 142282.46 | E10: =SUM(C10:D10) -> 204545.8
A11: 03-314 | B11: CALIFORNIA SCIENCE CENTER | C11: 681409.4 | D11: 426354.78 | E11: =SUM(C11:D11) -> 1107764.2
A12: 03-315 | B12: PUBLIC EMPLMT RELATION BD | C12: 0 | D12: 7914.61 | E12: =SUM(C12:D12) -> 7914.61
A13: 03-317 | B13: CA AFRICAN AMERICAN MUSEUM | C13: 6000 | D13: 41269.59 | E13: =SUM(C13:D13) -> 47269.59
A14: 03-325 | B14: FAIR POLITICAL PRACT COMM | C14: 4500 | D14: 45411.22 | E14: =SUM(C14:D14) -> 49911.22
A15: 03-326 | B15: DEPT FAIR EMPLMT & HOUSING | C15: 88752.72 | D15: 702553.34 | E15: =SUM(C15:D15) -> 791306.06
... A284: 99-817 | B284: DEPT CHILD SUPPORT SERVCS | C284: 97290.73 | D284: 138720.86 | E284: =SUM(C284:D284) -> 236011.59
A287: TOTAL | C287: =SUM(C2:C286) -> 1.4994149e+09 | D287: =SUM(D2:D286) -> 2.4868858e+09 | E287: =C287+D287 -> 3.9863007e+09 | F287: to Tab 1
C290: =C287 -> 1.4994149e+09 | D290: =D287 -> 2.4868858e+09 | E290: =E287 -> 3.9863007e+09 | F290: tab 3
C291: ='2. K0215-June 30, 2024'!H465 -> 1.4994149e+09 | D291: ='2. K0215-June 30, 2024'!I465 -> 2.4868858e+09 | E291: ='2. K0215-June 30, 2024'!J465 -> 3.9863007e+09 | F291: tab 2
C292: =C290-C291 -> 0 | D292: =D290-D291 -> 0 | E292: =E290-E291 -> 0

Sheet 4. Non Current Liab
A1: Workers' Compensation Liability
A2: Governmental Non Current Liability
A3: June 30, 2024
A5: FROM TAB 1
D6: Govn
B7: % of Current | C7: Govn | D7: Distributed
A8: Expenditure | B8: Govn WC | C8: Non Current | D8: Wrkrs Comp
A9: Codes | B9: Expense | C9: WC Liability | D9: Expenditure*
A10: 808 | B10: =+('1. Summary 2324'!D21+'1. Summary 2324'!D33+'1. Summary 2324'!D43+'1. Summary 2324'!D44+'1. Summary 2324'!D45+'1. Summary 2324'!D46)/(+'1. Summary 2324'!D$67+'1. Summary 2324'!D$30) -> 0.026308751 | C10: =+('1. Summary 2324'!G$89 -'1. Summary 2324'!F$86) -> -48772847 | D10: =(+B10*C$10) -> -1283152.7
A11: 810 | B11: =+(+'1. Summary 2324'!D22+'1. Summary 2324'!D23+'1. Summary 2324'!D34+'1. Summary 2324'!D47)/(+'1. Summary 2324'!D$67+'1. Summary 2324'!D$30) -> 0.0029774849 | C11: =+('1. Summary 2324'!G$89 -'1. Summary 2324'!F$86) -> -48772847 | D11: =(+B11*C$10) -> -145220.41
A12: 815 | B12: =+(+'1. Summary 2324'!D24+'1. Summary 2324'!D25+'1. Summary 2324'!D35+'1. Summary 2324'!D48+'1. Summary 2324'!D63+'1. Summary 2324'!D64+'1. Summary 2324'!D65)/(+'1. Summary 2324'!D$67+'1. Summary 2324'!D$30) -> 0.13243485 | C12: =+('1. Summary 2324'!G$89 -'1. Summary 2324'!F$86) -> -48772847 | D12: =(+B12*C$10) -> -6459224.7
A13: 820 | B13: =+('1. Summary 2324'!D26+'1. Summary 2324'!D36+'1. Summary 2324'!D39+'1. Summary 2324'!D54+'1. Summary 2324'!D55+'1. Summary 2324'!D56+'1. Summary 2324'!D57+'1. Summary 2324'!D58+'1. Summary 2324'!D59+'1. Summary 2324'!D60+'1. Summary 2324'!D61+'1. Summary 2324'!D66)/(+'1. Summary 2324'!D$67+'1. Summary 2324'!D$30) -> 0.08603593 | C13: =+('1. Summary 2324'!G$89 -'1. Summary 2324'!F$86) -> -48772847 | D13: =(+B13*C$10) -> -4196217.2
A14: 825 | B14: =+(+'1. Summary 2324'!D27+'1. Summary 2324'!D37+'1. Summary 2324'!D49+'1. Summary 2324'!D50+'1. Summary 2324'!D51+'1. Summary 2324'!D52+'1. Summary 2324'!D53+'1. Summary 2324'!D62)/(+'1. Summary 2324'!D$67+'1. Summary 2324'!D$30) -> 0.0035602294 | C14: =+('1. Summary 2324'!G$89 -'1. Summary 2324'!F$86) -> -48772847 | D14: =(+B14*C$10)+0.06 -> -173642.47
A15: 830 | B15: =+(+'1. Summary 2324'!D28+'1. Summary 2324'!D40+'1. Summary 2324'!D41+'1. Summary 2324'!D42)/(+'1. Summary 2324'!D$67+'1. Summary 2324'!D$30) -> 0.20313524 | C15: =+('1. Summary 2324'!G$89 -'1. Summary 2324'!F$86) -> -48772847 | D15: =(+B15*C$10) -> -9907483.8
A16: 835 | B16: =+(+'1. Summary 2324'!D29+'1. Summary 2324'!D38)/(+'1. Summary 2324'!D$67+'1. Summary 2324'!D$30) -> 0.54554752 | C16: =+('1. Summary 2324'!G$89 -'1. Summary 2324'!F$86) -> -48772847 | D16: =(+B16*C$10) -> -26607906
B17: =SUM(B10:B16) -> 1 | D17: =SUM(D10:D16) -> -48772847 | E17: Governmental Non Current WC Liability as of 06/30/22
A20: Note: "% of Current Govn WC Expense" should total to 100%, if it does not, check the formulas in each row and make sure the correct expenditure codes are included. The "% of Current Govn WC Expense" column will need to be updated if there are funds added to each expenditure code. Check the 'Breakdown of Workers' Compensation by Exp Code' section on the Summary tab for new funds. Do not change the decimal places, amounts could be a vey small percentage of the overall total.
A25: *Total may not foot due to rounding.
I59: Workers'
C60: =+C55+C56+C57 -> 0 | I60: Comp
H61: WC Liability | I61: Discounted | J61: %
A62: * State of California's Self-Insured Employee Workers' Compensation Program (SCIF) | H62: Discounts | I62: Liability | J62: Discount
A63: Actuarial Review as of June 30, 2003
A64: PricewaterhouseCoopers in 1,000s | E64: = | G64: 3458981 | H64: =+G64-I64 -> 708325 | I64: 2750656 | J64: =+H64/G64 -> 0.20477852
A65: Basic Financial Statements and Supplementary Information | G65: 89131 | H65: =+G65-I65 -> 11777 | I65: 77354 | J65: =+H65/G65 -> 0.13213136
A66: Total unpaid claims and claims adjustment at June 30, 2003
B67: Total Estimated Outstanding Workers' Compensation Liability | G67: =+G64+G65 -> 3548112 | H67: =+G67-I67 -> 720102 | I67: =+I64+I65 -> 2828010 | J67: =+H67/G67 -> 0.20295357
B68: (amounts in 1,000's)
A70: SCIF Discounted Workers' Compensation Liability (@ 20.5%) | G70: 2750656
A71: CSUS Discounted WC Liability (9%) | G71: 77354
B73: Total Discounted Workers' Compensation Liability (20.2%) | G73: =+G70+G71 -> 2828010
D86: 1844000

Sheet 5. Gov Wide Entries Fund 9142
A1: Workers' Compensation Liability
A2: Gov Wide Entries for Fund 9142
A3: June 30, 2024
A5: GL Account | B5: Current Year Exp Codes* | C5: REF | D5: Prior Year Exp Codes* | F5: What the 9142 2022/23 balances should be
A6: 0655 | F6: =-'1. Summary 2324'!F17 -> -6293359.8
A7: 0678 | F7: =-F6 -> 6293359.8
A8: 0692 | F8: =-'4. Non Current Liab'!D17 -> 48772847 | G8: from tab 4
A9: 0808 | B9: ='4. Non Current Liab'!D10 -> -1283152.7 | C9: tab 4 | F9: =(B9-D9) -> -1283152.7
A10: 0810 | B10: ='4. Non Current Liab'!D11 -> -145220.41 | C10: tab 4 | F10: =(B10-D10) -> -145220.41
A11: 0815 | B11: ='4. Non Current Liab'!D12 -> -6459224.7 | C11: tab 4 | F11: =(B11-D11) -> -6459224.7
A12: 0820 | B12: ='4. Non Current Liab'!D13 -> -4196217.2 | C12: tab 4 | F12: =(B12-D12) -> -4196217.2
A13: 0825 | B13: ='4. Non Current Liab'!D14 -> -173642.47 | C13: tab 4 | F13: =(B13-D13) -> -173642.47
A14: 0830 | B14: ='4. Non Current Liab'!D15 -> -9907483.8 | C14: tab 4 | F14: =(B14-D14) -> -9907483.8
A15: 0835 | B15: ='4. Non Current Liab'!D16 -> -26607906 | C15: tab 4 | F15: =(B15-D15) -> -26607906
A16: 0950 | F16: =D18 -> 0
A17: 0952
B18: =SUM(B9:B16) -> -48772847 | D18: =SUM(D9:D17) -> 0 | F18: =SUM(F6:F17) -> -3.7252903e-09 | G18: Sum
A20: *Totals may not foot due to rounding.
E85: 1844000

Sheet 6. CSU Breakdown
B1: Self-Insurance Claims Liability | I1: For table reference please attachment "D"
B2: CSURMA (California State University Risk Management Authority)
C4: Balance | I4: Balance | K4: Less | M4: Noncurrent
C5: 45108 | E5: Addition | G5: Deduction | I5: 45473 | K5: Current Portions | M5: Portion
B6: University
B7: Workers' Compensation
B8: Other Self-Insurance Claims Liability
B10: Auxiliary
B11: Workers' Compensation
B12: Other Self-Insurance Claims Liability
B14: Total | C14: =SUM(C7:C12) -> 0 | E14: =SUM(E7:E12) -> 0 | G14: =SUM(G7:G12) -> 0 | I14: =SUM(I7:I12) -> 0 | K14: =SUM(K7:K12) -> 0 | M14: =SUM(M7:M12) -> 0
B16: New Workers' Comp above | C16: =C7+C11 -> 0 | E16: =E7+E11 -> 0 | F16: * | G16: =G7+G11 -> 0 | H16: * | I16: =I7+I11 -> 0 | K16: =K7+K11 -> 0 | M16: =M7+M11 -> 0
B18: * Not part of Table 40 in Note 17; provided for Note
I19: To tab 1 - Actuarial Review
B21: Lottery Additions/Deductions | D21: E | I21: to tab 1
B22: Additions and Deductions, Enterprise | E22: =E21+E16 -> 0 | G22: =G21+G16 -> 0

Sheet 7. Recon
A1: RECONCILIATION OF WORKERS' COMPENSATION FROM STATEMENTS & GOVERNMENT WIDE ADJUSTMENT TO GL FINAL BALANCE
B3: 2023/2024 | C3: Workers' Compensation Liability
I4: Acct 655 | K4: Acct 692 | M4: Total
I5: Current Liab | K5: Noncurrent Liab | M5: 6/30/2023 Bal
B6: Internal Service Funds: | C6: Agency | D6: Fund
B7: Service Revolving Fund | C7: 7760 | D7: 0666 | E7: (Agency prepared statement) | I7: ='1. Summary 2324'!D77 -> 0 | K7: ='1. Summary 2324'!F77 -> 28118000 | M7: =K7+I7 -> 28118000 | O7: See Summary tab, 'Current/Non-Current Workers' Comp Liability for Enterprise and Internal Service Funds' section
B8: Technology Services Revolving Fund | C8: 7502 | D8: 9730 | E8: (Agency prepared statement) | I8: ='1. Summary 2324'!D78 -> 0 | K8: ='1. Summary 2324'!F78 -> 136487 | M8: =K8+I8 -> 136487 | O8: See Summary tab, 'Current/Non-Current Workers' Comp Liability for Enterprise and Internal Service Funds' section
B9: Prison Industries Revolving Fund | C9: 5420 | D9: 0678 | E9: (Audited Statement) | I9: ='1. Summary 2324'!D79 -> 0 | K9: ='1. Summary 2324'!F79 -> 0 | M9: =K9+I9 -> 0 | O9: See Summary tab, 'Current/Non-Current Workers' Comp Liability for Enterprise and Internal Service Funds' section
B10: Architecture Revolving Fund | C10: 9865 | D10: 0602 | E10: (Audited Statement) | I10: ='1. Summary 2324'!D80 -> 0 | K10: ='1. Summary 2324'!F80 -> 290000 | M10: =K10+I10 -> 290000 | O10: See Summary tab, 'Current/Non-Current Workers' Comp Liability for Enterprise and Internal Service Funds' section
B11: Public Safety Comm. Revolving Fund | C11: 0690 | D11: 9751 | E11: (Agency prepared statement) | I11: ='1. Summary 2324'!D81 -> 0 | K11: ='1. Summary 2324'!F81 -> 1210000 | M11: =K11+I11 -> 1210000 | O11: See Summary tab, 'Current/Non-Current Workers' Comp Liability for Enterprise and Internal Service Funds' section
B12: Natural Gas Services Program Fund | C12: 7760 | D12: 9746 | E12: (Agency prepared statement) | I12: ='1. Summary 2324'!D82 -> 0 | K12: ='1. Summary 2324'!F82 -> 3000 | M12: =K12+I12 -> 3000 | O12: See Summary tab, 'Current/Non-Current Workers' Comp Liability for Enterprise and Internal Service Funds' section
B13: State Motor Vehicle Insurance Account | C13: 7760 | D13: 0026 | E13: (Agency prepared statement) | I13: ='1. Summary 2324'!D83 -> 0 | K13: ='1. Summary 2324'!F83 -> 7000 | M13: =K13+I13 -> 7000 | O13: See Summary tab, 'Current/Non-Current Workers' Comp Liability for Enterprise and Internal Service Funds' section
B15: Other Government Activities:
B16: Government Wide Adjustment | D16: 9142 | E16: (Summary) | I16: ='1. Summary 2324'!F10 -> 6293359.8 | K16: ='1. Summary 2324'!J73 -> -48772847 | M16: =K16+I16 -> -42479487 | O16: MUST Adjusted Liability Below (cell 82)
O17: =IF((ROUND(M16,-3)/1000)=ROUND(M82,0),"Matches","Does not match") -> Matches
C19: Fund Class 1 Total - Governmental Activities | I19: =SUM(I7:I18) -> 6293359.8 | K19: =SUM(K7:K18) -> -19008360 | M19: =SUM(M7:M18) -> -12715000
B21: Enterprise Funds:
B22: State Lottery Fund | C22: 0850 | D22: 0562 | E22: (Audited Statement) | I22: ='1. Summary 2324'!D72 -> 0 | K22: ='1. Summary 2324'!F72 -> 8337000 | M22: =K22+I22 -> 8337000 | O22: Include in note under table, if not included in Note 9
B23: Inmate Welfare Fund | C23: 5225 | D23: 0917 | E23: (Agency prepared statement) | I23: ='1. Summary 2324'!D73 -> 0 | K23: ='1. Summary 2324'!F73 -> 4378000 | M23: =K23+I23 -> 4378000
C24: Fund Class 2 Total - Enterprise Activities | I24: =SUM(I22:I23) -> 0 | K24: =SUM(K22:K23) -> 12715000 | M24: =SUM(M22:M23) -> 12715000
B26: TOTAL PRIMARY GOVERNMENT WORKERS' COMPENSATION | I26: =I19+I24 -> 6293359.8 | K26: =K19+K24 -> -6293359.8 | M26: =M19+M24 -> 0 | O26: Should match Total Workers' Comp Liability From All State Programs
B27: Discretely Presented Component: | O27: =IF((ROUND(M26,-3)/1000)=ROUND(M68,0),"Matches","Does not match") -> Matches
B29: CA Housing Finance Fund (CPA) | D29: 0501 | M29: =I29+K29 -> 0
B30: CA School Finance Authority (CPA) | D30: 0526 | M30: =I30+K30 -> 0
B31: CA Expo & State Fair (CPA) | D31: 0510 | M31: =I31+K31 -> 0
B32: State Compensation Insurance Fund (CPA) | D32: 0512 | M32: =I32+K32 -> 0
B33: CA Alternative Energy Source Finance Authority | D33: 0528 | M33: =I33+K33 -> 0
B34: Calif Infrastructure & Economic Development Bank (CPA) | D34: 0649 &9328) | M34: =I34+K34 -> 0
B35: Federal Student Loan Reserve Fund | D35: 0783 | M35: =I35+K35 -> 0
B36: Student Loan Operating Fund | D36: 0784 | M36: =I36+K36 -> 0
B37: EDFUND (CPA 9/30/xx year-end)) | D37: 9940 | M37: =I37+K37 -> 0
B38: Del Mar Race Track Authority (CPA) | D38: 0795 | M38: =I38+K38 -> 0
B39: CA Health Facilities Finance Authority - no audit; look into loans | D39: 0904 | M39: =I39+K39 -> 0
B40: Education Facilities Authority Fund (CPA) - INPUT WITH 0954 | D40: 0911 | M40: =I40+K40 -> 0
B41: Student Loan Authority Fund(CPA) - INPUT WITH 0911 | D41: 0954 | M41: =I41+K41 -> 0
B42: CA Pollution Control Finance Authority | D42: 0930 | M42: =I42+K42 -> 0
B43: CA Urban Waterfront Area Restoration Fund | D43: 0982 | M43: =I43+K43 -> 0
B44: Race Track Leasing Commission (CPA) | D44: 0989 | M44: =I44+K44 -> 0
B45: California Health Trust Fund | D45: 3175 | M45: =I45+K45 -> 0
B46: SAFE-BIDCO | D46: 9935 | M46: =I46+K46 -> 0
B47: District Agriculture Association | D47: 9990 | M47: =I47+K47 -> 0
B48: CSU Auxiliary Organizations (From CSU Audit) | D48: 9970 | M48: =I48+K48 -> 0 | O48: GAAP System | P48: workbook
B49: UC Hastings School of Law (CPA) | D49: 9950 | M49: =I49+K49 -> 0
B50: University of CA (CPA) | C50: 6440 | D50: 0999 | M50: =I50+K50 -> 0 | O50: GAAP System | P50: workbook
C53: Fund Class 3 Total - Discretely Presented Component | M53: =SUM(M28:M52) -> 0
B55: TOTAL GOVERNMENT WIDE | M55: =SUM(M26+M53) -> 0 | O55: Should match Government Wide Ledger for Workers' Comp
A60: CALCULATION OF PRIMARY GOVERNMENT ADJUSTMENT:
B62: 2023/2024 | C62: State of California's Total Self-Insured Employee Workers' Compensation Programs, Discounted for Present Value:
C64: State of Ca Discounted Workers' Compensation Liability (SCIF Workers Compensation Program) from Actuarial Review | M64: ='1. Summary 2324'!J109 -> 0 | O64: actuarial report
C65: CSU WC Liability (CSURMA Workers' Compensation Program) from audited statements | M65: 0
D67: Total Workers' Compensation Liability From All State Programs
M68: =SUM(M64:M67) -> 0
B70: 2023/2024 | C70: Reduction from Totals for Audit Statement Entries Already Posted
C71: =B7 -> Service Revolving Fund | M71: =-M7/1000 -> -28118
C72: =B8 -> Technology Services Revolving Fund | M72: =-M8/1000 -> -136.487
C73: =B9 -> Prison Industries Revolving Fund | M73: =-M9/1000 -> 0
C74: =B10 -> Architecture Revolving Fund | M74: =-M10/1000 -> -290
C75: =B11 -> Public Safety Comm. Revolving Fund | M75: =-M11/1000 -> -1210
C76: =B12 -> Natural Gas Services Program Fund | M76: =-M12/1000 -> -3
C77: =B13 -> State Motor Vehicle Insurance Account | M77: =-M13/1000 -> -7
C79: =B22 -> State Lottery Fund | M79: =-M22/1000 -> -8337
C80: =B23 -> Inmate Welfare Fund | M80: =-M23/1000 -> -4378
D82: Adjustment to State Workers' Comp Liability for Primary Government | M82: =SUM(M68:M81) -> -42479.487
M86: Total
B87: NEED TO ADD ALL "OTHER SELF-INSURANCE" INFORMATION TO TASK FOR 2011/2012. Table 46 for Note 20 not to include other self-insurance per BSA unless risk increases | D87: 1844000
I88: Current Liab | K88: Noncurrent Liab | M88: =M5 -> 6/30/2023 Bal
B89: Other Self-Insurance Liabilities
B91: Primary Government | M91: =I91+K91 -> 0
B93: Discretely Presented ComponentS:
B95: CA Housing Finance Fund (CPA) | D95: 0501 | M95: =I95+K95 -> 0
B96: CA School Finance Authority (CPA) | D96: 0526 | M96: =I96+K96 -> 0
B97: CA Expo & State Fair (CPA) | D97: 0510 | M97: =I97+K97 -> 0
B98: State Compensation Insurance Fund (CPA) | D98: 0512 | M98: =I98+K98 -> 0
B99: CA Alternative Energy Source Finance Authority | D99: 0528 | M99: =I99+K99 -> 0
B100: Calif Infrastructure & Economic Development Bank (CPA) | D100: 0649 &9328) | M100: =I100+K100 -> 0
B101: Federal Student Loan Reserve Fund | D101: 0783 | M101: =I101+K101 -> 0
B102: Student Loan Operating Fund | D102: 0784 | M102: =I102+K102 -> 0
B103: EDFUND (CPA 9/30/xx year-end)) | D103: 9940 | M103: =I103+K103 -> 0
B104: Del Mar Race Track Authority (CPA) | D104: 0795 | M104: =I104+K104 -> 0
B105: CA Health Facilities Finance Authority - no audit; look into loans | D105: 0904 | M105: =I105+K105 -> 0
B106: Education Facilities Authority Fund (CPA) - INPUT WITH 0954 | D106: 0911 | M106: =I106+K106 -> 0
B107: Student Loan Authority Fund(CPA) - INPUT WITH 0911 | D107: 0954 | M107: =I107+K107 -> 0
B108: CA Pollution Control Finance Authority | D108: 0930 | M108: =I108+K108 -> 0
B109: CA Urban Waterfront Area Restoration Fund | D109: 0982 | M109: =I109+K109 -> 0
B110: Race Track Leasing Commission (CPA) | D110: 0989 | M110: =I110+K110 -> 0
B111: California Health Trust Fund | D111: 3175 | M111: =I111+K111 -> 0
B112: SAFE-BIDCO | D112: 9935 | M112: =I112+K112 -> 0
B113: District Agriculture Association | D113: 9990 | M113: =I113+K113 -> 0
B114: CSU Auxilliary Organizations (From CSU Audit) | D114: 9970 | M114: =I114+K114 -> 0
B115: UC Hastings School of Law (CPA) | D115: 9950 | M115: =I115+K115 -> 0
B116: University of CA (CPA) | C116: 6440 | D116: 0999 | M116: =I116+K116 -> 0
E120: Gov. Activities | G120: Enterprise | I120: Total Primary Gov.
C121: Beginning | E121: ='1. Summary 2324'!K19 -> -14535 | G121: ='1. Summary 2324'!L19 -> 14535 | I121: ='1. Summary 2324'!N19 -> 0
C122: Addition | E122: ='1. Summary 2324'!K20 -> 688411.03 | G122: ='1. Summary 2324'!L20 -> 0 | I122: ='1. Summary 2324'!N20 -> 688411.03
C123: Deduction | E123: ='1. Summary 2324'!K21 -> -686591.03 | G123: ='1. Summary 2324'!L21 -> -1820 | I123: ='1. Summary 2324'!N21 -> -688411.03
C124: Total | E124: ='1. Summary 2324'!K22 -> -12715 | G124: ='1. Summary 2324'!L22 -> 12715 | I124: ='1. Summary 2324'!N22 -> 0
C125: Current | E125: ='1. Summary 2324'!K23 -> 6293 | G125: ='1. Summary 2324'!L23 -> 0 | I125: ='1. Summary 2324'!N23 -> 6293
C126: NonCurrent | E126: ='1. Summary 2324'!K24 -> -19008 | G126: ='1. Summary 2324'!L24 -> 12715 | I126: ='1. Summary 2324'!N24 -> -6293 | O126: rounding included as needed
A130: NOTE 17: RISK MANAGEMENT
B132: TABLE 40
...

Sheet 8. K0717_2024_Jun 
A1: Column1
A2: K0717 MONTHLY SUMMARY REPORTS OF STATE AGENCY BILLING 06/30/2024 PAGE 1
A3: CHAPTER AGENCY TOTAL TOTAL TOTAL TOTAL TOTAL TOTAL TOTAL TOTAL BILL
A4: CODE CODE TD PAID PD PAID VR PAID SJDB PAID MED PAID PEN PAID MISC. PAID NET BENEFIT TOTAL
A5: 03 001 0.00 0.00 0.00 0.00 3,967.17 0.00 0.00 3,967.17 3,967.17
A6: 002 7,362.60 40,049.00 0.00 0.00 167,251.75 0.00 6,651.66 214,663.35 221,315.01
A7: 004 13,719.87 72,871.16 0.00 0.00 264,354.41 0.00 10,498.88 350,945.44 361,444.32
A8: 008 0.00 0.00 0.00 0.00 5.63- 0.00 0.00 5.63- 5.63-
A9: 009 0.00 0.00 0.00 0.00 606.02 0.00 0.00 606.02 606.02
A10: 016 0.00 0.00 0.00 0.00 21,893.28 0.00 1,398.20 21,893.28 23,291.48
A11: 037 0.00 0.00 0.00 0.00 10,636.48 0.00 0.00 10,636.48 10,636.48
A12: 040 0.00 3,480.00 0.00 0.00 35,646.07 0.00 404.10 39,126.07 39,530.17
... A330: 817 42,452.01 134,656.58 0.00 0.00 43,019.40 0.00 0.00 220,127.99 220,127.99
A331: TOTALS 87239135.37 230953301.68 17653.25 1552661.68 359675755.62 24117.93 7128404.66 679438507.60 686591030.19 | B331: 6.8659103e+08
B332: 6.8659103e+08

Sheet 9. Proprietary Funds
I2: Total Amount less Fund 0948000
I3: =SUM(Table_CY_GAAP[Amount])-SUMIFS(Table_CY_GAAP[[#All],[Amount]],Table_CY_GAAP[[#All],[Fund]],"0948000") -> -42479487
A4: Fund | B4: t2 | C4: T3 | D4: T4 | E4: Title | F4: GenCode | G4: GLAccount | H4: Fund&Glccount | I4: Amount | J4: FundName | K4: FundClass | L4: Hier1 | M4: MajorMinor | N4: Hier2 | O4: Color
A5: 0562000 | B5: LIABILITIES & DEFERRED INFLOW | C5: LIABILITIES | D5: LIABILITY-NON-CUR | E5: WORKERS COMPENSATION BENEFITS PAYABLE | F5: GBBI | G5: 06920000000 | H5: =Table_CY_GAAP[[#This Row],[Fund]]&Table_CY_GAAP[[#This Row],[GLAccount]] -> 056200006920000000 | I5: -8337000 | J5: STATE LOTTERY FUND | K5: 002 | L5: 400 | M5: 001 | N5: 600
A6: 0948000 | B6: LIABILITIES & DEFERRED INFLOW | C6: LIABILITIES | D6: LIABILITY-NON-CUR | E6: WORKERS COMPENSATION BENEFITS PAYABLE | F6: GBBI | G6: 06920000000 | H6: =Table_CY_GAAP[[#This Row],[Fund]]&Table_CY_GAAP[[#This Row],[GLAccount]] -> 094800006920000000 | I6: -67944000 | J6: CAL ST UNIV & COLL TRUST F | K6: 002 | L6: 400 | M6: 001 | N6: 700
A7: 0917000 | B7: LIABILITIES & DEFERRED INFLOW | C7: LIABILITIES | D7: LIABILITY-NON-CUR | E7: WORKERS COMPENSATION BENEFITS PAYABLE | F7: GBBI | G7: 06920000000 | H7: =Table_CY_GAAP[[#This Row],[Fund]]&Table_CY_GAAP[[#This Row],[GLAccount]] -> 091700006920000000 | I7: -4378000 | J7: INMATES' WELFARE FUND | K7: 002 | L7: 400 | M7: 002 | N7: 900
A8: 0666000 | B8: LIABILITIES & DEFERRED INFLOW | C8: LIABILITIES | D8: LIABILITY-NON-CUR | E8: WORKERS COMPENSATION BENEFITS PAYABLE | F8: GBBI | G8: 06920000000 | H8: =Table_CY_GAAP[[#This Row],[Fund]]&Table_CY_GAAP[[#This Row],[GLAccount]] -> 066600006920000000 | I8: -28118000 | J8: SERVICE REVOLVING FUND | K8: 001 | L8: 500 | M8: 002 | N8: 100
A9: 0602000 | B9: LIABILITIES & DEFERRED INFLOW | C9: LIABILITIES | D9: LIABILITY-NON-CUR | E9: WORKERS COMPENSATION BENEFITS PAYABLE | F9: GBBI | G9: 06920000000 | H9: =Table_CY_GAAP[[#This Row],[Fund]]&Table_CY_GAAP[[#This Row],[GLAccount]] -> 060200006920000000 | I9: -290000 | J9: ARCHITECTURE REVOLVING FUN | K9: 001 | L9: 500 | M9: 002 | N9: 500
A10: 9730000 | B10: LIABILITIES & DEFERRED INFLOW | C10: LIABILITIES | D10: LIABILITY-NON-CUR | E10: WORKERS COMPENSATION BENEFITS PAYABLE | F10: GBBI | G10: 06920000000 | H10: =Table_CY_GAAP[[#This Row],[Fund]]&Table_CY_GAAP[[#This Row],[GLAccount]] -> 973000006920000000 | I10: -136487 | J10: TECHNOLOGY SERVICES REVOLV | K10: 001 | L10: 500 | M10: 002 | N10: 600
A11: 0026000 | B11: LIABILITIES & DEFERRED INFLOW | C11: LIABILITIES | D11: LIABILITY-NON-CUR | E11: WORKERS COMPENSATION BENEFITS PAYABLE | F11: GBBI | G11: 06920000000 | H11: =Table_CY_GAAP[[#This Row],[Fund]]&Table_CY_GAAP[[#This Row],[GLAccount]] -> 002600006920000000 | I11: -7000 | J11: MOTOR VEHICLE INSURANCE AC | K11: 001 | L11: 500 | M11: 002 | N11: 900
A12: 9746000 | B12: LIABILITIES & DEFERRED INFLOW | C12: LIABILITIES | D12: LIABILITY-NON-CUR | E12: WORKERS COMPENSATION BENEFITS PAYABLE | F12: GBBI | G12: 06920000000 | H12: =Table_CY_GAAP[[#This Row],[Fund]]&Table_CY_GAAP[[#This Row],[GLAccount]] -> 974600006920000000 | I12: -3000 | J12: NATURAL GAS SERVICES PROG | K12: 001 | L12: 500 | M12: 002 | N12: 900
A13: 9751000 | B13: LIABILITIES & DEFERRED INFLOW | C13: LIABILITIES | D13: LIABILITY-NON-CUR | E13: WORKERS COMPENSATION BENEFITS PAYABLE | F13: GBBI | G13: 06920000000 | H13: =Table_CY_GAAP[[#This Row],[Fund]]&Table_CY_GAAP[[#This Row],[GLAccount]] -> 975100006920000000 | I13: -1210000 | J13: PUB SAFETY COMM REVOLVING | K13: 001 | L13: 500 | M13: 002 | N13: 900

Sheet TC 35
B1: STATE CONTROLLER'S USE ONLY | BM1: STATE CONTROLLER'S USE ONLY
B2: DOCUMENT NO. | L2: DATE | T2: MSG Code | V2: STATE OF CALIFORNIA | BM2: TC Code | BO2: PREPARED BY: | BS2: NCACCAM
V3: OFFICE OF THE STATE CONTROLLER
B4: S | BM4: 35
B5: STATE CONTROLLER'S USE ONLY | BF5: 1 | BH5: of | BI5: 11
BR7: DC | BS7: A | BT7: SCO USE | BW7: SOURCE
C8: FUND | J8: AGY | N8: FY | R8: M | S8: REF/ITEM | Y8: RED CAT | AD8: P/N | AF8: C | AG8: CAT | AI8: PGM | AK8: ELE | AM8: COMP | AP8: TASK | AS8: ACCT | AW8: SCO | AX8: REV/OBJ | BD8: AMOUNT | BT8: T | BU8: O | BV8: B | BW8: FUND
C9: 0001 | AS9: 0808 | BD9: ='1. Summary 2324'!G21 -> 122145.44 | BR9: D | BS9: G
B10: DESCRIPTION
B11: CURRENT WORKERS COMP AMT
C12: 0001 | AS12: 0810 | BD12: ='1. Summary 2324'!G22 -> 10202.535 | BR12: D | BS12: G
B13: DESCRIPTION
B14: CURRENT WORKERS COMP AMT
C15: 0001 | AS15: 0815 | BD15: ='1. Summary 2324'!G24 -> 603157.16 | BR15: D | BS15: G
B16: DESCRIPTION
B17: CURRENT WORKERS COMP AMT
C18: 0001 | AS18: 0820 | BD18: ='1. Summary 2324'!G26 -> 465705.82 | BR18: D | BS18: G
B19: DESCRIPTION
B20: CURRENT WORKERS COMP AMT
C21: 0001 | AS21: 0825 | BD21: ='1. Summary 2324'!G27 -> 1147.1634 | BR21: D | BS21: G
B22: DESCRIPTION
B23: CURRENT WORKERS COMP AMT
C24: 0001 | AS24: 0835 | BD24: ='1. Summary 2324'!G29 -> 3432683.1 | BR24: D | BS24: G
B25: DESCRIPTION
B26: CURRENT WORKERS COMP AMT
C27: 0001 | AS27: 0810 | BD27: 0 | BR27: D | BS27: G
B29: CURRENT WORKERS COMP AMT
C30: 0001 | AS30: 0678 | BD30: ='1. Summary 2324'!G30-'1. Summary 2324'!G25-'1. Summary 2324'!G23+0.02 -> 4635041.2 | BR30: C | BS30: G
B31: DESCRIPTION
B32: CURRENT WORKERS COMP AMT
B34: DESCRIPTION
B36: CA503 PC VERSION (7/99)

Sheet TC 35 (1)
B1: STATE CONTROLLER'S USE ONLY | BM1: STATE CONTROLLER'S USE ONLY
B2: DOCUMENT NO. | L2: DATE | T2: MSG Code | V2: STATE OF CALIFORNIA | BM2: TC Code | BO2: PREPARED BY: | BS2: ='TC 35'!BS2:CC3 -> NCACCAM
V3: OFFICE OF THE STATE CONTROLLER
B4: S | BM4: 35
B5: STATE CONTROLLER'S USE ONLY | BF5: 2 | BH5: of | BI5: 11
BR7: DC | BS7: A | BT7: SCO USE | BW7: SOURCE
C8: FUND | J8: AGY | N8: FY | R8: M | S8: REF/ITEM | Y8: RED CAT | AD8: P/N | AF8: C | AG8: CAT | AI8: PGM | AK8: ELE | AM8: COMP | AP8: TASK | AS8: ACCT | AW8: SCO | AX8: REV/OBJ | BD8: AMOUNT | BT8: T | BU8: O | BV8: B | BW8: FUND
C9: 1031 | AS9: 0810 | BD9: ='1. Summary 2324'!D23 -> 0 | BR9: D | BS9: G
B10: DESCRIPTION
B11: CURRENT WORKERS COMP AMT
C12: 1031 | AS12: 0678 | BD12: =BD9 -> 0 | BR12: C | BS12: G
B13: DESCRIPTION
B14: CURRENT WORKERS COMP AMT
B16: DESCRIPTION
B19: DESCRIPTION
B22: DESCRIPTION
B25: DESCRIPTION
B31: DESCRIPTION
B34: DESCRIPTION
B36: CA503 PC VERSION (7/99)

Sheet TC 35 (2)
B1: STATE CONTROLLER'S USE ONLY | BM1: STATE CONTROLLER'S USE ONLY
B2: DOCUMENT NO. | L2: DATE | T2: MSG Code | V2: STATE OF CALIFORNIA | BM2: TC Code | BO2: PREPARED BY: | BS2: ='TC 35'!BS2:CC3 -> NCACCAM
V3: OFFICE OF THE STATE CONTROLLER
B4: S | BM4: 35
B5: STATE CONTROLLER'S USE ONLY | BF5: 3 | BH5: of | BI5: 10
BR7: DC | BS7: A | BT7: SCO USE | BW7: SOURCE
C8: FUND | J8: AGY | N8: FY | R8: M | S8: REF/ITEM | Y8: RED CAT | AD8: P/N | AF8: C | AG8: CAT | AI8: PGM | AK8: ELE | AM8: COMP | AP8: TASK | AS8: ACCT | AW8: SCO | AX8: REV/OBJ | BD8: AMOUNT | BT8: T | BU8: O | BV8: B | BW8: FUND
C9: 0870 | AS9: 0815 | BD9: ='1. Summary 2324'!G25 -> 115957.23 | BR9: D | BS9: G
B10: DESCRIPTION
B11: CURRENT WORKERS COMP AMT
C12: 0870 | AS12: 0678 | BD12: =BD9 -> 115957.23 | BR12: C | BS12: G
B13: DESCRIPTION
B14: CURRENT WORKERS COMP AMT
B16: DESCRIPTION
B19: DESCRIPTION
B22: DESCRIPTION
B25: DESCRIPTION
B31: DESCRIPTION
B34: DESCRIPTION
B36: CA503 PC VERSION (7/99)

Sheet TC 35 (3)
A1: 14823.52 | B1: STATE CONTROLLER'S USE ONLY | BM1: STATE CONTROLLER'S USE ONLY
B2: DOCUMENT NO. | L2: DATE | T2: MSG Code | V2: STATE OF CALIFORNIA | BM2: TC Code | BO2: PREPARED BY: | BS2: NCACCAM
V3: OFFICE OF THE STATE CONTROLLER
B4: S | BM4: 35
B5: STATE CONTROLLER'S USE ONLY | BF5: 4 | BH5: of | BI5: 10
BR7: DC | BS7: A | BT7: SCO USE | BW7: SOURCE
C8: FUND | J8: AGY | N8: FY | R8: M | S8: REF/ITEM | Y8: RED CAT | AD8: P/N | AF8: C | AG8: CAT | AI8: PGM | AK8: ELE | AM8: COMP | AP8: TASK | AS8: ACCT | AW8: SCO | AX8: REV/OBJ | BD8: AMOUNT | BT8: T | BU8: O | BV8: B | BW8: FUND
C9: 0890 | AS9: 0808 | BD9: ='1. Summary 2324'!G33 -> 19752.146 | BR9: D | BS9: G
B10: DESCRIPTION
B11: CURRENT WORKERS COMP AMT
C12: 0890 | AS12: 0678 | BD12: =BD9 -> 19752.146 | BR12: C | BS12: G
B13: DESCRIPTION
B14: CURRENT WORKERS COMP AMT
C15: 0890 | AS15: 0810 | BD15: ='1. Summary 2324'!G34 -> 8535.8487 | BR15: D | BS15: G
B16: DESCRIPTION
B17: CURRENT WORKERS COMP AMT
C18: 0890 | AS18: 0678 | BD18: =BD15 -> 8535.8487 | BR18: C | BS18: G
B19: DESCRIPTION
B20: CURRENT WORKERS COMP AMT
C21: 0890 | AS21: 0815 | BD21: ='1. Summary 2324'!G35 -> 55405.76 | BR21: D | BS21: G
B22: DESCRIPTION
B23: CURRENT WORKERS COMP AMT
C24: 0890 | AS24: 0678 | BD24: =BD21 -> 55405.76 | BR24: C | BS24: G
B25: DESCRIPTION
B26: CURRENT WORKERS COMP AMT
C27: 0890 | AS27: 0820 | BD27: ='1. Summary 2324'!G36 -> 4930.8711 | BR27: D | BS27: G
B28: DESCRIPTION
B29: CURRENT WORKERS COMP AMT
C30: 0890 | AS30: 0678 | BD30: =BD27 -> 4930.8711 | BR30: C | BS30: G
B31: DESCRIPTION
B32: CURRENT WORKERS COMP AMT
C33: 0890 | AS33: 0825 | BD33: ='1. Summary 2324'!G37 -> 116.51072 | BR33: D | BS33: G
B34: DESCRIPTION
B35: CURRENT WORKERS COMP AMT
B36: CA503 PC VERSION (7/99)

Sheet TC 35 (4)
B1: STATE CONTROLLER'S USE ONLY | BM1: STATE CONTROLLER'S USE ONLY
B2: DOCUMENT NO. | L2: DATE | T2: MSG Code | V2: STATE OF CALIFORNIA | BM2: TC Code | BO2: PREPARED BY: | BS2: NCACCAM
V3: OFFICE OF THE STATE CONTROLLER
B4: S | BM4: 35
B5: STATE CONTROLLER'S USE ONLY | BF5: 5 | BH5: of | BI5: 10
BR7: DC | BS7: A | BT7: SCO USE | BW7: SOURCE
C8: FUND | J8: AGY | N8: FY | R8: M | S8: REF/ITEM | Y8: RED CAT | AD8: P/N | AF8: C | AG8: CAT | AI8: PGM | AK8: ELE | AM8: COMP | AP8: TASK | AS8: ACCT | AW8: SCO | AX8: REV/OBJ | BD8: AMOUNT | BT8: T | BU8: O | BV8: B | BW8: FUND
C9: 0890 | AS9: 0678 | BD9: ='TC 35 (3)'!BD33:BQ33 -> 116.51072 | BR9: C | BS9: G
B10: DESCRIPTION
B11: CURRENT WORKERS COMP AMT
C12: 0890 | AS12: 0835 | BD12: ='1. Summary 2324'!G38 -> 643.76922 | BR12: D | BS12: G
B13: DESCRIPTION
B14: CURRENT WORKERS COMP AMT
C15: 0890 | AS15: 0678 | BD15: =BD12 -> 643.76922 | BR15: C | BS15: G
B16: DESCRIPTION
B17: CURRENT WORKERS COMP AMT
C18: 0044 | AS18: 0820 | BD18: ='1. Summary 2324'!G39 -> 5156.6493 | BR18: D | BS18: G
B19: DESCRIPTION
B20: CURRENT WORKERS COMP AMT
C21: 0044 | AS21: 0678 | BD21: =BD18 -> 5156.6493 | BR21: C | BS21: G
B22: DESCRIPTION
B23: CURRENT WORKERS COMP AMT
C24: 0042 | AS24: 0830 | BD24: ='1. Summary 2324'!G40 -> 324916.76 | BR24: D | BS24: G
B25: DESCRIPTION
B26: CURRENT WORKERS COMP AMT
C27: 0042 | AS27: 0678 | BD27: =BD24 -> 324916.76 | BR27: C | BS27: G
B28: DESCRIPTION
B29: CURRENT WORKERS COMP AMT
C30: 0044 | AS30: 0830 | BD30: ='1. Summary 2324'!G41 -> 795989.62 | BR30: D | BS30: G
B31: DESCRIPTION
B32: CURRENT WORKERS COMP AMT
C33: 0044 | AS33: 0678 | BD33: =BD30 -> 795989.62 | BR33: C | BS33: G
B34: DESCRIPTION
B35: CURRENT WORKERS COMP AMT
B36: CA503 PC VERSION (7/99)

Sheet TC 35 (5)
B1: STATE CONTROLLER'S USE ONLY | BM1: STATE CONTROLLER'S USE ONLY
B2: DOCUMENT NO. | L2: DATE | T2: MSG Code | V2: STATE OF CALIFORNIA | BM2: TC Code | BO2: PREPARED BY: | BS2: NCACCAM
V3: OFFICE OF THE STATE CONTROLLER
B4: S | BM4: 35
B5: STATE CONTROLLER'S USE ONLY | BF5: 6 | BH5: of | BI5: 10
BR7: DC | BS7: A | BT7: SCO USE | BW7: SOURCE
C8: FUND | J8: AGY | N8: FY | R8: M | S8: REF/ITEM | Y8: RED CAT | AD8: P/N | AF8: C | AG8: CAT | AI8: PGM | AK8: ELE | AM8: COMP | AP8: TASK | AS8: ACCT | AW8: SCO | AX8: REV/OBJ | BD8: AMOUNT | BT8: T | BU8: O | BV8: B | BW8: FUND
B10: DESCRIPTION
B13: DESCRIPTION
C15: 0111 | AS15: 0808 | BD15: ='1. Summary 2324'!G43 -> 10445.355 | BR15: D | BS15: G
B16: DESCRIPTION
B17: CURRENT WORKERS COMP AMT
C18: 0111 | AS18: 0678 | BD18: =BD15 -> 10445.355 | BR18: C | BS18: G
B19: DESCRIPTION
B20: CURRENT WORKERS COMP AMT
C21: 0217 | AS21: 0808 | BD21: ='1. Summary 2324'!G44 -> 10723.658 | BR21: D | BS21: G
B22: DESCRIPTION
B23: CURRENT WORKERS COMP AMT
C24: 0217 | AS24: 0678 | BD24: =BD21 -> 10723.658 | BR24: C | BS24: G
B25: DESCRIPTION
B26: CURRENT WORKERS COMP AMT
C27: 0567 | AS27: 0808 | BD27: ='1. Summary 2324'!G45 -> 0 | BR27: D | BS27: G
B28: DESCRIPTION
B29: CURRENT WORKERS COMP AMT
C30: 0567 | AS30: 0678 | BD30: =BD27 -> 0 | BR30: C | BS30: G
B31: DESCRIPTION
B32: CURRENT WORKERS COMP AMT
C33: 0462 | AS33: 0808 | BD33: ='1. Summary 2324'!G46 -> 2503.8384 | BR33: D | BS33: G
B34: DESCRIPTION
B35: CURRENT WORKERS COMP AMT
B36: CA503 PC VERSION (7/99)

Sheet TC 35 (6)
B1: STATE CONTROLLER'S USE ONLY | BM1: STATE CONTROLLER'S USE ONLY
B2: DOCUMENT NO. | L2: DATE | T2: MSG Code | V2: STATE OF CALIFORNIA | BM2: TC Code | BO2: PREPARED BY: | BS2: NCACCAM
V3: OFFICE OF THE STATE CONTROLLER
B4: S | BM4: 35
B5: STATE CONTROLLER'S USE ONLY | BF5: 7 | BH5: of | BI5: 10
BR7: DC | BS7: A | BT7: SCO USE | BW7: SOURCE
C8: FUND | J8: AGY | N8: FY | R8: M | S8: REF/ITEM | Y8: RED CAT | AD8: P/N | AF8: C | AG8: CAT | AI8: PGM | AK8: ELE | AM8: COMP | AP8: TASK | AS8: ACCT | AW8: SCO | AX8: REV/OBJ | BD8: AMOUNT | BT8: T | BU8: O | BV8: B | BW8: FUND
C9: 0462 | AS9: 0678 | BD9: ='TC 35 (5)'!BD33:BQ33 -> 2503.8384 | BR9: C | BS9: G
B10: DESCRIPTION
B11: CURRENT WORKERS COMP AMT
C12: 0407 | AS12: 0810 | BD12: ='1. Summary 2324'!G47 -> 0 | BR12: D | BS12: G
B13: DESCRIPTION
B14: CURRENT WORKERS COMP AMT
C15: =C12 -> 0407 | AS15: 0678 | BD15: =BD12 -> 0 | BR15: C | BS15: G
B16: DESCRIPTION
B17: CURRENT WORKERS COMP AMT
C18: 0933 | AS18: 0815 | BD18: ='1. Summary 2324'!G48 -> 405.25443 | BR18: D | BS18: G
B19: DESCRIPTION
B20: CURRENT WORKERS COMP AMT
C21: =C18 -> 0933 | AS21: 0678 | BD21: =BD18 -> 405.25443 | BR21: C | BS21: G
B22: DESCRIPTION
B23: CURRENT WORKERS COMP AMT
C24: 0067 | AS24: 0825 | BD24: ='1. Summary 2324'!G49 -> 2519.7332 | BR24: D | BS24: G
B25: DESCRIPTION
B26: CURRENT WORKERS COMP AMT
C27: =C24 -> 0067 | AS27: 0678 | BD27: =BD24 -> 2519.7332 | BR27: C | BS27: G
B28: DESCRIPTION
B29: CURRENT WORKERS COMP AMT
C30: 0317 | AS30: 0825 | BD30: ='1. Summary 2324'!G50 -> 484.99205 | BR30: D | BS30: G
B31: DESCRIPTION
B32: CURRENT WORKERS COMP AMT
C33: =C30 -> 0317 | AS33: 0678 | BD33: =BD30 -> 484.99205 | BR33: C | BS33: G
B34: DESCRIPTION
B35: CURRENT WORKERS COMP AMT
B36: CA503 PC VERSION (7/99)

Sheet TC 35 (7)
B1: STATE CONTROLLER'S USE ONLY | BM1: STATE CONTROLLER'S USE ONLY
B2: DOCUMENT NO. | L2: DATE | T2: MSG Code | V2: STATE OF CALIFORNIA | BM2: TC Code | BO2: PREPARED BY: | BS2: NCACCAM
V3: OFFICE OF THE STATE CONTROLLER
B4: S | BM4: 35
B5: STATE CONTROLLER'S USE ONLY | BF5: 8 | BH5: of | BI5: 10
BR7: DC | BS7: A | BT7: SCO USE | BW7: SOURCE
C8: FUND | J8: AGY | N8: FY | R8: M | S8: REF/ITEM | Y8: RED CAT | AD8: P/N | AF8: C | AG8: CAT | AI8: PGM | AK8: ELE | AM8: COMP | AP8: TASK | AS8: ACCT | AW8: SCO | AX8: REV/OBJ | BD8: AMOUNT | BT8: T | BU8: O | BV8: B | BW8: FUND
C9: 3153 | AS9: 0825 | BD9: ='1. Summary 2324'!G51 -> 80.941962 | BR9: D | BS9: G
B10: DESCRIPTION
B11: CURRENT WORKERS COMP AMT
C12: =C9 -> 3153 | AS12: 0678 | BD12: =BD9 -> 80.941962 | BR12: C | BS12: G
B13: DESCRIPTION
B14: CURRENT WORKERS COMP AMT
C15: 0702 | AS15: 0825 | BD15: ='1. Summary 2324'!G52 -> 12644.035 | BR15: D | BS15: G
B16: DESCRIPTION
B17: CURRENT WORKERS COMP AMT
C18: =C15 -> 0702 | AS18: 0678 | BD18: =BD15 -> 12644.035 | BR18: C | BS18: G
B19: DESCRIPTION
B20: CURRENT WORKERS COMP AMT
C21: 3036 | AS21: 0825 | BD21: ='1. Summary 2324'!G53 -> 4116.8069 | BR21: D | BS21: G
B22: DESCRIPTION
B23: CURRENT WORKERS COMP AMT
C24: =C21 -> 3036 | AS24: 0678 | BD24: =BD21 -> 4116.8069 | BR24: C | BS24: G
B25: DESCRIPTION
B26: CURRENT WORKERS COMP AMT
C27: 0014 | AS27: 0820 | BD27: ='1. Summary 2324'!G54 -> 5582.616 | BR27: D | BS27: G
B28: DESCRIPTION
B29: CURRENT WORKERS COMP AMT
C30: =C27 -> 0014 | AS30: 0678 | BD30: =BD27 -> 5582.616 | BR30: C | BS30: G
B31: DESCRIPTION
B32: CURRENT WORKERS COMP AMT
C33: 3046 | AS33: 0820 | BD33: ='1. Summary 2324'!G55 -> 932.81427 | BR33: D | BS33: G
B34: DESCRIPTION
B35: CURRENT WORKERS COMP AMT
B36: CA503 PC VERSION (7/99)

Sheet TC 35 (8)
B1: STATE CONTROLLER'S USE ONLY | BM1: STATE CONTROLLER'S USE ONLY
B2: DOCUMENT NO. | L2: DATE | T2: MSG Code | V2: STATE OF CALIFORNIA | BM2: TC Code | BO2: PREPARED BY: | BS2: NCACCAM
V3: OFFICE OF THE STATE CONTROLLER
B4: S | BM4: 35 | BQ4: D
B5: STATE CONTROLLER'S USE ONLY | BF5: 9 | BH5: of | BI5: 10
BR7: DC | BS7: A | BT7: SCO USE | BW7: SOURCE
C8: FUND | J8: AGY | N8: FY | R8: M | S8: REF/ITEM | Y8: RED CAT | AD8: P/N | AF8: C | AG8: CAT | AI8: PGM | AK8: ELE | AM8: COMP | AP8: TASK | AS8: ACCT | AW8: SCO | AX8: REV/OBJ | BD8: AMOUNT | BT8: T | BU8: O | BV8: B | BW8: FUND
C9: 3046 | AS9: 0678 | BD9: ='TC 35 (7)'!BD33:BQ33 -> 932.81427 | BR9: C | BS9: G
B10: DESCRIPTION
B11: CURRENT WORKERS COMP AMT
C12: 0140 | AS12: 0820 | BD12: ='1. Summary 2324'!G56 -> 111.67591 | BR12: D | BS12: G
B13: DESCRIPTION
B14: CURRENT WORKERS COMP AMT
C15: =C12 -> 0140 | AS15: 0678 | BD15: =BD12 -> 111.67591 | BR15: C | BS15: G
B16: DESCRIPTION
B17: CURRENT WORKERS COMP AMT
C18: 0200 | AS18: 0820 | BD18: ='1. Summary 2324'!G57 -> 25907.333 | BR18: D | BS18: G
B19: DESCRIPTION
B20: CURRENT WORKERS COMP AMT
C21: =C18 -> 0200 | AS21: 0678 | BD21: =BD18 -> 25907.333 | BR21: C | BS21: G
B22: DESCRIPTION
B23: CURRENT WORKERS COMP AMT
C24: 3211 | AS24: 0820 | BD24: ='1. Summary 2324'!G58 -> 458.60612 | BR24: D | BS24: G
B25: DESCRIPTION
B26: CURRENT WORKERS COMP AMT
C27: =C24 -> 3211 | AS27: 0678 | BD27: =BD24 -> 458.60612 | BR27: C | BS27: G
B28: DESCRIPTION
B29: CURRENT WORKERS COMP AMT
C30: 0387 | AS30: 0820 | BD30: ='1. Summary 2324'!G59 -> 2869.7036 | BR30: D | BS30: G
B31: DESCRIPTION
B32: CURRENT WORKERS COMP AMT
C33: =C30 -> 0387 | AS33: 0678 | BD33: =BD30 -> 2869.7036 | BR33: C | BS33: G
B34: DESCRIPTION
B35: CURRENT WORKERS COMP AMT
B36: CA503 PC VERSION (7/99)

Sheet TC 35 (9)
B1: STATE CONTROLLER'S USE ONLY | BM1: STATE CONTROLLER'S USE ONLY
B2: DOCUMENT NO. | L2: DATE | T2: MSG Code | V2: STATE OF CALIFORNIA | BM2: TC Code | BO2: PREPARED BY: | BS2: NCACCAM
V3: OFFICE OF THE STATE CONTROLLER
B4: S | BM4: 35
B5: STATE CONTROLLER'S USE ONLY | BF5: 10 | BH5: of | BI5: 10
BR7: DC | BS7: A | BT7: SCO USE | BW7: SOURCE
C8: FUND | J8: AGY | N8: FY | R8: M | S8: REF/ITEM | Y8: RED CAT | AD8: P/N | AF8: C | AG8: CAT | AI8: PGM | AK8: ELE | AM8: COMP | AP8: TASK | AS8: ACCT | AW8: SCO | AX8: REV/OBJ | BD8: AMOUNT | BT8: T | BU8: O | BV8: B | BW8: FUND
C9: 0439 | AS9: 0820 | BD9: ='1. Summary 2324'!G60 -> 4171.5344 | BR9: D | BS9: G
B10: DESCRIPTION
B11: CURRENT WORKERS COMP AMT
C12: =C9 -> 0439 | AS12: 0678 | BD12: =BD9 -> 4171.5344 | BR12: C | BS12: G
B13: DESCRIPTION
B14: CURRENT WORKERS COMP AMT
C15: 0565001 | AS15: 0820 | BD15: ='1. Summary 2324'!G61 -> 0 | BR15: D | BS15: G
B16: DESCRIPTION
B17: CURRENT WORKERS COMP AMT
C18: 0565001 | AS18: 0678 | BD18: =BD15 -> 0 | BR18: C | BS18: G
B19: DESCRIPTION
B20: CURRENT WORKERS COMP AMT
C21: 0929 | AS21: 0825 | BD21: ='1. Summary 2324'!G62 -> 1295.622 | BR21: D | BS21: G
B22: DESCRIPTION
B23: CURRENT WORKERS COMP AMT
C24: 0929 | AS24: 0678 | BD24: =BD21 -> 1295.622 | BR24: C | BS24: G
B25: DESCRIPTION
B26: CURRENT WORKERS COMP AMT
C27: 0639 | AS27: 0815 | BD27: ='1. Summary 2324'!G63 -> 0 | BR27: D | BS27: G
B28: DESCRIPTION
B29: CURRENT WORKERS COMP AMT
C30: 0639 | AS30: 0678 | BD30: =BD27 -> 0 | BR30: C | BS30: G
B31: DESCRIPTION
B32: CURRENT WORKERS COMP AMT
C33: 0121 | AS33: 0815 | BD33: ='1. Summary 2324'!G64 -> 777.81924 | BR33: D | BS33: G
B34: DESCRIPTION
B35: CURRENT WORKERS COMP AMT
B36: CA503 PC VERSION (7/99)

Sheet TC 35 (10)
B1: STATE CONTROLLER'S USE ONLY | BM1: STATE CONTROLLER'S USE ONLY
B2: DOCUMENT NO. | L2: DATE | T2: MSG Code | V2: STATE OF CALIFORNIA | BM2: TC Code | BO2: PREPARED BY: | BS2: NCACCAM
V3: OFFICE OF THE STATE CONTROLLER
B4: S | BM4: 35
B5: STATE CONTROLLER'S USE ONLY | BF5: 11 | BH5: of | BI5: 11
BR7: DC | BS7: A | BT7: SCO USE | BW7: SOURCE
C8: FUND | J8: AGY | N8: FY | R8: M | S8: REF/ITEM | Y8: RED CAT | AD8: P/N | AF8: C | AG8: CAT | AI8: PGM | AK8: ELE | AM8: COMP | AP8: TASK | AS8: ACCT | AW8: SCO | AX8: REV/OBJ | BD8: AMOUNT | BT8: T | BU8: O | BV8: B | BW8: FUND
C9: 0121 | AS9: 0678 | BD9: ='TC 35 (9)'!BD33:BQ33 -> 777.81924 | BR9: C | BS9: G
B10: DESCRIPTION
B11: CURRENT WORKERS COMP AMT
C12: 0223 | AS12: 0815 | BD12: ='1. Summary 2324'!G65 -> 57756.943 | BR12: D | BS12: G
B13: DESCRIPTION
B14: CURRENT WORKERS COMP AMT
C15: =C12 -> 0223 | AS15: 0678 | BD15: =BD12 -> 57756.943 | BR15: C | BS15: G
B16: DESCRIPTION
B17: CURRENT WORKERS COMP AMT
C18: 0318 | AS18: 0820 | BD18: ='1. Summary 2324'!G66 -> 25627.447 | BR18: D | BS18: G
B19: DESCRIPTION
B20: CURRENT WORKERS COMP AMT
C21: =C18 -> 0318 | AS21: 0678 | BD21: =BD18 -> 25627.447 | BR21: C | BS21: G
B22: DESCRIPTION
B23: CURRENT WORKERS COMP AMT
C24: 0064 | AS24: 0830 | BD24: ='1. Summary 2324'!G42 -> 157496.76 | BR24: D | BS24: G
B26: CURRENT WORKERS COMP AMT
C27: 0064 | AS27: 0678 | BD27: =BD24 -> 157496.76 | BR27: C | BS27: G
B29: CURRENT WORKERS COMP AMT
B36: CA503 PC VERSION (7/99)

Sheet TC 35 0890 Entry
B1: STATE CONTROLLER'S USE ONLY | BM1: STATE CONTROLLER'S USE ONLY
B2: DOCUMENT NO. | L2: DATE | T2: MSG Code | V2: STATE OF CALIFORNIA | BM2: TC Code | BO2: PREPARED BY: | BS2: NCACCAM
V3: OFFICE OF THE STATE CONTROLLER
B4: S | BM4: 35
B5: STATE CONTROLLER'S USE ONLY | BF5: 1 | BH5: of | BI5: 1
BR7: DC | BS7: A | BT7: SCO USE | BW7: SOURCE
C8: FUND | J8: AGY | N8: FY | R8: M | S8: REF/ITEM | Y8: RED CAT | AD8: P/N | AF8: C | AG8: CAT | AI8: PGM | AK8: ELE | AM8: COMP | AP8: TASK | AS8: ACCT | AW8: SCO | AX8: REV/OBJ | BD8: AMOUNT | BT8: T | BU8: O | BV8: B | BW8: FUND
C9: 0890 | AS9: 0025 | BD9: ='TC 35 (3)'!BD9:BQ9+'TC 35 (3)'!BD15:BQ15+'TC 35 (3)'!BD21:BQ21+'TC 35 (3)'!BD27:BQ27+'TC 35 (3)'!BD33:BQ33+'TC 35 (4)'!BD12:BQ12 -> 89384.905 | BR9: D | BS9: G
B11: WC Record Asset DFOG
C12: 0890 | AS12: 0719 | BD12: =BD9 -> 89384.905 | BR12: C | BS12: G
B14: WC Record Asset DFOG
B36: CA503 PC VERSION (7/99)

Sheet 9142
B1: STATE CONTROLLER'S USE ONLY | BM1: STATE CONTROLLER'S USE ONLY
B2: DOCUMENT NO. | L2: DATE | T2: MSG Code | V2: STATE OF CALIFORNIA | BM2: TC Code | BO2: PREPARED BY: | BS2: NCACCAM
V3: OFFICE OF THE STATE CONTROLLER
B4: S | BM4: 35
B5: STATE CONTROLLER'S USE ONLY | BF5: 1 | BH5: of | BI5: 2
BR7: DC | BS7: A | BT7: SCO USE | BW7: SOURCE
C8: FUND | J8: AGY | N8: FY | R8: M | S8: REF/ITEM | Y8: RED CAT | AD8: P/N | AF8: C | AG8: CAT | AI8: PGM | AK8: ELE | AM8: COMP | AP8: TASK | AS8: ACCT | AW8: SCO | AX8: REV/OBJ | BD8: AMOUNT | BT8: T | BU8: O | BV8: B | BW8: FUND
C9: 9142 | AS9: 0655 | BD9: =IF('5. Gov Wide Entries Fund 9142'!F6<0,(-1*'5. Gov Wide Entries Fund 9142'!F6),'5. Gov Wide Entries Fund 9142'!F6) -> 6293359.8 | BR9: =IF('5. Gov Wide Entries Fund 9142'!F6<0,"C","D") -> C | BS9: G
B10: DESCRIPTION
B11: RELASS CY PORTION OF W/C
C12: 9142 | AS12: 0678 | BD12: =BD9 -> 6293359.8 | BR12: =IF(BR9="C","D","C") -> D | BS12: G
B13: DESCRIPTION
B14: RELASS CY PORTION OF W/C
C15: 9142 | AS15: 0692 | BD15: =IF('5. Gov Wide Entries Fund 9142'!F8<0,(-1*'5. Gov Wide Entries Fund 9142'!F8),'5. Gov Wide Entries Fund 9142'!F8) -> 48772847 | BR15: =IF('5. Gov Wide Entries Fund 9142'!F8<0,"C","D") -> D | BS15: G
B16: DESCRIPTION
B17: RECORD LT W/C LIAB
C18: 9142 | AS18: 0808 | BD18: =IF('5. Gov Wide Entries Fund 9142'!F9<0,(-1*'5. Gov Wide Entries Fund 9142'!F9),'5. Gov Wide Entries Fund 9142'!F9) -> 1283152.7 | BR18: =IF('5. Gov Wide Entries Fund 9142'!F9<0,"C","D") -> C | BS18: G
B19: DESCRIPTION
B20: RECORD CHANGE IN W/C LIAB
C21: 9142 | AS21: 0810 | BD21: =IF('5. Gov Wide Entries Fund 9142'!F10<0,(-1*'5. Gov Wide Entries Fund 9142'!F10),'5. Gov Wide Entries Fund 9142'!F10) -> 145220.41 | BR21: =IF('5. Gov Wide Entries Fund 9142'!F10<0,"C","D") -> C | BS21: G
B22: DESCRIPTION
B23: RECORD CHANGE IN W/C LIAB
C24: 9142 | AS24: 0815 | BD24: =IF('5. Gov Wide Entries Fund 9142'!F11<0,(-1*'5. Gov Wide Entries Fund 9142'!F11),'5. Gov Wide Entries Fund 9142'!F11) -> 6459224.7 | BR24: =IF('5. Gov Wide Entries Fund 9142'!F11<0,"C","D") -> C | BS24: G
B25: DESCRIPTION
B26: RECORD CHANGE IN W/C LIAB
C27: 9142 | AS27: 0820 | BD27: =IF('5. Gov Wide Entries Fund 9142'!F12<0,(-1*'5. Gov Wide Entries Fund 9142'!F12),'5. Gov Wide Entries Fund 9142'!F12) -> 4196217.2 | BR27: =IF('5. Gov Wide Entries Fund 9142'!F12<0,"C","D") -> C | BS27: G
B28: DESCRIPTION
B29: RECORD CHANGE IN W/C LIAB
C30: 9142 | AS30: 0825 | BD30: =IF('5. Gov Wide Entries Fund 9142'!F13<0,(-1*'5. Gov Wide Entries Fund 9142'!F13),'5. Gov Wide Entries Fund 9142'!F13) -> 173642.47 | BR30: =IF('5. Gov Wide Entries Fund 9142'!F13<0,"C","D") -> C | BS30: G
B31: DESCRIPTION
B32: RECORD CHANGE IN W/C LIAB
C33: 9142 | AS33: 0830 | BD33: =IF('5. Gov Wide Entries Fund 9142'!F14<0,(-1*'5. Gov Wide Entries Fund 9142'!F14),'5. Gov Wide Entries Fund 9142'!F14) -> 9907483.8 | BR33: =IF('5. Gov Wide Entries Fund 9142'!F14<0,"C","D") -> C | BS33: G
B34: DESCRIPTION
B35: RECORD CHANGE IN W/C LIAB
B36: CA503 PC VERSION (7/99)

Sheet 9142 (2)
B1: STATE CONTROLLER'S USE ONLY | BM1: STATE CONTROLLER'S USE ONLY
B2: DOCUMENT NO. | L2: DATE | T2: MSG Code | V2: STATE OF CALIFORNIA | BM2: TC Code | BO2: PREPARED BY: | BS2: ='9142'!BS2:CC3 -> NCACCAM
V3: OFFICE OF THE STATE CONTROLLER
B4: S | BM4: 35
B5: STATE CONTROLLER'S USE ONLY | BF5: 2 | BH5: of | BI5: 2
BR7: DC | BS7: A | BT7: SCO USE | BW7: SOURCE
C8: FUND | J8: AGY | N8: FY | R8: M | S8: REF/ITEM | Y8: RED CAT | AD8: P/N | AF8: C | AG8: CAT | AI8: PGM | AK8: ELE | AM8: COMP | AP8: TASK | AS8: ACCT | AW8: SCO | AX8: REV/OBJ | BD8: AMOUNT | BT8: T | BU8: O | BV8: B | BW8: FUND
C9: 9142 | AS9: 0835 | BD9: =IF('5. Gov Wide Entries Fund 9142'!F15<0,(-1*'5. Gov Wide Entries Fund 9142'!F15),'5. Gov Wide Entries Fund 9142'!F15) -> 26607906 | BR9: =IF('5. Gov Wide Entries Fund 9142'!F15<0,"C","D") -> C | BS9: G
B11: RECORD CHANGE IN W/C LIAB
C12: 9142 | AS12: 0950 | BD12: =IF('5. Gov Wide Entries Fund 9142'!F16<0,(-1*'5. Gov Wide Entries Fund 9142'!F16),'5. Gov Wide Entries Fund 9142'!F16) -> 0 | BR12: =IF('5. Gov Wide Entries Fund 9142'!F16<0,"C","D") -> D | BS12: G
B14: RECORD CHANGE IN W/C LIAB
B36: CA503 PC VERSION (7/99)

Sheet Check for Rounding
A1: Purpose: | B1: To check for rounding adjustments that need to be made for the TC 35 entries.
A2: Procedure: | B2: Check this worksheet to compare the TC 35 entries to the Summary tab. Numbers that will be posted from the "Summary tab (Actuals)" contain decimals greater than the hundredths place. "TC 35 tabs (Actuals)" are linked directly to those numbers and appear rounded because the decimal place was moved for formatting, but the numbers are still not truly rounded. Below are truly rounded numbers, "Rounded (Input)", that check if the numbers in total will tie back to the support in the Summary tab. Rounding should be checked before posting the TC 35's because there is a high chance for rounding discrepancies. If there are any differences in column D, then manually input rounding adjustments in column E, so that the total of the TC 35 entries agree to the Summary tab shown in "TC 35 (Adjusted Input)". This tab lets you see the entries overall to plan the rounding adjustments, but no adjustments are actually made in this tab to the TC 35 entries. Rounding adjustments need to be made in the respective TC 35 tab after rounding adjustments have been planned here.
A16: General Fund
A17: Summary tab (Actuals) | B17: TC 35 tabs (Actuals) | C17: Rounded (Input) | D17: Difference (C-B) | E17: Rounding Adjustment | F17: TC 35 (Adjusted Input)
A18: ='1. Summary 2324'!G21 -> 122145.44 | B18: =A18 -> 122145.44 | C18: =ROUND(A18,2) -> 122145.44 | D18: =C18-B18 -> 0.0026148036 | F18: =C18+E18 -> 122145.44
A19: ='1. Summary 2324'!G22 -> 10202.535 | B19: =A19 -> 10202.535 | C19: =ROUND(A19,2) -> 10202.53 | D19: =C19-B19 -> -0.0049683837 | F19: =C19+E19 -> 10202.53
A20: ='1. Summary 2324'!G24 -> 603157.16 | B20: =A20 -> 603157.16 | C20: =ROUND(A20,2) -> 603157.16 | D20: =C20-B20 -> -0.00070608326 | F20: =C20+E20 -> 603157.16
A21: ='1. Summary 2324'!G26 -> 465705.82 | B21: =A21 -> 465705.82 | C21: =ROUND(A21,2) -> 465705.82 | D21: =C21-B21 -> 0.0042805895 | F21: =C21+E21 -> 465705.82
A22: ='1. Summary 2324'!G27 -> 1147.1634 | B22: =A22 -> 1147.1634 | C22: =ROUND(A22,2) -> 1147.16 | D22: =C22-B22 -> -0.0033525841 | F22: =C22+E22 -> 1147.16
A23: ='1. Summary 2324'!G28 -> 0 | B23: =A23 -> 0 | C23: =ROUND(A23,2) -> 0 | D23: =C23-B23 -> 0 | F23: =C23+E23 -> 0
A24: ='1. Summary 2324'!G29 -> 3432683.1 | B24: =A24 -> 3432683.1 | C24: =ROUND(A24,2) -> 3432683.1 | D24: =C24-B24 -> -0.0040612756 | F24: =C24+E24 -> 3432683.1
A25: ='1. Summary 2324'!G30-'1. Summary 2324'!G25-'1. Summary 2324'!G23 -> 4635041.2 | B25: =A25 -> 4635041.2 | C25: =SUM(C18:C24) -> 4635041.2 | D25: =C25-B25 -> -0.0061929338 | F25: =C25+E25 -> 4635041.2 | G25: Total General Fund less Other Funds
A26: =A25-SUM(A18:A24) -> 0 | B26: =B25-SUM(B18:B24) -> 0 | C26: =C25-SUM(C18:C24) -> 0 | F26: =F25-SUM(F18:F24) -> 0 | G26: If Adjusted Input is 0, then Debits = Credits.
A27: ='1. Summary 2324'!G23 -> 0 | B27: =A27 -> 0 | C27: =ROUND(A27,2) -> 0 | D27: =C27-B27 -> 0 | F27: =C27+E27 -> 0 | G27: Fund 1031
A28: ='1. Summary 2324'!G25 -> 115957.23 | B28: =A28 -> 115957.23 | C28: =ROUND(A28,2) -> 115957.23 | D28: =C28-B28 -> -0.0031017047 | F28: =C28+E28 -> 115957.23 | G28: Fund 0870
A29: ='1. Summary 2324'!G30 -> 4750998.4 | B29: =B28+B25+B27 -> 4750998.4 | C29: =C28+C25+C27 -> 4750998.4 | D29: =C29-B29 -> -0.0092946384 | E29: =E28+E25+E27 -> 0 | F29: =F28+F25 -> 4750998.4 | G29: Total General Fund
G30: =IF(F29=ROUND('1. Summary 2324'!G30,2),"Total matches Summary tab","Adj for rounding/Check formulas") -> Adj for rounding/Check formulas
A31: Special Funds
A32: Summary tab (Actuals) | B32: TC 35 tabs (Actuals) | C32: Rounded (Input) | D32: Difference (C-B) | E32: Rounding Adjustment | F32: TC 35 (Adjusted Input)
A33: ='1. Summary 2324'!G33 -> 19752.146 | B33: =A33 -> 19752.146 | C33: =ROUND(A33,2) -> 19752.15 | D33: =C33-B33 -> 0.0043482237 | F33: =C33+E33 -> 19752.15
A34: ='1. Summary 2324'!G34 -> 8535.8487 | B34: =A34 -> 8535.8487 | C34: =ROUND(A34,2) -> 8535.85 | D34: =C34-B34 -> 0.00134725 | F34: =C34+E34 -> 8535.85
A35: ='1. Summary 2324'!G35 -> 55405.76 | B35: =A35 -> 55405.76 | C35: =ROUND(A35,2) -> 55405.76 | D35: =C35-B35 -> -2.0458152e-05 | F35: =C35+E35 -> 55405.76
A36: ='1. Summary 2324'!G36 -> 4930.8711 | B36: =A36 -> 4930.8711 | C36: =ROUND(A36,2) -> 4930.87 | D36: =C36-B36 -> -0.0011238316 | F36: =C36+E36 -> 4930.87
A37: ='1. Summary 2324'!G37 -> 116.51072 | B37: =A37 -> 116.51072 | C37: =ROUND(A37,2) -> 116.51 | D37: =C37-B37 -> -0.00071522527 | F37: =C37+E37 -> 116.51
A38: ='1. Summary 2324'!G38 -> 643.76922 | B38: =A38 -> 643.76922 | C38: =ROUND(A38,2) -> 643.77 | D38: =C38-B38 -> 0.00077973945 | F38: =C38+E38 -> 643.77
A39: =SUM(A33:A38) -> 89384.905 | B39: =A39 -> 89384.905 | C39: =SUM(C33:C38) -> 89384.91 | D39: =C39-B39 -> 0.0046156982 | E39: =SUM(E33:E38) -> 0 | F39: =SUM(F33:F38) -> 89384.91 | G39: Total Special Funds 0890
A40: ='1. Summary 2324'!G39 -> 5156.6493 | B40: =A40 -> 5156.6493 | C40: =ROUND(A40,2) -> 5156.65 | D40: =C40-B40 -> 0.00067425881 | F40: =C40+E40 -> 5156.65 | G40: =IF(F39=ROUND(SUM('1. Summary 2324'!G33:G38),2),"Total matches Summary tab","Adj for rounding/Check formulas") -> Total matches Summary tab
A41: ='1. Summary 2324'!G40 -> 324916.76 | B41: =A41 -> 324916.76 | C41: =ROUND(A41,2) -> 324916.76 | D41: =C41-B41 -> 0.0014793809 | F41: =C41+E41 -> 324916.76 | G41: =IF(F39=ROUND('TC 35 0890 Entry'!BD9:BD9,2),"Total matches 0890 TC 35 Input","Adj for rounding/Check formulas") -> Total matches 0890 TC 35 Input
A42: ='1. Summary 2324'!G41 -> 795989.62 | B42: =A42 -> 795989.62 | C42: =ROUND(A42,2) -> 795989.62 | D42: =C42-B42 -> -0.00084128673 | F42: =C42+E42 -> 795989.62
A43: ='1. Summary 2324'!G42 -> 157496.76 | B43: =A43 -> 157496.76 | C43: =ROUND(A43,2) -> 157496.76 | D43: =C43-B43 -> -0.003265722 | F43: =C43+E43 -> 157496.76
A44: ='1. Summary 2324'!G43 -> 10445.355 | B44: =A44 -> 10445.355 | C44: =ROUND(A44,2) -> 10445.35 | D44: =C44-B44 -> -0.0047362057 | F44: =C44+E44 -> 10445.35
A45: ='1. Summary 2324'!G44 -> 10723.658 | B45: =A45 -> 10723.658 | C45: =ROUND(A45,2) -> 10723.66 | D45: =C45-B45 -> 0.0016011258 | F45: =C45+E45 -> 10723.66
A46: ='1. Summary 2324'!G45 -> 0 | B46: =A46 -> 0 | C46: =ROUND(A46,2) -> 0 | D46: =C46-B46 -> 0 | F46: =C46+E46 -> 0
A47: ='1. Summary 2324'!G46 -> 2503.8384 | B47: =A47 -> 2503.8384 | C47: =ROUND(A47,2) -> 2503.84 | D47: =C47-B47 -> 0.0016154351 | F47: =C47+E47 -> 2503.84
A48: ='1. Summary 2324'!G47 -> 0 | B48: =A48 -> 0 | C48: =ROUND(A48,2) -> 0 | D48: =C48-B48 -> 0 | F48: =C48+E48 -> 0
A49: ='1. Summary 2324'!G48 -> 405.25443 | B49: =A49 -> 405.25443 | C49: =ROUND(A49,2) -> 405.25 | D49: =C49-B49 -> -0.0044255668 | F49: =C49+E49 -> 405.25
A50: ='1. Summary 2324'!G49 -> 2519.7332 | B50: =A50 -> 2519.7332 | C50: =ROUND(A50,2) -> 2519.73 | D50: =C50-B50 -> -0.0031872719 | F50: =C50+E50 -> 2519.73
A51: ='1. Summary 2324'!G50 -> 484.99205 | B51: =A51 -> 484.99205 | C51: =ROUND(A51,2) -> 484.99 | D51: =C51-B51 -> -0.0020511857 | F51: =C51+E51 -> 484.99
A52: ='1. Summary 2324'!G51 -> 80.941962 | B52: =A52 -> 80.941962 | C52: =ROUND(A52,2) -> 80.94 | D52: =C52-B52 -> -0.0019618038 | F52: =C52+E52 -> 80.94
A53: ='1. Summary 2324'!G52 -> 12644.035 | B53: =A53 -> 12644.035 | C53: =ROUND(A53,2) -> 12644.03 | D53: =C53-B53 -> -0.0047918573 | F53: =C53+E53 -> 12644.03
... A67: ='1. Summary 2324'!G66 -> 25627.447 | B67: =A67 -> 25627.447 | C67: =ROUND(A67,2) -> 25627.45 | D67: =C67-B67 -> 0.0032991141 | F67: =C67+E67 -> 25627.45
A68: ='1. Summary 2324'!G67 -> 1542361.4 | B68: =SUM(B40:B67)+B39 -> 1542361.4 | C68: =SUM(C40:C67)+C39 -> 1542361.4 | D68: =C68-B68 -> -0.015532362 | E68: =SUM(E40:E67)+E39 -> 0 | F68: =SUM(F40:F67)+F39 -> 1542361.4 | G68: Total Special Funds
G69: =IF(F68=ROUND('1. Summary 2324'!G67,2),"Total matches Summary tab","Adj for rounding/Check formulas") -> Adj for rounding/Check formulas
A70: Gov Wide Entries
A71: Gov Wide tab (Actuals) | B71: TC 35 tabs (Actuals) | C71: Rounded (Input) | D71: Difference (C-B) | E71: Rounding Adjustment | F71: TC 35 (Adjusted Input)
A72: ='5. Gov Wide Entries Fund 9142'!F6 -> -6293359.8 | B72: =A72 -> -6293359.8 | C72: =ROUND(A72,2) -> -6293359.8 | D72: =C72-B72 -> 0.0048270002 | F72: =C72 -> -6293359.8 | G72: Reclass Other Liabilities to Current Workers' Comp Liability
A73: ='5. Gov Wide Entries Fund 9142'!F7 -> 6293359.8 | B73: =A73 -> 6293359.8 | C73: =ROUND(A73,2) -> 6293359.8 | D73: =C73-B73 -> -0.0048270002 | F73: =C73 -> 6293359.8 | G73: =IF(F73=F68+F29,"Other Liabilities matches Reclass","Adj for rounding/Check formulas") -> Adj for rounding/Check formulas
A74: ='5. Gov Wide Entries Fund 9142'!F8 -> 48772847 | B74: =A74 -> 48772847 | C74: =ROUND(A74,2) -> 48772847 | D74: =C74-B74 -> -0.0048270002 | F74: =C74 -> 48772847
A75: ='5. Gov Wide Entries Fund 9142'!F9 -> -1283152.7 | B75: =A75 -> -1283152.7 | C75: =ROUND(A75,2) -> -1283152.7 | D75: =C75-B75 -> -0.0048183126 | F75: =C75 -> -1283152.7
A76: ='5. Gov Wide Entries Fund 9142'!F10 -> -145220.41 | B76: =A76 -> -145220.41 | C76: =ROUND(A76,2) -> -145220.41 | D76: =C76-B76 -> 0.0029864294 | F76: =C76 -> -145220.41
A77: ='5. Gov Wide Entries Fund 9142'!F11 -> -6459224.7 | B77: =A77 -> -6459224.7 | C77: =ROUND(A77,2) -> -6459224.7 | D77: =C77-B77 -> -0.0017577251 | F77: =C77 -> -6459224.7
A78: ='5. Gov Wide Entries Fund 9142'!F12 -> -4196217.2 | B78: =A78 -> -4196217.2 | C78: =ROUND(A78,2) -> -4196217.2 | D78: =C78-B78 -> 0.0023829704 | F78: =C78 -> -4196217.2
A79: ='5. Gov Wide Entries Fund 9142'!F13 -> -173642.47 | B79: =A79 -> -173642.47 | C79: =ROUND(A79,2) -> -173642.47 | D79: =C79-B79 -> -0.0048332324 | F79: =C79 -> -173642.47
A80: ='5. Gov Wide Entries Fund 9142'!F14 -> -9907483.8 | B80: =A80 -> -9907483.8 | C80: =ROUND(A80,2) -> -9907483.8 | D80: =C80-B80 -> -0.00087616779 | F80: =C80 -> -9907483.8
A81: ='5. Gov Wide Entries Fund 9142'!F15 -> -26607906 | B81: =A81 -> -26607906 | C81: =ROUND(A81,2) -> -26607906 | D81: =C81-B81 -> 0.001743041 | F81: =C81 -> -26607906
A82: ='5. Gov Wide Entries Fund 9142'!F16 -> 0 | B82: =A82 -> 0 | C82: =ROUND(A82,2) -> 0 | D82: =C82-B82 -> 0 | E82: 0.01 | F82: =C82+E82 -> 0.01 | G82: Total Gov Wide Entries
A83: =SUM(A72:A82) -> -3.7252903e-09 | B83: =A83 -> -3.7252903e-09 | C83: =SUM(C72:C82) -> -0.0099999905 | D83: =C83-B83 -> -0.0099999867 | E83: =SUM(E72:E82) -> 0.01 | F83: =SUM(F72:F82) -> 9.5367432e-09 | G83: If Adjusted Input is 0, then Debits = Credits.
