Workbook
Name ITEM_CAPCOST: #REF!
Name ITEM_CAPCOST: #REF!
Name ITEM_CAPCOST: #REF!
Name page\x2dtotal: #REF!
Name page\x2dtotal: #REF!
Name page\x2dtotal: #REF!
Name page\x2dtotal: #REF!
Name page\x2dtotal: #REF!
Name page\x2dtotal: #REF!
Name page\x2dtotal: #REF!
Name page\x2dtotal: #REF!
Name page\x2dtotal: #REF!
Name page\x2dtotal\x2dmaster0: #REF!
Name page\x2dtotal\x2dmaster0: #REF!
Name page\x2dtotal\x2dmaster0: #REF!
Name page\x2dtotal\x2dmaster0: #REF!
Name page\x2dtotal\x2dmaster0: #REF!
Name page\x2dtotal\x2dmaster0: #REF!
Name page\x2dtotal\x2dmaster0: #REF!
Name page\x2dtotal\x2dmaster0: #REF!
Name page\x2dtotal\x2dmaster0: #REF!
Name page\x2dtotal\x2dmaster0_1_1: #REF!
Name page\x2dtotal\x2dmaster0_2_1: '0001'!#REF!
Name page\x2dtotal\x2dmaster0_2_1: '0041'!#REF!
Name page\x2dtotal\x2dmaster0_2_1: '0042'!#REF!
Name page\x2dtotal\x2dmaster0_2_1: '0042 Revised'!#REF!
Name page\x2dtotal\x2dmaster0_2_1: '0046'!#REF!
Name page\x2dtotal\x2dmaster0_2_1: '0183'!#REF!
Name page\x2dtotal\x2dmaster0_2_1: '0523'!#REF!
Name page\x2dtotal\x2dmaster0_2_1: '0541'!#REF!
Name page\x2dtotal\x2dmaster0_2_1: '0653'!#REF!
Name page\x2dtotal\x2dmaster0_2_1: '0673'!#REF!
Name page\x2dtotal\x2dmaster0_2_1: '0703'!#REF!
Name page\x2dtotal\x2dmaster0_2_1: '0756'!#REF!
Name page\x2dtotal\x2dmaster0_2_1: '0942'!#REF!
Name page\x2dtotal\x2dmaster0_2_1: '2504'!#REF!
Name page\x2dtotal\x2dmaster0_2_1: '3007'!#REF!
Name page\x2dtotal\x2dmaster0_2_1: '3290'!#REF!
Name page\x2dtotal\x2dmaster0_2_1: '3291'!#REF!
Name page\x2dtotal\x2dmaster0_2_1: '6055'!#REF!
Name page\x2dtotal\x2dmaster0_2_1: '6056'!#REF!
Name page\x2dtotal\x2dmaster0_2_1: '6058'!#REF!
Name page\x2dtotal\x2dmaster0_2_1: '6059'!#REF!
Name page\x2dtotal\x2dmaster0_2_1: '6060'!#REF!
Name page\x2dtotal\x2dmaster0_2_1: '6062'!#REF!
Name page\x2dtotal\x2dmaster0_2_1: '6063'!#REF!
Name page\x2dtotal\x2dmaster0_2_1: '6064'!#REF!
Name page\x2dtotal\x2dmaster0_2_1: '6072'!#REF!
Name page\x2dtotal\x2dmaster0_2_1: '6801'!#REF!
Name page\x2dtotal\x2dmaster0_2_1: #REF!
Name page\x2dtotal\x2dmaster0_2_1: #REF!
Name page\x2dtotal\x2dmaster0_2_1: #REF!
Name page\x2dtotal\x2dmaster0_2_1: #REF!
Name page\x2dtotal\x2dmaster0_2_1: #REF!
Name page\x2dtotal\x2dmaster0_2_1: #REF!
Name page\x2dtotal\x2dmaster0_2_1: #REF!
Name page\x2dtotal\x2dmaster0_2_1: #REF!
Name page\x2dtotal\x2dmaster0_3_1: #REF!
Name page\x2dtotal\x2dmaster0_3_1: #REF!
Name page\x2dtotal\x2dmaster0_3_1: #REF!

Sheet 0001
I1: Page No : 1
A2: REPORT 18 – STATEMENT OF CHANGES IN CAPITAL ASSETS
A3: Department Name (2660)
A4: GENERAL FUND (0001)
A5: Fiscal Year 2023-24
A6: As of 06/30/2024
A7: Business Unit: | C7: 2660 - DEPARTMENT OF TRANSPORTATION | I7: Report ID: RPTGL075 | J7: RPTGL075
A8: Fund: | C8: 0001 - GENERAL FUND | I8: Run Date: | J8: =TODAY() -> 45723
I9: Run Time: | J9: =NOW() -> 45723.508
A14: Account – Description | F14: Beginning Balance | G14: Additions | H14: Deductions | J14: Ending Balance
A15: Tangible Assets
A16: 2310 Land a | F16: =F42 -> 886023.84 | G16: =G42 -> 69487.68 | J16: =F16+G16-H16 -> 955511.52
A17: 2321 Buildings | F17: 105422.6 | J17: =F17+G17-H17 -> 105422.6
A18: 2331 Improvements Other Than Buildings | J18: =F18+G18-H18 -> 0
A19: 2341 Equipment | F19: 934059.34 | G19: 76269.42 | H19: 368175.54 | J19: =F19+G19-H19 -> 642153.22
A20: 2350 Construction Work in Progress b | F20: 64122817 | G20: 72150164 | H20: 19313010 | J20: =F20+G20-H20 -> 1.1695997e+08
A21: 2361 Infrastructure - Non Depreciable b | F21: 5886148 | G21: 50235158 | J21: =F21+G21-H21 -> 56121306
A23: Intangible Assets
A24: 2411 Computer Software - Amortizable | J24: =F24+G24-H24 -> 0
A25: 2412 Land Use Rights - Amortizable | J25: =F25+G25-H25 -> 0
A26: 2413 Patents, Copyrights, and Trademarks - Amortizable | J26: =F26+G26-H26 -> 0
A27: 2414 Other Intangible Assets - Amortizable | J27: =F27+G27-H27 -> 0
A28: 2415 Right-to-Use Leased Land - Amortizable | J28: =F28+G28-H28 -> 0
A29: 2416 Right-to-Use Leased Buildings - Amortizable | J29: =F29+G29-H29 -> 0
A30: 2417 Right-to-Use Leased Equipment - Amortizable | J30: =F30+G30-H30 -> 0
A31: 2418 Right-to-Use Subscription-Based Information Technology Arrangements (SBITA) - Amortizable | J31: =F31+G31-H31 -> 0
A32: 2422 Land Use Rights - Non-Amortizable | J32: =F32+G32-H32 -> 0
A35: Fund: | B35: 0001 | F35: =SUM(F16:F34) -> 71934471 | G35: =SUM(G16:G34) -> 1.2253108e+08 | H35: =SUM(H16:H34) -> 19681185 | J35: =SUM(J16:J34) -> 1.7478436e+08
A37: Note:
F38: Total | G38: Additions | H38: Deductions | J38: Total
A39: Land - Operational Dept (2310-5000) | F39: 622702.5 | J39: =F39+G39-H39 -> 622702.5
A40: Land - Infrastructure Dept (2310-5900) b | F40: 263321.34 | G40: 69487.68 | H40: 0 | J40: =F40+G40-H40 -> 332809.02
A42: a - Total Land | F42: =SUM(F39:F41) -> 886023.84 | G42: =SUM(G39:G40) -> 69487.68 | H42: =SUM(H39:H40) -> 0 | J42: =SUM(J39:J41) -> 955511.52
A44: b - Infrastructure only.
A46: c - The $19,313,009.55 in Construction Work in Progress' Deductions which represents FY 2023/2024's Transfer from CWIP to Non-Depreciable Infrastructure (Completed).
A49: I certify (or declare) under penalty of perjury that the attached reports are true, accurate and complete, and were prepared following the applicable laws, regulations, policies, procedures, and instructions. I have not violated any of the provisions of Article 4, Chapter 1, Division 4, Title 1, Government Code (commencing with Section 1090) and Article 2, Chapter 1, Part 3, Division 3, Title 2, Government Code (commencing with Section 13030).
A54: Subscribed and executed this 30th day of August, 2024 at Sacramento, California.
I60: KIM PHAN, Chief
I61: Service Transactions & Asset
I62: Reconciliation Section

Sheet 0041
I1: Page No : 2
A2: REPORT 18 – STATEMENT OF CHANGES IN CAPITAL ASSETS
A3: Department Name (2660)
A4: AERONAUTICS FUND (0041)
A5: Fiscal Year 2023-24
A6: As of 06/30/2024
A7: Business Unit: | C7: 2660 - DEPARTMENT OF TRANSPORTATION | I7: Report ID: RPTGL075 | J7: RPTGL075
A8: Fund: | C8: 0041 AERONAUTICS FUND | I8: Run Date: | J8: =TODAY() -> 45723
I9: Run Time: | J9: =NOW() -> 45723.508
A14: Account – Description | F14: Beginning Balance | G14: Additions | H14: Deductions | J14: Ending Balance
A15: Tangible Assets
A16: 2310 Land a | J16: =F16+G16-H16 -> 0
A17: 2321 Buildings | J17: =F17+G17-H17 -> 0
A18: 2331 Improvements Other Than Buildings | J18: =F18+G18-H18 -> 0
A19: 2341 Equipment | F19: 1161084.4 | J19: =F19+G19-H19 -> 1161084.4
A20: 2350 Construction Work in Progress a | J20: =F20+G20-H20 -> 0
A21: 2361 Infrastructure - Non Depreciable a | J21: =F21+G21-H21 -> 0
A23: Intangible Assets
A24: 2411 Computer Software - Amortizable | F24: 46612.91 | G24: 244.97 | J24: =F24+G24-H24 -> 46857.88
A25: 2412 Land Use Rights - Amortizable | J25: =F25+G25-H25 -> 0
A26: 2413 Patents, Copyrights, and Trademarks - Amortizable | J26: =F26+G26-H26 -> 0
A27: 2414 Other Intangible Assets - Amortizable | J27: =F27+G27-H27 -> 0
A28: 2415 Right-to-Use Leased Land - Amortizable | J28: =F28+G28-H28 -> 0
A29: 2416 Right-to-Use Leased Buildings - Amortizable | J29: =F29+G29-H29 -> 0
A30: 2417 Right-to-Use Leased Equipment - Amortizable | J30: =F30+G30-H30 -> 0
A31: 2418 Right-to-Use Subscription-Based Information Technology Arrangements (SBITA) - Amortizable | F31: 2917.18 | G31: 586.15401 | H31: 1031.4191 | J31: =F31+G31-H31 -> 2471.9149
A32: 2422 Land Use Rights - Non-Amortizable | J32: =F32+G32-H32 -> 0
A35: Fund: | B35: 0041 | F35: =SUM(F16:F34) -> 1210614.5 | G35: =SUM(G16:G34) -> 831.12401 | H35: =SUM(H16:H34) -> 1031.4191 | J35: =SUM(J16:J34) -> 1210414.2
A37: Note:
A38: a - Infrastructure only.
A40: I certify (or declare) under penalty of perjury that the attached reports are true, accurate and complete, and were prepared following the applicable laws, regulations, policies, procedures, and instructions. I have not violated any of the provisions of Article 4, Chapter 1, Division 4, Title 1, Government Code (commencing with Section 1090) and Article 2, Chapter 1, Part 3, Division 3, Title 2, Government Code (commencing with Section 13030).
A46: Subscribed and executed this 30th day of August, 2024 at Sacramento, California.
I52: KIM PHAN, Chief
I53: Service Transactions & Asset
I54: Reconciliation Section

Sheet 0042
I1: Page No : 3
A2: REPORT 18 – STATEMENT OF CHANGES IN CAPITAL ASSETS
A3: Department Name (2660)
A4: STATE HIGHWAY ACCOUNT FUND (0042)
A5: Fiscal Year 2023-24
A6: As of 06/30/2024
A7: Business Unit: | C7: 2660 - DEPARTMENT OF TRANSPORTATION | I7: Report ID: | J7: RPTGL075
A8: Fund: | C8: 0042 - STATE HIGHWAY ACCOUNT FUND | I8: Run Date: | J8: =TODAY() -> 45723
I9: Run Time: | J9: =NOW() -> 45723.508
A14: Account – Description | F14: Beginning Balance | G14: Additions | H14: Deductions | J14: Ending Balance
A15: Tangible Assets
A16: 2310 Land a | F16: =F46 -> 1.564042e+10 | G16: =G46 -> 81451063 | H16: =H46 -> 9765407.8 | J16: =F16+G16-H16 -> 1.5712106e+10
A17: 2321 Buildings | F17: 1.4156632e+09 | G17: 42601673 | J17: =F17+G17-H17 -> 1.4582649e+09
A18: 2331 Improvements Other Than Buildings | J18: =F18+G18-H18 -> 0
A19: 2341 Equipment | F19: 1.4379425e+09 | G19: 1.8596728e+08 | H19: 496553.53 | J19: =F19+G19-H19 -> 1.6234132e+09 | K19: Use CT11 and CT12 for CY Additions and Deductions (Absolute Values)
A20: 2350 Construction Work in Progress a | F20: 7.8459633e+09 | G20: 1.4755909e+09 | H20: 8.4688869e+08 | J20: =F20+G20-H20 -> 8.4746656e+09
A21: 2361 Infrastructure - Non Depreciable b | F21: 7.6082172e+10 | G21: 9.4013799e+08 | H21: 34997799 | J21: =F21+G21-H21 -> 7.6987312e+10
A23: Intangible Assets
A24: 2411 Computer Software - Amortizable | F24: 2.0057783e+08 | G24: 9250221.4 | J24: =F24+G24-H24 -> 2.0982805e+08
A25: 2412 Land Use Rights - Amortizable | J25: =F25+G25-H25 -> 0
A26: 2413 Patents, Copyrights, and Trademarks - Amortizable | F26: 374638.98 | J26: =F26+G26-H26 -> 374638.98
A27: 2414 Other Intangible Assets - Amortizable | J27: =F27+G27-H27 -> 0
A28: 2415 Right-to-Use Leased Land - Amortizable | J28: =F28+G28-H28 -> 0
A29: 2416 Right-to-Use Leased Buildings - Amortizable | F29: 91516505 | G29: 22460939 | H29: 7311305 | J29: =F29+G29-H29 -> 1.0666614e+08
A30: 2417 Right-to-Use Leased Equipment - Amortizable | J30: =F30+G30-H30 -> 0
A31: 2418 Right-to-Use Subscription-Based Information Technology Arrangements (SBITA) - Amortizable | F31: 8479526.8 | G31: 1696224.9 | H31: 2870666.8 | J31: =F31+G31-H31 -> 7305084.9
A32: 2422 Land Use Rights - Non-Amortizable | J32: =F32+G32-H32 -> 0
A35: Fund: | B35: 0042 | F35: =SUM(F16:F34) -> 1.0272311e+11 | G35: =SUM(G16:G34) -> 2.7591563e+09 | H35: =SUM(H16:H34) -> 9.0233042e+08 | J35: =SUM(J16:J34) -> 1.0457994e+11
A37: Note:
F38: Total | G38: Additions | H38: Deductions | J38: Total
A39: Land - Excess Land (2310-1000) | F39: 117804433 | G39: 2590694 | H39: 2963759 | J39: =F39+G39-H39 -> 117431368
A40: Land - Park Lease (2310-4001) | F40: 45936 | J40: =F40+G40-H40 -> 45936
A41: Land - Operational Dept (2310-5000) | F41: 62974266 | G41: 716392.57 | J41: =F41+G41-H41 -> 63690658
A42: Land - Operational Federal (2310-5001) | F42: 1991250 | J42: =F42+G42-H42 -> 1991250
A43: Land - Infrastructure Dept (2310-5900) | F43: 1.3467719e+10 | G43: 58321705 | H43: 6801648.8 | J43: =F43+G43-H43 -> 1.3519239e+10
A44: Land - Infrastructure Federal (2310-5901) | F44: 1.9898852e+09 | G44: 19822272 | J44: =F44+G44-H44 -> 2.0097075e+09
A46: a - Total Land | F46: =SUM(F39:F45) -> 1.564042e+10 | G46: =SUM(G39:G45) -> 81451063 | H46: =SUM(H39:I44) -> 9765407.8 | J46: =SUM(J39:J45) -> 1.5712106e+10
A48: b - Infrastructure only.
A50: c1 - The $2,963,759 in Excess Land (0042) Deductions amount is the result of the following:
D52: 1. Deduction amount is the result of routine disposal/sales transactions. | J52: 1805530
D53: 2. To reverse an erroneous transaction in the Excess Land Management System (ELMS). | J53: 851525
D54: 3. An adjustment to correct the value at acquisition (VTA) amount in ELMS. | J54: 306704
J55: =SUM(J52:J54) -> 2963759
A57: c2 - The $6,801,648.83 in Infrastructure Land (0042) Deductions represents FY 2023/2024 Relinquishments.
A59: d - The $846,888,690.13 in Construction Work in Progress' Deductions which represents FY 2023/2024's Transfer from CWIP to Non-Depreciable Infrastructure (Completed).
A62: e - The $34,997,798.94 in Non-Depreciable Infrastructure's (0042) Deductions represents FY 2023/2024 Relinquishments.
A64: f - The $7,311,305.00 in deductions for Right-to-Use Leased Buildings - Amortizable represents FY2023/2024 removal of lease asset at the end of the lease term.
A67: g - The $2,870,666.77 in deductions for Right-to-Use Subscription-Based Information Technology Arrangements (SBITA) - Amortizable represents FY2023/2024 removal of SBITA Asset at the End of the Subscription Term .
A69: h - See "Beginning Balance Differential Report".
A72: I certify (or declare) under penalty of perjury that the attached reports are true, accurate and complete, and were prepared following the applicable laws, regulations, policies, procedures, and instructions. I have not violated any of the provisions of Article 4, Chapter 1, Division 4, Title 1, Government Code (commencing with Section 1090) and Article 2, Chapter 1, Part 3, Division 3, Title 2, Government Code (commencing with Section 13030).
A77: Subscribed and executed this 30th day of August, 2024 at Sacramento, California.
I83: KIM PHAN, Chief
I84: Service Transactions & Asset
I85: Reconciliation Section

Sheet F0042 Diff
A1: Department of Transportation (2660)
A2: Statement of Changes in Capital Assets Group of Accounts - Report 18
A3: Beginning Balance Differential Report
A4: State Highway Account Fund (0042)
A5: As of June 30, 2024
K7: Breakdown of Difference:
E8: (1) | G8: (2) | I8: (3) | K8: (4) | M8: (5) | O8: (6) | Q8: (7) | S8: (8) | T8: (9) | V8: (10)
E9: Prior Year Ending Balance | G9: Current Year Beginning Balance | I9: Difference | K9: Assets unreported in the prior year | M9: Non-capitalizable assets reported as capital assets in the prior year | O9: Availability Payment Arrangements (GASB 94) | Q9: Other amounts that make up the difference (provide description): Per SCO guidance, applying % to District Project Survey % adjustment for Prior Year Expenditures. | S9: Other amounts that make up the difference (provide description): incorrect entry was made in current year balance | T9: Other amounts that make up the difference (provide description): Prior Year Fund to Fund Adjustment. | V9: Restatement Amount (should agree to the difference calculated)
A11: Tangible Assets
B12: Land (2310) | E12: 1.5634135e+10 | G12: 1.564042e+10 | I12: =G12-E12 -> 6285322.6 | Q12: 6285322.6 | V12: =SUM(K12:T12) -> 6285322.6
B13: Buildings (2321) | E13: 1.4156632e+09 | G13: 1.4156632e+09 | I13: =G13-E13 -> 0 | V13: =SUM(K13:T13) -> 0
B14: Improvements Other Than Buildings (2331) | I14: =G14-E14 -> 0 | V14: =SUM(K14:T14) -> 0
B15: Equipment (2341) | E15: 1.4379425e+09 | G15: 1.4379425e+09 | I15: =G15-E15 -> 0 | V15: =SUM(K15:T15) -> 0
B16: Construction Work in Progress (2350) | E16: 7.859028e+09 | G16: 7.8459633e+09 | I16: =G16-E16 -> -13064680 | Q16: 3027102.2 | T16: -16091782 | V16: =SUM(K16:T16) -> -13064680
B17: Infrastructure - Non Depreciable (2361) | E17: 7.5953678e+10 | G17: 7.6082172e+10 | I17: =G17-E17 -> 1.2849325e+08 | Q17: 1.2047809e+08 | T17: 8015163.2 | V17: =SUM(K17:T17) -> 1.2849325e+08
A18: Intangible Assets | V18: =SUM(K18:T18) -> 0
B19: Computer Software - Amortizable (2411) | E19: 2.0057783e+08 | G19: 2.0057783e+08 | I19: =G19-E19 -> 0 | V19: =SUM(K19:T19) -> 0
B20: Land Use Rights - Amortizable (2412) | V20: =SUM(K20:T20) -> 0
B21: Patents, Copyrights, and Trademarks - Amortizable (2413) | E21: 374638.98 | G21: 374638.98 | I21: =G21-E21 -> 0 | V21: =SUM(K21:T21) -> 0
B22: Other Intangible Assets - Amortizable (2414) | V22: =SUM(K22:T22) -> 0
B23: Right-to-Use Leased Land - Amortizable () | V23: =SUM(K23:T23) -> 0
B24: Right-to-Use Leased Buildings - Amortizable (2416) | E24: 91516505 | G24: 91516505 | I24: =G24-E24 -> 0 | V24: =SUM(K24:T24) -> 0
B25: Right-to-Use Leased Equipment - Amortizable | V25: =SUM(K25:T25) -> 0
B26: Right-to-Use Subscription-Based Information Technology Arrangements (SBITA) - Amortizable (2418) | E26: 8479526.8 | G26: 8479526.8 | I26: =G26-E26 -> 0 | S26: 0 | V26: =SUM(K26:T26) -> 0
B27: Land Use Rights - Non-Amortizable (2422) | V27: =SUM(K27:T27) -> 0
B28: Patents, Copyrights, and Trademarks - Non-Amortizable | I28: =G28-E28 -> 0 | V28: =SUM(K28:T28) -> 0
A29: Total | E29: =SUM(E12:E28) -> 1.026014e+11 | G29: =SUM(G12:G28) -> 1.0272311e+11 | I29: =SUM(I12:I28) -> 1.2171389e+08 | K29: =SUM(K12:K28) -> 0 | M29: =SUM(M12:M28) -> 0 | O29: =SUM(O12:O28) -> 0 | Q29: =SUM(Q12:Q28) -> 1.2979051e+08 | S29: =SUM(S12:S28) -> 0 | T29: =SUM(T12:T28) -> -8076618.6 | V29: =SUM(V12:V28) -> 1.2171389e+08
A32: Report Instructions:
A33: Col. 1 - | C33: Enter Ending Balance from Prior Year Report 18.
A34: Col. 2 - | C34: Enter Beginning Balance from Current Year Report 18.
A35: Col. 3 - | C35: Compute difference between current year beginning balance and prior year ending balance.
C36: Research posting and source documents to identify and explain the difference.
A37: Col. 4 - 9 | C37: Breakdown and categorize the differences in columns 4 to 9.
A38: Col. 10 - | C38: Compute the sum of columns 4 to 8. The amount should agree with the computed difference in column 3.

Sheet 0042 Revised
I1: Page No : 3
A2: REPORT 18 – STATEMENT OF CHANGES IN CAPITAL ASSETS
A3: Department Name (2660)
A4: STATE HIGHWAY ACCOUNT FUND (0042)
A5: Fiscal Year 2023-24 Revised 2/6/2025
A6: =[1]Date!A2 -> As of 06/30/2024
A7: Business Unit: | C7: 2660 - DEPARTMENT OF TRANSPORTATION | I7: Report ID: | J7: RPTGL075
A8: Fund: | C8: 0042 - STATE HIGHWAY ACCOUNT FUND | I8: Run Date: | J8: =TODAY() -> 45723
I9: Run Time: | J9: =NOW() -> 45723.508
A14: Account – Description | F14: Beginning Balance | G14: Additions | H14: Deductions | J14: Ending Balance
A15: Tangible Assets
A16: 2310 Land a | F16: 1.4969009e+10 | G16: 81451063 | H16: 9765407.8 | J16: =F16+G16-H16 -> 1.5040695e+10
A17: 2321 Buildings | F17: 1.4156632e+09 | G17: 42601673 | J17: =F17+G17-H17 -> 1.4582649e+09
A18: 2331 Improvements Other Than Buildings | J18: =F18+G18-H18 -> 0
A19: 2341 Equipment | F19: 1.4379425e+09 | G19: 1.8596728e+08 | H19: 496553.53 | J19: =F19+G19-H19 -> 1.6234132e+09
A20: 2350 Construction Work in Progress a | F20: 7.8459633e+09 | G20: 1.4755909e+09 | H20: 8.4688869e+08 | J20: =F20+G20-H20 -> 8.4746656e+09
A21: 2361 Infrastructure - Non Depreciable b | F21: 7.6753583e+10 | G21: 9.4013799e+08 | H21: 34997799 | J21: =F21+G21-H21 -> 7.7658723e+10
A23: Intangible Assets
A24: 2411 Computer Software - Amortizable | F24: 2.0057783e+08 | G24: 9250221.4 | J24: =F24+G24-H24 -> 2.0982805e+08
A25: 2412 Land Use Rights - Amortizable | J25: =F25+G25-H25 -> 0
A26: 2413 Patents, Copyrights, and Trademarks - Amortizable | F26: 374638.98 | J26: =F26+G26-H26 -> 374638.98
A27: 2414 Other Intangible Assets - Amortizable | J27: =F27+G27-H27 -> 0
A28: 2415 Right-to-Use Leased Land - Amortizable | J28: =F28+G28-H28 -> 0
A29: 2416 Right-to-Use Leased Buildings - Amortizable | F29: 91516505 | G29: 22460939 | H29: 7311305 | J29: =F29+G29-H29 -> 1.0666614e+08
A30: 2417 Right-to-Use Leased Equipment - Amortizable | J30: =F30+G30-H30 -> 0
A31: 2418 Right-to-Use Subscription-Based Information Technology Arrangements (SBITA) - Amortizable | F31: 8479526.8 | G31: 1696224.9 | H31: 2870666.8 | J31: =F31+G31-H31 -> 7305084.9
A32: 2422 Land Use Rights - Non-Amortizable | J32: =F32+G32-H32 -> 0
A35: Fund: | B35: 0042 | F35: =SUM(F16:F34) -> 1.0272311e+11 | G35: =SUM(G16:G34) -> 2.7591563e+09 | H35: =SUM(H16:H34) -> 9.0233042e+08 | J35: =SUM(J16:J34) -> 1.0457994e+11
A37: Note:
F38: Total | G38: Additions | H38: Deductions | J38: Total
A39: Land - Excess Land (2310-1000) | F39: 117804433 | G39: 2590694 | H39: 2963759 | J39: =F39+G39-H39 -> 117431368
A40: Land - Park Lease (2310-4001) | F40: 45936 | J40: =F40+G40-H40 -> 45936
A41: Land - Operational Dept (2310-5000) | F41: 62974266 | G41: 716392.57 | J41: =F41+G41-H41 -> 63690658
A42: Land - Operational Federal (2310-5001) | F42: 1991250 | J42: =F42+G42-H42 -> 1991250
A43: Land - Infrastructure Dept (2310-5900) | F43: 1.3266296e+10 | G43: 58321705 | H43: 6801648.8 | J43: =F43+G43-H43 -> 1.3317816e+10
A44: Land - Infrastructure Federal (2310-5901) | F44: 1.5198974e+09 | G44: 19822272 | J44: =F44+G44-H44 -> 1.5397197e+09
A46: a - Total Land | F46: =SUM(F39:F45) -> 1.4969009e+10 | G46: =SUM(G39:G45) -> 81451063 | H46: =SUM(H39:I44) -> 9765407.8 | J46: =SUM(J39:J45) -> 1.5040695e+10
A48: b - Infrastructure only.
A50: c1 - The $2,963,759 in Excess Land (0042) Deductions amount is the result of the following:
D52: 1. Deduction amount is the result of routine disposal/sales transactions. | J52: 1805530
D53: 2. To reverse an erroneous transaction in the Excess Land Management System (ELMS). | J53: 851525
D54: 3. An adjustment to correct the value at acquisition (VTA) amount in ELMS. | J54: 306704
J55: =SUM(J52:J54) -> 2963759
A57: c2 - The $6,801,648.83 in Infrastructure Land (0042) Deductions represents FY 2023/2024 Relinquishments.
A59: d - The $846,888,690.13 in Construction Work in Progress' Deductions which represents FY 2023/2024's Transfer from CWIP to Non-Depreciable Infrastructure (Completed).
A62: e - The $34,997,798.94 in Non-Depreciable Infrastructure's (0042) Deductions represents FY 2023/2024 Relinquishments.
A64: f - The $7,311,305.00 in deductions for Right-to-Use Leased Buildings - Amortizable represents FY2023/2024 removal of lease asset at the end of the lease term.
A67: g - The $2,870,666.77 in deductions for Right-to-Use Subscription-Based Information Technology Arrangements (SBITA) - Amortizable represents FY2023/2024 removal of SBITA Asset at the End of the Subscription Term .
A69: h - See "Beginning Balance Differential Report".
A71: i - Per SCO, the $671,411,077.68 ($201,423,323.30 State & $469,987,754.38 Federal) GASB94 APA is reclassified from Infrastructure Land to Infrastructure - Non Depreciable.
A73: I certify (or declare) under penalty of perjury that the attached reports are true, accurate and complete, and were prepared following the applicable laws, regulations, policies, procedures, and instructions. I have not violated any of the provisions of Article 4, Chapter 1, Division 4, Title 1, Government Code (commencing with Section 1090) and Article 2, Chapter 1, Part 3, Division 3, Title 2, Government Code (commencing with Section 13030).
A78: =[1]Date!A10 -> Subscribed and executed this 30th day of August, 2024 at Sacramento, California.
I84: KIM PHAN, Chief
I85: Service Transactions & Asset
I86: Reconciliation Section

Sheet F0042 Diff Revised
A1: Department of Transportation (2660)
A2: Statement of Changes in Capital Assets Group of Accounts - Report 18
A3: Beginning Balance Differential Report
A4: State Highway Account Fund (0042)
A5: As of June 30, 2024 Revised 2/6/2025
K7: Breakdown of Difference:
E8: (1) | G8: (2) | I8: (3) | K8: (4) | M8: (5) | O8: (6) | Q8: (7) | S8: (8) | T8: (9) | V8: (10)
E9: Prior Year Ending Balance | G9: Current Year Beginning Balance | I9: Difference | K9: Assets unreported in the prior year | M9: Non-capitalizable assets reported as capital assets in the prior year | O9: Availability Payment Arrangements (GASB 94) | Q9: Other amounts that make up the difference (provide description): Per SCO guidance, applying % to District Project Survey % adjustment for Prior Year Expenditures. | S9: Other amounts that make up the difference (provide description): incorrect entry was made in current year balance | T9: Other amounts that make up the difference (provide description): Prior Year Fund to Fund Adjustment. | V9: Restatement Amount (should agree to the difference calculated)
A11: Tangible Assets
B12: Land (2310) | E12: 1.4962724e+10 | G12: 1.4969009e+10 | I12: =G12-E12 -> 6285322.6 | Q12: 6285322.6 | V12: =SUM(K12:T12) -> 6285322.6
B13: Buildings (2321) | E13: 1.4156632e+09 | G13: 1.4156632e+09 | I13: =G13-E13 -> 0 | V13: =SUM(K13:T13) -> 0
B14: Improvements Other Than Buildings (2331) | I14: =G14-E14 -> 0 | V14: =SUM(K14:T14) -> 0
B15: Equipment (2341) | E15: 1.4379425e+09 | G15: 1.4379425e+09 | I15: =G15-E15 -> 0 | V15: =SUM(K15:T15) -> 0
B16: Construction Work in Progress (2350) | E16: 7.859028e+09 | G16: 7.8459633e+09 | I16: =G16-E16 -> -13064680 | Q16: 3027102.2 | T16: -16091782 | V16: =SUM(K16:T16) -> -13064680
B17: Infrastructure - Non Depreciable (2361) | E17: 7.6625089e+10 | G17: 7.6753583e+10 | I17: =G17-E17 -> 1.2849325e+08 | Q17: 1.2047809e+08 | T17: 8015163.2 | V17: =SUM(K17:T17) -> 1.2849325e+08
A18: Intangible Assets | V18: =SUM(K18:T18) -> 0
B19: Computer Software - Amortizable (2411) | E19: 2.0057783e+08 | G19: 2.0057783e+08 | I19: =G19-E19 -> 0 | V19: =SUM(K19:T19) -> 0
B20: Land Use Rights - Amortizable (2412) | V20: =SUM(K20:T20) -> 0
B21: Patents, Copyrights, and Trademarks - Amortizable (2413) | E21: 374638.98 | G21: 374638.98 | I21: =G21-E21 -> 0 | V21: =SUM(K21:T21) -> 0
B22: Other Intangible Assets - Amortizable (2414) | V22: =SUM(K22:T22) -> 0
B23: Right-to-Use Leased Land - Amortizable () | V23: =SUM(K23:T23) -> 0
B24: Right-to-Use Leased Buildings - Amortizable (2416) | E24: 91516505 | G24: 91516505 | I24: =G24-E24 -> 0 | V24: =SUM(K24:T24) -> 0
B25: Right-to-Use Leased Equipment - Amortizable | V25: =SUM(K25:T25) -> 0
B26: Right-to-Use Subscription-Based Information Technology Arrangements (SBITA) - Amortizable (2418) | E26: 8479526.8 | G26: 8479526.8 | I26: =G26-E26 -> 0 | S26: 0 | V26: =SUM(K26:T26) -> 0
B27: Land Use Rights - Non-Amortizable (2422) | V27: =SUM(K27:T27) -> 0
B28: Patents, Copyrights, and Trademarks - Non-Amortizable | I28: =G28-E28 -> 0 | V28: =SUM(K28:T28) -> 0
A29: Total | E29: =SUM(E12:E28) -> 1.026014e+11 | G29: =SUM(G12:G28) -> 1.0272311e+11 | I29: =SUM(I12:I28) -> 1.2171389e+08 | K29: =SUM(K12:K28) -> 0 | M29: =SUM(M12:M28) -> 0 | O29: =SUM(O12:O28) -> 0 | Q29: =SUM(Q12:Q28) -> 1.2979051e+08 | S29: =SUM(S12:S28) -> 0 | T29: =SUM(T12:T28) -> -8076618.6 | V29: =SUM(V12:V28) -> 1.2171389e+08
A32: Report Instructions:
A33: Col. 1 - | C33: Enter Ending Balance from Prior Year Report 18.
A34: Col. 2 - | C34: Enter Beginning Balance from Current Year Report 18.
A35: Col. 3 - | C35: Compute difference between current year beginning balance and prior year ending balance.
C36: Research posting and source documents to identify and explain the difference.
A37: Col. 4 - 9 | C37: Breakdown and categorize the differences in columns 4 to 9.
A38: Col. 10 - | C38: Compute the sum of columns 4 to 8. The amount should agree with the computed difference in column 3.

Sheet 0046
I1: Page No : 4
A2: REPORT 18 – STATEMENT OF CHANGES IN CAPITAL ASSETS
A3: Department Name (2660)
A4: PUBLIC TRANSPORTATION ACCOUNT (0046)
A5: Fiscal Year 2023-24
A6: As of 06/30/2024
A7: Business Unit: | C7: 2660 - DEPARTMENT OF TRANSPORTATION | I7: Report ID: | J7: RPTGL075
A8: Fund: | C8: 0046 - PUBLIC TRANSPORTATION ACCOUNT | I8: Run Date: | J8: =TODAY() -> 45723
I9: Run Time: | J9: =NOW() -> 45723.508
A14: Account – Description | F14: Beginning Balance | G14: Additions | H14: Deductions | J14: Ending Balance
A15: Tangible Assets
A16: 2310 Land a | J16: =F16+G16-H16 -> 0
A17: 2321 Buildings | J17: =F17+G17-H17 -> 0
A18: 2331 Improvements Other Than Buildings | J18: =F18+G18-H18 -> 0
A19: 2341 Equipment | F19: 40064932 | G19: 1267363.2 | J19: =F19+G19-H19 -> 41332295
A20: 2350 Construction Work in Progress a | J20: =F20+G20-H20 -> 0
A21: 2361 Infrastructure - Non Depreciable a | F21: 7120136.5 | J21: =F21+G21-H21 -> 7120136.5
A23: Intangible Assets
A24: 2411 Computer Software - Amortizable | F24: 2193840.4 | G24: 432271.5 | J24: =F24+G24-H24 -> 2626111.9
A25: 2412 Land Use Rights - Amortizable | J25: =F25+G25-H25 -> 0
A26: 2413 Patents, Copyrights, and Trademarks - Amortizable | J26: =F26+G26-H26 -> 0
A27: 2414 Other Intangible Assets - Amortizable | J27: =F27+G27-H27 -> 0
A28: 2415 Right-to-Use Leased Land - Amortizable | J28: =F28+G28-H28 -> 0
A29: 2416 Right-to-Use Leased Buildings - Amortizable | J29: =F29+G29-H29 -> 0
A30: 2417 Right-to-Use Leased Equipment - Amortizable | F30: 17089708 | J30: =F30+G30-H30 -> 17089708
A31: 2418 Right-to-Use Subscription-Based Information Technology Arrangements (SBITA) - Amortizable | F31: 135390.6 | G31: 27869.276 | H31: 45732.922 | J31: =F31+G31-H31 -> 117526.95
A32: 2422 Land Use Rights - Non-Amortizable | J32: =F32+G32-H32 -> 0
A35: Fund: | B35: 0046 | F35: =SUM(F16:F34) -> 66604007 | G35: =SUM(G16:G33) -> 1727503.9 | H35: =SUM(H16:H33) -> 45732.922 | J35: =SUM(J16:J33) -> 68285778
A37: Note:
A38: a - Infrastructure only.
A41: I certify (or declare) under penalty of perjury that the attached reports are true, accurate and complete, and were prepared following the applicable laws, regulations, policies, procedures, and instructions. I have not violated any of the provisions of Article 4, Chapter 1, Division 4, Title 1, Government Code (commencing with Section 1090) and Article 2, Chapter 1, Part 3, Division 3, Title 2, Government Code (commencing with Section 13030).
A46: Subscribed and executed this 30th day of August, 2024 at Sacramento, California.
I52: KIM PHAN, Chief
I53: Service Transactions & Asset
I54: Reconciliation Section

Sheet 0183
I1: Page No : 5
A2: REPORT 18 – STATEMENT OF CHANGES IN CAPITAL ASSETS
A3: Department Name (2660)
A4: ENVIRONMENTAL ENHANCEMENT AND MITIGATION (0183)
A5: Fiscal Year 2023-24
A6: As of 06/30/2024
A7: Business Unit: | C7: 2660 - DEPARTMENT OF TRANSPORTATION | I7: Report ID: | J7: RPTGL075
A8: Fund: | C8: 0183 - ENVIRONMENTAL ENHANCEMENT AND MITIGATION | I8: Run Date: | J8: =TODAY() -> 45723
I9: Run Time: | J9: =NOW() -> 45723.508
A14: Account – Description | F14: Beginning Balance | G14: Additions | H14: Deductions | J14: Ending Balance
A15: Tangible Assets
A16: 2310 Land a | J16: =F16+G16-H16 -> 0
A17: 2321 Buildings | J17: =F17+G17-H17 -> 0
A18: 2331 Improvements Other Than Buildings | J18: =F18+G18-H18 -> 0
A19: 2341 Equipment | J19: =F19+G19-H19 -> 0
A20: 2350 Construction Work in Progress a | F20: 61012094 | J20: =F20+G20-H20 -> 61012094
A21: 2361 Infrastructure - Non Depreciable a | F21: 1657162.1 | J21: =F21+G21-H21 -> 1657162.1
A23: Intangible Assets
A24: 2411 Computer Software - Amortizable | J24: =F24+G24-H24 -> 0
A25: 2412 Land Use Rights - Amortizable | J25: =F25+G25-H25 -> 0
A26: 2413 Patents, Copyrights, and Trademarks - Amortizable | J26: =F26+G26-H26 -> 0
A27: 2414 Other Intangible Assets - Amortizable | J27: =F27+G27-H27 -> 0
A28: 2415 Right-to-Use Leased Land - Amortizable | J28: =F28+G28-H28 -> 0
A29: 2416 Right-to-Use Leased Buildings - Amortizable | J29: =F29+G29-H29 -> 0
A30: 2417 Right-to-Use Leased Equipment - Amortizable | J30: =F30+G30-H30 -> 0
A31: 2418 Right-to-Use Subscription-Based Information Technology Arrangements (SBITA) - Amortizable | J31: =F31+G31-H31 -> 0
A32: 2422 Land Use Rights - Non-Amortizable | J32: =F32+G32-H32 -> 0
A35: Fund: | B35: 0183 | F35: =SUM(F16:F34) -> 62669256 | G35: =SUM(G16:G34) -> 0 | H35: =SUM(H16:H34) -> 0 | J35: =SUM(J16:J34) -> 62669256
A37: Note:
A38: a - Infrastructure only.
A40: I certify (or declare) under penalty of perjury that the attached reports are true, accurate and complete, and were prepared following the applicable laws, regulations, policies, procedures, and instructions. I have not violated any of the provisions of Article 4, Chapter 1, Division 4, Title 1, Government Code (commencing with Section 1090) and Article 2, Chapter 1, Part 3, Division 3, Title 2, Government Code (commencing with Section 13030).
A46: Subscribed and executed this 30th day of August, 2024 at Sacramento, California.
I55: KIM PHAN, Chief
I56: Service Transactions & Asset
I57: Reconciliation Section

Sheet 0523
I1: Page No : 6
A2: REPORT 18 – STATEMENT OF CHANGES IN CAPITAL ASSETS
A3: Department Name (2660)
A4: EAST BAY STATE BUILDING AUTHORITY FUND (0523)
A5: Fiscal Year 2023-24
A6: As of 06/30/2024
A7: Business Unit: | C7: 2660 - DEPARTMENT OF TRANSPORTATION | I7: Report ID: | J7: RPTGL075
A8: Fund: | C8: 0523 EAST BAY STATE BUILDING AUTHORITY FUND | I8: Run Date: | J8: =TODAY() -> 45723
I9: Run Time: | J9: =NOW() -> 45723.508
A14: Account – Description | F14: Beginning Balance | G14: Additions | H14: Deductions | J14: Ending Balance
A15: Tangible Assets
A16: 2310 Land a | F16: 8000000 | J16: =F16+G16-H16 -> 8000000
A17: 2321 Buildings | F17: 2.8527591e+08 | J17: =F17+G17-H17 -> 2.8527591e+08
A18: 2331 Improvements Other Than Buildings | J18: =F18+G18-H18 -> 0
A19: 2341 Equipment | J19: =F19+G19-H19 -> 0
A20: 2350 Construction Work in Progress a | J20: =F20+G20-H20 -> 0
A21: 2361 Infrastructure - Non Depreciable a | J21: =F21+G21-H21 -> 0
A23: Intangible Assets
A24: 2411 Computer Software - Amortizable | J24: =F24+G24-H24 -> 0
A25: 2412 Land Use Rights - Amortizable | J25: =F25+G25-H25 -> 0
A26: 2413 Patents, Copyrights, and Trademarks - Amortizable | J26: =F26+G26-H26 -> 0
A27: 2414 Other Intangible Assets - Amortizable | J27: =F27+G27-H27 -> 0
A28: 2415 Right-to-Use Leased Land - Amortizable | J28: =F28+G28-H28 -> 0
A29: 2416 Right-to-Use Leased Buildings - Amortizable | J29: =F29+G29-H29 -> 0
A30: 2417 Right-to-Use Leased Equipment - Amortizable | J30: =F30+G30-H30 -> 0
A31: 2418 Right-to-Use Subscription-Based Information Technology Arrangements (SBITA) - Amortizable | J31: =F31+G31-H31 -> 0
A32: 2422 Land Use Rights - Non-Amortizable | J32: =F32+G32-H32 -> 0
A35: Fund: | B35: 0523 | F35: =SUM(F16:F34) -> 2.9327591e+08 | G35: =SUM(G16:G34) -> 0 | H35: =SUM(H16:H34) -> 0 | J35: =SUM(J16:J34) -> 2.9327591e+08
A37: Note:
A38: a - Infrastructure only.
A40: I certify (or declare) under penalty of perjury that the attached reports are true, accurate and complete, and were prepared following the applicable laws, regulations, policies, procedures, and instructions. I have not violated any of the provisions of Article 4, Chapter 1, Division 4, Title 1, Government Code (commencing with Section 1090) and Article 2, Chapter 1, Part 3, Division 3, Title 2, Government Code (commencing with Section 13030).
A46: Subscribed and executed this 30th day of August, 2024 at Sacramento, California.
I52: KIM PHAN, Chief
I53: Service Transactions & Asset
I54: Reconciliation Section

Sheet 0541
I1: Page No : 7
A2: REPORT 18 – STATEMENT OF CHANGES IN CAPITAL ASSETS
A3: Department Name (2660)
A4: SAN BERNARDINO STATE BUILDING AUTHORITY (0541)
A5: Fiscal Year 2023-24
A6: As of 06/30/2024
A7: Business Unit: | C7: 2660 - DEPARTMENT OF TRANSPORTATION | I7: Report ID: | J7: RPTGL075
A8: Fund: | C8: 0541 SAN BERNARDINO STATE BUILDING AUTHORITY | I8: Run Date: | J8: =TODAY() -> 45723
I9: Run Time: | J9: =NOW() -> 45723.508
A14: Account – Description | F14: Beginning Balance | G14: Additions | H14: Deductions | J14: Ending Balance
A15: Tangible Assets
A16: 2310 Land a | J16: =F16+G16-H16 -> 0
A17: 2321 Buildings | F17: 56772761 | J17: =F17+G17-H17 -> 56772761
A18: 2331 Improvements Other Than Buildings | J18: =F18+G18-H18 -> 0
A19: 2341 Equipment | J19: =F19+G19-H19 -> 0
A20: 2350 Construction Work in Progress a | J20: =F20+G20-H20 -> 0
A21: 2361 Infrastructure - Non Depreciable a | J21: =F21+G21-H21 -> 0
A23: Intangible Assets
A24: 2411 Computer Software - Amortizable | J24: =F24+G24-H24 -> 0
A25: 2412 Land Use Rights - Amortizable | J25: =F25+G25-H25 -> 0
A26: 2413 Patents, Copyrights, and Trademarks - Amortizable | J26: =F26+G26-H26 -> 0
A27: 2414 Other Intangible Assets - Amortizable | J27: =F27+G27-H27 -> 0
A28: 2415 Right-to-Use Leased Land - Amortizable | J28: =F28+G28-H28 -> 0
A29: 2416 Right-to-Use Leased Buildings - Amortizable | J29: =F29+G29-H29 -> 0
A30: 2417 Right-to-Use Leased Equipment - Amortizable | J30: =F30+G30-H30 -> 0
A31: 2418 Right-to-Use Subscription-Based Information Technology Arrangements (SBITA) - Amortizable | J31: =F31+G31-H31 -> 0
A32: 2422 Land Use Rights - Non-Amortizable | J32: =F32+G32-H32 -> 0
A35: Fund: | B35: 0541 | F35: =SUM(F16:F34) -> 56772761 | G35: =SUM(G16:G34) -> 0 | H35: =SUM(H16:H34) -> 0 | J35: =SUM(J16:J34) -> 56772761
A37: Note:
A38: a - Infrastructure only.
A40: I certify (or declare) under penalty of perjury that the attached reports are true, accurate and complete, and were prepared following the applicable laws, regulations, policies, procedures, and instructions. I have not violated any of the provisions of Article 4, Chapter 1, Division 4, Title 1, Government Code (commencing with Section 1090) and Article 2, Chapter 1, Part 3, Division 3, Title 2, Government Code (commencing with Section 13030).
A46: Subscribed and executed this 30th day of August, 2024 at Sacramento, California.
I52: KIM PHAN, Chief
I53: Service Transactions & Asset
I54: Reconciliation Section

Sheet 0653
I1: Page No : 8
A2: REPORT 18 – STATEMENT OF CHANGES IN CAPITAL ASSETS
A3: Department Name (2660)
A4: SEISMIC RETROFIT BOND FUND OF 1996 (0653)
A5: Fiscal Year 2023-24
A6: As of 06/30/2024
A7: Business Unit: | C7: 2660 - DEPARTMENT OF TRANSPORTATION | I7: Report ID: | J7: RPTGL075
A8: Fund: | C8: 0653 SEISMIC RETROFIT BOND FUND OF 1996 | I8: Run Date: | J8: =TODAY() -> 45723
I9: Run Time: | J9: =NOW() -> 45723.508
A14: Account – Description | F14: Beginning Balance | G14: Additions | H14: Deductions | J14: Ending Balance
A15: Tangible Assets
A16: 2310 Land a | F16: 300093.59 | J16: =F16+G16-H16 -> 300093.59
A17: 2321 Buildings | F17: 13055910 | J17: =F17+G17-H17 -> 13055910
A18: 2331 Improvements Other Than Buildings | J18: =F18+G18-H18 -> 0
A19: 2341 Equipment | F19: 267582.18 | J19: =F19+G19-H19 -> 267582.18
A20: 2350 Construction Work in Progress a | F20: 1743959.2 | J20: =F20+G20-H20 -> 1743959.2
A21: 2361 Infrastructure - Non Depreciable a | F21: 61523709 | J21: =F21+G21-H21 -> 61523709
A23: Intangible Assets
A24: 2411 Computer Software - Amortizable | J24: =F24+G24-H24 -> 0
A25: 2412 Land Use Rights - Amortizable | J25: =F25+G25-H25 -> 0
A26: 2413 Patents, Copyrights, and Trademarks - Amortizable | J26: =F26+G26-H26 -> 0
A27: 2414 Other Intangible Assets - Amortizable | J27: =F27+G27-H27 -> 0
A28: 2415 Right-to-Use Leased Land - Amortizable | J28: =F28+G28-H28 -> 0
A29: 2416 Right-to-Use Leased Buildings - Amortizable | J29: =F29+G29-H29 -> 0
A30: 2417 Right-to-Use Leased Equipment - Amortizable | J30: =F30+G30-H30 -> 0
A31: 2418 Right-to-Use Subscription-Based Information Technology Arrangements (SBITA) - Amortizable | J31: =F31+G31-H31 -> 0
A32: 2422 Land Use Rights - Non-Amortizable | J32: =F32+G32-H32 -> 0
A35: Fund: | B35: 0653 | F35: =SUM(F16:F34) -> 76891254 | G35: =SUM(G16:G34) -> 0 | H35: =SUM(H16:H34) -> 0 | J35: =SUM(J16:J34) -> 76891254
A37: Note:
A38: a - Infrastructure only.
A40: I certify (or declare) under penalty of perjury that the attached reports are true, accurate and complete, and were prepared following the applicable laws, regulations, policies, procedures, and instructions. I have not violated any of the provisions of Article 4, Chapter 1, Division 4, Title 1, Government Code (commencing with Section 1090) and Article 2, Chapter 1, Part 3, Division 3, Title 2, Government Code (commencing with Section 13030).
A46: Subscribed and executed this 30th day of August, 2024 at Sacramento, California.
I52: KIM PHAN, Chief
I53: Service Transactions & Asset
I54: Reconciliation Section

Sheet 0673
I1: Page No : 9
A2: REPORT 18 – STATEMENT OF CHANGES IN CAPITAL ASSETS
A3: Department Name (2660)
A4: PASSENGER EQUIPMENT ACQUISITION FUND (0673)
A5: Fiscal Year 2023-24
A6: As of 06/30/2024
A7: Business Unit: | C7: 2660 - DEPARTMENT OF TRANSPORTATION | I7: Report ID: | J7: RPTGL075
A8: Fund: | C8: 0673 PASSENGER EQUIPMENT ACQUISITION FUND | I8: Run Date: | J8: =TODAY() -> 45723
I9: Run Time: | J9: =NOW() -> 45723.508
A14: Account – Description | F14: Beginning Balance | G14: Additions | H14: Deductions | J14: Ending Balance
A15: Tangible Assets
A16: 2310 Land a | J16: =F16+G16-H16 -> 0
A17: 2321 Buildings | J17: =F17+G17-H17 -> 0
A18: 2331 Improvements Other Than Buildings | J18: =F18+G18-H18 -> 0
A19: 2341 Equipment | F19: 6674000 | J19: =F19+G19-H19 -> 6674000
A20: 2350 Construction Work in Progress a | J20: =F20+G20-H20 -> 0
A21: 2361 Infrastructure - Non Depreciable a | J21: =F21+G21-H21 -> 0
A23: Intangible Assets
A24: 2411 Computer Software - Amortizable | J24: =F24+G24-H24 -> 0
A25: 2412 Land Use Rights - Amortizable | J25: =F25+G25-H25 -> 0
A26: 2413 Patents, Copyrights, and Trademarks - Amortizable | J26: =F26+G26-H26 -> 0
A27: 2414 Other Intangible Assets - Amortizable | J27: =F27+G27-H27 -> 0
A28: 2415 Right-to-Use Leased Land - Amortizable | J28: =F28+G28-H28 -> 0
A29: 2416 Right-to-Use Leased Buildings - Amortizable | J29: =F29+G29-H29 -> 0
A30: 2417 Right-to-Use Leased Equipment - Amortizable | J30: =F30+G30-H30 -> 0
A31: 2418 Right-to-Use Subscription-Based Information Technology Arrangements (SBITA) - Amortizable | J31: =F31+G31-H31 -> 0
A32: 2422 Land Use Rights - Non-Amortizable | J32: =F32+G32-H32 -> 0
A35: Fund: | B35: 0673 | F35: =SUM(F16:F34) -> 6674000 | G35: =SUM(G16:G34) -> 0 | H35: =SUM(H16:H34) -> 0 | J35: =SUM(J16:J34) -> 6674000
A37: Note:
A38: a - Infrastructure only.
A40: I certify (or declare) under penalty of perjury that the attached reports are true, accurate and complete, and were prepared following the applicable laws, regulations, policies, procedures, and instructions. I have not violated any of the provisions of Article 4, Chapter 1, Division 4, Title 1, Government Code (commencing with Section 1090) and Article 2, Chapter 1, Part 3, Division 3, Title 2, Government Code (commencing with Section 13030).
A46: Subscribed and executed this 30th day of August, 2024 at Sacramento, California.
I52: KIM PHAN, Chief
I53: Service Transactions & Asset
I54: Reconciliation Section

Sheet 0703
I1: Page No : 10
A2: REPORT 18 – STATEMENT OF CHANGES IN CAPITAL ASSETS
A3: Department Name (2660)
A4: PROPOSITION 116 RAIL BONDS (0703)
A5: Fiscal Year 2023-24
A6: As of 06/30/2024
A7: Business Unit: | C7: 2660 - DEPARTMENT OF TRANSPORTATION | I7: Report ID: | J7: RPTGL075
A8: Fund: | C8: 0703 PROPOSITION 116 RAIL BONDS | I8: Run Date: | J8: =TODAY() -> 45723
I9: Run Time: | J9: =NOW() -> 45723.508
A14: Account – Description | F14: Beginning Balance | G14: Additions | H14: Deductions | J14: Ending Balance
A15: Tangible Assets
A16: 2310 Land a | J16: =F16+G16-H16 -> 0
A17: 2321 Buildings | J17: =F17+G17-H17 -> 0
A18: 2331 Improvements Other Than Buildings | J18: =F18+G18-H18 -> 0
A19: 2341 Equipment | F19: 70479745 | J19: =F19+G19-H19 -> 70479745
A20: 2350 Construction Work in Progress a | J20: =F20+G20-H20 -> 0
A21: 2361 Infrastructure - Non Depreciable a | J21: =F21+G21-H21 -> 0
A23: Intangible Assets
A24: 2411 Computer Software - Amortizable | J24: =F24+G24-H24 -> 0
A25: 2412 Land Use Rights - Amortizable | J25: =F25+G25-H25 -> 0
A26: 2413 Patents, Copyrights, and Trademarks - Amortizable | J26: =F26+G26-H26 -> 0
A27: 2414 Other Intangible Assets - Amortizable | J27: =F27+G27-H27 -> 0
A28: 2415 Right-to-Use Leased Land - Amortizable | J28: =F28+G28-H28 -> 0
A29: 2416 Right-to-Use Leased Buildings - Amortizable | J29: =F29+G29-H29 -> 0
A30: 2417 Right-to-Use Leased Equipment - Amortizable | J30: =F30+G30-H30 -> 0
A31: 2418 Right-to-Use Subscription-Based Information Technology Arrangements (SBITA) - Amortizable | J31: =F31+G31-H31 -> 0
A32: 2422 Land Use Rights - Non-Amortizable | J32: =F32+G32-H32 -> 0
A35: Fund: | B35: 0703 | F35: =SUM(F16:F34) -> 70479745 | G35: =SUM(G16:G34) -> 0 | H35: =SUM(H16:H34) -> 0 | J35: =SUM(J16:J34) -> 70479745
A37: Note:
A38: a - Infrastructure only.
A40: I certify (or declare) under penalty of perjury that the attached reports are true, accurate and complete, and were prepared following the applicable laws, regulations, policies, procedures, and instructions. I have not violated any of the provisions of Article 4, Chapter 1, Division 4, Title 1, Government Code (commencing with Section 1090) and Article 2, Chapter 1, Part 3, Division 3, Title 2, Government Code (commencing with Section 13030).
A46: Subscribed and executed this 30th day of August, 2024 at Sacramento, California.
I52: KIM PHAN, Chief
I53: Service Transactions & Asset
I54: Reconciliation Section

Sheet 0756
I1: Page No : 11
A2: REPORT 18 – STATEMENT OF CHANGES IN CAPITAL ASSETS
A3: Department Name (2660)
A4: PASSENGER RAIL BOND FUND - PROPOSITION 108 (0756)
A5: Fiscal Year 2023-24
A6: As of 06/30/2024
A7: Business Unit: | C7: 2660 - DEPARTMENT OF TRANSPORTATION | I7: Report ID: | J7: RPTGL075
A8: Fund: | C8: 0756 PASSENGER RAIL BOND FUND - PROPOSITION 108 | I8: Run Date: | J8: =TODAY() -> 45723
I9: Run Time: | J9: =NOW() -> 45723.508
A14: Account – Description | F14: Beginning Balance | G14: Additions | H14: Deductions | J14: Ending Balance
A15: Tangible Assets
A16: 2310 Land a | J16: =F16+G16-H16 -> 0
A17: 2321 Buildings | J17: =F17+G17-H17 -> 0
A18: 2331 Improvements Other Than Buildings | J18: =F18+G18-H18 -> 0
A19: 2341 Equipment | F19: 1.0175604e+08 | J19: =F19+G19-H19 -> 1.0175604e+08
A20: 2350 Construction Work in Progress a | J20: =F20+G20-H20 -> 0
A21: 2361 Infrastructure - Non Depreciable a | J21: =F21+G21-H21 -> 0
A23: Intangible Assets
A24: 2411 Computer Software - Amortizable | J24: =F24+G24-H24 -> 0
A25: 2412 Land Use Rights - Amortizable | J25: =F25+G25-H25 -> 0
A26: 2413 Patents, Copyrights, and Trademarks - Amortizable | J26: =F26+G26-H26 -> 0
A27: 2414 Other Intangible Assets - Amortizable | J27: =F27+G27-H27 -> 0
A28: 2415 Right-to-Use Leased Land - Amortizable | J28: =F28+G28-H28 -> 0
A29: 2416 Right-to-Use Leased Buildings - Amortizable | J29: =F29+G29-H29 -> 0
A30: 2417 Right-to-Use Leased Equipment - Amortizable | J30: =F30+G30-H30 -> 0
A31: 2418 Right-to-Use Subscription-Based Information Technology Arrangements (SBITA) - Amortizable | J31: =F31+G31-H31 -> 0
A32: 2422 Land Use Rights - Non-Amortizable | J32: =F32+G32-H32 -> 0
A35: Fund: | B35: 0756 | F35: =SUM(F16:F34) -> 1.0175604e+08 | G35: =SUM(G16:G34) -> 0 | H35: =SUM(H16:H34) -> 0 | J35: =SUM(J16:J34) -> 1.0175604e+08
A37: Note:
A38: a - Infrastructure only.
A40: I certify (or declare) under penalty of perjury that the attached reports are true, accurate and complete, and were prepared following the applicable laws, regulations, policies, procedures, and instructions. I have not violated any of the provisions of Article 4, Chapter 1, Division 4, Title 1, Government Code (commencing with Section 1090) and Article 2, Chapter 1, Part 3, Division 3, Title 2, Government Code (commencing with Section 13030).
A46: Subscribed and executed this 30th day of August, 2024 at Sacramento, California.
I52: KIM PHAN, Chief
I53: Service Transactions & Asset
I54: Reconciliation Section

Sheet 0942
I1: Page No : 12
A2: REPORT 18 – STATEMENT OF CHANGES IN CAPITAL ASSETS
A3: Department Name (2660)
A4: SPECIAL DEPOSITS FUND (0942)
A5: Fiscal Year 2023-24
A6: As of 06/30/2024
A7: Business Unit: | C7: 2660 - DEPARTMENT OF TRANSPORTATION | I7: Report ID: | J7: RPTGL075
A8: Fund: | C8: 0942 SPECIAL DEPOSITS FUND | I8: Run Date: | J8: =TODAY() -> 45723
I9: Run Time: | J9: =NOW() -> 45723.508
A14: Account – Description | F14: Beginning Balance | G14: Additions | H14: Deductions | J14: Ending Balance
A15: Tangible Assets
A16: 2310 Land a | J16: =F16+G16-H16 -> 0
A17: 2321 Buildings | J17: =F17+G17-H17 -> 0
A18: 2331 Improvements Other Than Buildings | J18: =F18+G18-H18 -> 0
A19: 2341 Equipment | J19: =F19+G19-H19 -> 0
A20: 2350 Construction Work in Progress a | F20: 56384988 | G20: 30051.7 | H20: 0 | J20: =F20+G20-H20 -> 56415040
A21: 2361 Infrastructure - Non Depreciable a | J21: =F21+G21-H21 -> 0
A23: Intangible Assets
A24: 2411 Computer Software - Amortizable | J24: =F24+G24-H24 -> 0
A25: 2412 Land Use Rights - Amortizable | J25: =F25+G25-H25 -> 0
A26: 2413 Patents, Copyrights, and Trademarks - Amortizable | J26: =F26+G26-H26 -> 0
A27: 2414 Other Intangible Assets - Amortizable | J27: =F27+G27-H27 -> 0
A28: 2415 Right-to-Use Leased Land - Amortizable | J28: =F28+G28-H28 -> 0
A29: 2416 Right-to-Use Leased Buildings - Amortizable | J29: =F29+G29-H29 -> 0
A30: 2417 Right-to-Use Leased Equipment - Amortizable | J30: =F30+G30-H30 -> 0
A31: 2418 Right-to-Use Subscription-Based Information Technology Arrangements (SBITA) - Amortizable | J31: =F31+G31-H31 -> 0
A32: 2422 Land Use Rights - Non-Amortizable | J32: =F32+G32-H32 -> 0
A35: Fund: | B35: 0942 | F35: =SUM(F16:F34) -> 56384988 | G35: =SUM(G16:G34) -> 30051.7 | H35: =SUM(H16:H34) -> 0 | J35: =SUM(J16:J34) -> 56415040
A37: Note:
A38: a - Infrastructure only.
A40: I certify (or declare) under penalty of perjury that the attached reports are true, accurate and complete, and were prepared following the applicable laws, regulations, policies, procedures, and instructions. I have not violated any of the provisions of Article 4, Chapter 1, Division 4, Title 1, Government Code (commencing with Section 1090) and Article 2, Chapter 1, Part 3, Division 3, Title 2, Government Code (commencing with Section 13030).
A46: Subscribed and executed this 30th day of August, 2024 at Sacramento, California.
I52: KIM PHAN, Chief
I53: Service Transactions & Asset
I54: Reconciliation Section

Sheet 2504
I1: Page No : 13
A2: REPORT 18 – STATEMENT OF CHANGES IN CAPITAL ASSETS
A3: Department Name (2660)
A4: Advance Mitigation Account, State Transportation Fund (2504)
A5: Fiscal Year 2023-24
A6: As of 06/30/2024
A7: Business Unit: | C7: 2660 - DEPARTMENT OF TRANSPORTATION | I7: Report ID: RPTGL075 | J7: RPTGL075
A8: Fund: | C8: 2504 ADVANCE MITIGATION ACCOUNT, State Transportation Fund | I8: Run Date: | J8: =TODAY() -> 45723
I9: Run Time: | J9: =NOW() -> 45723.508
A14: Account – Description | F14: Beginning Balance | G14: Additions | H14: Deductions | J14: Ending Balance
A15: Tangible Assets
A16: 2310 Land a | J16: =F16+G16-H16 -> 0
A17: 2321 Buildings | J17: =F17+G17-H17 -> 0
A18: 2331 Improvements Other Than Buildings | J18: =F18+G18-H18 -> 0
A19: 2341 Equipment | J19: =F19+G19-H19 -> 0
A20: 2350 Construction Work in Progress a | J20: =F20+G20-H20 -> 0
A21: 2361 Infrastructure - Non Depreciable a | J21: =F21+G21-H21 -> 0
A23: Intangible Assets
A24: 2411 Computer Software - Amortizable | J24: =F24+G24-H24 -> 0
A25: 2412 Land Use Rights - Amortizable | F25: 0 | H25: 0 | J25: =F25+G25-H25 -> 0
A26: 2413 Patents, Copyrights, and Trademarks - Amortizable | G26: 3187845 | J26: =F26+G26-H26 -> 3187845
A27: 2414 Other Intangible Assets - Amortizable | J27: =F27+G27-H27 -> 0
A28: 2415 Right-to-Use Leased Land - Amortizable | J28: =F28+G28-H28 -> 0
A29: 2416 Right-to-Use Leased Buildings - Amortizable | J29: =F29+G29-H29 -> 0
A30: 2417 Right-to-Use Leased Equipment - Amortizable | J30: =F30+G30-H30 -> 0
A31: 2418 Right-to-Use Subscription-Based Information Technology Arrangements (SBITA) - Amortizable | J31: =F31+G31-H31 -> 0
A32: 2422 Land Use Rights - Non-Amortizable | J32: =F32+G32-H32 -> 0
A35: Fund: | B35: 2504 | F35: =SUM(F23:F34) -> 0 | G35: =SUM(G23:G34) -> 3187845 | H35: =SUM(H23:H34) -> 0 | J35: =SUM(J23:J34) -> 3187845
A37: Note:
A38: a - Infrastructure only.
A40: I certify (or declare) under penalty of perjury that the attached reports are true, accurate and complete, and were prepared following the applicable laws, regulations, policies, procedures, and instructions. I have not violated any of the provisions of Article 4, Chapter 1, Division 4, Title 1, Government Code (commencing with Section 1090) and Article 2, Chapter 1, Part 3, Division 3, Title 2, Government Code (commencing with Section 13030).
A46: Subscribed and executed this 30th day of August, 2024 at Sacramento, California.
I52: KIM PHAN, Chief
I53: Service Transactions & Asset
I54: Reconciliation Section

Sheet 3007
I1: Page No : 14
A2: REPORT 18 – STATEMENT OF CHANGES IN CAPITAL ASSETS
A3: Department Name (2660)
A4: TRAFFIC CONGESTION RELIEF FUND (3007)
A5: Fiscal Year 2023-24
A6: As of 06/30/2024
A7: Business Unit: | C7: 2660 - DEPARTMENT OF TRANSPORTATION | I7: Report ID: | J7: RPTGL075
A8: Fund: | C8: 3007 TRAFFIC CONGESTION RELIEF FUND | I8: Run Date: | J8: =TODAY() -> 45723
I9: Run Time: | J9: =NOW() -> 45723.508
A14: Account – Description | F14: Beginning Balance | G14: Additions | H14: Deductions | J14: Ending Balance
A15: Tangible Assets
A16: 2310 Land a | F16: 3.2481782e+08 | G16: 2630.83 | H16: 0 | J16: =F16+G16-H16 -> 3.2482045e+08
A17: 2321 Buildings | J17: =F17+G17-H17 -> 0
A18: 2331 Improvements Other Than Buildings | J18: =F18+G18-H18 -> 0
A19: 2341 Equipment | F19: 122733.78 | J19: =F19+G19-H19 -> 122733.78
A20: 2350 Construction Work in Progress a | F20: 3.0664624e+08 | G20: 0 | H20: 0 | J20: =F20+G20-H20 -> 3.0664624e+08
A21: 2361 Infrastructure - Non Depreciable a | F21: 5.5697738e+08 | G21: 46709.76 | H21: 0 | J21: =F21+G21-H21 -> 5.5702409e+08
J22: =F22+G22-H22 -> 0
A23: Intangible Assets | J23: =F23+G23-H23 -> 0
A24: 2411 Computer Software - Amortizable | J24: =F24+G24-H24 -> 0
A25: 2412 Land Use Rights - Amortizable | J25: =F25+G25-H25 -> 0
A26: 2413 Patents, Copyrights, and Trademarks - Amortizable | J26: =F26+G26-H26 -> 0
A27: 2414 Other Intangible Assets - Amortizable | J27: =F27+G27-H27 -> 0
A28: 2415 Right-to-Use Leased Land - Amortizable | J28: =F28+G28-H28 -> 0
A29: 2416 Right-to-Use Leased Buildings - Amortizable | J29: =F29+G29-H29 -> 0
A30: 2417 Right-to-Use Leased Equipment - Amortizable | J30: =F30+G30-H30 -> 0
A31: 2418 Right-to-Use Subscription-Based Information Technology Arrangements (SBITA) - Amortizable | J31: =F31+G31-H31 -> 0
A32: 2422 Land Use Rights - Non-Amortizable | J32: =F32+G32-H32 -> 0
A35: Fund: | B35: 3007 | F35: =SUM(F16:F34) -> 1.1885642e+09 | G35: =SUM(G16:G34) -> 49340.59 | H35: =SUM(H16:H34) -> 0 | J35: =SUM(J16:J34) -> 1.1886135e+09
A37: Note:
A38: a - Infrastructure only.
A40: b - The $2,630.83 in Land Additions is part of a larger project, over $5K, that is multi-funded.
A42: c - See "Beginning Balance Differential Report".
A44: I certify (or declare) under penalty of perjury that the attached reports are true, accurate and complete, and were prepared following the applicable laws, regulations, policies, procedures, and instructions. I have not violated any of the provisions of Article 4, Chapter 1, Division 4, Title 1, Government Code (commencing with Section 1090) and Article 2, Chapter 1, Part 3, Division 3, Title 2, Government Code (commencing with Section 13030).
A50: Subscribed and executed this 30th day of August, 2024 at Sacramento, California.
I56: KIM PHAN, Chief
I57: Service Transactions & Asset
I58: Reconciliation Section

Sheet F3007 Diff
A1: Department of Transportation (2660)
A2: Statement of Changes in Capital Assets Group of Accounts - Report 18
A3: Beginning Balance Differential Report
A4: State Highway Account Fund (3007)
A5: As of June 30, 2024
K7: Breakdown of Difference:
E8: (1) | G8: (2) | I8: (3) | K8: (4) | M8: (5) | O8: (6) | Q8: (7) | S8: (8) | T8: (9) | V8: (10)
E9: Prior Year Ending Balance | G9: Current Year Beginning Balance | I9: Difference | K9: Assets unreported in the prior year | M9: Non-capitalizable assets reported as capital assets in the prior year | O9: Availability Payment Arrangements (GASB 94) | Q9: Other amounts that make up the difference (provide description): Per SCO guidance, applying % to District Project Survey % adjustment for Prior Year Expenditures. | S9: Other amounts that make up the difference (provide description): incorrect entry was made in current year balance | T9: Other amounts that make up the difference (provide description): GASB 87 FY 2021-2022 implementation beginning balance adjustment. | V9: Restatement Amount (should agree to the difference calculated)
A11: Tangible Assets
B12: Land (2310) | E12: 3.2481782e+08 | G12: 3.2481782e+08 | I12: =G12-E12 -> 0 | V12: =SUM(K12:T12) -> 0
B13: Buildings (2321) | E13: 0 | G13: 0 | I13: =G13-E13 -> 0 | V13: =SUM(K13:T13) -> 0
B14: Improvements Other Than Buildings (2331) | I14: =G14-E14 -> 0 | V14: =SUM(K14:T14) -> 0
B15: Equipment (2341) | E15: 122733.78 | G15: 122733.78 | I15: =G15-E15 -> 0 | V15: =SUM(K15:T15) -> 0
B16: Construction Work in Progress (2350) | E16: 3.0762842e+08 | G16: 3.0664624e+08 | I16: =G16-E16 -> -982176.8 | Q16: -982176.8 | V16: =SUM(K16:T16) -> -982176.8
B17: Infrastructure - Non Depreciable (2361) | E17: 5.5519998e+08 | G17: 5.5697738e+08 | I17: =G17-E17 -> 1777400 | Q17: 1777400 | V17: =SUM(K17:T17) -> 1777400
A18: Intangible Assets | V18: =SUM(K18:T18) -> 0
B19: Computer Software - Amortizable (2411) | E19: 0 | G19: 0 | I19: =G19-E19 -> 0 | V19: =SUM(K19:T19) -> 0
B20: Land Use Rights - Amortizable (2412) | V20: =SUM(K20:T20) -> 0
B21: Patents, Copyrights, and Trademarks - Amortizable (2413) | E21: 0 | G21: 0 | I21: =G21-E21 -> 0 | V21: =SUM(K21:T21) -> 0
B22: Other Intangible Assets - Amortizable (2414) | V22: =SUM(K22:T22) -> 0
B23: Right-to-Use Leased Land - Amortizable () | V23: =SUM(K23:T23) -> 0
B24: Right-to-Use Leased Buildings - Amortizable (2416) | E24: 0 | G24: 0 | I24: =G24-E24 -> 0 | V24: =SUM(K24:T24) -> 0
B25: Right-to-Use Leased Equipment - Amortizable | V25: =SUM(K25:T25) -> 0
B26: Right-to-Use Subscription-Based Information Technology Arrangements (SBITA) - Amortizable (2418) | E26: 0 | G26: 0 | I26: =G26-E26 -> 0 | S26: 0 | V26: =SUM(K26:T26) -> 0
B27: Land Use Rights - Non-Amortizable (2422) | V27: =SUM(K27:T27) -> 0
B28: Patents, Copyrights, and Trademarks - Non-Amortizable | I28: =G28-E28 -> 0 | V28: =SUM(K28:T28) -> 0
A29: Total | E29: =SUM(E12:E28) -> 1.1877689e+09 | G29: =SUM(G12:G28) -> 1.1885642e+09 | I29: =SUM(I12:I28) -> 795223.2 | K29: =SUM(K12:K28) -> 0 | M29: =SUM(M12:M28) -> 0 | O29: =SUM(O12:O28) -> 0 | Q29: =SUM(Q12:Q28) -> 795223.2 | S29: =SUM(S12:S28) -> 0 | T29: =SUM(T12:T28) -> 0 | V29: =SUM(V12:V28) -> 795223.2
A32: Report Instructions:
A33: Col. 1 - | C33: Enter Ending Balance from Prior Year Report 18.
A34: Col. 2 - | C34: Enter Beginning Balance from Current Year Report 18.
A35: Col. 3 - | C35: Compute difference between current year beginning balance and prior year ending balance.
C36: Research posting and source documents to identify and explain the difference.
A37: Col. 4 - 9 | C37: Breakdown and categorize the differences in columns 4 to 9.
A38: Col. 10 - | C38: Compute the sum of columns 4 to 8. The amount should agree with the computed difference in column 3.

Sheet 3290
I1: Page No : 15
A2: REPORT 18 – STATEMENT OF CHANGES IN CAPITAL ASSETS
A3: Department Name (2660)
A4: ROAD MAINTENANCE AND REHABILITATION ACCOUNT (3290)
A5: Fiscal Year 2023-24
A6: As of 06/30/2024
A7: Business Unit: | C7: 2660 - DEPARTMENT OF TRANSPORTATION | I7: Report ID: | J7: RPTGL075
A8: Fund: | C8: 3290 ROAD MAINTENANCE AND REHABILITATION ACCOUNT | I8: Run Date: | J8: =TODAY() -> 45723
I9: Run Time: | J9: =NOW() -> 45723.508
A14: Account – Description | F14: Beginning Balance | G14: Additions | H14: Deductions | J14: Ending Balance
A15: Tangible Assets
A16: 2310 Land a | F16: 18682476 | G16: 3384432.5 | J16: =F16+G16-H16 -> 22066908
A17: 2321 Buildings | F17: 0 | G17: 9485.68 | J17: =F17+G17-H17 -> 9485.68
A18: 2331 Improvements Other Than Buildings | J18: =F18+G18-H18 -> 0
A19: 2341 Equipment | F19: 1608024.9 | G19: 267420.37 | H19: 358620.74 | J19: =F19+G19-H19 -> 1516824.6
A20: 2350 Construction Work in Progress a | F20: 5.1405771e+08 | G20: 1.4160137e+08 | H20: 2.4375495e+08 | J20: =F20+G20-H20 -> 4.1190413e+08
A21: 2361 Infrastructure - Non Depreciable b | F21: 2.0764281e+08 | G21: 2.6748512e+08 | H21: 0 | J21: =F21+G21-H21 -> 4.7512793e+08
A23: Intangible Assets
A24: 2411 Computer Software - Amortizable | F24: 1140915.6 | G24: 7891.3 | J24: =F24+G24-H24 -> 1148806.9
A25: 2412 Land Use Rights - Amortizable | J25: =F25+G25-H25 -> 0
A26: 2413 Patents, Copyrights, and Trademarks - Amortizable | J26: =F26+G26-H26 -> 0
A27: 2414 Other Intangible Assets - Amortizable | J27: =F27+G27-H27 -> 0
A28: 2415 Right-to-Use Leased Land - Amortizable | J28: =F28+G28-H28 -> 0
A29: 2416 Right-to-Use Leased Buildings - Amortizable | F29: 9654616 | G29: 3564523.1 | H29: 1104181.1 | J29: =F29+G29-H29 -> 12114958
A30: 2417 Right-to-Use Leased Equipment - Amortizable | J30: =F30+G30-H30 -> 0
A31: 2418 Right-to-Use Subscription-Based Information Technology Arrangements (SBITA) - Amortizable | F31: 41712.96 | G31: 8849.98 | H31: 14112.76 | J31: =F31+G31-H31 -> 36450.18
A32: 2422 Land Use Rights - Non-Amortizable | J32: =F32+G32-H32 -> 0
A35: Fund: | B35: 3290 | F35: =SUM(F16:F34) -> 7.5282826e+08 | G35: =SUM(G16:G34) -> 4.163291e+08 | H35: =SUM(H16:H34) -> 2.4523187e+08 | J35: =SUM(J16:J34) -> 9.2392549e+08
A37: Note:
A38: a - Infrastructure only.
A40: b - Infrastructure only.
A42: c - The $243,754,951.19 in Construction Work in Progress' Deductions which represents FY 2023/2024's Transfer from CWIP to Non-Depreciable Infrastructure (Completed).
A45: d - The $1,104,181.11 in deductions for Right-to-Use Leased Buildings - Amortizable represents FY2023/2024 removal of lease asset at the end of the lease term.
A48: e - See "Beginning Balance Differential Report".
A50: I certify (or declare) under penalty of perjury that the attached reports are true, accurate and complete, and were prepared following the applicable laws, regulations, policies, procedures, and instructions. I have not violated any of the provisions of Article 4, Chapter 1, Division 4, Title 1, Government Code (commencing with Section 1090) and Article 2, Chapter 1, Part 3, Division 3, Title 2, Government Code (commencing with Section 13030).
A56: Subscribed and executed this 30th day of August, 2024 at Sacramento, California.
I62: KIM PHAN, Chief
I63: Service Transactions & Asset
I64: Reconciliation Section

Sheet F3290 Diff 
A1: Department of Transportation (2660)
A2: Statement of Changes in Capital Assets Group of Accounts - Report 18
A3: Beginning Balance Differential Report
A4: State Highway Account Fund (3290)
A5: As of June 30, 2024
K7: Breakdown of Difference:
E8: (1) | G8: (2) | I8: (3) | K8: (4) | M8: (5) | O8: (6) | Q8: (7) | S8: (8) | T8: (9) | V8: (10)
E9: Prior Year Ending Balance | G9: Current Year Beginning Balance | I9: Difference | K9: Assets unreported in the prior year | M9: Non-capitalizable assets reported as capital assets in the prior year | O9: Availability Payment Arrangements (GASB 94) | Q9: Other amounts that make up the difference (provide description): Per SCO guidance, applying % to District Project Survey % adjustment for Prior Year Expenditures. | S9: Other amounts that make up the difference (provide description): GASB 87 FY2021-2022 Implementation beginning balance adjustment | T9: Other amounts that make up the difference (provide description): Prior Year Fund to Fund Adjustment. | V9: Restatement Amount (should agree to the difference calculated)
A11: Tangible Assets
B12: Land (2310) | E12: 18207982 | G12: 18682476 | I12: =G12-E12 -> 474494.04 | Q12: 474494.04 | V12: =SUM(K12:T12) -> 474494.04
B13: Buildings (2321) | E13: 0 | G13: 0 | I13: =G13-E13 -> 0 | V13: =SUM(K13:T13) -> 0
B14: Improvements Other Than Buildings (2331) | I14: =G14-E14 -> 0 | V14: =SUM(K14:T14) -> 0
B15: Equipment (2341) | E15: 1608024.9 | G15: 1608024.9 | I15: =G15-E15 -> 0 | V15: =SUM(K15:T15) -> 0
B16: Construction Work in Progress (2350) | E16: 5.7001773e+08 | G16: 5.1405771e+08 | I16: =G16-E16 -> -55960018 | Q16: -55960018 | V16: =SUM(K16:T16) -> -55960018
B17: Infrastructure - Non Depreciable (2361) | E17: 2.1565797e+08 | G17: 2.0764281e+08 | I17: =G17-E17 -> -8015163.2 | T17: -8015163.2 | V17: =SUM(K17:T17) -> -8015163.2
A18: Intangible Assets | V18: =SUM(K18:T18) -> 0
B19: Computer Software - Amortizable (2411) | E19: 1140915.6 | G19: 1140915.6 | I19: =G19-E19 -> 0 | V19: =SUM(K19:T19) -> 0
B20: Land Use Rights - Amortizable (2412) | V20: =SUM(K20:T20) -> 0
B21: Patents, Copyrights, and Trademarks - Amortizable (2413) | E21: 0 | G21: 0 | I21: =G21-E21 -> 0 | V21: =SUM(K21:T21) -> 0
B22: Other Intangible Assets - Amortizable (2414) | V22: =SUM(K22:T22) -> 0
B23: Right-to-Use Leased Land - Amortizable () | V23: =SUM(K23:T23) -> 0
B24: Right-to-Use Leased Buildings - Amortizable (2416) | E24: 9717616 | G24: 9654616 | I24: =G24-E24 -> -63000 | S24: -63000 | V24: =SUM(K24:T24) -> -63000
B25: Right-to-Use Leased Equipment - Amortizable | V25: =SUM(K25:T25) -> 0
B26: Right-to-Use Subscription-Based Information Technology Arrangements (SBITA) - Amortizable (2418) | E26: 41712.956 | G26: 41712.956 | I26: =G26-E26 -> 0 | V26: =SUM(K26:T26) -> 0
B27: Land Use Rights - Non-Amortizable (2422) | V27: =SUM(K27:T27) -> 0
B28: Patents, Copyrights, and Trademarks - Non-Amortizable | I28: =G28-E28 -> 0 | V28: =SUM(K28:T28) -> 0
A29: Total | E29: =SUM(E12:E28) -> 8.1639195e+08 | G29: =SUM(G12:G28) -> 7.5282826e+08 | I29: =SUM(I12:I28) -> -63563687 | K29: =SUM(K12:K28) -> 0 | M29: =SUM(M12:M28) -> 0 | O29: =SUM(O12:O28) -> 0 | Q29: =SUM(Q12:Q28) -> -55485524 | S29: =SUM(S12:S28) -> -63000 | T29: =SUM(T12:T28) -> -8015163.2 | V29: =SUM(V12:V28) -> -63563687
A32: Report Instructions:
A33: Col. 1 - | C33: Enter Ending Balance from Prior Year Report 18.
A34: Col. 2 - | C34: Enter Beginning Balance from Current Year Report 18.
A35: Col. 3 - | C35: Compute difference between current year beginning balance and prior year ending balance.
C36: Research posting and source documents to identify and explain the difference.
A37: Col. 4 - 9 | C37: Breakdown and categorize the differences in columns 4 to 9.
A38: Col. 10 - | C38: Compute the sum of columns 4 to 8. The amount should agree with the computed difference in column 3.

Sheet 3291
I1: Page No : 16
A2: REPORT 18 – STATEMENT OF CHANGES IN CAPITAL ASSETS
A3: Department Name (2660)
A4: TRADE CORRIDOR ENHANCEMENT ACCOUNT (3291)
A5: Fiscal Year 2023-24
A6: As of 06/30/2024
A7: Business Unit: | C7: 2660 - DEPARTMENT OF TRANSPORTATION | I7: Report ID: | J7: RPTGL075
A8: Fund: | C8: 3291 TRADE CORRIDOR ENHANCEMENT ACCOUNT | I8: Run Date: | J8: =TODAY() -> 45723
I9: Run Time: | J9: =NOW() -> 45723.508
A14: Account – Description | F14: Beginning Balance | G14: Additions | H14: Deductions | J14: Ending Balance
A15: Tangible Assets
A16: 2310 Land a | F16: 9200788.3 | G16: 13780456 | H16: 0 | J16: =F16+G16-H16 -> 22981244
A17: 2321 Buildings | J17: =F17+G17-H17 -> 0
A18: 2331 Improvements Other Than Buildings | J18: =F18+G18-H18 -> 0
A19: 2341 Equipment | J19: =F19+G19-H19 -> 0
A20: 2350 Construction Work in Progress a | F20: 2.2039655e+08 | G20: 1.1642696e+08 | H20: 58815512 | J20: =F20+G20-H20 -> 2.78008e+08
A21: 2361 Infrastructure - Non Depreciable b | F21: 55102563 | G21: 61209866 | H21: 0 | J21: =F21+G21-H21 -> 1.1631243e+08
J22: =F22+G22-H22 -> 0
A23: Intangible Assets | J23: =F23+G23-H23 -> 0
A24: 2411 Computer Software - Amortizable | J24: =F24+G24-H24 -> 0
A25: 2412 Land Use Rights - Amortizable | J25: =F25+G25-H25 -> 0
A26: 2413 Patents, Copyrights, and Trademarks - Amortizable | J26: =F26+G26-H26 -> 0
A27: 2414 Other Intangible Assets - Amortizable | J27: =F27+G27-H27 -> 0
A28: 2415 Right-to-Use Leased Land - Amortizable | J28: =F28+G28-H28 -> 0
A29: 2416 Right-to-Use Leased Buildings - Amortizable | F29: 83839.33 | G29: 55003 | J29: =F29+G29-H29 -> 138842.33
A30: 2417 Right-to-Use Leased Equipment - Amortizable | J30: =F30+G30-H30 -> 0
A31: 2418 Right-to-Use Subscription-Based Information Technology Arrangements (SBITA) - Amortizable | J31: =F31+G31-H31 -> 0
A32: 2422 Land Use Rights - Non-Amortizable | J32: =F32+G32-H32 -> 0
A35: Fund: | B35: 3291 | F35: =SUM(F16:F34) -> 2.8478374e+08 | G35: =SUM(G16:G34) -> 1.9147228e+08 | H35: =SUM(H16:H34) -> 58815512 | J35: =SUM(J16:J34) -> 4.1744051e+08
A37: Note:
A38: a - Infrastructure only.
A40: b - Infrastructure only.
A42: c - The $58,815,511.57 in Construction Work in Progress' Deductions which represents FY 2023/2024's Transfer from CWIP to Non-Depreciable Infrastructure (Completed).
A45: d - See "Beginning Balance Differential Report".
A47: I certify (or declare) under penalty of perjury that the attached reports are true, accurate and complete, and were prepared following the applicable laws, regulations, policies, procedures, and instructions. I have not violated any of the provisions of Article 4, Chapter 1, Division 4, Title 1, Government Code (commencing with Section 1090) and Article 2, Chapter 1, Part 3, Division 3, Title 2, Government Code (commencing with Section 13030).
A52: Subscribed and executed this 30th day of August, 2024 at Sacramento, California.
I58: KIM PHAN, Chief
I59: Service Transactions & Asset
I60: Reconciliation Section

Sheet F3291 Diff 
A1: Department of Transportation (2660)
A2: Statement of Changes in Capital Assets Group of Accounts - Report 18
A3: Beginning Balance Differential Report
A4: State Highway Account Fund (3291)
A5: As of June 30, 2024
K7: Breakdown of Difference:
E8: (1) | G8: (2) | I8: (3) | K8: (4) | M8: (5) | O8: (6) | Q8: (7) | S8: (8) | T8: (9) | V8: (10)
E9: Prior Year Ending Balance | G9: Current Year Beginning Balance | I9: Difference | K9: Assets unreported in the prior year | M9: Non-capitalizable assets reported as capital assets in the prior year | O9: Availability Payment Arrangements (GASB 94) | Q9: Other amounts that make up the difference (provide description): Per SCO guidance, applying % to District Project Survey % adjustment for Prior Year Expenditures. | S9: Other amounts that make up the difference (provide description): incorrect entry was made in current year balance | T9: Other amounts that make up the difference (provide description): Prior Year Fund to Fund Adjustment. | V9: Restatement Amount (should agree to the difference calculated)
A11: Tangible Assets
B12: Land (2310) | E12: 9200788.3 | G12: 9200788.3 | I12: =G12-E12 -> 0 | V12: =SUM(K12:T12) -> 0
B13: Buildings (2321) | E13: 0 | G13: 0 | I13: =G13-E13 -> 0 | V13: =SUM(K13:T13) -> 0
B14: Improvements Other Than Buildings (2331) | I14: =G14-E14 -> 0 | V14: =SUM(K14:T14) -> 0
B15: Equipment (2341) | E15: 0 | G15: 0 | I15: =G15-E15 -> 0 | V15: =SUM(K15:T15) -> 0
B16: Construction Work in Progress (2350) | E16: 2.0731055e+08 | G16: 2.2039655e+08 | I16: =G16-E16 -> 13085998 | Q16: -3005784.2 | T16: 16091782 | V16: =SUM(K16:T16) -> 13085998
B17: Infrastructure - Non Depreciable (2361) | E17: 55102563 | G17: 55102563 | I17: =G17-E17 -> 0 | V17: =SUM(K17:T17) -> 0
A18: Intangible Assets | V18: =SUM(K18:T18) -> 0
B19: Computer Software - Amortizable (2411) | E19: 0 | G19: 0 | I19: =G19-E19 -> 0 | V19: =SUM(K19:T19) -> 0
B20: Land Use Rights - Amortizable (2412) | V20: =SUM(K20:T20) -> 0
B21: Patents, Copyrights, and Trademarks - Amortizable (2413) | E21: 0 | G21: 0 | I21: =G21-E21 -> 0 | V21: =SUM(K21:T21) -> 0
B22: Other Intangible Assets - Amortizable (2414) | V22: =SUM(K22:T22) -> 0
B23: Right-to-Use Leased Land - Amortizable () | V23: =SUM(K23:T23) -> 0
B24: Right-to-Use Leased Buildings - Amortizable (2416) | E24: 83839.33 | G24: 83839.33 | I24: =G24-E24 -> 0 | V24: =SUM(K24:T24) -> 0
B25: Right-to-Use Leased Equipment - Amortizable | V25: =SUM(K25:T25) -> 0
B26: Right-to-Use Subscription-Based Information Technology Arrangements (SBITA) - Amortizable (2418) | E26: 0 | G26: 0 | I26: =G26-E26 -> 0 | V26: =SUM(K26:T26) -> 0
B27: Land Use Rights - Non-Amortizable (2422) | V27: =SUM(K27:T27) -> 0
B28: Patents, Copyrights, and Trademarks - Non-Amortizable | I28: =G28-E28 -> 0 | V28: =SUM(K28:T28) -> 0
A29: Total | E29: =SUM(E12:E28) -> 2.7169774e+08 | G29: =SUM(G12:G28) -> 2.8478374e+08 | I29: =SUM(I12:I28) -> 13085998 | K29: =SUM(K12:K28) -> 0 | M29: =SUM(M12:M28) -> 0 | O29: =SUM(O12:O28) -> 0 | Q29: =SUM(Q12:Q28) -> -3005784.2 | S29: =SUM(S12:S28) -> 0 | T29: =SUM(T12:T28) -> 16091782 | V29: =SUM(V12:V28) -> 13085998
A32: Report Instructions:
A33: Col. 1 - | C33: Enter Ending Balance from Prior Year Report 18.
A34: Col. 2 - | C34: Enter Beginning Balance from Current Year Report 18.
A35: Col. 3 - | C35: Compute difference between current year beginning balance and prior year ending balance.
C36: Research posting and source documents to identify and explain the difference.
A37: Col. 4 - 9 | C37: Breakdown and categorize the differences in columns 4 to 9.
A38: Col. 10 - | C38: Compute the sum of columns 4 to 8. The amount should agree with the computed difference in column 3.

Sheet 6055
I1: Page No : 17
A2: REPORT 18 – STATEMENT OF CHANGES IN CAPITAL ASSETS
A3: Department Name (2660)
A4: CORRIDOR MOBILITY IMPROVEMENT ACCOUNT, HIGHWAY SAFETY, TRAFFIC REDUCTION, AIR QUALITY, AND PORT SECURITY FUND OF 2006 (6055)
A5: Fiscal Year 2023-24
A6: As of 06/30/2024
A7: Business Unit: | C7: 2660 - DEPARTMENT OF TRANSPORTATION | I7: Report ID: | J7: RPTGL075
A8: Fund: | C8: 6055 CORRIDOR MOBILITY IMPROVEMENT ACCOUNT, HIGHWAY SAFETY, TRAFFIC REDUCTION, AIR QUALITY, AND PORT SECURITY FUND OF 2006 | I8: Run Date: | J8: =TODAY() -> 45723
I9: Run Time: | J9: =NOW() -> 45723.508
A14: Account – Description | F14: Beginning Balance | G14: Additions | H14: Deductions | J14: Ending Balance
A15: Tangible Assets
A16: 2310 Land a | J16: =F16+G16-H16 -> 0
A17: 2321 Buildings | F17: 23461.91 | J17: =F17+G17-H17 -> 23461.91
A18: 2331 Improvements Other Than Buildings | J18: =F18+G18-H18 -> 0
A19: 2341 Equipment | J19: =F19+G19-H19 -> 0
A20: 2350 Construction Work in Progress a | F20: 4.3144013e+08 | G20: 0 | H20: 22202895 | J20: =F20+G20-H20 -> 4.0923723e+08
A21: 2361 Infrastructure - Non Depreciable a | F21: 2.8823923e+09 | G21: 22302352 | H21: 56386.78 | J21: =F21+G21-H21 -> 2.9046383e+09
J22: =F22+G22-H22 -> 0
A23: Intangible Assets | J23: =F23+G23-H23 -> 0
A24: 2411 Computer Software - Amortizable | F24: 163795.7 | J24: =F24+G24-H24 -> 163795.7
A25: 2412 Land Use Rights - Amortizable | J25: =F25+G25-H25 -> 0
A26: 2413 Patents, Copyrights, and Trademarks - Amortizable | J26: =F26+G26-H26 -> 0
A27: 2414 Other Intangible Assets - Amortizable | J27: =F27+G27-H27 -> 0
A28: 2415 Right-to-Use Leased Land - Amortizable | J28: =F28+G28-H28 -> 0
A29: 2416 Right-to-Use Leased Buildings - Amortizable | J29: =F29+G29-H29 -> 0
A30: 2417 Right-to-Use Leased Equipment - Amortizable | J30: =F30+G30-H30 -> 0
A31: 2418 Right-to-Use Subscription-Based Information Technology Arrangements (SBITA) - Amortizable | J31: =F31+G31-H31 -> 0
A32: 2422 Land Use Rights - Non-Amortizable | J32: =F32+G32-H32 -> 0
J33: =F33+G33-H33 -> 0
J34: =F34+G34-H34 -> 0
A35: Fund: | B35: 6055 | F35: =SUM(F16:F34) -> 3.3140197e+09 | G35: =SUM(G16:G34) -> 22302352 | H35: =SUM(H16:H34) -> 22259282 | J35: =F35+G35-H35 -> 3.3140628e+09
A37: Note:
A38: a - Infrastructure only.
A40: b - The $22,202,895.28 in Construction Work in Progress' Deductions which represents FY 2023/2024's Transfer from CWIP to Non-Depreciable Infrastructure (Completed).
A43: I certify (or declare) under penalty of perjury that the attached reports are true, accurate and complete, and were prepared following the applicable laws, regulations, policies, procedures, and instructions. I have not violated any of the provisions of Article 4, Chapter 1, Division 4, Title 1, Government Code (commencing with Section 1090) and Article 2, Chapter 1, Part 3, Division 3, Title 2, Government Code (commencing with Section 13030).
A48: Subscribed and executed this 30th day of August, 2024 at Sacramento, California.
I57: KIM PHAN, Chief
I58: Service Transactions & Asset
I59: Reconciliation Section

Sheet 6056
I1: Page No : 18
A2: REPORT 18 – STATEMENT OF CHANGES IN CAPITAL ASSETS
A3: Department Name (2660)
A4: TRADE CORRIDORS IMPROVEMENT FUND (6056)
A5: Fiscal Year 2023-24
A6: As of 06/30/2024
A7: Business Unit: | C7: 2660 - DEPARTMENT OF TRANSPORTATION | I7: Report ID: | J7: RPTGL075
A8: Fund: | C8: 6056 TRADE CORRIDORS IMPROVEMENT FUND | I8: Run Date: | J8: =TODAY() -> 45723
I9: Run Time: | J9: =NOW() -> 45723.508
A14: Account – Description | F14: Beginning Balance | G14: Additions | H14: Deductions | J14: Ending Balance
A15: Tangible Assets
A16: 2310 Land a | J16: =F16+G16-I16 -> 0
A17: 2321 Buildings | J17: =F17+G17-I17 -> 0
A18: 2331 Improvements Other Than Buildings | J18: =F18+G18-I18 -> 0
A19: 2341 Equipment | J19: =F19+G19-I19 -> 0
A20: 2350 Construction Work in Progress a | F20: 1.1738568e+08 | G20: 6018468.3 | H20: 1068422.4 | J20: =F20+G20-H20 -> 1.2233573e+08
A21: 2361 Infrastructure - Non Depreciable b | F21: 2.4468171e+08 | G21: 1100668.8 | H21: 0 | J21: =F21+G21-H21 -> 2.4578237e+08
J22: =F22+G22-I22 -> 0
A23: Intangible Assets | J23: =F23+G23-I23 -> 0
A24: 2411 Computer Software - Amortizable | F24: 7255.86 | J24: =F24+G24-I24 -> 7255.86
A25: 2412 Land Use Rights - Amortizable | J25: =F25+G25-I25 -> 0
A26: 2413 Patents, Copyrights, and Trademarks - Amortizable | J26: =F26+G26-I26 -> 0
A27: 2414 Other Intangible Assets - Amortizable | J27: =F27+G27-I27 -> 0
A28: 2415 Right-to-Use Leased Land - Amortizable | J28: =F28+G28-I28 -> 0
A29: 2416 Right-to-Use Leased Buildings - Amortizable | J29: =F29+G29-I29 -> 0
A30: 2417 Right-to-Use Leased Equipment - Amortizable | J30: =F30+G30-I30 -> 0
A31: 2418 Right-to-Use Subscription-Based Information Technology Arrangements (SBITA) - Amortizable | J31: =F31+G31-I31 -> 0
A32: 2422 Land Use Rights - Non-Amortizable | J32: =F32+G32-I32 -> 0
A35: Fund: | B35: 6056 | F35: =SUM(F16:F34) -> 3.6207464e+08 | G35: =SUM(G16:G34) -> 7119137.1 | H35: =SUM(H16:H34) -> 1068422.4 | J35: =SUM(J16:J34) -> 3.6812536e+08
A37: Note:
A38: a - Infrastructure only.
A40: b - Infrastructure only.
A42: c - The $1,068,422.43 in Construction Work in Progress' Deductions which represents FY 2023/2024's Transfer from CWIP to Non-Depreciable Infrastructure (Completed).
A45: d - See "Beginning Balance Differential Report".
A47: I certify (or declare) under penalty of perjury that the attached reports are true, accurate and complete, and were prepared following the applicable laws, regulations, policies, procedures, and instructions. I have not violated any of the provisions of Article 4, Chapter 1, Division 4, Title 1, Government Code (commencing with Section 1090) and Article 2, Chapter 1, Part 3, Division 3, Title 2, Government Code (commencing with Section 13030).
A52: Subscribed and executed this 30th day of August, 2024 at Sacramento, California.
I58: KIM PHAN, Chief
I59: Service Transactions & Asset
I60: Reconciliation Section

Sheet F6056 Diff
A1: Department of Transportation (2660)
A2: Statement of Changes in Capital Assets Group of Accounts - Report 18
A3: Beginning Balance Differential Report
A4: State Highway Account Fund (6056)
A5: As of June 30, 2024
K7: Breakdown of Difference:
E8: (1) | G8: (2) | I8: (3) | K8: (4) | M8: (5) | O8: (6) | Q8: (7) | S8: (8) | T8: (9) | V8: (10)
E9: Prior Year Ending Balance | G9: Current Year Beginning Balance | I9: Difference | K9: Assets unreported in the prior year | M9: Non-capitalizable assets reported as capital assets in the prior year | O9: Availability Payment Arrangements (GASB 94) | Q9: Other amounts that make up the difference (provide description): Per SCO guidance, applying % to District Project Survey % adjustment for Prior Year Expenditures. | S9: Other amounts that make up the difference (provide description): incorrect entry was made in current year balance | T9: Other amounts that make up the difference (provide description): Prior Year Fund to Fund Adjustment. | V9: Restatement Amount (should agree to the difference calculated)
A11: Tangible Assets
B12: Land (2310) | E12: 0 | G12: 0 | I12: =G12-E12 -> 0 | V12: =SUM(K12:T12) -> 0
B13: Buildings (2321) | E13: 0 | G13: 0 | I13: =G13-E13 -> 0 | V13: =SUM(K13:T13) -> 0
B14: Improvements Other Than Buildings (2331) | I14: =G14-E14 -> 0 | V14: =SUM(K14:T14) -> 0
B15: Equipment (2341) | E15: 0 | G15: 0 | I15: =G15-E15 -> 0 | V15: =SUM(K15:T15) -> 0
B16: Construction Work in Progress (2350) | E16: 1.1831317e+08 | G16: 1.1738568e+08 | I16: =G16-E16 -> -927487.15 | Q16: 927487.15 | V16: =SUM(K16:T16) -> 927487.15
B17: Infrastructure - Non Depreciable (2361) | E17: 2.4468171e+08 | G17: 2.4468171e+08 | I17: =G17-E17 -> 0 | V17: =SUM(K17:T17) -> 0
A18: Intangible Assets | V18: =SUM(K18:T18) -> 0
B19: Computer Software - Amortizable (2411) | E19: 7255.86 | G19: 7255.86 | I19: =G19-E19 -> 0 | V19: =SUM(K19:T19) -> 0
B20: Land Use Rights - Amortizable (2412) | V20: =SUM(K20:T20) -> 0
B21: Patents, Copyrights, and Trademarks - Amortizable (2413) | E21: 0 | G21: 0 | I21: =G21-E21 -> 0 | V21: =SUM(K21:T21) -> 0
B22: Other Intangible Assets - Amortizable (2414) | V22: =SUM(K22:T22) -> 0
B23: Right-to-Use Leased Land - Amortizable () | V23: =SUM(K23:T23) -> 0
B24: Right-to-Use Leased Buildings - Amortizable (2416) | E24: 0 | G24: 0 | I24: =G24-E24 -> 0 | V24: =SUM(K24:T24) -> 0
B25: Right-to-Use Leased Equipment - Amortizable | V25: =SUM(K25:T25) -> 0
B26: Right-to-Use Subscription-Based Information Technology Arrangements (SBITA) - Amortizable (2418) | E26: 0 | G26: 0 | I26: =G26-E26 -> 0 | S26: 0 | V26: =SUM(K26:T26) -> 0
B27: Land Use Rights - Non-Amortizable (2422) | V27: =SUM(K27:T27) -> 0
B28: Patents, Copyrights, and Trademarks - Non-Amortizable | I28: =G28-E28 -> 0 | V28: =SUM(K28:T28) -> 0
A29: Total | E29: =SUM(E12:E28) -> 3.6300213e+08 | G29: =SUM(G12:G28) -> 3.6207464e+08 | I29: =SUM(I12:I28) -> -927487.15 | K29: =SUM(K12:K28) -> 0 | M29: =SUM(M12:M28) -> 0 | O29: =SUM(O12:O28) -> 0 | Q29: =SUM(Q12:Q28) -> 927487.15 | S29: =SUM(S12:S28) -> 0 | T29: =SUM(T12:T28) -> 0 | V29: =SUM(V12:V28) -> 927487.15
A32: Report Instructions:
A33: Col. 1 - | C33: Enter Ending Balance from Prior Year Report 18.
A34: Col. 2 - | C34: Enter Beginning Balance from Current Year Report 18.
A35: Col. 3 - | C35: Compute difference between current year beginning balance and prior year ending balance.
C36: Research posting and source documents to identify and explain the difference.
A37: Col. 4 - 9 | C37: Breakdown and categorize the differences in columns 4 to 9.
A38: Col. 10 - | C38: Compute the sum of columns 4 to 8. The amount should agree with the computed difference in column 3.

Sheet 6058
I1: Page No : 19
A2: REPORT 18 – STATEMENT OF CHANGES IN CAPITAL ASSETS
A3: Department Name (2660)
A4: TRANSPORTATION FACILITIES ACCOUNT, HIGHWAY SAFETY, TRAFFIC REDUCTION, AIR QUALITY, AND PORT SECURITY FUND OF 2006 (6058)
A5: Fiscal Year 2023-24
A6: As of 06/30/2024
A7: Business Unit: | C7: 2660 - DEPARTMENT OF TRANSPORTATION | I7: Report ID: | J7: RPTGL075
A8: Fund: | C8: 6058 TRANSPORTATION FACILITIES ACCOUNT | I8: Run Date: | J8: =TODAY() -> 45723
I9: Run Time: | J9: =NOW() -> 45723.508
A14: Account – Description | F14: Beginning Balance | G14: Additions | H14: Deductions | J14: Ending Balance
A15: Tangible Assets
A16: 2310 Land a | J16: =F16+G16-H16 -> 0
A17: 2321 Buildings | J17: =F17+G17-H17 -> 0
A18: 2331 Improvements Other Than Buildings | J18: =F18+G18-H18 -> 0
A19: 2341 Equipment | F19: 5131.6 | J19: =F19+G19-H19 -> 5131.6
A20: 2350 Construction Work in Progress a | F20: 76044931 | G20: 11734707 | J20: =F20+G20-H20 -> 87779638
A21: 2361 Infrastructure - Non Depreciable a | F21: 1.4631467e+09 | G21: 17855.47 | J21: =F21+G21-H21 -> 1.4631646e+09
A23: Intangible Assets
A24: 2411 Computer Software - Amortizable | F24: 46218.78 | J24: =F24+G24-H24 -> 46218.78
A25: 2412 Land Use Rights - Amortizable | J25: =F25+G25-H25 -> 0
A26: 2413 Patents, Copyrights, and Trademarks - Amortizable | J26: =F26+G26-H26 -> 0
A27: 2414 Other Intangible Assets - Amortizable | J27: =F27+G27-H27 -> 0
A28: 2415 Right-to-Use Leased Land - Amortizable | J28: =F28+G28-H28 -> 0
A29: 2416 Right-to-Use Leased Buildings - Amortizable | J29: =F29+G29-H29 -> 0
A30: 2417 Right-to-Use Leased Equipment - Amortizable | J30: =F30+G30-H30 -> 0
A31: 2418 Right-to-Use Subscription-Based Information Technology Arrangements (SBITA) - Amortizable | J31: =F31+G31-H31 -> 0
A32: 2422 Land Use Rights - Non-Amortizable | J32: =F32+G32-H32 -> 0
A35: Fund: | B35: 6058 | F35: =SUM(F16:F34) -> 1.539243e+09 | G35: =SUM(G16:G34) -> 11752562 | H35: =SUM(H16:H34) -> 0 | J35: =SUM(J16:J34) -> 1.5509956e+09
A37: Note:
A38: a - Infrastructure only.
A40: b - See "Beginning Balance Differential Report".
A42: I certify (or declare) under penalty of perjury that the attached reports are true, accurate and complete, and were prepared following the applicable laws, regulations, policies, procedures, and instructions. I have not violated any of the provisions of Article 4, Chapter 1, Division 4, Title 1, Government Code (commencing with Section 1090) and Article 2, Chapter 1, Part 3, Division 3, Title 2, Government Code (commencing with Section 13030).
A48: Subscribed and executed this 30th day of August, 2024 at Sacramento, California.
I54: KIM PHAN, Chief
I55: Service Transactions & Asset
I56: Reconciliation Section

Sheet F6058 Diff 
A1: Department of Transportation (2660)
A2: Statement of Changes in Capital Assets Group of Accounts - Report 18
A3: Beginning Balance Differential Report
A4: State Highway Account Fund (6058)
A5: As of June 30, 2024
K7: Breakdown of Difference:
E8: (1) | G8: (2) | I8: (3) | K8: (4) | M8: (5) | O8: (6) | Q8: (7) | S8: (8) | T8: (9) | V8: (10)
E9: Prior Year Ending Balance | G9: Current Year Beginning Balance | I9: Difference | K9: Assets unreported in the prior year | M9: Non-capitalizable assets reported as capital assets in the prior year | O9: Availability Payment Arrangements (GASB 94) | Q9: Other amounts that make up the difference (provide description): Per SCO guidance, applying % to District Project Survey % adjustment for Prior Year Expenditures. | S9: Other amounts that make up the difference (provide description): incorrect entry was made in current year balance | T9: Other amounts that make up the difference (provide description): Prior Year Fund to Fund Adjustment. | V9: Restatement Amount (should agree to the difference calculated)
A11: Tangible Assets
B12: Land (2310) | E12: 0 | G12: 0 | I12: =G12-E12 -> 0 | V12: =SUM(K12:T12) -> 0
B13: Buildings (2321) | E13: 0 | G13: 0 | I13: =G13-E13 -> 0 | V13: =SUM(K13:T13) -> 0
B14: Improvements Other Than Buildings (2331) | I14: =G14-E14 -> 0 | V14: =SUM(K14:T14) -> 0
B15: Equipment (2341) | E15: 5131.6 | G15: 5131.6 | I15: =G15-E15 -> 0 | V15: =SUM(K15:T15) -> 0
B16: Construction Work in Progress (2350) | E16: 76044931 | G16: 76044931 | I16: =G16-E16 -> 0 | V16: =SUM(K16:T16) -> 0
B17: Infrastructure - Non Depreciable (2361) | E17: 1.4590015e+09 | G17: 1.4631467e+09 | I17: =G17-E17 -> 4145200 | Q17: 4145200 | V17: =SUM(K17:T17) -> 4145200
A18: Intangible Assets | V18: =SUM(K18:T18) -> 0
B19: Computer Software - Amortizable (2411) | E19: 46218.78 | G19: 46218.78 | I19: =G19-E19 -> 0 | V19: =SUM(K19:T19) -> 0
B20: Land Use Rights - Amortizable (2412) | V20: =SUM(K20:T20) -> 0
B21: Patents, Copyrights, and Trademarks - Amortizable (2413) | E21: 0 | G21: 0 | I21: =G21-E21 -> 0 | V21: =SUM(K21:T21) -> 0
B22: Other Intangible Assets - Amortizable (2414) | V22: =SUM(K22:T22) -> 0
B23: Right-to-Use Leased Land - Amortizable () | V23: =SUM(K23:T23) -> 0
B24: Right-to-Use Leased Buildings - Amortizable (2416) | E24: 0 | G24: 0 | I24: =G24-E24 -> 0 | V24: =SUM(K24:T24) -> 0
B25: Right-to-Use Leased Equipment - Amortizable | V25: =SUM(K25:T25) -> 0
B26: Right-to-Use Subscription-Based Information Technology Arrangements (SBITA) - Amortizable (2418) | E26: 0 | G26: 0 | I26: =G26-E26 -> 0 | S26: 0 | V26: =SUM(K26:T26) -> 0
B27: Land Use Rights - Non-Amortizable (2422) | V27: =SUM(K27:T27) -> 0
B28: Patents, Copyrights, and Trademarks - Non-Amortizable | I28: =G28-E28 -> 0 | V28: =SUM(K28:T28) -> 0
A29: Total | E29: =SUM(E12:E28) -> 1.5350978e+09 | G29: =SUM(G12:G28) -> 1.539243e+09 | I29: =SUM(I12:I28) -> 4145200 | K29: =SUM(K12:K28) -> 0 | M29: =SUM(M12:M28) -> 0 | O29: =SUM(O12:O28) -> 0 | Q29: =SUM(Q12:Q28) -> 4145200 | S29: =SUM(S12:S28) -> 0 | T29: =SUM(T12:T28) -> 0 | V29: =SUM(V12:V28) -> 4145200
A32: Report Instructions:
A33: Col. 1 - | C33: Enter Ending Balance from Prior Year Report 18.
A34: Col. 2 - | C34: Enter Beginning Balance from Current Year Report 18.
A35: Col. 3 - | C35: Compute difference between current year beginning balance and prior year ending balance.
C36: Research posting and source documents to identify and explain the difference.
A37: Col. 4 - 9 | C37: Breakdown and categorize the differences in columns 4 to 9.
A38: Col. 10 - | C38: Compute the sum of columns 4 to 8. The amount should agree with the computed difference in column 3.

Sheet 6059
I1: Page No : 20
A2: REPORT 18 – STATEMENT OF CHANGES IN CAPITAL ASSETS
A3: Department Name (2660)
A4: PUBLIC TRANSPORTATION MODERNIZATION, IMPROVEMENT AND SERVICE ENHANCEMENT ACCOUNT, HIGHWAY SAFETY, TRAFFIC REDUCTION, AIR QUALITY, AND PORT SECURITY FUND OF 2006 (6059)
A5: Fiscal Year 2023-24
A6: As of 06/30/2024
A7: Business Unit: | C7: 2660 - DEPARTMENT OF TRANSPORTATION | I7: Report ID: | J7: RPTGL075
A8: Fund: | C8: 6059 PUBLIC TRANSPORTATION ACCOUNT | I8: Run Date: | J8: =TODAY() -> 45723
I9: Run Time: | J9: =NOW() -> 45723.508
A14: Account – Description | F14: Beginning Balance | G14: Additions | H14: Deductions | J14: Ending Balance
A15: Tangible Assets
A16: 2310 Land a | J16: =F16+G16-H16 -> 0
A17: 2321 Buildings | J17: =F17+G17-H17 -> 0
A18: 2331 Improvements Other Than Buildings | J18: =F18+G18-H18 -> 0
A19: 2341 Equipment | F19: 1.1975235e+08 | G19: 6361920 | J19: =F19+G19-H19 -> 1.2611427e+08
A20: 2350 Construction Work in Progress a | J20: =F20+G20-H20 -> 0
A21: 2361 Infrastructure - Non Depreciable a | J21: =F21+G21-H21 -> 0
A23: Intangible Assets
A24: 2411 Computer Software - Amortizable | F24: 17650 | J24: =F24+G24-H24 -> 17650
A25: 2412 Land Use Rights - Amortizable | J25: =F25+G25-H25 -> 0
A26: 2413 Patents, Copyrights, and Trademarks - Amortizable | J26: =F26+G26-H26 -> 0
A27: 2414 Other Intangible Assets - Amortizable | J27: =F27+G27-H27 -> 0
A28: 2415 Right-to-Use Leased Land - Amortizable | J28: =F28+G28-H28 -> 0
A29: 2416 Right-to-Use Leased Buildings - Amortizable | J29: =F29+G29-H29 -> 0
A30: 2417 Right-to-Use Leased Equipment - Amortizable | J30: =F30+G30-H30 -> 0
A31: 2418 Right-to-Use Subscription-Based Information Technology Arrangements (SBITA) - Amortizable | J31: =F31+G31-H31 -> 0
A32: 2422 Land Use Rights - Non-Amortizable | J32: =F32+G32-H32 -> 0
A35: Fund: | B35: 6059 | F35: =SUM(F16:F34) -> 1.1977e+08 | G35: =SUM(G16:G34) -> 6361920 | H35: =SUM(H16:H34) -> 0 | J35: =SUM(J16:J34) -> 1.2613192e+08
A37: Note:
A38: a - Infrastructure only.
A40: I certify (or declare) under penalty of perjury that the attached reports are true, accurate and complete, and were prepared following the applicable laws, regulations, policies, procedures, and instructions. I have not violated any of the provisions of Article 4, Chapter 1, Division 4, Title 1, Government Code (commencing with Section 1090) and Article 2, Chapter 1, Part 3, Division 3, Title 2, Government Code (commencing with Section 13030).
A46: Subscribed and executed this 30th day of August, 2024 at Sacramento, California.
I52: KIM PHAN, Chief
I53: Service Transactions & Asset
I54: Reconciliation Section

Sheet 6060
I1: Page No : 21
A2: REPORT 18 – STATEMENT OF CHANGES IN CAPITAL ASSETS
A3: Department Name (2660)
A4: STATE AND LOCAL PARTNERSHIP PROGRAM ACCOUNT, HIGHWAY SAFETY, TRAFFIC REDUCTION, AIR QUALITY, AND PORT SECURITY FUND OF 2006 (6060)
A5: Fiscal Year 2023-24
A6: As of 06/30/2024
A7: Business Unit: | C7: 2660 - DEPARTMENT OF TRANSPORTATION | I7: Report ID: | J7: RPTGL075
A8: Fund: | C8: 6060 STATE AND LOCAL PARTNERSHIP PROGRAM ACCOUNT | I8: Run Date: | J8: =TODAY() -> 45723
I9: Run Time: | J9: =NOW() -> 45723.508
A14: Account – Description | F14: Beginning Balance | G14: Additions | H14: Deductions | J14: Ending Balance
A15: Tangible Assets
A16: 2310 Land a | J16: =F16+G16-I16 -> 0
A17: 2321 Buildings | J17: =F17+G17-I17 -> 0
A18: 2331 Improvements Other Than Buildings | J18: =F18+G18-I18 -> 0
A19: 2341 Equipment | J19: =F19+G19-I19 -> 0
A20: 2350 Construction Work in Progress a | F20: 70918750 | G20: 0 | H20: 1937804.6 | J20: =F20+G20-H20 -> 68980946
A21: 2361 Infrastructure - Non Depreciable a | F21: 1.6131754e+08 | G21: 1937804.6 | H21: 0 | J21: =F21+G21-H21 -> 1.6325535e+08
J22: =F22+G22-I22 -> 0
A23: Intangible Assets | J23: =F23+G23-I23 -> 0
A24: 2411 Computer Software - Amortizable | F24: 13398.02 | J24: =F24+G24-I24 -> 13398.02
A25: 2412 Land Use Rights - Amortizable | J25: =F25+G25-I25 -> 0
A26: 2413 Patents, Copyrights, and Trademarks - Amortizable | J26: =F26+G26-I26 -> 0
A27: 2414 Other Intangible Assets - Amortizable | J27: =F27+G27-I27 -> 0
A28: 2415 Right-to-Use Leased Land - Amortizable | J28: =F28+G28-I28 -> 0
A29: 2416 Right-to-Use Leased Buildings - Amortizable | J29: =F29+G29-I29 -> 0
A30: 2417 Right-to-Use Leased Equipment - Amortizable | J30: =F30+G30-I30 -> 0
A31: 2418 Right-to-Use Subscription-Based Information Technology Arrangements (SBITA) - Amortizable | J31: =F31+G31-I31 -> 0
A32: 2422 Land Use Rights - Non-Amortizable | J32: =F32+G32-I32 -> 0
A35: Fund: | B35: 6060 | F35: =SUM(F16:F34) -> 2.3224969e+08 | G35: =SUM(G16:G34) -> 1937804.6 | H35: =SUM(H16:H34) -> 1937804.6 | J35: =SUM(J16:J34) -> 2.3224969e+08
A37: Note:
A38: a - Infrastructure only.
A40: b - The $1,937,804.59 in Construction Work in Progress' Deductions which represents FY 2023/2024's Transfer from CWIP to Non-Depreciable Infrastructure (Completed).
A43: I certify (or declare) under penalty of perjury that the attached reports are true, accurate and complete, and were prepared following the applicable laws, regulations, policies, procedures, and instructions. I have not violated any of the provisions of Article 4, Chapter 1, Division 4, Title 1, Government Code (commencing with Section 1090) and Article 2, Chapter 1, Part 3, Division 3, Title 2, Government Code (commencing with Section 13030).
A48: Subscribed and executed this 30th day of August, 2024 at Sacramento, California.
I54: KIM PHAN, Chief
I55: Service Transactions & Asset
I56: Reconciliation Section

Sheet 6062
I1: Page No : 22
A2: REPORT 18 – STATEMENT OF CHANGES IN CAPITAL ASSETS
A3: Department Name (2660)
A4: LOCAL BRIDGE SEISMIC RETROFIT ACCOUNT, HIGHWAY SAFETY, TRAFFIC REDUCTION, AIR QUALITY, AND PORT SECURITY FUND OF 2006 (6062)
A5: Fiscal Year 2023-24
A6: As of 06/30/2024
A7: Business Unit: | C7: 2660 - DEPARTMENT OF TRANSPORTATION | I7: Report ID: | J7: RPTGL075
A8: Fund: | C8: 6062 LOCAL BRIDGE SEISMIC RETROFIT ACCOUNT | I8: Run Date: | J8: =TODAY() -> 45723
I9: Run Time: | J9: =NOW() -> 45723.508
A14: Account – Description | F14: Beginning Balance | G14: Additions | H14: Deductions | J14: Ending Balance
A15: Tangible Assets
A16: 2310 Land a | J16: =F16+G16-H16 -> 0
A17: 2321 Buildings | J17: =F17+G17-H17 -> 0
A18: 2331 Improvements Other Than Buildings | J18: =F18+G18-H18 -> 0
A19: 2341 Equipment | J19: =F19+G19-H19 -> 0
A20: 2350 Construction Work in Progress a | J20: =F20+G20-H20 -> 0
A21: 2361 Infrastructure - Non Depreciable a | J21: =F21+G21-H21 -> 0
A23: Intangible Assets
A24: 2411 Computer Software - Amortizable | F24: 3704.16 | J24: =F24+G24-H24 -> 3704.16
A25: 2412 Land Use Rights - Amortizable | J25: =F25+G25-H25 -> 0
A26: 2413 Patents, Copyrights, and Trademarks - Amortizable | J26: =F26+G26-H26 -> 0
A27: 2414 Other Intangible Assets - Amortizable | J27: =F27+G27-H27 -> 0
A28: 2415 Right-to-Use Leased Land - Amortizable | J28: =F28+G28-H28 -> 0
A29: 2416 Right-to-Use Leased Buildings - Amortizable | J29: =F29+G29-H29 -> 0
A30: 2417 Right-to-Use Leased Equipment - Amortizable | J30: =F30+G30-H30 -> 0
A31: 2418 Right-to-Use Subscription-Based Information Technology Arrangements (SBITA) - Amortizable | J31: =F31+G31-H31 -> 0
A32: 2422 Land Use Rights - Non-Amortizable | J32: =F32+G32-H32 -> 0
A35: Fund: | B35: 6062 | F35: =SUM(F16:F34) -> 3704.16 | G35: =SUM(G16:G34) -> 0 | H35: =SUM(H16:H34) -> 0 | J35: =SUM(J16:J34) -> 3704.16
A37: Note:
A38: a - Infrastructure only.
A40: I certify (or declare) under penalty of perjury that the attached reports are true, accurate and complete, and were prepared following the applicable laws, regulations, policies, procedures, and instructions. I have not violated any of the provisions of Article 4, Chapter 1, Division 4, Title 1, Government Code (commencing with Section 1090) and Article 2, Chapter 1, Part 3, Division 3, Title 2, Government Code (commencing with Section 13030).
A46: Subscribed and executed this 30th day of August, 2024 at Sacramento, California.
I52: KIM PHAN, Chief
I53: Service Transactions & Asset
I54: Reconciliation Section

Sheet 6063
I1: Page No : 23
A2: REPORT 18 – STATEMENT OF CHANGES IN CAPITAL ASSETS
A3: Department Name (2660)
A4: HIGHWAY-RAILROAD CROSSING SAFETY ACCOUNT, HIGHWAY SAFETY, TRAFFIC REDUCTION, AIR QUALITY, AND PORT SECURITY FUND OF 2006 (6063)
A5: Fiscal Year 2023-24
A6: As of 06/30/2024
A7: Business Unit: | C7: 2660 - DEPARTMENT OF TRANSPORTATION | I7: Report ID: | J7: RPTGL075
A8: Fund: | C8: 6063 HIGHWAY-RAILROAD CROSSING SAFETY ACCOUNT | I8: Run Date: | J8: =TODAY() -> 45723
I9: Run Time: | J9: =NOW() -> 45723.508
A14: Account – Description | F14: Beginning Balance | G14: Additions | H14: Deductions | J14: Ending Balance
A15: Tangible Assets
A16: 2310 Land a | J16: =F16+G16-H16 -> 0
A17: 2321 Buildings | J17: =F17+G17-H17 -> 0
A18: 2331 Improvements Other Than Buildings | J18: =F18+G18-H18 -> 0
A19: 2341 Equipment | J19: =F19+G19-H19 -> 0
A20: 2350 Construction Work in Progress a | J20: =F20+G20-H20 -> 0
A21: 2361 Infrastructure - Non Depreciable a | J21: =F21+G21-H21 -> 0
A23: Intangible Assets
A24: 2411 Computer Software - Amortizable | F24: 7986.09 | J24: =F24+G24-H24 -> 7986.09
A25: 2412 Land Use Rights - Amortizable | J25: =F25+G25-H25 -> 0
A26: 2413 Patents, Copyrights, and Trademarks - Amortizable | J26: =F26+G26-H26 -> 0
A27: 2414 Other Intangible Assets - Amortizable | J27: =F27+G27-H27 -> 0
A28: 2415 Right-to-Use Leased Land - Amortizable | J28: =F28+G28-H28 -> 0
A29: 2416 Right-to-Use Leased Buildings - Amortizable | J29: =F29+G29-H29 -> 0
A30: 2417 Right-to-Use Leased Equipment - Amortizable | J30: =F30+G30-H30 -> 0
A31: 2418 Right-to-Use Subscription-Based Information Technology Arrangements (SBITA) - Amortizable | J31: =F31+G31-H31 -> 0
A32: 2422 Land Use Rights - Non-Amortizable | J32: =F32+G32-H32 -> 0
A35: Fund: | B35: 6063 | F35: =SUM(F16:F34) -> 7986.09 | G35: =SUM(G16:G34) -> 0 | H35: =SUM(H16:H34) -> 0 | J35: =SUM(J16:J34) -> 7986.09
A37: Note:
A38: a - Infrastructure only.
A40: I certify (or declare) under penalty of perjury that the attached reports are true, accurate and complete, and were prepared following the applicable laws, regulations, policies, procedures, and instructions. I have not violated any of the provisions of Article 4, Chapter 1, Division 4, Title 1, Government Code (commencing with Section 1090) and Article 2, Chapter 1, Part 3, Division 3, Title 2, Government Code (commencing with Section 13030).
A46: Subscribed and executed this 30th day of August, 2024 at Sacramento, California.
I55: KIM PHAN, Chief
I56: Service Transactions & Asset
I57: Reconciliation Section

Sheet 6064
I1: Page No : 24
A2: REPORT 18 – STATEMENT OF CHANGES IN CAPITAL ASSETS
A3: Department Name (2660)
A4: HIGHWAY SAFETY, REHABILITATION, AND PRESERVATION ACCOUNT, HIGHWAY SAFETY, TRAFFIC REDUCTION, AIR QUALITY, AND PORT SECURITY FUND OF 2006 (6064)
A5: Fiscal Year 2023-24
A6: As of 06/30/2024
A7: Business Unit: | C7: 2660 - DEPARTMENT OF TRANSPORTATION | I7: Report ID: | J7: RPTGL075
A8: Fund: | C8: 6064 HIGHWAY SAFETY, REHABILITATION, AND PRESERVATION ACCOUNT | I8: Run Date: | J8: =TODAY() -> 45723
I9: Run Time: | J9: =NOW() -> 45723.508
A14: Account – Description | F14: Beginning Balance | G14: Additions | H14: Deductions | J14: Ending Balance
A15: Tangible Assets
A16: 2310 Land a | F16: 44393.46 | G16: 0 | H16: 0 | J16: =F16+G16-H16 -> 44393.46
A17: 2321 Buildings | F17: 12276284 | J17: =F17+G17-H17 -> 12276284
A18: 2331 Improvements Other Than Buildings | J18: =F18+G18-H18 -> 0
A19: 2341 Equipment | F19: 11381.36 | J19: =F19+G19-H19 -> 11381.36
A20: 2350 Construction Work in Progress a | F20: 2150338.8 | G20: 0 | H20: 0 | J20: =F20+G20-H20 -> 2150338.8
A21: 2361 Infrastructure - Non Depreciable a | F21: 1.3940397e+08 | G21: 764654.21 | H21: 0 | J21: =F21+G21-H21 -> 1.4016863e+08
A23: Intangible Assets
A24: 2411 Computer Software - Amortizable | F24: 19833.02 | J24: =F24+G24-H24 -> 19833.02
A25: 2412 Land Use Rights - Amortizable | J25: =F25+G25-H25 -> 0
A26: 2413 Patents, Copyrights, and Trademarks - Amortizable | J26: =F26+G26-H26 -> 0
A27: 2414 Other Intangible Assets - Amortizable | J27: =F27+G27-H27 -> 0
A28: 2415 Right-to-Use Leased Land - Amortizable | J28: =F28+G28-H28 -> 0
A29: 2416 Right-to-Use Leased Buildings - Amortizable | J29: =F29+G29-H29 -> 0
A30: 2417 Right-to-Use Leased Equipment - Amortizable | J30: =F30+G30-H30 -> 0
A31: 2418 Right-to-Use Subscription-Based Information Technology Arrangements (SBITA) - Amortizable | J31: =F31+G31-H31 -> 0
A32: 2422 Land Use Rights - Non-Amortizable | J32: =F32+G32-H32 -> 0
A35: Fund: | B35: 6064 | F35: =SUM(F16:F34) -> 1.539062e+08 | G35: =SUM(G16:G34) -> 764654.21 | H35: =SUM(H16:H34) -> 0 | J35: =SUM(J16:J34) -> 1.5467086e+08
A37: Note:
A38: a - Infrastructure only.
A40: I certify (or declare) under penalty of perjury that the attached reports are true, accurate and complete, and were prepared following the applicable laws, regulations, policies, procedures, and instructions. I have not violated any of the provisions of Article 4, Chapter 1, Division 4, Title 1, Government Code (commencing with Section 1090) and Article 2, Chapter 1, Part 3, Division 3, Title 2, Government Code (commencing with Section 13030).
A46: Subscribed and executed this 30th day of August, 2024 at Sacramento, California.
I52: KIM PHAN, Chief
I53: Service Transactions & Asset
I54: Reconciliation Section

Sheet 6072
I1: Page No : 25
A2: REPORT 18 – STATEMENT OF CHANGES IN CAPITAL ASSETS
A3: Department Name (2660)
A4: ROUTE 99 ACCOUNT, STATE, HIGHWAY SAFETY, TRAFFIC REDUCTION, AIR QUALITY, AND PORT SECURITY FUND OF 2006 (6072)
A5: Fiscal Year 2023-24
A6: As of 06/30/2024
A7: Business Unit: | C7: 2660 - DEPARTMENT OF TRANSPORTATION | I7: Report ID: | J7: RPTGL075
A8: Fund: | C8: 6072 ROUTE 99 ACCOUNT | I8: Run Date: | J8: =TODAY() -> 45723
I9: Run Time: | J9: =NOW() -> 45723.508
A14: Account – Description | F14: Beginning Balance | G14: Additions | H14: Deductions | J14: Ending Balance
A15: Tangible Assets
A16: 2310 Land a | F16: 54698810 | G16: 31959.16 | H16: 0 | J16: =F16+G16-H16 -> 54730769
A17: 2321 Buildings | J17: =F17+G17-H17 -> 0
A18: 2331 Improvements Other Than Buildings | J18: =F18+G18-H18 -> 0
A19: 2341 Equipment | F19: 15086.92 | J19: =F19+G19-H19 -> 15086.92
A20: 2350 Construction Work in Progress a | F20: 46019932 | G20: 2226435.2 | H20: 39558597 | J20: =F20+G20-H20 -> 8687770.7
A21: 2361 Infrastructure - Non Depreciable a | F21: 8.1173466e+08 | G21: 40116863 | H21: 0.01 | J21: =F21+G21-H21 -> 8.5185152e+08
J22: =F22+G22-H22 -> 0
A23: Intangible Assets | J23: =F23+G23-H23 -> 0
A24: 2411 Computer Software - Amortizable | F24: 25341.54 | J24: =F24+G24-H24 -> 25341.54
A25: 2412 Land Use Rights - Amortizable | J25: =F25+G25-H25 -> 0
A26: 2413 Patents, Copyrights, and Trademarks - Amortizable | J26: =F26+G26-H26 -> 0
A27: 2414 Other Intangible Assets - Amortizable | J27: =F27+G27-H27 -> 0
A28: 2415 Right-to-Use Leased Land - Amortizable | J28: =F28+G28-H28 -> 0
A29: 2416 Right-to-Use Leased Buildings - Amortizable | J29: =F29+G29-H29 -> 0
A30: 2417 Right-to-Use Leased Equipment - Amortizable | J30: =F30+G30-H30 -> 0
A31: 2418 Right-to-Use Subscription-Based Information Technology Arrangements (SBITA) - Amortizable | J31: =F31+G31-H31 -> 0
A32: 2422 Land Use Rights - Non-Amortizable | J32: =F32+G32-H32 -> 0
A35: Fund: | B35: 6072 | F35: =SUM(F16:F34) -> 9.1249383e+08 | G35: =SUM(G16:G34) -> 42375257 | H35: =SUM(H16:H34) -> 39558597 | J35: =SUM(J16:J34) -> 9.1531049e+08
A37: Note:
A38: a - Infrastructure only.
A40: b - The $39,558,596.76 in Construction Work in Progress' Deductions which represents FY 2023/2024's Transfer from CWIP to Non-Depreciable Infrastructure (Completed).
A43: I certify (or declare) under penalty of perjury that the attached reports are true, accurate and complete, and were prepared following the applicable laws, regulations, policies, procedures, and instructions. I have not violated any of the provisions of Article 4, Chapter 1, Division 4, Title 1, Government Code (commencing with Section 1090) and Article 2, Chapter 1, Part 3, Division 3, Title 2, Government Code (commencing with Section 13030).
A49: Subscribed and executed this 30th day of August, 2024 at Sacramento, California.
I55: KIM PHAN, Chief
I56: Service Transactions & Asset
I57: Reconciliation Section

Sheet 6801
I1: Page No : 26
A2: REPORT 18 – STATEMENT OF CHANGES IN CAPITAL ASSETS
A3: Department Name (2660)
A4: GARVEE BONDS CONSTRUCTION FUND (6801)
A5: Fiscal Year 2023-24
A6: As of 06/30/2024
A7: Business Unit: | C7: 2660 - DEPARTMENT OF TRANSPORTATION | I7: Report ID: | J7: RPTGL075
A8: Fund: | C8: 6801 GARVEE BONDS CONSTRUCTION FUND | I8: Run Date: | J8: =TODAY() -> 45723
I9: Run Time: | J9: =NOW() -> 45723.508
A14: Account – Description | F14: Beginning Balance | G14: Additions | H14: Deductions | J14: Ending Balance
A15: Tangible Assets
A16: 2310 Land a | F16: 64778024 | G16: 0 | H16: 0 | J16: =F16+G16-H16 -> 64778024
A17: 2321 Buildings | H17: 0 | J17: =F17+G17-H17 -> 0
A18: 2331 Improvements Other Than Buildings | H18: 0 | J18: =F18+G18-H18 -> 0
A19: 2341 Equipment | J19: =F19+G19-H19 -> 0
A20: 2350 Construction Work in Progress a | F20: 82137767 | G20: 0 | H20: 0 | J20: =F20+G20-H20 -> 82137767
A21: 2361 Infrastructure - Non Depreciable a | F21: 4.679722e+08 | H21: 0 | J21: =F21+G21-H21 -> 4.679722e+08
A23: Intangible Assets
A24: 2411 Computer Software - Amortizable | J24: =F24+G24-H24 -> 0
A25: 2412 Land Use Rights - Amortizable | J25: =F25+G25-H25 -> 0
A26: 2413 Patents, Copyrights, and Trademarks - Amortizable | J26: =F26+G26-H26 -> 0
A27: 2414 Other Intangible Assets - Amortizable | J27: =F27+G27-H27 -> 0
A28: 2415 Right-to-Use Leased Land - Amortizable | J28: =F28+G28-H28 -> 0
A29: 2416 Right-to-Use Leased Buildings - Amortizable | J29: =F29+G29-H29 -> 0
A30: 2417 Right-to-Use Leased Equipment - Amortizable | J30: =F30+G30-H30 -> 0
A31: 2418 Right-to-Use Subscription-Based Information Technology Arrangements (SBITA) - Amortizable | J31: =F31+G31-H31 -> 0
A32: 2422 Land Use Rights - Non-Amortizable | J32: =F32+G32-H32 -> 0
A35: Fund: | B35: 6081 | F35: =SUM(F16:F34) -> 6.1488799e+08 | G35: =SUM(G16:G34) -> 0 | H35: =SUM(H16:H34) -> 0 | J35: =SUM(J16:J34) -> 6.1488799e+08
A37: Note:
A38: a - Infrastructure only.
A40: I certify (or declare) under penalty of perjury that the attached reports are true, accurate and complete, and were prepared following the applicable laws, regulations, policies, procedures, and instructions. I have not violated any of the provisions of Article 4, Chapter 1, Division 4, Title 1, Government Code (commencing with Section 1090) and Article 2, Chapter 1, Part 3, Division 3, Title 2, Government Code (commencing with Section 13030).
A46: Subscribed and executed this 30th day of August, 2024 at Sacramento, California.
I52: KIM PHAN, Chief
I53: Service Transactions & Asset
I54: Reconciliation Section

Sheet Report 19
A1: Page No: 1 | F1: Page No : 27 | K1: Land | L1: Building | M1: Improvements Other Than Buildings | N1: Equipment | O1: Const WIP | P1: Non-Depreciable Infrastructure (means GASB34 completed projects) | Q1: Computer Software | R1: Land Use Rights - Amortizable | S1: Patents, Copyrights, and Trademarks - Amortizable | T1: Other Intangible Assets - Amortizable | U1: Right-to-Use Leased Land - Amortizable | V1: Right-to-Use Leased Building - Amortizable | W1: Right-to-Use Leased Equipment - Amortizable | X1: Right-to-Use SBITA - Amortizable | Y1: Land Use Rights - Non-Amortizable | Z1: Total | AA1: FXF
A2: REPORT 19 - STATEMENT OF CAPITAL ASSETS
A3: DEPARTMENT OF TRANSPORTATION (2660)
A4: Fiscal Year 2023-24
A5: As of 06/30/2024 | AB5: Variance | AD5: BB Only
A6: Business Unit: 2660 - DEPARTMENT OF TRANSPORTATION | F6: Report ID: | G6: RPTGL076 | J6: Fund 0001 | K6: 955511.52 | L6: 105422.6 | M6: 0 | N6: 642153.22 | O6: 1.1695997e+08 | P6: 56121306 | Q6: 0 | R6: 0 | S6: 0 | T6: 0 | U6: 0 | V6: 0 | W6: 0 | X6: 0 | Y6: 0 | Z6: 1.7478436e+08 | AA6: =SUM(K6:Y6) -> 1.7478436e+08 | AB6: =Z6-AA6 -> 0 | AD6: Fund 0001 | AE6: 71934471
F7: Run Date: | G7: =TODAY() -> 45723 | J7: Fund 0041 | K7: 0 | L7: 0 | M7: 0 | N7: 1161084.4 | O7: 0 | P7: 0 | Q7: 46857.88 | R7: 0 | S7: 0 | T7: 0 | U7: 0 | V7: 0 | W7: 0 | X7: 2471.9149 | Y7: 0 | Z7: 1210414.2 | AA7: =SUM(K7:Y7) -> 1210414.2 | AB7: =Z7-AA7 -> 0 | AD7: Fund 0041 | AE7: 1210614.5
F8: Run Time: | G8: =NOW() -> 45723.508 | J8: Fund 0042 | K8: 1.5712106e+10 | L8: 1.4582649e+09 | M8: 0 | N8: 1.6234132e+09 | O8: 8.4746656e+09 | P8: 7.6987312e+10 | Q8: 2.0982805e+08 | R8: 0 | S8: 374638.98 | T8: 0 | U8: 0 | V8: 1.0666614e+08 | W8: 0 | X8: 7305084.9 | Y8: 0 | Z8: 1.0457994e+11 | AA8: =SUM(K8:Y8) -> 1.0457994e+11 | AB8: =Z8-AA8 -> 0 | AD8: Fund 0042 | AE8: 1.0272311e+11
J9: Fund 0046 | K9: 0 | L9: 0 | M9: 0 | N9: 41332295 | O9: 0 | P9: 7120136.5 | Q9: 2626111.9 | R9: 0 | S9: 0 | T9: 0 | U9: 0 | V9: 0 | W9: 17089708 | X9: 117526.95 | Y9: 0 | Z9: 68285778 | AA9: =SUM(K9:Y9) -> 68285778 | AB9: =Z9-AA9 -> 0 | AD9: Fund 0046 | AE9: 66604007
A10: CAPITAL ASSETS: | C10: DEBIT BALANCE | E10: CREDIT BALANCE | J10: Fund 0183 | K10: 0 | L10: 0 | M10: 0 | N10: 0 | O10: 61012094 | P10: 1657162.1 | Q10: 0 | R10: 0 | S10: 0 | T10: 0 | U10: 0 | V10: 0 | W10: 0 | X10: 0 | Y10: 0 | Z10: 62669256 | AA10: =SUM(K10:Y10) -> 62669256 | AB10: =Z10-AA10 -> 0 | AD10: Fund 0183 | AE10: 62669256
A11: Tangible Assets | J11: Fund 0523 | K11: 8000000 | L11: 2.8527591e+08 | M11: 0 | N11: 0 | O11: 0 | P11: 0 | Q11: 0 | R11: 0 | S11: 0 | T11: 0 | U11: 0 | V11: 0 | W11: 0 | X11: 0 | Y11: 0 | Z11: 2.9327591e+08 | AA11: =SUM(K11:Y11) -> 2.9327591e+08 | AB11: =Z11-AA11 -> 0 | AD11: Fund 0523 | AE11: 2.9327591e+08
A12: 2310 - Land | B12: =K32 -> 1.6210783e+10 | J12: Fund 0541 | K12: 0 | L12: 56772761 | M12: 0 | N12: 0 | O12: 0 | P12: 0 | Q12: 0 | R12: 0 | S12: 0 | T12: 0 | U12: 0 | V12: 0 | W12: 0 | X12: 0 | Y12: 0 | Z12: 56772761 | AA12: =SUM(K12:Y12) -> 56772761 | AB12: =Z12-AA12 -> 0 | AD12: Fund 0541 | AE12: 56772761
A13: 2321 - Buildings | B13: =L32 -> 1.8257841e+09 | J13: Fund 0653 | K13: 300093.59 | L13: 13055910 | M13: 0 | N13: 267582.18 | O13: 1743959.2 | P13: 61523709 | Q13: 0 | R13: 0 | S13: 0 | T13: 0 | U13: 0 | V13: 0 | W13: 0 | X13: 0 | Y13: 0 | Z13: 76891254 | AA13: =SUM(K13:Y13) -> 76891254 | AB13: =Z13-AA13 -> 0 | AD13: Fund 0653 | AE13: 76891254
A14: 2341 - Equipment | B14: =N32 -> 1.9735115e+09 | J14: Fund 0673 | K14: 0 | L14: 0 | M14: 0 | N14: 6674000 | O14: 0 | P14: 0 | Q14: 0 | R14: 0 | S14: 0 | T14: 0 | U14: 0 | V14: 0 | W14: 0 | X14: 0 | Y14: 0 | Z14: 6674000 | AA14: =SUM(K14:Y14) -> 6674000 | AB14: =Z14-AA14 -> 0 | AD14: Fund 0673 | AE14: 6674000
A15: 2350 - Construction Work in Progress | B15: =O32 -> 1.0488664e+10 | J15: Fund 0703 | K15: 0 | L15: 0 | M15: 0 | N15: 70479745 | O15: 0 | P15: 0 | Q15: 0 | R15: 0 | S15: 0 | T15: 0 | U15: 0 | V15: 0 | W15: 0 | X15: 0 | Y15: 0 | Z15: 70479745 | AA15: =SUM(K15:Y15) -> 70479745 | AB15: =Z15-AA15 -> 0 | AD15: Fund 0703 | AE15: 70479745
A16: 2361 - Infrastructure - Non Depreciable | B16: =P32 -> 8.4499032e+10 | J16: Fund 0756 | K16: 0 | L16: 0 | M16: 0 | N16: 1.0175604e+08 | O16: 0 | P16: 0 | Q16: 0 | R16: 0 | S16: 0 | T16: 0 | U16: 0 | V16: 0 | W16: 0 | X16: 0 | Y16: 0 | Z16: 1.0175604e+08 | AA16: =SUM(K16:Y16) -> 1.0175604e+08 | AB16: =Z16-AA16 -> 0 | AD16: Fund 0756 | AE16: 1.0175604e+08
J17: Fund 0942 | K17: 0 | L17: 0 | M17: 0 | N17: 0 | O17: 56415040 | P17: 0 | Q17: 0 | R17: 0 | S17: 0 | T17: 0 | U17: 0 | V17: 0 | W17: 0 | X17: 0 | Y17: 0 | Z17: 56415040 | AA17: =SUM(K17:Y17) -> 56415040 | AB17: =Z17-AA17 -> 0 | AD17: Fund 0942 | AE17: 56384988
J18: Fund 2504 | K18: 0 | L18: 0 | M18: 0 | N18: 0 | O18: 0 | P18: 0 | Q18: 0 | R18: 3187845 | S18: 0 | T18: 0 | U18: 0 | V18: 0 | W18: 0 | X18: 0 | Y18: 0 | Z18: 3187845 | AA18: =SUM(K18:Y18) -> 3187845 | AB18: =Z18-AA18 -> 0 | AD18: Fund 2504 | AE18: 0
A19: Intangible Assets | J19: Fund 3007 | K19: 3.2482045e+08 | L19: 0 | M19: 0 | N19: 122733.78 | O19: 3.0664624e+08 | P19: 5.5702409e+08 | Q19: 0 | R19: 0 | S19: 0 | T19: 0 | U19: 0 | V19: 0 | W19: 0 | X19: 0 | Y19: 0 | Z19: 1.1886135e+09 | AA19: =SUM(K19:Y19) -> 1.1886135e+09 | AB19: =Z19-AA19 -> 0 | AD19: Fund 3007 | AE19: 1.1885642e+09
A20: 2411 - Computer Software - Amortizable | B20: =Q32 -> 2.1395501e+08 | J20: Fund 3290 | K20: 22066908 | L20: 9485.68 | M20: 0 | N20: 1516824.6 | O20: 4.1190413e+08 | P20: 4.7512793e+08 | Q20: 1148806.9 | R20: 0 | S20: 0 | T20: 0 | U20: 0 | V20: 12114958 | W20: 0 | X20: 36450.18 | Y20: 0 | Z20: 9.2392549e+08 | AA20: =SUM(K20:Y20) -> 9.2392549e+08 | AB20: =Z20-AA20 -> 0 | AD20: Fund 3290 | AE20: 7.5282826e+08
A21: 2412 - Land Use Rights - Amortizable | B21: =R32 -> 3187845 | J21: Fund 3291 | K21: 22981244 | L21: 0 | M21: 0 | N21: 0 | O21: 2.78008e+08 | P21: 1.1631243e+08 | Q21: 0 | R21: 0 | S21: 0 | T21: 0 | U21: 0 | V21: 138842.33 | W21: 0 | X21: 0 | Y21: 0 | Z21: 4.1744051e+08 | AA21: =SUM(K21:Y21) -> 4.1744051e+08 | AB21: =Z21-AA21 -> 0 | AD21: Fund 3291 | AE21: 2.8478374e+08
A22: 2413 - Patents, Copyrights, and Trademarks - Amortizable | B22: =S32 -> 374638.98 | J22: Fund 6055 | K22: 0 | L22: 23461.91 | M22: 0 | N22: 0 | O22: 4.0923723e+08 | P22: 2.9046383e+09 | Q22: 163795.7 | R22: 0 | S22: 0 | T22: 0 | U22: 0 | V22: 0 | W22: 0 | X22: 0 | Y22: 0 | Z22: 3.3140628e+09 | AA22: =SUM(K22:Y22) -> 3.3140628e+09 | AB22: =Z22-AA22 -> 0 | AD22: Fund 6055 | AE22: 3.3140197e+09
A23: 2414 - Other Intangible Assets-Amortizable | B23: =T32 -> 0 | J23: Fund 6056 | K23: 0 | L23: 0 | M23: 0 | N23: 0 | O23: 1.2233573e+08 | P23: 2.4578237e+08 | Q23: 7255.86 | R23: 0 | S23: 0 | T23: 0 | U23: 0 | V23: 0 | W23: 0 | X23: 0 | Y23: 0 | Z23: 3.6812536e+08 | AA23: =SUM(K23:Y23) -> 3.6812536e+08 | AB23: =Z23-AA23 -> 0 | AD23: Fund 6056 | AE23: 3.6207464e+08
A24: 2415 - Right-to-Use Leased Land - Amortizable | B24: =U32 -> 0 | J24: Fund 6058 | K24: 0 | L24: 0 | M24: 0 | N24: 5131.6 | O24: 87779638 | P24: 1.4631646e+09 | Q24: 46218.78 | R24: 0 | S24: 0 | T24: 0 | U24: 0 | V24: 0 | W24: 0 | X24: 0 | Y24: 0 | Z24: 1.5509956e+09 | AA24: =SUM(K24:Y24) -> 1.5509956e+09 | AB24: =Z24-AA24 -> 0 | AD24: Fund 6058 | AE24: 1.539243e+09
A25: 2416 - Rights Leased Buildgs-Amortizable | B25: =V32 -> 1.1891994e+08 | J25: Fund 6059 | K25: 0 | L25: 0 | M25: 0 | N25: 1.2611427e+08 | O25: 0 | P25: 0 | Q25: 17650 | R25: 0 | S25: 0 | T25: 0 | U25: 0 | V25: 0 | W25: 0 | X25: 0 | Y25: 0 | Z25: 1.2613192e+08 | AA25: =SUM(K25:Y25) -> 1.2613192e+08 | AB25: =Z25-AA25 -> 0 | AD25: Fund 6059 | AE25: 1.1977e+08
A26: 2417 - Right-to-Use Leased Equipment - Amortizable | B26: =W32 -> 17089708 | J26: Fund 6060 | K26: 0 | L26: 0 | M26: 0 | N26: 0 | O26: 68980946 | P26: 1.6325535e+08 | Q26: 13398.02 | R26: 0 | S26: 0 | T26: 0 | U26: 0 | V26: 0 | W26: 0 | X26: 0 | Y26: 0 | Z26: 2.3224969e+08 | AA26: =SUM(K26:Y26) -> 2.3224969e+08 | AB26: =Z26-AA26 -> 0 | AD26: Fund 6060 | AE26: 2.3224969e+08
A27: 2418 - Right-to-use SBITA - Amortizable | B27: =X32 -> 7461533.9 | J27: Fund 6062 | K27: 0 | L27: 0 | M27: 0 | N27: 0 | O27: 0 | P27: 0 | Q27: 3704.16 | R27: 0 | S27: 0 | T27: 0 | U27: 0 | V27: 0 | W27: 0 | X27: 0 | Y27: 0 | Z27: 3704.16 | AA27: =SUM(K27:Y27) -> 3704.16 | AB27: =Z27-AA27 -> 0 | AD27: Fund 6062 | AE27: 3704.16
A28: 2422 - Land Use Rights - Non-Amortizable | B28: =Y32 -> 0 | J28: Fund 6063 | K28: 0 | L28: 0 | M28: 0 | N28: 0 | O28: 0 | P28: 0 | Q28: 7986.09 | R28: 0 | S28: 0 | T28: 0 | U28: 0 | V28: 0 | W28: 0 | X28: 0 | Y28: 0 | Z28: 7986.09 | AA28: =SUM(K28:Y28) -> 7986.09 | AB28: =Z28-AA28 -> 0 | AD28: Fund 6063 | AE28: 7986.09
A29: TOTAL CAPITAL ASSETS | J29: Fund 6064 | K29: 44393.46 | L29: 12276284 | M29: 0 | N29: 11381.36 | O29: 2150338.8 | P29: 1.4016863e+08 | Q29: 19833.02 | R29: 0 | S29: 0 | T29: 0 | U29: 0 | V29: 0 | W29: 0 | X29: 0 | Y29: 0 | Z29: 1.5467086e+08 | AA29: =SUM(K29:Y29) -> 1.5467086e+08 | AB29: =Z29-AA29 -> 0 | AD29: Fund 6064 | AE29: 1.539062e+08
B30: =SUM(B12:C28) -> 1.1535876e+11 | J30: Fund 6072 | K30: 54730769 | L30: 0 | M30: 0 | N30: 15086.92 | O30: 8687770.7 | P30: 8.5185152e+08 | Q30: 25341.54 | R30: 0 | S30: 0 | T30: 0 | U30: 0 | V30: 0 | W30: 0 | X30: 0 | Y30: 0 | Z30: 9.1531049e+08 | AA30: =SUM(K30:Y30) -> 9.1531049e+08 | AB30: =Z30-AA30 -> 0 | AD30: Fund 6072 | AE30: 9.1249383e+08
J31: Fund 6801 | K31: 64778024 | L31: 0 | M31: 0 | N31: 0 | O31: 82137767 | P31: 4.679722e+08 | Q31: 0 | R31: 0 | S31: 0 | T31: 0 | U31: 0 | V31: 0 | W31: 0 | X31: 0 | Y31: 0 | Z31: 6.1488799e+08 | AA31: =SUM(K31:Y31) -> 6.1488799e+08 | AB31: =Z31-AA31 -> 0 | AD31: Fund 6801 | AE31: 6.1488799e+08
A32: INVESTMENT IN CAPITAL ASSETS FROM:2 | K32: =SUM(K6:K31) -> 1.6210783e+10 | L32: =SUM(L6:L31) -> 1.8257841e+09 | M32: =SUM(M6:M31) -> 0 | N32: =SUM(N6:N31) -> 1.9735115e+09 | O32: =SUM(O6:O31) -> 1.0488664e+10 | P32: =SUM(P6:P31) -> 8.4499032e+10 | Q32: =SUM(Q6:Q31) -> 2.1395501e+08 | R32: =SUM(R6:R31) -> 3187845 | ... AA32: =SUM(AA6:AA31) -> 1.1535876e+11 | AB32: =SUM(AB7:AB31) -> 0 | AE32: =SUM(AE6:AE31) -> 1.130626e+11
A34: Fund: 0001 - General Fund | D34: ='0001'!J35 -> 1.7478436e+08
A35: Fund: 0041 - Aeronautics Fund | D35: ='0041'!J35 -> 1210414.2
A36: Fund: 0042 - State Highway Account Fund | D36: ='0042'!J35 -> 1.0457994e+11
A37: Fund: 0046 - Transportation Planning & Development Account Fund | D37: ='0046'!J35 -> 68285778
A38: Fund: 0183 - Environmental Enhancement and Mitigation | E38: ='0183'!J35 -> 62669256
A39: Fund: 0523 - East Bay State Building Authority Fund | D39: ='0523'!J35 -> 2.9327591e+08
A40: Fund: 0541 - San Bernardino State Building Authority | D40: ='0541'!J35 -> 56772761
A41: Fund: 0653 - Seismic Retrofit Bond Fund of 1996 | D41: ='0653'!J35 -> 76891254
A42: Fund: 0673 - PASSENGER EQUIPMENT ACQUISITION FUND | D42: ='0673'!J35 -> 6674000
A43: Fund: 0703 - Proposition 116 | D43: ='0703'!J35 -> 70479745
A44: Fund: 0756 - Passenger Rail Bond | D44: ='0756'!J35 -> 1.0175604e+08
A45: Fund: 0942 - Special Deposits Fund | D45: ='0942'!J35 -> 56415040
A46: Fund: 2504 - Traffic Congestion Relief Fund | F46: ='2504'!J35 -> 3187845
A47: Fund: 3007 - Traffic Congestion Relief Fund | D47: ='3007'!J35 -> 1.1886135e+09
A48: Fund: 3290 - Road Maintenance and Rehabilitation Account | D48: ='3290'!J35 -> 9.2392549e+08
A49: Fund: 3291 - Trade Corridor Enhancement Account | D49: ='3291'!J35 -> 4.1744051e+08
A50: Fund: 6055 - Corridor Mobility Improvement Account, Highway Safety, Traffic Reduction, Air Quality, and Port Security Fund of 2006 | D50: ='6055'!J35 -> 3.3140628e+09
A51: Fund: 6056 - Trade Corridors Improvement Fund | D51: ='6056'!J35 -> 3.6812536e+08
A52: Fund: 6058 - Transportation Facilities Account, Highway Safety, Traffic Reduction, Air Quality, and Port Security Fund of 2006 | D52: ='6058'!J35 -> 1.5509956e+09
A53: Fund: 6059- Public Transportation Modernization, Improvement and Service Enhancement Account, Highway Safety, Traffic Reduction, Air Quality, and Port Security Fund of 2006 | D53: ='6059'!J35 -> 1.2613192e+08
A54: Fund: 6060 - State-Local Partnership Program Account, Highway Safety, Traffic Reduction, Air Quality, and Port Security Fund of 2006 | D54: ='6060'!J35 -> 2.3224969e+08
A55: Fund: 6062 - Local Bridge Seismic Retrofit Account, Highway Safety, Traffic Reduction, Air Quality, and Port Security Fund of 2006 | D55: ='6062'!J35 -> 3704.16
A56: Fund: 6063 - Highway-Railroad Crossing Safety Account, Highway Safety, Traffic Reduction, Air Quality, and Port Security Fund of 2006 | D56: ='6063'!J35 -> 7986.09
A57: Fund: 6064 - Highway Safety, Rehabilitation, and Preservation Account, Highway Safety, Traffic Reduction, Air Quality, and Port Security Fund of 2006 | D57: ='6064'!J35 -> 1.5467086e+08
A58: Fund: 6072 - Route 99 Account, State, Highway Safety, Traffic Reduction, Air Quality, and Port Security Fund of 2006 | D58: ='6072'!J35 -> 9.1531049e+08
A59: Fund: 6801 - Garvee Bonds Construction Fund | D59: ='6801'!J35 -> 6.1488799e+08
A60: TOTAL INVESTMENT IN CAPITAL ASSETS | D60: =SUM(D34:G59) -> 1.1535876e+11
A63: 1. Physical inventories of capital assets are made at least once every three years.
A64: 2. Subsidiary capital asset records are in agreement with the general ledger control accounts shown above.
A67: I certify (or declare) under penalty of perjury that the attached reports are true, accurate and complete, and were prepared following the applicable laws, regulations, policies, procedures, and instructions. I have not violated any of the provisions of Article 4, Chapter 1, Division 4, Title 1, Government Code (commencing with Section 1090) and Article 2, Chapter 1, Part 3, Division 3, Title 2, Government Code (commencing with Section 13030).
A72: Subscribed and executed this 30th day of August, 2024 at Sacramento, California.
D76: KIM PHAN, Chief
D77: Service Transactions & Asset
D78: Reconciliation Section
