Workbook

Sheet F0001
A1: San Joaquin River Conservancy (3830)
A2: Statement of Changes in Capital Assets Group of Accounts - Report 18
A3: General Fund (0001)
A4: As of June 30, 2024
A6: CAPITAL ASSETS | D6: Beginning Balance1 | F6: Additions | H6: Deductions | J6: Balance2 June 30, 2024
A8: Tangible Assets
B9: Land | D9: 13049661 | J9: =D9+F9-H9 -> 13049661
B10: Buildings | J10: =D10+F10-H10 -> 0
B11: Improvements Other Than Buildings | J11: =D11+F11-H11 -> 0
B12: Equipment | J12: =D12+F12-H12 -> 0
B13: Construction Work in Progress | J13: =D13+F13-H13 -> 0
B14: Infrastructure - Depreciable | J14: =D14+F14-H14 -> 0
A15: Intangible Assets | J15: =D15+F15-H15 -> 0
B16: Computer Software - Amortizable | J16: =D16+F16-H16 -> 0
B17: Land Use Rights - Amortizable | J17: =D17+F17-H17 -> 0
B18: Patents, Copyrights, and Trademarks - Amortizable | J18: =D18+F18-H18 -> 0
B19: Other Intangible Assets - Amortizable | J19: =D19+F19-H19 -> 0
B20: Land Use Rights - Non-Amortizable | J20: =D20+F20-H20 -> 0
B21: Patents, Copyrights, and Trademarks - Non-Amortizable | J21: =D21+F21-H21 -> 0
B22: Other Intangible Assets - Non-Amortizable | J22: =D22+F22-H22 -> 0
B23: Internally Generated Intangible Assets in Progress | J23: =D23+F23-H23 -> 0
A24: TOTAL CAPITAL ASSETS | D24: =SUM(D9:D23) -> 13049661 | F24: =SUM(F9:F23) -> 0 | H24: =SUM(H9:H23) -> 0 | J24: =SUM(J9:J23) -> 13049661
A27: 1 | B27: Asset beginning balances must agree with prior year ending balances. Any differences must be documented and explained in Report 18-
B28: Statement of Changes in Capital Assets Beginning Balance Differential Report. See illustration next page.
A29: 2 | B29: The ending balances should equal the debit balances on Report 19 for each asset type.

Sheet F0545
A1: San Joaquin River Conservancy (3830)
A2: Statement of Changes in Capital Assets Group of Accounts - Report 18
A3: River Parkway Subaccount (0545)
A4: ='F0001'!A4:J4 -> As of June 30, 2024
A6: CAPITAL ASSETS | D6: Beginning Balance1 | F6: Additions | H6: Deductions | J6: Balance2 June 30, 2024
A8: Tangible Assets
B9: Land | D9: 5192903 | J9: =D9+F9-H9 -> 5192903
B10: Buildings | J10: =D10+F10-H10 -> 0
B11: Improvements Other Than Buildings | J11: =D11+F11-H11 -> 0
B12: Equipment | J12: =D12+F12-H12 -> 0
B13: Construction Work in Progress | J13: =D13+F13-H13 -> 0
B14: Infrastructure - Depreciable | J14: =D14+F14-H14 -> 0
A15: Intangible Assets | J15: =D15+F15-H15 -> 0
B16: Computer Software - Amortizable | J16: =D16+F16-H16 -> 0
B17: Land Use Rights - Amortizable | J17: =D17+F17-H17 -> 0
B18: Patents, Copyrights, and Trademarks - Amortizable | J18: =D18+F18-H18 -> 0
B19: Other Intangible Assets - Amortizable | J19: =D19+F19-H19 -> 0
B20: Land Use Rights - Non-Amortizable | J20: =D20+F20-H20 -> 0
B21: Patents, Copyrights, and Trademarks - Non-Amortizable | J21: =D21+F21-H21 -> 0
B22: Other Intangible Assets - Non-Amortizable | J22: =D22+F22-H22 -> 0
B23: Internally Generated Intangible Assets in Progress | J23: =D23+F23-H23 -> 0
A24: TOTAL CAPITAL ASSETS | D24: =SUM(D9:D23) -> 5192903 | F24: =SUM(F9:F23) -> 0 | H24: =SUM(H9:H23) -> 0 | J24: =SUM(J9:J23) -> 5192903
A27: 1 | B27: Asset beginning balances must agree with prior year ending balances. Any differences must be documented and explained in Report 18-
B28: Statement of Changes in Capital Assets Beginning Balance Differential Report. See illustration next page.
A29: 2 | B29: The ending balances should equal the debit balances on Report 19 for each asset type.

Sheet F0786
A1: San Joaquin River Conservancy (3830)
A2: Statement of Changes in Capital Assets Group of Accounts - Report 18
A3: California Wildlife, Coastal, and Park Land Conservation Fund of 1988 (0786)
A4: ='F0001'!A4:J4 -> As of June 30, 2024
A6: CAPITAL ASSETS | D6: Beginning Balance1 | F6: Additions | H6: Deductions | J6: Balance2 June 30, 2024
A8: Tangible Assets
B9: Land | D9: 585000 | J9: =D9+F9-H9 -> 585000
B10: Buildings | J10: =D10+F10-H10 -> 0
B11: Improvements Other Than Buildings | J11: =D11+F11-H11 -> 0
B12: Equipment | J12: =D12+F12-H12 -> 0
B13: Construction Work in Progress | J13: =D13+F13-H13 -> 0
B14: Infrastructure - Depreciable | J14: =D14+F14-H14 -> 0
A15: Intangible Assets | J15: =D15+F15-H15 -> 0
B16: Computer Software - Amortizable | J16: =D16+F16-H16 -> 0
B17: Land Use Rights - Amortizable | J17: =D17+F17-H17 -> 0
B18: Patents, Copyrights, and Trademarks - Amortizable | J18: =D18+F18-H18 -> 0
B19: Other Intangible Assets - Amortizable | J19: =D19+F19-H19 -> 0
B20: Land Use Rights - Non-Amortizable | J20: =D20+F20-H20 -> 0
B21: Patents, Copyrights, and Trademarks - Non-Amortizable | J21: =D21+F21-H21 -> 0
B22: Other Intangible Assets - Non-Amortizable | J22: =D22+F22-H22 -> 0
B23: Internally Generated Intangible Assets in Progress | J23: =D23+F23-H23 -> 0
A24: TOTAL CAPITAL ASSETS | D24: =SUM(D9:D23) -> 585000 | F24: =SUM(F9:F23) -> 0 | H24: =SUM(H9:H23) -> 0 | J24: =SUM(J9:J23) -> 585000
A27: 1 | B27: Asset beginning balances must agree with prior year ending balances. Any differences must be documented and explained in Report 18-
B28: Statement of Changes in Capital Assets Beginning Balance Differential Report. See illustration next page.
A29: 2 | B29: The ending balances should equal the debit balances on Report 19 for each asset type.

Sheet F6015
A1: San Joaquin River Conservancy (3830)
A2: Statement of Changes in Capital Assets Group of Accounts - Report 18
A3: River Protection Subaccount (6015)
A4: ='F0001'!A4:J4 -> As of June 30, 2024
A6: CAPITAL ASSETS | D6: Beginning Balance1 | F6: Additions | H6: Deductions | J6: Balance2 June 30, 2024
A8: Tangible Assets
B9: Land | D9: 10985727 | J9: =D9+F9-H9 -> 10985727
B10: Buildings | J10: =D10+F10-H10 -> 0
B11: Improvements Other Than Buildings | J11: =D11+F11-H11 -> 0
B12: Equipment | J12: =D12+F12-H12 -> 0
B13: Construction Work in Progress | J13: =D13+F13-H13 -> 0
B14: Infrastructure - Depreciable | J14: =D14+F14-H14 -> 0
A15: Intangible Assets | J15: =D15+F15-H15 -> 0
B16: Computer Software - Amortizable | J16: =D16+F16-H16 -> 0
B17: Land Use Rights - Amortizable | J17: =D17+F17-H17 -> 0
B18: Patents, Copyrights, and Trademarks - Amortizable | J18: =D18+F18-H18 -> 0
B19: Other Intangible Assets - Amortizable | J19: =D19+F19-H19 -> 0
B20: Land Use Rights - Non-Amortizable | J20: =D20+F20-H20 -> 0
B21: Patents, Copyrights, and Trademarks - Non-Amortizable | J21: =D21+F21-H21 -> 0
B22: Other Intangible Assets - Non-Amortizable | J22: =D22+F22-H22 -> 0
B23: Internally Generated Intangible Assets in Progress | J23: =D23+F23-H23 -> 0
A24: TOTAL CAPITAL ASSETS | D24: =SUM(D9:D23) -> 10985727 | F24: =SUM(F9:F23) -> 0 | H24: =SUM(H9:H23) -> 0 | J24: =SUM(J9:J23) -> 10985727
A27: 1 | B27: Asset beginning balances must agree with prior year ending balances. Any differences must be documented and explained in Report 18-
B28: Statement of Changes in Capital Assets Beginning Balance Differential Report. See illustration next page.
A29: 2 | B29: The ending balances should equal the debit balances on Report 19 for each asset type.

Sheet F0262
A1: San Joaquin River Conservancy (3830)
A2: Statement of Changes in Capital Assets Group of Accounts - Report 18
A3: Habitat Conservation Fund (0262)
A4: ='F0001'!A4:J4 -> As of June 30, 2024
A6: CAPITAL ASSETS | D6: Beginning Balance1 | F6: Additions | H6: Deductions | J6: Balance2 June 30, 2024
A8: Tangible Assets
B9: Land | D9: 6233411.9 | J9: =D9+F9-H9 -> 6233411.9
B10: Buildings | J10: =D10+F10-H10 -> 0
B11: Improvements Other Than Buildings | J11: =D11+F11-H11 -> 0
B12: Equipment | J12: =D12+F12-H12 -> 0
B13: Construction Work in Progress | J13: =D13+F13-H13 -> 0
B14: Infrastructure - Depreciable | J14: =D14+F14-H14 -> 0
A15: Intangible Assets | J15: =D15+F15-H15 -> 0
B16: Computer Software - Amortizable | J16: =D16+F16-H16 -> 0
B17: Land Use Rights - Amortizable | J17: =D17+F17-H17 -> 0
B18: Patents, Copyrights, and Trademarks - Amortizable | J18: =D18+F18-H18 -> 0
B19: Other Intangible Assets - Amortizable | J19: =D19+F19-H19 -> 0
B20: Land Use Rights - Non-Amortizable | J20: =D20+F20-H20 -> 0
B21: Patents, Copyrights, and Trademarks - Non-Amortizable | J21: =D21+F21-H21 -> 0
B22: Other Intangible Assets - Non-Amortizable | J22: =D22+F22-H22 -> 0
B23: Internally Generated Intangible Assets in Progress | J23: =D23+F23-H23 -> 0
A24: TOTAL CAPITAL ASSETS | D24: =SUM(D9:D23) -> 6233411.9 | F24: =SUM(F9:F23) -> 0 | H24: =SUM(H9:H23) -> 0 | J24: =SUM(J9:J23) -> 6233411.9
A27: 1 | B27: Asset beginning balances must agree with prior year ending balances. Any differences must be documented and explained in Report 18-
B28: Statement of Changes in Capital Assets Beginning Balance Differential Report. See illustration next page.
A29: 2 | B29: The ending balances should equal the debit balances on Report 19 for each asset type.

Sheet F0005
A1: San Joaquin River Conservancy (3830)
A2: Statement of Changes in Capital Assets Group of Accounts - Report 18
A3: Safe Neighborhood Parks, Clean Water, Clean Air, and Coastal Protection Bond Fund (0005)
A4: ='F0001'!A4:J4 -> As of June 30, 2024
A6: CAPITAL ASSETS | D6: Beginning Balance1 | F6: Additions | H6: Deductions | J6: Balance2 June 30, 2024
A8: Tangible Assets
B9: Land | D9: 10320443 | J9: =D9+F9-H9 -> 10320443
B10: Buildings | J10: =D10+F10-H10 -> 0
B11: Improvements Other Than Buildings | J11: =D11+F11-H11 -> 0
B12: Equipment | J12: =D12+F12-H12 -> 0
B13: Construction Work in Progress | J13: =D13+F13-H13 -> 0
B14: Infrastructure - Depreciable | J14: =D14+F14-H14 -> 0
A15: Intangible Assets | J15: =D15+F15-H15 -> 0
B16: Computer Software - Amortizable | J16: =D16+F16-H16 -> 0
B17: Land Use Rights - Amortizable | J17: =D17+F17-H17 -> 0
B18: Patents, Copyrights, and Trademarks - Amortizable | J18: =D18+F18-H18 -> 0
B19: Other Intangible Assets - Amortizable | J19: =D19+F19-H19 -> 0
B20: Land Use Rights - Non-Amortizable | J20: =D20+F20-H20 -> 0
B21: Patents, Copyrights, and Trademarks - Non-Amortizable | J21: =D21+F21-H21 -> 0
B22: Other Intangible Assets - Non-Amortizable | J22: =D22+F22-H22 -> 0
B23: Internally Generated Intangible Assets in Progress | J23: =D23+F23-H23 -> 0
A24: TOTAL CAPITAL ASSETS | D24: =SUM(D9:D23) -> 10320443 | F24: =SUM(F9:F23) -> 0 | H24: =SUM(H9:H23) -> 0 | J24: =SUM(J9:J23) -> 10320443
A27: 1 | B27: Asset beginning balances must agree with prior year ending balances. Any differences must be documented and explained in Report 18-
B28: Statement of Changes in Capital Assets Beginning Balance Differential Report. See illustration next page.
A29: 2 | B29: The ending balances should equal the debit balances on Report 19 for each asset type.

Sheet R18 Differential
A1: San Joaquin River Conservancy (3830)
A2: Statement of Changes in Capital Assets Group of Accounts - Report 18
A3: Beginning Balance Differential Report
A4: General Fund (0001)
A5: As of June 30, 20XX
K7: Breakdown of Difference:
E8: (1) | G8: (2) | I8: (3) | K8: (4) | M8: (5) | O8: (6) | Q8: (7) | S8: (8) | U8: (9)
E9: Prior Year Ending Balance | G9: Current Year Beginning Balance | I9: Difference | K9: Assets unreported in the prior year | M9: Non-capitalizable assets reported as capital assets in the prior year | O9: Transfers from other departments (at historical cost/book value) | Q9: Other amounts that make up the difference (provide description): prior year asset classification was incorrect | S9: Other amounts that make up the difference (provide description): incorrect entry was made in current year balance | U9: Restatement Amount (should agree to the difference calculated)
A11: Tangible Assets
B12: Land | I12: =G12-E12 -> 0 | U12: =SUM(K12:S12) -> 0
B13: Buildings | I13: =G13-E13 -> 0 | U13: =SUM(K13:S13) -> 0
B14: Improvements Other Than Buildings | I14: =G14-E14 -> 0 | U14: =SUM(K14:S14) -> 0
B15: Equipment | I15: =G15-E15 -> 0 | U15: =SUM(K15:S15) -> 0
B16: Construction Work in Progress | I16: =G16-E16 -> 0 | U16: =SUM(K16:S16) -> 0
B17: Infrastructure - Depreciable | I17: =G17-E17 -> 0 | U17: =SUM(K17:S17) -> 0
A18: Intangible Assets
B19: Computer Software - Amortizable | I19: =G19-E19 -> 0 | U19: =SUM(K19:S19) -> 0
B20: Land Use Rights - Amortizable | I20: =G20-E20 -> 0 | U20: =SUM(K20:S20) -> 0
B21: Patents, Copyrights, and Trademarks - Amortizable | I21: =G21-E21 -> 0 | U21: =SUM(K21:S21) -> 0
B22: Other Intangible Assets - Amortizable | I22: =G22-E22 -> 0 | U22: =SUM(K22:S22) -> 0
B23: Land Use Rights - Non-Amortizable | I23: =G23-E23 -> 0 | U23: =SUM(K23:S23) -> 0
B24: Patents, Copyrights, and Trademarks - Non-Amortizable | I24: =G24-E24 -> 0 | U24: =SUM(K24:S24) -> 0
B25: Other Intangible Assets - Non-Amortizable | I25: =G25-E25 -> 0 | U25: =SUM(K25:S25) -> 0
B26: Internally Generated Intangible Assets in Progress | I26: =G26-E26 -> 0 | U26: =SUM(K26:S26) -> 0
A27: Total | E27: =SUM(E12:E26) -> 0 | G27: =SUM(G12:G26) -> 0 | I27: =SUM(I12:I26) -> 0 | K27: =SUM(K12:K26) -> 0 | M27: =SUM(M12:M26) -> 0 | O27: =SUM(O12:O26) -> 0 | Q27: =SUM(Q12:Q26) -> 0 | S27: =SUM(S12:S26) -> 0 | U27: =SUM(U12:U26) -> 0
A30: Report Instructions:
A31: Col. 1 - | C31: Enter Ending Balance from Prior Year Report 18.
A32: Col. 2 - | C32: Enter Beginning Balance from Current Year Report 18.
A33: Col. 3 - | C33: Compute difference between current year beginning balance and prior year ending balance.
C34: Research posting and source documents to identify and explain the difference.
A35: Col. 4 - 8 | C35: Breakdown and categorize the differences in columns 4 to 8.
A36: Col. 9 - | C36: Compute the sum of columns 4 to 8. The amount should agree with the computed difference in column 3.
