Workbook
Name ActuaryCredentialsGASB: [1]DeveloperInfo!$D$19
Name ActuaryNameGASB: [1]DeveloperInfo!$D$17
Name ActuaryTitleGASB: [1]DeveloperInfo!$D$18
Name AdjCNSDate: [1]DeveloperInfo!$D$33
Name AdjCNSDate1: [1]DeveloperInfo!$E$33
Name AdjCNSDateTempEnable: [1]DeveloperInfo!$F$34
Name AgencyCode: #REF!
Name AgencyCode1: #REF!
Name AnalystGASB: [1]DeveloperInfo!$D$20
Name Annuity: #REF!
Name Annuity1: #REF!
Name AnnuityLY: #REF!
Name ASTABPF: [1]DeveloperInfo!$D$36
Name ASTABPF1: [1]DeveloperInfo!$D$37
Name ASTEBPF: [1]DeveloperInfo!$F$37
Name ClientShortGASB: [1]DeveloperInfo!$D$9
Name CLPOWERDisc: [1]Adjust!$H$199
Name CLPOWERDiscMinus1: [1]Adjust!$L$199
Name CLPOWERDiscPlus1: [1]Adjust!$K$199
Name CLPOWERExp: [1]Adjust!$G$199
Name CNSDateDisc: [1]DeveloperInfo!$D$32
Name CNSDateDisc1: [1]DeveloperInfo!$E$32
Name ColaRate: [1]DeveloperInfo!$D$40
Name ConsultantNameGASB: [1]DeveloperInfo!$D$22
Name ConsultantTitleGASB: [1]DeveloperInfo!$D$23
Name Disc1DELTACENSUS: [1]Adjust!$G$102
Name Disc1INTNDIV12: [1]Adjust!$H$195
Name Disc1SINTADJBOM: [1]Adjust!$I$197
Name Disc1SINTNDIV12: [1]Adjust!$I$195
Name DiscDELTACENSUS: [1]Adjust!$H$102
Name DiscINTADJBOM: [1]Adjust!$J$197
Name DiscINTNDIV12: [1]Adjust!$J$195
Name DiscMinusOneINTADJBOM: [1]Adjust!$L$197
Name DiscMinusOneINTNDIV12: [1]Adjust!$L$195
Name DiscPlusOneINTADJBOM: [1]Adjust!$K$197
Name DiscPlusOneINTNDIV12: [1]Adjust!$K$195
Name EmployerRates: #REF!
Name EmployerRates1: #REF!
Name EmployerRatesLEO: #REF!
Name EmployerRatesLEO1: #REF!
Name ERData: [1]ER_DATA!$B$16:$EN$318
Name ERID: [1]ER_NPLExpense!$L$8
Name ERInfo: [1]ER_Input!$B$16:$Y$318
Name Exp1INTADJBOM: [1]Adjust!$G$197
Name Exp1INTNDIV12: [1]Adjust!$G$195
Name FracYearProj: [1]TPL!$C$43
Name FundOfficeContactGASB: [1]DeveloperInfo!$D$10
Name FYrsGASB: [1]DeveloperInfo!$D$54
Name GainLoss: [1]ER_Allocation!$P$12
Name GASBDiscMinusOneINTADJBOM: [1]Adjust!$L$197
Name GASBDiscMinusOneINTNDIV12: [1]Adjust!$L$195
Name InflRate: [1]DeveloperInfo!$D$38
Name InflRate1: [1]DeveloperInfo!$E$38
Name IntDisc: [1]DeveloperInfo!$F$47
Name IntDisc1: [1]DeveloperInfo!$D$47
Name IntDisc1S: [1]DeveloperInfo!$E$47
Name INTDiscMinusOne: [1]DeveloperInfo!$H$47
Name INTDiscPlusOne: [1]DeveloperInfo!$G$47
Name IntExp1: [1]DeveloperInfo!$I$47
Name MeasureDate: [1]DeveloperInfo!$D$31

Sheet Drop Down Menus
A1: 2021–2022 | B1: Governmental | C1: FI$Cal | D1: Yes | E1: Governmental Fund | G1: Please select fund type above.
A2: 2022–2023 | B2: Proprietary | C2: Non-FI$Cal | D2: No | E2: Proprietary - Internal Service Fund | F2: General government | G2: Cr: Acct 0808 - GENERAL GOV. (GAAP ADJ) | H2: Dr: Acct 0808 - GENERAL GOV. (GAAP ADJ)
A3: 2023–2024 | E3: Proprietary - Enterprise Fund | F3: Education | G3: Cr: Acct 0810 - EDUCATION EXP (GAAP ADJ) | H3: Dr: Acct 0810 - EDUCATION EXP (GAAP ADJ)
A4: 2024–2025 | F4: Health and human services | G4: Cr: Acct 0815 - HLTH&HUM SV SV.LAB(GAAP ADJ) | H4: Dr: Acct 0815 - HLTH&HUM SV SV.LAB(GAAP ADJ)
A5: 2025–2026 | F5: Resources | G5: Cr: Acct 0820 - NAT RES & ENVIRON (GAAP ADJ) | H5: Dr: Acct 0820 - NAT RES & ENVIRON (GAAP ADJ)
A6: 2026–2027 | F6: BUS, CONSUMER SERV, HOUSING | G6: Cr: Acct 0825 - BUS, CONSUMER SERV, HOUSING | H6: Dr: Acct 0825 - BUS, CONSUMER SERV, HOUSING
A7: 2027–2028 | F7: Transportation | G7: Cr: Acct 0830 - TRANSPORTATION (GAAP ADJ) | H7: Dr: Acct 0830 - TRANSPORTATION (GAAP ADJ)
A8: 2028–2029 | F8: CORRECTIONS AND REHABILITATION | G8: Cr: Acct 0835 - CORRECTIONS AND REHABILITATION | H8: Dr: Acct 0835 - CORRECTIONS AND REHABILITATION
A9: 2029–2030 | F9: Proprietary fund | G9: Cr: Acct 0870 - SERVICES & CHARGES (MG ADJ) | H9: Dr: Acct 0870 - SERVICES & CHARGES (MG ADJ)
A10: 2030–2031 | F10: Unidentified | G10: Cr: Acct 0XXX - FUNCTIONAL EXPENSE | H10: Dr: Acct 0XXX - FUNCTIONAL EXPENSE
A11: 2031–2032
A12: 2032–2033
A13: 2033–2034
A14: 2034–2035
A15: 2035–2036
A16: 2036–2037
A17: 2037–2038
A18: 2038–2039
A19: 2039–2040
A20: 2040–2041
A21: 2041–2042
A22: 2042–2043
... A101: 2121–2122

Sheet qryIndex02a
A1: Agency | B1: Title | C1: Hier1 | D1: Desc1 | E1: Desc2 | F1: Hier2 | G1: Hier3 | H1: Hier4 | I1: Hier5 | J1: EffectiveDate | K1: CancelDate
A2: 0000 | B2: BOND INTEREST AND REDEMPTION | C2: 9000 | D2: BOND INTEREST AND REDEMPTION | F2: 9030 | G2: 9600 | H2: 0000 | I2: 0000 | J2: 04/04/1984 | K2: 00/00/0000
A3: 0010 | B3: LEGISLATIVE, JUDICIAL AND EXEC | C3: 0808 | D3: GENERAL GOVERNMENT | F3: 0000 | G3: 0000 | H3: 0000 | I3: 0000 | J3: 07/11/2006 | K3: 00/00/0000
A4: 0015 | B4: ADD AGENCY TEST | C4: 0808 | D4: GENERAL GOVERNMENT | F4: 0000 | G4: 0000 | H4: 0000 | I4: 0000 | J4: 99/99/9999 | K4: 00/00/0000
A5: 0020 | B5: LEGISLATIVE | C5: 0808 | D5: GENERAL GOVERNMENT | F5: 0000 | G5: 0000 | H5: 0000 | I5: 0000 | J5: 99/99/9999 | K5: 00/00/0000
A6: 0100 | B6: LEGISLATURE | C6: 0808 | D6: GENERAL GOVERNMENT | F6: 0000 | G6: 0000 | H6: 0000 | I6: 0000 | J6: 99/99/9999 | K6: 00/00/0000
A7: 0110 | B7: SENATE | C7: 0808 | D7: GENERAL GOVERNMENT | F7: 0000 | G7: 0000 | H7: 0000 | I7: 0000 | J7: 06/26/1985 | K7: 00/00/0000
A8: 0120 | B8: ASSEMBLY | C8: 0808 | D8: GENERAL GOVERNMENT | F8: 0000 | G8: 0000 | H8: 0000 | I8: 0000 | J8: 06/26/1985 | K8: 00/00/0000
A9: 0130 | B9: LEGISLATIVE JOINT EXPENSES | C9: 0808 | D9: GENERAL GOVERNMENT | F9: 0000 | G9: 0000 | H9: 0000 | I9: 0000 | J9: 06/26/1985 | K9: 00/00/0000
A10: 0150 | B10: CONTRIB TO LEGIS RETIRE FUND | C10: 0808 | D10: GENERAL GOVERNMENT | F10: 0000 | G10: 0000 | H10: 0000 | I10: 0000 | J10: 07/11/2006 | K10: 00/00/0000
A11: 0155 | B11: AUDITOR GENERAL OFFICE | C11: 0808 | D11: GENERAL GOVERNMENT | F11: 0000 | G11: 0000 | H11: 0000 | I11: 0000 | J11: 99/99/9999 | K11: 00/00/0000
A12: 0160 | B12: LEGISLATIVE COUNSEL BUREAU | C12: 0808 | D12: GENERAL GOVERNMENT | F12: 0000 | G12: 0000 | H12: 0000 | I12: 0000 | J12: 04/04/1984 | K12: 00/00/0000
A13: 0170 | B13: CA LAW REVISION COMMISSION | C13: 0808 | D13: GENERAL GOVERNMENT | F13: 0000 | G13: 0000 | H13: 0000 | I13: 0000 | J13: 99/99/9999 | K13: 07/01/1985
... A190: 2140 | B190: STATE BANKING DEPARTMENT | C190: 0825 | D190: BUS, CONSUMER SERV, HOUSING | F190: 0000 | G190: 0000 | H190: 0000 | I190: 0000 | J190: 12/21/2016 | K190: 00/00/0000
A191: 2150 | B191: FINANCIAL INSTITUTIONS | C191: 0825 | D191: ADD BACK TO POST PY REVERSAL | E191: DELETE 16/17 | F191: 0000 | G191: 0000 | H191: 0000 | I191: 0000 | J191: 08/18/2016 | K191: 00/00/0000
A192: 2180 | B192: DEPART OF CORPORATIONS | C192: 0825 | D192: ADD BACK TO POST PY REVERSAL | E192: DELETE 16/17 | F192: 0000 | G192: 0000 | H192: 0000 | I192: 0000 | J192: 08/24/2016 | K192: 00/00/0000
A193: 2190 | B193: MAJOR MEDICAL INSURANCE BOARD | C193: 0825 | D193: BUS, CONSUMER SERV, HOUSING | F193: 0000 | G193: 0000 | H193: 0000 | I193: 0000 | J193: 12/21/2016 | K193: 00/00/0000
A194: 2200 | B194: DEPARTMENT OF COMMERCE | C194: 0825 | D194: BUS, CONSUMER SERV, HOUSING | F194: 0000 | G194: 0000 | H194: 0000 | I194: 0000 | J194: 12/21/2016 | K194: 00/00/0000
A195: 2220 | B195: OFFICE OF SMALL BUSINESS DEVEL | C195: 0825 | D195: BUS, CONSUMER SERV, HOUSING | F195: 0000 | G195: 0000 | H195: 0000 | I195: 0000 | J195: 12/21/2016 | K195: 00/00/0000
A196: 2222 | B196: ST ASST FD FOR ENTERPRISE | C196: 0825 | D196: BUS, CONSUMER SERV, HOUSING | F196: 0000 | G196: 0000 | H196: 0000 | I196: 0000 | J196: 12/21/2016 | K196: 00/00/0000
A197: 2225 | B197: UNITARY FUND PROGRAMS | C197: 0825 | D197: BUS, CONSUMER SERV, HOUSING | F197: 0000 | G197: 0000 | H197: 0000 | I197: 0000 | J197: 12/21/2016 | K197: 00/00/0000
A198: 2230 | B198: CA INDTRL DEV FINCL ADVRY COMM | C198: 0825 | D198: BUS, CONSUMER SERV, HOUSING | F198: 0000 | G198: 0000 | H198: 0000 | I198: 0000 | J198: 12/21/2016 | K198: 07/01/1985
A199: 2235 | B199: CA HOME LOAN MORTGAGE ASSN | C199: 0825 | D199: BUS, CONSUMER SERV, HOUSING | F199: 0000 | G199: 0000 | H199: 0000 | I199: 0000 | J199: 12/21/2016 | K199: 00/00/0000
A200: 2240 | B200: DEPT-HOUSING/COMMUNITY DEVEL | C200: 0825 | D200: BUS, CONSUMER SERV, HOUSING | F200: 0000 | G200: 0000 | H200: 0000 | I200: 0000 | J200: 12/12/2016 | K200: 00/00/1999
A201: 2245 | B201: CALIFORNIA HOUSING FINANCE AGY | C201: 0825 | D201: BUS, CONSUMER SERV, HOUSING | F201: 0000 | G201: 0000 | H201: 0000 | I201: 0000 | J201: 08/19/2016 | K201: 00/00/0000
A202: 2265 | B202: CALIFORNIA HOUSING INSURANCE | C202: 0825 | D202: BUS, CONSUMER SERV, HOUSING | F202: 0000 | G202: 0000 | H202: 0000 | I202: 0000 | J202: 12/21/2016 | K202: 00/00/0000
A203: 2270 | B203: MORTGAGE BOND ALLOC COMMITTEE | C203: 0825 | D203: BUS, CONSUMER SERV, HOUSING | F203: 0000 | G203: 0000 | H203: 0000 | I203: 0000 | J203: 12/21/2016 | K203: 07/01/1985
A204: 2290 | B204: DEPARTMENT OF INSURANCE | C204: 0825 | D204: BUS, CONSUMER SERV, HOUSING | F204: 0000 | G204: 0000 | H204: 0000 | I204: 0000 | J204: 12/21/2016 | K204: 00/00/1999
... A214: 2670 | B214: BD OF PILOT COMMISSIONERS-SF | C214: 0830 | D214: TRANSPORTATION | F214: 0000 | G214: 0000 | H214: 0000 | I214: 0000 | J214: 08/03/2017 | K214: 00/00/0000
A215: 2700 | B215: OFFICE OF TRAFFIC SAFETY | C215: 0830 | D215: TRANSPORTATION | E215: MERGED W/0521-ADD 4 PY ACCR RV | F215: 0000 | G215: 0000 | H215: 0000 | I215: 0000 | J215: 09/28/2016 | K215: 00/00/0000
A216: 2720 | B216: DEPT OF CAL HIGHWAY PATROL | C216: 0830 | D216: TRANSPORTATION | F216: 0000 | G216: 0000 | H216: 0000 | I216: 0000 | J216: 10/28/2016 | K216: 00/00/1999
A217: 2740 | B217: DEPARTMENT OF MOTOR VEHICLES | C217: 0830 | D217: TRANSPORTATION | F217: 0000 | G217: 0000 | H217: 0000 | I217: 0000 | J217: 10/28/2016 | K217: 00/00/0000
A218: 2780 | B218: STEPHEN P TEALE DATA CENTER | C218: 0825 | D218: BUS, CONSUMER SERV, HOUSING | F218: 0000 | G218: 0000 | H218: 0000 | I218: 0000 | J218: 12/21/2016 | K218: 00/00/0000
A219: 2900 | B219: TRADE AND COMMERCE | C219: 0825 | D219: BUS, CONSUMER SERV, HOUSING | F219: 0000 | G219: 0000 | H219: 0000 | I219: 0000 | J219: 12/21/2016 | K219: 00/00/0000
A220: 2920 | B220: TECHNOLOGY TRADE & COMMERCE AG | C220: 0825 | D220: BUS, CONSUMER SERV, HOUSING | F220: 0000 | G220: 0000 | H220: 0000 | I220: 0000 | J220: 12/21/2016 | K220: 00/00/0000
A221: 3000 | B221: NATURAL RESOURCES | C221: 0820 | D221: RESOURCES | F221: 0000 | G221: 0000 | H221: 0000 | I221: 0000 | J221: 08/25/2010 | K221: 00/00/0000
A222: 3100 | B222: EXPOSITION PARK | C222: 0820 | D222: RESOURCES | F222: 0000 | G222: 0000 | H222: 0000 | I222: 0000 | J222: 10/17/2018 | K222: 00/00/0000
A223: 3105 | B223: CALIFORNIA AFRO-AMERICAN MUSEU | C223: 0820 | D223: RESOURCES | F223: 0000 | G223: 0000 | H223: 0000 | I223: 0000 | J223: 09/05/2014 | K223: 00/00/0000
A224: 3110 | B224: SPECIAL RESOURCES PROGRAMS | C224: 0820 | D224: RESOURCES | F224: 0000 | G224: 0000 | H224: 0000 | I224: 0000 | J224: 07/11/2006 | K224: 00/00/1999
A225: 3125 | B225: CALIF TAHOE CONSERVANCY | C225: 0820 | D225: RESOURCES | F225: 0000 | G225: 0000 | H225: 0000 | I225: 0000 | J225: 04/18/1988 | K225: 00/00/1999
A226: 3130 | B226: WATERWAYS MANAGEMENT PLANNING | C226: 0820 | D226: RESOURCES | F226: 0000 | G226: 0000 | H226: 0000 | I226: 0000 | J226: 99/99/9999 | K226: 00/00/0000
A227: 3140 | B227: SEA GRANT PROGRAM | C227: 0820 | D227: RESOURCES | F227: 0000 | G227: 0000 | H227: 0000 | I227: 0000 | J227: 99/99/9999 | K227: 00/00/0000
... A278: 4140 | B278: OFFICE OF HEALTH PLAN & DEV | C278: 0815 | D278: HEALTH AND HUMAN SERVICES | F278: 0000 | G278: 0000 | H278: 0000 | I278: 0000 | J278: 10/28/2016 | K278: 00/00/0000
A279: 4150 | B279: DEPT OF MANAGED HEALTH CARE | C279: 0815 | D279: HEALTH AND HUMAN SERVICES | E279: RENUMBERED FROM 2400 | F279: 0000 | G279: 0000 | H279: 0000 | I279: 0000 | J279: 10/28/2016 | K279: 00/00/0000
A280: 4170 | B280: DEPARTMENT OF AGING | C280: 0815 | D280: HEALTH AND HUMAN SERVICES | F280: 0000 | G280: 0000 | H280: 0000 | I280: 0000 | J280: 10/28/2016 | K280: 00/00/1999
A281: 4180 | B281: COMMISSION ON AGING | C281: 0815 | D281: HEALTH AND HUMAN SERVICES | F281: 0000 | G281: 0000 | H281: 0000 | I281: 0000 | J281: 10/28/2016 | K281: 00/00/1999
A282: 4185 | B282: CALIFORNIA SENIOR LEGISLATURE | C282: 0815 | D282: HEALTH AND HUMAN SERVICES | F282: 0000 | G282: 0000 | H282: 0000 | I282: 0000 | J282: 10/28/2016 | K282: 00/00/0000
A283: 4210 | B283: GOV COUNCIL DRUG/ALCOHOL ABUSE | C283: 0815 | D283: HEALTH AND HUMAN SERVICES | F283: 0000 | G283: 0000 | H283: 0000 | I283: 0000 | J283: 10/28/2016 | K283: 00/00/0000
A284: 4220 | B284: GOV ADV COM CHILD DEVEL PROG | C284: 0815 | D284: HEALTH AND HUMAN SERVICES | F284: 0000 | G284: 0000 | H284: 0000 | I284: 0000 | J284: 10/28/2016 | K284: 00/00/0000
A285: 4250 | B285: CA. CHILDREN AND FAMILIES COMM | C285: 0815 | D285: HEALTH AND HUMAN SERVICES | F285: 0000 | G285: 0000 | H285: 0000 | I285: 0000 | J285: 10/28/2016 | K285: 00/00/0000
A286: 4260 | B286: DEPARTMENT OF HEALTH CARE SVCS | C286: 0815 | D286: HEALTH AND HUMAN SERVICES | F286: 0000 | G286: 0000 | H286: 0000 | I286: 0000 | J286: 10/28/2016 | K286: 00/00/0000
A287: 4265 | B287: DEPARTMENT OF PUBLIC HEALTH | C287: 0815 | D287: HEALTH AND HUMAN SERVICES | F287: 0000 | G287: 0000 | H287: 0000 | I287: 0000 | J287: 10/28/2016 | K287: 00/00/0000
A288: 4270 | B288: CAL MED ASSISTANCE COMMISSION | C288: 0815 | D288: HEALTH AND HUMAN SERVICES | F288: 0000 | G288: 0000 | H288: 0000 | I288: 0000 | J288: 10/28/2016 | K288: 00/00/1999
A289: 4280 | B289: MANAGED RISK MED INSUR BD. | C289: 0815 | D289: HEALTH AND HUMAN SERVICES | F289: 0000 | G289: 0000 | H289: 0000 | I289: 0000 | J289: 10/28/2016 | K289: 00/00/0000
A290: 4300 | B290: DEPT. DEVELOPMENTAL SVCS | C290: 0815 | D290: HEALTH AND HUMAN SERVICES | F290: 0000 | G290: 0000 | H290: 0000 | I290: 0000 | J290: 10/28/2016 | K290: 00/00/0000
A291: 4310 | B291: DO NOT USE AGENCY MERGED WITH | C291: 0815 | F291: 0000 | G291: 0000 | H291: 0000 | I291: 0000 | J291: 09/07/2018 | K291: 00/00/0000
A292: 4320 | B292: STATE HOSPITALS | C292: 0815 | D292: HEALTH AND HUMAN SERVICES | F292: 0000 | G292: 0000 | H292: 0000 | I292: 0000 | J292: 10/28/2016 | K292: 00/00/0000
A293: 4350 | B293: DO NOT USE AGENCY MERGED WITH | C293: 0815 | F293: 0000 | G293: 0000 | H293: 0000 | I293: 0000 | J293: 09/07/2018 | K293: 00/00/0000
A294: 4370 | B294: DO NOT USE AGENCY MERGED WITH | C294: 0815 | F294: 0000 | G294: 0000 | H294: 0000 | I294: 0000 | J294: 09/07/2018 | K294: 00/00/0000
A295: 4390 | B295: DO NOT USE AGENCY MERGED WITH | C295: 0815 | F295: 0000 | G295: 0000 | H295: 0000 | I295: 0000 | J295: 09/07/2018 | K295: 00/00/0000
A296: 4400 | B296: DO NOT USE AGENCY MERGED WITH | C296: 0815 | F296: 0000 | G296: 0000 | H296: 0000 | I296: 0000 | J296: 09/07/2018 | K296: 00/00/0000
A297: 4430 | B297: DO NOT USE AGENCY MERGED WITH | C297: 0815 | F297: 0000 | G297: 0000 | H297: 0000 | I297: 0000 | J297: 09/07/2018 | K297: 00/00/0000
A298: 4440 | B298: DEPT. OF STATE HOSPITAL | C298: 0815 | D298: HEALTH AND HUMAN SERVICES | F298: 0000 | G298: 0000 | H298: 0000 | I298: 0000 | J298: 10/28/2016 | K298: 00/00/0000
A299: 4450 | B299: SACRAMENTO STATE HOSPITAL | C299: 0815 | D299: HEALTH AND HUMAN SERVICES | F299: 0000 | G299: 0000 | H299: 0000 | I299: 0000 | J299: 10/28/2016 | K299: 00/00/1999
A300: 4460 | B300: STATE HOSPITALS | C300: 0815 | D300: HEALTH AND HUMAN SERVICES | F300: 0000 | G300: 0000 | H300: 0000 | I300: 0000 | J300: 10/28/2016 | K300: 00/00/0000
A301: 4470 | B301: ATASCADERO STATE HOSPITAL | C301: 0815 | D301: HEALTH AND HUMAN SERVICES | F301: 0000 | G301: 0000 | H301: 0000 | I301: 0000 | J301: 10/28/2016 | K301: 00/00/1999
A302: 4490 | B302: METROPOLITAN STATE HOSPITAL | C302: 0815 | D302: HEALTH AND HUMAN SERVICES | F302: 0000 | G302: 0000 | H302: 0000 | I302: 0000 | J302: 10/28/2016 | K302: 00/00/1999
A303: 4500 | B303: NAPA STATE HOSPITAL | C303: 0815 | D303: HEALTH AND HUMAN SERVICES | F303: 0000 | G303: 0000 | H303: 0000 | I303: 0000 | J303: 10/28/2016 | K303: 00/00/1999
A304: 4510 | B304: PATTON STATE HOSPITAL | C304: 0815 | D304: HEALTH AND HUMAN SERVICES | F304: 0000 | G304: 0000 | H304: 0000 | I304: 0000 | J304: 10/28/2016 | K304: 00/00/1999
A305: 4520 | B305: STOCKTON STATE HOSPITAL-DMH | C305: 0815 | D305: HEALTH AND HUMAN SERVICES | F305: 0000 | G305: 0000 | H305: 0000 | I305: 0000 | J305: 10/28/2016 | K305: 00/00/1999
A306: 4530 | B306: VACAVILLE STATE HOSPITAL | C306: 0815 | D306: HEALTH AND HUMAN SERVICES | F306: 0000 | G306: 0000 | H306: 0000 | I306: 0000 | J306: 10/28/2016 | K306: 00/00/0000
A307: 4540 | B307: COALINGA STATE HOSPITAL | C307: 0815 | D307: HEALTH AND HUMAN SERVICES | F307: 0000 | G307: 0000 | H307: 0000 | I307: 0000 | J307: 10/28/2016 | K307: 00/00/0000
A308: 4550 | B308: SALINAS STATE HOSPITAL | C308: 0815 | D308: HEALTH AND HUMAN SERVICES | F308: 0000 | G308: 0000 | H308: 0000 | I308: 0000 | J308: 10/28/2016 | K308: 00/00/0000
A309: 4560 | B309: MENTAL HEALTH SVCS OVERSIGHT | C309: 0815 | D309: HEALTH AND HUMAN SERVICES | F309: 0000 | G309: 0000 | H309: 0000 | I309: 0000 | J309: 10/28/2016 | K309: 00/00/0000
... A597: 9610 | B597: LEASE-REV NOTES & BONDS | C597: 9000 | D597: DEBT SERVICE INT & FISCAL CHGS | F597: 9030 | G597: 9610 | H597: 0000 | I597: 0000 | J597: 08/19/2016 | K597: 00/00/0000
A598: 9612 | B598: ENHN TOBAC ASSET-BACKED BND | C598: 0847 | D598: BOND INTEREST AND REDEMPTION | E598: WHEN TOBACCO REVENUE IS SHORT | F598: 0000 | G598: 0000 | H598: 0000 | I598: 0000 | J598: 08/19/2016 | K598: 00/00/0000
A599: 9613 | B599: UNENHANCED TOBACCO BD PROCEEDS | C599: 0808 | D599: GENERAL GOVERNMENT | F599: 0000 | G599: 0000 | H599: 0000 | I599: 0000 | J599: 02/26/2008 | K599: 00/00/0000
A600: 9618 | B600: ECONOMIC RECOVERY FINANCE COMM | C600: 0808 | D600: GENERAL GOVERNMENT | F600: 0000 | G600: 0000 | H600: 0000 | I600: 0000 | J600: 10/28/2005 | K600: 00/00/0000
A601: 9620 | B601: CASH MGMT & BUDGETARY LOANS | C601: 0850 | D601: DEBT SERVICE INT & FISCAL CHGS | F601: 0000 | G601: 0000 | H601: 0000 | I601: 0000 | J601: 08/19/2016 | K601: 00/00/0000
A602: 9625 | B602: INT PYMTS TO FEDERAL GOVT | C602: 0846 | D602: DEBT SERVICE INT & FISCAL CHGS | F602: 0000 | G602: 0000 | H602: 0000 | I602: 0000 | J602: 08/19/2016 | K602: 00/00/0000
A603: 9632 | B603: STATE MANDATED LOCAL COSTS | C603: 0808 | D603: GENERAL GOVERNMENT | F603: 0000 | G603: 0000 | H603: 0000 | I603: 0000 | J603: 99/99/9999 | K603: 00/00/0000
A604: 9634 | B604: GENERAL OBLIGATION BONDS | C604: 9000 | D604: GENERAL OBLIGATION BONDS | F604: 9030 | G604: 9634 | H604: 0000 | I604: 0000 | J604: 06/13/1988 | K604: 00/00/0000
A605: 9636 | B605: MISCELLANEOUS ADJUSTMENTS | C605: 9000 | D605: MISCELLANEOUS ADJUSTMENTS | F605: 9030 | G605: 9636 | H605: 0000 | I605: 0000 | J605: 06/13/1988 | K605: 00/00/0000
A606: 9650 | B606: HEALTH BENEFITS FOR ANNUITANTS | C606: 0808 | D606: GENERAL GOVERNMENT | F606: 0000 | G606: 0000 | H606: 0000 | I606: 0000 | J606: 04/04/1984 | K606: 00/00/0000
A607: 9651 | B607: PREFUND HEALTH & DENTAL BEN | C607: 0808 | D607: GENERAL GOVERNMENT | F607: 0000 | G607: 0000 | H607: 0000 | I607: 0000 | J607: 08/25/2010 | K607: 00/00/0000
A608: 9658 | B608: BUDGET STABILIZATION ACCOUNT | C608: 0808 | D608: GENERAL GOVERNMENT | F608: 0000 | G608: 0000 | H608: 0000 | I608: 0000 | J608: 07/11/2006 | K608: 00/00/0000
A609: 9670 | B609: LEGISLATIVE CLAIMS | C609: 0808 | D609: GENERAL GOVERNMENT | F609: 0000 | G609: 0000 | H609: 0000 | I609: 0000 | J609: 04/04/1984 | K609: 00/00/0000
A610: 9671 | B610: EQUITY CLAIMS OF BD OF CONTROL | C610: 0808 | D610: GENERAL GOVERNMENT | F610: 0000 | G610: 0000 | H610: 0000 | I610: 0000 | J610: 03/30/1994 | K610: 00/00/0000
... A635: 9885 | B635: RESERVE FOR ENCUMBRANCE | C635: 0808 | D635: GENERAL GOVERNMENT | F635: 0000 | G635: 0000 | H635: 0000 | I635: 0000 | J635: 01/23/1991 | K635: 00/00/0000
A636: 9889 | B636: PUBLIC SCHOOL SYSTEM STABILIZA | C636: 0810 | D636: PUBLIC SCHOOL SYSTEM | E636: STABILIZATION ACCOUNT | F636: 0000 | G636: 0000 | H636: 0000 | I636: 0000 | J636: 04/01/2020 | K636: 00/00/0000
A637: 9890 | B637: RES FOR ECONOMIC UNCERTAINTIES | C637: 0808 | D637: GENERAL GOVERNMENT | F637: 0000 | G637: 0000 | H637: 0000 | I637: 0000 | J637: 07/11/2006 | K637: 00/00/0000
A638: 9891 | B638: DEPT OF HEALTH HUMAN SERVICES | C638: 0815 | D638: HEALTH AND HUMAN SERVICES | F638: 0000 | G638: 0000 | H638: 0000 | I638: 0000 | J638: 10/28/2016 | K638: 00/00/0000
A639: 9892 | B639: SUPPLEMENTAL PENSION PAYMENTS | C639: 0843 | D639: INT. ON INTERFUND LOANS | F639: 0000 | G639: 0000 | H639: 0000 | I639: 0000 | J639: 11/22/2019 | K639: 00/00/0000
A640: 9895 | B640: PETROLEUM VIOLATION ESCROW PRO | C640: 0808 | D640: GENERAL GOVERNMENT | F640: 0000 | G640: 0000 | H640: 0000 | I640: 0000 | J640: 07/11/2006 | K640: 00/00/0000
A641: 9896 | B641: OUTER CONT SHELF LAND ACT | C641: 0808 | D641: GENERAL GOVERNMENT | F641: 0000 | G641: 0000 | H641: 0000 | I641: 0000 | J641: 07/11/2006 | K641: 00/00/0000
A642: 9898 | B642: PERS GENERAL FUND PAYMENT | C642: 0808 | D642: GENERAL GOVERNMENT | F642: 0000 | G642: 0000 | H642: 0000 | I642: 0000 | J642: 11/04/1998 | K642: 00/00/0000
A643: 9900 | B643: GEN FD CREDITS FROM SPEC FUNDS | C643: 0808 | D643: GENERAL GOVERNMENT | F643: 0000 | G643: 0000 | H643: 0000 | I643: 0000 | J643: 07/11/2006 | K643: 00/00/0000
A644: 9901 | B644: STATEWIDE GEN ADM EXP (PR) | C644: 0808 | D644: GENERAL GOVERNMENT | F644: 0000 | G644: 0000 | H644: 0000 | I644: 0000 | J644: 07/11/2006 | K644: 00/00/0000
A645: 9909 | B645: HLTH INS PORTABLTY ACCTABLTY | C645: 0815 | D645: HEALTH AND HUMAN SERVICES | F645: 0000 | G645: 0000 | H645: 0000 | I645: 0000 | J645: 10/28/2016 | K645: 00/00/0000
A646: 9910 | B646: GEN FD CREDITS FROM FED FUNDS | C646: 0808 | D646: GENERAL GOVERNMENT | F646: 0000 | G646: 0000 | H646: 0000 | I646: 0000 | J646: 07/11/2006 | K646: 00/00/0000
...

Sheet LS-Version Changes
A1: This sheet details the changes made between version 1 and version 2 of the GASB 87 Lessee Annual Reporting Submission Workbook. Familiarize yourself with the changes in the table below and follow the instructions for updating data from template version 1 to version 2.
A4: Version 1 | B4: Published on SCO website from August 2023 to March 2024 for use for the 2021-2022 reporting period.
A5: Version 2 | B5: Published on SCO website in March 2024 for use for reporting periods 2022-2023 and afterwards.
A7: The GASB 87 Annual Reporting Submission Workbook is required to be updated and submitted every year. See below for the summary of changes between versions.
A9: Summary of Changes
A10: Sheet | B10: Feature | C10: Location V1 | D10: Location V2 | E10: Description | F10: Required Action
A11: LS-Fund #### Journal Entries | B11: Revised - Instructions | C11: Row 1 | D11: Row 1 | E11: Financed purchase contracts were removed from the worksheet. This worksheet is now isolated to just leases that do not transfer ownership. There is a separate worksheet, "FP-Fund #### Journal Entries" to use if your fund has financed purchase contracts. | F11: Only use this worksheet for leases that do not transfer ownership.
A12: LS-Fund #### Journal Entries | B12: Added - Organization Name | C12: N/A | D12: Row 4 | E12: Added a row to type in the organization name. | F12: Type organization name.
A13: LS-Fund #### Journal Entries | B13: Removed - Fi$Cal or Non-Fi$Cal Departments | C13: Row 7 | D13: N/A | E13: The default is now non-Fi$Cal account numbers. A crosswalk between SCO GAAP and Fi$Cal account numbers can be found on the SCO Website under the heading "GASB 87 Supplemental Materials". https://sco.ca.gov/sard_gasb_87_reporting_instructions.html | F13: No action required.
A14: LS-Fund #### Journal Entries | B14: Added - Fund Type | C14: N/A | D14: Row 8 | E14: Select if the fund type is Governmental, Proprietary ISF, or Proprietary EF. This assists in the SCO's preparation of disclosures for the ACFR. | F14: Select one fund type.
A15: LS-Fund #### Journal Entries | B15: Added - Functional Expense | C15: N/A | D15: Row 9 | E15: Added a lookup of SCO GAAP functional expense based on organization code entered into row 5. This functional expense will automatically populate in Entry #1, 5, and 9. | F15: No action required.
A16: LS-Fund #### Journal Entries | B16: Added - Headers | C16: N/A | D16: Rows 12, 31, 53, 83, and 94 | E16: Added journal entry headers to help clarify when each set of entries are applicable. Informative only. | F16: No action required.
A17: LS-Fund #### Journal Entries | B17: Added - Asterisk Notes | C17: N/A | D17: Column A and Rows 27, 28, 43, 50, 71, 80, 91, 105, 106, 114, and 115 | E17: Added asterisks (* & **) and notes to instruct users on which lines should be used to prepare the Report 18, and which lines should be used to prepare the LS-Lease Liabilities and LS-Check Figures tabs. | F17: No action required.
A18: LS-Fund #### Journal Entries | B18: Revised - Entry #0 | C18: Row 10 | D18: Row 14 | E18: Entry #0, rolling the prior fiscal year ending balance for the current year opening balance, was revised to add "Acct 0950 - Beginning Fund Balances". This entry will remain blank if the fund did not have any leases in the prior year. | F18: No change in action required. Continue to populate Entry #0 based on amounts populated on the Lessee Template(s) for this fund.
A19: LS-Fund #### Journal Entries | B19: Revised - Entries #5 and #6, Account Numbers | C19: Rows 67-81 | D19: Rows 61-69 | E19: "Acct: 0845 - Debt Service - Principal" was updated to "Acct: 0848 - Debt Service - Principal Leases". "Acct: 0850 - Debt Service - Interest " was updated to "Acct: 0851 - Debt Service - Interest Leases" if a Governmental fund, and updated to "Acct: 0894 - Interest Expense and Fiscal Charges" if a Proprietary (ISF or EF) fund. | F19: No action required.
A20: LS-Fund #### Journal Entries | B20: Added - Entry #8 | C20: N/A | D20: Row 82 | E20: Entry #8 was added to write off the right-to-use asset and accumulated amortization at the end of the lease term. This entry will remain blank until the final fiscal year of the lease. | F20: No change in action required. Continue to populate Entry #8 based on amounts populated on the Lessee Template(s) for this fund.
A21: LS-Fund #### Journal Entries | B21: Added - Entry #9 | C21: N/A | D21: Row 95 | E21: Added Entry #9 to record an early termination of a lease or a lease modification in which there is a decrease to the lessee's right-to-use asset(s). The support for this journal entry is only found on the Lessee Modification Template, not the original Lessee Template. If there were no significant changes to lessee contracts during the fiscal year, this entry should remain blank. | F21: No change in action required. Continue to populate Entry #9 based on amounts populated on the Lessee Modification Template(s) for this fund.
... A29: LS-Check Figures | B29: Added - LS-Check Figures Tab | C29: N/A | D29: Tab "LS-Check Figures" | E29: Added a new worksheet tab to serve as a check figure between the three previous tabs, LS-Fund #### Journal Entries, LS-Department Note Disclosure, and LS-Lease Liabilities. Detailed instructions on how to complete this tab are provided on the "Instructions for Completing the GASB 87 Annual Reporting Submission Workbook" available on the SCO website. | F29: Complete tab and ensure there are no variances before submitting.

Sheet LS-Fund 0042 Journal Entries
A1: Lessee-Type Contracts Fund-by-Fund Journal Entries Form (to be submitted to the SCO annually—one form per fund)
A2: Manually complete every yellow field in this worksheet—there are no automatically calculated data-entry cells in this worksheet.
A3: Fiscal Year: | F3: 2022–2023
A4: Organization Name: | F4: Secretary for Transportation Agency
A5: Organization Code (4-Digits): | F5: 0521
A6: Fund Number (4-Digits): | F6: 42
A7: Fund Classification: | F7: Governmental
A8: Fund Type: | F8: Governmental Fund
A9: Functional Expense: | F9: =IFERROR(IF(F7="Proprietary","Proprietary Fund",VLOOKUP(F5,qryIndex02a!$A$2:$K$654,4,FALSE)),"Unidentified") -> TRANSPORTATION
A12: Establish Beginning Balances (existing leases only)
A13: Entry #
A14: 0 | B14: Roll forward prior year right-to-use leases to record opening balances. | M14: Combined Lessee Templates | P14: From SCO BB List | S14: Difference
A15: *Rpt 18 | B15: Dr: Acct 0476 - RIGHT-TO-USE LEASED LAND - AMORTIZABLE | J15: =M15 -> 0 | S15: =P15-M15 -> 0
A16: *Rpt 18 | B16: Dr: Acct 0478 - RIGHT-TO-USE LEASED EQUIPMENT - AMORTIZABLE | J16: =M16 -> 0 | S16: =P16-M16 -> 0
A17: *Rpt 18 | B17: Dr: Acct 0477 - RIGHT-TO-USE LEASED BUILDINGS - AMORTIZABLE | J17: =M17 -> 300394 | M17: 300394 | S17: =P17-M17 -> -300394
B18: Dr: Acct 0950 - BEGINNING FUND BALANCE | J18: =P18 -> 0 | P18: =IF(SUM($Q$20:$Q$23)>SUM($P$15:$P$17),SUM($Q$20:$Q$23)-SUM($P$15:$P$17),0) -> 0 | S18: =P18-M18 -> 0
B19: Dr: Acct 0952 - BEGINNING FUND ADJUSTMENT/PRIOR PERIOD ADJUSTMENT | J19: =IF(SUM($K$20:$K$24)>SUM($J$15:$J$18),SUM($K$20:$K$24)-SUM($J$15:$J$18),0) -> 0 | S19: =P19-M19 -> 0
C20: Cr: Acct 0485 - ACCUMULATED AMORTIZATION - RIGHT-TO-USE LEASED LAND | K20: =N20 -> 0 | S20: =P20-M20 -> 0
C21: Cr: Acct 0479 - ACCUMULATED AMORTIZATION - RIGHT-TO-USE LEASED EQUIPMENT | K21: =N21 -> 0 | S21: =Q21-N21 -> 0
C22: Cr: Acct 0486 - ACCUMULATED AMORTIZATION - RIGHT-TO-USE LEASED BUILDINGS | K22: =N22 -> 37549 | N22: 37549 | S22: =Q22-N22 -> -37549
A23: **LS LL/CF | C23: Cr: Acct 0691 - RIGHT-TO-USE LEASE LIABILITY | K23: =N23 -> 261463 | N23: 261463 | S23: =Q23-N23 -> -261463
C24: Cr: Acct 0950 - BEGINNING FUND BALANCE | K24: =Q24 -> 0 | Q24: =IF(SUM($Q$20:$Q$23)<SUM($P$15:$P$17),-SUM($Q$20:$Q$23)+SUM($P$15:$P$17),0) -> 0 | S24: =Q24-N24 -> 0
C25: Cr: Acct 0952 - BEGINNING FUND ADJUSTMENT/PRIOR PERIOD ADJUSTMENT | K25: =IF(SUM($K$20:$K$24)<SUM($J$15:$J$18),-SUM($K$20:$K$24)+SUM($J$15:$J$18),0) -> 1382 | S25: =Q25-N25 -> 0
J26: =SUM(J15:J25) -> 300394 | K26: =SUM(K15:K25) -> 300394 | L26: =IF(J26=K26,"<- Debits and Credits equal each other.","<- Debits and Credits do not equal each other.") -> <- Debits and Credits equal each other.
B27: * THESE ASSET AMOUNTS SHOULD BE REPORTED AS BEGINNING BALANCES ON REPORT 18.
B28: ** This amount should be included in the beginning balance column on the LS-Lease Liability and LS-Check Figures Tabs.
A31: Record New Leases (new leases only)
A32: 1 | B32: Record lease contract commencement (fund-based entries only)
B33: Dr: Acct 0842 - CAPITAL OUTLAY | J33: 2254138
C34: Cr: Acct 0789 - LEASE AND OTHER FINANCING PROCEEDS | K34: 2254138
C35: =IF($F$7="Proprietary","Cr: Acct 0870 - SERVICES & CHARGES (MG ADJ)",VLOOKUP($F$9,'Drop Down Menus'!$F$2:$G$10,2,FALSE)) -> Cr: Acct 0830 - TRANSPORTATION (GAAP ADJ)
J36: =SUM(J33:J35) -> 2254138 | K36: =SUM(K33:K35) -> 2254138 | L36: =IF(J36=K36,"<- Debits and Credits equal each other.","<- Debits and Credits do not equal each other.") -> <- Debits and Credits equal each other.
A38: 2 | B38: Record leased assets.
A39: *Rpt 18 | B39: Dr: Acct 0476 - RIGHT-TO-USE LEASED LAND - AMORTIZABLE
A40: *Rpt 18 | B40: Dr: Acct 0478 - RIGHT-TO-USE LEASED EQUIPMENT - AMORTIZABLE
A41: *Rpt 18 | B41: Dr: Acct 0477 - RIGHT-TO-USE LEASED BUILDINGS - AMORTIZABLE | J41: 2254138
C42: Cr: Acct 0842 - CAPITAL OUTLAY | K42: 2254138
B43: * THESE AMOUNTS SHOULD BE INCLUDED AS "ADDITIONS" ON REPORT 18. | J43: =SUM(J39:J42) -> 2254138 | K43: =SUM(K39:K42) -> 2254138 | L43: =IF(J43=K43,"<- Debits and Credits equal each other.","<- Debits and Credits do not equal each other.") -> <- Debits and Credits equal each other.
A46: 3 | B46: Replace proceeds from leases with right-to-use lease liability.
B47: Dr: Acct 0789 - LEASE AND OTHER FINANCING PROCEEDS | J47: 2254138
A48: **LS LL/CF | C48: Cr: Acct 0691 - RIGHT-TO-USE LEASE LIABILITY | K48: 2254138
J49: =SUM(J47:J48) -> 2254138 | K49: =SUM(K47:K48) -> 2254138 | L49: =IF(J49=K49,"<- Debits and Credits equal each other.","<- Debits and Credits do not equal each other.") -> <- Debits and Credits equal each other.
B50: ** This amount should be included in the additions column on the LS-Lease Liability and LS-Check Figures Tabs.
A53: Record Annual Activity (all leases)
A54: 4 | B54: Record amortization of the leased assets for the year.
B55: Dr: Acct 0875 - DEPRECIATION/AMORTIZATION | J55: 235214
C56: Cr: Acct 0485 - ACCUMULATED AMORTIZATION - RIGHT-TO-USE LEASED LAND
C57: Cr: Acct 0479 - ACCUMULATED AMORTIZATION - RIGHT-TO-USE LEASED EQUIPMENT
C58: Cr: Acct 0486 - ACCUMULATED AMORTIZATION - RIGHT-TO-USE LEASED BUILDINGS | K58: 235214
J59: =SUM(J55:J58) -> 235214 | K59: =SUM(K55:K58) -> 235214 | L59: =IF(J59=K59,"<- Debits and Credits equal each other.","<- Debits and Credits do not equal each other.") -> <- Debits and Credits equal each other.
A61: 5 | B61: Reclassify rents and leases exp. to lease contract principal and interest exp.
B62: Dr: Acct 0848 - DEBT SERVICE - PRINCIPAL LEASES | J62: 201376
B63: =IF(F7="Governmental","Dr: Acct 0851 - DEBT SERVICE - INTEREST LEASES","Dr: Acct 0894 - INTEREST EXPENSE AND FISCAL CHARGES") -> Dr: Acct 0851 - DEBT SERVICE - INTEREST LEASES | J63: 19464
C64: =IF($F$7="Proprietary","Cr: Acct 0870 - SERVICES & CHARGES (MG ADJ)",VLOOKUP($F$9,'Drop Down Menus'!$F$2:$G$10,2,FALSE)) -> Cr: Acct 0830 - TRANSPORTATION (GAAP ADJ) | K64: =+J62+J63 -> 220840
J65: =SUM(J62:J64) -> 220840 | K65: =SUM(K62:K64) -> 220840 | L65: =IF(J65=K65,"<- Debits and Credits equal each other.","<- Debits and Credits do not equal each other.") -> <- Debits and Credits equal each other.
A67: 6 | B67: Reduce lease contracts liability for total current year principal payments.
A68: **LS LL/CF | B68: Dr: Acct 0691 - RIGHT-TO-USE LEASE LIABILITY | J68: =J62 -> 201376
C69: Cr: Acct 0848 - DEBT SERVICE - PRINCIPAL LEASES | K69: =J68 -> 201376
J70: =SUM(J68:J69) -> 201376 | K70: =SUM(K68:K69) -> 201376 | L70: =IF(J70=K70,"<- Debits and Credits equal each other.","<- Debits and Credits do not equal each other.") -> <- Debits and Credits equal each other.
B71: ** This amount should be included in the deductions column on the LS-Lease Liability and LS-Check Figures Tabs.
A74: 7 | B74: Reclassify the principal amount due in the next FY to the current liability.
A75: **LS LL/CF | B75: Dr: Acct 0691 - RIGHT-TO-USE LEASE LIABILITY | J75: 208740
C76: Cr: Acct 0649 - RIGHT-TO-USE LEASE LIABILITY (CURRENT PORTION LT) | K76: 208740
B77: NOTE: This is an annual accrual. It is to be reversed at the start of the next fiscal year. SCO combines the current and non current amount in Entry #0 to reestablish the beginning balances. No action required. | J77: =SUM(J75:J76) -> 208740 | K77: =SUM(K75:K76) -> 208740 | L77: =IF(J77=K77,"<- Debits and Credits equal each other.","<- Debits and Credits do not equal each other.") -> <- Debits and Credits equal each other.
B80: ** This amount should be included in the due in one year column on the LS-Lease Liability and LS-Check Figures Tabs.
A83: Remove Lease Asset at the End of the Lease Term (only at the end of the lease term)
A84: 8 | B84: Record entry to write off the lease asset and accumulated amortization at the end of the lease term.
B85: Dr: Acct 0485 - ACCUMULATED AMORTIZATION - RIGHT-TO-USE LEASED LAND
B86: Dr: Acct 0479 - ACCUMULATED AMORTIZATION - RIGHT-TO-USE LEASED EQUIPMENT
B87: Dr: Acct 0486 - ACCUMULATED AMORTIZATION - RIGHT-TO-USE LEASED BUILDINGS
A88: *Rpt 18 | C88: Cr: Acct 0476 - RIGHT-TO-USE LEASED LAND - AMORTIZABLE
A89: *Rpt 18 | C89: Cr: Acct 0478 - RIGHT-TO-USE LEASED EQUIPMENT - AMORTIZABLE
A90: *Rpt 18 | C90: Cr: Acct 0477 - RIGHT-TO-USE LEASED BUILDINGS - AMORTIZABLE
B91: * THESE AMOUNTS SHOULD BE INCLUDED AS "DEDUCTIONS" ON REPORT 18. | J91: =SUM(J85:J90) -> 0 | K91: =SUM(K85:K90) -> 0 | L91: =IF(J91=K91,"<- Debits and Credits equal each other.","<- Debits and Credits do not equal each other.") -> <- Debits and Credits equal each other.
A94: Lease Remeasurement and Modifications (only if a significant modification occurred during the fiscal year)
A95: 9 | B95: Record early termination or lease modifications to decrease in the RTU leased asset.
A96: **LS LL/CF | B96: Dr: Acct 0691 - RIGHT-TO-USE LEASE LIABILITY | J96: 261463
B97: Dr: Acct 0485 - ACCUMULATED AMORTIZATION - RIGHT-TO-USE LEASED LAND
B98: Dr: Acct 0479 - ACCUMULATED AMORTIZATION - RIGHT-TO-USE LEASED EQUIPMENT
B99: Dr: Acct 0486 - ACCUMULATED AMORTIZATION - RIGHT-TO-USE LEASED BUILDINGS | J99: 37549
B100: =IF($F$7="Proprietary","Dr: Acct 0870 - SERVICES & CHARGES (MG ADJ)",VLOOKUP($F$9,'Drop Down Menus'!$F$2:$H$10,3,FALSE)) -> Dr: Acct 0830 - TRANSPORTATION (GAAP ADJ) | J100: 1382
A101: *Rpt 18 | C101: Cr: Acct 0476 - RIGHT-TO-USE LEASED LAND - AMORTIZABLE
A102: *Rpt 18 | C102: Cr: Acct 0478 - RIGHT-TO-USE LEASED EQUIPMENT - AMORTIZABLE
A103: *Rpt 18 | C103: Cr: Acct 0477 - RIGHT-TO-USE LEASED BUILDINGS - AMORTIZABLE | K103: 300394
C104: =IF($F$7="Proprietary","Dr: Acct 0870 - SERVICES & CHARGES (MG ADJ)",VLOOKUP($F$9,'Drop Down Menus'!$F$2:$G$10,2,FALSE)) -> Cr: Acct 0830 - TRANSPORTATION (GAAP ADJ)
B105: * THESE AMOUNTS SHOULD BE INCLUDED AS "DEDUCTIONS" ON REPORT 18. | J105: =SUM(J96:J104) -> 300394 | K105: =SUM(K96:K104) -> 300394 | L105: =IF(J105=K105,"<- Debits and Credits equal each other.","<- Debits and Credits do not equal each other.") -> <- Debits and Credits equal each other.
B106: ** This amount should be included in the deductions column on the LS-Lease Liability and LS-Check Figures Tabs.
A109: 10 | B109: Record lease modifications to increase in the RTU leased asset.
A110: *Rpt 18 | B110: Dr: Acct 0476 - RIGHT-TO-USE LEASED LAND - AMORTIZABLE
A111: *Rpt 18 | B111: Dr: Acct 0478 - RIGHT-TO-USE LEASED EQUIPMENT - AMORTIZABLE
A112: *Rpt 18 | B112: Dr: Acct 0477 - RIGHT-TO-USE LEASED BUILDINGS - AMORTIZABLE
A113: **LS LL/CF | C113: Cr: Acct 0691 - RIGHT-TO-USE LEASE LIABILITY
B114: * THESE AMOUNTS SHOULD BE INCLUDED AS "ADDITIONS" ON REPORT 18. | J114: =SUM(J110:J113) -> 0 | K114: =SUM(K110:K113) -> 0 | L114: =IF(J114=K114,"<- Debits and Credits equal each other.","<- Debits and Credits do not equal each other.") -> <- Debits and Credits equal each other.
B115: ** This amount should be included in the additions column on the LS-Lease Liability and LS-Check Figures Tabs.
D120: Informational - Ending Balances of Assets and Liabilities
K121: Debit (Credit)
D122: Acct 0476 - RIGHT-TO-USE LEASED LAND - AMORTIZABLE | K122: =J15+J39-K88-K101+J110 -> 0
D123: Acct 0478 - RIGHT-TO-USE LEASED EQUIPMENT - AMORTIZABLE | K123: =J16+J40-K89-K102+J111 -> 0
D124: Acct 0477 - RIGHT-TO-USE LEASED BUILDINGS - AMORTIZABLE | K124: =J17+J41-K90-K103+J112 -> 2254138
D125: Acct 0485 - ACCUMULATED AMORTIZATION - RIGHT-TO-USE LEASED LAND | K125: =-K20-K56+J85+J97 -> 0
...

Sheet LS-Fund 0044 Journal Entries
A1: Lessee-Type Contracts Fund-by-Fund Journal Entries Form (to be submitted to the SCO annually—one form per fund)
A2: Manually complete every yellow field in this worksheet—there are no automatically calculated data-entry cells in this worksheet.
A3: Fiscal Year: | F3: 2022–2023
A4: Organization Name: | F4: Secretary for Transportation Agency
A5: Organization Code (4-Digits): | F5: 0521
A6: Fund Number (4-Digits): | F6: 44
A7: Fund Classification: | F7: Governmental
A8: Fund Type: | F8: Governmental Fund
A9: Functional Expense: | F9: =IFERROR(IF(F7="Proprietary","Proprietary Fund",VLOOKUP(F5,qryIndex02a!$A$2:$K$654,4,FALSE)),"Unidentified") -> TRANSPORTATION
A12: Establish Beginning Balances (existing leases only)
A13: Entry #
A14: 0 | B14: Roll forward prior year right-to-use leases to record opening balances. | M14: Combined Lessee Templates | P14: From SCO BB List | S14: Difference
A15: *Rpt 18 | B15: Dr: Acct 0476 - RIGHT-TO-USE LEASED LAND - AMORTIZABLE | J15: =M15 -> 0 | S15: =P15-M15 -> 0
A16: *Rpt 18 | B16: Dr: Acct 0478 - RIGHT-TO-USE LEASED EQUIPMENT - AMORTIZABLE | J16: =M16 -> 0 | S16: =P16-M16 -> 0
A17: *Rpt 18 | B17: Dr: Acct 0477 - RIGHT-TO-USE LEASED BUILDINGS - AMORTIZABLE | J17: =M17 -> 99027 | M17: 99027 | S17: =P17-M17 -> -99027
B18: Dr: Acct 0950 - BEGINNING FUND BALANCE | J18: =P18 -> 0 | P18: =IF(SUM($Q$20:$Q$23)>SUM($P$15:$P$17),SUM($Q$20:$Q$23)-SUM($P$15:$P$17),0) -> 0 | S18: =P18-M18 -> 0
B19: Dr: Acct 0952 - BEGINNING FUND ADJUSTMENT/PRIOR PERIOD ADJUSTMENT | J19: =IF(SUM($K$20:$K$24)>SUM($J$15:$J$18),SUM($K$20:$K$24)-SUM($J$15:$J$18),0) -> 0 | S19: =P19-M19 -> 0
C20: Cr: Acct 0485 - ACCUMULATED AMORTIZATION - RIGHT-TO-USE LEASED LAND | K20: =N20 -> 0 | S20: =P20-M20 -> 0
C21: Cr: Acct 0479 - ACCUMULATED AMORTIZATION - RIGHT-TO-USE LEASED EQUIPMENT | K21: =N21 -> 0 | S21: =Q21-N21 -> 0
C22: Cr: Acct 0486 - ACCUMULATED AMORTIZATION - RIGHT-TO-USE LEASED BUILDINGS | K22: =N22 -> 12378 | N22: 12378 | S22: =Q22-N22 -> -12378
A23: **LS LL/CF | C23: Cr: Acct 0691 - RIGHT-TO-USE LEASE LIABILITY | K23: =N23 -> 86193 | N23: 86193 | S23: =Q23-N23 -> -86193
C24: Cr: Acct 0950 - BEGINNING FUND BALANCE | K24: =Q24 -> 0 | Q24: =IF(SUM($Q$20:$Q$23)<SUM($P$15:$P$17),-SUM($Q$20:$Q$23)+SUM($P$15:$P$17),0) -> 0 | S24: =Q24-N24 -> 0
C25: Cr: Acct 0952 - BEGINNING FUND ADJUSTMENT/PRIOR PERIOD ADJUSTMENT | K25: =IF(SUM($K$20:$K$24)<SUM($J$15:$J$18),-SUM($K$20:$K$24)+SUM($J$15:$J$18),0) -> 456 | S25: =Q25-N25 -> 0
J26: =SUM(J15:J25) -> 99027 | K26: =SUM(K15:K25) -> 99027 | L26: =IF(J26=K26,"<- Debits and Credits equal each other.","<- Debits and Credits do not equal each other.") -> <- Debits and Credits equal each other.
B27: * THESE ASSET AMOUNTS SHOULD BE REPORTED AS BEGINNING BALANCES ON REPORT 18.
B28: ** This amount should be included in the beginning balance column on the LS-Lease Liability and LS-Check Figures Tabs.
A31: Record New Leases (new leases only)
A32: 1 | B32: Record lease contract commencement (fund-based entries only)
B33: Dr: Acct 0842 - CAPITAL OUTLAY | J33: 706294
C34: Cr: Acct 0789 - LEASE AND OTHER FINANCING PROCEEDS | K34: 706294
C35: =IF($F$7="Proprietary","Cr: Acct 0870 - SERVICES & CHARGES (MG ADJ)",VLOOKUP($F$9,'Drop Down Menus'!$F$2:$G$10,2,FALSE)) -> Cr: Acct 0830 - TRANSPORTATION (GAAP ADJ)
J36: =SUM(J33:J35) -> 706294 | K36: =SUM(K33:K35) -> 706294 | L36: =IF(J36=K36,"<- Debits and Credits equal each other.","<- Debits and Credits do not equal each other.") -> <- Debits and Credits equal each other.
A38: 2 | B38: Record leased assets.
A39: *Rpt 18 | B39: Dr: Acct 0476 - RIGHT-TO-USE LEASED LAND - AMORTIZABLE
A40: *Rpt 18 | B40: Dr: Acct 0478 - RIGHT-TO-USE LEASED EQUIPMENT - AMORTIZABLE
A41: *Rpt 18 | B41: Dr: Acct 0477 - RIGHT-TO-USE LEASED BUILDINGS - AMORTIZABLE | J41: 706294
C42: Cr: Acct 0842 - CAPITAL OUTLAY | K42: 706294
B43: * THESE AMOUNTS SHOULD BE INCLUDED AS "ADDITIONS" ON REPORT 18. | J43: =SUM(J39:J42) -> 706294 | K43: =SUM(K39:K42) -> 706294 | L43: =IF(J43=K43,"<- Debits and Credits equal each other.","<- Debits and Credits do not equal each other.") -> <- Debits and Credits equal each other.
A46: 3 | B46: Replace proceeds from leases with right-to-use lease liability.
B47: Dr: Acct 0789 - LEASE AND OTHER FINANCING PROCEEDS | J47: 706294
A48: **LS LL/CF | C48: Cr: Acct 0691 - RIGHT-TO-USE LEASE LIABILITY | K48: 706294
J49: =SUM(J47:J48) -> 706294 | K49: =SUM(K47:K48) -> 706294 | L49: =IF(J49=K49,"<- Debits and Credits equal each other.","<- Debits and Credits do not equal each other.") -> <- Debits and Credits equal each other.
B50: ** This amount should be included in the additions column on the LS-Lease Liability and LS-Check Figures Tabs.
A53: Record Annual Activity (all leases)
A54: 4 | B54: Record amortization of the leased assets for the year.
B55: Dr: Acct 0875 - DEPRECIATION/AMORTIZATION | J55: 313961
C56: Cr: Acct 0485 - ACCUMULATED AMORTIZATION - RIGHT-TO-USE LEASED LAND
C57: Cr: Acct 0479 - ACCUMULATED AMORTIZATION - RIGHT-TO-USE LEASED EQUIPMENT
C58: Cr: Acct 0486 - ACCUMULATED AMORTIZATION - RIGHT-TO-USE LEASED BUILDINGS | K58: 313961
J59: =SUM(J55:J58) -> 313961 | K59: =SUM(K55:K58) -> 313961 | L59: =IF(J59=K59,"<- Debits and Credits equal each other.","<- Debits and Credits do not equal each other.") -> <- Debits and Credits equal each other.
A61: 5 | B61: Reclassify rents and leases exp. to lease contract principal and interest exp.
B62: Dr: Acct 0848 - DEBT SERVICE - PRINCIPAL LEASES | J62: 485939
B63: =IF(F7="Governmental","Dr: Acct 0851 - DEBT SERVICE - INTEREST LEASES","Dr: Acct 0894 - INTEREST EXPENSE AND FISCAL CHARGES") -> Dr: Acct 0851 - DEBT SERVICE - INTEREST LEASES | J63: 35496
C64: =IF($F$7="Proprietary","Cr: Acct 0870 - SERVICES & CHARGES (MG ADJ)",VLOOKUP($F$9,'Drop Down Menus'!$F$2:$G$10,2,FALSE)) -> Cr: Acct 0830 - TRANSPORTATION (GAAP ADJ) | K64: =+J62+J63 -> 521435
J65: =SUM(J62:J64) -> 521435 | K65: =SUM(K62:K64) -> 521435 | L65: =IF(J65=K65,"<- Debits and Credits equal each other.","<- Debits and Credits do not equal each other.") -> <- Debits and Credits equal each other.
A67: 6 | B67: Reduce lease contracts liability for total current year principal payments.
A68: **LS LL/CF | B68: Dr: Acct 0691 - RIGHT-TO-USE LEASE LIABILITY | J68: =J62 -> 485939
C69: Cr: Acct 0848 - DEBT SERVICE - PRINCIPAL LEASES | K69: =J68 -> 485939
J70: =SUM(J68:J69) -> 485939 | K70: =SUM(K68:K69) -> 485939 | L70: =IF(J70=K70,"<- Debits and Credits equal each other.","<- Debits and Credits do not equal each other.") -> <- Debits and Credits equal each other.
B71: ** This amount should be included in the deductions column on the LS-Lease Liability and LS-Check Figures Tabs.
A74: 7 | B74: Reclassify the principal amount due in the next FY to the current liability.
A75: **LS LL/CF | B75: Dr: Acct 0691 - RIGHT-TO-USE LEASE LIABILITY | J75: 279917
C76: Cr: Acct 0649 - RIGHT-TO-USE LEASE LIABILITY (CURRENT PORTION LT) | K76: =J75 -> 279917
B77: NOTE: This is an annual accrual. It is to be reversed at the start of the next fiscal year. SCO combines the current and non current amount in Entry #0 to reestablish the beginning balances. No action required. | J77: =SUM(J75:J76) -> 279917 | K77: =SUM(K75:K76) -> 279917 | L77: =IF(J77=K77,"<- Debits and Credits equal each other.","<- Debits and Credits do not equal each other.") -> <- Debits and Credits equal each other.
B80: ** This amount should be included in the due in one year column on the LS-Lease Liability and LS-Check Figures Tabs.
A83: Remove Lease Asset at the End of the Lease Term (only at the end of the lease term)
A84: 8 | B84: Record entry to write off the lease asset and accumulated amortization at the end of the lease term.
B85: Dr: Acct 0485 - ACCUMULATED AMORTIZATION - RIGHT-TO-USE LEASED LAND
B86: Dr: Acct 0479 - ACCUMULATED AMORTIZATION - RIGHT-TO-USE LEASED EQUIPMENT
B87: Dr: Acct 0486 - ACCUMULATED AMORTIZATION - RIGHT-TO-USE LEASED BUILDINGS
A88: *Rpt 18 | C88: Cr: Acct 0476 - RIGHT-TO-USE LEASED LAND - AMORTIZABLE
A89: *Rpt 18 | C89: Cr: Acct 0478 - RIGHT-TO-USE LEASED EQUIPMENT - AMORTIZABLE
A90: *Rpt 18 | C90: Cr: Acct 0477 - RIGHT-TO-USE LEASED BUILDINGS - AMORTIZABLE
B91: * THESE AMOUNTS SHOULD BE INCLUDED AS "DEDUCTIONS" ON REPORT 18. | J91: =SUM(J85:J90) -> 0 | K91: =SUM(K85:K90) -> 0 | L91: =IF(J91=K91,"<- Debits and Credits equal each other.","<- Debits and Credits do not equal each other.") -> <- Debits and Credits equal each other.
A94: Lease Remeasurement and Modifications (only if a significant modification occurred during the fiscal year)
A95: 9 | B95: Record early termination or lease modifications to decrease in the RTU leased asset.
A96: **LS LL/CF | B96: Dr: Acct 0691 - RIGHT-TO-USE LEASE LIABILITY | J96: 86193
B97: Dr: Acct 0485 - ACCUMULATED AMORTIZATION - RIGHT-TO-USE LEASED LAND
B98: Dr: Acct 0479 - ACCUMULATED AMORTIZATION - RIGHT-TO-USE LEASED EQUIPMENT
B99: Dr: Acct 0486 - ACCUMULATED AMORTIZATION - RIGHT-TO-USE LEASED BUILDINGS | J99: 12378
B100: =IF($F$7="Proprietary","Dr: Acct 0870 - SERVICES & CHARGES (MG ADJ)",VLOOKUP($F$9,'Drop Down Menus'!$F$2:$H$10,3,FALSE)) -> Dr: Acct 0830 - TRANSPORTATION (GAAP ADJ) | J100: 456
A101: *Rpt 18 | C101: Cr: Acct 0476 - RIGHT-TO-USE LEASED LAND - AMORTIZABLE
A102: *Rpt 18 | C102: Cr: Acct 0478 - RIGHT-TO-USE LEASED EQUIPMENT - AMORTIZABLE
A103: *Rpt 18 | C103: Cr: Acct 0477 - RIGHT-TO-USE LEASED BUILDINGS - AMORTIZABLE | K103: 99027
C104: =IF($F$7="Proprietary","Dr: Acct 0870 - SERVICES & CHARGES (MG ADJ)",VLOOKUP($F$9,'Drop Down Menus'!$F$2:$G$10,2,FALSE)) -> Cr: Acct 0830 - TRANSPORTATION (GAAP ADJ)
B105: * THESE AMOUNTS SHOULD BE INCLUDED AS "DEDUCTIONS" ON REPORT 18. | J105: =SUM(J96:J104) -> 99027 | K105: =SUM(K96:K104) -> 99027 | L105: =IF(J105=K105,"<- Debits and Credits equal each other.","<- Debits and Credits do not equal each other.") -> <- Debits and Credits equal each other.
B106: ** This amount should be included in the deductions column on the LS-Lease Liability and LS-Check Figures Tabs.
A109: 10 | B109: Record lease modifications to increase in the RTU leased asset.
A110: *Rpt 18 | B110: Dr: Acct 0476 - RIGHT-TO-USE LEASED LAND - AMORTIZABLE
A111: *Rpt 18 | B111: Dr: Acct 0478 - RIGHT-TO-USE LEASED EQUIPMENT - AMORTIZABLE
A112: *Rpt 18 | B112: Dr: Acct 0477 - RIGHT-TO-USE LEASED BUILDINGS - AMORTIZABLE | J112: =99027+1644411+252020 -> 1995458
A113: **LS LL/CF | C113: Cr: Acct 0691 - RIGHT-TO-USE LEASE LIABILITY | K113: =99027+1644411+252020 -> 1995458
B114: * THESE AMOUNTS SHOULD BE INCLUDED AS "ADDITIONS" ON REPORT 18. | J114: =SUM(J110:J113) -> 1995458 | K114: =SUM(K110:K113) -> 1995458 | L114: =IF(J114=K114,"<- Debits and Credits equal each other.","<- Debits and Credits do not equal each other.") -> <- Debits and Credits equal each other.
B115: ** This amount should be included in the additions column on the LS-Lease Liability and LS-Check Figures Tabs.
D120: Informational - Ending Balances of Assets and Liabilities
K121: Debit (Credit)
D122: Acct 0476 - RIGHT-TO-USE LEASED LAND - AMORTIZABLE | K122: =J15+J39-K88-K101+J110 -> 0
D123: Acct 0478 - RIGHT-TO-USE LEASED EQUIPMENT - AMORTIZABLE | K123: =J16+J40-K89-K102+J111 -> 0
D124: Acct 0477 - RIGHT-TO-USE LEASED BUILDINGS - AMORTIZABLE | K124: =J17+J41-K90-K103+J112 -> 2701752
D125: Acct 0485 - ACCUMULATED AMORTIZATION - RIGHT-TO-USE LEASED LAND | K125: =-K20-K56+J85+J97 -> 0
...

Sheet LS-Fund 0046 Journal Entries
A1: Lessee-Type Contracts Fund-by-Fund Journal Entries Form (to be submitted to the SCO annually—one form per fund)
A2: Manually complete every yellow field in this worksheet—there are no automatically calculated data-entry cells in this worksheet.
A3: Fiscal Year: | F3: 2022–2023
A4: Organization Name: | F4: Secretary for Transportation Agency
A5: Organization Code (4-Digits): | F5: 0521
A6: Fund Number (4-Digits): | F6: 46
A7: Fund Classification: | F7: Governmental
A8: Fund Type: | F8: Governmental Fund
A9: Functional Expense: | F9: =IFERROR(IF(F7="Proprietary","Proprietary Fund",VLOOKUP(F5,qryIndex02a!$A$2:$K$654,4,FALSE)),"Unidentified") -> TRANSPORTATION
A12: Establish Beginning Balances (existing leases only)
A13: Entry #
A14: 0 | B14: Roll forward prior year right-to-use leases to record opening balances. | M14: Combined Lessee Templates | P14: From SCO BB List | S14: Difference
A15: *Rpt 18 | B15: Dr: Acct 0476 - RIGHT-TO-USE LEASED LAND - AMORTIZABLE | J15: =M15 -> 0 | S15: =P15-M15 -> 0
A16: *Rpt 18 | B16: Dr: Acct 0478 - RIGHT-TO-USE LEASED EQUIPMENT - AMORTIZABLE | J16: =M16 -> 0 | S16: =P16-M16 -> 0
A17: *Rpt 18 | B17: Dr: Acct 0477 - RIGHT-TO-USE LEASED BUILDINGS - AMORTIZABLE | J17: =M17 -> 100596 | M17: 100596 | S17: =P17-M17 -> -100596
B18: Dr: Acct 0950 - BEGINNING FUND BALANCE | J18: =P18 -> 0 | P18: =IF(SUM($Q$20:$Q$23)>SUM($P$15:$P$17),SUM($Q$20:$Q$23)-SUM($P$15:$P$17),0) -> 0 | S18: =P18-M18 -> 0
B19: Dr: Acct 0952 - BEGINNING FUND ADJUSTMENT/PRIOR PERIOD ADJUSTMENT | J19: =IF(SUM($K$20:$K$24)>SUM($J$15:$J$18),SUM($K$20:$K$24)-SUM($J$15:$J$18),0) -> 0 | S19: =P19-M19 -> 0
C20: Cr: Acct 0485 - ACCUMULATED AMORTIZATION - RIGHT-TO-USE LEASED LAND | K20: =N20 -> 0 | S20: =P20-M20 -> 0
C21: Cr: Acct 0479 - ACCUMULATED AMORTIZATION - RIGHT-TO-USE LEASED EQUIPMENT | K21: =N21 -> 0 | S21: =Q21-N21 -> 0
C22: Cr: Acct 0486 - ACCUMULATED AMORTIZATION - RIGHT-TO-USE LEASED BUILDINGS | K22: =N22 -> 12575 | N22: 12575 | S22: =Q22-N22 -> -12575
A23: **LS LL/CF | C23: Cr: Acct 0691 - RIGHT-TO-USE LEASE LIABILITY | K23: =N23 -> 87559 | N23: 87559 | S23: =Q23-N23 -> -87559
C24: Cr: Acct 0950 - BEGINNING FUND BALANCE | K24: =Q24 -> 0 | Q24: =IF(SUM($Q$20:$Q$23)<SUM($P$15:$P$17),-SUM($Q$20:$Q$23)+SUM($P$15:$P$17),0) -> 0 | S24: =Q24-N24 -> 0
C25: Cr: Acct 0952 - BEGINNING FUND ADJUSTMENT/PRIOR PERIOD ADJUSTMENT | K25: =IF(SUM($K$20:$K$24)<SUM($J$15:$J$18),-SUM($K$20:$K$24)+SUM($J$15:$J$18),0) -> 462 | S25: =Q25-N25 -> 0
J26: =SUM(J15:J25) -> 100596 | K26: =SUM(K15:K25) -> 100596 | L26: =IF(J26=K26,"<- Debits and Credits equal each other.","<- Debits and Credits do not equal each other.") -> <- Debits and Credits equal each other.
B27: * THESE ASSET AMOUNTS SHOULD BE REPORTED AS BEGINNING BALANCES ON REPORT 18.
B28: ** This amount should be included in the beginning balance column on the LS-Lease Liability and LS-Check Figures Tabs.
A31: Record New Leases (new leases only)
A32: 1 | B32: Record lease contract commencement (fund-based entries only)
B33: Dr: Acct 0842 - CAPITAL OUTLAY | J33: 745203
C34: Cr: Acct 0789 - LEASE AND OTHER FINANCING PROCEEDS | K34: 745203
C35: =IF($F$7="Proprietary","Cr: Acct 0870 - SERVICES & CHARGES (MG ADJ)",VLOOKUP($F$9,'Drop Down Menus'!$F$2:$G$10,2,FALSE)) -> Cr: Acct 0830 - TRANSPORTATION (GAAP ADJ)
J36: =SUM(J33:J35) -> 745203 | K36: =SUM(K33:K35) -> 745203 | L36: =IF(J36=K36,"<- Debits and Credits equal each other.","<- Debits and Credits do not equal each other.") -> <- Debits and Credits equal each other.
A38: 2 | B38: Record leased assets.
A39: *Rpt 18 | B39: Dr: Acct 0476 - RIGHT-TO-USE LEASED LAND - AMORTIZABLE
A40: *Rpt 18 | B40: Dr: Acct 0478 - RIGHT-TO-USE LEASED EQUIPMENT - AMORTIZABLE
A41: *Rpt 18 | B41: Dr: Acct 0477 - RIGHT-TO-USE LEASED BUILDINGS - AMORTIZABLE | J41: 745203
C42: Cr: Acct 0842 - CAPITAL OUTLAY | K42: 745203
B43: * THESE AMOUNTS SHOULD BE INCLUDED AS "ADDITIONS" ON REPORT 18. | J43: =SUM(J39:J42) -> 745203 | K43: =SUM(K39:K42) -> 745203 | L43: =IF(J43=K43,"<- Debits and Credits equal each other.","<- Debits and Credits do not equal each other.") -> <- Debits and Credits equal each other.
A46: 3 | B46: Replace proceeds from leases with right-to-use lease liability.
B47: Dr: Acct 0789 - LEASE AND OTHER FINANCING PROCEEDS | J47: 745203
A48: **LS LL/CF | C48: Cr: Acct 0691 - RIGHT-TO-USE LEASE LIABILITY | K48: 745203
J49: =SUM(J47:J48) -> 745203 | K49: =SUM(K47:K48) -> 745203 | L49: =IF(J49=K49,"<- Debits and Credits equal each other.","<- Debits and Credits do not equal each other.") -> <- Debits and Credits equal each other.
B50: ** This amount should be included in the additions column on the LS-Lease Liability and LS-Check Figures Tabs.
A53: Record Annual Activity (all leases)
A54: 4 | B54: Record amortization of the leased assets for the year.
B55: Dr: Acct 0875 - DEPRECIATION/AMORTIZATION | J55: 77760
C56: Cr: Acct 0485 - ACCUMULATED AMORTIZATION - RIGHT-TO-USE LEASED LAND
C57: Cr: Acct 0479 - ACCUMULATED AMORTIZATION - RIGHT-TO-USE LEASED EQUIPMENT
C58: Cr: Acct 0486 - ACCUMULATED AMORTIZATION - RIGHT-TO-USE LEASED BUILDINGS | K58: 77760
J59: =SUM(J55:J58) -> 77760 | K59: =SUM(K55:K58) -> 77760 | L59: =IF(J59=K59,"<- Debits and Credits equal each other.","<- Debits and Credits do not equal each other.") -> <- Debits and Credits equal each other.
A61: 5 | B61: Reclassify rents and leases exp. to lease contract principal and interest exp.
B62: Dr: Acct 0848 - DEBT SERVICE - PRINCIPAL LEASES | J62: 66574
B63: =IF(F7="Governmental","Dr: Acct 0851 - DEBT SERVICE - INTEREST LEASES","Dr: Acct 0894 - INTEREST EXPENSE AND FISCAL CHARGES") -> Dr: Acct 0851 - DEBT SERVICE - INTEREST LEASES | J63: 6435
C64: =IF($F$7="Proprietary","Cr: Acct 0870 - SERVICES & CHARGES (MG ADJ)",VLOOKUP($F$9,'Drop Down Menus'!$F$2:$G$10,2,FALSE)) -> Cr: Acct 0830 - TRANSPORTATION (GAAP ADJ) | K64: =+J62+J63 -> 73009
J65: =SUM(J62:J64) -> 73009 | K65: =SUM(K62:K64) -> 73009 | L65: =IF(J65=K65,"<- Debits and Credits equal each other.","<- Debits and Credits do not equal each other.") -> <- Debits and Credits equal each other.
A67: 6 | B67: Reduce lease contracts liability for total current year principal payments.
A68: **LS LL/CF | B68: Dr: Acct 0691 - RIGHT-TO-USE LEASE LIABILITY | J68: =J62 -> 66574
C69: Cr: Acct 0848 - DEBT SERVICE - PRINCIPAL LEASES | K69: =J68 -> 66574
J70: =SUM(J68:J69) -> 66574 | K70: =SUM(K68:K69) -> 66574 | L70: =IF(J70=K70,"<- Debits and Credits equal each other.","<- Debits and Credits do not equal each other.") -> <- Debits and Credits equal each other.
B71: ** This amount should be included in the deductions column on the LS-Lease Liability and LS-Check Figures Tabs.
A74: 7 | B74: Reclassify the principal amount due in the next FY to the current liability.
A75: **LS LL/CF | B75: Dr: Acct 0691 - RIGHT-TO-USE LEASE LIABILITY | J75: 69008
C76: Cr: Acct 0649 - RIGHT-TO-USE LEASE LIABILITY (CURRENT PORTION LT) | K76: =J75 -> 69008
B77: NOTE: This is an annual accrual. It is to be reversed at the start of the next fiscal year. SCO combines the current and non current amount in Entry #0 to reestablish the beginning balances. No action required. | J77: =SUM(J75:J76) -> 69008 | K77: =SUM(K75:K76) -> 69008 | L77: =IF(J77=K77,"<- Debits and Credits equal each other.","<- Debits and Credits do not equal each other.") -> <- Debits and Credits equal each other.
B80: ** This amount should be included in the due in one year column on the LS-Lease Liability and LS-Check Figures Tabs.
A83: Remove Lease Asset at the End of the Lease Term (only at the end of the lease term)
A84: 8 | B84: Record entry to write off the lease asset and accumulated amortization at the end of the lease term.
B85: Dr: Acct 0485 - ACCUMULATED AMORTIZATION - RIGHT-TO-USE LEASED LAND
B86: Dr: Acct 0479 - ACCUMULATED AMORTIZATION - RIGHT-TO-USE LEASED EQUIPMENT
B87: Dr: Acct 0486 - ACCUMULATED AMORTIZATION - RIGHT-TO-USE LEASED BUILDINGS
A88: *Rpt 18 | C88: Cr: Acct 0476 - RIGHT-TO-USE LEASED LAND - AMORTIZABLE
A89: *Rpt 18 | C89: Cr: Acct 0478 - RIGHT-TO-USE LEASED EQUIPMENT - AMORTIZABLE
A90: *Rpt 18 | C90: Cr: Acct 0477 - RIGHT-TO-USE LEASED BUILDINGS - AMORTIZABLE
B91: * THESE AMOUNTS SHOULD BE INCLUDED AS "DEDUCTIONS" ON REPORT 18. | J91: =SUM(J85:J90) -> 0 | K91: =SUM(K85:K90) -> 0 | L91: =IF(J91=K91,"<- Debits and Credits equal each other.","<- Debits and Credits do not equal each other.") -> <- Debits and Credits equal each other.
A94: Lease Remeasurement and Modifications (only if a significant modification occurred during the fiscal year)
A95: 9 | B95: Record early termination or lease modifications to decrease in the RTU leased asset.
A96: **LS LL/CF | B96: Dr: Acct 0691 - RIGHT-TO-USE LEASE LIABILITY | J96: 87559
B97: Dr: Acct 0485 - ACCUMULATED AMORTIZATION - RIGHT-TO-USE LEASED LAND
B98: Dr: Acct 0479 - ACCUMULATED AMORTIZATION - RIGHT-TO-USE LEASED EQUIPMENT
B99: Dr: Acct 0486 - ACCUMULATED AMORTIZATION - RIGHT-TO-USE LEASED BUILDINGS | J99: 12575
B100: =IF($F$7="Proprietary","Dr: Acct 0870 - SERVICES & CHARGES (MG ADJ)",VLOOKUP($F$9,'Drop Down Menus'!$F$2:$H$10,3,FALSE)) -> Dr: Acct 0830 - TRANSPORTATION (GAAP ADJ) | J100: 462
A101: *Rpt 18 | C101: Cr: Acct 0476 - RIGHT-TO-USE LEASED LAND - AMORTIZABLE
A102: *Rpt 18 | C102: Cr: Acct 0478 - RIGHT-TO-USE LEASED EQUIPMENT - AMORTIZABLE
A103: *Rpt 18 | C103: Cr: Acct 0477 - RIGHT-TO-USE LEASED BUILDINGS - AMORTIZABLE | K103: 100596
C104: =IF($F$7="Proprietary","Dr: Acct 0870 - SERVICES & CHARGES (MG ADJ)",VLOOKUP($F$9,'Drop Down Menus'!$F$2:$G$10,2,FALSE)) -> Cr: Acct 0830 - TRANSPORTATION (GAAP ADJ)
B105: * THESE AMOUNTS SHOULD BE INCLUDED AS "DEDUCTIONS" ON REPORT 18. | J105: =SUM(J96:J104) -> 100596 | K105: =SUM(K96:K104) -> 100596 | L105: =IF(J105=K105,"<- Debits and Credits equal each other.","<- Debits and Credits do not equal each other.") -> <- Debits and Credits equal each other.
B106: ** This amount should be included in the deductions column on the LS-Lease Liability and LS-Check Figures Tabs.
A109: 10 | B109: Record lease modifications to increase in the RTU leased asset.
A110: *Rpt 18 | B110: Dr: Acct 0476 - RIGHT-TO-USE LEASED LAND - AMORTIZABLE
A111: *Rpt 18 | B111: Dr: Acct 0478 - RIGHT-TO-USE LEASED EQUIPMENT - AMORTIZABLE
A112: *Rpt 18 | B112: Dr: Acct 0477 - RIGHT-TO-USE LEASED BUILDINGS - AMORTIZABLE
A113: **LS LL/CF | C113: Cr: Acct 0691 - RIGHT-TO-USE LEASE LIABILITY
B114: * THESE AMOUNTS SHOULD BE INCLUDED AS "ADDITIONS" ON REPORT 18. | J114: =SUM(J110:J113) -> 0 | K114: =SUM(K110:K113) -> 0 | L114: =IF(J114=K114,"<- Debits and Credits equal each other.","<- Debits and Credits do not equal each other.") -> <- Debits and Credits equal each other.
B115: ** This amount should be included in the additions column on the LS-Lease Liability and LS-Check Figures Tabs.
D120: Informational - Ending Balances of Assets and Liabilities
K121: Debit (Credit)
D122: Acct 0476 - RIGHT-TO-USE LEASED LAND - AMORTIZABLE | K122: =J15+J39-K88-K101+J110 -> 0
D123: Acct 0478 - RIGHT-TO-USE LEASED EQUIPMENT - AMORTIZABLE | K123: =J16+J40-K89-K102+J111 -> 0
D124: Acct 0477 - RIGHT-TO-USE LEASED BUILDINGS - AMORTIZABLE | K124: =J17+J41-K90-K103+J112 -> 745203
D125: Acct 0485 - ACCUMULATED AMORTIZATION - RIGHT-TO-USE LEASED LAND | K125: =-K20-K56+J85+J97 -> 0
...

Sheet LS-Fund 0890 Journal Entries
A1: Lessee-Type Contracts Fund-by-Fund Journal Entries Form (to be submitted to the SCO annually—one form per fund)
A2: Manually complete every yellow field in this worksheet—there are no automatically calculated data-entry cells in this worksheet.
A3: Fiscal Year: | F3: 2022–2023
A4: Organization Name: | F4: Secretary for Transportation Agency
A5: Organization Code (4-Digits): | F5: 0521
A6: Fund Number (4-Digits): | F6: 890
A7: Fund Classification: | F7: Governmental
A8: Fund Type: | F8: Governmental Fund
A9: Functional Expense: | F9: =IFERROR(IF(F7="Proprietary","Proprietary Fund",VLOOKUP(F5,qryIndex02a!$A$2:$K$654,4,FALSE)),"Unidentified") -> TRANSPORTATION
A12: Establish Beginning Balances (existing leases only)
A13: Entry #
A14: 0 | B14: Roll forward prior year right-to-use leases to record opening balances. | M14: Combined Lessee Templates | P14: From SCO BB List | S14: Difference
A15: *Rpt 18 | B15: Dr: Acct 0476 - RIGHT-TO-USE LEASED LAND - AMORTIZABLE | J15: =M15 -> 0 | S15: =P15-M15 -> 0
A16: *Rpt 18 | B16: Dr: Acct 0478 - RIGHT-TO-USE LEASED EQUIPMENT - AMORTIZABLE | J16: =M16 -> 0 | S16: =P16-M16 -> 0
A17: *Rpt 18 | B17: Dr: Acct 0477 - RIGHT-TO-USE LEASED BUILDINGS - AMORTIZABLE | J17: =M17 -> 1243420 | M17: 1243420 | S17: =P17-M17 -> -1243420
B18: Dr: Acct 0950 - BEGINNING FUND BALANCE | J18: =P18 -> 0 | P18: =IF(SUM($Q$20:$Q$23)>SUM($P$15:$P$17),SUM($Q$20:$Q$23)-SUM($P$15:$P$17),0) -> 0 | S18: =P18-M18 -> 0
B19: Dr: Acct 0952 - BEGINNING FUND ADJUSTMENT/PRIOR PERIOD ADJUSTMENT | J19: =IF(SUM($K$20:$K$24)>SUM($J$15:$J$18),SUM($K$20:$K$24)-SUM($J$15:$J$18),0) -> 0 | S19: =P19-M19 -> 0
C20: Cr: Acct 0485 - ACCUMULATED AMORTIZATION - RIGHT-TO-USE LEASED LAND | K20: =N20 -> 0 | S20: =P20-M20 -> 0
C21: Cr: Acct 0479 - ACCUMULATED AMORTIZATION - RIGHT-TO-USE LEASED EQUIPMENT | K21: =N21 -> 0 | S21: =Q21-N21 -> 0
C22: Cr: Acct 0486 - ACCUMULATED AMORTIZATION - RIGHT-TO-USE LEASED BUILDINGS | K22: =N22 -> 155428 | N22: 155428 | S22: =Q22-N22 -> -155428
A23: **LS LL/CF | C23: Cr: Acct 0691 - RIGHT-TO-USE LEASE LIABILITY | K23: =N23 -> 1082272 | N23: 1082272 | S23: =Q23-N23 -> -1082272
C24: Cr: Acct 0950 - BEGINNING FUND BALANCE | K24: =Q24 -> 0 | Q24: =IF(SUM($Q$20:$Q$23)<SUM($P$15:$P$17),-SUM($Q$20:$Q$23)+SUM($P$15:$P$17),0) -> 0 | S24: =Q24-N24 -> 0
C25: Cr: Acct 0952 - BEGINNING FUND ADJUSTMENT/PRIOR PERIOD ADJUSTMENT | K25: =IF(SUM($K$20:$K$24)<SUM($J$15:$J$18),-SUM($K$20:$K$24)+SUM($J$15:$J$18),0) -> 5720 | S25: =Q25-N25 -> 0
J26: =SUM(J15:J25) -> 1243420 | K26: =SUM(K15:K25) -> 1243420 | L26: =IF(J26=K26,"<- Debits and Credits equal each other.","<- Debits and Credits do not equal each other.") -> <- Debits and Credits equal each other.
B27: * THESE ASSET AMOUNTS SHOULD BE REPORTED AS BEGINNING BALANCES ON REPORT 18.
B28: ** This amount should be included in the beginning balance column on the LS-Lease Liability and LS-Check Figures Tabs.
A31: Record New Leases (new leases only)
A32: 1 | B32: Record lease contract commencement (fund-based entries only)
B33: Dr: Acct 0842 - CAPITAL OUTLAY
C34: Cr: Acct 0789 - LEASE AND OTHER FINANCING PROCEEDS
C35: =IF($F$7="Proprietary","Cr: Acct 0870 - SERVICES & CHARGES (MG ADJ)",VLOOKUP($F$9,'Drop Down Menus'!$F$2:$G$10,2,FALSE)) -> Cr: Acct 0830 - TRANSPORTATION (GAAP ADJ)
J36: =SUM(J33:J35) -> 0 | K36: =SUM(K33:K35) -> 0 | L36: =IF(J36=K36,"<- Debits and Credits equal each other.","<- Debits and Credits do not equal each other.") -> <- Debits and Credits equal each other.
A38: 2 | B38: Record leased assets.
A39: *Rpt 18 | B39: Dr: Acct 0476 - RIGHT-TO-USE LEASED LAND - AMORTIZABLE
A40: *Rpt 18 | B40: Dr: Acct 0478 - RIGHT-TO-USE LEASED EQUIPMENT - AMORTIZABLE
A41: *Rpt 18 | B41: Dr: Acct 0477 - RIGHT-TO-USE LEASED BUILDINGS - AMORTIZABLE
C42: Cr: Acct 0842 - CAPITAL OUTLAY
B43: * THESE AMOUNTS SHOULD BE INCLUDED AS "ADDITIONS" ON REPORT 18. | J43: =SUM(J39:J42) -> 0 | K43: =SUM(K39:K42) -> 0 | L43: =IF(J43=K43,"<- Debits and Credits equal each other.","<- Debits and Credits do not equal each other.") -> <- Debits and Credits equal each other.
A46: 3 | B46: Replace proceeds from leases with right-to-use lease liability.
B47: Dr: Acct 0789 - LEASE AND OTHER FINANCING PROCEEDS
A48: **LS LL/CF | C48: Cr: Acct 0691 - RIGHT-TO-USE LEASE LIABILITY
J49: =SUM(J47:J48) -> 0 | K49: =SUM(K47:K48) -> 0 | L49: =IF(J49=K49,"<- Debits and Credits equal each other.","<- Debits and Credits do not equal each other.") -> <- Debits and Credits equal each other.
B50: ** This amount should be included in the additions column on the LS-Lease Liability and LS-Check Figures Tabs.
A53: Record Annual Activity (all leases)
A54: 4 | B54: Record amortization of the leased assets for the year.
B55: Dr: Acct 0875 - DEPRECIATION/AMORTIZATION
C56: Cr: Acct 0485 - ACCUMULATED AMORTIZATION - RIGHT-TO-USE LEASED LAND
C57: Cr: Acct 0479 - ACCUMULATED AMORTIZATION - RIGHT-TO-USE LEASED EQUIPMENT
C58: Cr: Acct 0486 - ACCUMULATED AMORTIZATION - RIGHT-TO-USE LEASED BUILDINGS
J59: =SUM(J55:J58) -> 0 | K59: =SUM(K55:K58) -> 0 | L59: =IF(J59=K59,"<- Debits and Credits equal each other.","<- Debits and Credits do not equal each other.") -> <- Debits and Credits equal each other.
A61: 5 | B61: Reclassify rents and leases exp. to lease contract principal and interest exp.
B62: Dr: Acct 0848 - DEBT SERVICE - PRINCIPAL LEASES
B63: =IF(F7="Governmental","Dr: Acct 0851 - DEBT SERVICE - INTEREST LEASES","Dr: Acct 0894 - INTEREST EXPENSE AND FISCAL CHARGES") -> Dr: Acct 0851 - DEBT SERVICE - INTEREST LEASES
C64: =IF($F$7="Proprietary","Cr: Acct 0870 - SERVICES & CHARGES (MG ADJ)",VLOOKUP($F$9,'Drop Down Menus'!$F$2:$G$10,2,FALSE)) -> Cr: Acct 0830 - TRANSPORTATION (GAAP ADJ)
J65: =SUM(J62:J64) -> 0 | K65: =SUM(K62:K64) -> 0 | L65: =IF(J65=K65,"<- Debits and Credits equal each other.","<- Debits and Credits do not equal each other.") -> <- Debits and Credits equal each other.
A67: 6 | B67: Reduce lease contracts liability for total current year principal payments.
A68: **LS LL/CF | B68: Dr: Acct 0691 - RIGHT-TO-USE LEASE LIABILITY
C69: Cr: Acct 0848 - DEBT SERVICE - PRINCIPAL LEASES
J70: =SUM(J68:J69) -> 0 | K70: =SUM(K68:K69) -> 0 | L70: =IF(J70=K70,"<- Debits and Credits equal each other.","<- Debits and Credits do not equal each other.") -> <- Debits and Credits equal each other.
B71: ** This amount should be included in the deductions column on the LS-Lease Liability and LS-Check Figures Tabs.
A74: 7 | B74: Reclassify the principal amount due in the next FY to the current liability.
A75: **LS LL/CF | B75: Dr: Acct 0691 - RIGHT-TO-USE LEASE LIABILITY
C76: Cr: Acct 0649 - RIGHT-TO-USE LEASE LIABILITY (CURRENT PORTION LT)
B77: NOTE: This is an annual accrual. It is to be reversed at the start of the next fiscal year. SCO combines the current and non current amount in Entry #0 to reestablish the beginning balances. No action required. | J77: =SUM(J75:J76) -> 0 | K77: =SUM(K75:K76) -> 0 | L77: =IF(J77=K77,"<- Debits and Credits equal each other.","<- Debits and Credits do not equal each other.") -> <- Debits and Credits equal each other.
B80: ** This amount should be included in the due in one year column on the LS-Lease Liability and LS-Check Figures Tabs.
A83: Remove Lease Asset at the End of the Lease Term (only at the end of the lease term)
A84: 8 | B84: Record entry to write off the lease asset and accumulated amortization at the end of the lease term.
B85: Dr: Acct 0485 - ACCUMULATED AMORTIZATION - RIGHT-TO-USE LEASED LAND
B86: Dr: Acct 0479 - ACCUMULATED AMORTIZATION - RIGHT-TO-USE LEASED EQUIPMENT
B87: Dr: Acct 0486 - ACCUMULATED AMORTIZATION - RIGHT-TO-USE LEASED BUILDINGS
A88: *Rpt 18 | C88: Cr: Acct 0476 - RIGHT-TO-USE LEASED LAND - AMORTIZABLE
A89: *Rpt 18 | C89: Cr: Acct 0478 - RIGHT-TO-USE LEASED EQUIPMENT - AMORTIZABLE
A90: *Rpt 18 | C90: Cr: Acct 0477 - RIGHT-TO-USE LEASED BUILDINGS - AMORTIZABLE
B91: * THESE AMOUNTS SHOULD BE INCLUDED AS "DEDUCTIONS" ON REPORT 18. | J91: =SUM(J85:J90) -> 0 | K91: =SUM(K85:K90) -> 0 | L91: =IF(J91=K91,"<- Debits and Credits equal each other.","<- Debits and Credits do not equal each other.") -> <- Debits and Credits equal each other.
A94: Lease Remeasurement and Modifications (only if a significant modification occurred during the fiscal year)
A95: 9 | B95: Record early termination or lease modifications to decrease in the RTU leased asset.
A96: **LS LL/CF | B96: Dr: Acct 0691 - RIGHT-TO-USE LEASE LIABILITY | J96: 1082272
B97: Dr: Acct 0485 - ACCUMULATED AMORTIZATION - RIGHT-TO-USE LEASED LAND
B98: Dr: Acct 0479 - ACCUMULATED AMORTIZATION - RIGHT-TO-USE LEASED EQUIPMENT
B99: Dr: Acct 0486 - ACCUMULATED AMORTIZATION - RIGHT-TO-USE LEASED BUILDINGS | J99: 155428
B100: =IF($F$7="Proprietary","Dr: Acct 0870 - SERVICES & CHARGES (MG ADJ)",VLOOKUP($F$9,'Drop Down Menus'!$F$2:$H$10,3,FALSE)) -> Dr: Acct 0830 - TRANSPORTATION (GAAP ADJ) | J100: 5720
A101: *Rpt 18 | C101: Cr: Acct 0476 - RIGHT-TO-USE LEASED LAND - AMORTIZABLE
A102: *Rpt 18 | C102: Cr: Acct 0478 - RIGHT-TO-USE LEASED EQUIPMENT - AMORTIZABLE
A103: *Rpt 18 | C103: Cr: Acct 0477 - RIGHT-TO-USE LEASED BUILDINGS - AMORTIZABLE | K103: 1243420
C104: =IF($F$7="Proprietary","Dr: Acct 0870 - SERVICES & CHARGES (MG ADJ)",VLOOKUP($F$9,'Drop Down Menus'!$F$2:$G$10,2,FALSE)) -> Cr: Acct 0830 - TRANSPORTATION (GAAP ADJ)
B105: * THESE AMOUNTS SHOULD BE INCLUDED AS "DEDUCTIONS" ON REPORT 18. | J105: =SUM(J96:J104) -> 1243420 | K105: =SUM(K96:K104) -> 1243420 | L105: =IF(J105=K105,"<- Debits and Credits equal each other.","<- Debits and Credits do not equal each other.") -> <- Debits and Credits equal each other.
B106: ** This amount should be included in the deductions column on the LS-Lease Liability and LS-Check Figures Tabs.
A109: 10 | B109: Record lease modifications to increase in the RTU leased asset.
A110: *Rpt 18 | B110: Dr: Acct 0476 - RIGHT-TO-USE LEASED LAND - AMORTIZABLE
A111: *Rpt 18 | B111: Dr: Acct 0478 - RIGHT-TO-USE LEASED EQUIPMENT - AMORTIZABLE
A112: *Rpt 18 | B112: Dr: Acct 0477 - RIGHT-TO-USE LEASED BUILDINGS - AMORTIZABLE
A113: **LS LL/CF | C113: Cr: Acct 0691 - RIGHT-TO-USE LEASE LIABILITY
B114: * THESE AMOUNTS SHOULD BE INCLUDED AS "ADDITIONS" ON REPORT 18. | J114: =SUM(J110:J113) -> 0 | K114: =SUM(K110:K113) -> 0 | L114: =IF(J114=K114,"<- Debits and Credits equal each other.","<- Debits and Credits do not equal each other.") -> <- Debits and Credits equal each other.
B115: ** This amount should be included in the additions column on the LS-Lease Liability and LS-Check Figures Tabs.
D120: Informational - Ending Balances of Assets and Liabilities
K121: Debit (Credit)
D122: Acct 0476 - RIGHT-TO-USE LEASED LAND - AMORTIZABLE | K122: =J15+J39-K88-K101+J110 -> 0
D123: Acct 0478 - RIGHT-TO-USE LEASED EQUIPMENT - AMORTIZABLE | K123: =J16+J40-K89-K102+J111 -> 0
D124: Acct 0477 - RIGHT-TO-USE LEASED BUILDINGS - AMORTIZABLE | K124: =J17+J41-K90-K103+J112 -> 0
D125: Acct 0485 - ACCUMULATED AMORTIZATION - RIGHT-TO-USE LEASED LAND | K125: =-K20-K56+J85+J97 -> 0
...

Sheet LS-Department Note Disclosure
A1: Submit one form for the department to the SCO annually.
A2: Note: There are three tables of note disclosures on this form —1) governmental funds, 2) proprietary - internal service funds, and 3) proprietary - enterprise funds. Complete all applicable tables before submitting to the SCO.
A3: Manually complete every yellow field in this worksheet—there are no automatically calculated cells in this worksheet.
A4: Complete the fields below using aggregated and summarized information from all of your department's completed contract template forms.
A5: The fields in this worksheet should contain the sums of the department's contracts' corresponding information in their note disclosure worksheets.
A7: I. Governmental funds
A8: Fiscal Year: | B8: 2022–2023
A9: Organization Code:
A10: Organization Name:
A11: The below information must be entered manually.
B12: Principal Payments | C12: Interest Payments | D12: ="All of the below questions are for Fiscal Year "&$B$8&":" -> All of the below questions are for Fiscal Year 2022–2023:
A13: =RIGHT(B8,4)&"–"&RIGHT(B8,4)+1 -> 2023–2024 | B13: 557665 | C13: 42244 | D13: 1. Did your leasing arrangements have any variable payments which ARE NOT included in the measurement of the lease liability?
A14: =LEFT(A13,4)+1&"–"&RIGHT(A13,4)+1 -> 2024–2025 | B14: 577579 | C14: 37143
A15: =LEFT(A14,4)+1&"–"&RIGHT(A14,4)+1 -> 2025–2026 | B15: 597908 | C15: 31861 | D15: No
A16: =LEFT(A15,4)+1&"–"&RIGHT(A15,4)+1 -> 2026–2027 | B16: 618659 | C16: 26395 | D16: ="If yes, record the dollar amount of variable payments below for fiscal year "&$B$8&":" -> If yes, record the dollar amount of variable payments below for fiscal year 2022–2023:
A17: =LEFT(A16,4)+1&"–"&RIGHT(A16,4)+1 -> 2027–2028 | B17: 639843 | C17: 20740
A18: =LEFT(A17,4)+1&"–"&RIGHT(A17,4)+5 -> 2028–2033 | B18: =1955551-1 -> 1955550 | C18: 29123 | D18: 2. Do your leasing arrangements have any residual value guarantees provided by YOU which ARE NOT included in the measurement of the lease liability?
A19: =LEFT(A18,4)+5&"–"&RIGHT(A18,4)+5 -> 2033–2038
A20: =LEFT(A19,4)+5&"–"&RIGHT(A19,4)+5 -> 2038–2043 | D20: No
A21: =LEFT(A20,4)+5&"–"&RIGHT(A20,4)+5 -> 2043–2048 | D21: ="If yes, record the dollar amount of any payments made for residual value guarantees below for fiscal year "&$B$8&":" -> If yes, record the dollar amount of any payments made for residual value guarantees below for fiscal year 2022–2023:
A22: =LEFT(A21,4)+5&"–"&RIGHT(A21,4)+5 -> 2048–2053
A23: =LEFT(A22,4)+5&"–"&RIGHT(A22,4)+5 -> 2053–2058
A24: =LEFT(A23,4)+5&"–"&RIGHT(A23,4)+5 -> 2058–2063 | D24: ="3. Record the dollar amount of any other payments for this lease, such as termination penalties, not previously recorded in the payment schedule for fiscal year "&$B$8&":" -> 3. Record the dollar amount of any other payments for this lease, such as termination penalties, not previously recorded in the payment schedule for fiscal year 2022–2023:
A25: =LEFT(A24,4)+5&"–"&RIGHT(A24,4)+5 -> 2063–2068
A26: =LEFT(A25,4)+5&"–"&RIGHT(A25,4)+5 -> 2068–2073
A27: =LEFT(A26,4)+5&"–"&RIGHT(A26,4)+5 -> 2073–2078 | D27: ="4. Did you receive any lease incentives from the lessor (not already included in the lease measurment) during fiscal year "&$B$8&"? If so, record the amount below:" -> 4. Did you receive any lease incentives from the lessor (not already included in the lease measurment) during fiscal year 2022–2023? If so, record the amount below:
A28: =LEFT(A27,4)+5&"–"&RIGHT(A27,4)+5 -> 2078–2083
A29: =LEFT(A28,4)+5&"–"&RIGHT(A28,4)+5 -> 2083–2088 | D29: No
A30: =LEFT(A29,4)+5&"–"&RIGHT(A29,4)+5 -> 2088–2093 | D30: =CONCATENATE("5. Are there any lease commitments known that have yet to commence as of June 30, ",RIGHT(B8,4),"?") -> 5. Are there any lease commitments known that have yet to commence as of June 30, 2023?
A31: =LEFT(A30,4)+5&"–"&RIGHT(A30,4)+5 -> 2093–2098 | D31: No
A32: =LEFT(A31,4)+5&"–"&RIGHT(A31,4)+5 -> 2098–2103 | D32: ="If yes, record the dollar amount of any lease commitments not commenced below for fiscal year "&A13&"." -> If yes, record the dollar amount of any lease commitments not commenced below for fiscal year 2023–2024.
A33: =LEFT(A32,4)+5&"–"&RIGHT(A32,4)+5 -> 2103–2108
A34: =LEFT(A33,4)+5&"–"&RIGHT(A33,4)+5 -> 2108–2113
A35: =LEFT(A34,4)+5&"–"&RIGHT(A34,4)+5 -> 2113–2118
A36: =LEFT(A35,4)+5&"–"&RIGHT(A35,4)+5 -> 2118–2123
A38: II. Proprietary - INTERNAL SERVICE FUNDS
A39: Fiscal Year: | B39: =B8 -> 2022–2023
A40: Organization Code: | B40: =B9 -> 0
A41: Organization Name: | B41: =B10 -> 0
A42: The below information must be entered manually.
B43: Principal Payments | C43: Interest Payments | D43: ="All of the below questions are for Fiscal Year "&$B$8&":" -> All of the below questions are for Fiscal Year 2022–2023:
A44: =RIGHT(B39,4)&"–"&RIGHT(B39,4)+1 -> 2023–2024 | D44: 1. Did your leasing arrangements have any variable payments which ARE NOT included in the measurement of the lease liability?
A45: =LEFT(A44,4)+1&"–"&RIGHT(A44,4)+1 -> 2024–2025
A46: =LEFT(A45,4)+1&"–"&RIGHT(A45,4)+1 -> 2025–2026
A47: =LEFT(A46,4)+1&"–"&RIGHT(A46,4)+1 -> 2026–2027 | D47: ="If yes, record the dollar amount of variable payments below for fiscal year "&$B$8&":" -> If yes, record the dollar amount of variable payments below for fiscal year 2022–2023:
A48: =LEFT(A47,4)+1&"–"&RIGHT(A47,4)+1 -> 2027–2028
A49: =LEFT(A48,4)+1&"–"&RIGHT(A48,4)+5 -> 2028–2033 | D49: 2. Do your leasing arrangements have any residual value guarantees provided by YOU which ARE NOT included in the measurement of the lease liability?
A50: =LEFT(A49,4)+5&"–"&RIGHT(A49,4)+5 -> 2033–2038
A51: =LEFT(A50,4)+5&"–"&RIGHT(A50,4)+5 -> 2038–2043
A52: =LEFT(A51,4)+5&"–"&RIGHT(A51,4)+5 -> 2043–2048 | D52: ="If yes, record the dollar amount of any payments made for residual value guarantees below for fiscal year "&$B$8&":" -> If yes, record the dollar amount of any payments made for residual value guarantees below for fiscal year 2022–2023:
A53: =LEFT(A52,4)+5&"–"&RIGHT(A52,4)+5 -> 2048–2053
A54: =LEFT(A53,4)+5&"–"&RIGHT(A53,4)+5 -> 2053–2058
A55: =LEFT(A54,4)+5&"–"&RIGHT(A54,4)+5 -> 2058–2063 | D55: ="3. Record the dollar amount of any other payments for this lease, such as termination penalties, not previously recorded in the payment schedule for fiscal year "&$B$8&":" -> 3. Record the dollar amount of any other payments for this lease, such as termination penalties, not previously recorded in the payment schedule for fiscal year 2022–2023:
A56: =LEFT(A55,4)+5&"–"&RIGHT(A55,4)+5 -> 2063–2068
A57: =LEFT(A56,4)+5&"–"&RIGHT(A56,4)+5 -> 2068–2073
A58: =LEFT(A57,4)+5&"–"&RIGHT(A57,4)+5 -> 2073–2078 | D58: ="4. Did you receive any lease incentives from the lessor (not already included in the lease measurment) during fiscal year "&$B$8&"? If so, record the amount below:" -> 4. Did you receive any lease incentives from the lessor (not already included in the lease measurment) during fiscal year 2022–2023? If so, record the amount below:
A59: =LEFT(A58,4)+5&"–"&RIGHT(A58,4)+5 -> 2078–2083
A60: =LEFT(A59,4)+5&"–"&RIGHT(A59,4)+5 -> 2083–2088
A61: =LEFT(A60,4)+5&"–"&RIGHT(A60,4)+5 -> 2088–2093 | D61: =CONCATENATE("5. Are there any lease commitments known that have yet to commence as of June 30, ",RIGHT(B39,4),"?") -> 5. Are there any lease commitments known that have yet to commence as of June 30, 2023?
A62: =LEFT(A61,4)+5&"–"&RIGHT(A61,4)+5 -> 2093–2098
A63: =LEFT(A62,4)+5&"–"&RIGHT(A62,4)+5 -> 2098–2103 | D63: ="If yes, record the dollar amount of any lease commitments not commenced below for fiscal year "&A44&"." -> If yes, record the dollar amount of any lease commitments not commenced below for fiscal year 2023–2024.
A64: =LEFT(A63,4)+5&"–"&RIGHT(A63,4)+5 -> 2103–2108
A65: =LEFT(A64,4)+5&"–"&RIGHT(A64,4)+5 -> 2108–2113
A66: =LEFT(A65,4)+5&"–"&RIGHT(A65,4)+5 -> 2113–2118
A67: =LEFT(A66,4)+5&"–"&RIGHT(A66,4)+5 -> 2118–2123
A69: III. Proprietary - ENTERPRISE FUNDS
A70: Fiscal Year: | B70: =B8 -> 2022–2023
A71: Organization Code: | B71: =B9 -> 0
A72: Organization Name: | B72: =B10 -> 0
A73: The below information must be entered manually.
B74: Principal Payments | C74: Interest Payments | D74: ="All of the below questions are for Fiscal Year "&$B$8&":" -> All of the below questions are for Fiscal Year 2022–2023:
A75: =RIGHT(B70,4)&"–"&RIGHT(B70,4)+1 -> 2023–2024 | D75: 1. Did your leasing arrangements have any variable payments which ARE NOT included in the measurement of the lease liability?
A76: =LEFT(A75,4)+1&"–"&RIGHT(A75,4)+1 -> 2024–2025
A77: =LEFT(A76,4)+1&"–"&RIGHT(A76,4)+1 -> 2025–2026
A78: =LEFT(A77,4)+1&"–"&RIGHT(A77,4)+1 -> 2026–2027 | D78: ="If yes, record the dollar amount of variable payments below for fiscal year "&$B$8&":" -> If yes, record the dollar amount of variable payments below for fiscal year 2022–2023:
A79: =LEFT(A78,4)+1&"–"&RIGHT(A78,4)+1 -> 2027–2028
A80: =LEFT(A79,4)+1&"–"&RIGHT(A79,4)+5 -> 2028–2033 | D80: 2. Do your leasing arrangements have any residual value guarantees provided by YOU which ARE NOT included in the measurement of the lease liability?
A81: =LEFT(A80,4)+5&"–"&RIGHT(A80,4)+5 -> 2033–2038
A82: =LEFT(A81,4)+5&"–"&RIGHT(A81,4)+5 -> 2038–2043
A83: =LEFT(A82,4)+5&"–"&RIGHT(A82,4)+5 -> 2043–2048 | D83: ="If yes, record the dollar amount of any payments made for residual value guarantees below for fiscal year "&$B$8&":" -> If yes, record the dollar amount of any payments made for residual value guarantees below for fiscal year 2022–2023:
A84: =LEFT(A83,4)+5&"–"&RIGHT(A83,4)+5 -> 2048–2053
A85: =LEFT(A84,4)+5&"–"&RIGHT(A84,4)+5 -> 2053–2058
A86: =LEFT(A85,4)+5&"–"&RIGHT(A85,4)+5 -> 2058–2063 | D86: ="3. Record the dollar amount of any other payments for this lease, such as termination penalties, not previously recorded in the payment schedule for fiscal year "&$B$8&":" -> 3. Record the dollar amount of any other payments for this lease, such as termination penalties, not previously recorded in the payment schedule for fiscal year 2022–2023:
A87: =LEFT(A86,4)+5&"–"&RIGHT(A86,4)+5 -> 2063–2068
A88: =LEFT(A87,4)+5&"–"&RIGHT(A87,4)+5 -> 2068–2073
A89: =LEFT(A88,4)+5&"–"&RIGHT(A88,4)+5 -> 2073–2078 | D89: ="4. Did you receive any lease incentives from the lessor (not already included in the lease measurment) during fiscal year "&$B$8&"? If so, record the amount below:" -> 4. Did you receive any lease incentives from the lessor (not already included in the lease measurment) during fiscal year 2022–2023? If so, record the amount below:
A90: =LEFT(A89,4)+5&"–"&RIGHT(A89,4)+5 -> 2078–2083
A91: =LEFT(A90,4)+5&"–"&RIGHT(A90,4)+5 -> 2083–2088
A92: =LEFT(A91,4)+5&"–"&RIGHT(A91,4)+5 -> 2088–2093 | D92: =CONCATENATE("5. Are there any lease commitments known that have yet to commence as of June 30, ",RIGHT(B70,4),"?") -> 5. Are there any lease commitments known that have yet to commence as of June 30, 2023?
A93: =LEFT(A92,4)+5&"–"&RIGHT(A92,4)+5 -> 2093–2098
A94: =LEFT(A93,4)+5&"–"&RIGHT(A93,4)+5 -> 2098–2103 | D94: ="If yes, record the dollar amount of any lease commitments not commenced below for fiscal year "&A75&"." -> If yes, record the dollar amount of any lease commitments not commenced below for fiscal year 2023–2024.
A95: =LEFT(A94,4)+5&"–"&RIGHT(A94,4)+5 -> 2103–2108
A96: =LEFT(A95,4)+5&"–"&RIGHT(A95,4)+5 -> 2108–2113
A97: =LEFT(A96,4)+5&"–"&RIGHT(A96,4)+5 -> 2113–2118
A98: =LEFT(A97,4)+5&"–"&RIGHT(A97,4)+5 -> 2118–2123

Sheet LS-Lease Liabilities
J3: Schedule of Changes in Lease Liabilities
J4: =CONCATENATE("FY ",'LS-Fund 0042 Journal Entries'!F3) -> FY 2022–2023
J5: =CONCATENATE("Business Unit ",'LS-Department Note Disclosure'!B9," - ",'LS-Department Note Disclosure'!B10) -> Business Unit -
F7: =CONCATENATE("Balance July 1, ",MID(J4,4,4)) -> Balance July 1, 2022 | H7: Additions | J7: Deductions | L7: =CONCATENATE("Balance June 30, ",RIGHT(J4,4)) -> Balance June 30, 2023 | N7: Due Within One Year | P7: Noncurrent Liabilities
F8: (Entry #0) | H8: (Entry #3 & 10) | J8: (Entry #6 & 9) | N8: (Entry #7)
C9: Governmental Funds
D10: Lease Liability | F10: =+'LS-Fund 0042 Journal Entries'!K23+'LS-Fund 0044 Journal Entries'!K23+'LS-Fund 0046 Journal Entries'!K23+'LS-Fund 0890 Journal Entries'!K23 -> 1517487 | H10: =+'LS-Fund 0042 Journal Entries'!K48+'LS-Fund 0042 Journal Entries'!K113+'LS-Fund 0044 Journal Entries'!K48+'LS-Fund 0044 Journal Entries'!K113+'LS-Fund 0046 Journal Entries'!K48+'LS-Fund 0046 Journal Entries'!K113+'LS-Fund 0890 Journal Entries'!K48+'LS-Fund 0890 Journal Entries'!K113 -> 5701093 | J10: =+'LS-Fund 0042 Journal Entries'!K69+'LS-Fund 0042 Journal Entries'!J96+'LS-Fund 0044 Journal Entries'!J68+'LS-Fund 0044 Journal Entries'!J96+'LS-Fund 0046 Journal Entries'!J68+'LS-Fund 0046 Journal Entries'!J96+'LS-Fund 0890 Journal Entries'!J68+'LS-Fund 0890 Journal Entries'!J96 -> 2271376 | L10: =SUM(F10+H10-J10) -> 4947204 | N10: ='LS-Fund 0042 Journal Entries'!J75+'LS-Fund 0044 Journal Entries'!J75+'LS-Fund 0046 Journal Entries'!J75 -> 557665 | P10: =L10-N10 -> 4389539
C11: Total Governmental Funds | F11: =SUM(F10:F10) -> 1517487 | H11: =SUM(H10:H10) -> 5701093 | J11: =SUM(J10:J10) -> 2271376 | L11: =SUM(L10:L10) -> 4947204 | N11: =SUM(N10:N10) -> 557665 | P11: =SUM(P10:P10) -> 4389539
C13: Proprietary - Internal Service Funds
D14: Lease Liability | L14: =SUM(F14+H14-J14) -> 0 | P14: =L14-N14 -> 0
C15: Total Proprietary - Internal Service Funds | F15: =SUM(F14:F14) -> 0 | H15: =SUM(H14:H14) -> 0 | J15: =SUM(J14:J14) -> 0 | L15: =SUM(L14:L14) -> 0 | N15: =SUM(N14:N14) -> 0 | P15: =SUM(P14:P14) -> 0
C17: Proprietary - Enterprise Funds
D18: Lease Liability | L18: =SUM(F18+H18-J18) -> 0 | P18: =L18-N18 -> 0
C19: Total Proprietary - Enterprise Funds | F19: =SUM(F18:F18) -> 0 | H19: =SUM(H18:H18) -> 0 | J19: =SUM(J18:J18) -> 0 | L19: =SUM(L18:L18) -> 0 | N19: =SUM(N18:N18) -> 0 | P19: =SUM(P18:P18) -> 0

Sheet LS-Check Figures  
A1: GASB Statement No. 87 Leases
A2: Check Figures
A4: Purpose:
A5: The purpose of this workbook is to check the figures entered in the journal entries reconcile to the future principal payments disclosed and the changes in the schedule of the lease liabilities.
A8: NOTE: If multiple funds are included in this workbook, manually complete every yellow field by consolidating the entries by fund type (Governmental, Proprietary ISF, and Proprietary EF).
A10: 1. To reconcile the journal entries of RTU Lease Liability with the principal payments in Note Disclosure.
B11: a) Governmental Funds
B13: Journal Entries | N13: Department Note Disclosure
B14: Beginning Balance | D14: Additions | F14: Deductions | H14: Deductions (Mod) | J14: Additions (Mod)
B15: Entry #0 | C15: + | D15: Entry #3 | E15: - | F15: Entry #6 | G15: - | H15: Entry #9 | I15: + | J15: Entry #10 | N15: Sum Principal Payments | P15: Variance
B16: =+'LS-Fund 0042 Journal Entries'!K23+'LS-Fund 0044 Journal Entries'!K23+'LS-Fund 0046 Journal Entries'!K23+'LS-Fund 0890 Journal Entries'!K23 -> 1517487 | C16: + | D16: =+'LS-Fund 0042 Journal Entries'!K48+'LS-Fund 0044 Journal Entries'!K48+'LS-Fund 0046 Journal Entries'!K48+'LS-Fund 0890 Journal Entries'!K48 -> 3705635 | E16: - | F16: =+'LS-Fund 0042 Journal Entries'!J68+'LS-Fund 0044 Journal Entries'!J68+'LS-Fund 0046 Journal Entries'!J68+'LS-Fund 0890 Journal Entries'!J68 -> 753889 | G16: - | H16: =+'LS-Fund 0042 Journal Entries'!J96+'LS-Fund 0044 Journal Entries'!J96+'LS-Fund 0046 Journal Entries'!J96+'LS-Fund 0890 Journal Entries'!J96 -> 1517487 | I16: + | J16: =+'LS-Fund 0042 Journal Entries'!K113+'LS-Fund 0044 Journal Entries'!K113+'LS-Fund 0046 Journal Entries'!K113+'LS-Fund 0890 Journal Entries'!K113 -> 1995458 | K16: = | L16: =+B16+D16-F16-H16+J16 -> 4947204 | N16: =SUM('LS-Department Note Disclosure'!B13:B36) -> 4947204 | P16: =L16-N16 -> 0
D18: =IF(OR(P16>0, (P16<0)), "Please review and correct the variance.","")
B19: b) Proprietary - Internal Service Funds
B21: Journal Entries | N21: Department Note Disclosure
B22: Beginning Balance | D22: Additions | F22: Deductions | H22: Deductions (Mod) | J22: Additions (Mod)
B23: Entry #0 | C23: + | D23: Entry #3 | E23: - | F23: Entry #6 | G23: - | H23: Entry #9 | I23: + | J23: Entry #10 | N23: Sum Principal Payments | P23: Variance
B24: =IF('LS-Fund 0042 Journal Entries'!$F$8="Proprietary - Internal Service Fund",'LS-Fund 0042 Journal Entries'!$K$23,0) -> 0 | C24: + | D24: =IF('LS-Fund 0042 Journal Entries'!$F$8="Proprietary - Internal Service Fund",'LS-Fund 0042 Journal Entries'!$K$48,0) -> 0 | E24: - | F24: =IF('LS-Fund 0042 Journal Entries'!$F$8="Proprietary - Internal Service Fund",'LS-Fund 0042 Journal Entries'!$J$68,0) -> 0 | G24: - | H24: =IF('LS-Fund 0042 Journal Entries'!$F$8="Proprietary - Internal Service Fund",'LS-Fund 0042 Journal Entries'!$J$96,0) -> 0 | I24: + | J24: =IF('LS-Fund 0042 Journal Entries'!$F$8="Proprietary - Internal Service Fund",'LS-Fund 0042 Journal Entries'!$K$113,0) -> 0 | K24: = | L24: =+B24+D24-F24-H24+J24 -> 0 | N24: =SUM('LS-Department Note Disclosure'!B44:B67) -> 0 | P24: =L24-N24 -> 0
D26: =IF(OR(P24>0, (P24<0)), "Please review and correct the variance.","")
B28: c) Proprietary - Enterprise Funds
B30: Journal Entries | N30: Department Note Disclosure
B31: Beginning Balance | D31: Additions | F31: Deductions | H31: Deductions (Mod) | J31: Additions (Mod)
B32: Entry #0 | C32: + | D32: Entry #3 | E32: - | F32: Entry #6 | G32: - | H32: Entry #9 | I32: + | J32: Entry #10 | N32: Sum Principal Payments | P32: Variance
B33: =IF('LS-Fund 0042 Journal Entries'!$F$8="Proprietary - Enterprise Fund",'LS-Fund 0042 Journal Entries'!$K$23,0) -> 0 | C33: + | D33: =IF('LS-Fund 0042 Journal Entries'!$F$8="Proprietary - Enterprise Fund",'LS-Fund 0042 Journal Entries'!$K$48,0) -> 0 | E33: - | F33: =IF('LS-Fund 0042 Journal Entries'!$F$8="Proprietary - Enterprise Fund",'LS-Fund 0042 Journal Entries'!$J$68,0) -> 0 | G33: - | H33: =IF('LS-Fund 0042 Journal Entries'!$F$8="Proprietary - Enterprise Fund",'LS-Fund 0042 Journal Entries'!$J$96,0) -> 0 | I33: + | J33: =IF('LS-Fund 0042 Journal Entries'!$F$8="Proprietary - Enterprise Fund",'LS-Fund 0042 Journal Entries'!$K$113,0) -> 0 | K33: = | L33: =+B33+D33-F33-H33+J33 -> 0 | N33: =SUM('LS-Department Note Disclosure'!B75:B98) -> 0 | P33: =L33-N33 -> 0
D35: =IF(OR(P33>0, (P33<0)), "Please review and correct the variance.","")
A37: 2. To match the journal entry to the principal amount due in the next fiscal year in Note Disclosure.
B38: a) Governmental Funds
B40: Journal Entries | N40: Department Note Disclosure
B41: Entry #7 | C41: Due within one year | N41: =CONCATENATE('LS-Department Note Disclosure'!$A$13," Principal Payments") -> 2023–2024 Principal Payments | P41: Variance
B42: =+'LS-Fund 0042 Journal Entries'!J75+'LS-Fund 0044 Journal Entries'!J75+'LS-Fund 0046 Journal Entries'!J75+'LS-Fund 0890 Journal Entries'!J75 -> 557665 | N42: ='LS-Department Note Disclosure'!B13 -> 557665 | P42: =B42-N42 -> 0
D44: =IF(OR(P42>0, (P42<0)), "Please review and correct the variance.","")
B45: b) Proprietary - Internal Service Funds
B47: Journal Entries | N47: Department Note Disclosure
B48: Entry #7 | C48: Due within one year | N48: =CONCATENATE('LS-Department Note Disclosure'!$A$44," Principal Payments") -> 2023–2024 Principal Payments | P48: Variance
B49: =IF('LS-Fund 0042 Journal Entries'!$F$8="Proprietary - Internal Service Fund",'LS-Fund 0042 Journal Entries'!$K$76,0) -> 0 | N49: ='LS-Department Note Disclosure'!B44 -> 0 | P49: =B49-N49 -> 0
D51: =IF(OR(P49>0, (P49<0)), "Please review and correct the variance.","")
B53: c) Proprietary - Enterprise Funds
B55: Journal Entries | N55: Department Note Disclosure
B56: Entry #7 | C56: Due within one year | N56: =CONCATENATE('LS-Department Note Disclosure'!$A$75," Principal Payments") -> 2023–2024 Principal Payments | P56: Variance
B57: =IF('LS-Fund 0042 Journal Entries'!$F$8="Proprietary - Enterprise Fund",'LS-Fund 0042 Journal Entries'!$K$76,0) -> 0 | N57: ='LS-Department Note Disclosure'!B75 -> 0 | P57: =B57-N57 -> 0
D59: =IF(OR(P57>0, (P57<0)), "Please review and correct the variance.","")
A61: 3. To reconcile the journal entries of RTU Lease Liability with the schedule of changes in Lease Liabilities.
B62: a) Governmental Funds
B64: Journal Entries | J64: Totals | L64: Schedule of Changes in Lease Liabilities
P65: Variance
B66: Entry #0 | D66: =$B$16 -> 1517487 | J66: =SUM(D66) -> 1517487 | L66: =CONCATENATE("Balance July 1, ",LEFT('LS-Department Note Disclosure'!$B$8,4)) -> Balance July 1, 2022 | N66: ='LS-Lease Liabilities'!F10 -> 1517487 | P66: =J66-N66 -> 0
B67: Entry #3 | D67: =$D$16 -> 3705635 | E67: + | F67: Entry #10 | H67: =$J$16 -> 1995458 | J67: =SUM(D67,H67) -> 5701093 | L67: Additions | N67: ='LS-Lease Liabilities'!H10 -> 5701093 | P67: =J67-N67 -> 0
B68: Entry #6 | D68: =$F$16 -> 753889 | E68: + | F68: Entry #9 | H68: =$H$16 -> 1517487 | J68: =SUM(D68,H68) -> 2271376 | L68: Deductions | N68: ='LS-Lease Liabilities'!J10 -> 2271376 | P68: =J68-N68 -> 0
B69: Entry #7 | D69: =$B$42 -> 557665 | J69: =SUM(D69) -> 557665 | L69: Due Within One Year | N69: ='LS-Lease Liabilities'!N10 -> 557665 | P69: =J69-N69 -> 0
D71: =IF(OR(P66>0, (P66<0),P67>0,P67<0,P68>0,P68<0,P69>0,P69<0), "Please review and correct the variance.","")
B73: b) Proprietary - Internal Service Funds
B75: Journal Entries | J75: Totals | L75: Schedule of Changes in Lease Liabilities
P76: Variance
B77: Entry #0 | D77: =B24 -> 0 | J77: =SUM(D77) -> 0 | L77: =CONCATENATE("Balance July 1, ",LEFT('LS-Department Note Disclosure'!$B$8,4)) -> Balance July 1, 2022 | N77: ='LS-Lease Liabilities'!F14 -> 0 | P77: =J77-N77 -> 0
B78: Entry #3 | D78: =D24 -> 0 | E78: + | F78: Entry #10 | H78: =$J$24 -> 0 | J78: =SUM(D78,H78) -> 0 | L78: Additions | N78: ='LS-Lease Liabilities'!H14 -> 0 | P78: =J78-N78 -> 0
B79: Entry #6 | D79: =F24 -> 0 | E79: + | F79: Entry #9 | H79: =$H$24 -> 0 | J79: =SUM(D79,H79) -> 0 | L79: Deductions | N79: ='LS-Lease Liabilities'!J14 -> 0 | P79: =J79-N79 -> 0
B80: Entry #7 | D80: =B49 -> 0 | J80: =SUM(D80) -> 0 | L80: Due Within One Year | N80: ='LS-Lease Liabilities'!N14 -> 0 | P80: =J80-N80 -> 0
B84: c) Proprietary - Enterprise Funds
B86: Journal Entries | J86: Totals | L86: Schedule of Changes in Lease Liabilities
P87: Variance
B88: Entry #0 | D88: =B33 -> 0 | J88: =SUM(D88) -> 0 | L88: =CONCATENATE("Balance July 1, ",LEFT('LS-Department Note Disclosure'!$B$8,4)) -> Balance July 1, 2022 | N88: ='LS-Lease Liabilities'!F18 -> 0 | P88: =J88-N88 -> 0
B89: Entry #3 | D89: =D33 -> 0 | E89: + | F89: Entry #10 | H89: =$J$33 -> 0 | J89: =SUM(D89,H89) -> 0 | L89: Additions | N89: ='LS-Lease Liabilities'!H18 -> 0 | P89: =J89-N89 -> 0
B90: Entry #6 | D90: =F33 -> 0 | E90: + | F90: Entry #9 | H90: =$H$33 -> 0 | J90: =SUM(D90,H90) -> 0 | L90: Deductions | N90: ='LS-Lease Liabilities'!J18 -> 0 | P90: =J90-N90 -> 0
B91: Entry #7 | D91: =B57 -> 0 | J91: =SUM(D91) -> 0 | L91: Due Within One Year | N91: ='LS-Lease Liabilities'!N18 -> 0 | P91: =J91-N91 -> 0
D93: =IF(OR(P88>0, (P88<0),P89>0,P89<0,P90>0,P90<0,P91>0,P91<0), "Please review and correct the variance.","")
