Workbook
Name ActuaryCredentialsGASB: [1]DeveloperInfo!$D$19
Name ActuaryNameGASB: [1]DeveloperInfo!$D$17
Name ActuaryTitleGASB: [1]DeveloperInfo!$D$18
Name AdjCNSDate: [1]DeveloperInfo!$D$33
Name AdjCNSDate1: [1]DeveloperInfo!$E$33
Name AdjCNSDateTempEnable: [1]DeveloperInfo!$F$34
Name AgencyCode: #REF!
Name AgencyCode1: #REF!
Name AnalystGASB: [1]DeveloperInfo!$D$20
Name Annuity: #REF!
Name Annuity1: #REF!
Name AnnuityLY: #REF!
Name AssetClasses: '[2]Drop-down menus'!#REF!
Name ASTABPF: [1]DeveloperInfo!$D$36
Name ASTABPF1: [1]DeveloperInfo!$D$37
Name ASTEBPF: [1]DeveloperInfo!$F$37
Name ClientShortGASB: [1]DeveloperInfo!$D$9
Name CLPOWERDisc: [1]Adjust!$H$199
Name CLPOWERDiscMinus1: [1]Adjust!$L$199
Name CLPOWERDiscPlus1: [1]Adjust!$K$199
Name CLPOWERExp: [1]Adjust!$G$199
Name CNSDateDisc: [1]DeveloperInfo!$D$32
Name CNSDateDisc1: [1]DeveloperInfo!$E$32
Name ColaRate: [1]DeveloperInfo!$D$40
Name ConsultantNameGASB: [1]DeveloperInfo!$D$22
Name ConsultantTitleGASB: [1]DeveloperInfo!$D$23
Name Disc1DELTACENSUS: [1]Adjust!$G$102
Name Disc1INTNDIV12: [1]Adjust!$H$195
Name Disc1SINTADJBOM: [1]Adjust!$I$197
Name Disc1SINTNDIV12: [1]Adjust!$I$195
Name DiscDELTACENSUS: [1]Adjust!$H$102
Name DiscINTADJBOM: [1]Adjust!$J$197
Name DiscINTNDIV12: [1]Adjust!$J$195
Name DiscMinusOneINTADJBOM: [1]Adjust!$L$197
Name DiscMinusOneINTNDIV12: [1]Adjust!$L$195
Name DiscPlusOneINTADJBOM: [1]Adjust!$K$197
Name DiscPlusOneINTNDIV12: [1]Adjust!$K$195
Name EmployerRates: #REF!
Name EmployerRates1: #REF!
Name EmployerRatesLEO: #REF!
Name EmployerRatesLEO1: #REF!
Name ERData: [1]ER_DATA!$B$16:$EN$318
Name ERID: [1]ER_NPLExpense!$L$8
Name ERInfo: [1]ER_Input!$B$16:$Y$318
Name Exp1INTADJBOM: [1]Adjust!$G$197
Name Exp1INTNDIV12: [1]Adjust!$G$195
Name FracYearProj: [1]TPL!$C$43
Name FundOfficeContactGASB: [1]DeveloperInfo!$D$10
Name FYrsGASB: [1]DeveloperInfo!$D$54
Name GainLoss: [1]ER_Allocation!$P$12
Name GASBDiscMinusOneINTADJBOM: [1]Adjust!$L$197
Name GASBDiscMinusOneINTNDIV12: [1]Adjust!$L$195
Name InflRate: [1]DeveloperInfo!$D$38
Name InflRate1: [1]DeveloperInfo!$E$38
Name IntDisc: [1]DeveloperInfo!$F$47
Name IntDisc1: [1]DeveloperInfo!$D$47
Name IntDisc1S: [1]DeveloperInfo!$E$47
Name INTDiscMinusOne: [1]DeveloperInfo!$H$47
Name INTDiscPlusOne: [1]DeveloperInfo!$G$47
Name IntExp1: [1]DeveloperInfo!$I$47

Sheet LS-Fund 0042 Journal Entries
A1: Lessee-Type Contracts Fund-by-Fund Journal Entries Form (to be submitted to the SCO annually—one form per fund)
A2: Manually complete every yellow field in this worksheet—there are no automatically calculated data-entry cells in this worksheet.
A3: Fiscal Year: | F3: 2022–2023
A4: Organization Name: | F4: Department of Transportation
A5: Organization Code (4-Digits): | F5: 2660
A6: Fund Number (4-Digits): | F6: 42
A7: Fund Classification: | F7: Governmental
A8: Fund Type: | F8: Governmental Fund
A9: Functional Expense: | F9: =IFERROR(IF(F7="Proprietary","Proprietary Fund",VLOOKUP(F5,[3]qryIndex02a!$A$2:$K$654,4,FALSE)),"Unidentified") -> TRANSPORTATION
A12: Establish Beginning Balances (existing leases only)
A13: Entry #
A14: 0 | B14: Roll forward prior year right-to-use leases to record opening balances. | M14: Combined Lessee Templates | P14: From SCO BB List | S14: Difference
A15: *Rpt 18 | B15: Dr: Acct 0476 - RIGHT-TO-USE LEASED LAND - AMORTIZABLE | J15: =M15 -> 0 | P15: 0 | S15: =P15-M15 -> 0
A16: *Rpt 18 | B16: Dr: Acct 0478 - RIGHT-TO-USE LEASED EQUIPMENT - AMORTIZABLE | J16: =M16 -> 0 | P16: 0 | S16: =P16-M16 -> 0
A17: *Rpt 18 | B17: Dr: Acct 0477 - RIGHT-TO-USE LEASED BUILDINGS - AMORTIZABLE | J17: =M17 -> 88282279 | M17: 88282279 | P17: 88282279 | S17: =P17-M17 -> 0
B18: Dr: Acct 0950 - BEGINNING FUND BALANCE | J18: =P18 -> 295241 | M18: 361780 | P18: =IF(SUM($Q$21:$Q$23)>SUM($P$15:$P$17),SUM($Q$21:$Q$23)-SUM($P$15:$P$17),0) -> 295241 | S18: =P18-M18 -> -66539
B19: Dr: Acct 0952 - BEGINNING FUND ADJUSTMENT/PRIOR PERIOD ADJUSTMENT | J19: =IF(SUM($K$21:$K$24)>SUM($J$15:$J$18),SUM($K$21:$K$24)-SUM($J$15:$J$18),0) -> 0 | S19: =P19-M19 -> 0
C20: Cr: Acct 0485 - ACCUMULATED AMORTIZATION - RIGHT-TO-USE LEASED LAND | K20: =N20 -> 0 | Q20: 0 | S20: =P20-M20 -> 0
C21: Cr: Acct 0479 - ACCUMULATED AMORTIZATION - RIGHT-TO-USE LEASED EQUIPMENT | K21: =N21 -> 0 | Q21: 0 | S21: =Q21-N21 -> 0
C22: Cr: Acct 0486 - ACCUMULATED AMORTIZATION - RIGHT-TO-USE LEASED BUILDINGS | K22: =N22 -> 18684623 | N22: 18684623 | Q22: 18684623 | S22: =Q22-N22 -> 0
A23: **LS LL/CF | C23: Cr: Acct 0691 - RIGHT-TO-USE LEASE LIABILITY | K23: =N23 -> 69892896 | N23: 69892896 | Q23: 69892897 | S23: =Q23-N23 -> 1
C24: Cr: Acct 0950 - BEGINNING FUND BALANCE | K24: =Q24 -> 0 | N24: 66540 | Q24: =IF(SUM($Q$39:$Q$41)<SUM($P$33:$P$35),-SUM($Q$39:$Q$41)+SUM($P$33:$P$35),0) -> 0 | S24: =Q24-N24 -> -66540
C25: Cr: Acct 0952 - BEGINNING FUND ADJUSTMENT/PRIOR PERIOD ADJUSTMENT | K25: =IF(SUM($K$21:$K$24)<SUM($J$15:$J$18),-SUM($K$21:$K$24)+SUM($J$15:$J$18),0) -> 1 | S25: =Q25-N25 -> 0
J26: =SUM(J15:J25) -> 88577520 | K26: =SUM(K15:K25) -> 88577520 | L26: =IF(J26=K26,"<- Debits and Credits equal each other.","<- Debits and Credits do not equal each other.") -> <- Debits and Credits equal each other.
B27: * THESE ASSET AMOUNTS SHOULD BE REPORTED AS BEGINNING BALANCES ON REPORT 18.
B28: ** This amount should be included in the beginning balance column on the LS-Lease Liability and LS-Check Figures Tabs.
A31: Record New Leases (new leases only)
A32: 1 | B32: Record lease contract commencement (fund-based entries only)
B33: Dr: Acct 0842 - CAPITAL OUTLAY | J33: 4233406
C34: Cr: Acct 0789 - LEASE AND OTHER FINANCING PROCEEDS | K34: =J33 -> 4233406
C35: =IF($F$7="Proprietary","Cr: Acct 0870 - SERVICES & CHARGES (MG ADJ)",VLOOKUP($F$9,'[3]Drop Down Menus'!$F$2:$G$10,2,FALSE)) -> Cr: Acct 0830 - TRANSPORTATION (GAAP ADJ)
J36: =SUM(J33:J35) -> 4233406 | K36: =SUM(K33:K35) -> 4233406 | L36: =IF(J36=K36,"<- Debits and Credits equal each other.","<- Debits and Credits do not equal each other.") -> <- Debits and Credits equal each other.
A38: 2 | B38: Record leased assets.
A39: *Rpt 18 | B39: Dr: Acct 0476 - RIGHT-TO-USE LEASED LAND - AMORTIZABLE
A40: *Rpt 18 | B40: Dr: Acct 0478 - RIGHT-TO-USE LEASED EQUIPMENT - AMORTIZABLE
A41: *Rpt 18 | B41: Dr: Acct 0477 - RIGHT-TO-USE LEASED BUILDINGS - AMORTIZABLE | J41: =K34 -> 4233406
C42: Cr: Acct 0842 - CAPITAL OUTLAY | K42: =J41 -> 4233406
B43: * THESE AMOUNTS SHOULD BE INCLUDED AS "ADDITIONS" ON REPORT 18. | J43: =SUM(J39:J42) -> 4233406 | K43: =SUM(K39:K42) -> 4233406 | L43: =IF(J43=K43,"<- Debits and Credits equal each other.","<- Debits and Credits do not equal each other.") -> <- Debits and Credits equal each other.
A46: 3 | B46: Replace proceeds from leases with right-to-use lease liability.
B47: Dr: Acct 0789 - LEASE AND OTHER FINANCING PROCEEDS | J47: =K34 -> 4233406
A48: **LS LL/CF | C48: Cr: Acct 0691 - RIGHT-TO-USE LEASE LIABILITY | K48: =J47 -> 4233406
J49: =SUM(J47:J48) -> 4233406 | K49: =SUM(K47:K48) -> 4233406 | L49: =IF(J49=K49,"<- Debits and Credits equal each other.","<- Debits and Credits do not equal each other.") -> <- Debits and Credits equal each other.
B50: ** This amount should be included in the additions column on the LS-Lease Liability and LS-Check Figures Tabs.
A53: Record Annual Activity (all leases)
A54: 4 | B54: Record amortization of the leased assets for the year.
B55: Dr: Acct 0875 - DEPRECIATION/AMORTIZATION | J55: 19679605
C56: Cr: Acct 0485 - ACCUMULATED AMORTIZATION - RIGHT-TO-USE LEASED LAND
C57: Cr: Acct 0479 - ACCUMULATED AMORTIZATION - RIGHT-TO-USE LEASED EQUIPMENT
C58: Cr: Acct 0486 - ACCUMULATED AMORTIZATION - RIGHT-TO-USE LEASED BUILDINGS | K58: =J55 -> 19679605
J59: =SUM(J55:J58) -> 19679605 | K59: =SUM(K55:K58) -> 19679605 | L59: =IF(J59=K59,"<- Debits and Credits equal each other.","<- Debits and Credits do not equal each other.") -> <- Debits and Credits equal each other.
A61: 5 | B61: Reclassify rents and leases exp. to lease contract principal and interest exp.
B62: Dr: Acct 0848 - DEBT SERVICE - PRINCIPAL LEASES | J62: 19625300
B63: =IF(F7="Governmental","Dr: Acct 0851 - DEBT SERVICE - INTEREST LEASES","Dr: Acct 0894 - INTEREST EXPENSE AND FISCAL CHARGES") -> Dr: Acct 0851 - DEBT SERVICE - INTEREST LEASES | J63: 229547
C64: =IF($F$7="Proprietary","Cr: Acct 0870 - SERVICES & CHARGES (MG ADJ)",VLOOKUP($F$9,'[3]Drop Down Menus'!$F$2:$G$10,2,FALSE)) -> Cr: Acct 0830 - TRANSPORTATION (GAAP ADJ) | K64: =J62+J63 -> 19854847
J65: =SUM(J62:J64) -> 19854847 | K65: =SUM(K62:K64) -> 19854847 | L65: =IF(J65=K65,"<- Debits and Credits equal each other.","<- Debits and Credits do not equal each other.") -> <- Debits and Credits equal each other.
A67: 6 | B67: Reduce lease contracts liability for total current year principal payments.
A68: **LS LL/CF | B68: Dr: Acct 0691 - RIGHT-TO-USE LEASE LIABILITY | J68: =J62 -> 19625300
C69: Cr: Acct 0848 - DEBT SERVICE - PRINCIPAL LEASES | K69: =J68 -> 19625300
J70: =SUM(J68:J69) -> 19625300 | K70: =SUM(K68:K69) -> 19625300 | L70: =IF(J70=K70,"<- Debits and Credits equal each other.","<- Debits and Credits do not equal each other.") -> <- Debits and Credits equal each other.
B71: ** This amount should be included in the deductions column on the LS-Lease Liability and LS-Check Figures Tabs.
A74: 7 | B74: Reclassify the principal amount due in the next FY to the current liability.
A75: **LS LL/CF | B75: Dr: Acct 0691 - RIGHT-TO-USE LEASE LIABILITY | J75: 18982995
C76: Cr: Acct 0649 - RIGHT-TO-USE LEASE LIABILITY (CURRENT PORTION LT) | K76: =J75 -> 18982995
B77: NOTE: This is an annual accrual. It is to be reversed at the start of the next fiscal year. SCO combines the current and non current amount in Entry #0 to reestablish the beginning balances. No action required. | J77: =SUM(J75:J76) -> 18982995 | K77: =SUM(K75:K76) -> 18982995 | L77: =IF(J77=K77,"<- Debits and Credits equal each other.","<- Debits and Credits do not equal each other.") -> <- Debits and Credits equal each other.
B80: ** This amount should be included in the due in one year column on the LS-Lease Liability and LS-Check Figures Tabs.
A83: Remove Lease Asset at the End of the Lease Term (only at the end of the lease term)
A84: 8 | B84: Record entry to write off the lease asset and accumulated amortization at the end of the lease term.
B85: Dr: Acct 0485 - ACCUMULATED AMORTIZATION - RIGHT-TO-USE LEASED LAND
B86: Dr: Acct 0479 - ACCUMULATED AMORTIZATION - RIGHT-TO-USE LEASED EQUIPMENT
B87: Dr: Acct 0486 - ACCUMULATED AMORTIZATION - RIGHT-TO-USE LEASED BUILDINGS | J87: 999180
A88: *Rpt 18 | C88: Cr: Acct 0476 - RIGHT-TO-USE LEASED LAND - AMORTIZABLE
A89: *Rpt 18 | C89: Cr: Acct 0478 - RIGHT-TO-USE LEASED EQUIPMENT - AMORTIZABLE
A90: *Rpt 18 | C90: Cr: Acct 0477 - RIGHT-TO-USE LEASED BUILDINGS - AMORTIZABLE | K90: 999180
B91: * THESE AMOUNTS SHOULD BE INCLUDED AS "DEDUCTIONS" ON REPORT 18. | J91: =SUM(J85:J90) -> 999180 | K91: =SUM(K85:K90) -> 999180 | L91: =IF(J91=K91,"<- Debits and Credits equal each other.","<- Debits and Credits do not equal each other.") -> <- Debits and Credits equal each other.
A94: Lease Remeasurement and Modifications (only if a significant modification occurred during the fiscal year)
A95: 9 | B95: Record early termination or lease modifications to decrease in the RTU leased asset.
A96: **LS LL/CF | B96: Dr: Acct 0691 - RIGHT-TO-USE LEASE LIABILITY
B97: Dr: Acct 0485 - ACCUMULATED AMORTIZATION - RIGHT-TO-USE LEASED LAND
B98: Dr: Acct 0479 - ACCUMULATED AMORTIZATION - RIGHT-TO-USE LEASED EQUIPMENT
B99: Dr: Acct 0486 - ACCUMULATED AMORTIZATION - RIGHT-TO-USE LEASED BUILDINGS
B100: =IF($F$7="Proprietary","Dr: Acct 0870 - SERVICES & CHARGES (MG ADJ)",VLOOKUP($F$9,'[3]Drop Down Menus'!$F$2:$H$10,3,FALSE)) -> Dr: Acct 0830 - TRANSPORTATION (GAAP ADJ)
A101: *Rpt 18 | C101: Cr: Acct 0476 - RIGHT-TO-USE LEASED LAND - AMORTIZABLE
A102: *Rpt 18 | C102: Cr: Acct 0478 - RIGHT-TO-USE LEASED EQUIPMENT - AMORTIZABLE
A103: *Rpt 18 | C103: Cr: Acct 0477 - RIGHT-TO-USE LEASED BUILDINGS - AMORTIZABLE
C104: =IF($F$7="Proprietary","Dr: Acct 0870 - SERVICES & CHARGES (MG ADJ)",VLOOKUP($F$9,'[3]Drop Down Menus'!$F$2:$G$10,2,FALSE)) -> Cr: Acct 0830 - TRANSPORTATION (GAAP ADJ)
B105: * THESE AMOUNTS SHOULD BE INCLUDED AS "DEDUCTIONS" ON REPORT 18. | J105: =SUM(J96:J104) -> 0 | K105: =SUM(K96:K104) -> 0 | L105: =IF(J105=K105,"<- Debits and Credits equal each other.","<- Debits and Credits do not equal each other.") -> <- Debits and Credits equal each other.
B106: ** This amount should be included in the deductions column on the LS-Lease Liability and LS-Check Figures Tabs.
A109: 10 | B109: Record lease modifications to increase in the RTU leased asset.
A110: *Rpt 18 | B110: Dr: Acct 0476 - RIGHT-TO-USE LEASED LAND - AMORTIZABLE
A111: *Rpt 18 | B111: Dr: Acct 0478 - RIGHT-TO-USE LEASED EQUIPMENT - AMORTIZABLE
A112: *Rpt 18 | B112: Dr: Acct 0477 - RIGHT-TO-USE LEASED BUILDINGS - AMORTIZABLE
A113: **LS LL/CF | C113: Cr: Acct 0691 - RIGHT-TO-USE LEASE LIABILITY
B114: * THESE AMOUNTS SHOULD BE INCLUDED AS "ADDITIONS" ON REPORT 18. | J114: =SUM(J110:J113) -> 0 | K114: =SUM(K110:K113) -> 0 | L114: =IF(J114=K114,"<- Debits and Credits equal each other.","<- Debits and Credits do not equal each other.") -> <- Debits and Credits equal each other.
B115: ** This amount should be included in the additions column on the LS-Lease Liability and LS-Check Figures Tabs.
D120: Informational - Ending Balances of Assets and Liabilities
K121: Debit (Credit)
D122: Acct 0476 - RIGHT-TO-USE LEASED LAND - AMORTIZABLE | K122: =J15+J39-K88-K101+J110 -> 0
D123: Acct 0478 - RIGHT-TO-USE LEASED EQUIPMENT - AMORTIZABLE | K123: =J16+J40-K89-K102+J111 -> 0
D124: Acct 0477 - RIGHT-TO-USE LEASED BUILDINGS - AMORTIZABLE | K124: =J17+J41-K90-K103+J112 -> 91516505
D125: Acct 0485 - ACCUMULATED AMORTIZATION - RIGHT-TO-USE LEASED LAND | K125: =-K20-K56+J85+J97 -> 0
...

Sheet LS-Fund 0046 Journal Entrie
A1: Lessee-Type Contracts Fund-by-Fund Journal Entries Form (to be submitted to the SCO annually—one form per fund)
A2: Manually complete every yellow field in this worksheet—there are no automatically calculated data-entry cells in this worksheet.
A3: Fiscal Year: | F3: 2022–2023
A4: Organization Name: | F4: Department of Transportation
A5: Organization Code (4-Digits): | F5: 2660
A6: Fund Number (4-Digits): | F6: 46
A7: Fund Classification: | F7: Governmental
A8: Fund Type: | F8: Governmental Fund
A9: Functional Expense: | F9: =IFERROR(IF(F7="Proprietary","Proprietary Fund",VLOOKUP(F5,[3]qryIndex02a!$A$2:$K$654,4,FALSE)),"Unidentified") -> TRANSPORTATION
A12: Establish Beginning Balances (existing leases only)
A13: Entry #
A14: 0 | B14: Roll forward prior year right-to-use leases to record opening balances. | M14: Combined Lessee Templates | P14: From SCO BB List | S14: Difference
A15: *Rpt 18 | B15: Dr: Acct 0476 - RIGHT-TO-USE LEASED LAND - AMORTIZABLE | J15: =M15 -> 0 | P15: 0 | S15: =P15-M15 -> 0
A16: *Rpt 18 | B16: Dr: Acct 0478 - RIGHT-TO-USE LEASED EQUIPMENT - AMORTIZABLE | J16: =M16 -> 0 | M16: 0 | P16: 0 | S16: =P16-M16 -> 0
A17: *Rpt 18 | B17: Dr: Acct 0477 - RIGHT-TO-USE LEASED BUILDINGS - AMORTIZABLE | J17: =M17 -> 0 | P17: 0 | S17: =P17-M17 -> 0
B18: Dr: Acct 0950 - BEGINNING FUND BALANCE | J18: =P18 -> 0 | M18: 0 | P18: =IF(SUM($Q$21:$Q$23)>SUM($P$15:$P$17),SUM($Q$21:$Q$23)-SUM($P$15:$P$17),0) -> 0 | S18: =P18-M18 -> 0
B19: Dr: Acct 0952 - BEGINNING FUND ADJUSTMENT/PRIOR PERIOD ADJUSTMENT | J19: =IF(SUM($K$21:$K$24)>SUM($J$15:$J$18),SUM($K$21:$K$24)-SUM($J$15:$J$18),0) -> 0 | M19: 0 | S19: =P19-M19 -> 0
C20: Cr: Acct 0485 - ACCUMULATED AMORTIZATION - RIGHT-TO-USE LEASED LAND | K20: =N20 -> 0 | Q20: 0 | S20: =P20-M20 -> 0
C21: Cr: Acct 0479 - ACCUMULATED AMORTIZATION - RIGHT-TO-USE LEASED EQUIPMENT | K21: =N21 -> 0 | N21: 0 | Q21: 0 | S21: =Q21-N21 -> 0
C22: Cr: Acct 0486 - ACCUMULATED AMORTIZATION - RIGHT-TO-USE LEASED BUILDINGS | K22: =N22 -> 0 | Q22: 0 | S22: =Q22-N22 -> 0
A23: **LS LL/CF | C23: Cr: Acct 0691 - RIGHT-TO-USE LEASE LIABILITY | K23: =N23 -> 0 | N23: 0 | Q23: 0 | S23: =Q23-N23 -> 0
C24: Cr: Acct 0950 - BEGINNING FUND BALANCE | K24: =Q24 -> 0 | N24: 0 | Q24: =IF(SUM($Q$39:$Q$41)<SUM($P$33:$P$35),-SUM($Q$39:$Q$41)+SUM($P$33:$P$35),0) -> 0 | S24: =Q24-N24 -> 0
C25: Cr: Acct 0952 - BEGINNING FUND ADJUSTMENT/PRIOR PERIOD ADJUSTMENT | K25: =IF(SUM($K$21:$K$24)<SUM($J$15:$J$18),-SUM($K$21:$K$24)+SUM($J$15:$J$18),0) -> 0 | N25: 0 | S25: =Q25-N25 -> 0
J26: =SUM(J15:J25) -> 0 | K26: =SUM(K15:K25) -> 0 | L26: =IF(J26=K26,"<- Debits and Credits equal each other.","<- Debits and Credits do not equal each other.") -> <- Debits and Credits equal each other.
B27: * THESE ASSET AMOUNTS SHOULD BE REPORTED AS BEGINNING BALANCES ON REPORT 18.
B28: ** This amount should be included in the beginning balance column on the LS-Lease Liability and LS-Check Figures Tabs.
A31: Record New Leases (new leases only)
A32: 1 | B32: Record lease contract commencement (fund-based entries only)
B33: Dr: Acct 0842 - CAPITAL OUTLAY | J33: 17089708
C34: Cr: Acct 0789 - LEASE AND OTHER FINANCING PROCEEDS | K34: =J33 -> 17089708
C35: =IF($F$7="Proprietary","Cr: Acct 0870 - SERVICES & CHARGES (MG ADJ)",VLOOKUP($F$9,'[3]Drop Down Menus'!$F$2:$G$10,2,FALSE)) -> Cr: Acct 0830 - TRANSPORTATION (GAAP ADJ)
J36: =SUM(J33:J35) -> 17089708 | K36: =SUM(K33:K35) -> 17089708 | L36: =IF(J36=K36,"<- Debits and Credits equal each other.","<- Debits and Credits do not equal each other.") -> <- Debits and Credits equal each other.
A38: 2 | B38: Record leased assets.
A39: *Rpt 18 | B39: Dr: Acct 0476 - RIGHT-TO-USE LEASED LAND - AMORTIZABLE
A40: *Rpt 18 | B40: Dr: Acct 0478 - RIGHT-TO-USE LEASED EQUIPMENT - AMORTIZABLE | J40: =K42 -> 17089708
A41: *Rpt 18 | B41: Dr: Acct 0477 - RIGHT-TO-USE LEASED BUILDINGS - AMORTIZABLE
C42: Cr: Acct 0842 - CAPITAL OUTLAY | K42: =J33 -> 17089708
B43: * THESE AMOUNTS SHOULD BE INCLUDED AS "ADDITIONS" ON REPORT 18. | J43: =SUM(J39:J42) -> 17089708 | K43: =SUM(K39:K42) -> 17089708 | L43: =IF(J43=K43,"<- Debits and Credits equal each other.","<- Debits and Credits do not equal each other.") -> <- Debits and Credits equal each other.
A46: 3 | B46: Replace proceeds from leases with right-to-use lease liability.
B47: Dr: Acct 0789 - LEASE AND OTHER FINANCING PROCEEDS | J47: =K34 -> 17089708
A48: **LS LL/CF | C48: Cr: Acct 0691 - RIGHT-TO-USE LEASE LIABILITY | K48: =J47 -> 17089708
J49: =SUM(J47:J48) -> 17089708 | K49: =SUM(K47:K48) -> 17089708 | L49: =IF(J49=K49,"<- Debits and Credits equal each other.","<- Debits and Credits do not equal each other.") -> <- Debits and Credits equal each other.
B50: ** This amount should be included in the additions column on the LS-Lease Liability and LS-Check Figures Tabs.
A53: Record Annual Activity (all leases)
A54: 4 | B54: Record amortization of the leased assets for the year.
B55: Dr: Acct 0875 - DEPRECIATION/AMORTIZATION | J55: 2010554
C56: Cr: Acct 0485 - ACCUMULATED AMORTIZATION - RIGHT-TO-USE LEASED LAND
C57: Cr: Acct 0479 - ACCUMULATED AMORTIZATION - RIGHT-TO-USE LEASED EQUIPMENT | K57: =J55 -> 2010554
C58: Cr: Acct 0486 - ACCUMULATED AMORTIZATION - RIGHT-TO-USE LEASED BUILDINGS
J59: =SUM(J55:J58) -> 2010554 | K59: =SUM(K55:K58) -> 2010554 | L59: =IF(J59=K59,"<- Debits and Credits equal each other.","<- Debits and Credits do not equal each other.") -> <- Debits and Credits equal each other.
A61: 5 | B61: Reclassify rents and leases exp. to lease contract principal and interest exp.
B62: Dr: Acct 0848 - DEBT SERVICE - PRINCIPAL LEASES | J62: 2010555
B63: =IF(F7="Governmental","Dr: Acct 0851 - DEBT SERVICE - INTEREST LEASES","Dr: Acct 0894 - INTEREST EXPENSE AND FISCAL CHARGES") -> Dr: Acct 0851 - DEBT SERVICE - INTEREST LEASES | J63: 3217
C64: =IF($F$7="Proprietary","Cr: Acct 0870 - SERVICES & CHARGES (MG ADJ)",VLOOKUP($F$9,'[3]Drop Down Menus'!$F$2:$G$10,2,FALSE)) -> Cr: Acct 0830 - TRANSPORTATION (GAAP ADJ) | K64: =J62+J63 -> 2013772
J65: =SUM(J62:J64) -> 2013772 | K65: =SUM(K62:K64) -> 2013772 | L65: =IF(J65=K65,"<- Debits and Credits equal each other.","<- Debits and Credits do not equal each other.") -> <- Debits and Credits equal each other.
A67: 6 | B67: Reduce lease contracts liability for total current year principal payments.
A68: **LS LL/CF | B68: Dr: Acct 0691 - RIGHT-TO-USE LEASE LIABILITY | J68: =J62 -> 2010555
C69: Cr: Acct 0848 - DEBT SERVICE - PRINCIPAL LEASES | K69: =J68 -> 2010555
J70: =SUM(J68:J69) -> 2010555 | K70: =SUM(K68:K69) -> 2010555 | L70: =IF(J70=K70,"<- Debits and Credits equal each other.","<- Debits and Credits do not equal each other.") -> <- Debits and Credits equal each other.
B71: ** This amount should be included in the deductions column on the LS-Lease Liability and LS-Check Figures Tabs.
A74: 7 | B74: Reclassify the principal amount due in the next FY to the current liability.
A75: **LS LL/CF | B75: Dr: Acct 0691 - RIGHT-TO-USE LEASE LIABILITY | J75: 12059702
C76: Cr: Acct 0649 - RIGHT-TO-USE LEASE LIABILITY (CURRENT PORTION LT) | K76: =J75 -> 12059702
B77: NOTE: This is an annual accrual. It is to be reversed at the start of the next fiscal year. SCO combines the current and non current amount in Entry #0 to reestablish the beginning balances. No action required. | J77: =SUM(J75:J76) -> 12059702 | K77: =SUM(K75:K76) -> 12059702 | L77: =IF(J77=K77,"<- Debits and Credits equal each other.","<- Debits and Credits do not equal each other.") -> <- Debits and Credits equal each other.
B80: ** This amount should be included in the due in one year column on the LS-Lease Liability and LS-Check Figures Tabs.
A83: Remove Lease Asset at the End of the Lease Term (only at the end of the lease term)
A84: 8 | B84: Record entry to write off the lease asset and accumulated amortization at the end of the lease term.
B85: Dr: Acct 0485 - ACCUMULATED AMORTIZATION - RIGHT-TO-USE LEASED LAND
B86: Dr: Acct 0479 - ACCUMULATED AMORTIZATION - RIGHT-TO-USE LEASED EQUIPMENT | J86: 0
B87: Dr: Acct 0486 - ACCUMULATED AMORTIZATION - RIGHT-TO-USE LEASED BUILDINGS
A88: *Rpt 18 | C88: Cr: Acct 0476 - RIGHT-TO-USE LEASED LAND - AMORTIZABLE
A89: *Rpt 18 | C89: Cr: Acct 0478 - RIGHT-TO-USE LEASED EQUIPMENT - AMORTIZABLE | K89: 0
A90: *Rpt 18 | C90: Cr: Acct 0477 - RIGHT-TO-USE LEASED BUILDINGS - AMORTIZABLE
B91: * THESE AMOUNTS SHOULD BE INCLUDED AS "DEDUCTIONS" ON REPORT 18. | J91: =SUM(J85:J90) -> 0 | K91: =SUM(K85:K90) -> 0 | L91: =IF(J91=K91,"<- Debits and Credits equal each other.","<- Debits and Credits do not equal each other.") -> <- Debits and Credits equal each other.
A94: Lease Remeasurement and Modifications (only if a significant modification occurred during the fiscal year)
A95: 9 | B95: Record early termination or lease modifications to decrease in the RTU leased asset.
A96: **LS LL/CF | B96: Dr: Acct 0691 - RIGHT-TO-USE LEASE LIABILITY
B97: Dr: Acct 0485 - ACCUMULATED AMORTIZATION - RIGHT-TO-USE LEASED LAND
B98: Dr: Acct 0479 - ACCUMULATED AMORTIZATION - RIGHT-TO-USE LEASED EQUIPMENT
B99: Dr: Acct 0486 - ACCUMULATED AMORTIZATION - RIGHT-TO-USE LEASED BUILDINGS
B100: =IF($F$7="Proprietary","Dr: Acct 0870 - SERVICES & CHARGES (MG ADJ)",VLOOKUP($F$9,'[3]Drop Down Menus'!$F$2:$H$10,3,FALSE)) -> Dr: Acct 0830 - TRANSPORTATION (GAAP ADJ)
A101: *Rpt 18 | C101: Cr: Acct 0476 - RIGHT-TO-USE LEASED LAND - AMORTIZABLE
A102: *Rpt 18 | C102: Cr: Acct 0478 - RIGHT-TO-USE LEASED EQUIPMENT - AMORTIZABLE
A103: *Rpt 18 | C103: Cr: Acct 0477 - RIGHT-TO-USE LEASED BUILDINGS - AMORTIZABLE
C104: =IF($F$7="Proprietary","Dr: Acct 0870 - SERVICES & CHARGES (MG ADJ)",VLOOKUP($F$9,'[3]Drop Down Menus'!$F$2:$G$10,2,FALSE)) -> Cr: Acct 0830 - TRANSPORTATION (GAAP ADJ)
B105: * THESE AMOUNTS SHOULD BE INCLUDED AS "DEDUCTIONS" ON REPORT 18. | J105: =SUM(J96:J104) -> 0 | K105: =SUM(K96:K104) -> 0 | L105: =IF(J105=K105,"<- Debits and Credits equal each other.","<- Debits and Credits do not equal each other.") -> <- Debits and Credits equal each other.
B106: ** This amount should be included in the deductions column on the LS-Lease Liability and LS-Check Figures Tabs.
A109: 10 | B109: Record lease modifications to increase in the RTU leased asset.
A110: *Rpt 18 | B110: Dr: Acct 0476 - RIGHT-TO-USE LEASED LAND - AMORTIZABLE
A111: *Rpt 18 | B111: Dr: Acct 0478 - RIGHT-TO-USE LEASED EQUIPMENT - AMORTIZABLE
A112: *Rpt 18 | B112: Dr: Acct 0477 - RIGHT-TO-USE LEASED BUILDINGS - AMORTIZABLE
A113: **LS LL/CF | C113: Cr: Acct 0691 - RIGHT-TO-USE LEASE LIABILITY
B114: * THESE AMOUNTS SHOULD BE INCLUDED AS "ADDITIONS" ON REPORT 18. | J114: =SUM(J110:J113) -> 0 | K114: =SUM(K110:K113) -> 0 | L114: =IF(J114=K114,"<- Debits and Credits equal each other.","<- Debits and Credits do not equal each other.") -> <- Debits and Credits equal each other.
B115: ** This amount should be included in the additions column on the LS-Lease Liability and LS-Check Figures Tabs.
D120: Informational - Ending Balances of Assets and Liabilities
K121: Debit (Credit)
D122: Acct 0476 - RIGHT-TO-USE LEASED LAND - AMORTIZABLE | K122: =J15+J39-K88-K101+J110 -> 0
D123: Acct 0478 - RIGHT-TO-USE LEASED EQUIPMENT - AMORTIZABLE | K123: =J16+J40-K89-K102+J111 -> 17089708
D124: Acct 0477 - RIGHT-TO-USE LEASED BUILDINGS - AMORTIZABLE | K124: =J17+J41-K90-K103+J112 -> 0
D125: Acct 0485 - ACCUMULATED AMORTIZATION - RIGHT-TO-USE LEASED LAND | K125: =-K20-K56+J85+J97 -> 0
...

Sheet LS-Fund 3290 Journal Entrie
A1: Lessee-Type Contracts Fund-by-Fund Journal Entries Form (to be submitted to the SCO annually—one form per fund)
A2: Manually complete every yellow field in this worksheet—there are no automatically calculated data-entry cells in this worksheet.
A3: Fiscal Year: | F3: 2022–2023
A4: Organization Name: | F4: Department of Transportation
A5: Organization Code (4-Digits): | F5: 2660
A6: Fund Number (4-Digits): | F6: 3290
A7: Fund Classification: | F7: Governmental
A8: Fund Type: | F8: Governmental Fund
A9: Functional Expense: | F9: =IFERROR(IF(F7="Proprietary","Proprietary Fund",VLOOKUP(F5,[3]qryIndex02a!$A$2:$K$654,4,FALSE)),"Unidentified") -> TRANSPORTATION
A12: Establish Beginning Balances (existing leases only)
A13: Entry #
A14: 0 | B14: Roll forward prior year right-to-use leases to record opening balances. | M14: Combined Lessee Templates | P14: From SCO BB List | S14: Difference
A15: *Rpt 18 | B15: Dr: Acct 0476 - RIGHT-TO-USE LEASED LAND - AMORTIZABLE | J15: =M15 -> 0 | S15: =P15-M15 -> 0
A16: *Rpt 18 | B16: Dr: Acct 0478 - RIGHT-TO-USE LEASED EQUIPMENT - AMORTIZABLE | J16: =M16 -> 0 | S16: =P16-M16 -> 0
A17: *Rpt 18 | B17: Dr: Acct 0477 - RIGHT-TO-USE LEASED BUILDINGS - AMORTIZABLE | J17: =M17 -> 4195765 | M17: 4195765 | P17: 3763842 | S17: =P17-M17 -> -431923
B18: Dr: Acct 0950 - BEGINNING FUND BALANCE | J18: =P18 -> 17601 | M18: 17601 | P18: =IF(SUM($Q$21:$Q$23)>SUM($P$15:$P$17),SUM($Q$21:$Q$23)-SUM($P$15:$P$17),0) -> 17601 | S18: =P18-M18 -> 0
B19: Dr: Acct 0952 - BEGINNING FUND ADJUSTMENT/PRIOR PERIOD ADJUSTMENT | J19: =IF(SUM($K$21:$K$24)>SUM($J$15:$J$18),SUM($K$21:$K$24)-SUM($J$15:$J$18),0) -> 296 | M19: 295 | S19: =P19-M19 -> -295
C20: Cr: Acct 0485 - ACCUMULATED AMORTIZATION - RIGHT-TO-USE LEASED LAND | K20: =N20 -> 0 | S20: =P20-M20 -> 0
C21: Cr: Acct 0479 - ACCUMULATED AMORTIZATION - RIGHT-TO-USE LEASED EQUIPMENT | K21: =N21 -> 0 | S21: =Q21-N21 -> 0
C22: Cr: Acct 0486 - ACCUMULATED AMORTIZATION - RIGHT-TO-USE LEASED BUILDINGS | K22: =N22 -> 1187192 | N22: 1187192 | Q22: 1050795 | S22: =Q22-N22 -> -136397
A23: **LS LL/CF | C23: Cr: Acct 0691 - RIGHT-TO-USE LEASE LIABILITY | K23: =N23 -> 3026470 | N23: 3026470 | Q23: 2730648 | S23: =Q23-N23 -> -295822
C24: Cr: Acct 0950 - BEGINNING FUND BALANCE | K24: =Q24 -> 0 | Q24: =IF(SUM($Q$39:$Q$41)<SUM($P$33:$P$35),-SUM($Q$39:$Q$41)+SUM($P$33:$P$35),0) -> 0 | S24: =Q24-N24 -> 0
C25: Cr: Acct 0952 - BEGINNING FUND ADJUSTMENT/PRIOR PERIOD ADJUSTMENT | K25: =IF(SUM($K$21:$K$24)<SUM($J$15:$J$18),-SUM($K$21:$K$24)+SUM($J$15:$J$18),0) -> 0 | S25: =Q25-N25 -> 0
J26: =SUM(J15:J25) -> 4213662 | K26: =SUM(K15:K25) -> 4213662 | L26: =IF(J26=K26,"<- Debits and Credits equal each other.","<- Debits and Credits do not equal each other.") -> <- Debits and Credits equal each other.
B27: * THESE ASSET AMOUNTS SHOULD BE REPORTED AS BEGINNING BALANCES ON REPORT 18.
B28: ** This amount should be included in the beginning balance column on the LS-Lease Liability and LS-Check Figures Tabs.
A31: Record New Leases (new leases only)
A32: 1 | B32: Record lease contract commencement (fund-based entries only)
B33: Dr: Acct 0842 - CAPITAL OUTLAY | J33: 5740523
C34: Cr: Acct 0789 - LEASE AND OTHER FINANCING PROCEEDS | K34: =J33 -> 5740523
C35: =IF($F$7="Proprietary","Cr: Acct 0870 - SERVICES & CHARGES (MG ADJ)",VLOOKUP($F$9,'[3]Drop Down Menus'!$F$2:$G$10,2,FALSE)) -> Cr: Acct 0830 - TRANSPORTATION (GAAP ADJ)
J36: =SUM(J33:J35) -> 5740523 | K36: =SUM(K33:K35) -> 5740523 | L36: =IF(J36=K36,"<- Debits and Credits equal each other.","<- Debits and Credits do not equal each other.") -> <- Debits and Credits equal each other.
A38: 2 | B38: Record leased assets.
A39: *Rpt 18 | B39: Dr: Acct 0476 - RIGHT-TO-USE LEASED LAND - AMORTIZABLE
A40: *Rpt 18 | B40: Dr: Acct 0478 - RIGHT-TO-USE LEASED EQUIPMENT - AMORTIZABLE
A41: *Rpt 18 | B41: Dr: Acct 0477 - RIGHT-TO-USE LEASED BUILDINGS - AMORTIZABLE | J41: =K34 -> 5740523
C42: Cr: Acct 0842 - CAPITAL OUTLAY | K42: =J41 -> 5740523
B43: * THESE AMOUNTS SHOULD BE INCLUDED AS "ADDITIONS" ON REPORT 18. | J43: =SUM(J39:J42) -> 5740523 | K43: =SUM(K39:K42) -> 5740523 | L43: =IF(J43=K43,"<- Debits and Credits equal each other.","<- Debits and Credits do not equal each other.") -> <- Debits and Credits equal each other.
A46: 3 | B46: Replace proceeds from leases with right-to-use lease liability.
B47: Dr: Acct 0789 - LEASE AND OTHER FINANCING PROCEEDS | J47: =K34 -> 5740523
A48: **LS LL/CF | C48: Cr: Acct 0691 - RIGHT-TO-USE LEASE LIABILITY | K48: =J47 -> 5740523
J49: =SUM(J47:J48) -> 5740523 | K49: =SUM(K47:K48) -> 5740523 | L49: =IF(J49=K49,"<- Debits and Credits equal each other.","<- Debits and Credits do not equal each other.") -> <- Debits and Credits equal each other.
B50: ** This amount should be included in the additions column on the LS-Lease Liability and LS-Check Figures Tabs.
A53: Record Annual Activity (all leases)
A54: 4 | B54: Record amortization of the leased assets for the year.
B55: Dr: Acct 0875 - DEPRECIATION/AMORTIZATION | J55: 1700646
C56: Cr: Acct 0485 - ACCUMULATED AMORTIZATION - RIGHT-TO-USE LEASED LAND
C57: Cr: Acct 0479 - ACCUMULATED AMORTIZATION - RIGHT-TO-USE LEASED EQUIPMENT
C58: Cr: Acct 0486 - ACCUMULATED AMORTIZATION - RIGHT-TO-USE LEASED BUILDINGS | K58: =J55 -> 1700646
J59: =SUM(J55:J58) -> 1700646 | K59: =SUM(K55:K58) -> 1700646 | L59: =IF(J59=K59,"<- Debits and Credits equal each other.","<- Debits and Credits do not equal each other.") -> <- Debits and Credits equal each other.
A61: 5 | B61: Reclassify rents and leases exp. to lease contract principal and interest exp.
B62: Dr: Acct 0848 - DEBT SERVICE - PRINCIPAL LEASES | J62: 1691777
B63: =IF(F7="Governmental","Dr: Acct 0851 - DEBT SERVICE - INTEREST LEASES","Dr: Acct 0894 - INTEREST EXPENSE AND FISCAL CHARGES") -> Dr: Acct 0851 - DEBT SERVICE - INTEREST LEASES | J63: 9487
C64: =IF($F$7="Proprietary","Cr: Acct 0870 - SERVICES & CHARGES (MG ADJ)",VLOOKUP($F$9,'[3]Drop Down Menus'!$F$2:$G$10,2,FALSE)) -> Cr: Acct 0830 - TRANSPORTATION (GAAP ADJ) | K64: =J62+J63 -> 1701264
J65: =SUM(J62:J64) -> 1701264 | K65: =SUM(K62:K64) -> 1701264 | L65: =IF(J65=K65,"<- Debits and Credits equal each other.","<- Debits and Credits do not equal each other.") -> <- Debits and Credits equal each other.
A67: 6 | B67: Reduce lease contracts liability for total current year principal payments.
A68: **LS LL/CF | B68: Dr: Acct 0691 - RIGHT-TO-USE LEASE LIABILITY | J68: =J62 -> 1691777
C69: Cr: Acct 0848 - DEBT SERVICE - PRINCIPAL LEASES | K69: =J68 -> 1691777
J70: =SUM(J68:J69) -> 1691777 | K70: =SUM(K68:K69) -> 1691777 | L70: =IF(J70=K70,"<- Debits and Credits equal each other.","<- Debits and Credits do not equal each other.") -> <- Debits and Credits equal each other.
B71: ** This amount should be included in the deductions column on the LS-Lease Liability and LS-Check Figures Tabs.
A74: 7 | B74: Reclassify the principal amount due in the next FY to the current liability.
A75: **LS LL/CF | B75: Dr: Acct 0691 - RIGHT-TO-USE LEASE LIABILITY | J75: 2393111
C76: Cr: Acct 0649 - RIGHT-TO-USE LEASE LIABILITY (CURRENT PORTION LT) | K76: =J75 -> 2393111
B77: NOTE: This is an annual accrual. It is to be reversed at the start of the next fiscal year. SCO combines the current and non current amount in Entry #0 to reestablish the beginning balances. No action required. | J77: =SUM(J75:J76) -> 2393111 | K77: =SUM(K75:K76) -> 2393111 | L77: =IF(J77=K77,"<- Debits and Credits equal each other.","<- Debits and Credits do not equal each other.") -> <- Debits and Credits equal each other.
B80: ** This amount should be included in the due in one year column on the LS-Lease Liability and LS-Check Figures Tabs.
A83: Remove Lease Asset at the End of the Lease Term (only at the end of the lease term)
A84: 8 | B84: Record entry to write off the lease asset and accumulated amortization at the end of the lease term.
B85: Dr: Acct 0485 - ACCUMULATED AMORTIZATION - RIGHT-TO-USE LEASED LAND
B86: Dr: Acct 0479 - ACCUMULATED AMORTIZATION - RIGHT-TO-USE LEASED EQUIPMENT
B87: Dr: Acct 0486 - ACCUMULATED AMORTIZATION - RIGHT-TO-USE LEASED BUILDINGS | J87: 281672
A88: *Rpt 18 | C88: Cr: Acct 0476 - RIGHT-TO-USE LEASED LAND - AMORTIZABLE
A89: *Rpt 18 | C89: Cr: Acct 0478 - RIGHT-TO-USE LEASED EQUIPMENT - AMORTIZABLE
A90: *Rpt 18 | C90: Cr: Acct 0477 - RIGHT-TO-USE LEASED BUILDINGS - AMORTIZABLE | K90: =J87 -> 281672
B91: * THESE AMOUNTS SHOULD BE INCLUDED AS "DEDUCTIONS" ON REPORT 18. | J91: =SUM(J85:J90) -> 281672 | K91: =SUM(K85:K90) -> 281672 | L91: =IF(J91=K91,"<- Debits and Credits equal each other.","<- Debits and Credits do not equal each other.") -> <- Debits and Credits equal each other.
A94: Lease Remeasurement and Modifications (only if a significant modification occurred during the fiscal year)
A95: 9 | B95: Record early termination or lease modifications to decrease in the RTU leased asset.
A96: **LS LL/CF | B96: Dr: Acct 0691 - RIGHT-TO-USE LEASE LIABILITY
B97: Dr: Acct 0485 - ACCUMULATED AMORTIZATION - RIGHT-TO-USE LEASED LAND
B98: Dr: Acct 0479 - ACCUMULATED AMORTIZATION - RIGHT-TO-USE LEASED EQUIPMENT
B99: Dr: Acct 0486 - ACCUMULATED AMORTIZATION - RIGHT-TO-USE LEASED BUILDINGS
B100: =IF($F$7="Proprietary","Dr: Acct 0870 - SERVICES & CHARGES (MG ADJ)",VLOOKUP($F$9,'[3]Drop Down Menus'!$F$2:$H$10,3,FALSE)) -> Dr: Acct 0830 - TRANSPORTATION (GAAP ADJ)
A101: *Rpt 18 | C101: Cr: Acct 0476 - RIGHT-TO-USE LEASED LAND - AMORTIZABLE
A102: *Rpt 18 | C102: Cr: Acct 0478 - RIGHT-TO-USE LEASED EQUIPMENT - AMORTIZABLE
A103: *Rpt 18 | C103: Cr: Acct 0477 - RIGHT-TO-USE LEASED BUILDINGS - AMORTIZABLE
C104: =IF($F$7="Proprietary","Dr: Acct 0870 - SERVICES & CHARGES (MG ADJ)",VLOOKUP($F$9,'[3]Drop Down Menus'!$F$2:$G$10,2,FALSE)) -> Cr: Acct 0830 - TRANSPORTATION (GAAP ADJ)
B105: * THESE AMOUNTS SHOULD BE INCLUDED AS "DEDUCTIONS" ON REPORT 18. | J105: =SUM(J96:J104) -> 0 | K105: =SUM(K96:K104) -> 0 | L105: =IF(J105=K105,"<- Debits and Credits equal each other.","<- Debits and Credits do not equal each other.") -> <- Debits and Credits equal each other.
B106: ** This amount should be included in the deductions column on the LS-Lease Liability and LS-Check Figures Tabs.
A109: 10 | B109: Record lease modifications to increase in the RTU leased asset.
A110: *Rpt 18 | B110: Dr: Acct 0476 - RIGHT-TO-USE LEASED LAND - AMORTIZABLE
A111: *Rpt 18 | B111: Dr: Acct 0478 - RIGHT-TO-USE LEASED EQUIPMENT - AMORTIZABLE
A112: *Rpt 18 | B112: Dr: Acct 0477 - RIGHT-TO-USE LEASED BUILDINGS - AMORTIZABLE
A113: **LS LL/CF | C113: Cr: Acct 0691 - RIGHT-TO-USE LEASE LIABILITY
B114: * THESE AMOUNTS SHOULD BE INCLUDED AS "ADDITIONS" ON REPORT 18. | J114: =SUM(J110:J113) -> 0 | K114: =SUM(K110:K113) -> 0 | L114: =IF(J114=K114,"<- Debits and Credits equal each other.","<- Debits and Credits do not equal each other.") -> <- Debits and Credits equal each other.
B115: ** This amount should be included in the additions column on the LS-Lease Liability and LS-Check Figures Tabs.
D120: Informational - Ending Balances of Assets and Liabilities
K121: Debit (Credit)
D122: Acct 0476 - RIGHT-TO-USE LEASED LAND - AMORTIZABLE | K122: =J15+J39-K88-K101+J110 -> 0
D123: Acct 0478 - RIGHT-TO-USE LEASED EQUIPMENT - AMORTIZABLE | K123: =J16+J40-K89-K102+J111 -> 0
D124: Acct 0477 - RIGHT-TO-USE LEASED BUILDINGS - AMORTIZABLE | K124: =J17+J41-K90-K103+J112 -> 9654616
D125: Acct 0485 - ACCUMULATED AMORTIZATION - RIGHT-TO-USE LEASED LAND | K125: =-K20-K56+J85+J97 -> 0
...

Sheet LS-Fund 3291 Journal Entrie
A1: Lessee-Type Contracts Fund-by-Fund Journal Entries Form (to be submitted to the SCO annually—one form per fund)
A2: Manually complete every yellow field in this worksheet—there are no automatically calculated data-entry cells in this worksheet.
A3: Fiscal Year: | F3: 2022–2023
A4: Organization Name: | F4: Department of Transportation
A5: Organization Code (4-Digits): | F5: 2660
A6: Fund Number (4-Digits): | F6: 3291
A7: Fund Classification: | F7: Governmental
A8: Fund Type: | F8: Governmental Fund
A9: Functional Expense: | F9: =IFERROR(IF(F7="Proprietary","Proprietary Fund",VLOOKUP(F5,[3]qryIndex02a!$A$2:$K$654,4,FALSE)),"Unidentified") -> TRANSPORTATION
A12: Establish Beginning Balances (existing leases only)
A13: Entry #
A14: 0 | B14: Roll forward prior year right-to-use leases to record opening balances. | M14: Combined Lessee Templates | P14: From SCO BB List | S14: Difference
A15: *Rpt 18 | B15: Dr: Acct 0476 - RIGHT-TO-USE LEASED LAND - AMORTIZABLE | J15: =M15 -> 0 | S15: =P15-M15 -> 0
A16: *Rpt 18 | B16: Dr: Acct 0478 - RIGHT-TO-USE LEASED EQUIPMENT - AMORTIZABLE | J16: =M16 -> 0 | S16: =P16-M16 -> 0
A17: *Rpt 18 | B17: Dr: Acct 0477 - RIGHT-TO-USE LEASED BUILDINGS - AMORTIZABLE | J17: =M17 -> 83839 | M17: 83839 | P17: 83839 | S17: =P17-M17 -> 0
B18: Dr: Acct 0950 - BEGINNING FUND BALANCE | J18: =P18 -> 151 | M18: 150 | P18: =IF(SUM($Q$21:$Q$23)>SUM($P$15:$P$17),SUM($Q$21:$Q$23)-SUM($P$15:$P$17),0) -> 151 | S18: =P18-M18 -> 1
B19: Dr: Acct 0952 - BEGINNING FUND ADJUSTMENT/PRIOR PERIOD ADJUSTMENT | J19: =IF(SUM($K$21:$K$24)>SUM($J$15:$J$18),SUM($K$21:$K$24)-SUM($J$15:$J$18),0) -> 0 | S19: =P19-M19 -> 0
C20: Cr: Acct 0485 - ACCUMULATED AMORTIZATION - RIGHT-TO-USE LEASED LAND | K20: =N20 -> 0 | S20: =P20-M20 -> 0
C21: Cr: Acct 0479 - ACCUMULATED AMORTIZATION - RIGHT-TO-USE LEASED EQUIPMENT | K21: =N21 -> 0 | S21: =Q21-N21 -> 0
C22: Cr: Acct 0486 - ACCUMULATED AMORTIZATION - RIGHT-TO-USE LEASED BUILDINGS | K22: =N22 -> 4658 | N22: 4658 | Q22: 4658 | S22: =Q22-N22 -> 0
A23: **LS LL/CF | C23: Cr: Acct 0691 - RIGHT-TO-USE LEASE LIABILITY | K23: =N23 -> 79332 | N23: 79332 | Q23: 79332 | S23: =Q23-N23 -> 0
C24: Cr: Acct 0950 - BEGINNING FUND BALANCE | K24: =Q24 -> 0 | Q24: =IF(SUM($Q$39:$Q$41)<SUM($P$33:$P$35),-SUM($Q$39:$Q$41)+SUM($P$33:$P$35),0) -> 0 | S24: =Q24-N24 -> 0
C25: Cr: Acct 0952 - BEGINNING FUND ADJUSTMENT/PRIOR PERIOD ADJUSTMENT | K25: =IF(SUM($K$21:$K$24)<SUM($J$15:$J$18),-SUM($K$21:$K$24)+SUM($J$15:$J$18),0) -> 0 | S25: =Q25-N25 -> 0
J26: =SUM(J15:J25) -> 83990 | K26: =SUM(K15:K25) -> 83990 | L26: =IF(J26=K26,"<- Debits and Credits equal each other.","<- Debits and Credits do not equal each other.") -> <- Debits and Credits equal each other.
B27: * THESE ASSET AMOUNTS SHOULD BE REPORTED AS BEGINNING BALANCES ON REPORT 18.
B28: ** This amount should be included in the beginning balance column on the LS-Lease Liability and LS-Check Figures Tabs.
A31: Record New Leases (new leases only)
A32: 1 | B32: Record lease contract commencement (fund-based entries only)
B33: Dr: Acct 0842 - CAPITAL OUTLAY | J33: 0
C34: Cr: Acct 0789 - LEASE AND OTHER FINANCING PROCEEDS | K34: =J33 -> 0
C35: =IF($F$7="Proprietary","Cr: Acct 0870 - SERVICES & CHARGES (MG ADJ)",VLOOKUP($F$9,'[3]Drop Down Menus'!$F$2:$G$10,2,FALSE)) -> Cr: Acct 0830 - TRANSPORTATION (GAAP ADJ) | K35: 0
J36: =SUM(J33:J35) -> 0 | K36: =SUM(K33:K35) -> 0 | L36: =IF(J36=K36,"<- Debits and Credits equal each other.","<- Debits and Credits do not equal each other.") -> <- Debits and Credits equal each other.
A38: 2 | B38: Record leased assets.
A39: *Rpt 18 | B39: Dr: Acct 0476 - RIGHT-TO-USE LEASED LAND - AMORTIZABLE | J39: 0
A40: *Rpt 18 | B40: Dr: Acct 0478 - RIGHT-TO-USE LEASED EQUIPMENT - AMORTIZABLE | J40: 0
A41: *Rpt 18 | B41: Dr: Acct 0477 - RIGHT-TO-USE LEASED BUILDINGS - AMORTIZABLE | J41: =K34 -> 0
C42: Cr: Acct 0842 - CAPITAL OUTLAY | K42: =J41 -> 0
B43: * THESE AMOUNTS SHOULD BE INCLUDED AS "ADDITIONS" ON REPORT 18. | J43: =SUM(J39:J42) -> 0 | K43: =SUM(K39:K42) -> 0 | L43: =IF(J43=K43,"<- Debits and Credits equal each other.","<- Debits and Credits do not equal each other.") -> <- Debits and Credits equal each other.
A46: 3 | B46: Replace proceeds from leases with right-to-use lease liability.
B47: Dr: Acct 0789 - LEASE AND OTHER FINANCING PROCEEDS | J47: =K34 -> 0
A48: **LS LL/CF | C48: Cr: Acct 0691 - RIGHT-TO-USE LEASE LIABILITY | K48: =J47 -> 0
J49: =SUM(J47:J48) -> 0 | K49: =SUM(K47:K48) -> 0 | L49: =IF(J49=K49,"<- Debits and Credits equal each other.","<- Debits and Credits do not equal each other.") -> <- Debits and Credits equal each other.
B50: ** This amount should be included in the additions column on the LS-Lease Liability and LS-Check Figures Tabs.
A53: Record Annual Activity (all leases)
A54: 4 | B54: Record amortization of the leased assets for the year.
B55: Dr: Acct 0875 - DEPRECIATION/AMORTIZATION | J55: 27946
C56: Cr: Acct 0485 - ACCUMULATED AMORTIZATION - RIGHT-TO-USE LEASED LAND
C57: Cr: Acct 0479 - ACCUMULATED AMORTIZATION - RIGHT-TO-USE LEASED EQUIPMENT
C58: Cr: Acct 0486 - ACCUMULATED AMORTIZATION - RIGHT-TO-USE LEASED BUILDINGS | K58: =J55 -> 27946
J59: =SUM(J55:J58) -> 27946 | K59: =SUM(K55:K58) -> 27946 | L59: =IF(J59=K59,"<- Debits and Credits equal each other.","<- Debits and Credits do not equal each other.") -> <- Debits and Credits equal each other.
A61: 5 | B61: Reclassify rents and leases exp. to lease contract principal and interest exp.
B62: Dr: Acct 0848 - DEBT SERVICE - PRINCIPAL LEASES | J62: 27212
B63: =IF(F7="Governmental","Dr: Acct 0851 - DEBT SERVICE - INTEREST LEASES","Dr: Acct 0894 - INTEREST EXPENSE AND FISCAL CHARGES") -> Dr: Acct 0851 - DEBT SERVICE - INTEREST LEASES | J63: 134
C64: =IF($F$7="Proprietary","Cr: Acct 0870 - SERVICES & CHARGES (MG ADJ)",VLOOKUP($F$9,'[3]Drop Down Menus'!$F$2:$G$10,2,FALSE)) -> Cr: Acct 0830 - TRANSPORTATION (GAAP ADJ) | K64: =J62+J63 -> 27346
J65: =SUM(J62:J64) -> 27346 | K65: =SUM(K62:K64) -> 27346 | L65: =IF(J65=K65,"<- Debits and Credits equal each other.","<- Debits and Credits do not equal each other.") -> <- Debits and Credits equal each other.
A67: 6 | B67: Reduce lease contracts liability for total current year principal payments.
A68: **LS LL/CF | B68: Dr: Acct 0691 - RIGHT-TO-USE LEASE LIABILITY | J68: =J62 -> 27212
C69: Cr: Acct 0848 - DEBT SERVICE - PRINCIPAL LEASES | K69: =J68 -> 27212
J70: =SUM(J68:J69) -> 27212 | K70: =SUM(K68:K69) -> 27212 | L70: =IF(J70=K70,"<- Debits and Credits equal each other.","<- Debits and Credits do not equal each other.") -> <- Debits and Credits equal each other.
B71: ** This amount should be included in the deductions column on the LS-Lease Liability and LS-Check Figures Tabs.
A74: 7 | B74: Reclassify the principal amount due in the next FY to the current liability.
A75: **LS LL/CF | B75: Dr: Acct 0691 - RIGHT-TO-USE LEASE LIABILITY | J75: 28087
C76: Cr: Acct 0649 - RIGHT-TO-USE LEASE LIABILITY (CURRENT PORTION LT) | K76: =J75 -> 28087
B77: NOTE: This is an annual accrual. It is to be reversed at the start of the next fiscal year. SCO combines the current and non current amount in Entry #0 to reestablish the beginning balances. No action required. | J77: =SUM(J75:J76) -> 28087 | K77: =SUM(K75:K76) -> 28087 | L77: =IF(J77=K77,"<- Debits and Credits equal each other.","<- Debits and Credits do not equal each other.") -> <- Debits and Credits equal each other.
B80: ** This amount should be included in the due in one year column on the LS-Lease Liability and LS-Check Figures Tabs.
A83: Remove Lease Asset at the End of the Lease Term (only at the end of the lease term)
A84: 8 | B84: Record entry to write off the lease asset and accumulated amortization at the end of the lease term.
B85: Dr: Acct 0485 - ACCUMULATED AMORTIZATION - RIGHT-TO-USE LEASED LAND
B86: Dr: Acct 0479 - ACCUMULATED AMORTIZATION - RIGHT-TO-USE LEASED EQUIPMENT
B87: Dr: Acct 0486 - ACCUMULATED AMORTIZATION - RIGHT-TO-USE LEASED BUILDINGS | J87: 0
A88: *Rpt 18 | C88: Cr: Acct 0476 - RIGHT-TO-USE LEASED LAND - AMORTIZABLE
A89: *Rpt 18 | C89: Cr: Acct 0478 - RIGHT-TO-USE LEASED EQUIPMENT - AMORTIZABLE
A90: *Rpt 18 | C90: Cr: Acct 0477 - RIGHT-TO-USE LEASED BUILDINGS - AMORTIZABLE | K90: 0
B91: * THESE AMOUNTS SHOULD BE INCLUDED AS "DEDUCTIONS" ON REPORT 18. | J91: =SUM(J85:J90) -> 0 | K91: =SUM(K85:K90) -> 0 | L91: =IF(J91=K91,"<- Debits and Credits equal each other.","<- Debits and Credits do not equal each other.") -> <- Debits and Credits equal each other.
A94: Lease Remeasurement and Modifications (only if a significant modification occurred during the fiscal year)
A95: 9 | B95: Record early termination or lease modifications to decrease in the RTU leased asset.
A96: **LS LL/CF | B96: Dr: Acct 0691 - RIGHT-TO-USE LEASE LIABILITY
B97: Dr: Acct 0485 - ACCUMULATED AMORTIZATION - RIGHT-TO-USE LEASED LAND
B98: Dr: Acct 0479 - ACCUMULATED AMORTIZATION - RIGHT-TO-USE LEASED EQUIPMENT
B99: Dr: Acct 0486 - ACCUMULATED AMORTIZATION - RIGHT-TO-USE LEASED BUILDINGS
B100: =IF($F$7="Proprietary","Dr: Acct 0870 - SERVICES & CHARGES (MG ADJ)",VLOOKUP($F$9,'[3]Drop Down Menus'!$F$2:$H$10,3,FALSE)) -> Dr: Acct 0830 - TRANSPORTATION (GAAP ADJ)
A101: *Rpt 18 | C101: Cr: Acct 0476 - RIGHT-TO-USE LEASED LAND - AMORTIZABLE
A102: *Rpt 18 | C102: Cr: Acct 0478 - RIGHT-TO-USE LEASED EQUIPMENT - AMORTIZABLE
A103: *Rpt 18 | C103: Cr: Acct 0477 - RIGHT-TO-USE LEASED BUILDINGS - AMORTIZABLE
C104: =IF($F$7="Proprietary","Dr: Acct 0870 - SERVICES & CHARGES (MG ADJ)",VLOOKUP($F$9,'[3]Drop Down Menus'!$F$2:$G$10,2,FALSE)) -> Cr: Acct 0830 - TRANSPORTATION (GAAP ADJ)
B105: * THESE AMOUNTS SHOULD BE INCLUDED AS "DEDUCTIONS" ON REPORT 18. | J105: =SUM(J96:J104) -> 0 | K105: =SUM(K96:K104) -> 0 | L105: =IF(J105=K105,"<- Debits and Credits equal each other.","<- Debits and Credits do not equal each other.") -> <- Debits and Credits equal each other.
B106: ** This amount should be included in the deductions column on the LS-Lease Liability and LS-Check Figures Tabs.
A109: 10 | B109: Record lease modifications to increase in the RTU leased asset.
A110: *Rpt 18 | B110: Dr: Acct 0476 - RIGHT-TO-USE LEASED LAND - AMORTIZABLE
A111: *Rpt 18 | B111: Dr: Acct 0478 - RIGHT-TO-USE LEASED EQUIPMENT - AMORTIZABLE
A112: *Rpt 18 | B112: Dr: Acct 0477 - RIGHT-TO-USE LEASED BUILDINGS - AMORTIZABLE
A113: **LS LL/CF | C113: Cr: Acct 0691 - RIGHT-TO-USE LEASE LIABILITY
B114: * THESE AMOUNTS SHOULD BE INCLUDED AS "ADDITIONS" ON REPORT 18. | J114: =SUM(J110:J113) -> 0 | K114: =SUM(K110:K113) -> 0 | L114: =IF(J114=K114,"<- Debits and Credits equal each other.","<- Debits and Credits do not equal each other.") -> <- Debits and Credits equal each other.
B115: ** This amount should be included in the additions column on the LS-Lease Liability and LS-Check Figures Tabs.
D120: Informational - Ending Balances of Assets and Liabilities
K121: Debit (Credit)
D122: Acct 0476 - RIGHT-TO-USE LEASED LAND - AMORTIZABLE | K122: =J15+J39-K88-K101+J110 -> 0
D123: Acct 0478 - RIGHT-TO-USE LEASED EQUIPMENT - AMORTIZABLE | K123: =J16+J40-K89-K102+J111 -> 0
D124: Acct 0477 - RIGHT-TO-USE LEASED BUILDINGS - AMORTIZABLE | K124: =J17+J41-K90-K103+J112 -> 83839
D125: Acct 0485 - ACCUMULATED AMORTIZATION - RIGHT-TO-USE LEASED LAND | K125: =-K20-K56+J85+J97 -> 0
...

Sheet LS-Fund 6072 Journal Entrie 
A1: Lessee-Type Contracts Fund-by-Fund Journal Entries Form (to be submitted to the SCO annually—one form per fund)
A2: Manually complete every yellow field in this worksheet—there are no automatically calculated data-entry cells in this worksheet.
A3: Fiscal Year: | F3: 2022–2023
A4: Organization Name: | F4: Department of Transportation
A5: Organization Code (4-Digits): | F5: 2660
A6: Fund Number (4-Digits): | F6: 6072
A7: Fund Classification: | F7: Governmental
A8: Fund Type: | F8: Governmental Fund
A9: Functional Expense: | F9: =IFERROR(IF(F7="Proprietary","Proprietary Fund",VLOOKUP(F5,[3]qryIndex02a!$A$2:$K$654,4,FALSE)),"Unidentified") -> TRANSPORTATION
A12: Establish Beginning Balances (existing leases only)
A13: Entry #
A14: 0 | B14: Roll forward prior year right-to-use leases to record opening balances. | M14: Combined Lessee Templates | P14: From SCO BB List | S14: Difference
A15: *Rpt 18 | B15: Dr: Acct 0476 - RIGHT-TO-USE LEASED LAND - AMORTIZABLE | J15: =M15 -> 0 | P15: 0 | S15: =P15-M15 -> 0
A16: *Rpt 18 | B16: Dr: Acct 0478 - RIGHT-TO-USE LEASED EQUIPMENT - AMORTIZABLE | J16: =M16 -> 0 | P16: 0 | S16: =P16-M16 -> 0
A17: *Rpt 18 | B17: Dr: Acct 0477 - RIGHT-TO-USE LEASED BUILDINGS - AMORTIZABLE | J17: =M17 -> 127178 | M17: 127178 | P17: 127178 | S17: =P17-M17 -> 0
B18: Dr: Acct 0950 - BEGINNING FUND BALANCE | J18: =P18 -> 32 | M18: 32 | P18: =IF(SUM($Q$21:$Q$23)>SUM($P$15:$P$17),SUM($Q$21:$Q$23)-SUM($P$15:$P$17),0) -> 32 | S18: =P18-M18 -> 0
B19: Dr: Acct 0952 - BEGINNING FUND ADJUSTMENT/PRIOR PERIOD ADJUSTMENT | J19: =IF(SUM($K$21:$K$24)>SUM($J$15:$J$18),SUM($K$21:$K$24)-SUM($J$15:$J$18),0) -> 0 | S19: =P19-M19 -> 0
C20: Cr: Acct 0485 - ACCUMULATED AMORTIZATION - RIGHT-TO-USE LEASED LAND | K20: =N20 -> 0 | S20: =P20-M20 -> 0
C21: Cr: Acct 0479 - ACCUMULATED AMORTIZATION - RIGHT-TO-USE LEASED EQUIPMENT | K21: =N21 -> 0 | S21: =Q21-N21 -> 0
C22: Cr: Acct 0486 - ACCUMULATED AMORTIZATION - RIGHT-TO-USE LEASED BUILDINGS | K22: =N22 -> 95383 | N22: 95383 | Q22: 95383 | S22: =Q22-N22 -> 0
A23: **LS LL/CF | C23: Cr: Acct 0691 - RIGHT-TO-USE LEASE LIABILITY | K23: =N23 -> 31826 | N23: 31826 | Q23: 31827 | S23: =Q23-N23 -> 1
C24: Cr: Acct 0950 - BEGINNING FUND BALANCE | K24: =Q24 -> 0 | Q24: =IF(SUM($Q$39:$Q$41)<SUM($P$33:$P$35),-SUM($Q$39:$Q$41)+SUM($P$33:$P$35),0) -> 0 | S24: =Q24-N24 -> 0
C25: Cr: Acct 0952 - BEGINNING FUND ADJUSTMENT/PRIOR PERIOD ADJUSTMENT | K25: =IF(SUM($K$21:$K$24)<SUM($J$15:$J$18),-SUM($K$21:$K$24)+SUM($J$15:$J$18),0) -> 1 | S25: =Q25-N25 -> 0
J26: =SUM(J15:J25) -> 127210 | K26: =SUM(K15:K25) -> 127210 | L26: =IF(J26=K26,"<- Debits and Credits equal each other.","<- Debits and Credits do not equal each other.") -> <- Debits and Credits equal each other.
B27: * THESE ASSET AMOUNTS SHOULD BE REPORTED AS BEGINNING BALANCES ON REPORT 18.
B28: ** This amount should be included in the beginning balance column on the LS-Lease Liability and LS-Check Figures Tabs.
A31: Record New Leases (new leases only)
A32: 1 | B32: Record lease contract commencement (fund-based entries only)
B33: Dr: Acct 0842 - CAPITAL OUTLAY | J33: 0
C34: Cr: Acct 0789 - LEASE AND OTHER FINANCING PROCEEDS | K34: =J33 -> 0
C35: =IF($F$7="Proprietary","Cr: Acct 0870 - SERVICES & CHARGES (MG ADJ)",VLOOKUP($F$9,'[3]Drop Down Menus'!$F$2:$G$10,2,FALSE)) -> Cr: Acct 0830 - TRANSPORTATION (GAAP ADJ) | K35: 0
J36: =SUM(J33:J35) -> 0 | K36: =SUM(K33:K35) -> 0 | L36: =IF(J36=K36,"<- Debits and Credits equal each other.","<- Debits and Credits do not equal each other.") -> <- Debits and Credits equal each other.
A38: 2 | B38: Record leased assets.
A39: *Rpt 18 | B39: Dr: Acct 0476 - RIGHT-TO-USE LEASED LAND - AMORTIZABLE | J39: 0
A40: *Rpt 18 | B40: Dr: Acct 0478 - RIGHT-TO-USE LEASED EQUIPMENT - AMORTIZABLE | J40: 0
A41: *Rpt 18 | B41: Dr: Acct 0477 - RIGHT-TO-USE LEASED BUILDINGS - AMORTIZABLE | J41: =K34 -> 0
C42: Cr: Acct 0842 - CAPITAL OUTLAY | K42: =J41 -> 0
B43: * THESE AMOUNTS SHOULD BE INCLUDED AS "ADDITIONS" ON REPORT 18. | J43: =SUM(J39:J42) -> 0 | K43: =SUM(K39:K42) -> 0 | L43: =IF(J43=K43,"<- Debits and Credits equal each other.","<- Debits and Credits do not equal each other.") -> <- Debits and Credits equal each other.
A46: 3 | B46: Replace proceeds from leases with right-to-use lease liability.
B47: Dr: Acct 0789 - LEASE AND OTHER FINANCING PROCEEDS | J47: =K34 -> 0
A48: **LS LL/CF | C48: Cr: Acct 0691 - RIGHT-TO-USE LEASE LIABILITY | K48: =J47 -> 0
J49: =SUM(J47:J48) -> 0 | K49: =SUM(K47:K48) -> 0 | L49: =IF(J49=K49,"<- Debits and Credits equal each other.","<- Debits and Credits do not equal each other.") -> <- Debits and Credits equal each other.
B50: ** This amount should be included in the additions column on the LS-Lease Liability and LS-Check Figures Tabs.
A53: Record Annual Activity (all leases)
A54: 4 | B54: Record amortization of the leased assets for the year.
B55: Dr: Acct 0875 - DEPRECIATION/AMORTIZATION | J55: 31794
C56: Cr: Acct 0485 - ACCUMULATED AMORTIZATION - RIGHT-TO-USE LEASED LAND
C57: Cr: Acct 0479 - ACCUMULATED AMORTIZATION - RIGHT-TO-USE LEASED EQUIPMENT
C58: Cr: Acct 0486 - ACCUMULATED AMORTIZATION - RIGHT-TO-USE LEASED BUILDINGS | K58: =J55 -> 31794
J59: =SUM(J55:J58) -> 31794 | K59: =SUM(K55:K58) -> 31794 | L59: =IF(J59=K59,"<- Debits and Credits equal each other.","<- Debits and Credits do not equal each other.") -> <- Debits and Credits equal each other.
A61: 5 | B61: Reclassify rents and leases exp. to lease contract principal and interest exp.
B62: Dr: Acct 0848 - DEBT SERVICE - PRINCIPAL LEASES | J62: 31826
B63: =IF(F7="Governmental","Dr: Acct 0851 - DEBT SERVICE - INTEREST LEASES","Dr: Acct 0894 - INTEREST EXPENSE AND FISCAL CHARGES") -> Dr: Acct 0851 - DEBT SERVICE - INTEREST LEASES | J63: 13
C64: =IF($F$7="Proprietary","Cr: Acct 0870 - SERVICES & CHARGES (MG ADJ)",VLOOKUP($F$9,'[3]Drop Down Menus'!$F$2:$G$10,2,FALSE)) -> Cr: Acct 0830 - TRANSPORTATION (GAAP ADJ) | K64: =J62+J63 -> 31839
J65: =SUM(J62:J64) -> 31839 | K65: =SUM(K62:K64) -> 31839 | L65: =IF(J65=K65,"<- Debits and Credits equal each other.","<- Debits and Credits do not equal each other.") -> <- Debits and Credits equal each other.
A67: 6 | B67: Reduce lease contracts liability for total current year principal payments.
A68: **LS LL/CF | B68: Dr: Acct 0691 - RIGHT-TO-USE LEASE LIABILITY | J68: =J62 -> 31826
C69: Cr: Acct 0848 - DEBT SERVICE - PRINCIPAL LEASES | K69: =J68 -> 31826
J70: =SUM(J68:J69) -> 31826 | K70: =SUM(K68:K69) -> 31826 | L70: =IF(J70=K70,"<- Debits and Credits equal each other.","<- Debits and Credits do not equal each other.") -> <- Debits and Credits equal each other.
B71: ** This amount should be included in the deductions column on the LS-Lease Liability and LS-Check Figures Tabs.
A74: 7 | B74: Reclassify the principal amount due in the next FY to the current liability.
A75: **LS LL/CF | B75: Dr: Acct 0691 - RIGHT-TO-USE LEASE LIABILITY | J75: 0
C76: Cr: Acct 0649 - RIGHT-TO-USE LEASE LIABILITY (CURRENT PORTION LT) | K76: =J75 -> 0
B77: NOTE: This is an annual accrual. It is to be reversed at the start of the next fiscal year. SCO combines the current and non current amount in Entry #0 to reestablish the beginning balances. No action required. | J77: =SUM(J75:J76) -> 0 | K77: =SUM(K75:K76) -> 0 | L77: =IF(J77=K77,"<- Debits and Credits equal each other.","<- Debits and Credits do not equal each other.") -> <- Debits and Credits equal each other.
B80: ** This amount should be included in the due in one year column on the LS-Lease Liability and LS-Check Figures Tabs.
A83: Remove Lease Asset at the End of the Lease Term (only at the end of the lease term)
A84: 8 | B84: Record entry to write off the lease asset and accumulated amortization at the end of the lease term.
B85: Dr: Acct 0485 - ACCUMULATED AMORTIZATION - RIGHT-TO-USE LEASED LAND
B86: Dr: Acct 0479 - ACCUMULATED AMORTIZATION - RIGHT-TO-USE LEASED EQUIPMENT
B87: Dr: Acct 0486 - ACCUMULATED AMORTIZATION - RIGHT-TO-USE LEASED BUILDINGS | J87: 127178
A88: *Rpt 18 | C88: Cr: Acct 0476 - RIGHT-TO-USE LEASED LAND - AMORTIZABLE
A89: *Rpt 18 | C89: Cr: Acct 0478 - RIGHT-TO-USE LEASED EQUIPMENT - AMORTIZABLE
A90: *Rpt 18 | C90: Cr: Acct 0477 - RIGHT-TO-USE LEASED BUILDINGS - AMORTIZABLE | K90: 127178
B91: * THESE AMOUNTS SHOULD BE INCLUDED AS "DEDUCTIONS" ON REPORT 18. | J91: =SUM(J85:J90) -> 127178 | K91: =SUM(K85:K90) -> 127178 | L91: =IF(J91=K91,"<- Debits and Credits equal each other.","<- Debits and Credits do not equal each other.") -> <- Debits and Credits equal each other.
A94: Lease Remeasurement and Modifications (only if a significant modification occurred during the fiscal year)
A95: 9 | B95: Record early termination or lease modifications to decrease in the RTU leased asset.
A96: **LS LL/CF | B96: Dr: Acct 0691 - RIGHT-TO-USE LEASE LIABILITY
B97: Dr: Acct 0485 - ACCUMULATED AMORTIZATION - RIGHT-TO-USE LEASED LAND
B98: Dr: Acct 0479 - ACCUMULATED AMORTIZATION - RIGHT-TO-USE LEASED EQUIPMENT
B99: Dr: Acct 0486 - ACCUMULATED AMORTIZATION - RIGHT-TO-USE LEASED BUILDINGS
B100: =IF($F$7="Proprietary","Dr: Acct 0870 - SERVICES & CHARGES (MG ADJ)",VLOOKUP($F$9,'[3]Drop Down Menus'!$F$2:$H$10,3,FALSE)) -> Dr: Acct 0830 - TRANSPORTATION (GAAP ADJ)
A101: *Rpt 18 | C101: Cr: Acct 0476 - RIGHT-TO-USE LEASED LAND - AMORTIZABLE
A102: *Rpt 18 | C102: Cr: Acct 0478 - RIGHT-TO-USE LEASED EQUIPMENT - AMORTIZABLE
A103: *Rpt 18 | C103: Cr: Acct 0477 - RIGHT-TO-USE LEASED BUILDINGS - AMORTIZABLE
C104: =IF($F$7="Proprietary","Dr: Acct 0870 - SERVICES & CHARGES (MG ADJ)",VLOOKUP($F$9,'[3]Drop Down Menus'!$F$2:$G$10,2,FALSE)) -> Cr: Acct 0830 - TRANSPORTATION (GAAP ADJ)
B105: * THESE AMOUNTS SHOULD BE INCLUDED AS "DEDUCTIONS" ON REPORT 18. | J105: =SUM(J96:J104) -> 0 | K105: =SUM(K96:K104) -> 0 | L105: =IF(J105=K105,"<- Debits and Credits equal each other.","<- Debits and Credits do not equal each other.") -> <- Debits and Credits equal each other.
B106: ** This amount should be included in the deductions column on the LS-Lease Liability and LS-Check Figures Tabs.
A109: 10 | B109: Record lease modifications to increase in the RTU leased asset.
A110: *Rpt 18 | B110: Dr: Acct 0476 - RIGHT-TO-USE LEASED LAND - AMORTIZABLE
A111: *Rpt 18 | B111: Dr: Acct 0478 - RIGHT-TO-USE LEASED EQUIPMENT - AMORTIZABLE
A112: *Rpt 18 | B112: Dr: Acct 0477 - RIGHT-TO-USE LEASED BUILDINGS - AMORTIZABLE
A113: **LS LL/CF | C113: Cr: Acct 0691 - RIGHT-TO-USE LEASE LIABILITY
B114: * THESE AMOUNTS SHOULD BE INCLUDED AS "ADDITIONS" ON REPORT 18. | J114: =SUM(J110:J113) -> 0 | K114: =SUM(K110:K113) -> 0 | L114: =IF(J114=K114,"<- Debits and Credits equal each other.","<- Debits and Credits do not equal each other.") -> <- Debits and Credits equal each other.
B115: ** This amount should be included in the additions column on the LS-Lease Liability and LS-Check Figures Tabs.
D120: Informational - Ending Balances of Assets and Liabilities
K121: Debit (Credit)
D122: Acct 0476 - RIGHT-TO-USE LEASED LAND - AMORTIZABLE | K122: =J15+J39-K88-K101+J110 -> 0
D123: Acct 0478 - RIGHT-TO-USE LEASED EQUIPMENT - AMORTIZABLE | K123: =J16+J40-K89-K102+J111 -> 0
D124: Acct 0477 - RIGHT-TO-USE LEASED BUILDINGS - AMORTIZABLE | K124: =J17+J41-K90-K103+J112 -> 0
D125: Acct 0485 - ACCUMULATED AMORTIZATION - RIGHT-TO-USE LEASED LAND | K125: =-K20-K56+J85+J97 -> 0
...

Sheet LS-Department Note Disclosure
A1: Submit one form for the department to the SCO annually.
A2: Note: There are three tables of note disclosures on this form —1) governmental funds, 2) proprietary - internal service funds, and 3) proprietary - enterprise funds. Complete all applicable tables before submitting to the SCO.
A3: Manually complete every yellow field in this worksheet—there are no automatically calculated cells in this worksheet.
A4: Complete the fields below using aggregated and summarized information from all of your department's completed contract template forms.
A5: The fields in this worksheet should contain the sums of the department's contracts' corresponding information in their note disclosure worksheets.
A7: I. Governmental funds
A8: Fiscal Year: | B8: 2022–2023
A9: Organization Code: | B9: 2660
A10: Organization Name: | B10: Department of Transportation
A11: The below information must be entered manually.
B12: Principal Payments | C12: Interest Payments | D12: ="All of the below questions are for Fiscal Year "&$B$8&":" -> All of the below questions are for Fiscal Year 2022–2023:
A13: =RIGHT(B8,4)&"–"&RIGHT(B8,4)+1 -> 2023–2024 | B13: 33463895 | C13: 205806 | D13: 1. Did your leasing arrangements have any variable payments which ARE NOT included in the measurement of the lease liability?
A14: =LEFT(A13,4)+1&"–"&RIGHT(A13,4)+1 -> 2024–2025 | B14: 21928739 | C14: 117697
A15: =LEFT(A14,4)+1&"–"&RIGHT(A14,4)+1 -> 2025–2026 | B15: 15979935 | C15: 60154 | D15: No
A16: =LEFT(A15,4)+1&"–"&RIGHT(A15,4)+1 -> 2026–2027 | B16: 4063074 | C16: 19847 | D16: ="If yes, record the dollar amount of variable payments below for fiscal year "&$B$8&":" -> If yes, record the dollar amount of variable payments below for fiscal year 2022–2023:
A17: =LEFT(A16,4)+1&"–"&RIGHT(A16,4)+1 -> 2027–2028 | B17: 983008 | C17: 6987
A18: =LEFT(A17,4)+1&"–"&RIGHT(A17,4)+5 -> 2028–2033 | B18: =288839+1 -> 288840 | C18: 542 | D18: 2. Do your leasing arrangements have any residual value guarantees provided by YOU which ARE NOT included in the measurement of the lease liability?
A19: =LEFT(A18,4)+5&"–"&RIGHT(A18,4)+5 -> 2033–2038 | B19: 0 | C19: 0
A20: =LEFT(A19,4)+5&"–"&RIGHT(A19,4)+5 -> 2038–2043 | B20: 0 | C20: 0 | D20: No
A21: =LEFT(A20,4)+5&"–"&RIGHT(A20,4)+5 -> 2043–2048 | D21: ="If yes, record the dollar amount of any payments made for residual value guarantees below for fiscal year "&$B$8&":" -> If yes, record the dollar amount of any payments made for residual value guarantees below for fiscal year 2022–2023:
A22: =LEFT(A21,4)+5&"–"&RIGHT(A21,4)+5 -> 2048–2053
A23: =LEFT(A22,4)+5&"–"&RIGHT(A22,4)+5 -> 2053–2058
A24: =LEFT(A23,4)+5&"–"&RIGHT(A23,4)+5 -> 2058–2063 | D24: ="3. Record the dollar amount of any other payments for this lease, such as termination penalties, not previously recorded in the payment schedule for fiscal year "&$B$8&":" -> 3. Record the dollar amount of any other payments for this lease, such as termination penalties, not previously recorded in the payment schedule for fiscal year 2022–2023:
A25: =LEFT(A24,4)+5&"–"&RIGHT(A24,4)+5 -> 2063–2068
A26: =LEFT(A25,4)+5&"–"&RIGHT(A25,4)+5 -> 2068–2073 | D26: 0
A27: =LEFT(A26,4)+5&"–"&RIGHT(A26,4)+5 -> 2073–2078 | D27: ="4. Did you receive any lease incentives from the lessor (not already included in the lease measurment) during fiscal year "&$B$8&"? If so, record the amount below:" -> 4. Did you receive any lease incentives from the lessor (not already included in the lease measurment) during fiscal year 2022–2023? If so, record the amount below:
A28: =LEFT(A27,4)+5&"–"&RIGHT(A27,4)+5 -> 2078–2083
A29: =LEFT(A28,4)+5&"–"&RIGHT(A28,4)+5 -> 2083–2088 | D29: No
A30: =LEFT(A29,4)+5&"–"&RIGHT(A29,4)+5 -> 2088–2093 | D30: =CONCATENATE("5. Are there any lease commitments known that have yet to commence as of June 30, ",RIGHT(B8,4),"?") -> 5. Are there any lease commitments known that have yet to commence as of June 30, 2023?
A31: =LEFT(A30,4)+5&"–"&RIGHT(A30,4)+5 -> 2093–2098 | D31: No
A32: =LEFT(A31,4)+5&"–"&RIGHT(A31,4)+5 -> 2098–2103 | D32: ="If yes, record the dollar amount of any lease commitments not commenced below for fiscal year "&A13&"." -> If yes, record the dollar amount of any lease commitments not commenced below for fiscal year 2023–2024.
A33: =LEFT(A32,4)+5&"–"&RIGHT(A32,4)+5 -> 2103–2108
A34: =LEFT(A33,4)+5&"–"&RIGHT(A33,4)+5 -> 2108–2113
A35: =LEFT(A34,4)+5&"–"&RIGHT(A34,4)+5 -> 2113–2118
A36: =LEFT(A35,4)+5&"–"&RIGHT(A35,4)+5 -> 2118–2123
A38: II. Proprietary - INTERNAL SERVICE FUNDS
A39: Fiscal Year: | B39: =B8 -> 2022–2023
A40: Organization Code: | B40: =B9 -> 2660
A41: Organization Name: | B41: =B10 -> Department of Transportation
A42: The below information must be entered manually.
B43: Principal Payments | C43: Interest Payments | D43: ="All of the below questions are for Fiscal Year "&$B$8&":" -> All of the below questions are for Fiscal Year 2022–2023:
A44: =RIGHT(B39,4)&"–"&RIGHT(B39,4)+1 -> 2023–2024 | D44: 1. Did your leasing arrangements have any variable payments which ARE NOT included in the measurement of the lease liability?
A45: =LEFT(A44,4)+1&"–"&RIGHT(A44,4)+1 -> 2024–2025
A46: =LEFT(A45,4)+1&"–"&RIGHT(A45,4)+1 -> 2025–2026
A47: =LEFT(A46,4)+1&"–"&RIGHT(A46,4)+1 -> 2026–2027 | D47: ="If yes, record the dollar amount of variable payments below for fiscal year "&$B$8&":" -> If yes, record the dollar amount of variable payments below for fiscal year 2022–2023:
A48: =LEFT(A47,4)+1&"–"&RIGHT(A47,4)+1 -> 2027–2028
A49: =LEFT(A48,4)+1&"–"&RIGHT(A48,4)+5 -> 2028–2033 | D49: 2. Do your leasing arrangements have any residual value guarantees provided by YOU which ARE NOT included in the measurement of the lease liability?
A50: =LEFT(A49,4)+5&"–"&RIGHT(A49,4)+5 -> 2033–2038
A51: =LEFT(A50,4)+5&"–"&RIGHT(A50,4)+5 -> 2038–2043
A52: =LEFT(A51,4)+5&"–"&RIGHT(A51,4)+5 -> 2043–2048 | D52: ="If yes, record the dollar amount of any payments made for residual value guarantees below for fiscal year "&$B$8&":" -> If yes, record the dollar amount of any payments made for residual value guarantees below for fiscal year 2022–2023:
A53: =LEFT(A52,4)+5&"–"&RIGHT(A52,4)+5 -> 2048–2053
A54: =LEFT(A53,4)+5&"–"&RIGHT(A53,4)+5 -> 2053–2058
A55: =LEFT(A54,4)+5&"–"&RIGHT(A54,4)+5 -> 2058–2063 | D55: ="3. Record the dollar amount of any other payments for this lease, such as termination penalties, not previously recorded in the payment schedule for fiscal year "&$B$8&":" -> 3. Record the dollar amount of any other payments for this lease, such as termination penalties, not previously recorded in the payment schedule for fiscal year 2022–2023:
A56: =LEFT(A55,4)+5&"–"&RIGHT(A55,4)+5 -> 2063–2068
A57: =LEFT(A56,4)+5&"–"&RIGHT(A56,4)+5 -> 2068–2073
A58: =LEFT(A57,4)+5&"–"&RIGHT(A57,4)+5 -> 2073–2078 | D58: ="4. Did you receive any lease incentives from the lessor (not already included in the lease measurment) during fiscal year "&$B$8&"? If so, record the amount below:" -> 4. Did you receive any lease incentives from the lessor (not already included in the lease measurment) during fiscal year 2022–2023? If so, record the amount below:
A59: =LEFT(A58,4)+5&"–"&RIGHT(A58,4)+5 -> 2078–2083
A60: =LEFT(A59,4)+5&"–"&RIGHT(A59,4)+5 -> 2083–2088
A61: =LEFT(A60,4)+5&"–"&RIGHT(A60,4)+5 -> 2088–2093 | D61: =CONCATENATE("5. Are there any lease commitments known that have yet to commence as of June 30, ",RIGHT(B39,4),"?") -> 5. Are there any lease commitments known that have yet to commence as of June 30, 2023?
A62: =LEFT(A61,4)+5&"–"&RIGHT(A61,4)+5 -> 2093–2098
A63: =LEFT(A62,4)+5&"–"&RIGHT(A62,4)+5 -> 2098–2103 | D63: ="If yes, record the dollar amount of any lease commitments not commenced below for fiscal year "&A44&"." -> If yes, record the dollar amount of any lease commitments not commenced below for fiscal year 2023–2024.
A64: =LEFT(A63,4)+5&"–"&RIGHT(A63,4)+5 -> 2103–2108
A65: =LEFT(A64,4)+5&"–"&RIGHT(A64,4)+5 -> 2108–2113
A66: =LEFT(A65,4)+5&"–"&RIGHT(A65,4)+5 -> 2113–2118
A67: =LEFT(A66,4)+5&"–"&RIGHT(A66,4)+5 -> 2118–2123
A69: III. Proprietary - ENTERPRISE FUNDS
A70: Fiscal Year: | B70: =B8 -> 2022–2023
A71: Organization Code: | B71: =B9 -> 2660
A72: Organization Name: | B72: =B10 -> Department of Transportation
A73: The below information must be entered manually.
B74: Principal Payments | C74: Interest Payments | D74: ="All of the below questions are for Fiscal Year "&$B$8&":" -> All of the below questions are for Fiscal Year 2022–2023:
A75: =RIGHT(B70,4)&"–"&RIGHT(B70,4)+1 -> 2023–2024 | D75: 1. Did your leasing arrangements have any variable payments which ARE NOT included in the measurement of the lease liability?
A76: =LEFT(A75,4)+1&"–"&RIGHT(A75,4)+1 -> 2024–2025
A77: =LEFT(A76,4)+1&"–"&RIGHT(A76,4)+1 -> 2025–2026
A78: =LEFT(A77,4)+1&"–"&RIGHT(A77,4)+1 -> 2026–2027 | D78: ="If yes, record the dollar amount of variable payments below for fiscal year "&$B$8&":" -> If yes, record the dollar amount of variable payments below for fiscal year 2022–2023:
A79: =LEFT(A78,4)+1&"–"&RIGHT(A78,4)+1 -> 2027–2028
A80: =LEFT(A79,4)+1&"–"&RIGHT(A79,4)+5 -> 2028–2033 | D80: 2. Do your leasing arrangements have any residual value guarantees provided by YOU which ARE NOT included in the measurement of the lease liability?
A81: =LEFT(A80,4)+5&"–"&RIGHT(A80,4)+5 -> 2033–2038
A82: =LEFT(A81,4)+5&"–"&RIGHT(A81,4)+5 -> 2038–2043
A83: =LEFT(A82,4)+5&"–"&RIGHT(A82,4)+5 -> 2043–2048 | D83: ="If yes, record the dollar amount of any payments made for residual value guarantees below for fiscal year "&$B$8&":" -> If yes, record the dollar amount of any payments made for residual value guarantees below for fiscal year 2022–2023:
A84: =LEFT(A83,4)+5&"–"&RIGHT(A83,4)+5 -> 2048–2053
A85: =LEFT(A84,4)+5&"–"&RIGHT(A84,4)+5 -> 2053–2058
A86: =LEFT(A85,4)+5&"–"&RIGHT(A85,4)+5 -> 2058–2063 | D86: ="3. Record the dollar amount of any other payments for this lease, such as termination penalties, not previously recorded in the payment schedule for fiscal year "&$B$8&":" -> 3. Record the dollar amount of any other payments for this lease, such as termination penalties, not previously recorded in the payment schedule for fiscal year 2022–2023:
A87: =LEFT(A86,4)+5&"–"&RIGHT(A86,4)+5 -> 2063–2068
A88: =LEFT(A87,4)+5&"–"&RIGHT(A87,4)+5 -> 2068–2073
A89: =LEFT(A88,4)+5&"–"&RIGHT(A88,4)+5 -> 2073–2078 | D89: ="4. Did you receive any lease incentives from the lessor (not already included in the lease measurment) during fiscal year "&$B$8&"? If so, record the amount below:" -> 4. Did you receive any lease incentives from the lessor (not already included in the lease measurment) during fiscal year 2022–2023? If so, record the amount below:
A90: =LEFT(A89,4)+5&"–"&RIGHT(A89,4)+5 -> 2078–2083
A91: =LEFT(A90,4)+5&"–"&RIGHT(A90,4)+5 -> 2083–2088
A92: =LEFT(A91,4)+5&"–"&RIGHT(A91,4)+5 -> 2088–2093 | D92: =CONCATENATE("5. Are there any lease commitments known that have yet to commence as of June 30, ",RIGHT(B70,4),"?") -> 5. Are there any lease commitments known that have yet to commence as of June 30, 2023?
A93: =LEFT(A92,4)+5&"–"&RIGHT(A92,4)+5 -> 2093–2098
A94: =LEFT(A93,4)+5&"–"&RIGHT(A93,4)+5 -> 2098–2103 | D94: ="If yes, record the dollar amount of any lease commitments not commenced below for fiscal year "&A75&"." -> If yes, record the dollar amount of any lease commitments not commenced below for fiscal year 2023–2024.
A95: =LEFT(A94,4)+5&"–"&RIGHT(A94,4)+5 -> 2103–2108
A96: =LEFT(A95,4)+5&"–"&RIGHT(A95,4)+5 -> 2108–2113
A97: =LEFT(A96,4)+5&"–"&RIGHT(A96,4)+5 -> 2113–2118
A98: =LEFT(A97,4)+5&"–"&RIGHT(A97,4)+5 -> 2118–2123

Sheet LS-Lease Liabilities
J3: Schedule of Changes in Lease Liabilities
J4: =CONCATENATE("FY ",'LS-Fund 0042 Journal Entries'!F3) -> FY 2022–2023
J5: =CONCATENATE("Business Unit ",'LS-Department Note Disclosure'!B9," - ",'LS-Department Note Disclosure'!B10) -> Business Unit 2660 - Department of Transportation
F7: =CONCATENATE("Balance July 1, ",MID(J4,4,4)) -> Balance July 1, 2022 | H7: Additions | J7: Deductions | L7: =CONCATENATE("Balance June 30, ",RIGHT(J4,4)) -> Balance June 30, 2023 | N7: Due Within One Year | P7: Noncurrent Liabilities
F8: (Entry #0) | H8: (Entry #3 & 10) | J8: (Entry #6 & 9) | N8: (Entry #7)
C9: Governmental Funds
D10: Lease Liability | F10: ='LS-Fund 0042 Journal Entries'!K23+'LS-Fund 0046 Journal Entrie'!K23+'LS-Fund 3290 Journal Entrie'!K23+'LS-Fund 3291 Journal Entrie'!K23+'LS-Fund 6072 Journal Entrie '!K23 -> 73030524 | H10: ='LS-Fund 0042 Journal Entries'!K48+'LS-Fund 0046 Journal Entrie'!K48+'LS-Fund 3290 Journal Entrie'!K48+'LS-Fund 3291 Journal Entrie'!K48+'LS-Fund 6072 Journal Entrie '!K48 -> 27063637 | J10: ='LS-Fund 0042 Journal Entries'!J68+'LS-Fund 0046 Journal Entrie'!J68+'LS-Fund 3290 Journal Entrie'!J68+'LS-Fund 3291 Journal Entrie'!J68+'LS-Fund 6072 Journal Entrie '!J68 -> 23386670 | L10: =SUM(F10+H10-J10) -> 76707491 | N10: ='LS-Fund 0042 Journal Entries'!J75+'LS-Fund 0046 Journal Entrie'!J75+'LS-Fund 3290 Journal Entrie'!J75+'LS-Fund 3291 Journal Entrie'!J75+'LS-Fund 6072 Journal Entrie '!J75 -> 33463895 | P10: =L10-N10 -> 43243596
C11: Total Governmental Funds | F11: =SUM(F10:F10) -> 73030524 | H11: =SUM(H10:H10) -> 27063637 | J11: =SUM(J10:J10) -> 23386670 | L11: =SUM(L10:L10) -> 76707491 | N11: =SUM(N10:N10) -> 33463895 | P11: =SUM(P10:P10) -> 43243596
C13: Proprietary - Internal Service Funds
D14: Lease Liability | L14: =SUM(F14+H14-J14) -> 0 | P14: =L14-N14 -> 0
C15: Total Proprietary - Internal Service Funds | F15: =SUM(F14:F14) -> 0 | H15: =SUM(H14:H14) -> 0 | J15: =SUM(J14:J14) -> 0 | L15: =SUM(L14:L14) -> 0 | N15: =SUM(N14:N14) -> 0 | P15: =SUM(P14:P14) -> 0
C17: Proprietary - Enterprise Funds
D18: Lease Liability | L18: =SUM(F18+H18-J18) -> 0 | P18: =L18-N18 -> 0
C19: Total Proprietary - Enterprise Funds | F19: =SUM(F18:F18) -> 0 | H19: =SUM(H18:H18) -> 0 | J19: =SUM(J18:J18) -> 0 | L19: =SUM(L18:L18) -> 0 | N19: =SUM(N18:N18) -> 0 | P19: =SUM(P18:P18) -> 0

Sheet LS-Check Figures  
A1: GASB Statement No. 87 Leases
A2: Check Figures
A4: Purpose:
A5: The purpose of this workbook is to check the figures entered in the journal entries reconcile to the future principal payments disclosed and the changes in the schedule of the lease liabilities.
A8: NOTE: If multiple funds are included in this workbook, manually complete every yellow field by consolidating the entries by fund type (Governmental, Proprietary ISF, and Proprietary EF).
A10: 1. To reconcile the journal entries of RTU Lease Liability with the principal payments in Note Disclosure.
B11: a) Governmental Funds
B13: Journal Entries | N13: Department Note Disclosure
B14: Beginning Balance | D14: Additions | F14: Deductions | H14: Deductions (Mod) | J14: Additions (Mod)
B15: Entry #0 | C15: + | D15: Entry #3 | E15: - | F15: Entry #6 | G15: - | H15: Entry #9 | I15: + | J15: Entry #10 | N15: Sum Principal Payments | P15: Variance
B16: ='LS-Fund 0042 Journal Entries'!K23+'LS-Fund 0046 Journal Entrie'!K23+'LS-Fund 3290 Journal Entrie'!K23+'LS-Fund 3291 Journal Entrie'!K23+'LS-Fund 6072 Journal Entrie '!K23 -> 73030524 | C16: + | D16: ='LS-Fund 0042 Journal Entries'!K48+'LS-Fund 0046 Journal Entrie'!K48+'LS-Fund 3290 Journal Entrie'!K48+'LS-Fund 3291 Journal Entrie'!K48+'LS-Fund 6072 Journal Entrie '!K48 -> 27063637 | E16: - | F16: ='LS-Fund 0042 Journal Entries'!J68+'LS-Fund 0046 Journal Entrie'!J68+'LS-Fund 3290 Journal Entrie'!J68+'LS-Fund 3291 Journal Entrie'!J68+'LS-Fund 6072 Journal Entrie '!J68 -> 23386670 | G16: - | H16: 0 | I16: + | J16: 0 | K16: = | L16: =+B16+D16-F16-H16+J16 -> 76707491 | N16: =SUM('LS-Department Note Disclosure'!B13:B36) -> 76707491 | P16: =L16-N16 -> 0
D18: =IF(OR(P16>0, (P16<0)), "Please review and correct the variance.","")
B19: b) Proprietary - Internal Service Funds
B21: Journal Entries | N21: Department Note Disclosure
B22: Beginning Balance | D22: Additions | F22: Deductions | H22: Deductions (Mod) | J22: Additions (Mod)
B23: Entry #0 | C23: + | D23: Entry #3 | E23: - | F23: Entry #6 | G23: - | H23: Entry #9 | I23: + | J23: Entry #10 | N23: Sum Principal Payments | P23: Variance
C24: + | D24: =IF('LS-Fund 0042 Journal Entries'!$F$8="Proprietary - Internal Service Fund",'LS-Fund 0042 Journal Entries'!$K$48,0) -> 0 | E24: - | G24: - | I24: + | J24: =IF('LS-Fund 0042 Journal Entries'!$F$8="Proprietary - Internal Service Fund",'LS-Fund 0042 Journal Entries'!$K$113,0) -> 0 | K24: = | L24: =+B24+D24-F24-H24+J24 -> 0 | N24: =SUM('LS-Department Note Disclosure'!B44:B67) -> 0 | P24: =L24-N24 -> 0
D26: =IF(OR(P24>0, (P24<0)), "Please review and correct the variance.","")
B28: c) Proprietary - Enterprise Funds
B30: Journal Entries | N30: Department Note Disclosure
B31: Beginning Balance | D31: Additions | F31: Deductions | H31: Deductions (Mod) | J31: Additions (Mod)
B32: Entry #0 | C32: + | D32: Entry #3 | E32: - | F32: Entry #6 | G32: - | H32: Entry #9 | I32: + | J32: Entry #10 | N32: Sum Principal Payments | P32: Variance
B33: =IF('LS-Fund 0042 Journal Entries'!$F$8="Proprietary - Enterprise Fund",'LS-Fund 0042 Journal Entries'!$K$23,0) -> 0 | C33: + | D33: =IF('LS-Fund 0042 Journal Entries'!$F$8="Proprietary - Enterprise Fund",'LS-Fund 0042 Journal Entries'!$K$48,0) -> 0 | E33: - | F33: =IF('LS-Fund 0042 Journal Entries'!$F$8="Proprietary - Enterprise Fund",'LS-Fund 0042 Journal Entries'!$J$68,0) -> 0 | G33: - | H33: =IF('LS-Fund 0042 Journal Entries'!$F$8="Proprietary - Enterprise Fund",'LS-Fund 0042 Journal Entries'!$J$96,0) -> 0 | I33: + | J33: =IF('LS-Fund 0042 Journal Entries'!$F$8="Proprietary - Enterprise Fund",'LS-Fund 0042 Journal Entries'!$K$113,0) -> 0 | K33: = | L33: =+B33+D33-F33-H33+J33 -> 0 | N33: =SUM('LS-Department Note Disclosure'!B75:B98) -> 0 | P33: =L33-N33 -> 0
D35: =IF(OR(P33>0, (P33<0)), "Please review and correct the variance.","")
A37: 2. To match the journal entry to the principal amount due in the next fiscal year in Note Disclosure.
B38: a) Governmental Funds
B40: Journal Entries | N40: Department Note Disclosure
B41: Entry #7 | C41: Due within one year | N41: =CONCATENATE('LS-Department Note Disclosure'!$A$13," Principal Payments") -> 2023–2024 Principal Payments | P41: Variance
B42: ='LS-Fund 0042 Journal Entries'!J75+'LS-Fund 0046 Journal Entrie'!J75+'LS-Fund 3290 Journal Entrie'!J75+'LS-Fund 3291 Journal Entrie'!J75+'LS-Fund 6072 Journal Entrie '!J75 -> 33463895 | N42: ='LS-Department Note Disclosure'!B13 -> 33463895 | P42: =B42-N42 -> 0
D44: =IF(OR(P42>0, (P42<0)), "Please review and correct the variance.","")
B45: b) Proprietary - Internal Service Funds
B47: Journal Entries | N47: Department Note Disclosure
B48: Entry #7 | C48: Due within one year | N48: =CONCATENATE('LS-Department Note Disclosure'!$A$44," Principal Payments") -> 2023–2024 Principal Payments | P48: Variance
N49: ='LS-Department Note Disclosure'!B44 -> 0 | P49: =B49-N49 -> 0
D51: =IF(OR(P49>0, (P49<0)), "Please review and correct the variance.","")
B53: c) Proprietary - Enterprise Funds
B55: Journal Entries | N55: Department Note Disclosure
B56: Entry #7 | C56: Due within one year | N56: =CONCATENATE('LS-Department Note Disclosure'!$A$75," Principal Payments") -> 2023–2024 Principal Payments | P56: Variance
B57: =IF('LS-Fund 0042 Journal Entries'!$F$8="Proprietary - Enterprise Fund",'LS-Fund 0042 Journal Entries'!$K$76,0) -> 0 | N57: ='LS-Department Note Disclosure'!B75 -> 0 | P57: =B57-N57 -> 0
D59: =IF(OR(P57>0, (P57<0)), "Please review and correct the variance.","")
A61: 3. To reconcile the journal entries of RTU Lease Liability with the schedule of changes in Lease Liabilities.
B62: a) Governmental Funds
B64: Journal Entries | J64: Totals | L64: Schedule of Changes in Lease Liabilities
P65: Variance
B66: Entry #0 | D66: =$B$16 -> 73030524 | J66: =SUM(D66) -> 73030524 | L66: =CONCATENATE("Balance July 1, ",LEFT('LS-Department Note Disclosure'!$B$8,4)) -> Balance July 1, 2022 | N66: ='LS-Lease Liabilities'!F10 -> 73030524 | P66: =J66-N66 -> 0
B67: Entry #3 | D67: =$D$16 -> 27063637 | E67: + | F67: Entry #10 | H67: =$J$16 -> 0 | J67: =SUM(D67,H67) -> 27063637 | L67: Additions | N67: ='LS-Lease Liabilities'!H10 -> 27063637 | P67: =J67-N67 -> 0
B68: Entry #6 | D68: =$F$16 -> 23386670 | E68: + | F68: Entry #9 | H68: =$H$16 -> 0 | J68: =SUM(D68,H68) -> 23386670 | L68: Deductions | N68: ='LS-Lease Liabilities'!J10 -> 23386670 | P68: =J68-N68 -> 0
B69: Entry #7 | D69: =$B$42 -> 33463895 | J69: =SUM(D69) -> 33463895 | L69: Due Within One Year | N69: ='LS-Lease Liabilities'!N10 -> 33463895 | P69: =J69-N69 -> 0
D71: =IF(OR(P66>0, (P66<0),P67>0,P67<0,P68>0,P68<0,P69>0,P69<0), "Please review and correct the variance.","")
B73: b) Proprietary - Internal Service Funds
B75: Journal Entries | J75: Totals | L75: Schedule of Changes in Lease Liabilities
P76: Variance
B77: Entry #0 | D77: =B24 -> 0 | J77: =SUM(D77) -> 0 | L77: =CONCATENATE("Balance July 1, ",LEFT('LS-Department Note Disclosure'!$B$8,4)) -> Balance July 1, 2022 | N77: ='LS-Lease Liabilities'!F14 -> 0 | P77: =J77-N77 -> 0
B78: Entry #3 | D78: =D24 -> 0 | E78: + | F78: Entry #10 | H78: =$J$24 -> 0 | J78: =SUM(D78,H78) -> 0 | L78: Additions | N78: ='LS-Lease Liabilities'!H14 -> 0 | P78: =J78-N78 -> 0
B79: Entry #6 | D79: =F24 -> 0 | E79: + | F79: Entry #9 | H79: =$H$24 -> 0 | J79: =SUM(D79,H79) -> 0 | L79: Deductions | N79: ='LS-Lease Liabilities'!J14 -> 0 | P79: =J79-N79 -> 0
B80: Entry #7 | D80: =B49 -> 0 | J80: =SUM(D80) -> 0 | L80: Due Within One Year | N80: ='LS-Lease Liabilities'!N14 -> 0 | P80: =J80-N80 -> 0
B84: c) Proprietary - Enterprise Funds
B86: Journal Entries | J86: Totals | L86: Schedule of Changes in Lease Liabilities
P87: Variance
B88: Entry #0 | D88: =B33 -> 0 | J88: =SUM(D88) -> 0 | L88: =CONCATENATE("Balance July 1, ",LEFT('LS-Department Note Disclosure'!$B$8,4)) -> Balance July 1, 2022 | N88: ='LS-Lease Liabilities'!F18 -> 0 | P88: =J88-N88 -> 0
B89: Entry #3 | D89: =D33 -> 0 | E89: + | F89: Entry #10 | H89: =$J$33 -> 0 | J89: =SUM(D89,H89) -> 0 | L89: Additions | N89: ='LS-Lease Liabilities'!H18 -> 0 | P89: =J89-N89 -> 0
B90: Entry #6 | D90: =F33 -> 0 | E90: + | F90: Entry #9 | H90: =$H$33 -> 0 | J90: =SUM(D90,H90) -> 0 | L90: Deductions | N90: ='LS-Lease Liabilities'!J18 -> 0 | P90: =J90-N90 -> 0
B91: Entry #7 | D91: =B57 -> 0 | J91: =SUM(D91) -> 0 | L91: Due Within One Year | N91: ='LS-Lease Liabilities'!N18 -> 0 | P91: =J91-N91 -> 0
D93: =IF(OR(P88>0, (P88<0),P89>0,P89<0,P90>0,P90<0,P91>0,P91<0), "Please review and correct the variance.","")
